Workbook
Name AdditionalInstructions: IndexInformation!$B$42
Name Address: ImportantDisclosures!$A$2:$A$2
Name ANA: ModPubIndex!$A$7
Name Authors: ImportantDisclosures!$A$7
Name Authors: IndexInformation!$B$18
Name BRO: ModPubIndex!$A$1
Name CopyrightStamp: ImportantDisclosures!$A$27
Name COU: ModPubIndex!$A$5
Name CQEnd: IndexInformation!$B$31
Name Currency: IndexInformation!$B$24
Name CurrentStockPrice: IndexInformation!$B$23
Name CurrQtrEPS: IndexInformation!$B$29
Name CurrYearEPS: IndexInformation!$B$11
Name CurrYearTotalRevenue: IndexInformation!$B$10
Name CurrYearTotalRevenueActual: IndexInformation!$B$32
Name CUSIP: IndexInformation!$B$20
Name CYEnd: IndexInformation!$B$30
Name Date: ImportantDisclosures!$A$8
Name Deleted: IndexInformation!$B$27
Name Description: IndexInformation!$B$7
Name Discipline: IndexInformation!$B$3
Name DISCIPLINE: ModPubIndex!$A$12
Name DisclosuresText: ImportantDisclosures!$A$22
Name Distribution: IndexInformation!$B$26
Name DistTable: ImportantDisclosures!#REF!
Name DistTablePreamble: ImportantDisclosures!#REF!
Name DOCDAT: ModPubIndex!$A$2
Name DOCTIME: ModPubIndex!$A$3
Name DocType: IndexInformation!$B$5
Name EMAIL_ALERT: ModPubIndex!$A$10
Name EmailAlert: IndexInformation!$B$28
Name FiveYearGrowthRate: IndexInformation!$B$16
Name FollowingYearEPS: IndexInformation!$B$15
Name FollowingYearTotalRevenue: IndexInformation!$B$14
Name FollowingYearTotalRevenueActual: IndexInformation!$B$34
Name HL: ModPubIndex!$A$8
Name IND: ModPubIndex!$A$9
Name Industry: ImportantDisclosures!$A$12
Name IndustryId: IndexInformation!$B$40
Name IndustryRating: ImportantDisclosures!$A$13
Name KeepVersions: IndexInformation!$B$8
Name LanguageCode: IndexInformation!$B$38
Name LastCell: ImportantDisclosures!$A$22
Name Linking_1: IS!$A$5:$CM$57
Name Linking_10: [7]BBB!$L$37
Name Linking_11: [7]BBB!$N$37
Name Linking_12: [7]BBB!$P$37
Name Linking_13: [7]BBB!$L$41
Name Linking_14: [7]BBB!$N$41
Name Linking_15: [7]BBB!$P$41
Name Linking_16: [7]Variance!$A$12:$I$41
Name Linking_17: [7]Guidance!$A$5:$I$19
Name Linking_18: '[7]Model Changes'!$A$7:$G$57
Name Linking_19: '[7]EPS Preview'!$A$8:$E$33
Name Linking_2: BDX!$A$5:$CM$74
Name Linking_3: BS!$A$5:$CM$53
Name Linking_4: CFS!$A$5:$CM$59
Name Linking_5: [7]BBB!$L$31
Name Linking_6: [7]BBB!$P$31
Name Linking_7: [7]BBB!$L$34

Sheet ImportantDisclosures
A2: 1585 Broadway
A3: New York, NY 10036-8293
A4: United States
A5: Tel: +1 (1)212 761 4000
A7: Authors: David Lewis, Varun Kuchibhatla
A8: Date: 14 Apr 2018
A10: Ticker: BDX.N
A11: Stock Rating: Equal-Weight
A12: Industry: Medical Technology
A13: Industry View: Attractive
A14: Price as of 14 Apr 2018: 225.45
A15: Target Price: 250
... A123: Equal-weight and Not-Rated to hold and Underweight to sell recommendations, respectively.
B125: Coverage Universe | D125: Investment Banking Clients (IBC) | G125: Other Material Investment Services Clients (MISC)
A126: Stock Rating Category | B126: Count | C126: % of Total | D126: Count | E126: % of Total IBC | F126: % of Rating Category | G126: Count | H126: % of Total Other MISC
A127: Overweight/Buy | B127: 1189 | C127: 0.38 | D127: 315 | E127: 0.41 | F127: 0.26 | G127: 555 | H127: 0.39
A128: Equal-weight/Hold | B128: 1355 | C128: 0.43 | D128: 364 | E128: 0.47 | F128: 0.27 | G128: 644 | H128: 0.45
A129: Not-Rated/Hold | B129: 53 | C129: 0.02 | D129: 4 | E129: 0.01 | F129: 0.08 | G129: 7 | H129: 0
A130: Underweight/Sell | B130: 545 | C130: 0.17 | D130: 84 | E130: 0.11 | F130: 0.15 | G130: 214 | H130: 0.15
A131: Total | B131: 3142 | D131: 767 | G131: 1420
A133: Data include common stock and ADRs currently assigned ratings. Investment Banking Clients are companies
A134: from whom Morgan Stanley received investment banking compensation in the last 12 months. Due to rounding
A135: off of decimals, the percentages provided in the "% of total" column may not add up to exactly 100
A136: percent.
A138: Analyst Stock Ratings
A140: Overweight (O). The stock's total return is expected to exceed the average total return of the analyst's
A141: industry (or industry team's) coverage universe, on a risk-adjusted basis, over the next 12-18 months.
A143: Equal-weight (E). The stock's total return is expected to be in line with the average total return of
A144: the analyst's industry (or industry team's) coverage universe, on a risk-adjusted basis, over the next
A145: 12-18 months.
A147: Not-Rated (NR). Currently the analyst does not have adequate conviction about the stock's total return
A148: relative to the average total return of the analyst's industry (or industry team's) coverage universe,
... A394: © Copyright 2018 Morgan Stanley

Sheet TOC
A4: Becton Dickinson | D4: BDX.N
A6: Click on the following to go to specific sections of our BDX model:
A9: Quarterly Income Statement
A11: Quarterly Sales by Segment
A13: Quarterly Balance Sheet
A15: Quarterly Cash Flow Statement

Sheet IS
A1: Becton Dickinson
A2: Income Statement
A3: Dollars in millions, except per share data
A4: Fiscal year ends Sep 30
C5: 2007 | G5: =C5 -> 2007 | I5: =C5+1 -> 2008 | M5: =I5 -> 2008 | O5: =I5+1 -> 2009 | S5: =O5 -> 2009 | U5: =O5+1 -> 2010 | Y5: =U5 -> 2010 | AA5: =U5+1 -> 2011 | AE5: =AA5 -> 2011 | AG5: =AA5+1 -> 2012 | AK5: =AG5 -> 2012 | AM5: =AG5+1 -> 2013 | AQ5: =AM5 -> 2013 | AS5: =AM5+1 -> 2014 | AW5: =AS5 -> 2014 | AY5: =AS5+1 -> 2015 | BC5: =AY5 -> 2015 | BE5: =AY5+1 -> 2016 | BI5: =BE5 -> 2016 | BK5: =BE5+1 -> 2017 | BO5: =BK5 -> 2017 | BQ5: =BK5+1 -> 2018 | BU5: =BQ5 -> 2018 | BW5: =BQ5+1 -> 2019 | CA5: =BW5 -> 2019 | CC5: =BW5+1 -> 2020 | CG5: =CC5 -> 2020 | CI5: =CC5+1 -> 2021 | CM5: =CI5 -> 2021
C6: 39082 | D6: 39172 | E6: 39263 | F6: 39355 | I6: =F6+FLOOR(365/4,1)+1 -> 39447 | J6: =D6+365+1 -> 39538 | K6: =J6+FLOOR(365/4,1) -> 39629 | L6: =K6+FLOOR(365/4,1)+1 -> 39721 | O6: =L6+FLOOR(365/4,1)+1 -> 39813 | P6: =J6+365 -> 39903 | Q6: =P6+FLOOR(365/4,1) -> 39994 | R6: =Q6+FLOOR(365/4,1)+1 -> 40086 | U6: =R6+FLOOR(365/4,1)+1 -> 40178 | V6: =P6+365 -> 40268 | W6: =V6+FLOOR(365/4,1) -> 40359 | X6: =W6+FLOOR(365/4,1)+1 -> 40451 | AA6: =X6+FLOOR(365/4,1)+1 -> 40543 | AB6: =V6+365 -> 40633 | AC6: =AB6+FLOOR(365/4,1) -> 40724 | AD6: =AC6+FLOOR(365/4,1)+1 -> 40816 | AG6: =AD6+FLOOR(365/4,1)+1 -> 40908 | AH6: =AB6+365+1 -> 40999 | AI6: =AH6+FLOOR(365/4,1) -> 41090 | AJ6: =AI6+FLOOR(365/4,1)+1 -> 41182 | AM6: =AJ6+FLOOR(365/4,1)+1 -> 41274 | AN6: =AH6+365 -> 41364 | AO6: =AN6+FLOOR(365/4,1) -> 41455 | AP6: =AO6+FLOOR(365/4,1)+1 -> 41547 | AS6: =AP6+FLOOR(365/4,1)+1 -> 41639 | AT6: =AN6+365 -> 41729 | AU6: =AT6+FLOOR(365/4,1) -> 41820 | AV6: =AU6+FLOOR(365/4,1)+1 -> 41912 | AY6: =AV6+FLOOR(365/4,1)+1 -> 42004 | AZ6: =AT6+365 -> 42094 | BA6: =AZ6+FLOOR(365/4,1) -> 42185 | BB6: =BA6+FLOOR(365/4,1)+1 -> 42277 | BE6: =BB6+FLOOR(365/4,1)+1 -> 42369 | BF6: =AZ6+365+1 -> 42460 | BG6: =BF6+FLOOR(365/4,1) -> 42551 | BH6: =BG6+FLOOR(365/4,1)+1 -> 42643 | BK6: =BH6+FLOOR(365/4,1)+1 -> 42735 | BL6: =BF6+365 -> 42825 | BM6: =BL6+FLOOR(365/4,1) -> 42916 | BN6: =BM6+FLOOR(365/4,1)+1 -> 43008 | BQ6: =BN6+FLOOR(365/4,1)+1 -> 43100 | BR6: =BL6+365 -> 43190 | BS6: =BR6+FLOOR(365/4,1) -> 43281 | BT6: =BS6+FLOOR(365/4,1)+1 -> 43373 | BW6: =BT6+FLOOR(365/4,1)+1 -> 43465 | BX6: =BR6+365 -> 43555 | BY6: =BX6+FLOOR(365/4,1) -> 43646 | BZ6: =BY6+FLOOR(365/4,1)+1 -> 43738 | CC6: =BZ6+FLOOR(365/4,1)+1 -> 43830 | CD6: =BX6+365+1 -> 43921 | CE6: =CD6+FLOOR(365/4,1) -> 44012 | CF6: =CE6+FLOOR(365/4,1)+1 -> 44104 | CI6: =CF6+FLOOR(365/4,1)+1 -> 44196 | CJ6: =CD6+365 -> 44286 | CK6: =CJ6+FLOOR(365/4,1) -> 44377 | CL6: =CK6+FLOOR(365/4,1)+1 -> 44469
A7: Revenue | C7: 1501.534 | D7: 1575.922 | E7: 1631.159 | F7: 1651.101 | G7: 6359.716 | I7: 1705.767 | J7: 1746.925 | K7: 1867.588 | L7: 1835.631 | M7: 7155.911 | O7: 1673.148 | P7: 1683.142 | Q7: 1776.409 | R7: 1854.023 | S7: =SUM(O7:R7) -> 6986.722 | U7: 1868.818 | V7: 1799.409 | W7: 1830.911 | X7: 1873.195 | Y7: =SUM(U7:X7) -> 7372.333 | AA7: 1783.3537 | AB7: 1860.614 | AC7: 1951.889 | AD7: 1988.181 | AE7: =SUM(AA7:AD7) -> 7584.0377 | AG7: 1831.72 | AH7: 1928.961 | AI7: 1980.53 | AJ7: 1967.171 | AK7: =SUM(AG7:AJ7) -> 7708.382 | AM7: 1900.192 | AN7: 2000.375 | AO7: 2052.664 | AP7: 2100 | AQ7: =SUM(AM7:AP7) -> 8053.231 | AS7: 2014.9 | AT7: 2072 | AU7: 2156.8 | AV7: 2201.99 | AW7: =SUM(AS7:AV7) -> 8445.69 | AY7: 2051.14 | AZ7: 2050.45 | BA7: 3133 | BB7: 3067 | BC7: =SUM(AY7:BB7) -> 10301.59 | BE7: 2992.24 | BF7: 3071 | BG7: 3200 | BH7: 3234 | BI7: =SUM(BE7:BH7) -> 12497.24 | BK7: 2922 | BL7: 2969 | BM7: 3035 | BN7: 3166.49 | BO7: =SUM(BK7:BN7) -> 12092.49 | BQ7: 3080 | BR7: =BDX!BR69 -> 4160.551 | BS7: =BDX!BS69 -> 4300.105 | BT7: =BDX!BT69 -> 4359.769 | BU7: =SUM(BQ7:BT7) -> 15900.425 | BW7: =BDX!BW69 -> 4322.2334 | BX7: =BDX!BX69 -> 4385.98 | BY7: =BDX!BY69 -> 4527.9818 | BZ7: =BDX!BZ69 -> 4590.2554 | CA7: =SUM(BW7:BZ7) -> 17826.451 | CC7: =BDX!CC69 -> 4552.9028 | CD7: =BDX!CD69 -> 4618.0674 | CE7: =BDX!CE69 -> 4769.8669 | CF7: =BDX!CF69 -> 4834.8831 | CG7: =SUM(CC7:CF7) -> 18775.72 | CI7: =BDX!CI69 -> 4797.2495 | CJ7: =BDX!CJ69 -> 4863.7671 | CK7: =BDX!CK69 -> 5026.0855 | CL7: =BDX!CL69 -> 5093.9644 | CM7: =SUM(CI7:CL7) -> 19781.067
A8: COGS | AM8: 894.063 | AN8: 982.256 | AO8: 992.673 | AP8: 1014 | AQ8: =SUM(AM8:AP8) -> 3882.992 | AS8: 980 | AT8: 1019 | AU8: 1046 | AV8: 1079 | AW8: =SUM(AS8:AV8) -> 4124 | AY8: =AY9+AY10 -> 1005.6 | AZ8: =AZ9+AZ10 -> 1005.6 | BA8: =BA9+BA10 -> 1641.2 | BB8: =BB9+BB10 -> 1597.6 | BC8: =SUM(AY8:BB8) -> 5250 | BE8: =BE9+BE10 -> 1562.8 | BF8: =BF9+BF10 -> 1569.95 | BG8: =BG9+BG10 -> 1635.7 | BH8: =BH9+BH10 -> 1661.1 | BI8: =SUM(BE8:BH8) -> 6429.55 | BK8: =BK9+BK10 -> 1458.3 | BL8: =BL9+BL10 -> 1523.9 | BM8: =BM9+BM10 -> 1518.8 | BN8: =BN9+BN10 -> 1600.7 | BO8: =SUM(BK8:BN8) -> 6101.7 | BQ8: =BQ9+BQ10 -> 1512.5 | BR8: =BR9+BR10 -> 2016.9441 | BS8: =BS9+BS10 -> 2043.2493 | BT8: =BT9+BT10 -> 2060.0063 | BU8: =SUM(BQ8:BT8) -> 7632.6997 | BW8: =BW9+BW10 -> 2044.0537 | BX8: =BX9+BX10 -> 2066.76 | BY8: =BY9+BY10 -> 2131.4967 | BZ8: =BZ9+BZ10 -> 2148.7825 | CA8: =SUM(BW8:BZ8) -> 8391.0929 | CC8: =CC9+CC10 -> 2101.112 | CD8: =CD9+CD10 -> 2123.6024 | CE8: =CE9+CE10 -> 2191.3691 | CF8: =CF9+CF10 -> 2208.7461 | CG8: =SUM(CC8:CF8) -> 8624.8296 | CI8: =CI9+CI10 -> 2178.774 | CJ8: =CJ9+CJ10 -> 2235.2953 | CK8: =CK9+CK10 -> 2252.7213 | CL8: =CL9+CL10 -> 2270.16 | CM8: =SUM(CI8:CL8) -> 8936.9507
A9: Amortization of Intangibles | AM9: =CFS!AM13*0.925 -> 17.870075 | AN9: =CFS!AN13*0.925 -> 19.8875 | AO9: =CFS!AO13*0.925 -> 19.94115 | AP9: =CFS!AP13*0.925 -> 19.076275 | AQ9: =SUM(AM9:AP9) -> 76.775 | AS9: =CFS!AS13*0.88 -> 18.48 | AT9: =CFS!AT13*0.88 -> 18.48 | AU9: =CFS!AU13*0.88 -> 18.48 | AV9: =CFS!AV13*0.88 -> 18.92 | AW9: =SUM(AS9:AV9) -> 74.36 | AY9: =CFS!AY13*0.88 -> 17.6 | AZ9: =CFS!AZ13*0.88 -> 17.6 | BA9: =CFS!BA13*0.9 -> 136.8 | BB9: =CFS!BB13*0.9 -> 138.6 | BC9: =SUM(AY9:BB9) -> 310.6 | BE9: =CFS!BE13*0.9 -> 136.8 | BF9: =CFS!BF13*0.9 -> 124.2 | BG9: =CFS!BG13*0.9 -> 119.7 | BH9: =CFS!BH13*0.9 -> 116.1 | BI9: =SUM(BE9:BH9) -> 496.8 | BK9: =CFS!BK13*0.9 -> 123.3 | BL9: =CFS!BL13*0.9 -> 117.9 | BM9: =CFS!BM13*0.9 -> 118.8 | BN9: =CFS!BN13*0.9 -> 119.7 | BO9: =SUM(BK9:BN9) -> 479.7 | BQ9: =CFS!BQ13*0.9 -> 121.5 | BR9: =CFS!BR13*0.9 -> 207.10446 | BS9: =CFS!BS13*0.9 -> 207.10446 | BT9: =CFS!BT13*0.9 -> 207.10446 | BU9: =SUM(BQ9:BT9) -> 742.81339 | BW9: =CFS!BW13*0.9 -> 207.10446 | BX9: =CFS!BX13*0.9 -> 207.10446 | BY9: =CFS!BY13*0.9 -> 207.10446 | BZ9: =CFS!BZ13*0.9 -> 207.10446 | CA9: =SUM(BW9:BZ9) -> 828.41786 | CC9: =CFS!CC13*0.9 -> 207.10446 | CD9: =CFS!CD13*0.9 -> 207.10446 | CE9: =CFS!CE13*0.9 -> 207.10446 | CF9: =CFS!CF13*0.9 -> 207.10446 | CG9: =SUM(CC9:CF9) -> 828.41786 | CI9: =CFS!CI13*0.9 -> 207.10446 | CJ9: =CFS!CJ13*0.9 -> 207.10446 | CK9: =CFS!CK13*0.9 -> 207.10446 | CL9: =CFS!CL13*0.9 -> 207.10446 | CM9: =SUM(CI9:CL9) -> 828.41786
A10: Adj COGS | C10: 708.933 | D10: 764.54 | E10: 791.071 | F10: 807.377 | G10: =SUM(C10:F10) -> 3071.921 | I10: 829.846 | J10: 853.807 | K10: 917.362 | L10: 891.546 | M10: =SUM(I10:L10) -> 3492.561 | O10: 775.542 | P10: 807.382 | Q10: 838.555 | R10: 890.197 | S10: =SUM(O10:R10) -> 3311.676 | U10: 894.324 | V10: 864.492 | W10: 883.434 | X10: 900.933 | Y10: =SUM(U10:X10) -> 3543.183 | AA10: 840.166 | AB10: 891.262 | AC10: 922.652 | AD10: 971.041 | AE10: =AE7-AE11 -> 3625.121 | AG10: 900.465 | AH10: 941.184 | AI10: 947.395 | AJ10: =966.345-10 -> 956.345 | AK10: =AK7-AK11 -> 3745.389 | AM10: =AM8-AM9 -> 876.19292 | AN10: =AN8-AN9 -> 962.3685 | AO10: =AO8-AO9 -> 972.73185 | AP10: =AP8-AP9 -> 994.92372 | AQ10: =AQ8-AQ9 -> 3806.217 | AS10: =AS8-AS9 -> 961.52 | AT10: =AT8-AT9 -> 1000.52 | AU10: =AU8-AU9 -> 1027.52 | AV10: =AV8-AV9 -> 1060.08 | AW10: =AW7-AW11 -> 4049.64 | AY10: 988 | AZ10: =2051-1063 -> 988 | BA10: =1932+13-444+3+0.4 -> 1504.4 | BB10: =1630-178+7 -> 1459 | BC10: =BC7-BC11 -> 4939.4 | BE10: =2992-1566 -> 1426 | BF10: 1445.75 | BG10: =3200-1684 -> 1516 | BH10: =3234-1689 -> 1545 | BI10: =BI7-BI11 -> 5932.75 | BK10: =2922-1587 -> 1335 | BL10: =2969-1563 -> 1406 | BM10: =3035-1635 -> 1400 | BN10: 1481 | BO10: =BO7-BO11 -> 5622 | BQ10: =1530-133-6 -> 1391 | BR10: =BR7-BR11 -> 1809.8397 | BS10: =BS7-BS11 -> 1836.1448 | BT10: =BT7-BT11 -> 1852.9018 | BU10: =BU7-BU11 -> 6889.8863 | BW10: =BW7-BW11 -> 1836.9492 | BX10: =BX7-BX11 -> 1859.6555 | BY10: =BY7-BY11 -> 1924.3923 | BZ10: =BZ7-BZ11 -> 1941.678 | CA10: =CA7-CA11 -> 7562.675 | CC10: =CC7-CC11 -> 1894.0076 | CD10: =CD7-CD11 -> 1916.498 | CE10: =CE7-CE11 -> 1984.2646 | CF10: =CF7-CF11 -> 2001.6416 | CG10: =CG7-CG11 -> 7796.4118 | CI10: =CI7-CI11 -> 1971.6696 | CJ10: =CJ7-CJ11 -> 2028.1909 | CK10: =CK7-CK11 -> 2045.6168 | CL10: =CL7-CL11 -> 2063.0556 | CM10: =CM7-CM11 -> 8108.5328
A11: Gross Profit | C11: =C7-C10 -> 792.601 | D11: =D7-D10 -> 811.382 | E11: =E7-E10 -> 840.088 | F11: =F7-F10 -> 843.724 | G11: =G7-G10 -> 3287.795 | I11: =I7-I10 -> 875.921 | J11: =J7-J10 -> 893.118 | K11: =K7-K10 -> 950.226 | L11: =L7-L10 -> 944.085 | M11: =SUM(I11:L11) -> 3663.35 | O11: =O7-O10 -> 897.606 | P11: =P7-P10 -> 875.76 | Q11: =Q7-Q10 -> 937.854 | R11: =R7-R10 -> 963.826 | S11: =SUM(O11:R11) -> 3675.046 | U11: =U7-U10 -> 974.494 | V11: =V7-V10 -> 934.917 | W11: =W7-W10 -> 947.477 | X11: =X7-X10 -> 972.262 | Y11: =SUM(U11:X11) -> 3829.15 | AA11: =AA7-AA10 -> 943.1877 | AB11: =AB7-AB10 -> 969.352 | AC11: =AC7-AC10 -> 1029.237 | AD11: =AD7-AD10 -> 1017.14 | AE11: =SUM(AA11:AD11) -> 3958.9167 | AG11: =AG7-AG10 -> 931.255 | AH11: =AH7-AH10 -> 987.777 | AI11: =AI7-AI10 -> 1033.135 | AJ11: =AJ7-AJ10 -> 1010.826 | AK11: =SUM(AG11:AJ11) -> 3962.993 | AM11: =AM7-AM10 -> 1023.9991 | AN11: =AN7-AN10 -> 1038.0065 | AO11: =AO7-AO10 -> 1079.9321 | AP11: =AP7-AP10 -> 1105.0763 | AQ11: =SUM(AM11:AP11) -> 4247.014 | AS11: =AS7-AS10 -> 1053.38 | AT11: =AT7-AT10 -> 1071.48 | AU11: =AU7-AU10 -> 1129.28 | AV11: =AV7-AV10 -> 1141.91 | AW11: =SUM(AS11:AV11) -> 4396.05 | AY11: =AY7-AY10 -> 1063.14 | AZ11: =AZ7-AZ10 -> 1062.45 | BA11: =BA7-BA10 -> 1628.6 | BB11: =BB7-BB10 -> 1608 | BC11: =SUM(AY11:BB11) -> 5362.19 | BE11: =BE7-BE10 -> 1566.24 | BF11: =BF7-BF10 -> 1625.25 | BG11: =BG7-BG10 -> 1684 | BH11: =BH7-BH10 -> 1689 | BI11: =SUM(BE11:BH11) -> 6564.49 | BK11: =BK7-BK10 -> 1587 | BL11: =BL7-BL10 -> 1563 | BM11: =BM7-BM10 -> 1635 | BN11: =BN7-BN10 -> 1685.49 | BO11: =SUM(BK11:BN11) -> 6470.49 | BQ11: =BQ7-BQ10 -> 1689 | BR11: =BR7*BR37 -> 2350.7113 | BS11: =BS7*BS37 -> 2463.9602 | BT11: =BT7*BT37 -> 2506.8672 | BU11: =SUM(BQ11:BT11) -> 9010.5387 | BW11: =BW7*BW37 -> 2485.2842 | BX11: =BX7*BX37 -> 2526.3245 | BY11: =BY7*BY37 -> 2603.5896 | BZ11: =BZ7*BZ37 -> 2648.5774 | CA11: =SUM(BW11:BZ11) -> 10263.776 | CC11: =CC7*CC37 -> 2658.8953 | CD11: =CD7*CD37 -> 2701.5694 | CE11: =CE7*CE37 -> 2785.6022 | CF11: =CF7*CF37 -> 2833.2415 | CG11: =SUM(CC11:CF11) -> 10979.308 | CI11: =CI7*CI37 -> 2825.58 | CJ11: =CJ7*CJ37 -> 2835.5762 | CK11: =CK7*CK37 -> 2980.4687 | CL11: =CL7*CL37 -> 3030.9088 | CM11: =SUM(CI11:CL11) -> 11672.534
A12: Adj SG&A | C12: 384.084 | D12: 406.631 | E12: 412.164 | F12: 399.525 | G12: =SUM(C12:F12) -> 1602.404 | I12: =421.718 -> 421.718 | J12: 415.523 | K12: 440.588 | L12: 437.216 | M12: =SUM(I12:L12) -> 1715.045 | O12: 399.668 | P12: 430.608 | Q12: 423.513 | R12: 427.008 | S12: =SUM(O12:R12) -> 1680.797 | U12: 445.673 | V12: 421.076 | W12: 416.468 | X12: 438.139 | Y12: =SUM(U12:X12) -> 1721.356 | AA12: 440.955 | AB12: 435.024 | AC12: 467.968 | AD12: 479.591 | AE12: =SUM(AA12:AD12) -> 1823.538 | AG12: 482.271 | AH12: 487.694 | AI12: 469.13 | AJ12: =484.259-8 -> 476.259 | AK12: =SUM(AG12:AJ12) -> 1915.354 | AM12: 495.878 | AN12: =514.61 -> 514.61 | AO12: =534.32-22 -> 512.32 | AP12: =877-341-6 -> 530 | AQ12: =SUM(AM12:AP12) -> 2052.808 | AS12: =531 -> 531 | AT12: =525-11 -> 514 | AU12: 528 | AV12: 542 | AW12: =SUM(AS12:AV12) -> 2115 | AY12: 532 | AZ12: 511 | BA12: =764-3+0.4 -> 761.4 | BB12: =756-9 -> 747 | BC12: =SUM(AY12:BB12) -> 2551.4 | BE12: 745 | BF12: 750.75 | BG12: 728 | BH12: 789 | BI12: =SUM(BE12:BH12) -> 3012.75 | BK12: 711 | BL12: 721 | BM12: 719 | BN12: 774 | BO12: =SUM(BK12:BN12) -> 2925 | BQ12: =774-1-1 -> 772 | BR12: =BR13+BR14 -> 1027.6561 | BS12: =BS13+BS14 -> 1023.425 | BT12: =BT13+BT14 -> 1068.1434 | BU12: =SUM(BQ12:BT12) -> 3891.2245 | BW12: =BW13+BW14 -> 1037.336 | BX12: =BX13+BX14 -> 1039.4773 | BY12: =BY13+BY14 -> 1064.0757 | BZ12: =BZ13+BZ14 -> 1092.4808 | CA12: =SUM(BW12:BZ12) -> 4233.3698 | CC12: =CC13+CC14 -> 1047.1677 | CD12: =CD13+CD14 -> 1048.3013 | CE12: =CE13+CE14 -> 1073.22 | CF12: =CF13+CF14 -> 1102.3534 | CG12: =SUM(CC12:CF12) -> 4271.0424 | CI12: =CI13+CI14 -> 1074.5839 | CJ12: =CJ13+CJ14 -> 1074.8925 | CK12: =CK13+CK14 -> 1100.7127 | CL12: =CL13+CL14 -> 1130.8601 | CM12: =SUM(CI12:CL12) -> 4381.0492
A13: Core SG&A | C13: =C12-C14 -> 384.084 | D13: =D12-D14 -> 406.631 | E13: =E12-E14 -> 412.164 | F13: =F12-F14 -> 399.525 | G13: =SUM(C13:F13) -> 1602.404 | I13: =I12-I14 -> 421.718 | J13: =J12-J14 -> 415.523 | K13: =K12-K14 -> 440.588 | L13: =L12-L14 -> 437.216 | M13: =SUM(I13:L13) -> 1715.045 | O13: =O12-O14 -> 399.668 | P13: =P12-P14 -> 430.608 | Q13: =Q12-Q14 -> 423.513 | R13: =R12-R14 -> 427.008 | S13: =SUM(O13:R13) -> 1680.797 | U13: =U12-U14 -> 445.673 | V13: =V12-V14 -> 421.076 | W13: =W12-W14 -> 416.468 | X13: =X12-X14 -> 438.139 | Y13: =SUM(U13:X13) -> 1721.356 | AA13: =AA12-AA14 -> 440.955 | AB13: =AB12-AB14 -> 435.024 | AC13: =AC12-AC14 -> 467.968 | AD13: =AD12-AD14 -> 479.591 | AE13: =SUM(AA13:AD13) -> 1823.538 | AG13: =AG12-AG14 -> 482.271 | AH13: =AH12-AH14 -> 487.694 | AI13: =AI12-AI14 -> 469.13 | AJ13: =AJ12-AJ14 -> 476.259 | AK13: =SUM(AG13:AJ13) -> 1915.354 | AM13: =AM12-AM14 -> 495.878 | AN13: =AN12-AN14 -> 500.60737 | AO13: =AO12-AO14 -> 497.95135 | AP13: =AP12-AP14 -> 516.98 | AQ13: =SUM(AM13:AP13) -> 2011.4167 | AS13: =AS12-AS14 -> 518.50762 | AT13: =AT12-AT14 -> 499.496 | AU13: =AU12-AU14 -> 512.9024 | AV13: =AV12-AV14 -> 526.58607 | AW13: =SUM(AS13:AV13) -> 2057.4921 | AY13: =AY12-AY14 -> 519.28293 | AZ13: =AZ12-AZ14 -> 498.6973 | BA13: =BA12-BA14 -> 742.602 | BB13: =BB12-BB14 -> 728.598 | BC13: =SUM(AY13:BB13) -> 2489.1802 | BE13: =BE12-BE14 -> 745 | BF13: =BF12-BF14 -> 750.75 | BG13: =BG12-BG14 -> 728 | BH13: =BH12-BH14 -> 789 | BI13: =SUM(BE13:BH13) -> 3012.75 | BK13: =+BK12-BK14 -> 711 | BL13: =BL12-BL14 -> 721 | BM13: =BM12-BM14 -> 719 | BN13: =BN12-BN14 -> 774 | BO13: =SUM(BK13:BN13) -> 2925 | BQ13: =+BQ12-BQ14 -> 772 | BR13: =BR7*BR39 -> 1027.6561 | BS13: =BS7*BS39 -> 1023.425 | BT13: =BT7*BT39 -> 1068.1434 | BU13: =SUM(BQ13:BT13) -> 3891.2245 | BW13: =BW7*BW39 -> 1037.336 | BX13: =BX7*BX39 -> 1039.4773 | BY13: =BY7*BY39 -> 1064.0757 | BZ13: =BZ7*BZ39 -> 1092.4808 | CA13: =SUM(BW13:BZ13) -> 4233.3698 | CC13: =CC7*CC39 -> 1047.1677 | CD13: =CD7*CD39 -> 1048.3013 | CE13: =CE7*CE39 -> 1073.22 | CF13: =CF7*CF39 -> 1102.3534 | CG13: =SUM(CC13:CF13) -> 4271.0424 | CI13: =CI7*CI39 -> 1074.5839 | CJ13: =CJ7*CJ39 -> 1074.8925 | CK13: =CK7*CK39 -> 1100.7127 | CL13: =CL7*CL39 -> 1130.8601 | CM13: =SUM(CI13:CL13) -> 4381.0492
A14: Medtech Tax | C14: 0 | D14: 0 | E14: 0 | F14: 0 | G14: =SUM(C14:F14) -> 0 | I14: 0 | J14: 0 | K14: 0 | L14: 0 | M14: =SUM(I14:L14) -> 0 | O14: 0 | P14: 0 | Q14: 0 | R14: 0 | S14: =SUM(O14:R14) -> 0 | U14: 0 | V14: 0 | W14: 0 | X14: 0 | Y14: =SUM(U14:X14) -> 0 | AA14: 0 | AB14: 0 | AC14: 0 | AD14: 0 | AE14: =SUM(AA14:AD14) -> 0 | AG14: 0 | AH14: 0 | AI14: 0 | AJ14: 0 | AK14: =SUM(AG14:AJ14) -> 0 | AM14: 0 | AN14: =AN7*AN40 -> 14.002625 | AO14: =AO7*AO40 -> 14.368648 | AP14: =AP7*AP40 -> 13.02 | AQ14: =SUM(AM14:AP14) -> 41.391273 | AS14: =AS7*AS40 -> 12.49238 | AT14: =AT7*AT40 -> 14.504 | AU14: =AU7*AU40 -> 15.0976 | AV14: =AV7*AV40 -> 15.41393 | AW14: =SUM(AS14:AV14) -> 57.50791 | AY14: =AY7*AY40 -> 12.717068 | AZ14: =AZ7*AZ40 -> 12.3027 | BA14: =BA7*BA40 -> 18.798 | BB14: =BB7*BB40 -> 18.402 | BC14: =SUM(AY14:BB14) -> 62.219768 | BE14: =BE7*BE40 -> 0 | BF14: =BF7*BF40 -> 0 | BG14: =BG7*BG40 -> 0 | BH14: =BH7*BH40 -> 0 | BI14: =SUM(BE14:BH14) -> 0 | BK14: =BK7*BK40 -> 0 | BL14: =BL7*BL40 -> 0 | BM14: =BM7*BM40 -> 0 | BN14: =BN7*BN40 -> 0 | BO14: =SUM(BK14:BN14) -> 0 | BQ14: =BQ7*BQ40 -> 0 | BR14: =BR7*BR40 -> 0 | BS14: =BS7*BS40 -> 0 | BT14: =BT7*BT40 -> 0 | BU14: =SUM(BQ14:BT14) -> 0 | BW14: =BW7*BW40 -> 0 | BX14: =BX7*BX40 -> 0 | BY14: =BY7*BY40 -> 0 | BZ14: =BZ7*BZ40 -> 0 | CA14: =SUM(BW14:BZ14) -> 0 | CC14: =CC7*CC40 -> 0 | CD14: =CD7*CD40 -> 0 | CE14: =CE7*CE40 -> 0 | CF14: =CF7*CF40 -> 0 | CG14: =SUM(CC14:CF14) -> 0 | CI14: =CI7*CI40 -> 0 | CJ14: =CJ7*CJ40 -> 0 | CK14: =CK7*CK40 -> 0 | CL14: =CL7*CL40 -> 0 | CM14: =SUM(CI14:CL14) -> 0
A15: R&D | C15: 79.94 | D15: 86.687 | E15: 92.993 | F15: 100.43 | G15: =SUM(C15:F15) -> 360.05 | I15: 91.527 | J15: 96.034 | K15: 100.071 | L15: 108.606 | M15: =SUM(I15:L15) -> 396.238 | O15: 96.356 | P15: 97.7 | Q15: 97.621 | R15: 112.89 | S15: =SUM(O15:R15) -> 404.567 | U15: 99.151 | V15: 100.193 | W15: 108.047 | X15: 123.606 | Y15: =SUM(U15:X15) -> 430.997 | AA15: 113.568 | AB15: 117.343 | AC15: 114.078 | AD15: =124.528-9.27 -> 115.258 | AE15: =SUM(AA15:AD15) -> 460.247 | AG15: 112.227 | AH15: 116.753 | AI15: 114.987 | AJ15: =127.787-2 -> 125.787 | AK15: =SUM(AG15:AJ15) -> 469.754 | AM15: 118.162 | AN15: 122.377 | AO15: 121.116 | AP15: 133 | AQ15: =SUM(AM15:AP15) -> 494.655 | AS15: 126 | AT15: =147-20 -> 127 | AU15: 128 | AV15: 133 | AW15: =SUM(AS15:AV15) -> 514 | AY15: 129 | AZ15: 129 | BA15: =178+2+0.1 -> 180.1 | BB15: 196 | BC15: =SUM(AY15:BB15) -> 634.1 | BE15: 187 | BF15: 181.75 | BG15: 207 | BH15: 253 | BI15: =SUM(BE15:BH15) -> 828.75 | BK15: 182 | BL15: 187 | BM15: =186-1 -> 185 | BN15: 221 | BO15: =SUM(BK15:BN15) -> 775 | BQ15: 192 | BR15: =BR7*BR41 -> 270.43581 | BS15: =BS7*BS41 -> 283.80693 | BT15: =BT7*BT41 -> 296.46429 | BU15: =SUM(BQ15:BT15) -> 1042.707 | BW15: =BW7*BW41 -> 289.58964 | BX15: =BX7*BX41 -> 289.47468 | BY15: =BY7*BY41 -> 298.8468 | BZ15: =BZ7*BZ41 -> 302.95686 | CA15: =SUM(BW15:BZ15) -> 1180.868 | CC15: =CC7*CC41 -> 291.38578 | CD15: =CD7*CD41 -> 290.93825 | CE15: =CE7*CE41 -> 300.50161 | CF15: =CF7*CF41 -> 304.59764 | CG15: =SUM(CC15:CF15) -> 1187.4233 | CI15: =CI7*CI41 -> 299.8281 | CJ15: =CJ7*CJ41 -> 299.12167 | CK15: =CK7*CK41 -> 309.10426 | CL15: =CL7*CL41 -> 313.27881 | CM15: =SUM(CI15:CL15) -> 1221.3328
A16: Total Operating Expenses | C16: =C12+C15 -> 464.024 | D16: =D12+D15 -> 493.318 | E16: =E12+E15 -> 505.157 | F16: =F12+F15 -> 499.955 | G16: =G12+G15 -> 1962.454 | I16: =I12+I15 -> 513.245 | J16: =J12+J15 -> 511.557 | K16: =K12+K15 -> 540.659 | L16: =L12+L15 -> 545.822 | M16: =M12+M15 -> 2111.283 | O16: =O12+O15 -> 496.024 | P16: =P12+P15 -> 528.308 | Q16: =Q12+Q15 -> 521.134 | R16: =R12+R15 -> 539.898 | S16: =S12+S15 -> 2085.364 | U16: =U12+U15 -> 544.824 | V16: =V12+V15 -> 521.269 | W16: =W12+W15 -> 524.515 | X16: =X12+X15 -> 561.745 | Y16: =Y12+Y15 -> 2152.353 | AA16: =AA12+AA15 -> 554.523 | AB16: =AB12+AB15 -> 552.367 | AC16: =AC12+AC15 -> 582.046 | AD16: =AD12+AD15 -> 594.849 | AE16: =AE12+AE15 -> 2283.785 | AG16: =AG12+AG15 -> 594.498 | AH16: =AH12+AH15 -> 604.447 | AI16: =AI12+AI15 -> 584.117 | AJ16: =AJ12+AJ15 -> 602.046 | AK16: =AK12+AK15 -> 2385.108 | AM16: =AM12+AM15 -> 614.04 | AN16: =AN12+AN15 -> 636.987 | AO16: =AO12+AO15 -> 633.436 | AP16: =AP12+AP15 -> 663 | AQ16: =AQ12+AQ15 -> 2547.463 | AS16: =AS12+AS15 -> 657 | AT16: =AT12+AT15 -> 641 | AU16: =AU12+AU15 -> 656 | AV16: =AV12+AV15 -> 675 | AW16: =AW12+AW15 -> 2629 | AY16: =AY12+AY15 -> 661 | AZ16: =AZ12+AZ15 -> 640 | BA16: =BA12+BA15 -> 941.5 | BB16: =BB12+BB15 -> 943 | BC16: =BC12+BC15 -> 3185.5 | BE16: =BE12+BE15 -> 932 | BF16: =BF12+BF15 -> 932.5 | BG16: =BG12+BG15 -> 935 | BH16: =BH12+BH15 -> 1042 | BI16: =BI12+BI15 -> 3841.5 | BK16: =BK12+BK15 -> 893 | BL16: =BL12+BL15 -> 908 | BM16: =BM12+BM15 -> 904 | BN16: =BN12+BN15 -> 995 | BO16: =BO12+BO15 -> 3700 | BQ16: =BQ12+BQ15 -> 964 | BR16: =BR12+BR15 -> 1298.0919 | BS16: =BS12+BS15 -> 1307.2319 | BT16: =BT12+BT15 -> 1364.6077 | BU16: =BU12+BU15 -> 4933.9315 | BW16: =BW12+BW15 -> 1326.9257 | BX16: =BX12+BX15 -> 1328.9519 | BY16: =BY12+BY15 -> 1362.9225 | BZ16: =BZ12+BZ15 -> 1395.4376 | CA16: =CA12+CA15 -> 5414.2378 | CC16: =CC12+CC15 -> 1338.5534 | CD16: =CD12+CD15 -> 1339.2395 | CE16: =CE12+CE15 -> 1373.7217 | CF16: =CF12+CF15 -> 1406.951 | CG16: =CG12+CG15 -> 5458.4656 | CI16: =CI12+CI15 -> 1374.412 | CJ16: =CJ12+CJ15 -> 1374.0142 | CK16: =CK12+CK15 -> 1409.817 | CL16: =CL12+CL15 -> 1444.1389 | CM16: =CM12+CM15 -> 5602.3821
A17: Operating Income | C17: =C11-C12-C15 -> 328.577 | D17: =D11-D12-D15 -> 318.064 | E17: =E11-E12-E15 -> 334.931 | F17: =F11-F12-F15 -> 343.769 | G17: =G11-G12-G15 -> 1325.341 | I17: =I11-I12-I15 -> 362.676 | J17: =J11-J12-J15 -> 381.561 | K17: =K11-K12-K15 -> 409.567 | L17: =L11-L12-L15 -> 398.263 | M17: =M11-M12-M15 -> 1552.067 | O17: =O11-O12-O15 -> 401.582 | P17: =P11-P12-P15 -> 347.452 | Q17: =Q11-Q12-Q15 -> 416.72 | R17: =R11-R12-R15 -> 423.928 | S17: =S11-S12-S15 -> 1589.682 | U17: =U11-U12-U15 -> 429.67 | V17: =V11-V12-V15 -> 413.648 | W17: =W11-W12-W15 -> 422.962 | X17: =X11-X12-X15 -> 410.517 | Y17: =Y11-Y12-Y15 -> 1676.797 | AA17: =AA11-AA12-AA15 -> 388.6647 | AB17: =AB11-AB12-AB15 -> 416.985 | AC17: =AC11-AC12-AC15 -> 447.191 | AD17: =AD11-AD12-AD15 -> 422.291 | AE17: =AE11-AE12-AE15 -> 1675.1317 | AG17: =AG11-AG12-AG15 -> 336.757 | AH17: =AH11-AH12-AH15 -> 383.33 | AI17: =AI11-AI12-AI15 -> 449.018 | AJ17: =AJ11-AJ12-AJ15 -> 408.78 | AK17: =SUM(AG17:AJ17) -> 1577.885 | AM17: =AM11-AM12-AM15 -> 409.95907 | AN17: =AN11-AN12-AN15 -> 401.0195 | AO17: =AO11-AO12-AO15 -> 446.49615 | AP17: =AP11-AP12-AP15 -> 442.07627 | AQ17: =SUM(AM17:AP17) -> 1699.551 | AS17: =AS11-AS12-AS15 -> 396.38 | AT17: =AT11-AT12-AT15 -> 430.48 | AU17: =AU11-AU12-AU15 -> 473.28 | AV17: =AV11-AV12-AV15 -> 466.91 | AW17: =SUM(AS17:AV17) -> 1767.05 | AY17: =AY11-AY12-AY15 -> 402.14 | AZ17: =AZ11-AZ12-AZ15 -> 422.45 | BA17: =BA11-BA12-BA15 -> 687.1 | BB17: =BB11-BB12-BB15 -> 665 | BC17: =SUM(AY17:BB17) -> 2176.69 | BE17: =BE11-BE12-BE15 -> 634.24 | BF17: =BF11-BF12-BF15 -> 692.75 | BG17: =BG11-BG12-BG15 -> 749 | BH17: =BH11-BH12-BH15 -> 647 | BI17: =SUM(BE17:BH17) -> 2722.99 | BK17: =BK11-BK12-BK15 -> 694 | BL17: =BL11-BL12-BL15 -> 655 | BM17: =BM11-BM12-BM15 -> 731 | BN17: =BN11-BN12-BN15 -> 690.49 | BO17: =SUM(BK17:BN17) -> 2770.49 | BQ17: =BQ11-BQ12-BQ15 -> 725 | BR17: =BR11-BR12-BR15 -> 1052.6194 | BS17: =BS11-BS12-BS15 -> 1156.7282 | BT17: =BT11-BT12-BT15 -> 1142.2595 | BU17: =SUM(BQ17:BT17) -> 4076.6071 | BW17: =BW11-BW12-BW15 -> 1158.3585 | BX17: =BX11-BX12-BX15 -> 1197.3725 | BY17: =BY11-BY12-BY15 -> 1240.667 | BZ17: =BZ11-BZ12-BZ15 -> 1253.1397 | CA17: =SUM(BW17:BZ17) -> 4849.5378 | CC17: =CC11-CC12-CC15 -> 1320.3418 | CD17: =CD11-CD12-CD15 -> 1362.3299 | CE17: =CE11-CE12-CE15 -> 1411.8806 | CF17: =CF11-CF12-CF15 -> 1426.2905 | CG17: =SUM(CC17:CF17) -> 5520.8428 | CI17: =CI11-CI12-CI15 -> 1451.168 | CJ17: =CJ11-CJ12-CJ15 -> 1461.562 | CK17: =CK11-CK12-CK15 -> 1570.6517 | CL17: =CL11-CL12-CL15 -> 1586.7699 | CM17: =SUM(CI17:CL17) -> 6070.1516
A18: EBITDA | C18: =CFS!C11+C17 -> 429.658 | D18: =CFS!D11+D17 -> 428.011 | E18: =CFS!E11+E17 -> 447.468 | F18: =CFS!F11+F17 -> 461.545 | G18: =SUM(C18:F18) -> 1766.682 | I18: =CFS!I11+I17 -> 477.888 | J18: =CFS!J11+J17 -> 498.408 | K18: =CFS!K11+K17 -> 530.621 | L18: =CFS!L11+L17 -> 522.572 | M18: =SUM(I18:L18) -> 2029.489 | O18: =CFS!O11+O17 -> 518.1 | P18: =CFS!P11+P17 -> 464.73 | Q18: =CFS!Q11+Q17 -> 535.17 | R18: =CFS!R11+R17 -> 541.875 | S18: =SUM(O18:R18) -> 2059.875 | U18: =CFS!U11+U17 -> 554.891 | V18: =CFS!V11+V17 -> 540.454 | W18: =CFS!W11+W17 -> 553.94 | X18: =CFS!X11+X17 -> 529.625 | Y18: =SUM(U18:X18) -> 2178.91 | AA18: =CFS!AA11+AA17 -> 511.8567 | AB18: =CFS!AB11+AB17 -> 539.19 | AC18: =CFS!AC11+AC17 -> 574.004 | AD18: =CFS!AD11+AD17 -> 554.17 | AE18: =SUM(AA18:AD18) -> 2179.2207 | AG18: =CFS!AG11+AG17 -> 472.375 | AH18: =CFS!AH11+AH17 -> 513.593 | AI18: =CFS!AI11+AI17 -> 566.696 | AJ18: =CFS!AJ11+AJ17 -> 536.159 | AK18: =SUM(AG18:AJ18) -> 2088.823 | AM18: =CFS!AM11+AM17 -> 538.79207 | AN18: =CFS!AN11+AN17 -> 537.6635 | AO18: =CFS!AO11+AO17 -> 584.70015 | AP18: =CFS!AP11+AP17 -> 584.39527 | AQ18: =SUM(AM18:AP18) -> 2245.551 | AS18: =CFS!AS11+AS17 -> 538.38 | AT18: =CFS!AT11+AT17 -> 560.48 | AU18: =CFS!AU11+AU17 -> 614.28 | AV18: =CFS!AV11+AV17 -> 616.41 | AW18: =SUM(AS18:AV18) -> 2329.55 | AY18: =CFS!AY12+AY17 -> 511.14 | AZ18: =CFS!AZ12+AZ17 -> 530.45 | BA18: =CFS!BA12+BA17 -> 811.6 | BB18: =CFS!BB12+BB17 -> 803.5 | BC18: =SUM(AY18:BB18) -> 2656.69 | BE18: =CFS!BE12+BE17 -> 771.24 | BF18: =CFS!BF12+BF17 -> 834.75 | BG18: =CFS!BG12+BG17 -> 888 | BH18: =CFS!BH12+BH17 -> 791 | BI18: =SUM(BE18:BH18) -> 3284.99 | BK18: =CFS!BK12+BK17 -> 819 | BL18: =CFS!BL12+BL17 -> 785 | BM18: =CFS!BM12+BM17 -> 878 | BN18: =CFS!BN12+BN17 -> 843.49 | BO18: =SUM(BK18:BN18) -> 3325.49 | BQ18: =CFS!BQ12+BQ17 -> 880 | BR18: =CFS!BR12+BR17 -> 1226.9125 | BS18: =CFS!BS12+BS17 -> 1334.9007 | BT18: =CFS!BT12+BT17 -> 1324.3112 | BU18: =SUM(BQ18:BT18) -> 4766.1244 | BW18: =CFS!BW12+BW17 -> 1344.2896 | BX18: =CFS!BX12+BX17 -> 1386.9243 | BY18: =CFS!BY12+BY17 -> 1433.8394 | BZ18: =CFS!BZ12+BZ17 -> 1449.9328 | CA18: =SUM(BW18:BZ18) -> 5614.9861 | CC18: =CFS!CC12+CC17 -> 1520.7556 | CD18: =CFS!CD12+CD17 -> 1566.3644 | CE18: =CFS!CE12+CE17 -> 1619.5358 | CF18: =CFS!CF12+CF17 -> 1637.5664 | CG18: =SUM(CC18:CF18) -> 6344.2221 | CI18: =CFS!CI12+CI17 -> 1666.0645 | CJ18: =CFS!CJ12+CJ17 -> 1680.0792 | CK18: =CFS!CK12+CK17 -> 1792.7897 | CL18: =CFS!CL12+CL17 -> 1812.5285 | CM18: =SUM(CI18:CL18) -> 6951.462
A19: Net Interest Income (Expense) | C19: =C21-C20 -> 3.246 | D19: =D21-D20 -> -2.6 | E19: =E21-E20 -> 0.34 | F19: =F21-F20 -> -1.185 | G19: =G21-G20 -> -0.199 | I19: =I21-I20 -> 3.189 | J19: =J21-J20 -> -0.093 | K19: =K21-K20 -> 1.939 | L19: =L21-L20 -> -2.01 | M19: =SUM(I19:L19) -> 3.025 | O19: =O21-O20 -> -6.173 | P19: =P21-P20 -> -3.183 | Q19: =Q21-Q20 -> 1.479 | R19: =R21-R20 -> 0.636 | S19: =SUM(O19:R19) -> -7.241 | U19: =U21-U20 -> -4.198 | V19: =V21-V20 -> -3.261 | W19: =W21-W20 -> -10.991 | X19: =X21-X20 -> 2.316 | Y19: =SUM(U19:X19) -> -16.134 | AA19: =AA21-AA20 -> -0.331 | AB19: =AB21-AB20 -> -9.357 | AC19: =AC21-AC20 -> -10.703 | AD19: =AD21-AD20 -> -20.419 | AE19: =SUM(AA19:AD19) -> -40.81 | AG19: =AG21-AG20 -> -13.93 | AH19: =AH21-AH20 -> -18.462 | AI19: =AI21-AI20 -> -28.596 | AJ19: =AJ21-AJ20 -> -23.338 | AK19: =SUM(AG19:AJ19) -> -84.326 | AM19: =AM21-AM20 -> -27.107 | AN19: =AN21-AN20 -> -22.914 | AO19: =AO21-AO20 -> -28.301 | AP19: =AP21-AP20 -> -20 | AQ19: =SUM(AM19:AP19) -> -98.322 | AS19: =AS21-AS20 -> -20 | AT19: =AT21-AT20 -> -23 | AU19: =AU21-AU20 -> -21 | AV19: =AV21-AV20 -> -26 | AW19: =SUM(AS19:AV19) -> -90 | AY19: =AY21-AY20 -> -22 | AZ19: =AZ21-AZ20 -> -25 | BA19: =BA21-BA20 -> -106 | BB19: =BB21-BB20 -> -112 | BC19: =SUM(AY19:BB19) -> -265 | BE19: =BE21-BE20 -> -99 | BF19: =BF21-BF20 -> -104 | BG19: =BG21-BG20 -> -100 | BH19: =BH21-BH20 -> -96 | BI19: =SUM(BE19:BH19) -> -399 | BK19: =BK21-BK20 -> -96 | BL19: =BL21-BL20 -> -83 | BM19: =BM21-BM20 -> -81 | BN19: =BN21-BN20 -> -68 | BO19: =SUM(BK19:BN19) -> -328 | BQ19: =BQ21-BQ20 -> -65 | BR19: =BR21-BR20 -> -185.25457 | BS19: =BS21-BS20 -> -184.7588 | BT19: =BT21-BT20 -> -180.7981 | BU19: =SUM(BQ19:BT19) -> -615.81146 | BW19: =BW21-BW20 -> -176.72912 | BX19: =BX21-BX20 -> -172.32783 | BY19: =BY21-BY20 -> -169.46154 | BZ19: =BZ21-BZ20 -> -168.02538 | CA19: =SUM(BW19:BZ19) -> -686.54387 | CC19: =CC21-CC20 -> -163.77349 | CD19: =CD21-CD20 -> -158.95453 | CE19: =CE21-CE20 -> -153.12141 | CF19: =CF21-CF20 -> -148.29192 | CG19: =SUM(CC19:CF19) -> -624.14136 | CI19: =CI21-CI20 -> -142.22454 | CJ19: =CJ21-CJ20 -> -138.63762 | CK19: =CK21-CK20 -> -132.35501 | CL19: =CL21-CL20 -> -125.59378 | CM19: =SUM(CI19:CL19) -> -538.81095
A20: Interest Expense | C20: 12.868 | D20: 11.686 | E20: 11.598 | F20: 10.268 | G20: =SUM(C20:F20) -> 46.42 | I20: 10.339 | J20: 8.098 | K20: 9.017 | L20: 8.889 | M20: =SUM(I20:L20) -> 36.343 | O20: 7.824 | P20: 7.495 | Q20: 11.288 | R20: 13.782 | S20: =SUM(O20:R20) -> 40.389 | U20: 12.987 | V20: 12.913 | W20: 13.085 | X20: 12.278 | Y20: =SUM(U20:X20) -> 51.263 | AA20: 15.553 | AB20: 23.921 | AC20: 22.211 | AD20: 22.334 | AE20: =SUM(AA20:AD20) -> 84.019 | AG20: 29.378 | AH20: 35.14 | AI20: 34.849 | AJ20: 35.292 | AK20: =SUM(AG20:AJ20) -> 134.659 | AM20: 35.029 | AN20: 34.732 | AO20: 34.573 | AP20: 34 | AQ20: =SUM(AM20:AP20) -> 138.334 | AS20: 34 | AT20: 33 | AU20: 33 | AV20: 35 | AW20: =SUM(AS20:AV20) -> 135 | AY20: 32 | AZ20: 33 | BA20: =105+8-5 -> 108 | BB20: =99+8 -> 107 | BC20: =SUM(AY20:BB20) -> 280 | BE20: =97+8 -> 105 | BF20: 107 | BG20: 105 | BH20: =95+8 -> 103 | BI20: =SUM(BE20:BH20) -> 420 | BK20: 101 | BL20: =86+4 -> 90 | BM20: =184-87 -> 97 | BN20: =156-44+1 -> 113 | BO20: =SUM(BK20:BN20) -> 401 | BQ20: =158-50+1 -> 109 | BR20: 187.51957 | BS20: 186.58207 | BT20: 183.19457 | BU20: =SUM(BQ20:BT20) -> 666.2962 | BW20: 179.85082 | BX20: 175.78832 | BY20: 173.28832 | BZ20: 171.4362 | CA20: =SUM(BW20:BZ20) -> 700.36365 | CC20: 168.8487 | CD20: 163.73151 | CE20: 156.22701 | CF20: 152.09201 | CG20: =SUM(CC20:CF20) -> 640.89923 | CI20: 145.77951 | CJ20: 144.15451 | CK20: 139.40009 | CL20: 133.15009 | CM20: =SUM(CI20:CL20) -> 562.48422
A21: Interest Income | C21: 16.114 | D21: 9.086 | E21: 11.938 | F21: 9.083 | G21: =SUM(C21:F21) -> 46.221 | I21: 13.528 | J21: 8.005 | K21: 10.956 | L21: 6.879 | M21: =SUM(I21:L21) -> 39.368 | O21: 1.651 | P21: 4.312 | Q21: 12.767 | R21: 14.418 | S21: =SUM(O21:R21) -> 33.148 | U21: 8.789 | V21: 9.652 | W21: 2.094 | X21: 14.594 | Y21: =SUM(U21:X21) -> 35.129 | AA21: 15.222 | AB21: 14.564 | AC21: 11.508 | AD21: 1.915 | AE21: =SUM(AA21:AD21) -> 43.209 | AG21: 15.448 | AH21: 16.678 | AI21: 6.253 | AJ21: 11.954 | AK21: =SUM(AG21:AJ21) -> 50.333 | AM21: 7.922 | AN21: 11.818 | AO21: 6.272 | AP21: 14 | AQ21: =SUM(AM21:AP21) -> 40.012 | AS21: 14 | AT21: 10 | AU21: 12 | AV21: 9 | AW21: =SUM(AS21:AV21) -> 45 | AY21: 10 | AZ21: 8 | BA21: 2 | BB21: -5 | BC21: =SUM(AY21:BB21) -> 15 | BE21: 6 | BF21: 3 | BG21: 5 | BH21: 7 | BI21: =SUM(BE21:BH21) -> 21 | BK21: 5 | BL21: 7 | BM21: =19-3 -> 16 | BN21: 45 | BO21: =SUM(BK21:BN21) -> 73 | BQ21: 44 | BR21: 2.265 | BS21: 1.8232697 | BT21: 2.3964723 | BU21: =SUM(BQ21:BT21) -> 50.484742 | BW21: 3.1217027 | BX21: 3.4604877 | BY21: 3.8267791 | BZ21: 3.4108132 | CA21: =SUM(BW21:BZ21) -> 13.819783 | CC21: 5.0752048 | CD21: 4.7769788 | CE21: 3.1056021 | CF21: 3.8000895 | CG21: =SUM(CC21:CF21) -> 16.757875 | CI21: 3.5549717 | CJ21: 5.5168967 | CK21: 7.0450876 | CL21: 7.5563129 | CM21: =SUM(CI21:CL21) -> 23.673269
A22: Other Income (Expense) | C22: -2.368 | D22: 5.872 | E22: 1.774 | F22: -4.334 | G22: =SUM(C22:F22) -> 0.944 | I22: 0.707 | J22: 0.828 | K22: -1.285 | L22: =-1.734-1.804 -> -3.538 | M22: =SUM(I22:L22) -> -3.288 | O22: 9.411 | P22: -5.701 | Q22: =-4.246 -> -4.246 | R22: =-3.312 -> -3.312 | S22: =SUM(O22:R22) -> -3.848 | U22: -2.354 | V22: 0.164 | W22: 1.402 | X22: 1.285 | Y22: =SUM(U22:X22) -> 0.497 | AA22: -4.596 | AB22: -2.522 | AC22: -1.318 | AD22: 1.272 | AE22: =SUM(AA22:AD22) -> -7.164 | AG22: -0.385 | AH22: 4.657 | AI22: -1.881 | AJ22: -3.543 | AK22: =SUM(AG22:AJ22) -> -1.152 | AM22: 0.714 | AN22: 2.253 | AO22: 2.809 | AP22: 3 | AQ22: =SUM(AM22:AP22) -> 8.776 | AS22: 1 | AT22: =5-8 -> -3 | AU22: -2 | AV22: 1 | AW22: =SUM(AS22:AV22) -> -3 | AY22: 2 | AZ22: 6 | BA22: 5 | BB22: -2 | BC22: =SUM(AY22:BB22) -> 11 | BE22: 6 | BF22: 6 | BG22: -1 | BH22: 1 | BI22: =SUM(BE22:BH22) -> 12 | BK22: 13 | BL22: 1 | BM22: -7 | BN22: -8 | BO22: =SUM(BK22:BN22) -> -1 | BQ22: =-11+1 -> -10 | BR22: 47 | BS22: 47 | BT22: 47 | BU22: =SUM(BQ22:BT22) -> 131 | BW22: 47 | BX22: 47 | BY22: 47 | BZ22: 20 | CA22: =SUM(BW22:BZ22) -> 161 | CC22: 10 | CD22: 10 | CE22: 10 | CF22: 10 | CG22: =SUM(CC22:CF22) -> 40 | CI22: 10 | CJ22: 10 | CK22: 10 | CL22: 10 | CM22: =SUM(CI22:CL22) -> 40
A23: Pretax Income | C23: =C17+C19+C22 -> 329.455 | D23: =D17+D19+D22 -> 321.336 | E23: =E17+E19+E22 -> 337.045 | F23: =F17+F19+F22 -> 338.25 | G23: =G17+G19+G22 -> 1326.086 | I23: =I17+I19+I22 -> 366.572 | J23: =J17+J19+J22 -> 382.296 | K23: =K17+K19+K22 -> 410.221 | L23: =L17+L19+L22 -> 392.715 | M23: =M17+M19+M22 -> 1551.804 | O23: =O17+O19+O22 -> 404.82 | P23: =P17+P19+P22 -> 338.568 | Q23: =Q17+Q19+Q22 -> 413.953 | R23: =R17+R19+R22 -> 421.252 | S23: =S17+S19+S22 -> 1578.593 | U23: =U17+U19+U22 -> 423.118 | V23: =V17+V19+V22 -> 410.551 | W23: =W17+W19+W22 -> 413.373 | X23: =X17+X19+X22 -> 414.118 | Y23: =SUM(U23:X23) -> 1661.16 | AA23: =AA17+AA19+AA22 -> 383.7377 | AB23: =AB17+AB19+AB22 -> 405.106 | AC23: =AC17+AC19+AC22 -> 435.17 | AD23: =AD17+AD19+AD22 -> 403.144 | AE23: =SUM(AA23:AD23) -> 1627.1577 | AG23: =AG17+AG19+AG22 -> 322.442 | AH23: =AH17+AH19+AH22 -> 369.525 | AI23: =AI17+AI19+AI22 -> 418.541 | AJ23: =AJ17+AJ19+AJ22 -> 381.899 | AK23: =SUM(AG23:AJ23) -> 1492.407 | AM23: =AM17+AM19+AM22 -> 383.56607 | AN23: =AN17+AN19+AN22 -> 380.3585 | AO23: =AO17+AO19+AO22 -> 421.00415 | AP23: =AP17+AP19+AP22 -> 425.07627 | AQ23: =SUM(AM23:AP23) -> 1610.005 | AS23: =AS17+AS19+AS22 -> 377.38 | AT23: =AT17+AT19+AT22 -> 404.48 | AU23: =AU17+AU19+AU22 -> 450.28 | AV23: =AV17+AV19+AV22 -> 441.91 | AW23: =SUM(AS23:AV23) -> 1674.05 | AY23: =AY17+AY19+AY22 -> 382.14 | AZ23: =AZ17+AZ19+AZ22 -> 403.45 | BA23: =BA17+BA19+BA22 -> 586.1 | BB23: =BB17+BB19+BB22 -> 551 | BC23: =SUM(AY23:BB23) -> 1922.69 | BE23: =BE17+BE19+BE22 -> 541.24 | BF23: =BF17+BF19+BF22 -> 594.75 | BG23: =BG17+BG19+BG22 -> 648 | BH23: =BH17+BH19+BH22 -> 552 | BI23: =SUM(BE23:BH23) -> 2335.99 | BK23: =BK17+BK19+BK22 -> 611 | BL23: =BL17+BL19+BL22 -> 573 | BM23: =BM17+BM19+BM22 -> 643 | BN23: =BN17+BN19+BN22 -> 614.49 | BO23: =SUM(BK23:BN23) -> 2441.49 | BQ23: =BQ17+BQ19+BQ22 -> 650 | BR23: =BR17+BR19+BR22 -> 914.36484 | BS23: =BS17+BS19+BS22 -> 1018.9694 | BT23: =BT17+BT19+BT22 -> 1008.4614 | BU23: =SUM(BQ23:BT23) -> 3591.7957 | BW23: =BW17+BW19+BW22 -> 1028.6294 | BX23: =BX17+BX19+BX22 -> 1072.0447 | BY23: =BY17+BY19+BY22 -> 1118.2055 | BZ23: =BZ17+BZ19+BZ22 -> 1105.1143 | CA23: =SUM(BW23:BZ23) -> 4323.994 | CC23: =CC17+CC19+CC22 -> 1166.5683 | CD23: =CD17+CD19+CD22 -> 1213.3754 | CE23: =CE17+CE19+CE22 -> 1268.7592 | CF23: =CF17+CF19+CF22 -> 1287.9986 | CG23: =SUM(CC23:CF23) -> 4936.7015 | CI23: =CI17+CI19+CI22 -> 1318.9434 | CJ23: =CJ17+CJ19+CJ22 -> 1332.9244 | CK23: =CK17+CK19+CK22 -> 1448.2967 | CL23: =CL17+CL19+CL22 -> 1471.1761 | CM23: =SUM(CI23:CL23) -> 5571.3407
A24: Income Taxes | C24: 83.657 | D24: 85.796712 | E24: 89.182 | F24: 89.142 | G24: =SUM(C24:F24) -> 347.77771 | I24: 95.676 | J24: 106.661 | K24: 112.811 | L24: 110.541 | M24: =SUM(I24:L24) -> 425.689 | O24: 108.213 | P24: 89.702 | Q24: 86.508 | R24: 126.824 | S24: =SUM(O24:R24) -> 411.247 | U24: 119.025 | V24: 125.517 | W24: 119.213 | X24: 121.065 | Y24: =SUM(U24:X24) -> 484.82 | AA24: 85.291 | AB24: 109.256 | AC24: 113.63 | AD24: =108.827+(9.27-6) -> 112.097 | AE24: =SUM(AA24:AD24) -> 420.274 | AG24: 73.898 | AH24: 94.401 | AI24: 106.96 | AJ24: =87.621+7 -> 94.621 | AK24: =SUM(AG24:AJ24) -> 369.88 | AM24: 100.80802 | AN24: 90.31725 | AO24: 101.16734 | AP24: 106.72288 | AQ24: =SUM(AM24:AP24) -> 399.0155 | AS24: 93.8212 | AT24: 89.8212 | AU24: 105.8212 | AV24: 98.9598 | AW24: =SUM(AS24:AV24) -> 388.4234 | AY24: 80.1 | AZ24: 86 | BA24: =-23+2+3+9+28+128-2+0 -> 145 | BB24: =9+3+15+51+54 -> 132 | BC24: =SUM(AY24:BB24) -> 443.1 | BE24: 116.4 | BF24: 122.4 | BG24: 138 | BH24: 90 | BI24: =SUM(BE24:BH24) -> 466.8 | BK24: 104 | BL24: 72 | BM24: 106 | BN24: 90 | BO24: =SUM(BK24:BN24) -> 372 | BQ24: =241-135 -> 106 | BR24: =BR23*BR25 -> 155.44202 | BS24: =BS23*BS25 -> 173.22481 | BT24: =BT23*BT25 -> 171.43844 | BU24: =SUM(BQ24:BT24) -> 606.10526 | BW24: =BW23*BW25 -> 172.29543 | BX24: =BX23*BX25 -> 179.56749 | BY24: =BY23*BY25 -> 187.29942 | BZ24: =BZ23*BZ25 -> 185.10665 | CA24: =SUM(BW24:BZ24) -> 724.26899 | CC24: =CC23*CC25 -> 192.48378 | CD24: =CD23*CD25 -> 200.20693 | CE24: =CE23*CE25 -> 209.34526 | CF24: =CF23*CF25 -> 212.51977 | CG24: =SUM(CC24:CF24) -> 814.55574 | CI24: =CI23*CI25 -> 217.62567 | CJ24: =CJ23*CJ25 -> 219.93252 | CK24: =CK23*CK25 -> 238.96896 | CL24: =CL23*CL25 -> 242.74406 | CM24: =SUM(CI24:CL24) -> 919.27121
A25: Tax Rate | C25: =C24/C23 -> 0.25392542 | D25: =D24/D23 -> 0.267 | E25: =E24/E23 -> 0.26459968 | F25: =F24/F23 -> 0.2635388 | G25: =G24/G23 -> 0.26225879 | I25: =I24/I23 -> 0.26100193 | J25: =J24/J23 -> 0.27900109 | K25: =K24/K23 -> 0.27500055 | L25: =L24/L23 -> 0.28147894 | M25: =M24/M23 -> 0.27431879 | O25: =O24/O23 -> 0.2673114 | P25: =P24/P23 -> 0.2649453 | Q25: =Q24/Q23 -> 0.20898025 | R25: =R24/R23 -> 0.30106445 | S25: =S24/S23 -> 0.2605149 | U25: =U24/U23 -> 0.28130451 | V25: =V24/V23 -> 0.30572816 | W25: =W24/W23 -> 0.28839087 | X25: =X24/X23 -> 0.29234421 | Y25: =Y24/Y23 -> 0.29185629 | AA25: =AA24/AA23 -> 0.2222638 | AB25: =AB24/AB23 -> 0.26969731 | AC25: =AC24/AC23 -> 0.26111635 | AD25: =AD24/AD23 -> 0.27805697 | AE25: =AE24/AE23 -> 0.2582872 | AG25: =AG24/AG23 -> 0.2291823 | AH25: =AH24/AH23 -> 0.2554658 | AI25: =AI24/AI23 -> 0.25555441 | AJ25: =AJ24/AJ23 -> 0.24776446 | AK25: =AK24/AK23 -> 0.24784124 | AM25: =AM24/AM23 -> 0.26281788 | AN25: =AN24/AN23 -> 0.23745296 | AO25: =AO24/AO23 -> 0.24030011 | AP25: =AP24/AP23 -> 0.25106761 | AQ25: =AQ24/AQ23 -> 0.24783494 | AS25: =AS24/AS23 -> 0.24861201 | AT25: =AT24/AT23 -> 0.22206586 | AU25: =AU24/AU23 -> 0.23501199 | AV25: =AV24/AV23 -> 0.22393655 | AW25: =AW24/AW23 -> 0.23202616 | AY25: =AY24/AY23 -> 0.20960904 | AZ25: =AZ24/AZ23 -> 0.21316148 | BA25: =BA24/BA23 -> 0.24739805 | BB25: =BB24/BB23 -> 0.23956443 | BC25: =BC24/BC23 -> 0.23045837 | BE25: =BE24/BE23 -> 0.21506171 | BF25: =BF24/BF23 -> 0.20580076 | BG25: =BG24/BG23 -> 0.21296296 | BH25: =BH24/BH23 -> 0.16304348 | BI25: =BI24/BI23 -> 0.19982962 | BK25: =+BK24/BK23 -> 0.17021277 | BL25: =BL24/BL23 -> 0.12565445 | BM25: =BM24/BM23 -> 0.16485226 | BN25: =BN24/BN23 -> 0.14646292 | BO25: =BO24/BO23 -> 0.15236597 | BQ25: =+BQ24/BQ23 -> 0.16307692 | BR25: 0.17 | BS25: 0.17 | BT25: 0.17 | BU25: =BU24/BU23 -> 0.16874714 | BW25: 0.1675 | BX25: =BW25 -> 0.1675 | BY25: =BX25 -> 0.1675 | BZ25: =BY25 -> 0.1675 | CA25: =CA24/CA23 -> 0.1675 | CC25: 0.165 | CD25: =CC25 -> 0.165 | CE25: =CD25 -> 0.165 | CF25: =CE25 -> 0.165 | CG25: =CG24/CG23 -> 0.165 | CI25: 0.165 | CJ25: =CI25 -> 0.165 | CK25: =CJ25 -> 0.165 | CL25: =CK25 -> 0.165 | CM25: =CM24/CM23 -> 0.165
A26: Income from cont. ops | C26: =C23-C24 -> 245.798 | D26: =D23-D24 -> 235.53929 | E26: =E23-E24 -> 247.863 | F26: =F23-F24 -> 249.108 | G26: =G23-G24 -> 978.30829 | I26: =I23-I24 -> 270.896 | J26: =J23-J24 -> 275.635 | K26: =K23-K24 -> 297.41 | L26: =L23-L24 -> 282.174 | M26: =M23-M24 -> 1126.115 | O26: =O23-O24 -> 296.607 | P26: =P23-P24 -> 248.866 | Q26: =Q23-Q24 -> 327.445 | R26: =R23-R24 -> 294.428 | S26: =S23-S24 -> 1167.346 | U26: =U23-U24 -> 304.093 | V26: =V23-V24 -> 285.034 | W26: =W23-W24 -> 294.16 | X26: =X23-X24 -> 293.053 | Y26: =Y23-Y24 -> 1176.34 | AA26: =AA23-AA24 -> 298.4467 | AB26: =AB23-AB24 -> 295.85 | AC26: =AC23-AC24 -> 321.54 | AD26: =AD23-AD24 -> 291.047 | AE26: =AE23-AE24 -> 1206.8837 | AG26: =AG23-AG24 -> 248.544 | AH26: =AH23-AH24 -> 275.124 | AI26: =AI23-AI24 -> 311.581 | AJ26: =AJ23-AJ24 -> 287.278 | AK26: =AK23-AK24 -> 1122.527 | AM26: =AM23-AM24 -> 282.75805 | AN26: =AN23-AN24 -> 290.04125 | AO26: =AO23-AO24 -> 319.8368 | AP26: =AP23-AP24 -> 318.35339 | AQ26: =AQ23-AQ24 -> 1210.9895 | AS26: =AS23-AS24 -> 283.5588 | AT26: =AT23-AT24 -> 314.6588 | AU26: =AU23-AU24 -> 344.4588 | AV26: =AV23-AV24 -> 342.9502 | AW26: =AW23-AW24 -> 1285.6266 | AY26: =AY23-AY24 -> 302.04 | AZ26: =AZ23-AZ24 -> 317.45 | BA26: =BA23-BA24 -> 441.1 | BB26: =BB23-BB24 -> 419 | BC26: =BC23-BC24 -> 1479.59 | BE26: =BE23-BE24 -> 424.84 | BF26: =BF23-BF24 -> 472.35 | BG26: =BG23-BG24 -> 510 | BH26: =BH23-BH24 -> 462 | BI26: =BI23-BI24 -> 1869.19 | BK26: =BK23-BK24 -> 507 | BL26: =BL23-BL24 -> 501 | BM26: =BM23-BM24 -> 537 | BN26: =BN23-BN24 -> 524.49 | BO26: =BO23-BO24 -> 2069.49 | BQ26: =BQ23-BQ24 -> 544 | BR26: =BR23-BR24 -> 758.92281 | BS26: =BS23-BS24 -> 845.74464 | BT26: =BT23-BT24 -> 837.02295 | BU26: =BU23-BU24 -> 2985.6904 | BW26: =BW23-BW24 -> 856.334 | BX26: =BX23-BX24 -> 892.47722 | BY26: =BY23-BY24 -> 930.90606 | BZ26: =BZ23-BZ24 -> 920.00769 | CA26: =CA23-CA24 -> 3599.725 | CC26: =CC23-CC24 -> 974.08456 | CD26: =CD23-CD24 -> 1013.1684 | CE26: =CE23-CE24 -> 1059.4139 | CF26: =CF23-CF24 -> 1075.4788 | CG26: =CG23-CG24 -> 4122.1457 | CI26: =CI23-CI24 -> 1101.3178 | CJ26: =CJ23-CJ24 -> 1112.9919 | CK26: =CK23-CK24 -> 1209.3278 | CL26: =CL23-CL24 -> 1228.4321 | CM26: =CM23-CM24 -> 4652.0695
A27: Income from Discont. Ops before Income Tax | C27: 0 | D27: 0 | E27: 0 | F27: 0 | G27: =SUM(C27:F27) -> 0 | I27: 0 | J27: 0 | K27: 0 | L27: 0 | M27: =SUM(I27:L27) -> 0 | O27: 20.234 | P27: 15.944 | Q27: 17.579 | R27: 30.476 | S27: =SUM(O27:R27) -> 84.233 | U27: 16.9 | V27: 16.698 | W27: 17.088 | X27: =103.642+27.645 -> 131.287 | Y27: =SUM(U27:X27) -> 181.973 | AA27: 26.298 | AB27: 24.688 | AC27: 30.53 | AD27: 23.793 | AE27: =SUM(AA27:AD27) -> 105.309 | AG27: 21.768 | AH27: 23.453 | AI27: =15.285+7.288 -> 22.573 | AJ27: =14.765+9.108 -> 23.873 | AK27: =SUM(AG27:AJ27) -> 91.667 | AM27: =355.187+216.336 -> 571.523 | AN27: -1.66 | AO27: =AO28+9.672 -> 16.104 | AP27: 1 | AQ27: =SUM(AM27:AP27) -> 586.967 | AS27: 0 | AT27: 0 | AU27: 0 | AV27: 0 | AW27: =SUM(AS27:AV27) -> 0 | AY27: 0 | AZ27: 0 | BA27: 0 | BB27: 0 | BC27: =SUM(AY27:BB27) -> 0 | BE27: 0 | BF27: 0 | BG27: 0 | BH27: 0 | BI27: =SUM(BE27:BH27) -> 0 | BK27: 0 | BL27: 0 | BM27: 0 | BN27: 0 | BO27: =SUM(BK27:BN27) -> 0 | BQ27: 0 | BR27: 0 | BS27: 0 | BT27: 0 | BU27: =SUM(BQ27:BT27) -> 0 | BW27: 0 | BX27: 0 | BY27: 0 | BZ27: 0 | CA27: =SUM(BW27:BZ27) -> 0 | CC27: 0 | CD27: 0 | CE27: 0 | CF27: 0 | CG27: =SUM(CC27:CF27) -> 0 | CI27: 0 | CJ27: 0 | CK27: 0 | CL27: 0 | CM27: =SUM(CI27:CL27) -> 0
A28: Income Taxes | C28: 0 | D28: 0 | E28: 0 | F28: 0 | G28: =SUM(C28:F28) -> 0 | I28: 0 | J28: 0 | K28: 0 | L28: 0 | M28: =SUM(I28:L28) -> 0 | O28: 4.773 | P28: 3.521 | Q28: 3.997 | R28: 7.684 | S28: =SUM(O28:R28) -> 19.975 | U28: 4.617 | V28: 4.101 | W28: 4.34 | X28: 27.645 | Y28: =SUM(U28:X28) -> 40.703 | AA28: 8.807 | AB28: 8.519 | AC28: 9.012 | AD28: 8.86 | AE28: =SUM(AA28:AD28) -> 35.198 | AG28: 7.327 | AH28: 7.544 | AI28: 7.288 | AJ28: 9.108 | AK28: =SUM(AG28:AJ28) -> 31.267 | AM28: 216.336 | AN28: -1.177 | AO28: 6.432 | AP28: 1 | AQ28: =SUM(AM28:AP28) -> 222.591 | AS28: 0 | AT28: 0 | AU28: 0 | AV28: 0 | AW28: =SUM(AS28:AV28) -> 0 | AY28: 0 | AZ28: 0 | BA28: 0 | BB28: 0 | BC28: =SUM(AY28:BB28) -> 0 | BE28: 0 | BF28: 0 | BG28: 0 | BH28: 0 | BI28: =SUM(BE28:BH28) -> 0 | BK28: 0 | BL28: 0 | BM28: 0 | BN28: 0 | BO28: =SUM(BK28:BN28) -> 0 | BQ28: 0 | BR28: 0 | BS28: 0 | BT28: 0 | BU28: =SUM(BQ28:BT28) -> 0 | BW28: 0 | BX28: 0 | BY28: 0 | BZ28: 0 | CA28: =SUM(BW28:BZ28) -> 0 | CC28: 0 | CD28: 0 | CE28: 0 | CF28: 0 | CG28: =SUM(CC28:CF28) -> 0 | CI28: 0 | CJ28: 0 | CK28: 0 | CL28: 0 | CM28: =SUM(CI28:CL28) -> 0
A29: Income from discont. Ops, net of tax | C29: =C27-C28 -> 0 | D29: =D27-D28 -> 0 | E29: =E27-E28 -> 0 | F29: =F27-F28 -> 0 | G29: =G27-G28 -> 0 | I29: =I27-I28 -> 0 | J29: =J27-J28 -> 0 | K29: =K27-K28 -> 0 | L29: =L27-L28 -> 0 | M29: =M27-M28 -> 0 | O29: =O27-O28 -> 15.461 | P29: =P27-P28 -> 12.423 | Q29: =Q27-Q28 -> 13.582 | R29: =R27-R28 -> 22.792 | S29: =S27-S28 -> 64.258 | U29: =U27-U28 -> 12.283 | V29: =V27-V28 -> 12.597 | W29: =W27-W28 -> 12.748 | X29: =X27-X28 -> 103.642 | Y29: =Y27-Y28 -> 141.27 | AA29: =AA27-AA28 -> 17.491 | AB29: =AB27-AB28 -> 16.169 | AC29: =AC27-AC28 -> 21.518 | AD29: =AD27-AD28 -> 14.933 | AE29: =AE27-AE28 -> 70.111 | AG29: =AG27-AG28 -> 14.441 | AH29: =AH27-AH28 -> 15.909 | AI29: =AI27-AI28 -> 15.285 | AJ29: =AJ27-AJ28 -> 14.765 | AK29: =SUM(AG29:AJ29) -> 60.4 | AM29: =AM27-AM28 -> 355.187 | AN29: =AN27-AN28 -> -0.483 | AO29: =AO27-AO28 -> 9.672 | AP29: =AP27-AP28 -> 0 | AQ29: =AQ27-AQ28 -> 364.376 | AS29: =AS27-AS28 -> 0 | AT29: =AT27-AT28 -> 0 | AU29: =AU27-AU28 -> 0 | AV29: =AV27-AV28 -> 0 | AW29: =SUM(AS29:AV29) -> 0 | AY29: =AY27-AY28 -> 0 | AZ29: =AZ27-AZ28 -> 0 | BA29: =BA27-BA28 -> 0 | BB29: =BB27-BB28 -> 0 | BC29: =SUM(AY29:BB29) -> 0 | BE29: =BE27-BE28 -> 0 | BF29: =BF27-BF28 -> 0 | BG29: =BG27-BG28 -> 0 | BH29: =BH27-BH28 -> 0 | BI29: =SUM(BE29:BH29) -> 0 | BK29: =BK27-BK28 -> 0 | BL29: =BL27-BL28 -> 0 | BM29: =BM27-BM28 -> 0 | BN29: =BN27-BN28 -> 0 | BO29: =SUM(BK29:BN29) -> 0 | BQ29: =BQ27-BQ28 -> 0 | BR29: =BR27-BR28 -> 0 | BS29: =BS27-BS28 -> 0 | BT29: =BT27-BT28 -> 0 | BU29: =SUM(BQ29:BT29) -> 0 | BW29: =BW27-BW28 -> 0 | BX29: =BX27-BX28 -> 0 | BY29: =BY27-BY28 -> 0 | BZ29: =BZ27-BZ28 -> 0 | CA29: =SUM(BW29:BZ29) -> 0 | CC29: =CC27-CC28 -> 0 | CD29: =CD27-CD28 -> 0 | CE29: =CE27-CE28 -> 0 | CF29: =CF27-CF28 -> 0 | CG29: =SUM(CC29:CF29) -> 0 | CI29: =CI27-CI28 -> 0 | CJ29: =CJ27-CJ28 -> 0 | CK29: =CK27-CK28 -> 0 | CL29: =CL27-CL28 -> 0 | CM29: =SUM(CI29:CL29) -> 0
A30: Preferred Stock Dividends | BR30: =IF(CFS!BR110<CFS!BR115,CFS!BR107,0) -> 38.28125 | BS30: =IF(CFS!BS110<CFS!BS115,CFS!BS107,0) -> 38.28125 | BT30: =IF(CFS!BT110<CFS!BT115,CFS!BT107,0) -> 38.28125 | BU30: =SUM(BQ30:BT30) -> 114.84375 | BW30: =IF(CFS!BW110<CFS!BW115,CFS!BW107,0) -> 38.28125 | BX30: =IF(CFS!BX110<CFS!BX115,CFS!BX107,0) -> 38.28125 | BY30: =IF(CFS!BY110<CFS!BY115,CFS!BY107,0) -> 38.28125 | BZ30: =IF(CFS!BZ110<CFS!BZ115,CFS!BZ107,0) -> 38.28125 | CA30: =SUM(BW30:BZ30) -> 153.125 | CC30: =IF(CFS!CC110<CFS!CC115,CFS!CC107,0) -> 0 | CD30: =IF(CFS!CD110<CFS!CD115,CFS!CD107,0) -> 0 | CG30: =SUM(CC30:CF30) -> 0
A31: Net Income | C31: =C26+C29 -> 245.798 | D31: =D26+D29 -> 235.53929 | E31: =E26+E29 -> 247.863 | F31: =F26+F29 -> 249.108 | G31: =G26+G29 -> 978.30829 | I31: =I26+I29 -> 270.896 | J31: =J26+J29 -> 275.635 | K31: =K26+K29 -> 297.41 | L31: =L26+L29 -> 282.174 | M31: =M26+M29 -> 1126.115 | O31: =O26+O29 -> 312.068 | P31: =P26+P29 -> 261.289 | Q31: =Q26+Q29 -> 341.027 | R31: =R26+R29 -> 317.22 | S31: =S26+S29 -> 1231.604 | U31: =U26+U29 -> 316.376 | V31: =V26+V29 -> 297.631 | W31: =W26+W29 -> 306.908 | X31: =X26+X29 -> 396.695 | Y31: =Y26+Y29 -> 1317.61 | AA31: =AA26+AA29 -> 315.9377 | AB31: =AB26+AB29 -> 312.019 | AC31: =AC26+AC29 -> 343.058 | AD31: =AD26+AD29 -> 305.98 | AE31: =AE26+AE29 -> 1276.9947 | AG31: =AG26+AG29 -> 262.985 | AH31: =AH26+AH29 -> 291.033 | AI31: =AI26+AI29 -> 326.866 | AJ31: =AJ26+AJ29 -> 302.043 | AK31: =AK26+AK29 -> 1182.927 | AM31: =AM26+AM29 -> 637.94505 | AN31: =AN26+AN29 -> 289.55825 | AO31: =AO26+AO29 -> 329.5088 | AP31: =AP26+AP29 -> 318.35339 | AQ31: =AQ26+AQ29 -> 1575.3655 | AS31: =AS26+AS29 -> 283.5588 | AT31: =AT26+AT29 -> 314.6588 | AU31: =AU26+AU29 -> 344.4588 | AV31: =AV26+AV29 -> 342.9502 | AW31: =AW26+AW29 -> 1285.6266 | AY31: =AY26+AY29 -> 302.04 | AZ31: =AZ26+AZ29 -> 317.45 | BA31: =BA26+BA29 -> 441.1 | BB31: =BB26+BB29 -> 419 | BC31: =BC26+BC29 -> 1479.59 | BE31: =BE26+BE29 -> 424.84 | BF31: =BF26+BF29 -> 472.35 | BG31: =BG26+BG29 -> 510 | BH31: =BH26+BH29 -> 462 | BI31: =BI26+BI29 -> 1869.19 | BK31: =BK26+BK29 -> 507 | BL31: =BL26+BL29 -> 501 | BM31: =BM26+BM29 -> 537 | BN31: =BN26+BN29 -> 524.49 | BO31: =BO26+BO29 -> 2069.49 | BQ31: =BQ26+BQ29-BQ30 -> 544 | BR31: =BR26+BR29-BR30 -> 720.64156 | BS31: =BS26+BS29-BS30 -> 807.46339 | BT31: =BT26+BT29-BT30 -> 798.7417 | BU31: =BU26+BU29-BU30 -> 2870.8467 | BW31: =BW26+BW29-BW30 -> 818.05275 | BX31: =BX26+BX29-BX30 -> 854.19597 | BY31: =BY26+BY29-BY30 -> 892.62481 | BZ31: =BZ26+BZ29-BZ30 -> 881.72644 | CA31: =CA26+CA29-CA30 -> 3446.6 | CC31: =CC26+CC29-CC30 -> 974.08456 | CD31: =CD26+CD29-CD30 -> 1013.1684 | CE31: =CE26+CE29-CE30 -> 1059.4139 | CF31: =CF26+CF29-CF30 -> 1075.4788 | CG31: =CG26+CG29-CG30 -> 4122.1457 | CI31: =CI26+CI29-CI30 -> 1101.3178 | CJ31: =CJ26+CJ29-CJ30 -> 1112.9919 | CK31: =CK26+CK29-CK30 -> 1209.3278 | CL31: =CL26+CL29-CL30 -> 1228.4321 | CM31: =CM26+CM29-CM30 -> 4652.0695
A32: Net Income to Common | BQ32: 544 | BR32: =BR26-IF(CFS!BR110<CFS!BR115,CFS!BR107) -> 720.64156 | BS32: =BS26-IF(CFS!BS110<CFS!BS115,CFS!BS107) -> 807.46339 | BT32: =BT26-IF(CFS!BT110<CFS!BT115,CFS!BT107) -> 798.7417 | BU32: =SUM(BQ32:BT32) -> 2870.8467 | BW32: =BW26-IF(CFS!BW110<CFS!BW115,CFS!BW107) -> 818.05275 | BX32: =BX26-IF(CFS!BX110<CFS!BX115,CFS!BX107) -> 854.19597 | BY32: =BY26-IF(CFS!BY110<CFS!BY115,CFS!BY107) -> 892.62481 | BZ32: =BZ26-IF(CFS!BZ110<CFS!BZ115,CFS!BZ107) -> 881.72644 | CA32: =SUM(BW32:BZ32) -> 3446.6 | CC32: =CC26-IF(CFS!CC110<CFS!CC115,CFS!CC107) -> 974.08456 | CD32: =CD26-IF(CFS!CD110<CFS!CD115,CFS!CD107) -> 1013.1684 | CE32: =CE26-IF(CFS!CE110<CFS!CE115,CFS!CE107) -> 1059.4139 | CF32: =CF26-IF(CFS!CF110<CFS!CF115,CFS!CF107) -> 1075.4788 | CG32: =SUM(CC32:CF32) -> 4122.1457 | CI32: =CI26-IF(CFS!CI110<CFS!CI115,CFS!CI107) -> 1101.3178 | CJ32: =CJ26-IF(CFS!CJ110<CFS!CJ115,CFS!CJ107) -> 1112.9919 | CK32: =CK26-IF(CFS!CK110<CFS!CK115,CFS!CK107) -> 1209.3278 | CL32: =CL26-IF(CFS!CL110<CFS!CL115,CFS!CL107) -> 1228.4321 | CM32: =SUM(CI32:CL32) -> 4652.0695
A33: Fully Diluted Shares | C33: 254.941 | D33: 254.74 | E33: 254.128 | F33: 253.009 | G33: 254.81 | I33: 253.116 | J33: 252.788 | K33: 251.648 | L33: 251.197 | M33: 252.681 | O33: 248.311 | P33: 245.89 | Q33: 245.696 | R33: 245.056 | S33: 246.798 | U33: 242.965 | V33: 240.863 | W33: 238.319 | X33: 236.316 | Y33: 240.136 | AA33: 232.915 | AB33: 225.467 | AC33: 223.567 | AD33: 220.859 | AE33: =AVERAGE(AA33:AD33) -> 225.702 | AG33: 217.634 | AH33: 209.803 | AI33: 205.29 | AJ33: 202.439 | AK33: =AVERAGE(AG33:AJ33) -> 208.7915 | AM33: 199.57 | AN33: 198.143 | AO33: 198.719 | AP33: 198.628 | AQ33: =AVERAGE(AM33:AP33) -> 198.765 | AS33: 198.11 | AT33: 197.488 | AU33: 197.005 | AV33: 196.46 | AW33: 197.709 | AY33: 197 | AZ33: 197 | BA33: 214.928 | BB33: 215.719 | BC33: 206.833 | BE33: 216.294 | BF33: 216.538 | BG33: 217.372 | BH33: 217.916 | BI33: =AVERAGE(BE33:BH33) -> 217.03 | BK33: 217.739 | BL33: 217.866 | BM33: 218.184 | BN33: 218.632 | BO33: =AVERAGE(BK33:BN33) -> 218.10525 | BQ33: 218.997 | BR33: =CFS!BR81 -> 275.03953 | BS33: =CFS!BS81 -> 275.141 | BT33: =CFS!BT81 -> 275.34395 | BU33: =AVERAGE(BQ33:BT33) -> 261.13037 | BW33: =CFS!BW81 -> 275.15529 | BX33: =CFS!BX81 -> 275.66038 | BY33: =CFS!BY81 -> 276.16745 | BZ33: =CFS!BZ81 -> 276.67453 | CA33: =AVERAGE(BW33:BZ33) -> 275.91441 | CC33: =CFS!CC81 -> 289.49086 | CD33: =CFS!CD81 -> 290.30291 | CE33: =CFS!CE81 -> 290.64568 | CF33: =CFS!CF81 -> 290.70565 | CG33: =AVERAGE(CC33:CF33) -> 290.28627 | CI33: =CFS!CI81 -> 291.52497 | CJ33: =CFS!CJ81 -> 292.53788 | CK33: =CFS!CK81 -> 293.04501 | CL33: =CFS!CL81 -> 293.55215 | CM33: =AVERAGE(CI33:CL33) -> 292.665
A34: Diluted EPS | C34: =C26/C33 -> 0.9641368 | D34: =D26/D33 -> 0.92462624 | E34: =E26/E33 -> 0.97534707 | F34: =F26/F33 -> 0.98458158 | G34: =G26/G33 -> 3.8393638 | I34: =I26/I33 -> 1.0702445 | J34: =J26/J33 -> 1.0903801 | K34: =K26/K33 -> 1.1818492 | L34: =L26/L33 -> 1.1233176 | M34: =M26/M33 -> 4.4566667 | O34: =O26/O33 -> 1.194498 | P34: =P26/P33 -> 1.012103 | Q34: =Q26/Q33 -> 1.3327242 | R34: =R26/R33 -> 1.2014723 | S34: =S26/S33 -> 4.7299654 | U34: =U26/U33 -> 1.2515918 | V34: =V26/V33 -> 1.1833864 | W34: =W26/W33 -> 1.234312 | X34: =X26/X33 -> 1.2400895 | Y34: =Y26/Y33 -> 4.8986408 | AA34: =AA26/AA33 -> 1.2813546 | AB34: =AB26/AB33 -> 1.3121654 | AC34: =AC26/AC33 -> 1.4382266 | AD34: =AD26/AD33 -> 1.3177955 | AE34: =AE26/AE33 -> 5.3472442 | AG34: =AG26/AG33 -> 1.1420274 | AH34: =AH26/AH33 -> 1.3113445 | AI34: =AI26/AI33 -> 1.5177602 | AJ34: =AJ26/AJ33 -> 1.4190843 | AK34: =AK26/AK33 -> 5.376306 | AM34: =AM26/AM33 -> 1.4168365 | AN34: =AN26/AN33 -> 1.4637976 | AO34: =AO26/AO33 -> 1.6094928 | AP34: =AP26/AP33 -> 1.6027619 | AQ34: =AQ26/AQ33 -> 6.0925691 | AS34: =AS26/AS33 -> 1.43132 | AT34: =AT26/AT33 -> 1.5933059 | AU34: =AU26/AU33 -> 1.7484774 | AV34: =AV26/AV33 -> 1.745649 | AW34: =AW26/AW33 -> 6.5026205 | AY34: =AY26/AY33 -> 1.533198 | AZ34: =AZ26/AZ33 -> 1.6114213 | BA34: =BA26/BA33 -> 2.0523152 | BB34: =BB26/BB33 -> 1.9423417 | BC34: =BC26/BC33 -> 7.153549 | BE34: =BE26/BE33 -> 1.9641784 | BF34: =BF26/BF33 -> 2.1813723 | BG34: =BG26/BG33 -> 2.3462083 | BH34: =BH26/BH33 -> 2.120083 | BI34: =BI26/BI33 -> 8.6125881 | BK34: =BK26/BK33 -> 2.3284758 | BL34: =BL26/BL33 -> 2.2995786 | BM34: =BM26/BM33 -> 2.4612254 | BN34: =BN26/BN33 -> 2.3989626 | BO34: =BO26/BO33 -> 9.4884924 | BQ34: =BQ26/BQ33 -> 2.4840523 | BR34: =BR32/BR33 -> 2.6201382 | BS34: =BS32/BS33 -> 2.9347258 | BT34: =BT32/BT33 -> 2.9008871 | BU34: =BU32/BU33 -> 10.993921 | BW34: =BW32/BW33 -> 2.9730584 | BX34: =BX32/BX33 -> 3.098726 | BY34: =BY32/BY33 -> 3.2321869 | BZ34: =BZ32/BZ33 -> 3.1868725 | CA34: =CA32/CA33 -> 12.491555 | CC34: =CC32/CC33 -> 3.3648197 | CD34: =CD32/CD33 -> 3.4900389 | CE34: =CE26/CE33 -> 3.6450359 | CF34: =CF26/CF33 -> 3.6995457 | CG34: =CG32/CG33 -> 14.200278 | CI34: =CI26/CI33 -> 3.777782 | CJ34: =CJ26/CJ33 -> 3.8046077 | CK34: =CK26/CK33 -> 4.1267646 | CL34: =CL26/CL33 -> 4.184715 | CM34: =CM26/CM33 -> 15.895544
A36: Margin Analysis
A37: Gross Profit | C37: =C11/C7 -> 0.52786084 | D37: =D11/D7 -> 0.51486178 | E37: =E11/E7 -> 0.51502521 | F37: =F11/F7 -> 0.5110069 | G37: =G11/G7 -> 0.51697198 | I37: =I11/I7 -> 0.51350565 | J37: =J11/J7 -> 0.51125148 | K37: =K11/K7 -> 0.50879851 | L37: =L11/L7 -> 0.51431088 | M37: =M11/M7 -> 0.51193342 | O37: =O11/O7 -> 0.53647735 | P37: =P11/P7 -> 0.52031261 | Q37: =Q11/Q7 -> 0.52794936 | R37: =R11/R7 -> 0.51985655 | S37: =S11/S7 -> 0.52600433 | U37: =U11/U7 -> 0.52144939 | V37: =V11/V7 -> 0.51956893 | W37: =W11/W7 -> 0.51748938 | X37: =X11/X7 -> 0.5190394 | Y37: =Y11/Y7 -> 0.51939461 | AA37: =AA11/AA7 -> 0.52888426 | AB37: =AB11/AB7 -> 0.52098501 | AC37: =AC11/AC7 -> 0.52730304 | AD37: =AD11/AD7 -> 0.51159326 | AE37: =AE11/AE7 -> 0.52200646 | AG37: =AG11/AG7 -> 0.50840467 | AH37: =AH11/AH7 -> 0.51207723 | AI37: =AI11/AI7 -> 0.52164572 | AJ37: =AJ11/AJ7 -> 0.51384755 | AK37: =AK11/AK7 -> 0.51411476 | AM37: =AM11/AM7 -> 0.53889243 | AN37: =AN11/AN7 -> 0.51890596 | AO37: =AO11/AO7 -> 0.52611248 | AP37: =AP11/AP7 -> 0.5262268 | AQ37: =AQ11/AQ7 -> 0.52736771 | AS37: =AS11/AS7 -> 0.52279518 | AT37: =AT11/AT7 -> 0.51712355 | AU37: =AU11/AU7 -> 0.5235905 | AV37: =AV11/AV7 -> 0.51858092 | AW37: =AW11/AW7 -> 0.52050809 | AY37: =AY11/AY7 -> 0.51831664 | AZ37: =AZ11/AZ7 -> 0.51815455 | BA37: =BA11/BA7 -> 0.51982126 | BB37: =BB11/BB7 -> 0.52429084 | BC37: =BC11/BC7 -> 0.52052062 | BE37: =BE11/BE7 -> 0.52343395 | BF37: =BF11/BF7 -> 0.52922501 | BG37: =BG11/BG7 -> 0.52625 | BH37: =BH11/BH7 -> 0.52226345 | BI37: =BI11/BI7 -> 0.52527518 | BK37: =BK11/BK7 -> 0.54312115 | BL37: =BL11/BL7 -> 0.52643988 | BM37: =BM11/BM7 -> 0.53871499 | BN37: =BN11/BN7 -> 0.5322897 | BO37: =BO11/BO7 -> 0.53508335 | BQ37: =BQ11/BQ7 -> 0.54837662 | BR37: 0.565 | BS37: 0.573 | BT37: 0.575 | BU37: =BU11/BU7 -> 0.5666854 | BW37: 0.575 | BX37: 0.576 | BY37: 0.575 | BZ37: 0.577 | CA37: =CA11/CA7 -> 0.57576103 | CC37: =BW37+0.009 -> 0.584 | CD37: =BX37+0.009 -> 0.585 | CE37: =BY37+0.009 -> 0.584 | CF37: =BZ37+0.009 -> 0.586 | CG37: =CG11/CG7 -> 0.58476097 | CI37: 0.589 | CJ37: 0.583 | CK37: 0.593 | CL37: 0.595 | CM37: =CM11/CM7 -> 0.59008617
A38: Adjusted SG&A | C38: =C12/C7 -> 0.25579441 | D38: =D12/D7 -> 0.25802736 | E38: =E12/E7 -> 0.25268168 | F38: =F12/F7 -> 0.2419749 | G38: =G12/G7 -> 0.25196157 | I38: =I12/I7 -> 0.24723072 | J38: =J12/J7 -> 0.23785967 | K38: =K12/K7 -> 0.23591285 | L38: =L12/L7 -> 0.23818295 | M38: =M12/M7 -> 0.2396683 | O38: =O12/O7 -> 0.23887188 | P38: =P12/P7 -> 0.25583581 | Q38: =Q12/Q7 -> 0.23840962 | R38: =R12/R7 -> 0.23031429 | S38: =S12/S7 -> 0.24057018 | U38: =U12/U7 -> 0.23847855 | V38: =V12/V7 -> 0.23400794 | W38: =W12/W7 -> 0.22746491 | X38: =X12/X7 -> 0.2338993 | Y38: =Y12/Y7 -> 0.23348864 | AA38: =AA12/AA7 -> 0.24726166 | AB38: =AB12/AB7 -> 0.23380669 | AC38: =AC12/AC7 -> 0.23975134 | AD38: =AD12/AD7 -> 0.241221 | AE38: =AE12/AE7 -> 0.24044422 | AG38: =AG12/AG7 -> 0.2632886 | AH38: =AH12/AH7 -> 0.2528273 | AI38: =AI12/AI7 -> 0.23687094 | AJ38: =AJ12/AJ7 -> 0.24210351 | AK38: =AK12/AK7 -> 0.24847679 | AM38: =AM12/AM7 -> 0.26096205 | AN38: =AN12/AN7 -> 0.25725676 | AO38: =AO12/AO7 -> 0.24958785 | AP38: =AP12/AP7 -> 0.25238095 | AQ38: =AQ12/AQ7 -> 0.25490489 | AS38: =AS12/AS7 -> 0.26353665 | AT38: =AT12/AT7 -> 0.2480695 | AU38: =AU12/AU7 -> 0.24480712 | AV38: =AV12/AV7 -> 0.24614099 | AW38: =AW12/AW7 -> 0.25042359 | AY38: =AY12/AY7 -> 0.25936796 | AZ38: =AZ12/AZ7 -> 0.24921359 | BA38: =BA12/BA7 -> 0.24302585 | BB38: =BB12/BB7 -> 0.24356048 | BC38: =BC12/BC7 -> 0.24767051 | BE38: =BE12/BE7 -> 0.24897735 | BF38: =BF12/BF7 -> 0.24446434 | BG38: =BG12/BG7 -> 0.2275 | BH38: =BH12/BH7 -> 0.24397032 | BI38: =BI12/BI7 -> 0.24107323 | BK38: =BK12/BK7 -> 0.24332649 | BL38: =BL12/BL7 -> 0.24284271 | BM38: =BM12/BM7 -> 0.2369028 | BN38: =BN12/BN7 -> 0.24443469 | BO38: =BO12/BO7 -> 0.24188567 | BQ38: =BQ12/BQ7 -> 0.25064935 | BR38: =BR12/BR7 -> 0.247 | BS38: =BS12/BS7 -> 0.238 | BT38: =BT12/BT7 -> 0.245 | BU38: =BU12/BU7 -> 0.24472456 | BW38: =BW12/BW7 -> 0.24 | BX38: =BX12/BX7 -> 0.237 | BY38: =BY12/BY7 -> 0.235 | BZ38: =BZ12/BZ7 -> 0.238 | CA38: =CA12/CA7 -> 0.23747688 | CC38: =CC12/CC7 -> 0.23 | CD38: =CD12/CD7 -> 0.227 | CE38: =CE12/CE7 -> 0.225 | CF38: =CF12/CF7 -> 0.228 | CG38: =CG12/CG7 -> 0.22747688 | CI38: =CI12/CI7 -> 0.224 | CJ38: =CJ12/CJ7 -> 0.221 | CK38: =CK12/CK7 -> 0.219 | CL38: =CL12/CL7 -> 0.222 | CM38: =CM12/CM7 -> 0.2214769
A39: Core SG&A | C39: =C13/C7 -> 0.25579441 | D39: =D13/D7 -> 0.25802736 | E39: =E13/E7 -> 0.25268168 | F39: =F13/F7 -> 0.2419749 | G39: =G13/G7 -> 0.25196157 | I39: =I13/I7 -> 0.24723072 | J39: =J13/J7 -> 0.23785967 | K39: =K13/K7 -> 0.23591285 | L39: =L13/L7 -> 0.23818295 | M39: =M13/M7 -> 0.2396683 | O39: =O13/O7 -> 0.23887188 | P39: =P13/P7 -> 0.25583581 | Q39: =Q13/Q7 -> 0.23840962 | R39: =R13/R7 -> 0.23031429 | S39: =S13/S7 -> 0.24057018 | U39: =U13/U7 -> 0.23847855 | V39: =V13/V7 -> 0.23400794 | W39: =W13/W7 -> 0.22746491 | X39: =X13/X7 -> 0.2338993 | Y39: =Y13/Y7 -> 0.23348864 | AA39: =AA13/AA7 -> 0.24726166 | AB39: =AB13/AB7 -> 0.23380669 | AC39: =AC13/AC7 -> 0.23975134 | AD39: =AD13/AD7 -> 0.241221 | AE39: =AE13/AE7 -> 0.24044422 | AG39: =AG13/AG7 -> 0.2632886 | AH39: =AH13/AH7 -> 0.2528273 | AI39: =AI13/AI7 -> 0.23687094 | AJ39: =AJ13/AJ7 -> 0.24210351 | AK39: =AK13/AK7 -> 0.24847679 | AM39: =AM13/AM7 -> 0.26096205 | AN39: =AN13/AN7 -> 0.25025676 | AO39: =AO13/AO7 -> 0.24258785 | AP39: =AP13/AP7 -> 0.24618095 | AQ39: =AQ13/AQ7 -> 0.24976518 | AS39: =AS13/AS7 -> 0.25733665 | AT39: =AT13/AT7 -> 0.2410695 | AU39: =AU13/AU7 -> 0.23780712 | AV39: =AV13/AV7 -> 0.23914099 | AW39: =AW13/AW7 -> 0.24361445 | AY39: =AY13/AY7 -> 0.25316796 | AZ39: =AZ13/AZ7 -> 0.24321359 | BA39: =BA13/BA7 -> 0.23702585 | BB39: =BB13/BB7 -> 0.23756048 | BC39: =BC13/BC7 -> 0.24163068 | BE39: =BE13/BE7 -> 0.24897735 | BF39: =BF13/BF7 -> 0.24446434 | BG39: =BG13/BG7 -> 0.2275 | BH39: =BH13/BH7 -> 0.24397032 | BI39: =BI13/BI7 -> 0.24107323 | BK39: =BK13/BK7 -> 0.24332649 | BL39: =BL13/BL7 -> 0.24284271 | BM39: =BM13/BM7 -> 0.2369028 | BN39: =BN13/BN7 -> 0.24443469 | BO39: =BO13/BO7 -> 0.24188567 | BQ39: =BQ13/BQ7 -> 0.25064935 | BR39: 0.247 | BS39: 0.238 | BT39: 0.245 | BU39: =BU13/BU7 -> 0.24472456 | BW39: 0.24 | BX39: 0.237 | BY39: 0.235 | BZ39: 0.238 | CA39: =CA13/CA7 -> 0.23747688 | CC39: =BW39-0.01 -> 0.23 | CD39: =BX39-0.01 -> 0.227 | CE39: =BY39-0.01 -> 0.225 | CF39: =BZ39-0.01 -> 0.228 | CG39: =CG13/CG7 -> 0.22747688 | CI39: =CC39-0.006 -> 0.224 | CJ39: =CD39-0.006 -> 0.221 | CK39: =CE39-0.006 -> 0.219 | CL39: =CF39-0.006 -> 0.222 | CM39: =CM13/CM7 -> 0.2214769
A40: Medtech Tax | C40: =C14/C7 -> 0 | D40: =D14/D7 -> 0 | E40: =E14/E7 -> 0 | F40: =F14/F7 -> 0 | G40: =G14/G7 -> 0 | I40: =I14/I7 -> 0 | J40: =J14/J7 -> 0 | K40: =K14/K7 -> 0 | L40: =L14/L7 -> 0 | M40: =M14/M7 -> 0 | O40: =O14/O7 -> 0 | P40: =P14/P7 -> 0 | Q40: =Q14/Q7 -> 0 | R40: =R14/R7 -> 0 | S40: =S14/S7 -> 0 | U40: =U14/U7 -> 0 | V40: =V14/V7 -> 0 | W40: =W14/W7 -> 0 | X40: =X14/X7 -> 0 | Y40: =Y14/Y7 -> 0 | AA40: =AA14/AA7 -> 0 | AB40: =AB14/AB7 -> 0 | AC40: =AC14/AC7 -> 0 | AD40: =AD14/AD7 -> 0 | AE40: =AE14/AE7 -> 0 | AG40: =AG14/AG7 -> 0 | AH40: =AH14/AH7 -> 0 | AI40: =AI14/AI7 -> 0 | AJ40: =AJ14/AJ7 -> 0 | AK40: =AK14/AK7 -> 0 | AM40: =AM14/AM7 -> 0 | AN40: 0.007 | AO40: 0.007 | AP40: 0.0062 | AQ40: =AQ14/AQ7 -> 0.0051397101 | AS40: 0.0062 | AT40: 0.007 | AU40: 0.007 | AV40: 0.007 | AW40: =AW14/AW7 -> 0.0068091429 | AY40: 0.0062 | AZ40: 0.006 | BA40: 0.006 | BB40: 0.006 | BC40: =BC14/BC7 -> 0.0060398218 | BE40: 0 | BF40: 0 | BG40: 0 | BH40: 0 | BI40: =BI14/BI7 -> 0 | BK40: 0 | BL40: 0 | BM40: 0 | BN40: 0 | BO40: =BO14/BO7 -> 0 | BQ40: 0 | BR40: 0 | BS40: 0 | BT40: 0 | BU40: =BU14/BU7 -> 0 | BW40: 0 | BX40: 0 | BY40: 0 | BZ40: 0 | CA40: =CA14/CA7 -> 0 | CC40: 0 | CD40: 0 | CE40: 0 | CF40: 0 | CG40: =CG14/CG7 -> 0 | CI40: 0 | CJ40: 0 | CK40: 0 | CL40: 0 | CM40: =CM14/CM7 -> 0
A41: R&D | C41: =C15/C7 -> 0.053238888 | D41: =D15/D7 -> 0.055007164 | E41: =E15/E7 -> 0.057010383 | F41: =F15/F7 -> 0.060826079 | G41: =G15/G7 -> 0.056614163 | I41: =I15/I7 -> 0.053657387 | J41: =J15/J7 -> 0.054973167 | K41: =K15/K7 -> 0.053583017 | L41: =L15/L7 -> 0.059165486 | M41: =M15/M7 -> 0.055372125 | O41: =O15/O7 -> 0.057589645 | P41: =P15/P7 -> 0.058046202 | Q41: =Q15/Q7 -> 0.054954124 | R41: =R15/R7 -> 0.060889212 | S41: =S15/S7 -> 0.057905123 | U41: =U15/U7 -> 0.053055461 | V41: =V15/V7 -> 0.05568106 | W41: =W15/W7 -> 0.059012699 | X41: =X15/X7 -> 0.065986723 | Y41: =Y15/Y7 -> 0.058461412 | AA41: =AA15/AA7 -> 0.063682263 | AB41: =AB15/AB7 -> 0.063066816 | AC41: =AC15/AC7 -> 0.058444922 | AD41: =AD15/AD7 -> 0.057971583 | AE41: =AE15/AE7 -> 0.060686275 | AG41: =AG15/AG7 -> 0.061268644 | AH41: =AH15/AH7 -> 0.060526366 | AI41: =AI15/AI7 -> 0.058058701 | AJ41: =AJ15/AJ7 -> 0.063943094 | AK41: =AK15/AK7 -> 0.060940675 | AM41: =AM15/AM7 -> 0.062184242 | AN41: =AN15/AN7 -> 0.061177029 | AO41: =AO15/AO7 -> 0.059004299 | AP41: =AP15/AP7 -> 0.063333333 | AQ41: =AQ15/AQ7 -> 0.061423173 | AS41: =AS15/AS7 -> 0.062534121 | AT41: =AT15/AT7 -> 0.061293436 | AU41: =AU15/AU7 -> 0.059347181 | AV41: =AV15/AV7 -> 0.060399911 | AW41: =AW15/AW7 -> 0.060859444 | AY41: =AY15/AY7 -> 0.062891855 | AZ41: =AZ15/AZ7 -> 0.062913019 | BA41: =BA15/BA7 -> 0.057484839 | BB41: =BB15/BB7 -> 0.063906097 | BC41: =BC15/BC7 -> 0.061553605 | BE41: =BE15/BE7 -> 0.062494987 | BF41: =BF15/BF7 -> 0.059182677 | BG41: =BG15/BG7 -> 0.0646875 | BH41: =BH15/BH7 -> 0.078231293 | BI41: =BI15/BI7 -> 0.066314642 | BK41: =BK15/BK7 -> 0.062286105 | BL41: =BL15/BL7 -> 0.06298417 | BM41: =BM15/BM7 -> 0.060955519 | BN41: =BN15/BN7 -> 0.069793367 | BO41: =BO15/BO7 -> 0.064089365 | BQ41: =BQ15/BQ7 -> 0.062337662 | BR41: 0.065 | BS41: 0.066 | BT41: 0.068 | BU41: =BU15/BU7 -> 0.065577306 | BW41: 0.067 | BX41: 0.066 | BY41: 0.066 | BZ41: 0.066 | CA41: =CA15/CA7 -> 0.066242462 | CC41: =BW41-0.003 -> 0.064 | CD41: =BX41-0.003 -> 0.063 | CE41: =BY41-0.003 -> 0.063 | CF41: =BZ41-0.003 -> 0.063 | CG41: =CG15/CG7 -> 0.063242489 | CI41: =CC41-0.0015 -> 0.0625 | CJ41: =CD41-0.0015 -> 0.0615 | CK41: =CE41-0.0015 -> 0.0615 | CL41: =CF41-0.0015 -> 0.0615 | CM41: =CM15/CM7 -> 0.061742517
A42: Operating Income | C42: =C17/C7 -> 0.21882755 | D42: =D17/D7 -> 0.20182725 | E42: =E17/E7 -> 0.20533314 | F42: =F17/F7 -> 0.20820592 | G42: =G17/G7 -> 0.20839626 | I42: =I17/I7 -> 0.21261755 | J42: =J17/J7 -> 0.21841865 | K42: =K17/K7 -> 0.21930265 | L42: =L17/L7 -> 0.21696245 | M42: =M17/M7 -> 0.216893 | O42: =O17/O7 -> 0.24001583 | P42: =P17/P7 -> 0.20643059 | Q42: =Q17/Q7 -> 0.23458562 | R42: =R17/R7 -> 0.22865304 | S42: =S17/S7 -> 0.22752902 | U42: =U17/U7 -> 0.22991538 | V42: =V17/V7 -> 0.22987992 | W42: =W17/W7 -> 0.23101178 | X42: =X17/X7 -> 0.21915337 | Y42: =Y17/Y7 -> 0.22744456 | AA42: =AA17/AA7 -> 0.21794033 | AB42: =AB17/AB7 -> 0.2241115 | AC42: =AC17/AC7 -> 0.22910678 | AD42: =AD17/AD7 -> 0.21240068 | AE42: =AE17/AE7 -> 0.22087597 | AG42: =AG17/AG7 -> 0.18384742 | AH42: =AH17/AH7 -> 0.19872356 | AI42: =AI17/AI7 -> 0.22671608 | AJ42: =AJ17/AJ7 -> 0.20780095 | AK42: =AK17/AK7 -> 0.2046973 | AM42: =AM17/AM7 -> 0.21574613 | AN42: =AN17/AN7 -> 0.20047216 | AO42: =AO17/AO7 -> 0.21752033 | AP42: =AP17/AP7 -> 0.21051251 | AQ42: =AQ17/AQ7 -> 0.21103964 | AS42: =AS17/AS7 -> 0.1967244 | AT42: =AT17/AT7 -> 0.20776062 | AU42: =AU17/AU7 -> 0.2194362 | AV42: =AV17/AV7 -> 0.21204002 | AW42: =AW17/AW7 -> 0.20922506 | AY42: =AY17/AY7 -> 0.19605683 | AZ42: =AZ17/AZ7 -> 0.20602795 | BA42: =BA17/BA7 -> 0.21931056 | BB42: =BB17/BB7 -> 0.21682426 | BC42: =BC17/BC7 -> 0.21129651 | BE42: =BE17/BE7 -> 0.21196161 | BF42: =BF17/BF7 -> 0.22557799 | BG42: =BG17/BG7 -> 0.2340625 | BH42: =BH17/BH7 -> 0.20006184 | BI42: =BI17/BI7 -> 0.21788731 | BK42: =BK17/BK7 -> 0.23750856 | BL42: =BL17/BL7 -> 0.220613 | BM42: =BM17/BM7 -> 0.24085667 | BN42: =BN17/BN7 -> 0.21806164 | BO42: =BO17/BO7 -> 0.22910831 | BQ42: =BQ17/BQ7 -> 0.23538961 | BR42: =BR17/BR7 -> 0.253 | BS42: =BS17/BS7 -> 0.269 | BT42: =BT17/BT7 -> 0.262 | BU42: =BU17/BU7 -> 0.25638353 | BW42: =BW17/BW7 -> 0.268 | BX42: =BX17/BX7 -> 0.273 | BY42: =BY17/BY7 -> 0.274 | BZ42: =BZ17/BZ7 -> 0.273 | CA42: =CA17/CA7 -> 0.27204169 | CC42: =CC17/CC7 -> 0.29 | CD42: =CD17/CD7 -> 0.295 | CE42: =CE17/CE7 -> 0.296 | CF42: =CF17/CF7 -> 0.295 | CG42: =CG17/CG7 -> 0.2940416 | CI42: =CI17/CI7 -> 0.3025 | CJ42: =CJ17/CJ7 -> 0.3005 | CK42: =CK17/CK7 -> 0.3125 | CL42: =CL17/CL7 -> 0.3115 | CM42: =CM17/CM7 -> 0.30686675
A43: Incremetal Operating Profit | C43: 0.16777321 | D43: 0.15397291 | E43: 0.27824476 | F43: 0.26930999 | G43: 0.22606593 | I43: =(I17-C17)/(I7-C7) -> 0.16696126 | J43: =(J17-D17)/(J7-D7) -> 0.37132097 | K43: =(K17-E17)/(K7-E7) -> 0.31568039 | L43: =(L17-F17)/(L7-F7) -> 0.29531242 | M43: =(M17-G17)/(M7-G7) -> 0.2847619 | O43: =(O17-I17)/(O7-I7) -> -1.1927404 | P43: =(P17-J17)/(P7-J7) -> 0.53476632 | Q43: =(Q17-K17)/(Q7-K7) -> -0.078450082 | R43: =(R17-L17)/(R7-L7) -> 1.3954437 | S43: =(S17-M17)/(S7-M7) -> -0.22232533 | U43: =(U17-O17)/(U7-O7) -> 0.14354781 | V43: =(V17-P17)/(V7-P7) -> 0.5693447 | W43: =(W17-Q17)/(W7-Q7) -> 0.11452791 | X43: =(X17-R17)/(X7-R7) -> -0.6995097 | Y43: =(Y17-S17)/(Y7-S7) -> 0.2259142 | AA43: =(AA17-U17)/(AA7-U7) -> 0.47979449 | AB43: =(AB17-V17)/(AB7-V7) -> 0.054521689 | AC43: =(AC17-W17)/(AC7-W7) -> 0.20027608 | AD43: =(AD17-X17)/(AD7-X7) -> 0.10239507 | AE43: =(AE17-Y17)/(AE7-Y7) -> -0.0078661456 | AG43: =(AG17-AA17)/(AG7-AA7) -> -1.0732204 | AH43: =(AH17-AB17)/(AH7-AB7) -> -0.49241371 | AI43: =(AI17-AC17)/(AI7-AC7) -> 0.063789672 | AJ43: =(AJ17-AD17)/(AJ7-AD7) -> 0.64307473 | AK43: =(AK17-AE17)/(AK7-AE7) -> -0.78207606 | AM43: =(AM17-AG17)/(AM7-AG7) -> 1.0690804 | AN43: =(AN17-AH17)/(AN7-AH7) -> 0.24770353 | AO43: =(AO17-AI17)/(AO7-AI7) -> -0.034960629 | AP43: =(AP17-AJ17)/(AP7-AJ7) -> 0.25067022 | AQ43: =(AQ17-AK17)/(AQ7-AK7) -> 0.35280949 | AS43: =(AS17-AM17)/(AS7-AM7) -> -0.11837949 | AT43: =(AT17-AN17)/(AT7-AN7) -> 0.41131588 | AU43: =(AU17-AO17)/(AU7-AO7) -> 0.25720068 | AV43: =(AV17-AP17)/(AV7-AP7) -> 0.24349176 | AW43: =(AW17-AQ17)/(AW7-AQ7) -> 0.17198994 | AY43: =(AY17-AS17)/(AY7-AS7) -> 0.1589404 | AZ43: =(AZ17-AT17)/(AZ7-AT7) -> 0.37262181 | BA43: =(BA17-AU17)/(BA7-AU7) -> 0.21903299 | BB43: =(BB17-AV17)/(BB7-AV7) -> 0.22900313 | BC43: =(BC17-AW17)/(BC7-AW7) -> 0.2207231 | BE43: =(BE17-AY17)/(BE7-AY7) -> 0.24662629 | BF43: =(BF17-AZ17)/(BF7-AZ7) -> 0.26485718 | BG43: =(BG17-BA17)/(BG7-BA7) -> 0.9238806 | BH43: =(BH17-BB17)/(BH7-BB7) -> -0.10778443 | BI43: =(BI17-BC17)/(BI7-BC7) -> 0.24881015 | BK43: =(BK17-BE17)/(BK7-BE7) -> -0.85079727 | BL43: =(BL17-BF17)/(BL7-BF7) -> 0.37009804 | BM43: =(BM17-BG17)/(BM7-BG7) -> 0.10909091 | BN43: =(BN17-BH17)/(BN7-BH7) -> -0.64420086 | BO43: =(BO17-BI17)/(BO7-BI7) -> -0.11735639 | BQ43: =(BQ17-BK17)/(BQ7-BK7) -> 0.19620253 | BR43: =(BR17-BL17)/(BR7-BL7) -> 0.33369902 | BS43: =(BS17-BM17)/(BS7-BM7) -> 0.33651614 | BT43: =(BT17-BN17)/(BT7-BN7) -> 0.37859501 | BU43: =(BU17-BO17)/(BU7-BO7) -> 0.3429988 | BW43: =(BW17-BQ17)/(BW7-BQ7) -> 0.34885437 | BX43: =(BX17-BR17)/(BX7-BR7) -> 0.64212297 | BY43: =(BY17-BS17)/(BY7-BS7) -> 0.36835152 | BZ43: =(BZ17-BT17)/(BZ7-BT7) -> 0.48107067 | CA43: =(CA17-BU17)/(CA7-BU7) -> 0.40130863 | CC43: =(CC17-BW17)/(CC7-BW7) -> 0.70223115 | CD43: =(CD17-BX17)/(CD7-BX7) -> 0.71075526 | CE43: =(CE17-BY17)/(CE7-BY7) -> 0.70783036 | CF43: =(CF17-BZ17)/(CF7-BZ7) -> 0.70781343 | CG43: =(CG17-CA17)/(CG7-CA7) -> 0.70718052 | CI43: =(CI17-CC17)/(CI7-CC7) -> 0.53541203 | CJ43: =(CJ17-CD17)/(CJ7-CD7) -> 0.40387568 | CK43: =(CK17-CE17)/(CK7-CE7) -> 0.61967044 | CL43: =(CL17-CF17)/(CL7-CF7) -> 0.61941719 | CM43: =(CM17-CG17)/(CM7-CG7) -> 0.54638765
A44: Pretax Income | C44: =C23/C7 -> 0.21941228 | D44: =D23/D7 -> 0.20390349 | E44: =E23/E7 -> 0.20662915 | F44: =F23/F7 -> 0.2048633 | G44: =G23/G7 -> 0.2085134 | I44: =I23/I7 -> 0.21490157 | J44: =J23/J7 -> 0.21883939 | K44: =K23/K7 -> 0.21965284 | L44: =L23/L7 -> 0.21394006 | M44: =M23/M7 -> 0.21685625 | O44: =O23/O7 -> 0.2419511 | P44: =P23/P7 -> 0.20115237 | Q44: =Q23/Q7 -> 0.23302798 | R44: =R23/R7 -> 0.22720969 | S44: =S23/S7 -> 0.22594187 | U44: =U23/U7 -> 0.22640942 | V44: =V23/V7 -> 0.2281588 | W44: =W23/W7 -> 0.22577449 | X44: =X23/X7 -> 0.22107576 | Y44: =Y23/Y7 -> 0.22532352 | AA44: =AA23/AA7 -> 0.21517756 | AB44: =AB23/AB7 -> 0.21772705 | AC44: =AC23/AC7 -> 0.22294813 | AD44: =AD23/AD7 -> 0.20277027 | AE44: =AE23/AE7 -> 0.21455032 | AG44: =AG23/AG7 -> 0.17603236 | AH44: =AH23/AH7 -> 0.19156686 | AI44: =AI23/AI7 -> 0.21132778 | AJ44: =AJ23/AJ7 -> 0.19413615 | AK44: =AK23/AK7 -> 0.19360833 | AM44: =AM23/AM7 -> 0.20185648 | AN44: =AN23/AN7 -> 0.1901436 | AO44: =AO23/AO7 -> 0.20510135 | AP44: =AP23/AP7 -> 0.20241727 | AQ44: =AQ23/AQ7 -> 0.19992038 | AS44: =AS23/AS7 -> 0.18729465 | AT44: =AT23/AT7 -> 0.19521236 | AU44: =AU23/AU7 -> 0.20877226 | AV44: =AV23/AV7 -> 0.20068665 | AW44: =AW23/AW7 -> 0.19821353 | AY44: =AY23/AY7 -> 0.18630615 | AZ44: =AZ23/AZ7 -> 0.19676169 | BA44: =BA23/BA7 -> 0.18707309 | BB44: =BB23/BB7 -> 0.17965439 | BC44: =BC23/BC7 -> 0.18664012 | BE44: =BE23/BE7 -> 0.18088121 | BF44: =BF23/BF7 -> 0.19366656 | BG44: =BG23/BG7 -> 0.2025 | BH44: =BH23/BH7 -> 0.17068646 | BI44: =BI23/BI7 -> 0.18692047 | BK44: =BK23/BK7 -> 0.20910335 | BL44: =BL23/BL7 -> 0.19299427 | BM44: =BM23/BM7 -> 0.21186161 | BN44: =BN23/BN7 -> 0.1940603 | BO44: =BO23/BO7 -> 0.20190135 | BQ44: =BQ23/BQ7 -> 0.21103896 | BR44: =BR23/BR7 -> 0.21977013 | BS44: =BS23/BS7 -> 0.23696385 | BT44: =BT23/BT7 -> 0.23131074 | BU44: =BU23/BU7 -> 0.22589306 | BW44: =BW23/BW7 -> 0.23798563 | BX44: =BX23/BX7 -> 0.24442535 | BY44: =BY23/BY7 -> 0.2469545 | BZ44: =BZ23/BZ7 -> 0.24075226 | CA44: =CA23/CA7 -> 0.24256057 | CC44: =CC23/CC7 -> 0.25622518 | CD44: =CD23/CD7 -> 0.26274527 | CE44: =CE23/CE7 -> 0.26599467 | CF44: =CF23/CF7 -> 0.26639705 | CG44: =CG23/CG7 -> 0.26293007 | CI44: =CI23/CI7 -> 0.27493743 | CJ44: =CJ23/CJ7 -> 0.27405185 | CK44: =CK23/CK7 -> 0.288156 | CL44: =CL23/CL7 -> 0.2888077 | CM44: =CM23/CM7 -> 0.28165017
A45: Net Income | C45: =C31/C7 -> 0.16369792 | D45: =D31/D7 -> 0.14946126 | E45: =E31/E7 -> 0.15195514 | F45: =F31/F7 -> 0.15087387 | G45: =G31/G7 -> 0.15382893 | I45: =I31/I7 -> 0.15881184 | J45: =J31/J7 -> 0.15778296 | K45: =K31/K7 -> 0.15924819 | L45: =L31/L7 -> 0.15372044 | M45: =M31/M7 -> 0.1573685 | O45: =O31/O7 -> 0.18651548 | P45: =P31/P7 -> 0.15523883 | Q45: =Q31/Q7 -> 0.1919755 | R45: =R31/R7 -> 0.1710982 | S45: =S31/S7 -> 0.1762778 | U45: =U31/U7 -> 0.16929203 | V45: =V31/V7 -> 0.16540486 | W45: =W31/W7 -> 0.16762584 | X45: =X31/X7 -> 0.21177453 | Y45: =Y31/Y7 -> 0.17872361 | AA45: =AA31/AA7 -> 0.1771593 | AB45: =AB31/AB7 -> 0.16769679 | AC45: =AC31/AC7 -> 0.17575692 | AD45: =AD31/AD7 -> 0.15389947 | AE45: =AE31/AE7 -> 0.16837927 | AG45: =AG31/AG7 -> 0.14357271 | AH45: =AH31/AH7 -> 0.15087552 | AI45: =AI31/AI7 -> 0.16503966 | AJ45: =AJ31/AJ7 -> 0.15354181 | AK45: =AK31/AK7 -> 0.15345983 | AM45: =AM31/AM7 -> 0.33572663 | AN45: =AN31/AN7 -> 0.14475198 | AO45: =AO31/AO7 -> 0.1605274 | AP45: =AP31/AP7 -> 0.15159685 | AQ45: =AQ31/AQ7 -> 0.19561906 | AS45: =AS31/AS7 -> 0.14073095 | AT45: =AT31/AT7 -> 0.15186236 | AU45: =AU31/AU7 -> 0.15970827 | AV45: =AV31/AV7 -> 0.15574558 | AW45: =AW31/AW7 -> 0.1522228 | AY45: =AY31/AY7 -> 0.1472547 | AZ45: =AZ31/AZ7 -> 0.15481967 | BA45: =BA31/BA7 -> 0.14079157 | BB45: =BB31/BB7 -> 0.13661559 | BC45: =BC31/BC7 -> 0.14362734 | BE45: =BE31/BE7 -> 0.14198059 | BF45: =BF31/BF7 -> 0.15380983 | BG45: =BG31/BG7 -> 0.159375 | BH45: =BH31/BH7 -> 0.14285714 | BI45: =BI31/BI7 -> 0.14956822 | BK45: =BK31/BK7 -> 0.17351129 | BL45: =BL31/BL7 -> 0.16874368 | BM45: =BM31/BM7 -> 0.17693575 | BN45: =BN31/BN7 -> 0.16563766 | BO45: =BO31/BO7 -> 0.17113845 | BQ45: =BQ31/BQ7 -> 0.17662338 | BR45: =BR31/BR7 -> 0.1732082 | BS45: =BS31/BS7 -> 0.1877776 | BT45: =BT31/BT7 -> 0.18320734 | BU45: =BU31/BU7 -> 0.18055157 | BW45: =BW31/BW7 -> 0.18926621 | BX45: =BX31/BX7 -> 0.19475601 | BY45: =BY31/BY7 -> 0.19713525 | BZ45: =BZ31/BZ7 -> 0.19208658 | CA45: =CA31/CA7 -> 0.19334191 | CC45: =CC31/CC7 -> 0.21394802 | CD45: =CD31/CD7 -> 0.2193923 | CE45: =CE31/CE7 -> 0.22210555 | CF45: =CF31/CF7 -> 0.22244154 | CG45: =CG31/CG7 -> 0.21954661 | CI45: =CI31/CI7 -> 0.22957275 | CJ45: =CJ31/CJ7 -> 0.2288333 | CK45: =CK31/CK7 -> 0.24061026 | CL45: =CL31/CL7 -> 0.24115443 | CM45: =CM31/CM7 -> 0.23517789
A47: Growth Rate Analysis
A48: Revenue Growth | C48: 0.077263476 | D48: 0.10652595 | E48: 0.11926527 | F48: 0.12878275 | G48: 0.10832689 | I48: =I7/C7-1 -> 0.13601623 | J48: =J7/D7-1 -> 0.10850981 | K48: =K7/E7-1 -> 0.1449454 | L48: =L7/F7-1 -> 0.11176179 | M48: =M7/G7-1 -> 0.12519348 | O48: =O7/I7-1 -> -0.019122776 | P48: =P7/J7-1 -> -0.036511585 | Q48: =Q7/K7-1 -> -0.048821796 | R48: =R7/L7-1 -> 0.010019443 | S48: =S7/M7-1 -> -0.023643251 | U48: =U7/O7-1 -> 0.11694722 | V48: =V7/P7-1 -> 0.069077357 | W48: =W7/Q7-1 -> 0.030680997 | X48: =X7/R7-1 -> 0.010340756 | Y48: =Y7/S7-1 -> 0.055191977 | AA48: =AA7/U7-1 -> -0.045731741 | AB48: =AB7/V7-1 -> 0.034013946 | AC48: =AC7/W7-1 -> 0.066075303 | AD48: =AD7/X7-1 -> 0.06138496 | AE48: =AE7/Y7-1 -> 0.028716107 | AG48: =AG7/AA7-1 -> 0.02712098 | AH48: =AH7/AB7-1 -> 0.036733573 | AI48: =AI7/AC7-1 -> 0.014673478 | AJ48: =AJ7/AD7-1 -> -0.010567448 | AK48: =AK7/AE7-1 -> 0.016395528 | AM48: =AM7/AG7-1 -> 0.037381259 | AN48: =AN7/AH7-1 -> 0.037022003 | AO48: =AO7/AI7-1 -> 0.036421564 | AP48: =AP7/AJ7-1 -> 0.067522854 | AQ48: =AQ7/AK7-1 -> 0.044736885 | AS48: =AS7/AM7-1 -> 0.060366531 | AT48: =AT7/AN7-1 -> 0.035805786 | AU48: =AU7/AO7-1 -> 0.050732122 | AV48: =AV7/AP7-1 -> 0.048566667 | AW48: =AW7/AQ7-1 -> 0.048733111 | AY48: =AY7/AS7-1 -> 0.017986004 | AZ48: =AZ7/AT7-1 -> -0.010400579 | BA48: =BA7/AU7-1 -> 0.45261499 | BB48: =BB7/AV7-1 -> 0.39283103 | BC48: =BC7/AW7-1 -> 0.21974522 | BE48: =BE7/AY7-1 -> 0.45881802 | BF48: =BF7/AZ7-1 -> 0.49772001 | BG48: =BG7/BA7-1 -> 0.021385254 | BH48: =BH7/BB7-1 -> 0.054450603 | BI48: =BI7/BC7-1 -> 0.213137 | BK48: =BK7/BE7-1 -> -0.023474053 | BL48: =BL7/BF7-1 -> -0.033213937 | BM48: =BM7/BG7-1 -> -0.0515625 | BN48: =BN7/BH7-1 -> -0.020875077 | BO48: =BO7/BI7-1 -> -0.032387151 | BQ48: =BQ7/BK7-1 -> 0.054072553 | BR48: =BR7/BL7-1 -> 0.40133075 | BS48: =BS7/BM7-1 -> 0.41683855 | BT48: =BT7/BN7-1 -> 0.37684597 | BU48: =BU7/BO7-1 -> 0.31490082 | BW48: =BW7/BQ7-1 -> 0.40332253 | BX48: =BX7/BR7-1 -> 0.054182485 | BY48: =BY7/BS7-1 -> 0.052993318 | BZ48: =BZ7/BT7-1 -> 0.052866653 | CA48: =CA7/BU7-1 -> 0.12113045 | CC48: =CC7/BW7-1 -> 0.053368116 | CD48: =CD7/BX7-1 -> 0.052915747 | CE48: =CE7/BY7-1 -> 0.053420053 | CF48: =CF7/BZ7-1 -> 0.05329284 | CG48: =CG7/CA7-1 -> 0.053250625 | CI48: =CI7/CC7-1 -> 0.053668331 | CJ48: =CJ7/CD7-1 -> 0.053204001 | CK48: =CK7/CE7-1 -> 0.053716107 | CL48: =CL7/CF7-1 -> 0.053585836 | CM48: =CM7/CG7-1 -> 0.053545019
A49: Gross Profit | C49: 0.088894689 | D49: 0.11846725 | E49: 0.13858827 | F49: 0.11945909 | G49: 0.11645281 | I49: =I11/C11-1 -> 0.10512225 | J49: =J11/D11-1 -> 0.10073677 | K49: =K11/E11-1 -> 0.13110293 | L49: =L11/F11-1 -> 0.11895004 | M49: =M11/G11-1 -> 0.11422701 | O49: =O11/I11-1 -> 0.024756799 | P49: =P11/J11-1 -> -0.019435282 | Q49: =Q11/K11-1 -> -0.01302006 | R49: =R11/L11-1 -> 0.020910193 | S49: =S11/M11-1 -> 0.0031927061 | U49: =U11/O11-1 -> 0.085658964 | V49: =V11/P11-1 -> 0.067549329 | W49: =W11/Q11-1 -> 0.010260659 | X49: =X11/R11-1 -> 0.0087526172 | Y49: =Y11/S11-1 -> 0.041932536 | AA49: =AA11/U11-1 -> -0.032125698 | AB49: =AB11/V11-1 -> 0.036832147 | AC49: =AC11/W11-1 -> 0.086292332 | AD49: =AD11/X11-1 -> 0.04615834 | AE49: =AE11/Y11-1 -> 0.033889166 | AG49: =AG11/AA11-1 -> -0.012651458 | AH49: =AH11/AB11-1 -> 0.019007543 | AI49: =AI11/AC11-1 -> 0.0037872715 | AJ49: =AJ11/AD11-1 -> -0.0062076017 | AK49: =AK11/AE11-1 -> 0.0010296504 | AM49: =AM11/AG11-1 -> 0.099590418 | AN49: =AN11/AH11-1 -> 0.050851052 | AO49: =AO11/AI11-1 -> 0.045296258 | AP49: =AP11/AJ11-1 -> 0.09324085 | AQ49: =AQ11/AK11-1 -> 0.071668307 | AS49: =AS11/AM11-1 -> 0.028692335 | AT49: =AT11/AN11-1 -> 0.032247871 | AU49: =AU11/AO11-1 -> 0.045695324 | AV49: =AV11/AP11-1 -> 0.033331387 | AW49: =AW11/AQ11-1 -> 0.035091949 | AY49: =AY11/AS11-1 -> 0.0092654123 | AZ49: =AZ11/AT11-1 -> -0.0084275955 | BA49: =BA11/AU11-1 -> 0.44215784 | BB49: =BB11/AV11-1 -> 0.40816702 | BC49: =BC11/AW11-1 -> 0.21977457 | BE49: =BE11/AY11-1 -> 0.47322084 | BF49: =BF11/AZ11-1 -> 0.52971905 | BG49: =BG11/BA11-1 -> 0.034016947 | BH49: =BH11/BB11-1 -> 0.050373134 | BI49: =BI11/BC11-1 -> 0.22421809 | BK49: =BK11/BE11-1 -> 0.013254674 | BL49: =BL11/BF11-1 -> -0.0383018 | BM49: =BM11/BG11-1 -> -0.029097387 | BN49: =BN11/BH11-1 -> -0.0020781528 | BO49: =BO11/BI11-1 -> -0.014319467 | BQ49: =BQ11/BK11-1 -> 0.064272212 | BR49: =BR11/BL11-1 -> 0.50397397 | BS49: =BS11/BM11-1 -> 0.50700928 | BT49: =BT11/BN11-1 -> 0.48732248 | BU49: =BU11/BO11-1 -> 0.39255893 | BW49: =BW11/BQ11-1 -> 0.47145305 | BX49: =BX11/BR11-1 -> 0.074706392 | BY49: =BY11/BS11-1 -> 0.056668687 | BZ49: =BZ11/BT11-1 -> 0.056528798 | CA49: =CA11/BU11-1 -> 0.13908568 | CC49: =CC11/BW11-1 -> 0.069855617 | CD49: =CD11/BX11-1 -> 0.069367555 | CE49: =CE11/BY11-1 -> 0.069908367 | CF49: =CF11/BZ11-1 -> 0.069722018 | CG49: =CG11/CA11-1 -> 0.069714391 | CI49: =CI11/CC11-1 -> 0.062689464 | CJ49: =CJ11/CD11-1 -> 0.049603304 | CK49: =CK11/CE11-1 -> 0.069954883 | CL49: =CL11/CF11-1 -> 0.069767189 | CM49: =CM11/CG11-1 -> 0.063139246
A50: SG&A | C50: 0.12044209 | D50: 0.14118971 | E50: 0.12038044 | F50: 0.056240284 | G50: 0.098917407 | I50: =I12/C12-1 -> 0.097983774 | J50: =J12/D12-1 -> 0.021867492 | K50: =K12/E12-1 -> 0.06896284 | L50: =L12/F12-1 -> 0.094339528 | M50: =M12/G12-1 -> 0.070295007 | O50: =O12/I12-1 -> -0.052286125 | P50: =P12/J12-1 -> 0.036303646 | Q50: =Q12/K12-1 -> -0.038755027 | R50: =R12/L12-1 -> -0.023347727 | S50: =S12/M12-1 -> -0.019969155 | U50: =U12/O12-1 -> 0.11510804 | V50: =V12/P12-1 -> -0.022136142 | W50: =W12/Q12-1 -> -0.016634672 | X50: =X12/R12-1 -> 0.026067427 | Y50: =Y12/S12-1 -> 0.024130814 | AA50: =AA12/U12-1 -> -0.010586237 | AB50: =AB12/V12-1 -> 0.033124662 | AC50: =AC12/W12-1 -> 0.12365896 | AD50: =AD12/X12-1 -> 0.094609245 | AE50: =AE12/Y12-1 -> 0.059361341 | AG50: =AG12/AA12-1 -> 0.093696636 | AH50: =AH12/AB12-1 -> 0.12107378 | AI50: =AI12/AC12-1 -> 0.0024830758 | AJ50: =AJ12/AD12-1 -> -0.0069475866 | AK50: =AK12/AE12-1 -> 0.050350473 | AM50: =AM12/AG12-1 -> 0.028214427 | AN50: =AN12/AH12-1 -> 0.055190345 | AO50: =AO12/AI12-1 -> 0.092064033 | AP50: =AP12/AJ12-1 -> 0.11283986 | AQ50: =AQ12/AK12-1 -> 0.07176428 | AS50: =AS12/AM12-1 -> 0.070827905 | AT50: =AT12/AN12-1 -> -0.0011853637 | AU50: =AU12/AO12-1 -> 0.030605871 | AV50: =AV12/AP12-1 -> 0.022641509 | AW50: =AW12/AQ12-1 -> 0.030296063 | AY50: =AY12/AS12-1 -> 0.0018832392 | AZ50: =AZ12/AT12-1 -> -0.0058365759 | BA50: =BA12/AU12-1 -> 0.44204545 | BB50: =BB12/AV12-1 -> 0.37822878 | BC50: =BC12/AW12-1 -> 0.2063357 | BE50: =BE12/AY12-1 -> 0.40037594 | BF50: =BF12/AZ12-1 -> 0.46917808 | BG50: =BG12/BA12-1 -> -0.043866562 | BH50: =BH12/BB12-1 -> 0.0562249 | BI50: =BI12/BC12-1 -> 0.18082229 | BK50: =BK12/BE12-1 -> -0.045637584 | BL50: =BL12/BF12-1 -> -0.03962704 | BM50: =BM12/BG12-1 -> -0.012362637 | BN50: =BN12/BH12-1 -> -0.019011407 | BO50: =BO12/BI12-1 -> -0.029126214 | BQ50: =BQ12/BK12-1 -> 0.085794655 | BR50: =BR12/BL12-1 -> 0.42532052 | BS50: =BS12/BM12-1 -> 0.42340054 | BT50: =BT12/BN12-1 -> 0.38003024 | BU50: =BU12/BO12-1 -> 0.33033316 | BW50: =BW12/BQ12-1 -> 0.3436995 | BX50: =BX12/BR12-1 -> 0.011503032 | BY50: =BY12/BS12-1 -> 0.039720293 | BZ50: =BZ12/BT12-1 -> 0.022784749 | CA50: =CA12/BU12-1 -> 0.087927411 | CC50: =CC12/BW12-1 -> 0.0094777782 | CD50: =CD12/BX12-1 -> 0.0084889218 | CE50: =CE12/BY12-1 -> 0.0085936681 | CF50: =CF12/BZ12-1 -> 0.0090368383 | CG50: =CG12/CA12-1 -> 0.0088989551 | CI50: =CI12/CC12-1 -> 0.026181331 | CJ50: =CJ12/CD12-1 -> 0.02536601 | CK50: =CK12/CE12-1 -> 0.025617011 | CL50: =CL12/CF12-1 -> 0.025859893 | CM50: =CM12/CG12-1 -> 0.025756451
A51: R&D | C51: 0.16941442 | D51: 0.16491299 | E51: 0.21244084 | F51: 0.21882547 | G51: 0.19272407 | I51: =I15/C15-1 -> 0.14494621 | J51: =J15/D15-1 -> 0.1078247 | K51: =K15/E15-1 -> 0.076113256 | L51: =L15/F15-1 -> 0.081409937 | M51: =M15/G15-1 -> 0.10050826 | O51: =O15/I15-1 -> 0.052760388 | P51: =P15/J15-1 -> 0.017348023 | Q51: =Q15/K15-1 -> -0.024482617 | R51: =R15/L15-1 -> 0.039445335 | S51: =S15/M15-1 -> 0.021020195 | U51: =U15/O15-1 -> 0.029007016 | V51: =V15/P15-1 -> 0.025516888 | W51: =W15/Q15-1 -> 0.10680079 | X51: =X15/R15-1 -> 0.094924263 | Y51: =Y15/S15-1 -> 0.065329105 | AA51: =AA15/U15-1 -> 0.14540448 | AB51: =AB15/V15-1 -> 0.17116964 | AC51: =AC15/W15-1 -> 0.055818301 | AD51: =AD15/X15-1 -> -0.067537175 | AE51: =AE15/Y15-1 -> 0.067865902 | AG51: =AG15/AA15-1 -> -0.011807904 | AH51: =AH15/AB15-1 -> -0.0050279949 | AI51: =AI15/AC15-1 -> 0.0079682323 | AJ51: =AJ15/AD15-1 -> 0.091351576 | AK51: =AK15/AE15-1 -> 0.0206563 | AM51: =AM15/AG15-1 -> 0.052883887 | AN51: =AN15/AH15-1 -> 0.048170068 | AO51: =AO15/AI15-1 -> 0.053301678 | AP51: =AP15/AJ15-1 -> 0.057342969 | AQ51: =AQ15/AK15-1 -> 0.053008596 | AS51: =AS15/AM15-1 -> 0.066332662 | AT51: =AT15/AN15-1 -> 0.037776706 | AU51: =AU15/AO15-1 -> 0.056838073 | AV51: =AV15/AP15-1 -> 0 | AW51: =AW15/AQ15-1 -> 0.039108065 | AY51: =AY15/AS15-1 -> 0.023809524 | AZ51: =AZ15/AT15-1 -> 0.015748031 | BA51: =BA15/AU15-1 -> 0.40703125 | BB51: =BB15/AV15-1 -> 0.47368421 | BC51: =BC15/AW15-1 -> 0.23365759 | BE51: =BE15/AY15-1 -> 0.4496124 | BF51: =BF15/AZ15-1 -> 0.40891473 | BG51: =BG15/BA15-1 -> 0.14936147 | BH51: =BH15/BB15-1 -> 0.29081633 | BI51: =BI15/BC15-1 -> 0.30697051 | BK51: =BK15/BE15-1 -> -0.026737968 | BL51: =BL15/BF15-1 -> 0.028885832 | BM51: =BM15/BG15-1 -> -0.10628019 | BN51: =BN15/BH15-1 -> -0.12648221 | BO51: =BO15/BI15-1 -> -0.064856712 | BQ51: =BQ15/BK15-1 -> 0.054945055 | BR51: =BR15/BL15-1 -> 0.44618083 | BS51: =BS15/BM15-1 -> 0.53409151 | BT51: =BT15/BN15-1 -> 0.34146738 | BU51: =BU15/BO15-1 -> 0.34542843 | BW51: =BW15/BQ15-1 -> 0.50827936 | BX51: =BX15/BR15-1 -> 0.070400677 | BY51: =BY15/BS15-1 -> 0.052993318 | BZ51: =BZ15/BT15-1 -> 0.021899987 | CA51: =CA15/BU15-1 -> 0.13250216 | CC51: =CC15/BW15-1 -> 0.0062023799 | CD51: =CD15/BX15-1 -> 0.0050559399 | CE51: =CE15/BY15-1 -> 0.0055373236 | CF51: =CF15/BZ15-1 -> 0.0054158927 | CG51: =CG15/CA15-1 -> 0.0055512597 | CI51: =CI15/CC15-1 -> 0.02897298 | CJ51: =CJ15/CD15-1 -> 0.028127716 | CK51: =CK15/CE15-1 -> 0.028627628 | CL51: =CL15/CF15-1 -> 0.028500459 | CM51: =CM15/CG15-1 -> 0.028557267
A52: Operating Expenses | C52: 0.1117383 | D52: 0.14528819 | E52: 0.11942677 | F52: 0.085322728 | G52: 0.11500661 | I52: =I16/C16-1 -> 0.10607425 | J52: =J16/D16-1 -> 0.036972095 | K52: =K16/E16-1 -> 0.070279141 | L52: =L16/F16-1 -> 0.091742257 | M52: =M16/G16-1 -> 0.075838211 | O52: =O16/I16-1 -> -0.033553176 | P52: =P16/J16-1 -> 0.032745129 | Q52: =Q16/K16-1 -> -0.036113336 | R52: =R16/L16-1 -> -0.010853355 | S52: =S16/M16-1 -> -0.012276421 | U52: =U16/O16-1 -> 0.098382336 | V52: =V16/P16-1 -> -0.013323667 | W52: =W16/Q16-1 -> 0.0064877747 | X52: =X16/R16-1 -> 0.040465051 | Y52: =Y16/S16-1 -> 0.032123409 | AA52: =AA16/U16-1 -> 0.017802079 | AB52: =AB16/V16-1 -> 0.059658257 | AC52: =AC16/W16-1 -> 0.10968418 | AD52: =AD16/X16-1 -> 0.058930654 | AE52: =AE16/Y16-1 -> 0.061064333 | AG52: =AG16/AA16-1 -> 0.072088985 | AH52: =AH16/AB16-1 -> 0.09428514 | AI52: =AI16/AC16-1 -> 0.003558138 | AJ52: =AJ16/AD16-1 -> 0.012098869 | AK52: =AK16/AE16-1 -> 0.04436626 | AM52: =AM16/AG16-1 -> 0.032871431 | AN52: =AN16/AH16-1 -> 0.053834331 | AO52: =AO16/AI16-1 -> 0.084433427 | AP52: =AP16/AJ16-1 -> 0.10124476 | AQ52: =AQ16/AK16-1 -> 0.068070293 | AS52: =AS16/AM16-1 -> 0.069962869 | AT52: =AT16/AN16-1 -> 0.0062999716 | AU52: =AU16/AO16-1 -> 0.035621594 | AV52: =AV16/AP16-1 -> 0.018099548 | AW52: =AW16/AQ16-1 -> 0.032007138 | AY52: =AY16/AS16-1 -> 0.0060882801 | AZ52: =AZ16/AT16-1 -> -0.0015600624 | BA52: =BA16/AU16-1 -> 0.43521341 | BB52: =BB16/AV16-1 -> 0.39703704 | BC52: =BC16/AW16-1 -> 0.21167744 | BE52: =BE16/AY16-1 -> 0.40998487 | BF52: =BF16/AZ16-1 -> 0.45703125 | BG52: =BG16/BA16-1 -> -0.0069038768 | BH52: =BH16/BB16-1 -> 0.10498409 | BI52: =BI16/BC16-1 -> 0.20593313 | BK52: =BK16/BE16-1 -> -0.041845494 | BL52: =BL16/BF16-1 -> -0.026273458 | BM52: =BM16/BG16-1 -> -0.03315508 | BN52: =BN16/BH16-1 -> -0.045105566 | BO52: =BO16/BI16-1 -> -0.03683457 | BQ52: =BQ16/BK16-1 -> 0.079507279 | BR52: =BR16/BL16-1 -> 0.42961664 | BS52: =BS16/BM16-1 -> 0.44605301 | BT52: =BT16/BN16-1 -> 0.37146502 | BU52: =BU16/BO16-1 -> 0.33349501 | BW52: =BW16/BQ16-1 -> 0.37647889 | BX52: =BX16/BR16-1 -> 0.023773375 | BY52: =BY16/BS16-1 -> 0.042601936 | BZ52: =BZ16/BT16-1 -> 0.022592532 | CA52: =CA16/BU16-1 -> 0.097347567 | CC52: =CC16/BW16-1 -> 0.0087629519 | CD52: =CD16/BX16-1 -> 0.0077411436 | CE52: =CE16/BY16-1 -> 0.0079235062 | CF52: =CF16/BZ16-1 -> 0.008250712 | CG52: =CG16/CA16-1 -> 0.0081688087 | CI52: =CI16/CC16-1 -> 0.026789037 | CJ52: =CJ16/CD16-1 -> 0.025965967 | CK52: =CK16/CE16-1 -> 0.026275583 | CL52: =CL16/CF16-1 -> 0.026431562 | CM52: =CM16/CG16-1 -> 0.026365735
A53: Operating Income | C53: 0.058188329 | D53: 0.079265975 | E53: 0.16876215 | F53: 0.17312089 | G53: 0.11860114 | I53: =I17/C17-1 -> 0.10377781 | J53: =J17/D17-1 -> 0.19963592 | K53: =K17/E17-1 -> 0.22283993 | L53: =L17/F17-1 -> 0.15851924 | M53: =M17/G17-1 -> 0.17106994 | O53: =O17/I17-1 -> 0.10727481 | P53: =P17/J17-1 -> -0.089393308 | Q53: =Q17/K17-1 -> 0.017464786 | R53: =R17/L17-1 -> 0.064442341 | S53: =S17/M17-1 -> 0.024235423 | U53: =U17/O17-1 -> 0.069943374 | V53: =V17/P17-1 -> 0.1905184 | W53: =W17/Q17-1 -> 0.014978883 | X53: =X17/R17-1 -> -0.031635089 | Y53: =Y17/S17-1 -> 0.054800268 | AA53: =AA17/U17-1 -> -0.095434403 | AB53: =AB17/V17-1 -> 0.0080672456 | AC53: =AC17/W17-1 -> 0.057284106 | AD53: =AD17/X17-1 -> 0.028680907 | AE53: =AE17/Y17-1 -> -0.00099314348 | AG53: =AG17/AA17-1 -> -0.13355393 | AH53: =AH17/AB17-1 -> -0.080710337 | AI53: =AI17/AC17-1 -> 0.0040855026 | AJ53: =AJ17/AD17-1 -> -0.031994525 | AK53: =AK17/AE17-1 -> -0.058053167 | AM53: =AM17/AG17-1 -> 0.21737358 | AN53: =AN17/AH17-1 -> 0.046146923 | AO53: =AO17/AI17-1 -> -0.0056163673 | AP53: =AP17/AJ17-1 -> 0.081452799 | AQ53: =AQ17/AK17-1 -> 0.077107014 | AS53: =AS17/AM17-1 -> -0.033123001 | AT53: =AT17/AN17-1 -> 0.073464009 | AU53: =AU17/AO17-1 -> 0.059986743 | AV53: =AV17/AP17-1 -> 0.056175204 | AW53: =AW17/AQ17-1 -> 0.039715784 | AY53: =AY17/AS17-1 -> 0.01453151 | AZ53: =AZ17/AT17-1 -> -0.018653596 | BA53: =BA17/AU17-1 -> 0.4517833 | BB53: =BB17/AV17-1 -> 0.42425735 | BC53: =BC17/AW17-1 -> 0.2318214 | BE53: =BE17/AY17-1 -> 0.57716218 | BF53: =BF17/AZ17-1 -> 0.63983903 | BG53: =BG17/BA17-1 -> 0.090088779 | BH53: =BH17/BB17-1 -> -0.027067669 | BI53: =BI17/BC17-1 -> 0.2509774 | BK53: =BK17/BE17-1 -> 0.094223007 | BL53: =BL17/BF17-1 -> -0.054492963 | BM53: =BM17/BG17-1 -> -0.024032043 | BN53: =BN17/BH17-1 -> 0.067217929 | BO53: =BO17/BI17-1 -> 0.01744406 | BQ53: =BQ17/BK17-1 -> 0.044668588 | BR53: =BR17/BL17-1 -> 0.60705252 | BS53: =BS17/BM17-1 -> 0.58239158 | BT53: =BT17/BN17-1 -> 0.65427374 | BU53: =BU17/BO17-1 -> 0.47143903 | BW53: =BW17/BQ17-1 -> 0.59773593 | BX53: =BX17/BR17-1 -> 0.13751707 | BY53: =BY17/BS17-1 -> 0.072565684 | BZ53: =BZ17/BT17-1 -> 0.097070978 | CA53: =CA17/BU17-1 -> 0.18960147 | CC53: =CC17/BW17-1 -> 0.13983863 | CD53: =CD17/BX17-1 -> 0.1377661 | CE53: =CE17/BY17-1 -> 0.13800123 | CF53: =CF17/BZ17-1 -> 0.13817358 | CG53: =CG17/CA17-1 -> 0.13842659 | CI53: =CI17/CC17-1 -> 0.09908507 | CJ53: =CJ17/CD17-1 -> 0.072840008 | CK53: =CK17/CE17-1 -> 0.11245366 | CL53: =CL17/CF17-1 -> 0.11251521 | CM53: =CM17/CG17-1 -> 0.099497273
A54: Pre-Tax Income | C54: 0.07224571 | D54: 0.1010372 | E54: 0.19985404 | F54: 0.16755895 | G54: 0.13407759 | I54: =I23/C23-1 -> 0.11266182 | J54: =J23/D23-1 -> 0.18970797 | K54: =K23/E23-1 -> 0.21711047 | L54: =L23/F23-1 -> 0.16101996 | M54: =M23/G23-1 -> 0.1702137 | O54: =O23/I23-1 -> 0.10433967 | P54: =P23/J23-1 -> -0.11438257 | Q54: =Q23/K23-1 -> 0.0090975352 | R54: =R23/L23-1 -> 0.072665928 | S54: =S23/M23-1 -> 0.017263134 | U54: =U23/O23-1 -> 0.045200336 | V54: =V23/P23-1 -> 0.21261017 | W54: =W23/Q23-1 -> -0.0014011252 | X54: =X23/R23-1 -> -0.016935231 | Y54: =Y23/S23-1 -> 0.052304172 | AA54: =AA23/U23-1 -> -0.093071673 | AB54: =AB23/V23-1 -> -0.013262664 | AC54: =AC23/W23-1 -> 0.052729617 | AD54: =AD23/X23-1 -> -0.026499693 | AE54: =AE23/Y23-1 -> -0.02046901 | AG54: =AG23/AA23-1 -> -0.15973333 | AH54: =AH23/AB23-1 -> -0.087831333 | AI54: =AI23/AC23-1 -> -0.038212653 | AJ54: =AJ23/AD23-1 -> -0.052698291 | AK54: =AK23/AE23-1 -> -0.082813547 | AM54: =AM23/AG23-1 -> 0.18956611 | AN54: =AN23/AH23-1 -> 0.029317367 | AO54: =AO23/AI23-1 -> 0.0058850865 | AP54: =AP23/AJ23-1 -> 0.11305941 | AQ54: =AQ23/AK23-1 -> 0.07879754 | AS54: =AS23/AM23-1 -> -0.016127795 | AT54: =AT23/AN23-1 -> 0.063417802 | AU54: =AU23/AO23-1 -> 0.069538151 | AV54: =AV23/AP23-1 -> 0.039601657 | AW54: =AW23/AQ23-1 -> 0.03977938 | AY54: =AY23/AS23-1 -> 0.012613281 | AZ54: =AZ23/AT23-1 -> -0.0025464794 | BA54: =BA23/AU23-1 -> 0.30163454 | BB54: =BB23/AV23-1 -> 0.24686022 | BC54: =BC23/AW23-1 -> 0.14852603 | BE54: =BE23/AY23-1 -> 0.41633956 | BF54: =BF23/AZ23-1 -> 0.47416037 | BG54: =BG23/BA23-1 -> 0.10561338 | BH54: =BH23/BB23-1 -> 0.001814882 | BI54: =BI23/BC23-1 -> 0.21495925 | BK54: =BK23/BE23-1 -> 0.12888922 | BL54: =BL23/BF23-1 -> -0.036569987 | BM54: =BM23/BG23-1 -> -0.0077160494 | BN54: =BN23/BH23-1 -> 0.11320652 | BO54: =BO23/BI23-1 -> 0.045162865 | BQ54: =BQ23/BK23-1 -> 0.063829787 | BR54: =BR23/BL23-1 -> 0.59575015 | BS54: =BS23/BM23-1 -> 0.58471143 | BT54: =BT23/BN23-1 -> 0.64113555 | BU54: =BU23/BO23-1 -> 0.47114904 | BW54: =BW23/BQ23-1 -> 0.58250682 | BX54: =BX23/BR23-1 -> 0.17244744 | BY54: =BY23/BS23-1 -> 0.097388628 | BZ54: =BZ23/BT23-1 -> 0.095842003 | CA54: =CA23/BU23-1 -> 0.20385299 | CC54: =CC23/BW23-1 -> 0.1340997 | CD54: =CD23/BX23-1 -> 0.13183279 | CE54: =CE23/BY23-1 -> 0.13463867 | CF54: =CF23/BZ23-1 -> 0.16548899 | CG54: =CG23/CA23-1 -> 0.14169944 | CI54: =CI23/CC23-1 -> 0.13061825 | CJ54: =CJ23/CD23-1 -> 0.098526009 | CK54: =CK23/CE23-1 -> 0.1415064 | CL54: =CL23/CF23-1 -> 0.14221873 | CM54: =CM23/CG23-1 -> 0.12855532
A55: Net Income | C55: 0.09879391 | D55: 0.11648276 | E55: 0.17431101 | F55: 0.14801075 | G55: 0.13451251 | I55: =I26/C26-1 -> 0.10210824 | J55: =J26/D26-1 -> 0.1702294 | K55: =K26/E26-1 -> 0.19989672 | L55: =L26/F26-1 -> 0.13273761 | M55: =M26/G26-1 -> 0.15108398 | O55: =O26/I26-1 -> 0.094910962 | P55: =P26/J26-1 -> -0.097117565 | Q55: =Q26/K26-1 -> 0.10098853 | R55: =R26/L26-1 -> 0.043427105 | S55: =S26/M26-1 -> 0.03661349 | U55: =U26/O26-1 -> 0.025238784 | V55: =V26/P26-1 -> 0.14533122 | W55: =W26/Q26-1 -> -0.10165066 | X55: =X26/R26-1 -> -0.0046700721 | Y55: =Y26/S26-1 -> 0.0077046565 | AA55: =AA26/U26-1 -> -0.018567675 | AB55: =AB26/V26-1 -> 0.03794635 | AC55: =AC26/W26-1 -> 0.093078597 | AD55: =AD26/X26-1 -> -0.0068451782 | AE55: =AE26/Y26-1 -> 0.025965027 | AG55: =AG26/AA26-1 -> -0.16720808 | AH55: =AH26/AB26-1 -> -0.070055772 | AI55: =AI26/AC26-1 -> -0.030972818 | AJ55: =AJ26/AD26-1 -> -0.012949798 | AK55: =AK26/AE26-1 -> -0.069896296 | AM55: =AM26/AG26-1 -> 0.13765793 | AN55: =AN26/AH26-1 -> 0.054220097 | AO55: =AO26/AI26-1 -> 0.026496497 | AP55: =AP26/AJ26-1 -> 0.10817185 | AQ55: =AQ26/AK26-1 -> 0.078806568 | AS55: =AS26/AM26-1 -> 0.0028319176 | AT55: =AT26/AN26-1 -> 0.084876031 | AU55: =AU26/AO26-1 -> 0.076982994 | AV55: =AV26/AP26-1 -> 0.07726259 | AW55: =AW26/AQ26-1 -> 0.061633152 | AY55: =AY26/AS26-1 -> 0.0651759 | AZ55: =AZ26/AT26-1 -> 0.0088705607 | BA55: =BA26/AU26-1 -> 0.28055953 | BB55: =BB26/AV26-1 -> 0.22175173 | BC55: =BC26/AW26-1 -> 0.15087071 | BE55: =BE26/AY26-1 -> 0.40656867 | BF55: =BF26/AZ26-1 -> 0.48795086 | BG55: =BG26/BA26-1 -> 0.15620041 | BH55: =BH26/BB26-1 -> 0.1026253 | BI55: =BI26/BC26-1 -> 0.26331619 | BK55: =BK26/BE26-1 -> 0.19339045 | BL55: =BL26/BF26-1 -> 0.060654176 | BM55: =BM26/BG26-1 -> 0.052941176 | BN55: =BN26/BH26-1 -> 0.13525974 | BO55: =BO26/BI26-1 -> 0.10715872 | BQ55: =BQ26/BK26-1 -> 0.072978304 | BR55: =BR26/BL26-1 -> 0.51481599 | BS55: =BS26/BM26-1 -> 0.57494347 | BT55: =BT26/BN26-1 -> 0.59587971 | BU55: =BU26/BO26-1 -> 0.44271797 | BW55: =BW26/BQ26-1 -> 0.57414339 | BX55: =BX26/BR26-1 -> 0.17597891 | BY55: =BY26/BS26-1 -> 0.10069402 | BZ55: =BZ26/BT26-1 -> 0.099142731 | CA55: =CA26/BU26-1 -> 0.20565916 | CC55: =CC26/BW26-1 -> 0.13750541 | CD55: =CD26/BX26-1 -> 0.13523169 | CE55: =CE26/BY26-1 -> 0.13804599 | CF55: =CF26/BZ26-1 -> 0.16898896 | CG55: =CG26/CA26-1 -> 0.14512796 | CI55: =CI26/CC26-1 -> 0.13061825 | CJ55: =CJ26/CD26-1 -> 0.098526009 | CK55: =CK26/CE26-1 -> 0.1415064 | CL55: =CL26/CF26-1 -> 0.14221873 | CM55: =CM26/CG26-1 -> 0.12855532
A56: EPS | C56: 0.102716 | D56: 0.13208126 | E56: 0.17866394 | F56: 0.15633239 | G56: 0.13988097 | I56: =I34/C34-1 -> 0.11005458 | J56: =J34/D34-1 -> 0.17926578 | K56: =K34/E34-1 -> 0.21172174 | L56: =L34/F34-1 -> 0.14090857 | M56: =M34/G34-1 -> 0.16078261 | O56: =O34/I34-1 -> 0.11609829 | P56: =P34/J34-1 -> -0.071788828 | Q56: =Q34/K34-1 -> 0.12766005 | R56: =R34/L34-1 -> 0.069574948 | S56: =S34/M34-1 -> 0.061323565 | U56: =U34/O34-1 -> 0.047797286 | V56: =V34/P34-1 -> 0.16923518 | W56: =W34/Q34-1 -> -0.073842876 | X56: =X34/R34-1 -> 0.032141585 | Y56: =Y34/S34-1 -> 0.035661016 | AA56: =AA34/U34-1 -> 0.02377994 | AB56: =AB34/V34-1 -> 0.10882245 | AC56: =AC34/W34-1 -> 0.16520505 | AD56: =AD34/X34-1 -> 0.062661584 | AE56: =AE34/Y34-1 -> 0.091577114 | AG56: =AG34/AA34-1 -> -0.10873425 | AH56: =AH34/AB34-1 -> -0.00062565661 | AI56: =AI34/AC34-1 -> 0.055299819 | AJ56: =AJ34/AD34-1 -> 0.076862267 | AK56: =AK34/AE34-1 -> 0.0054349256 | AM56: =AM34/AG34-1 -> 0.24063259 | AN56: =AN34/AH34-1 -> 0.11625714 | AO56: =AO34/AI34-1 -> 0.060439444 | AP56: =AP34/AJ34-1 -> 0.12943392 | AQ56: =AQ34/AK34-1 -> 0.13322588 | AS56: =AS34/AM34-1 -> 0.010222431 | AT56: =AT34/AN34-1 -> 0.088474192 | AU56: =AU34/AO34-1 -> 0.086353055 | AV56: =AV34/AP34-1 -> 0.089150533 | AW56: =AW34/AQ34-1 -> 0.067303529 | AY56: =AY34/AS34-1 -> 0.071177653 | AZ56: =AZ34/AT34-1 -> 0.011369692 | BA56: =BA34/AU34-1 -> 0.17377276 | BB56: =BB34/AV34-1 -> 0.11267596 | BC56: =BC34/AW34-1 -> 0.10010249 | BE56: =BE34/AY34-1 -> 0.281099 | BF56: =BF34/AZ34-1 -> 0.35369459 | BG56: =BG34/BA34-1 -> 0.14320079 | BH56: =BH34/BB34-1 -> 0.091508777 | BI56: =BI34/BC34-1 -> 0.20396018 | BK56: =BK34/BE34-1 -> 0.18547065 | BL56: =BL34/BF34-1 -> 0.054188969 | BM56: =BM34/BG34-1 -> 0.04902252 | BN56: =BN34/BH34-1 -> 0.13154187 | BO56: =BO34/BI34-1 -> 0.10170047 | BQ56: =BQ34/BK34-1 -> 0.066814718 | BR56: =BR34/BL34-1 -> 0.13939924 | BS56: =BS34/BM34-1 -> 0.19238401 | BT56: =BT34/BN34-1 -> 0.20922561 | BU56: =BU34/BO34-1 -> 0.15865836 | BW56: =BW34/BQ34-1 -> 0.19685822 | BX56: =BX34/BR34-1 -> 0.18265748 | BY56: =BY34/BS34-1 -> 0.10135909 | BZ56: =BZ34/BT34-1 -> 0.098585502 | CA56: =CA34/BU34-1 -> 0.13622381 | CC56: =CC34/BW34-1 -> 0.13177047 | CD56: =CD34/BX34-1 -> 0.12628186 | CE56: =CE34/BY34-1 -> 0.12773053 | CF56: =CF34/BZ34-1 -> 0.16087032 | CG56: =CG34/CA34-1 -> 0.13679026 | CI56: =CI34/CC34-1 -> 0.12272938 | CJ56: =CJ34/CD34-1 -> 0.090133323 | CK56: =CK34/CE34-1 -> 0.13216021 | CL56: =CL34/CF34-1 -> 0.13114294 | CM56: =CM34/CG34-1 -> 0.11938262
A57: Share Count | C57: -0.0035567576 | D57: -0.013778605 | E57: -0.0036931039 | F57: -0.0071965877 | G57: -0.0047096712 | I57: =I33/C33-1 -> -0.007158519 | J57: =J33/D33-1 -> -0.0076627149 | K57: =K33/E33-1 -> -0.0097588617 | L57: =L33/F33-1 -> -0.0071618006 | M57: =M33/G33-1 -> -0.0083552451 | O57: =O33/I33-1 -> -0.018983391 | P57: =P33/J33-1 -> -0.027287688 | Q57: =Q33/K33-1 -> -0.023652085 | R57: =R33/L33-1 -> -0.024446948 | S57: =S33/M33-1 -> -0.02328232 | U57: =U33/O33-1 -> -0.021529453 | V57: =V33/P33-1 -> -0.020444101 | W57: =W33/Q33-1 -> -0.030024909 | X57: =X33/R33-1 -> -0.035665317 | Y57: =Y33/S33-1 -> -0.026993736 | AA57: =AA33/U33-1 -> -0.041363982 | AB57: =AB33/V33-1 -> -0.063920154 | AC57: =AC33/W33-1 -> -0.061900226 | AD57: =AD33/X33-1 -> -0.065408182 | AE57: =AE33/Y33-1 -> -0.060107606 | AG57: =AG33/AA33-1 -> -0.065607625 | AH57: =AH33/AB33-1 -> -0.069473581 | AI57: =AI33/AC33-1 -> -0.081751779 | AJ57: =AJ33/AD33-1 -> -0.083401627 | AK57: =AK33/AE33-1 -> -0.074924015 | AM57: =AM33/AG33-1 -> -0.083001737 | AN57: =AN33/AH33-1 -> -0.055575945 | AO57: =AO33/AI33-1 -> -0.032008378 | AP57: =AP33/AJ33-1 -> -0.018825424 | AQ57: =AQ33/AK33-1 -> -0.048021591 | AS57: =AS33/AM33-1 -> -0.0073157288 | AT57: =AT33/AN33-1 -> -0.0033056934 | AU57: =AU33/AO33-1 -> -0.0086252447 | AV57: =AV33/AP33-1 -> -0.010914876 | AW57: =AW33/AQ33-1 -> -0.0053128066 | AY57: =AY33/AS33-1 -> -0.0056029479 | AZ57: =AZ33/AT33-1 -> -0.0024710362 | BA57: =BA33/AU33-1 -> 0.090977386 | BB57: =BB33/AV33-1 -> 0.098030133 | BC57: =BC33/AW33-1 -> 0.046148633 | BE57: =BE33/AY33-1 -> 0.097939086 | BF57: =BF33/AZ33-1 -> 0.099177665 | BG57: =BG33/BA33-1 -> 0.01137125 | BH57: =BH33/BB33-1 -> 0.010184546 | BI57: =BI33/BC33-1 -> 0.049300644 | BK57: =BK33/BE33-1 -> 0.0066807216 | BL57: =BL33/BF33-1 -> 0.0061328728 | BM57: =BM33/BG33-1 -> 0.0037355317 | BN57: =BN33/BH33-1 -> 0.0032856697 | BO57: =BO33/BI33-1 -> 0.0049543842 | BQ57: =BQ33/BK33-1 -> 0.0057775594 | BR57: =BR33/BL33-1 -> 0.2624252 | BS57: =BS33/BM33-1 -> 0.26105031 | BT57: =BT33/BN33-1 -> 0.25939454 | BU57: =BU33/BO33-1 -> 0.19726769 | BW57: =BW33/BQ33-1 -> 0.25643407 | BX57: =BX33/BR33-1 -> 0.0022573035 | BY57: =BY33/BS33-1 -> 0.0037306256 | BZ57: =BZ33/BT33-1 -> 0.0048324305 | CA57: =CA33/BU33-1 -> 0.05661556 | CC57: =CC33/BW33-1 -> 0.052099927 | CD57: =CD33/BX33-1 -> 0.053118003 | CE57: =CE33/BY33-1 -> 0.052425538 | CF57: =CF33/BZ33-1 -> 0.050713456 | CG57: =CG33/CA33-1 -> 0.052088117 | CI57: =CI33/CC33-1 -> 0.0070265032 | CJ57: =CJ33/CD33-1 -> 0.0076987704 | CK57: =CK33/CE33-1 -> 0.0082551884 | CL57: =CL33/CF33-1 -> 0.0097916807 | CM57: =CM33/CG33-1 -> 0.0081944243
A59: Calendar Year Calculations | G59: =G5 -> 2007 | M59: =M5 -> 2008 | S59: =S5 -> 2009 | Y59: =Y5 -> 2010 | AE59: =AE5 -> 2011 | AK59: =AK5 -> 2012 | AQ59: =AQ5 -> 2013 | AW59: =AW5 -> 2014 | BC59: =BC5 -> 2015 | BI59: =BI5 -> 2016 | BO59: =BO5 -> 2017 | BU59: =BU5 -> 2018 | CA59: =CA5 -> 2019 | CG59: =CG5 -> 2020 | CM59: =CM5 -> 2021
A60: Revenues | G60: =SUM(D7:F7)+I7 -> 6563.949 | M60: =SUM(J7:L7)+O7 -> 7123.292 | S60: =SUM(P7:R7)+U7 -> 7182.392 | Y60: =SUM(V7:X7)+AA7 -> 7286.8687 | AE60: =SUM(AB7:AD7)+AG7 -> 7632.404 | AK60: =SUM(AH7:AJ7)+AM7 -> 7776.854 | AQ60: =SUM(AN7:AP7)+AS7 -> 8167.939 | AW60: =SUM(AT7:AV7)+AY7 -> 8481.93 | BC60: =SUM(AZ7:BB7)+BE7 -> 11242.69 | BI60: =SUM(BF7:BH7)+BK7 -> 12427 | BO60: =SUM(BL7:BN7)+BQ7 -> 12250.49 | BU60: =SUM(BR7:BT7)+BW7 -> 17142.658 | CA60: =SUM(BX7:BZ7)+CC7 -> 18057.12 | CG60: =SUM(CD7:CF7)+CI7 -> 19020.067
A61: Gross Profit | G61: =SUM(D11:F11)+I11 -> 3371.115 | M61: =SUM(J11:L11)+O11 -> 3685.035 | S61: =SUM(P11:R11)+U11 -> 3751.934 | Y61: =SUM(V11:X11)+AA11 -> 3797.8437 | AE61: =SUM(AB11:AD11)+AG11 -> 3946.984 | AK61: =SUM(AH11:AJ11)+AM11 -> 4055.7371 | AQ61: =SUM(AN11:AP11)+AS11 -> 4276.3949 | AW61: =SUM(AT11:AV11)+AY11 -> 4405.81 | BC61: =SUM(AZ11:BB11)+BE11 -> 5865.29 | BI61: =SUM(BF11:BH11)+BK11 -> 6585.25 | BO61: =SUM(BL11:BN11)+BQ11 -> 6572.49 | BU61: =SUM(BR11:BT11)+BW11 -> 9806.8229 | CA61: =SUM(BX11:BZ11)+CC11 -> 10437.387 | CG61: =SUM(CD11:CF11)+CI11 -> 11145.993
A62: SG&A | G62: =SUM(D12:F12)+I12 -> 1640.038 | M62: =SUM(J12:L12)+O12 -> 1692.995 | S62: =SUM(P12:R12)+U12 -> 1726.802 | Y62: =SUM(V12:X12)+AA12 -> 1716.638 | AE62: =SUM(AB12:AD12)+AG12 -> 1864.854 | AK62: =SUM(AH12:AJ12)+AM12 -> 1928.961 | AQ62: =SUM(AN12:AP12)+AS12 -> 2087.93 | AW62: =SUM(AT12:AV12)+AY12 -> 2116 | BC62: =SUM(AZ12:BB12)+BE12 -> 2764.4 | BI62: =SUM(BF12:BH12)+BK12 -> 2978.75 | BO62: =SUM(BL12:BN12)+BQ12 -> 2986 | BU62: =SUM(BR12:BT12)+BW12 -> 4156.5605 | CA62: =SUM(BX12:BZ12)+CC12 -> 4243.2014 | CG62: =SUM(CD12:CF12)+CI12 -> 4298.4586
A63: R&D | G63: =SUM(D15:F15)+I15 -> 371.637 | M63: =SUM(J15:L15)+O15 -> 401.067 | S63: =SUM(P15:R15)+U15 -> 407.362 | Y63: =SUM(V15:X15)+AA15 -> 445.414 | AE63: =SUM(AB15:AD15)+AG15 -> 458.906 | AK63: =SUM(AH15:AJ15)+AM15 -> 475.689 | AQ63: =SUM(AN15:AP15)+AS15 -> 502.493 | AW63: =SUM(AT15:AV15)+AY15 -> 517 | BC63: =SUM(AZ15:BB15)+BE15 -> 692.1 | BI63: =SUM(BF15:BH15)+BK15 -> 823.75 | BO63: =SUM(BL15:BN15)+BQ15 -> 785 | BU63: =SUM(BR15:BT15)+BW15 -> 1140.2967 | CA63: =SUM(BX15:BZ15)+CC15 -> 1182.6641 | CG63: =SUM(CD15:CF15)+CI15 -> 1195.8656
A64: Operating Expenses | G64: =SUM(D16:F16)+I16 -> 2011.675 | M64: =SUM(J16:L16)+O16 -> 2094.062 | S64: =SUM(P16:R16)+U16 -> 2134.164 | Y64: =SUM(V16:X16)+AA16 -> 2162.052 | AE64: =SUM(AB16:AD16)+AG16 -> 2323.76 | AK64: =SUM(AH16:AJ16)+AM16 -> 2404.65 | AQ64: =SUM(AN16:AP16)+AS16 -> 2590.423 | AW64: =SUM(AT16:AV16)+AY16 -> 2633 | BC64: =SUM(AZ16:BB16)+BE16 -> 3456.5 | BI64: =SUM(BF16:BH16)+BK16 -> 3802.5 | BO64: =SUM(BL16:BN16)+BQ16 -> 3771 | BU64: =SUM(BR16:BT16)+BW16 -> 5296.8572 | CA64: =SUM(BX16:BZ16)+CC16 -> 5425.8655 | CG64: =SUM(CD16:CF16)+CI16 -> 5494.3242
A65: Operating Income | G65: =SUM(D17:F17)+I17 -> 1359.44 | M65: =SUM(J17:L17)+O17 -> 1590.973 | S65: =SUM(P17:R17)+U17 -> 1617.77 | Y65: =SUM(V17:X17)+AA17 -> 1635.7917 | AE65: =SUM(AB17:AD17)+AG17 -> 1623.224 | AK65: =SUM(AH17:AJ17)+AM17 -> 1651.0871 | AQ65: =SUM(AN17:AP17)+AS17 -> 1685.9719 | AW65: =SUM(AT17:AV17)+AY17 -> 1772.81 | BC65: =SUM(AZ17:BB17)+BE17 -> 2408.79 | BI65: =SUM(BF17:BH17)+BK17 -> 2782.75 | BO65: =SUM(BL17:BN17)+BQ17 -> 2801.49 | BU65: =SUM(BR17:BT17)+BW17 -> 4509.9657 | CA65: =SUM(BX17:BZ17)+CC17 -> 5011.5211 | CG65: =SUM(CD17:CF17)+CI17 -> 5651.669
A66: EBITDA | G66: =SUM(D18:F18)+I18 -> 1814.912 | M66: =SUM(J18:L18)+O18 -> 2069.701 | S66: =SUM(P18:R18)+U18 -> 2096.666 | Y66: =SUM(V18:X18)+AA18 -> 2135.8757 | AE66: =SUM(AB18:AD18)+AG18 -> 2139.739 | AK66: =SUM(AH18:AJ18)+AM18 -> 2155.2401 | AQ66: =SUM(AN18:AP18)+AS18 -> 2245.1389 | AW66: =SUM(AT18:AV18)+AY18 -> 2302.31 | BC66: =SUM(AZ18:BB18)+BE18 -> 2916.79 | BI66: =SUM(BF18:BH18)+BK18 -> 3332.75 | BO66: =SUM(BL18:BN18)+BQ18 -> 3386.49 | BU66: =SUM(BR18:BT18)+BW18 -> 5230.414 | CA66: =SUM(BX18:BZ18)+CC18 -> 5791.4521 | CG66: =SUM(CD18:CF18)+CI18 -> 6489.5311
A67: Pre-Tax Income | G67: =SUM(D23:F23)+I23 -> 1363.203 | M67: =SUM(J23:L23)+O23 -> 1590.052 | S67: =SUM(P23:R23)+U23 -> 1596.891 | Y67: =SUM(V23:X23)+AA23 -> 1621.7797 | AE67: =SUM(AB23:AD23)+AG23 -> 1565.862 | AK67: =SUM(AH23:AJ23)+AM23 -> 1553.5311 | AQ67: =SUM(AN23:AP23)+AS23 -> 1603.8189 | AW67: =SUM(AT23:AV23)+AY23 -> 1678.81 | BC67: =SUM(AZ23:BB23)+BE23 -> 2081.79 | BI67: =SUM(BF23:BH23)+BK23 -> 2405.75 | BO67: =SUM(BL23:BN23)+BQ23 -> 2480.49 | BU67: =SUM(BR23:BT23)+BW23 -> 3970.4251 | CA67: =SUM(BX23:BZ23)+CC23 -> 4461.9329 | CG67: =SUM(CD23:CF23)+CI23 -> 5089.0766
A68: Taxes | G68: =SUM(D24:F24)+I24 -> 359.79671 | M68: =SUM(J24:L24)+O24 -> 438.226 | S68: =SUM(P24:R24)+U24 -> 422.059 | Y68: =SUM(V24:X24)+AA24 -> 451.086 | AE68: =SUM(AB24:AD24)+AG24 -> 408.881 | AK68: =SUM(AH24:AJ24)+AM24 -> 396.79002 | AQ68: =SUM(AN24:AP24)+AS24 -> 392.02868 | AW68: =SUM(AT24:AV24)+AY24 -> 374.7022 | BC68: =SUM(AZ24:BB24)+BE24 -> 479.4 | BI68: =SUM(BF24:BH24)+BK24 -> 454.4 | BO68: =SUM(BL24:BN24)+BQ24 -> 374 | BU68: =SUM(BR24:BT24)+BW24 -> 672.40069 | CA68: =SUM(BX24:BZ24)+CC24 -> 744.45733 | CG68: =SUM(CD24:CF24)+CI24 -> 839.69764
A69: Effective Tax Rate | G69: =G68/G67 -> 0.2639348 | M69: =M68/M67 -> 0.27560482 | S69: =S68/S67 -> 0.26430044 | Y69: =Y68/Y67 -> 0.27814259 | AE69: =AE68/AE67 -> 0.26112199 | AK69: =AK68/AK67 -> 0.25541171 | AQ69: =AQ68/AQ67 -> 0.2444345 | AW69: =AW68/AW67 -> 0.22319512 | BC69: =BC68/BC67 -> 0.23028259 | BI69: =BI68/BI67 -> 0.18888081 | BO69: =BO68/BO67 -> 0.15077666 | BU69: =BU68/BU67 -> 0.16935232 | CA69: =CA68/CA67 -> 0.16684638 | CG69: =CG68/CG67 -> 0.165
A70: Net Income | G70: =SUM(D26:F26)+I26 -> 1003.4063 | M70: =SUM(J26:L26)+O26 -> 1151.826 | S70: =SUM(P26:R26)+U26 -> 1174.832 | Y70: =SUM(V26:X26)+AA26 -> 1170.6937 | AE70: =SUM(AB26:AD26)+AG26 -> 1156.981 | AK70: =SUM(AH26:AJ26)+AM26 -> 1156.7411 | AQ70: =SUM(AN26:AP26)+AS26 -> 1211.7902 | AW70: =SUM(AT26:AV26)+AY26 -> 1304.1078 | BC70: =SUM(AZ26:BB26)+BE26 -> 1602.39 | BI70: =SUM(BF26:BH26)+BK26 -> 1951.35 | BO70: =SUM(BL26:BN26)+BQ26 -> 2106.49 | BU70: =SUM(BR26:BT26)+BW26 -> 3298.0244 | CA70: =SUM(BX26:BZ26)+CC26 -> 3717.4755 | CG70: =SUM(CD26:CF26)+CI26 -> 4249.3789
A71: EPS | G71: =SUM(D34:F34)+I34 -> 3.9547994 | M71: =SUM(J34:L34)+O34 -> 4.5900449 | S71: =SUM(P34:R34)+U34 -> 4.7978913 | Y71: =SUM(V34:X34)+AA34 -> 4.9391425 | AE71: =SUM(AB34:AD34)+AG34 -> 5.2102149 | AK71: =SUM(AH34:AJ34)+AM34 -> 5.6650254 | AQ71: =SUM(AN34:AP34)+AS34 -> 6.1073723 | AW71: =SUM(AT34:AV34)+AY34 -> 6.6206303 | BC71: =SUM(AZ34:BB34)+BE34 -> 7.5702566 | BI71: =SUM(BF34:BH34)+BK34 -> 8.9761395 | BO71: =SUM(BL34:BN34)+BQ34 -> 9.643819 | BU71: =SUM(BR34:BT34)+BW34 -> 11.428809 | CA71: =SUM(BX34:BZ34)+CC34 -> 12.882605 | CG71: =SUM(CD34:CF34)+CI34 -> 14.612402
A72: Share Count | G72: =G70/G71 -> 253.71863 | M72: =M70/M71 -> 250.94003 | S72: =S70/S71 -> 244.86424 | Y72: =Y70/Y71 -> 237.02367 | AE72: =AE70/AE71 -> 222.06013 | AK72: =AK70/AK71 -> 204.18991 | AQ72: =AQ70/AQ71 -> 198.41434 | AW72: =AW70/AW71 -> 196.97638 | BC72: =BC70/BC71 -> 211.66918 | BI72: =BI70/BI71 -> 217.39301 | BO72: =BO70/BO71 -> 218.42903 | BU72: =BU70/BU71 -> 288.57113 | CA72: =CA70/CA71 -> 288.56551 | CG72: =CG70/CG71 -> 290.80632
A74: Quarterly Distribution
A75: Sales | C75: 0.23610079 | D75: 0.24779754 | E75: 0.25648299 | F75: 0.25961867 | I75: =I7/M7 -> 0.23837175 | J75: =J7/M7 -> 0.24412335 | K75: =K7/M7 -> 0.26098536 | L75: =L7/M7 -> 0.25651954 | O75: =O7/S7 -> 0.23947539 | P75: =P7/S7 -> 0.24090582 | Q75: =Q7/S7 -> 0.254255 | R75: =R7/S7 -> 0.26536379 | U75: =U7/Y7 -> 0.25349072 | V75: =V7/Y7 -> 0.24407593 | W75: =W7/Y7 -> 0.24834893 | X75: =X7/Y7 -> 0.25408443 | AA75: =AA7/AE7 -> 0.23514568 | AB75: =AB7/AE7 -> 0.2453329 | AC75: =AC7/AE7 -> 0.25736805 | AD75: =AD7/AE7 -> 0.26215336 | AG75: =AG7/AK7 -> 0.23762704 | AH75: =AH7/AK7 -> 0.25024201 | AI75: =AI7/AK7 -> 0.256932 | AJ75: =AJ7/AK7 -> 0.25519895 | AM75: =AM7/AQ7 -> 0.23595399 | AN75: =AN7/AQ7 -> 0.24839409 | AO75: =AO7/AQ7 -> 0.25488701 | AP75: =AP7/AQ7 -> 0.2607649 | AS75: =AS7/AW7 -> 0.23857139 | AT75: =AT7/AW7 -> 0.24533223 | AU75: =AU7/AW7 -> 0.25537286 | AV75: =AV7/AW7 -> 0.26072352 | AY75: =AY7/BC7 -> 0.19910907 | AZ75: =AZ7/BC7 -> 0.19904209 | BA75: =BA7/BC7 -> 0.30412781 | BB75: =BB7/BC7 -> 0.29772103 | BE75: =BE7/BI7 -> 0.23943207 | BF75: =BF7/BI7 -> 0.24573426 | BG75: =BG7/BI7 -> 0.25605654 | BH75: =BH7/BI7 -> 0.25877714 | BK75: =BK7/BO7 -> 0.24163758 | BL75: =BL7/BO7 -> 0.24552429 | BM75: =BM7/BO7 -> 0.25098222 | BN75: =BN7/BO7 -> 0.26185591 | BQ75: =BQ7/BU7 -> 0.19370551 | BR75: =BR7/BU7 -> 0.26166288 | BS75: =BS7/BU7 -> 0.27043963 | BT75: =BT7/BU7 -> 0.27419198 | BW75: =BW7/CA7 -> 0.24246181 | BX75: =BX7/CA7 -> 0.24603776 | BY75: =BY7/CA7 -> 0.25400356 | BZ75: =BZ7/CA7 -> 0.25749688 | CC75: =CC7/CG7 -> 0.24248885 | CD75: =CD7/CG7 -> 0.24595953 | CE75: =CE7/CG7 -> 0.25404441 | CF75: =CF7/CG7 -> 0.2575072 | CI75: =CI7/CM7 -> 0.24251723 | CJ75: =CJ7/CM7 -> 0.24587992 | CK75: =CK7/CM7 -> 0.25408567 | CL75: =CL7/CM7 -> 0.25751718
A76: Three Year Average | O76: 0.23912714 | P76: 0.24670725 | Q76: 0.25714826 | R76: 0.25701735 | U76: =AVERAGE(C75,I75,O75) -> 0.23798264 | V76: =AVERAGE(D75,J75,P75) -> 0.24427557 | W76: =AVERAGE(E75,K75,Q75) -> 0.25724112 | X76: =AVERAGE(F75,L75,R75) -> 0.26050066 | AA76: =AVERAGE(I75,O75,U75) -> 0.24377929 | AB76: =AVERAGE(J75,P75,V75) -> 0.24303503 | AC76: =AVERAGE(K75,Q75,W75) -> 0.25452976 | AD76: =AVERAGE(L75,R75,X75) -> 0.25865592 | AG76: =AVERAGE(O75,U75,AA75) -> 0.24270393 | AH76: =AVERAGE(P75,V75,AB75) -> 0.24343822 | AI76: =AVERAGE(Q75,W75,AC75) -> 0.25332399 | AJ76: =AVERAGE(R75,X75,AD75) -> 0.26053386 | AM76: =AVERAGE(U75,AA75,AG75) -> 0.24208781 | AN76: =AVERAGE(V75,AB75,AH75) -> 0.24655028 | AO76: =AVERAGE(W75,AC75,AI75) -> 0.25421633 | AP76: =AVERAGE(X75,AD75,AJ75) -> 0.25714558 | AS76: =AVERAGE(AA75,AG75,AM75) -> 0.23624224 | AT76: =AVERAGE(AB75,AH75,AN75) -> 0.24798967 | AU76: =AVERAGE(AC75,AI75,AO75) -> 0.25639569 | AV76: =AVERAGE(AD75,AJ75,AP75) -> 0.25937241 | AY76: =AVERAGE(AG75,AM75,AS75) -> 0.23738414 | AZ76: =AVERAGE(AH75,AN75,AT75) -> 0.24798945 | BA76: =AVERAGE(AI75,AO75,AU75) -> 0.25573062 | BB76: =AVERAGE(AJ75,AP75,AV75) -> 0.25889579 | BE76: =AVERAGE(AM75,AS75,AY75) -> 0.22454482 | BF76: =AVERAGE(AN75,AT75,AZ75) -> 0.23092281 | BG76: =AVERAGE(AO75,AU75,BA75) -> 0.27146256 | BH76: =AVERAGE(AP75,AV75,BB75) -> 0.27306982 | BK76: =AVERAGE(AS75,AY75,BE75) -> 0.22570418 | BL76: =AVERAGE(AT75,AZ75,BF75) -> 0.23003619 | BM76: =AVERAGE(AU75,BA75,BG75) -> 0.2718524 | BN76: =AVERAGE(AV75,BB75,BH75) -> 0.27240723 | BQ76: =AVERAGE(AY75,BE75,BK75) -> 0.22672624 | BR76: =AVERAGE(AZ75,BF75,BL75) -> 0.23010021 | BS76: =AVERAGE(BA75,BG75,BM75) -> 0.27038886 | BT76: =AVERAGE(BB75,BH75,BN75) -> 0.27278469 | BW76: =AVERAGE(BE75,BK75,BQ75) -> 0.22492505 | BX76: =AVERAGE(BF75,BL75,BR75) -> 0.25097381 | BY76: =AVERAGE(BG75,BM75,BS75) -> 0.25915946 | BZ76: =AVERAGE(BH75,BN75,BT75) -> 0.26494168 | CC76: =AVERAGE(BK75,BQ75,BW75) -> 0.22593497 | CD76: =AVERAGE(BL75,BR75,BX75) -> 0.25107498 | CE76: =AVERAGE(BM75,BS75,BY75) -> 0.25847513 | CF76: =AVERAGE(BN75,BT75,BZ75) -> 0.26451492 | CI76: =AVERAGE(BQ75,BW75,CC75) -> 0.22621872 | CJ76: =AVERAGE(BR75,BX75,CD75) -> 0.25122006 | CK76: =AVERAGE(BS75,BY75,CE75) -> 0.25949587 | CL76: =AVERAGE(BT75,BZ75,CF75) -> 0.26306535
A77: Gross Profit | C77: 0.24107373 | D77: 0.24678607 | E77: 0.25551715 | F77: 0.25662306 | I77: =I11/M11 -> 0.23910383 | J77: =J11/M11 -> 0.24379816 | K77: =K11/M11 -> 0.25938717 | L77: =L11/M11 -> 0.25771084 | O77: =O11/S11 -> 0.24424347 | P77: =P11/S11 -> 0.23829906 | Q77: =Q11/S11 -> 0.25519517 | R77: =R11/S11 -> 0.2622623 | U77: =U11/Y11 -> 0.25449356 | V77: =V11/Y11 -> 0.24415784 | W77: =W11/Y11 -> 0.24743794 | X77: =X11/Y11 -> 0.25391066 | AA77: =AA11/AE11 -> 0.23824389 | AB77: =AB11/AE11 -> 0.24485284 | AC77: =AC11/AE11 -> 0.25997945 | AD77: =AD11/AE11 -> 0.25692382 | AG77: =AG11/AK11 -> 0.2349878 | AH77: =AH11/AK11 -> 0.24925025 | AI77: =AI11/AK11 -> 0.26069564 | AJ77: =AJ11/AK11 -> 0.25506631 | AM77: =AM11/AQ11 -> 0.24111036 | AN77: =AN11/AQ11 -> 0.24440854 | AO77: =AO11/AQ11 -> 0.25428034 | AP77: =AP11/AQ11 -> 0.26020076 | AS77: =AS11/AW11 -> 0.23961966 | AT77: =AT11/AW11 -> 0.24373699 | AU77: =AU11/AW11 -> 0.25688516 | AV77: =AV11/AW11 -> 0.25975819 | AY77: =AY11/BC11 -> 0.19826601 | AZ77: =AZ11/BC11 -> 0.19813733 | BA77: =BA11/BC11 -> 0.30371919 | BB77: =BB11/BC11 -> 0.29987748 | BE77: =BE11/BI11 -> 0.23859279 | BF77: =BF11/BI11 -> 0.24758207 | BG77: =BG11/BI11 -> 0.25653173 | BH77: =BH11/BI11 -> 0.25729341 | BK77: =BK11/BO11 -> 0.24526736 | BL77: =BL11/BO11 -> 0.24155821 | BM77: =BM11/BO11 -> 0.25268565 | BN77: =BN11/BO11 -> 0.26048877 | BQ77: =BQ11/BU11 -> 0.18744717 | BR77: =BR11/BU11 -> 0.26088466 | BS77: =BS11/BU11 -> 0.27345315 | BT77: =BT11/BU11 -> 0.27821502 | BW77: =BW11/CA11 -> 0.24214132 | BX77: =BX11/CA11 -> 0.24613988 | BY77: =BY11/CA11 -> 0.25366782 | BZ77: =BZ11/CA11 -> 0.25805098 | CC77: =CC11/CG11 -> 0.24217329 | CD77: =CD11/CG11 -> 0.24606007 | CE77: =CE11/CG11 -> 0.25371382 | CF77: =CF11/CG11 -> 0.25805282 | CI77: =CI11/CM11 -> 0.24207083 | CJ77: =CJ11/CM11 -> 0.24292722 | CK77: =CK11/CM11 -> 0.25534034 | CL77: =CL11/CM11 -> 0.2596616
A78: Three Year Average | O78: 0.24245082 | P78: 0.24564194 | Q78: 0.25515131 | R78: 0.25675593 | U78: =AVERAGE(C77,I77,O77) -> 0.24147368 | V78: =AVERAGE(D77,J77,P77) -> 0.2429611 | W78: =AVERAGE(E77,K77,Q77) -> 0.25669983 | X78: =AVERAGE(F77,L77,R77) -> 0.2588654 | AA78: =AVERAGE(I77,O77,U77) -> 0.24594695 | AB78: =AVERAGE(J77,P77,V77) -> 0.24208502 | AC78: =AVERAGE(K77,Q77,W77) -> 0.25400676 | AD78: =AVERAGE(L77,R77,X77) -> 0.25796126 | AG78: =AVERAGE(O77,U77,AA77) -> 0.24566031 | AH78: =AVERAGE(P77,V77,AB77) -> 0.24243658 | AI78: =AVERAGE(Q77,W77,AC77) -> 0.25420419 | AJ78: =AVERAGE(R77,X77,AD77) -> 0.25769892 | AM78: =AVERAGE(U77,AA77,AG77) -> 0.24257508 | AN78: =AVERAGE(V77,AB77,AH77) -> 0.24608698 | AO78: =AVERAGE(W77,AC77,AI77) -> 0.25603768 | AP78: =AVERAGE(X77,AD77,AJ77) -> 0.25530026 | AS78: =AVERAGE(AA77,AG77,AM77) -> 0.23811401 | AT78: =AVERAGE(AB77,AH77,AN77) -> 0.24617054 | AU78: =AVERAGE(AC77,AI77,AO77) -> 0.25831848 | AV78: =AVERAGE(AD77,AJ77,AP77) -> 0.25739696 | AY78: =AVERAGE(AG77,AM77,AS77) -> 0.23857261 | AZ78: =AVERAGE(AH77,AN77,AT77) -> 0.24579859 | BA78: =AVERAGE(AI77,AO77,AU77) -> 0.25728705 | BB78: =AVERAGE(AJ77,AP77,AV77) -> 0.25834175 | BE78: =AVERAGE(AM77,AS77,AY77) -> 0.22633201 | BF78: =AVERAGE(AN77,AT77,AZ77) -> 0.22876095 | BG78: =AVERAGE(AO77,AU77,BA77) -> 0.27162823 | BH78: =AVERAGE(AP77,AV77,BB77) -> 0.27327881 | BK78: =AVERAGE(AS77,AY77,BE77) -> 0.22549282 | BL78: =AVERAGE(AT77,AZ77,BF77) -> 0.2298188 | BM78: =AVERAGE(AU77,BA77,BG77) -> 0.27237869 | BN78: =AVERAGE(AV77,BB77,BH77) -> 0.27230969 | BQ78: =AVERAGE(AY77,BE77,BK77) -> 0.22737539 | BR78: =AVERAGE(AZ77,BF77,BL77) -> 0.22909254 | BS78: =AVERAGE(BA77,BG77,BM77) -> 0.27097886 | BT78: =AVERAGE(BB77,BH77,BN77) -> 0.27255322 | BW78: =AVERAGE(BE77,BK77,BQ77) -> 0.22376911 | BX78: =AVERAGE(BF77,BL77,BR77) -> 0.25000831 | BY78: =AVERAGE(BG77,BM77,BS77) -> 0.26089018 | BZ78: =AVERAGE(BH77,BN77,BT77) -> 0.2653324 | CC78: =AVERAGE(BK77,BQ77,BW77) -> 0.22495195 | CD78: =AVERAGE(BL77,BR77,BX77) -> 0.24952758 | CE78: =AVERAGE(BM77,BS77,BY77) -> 0.25993554 | CF78: =AVERAGE(BN77,BT77,BZ77) -> 0.26558492 | CI78: =AVERAGE(BQ77,BW77,CC77) -> 0.2239206 | CJ78: =AVERAGE(BR77,BX77,CD77) -> 0.2510282 | CK78: =AVERAGE(BS77,BY77,CE77) -> 0.26027826 | CL78: =AVERAGE(BT77,BZ77,CF77) -> 0.26477294
A79: SG&A | C79: 0.23969236 | D79: 0.2537631 | E79: 0.25721603 | F79: 0.24932851 | I79: =I13/M13 -> 0.24589326 | J79: =J13/M13 -> 0.24228111 | K79: =K13/M13:M13 -> 0.25689588 | L79: =L13/M13 -> 0.25492975 | O79: =O13/S13 -> 0.23778481 | P79: =P13/S13 -> 0.25619275 | Q79: =Q13/S13:S13 -> 0.25197153 | R79: =R13/S13 -> 0.25405091 | U79: =U13/Y13 -> 0.25890809 | V79: =V13/Y13 -> 0.24461878 | W79: =W13/Y13:Y13 -> 0.24194182 | X79: =X13/Y13 -> 0.25453131 | AA79: =AA13/AE13 -> 0.24181289 | AB79: =AB13/AE13 -> 0.23856042 | AC79: =AC13/AE13:AE13 -> 0.2566264 | AD79: =AD13/AE13 -> 0.26300028 | AG79: =AG13/AK13 -> 0.2517921 | AH79: =AH13/AK13 -> 0.25462343 | AI79: =AI13/AK13:AK13 -> 0.24493122 | AJ79: =AJ13/AK13 -> 0.24865325 | AM79: =AM13/AQ13 -> 0.24653171 | AN79: =AN13/AQ13 -> 0.24888297 | AO79: =AO13/AQ13:AQ13 -> 0.2475625 | AP79: =AP13/AQ13 -> 0.25702282 | AS79: =AS13/AW13 -> 0.25200953 | AT79: =AT13/AW13 -> 0.24276934 | AU79: =AU13/AW13:AW13 -> 0.24928524 | AV79: =AV13/AW13 -> 0.25593589 | AY79: =AY13/BC13 -> 0.20861604 | AZ79: =AZ13/BC13 -> 0.200346 | BA79: =BA13/BC13:BC13 -> 0.29833195 | BB79: =BB13/BC13 -> 0.292706 | BE79: =BE13/BI13 -> 0.24728238 | BF79: =BF13/BI13 -> 0.24919094 | BG79: =BG13/BI13:BI13 -> 0.2416397 | BH79: =BH13/BI13 -> 0.26188698 | BK79: =BK13/BO13 -> 0.24307692 | BL79: =BL13/BO13 -> 0.24649573 | BM79: =BM13/BO13:BO13 -> 0.24581197 | BN79: =BN13/BO13 -> 0.26461538 | BQ79: =BQ13/BU13 -> 0.19839513 | BR79: =BR13/BU13 -> 0.26409581 | BS79: =BS13/BU13:BU13 -> 0.26300847 | BT79: =BT13/BU13 -> 0.27450059 | BW79: =BW13/CA13 -> 0.24503789 | BX79: =BX13/CA13 -> 0.24554369 | BY79: =BY13/CA13:CA13 -> 0.25135431 | BZ79: =BZ13/CA13 -> 0.2580641 | CC79: =CC13/CG13 -> 0.24517848 | CD79: =CD13/CG13 -> 0.2454439 | CE79: =CE13/CG13:CG13 -> 0.25127825 | CF79: =CF13/CG13 -> 0.25809937 | CI79: =CI13/CM13 -> 0.24528003 | CJ79: =CJ13/CM13 -> 0.24535048 | CK79: =CK13/CM13:CM13 -> 0.25124409 | CL79: =CL13/CM13 -> 0.2581254
A80: Three Year Average | O80: 0.24164863 | P80: 0.24680244 | Q80: 0.25699532 | R80: 0.25455361 | U80: =AVERAGE(C79,I79,O79) -> 0.24112348 | V80: =AVERAGE(D79,J79,P79) -> 0.25074565 | W80: =AVERAGE(E79,K79,Q79) -> 0.25536115 | X80: =AVERAGE(F79,L79,R79) -> 0.25276972 | AA80: =AVERAGE(I79,O79,U79) -> 0.24752872 | AB80: =AVERAGE(J79,P79,V79) -> 0.24769754 | AC80: =AVERAGE(K79,Q79,W79) -> 0.25026975 | AD80: =AVERAGE(L79,R79,X79) -> 0.25450399 | AG80: =AVERAGE(O79,U79,AA79) -> 0.2461686 | AH80: =AVERAGE(P79,V79,AB79) -> 0.24645732 | AI80: =AVERAGE(Q79,W79,AC79) -> 0.25017992 | AJ80: =AVERAGE(R79,X79,AD79) -> 0.25719416 | AM80: =AVERAGE(U79,AA79,AG79) -> 0.25083769 | AN80: =AVERAGE(V79,AB79,AH79) -> 0.24593421 | AO80: =AVERAGE(W79,AC79,AI79) -> 0.24783315 | AP80: =AVERAGE(X79,AD79,AJ79) -> 0.25539495 | AS80: =AVERAGE(AA79,AG79,AM79) -> 0.24671223 | AT80: =AVERAGE(AB79,AH79,AN79) -> 0.24735561 | AU80: =AVERAGE(AC79,AI79,AO79) -> 0.24970671 | AV80: =AVERAGE(AD79,AJ79,AP79) -> 0.25622545 | AY80: =AVERAGE(AG79,AM79,AS79) -> 0.25011111 | AZ80: =AVERAGE(AH79,AN79,AT79) -> 0.24875858 | BA80: =AVERAGE(AI79,AO79,AU79) -> 0.24725965 | BB80: =AVERAGE(AJ79,AP79,AV79) -> 0.25387065 | BE80: =AVERAGE(AM79,AS79,AY79) -> 0.23571909 | BF80: =AVERAGE(AN79,AT79,AZ79) -> 0.2306661 | BG80: =AVERAGE(AO79,AU79,BA79) -> 0.2650599 | BH80: =AVERAGE(AP79,AV79,BB79) -> 0.26855491 | BK80: =AVERAGE(AS79,AY79,BE79) -> 0.23596932 | BL80: =AVERAGE(AT79,AZ79,BF79) -> 0.23076876 | BM80: =AVERAGE(AU79,BA79,BG79) -> 0.26308563 | BN80: =AVERAGE(AV79,BB79,BH79) -> 0.27017629 | BQ80: =AVERAGE(AY79,BE79,BK79) -> 0.23299178 | BR80: =AVERAGE(AZ79,BF79,BL79) -> 0.23201089 | BS80: =AVERAGE(BA79,BG79,BM79) -> 0.26192787 | BT80: =AVERAGE(BB79,BH79,BN79) -> 0.27306946 | BW80: =AVERAGE(BE79,BK79,BQ79) -> 0.22958481 | BX80: =AVERAGE(BF79,BL79,BR79) -> 0.25326083 | BY80: =AVERAGE(BG79,BM79,BS79) -> 0.25015338 | BZ80: =AVERAGE(BH79,BN79,BT79) -> 0.26700098 | CC80: =AVERAGE(BK79,BQ79,BW79) -> 0.22883665 | CD80: =AVERAGE(BL79,BR79,BX79) -> 0.25204508 | CE80: =AVERAGE(BM79,BS79,BY79) -> 0.25339158 | CF80: =AVERAGE(BN79,BT79,BZ79) -> 0.26572669 | CI80: =AVERAGE(BQ79,BW79,CC79) -> 0.22953717 | CJ80: =AVERAGE(BR79,BX79,CD79) -> 0.25169447 | CK80: =AVERAGE(BS79,BY79,CE79) -> 0.25521367 | CL80: =AVERAGE(BT79,BZ79,CF79) -> 0.26355469
A81: R&D | C81: 0.22202472 | D81: 0.24076378 | E81: 0.25827802 | F81: 0.27893348 | I81: =I15/M15 -> 0.23098996 | J81: =J15/M15 -> 0.24236444 | K81: =K15/M15 -> 0.25255276 | L81: =L15/M15 -> 0.27409284 | O81: =O15/S15 -> 0.23817069 | P81: =P15/S15 -> 0.24149276 | Q81: =Q15/S15 -> 0.24129749 | R81: =R15/S15 -> 0.27903907 | U81: =U15/Y15 -> 0.23005033 | V81: =V15/Y15 -> 0.23246798 | W81: =W15/Y15 -> 0.25069084 | X81: =X15/Y15 -> 0.28679086 | AA81: =AA15/AE15 -> 0.24675446 | AB81: =AB15/AE15 -> 0.25495658 | AC81: =AC15/AE15 -> 0.24786256 | AD81: =AD15/AE15 -> 0.2504264 | AG81: =AG15/AK15 -> 0.2389059 | AH81: =AH15/AK15 -> 0.24854073 | AI81: =AI15/AK15 -> 0.24478131 | AJ81: =AJ15/AK15 -> 0.26777207 | AM81: =AM15/AQ15 -> 0.2388776 | AN81: =AN15/AQ15 -> 0.24739869 | AO81: =AO15/AQ15 -> 0.24484944 | AP81: =AP15/AQ15 -> 0.26887427 | AS81: =AS15/AW15 -> 0.24513619 | AT81: =AT15/AW15 -> 0.24708171 | AU81: =AU15/AW15 -> 0.24902724 | AV81: =AV15/AW15 -> 0.25875486 | AY81: =AY15/BC15 -> 0.20343794 | AZ81: =AZ15/BC15 -> 0.20343794 | BA81: =BA15/BC15 -> 0.2840246 | BB81: =BB15/BC15 -> 0.30909951 | BE81: =BE15/BI15 -> 0.22564103 | BF81: =BF15/BI15 -> 0.21930618 | BG81: =BG15/BI15 -> 0.24977376 | BH81: =BH15/BI15 -> 0.30527903 | BK81: =BK15/BO15 -> 0.23483871 | BL81: =BL15/BO15 -> 0.24129032 | BM81: =BM15/BO15 -> 0.23870968 | BN81: =BN15/BO15 -> 0.28516129 | BQ81: =BQ15/BU15 -> 0.18413609 | BR81: =BR15/BU15 -> 0.25935935 | BS81: =BS15/BU15 -> 0.27218281 | BT81: =BT15/BU15 -> 0.28432175 | BW81: =BW15/CA15 -> 0.24523456 | BX81: =BX15/CA15 -> 0.24513721 | BY81: =BY15/CA15 -> 0.25307385 | BZ81: =BZ15/CA15 -> 0.25655438 | CC81: =CC15/CG15 -> 0.24539336 | CD81: =CD15/CG15 -> 0.24501646 | CE81: =CE15/CG15 -> 0.25307034 | CF81: =CF15/CG15 -> 0.25651985 | CI81: =CI15/CM15 -> 0.24549254 | CJ81: =CJ15/CM15 -> 0.24491413 | CK81: =CK15/CM15 -> 0.25308765 | CL81: =CL15/CM15 -> 0.25650568
A82: Three Year Average | O82: 0.22648832 | P82: 0.24321333 | Q82: 0.25496955 | R82: 0.2753288 | U82: =AVERAGE(C81,I81,O81) -> 0.23039512 | V82: =AVERAGE(D81,J81,P81) -> 0.24154033 | W82: =AVERAGE(E81,K81,Q81) -> 0.25070942 | X82: =AVERAGE(F81,L81,R81) -> 0.27735513 | AA82: =AVERAGE(I81,O81,U81) -> 0.23307032 | AB82: =AVERAGE(J81,P81,V81) -> 0.23877506 | AC82: =AVERAGE(K81,Q81,W81) -> 0.24818036 | AD82: =AVERAGE(L81,R81,X81) -> 0.27997426 | AG82: =AVERAGE(O81,U81,AA81) -> 0.23832516 | AH82: =AVERAGE(P81,V81,AB81) -> 0.24297244 | AI82: =AVERAGE(Q81,W81,AC81) -> 0.24661696 | AJ82: =AVERAGE(R81,X81,AD81) -> 0.27208544 | AM82: =AVERAGE(U81,AA81,AG81) -> 0.23857023 | AN82: =AVERAGE(V81,AB81,AH81) -> 0.24532176 | AO82: =AVERAGE(W81,AC81,AI81) -> 0.24777824 | AP82: =AVERAGE(X81,AD81,AJ81) -> 0.26832978 | AS82: =AVERAGE(AA81,AG81,AM81) -> 0.24151265 | AT82: =AVERAGE(AB81,AH81,AN81) -> 0.25029867 | AU82: =AVERAGE(AC81,AI81,AO81) -> 0.2458311 | AV82: =AVERAGE(AD81,AJ81,AP81) -> 0.26235758 | AY82: =AVERAGE(AG81,AM81,AS81) -> 0.24097323 | AZ82: =AVERAGE(AH81,AN81,AT81) -> 0.24767371 | BA82: =AVERAGE(AI81,AO81,AU81) -> 0.24621933 | BB82: =AVERAGE(AJ81,AP81,AV81) -> 0.26513373 | BE82: =AVERAGE(AM81,AS81,AY81) -> 0.22915058 | BF82: =AVERAGE(AN81,AT81,AZ81) -> 0.23263945 | BG82: =AVERAGE(AO81,AU81,BA81) -> 0.25930043 | BH82: =AVERAGE(AP81,AV81,BB81) -> 0.27890955 | BK82: =AVERAGE(AS81,AY81,BE81) -> 0.22473839 | BL82: =AVERAGE(AT81,AZ81,BF81) -> 0.22327528 | BM82: =AVERAGE(AU81,BA81,BG81) -> 0.26094186 | BN82: =AVERAGE(AV81,BB81,BH81) -> 0.29104447 | BQ82: =AVERAGE(AY81,BE81,BK81) -> 0.22130589 | BR82: =AVERAGE(AZ81,BF81,BL81) -> 0.22134482 | BS82: =AVERAGE(BA81,BG81,BM81) -> 0.25750268 | BT82: =AVERAGE(BB81,BH81,BN81) -> 0.29984661 | BW82: =AVERAGE(BE81,BK81,BQ81) -> 0.21487194 | BX82: =AVERAGE(BF81,BL81,BR81) -> 0.23998528 | BY82: =AVERAGE(BG81,BM81,BS81) -> 0.25355541 | BZ82: =AVERAGE(BH81,BN81,BT81) -> 0.29158736 | CC82: =AVERAGE(BK81,BQ81,BW81) -> 0.22140312 | CD82: =AVERAGE(BL81,BR81,BX81) -> 0.24859563 | CE82: =AVERAGE(BM81,BS81,BY81) -> 0.25465544 | CF82: =AVERAGE(BN81,BT81,BZ81) -> 0.27534581 | CI82: =AVERAGE(BQ81,BW81,CC81) -> 0.22492134 | CJ82: =AVERAGE(BR81,BX81,CD81) -> 0.24983767 | CK82: =AVERAGE(BS81,BY81,CE81) -> 0.25944233 | CL82: =AVERAGE(BT81,BZ81,CF81) -> 0.26579866
A83: Operating Income | C83: 0.24791884 | D83: 0.23998654 | E83: 0.25271308 | F83: 0.25938155 | I83: =I17/M17 -> 0.2336729 | J83: =J17/M17 -> 0.24584055 | K83: =K17/M17 -> 0.26388487 | L83: =L17/M17 -> 0.25660168 | O83: =O17/S17 -> 0.25261782 | P83: =P17/S17 -> 0.21856698 | Q83: =Q17/S17 -> 0.26214048 | R83: =R17/S17 -> 0.26667472 | U83: =U17/Y17 -> 0.25624449 | V83: =V17/Y17 -> 0.24668937 | W83: =W17/Y17 -> 0.25224401 | X83: =X17/Y17 -> 0.24482212 | AA83: =AA17/AE17 -> 0.23202038 | AB83: =AB17/AE17 -> 0.2489267 | AC83: =AC17/AE17 -> 0.26695871 | AD83: =AD17/AE17 -> 0.25209421 | AG83: =AG17/AK17 -> 0.21342303 | AH83: =AH17/AK17 -> 0.24293912 | AI83: =AI17/AK17 -> 0.28456953 | AJ83: =AJ17/AK17 -> 0.25906831 | AM83: =AM17/AQ17 -> 0.24121611 | AN83: =AN17/AQ17 -> 0.23595614 | AO83: =AO17/AQ17 -> 0.26271418 | AP83: =AP17/AQ17 -> 0.26011357 | AS83: =AS17/AW17 -> 0.22431737 | AT83: =AT17/AW17 -> 0.24361506 | AU83: =AU17/AW17 -> 0.26783622 | AV83: =AV17/AW17 -> 0.26423135 | AY83: =AY17/BC17 -> 0.1847484 | AZ83: =AZ17/BC17 -> 0.19407908 | BA83: =BA17/BC17 -> 0.31566277 | BB83: =BB17/BC17 -> 0.30550974 | BE83: =BE17/BI17 -> 0.23292043 | BF83: =BF17/BI17 -> 0.25440784 | BG83: =BG17/BI17 -> 0.27506528 | BH83: =BH17/BI17 -> 0.23760645 | BK83: =BK17/BO17 -> 0.2504972 | BL83: =BL17/BO17 -> 0.23642027 | BM83: =BM17/BO17 -> 0.26385224 | BN83: =BN17/BO17 -> 0.24923028 | BQ83: =BQ17/BU17 -> 0.17784397 | BR83: =BR17/BU17 -> 0.25820968 | BS83: =BS17/BU17 -> 0.28374779 | BT83: =BT17/BU17 -> 0.28019857 | BW83: =BW17/CA17 -> 0.23885958 | BX83: =BX17/CA17 -> 0.24690446 | BY83: =BY17/CA17 -> 0.25583201 | BZ83: =BZ17/CA17 -> 0.25840395 | CC83: =CC17/CG17 -> 0.23915584 | CD83: =CD17/CG17 -> 0.24676121 | CE83: =CE17/CG17 -> 0.25573642 | CF83: =CF17/CG17 -> 0.25834652 | CI83: =CI17/CM17 -> 0.23906618 | CJ83: =CJ17/CM17 -> 0.2407785 | CK83: =CK17/CM17 -> 0.25875 | CL83: =CL17/CM17 -> 0.26140532
A84: Three Year Average | O84: 0.24788815 | P84: 0.24485341 | Q84: 0.25282169 | R84: 0.25443675 | U84: =AVERAGE(C83,I83,O83) -> 0.24473652 | V84: =AVERAGE(D83,J83,P83) -> 0.23479802 | W84: =AVERAGE(E83,K83,Q83) -> 0.25957947 | X84: =AVERAGE(F83,L83,R83) -> 0.26088598 | AA84: =AVERAGE(I83,O83,U83) -> 0.24751174 | AB84: =AVERAGE(J83,P83,V83) -> 0.2370323 | AC84: =AVERAGE(K83,Q83,W83) -> 0.25942312 | AD84: =AVERAGE(L83,R83,X83) -> 0.25603284 | AG84: =AVERAGE(O83,U83,AA83) -> 0.2469609 | AH84: =AVERAGE(P83,V83,AB83) -> 0.23806102 | AI84: =AVERAGE(Q83,W83,AC83) -> 0.26044773 | AJ84: =AVERAGE(R83,X83,AD83) -> 0.25453035 | AM84: =AVERAGE(U83,AA83,AG83) -> 0.23389597 | AN84: =AVERAGE(V83,AB83,AH83) -> 0.24618506 | AO84: =AVERAGE(W83,AC83,AI83) -> 0.26792409 | AP84: =AVERAGE(X83,AD83,AJ83) -> 0.25199488 | AS84: =AVERAGE(AA83,AG83,AM83) -> 0.22888651 | AT84: =AVERAGE(AB83,AH83,AN83) -> 0.24260732 | AU84: =AVERAGE(AC83,AI83,AO83) -> 0.27141414 | AV84: =AVERAGE(AD83,AJ83,AP83) -> 0.25709203 | AY84: =AVERAGE(AG83,AM83,AS83) -> 0.22631883 | AZ84: =AVERAGE(AH83,AN83,AT83) -> 0.24083678 | BA84: =AVERAGE(AI83,AO83,AU83) -> 0.27170665 | BB84: =AVERAGE(AJ83,AP83,AV83) -> 0.26113774 | BE84: =AVERAGE(AM83,AS83,AY83) -> 0.21676062 | BF84: =AVERAGE(AN83,AT83,AZ83) -> 0.2245501 | BG84: =AVERAGE(AO83,AU83,BA83) -> 0.28207106 | BH84: =AVERAGE(AP83,AV83,BB83) -> 0.27661822 | BK84: =AVERAGE(AS83,AY83,BE83) -> 0.2139954 | BL84: =AVERAGE(AT83,AZ83,BF83) -> 0.23070066 | BM84: =AVERAGE(AU83,BA83,BG83) -> 0.28618809 | BN84: =AVERAGE(AV83,BB83,BH83) -> 0.26911585 | BQ84: =AVERAGE(AY83,BE83,BK83) -> 0.22272201 | BR84: =AVERAGE(AZ83,BF83,BL83) -> 0.2283024 | BS84: =AVERAGE(BA83,BG83,BM83) -> 0.2848601 | BT84: =AVERAGE(BB83,BH83,BN83) -> 0.26411549 | BW84: =AVERAGE(BE83,BK83,BQ83) -> 0.22042053 | BX84: =AVERAGE(BF83,BL83,BR83) -> 0.24967926 | BY84: =AVERAGE(BG83,BM83,BS83) -> 0.27422177 | BZ84: =AVERAGE(BH83,BN83,BT83) -> 0.25567843 | CC84: =AVERAGE(BK83,BQ83,BW83) -> 0.22240025 | CD84: =AVERAGE(BL83,BR83,BX83) -> 0.24717814 | CE84: =AVERAGE(BM83,BS83,BY83) -> 0.26781068 | CF84: =AVERAGE(BN83,BT83,BZ83) -> 0.26261093 | CI84: =AVERAGE(BQ83,BW83,CC83) -> 0.2186198 | CJ84: =AVERAGE(BR83,BX83,CD83) -> 0.25062512 | CK84: =AVERAGE(BS83,BY83,CE83) -> 0.26510541 | CL84: =AVERAGE(BT83,BZ83,CF83) -> 0.26564968
A85: EPS | C85: 0.2511189 | D85: 0.24082798 | E85: 0.25403872 | F85: 0.25644394 | I85: =I34/M34 -> 0.24014461 | J85: =J34/M34 -> 0.24466269 | K85: =K34/M34 -> 0.26518682 | L85: =L34/M34 -> 0.2520533 | O85: =O34/S34 -> 0.25253843 | P85: =P34/S34 -> 0.21397682 | Q85: =Q34/S34 -> 0.28176193 | R85: =R34/S34 -> 0.25401292 | U85: =U34/Y34 -> 0.25549777 | V85: =V34/Y34 -> 0.24157444 | W85: =W34/Y34 -> 0.2519703 | X85: =X34/Y34 -> 0.25314972 | AA85: =AA34/AE34 -> 0.23962896 | AB85: =AB34/AE34 -> 0.24539097 | AC85: =AC34/AE34 -> 0.26896594 | AD85: =AD34/AE34 -> 0.24644387 | AG85: =AG34/AK34 -> 0.21241861 | AH85: =AH34/AK34 -> 0.24391179 | AI85: =AI34/AK34 -> 0.2823054 | AJ85: =AJ34/AK34 -> 0.26395154 | AM85: =AM34/AQ34 -> 0.23255156 | AN85: =AN34/AQ34 -> 0.2402595 | AO85: =AO34/AQ34 -> 0.26417309 | AP85: =AP34/AQ34 -> 0.26306832 | AS85: =AS34/AW34 -> 0.22011433 | AT85: =AT34/AW34 -> 0.2450252 | AU85: =AU34/AW34 -> 0.26888813 | AV85: =AV34/AW34 -> 0.26845315 | AY85: =AY34/BC34 -> 0.2143269 | AZ85: =AZ34/BC34 -> 0.2252618 | BA85: =BA34/BC34 -> 0.28689469 | BB85: =BB34/BC34 -> 0.2715214 | BE85: =BE34/BI34 -> 0.22805902 | BF85: =BF34/BI34 -> 0.25327721 | BG85: =BG34/BI34 -> 0.27241618 | BH85: =BH34/BI34 -> 0.24616096 | BK85: =BK34/BO34 -> 0.24539998 | BL85: =BL34/BO34 -> 0.24235448 | BM85: =BM34/BO34 -> 0.25939056 | BN85: =BN34/BO34 -> 0.25282864 | BQ85: =BQ34/BU34 -> 0.2259478 | BR85: =BR34/BU34 -> 0.23832609 | BS85: =BS34/BU34 -> 0.26694078 | BT85: =BT34/BU34 -> 0.26386283 | BW85: =BW34/CA34 -> 0.23800547 | BX85: =BX34/CA34 -> 0.24806568 | BY85: =BY34/CA34 -> 0.25874977 | BZ85: =BZ34/CA34 -> 0.25512216 | CC85: =CC34/CG34 -> 0.2369545 | CD85: =CD34/CG34 -> 0.24577258 | CE85: =CE34/CG34 -> 0.25668765 | CF85: =CF34/CG34 -> 0.26052629 | CI85: =CI34/CM34 -> 0.23766295 | CJ85: =CJ34/CM34 -> 0.23935058 | CK85: =CK34/CM34 -> 0.2596177 | CL85: =CL34/CM34 -> 0.2632634
A86: Three Year Average | O86: 0.25028196 | P86: 0.2426593 | Q86: 0.25496844 | R86: 0.25376423 | U86: =AVERAGE(C85,I85,O85) -> 0.24793398 | V86: =AVERAGE(D85,J85,P85) -> 0.23315583 | W86: =AVERAGE(E85,K85,Q85) -> 0.26699582 | X86: =AVERAGE(F85,L85,R85) -> 0.25417005 | AA86: =AVERAGE(I85,O85,U85) -> 0.2493936 | AB86: =AVERAGE(J85,P85,V85) -> 0.23340465 | AC86: =AVERAGE(K85,Q85,W85) -> 0.26630635 | AD86: =AVERAGE(L85,R85,X85) -> 0.25307198 | AG86: =AVERAGE(O85,U85,AA85) -> 0.24922172 | AH86: =AVERAGE(P85,V85,AB85) -> 0.23364741 | AI86: =AVERAGE(Q85,W85,AC85) -> 0.26756606 | AJ86: =AVERAGE(R85,X85,AD85) -> 0.25120217 | AM86: =AVERAGE(U85,AA85,AG85) -> 0.23584845 | AN86: =AVERAGE(V85,AB85,AH85) -> 0.24362573 | AO86: =AVERAGE(W85,AC85,AI85) -> 0.26774722 | AP86: =AVERAGE(X85,AD85,AJ85) -> 0.25451504 | AS86: =AVERAGE(AA85,AG85,AM85) -> 0.22819971 | AT86: =AVERAGE(AB85,AH85,AN85) -> 0.24318742 | AU86: =AVERAGE(AC85,AI85,AO85) -> 0.27181481 | AV86: =AVERAGE(AD85,AJ85,AP85) -> 0.25782124 | AY86: =AVERAGE(AG85,AM85,AS85) -> 0.22169483 | AZ86: =AVERAGE(AH85,AN85,AT85) -> 0.2430655 | BA86: =AVERAGE(AI85,AO85,AU85) -> 0.27178887 | BB86: =AVERAGE(AJ85,AP85,AV85) -> 0.26515767 | BE86: =AVERAGE(AM85,AS85,AY85) -> 0.22233093 | BF86: =AVERAGE(AN85,AT85,AZ85) -> 0.23684883 | BG86: =AVERAGE(AO85,AU85,BA85) -> 0.27331864 | BH86: =AVERAGE(AP85,AV85,BB85) -> 0.26768096 | BK86: =AVERAGE(AS85,AY85,BE85) -> 0.22083342 | BL86: =AVERAGE(AT85,AZ85,BF85) -> 0.24118807 | BM86: =AVERAGE(AU85,BA85,BG85) -> 0.27606633 | BN86: =AVERAGE(AV85,BB85,BH85) -> 0.26204517 | BQ86: =AVERAGE(AY85,BE85,BK85) -> 0.22926197 | BR86: =AVERAGE(AZ85,BF85,BL85) -> 0.24029783 | BS86: =AVERAGE(BA85,BG85,BM85) -> 0.27290048 | BT86: =AVERAGE(BB85,BH85,BN85) -> 0.256837 | BW86: =AVERAGE(BE85,BK85,BQ85) -> 0.2331356 | BX86: =AVERAGE(BF85,BL85,BR85) -> 0.24465259 | BY86: =AVERAGE(BG85,BM85,BS85) -> 0.26624917 | BZ86: =AVERAGE(BH85,BN85,BT85) -> 0.25428414 | CC86: =AVERAGE(BK85,BQ85,BW85) -> 0.23645109 | CD86: =AVERAGE(BL85,BR85,BX85) -> 0.24291541 | CE86: =AVERAGE(BM85,BS85,BY85) -> 0.2616937 | CF86: =AVERAGE(BN85,BT85,BZ85) -> 0.25727121 | CI86: =AVERAGE(BQ85,BW85,CC85) -> 0.23363593 | CJ86: =AVERAGE(BR85,BX85,CD85) -> 0.24405478 | CK86: =AVERAGE(BS85,BY85,CE85) -> 0.26079273 | CL86: =AVERAGE(BT85,BZ85,CF85) -> 0.25983709
A88: Reconciliation to GAAP
A89: In-process R&D | C89: 0 | D89: 0 | E89: 7.394 | F89: 114.739 | G89: =SUM(E89:F89) -> 122.133 | I89: 0 | J89: 0 | K89: 0 | L89: 0 | M89: =SUM(I89:L89) -> 0 | O89: 0 | P89: 0 | Q89: 0 | R89: 0 | S89: =SUM(O89:R89) -> 0 | U89: 0 | V89: 0 | W89: 0 | X89: 0 | Y89: =SUM(U89:X89) -> 0 | AA89: 0 | AB89: 0 | AC89: 0 | AD89: 0 | AE89: =SUM(AA89:AD89) -> 0 | AG89: 0 | AH89: 0 | AI89: 0 | AJ89: 0 | AK89: =SUM(AG89:AJ89) -> 0 | AM89: 0 | AN89: 0 | AO89: 0 | AP89: 0 | AQ89: =SUM(AM89:AP89) -> 0 | AS89: 0 | AT89: 20 | AU89: 0 | AV89: 0 | AW89: =SUM(AS89:AV89) -> 20 | AY89: 0 | AZ89: 0 | BA89: 0 | BB89: 0 | BC89: =SUM(AY89:BB89) -> 0 | BE89: 0 | BF89: 0 | BG89: 0 | BH89: 0 | BI89: =SUM(BE89:BH89) -> 0 | BK89: 0 | BL89: 0 | BM89: 0 | BN89: 0 | BO89: =SUM(BK89:BN89) -> 0 | BQ89: 0 | BR89: 0 | BS89: 0 | BT89: 0 | BU89: =SUM(BQ89:BT89) -> 0 | BW89: 0 | BX89: 0 | BY89: 0 | BZ89: 0 | CA89: =SUM(BW89:BZ89) -> 0 | CC89: 0 | CD89: 0 | CE89: 0 | CF89: 0 | CG89: =SUM(CC89:CF89) -> 0 | CI89: 0 | CJ89: 0 | CK89: 0 | CL89: 0 | CM89: =SUM(CI89:CL89) -> 0
A90: (Gains)/losses on asset sale | C90: 0 | D90: 0 | E90: 0 | F90: 0 | G90: 0 | I90: 0 | J90: 0 | K90: 0 | L90: 0 | M90: =SUM(I90:L90) -> 0 | O90: 0 | P90: 0 | Q90: 0 | R90: 0 | S90: =SUM(O90:R90) -> 0 | U90: 0 | V90: 0 | W90: 0 | X90: 0 | Y90: =SUM(U90:X90) -> 0 | AA90: 0 | AB90: 0 | AC90: 0 | AD90: 0 | AE90: =SUM(AA90:AD90) -> 0 | AG90: 0 | AH90: 0 | AI90: 0 | AJ90: 0 | AK90: =SUM(AG90:AJ90) -> 0 | AM90: 0 | AN90: 0 | AO90: 0 | AP90: 0 | AQ90: =SUM(AM90:AP90) -> 0 | AS90: 0 | AT90: -8 | AU90: 0 | AV90: 0 | AW90: =SUM(AS90:AV90) -> -8 | AY90: 0 | AZ90: 0 | BA90: 0 | BB90: 0 | BC90: =SUM(AY90:BB90) -> 0 | BE90: 0 | BF90: 0 | BG90: 0 | BH90: 0 | BI90: =SUM(BE90:BH90) -> 0 | BK90: 0 | BL90: 0 | BM90: 0 | BN90: 0 | BO90: =SUM(BK90:BN90) -> 0 | BQ90: 0 | BR90: 0 | BS90: 0 | BT90: 0 | BU90: =SUM(BQ90:BT90) -> 0 | BW90: 0 | BX90: 0 | BY90: 0 | BZ90: 0 | CA90: =SUM(BW90:BZ90) -> 0 | CC90: 0 | CD90: 0 | CE90: 0 | CF90: 0 | CG90: =SUM(CC90:CF90) -> 0 | CI90: 0 | CJ90: 0 | CK90: 0 | CL90: 0 | CM90: =SUM(CI90:CL90) -> 0
A91: (Gains)/losses on redemption of debt | C91: 0 | D91: 0 | E91: 0 | F91: 0 | G91: 0 | I91: 0 | J91: 0 | K91: 0 | L91: 0 | M91: =SUM(I91:L91) -> 0 | O91: 0 | P91: 0 | Q91: 0 | R91: 0 | S91: =SUM(O91:R91) -> 0 | U91: 0 | V91: 0 | W91: 0 | X91: 0 | Y91: =SUM(U91:X91) -> 0 | AA91: 0 | AB91: 0 | AC91: 0 | AD91: 0 | AE91: =SUM(AA91:AD91) -> 0 | AG91: 0 | AH91: 0 | AI91: 0 | AJ91: 0 | AK91: =SUM(AG91:AJ91) -> 0 | AM91: 0 | AN91: 0 | AO91: 0 | AP91: 0 | AQ91: =SUM(AM91:AP91) -> 0 | AS91: 0 | AT91: 0 | AU91: 0 | AV91: 0 | AW91: =SUM(AS91:AV91) -> 0 | AY91: 0 | AZ91: 0 | BA91: 0 | BB91: 0 | BC91: =SUM(AY91:BB91) -> 0 | BE91: 0 | BF91: 0 | BG91: 0 | BH91: 0 | BI91: =SUM(BE91:BH91) -> 0 | BK91: 0 | BL91: 0 | BM91: 0 | BN91: 0 | BO91: =SUM(BK91:BN91) -> 0 | BQ91: 0 | BR91: 0 | BS91: 0 | BT91: 0 | BU91: =SUM(BQ91:BT91) -> 0 | BW91: 0 | BX91: 0 | BY91: 0 | BZ91: 0 | CA91: =SUM(BW91:BZ91) -> 0 | CC91: 0 | CD91: 0 | CE91: 0 | CF91: 0 | CG91: =SUM(CC91:CF91) -> 0 | CI91: 0 | CJ91: 0 | CK91: 0 | CL91: 0 | CM91: =SUM(CI91:CL91) -> 0
A92: Change in accounting | C92: 0 | D92: 0 | E92: 0 | F92: 0 | G92: 0 | I92: 0 | J92: 0 | K92: 0 | L92: 0 | M92: =SUM(I92:L92) -> 0 | O92: 0 | P92: 0 | Q92: 0 | R92: 0 | S92: =SUM(O92:R92) -> 0 | U92: 0 | V92: 0 | W92: 0 | X92: 0 | Y92: =SUM(U92:X92) -> 0 | AA92: 0 | AB92: 0 | AC92: 0 | AD92: 0 | AE92: =SUM(AA92:AD92) -> 0 | AG92: 0 | AH92: 0 | AI92: 0 | AJ92: 0 | AK92: =SUM(AG92:AJ92) -> 0 | AM92: 0 | AN92: 0 | AO92: 0 | AP92: 0 | AQ92: =SUM(AM92:AP92) -> 0 | AS92: 0 | AT92: 0 | AU92: 0 | AV92: 0 | AW92: =SUM(AS92:AV92) -> 0 | AY92: 0 | AZ92: -9 | BA92: =(447-148)-8 -> 291 | BB92: 27 | BC92: =SUM(AY92:BB92) -> 309 | BE92: =-3+0.04 -> -2.96 | BF92: 0 | BG92: 0 | BH92: 2 | BI92: =SUM(BE92:BH92) -> -0.96 | BK92: 0 | BL92: 0 | BM92: 741 | BN92: 0 | BO92: =SUM(BK92:BN92) -> 741 | BQ92: 0 | BR92: 0 | BS92: 0 | BT92: 0 | BU92: =SUM(BQ92:BT92) -> 0 | BW92: 0 | BX92: 0 | BY92: 0 | BZ92: 0 | CA92: =SUM(BW92:BZ92) -> 0 | CC92: 0 | CD92: 0 | CE92: 0 | CF92: 0 | CG92: =SUM(CC92:CF92) -> 0 | CI92: 0 | CJ92: 0 | CK92: 0 | CL92: 0 | CM92: =SUM(CI92:CL92) -> 0
A93: Restructuring Charges | C93: 0 | D93: 0 | E93: 0 | F93: 0 | G93: 0 | I93: 0 | J93: 0 | K93: 0 | L93: 0 | M93: =SUM(I93:L93) -> 0 | O93: 0 | P93: 0 | Q93: 0 | R93: 0 | S93: =SUM(O93:R93) -> 0 | U93: 0 | V93: 0 | W93: 0 | X93: 0 | Y93: =SUM(U93:X93) -> 0 | AA93: 0 | AB93: 0 | AC93: 0 | AD93: 0 | AE93: =SUM(AA93:AD93) -> 0 | AG93: 0 | AH93: 0 | AI93: 0 | AJ93: 0 | AK93: =SUM(AG93:AJ93) -> 0 | AM93: 0 | AN93: 0 | AO93: 0 | AP93: 0 | AQ93: =SUM(AM93:AP93) -> 0 | AS93: 0 | AT93: 0 | AU93: 9 | AV93: 0 | AW93: =SUM(AS93:AV93) -> 9 | AY93: 0 | AZ93: 0 | BA93: =24+75+5 -> 104 | BB93: =135+40 -> 175 | BC93: =SUM(AY93:BB93) -> 279 | BE93: 85 | BF93: 64 | BG93: 49 | BH93: 328 | BI93: =SUM(BE93:BH93) -> 526 | BK93: 35 | BL93: 11 | BM93: 8 | BN93: 30 | BO93: =SUM(BK93:BN93) -> 84 | BQ93: 236 | BR93: 175 | BS93: 125 | BT93: 100 | BU93: =SUM(BQ93:BT93) -> 636 | BW93: 100 | BX93: 100 | BY93: 100 | BZ93: 100 | CA93: =SUM(BW93:BZ93) -> 400 | CC93: 75 | CD93: 50 | CE93: 25 | CF93: 25 | CG93: =SUM(CC93:CF93) -> 175 | CI93: 10 | CJ93: 10 | CK93: 10 | CL93: 10 | CM93: =SUM(CI93:CL93) -> 40
A94: M&A related costs | C94: 0 | D94: 0 | E94: 0 | F94: 0 | G94: 0 | I94: 0 | J94: 0 | K94: 0 | L94: 0 | M94: =SUM(I94:L94) -> 0 | O94: 0 | P94: 0 | Q94: 0 | R94: 0 | S94: =SUM(O94:R94) -> 0 | U94: 0 | V94: 0 | W94: 0 | X94: 0 | Y94: =SUM(U94:X94) -> 0 | AA94: 0 | AB94: 0 | AC94: 0 | AD94: 0 | AE94: =SUM(AA94:AD94) -> 0 | AG94: 0 | AH94: 0 | AI94: 0 | AJ94: 0 | AK94: =SUM(AG94:AJ94) -> 0 | AM94: 0 | AN94: 0 | AO94: 0 | AP94: 0 | AQ94: =SUM(AM94:AP94) -> 0 | AS94: 0 | AT94: 0 | AU94: 0 | AV94: 0 | AW94: =SUM(AS94:AV94) -> 0 | AY94: 23 | AZ94: 112.5 | BA94: =-5+9 -> 4 | BB94: =7 -> 7 | BC94: =SUM(AY94:BB94) -> 146.5 | BE94: 35 | BF94: 40 | BG94: 40 | BH94: 77 | BI94: =SUM(BE94:BH94) -> 192 | BK94: =46+6 -> 52 | BL94: 63 | BM94: =50+23 -> 73 | BN94: =78+2 -> 80 | BO94: =SUM(BK94:BN94) -> 268 | BQ94: =74+44+50 -> 168 | BR94: 100 | BS94: 75 | BT94: 50 | BU94: =SUM(BQ94:BT94) -> 393 | BW94: 50 | BX94: 50 | BY94: 50 | BZ94: 50 | CA94: =SUM(BW94:BZ94) -> 200 | CC94: 40 | CD94: 40 | CE94: 40 | CF94: 40 | CG94: =SUM(CC94:CF94) -> 160 | CI94: 20 | CJ94: 20 | CK94: 20 | CL94: 20 | CM94: =SUM(CI94:CL94) -> 80
A95: Litigation Charges | C95: 0 | D95: 0 | E95: 0 | F95: 0 | G95: 0 | I95: 0 | J95: 0 | K95: 0 | L95: 0 | M95: =SUM(I95:L95) -> 0 | O95: 0 | P95: 0 | Q95: 0 | R95: 0 | S95: =SUM(O95:R95) -> 0 | U95: 0 | V95: 0 | W95: 0 | X95: 0 | Y95: =SUM(U95:X95) -> 0 | AA95: 0 | AB95: 0 | AC95: 0 | AD95: 0 | AE95: =SUM(AA95:AD95) -> 0 | AG95: 0 | AH95: 0 | AI95: 0 | AJ95: 0 | AK95: =SUM(AG95:AJ95) -> 0 | AM95: 0 | AN95: 0 | AO95: 22 | AP95: 341 | AQ95: =SUM(AM95:AP95) -> 363 | AS95: 0 | AT95: 0 | AU95: 0 | AV95: 0 | AW95: =SUM(AS95:AV95) -> 0 | AY95: 12 | AZ95: 0 | BA95: 0 | BB95: 0 | BC95: =SUM(AY95:BB95) -> 12 | BE95: 0 | BF95: 0 | BG95: 0 | BH95: 0 | BI95: =SUM(BE95:BH95) -> 0 | BK95: -336 | BL95: 0 | BM95: 0 | BN95: -1 | BO95: =SUM(BK95:BN95) -> -337 | BQ95: 0 | BR95: 0 | BS95: 0 | BT95: 0 | BU95: =SUM(BQ95:BT95) -> 0 | BW95: 0 | BX95: 0 | BY95: 0 | BZ95: 0 | CA95: =SUM(BW95:BZ95) -> 0 | CC95: 0 | CD95: 0 | CE95: 0 | CF95: 0 | CG95: =SUM(CC95:CF95) -> 0 | CI95: 0 | CJ95: 0 | CK95: 0 | CL95: 0 | CM95: =SUM(CI95:CL95) -> 0
A96: Amortization | AM96: 17.870075 | AN96: 19.8875 | AO96: 19.94115 | AP96: 19.076275 | AQ96: =SUM(AM96:AP96) -> 76.775 | AS96: 18.48 | AT96: 18.48 | AU96: 18.48 | AV96: 18.92 | AW96: =SUM(AS96:AV96) -> 74.36 | AY96: 18 | AZ96: 17.5 | BA96: 148 | BB96: 152 | BC96: =SUM(AY96:BB96) -> 335.5 | BE96: 157.8 | BF96: =136+1 -> 137 | BG96: 135 | BH96: =141-8 -> 133 | BI96: =SUM(BE96:BH96) -> 562.8 | BK96: 133 | BL96: 129 | BM96: =132-3-23 -> 106 | BN96: 130 | BO96: =SUM(BK96:BN96) -> 498 | BQ96: 135 | BR96: =CFS!BR13+CFS!BR14 -> 295.24464 | BS96: =CFS!BS13+CFS!BS14 -> 295.24464 | BT96: =CFS!BT13+CFS!BT14 -> 295.24464 | BU96: =SUM(BQ96:BT96) -> 1020.7339 | BW96: =CFS!BW13+CFS!BW14 -> 295.24464 | BX96: =CFS!BX13+CFS!BX14 -> 295.24464 | BY96: =CFS!BY13+CFS!BY14 -> 295.24464 | BZ96: =CFS!BZ13+CFS!BZ14 -> 295.24464 | CA96: =SUM(BW96:BZ96) -> 1180.9786 | CC96: =CFS!CC13+CFS!CC14 -> 295.24464 | CD96: =CFS!CD13+CFS!CD14 -> 295.24464 | CE96: =CFS!CE13+CFS!CE14 -> 295.24464 | CF96: =CFS!CF13+CFS!CF14 -> 295.24464 | CG96: =SUM(CC96:CF96) -> 1180.9786 | CI96: =CFS!CI13+CFS!CI14 -> 295.24464 | CJ96: =CFS!CJ13+CFS!CJ14 -> 295.24464 | CK96: =CFS!CK13+CFS!CK14 -> 295.24464 | CL96: =CFS!CL13+CFS!CL14 -> 295.24464 | CM96: =SUM(CI96:CL96) -> 1180.9786
A97: Other | C97: 103.00914 | D97: -6.9444914 | E97: -4.34 | F97: =-116.571-8.786644 -> -125.35764 | G97: =SUM(C97:F97) -> -33.632996 | I97: -0.66639559 | J97: -0.54321729 | K97: 0.358613 | L97: 0 | M97: =SUM(I97:L97) -> -0.85099987 | O97: 0 | P97: 0 | Q97: 0 | R97: 0 | S97: =SUM(O97:R97) -> 0 | U97: 0 | V97: 0 | W97: 0 | X97: 0 | Y97: =SUM(U97:X97) -> 0 | AA97: 0 | AB97: 0 | AC97: 0 | AD97: 9.27 | AE97: =SUM(AA97:AD97) -> 9.27 | AG97: 0 | AH97: 0 | AI97: 0 | AJ97: 20 | AK97: =SUM(AG97:AJ97) -> 20 | AM97: 0 | AN97: 0 | AO97: 0 | AP97: 6 | AQ97: =SUM(AM97:AP97) -> 6 | AS97: 0 | AT97: 11 | AU97: 0 | AV97: 0 | AW97: =SUM(AS97:AV97) -> 11 | AY97: 44 | AZ97: 58 | BA97: 0 | BB97: 0 | BC97: =SUM(AY97:BB97) -> 102 | BE97: 0 | BF97: -21.6 | BG97: =7+3-8-1 -> 1 | BH97: 3 | BI97: =SUM(BE97:BH97) -> -17.6 | BK97: =-7+42-1 -> 34 | BL97: =8+1 -> 9 | BM97: =87+31 -> 118 | BN97: =6+44 -> 50 | BO97: =SUM(BK97:BN97) -> 211 | BQ97: =7-1 -> 6 | BR97: 0 | BS97: 0 | BT97: 0 | BU97: =SUM(BQ97:BT97) -> 6 | BW97: 0 | BX97: 0 | BY97: 0 | BZ97: 0 | CA97: =SUM(BW97:BZ97) -> 0 | CC97: 0 | CD97: 0 | CE97: 0 | CF97: 0 | CG97: =SUM(CC97:CF97) -> 0 | CI97: 0 | CJ97: 0 | CK97: 0 | CL97: 0 | CM97: =SUM(CI97:CL97) -> 0
A98: Tax impact of adjustments | C98: 0 | D98: 0 | E98: 0 | F98: 0 | G98: =SUM(C98:F98) -> 0 | I98: 0 | J98: 0 | K98: 0 | L98: 0 | M98: =SUM(I98:L98) -> 0 | O98: 0 | P98: 0 | Q98: 0 | R98: 0 | S98: =SUM(O98:R98) -> 0 | U98: 0 | V98: 0 | W98: 0 | X98: 0 | Y98: =SUM(U98:X98) -> 0 | AA98: 0 | AB98: 0 | AC98: 0 | AD98: =-(9.27-6) -> -3.27 | AE98: =SUM(AA98:AD98) -> -3.27 | AG98: 0 | AH98: 0 | AI98: 0 | AJ98: =-(20-13) -> -7 | AK98: =SUM(AG98:AJ98) -> -7 | AM98: =-AM96*0.3 -> -5.3610225 | AN98: =-AN96*0.3 -> -5.96625 | AO98: =-(22-14)-AO96*0.3 -> -13.982345 | AP98: =-((341-211)+(6-4))-AP96*0.3 -> -137.72288 | AQ98: =SUM(AM98:AP98) -> -163.0325 | AS98: =-AS96*0.315 -> -5.8212 | AT98: =-((20-12)+(11-8)-(8-5))-AT96*0.315 -> -13.8212 | AU98: =-(9-6)-AU96*0.315 -> -8.8212 | AV98: =-SUM(AV89:AV97)*0.315 -> -5.9598 | AW98: =SUM(AS98:AV98) -> -34.4234 | AY98: =-(16+5+6+4) -> -31 | AZ98: =-(24+47+6) -> -77 | BA98: =-(2+3+9+28+128-2) -> -168 | BB98: =-3-15-51-54 -> -123 | BC98: =SUM(AY98:BB98) -> -399 | BE98: =-(34+32+13) -> -79 | BF98: =-(41+29+15) -> -85 | BG98: -106 | BH98: -99 | BI98: =SUM(BE98:BH98) -> -369 | BK98: 27 | BL98: -54 | BM98: -377 | BN98: -91 | BO98: =SUM(BK98:BN98) -> -495 | BQ98: 135 | BR98: =-(SUM(BR89:BR97)-BR96)*BR25-BR96*0.35 -> -150.08563 | BS98: =-(SUM(BS89:BS97)-BS96)*BS25-BS96*0.35 -> -137.33562 | BT98: =-(SUM(BT89:BT97)-BT96)*BT25-BT96*0.35 -> -128.83563 | BU98: =SUM(BQ98:BT98) -> -281.25688 | BW98: =-(SUM(BW89:BW97)-BW96)*BW25-BW96*0.35 -> -128.46062 | BX98: =-(SUM(BX89:BX97)-BX96)*BX25-BX96*0.35 -> -128.46062 | BY98: =-(SUM(BY89:BY97)-BY96)*BY25-BY96*0.35 -> -128.46062 | BZ98: =-(SUM(BZ89:BZ97)-BZ96)*BZ25-BZ96*0.35 -> -128.46062 | CA98: =SUM(BW98:BZ98) -> -513.8425 | CC98: =-(SUM(CC89:CC97)-CC96)*CC25-CC96*0.35 -> -122.31063 | CD98: =-(SUM(CD89:CD97)-CD96)*CD25-CD96*0.35 -> -118.18563 | CE98: =-(SUM(CE89:CE97)-CE96)*CE25-CE96*0.35 -> -114.06063 | CF98: =-(SUM(CF89:CF97)-CF96)*CF25-CF96*0.35 -> -114.06063 | CG98: =SUM(CC98:CF98) -> -468.6175 | CI98: =-(SUM(CI89:CI97)-CI96)*CI25-CI96*0.35 -> -108.28563 | CJ98: =-(SUM(CJ89:CJ97)-CJ96)*CJ25-CJ96*0.35 -> -108.28563 | CK98: =-(SUM(CK89:CK97)-CK96)*CK25-CK96*0.35 -> -108.28563 | CL98: =-(SUM(CL89:CL97)-CL96)*CL25-CL96*0.35 -> -108.28563 | CM98: =SUM(CI98:CL98) -> -433.1425
A99: GAAP Net Income | C99: =C31-SUM(C89:C98) -> 142.78886 | D99: =D31-SUM(D89:D98) -> 242.48378 | E99: =E31-SUM(E89:E98) -> 244.809 | F99: =F31-SUM(F89:F98) -> 259.72664 | G99: =G31-SUM(G89:G98) -> 889.80828 | I99: =I31-SUM(I89:I98) -> 271.5624 | J99: =J31-SUM(J89:J98) -> 276.17822 | K99: =K31-SUM(K89:K98) -> 297.05139 | L99: =L31-SUM(L89:L98) -> 282.174 | M99: =M31-SUM(M89:M98) -> 1126.966 | O99: =O31-SUM(O89:O98) -> 312.068 | P99: =P31-SUM(P89:P98) -> 261.289 | Q99: =Q31-SUM(Q89:Q98) -> 341.027 | R99: =R31-SUM(R89:R98) -> 317.22 | S99: =S31-SUM(S89:S98) -> 1231.604 | U99: =U31-SUM(U89:U98) -> 316.376 | V99: =V31-SUM(V89:V98) -> 297.631 | W99: =W31-SUM(W89:W98) -> 306.908 | X99: =X31-SUM(X89:X98) -> 396.695 | Y99: =Y31-SUM(Y89:Y98) -> 1317.61 | AA99: =AA31-SUM(AA89:AA98) -> 315.9377 | AB99: =AB31-SUM(AB89:AB98) -> 312.019 | AC99: =AC31-SUM(AC89:AC98) -> 343.058 | AD99: =AD31-SUM(AD89:AD98) -> 299.98 | AE99: =AE31-SUM(AE89:AE98) -> 1270.9947 | AG99: =AG31-SUM(AG89:AG98) -> 262.985 | AH99: =AH31-SUM(AH89:AH98) -> 291.033 | AI99: =AI31-SUM(AI89:AI98) -> 326.866 | AJ99: =AJ31-SUM(AJ89:AJ98) -> 289.043 | AK99: =AK31-SUM(AK89:AK98) -> 1169.927 | AM99: =AM31-SUM(AM89:AM98) -> 625.436 | AN99: =AN31-SUM(AN89:AN98) -> 275.637 | AO99: =AO31-SUM(AO89:AO98) -> 301.55 | AP99: =AP31-SUM(AP89:AP98) -> 90 | AQ99: =AQ31-SUM(AQ89:AQ98) -> 1292.623 | AS99: =AS31-SUM(AS89:AS98) -> 270.9 | AT99: =AT31-SUM(AT89:AT98) -> 287 | AU99: =AU31-SUM(AU89:AU98) -> 325.8 | AV99: =AV31-SUM(AV89:AV98) -> 329.99 | AW99: =AW31-SUM(AW89:AW98) -> 1213.69 | AY99: =AY31-SUM(AY89:AY98) -> 236.04 | AZ99: =AZ31-SUM(AZ89:AZ98) -> 215.45 | BA99: =BA31-SUM(BA89:BA98) -> 62.1 | BB99: =BB31-SUM(BB89:BB98) -> 181 | BC99: =BC31-SUM(BC89:BC98) -> 694.59 | BE99: =BE31-SUM(BE89:BE98) -> 229 | BF99: =BF31-SUM(BF89:BF98) -> 337.95 | BG99: =BG31-SUM(BG89:BG98) -> 391 | BH99: =BH31-SUM(BH89:BH98) -> 18 | BI99: =BI31-SUM(BI89:BI98) -> 975.95 | BK99: =BK31-SUM(BK89:BK98) -> 562 | BL99: =BL31-SUM(BL89:BL98) -> 343 | BM99: =BM31-SUM(BM89:BM98) -> -132 | BN99: =BN31-SUM(BN89:BN98) -> 326.49 | BO99: =BO31-SUM(BO89:BO98) -> 1099.49 | BQ99: =BQ31-SUM(BQ89:BQ98) -> -136 | BR99: =BR31-SUM(BR89:BR98) -> 300.48255 | BS99: =BS31-SUM(BS89:BS98) -> 449.55437 | BT99: =BT31-SUM(BT89:BT98) -> 482.33268 | BU99: =BU31-SUM(BU89:BU98) -> 1096.3696 | BW99: =BW31-SUM(BW89:BW98) -> 501.26874 | BX99: =BX31-SUM(BX89:BX98) -> 537.41195 | BY99: =BY31-SUM(BY89:BY98) -> 575.8408 | BZ99: =BZ31-SUM(BZ89:BZ98) -> 564.94242 | CA99: =CA31-SUM(CA89:CA98) -> 2179.4639 | CC99: =CC31-SUM(CC89:CC98) -> 686.15054 | CD99: =CD31-SUM(CD89:CD98) -> 746.1094 | CE99: =CE31-SUM(CE89:CE98) -> 813.2299 | CF99: =CF31-SUM(CF89:CF98) -> 829.29481 | CG99: =CG31-SUM(CG89:CG98) -> 3074.7847 | CI99: =CI31-SUM(CI89:CI98) -> 884.35876 | CJ99: =CJ31-SUM(CJ89:CJ98) -> 896.03284 | CK99: =CK31-SUM(CK89:CK98) -> 992.36875 | CL99: =CL31-SUM(CL89:CL98) -> 1011.473 | CM99: =CM31-SUM(CM89:CM98) -> 3784.2334
BV100: =1775.538845-BV99 -> 1775.5388
A101: Segment EBIT
A102: EBIT
A103: BD Medical | C103: 246.143 | D103: 234.132 | E103: 247.275 | F103: 244.44 | G103: 971.99 | I103: 262.408 | J103: 251.288 | K103: 285.254 | L103: 269.193 | M103: 1068.143 | O103: 262.294 | P103: 251.448 | Q103: 303.663 | R103: =S103-SUM(O103:Q103) -> 231.831 | S103: 1049.236 | U103: 319.105 | V103: 280.342 | W103: 290.27 | X103: =Y103-SUM(U103:W103) -> 228.602 | Y103: 1118.319 | AO103: 334 | AS103: 300 | AT103: 317 | AU103: 356 | AV103: =AW103-SUM(AS103:AU103) -> 318 | AW103: 1291 | AY103: 304 | AZ103: 328 | BA103: 483 | BB103: =BC103-SUM(AY103:BA103) -> 415 | BC103: 1530 | BE103: 465 | BF103: 513 | BG103: 571 | BH103: =BI103-SUM(BE103:BG103) -> 503 | BI103: 2052 | BK103: 548 | BL103: 537
A104: BD Diagnostic | C104: 114.394 | D104: 109.374 | E104: 115.322 | F104: 118.427 | G104: 457.517 | I104: 126.926 | J104: 125.375 | K104: 135.443 | L104: 138.003 | M104: 525.747 | O104: 154.535 | P104: 141.266 | Q104: 154.836 | R104: =S104-SUM(O104:Q104) -> 156.613 | S104: 607.25 | U104: 162.401 | V104: 143.685 | W104: 146.703 | X104: =Y104-SUM(U104:W104) -> 154.622 | Y104: 607.411 | AO104: 159 | AS104: 162 | AT104: 131 | AU104: 155 | AV104: =AW104-SUM(AS104:AU104) -> 137 | AW104: 585 | AY104: 214 | AZ104: 200 | BA104: 197 | BB104: =BC104-SUM(AY104:BA104) -> 228 | BC104: 839 | BE104: 202 | BF104: 202 | BG104: 200 | BH104: =BI104-SUM(BE104:BG104) -> 189 | BI104: 793 | BK104: 198 | BL104: 177
A105: BD Bioscience | C105: 56.235 | D105: 67.91 | E105: 65.937 | F105: 76.118 | G105: 266.2 | I105: 78.675 | J105: 83.994 | K105: 82.832 | L105: 88.119 | M105: 333.62 | O105: 99.689 | P105: 92.147 | Q105: 76.176 | R105: =S105-SUM(O105:Q105) -> 94.332 | S105: 362.344 | U105: 85.465 | V105: 97.23 | W105: 87.101 | X105: =Y105-SUM(U105:W105) -> 84.433 | Y105: 354.229 | AO105: 58 | AS105: 66 | AT105: 67 | AU105: 66 | AV105: =AW105-SUM(AS105:AU105) -> 76 | AW105: 275
...

Sheet BDX
A1: =TOC!$A$4 -> Becton Dickinson
A2: BD Revenue Build
A3: Dollars in millions, except per share data
A4: Fiscal year ends Sep 30
C5: 2007 | G5: =C5 -> 2007 | I5: =C5+1 -> 2008 | M5: =I5 -> 2008 | O5: =I5+1 -> 2009 | S5: =O5 -> 2009 | U5: =O5+1 -> 2010 | Y5: =U5 -> 2010 | AA5: =U5+1 -> 2011 | AE5: =AA5 -> 2011 | AG5: =AA5+1 -> 2012 | AK5: =AG5 -> 2012 | AM5: =AG5+1 -> 2013 | AQ5: =AM5 -> 2013 | AS5: =AM5+1 -> 2014 | AW5: =AS5 -> 2014 | AY5: =AS5+1 -> 2015 | BC5: =AY5 -> 2015 | BE5: =AY5+1 -> 2016 | BI5: =BE5 -> 2016 | BK5: =BE5+1 -> 2017 | BO5: =BK5 -> 2017 | BQ5: =BK5+1 -> 2018 | BU5: =BQ5 -> 2018 | BW5: =BQ5+1 -> 2019 | CA5: =BW5 -> 2019 | CC5: =BW5+1 -> 2020 | CG5: =CC5 -> 2020 | CI5: =CC5+1 -> 2021 | CM5: =CI5 -> 2021
C6: 39082 | D6: 39172 | E6: 39263 | F6: 39355 | I6: =F6+FLOOR(365/4,1)+1 -> 39447 | J6: =D6+365+1 -> 39538 | K6: =J6+FLOOR(365/4,1) -> 39629 | L6: =K6+FLOOR(365/4,1)+1 -> 39721 | O6: =L6+FLOOR(365/4,1)+1 -> 39813 | P6: =J6+365 -> 39903 | Q6: =P6+FLOOR(365/4,1) -> 39994 | R6: =Q6+FLOOR(365/4,1)+1 -> 40086 | U6: =R6+FLOOR(365/4,1)+1 -> 40178 | V6: =P6+365 -> 40268 | W6: =V6+FLOOR(365/4,1) -> 40359 | X6: =W6+FLOOR(365/4,1)+1 -> 40451 | AA6: =X6+FLOOR(365/4,1)+1 -> 40543 | AB6: =V6+365 -> 40633 | AC6: =AB6+FLOOR(365/4,1) -> 40724 | AD6: =AC6+FLOOR(365/4,1)+1 -> 40816 | AG6: =AD6+FLOOR(365/4,1)+1 -> 40908 | AH6: =AB6+365+1 -> 40999 | AI6: =AH6+FLOOR(365/4,1) -> 41090 | AJ6: =AI6+FLOOR(365/4,1)+1 -> 41182 | AM6: =AJ6+FLOOR(365/4,1)+1 -> 41274 | AN6: =AH6+365 -> 41364 | AO6: =AN6+FLOOR(365/4,1) -> 41455 | AP6: =AO6+FLOOR(365/4,1)+1 -> 41547 | AS6: =AP6+FLOOR(365/4,1)+1 -> 41639 | AT6: =AN6+365 -> 41729 | AU6: =AT6+FLOOR(365/4,1) -> 41820 | AV6: =AU6+FLOOR(365/4,1)+1 -> 41912 | AY6: =AV6+FLOOR(365/4,1)+1 -> 42004 | AZ6: =AT6+365 -> 42094 | BA6: =AZ6+FLOOR(365/4,1) -> 42185 | BB6: =BA6+FLOOR(365/4,1)+1 -> 42277 | BE6: =BB6+FLOOR(365/4,1)+1 -> 42369 | BF6: =AZ6+365+1 -> 42460 | BG6: =BF6+FLOOR(365/4,1) -> 42551 | BH6: =BG6+FLOOR(365/4,1)+1 -> 42643 | BK6: =BH6+FLOOR(365/4,1)+1 -> 42735 | BL6: =BF6+365 -> 42825 | BM6: =BL6+FLOOR(365/4,1) -> 42916 | BN6: =BM6+FLOOR(365/4,1)+1 -> 43008 | BQ6: =BN6+FLOOR(365/4,1)+1 -> 43100 | BR6: =BL6+365 -> 43190 | BS6: =BR6+FLOOR(365/4,1) -> 43281 | BT6: =BS6+FLOOR(365/4,1)+1 -> 43373 | BW6: =BT6+FLOOR(365/4,1)+1 -> 43465 | BX6: =BR6+365 -> 43555 | BY6: =BX6+FLOOR(365/4,1) -> 43646 | BZ6: =BY6+FLOOR(365/4,1)+1 -> 43738 | CC6: =BZ6+FLOOR(365/4,1)+1 -> 43830 | CD6: =BX6+365+1 -> 43921 | CE6: =CD6+FLOOR(365/4,1) -> 44012 | CF6: =CE6+FLOOR(365/4,1)+1 -> 44104 | CI6: =CF6+FLOOR(365/4,1)+1 -> 44196 | CJ6: =CD6+365 -> 44286 | CK6: =CJ6+FLOOR(365/4,1) -> 44377 | CL6: =CK6+FLOOR(365/4,1)+1 -> 44469
A7: BD Medical
A8: US | BE8: =Med!BE76 -> 1104 | BF8: =Med!BF76 -> 1103 | BG8: =Med!BG76 -> 1163 | BH8: =Med!BH76 -> 1140 | BI8: =SUM(BE8:BH8) -> 4510 | BK8: =Med!BK76 -> 1179 | BL8: =Med!BL76 -> 1152 | BM8: =Med!BM76 -> 1148 | BN8: =Med!BN76 -> 1174 | BO8: =SUM(BK8:BN8) -> 4653 | BQ8: =Med!BQ76 -> 1183 | BR8: =Med!BR76 -> 1200.76 | BS8: =Med!BS76 -> 1225.85 | BT8: =Med!BT76 -> 1237.7 | BU8: =SUM(BQ8:BT8) -> 4847.31 | BW8: =Med!BW76 -> 1244.425 | BX8: =Med!BX76 -> 1262.7414 | BY8: =Med!BY76 -> 1288.8673 | BZ8: =Med!BZ76 -> 1301.3142 | CA8: =SUM(BW8:BZ8) -> 5097.3479 | CC8: =Med!CC76 -> 1309.5874 | CD8: =Med!CD76 -> 1328.5124 | CE8: =Med!CE76 -> 1355.7745 | CF8: =Med!CF76 -> 1368.8674 | CG8: =SUM(CC8:CF8) -> 5362.7416 | CI8: =Med!CI76 -> 1378.1847 | CJ8: =Med!CJ76 -> 1397.7375 | CK8: =Med!CK76 -> 1426.1873 | CL8: =Med!CL76 -> 1439.9593 | CM8: =SUM(CI8:CL8) -> 5642.0688
A9: Y/Y Growth | BK9: =Med!BK77 -> 0.067934783 | BL9: =Med!BL77 -> 0.044424297 | BM9: =Med!BM77 -> -0.012897678 | BN9: =Med!BN77 -> 0.029824561 | BO9: =SUM(BK9:BN9) -> 0.12928596 | BQ9: =Med!BQ77 -> 0.0033927057 | BR9: =Med!BR77 -> 0.042326389 | BS9: =Med!BS77 -> 0.067813589 | BT9: =Med!BT77 -> 0.054258944 | BU9: =SUM(BQ9:BT9) -> 0.16779163 | BW9: =Med!BW77 -> 0.051923077 | BX9: =Med!BX77 -> 0.051618475 | BY9: =Med!BY77 -> 0.051407064 | BZ9: =Med!BZ77 -> 0.051397067 | CA9: =SUM(BW9:BZ9) -> 0.20634568 | CC9: =Med!CC77 -> 0.052363441 | CD9: =Med!CD77 -> 0.052085877 | CE9: =Med!CE77 -> 0.051911568 | CF9: =Med!CF77 -> 0.051911528 | CG9: =SUM(CC9:CF9) -> 0.20827241 | CI9: =Med!CI77 -> 0.052380903 | CJ9: =Med!CJ77 -> 0.052107248 | CK9: =Med!CK77 -> 0.05193549 | CL9: =Med!CL77 -> 0.051934847 | CM9: =SUM(CI9:CL9) -> 0.20835849
A10: M&A / Other | BK10: =Med!BK78 -> 0 | BL10: =Med!BL78 -> 0 | BM10: =Med!BM78 -> 0 | BN10: =Med!BN78 -> 0 | BO10: =SUM(BK10:BN10) -> 0 | BQ10: =Med!BQ78 -> 0 | BR10: =Med!BR78 -> 0 | BS10: =Med!BS78 -> 0 | BT10: =Med!BT78 -> 0 | BU10: =SUM(BQ10:BT10) -> 0 | BW10: =Med!BW78 -> 0 | BX10: =Med!BX78 -> 0 | BY10: =Med!BY78 -> 0 | BZ10: =Med!BZ78 -> 0 | CA10: =SUM(BW10:BZ10) -> 0 | CC10: =Med!CC78 -> 0 | CD10: =Med!CD78 -> 0 | CE10: =Med!CE78 -> 0 | CF10: =Med!CF78 -> 0 | CG10: =SUM(CC10:CF10) -> 0 | CI10: =Med!CI78 -> 0 | CJ10: =Med!CJ78 -> 0 | CK10: =Med!CK78 -> 0 | CL10: =Med!CL78 -> 0 | CM10: =SUM(CI10:CL10) -> 0
A11: Organic Growth | BK11: =Med!BK79 -> 0.067934783 | BL11: =Med!BL79 -> 0.044424297 | BM11: =Med!BM79 -> -0.012897678 | BN11: =Med!BN79 -> 0.029824561 | BO11: =SUM(BK11:BN11) -> 0.12928596 | BQ11: =Med!BQ79 -> 0.0033927057 | BR11: =Med!BR79 -> 0.042326389 | BS11: =Med!BS79 -> 0.067813589 | BT11: =Med!BT79 -> 0.054258944 | BU11: =SUM(BQ11:BT11) -> 0.16779163 | BW11: =Med!BW79 -> 0.051923077 | BX11: =Med!BX79 -> 0.051618475 | BY11: =Med!BY79 -> 0.051407064 | BZ11: =Med!BZ79 -> 0.051397067 | CA11: =SUM(BW11:BZ11) -> 0.20634568 | CC11: =Med!CC79 -> 0.052363441 | CD11: =Med!CD79 -> 0.052085877 | CE11: =Med!CE79 -> 0.051911568 | CF11: =Med!CF79 -> 0.051911528 | CG11: =SUM(CC11:CF11) -> 0.20827241 | CI11: =Med!CI79 -> 0.052380903 | CJ11: =Med!CJ79 -> 0.052107248 | CK11: =Med!CK79 -> 0.05193549 | CL11: =Med!CL79 -> 0.051934847 | CM11: =SUM(CI11:CL11) -> 0.20835849
A12: International | BE12: =Med!BE80 -> 742 | BF12: =Med!BF80 -> 811 | BG12: =Med!BG80 -> 893 | BH12: =Med!BH80 -> 904 | BI12: =SUM(BE12:BH12) -> 3350 | BK12: =Med!BK80 -> 804 | BL12: =Med!BL80 -> 854 | BM12: =Med!BM80 -> 924 | BN12: =Med!BN80 -> 972 | BO12: =SUM(BK12:BN12) -> 3554 | BQ12: =Med!BQ80 -> 880 | BR12: =Med!BR80 -> 946.39583 | BS12: =Med!BS80 -> 1019.7043 | BT12: =Med!BT80 -> 1041.8978 | BU12: =SUM(BQ12:BT12) -> 3887.9979 | BW12: =Med!BW80 -> 961.46942 | BX12: =Med!BX80 -> 1005.4446 | BY12: =Med!BY80 -> 1080.7043 | BZ12: =Med!BZ80 -> 1104.2799 | CA12: =SUM(BW12:BZ12) -> 4151.8982 | CC12: =Med!CC80 -> 1019.7304 | CD12: =Med!CD80 -> 1065.5282 | CE12: =Med!CE80 -> 1145.4141 | CF12: =Med!CF80 -> 1170.4623 | CG12: =SUM(CC12:CF12) -> 4401.135 | CI12: =Med!CI80 -> 1081.5746 | CJ12: =Med!CJ80 -> 1129.2615 | CK12: =Med!CK80 -> 1214.0633 | CL12: =Med!CL80 -> 1240.6806 | CM12: =SUM(CI12:CL12) -> 4665.5801
A13: Y/Y Growth | BK13: =Med!BK81 -> 0.083557951 | BL13: =Med!BL81 -> 0.053020962 | BM13: =Med!BM81 -> 0.034714446 | BN13: =Med!BN81 -> 0.075221239 | BO13: =SUM(BK13:BN13) -> 0.2465146 | BQ13: =Med!BQ81 -> 0.094527363 | BR13: =Med!BR81 -> 0.10819183 | BS13: =Med!BS81 -> 0.10357611 | BT13: =Med!BT81 -> 0.071911304 | BU13: =SUM(BQ13:BT13) -> 0.37820661 | BW13: =Med!BW81 -> 0.092578882 | BX13: =Med!BX81 -> 0.062393358 | BY13: =Med!BY81 -> 0.059821219 | BZ13: =Med!BZ81 -> 0.059873526 | CA13: =SUM(BW13:BZ13) -> 0.27466698 | CC13: =Med!CC81 -> 0.06059573 | CD13: =Med!CD81 -> 0.059758238 | CE13: =Med!CE81 -> 0.05987749 | CF13: =Med!CF81 -> 0.059932654 | CG13: =SUM(CC13:CF13) -> 0.24016411 | CI13: =Med!CI81 -> 0.060647653 | CJ13: =Med!CJ81 -> 0.059813759 | CK13: =Med!CK81 -> 0.05993393 | CL13: =Med!CL81 -> 0.059991968 | CM13: =SUM(CI13:CL13) -> 0.24038731
A14: FX Impact | BK14: =Med!BK82 -> -0.013402965 | BL14: =Med!BL82 -> -0.020720099 | BM14: =Med!BM82 -> -0.024181411 | BN14: =Med!BN82 -> 0.0076161504 | BO14: =SUM(BK14:BN14) -> -0.050688324 | BQ14: =Med!BQ82 -> 0.042186567 | BR14: =Med!BR82 -> 0.053824152 | BS14: =Med!BS82 -> 0.041563119 | BT14: =Med!BT82 -> 0.017281675 | BU14: =SUM(BQ14:BT14) -> 0.15485551 | BW14: =Med!BW82 -> 0.032033428 | BX14: =Med!BX82 -> 0.0026903296 | BY14: =Med!BY82 -> 0 | BZ14: =Med!BZ82 -> 0 | CA14: =SUM(BW14:BZ14) -> 0.034723757 | CC14: =Med!CC82 -> 0 | CD14: =Med!CD82 -> 0 | CE14: =Med!CE82 -> 0 | CF14: =Med!CF82 -> 0 | CG14: =SUM(CC14:CF14) -> 0 | CI14: =Med!CI82 -> 0 | CJ14: =Med!CJ82 -> 0 | CK14: =Med!CK82 -> 0 | CL14: =Med!CL82 -> 0 | CM14: =SUM(CI14:CL14) -> 0
A15: CC Growth | BK15: =Med!BK83 -> 0.096960916 | BL15: =Med!BL83 -> 0.07374106 | BM15: =Med!BM83 -> 0.058895857 | BN15: =Med!BN83 -> 0.067605088 | BO15: =SUM(BK15:BN15) -> 0.29720292 | BQ15: =Med!BQ83 -> 0.052340796 | BR15: =Med!BR83 -> 0.054367681 | BS15: =Med!BS83 -> 0.062012987 | BT15: =Med!BT83 -> 0.05462963 | BU15: =SUM(BQ15:BT15) -> 0.22335109 | BW15: =Med!BW83 -> 0.060545455 | BX15: =Med!BX83 -> 0.059703028 | BY15: =Med!BY83 -> 0.059821219 | BZ15: =Med!BZ83 -> 0.059873526 | CA15: =SUM(BW15:BZ15) -> 0.23994323 | CC15: =Med!CC83 -> 0.06059573 | CD15: =Med!CD83 -> 0.059758238 | CE15: =Med!CE83 -> 0.05987749 | CF15: =Med!CF83 -> 0.059932654 | CG15: =SUM(CC15:CF15) -> 0.24016411 | CI15: =Med!CI83 -> 0.060647653 | CJ15: =Med!CJ83 -> 0.059813759 | CK15: =Med!CK83 -> 0.05993393 | CL15: =Med!CL83 -> 0.059991968 | CM15: =SUM(CI15:CL15) -> 0.24038731
A16: M&A / Other | BK16: =Med!BK84 -> 0 | BL16: =Med!BL84 -> 0 | BM16: =Med!BM84 -> 0 | BN16: =Med!BN84 -> 0 | BO16: =SUM(BK16:BN16) -> 0 | BQ16: =Med!BQ84 -> 0 | BR16: =Med!BR84 -> 0 | BS16: =Med!BS84 -> 0 | BT16: =Med!BT84 -> 0 | BU16: =SUM(BQ16:BT16) -> 0 | BW16: =Med!BW84 -> 0 | BX16: =Med!BX84 -> 0 | BY16: =Med!BY84 -> 0 | BZ16: =Med!BZ84 -> 0 | CA16: =SUM(BW16:BZ16) -> 0 | CC16: =Med!CC84 -> 0 | CD16: =Med!CD84 -> 0 | CE16: =Med!CE84 -> 0 | CF16: =Med!CF84 -> 0 | CG16: =SUM(CC16:CF16) -> 0 | CI16: =Med!CI84 -> 0 | CJ16: =Med!CJ84 -> 0 | CK16: =Med!CK84 -> 0 | CL16: =Med!CL84 -> 0 | CM16: =SUM(CI16:CL16) -> 0
A17: Organic Growth | BK17: =Med!BK85 -> 0.096960916 | BL17: =Med!BL85 -> 0.07374106 | BM17: =Med!BM85 -> 0.058895857 | BN17: =Med!BN85 -> 0.067605088 | BO17: =SUM(BK17:BN17) -> 0.29720292 | BQ17: =Med!BQ85 -> 0.052340796 | BR17: =Med!BR85 -> 0.054367681 | BS17: =Med!BS85 -> 0.062012987 | BT17: =Med!BT85 -> 0.05462963 | BU17: =SUM(BQ17:BT17) -> 0.22335109 | BW17: =Med!BW85 -> 0.060545455 | BX17: =Med!BX85 -> 0.059703028 | BY17: =Med!BY85 -> 0.059821219 | BZ17: =Med!BZ85 -> 0.059873526 | CA17: =SUM(BW17:BZ17) -> 0.23994323 | CC17: =Med!CC85 -> 0.06059573 | CD17: =Med!CD85 -> 0.059758238 | CE17: =Med!CE85 -> 0.05987749 | CF17: =Med!CF85 -> 0.059932654 | CG17: =SUM(CC17:CF17) -> 0.24016411 | CI17: =Med!CI85 -> 0.060647653 | CJ17: =Med!CJ85 -> 0.059813759 | CK17: =Med!CK85 -> 0.05993393 | CL17: =Med!CL85 -> 0.059991968 | CM17: =SUM(CI17:CL17) -> 0.24038731
A18: Total | BE18: =Med!BE86 -> 1846 | BF18: =Med!BF86 -> 1914 | BG18: =Med!BG86 -> 2056 | BH18: =Med!BH86 -> 2044 | BI18: =SUM(BE18:BH18) -> 7860 | BK18: =Med!BK86 -> 1983 | BL18: =Med!BL86 -> 2006 | BM18: =Med!BM86 -> 2072 | BN18: =Med!BN86 -> 2146 | BO18: =SUM(BK18:BN18) -> 8207 | BQ18: =Med!BQ86 -> 2063 | BR18: =Med!BR86 -> 2147.1558 | BS18: =Med!BS86 -> 2245.5543 | BT18: =Med!BT86 -> 2279.5978 | BU18: =SUM(BQ18:BT18) -> 8735.3079 | BW18: =Med!BW86 -> 2205.8944 | BX18: =Med!BX86 -> 2268.186 | BY18: =Med!BY86 -> 2369.5716 | BZ18: =Med!BZ86 -> 2405.594 | CA18: =SUM(BW18:BZ18) -> 9249.2461 | CC18: =Med!CC86 -> 2329.3177 | CD18: =Med!CD86 -> 2394.0406 | CE18: =Med!CE86 -> 2501.1886 | CF18: =Med!CF86 -> 2539.3297 | CG18: =SUM(CC18:CF18) -> 9763.8766 | CI18: =Med!CI86 -> 2459.7594 | CJ18: =Med!CJ86 -> 2526.999 | CK18: =Med!CK86 -> 2640.2506 | CL18: =Med!CL86 -> 2680.6399 | CM18: =SUM(CI18:CL18) -> 10307.649
A19: Y/Y Growth | BK19: =Med!BK87 -> 0.074214518 | BL19: =Med!BL87 -> 0.048066876 | BM19: =Med!BM87 -> 0.0077821012 | BN19: =Med!BN87 -> 0.049902153 | BO19: =SUM(BK19:BN19) -> 0.17996565 | BQ19: =Med!BQ87 -> 0.040342915 | BR19: =Med!BR87 -> 0.070366812 | BS19: =Med!BS87 -> 0.083761738 | BT19: =Med!BT87 -> 0.062254328 | BU19: =SUM(BQ19:BT19) -> 0.25672579 | BW19: =Med!BW87 -> 0.06926535 | BX19: =Med!BX87 -> 0.05636769 | BY19: =Med!BY87 -> 0.055227925 | BZ19: =Med!BZ87 -> 0.055271261 | CA19: =SUM(BW19:BZ19) -> 0.23613223 | CC19: =Med!CC87 -> 0.055951597 | CD19: =Med!CD87 -> 0.055486892 | CE19: =Med!CE87 -> 0.055544632 | CF19: =Med!CF87 -> 0.055593599 | CG19: =SUM(CC19:CF19) -> 0.22257672 | CI19: =Med!CI87 -> 0.055999927 | CJ19: =Med!CJ87 -> 0.055537226 | CK19: =Med!CK87 -> 0.055598359 | CL19: =Med!CL87 -> 0.055648645 | CM19: =SUM(CI19:CL19) -> 0.22278416
A20: FX Impact | BK20: =Med!BK88 -> -0.0053873239 | BL20: =Med!BL88 -> -0.0087795193 | BM20: =Med!BM88 -> -0.010502918 | BN20: =Med!BN88 -> 0.0033683953 | BO20: =SUM(BK20:BN20) -> -0.021301366 | BQ20: =Med!BQ88 -> 0.017104387 | BR20: =Med!BR88 -> 0.02291417 | BS20: =Med!BS88 -> 0.018534904 | BT20: =Med!BT88 -> 0.0078274874 | BU20: =SUM(BQ20:BT20) -> 0.066380949 | BW20: =Med!BW88 -> 0.013664283 | BX20: =Med!BX88 -> 0.001185809 | BY20: =Med!BY88 -> 0 | BZ20: =Med!BZ88 -> 0 | CA20: =SUM(BW20:BZ20) -> 0.014850092 | CC20: =Med!CC88 -> 0 | CD20: =Med!CD88 -> 0 | CE20: =Med!CE88 -> 0 | CF20: =Med!CF88 -> 0 | CG20: =SUM(CC20:CF20) -> 0 | CI20: =Med!CI88 -> 0 | CJ20: =Med!CJ88 -> 0 | CK20: =Med!CK88 -> 0 | CL20: =Med!CL88 -> 0 | CM20: =SUM(CI20:CL20) -> 0
A21: CC Growth | BK21: =Med!BK89 -> 0.079601842 | BL21: =Med!BL89 -> 0.056846395 | BM21: =Med!BM89 -> 0.018285019 | BN21: =Med!BN89 -> 0.046533757 | BO21: =SUM(BK21:BN21) -> 0.20126701 | BQ21: =Med!BQ89 -> 0.023238527 | BR21: =Med!BR89 -> 0.047452642 | BS21: =Med!BS89 -> 0.065226834 | BT21: =Med!BT89 -> 0.054426841 | BU21: =SUM(BQ21:BT21) -> 0.19034484 | BW21: =Med!BW89 -> 0.055601066 | BX21: =Med!BX89 -> 0.055181881 | BY21: =Med!BY89 -> 0.055227925 | BZ21: =Med!BZ89 -> 0.055271261 | CA21: =SUM(BW21:BZ21) -> 0.22128213 | CC21: =Med!CC89 -> 0.055951597 | CD21: =Med!CD89 -> 0.055486892 | CE21: =Med!CE89 -> 0.055544632 | CF21: =Med!CF89 -> 0.055593599 | CG21: =SUM(CC21:CF21) -> 0.22257672 | CI21: =Med!CI89 -> 0.055999927 | CJ21: =Med!CJ89 -> 0.055537226 | CK21: =Med!CK89 -> 0.055598359 | CL21: =Med!CL89 -> 0.055648645 | CM21: =SUM(CI21:CL21) -> 0.22278416
A22: M&A / Other | BK22: =Med!BK90 -> 0 | BL22: =Med!BL90 -> 0 | BM22: =Med!BM90 -> 0 | BN22: =Med!BN90 -> 0 | BO22: =SUM(BK22:BN22) -> 0 | BQ22: =Med!BQ90 -> 0 | BR22: =Med!BR90 -> 0 | BS22: =Med!BS90 -> 0 | BT22: =Med!BT90 -> 0 | BU22: =SUM(BQ22:BT22) -> 0 | BW22: =Med!BW90 -> 0 | BX22: =Med!BX90 -> 0 | BY22: =Med!BY90 -> 0 | BZ22: =Med!BZ90 -> 0 | CA22: =SUM(BW22:BZ22) -> 0 | CC22: =Med!CC90 -> 0 | CD22: =Med!CD90 -> 0 | CE22: =Med!CE90 -> 0 | CF22: =Med!CF90 -> 0 | CG22: =SUM(CC22:CF22) -> 0 | CI22: =Med!CI90 -> 0 | CJ22: =Med!CJ90 -> 0 | CK22: =Med!CK90 -> 0 | CL22: =Med!CL90 -> 0 | CM22: =SUM(CI22:CL22) -> 0
A23: Organic Growth | BK23: =Med!BK91 -> 0.079601842 | BL23: =Med!BL91 -> 0.056846395 | BM23: =Med!BM91 -> 0.018285019 | BN23: =Med!BN91 -> 0.046533757 | BO23: =SUM(BK23:BN23) -> 0.20126701 | BQ23: =Med!BQ91 -> 0.023238527 | BR23: =Med!BR91 -> 0.047452642 | BS23: =Med!BS91 -> 0.065226834 | BT23: =Med!BT91 -> 0.054426841 | BU23: =SUM(BQ23:BT23) -> 0.19034484 | BW23: =Med!BW91 -> 0.055601066 | BX23: =Med!BX91 -> 0.055181881 | BY23: =Med!BY91 -> 0.055227925 | BZ23: =Med!BZ91 -> 0.055271261 | CA23: =SUM(BW23:BZ23) -> 0.22128213 | CC23: =Med!CC91 -> 0.055951597 | CD23: =Med!CD91 -> 0.055486892 | CE23: =Med!CE91 -> 0.055544632 | CF23: =Med!CF91 -> 0.055593599 | CG23: =SUM(CC23:CF23) -> 0.22257672 | CI23: =Med!CI91 -> 0.055999927 | CJ23: =Med!CJ91 -> 0.055537226 | CK23: =Med!CK91 -> 0.055598359 | CL23: =Med!CL91 -> 0.055648645 | CM23: =SUM(CI23:CL23) -> 0.22278416
A24: BD Life Sciences
A25: US | I25: =LS!I59 -> 346.846 | J25: =LS!J59 -> 359.357 | K25: =LS!K59 -> 360.304 | L25: =LS!L59 -> 380.031 | M25: =LS!M59 -> 1446.538 | O25: =LS!O59 -> 364.947 | P25: =LS!P59 -> 356.883 | Q25: =LS!Q59 -> 369.892 | R25: =LS!R59 -> 389.667 | S25: =LS!S59 -> 1481.389 | U25: =LS!U59 -> 387.809 | V25: =LS!V59 -> 371.024 | W25: =LS!W59 -> 387.886 | X25: =LS!X59 -> 394.486 | Y25: =LS!Y59 -> 1541.205 | AA25: =LS!AA59 -> 398.606 | AB25: =LS!AB59 -> 403.044 | AC25: =LS!AC59 -> 410.716 | AD25: =LS!AD59 -> 410.502 | AE25: =LS!AE59 -> 1622.868 | AG25: =LS!AG59 -> 391.415 | AH25: =LS!AH59 -> 402.718 | AI25: =LS!AI59 -> 406.914 | AJ25: =LS!AJ59 -> 401.567 | AK25: =LS!AK59 -> 1602.614 | AM25: =LS!AM59 -> 404.735 | AN25: =LS!AN59 -> 411.079 | AO25: =LS!AO59 -> 399.022 | AP25: =LS!AP59 -> 411 | AQ25: =LS!AQ59 -> 1625.836 | AS25: =LS!AS59 -> 408 | AT25: =LS!AT59 -> 391 | AU25: =LS!AU59 -> 402.8 | AV25: =LS!AV59 -> 414.8 | AW25: =LS!AW59 -> 1616.6 | AY25: =LS!AY59 -> 423.85 | AZ25: =LS!AZ59 -> 415.7 | BA25: =LS!BA59 -> 414.7 | BB25: =LS!BB59 -> 429 | BC25: =LS!BC59 -> 1683.25 | BE25: =LS!BE59 -> 425 | BF25: =LS!BF59 -> 441 | BG25: =LS!BG59 -> 428 | BH25: =LS!BH59 -> 454 | BI25: =LS!BI59 -> 1748 | BK25: =LS!BK59 -> 437 | BL25: =LS!BL59 -> 468 | BM25: =LS!BM59 -> 451 | BN25: =LS!BN59 -> 463 | BO25: =LS!BO59 -> 1819 | BQ25: =LS!BQ59 -> 459 | BR25: =LS!BR59 -> 484.195 | BS25: =LS!BS59 -> 466.705 | BT25: =LS!BT59 -> 486.905 | BU25: =LS!BU59 -> 1896.805 | BW25: =LS!BW59 -> 475.31 | BX25: =LS!BX59 -> 501.46285 | BY25: =LS!BY59 -> 483.46655 | BZ25: =LS!BZ59 -> 504.44165 | CA25: =LS!CA59 -> 1964.681 | CC25: =LS!CC59 -> 492.2144 | CD25: =LS!CD59 -> 519.36269 | CE25: =LS!CE59 -> 500.84533 | CF25: =LS!CF59 -> 522.6263 | CG25: =LS!CG59 -> 2035.0487 | CI25: =LS!CI59 -> 509.73544 | CJ25: =LS!CJ59 -> 537.91828 | CK25: =LS!CK59 -> 518.86465 | CL25: =LS!CL59 -> 541.48354 | CM25: =LS!CM59 -> 2108.0019
A26: Y/Y Growth | I26: =LS!I60 -> 0.13820012 | J26: =LS!J60 -> 0.064701543 | K26: =LS!K60 -> 0.045474593 | L26: =LS!L60 -> 0.061906917 | M26: =LS!M60 -> 0.07568568 | O26: =LS!O60 -> 0.052187426 | P26: =LS!P60 -> -0.0068845187 | Q26: =LS!Q60 -> 0.026610862 | R26: =LS!R60 -> 0.025355826 | S26: =LS!S60 -> 0.024092696 | U26: =LS!U60 -> 0.062644713 | V26: =LS!V60 -> 0.03962363 | W26: =LS!W60 -> 0.048646632 | X26: =LS!X60 -> 0.01236697 | Y26: =LS!Y60 -> 0.040378321 | AA26: =LS!AA60 -> 0.027841025 | AB26: =LS!AB60 -> 0.086301695 | AC26: =LS!AC60 -> 0.058857499 | AD26: =LS!AD60 -> 0.040599666 | AE26: =LS!AE60 -> 0.052986462 | AG26: =LS!AG60 -> -0.018040371 | AH26: =LS!AH60 -> -0.00080884469 | AI26: =LS!AI60 -> -0.0092570048 | AJ26: =LS!AJ60 -> -0.021766033 | AK26: =LS!AK60 -> -0.012480374 | AM26: =LS!AM60 -> 0.034030377 | AN26: =LS!AN60 -> 0.020761426 | AO26: =LS!AO60 -> -0.019394762 | AP26: =LS!AP60 -> 0.023490476 | AQ26: =LS!AQ60 -> 0.014490077 | AS26: =LS!AS60 -> 0.0080670068 | AT26: =LS!AT60 -> -0.048844626 | AU26: =LS!AU60 -> 0.0094681496 | AV26: =LS!AV60 -> 0.0092457421 | AW26: =LS!AW60 -> -0.0056807698 | AY26: =LS!AY60 -> 0.038848039 | AZ26: =LS!AZ60 -> 0.063171355 | BA26: =LS!BA60 -> 0.029543198 | BB26: =LS!BB60 -> 0.034233365 | BC26: =LS!BC60 -> 0.041228504 | BE26: =LS!BE60 -> 0.002713224 | BF26: =LS!BF60 -> 0.060861198 | BG26: =LS!BG60 -> 0.032071377 | BH26: =LS!BH60 -> 0.058275058 | BI26: =LS!BI60 -> 0.038467251 | BK26: =LS!BK60 -> 0.028235294 | BL26: =LS!BL60 -> 0.06122449 | BM26: =LS!BM60 -> 0.053738318 | BN26: =LS!BN60 -> 0.019823789 | BO26: =LS!BO60 -> 0.040617849 | BQ26: =LS!BQ60 -> 0.050343249 | BR26: =LS!BR60 -> 0.034604701 | BS26: =LS!BS60 -> 0.034822616 | BT26: =LS!BT60 -> 0.05163067 | BU26: =LS!BU60 -> 0.042773502 | BW26: =LS!BW60 -> 0.035533769 | BX26: =LS!BX60 -> 0.035663008 | BY26: =LS!BY60 -> 0.035914657 | BZ26: =LS!BZ60 -> 0.036016574 | CA26: =LS!CA60 -> 0.035784411 | CC26: =LS!CC60 -> 0.035565 | CD26: =LS!CD60 -> 0.035695247 | CE26: =LS!CE60 -> 0.035946185 | CF26: =LS!CF60 -> 0.036049074 | CG26: =LS!CG60 -> 0.035816334 | CI26: =LS!CI60 -> 0.035596357 | CJ26: =LS!CJ60 -> 0.035727612 | CK26: =LS!CK60 -> 0.035977825 | CL26: =LS!CL60 -> 0.036081685 | CM26: =LS!CM60 -> 0.035848376
A27: M&A / Other | I27: =LS!I61 -> 0 | J27: =LS!J61 -> 0 | K27: =LS!K61 -> 0 | L27: =LS!L61 -> 0 | M27: =LS!M61 -> 0 | O27: =LS!O61 -> 0 | P27: =LS!P61 -> 0 | Q27: =LS!Q61 -> 0 | R27: =LS!R61 -> 0 | S27: =LS!S61 -> 0 | U27: =LS!U61 -> 0 | V27: =LS!V61 -> 0 | W27: =LS!W61 -> 0 | X27: =LS!X61 -> 0 | Y27: =LS!Y61 -> 0 | AA27: =LS!AA61 -> 0 | AB27: =LS!AB61 -> 0 | AC27: =LS!AC61 -> 0 | AD27: =LS!AD61 -> 0 | AE27: =LS!AE61 -> 0 | AG27: =LS!AG61 -> 0 | AH27: =LS!AH61 -> 0 | AI27: =LS!AI61 -> 0 | AJ27: =LS!AJ61 -> 0 | AK27: =LS!AK61 -> 0 | AM27: =LS!AM61 -> 0 | AN27: =LS!AN61 -> 0 | AO27: =LS!AO61 -> 0 | AP27: =LS!AP61 -> 0 | AQ27: =LS!AQ61 -> 0 | AS27: =LS!AS61 -> 0 | AT27: =LS!AT61 -> 0 | AU27: =LS!AU61 -> 0 | AV27: =LS!AV61 -> 0 | AW27: =LS!AW61 -> 0 | AY27: =LS!AY61 -> 0 | AZ27: =LS!AZ61 -> 0 | BA27: =LS!BA61 -> 0 | BB27: =LS!BB61 -> 0 | BC27: =LS!BC61 -> 0 | BE27: =LS!BE61 -> 0 | BF27: =LS!BF61 -> 0 | BG27: =LS!BG61 -> 0 | BH27: =LS!BH61 -> 0 | BI27: =LS!BI61 -> 0 | BK27: =LS!BK61 -> 0 | BL27: =LS!BL61 -> 0 | BM27: =LS!BM61 -> 0 | BN27: =LS!BN61 -> 0 | BO27: =LS!BO61 -> 0 | BQ27: =LS!BQ61 -> 0 | BR27: =LS!BR61 -> 0 | BS27: =LS!BS61 -> 0 | BT27: =LS!BT61 -> 0 | BU27: =LS!BU61 -> 0 | BW27: =LS!BW61 -> 0 | BX27: =LS!BX61 -> 0 | BY27: =LS!BY61 -> 0 | BZ27: =LS!BZ61 -> 0 | CA27: =LS!CA61 -> 0 | CC27: =LS!CC61 -> 0 | CD27: =LS!CD61 -> 0 | CE27: =LS!CE61 -> 0 | CF27: =LS!CF61 -> 0 | CG27: =LS!CG61 -> 0 | CI27: =LS!CI61 -> 0 | CJ27: =LS!CJ61 -> 0 | CK27: =LS!CK61 -> 0 | CL27: =LS!CL61 -> 0 | CM27: =LS!CM61 -> 0
A28: Organic Growth | I28: =LS!I62 -> 0.13820012 | J28: =LS!J62 -> 0.064701543 | K28: =LS!K62 -> 0.045474593 | L28: =LS!L62 -> 0.061906917 | M28: =LS!M62 -> 0.07568568 | O28: =LS!O62 -> 0.052187426 | P28: =LS!P62 -> -0.0068845187 | Q28: =LS!Q62 -> 0.026610862 | R28: =LS!R62 -> 0.025355826 | S28: =LS!S62 -> 0.024092696 | U28: =LS!U62 -> 0.062644713 | V28: =LS!V62 -> 0.03962363 | W28: =LS!W62 -> 0.048646632 | X28: =LS!X62 -> 0.01236697 | Y28: =LS!Y62 -> 0.040378321 | AA28: =LS!AA62 -> 0.027841025 | AB28: =LS!AB62 -> 0.086301695 | AC28: =LS!AC62 -> 0.058857499 | AD28: =LS!AD62 -> 0.040599666 | AE28: =LS!AE62 -> 0.052986462 | AG28: =LS!AG62 -> -0.018040371 | AH28: =LS!AH62 -> -0.00080884469 | AI28: =LS!AI62 -> -0.0092570048 | AJ28: =LS!AJ62 -> -0.021766033 | AK28: =LS!AK62 -> -0.012480374 | AM28: =LS!AM62 -> 0.034030377 | AN28: =LS!AN62 -> 0.020761426 | AO28: =LS!AO62 -> -0.019394762 | AP28: =LS!AP62 -> 0.023490476 | AQ28: =LS!AQ62 -> 0.014490077 | AS28: =LS!AS62 -> 0.0080670068 | AT28: =LS!AT62 -> -0.048844626 | AU28: =LS!AU62 -> 0.0094681496 | AV28: =LS!AV62 -> 0.0092457421 | AW28: =LS!AW62 -> -0.0056807698 | AY28: =LS!AY62 -> 0.038848039 | AZ28: =LS!AZ62 -> 0.063171355 | BA28: =LS!BA62 -> 0.029543198 | BB28: =LS!BB62 -> 0.034233365 | BC28: =LS!BC62 -> 0.041228504 | BE28: =LS!BE62 -> 0.002713224 | BF28: =LS!BF62 -> 0.060861198 | BG28: =LS!BG62 -> 0.032071377 | BH28: =LS!BH62 -> 0.058275058 | BI28: =LS!BI62 -> 0.038467251 | BK28: =LS!BK62 -> 0.028235294 | BL28: =LS!BL62 -> 0.06122449 | BM28: =LS!BM62 -> 0.053738318 | BN28: =LS!BN62 -> 0.019823789 | BO28: =LS!BO62 -> 0.040617849 | BQ28: =LS!BQ62 -> 0.050343249 | BR28: =LS!BR62 -> 0.034604701 | BS28: =LS!BS62 -> 0.034822616 | BT28: =LS!BT62 -> 0.05163067 | BU28: =LS!BU62 -> 0.042773502 | BW28: =LS!BW62 -> 0.035533769 | BX28: =LS!BX62 -> 0.035663008 | BY28: =LS!BY62 -> 0.035914657 | BZ28: =LS!BZ62 -> 0.036016574 | CA28: =LS!CA62 -> 0.035784411 | CC28: =LS!CC62 -> 0.035565 | CD28: =LS!CD62 -> 0.035695247 | CE28: =LS!CE62 -> 0.035946185 | CF28: =LS!CF62 -> 0.036049074 | CG28: =LS!CG62 -> 0.035816334 | CI28: =LS!CI62 -> 0.035596357 | CJ28: =LS!CJ62 -> 0.035727612 | CK28: =LS!CK62 -> 0.035977825 | CL28: =LS!CL62 -> 0.036081685 | CM28: =LS!CM62 -> 0.035848376
A29: International | I29: =LS!I63 -> 381.018 | J29: =LS!J63 -> 390.936 | K29: =LS!K63 -> 415.194 | L29: =LS!L63 -> 426.637 | M29: =LS!M63 -> 1613.785 | O29: =LS!O63 -> 404.765 | P29: =LS!P63 -> 413.75 | Q29: =LS!Q63 -> 406.256 | R29: =LS!R63 -> 424.576 | S29: =LS!S63 -> 1649.347 | U29: =LS!U63 -> 439 | V29: =LS!V63 -> 427.123 | W29: =LS!W63 -> 418.816 | X29: =LS!X63 -> 443.973 | Y29: =LS!Y63 -> 1728.912 | AA29: =LS!AA63 -> 458.2007 | AB29: =LS!AB63 -> 476.238 | AC29: =LS!AC63 -> 496.337 | AD29: =LS!AD63 -> 523.088 | AE29: =LS!AE63 -> 1953.8637 | AG29: =LS!AG63 -> 489.908 | AH29: =LS!AH63 -> 505.056 | AI29: =LS!AI63 -> 503.54 | AJ29: =LS!AJ63 -> 516.572 | AK29: =LS!AK63 -> 2015.076 | AM29: =LS!AM63 -> 512.084 | AN29: =LS!AN63 -> 527.225 | AO29: =LS!AO63 -> 513.144 | AP29: =LS!AP63 -> 569 | AQ29: =LS!AQ63 -> 2121.453 | AS29: =LS!AS63 -> 543.4 | AT29: =LS!AT63 -> 564 | AU29: =LS!AU63 -> 553.5 | AV29: =LS!AV63 -> 593.89 | AW29: =LS!AW63 -> 2254.79 | AY29: =LS!AY63 -> 555.65 | AZ29: =LS!AZ63 -> 529.25 | BA29: =LS!BA63 -> 506 | BB29: =LS!BB63 -> 547 | BC29: =LS!BC63 -> 2137.9 | BE29: =LS!BE63 -> 507 | BF29: =LS!BF63 -> 495 | BG29: =LS!BG63 -> 535 | BH29: =LS!BH63 -> 543 | BI29: =LS!BI63 -> 2080 | BK29: =LS!BK63 -> 521 | BL29: =LS!BL63 -> 515 | BM29: =LS!BM63 -> 547 | BN29: =LS!BN63 -> 588 | BO29: =LS!BO63 -> 2171 | BQ29: =LS!BQ63 -> 586 | BR29: =LS!BR63 -> 601.78926 | BS29: =LS!BS63 -> 635.22649 | BT29: =LS!BT63 -> 631.29781 | BU29: =LS!BU63 -> 2454.3136 | BW29: =LS!BW63 -> 655.59389 | BX29: =LS!BX63 -> 638.51181 | BY29: =LS!BY63 -> 670.28031 | BZ29: =LS!BZ63 -> 665.95915 | CA29: =LS!CA63 -> 2630.3452 | CC29: =LS!CC63 -> 691.60781 | CD29: =LS!CD63 -> 673.7817 | CE29: =LS!CE63 -> 707.30083 | CF29: =LS!CF63 -> 702.55484 | CG29: =LS!CG63 -> 2775.2452 | CI29: =LS!CI63 -> 729.63264 | CJ29: =LS!CJ63 -> 711.03245 | CK29: =LS!CK63 -> 746.4003 | CL29: =LS!CL63 -> 741.19466 | CM29: =LS!CM63 -> 2928.26
A30: Y/Y Growth | I30: =LS!I64 -> 0.24248106 | J30: =LS!J64 -> 0.20687569 | K30: =LS!K64 -> 0.24282417 | L30: =LS!L64 -> 0.21299837 | M30: =LS!M64 -> 0.2259292 | O30: =LS!O64 -> 0.062325139 | P30: =LS!P64 -> 0.058357378 | Q30: =LS!Q64 -> -0.021527286 | R30: =LS!R64 -> -0.0048308046 | S30: =LS!S64 -> 0.022036393 | U30: =LS!U64 -> 0.084579941 | V30: =LS!V64 -> 0.03232145 | W30: =LS!W64 -> 0.030916466 | X30: =LS!X64 -> 0.045685578 | Y30: =LS!Y64 -> 0.048240304 | AA30: =LS!AA64 -> 0.043737358 | AB30: =LS!AB64 -> 0.1149903 | AC30: =LS!AC64 -> 0.1850956 | AD30: =LS!AD64 -> 0.17819777 | AE30: =LS!AE64 -> 0.13011171 | AG30: =LS!AG64 -> 0.069199589 | AH30: =LS!AH64 -> 0.060511761 | AI30: =LS!AI64 -> 0.014512317 | AJ30: =LS!AJ64 -> -0.012456795 | AK30: =LS!AK64 -> 0.031328849 | AM30: =LS!AM64 -> 0.045265642 | AN30: =LS!AN64 -> 0.043894142 | AO30: =LS!AO64 -> 0.019072963 | AP30: =LS!AP64 -> 0.10149214 | AQ30: =LS!AQ64 -> 0.052790565 | AS30: =LS!AS64 -> 0.061154029 | AT30: =LS!AT64 -> 0.069752003 | AU30: =LS!AU64 -> 0.078644591 | AV30: =LS!AV64 -> 0.043743409 | AW30: =LS!AW64 -> 0.062851734 | AY30: =LS!AY64 -> 0.022543246 | AZ30: =LS!AZ64 -> -0.061613475 | BA30: =LS!BA64 -> -0.085817525 | BB30: =LS!BB64 -> -0.078954015 | BC30: =LS!BC64 -> -0.051840748 | BE30: =LS!BE64 -> -0.087555116 | BF30: =LS!BF64 -> -0.064714218 | BG30: =LS!BG64 -> 0.057312253 | BH30: =LS!BH64 -> -0.0073126143 | BI30: =LS!BI64 -> -0.027082651 | BK30: =LS!BK64 -> 0.027613412 | BL30: =LS!BL64 -> 0.04040404 | BM30: =LS!BM64 -> 0.022429907 | BN30: =LS!BN64 -> 0.082872928 | BO30: =LS!BO64 -> 0.04375 | BQ30: =LS!BQ64 -> 0.12476008 | BR30: =LS!BR64 -> 0.16852284 | BS30: =LS!BS64 -> 0.16129158 | BT30: =LS!BT64 -> 0.073635727 | BU30: =LS!BU64 -> 0.13049911 | BW30: =LS!BW64 -> 0.11876091 | BX30: =LS!BX64 -> 0.061022274 | BY30: =LS!BY64 -> 0.055183178 | BZ30: =LS!BZ64 -> 0.054904905 | CA30: =LS!CA64 -> 0.071723356 | CC30: =LS!CC64 -> 0.054933264 | CD30: =LS!CD64 -> 0.055237634 | CE30: =LS!CE64 -> 0.055231399 | CF30: =LS!CF64 -> 0.054951843 | CG30: =LS!CG64 -> 0.055087826 | CI30: =LS!CI64 -> 0.05498034 | CJ30: =LS!CJ64 -> 0.055286089 | CK30: =LS!CK64 -> 0.055279828 | CL30: =LS!CL64 -> 0.054999008 | CM30: =LS!CM64 -> 0.055135624
A31: FX Impact | I31: =LS!I65 -> 0.079229463 | J31: =LS!J65 -> 0.09958423 | K31: =LS!K65 -> 0.12630857 | L31: =LS!L65 -> 0.0821105 | M31: =LS!M65 -> 0.096955826 | O31: =LS!O65 -> -0.037325567 | P31: =LS!P65 -> -0.041248261 | Q31: =LS!Q65 -> -0.09450848 | R31: =LS!R65 -> -0.048702039 | S31: =LS!S65 -> -0.055995432 | U31: =LS!U65 -> 0.025046956 | V31: =LS!V65 -> -0.019744059 | W31: =LS!W65 -> -0.023066345 | X31: =LS!X65 -> -0.028270373 | Y31: =LS!Y65 -> -0.011765102 | AA31: =LS!AA65 -> 0.0044863508 | AB31: =LS!AB65 -> 0.052068088 | AC31: =LS!AC65 -> 0.093755859 | AD31: =LS!AD65 -> 0.090083163 | AE31: =LS!AE65 -> 0.059846847 | AG31: =LS!AG65 -> 0.0011211177 | AH31: =LS!AH65 -> -0.014474229 | AI31: =LS!AI65 -> -0.053244243 | AJ31: =LS!AJ65 -> -0.088481577 | AK31: =LS!AK65 -> -0.040478883 | AM31: =LS!AM65 -> -0.023053212 | AN31: =LS!AN65 -> -0.0066177968 | AO31: =LS!AO65 -> -0.029102474 | AP31: =LS!AP65 -> -0.019614536 | AQ31: =LS!AQ65 -> -0.019563972 | AS31: =LS!AS65 -> -0.015607086 | AT31: =LS!AT65 -> -0.033471821 | AU31: =LS!AU65 -> 0.0048063039 | AV31: =LS!AV65 -> 0.00060808436 | AW31: =LS!AW65 -> -0.010760075 | AY31: =LS!AY65 -> -0.062932278 | AZ31: =LS!AZ65 -> -0.09316844 | BA31: =LS!BA65 -> -0.13730804 | BB31: =LS!BB65 -> -0.13638889 | BC31: =LS!BC65 -> -0.10810071 | BE31: =LS!BE65 -> -0.11356069 | BF31: =LS!BF65 -> -0.078034955 | BG31: =LS!BG65 -> -0.024901186 | BH31: =LS!BH65 -> -0.012065814 | BI31: =LS!BI65 -> -0.057813742 | BK31: =LS!BK65 -> -0.0077475345 | BL31: =LS!BL65 -> -0.015050505 | BM31: =LS!BM65 -> -0.021431776 | BN31: =LS!BN65 -> -0.00033149171 | BO31: =LS!BO65 -> -0.011069231 | BQ31: =LS!BQ65 -> 0.033017274 | BR31: =LS!BR65 -> 0.11629954 | BS31: =LS!BS65 -> 0.091483537 | BT31: =LS!BT65 -> 0.037224162 | BU31: =LS!BU65 -> 0.068643743 | BW31: =LS!BW65 -> 0.063871833 | BX31: =LS!BX65 -> 0.0058326249 | BY31: =LS!BY65 -> 0 | BZ31: =LS!BZ65 -> 0 | CA31: =LS!CA65 -> 0.016680389 | CC31: =LS!CC65 -> 0 | CD31: =LS!CD65 -> 0 | CE31: =LS!CE65 -> 0 | CF31: =LS!CF65 -> 0 | CG31: =LS!CG65 -> 0 | CI31: =LS!CI65 -> 0 | CJ31: =LS!CJ65 -> 0 | CK31: =LS!CK65 -> 0 | CL31: =LS!CL65 -> 0 | CM31: =LS!CM65 -> 0
A32: CC Growth | I32: =LS!I66 -> 0.1632516 | J32: =LS!J66 -> 0.10729146 | K32: =LS!K66 -> 0.1165156 | L32: =LS!L66 -> 0.13088787 | M32: =LS!M66 -> 0.12897337 | O32: =LS!O66 -> 0.099650707 | P32: =LS!P66 -> 0.099605639 | Q32: =LS!Q66 -> 0.072981194 | R32: =LS!R66 -> 0.043871235 | S32: =LS!S66 -> 0.078031825 | U32: =LS!U66 -> 0.059532986 | V32: =LS!V66 -> 0.052065509 | W32: =LS!W66 -> 0.053982811 | X32: =LS!X66 -> 0.073955951 | Y32: =LS!Y66 -> 0.060005406 | AA32: =LS!AA66 -> 0.039251007 | AB32: =LS!AB66 -> 0.062922207 | AC32: =LS!AC66 -> 0.091339743 | AD32: =LS!AD66 -> 0.088114611 | AE32: =LS!AE66 -> 0.070264865 | AG32: =LS!AG66 -> 0.068078471 | AH32: =LS!AH66 -> 0.07498599 | AI32: =LS!AI66 -> 0.067756561 | AJ32: =LS!AJ66 -> 0.076024782 | AK32: =LS!AK66 -> 0.071807732 | AM32: =LS!AM66 -> 0.068318854 | AN32: =LS!AN66 -> 0.050511939 | AO32: =LS!AO66 -> 0.048175438 | AP32: =LS!AP66 -> 0.12110668 | AQ32: =LS!AQ66 -> 0.072354537 | AS32: =LS!AS66 -> 0.076761115 | AT32: =LS!AT66 -> 0.10322382 | AU32: =LS!AU66 -> 0.073838287 | AV32: =LS!AV66 -> 0.043135325 | AW32: =LS!AW66 -> 0.073611809 | AY32: =LS!AY66 -> 0.085475524 | AZ32: =LS!AZ66 -> 0.031554965 | BA32: =LS!BA66 -> 0.051490515 | BB32: =LS!BB66 -> 0.057434879 | BC32: =LS!BC66 -> 0.056259962 | BE32: =LS!BE66 -> 0.026005579 | BF32: =LS!BF66 -> 0.013320737 | BG32: =LS!BG66 -> 0.082213439 | BH32: =LS!BH66 -> 0.0047531993 | BI32: =LS!BI66 -> 0.030731091 | BK32: =LS!BK66 -> 0.035360947 | BL32: =LS!BL66 -> 0.055454545 | BM32: =LS!BM66 -> 0.043861682 | BN32: =LS!BN66 -> 0.08320442 | BO32: =LS!BO66 -> 0.054819231 | BQ32: =LS!BQ66 -> 0.091742802 | BR32: =LS!BR66 -> 0.052223301 | BS32: =LS!BS66 -> 0.069808044 | BT32: =LS!BT66 -> 0.036411565 | BU32: =LS!BU66 -> 0.061855366 | BW32: =LS!BW66 -> 0.054889078 | BX32: =LS!BX66 -> 0.055189649 | BY32: =LS!BY66 -> 0.055183178 | BZ32: =LS!BZ66 -> 0.054904905 | CA32: =LS!CA66 -> 0.055042967 | CC32: =LS!CC66 -> 0.054933264 | CD32: =LS!CD66 -> 0.055237634 | CE32: =LS!CE66 -> 0.055231399 | CF32: =LS!CF66 -> 0.054951843 | CG32: =LS!CG66 -> 0.055087826 | CI32: =LS!CI66 -> 0.05498034 | CJ32: =LS!CJ66 -> 0.055286089 | CK32: =LS!CK66 -> 0.055279828 | CL32: =LS!CL66 -> 0.054999008 | CM32: =LS!CM66 -> 0.055135624
A33: M&A / Other | I33: =LS!I67 -> 0 | J33: =LS!J67 -> 0 | K33: =LS!K67 -> 0 | L33: =LS!L67 -> 0 | M33: =LS!M67 -> 0 | O33: =LS!O67 -> 0 | P33: =LS!P67 -> 0 | Q33: =LS!Q67 -> 0 | R33: =LS!R67 -> 0 | S33: =LS!S67 -> 0 | U33: =LS!U67 -> 0 | V33: =LS!V67 -> 0 | W33: =LS!W67 -> 0 | X33: =LS!X67 -> 0 | Y33: =LS!Y67 -> 0 | AA33: =LS!AA67 -> 0.011029613 | AB33: =LS!AB67 -> 0.021066531 | AC33: =LS!AC67 -> 0.02844686 | AD33: =LS!AD67 -> 0.025641199 | AE33: =LS!AE67 -> 0.021480561 | AG33: =LS!AG67 -> 0 | AH33: =LS!AH67 -> 0 | AI33: =LS!AI67 -> 0 | AJ33: =LS!AJ67 -> 0 | AK33: =LS!AK67 -> 0 | AM33: =LS!AM67 -> 0.0036902439 | AN33: =LS!AN67 -> 0.0038339115 | AO33: =LS!AO67 -> 0.0035057791 | AP33: =LS!AP67 -> 0.0035898965 | AQ33: =LS!AQ67 -> 0.0036544329 | AS33: =LS!AS67 -> 0.0035286984 | AT33: =LS!AT67 -> 0 | AU33: =LS!AU67 -> 0 | AV33: =LS!AV67 -> 0 | AW33: =LS!AW67 -> 0.00085176999 | AY33: =LS!AY67 -> 0 | AZ33: =LS!AZ67 -> 0 | BA33: =LS!BA67 -> 0 | BB33: =LS!BB67 -> 0 | BC33: =LS!BC67 -> 0 | BE33: =LS!BE67 -> 0 | BF33: =LS!BF67 -> 0 | BG33: =LS!BG67 -> 0 | BH33: =LS!BH67 -> 0 | BI33: =LS!BI67 -> 0 | BK33: =LS!BK67 -> 0 | BL33: =LS!BL67 -> 0 | BM33: =LS!BM67 -> 0 | BN33: =LS!BN67 -> 0 | BO33: =LS!BO67 -> 0 | BQ33: =LS!BQ67 -> 0 | BR33: =LS!BR67 -> 0 | BS33: =LS!BS67 -> 0 | BT33: =LS!BT67 -> 0 | BU33: =LS!BU67 -> 0 | BW33: =LS!BW67 -> 0 | BX33: =LS!BX67 -> 0 | BY33: =LS!BY67 -> 0 | BZ33: =LS!BZ67 -> 0 | CA33: =LS!CA67 -> 0 | CC33: =LS!CC67 -> 0 | CD33: =LS!CD67 -> 0 | CE33: =LS!CE67 -> 0 | CF33: =LS!CF67 -> 0 | CG33: =LS!CG67 -> 0 | CI33: =LS!CI67 -> 0 | CJ33: =LS!CJ67 -> 0 | CK33: =LS!CK67 -> 0 | CL33: =LS!CL67 -> 0 | CM33: =LS!CM67 -> 0
A34: Organic Growth | I34: =LS!I68 -> 0.1632516 | J34: =LS!J68 -> 0.10729146 | K34: =LS!K68 -> 0.1165156 | L34: =LS!L68 -> 0.13088787 | M34: =LS!M68 -> 0.12897337 | O34: =LS!O68 -> 0.099650707 | P34: =LS!P68 -> 0.099605639 | Q34: =LS!Q68 -> 0.072981194 | R34: =LS!R68 -> 0.043871235 | S34: =LS!S68 -> 0.078031825 | U34: =LS!U68 -> 0.059532986 | V34: =LS!V68 -> 0.052065509 | W34: =LS!W68 -> 0.053982811 | X34: =LS!X68 -> 0.073955951 | Y34: =LS!Y68 -> 0.060005406 | AA34: =LS!AA68 -> 0.028221394 | AB34: =LS!AB68 -> 0.041855676 | AC34: =LS!AC68 -> 0.062892884 | AD34: =LS!AD68 -> 0.062473412 | AE34: =LS!AE68 -> 0.048784304 | AG34: =LS!AG68 -> 0.068078471 | AH34: =LS!AH68 -> 0.07498599 | AI34: =LS!AI68 -> 0.067756561 | AJ34: =LS!AJ68 -> 0.076024782 | AK34: =LS!AK68 -> 0.071807732 | AM34: =LS!AM68 -> 0.06462861 | AN34: =LS!AN68 -> 0.046678028 | AO34: =LS!AO68 -> 0.044669659 | AP34: =LS!AP68 -> 0.11751678 | AQ34: =LS!AQ68 -> 0.068700104 | AS34: =LS!AS68 -> 0.073232417 | AT34: =LS!AT68 -> 0.10322382 | AU34: =LS!AU68 -> 0.073838287 | AV34: =LS!AV68 -> 0.043135325 | AW34: =LS!AW68 -> 0.072760039 | AY34: =LS!AY68 -> 0.085475524 | AZ34: =LS!AZ68 -> 0.031554965 | BA34: =LS!BA68 -> 0.051490515 | BB34: =LS!BB68 -> 0.057434879 | BC34: =LS!BC68 -> 0.056259962 | BE34: =LS!BE68 -> 0.026005579 | BF34: =LS!BF68 -> 0.013320737 | BG34: =LS!BG68 -> 0.082213439 | BH34: =LS!BH68 -> 0.0047531993 | BI34: =LS!BI68 -> 0.030731091 | BK34: =LS!BK68 -> 0.035360947 | BL34: =LS!BL68 -> 0.055454545 | BM34: =LS!BM68 -> 0.043861682 | BN34: =LS!BN68 -> 0.08320442 | BO34: =LS!BO68 -> 0.054819231 | BQ34: =LS!BQ68 -> 0.091742802 | BR34: =LS!BR68 -> 0.052223301 | BS34: =LS!BS68 -> 0.069808044 | BT34: =LS!BT68 -> 0.036411565 | BU34: =LS!BU68 -> 0.061855366 | BW34: =LS!BW68 -> 0.054889078 | BX34: =LS!BX68 -> 0.055189649 | BY34: =LS!BY68 -> 0.055183178 | BZ34: =LS!BZ68 -> 0.054904905 | CA34: =LS!CA68 -> 0.055042967 | CC34: =LS!CC68 -> 0.054933264 | CD34: =LS!CD68 -> 0.055237634 | CE34: =LS!CE68 -> 0.055231399 | CF34: =LS!CF68 -> 0.054951843 | CG34: =LS!CG68 -> 0.055087826 | CI34: =LS!CI68 -> 0.05498034 | CJ34: =LS!CJ68 -> 0.055286089 | CK34: =LS!CK68 -> 0.055279828 | CL34: =LS!CL68 -> 0.054999008 | CM34: =LS!CM68 -> 0.055135624
A35: Total | I35: =LS!I69 -> 727.864 | J35: =LS!J69 -> 750.293 | K35: =LS!K69 -> 775.498 | L35: =LS!L69 -> 806.668 | M35: =LS!M69 -> 3060.323 | O35: =LS!O69 -> 769.712 | P35: =LS!P69 -> 770.633 | Q35: =LS!Q69 -> 776.148 | R35: =LS!R69 -> 814.243 | S35: =LS!S69 -> 3130.736 | U35: =LS!U69 -> 826.809 | V35: =LS!V69 -> 798.147 | W35: =LS!W69 -> 806.702 | X35: =LS!X69 -> 838.459 | Y35: =LS!Y69 -> 3270.117 | AA35: =LS!AA69 -> 856.8067 | AB35: =LS!AB69 -> 879.282 | AC35: =LS!AC69 -> 907.053 | AD35: =LS!AD69 -> 933.59 | AE35: =LS!AE69 -> 3576.7317 | AG35: =LS!AG69 -> 881.323 | AH35: =LS!AH69 -> 907.774 | AI35: =LS!AI69 -> 910.454 | AJ35: =LS!AJ69 -> 918.139 | AK35: =LS!AK69 -> 3617.69 | AM35: =LS!AM69 -> 916.819 | AN35: =LS!AN69 -> 938.304 | AO35: =LS!AO69 -> 912.166 | AP35: =LS!AP69 -> 980 | AQ35: =LS!AQ69 -> 3747.289 | AS35: =LS!AS69 -> 951.4 | AT35: =LS!AT69 -> 955 | AU35: =LS!AU69 -> 956.3 | AV35: =LS!AV69 -> 1008.69 | AW35: =LS!AW69 -> 3871.39 | AY35: =LS!AY69 -> 979.5 | AZ35: =LS!AZ69 -> 944.95 | BA35: =LS!BA69 -> 920.7 | BB35: =LS!BB69 -> 976 | BC35: =LS!BC69 -> 3821.15 | BE35: =LS!BE69 -> 932 | BF35: =LS!BF69 -> 936 | BG35: =LS!BG69 -> 963 | BH35: =LS!BH69 -> 997 | BI35: =LS!BI69 -> 3828 | BK35: =LS!BK69 -> 958 | BL35: =LS!BL69 -> 983 | BM35: =LS!BM69 -> 998 | BN35: =LS!BN69 -> 1051 | BO35: =LS!BO69 -> 3990 | BQ35: =LS!BQ69 -> 1045 | BR35: =LS!BR69 -> 1085.9843 | BS35: =LS!BS69 -> 1101.9315 | BT35: =LS!BT69 -> 1118.2028 | BU35: =LS!BU69 -> 4351.1186 | BW35: =LS!BW69 -> 1130.9039 | BX35: =LS!BX69 -> 1139.9747 | BY35: =LS!BY69 -> 1153.7469 | BZ35: =LS!BZ69 -> 1170.4008 | CA35: =LS!CA69 -> 4595.0262 | CC35: =LS!CC69 -> 1183.8222 | CD35: =LS!CD69 -> 1193.1444 | CE35: =LS!CE69 -> 1208.1462 | CF35: =LS!CF69 -> 1225.1811 | CG35: =LS!CG69 -> 4810.2939 | CI35: =LS!CI69 -> 1239.3681 | CJ35: =LS!CJ69 -> 1248.9507 | CK35: =LS!CK69 -> 1265.265 | CL35: =LS!CL69 -> 1282.6782 | CM35: =LS!CM69 -> 5036.262
A36: Y/Y Growth | I36: =LS!I70 -> 0.19050493 | J36: =LS!J70 -> 0.13432752 | K36: =LS!K70 -> 0.14261424 | L36: =LS!L70 -> 0.13679737 | M36: =LS!M70 -> 0.15000624 | O36: =LS!O70 -> 0.057494257 | P36: =LS!P70 -> 0.027109409 | Q36: =LS!Q70 -> 0.00083817108 | R36: =LS!R70 -> 0.0093904803 | S36: =LS!S70 -> 0.023008356 | U36: =LS!U70 -> 0.074179693 | V36: =LS!V70 -> 0.035703117 | W36: =LS!W70 -> 0.039366203 | X36: =LS!X70 -> 0.029740507 | Y36: =LS!Y70 -> 0.044520202 | AA36: =LS!AA70 -> 0.036281294 | AB36: =LS!AB70 -> 0.10165421 | AC36: =LS!AC70 -> 0.12439662 | AD36: =LS!AD70 -> 0.11345933 | AE36: =LS!AE70 -> 0.093762608 | AG36: =LS!AG70 -> 0.028613572 | AH36: =LS!AH70 -> 0.032403711 | AI36: =LS!AI70 -> 0.0037495053 | AJ36: =LS!AJ70 -> -0.016550092 | AK36: =LS!AK70 -> 0.01145132 | AM36: =LS!AM70 -> 0.040275813 | AN36: =LS!AN70 -> 0.033631719 | AO36: =LS!AO70 -> 0.0018803806 | AP36: =LS!AP70 -> 0.067376508 | AQ36: =LS!AQ70 -> 0.035823689 | AS36: =LS!AS70 -> 0.037718459 | AT36: =LS!AT70 -> 0.017793807 | AU36: =LS!AU70 -> 0.048383737 | AV36: =LS!AV70 -> 0.02927551 | AW36: =LS!AW70 -> 0.033117542 | AY36: =LS!AY70 -> 0.029535421 | AZ36: =LS!AZ70 -> -0.01052356 | BA36: =LS!BA70 -> -0.037226812 | BB36: =LS!BB70 -> -0.032408371 | BC36: =LS!BC70 -> -0.012977251 | BE36: =LS!BE70 -> -0.04849413 | BF36: =LS!BF70 -> -0.0094714006 | BG36: =LS!BG70 -> 0.045943304 | BH36: =LS!BH70 -> 0.021516393 | BI36: =LS!BI70 -> 0.001792654 | BK36: =LS!BK70 -> 0.027896996 | BL36: =LS!BL70 -> 0.050213675 | BM36: =LS!BM70 -> 0.036344756 | BN36: =LS!BN70 -> 0.054162487 | BO36: =LS!BO70 -> 0.042319749 | BQ36: =LS!BQ70 -> 0.090814196 | BR36: =LS!BR70 -> 0.10476527 | BS36: =LS!BS70 -> 0.10413977 | BT36: =LS!BT70 -> 0.063941777 | BU36: =LS!BU70 -> 0.090505906 | BW36: =LS!BW70 -> 0.082204683 | BX36: =LS!BX70 -> 0.049715637 | BY36: =LS!BY70 -> 0.047022312 | BZ36: =LS!BZ70 -> 0.046680258 | CA36: =LS!CA70 -> 0.056056311 | CC36: =LS!CC70 -> 0.046792935 | CD36: =LS!CD70 -> 0.046641144 | CE36: =LS!CE70 -> 0.047150115 | CF36: =LS!CF70 -> 0.046804767 | CG36: =LS!CG70 -> 0.046847974 | CI36: =LS!CI70 -> 0.046920789 | CJ36: =LS!CJ70 -> 0.046772498 | CK36: =LS!CK70 -> 0.047278049 | CL36: =LS!CL70 -> 0.046929433 | CM36: =LS!CM70 -> 0.046975938
... A40: Organic Growth | I40: =LS!I74 -> 0.15076534 | J40: =LS!J74 -> 0.085558813 | K40: =LS!K74 -> 0.080442485 | L40: =LS!L74 -> 0.096098226 | M40: =LS!M74 -> 0.10204536 | O40: =LS!O74 -> 0.077033227 | P40: =LS!P74 -> 0.048601586 | Q40: =LS!Q74 -> 0.051437082 | R40: =LS!R74 -> 0.035148403 | S40: =LS!S74 -> 0.05253615 | U40: =LS!U74 -> 0.061008363 | V40: =LS!V74 -> 0.046303629 | W40: =LS!W74 -> 0.051439727 | X40: =LS!X74 -> 0.044481711 | Y40: =LS!Y74 -> 0.050718341 | AA40: =LS!AA74 -> 0.028042985 | AB40: =LS!AB74 -> 0.062516707 | AC40: =LS!AC74 -> 0.060952552 | AD40: =LS!AD74 -> 0.052182048 | AE40: =LS!AE74 -> 0.050764779 | AG40: =LS!AG74 -> 0.028014024 | AH40: =LS!AH74 -> 0.040243264 | AI40: =LS!AI74 -> 0.032884614 | AJ40: =LS!AJ74 -> 0.033025901 | AK40: =LS!AK74 -> 0.033563748 | AM40: =LS!AM74 -> 0.051039259 | AN40: =LS!AN74 -> 0.035180582 | AO40: =LS!AO74 -> 0.01603701 | AP40: =LS!AP74 -> 0.076392442 | AQ40: =LS!AQ74 -> 0.044685402 | AS40: =LS!AS74 -> 0.044464773 | AT40: =LS!AT74 -> 0.036601337 | AU40: =LS!AU74 -> 0.045679924 | AV40: =LS!AV74 -> 0.028922449 | AW40: =LS!AW74 -> 0.038726931 | AY40: =LS!AY74 -> 0.065479714 | AZ40: =LS!AZ74 -> 0.044499476 | BA40: =LS!BA74 -> 0.042246157 | BB40: =LS!BB74 -> 0.047893803 | BC40: =LS!BC74 -> 0.049983184 | BE40: =LS!BE74 -> 0.015926493 | BF40: =LS!BF74 -> 0.034234616 | BG40: =LS!BG74 -> 0.059628543 | BH40: =LS!BH74 -> 0.028278689 | BI40: =LS!BI74 -> 0.034138937 | BK40: =LS!BK74 -> 0.032111588 | BL40: =LS!BL74 -> 0.058173077 | BM40: =LS!BM74 -> 0.048251298 | BN40: =LS!BN74 -> 0.054343029 | BO40: =LS!BO74 -> 0.048334378 | BQ40: =LS!BQ74 -> 0.072858038 | BR40: =LS!BR74 -> 0.043835198 | BS40: =LS!BS74 -> 0.053997996 | BT40: =LS!BT74 -> 0.04311608 | BU40: =LS!BU74 -> 0.05315614 | BW40: =LS!BW74 -> 0.04638756 | BX40: =LS!BX74 -> 0.046483536 | BY40: =LS!BY74 -> 0.047022312 | BZ40: =LS!BZ74 -> 0.046680258 | CA40: =LS!CA74 -> 0.046647488 | CC40: =LS!CC74 -> 0.046792935 | CD40: =LS!CD74 -> 0.046641144 | CE40: =LS!CE74 -> 0.047150115 | CF40: =LS!CF74 -> 0.046804767 | CG40: =LS!CG74 -> 0.046847974 | CI40: =LS!CI74 -> 0.046920789 | CJ40: =LS!CJ74 -> 0.046772498 | CK40: =LS!CK74 -> 0.047278049 | CL40: =LS!CL74 -> 0.046929433 | CM40: =LS!CM74 -> 0.046975938
A41: BD Interventional
A42: US | BE42: =Int!BE59 -> 574 | BF42: =Int!BF59 -> 594 | BG42: =Int!BG59 -> 588 | BH42: =Int!BH59 -> 607 | BI42: =Int!BI59 -> 2363 | BK42: =Int!BK59 -> 615 | BL42: =Int!BL59 -> 611 | BM42: =Int!BM59 -> 610 | BN42: =Int!BN59 -> 615 | BO42: =Int!BO59 -> 2451 | BQ42: =Int!BQ59 -> 617 | BR42: =Int!BR59 -> 638.539 | BS42: =Int!BS59 -> 635.705 | BT42: =Int!BT59 -> 649.77 | BU42: =Int!BU59 -> 2541.014 | BW42: =Int!BW59 -> 641.65 | BX42: =Int!BX59 -> 663.90747 | BY42: =Int!BY59 -> 661.17517 | BZ42: =Int!BZ59 -> 675.8619 | CA42: =Int!CA59 -> 2642.5945 | CC42: =Int!CC59 -> 667.408 | CD42: =Int!CD59 -> 690.40622 | CE42: =Int!CE59 -> 687.78995 | CF42: =Int!CF59 -> 703.12912 | CG42: =Int!CG59 -> 2748.7333 | CI42: =Int!CI59 -> 694.32904 | CJ42: =Int!CJ59 -> 718.09091 | CK42: =Int!CK59 -> 715.60606 | CL42: =Int!CL59 -> 731.63004 | CM42: =Int!CM59 -> 2859.6561
A43: Y/Y Growth | BK43: =Int!BK60 -> 0.071428571 | BL43: =Int!BL60 -> 0.028619529 | BM43: =Int!BM60 -> 0.037414966 | BN43: =Int!BN60 -> 0.013179572 | BO43: =Int!BO60 -> 0.037240796 | BQ43: =Int!BQ60 -> 0.0032520325 | BR43: =Int!BR60 -> 0.045072013 | BS43: =Int!BS60 -> 0.042139344 | BT43: =Int!BT60 -> 0.056536585 | BU43: =Int!BU60 -> 0.036725418 | BW43: =Int!BW60 -> 0.039951378 | BX43: =Int!BX60 -> 0.03972892 | BY43: =Int!BY60 -> 0.040066029 | BZ43: =Int!BZ60 -> 0.040155594 | CA43: =Int!CA60 -> 0.03997638 | CC43: =Int!CC60 -> 0.04014338 | CD43: =Int!CD60 -> 0.03991333 | CE43: =Int!CE60 -> 0.040253738 | CF43: =Int!CF60 -> 0.040344361 | CG43: =Int!CG60 -> 0.040164598 | CI43: =Int!CI60 -> 0.040336711 | CJ43: =Int!CJ60 -> 0.040099124 | CK43: =Int!CK60 -> 0.04044275 | CL43: =Int!CL60 -> 0.040534408 | CM43: =Int!CM60 -> 0.04035414
A44: M&A / Other | BK44: =Int!BK61 -> 0.030487805 | BL44: =Int!BL61 -> 0.0088383838 | BM44: =Int!BM61 -> 0 | BN44: =Int!BN61 -> 0 | BO44: =Int!BO61 -> 0.009627592 | BQ44: =Int!BQ61 -> 0 | BR44: =Int!BR61 -> 0 | BS44: =Int!BS61 -> 0 | BT44: =Int!BT61 -> 0 | BU44: =Int!BU61 -> 0 | BW44: =Int!BW61 -> 0 | BX44: =Int!BX61 -> 0 | BY44: =Int!BY61 -> 0 | BZ44: =Int!BZ61 -> 0 | CA44: =Int!CA61 -> 0 | CC44: =Int!CC61 -> 0 | CD44: =Int!CD61 -> 0 | CE44: =Int!CE61 -> 0 | CF44: =Int!CF61 -> 0 | CG44: =Int!CG61 -> 0 | CI44: =Int!CI61 -> 0 | CJ44: =Int!CJ61 -> 0 | CK44: =Int!CK61 -> 0 | CL44: =Int!CL61 -> 0 | CM44: =Int!CM61 -> 0
A45: Organic Growth | BK45: =Int!BK62 -> 0.040940767 | BL45: =Int!BL62 -> 0.019781145 | BM45: =Int!BM62 -> 0.037414966 | BN45: =Int!BN62 -> 0.013179572 | BO45: =Int!BO62 -> 0.027613204 | BQ45: =Int!BQ62 -> 0.0032520325 | BR45: =Int!BR62 -> 0.045072013 | BS45: =Int!BS62 -> 0.042139344 | BT45: =Int!BT62 -> 0.056536585 | BU45: =Int!BU62 -> 0.036725418 | BW45: =Int!BW62 -> 0.039951378 | BX45: =Int!BX62 -> 0.03972892 | BY45: =Int!BY62 -> 0.040066029 | BZ45: =Int!BZ62 -> 0.040155594 | CA45: =Int!CA62 -> 0.03997638 | CC45: =Int!CC62 -> 0.04014338 | CD45: =Int!CD62 -> 0.03991333 | CE45: =Int!CE62 -> 0.040253738 | CF45: =Int!CF62 -> 0.040344361 | CG45: =Int!CG62 -> 0.040164598 | CI45: =Int!CI62 -> 0.040336711 | CJ45: =Int!CJ62 -> 0.040099124 | CK45: =Int!CK62 -> 0.04044275 | CL45: =Int!CL62 -> 0.040534408 | CM45: =Int!CM62 -> 0.04035414
A46: International | BE46: =Int!BE63 -> 235 | BF46: =Int!BF63 -> 222 | BG46: =Int!BG63 -> 266 | BH46: =Int!BH63 -> 263 | BI46: =Int!BI63 -> 986 | BK46: =Int!BK63 -> 276 | BL46: =Int!BL63 -> 251 | BM46: =Int!BM63 -> 280 | BN46: =Int!BN63 -> 282 | BO46: =Int!BO63 -> 1089 | BQ46: =Int!BQ63 -> 308 | BR46: =Int!BR63 -> 288.87191 | BS46: =Int!BS63 -> 316.91418 | BT46: =Int!BT63 -> 312.1984 | BU46: =Int!BU63 -> 1225.9845 | BW46: =Int!BW63 -> 343.78508 | BX46: =Int!BX63 -> 313.91183 | BY46: =Int!BY63 -> 343.48817 | BZ46: =Int!BZ63 -> 338.39866 | CA46: =Int!CA63 -> 1339.5837 | CC46: =Int!CC63 -> 372.35491 | CD46: =Int!CD63 -> 340.47616 | CE46: =Int!CE63 -> 372.74214 | CF46: =Int!CF63 -> 367.24322 | CG46: =Int!CG63 -> 1452.8164 | CI46: =Int!CI63 -> 403.79307 | CJ46: =Int!CJ63 -> 369.72642 | CK46: =Int!CK63 -> 404.96393 | CL46: =Int!CL63 -> 399.01624 | CM46: =Int!CM63 -> 1577.4997
