Workbook
Name AdditionalInstructions: IndexInformation!$B$42
Name Address: ImportantDisclosures!$A$2:$A$2
Name ANA: ModPubIndex!$A$7
Name Authors: ImportantDisclosures!$A$7
Name Authors: IndexInformation!$B$18
Name BRO: ModPubIndex!$A$1
Name CopyrightStamp: ImportantDisclosures!$A$27
Name COU: ModPubIndex!$A$5
Name CQEnd: IndexInformation!$B$31
Name Currency: IndexInformation!$B$24
Name CurrentStockPrice: IndexInformation!$B$23
Name CurrQtrEPS: IndexInformation!$B$29
Name CurrYearEPS: IndexInformation!$B$11
Name CurrYearTotalRevenue: IndexInformation!$B$10
Name CurrYearTotalRevenueActual: IndexInformation!$B$32
Name CUSIP: IndexInformation!$B$20
Name CYEnd: IndexInformation!$B$30
Name Date: ImportantDisclosures!$A$8
Name Deleted: IndexInformation!$B$27
Name Description: IndexInformation!$B$7
Name Discipline: IndexInformation!$B$3
Name DISCIPLINE: ModPubIndex!$A$12
Name DisclosuresText: ImportantDisclosures!$A$22
Name Distribution: IndexInformation!$B$26
Name DistTable: ImportantDisclosures!#REF!
Name DistTablePreamble: ImportantDisclosures!#REF!
Name DOCDAT: ModPubIndex!$A$2
Name DOCTIME: ModPubIndex!$A$3
Name DocType: IndexInformation!$B$5
Name EMAIL_ALERT: ModPubIndex!$A$10
Name EmailAlert: IndexInformation!$B$28
Name FiveYearGrowthRate: IndexInformation!$B$16
Name FollowingYearEPS: IndexInformation!$B$15
Name FollowingYearTotalRevenue: IndexInformation!$B$14
Name FollowingYearTotalRevenueActual: IndexInformation!$B$34
Name HL: ModPubIndex!$A$8
Name IND: ModPubIndex!$A$9
Name Industry: ImportantDisclosures!$A$12
Name IndustryId: IndexInformation!$B$40
Name IndustryRating: ImportantDisclosures!$A$13
Name KeepVersions: IndexInformation!$B$8
Name LanguageCode: IndexInformation!$B$38
Name LastCell: ImportantDisclosures!$A$22
Name Linking_1: IS!$A$7:$DM$109
Name Linking_10: IS!$A$7:$DR$109
Name Linking_11: CF!$A$7:$DR$78
Name Linking_12: IS!$A$7:$DW$109
Name Linking_2: BS!$A$6:$DM$70
Name Linking_3: CF!$A$7:$DM$95
Name Linking_4: IS!$A$5:$DM$82
Name Linking_5: BS!$A$5:$DM$57
Name Linking_6: CF!$A$5:$DM$95
Name Linking_7: IS!$A$7:$DR$108
Name Linking_8: BS!$A$6:$DR$57
Name Linking_9: CF!$A$9:$DR$78
Name Linking_Range_1: IS!$A$7:$DC$100
Name Linking_Range_12: BS!$A$5:$DC$75
Name Linking_Range_13: CF!$A$5:$DC$90
Name Linking_Range_15: IS!$A$5:$DH$82
Name Linking_Range_16: BS!$A$5:$DH$57

Sheet ImportantDisclosures
A2: 1585 Broadway
A3: New York, NY 10036-8293
A4: United States
A5: Tel: +1 (1)212 761 4000
A7: Authors: John Glass
A8: Date: 16 Apr 2018
A10: Ticker: SBUX.O
A11: Stock Rating: Overweight
A12: Industry: Restaurants
A13: Industry View: In-Line
A14: Price as of 16 Apr 2018: 59.36
A15: Target Price: 72
... A129: Equal-weight and Not-Rated to hold and Underweight to sell recommendations, respectively.
B131: Coverage Universe | D131: Investment Banking Clients (IBC) | G131: Other Material Investment Services Clients (MISC)
A132: Stock Rating Category | B132: Count | C132: % of Total | D132: Count | E132: % of Total IBC | F132: % of Rating Category | G132: Count | H132: % of Total Other MISC
A133: Overweight/Buy | B133: 1189 | C133: 0.38 | D133: 315 | E133: 0.41 | F133: 0.26 | G133: 555 | H133: 0.39
A134: Equal-weight/Hold | B134: 1355 | C134: 0.43 | D134: 364 | E134: 0.47 | F134: 0.27 | G134: 644 | H134: 0.45
A135: Not-Rated/Hold | B135: 53 | C135: 0.02 | D135: 4 | E135: 0.01 | F135: 0.08 | G135: 7 | H135: 0
A136: Underweight/Sell | B136: 545 | C136: 0.17 | D136: 84 | E136: 0.11 | F136: 0.15 | G136: 214 | H136: 0.15
A137: Total | B137: 3142 | D137: 767 | G137: 1420
A139: Data include common stock and ADRs currently assigned ratings. Investment Banking Clients are companies
A140: from whom Morgan Stanley received investment banking compensation in the last 12 months. Due to rounding
A141: off of decimals, the percentages provided in the "% of total" column may not add up to exactly 100
A142: percent.
A144: Analyst Stock Ratings
A146: Overweight (O). The stock's total return is expected to exceed the average total return of the analyst's
A147: industry (or industry team's) coverage universe, on a risk-adjusted basis, over the next 12-18 months.
A149: Equal-weight (E). The stock's total return is expected to be in line with the average total return of
A150: the analyst's industry (or industry team's) coverage universe, on a risk-adjusted basis, over the next
A151: 12-18 months.
A153: Not-Rated (NR). Currently the analyst does not have adequate conviction about the stock's total return
A154: relative to the average total return of the analyst's industry (or industry team's) coverage universe,
... A400: © Copyright 2018 Morgan Stanley

Sheet Intro
C1: Ticker (Nasdaq): SBUX | F1: Price Target/Base Case | I1: 72
C2: Snapshot
C3: (data in $ millions except EPS & Units) | D3: FY03 | E3: FY04 | F3: FY05 | G3: FY06 | H3: FY07 | I3: FY08 | J3: FY09 | K3: FY10 | L3: FY11 | M3: FY12 | N3: FY13 | O3: FY14 | P3: FY15 | Q3: FY16 | R3: FY17 | S3: FY18E | T3: FY19E | V3: 3yr ('17/'14) CAGR
A4: Starbucks Corporation | C4: Revenue | D4: =IS!AU17 -> 4075.521 | E4: =IS!AZ17 -> 5294.247 | F4: =IS!BE17 -> 6369.3 | G4: =IS!BJ17 -> 7786.942 | H4: =IS!BO17 -> 9411.497 | I4: =IS!BT17 -> 10383 | J4: =IS!BY17 -> 9774.6 | K4: =IS!CD17 -> 10707.4 | L4: =IS!CI17 -> 11700.6 | M4: =IS!CN17 -> 13276.9 | N4: =IS!CS17 -> 14866.9 | O4: =IS!CX17 -> 16447.9 | P4: =IS!DC17 -> 19162.7 | Q4: =IS!DH17 -> 21315.9 | R4: =IS!DM17 -> 22386.7 | S4: =IS!DR17 -> 24765.707 | T4: =IS!DW17 -> 27224.617 | V4: =(R4/O4)^(1/3)-1 -> 0.10822142
A5: John S. Glass | C5: Revenue Growth | D5: =IS!AU73 -> 0.23917148 | E5: =IS!AZ73 -> 0.29903563 | F5: =IS!BE73 -> 0.20306061 | G5: =IS!BJ73 -> 0.22257422 | H5: =IS!BO73 -> 0.20862554 | I5: =IS!BT73 -> 0.10322513 | J5: =J4/I4-1 -> -0.058595782 | K5: =K4/J4-1 -> 0.095431015 | L5: =L4/K4-1 -> 0.092758279 | M5: =M4/L4-1 -> 0.13471959 | N5: =N4/M4-1 -> 0.11975687 | O5: =O4/N4-1 -> 0.10634362 | P5: =P4/O4-1 -> 0.16505451 | Q5: =Q4/P4-1 -> 0.11236412 | ... T5: =T4/S4-1 -> 0.099286898
A6: (617) 856-8752 | C6: Operating Income | D6: =IS!AU30 -> 424.712 | E6: =IS!AZ30 -> 606.817 | F6: =IS!BE30 -> 780.615 | G6: =IS!BJ30 -> 893.986 | H6: =IS!BO30 -> 1053.945 | I6: =IS!BT30 -> 805.86 | J6: =IS!BY30 -> 894.4 | K6: =IS!CD30 -> 1472.4 | L6: =IS!CI30 -> 1698.3 | M6: =IS!CN30 -> 1997.6 | N6: =IS!CS30 -> 2458.8 | O6: =IS!CX30 -> 3060.8 | P6: =IS!DC30 -> 3655.6 | Q6: =IS!DH30 -> 4197.8122 | R6: =IS!DM30 -> 4412.5 | S6: =IS!DR30 -> 4685.1725 | T6: =IS!DW30 -> 5280.614 | V6: =(R6/O6)^(1/3)-1 -> 0.12966565
A7: john.glass@morganstanley.com | C7: Operating Income Growth | D7: =IS!AU77 -> 0.34258926 | E7: =IS!AZ77 -> 0.42877291 | F7: =IS!BE77 -> 0.28640925 | G7: =IS!BJ77 -> 0.14523293 | H7: =IS!BO77 -> 0.17892786 | I7: =IS!BT77 -> -0.52192951 | J7: =J6/I6-1 -> 0.1098702 | K7: =K6/J6-1 -> 0.64624329 | L7: =L6/K6-1 -> 0.15342298 | M7: =M6/L6-1 -> 0.17623506 | N7: =N6/M6-1 -> 0.23087705 | O7: =O6/N6-1 -> 0.24483488 | P7: =P6/O6-1 -> 0.19432828 | Q7: =Q6/P6-1 -> 0.14832372 | ... T7: =T6/S6-1 -> 0.12709063
C8: Operating EPS | D8: =IS!AU50 -> 0.16702712 | E8: =IS!AZ50 -> 0.23647394 | F8: =IS!BE50 -> 0.30319885 | G8: =IS!BJ53 -> 0.35601891 | H8: =IS!BO50 -> 0.43688973 | I8: =IS!BT50 -> 0.35543985 | J8: =IS!BY50 -> 0.39916879 | K8: =IS!CD50 -> 0.64447783 | L8: =IS!CI50 -> 0.75935429 | M8: =IS!CN50 -> 0.89527814 | N8: =IS!CS50 -> 1.0966155 | O8: =IS!CX50 -> 1.3161531 | P8: =IS!DC50 -> 1.5831266 | Q8: =IS!DH50 -> 1.906739 | R8: =IS!DM50 -> 2.0698592 | S8: =IS!DR50 -> 2.4812693 | T8: =IS!DW50 -> 2.7963085 | V8: =(R8/O8)^(1/3)-1 -> 0.16290652
A9: Chris Carril | C9: Operating EPS Growth | D9: =IS!AU81 -> 0.2486635 | E9: =IS!AZ81 -> 0.41578171 | F9: =IS!BE81 -> 0.28216603 | G9: =IS!BJ81 -> 0.3325096 | H9: =IS!BO81 -> 0.19082649 | I9: =IS!BT81 -> -0.1864312 | J9: =J8/I8-1 -> 0.12302767 | K9: =K8/J8-1 -> 0.61454966 | L9: =L8/K8-1 -> 0.17824734 | M9: =M8/L8-1 -> 0.17899924 | N9: =N8/M8-1 -> 0.22488807 | O9: =O8/N8-1 -> 0.20019556 | P9: =P8/O8-1 -> 0.20284382 | Q9: =Q8/P8-1 -> 0.20441351 | ... T9: =T8/S8-1 -> 0.12696696
A10: (617) 856-8750 | C10: TOTAL SSS | J10: =IS!BY100 -> -0.06 | K10: =IS!CD100 -> 0.07 | L10: =IS!CI100 -> 0.08 | M10: =IS!CN100 -> 0.07 | N10: =IS!CS100 -> 0.07 | O10: =IS!CX100 -> 0.06 | P10: =IS!DC100 -> 0.07 | Q10: =IS!DH100 -> 0.05 | R10: =IS!DM100 -> 0.03 | S10: =IS!DR100 -> 0.022274723 | T10: =IS!DW100 -> 0.037320364 | V10: =AVERAGE(P10:R10) -> 0.05
A11: christopher.carril@morganstanley.com | C11: Total Units | D11: 7225 | E11: 8569 | F11: 10241 | G11: 12440 | H11: 15011 | I11: 16680 | J11: =IS!BY90 -> 16635 | K11: =IS!CD90 -> 16858 | L11: =IS!CI90 -> 17003 | M11: =IS!CN90 -> 18066 | N11: =IS!CS90 -> 19767 | O11: =IS!CX90 -> 21366 | P11: =IS!DC90 -> 23043 | Q11: =IS!DH90 -> 25085 | R11: =IS!DM90 -> 27339 | S11: =IS!DR90 -> 29357 | T11: =IS!DW90 -> 31711 | V11: =(R11/O11)^(1/3)-1 -> 0.085641576
C12: Total Unit Growth | D12: 0.22748896 | E12: 0.18602076 | F12: 0.19512195 | G12: 0.21472512 | H12: 0.20667203 | I12: 0.089124045 | J12: =J11/I11-1 -> -0.0026978417 | K12: =K11/J11-1 -> 0.01340547 | L12: =L11/K11-1 -> 0.0086012576 | M12: =M11/L11-1 -> 0.062518379 | N12: =N11/M11-1 -> 0.094154766 | O12: =O11/N11-1 -> 0.080892396 | P12: =P11/O11-1 -> 0.078489188 | Q12: =Q11/P11-1 -> 0.088616934 | ... T12: =T11/S11-1 -> 0.080185305
C13: Calendarized Results and Estimates
A14: Go To: | C14: (data in $ millions except EPS & Units) | F14: CY05 | G14: CY06 | H14: CY07 | I14: CY08 | J14: CY09 | K14: CY10 | L14: CY11 | M14: CY12 | N14: CY13 | O14: CY14 | P14: CY15 | Q14: CY16 | R14: CY17E | S14: CY18E | T14: CY19E | V14: CY
A15: Income Statement | C15: Revenue | F15: =IS!EN17 -> 6713.848 | G15: =IS!EO17 -> 8208.573 | H15: =IS!EP17 -> 9823.374 | I15: =IS!EQ17 -> 10230.6 | J15: =IS!ER17 -> 9882.1 | K15: =IS!ES17 -> 10935.5 | L15: =IS!ET17 -> 12179.8 | M15: =IS!EU17 -> 13640.1 | ... T15: =IS!FB17 -> 27861.787 | V15: =(R15/O15)^(1/3)-1 -> 0.10137789
A16: Balance Sheet | C16: Revenue Growth | G16: =G15/F15-1 -> 0.22263313 | H16: =H15/G15-1 -> 0.19672128 | I16: =I15/H15-1 -> 0.0414548 | J16: =J15/I15-1 -> -0.034064473 | K16: =K15/J15-1 -> 0.10659678 | L16: =L15/K15-1 -> 0.11378538 | M16: =M15/L15-1 -> 0.11989524 | N16: =N15/M15-1 -> 0.12266772 | ... T16: =T15/S15-1 -> 0.095707154
A17: Statement of Cash Flows | C17: EBITDA (before charges) | F17: =IS!EN31 -> 1212.863 | G17: =IS!EO31 -> 1364.832 | H17: =IS!EP31 -> 1582.337 | I17: =IS!EQ31+IS!EQ26 -> 1558.76 | J17: =IS!ER31+IS!ER26 -> 1603.1 | K17: =IS!ES32 -> 2111 | L17: =IS!ET31 -> 2282.8 | M17: =IS!EU31 -> 2636.6 | N17: =IS!EV31 -> 3263.7 | O17: =IS!EW31 -> 3928.9 | P17: =IS!EX31 -> 4666.9 | Q17: =IS!EY31 -> 5241.6 | R17: =IS!EZ31 -> 5138.6 | S17: =IS!FA31 -> 5886.6204 | T17: =IS!FB31 -> 6591.5957 | V17: =(R17/O17)^(1/3)-1 -> 0.093598601
A18: Unit Detail | C18: EBITDA Growth | G18: =G17/F17-1 -> 0.12529775 | H18: =H17/G17-1 -> 0.15936394 | I18: =I17/H17-1 -> -0.014900113 | J18: =J17/I17-1 -> 0.028445688 | K18: =K17/J17-1 -> 0.31682365 | L18: =L17/K17-1 -> 0.081383231 | M18: =M17/L17-1 -> 0.15498511 | N18: =N17/M17-1 -> 0.23784419 | ... T18: =T17/S17-1 -> 0.11975892
A19: Revenue Drivers | C19: Operating EPS | F19: =IS!EN50 -> 0.32499222 | G19: =IS!EO50 -> 0.38757124 | H19: =IS!EP50 -> 0.44435823 | I19: =IS!EQ50 -> 0.28940379 | J19: =IS!ER50 -> 0.49203964 | K19: =IS!ES50 -> 0.70209063 | L19: =IS!ET50 -> 0.76232674 | M19: =IS!EU50 -> 0.92981944 | ... T19: =IS!FB50 -> 2.8883687 | V19: =(R19/O19)^(1/3)-1 -> -0.054956808
A20: Segment Details | C20: Operating EPS Growth | G20: =G19/F19-1 -> 0.19255543 | H20: =H19/G19-1 -> 0.14652015 | I20: =I19/H19-1 -> -0.34871513 | J20: =J19/I19-1 -> 0.70018378 | K20: =K19/J19-1 -> 0.42689853 | L20: =L19/K19-1 -> 0.085795349 | M20: =M19/L19-1 -> 0.21971248 | N20: =N19/M19-1 -> 0.24407307 | ... T20: =T19/S19-1 -> 0.15341518
C21: Free Cash Flow (CFO less Capex) | G21: =CF!EE85 -> 306.726 | H21: =CF!EF85 -> 387.011 | I21: =CF!EG85 -> 251.1 | J21: =CF!EH85 -> 1091.5 | K21: =CF!EI85 -> 1139.9 | L21: =CF!EJ85 -> 848.6 | M21: =CF!EK85 -> 1375.5 | N21: =CF!EL85 -> -725.9 | ... T21: =CF!ER85 -> 3183.128 | V21: =(R21/O21)^(1/3)-1 -> 0.1857646
C23: Valuation Information
N24: =N14 -> CY13 | O24: =O14 -> CY14 | P24: =P14 -> CY15 | Q24: =Q14 -> CY16 | R24: =R14 -> CY17E | S24: CY18E | T24: CY19E
C25: Current stock price | D25: 60.61
C26: Current shares outstanding | D26: =IS!DL54 -> 1451.2
C27: Market Cap | D27: =D26*D25 -> 87957.232
C28: Current net debt | D28: =BS!DL45-BS!DL9+BS!DL35 -> 1470.3
C29: Enterprise Value | D29: =D28+D27 -> 89427.532
C30: Rent (fiscal year) | F30: 416.916 | G30: 498.8 | H30: 638.1 | I30: 741.1 | J30: 714.7 | K30: 714.6 | L30: 749.9 | M30: 803.7 | N30: 894.7 | O30: 974.2 | P30: 1137.8 | Q30: 1223.2 | R30: 1239.8738 | S30: 1322.1023 | T30: 1398.9205
C31: Capitalized Rent | N31: =N30*8 -> 7157.6 | O31: =O30*8 -> 7793.6 | P31: =P30*8 -> 9102.4 | Q31: =Q30*8 -> 9785.6 | R31: =R30*8 -> 9918.9905 | S31: =S30*8 -> 10576.818 | T31: =T30*8 -> 11191.364
C32: Debt to EBITDA | N32: =-$D$28/N17 -> -0.45050097 | O32: =-$D$28/O17 -> -0.37422688 | P32: =-$D$28/P17 -> -0.31504853 | Q32: =-$D$28/Q17 -> -0.28050595 | R32: =-$D$28/R17 -> -0.28612852 | S32: =-$D$28/S17 -> -0.2497698 | T32: =-$D$28/T17 -> -0.22305676
C33: Rent Adjusted Debt to EBITDAR | N33: =(N31+$D$28)/(N17+N30) -> 2.0748124 | O33: =(O31+$D$28)/(O17+O30) -> 1.8893965 | P33: =(P31+$D$28)/(P17+P30) -> 1.8214033 | Q33: =(Q31+$D$28)/(Q17+Q30) -> 1.7411057 | R33: =(R31+$D$28)/(R17+R30) -> 1.7855824 | S33: =(S31+$D$28)/(S17+S30) -> 1.6711862 | T33: =(T31+$D$28)/(T17+T30) -> 1.5845864
C34: EV/EBITDA (before charges) | N34: =$D$29/N17 -> 27.400659 | O34: =$D$29/O17 -> 22.761468 | P34: =$D$29/P17 -> 19.162084 | Q34: =$D$29/Q17 -> 17.061113 | R34: =$D$29/R17 -> 17.403093 | S34: =$D$29/S17 -> 15.191659 | T34: =$D$29/T17 -> 13.566902
C35: Rent Adjusted EV/EBITDAR (before charges) | N35: =($D$29+N31)/(N17+N30) -> 23.226513 | O35: =($D$29+O31)/(O17+O30) -> 19.828503 | P35: =($D$29+P31)/(P17+P30) -> 16.974164 | Q35: =($D$29+Q31)/(Q17+Q30) -> 15.346667 | R35: =($D$29+R31)/(R17+R30) -> 15.575281 | S35: =($D$29+S31)/(S17+S30) -> 13.872687 | T35: =($D$29+T31)/(T17+T30) -> 12.59229
C36: FCF Yield | N36: =N21/$D$27 -> -0.0082528745 | O36: =O21/$D$27 -> 0.025447595 | P36: =P21/$D$27 -> 0.029744001 | Q36: =Q21/$D$27 -> 0.034322362 | R36: =R21/$D$27 -> 0.042426986 | S36: =S21/$D$27 -> 0.030351808 | T36: =T21/$D$27 -> 0.036189497
C37: P/S | N37: =$D$27/N15 -> 5.7438457 | O37: =$D$27/O15 -> 5.1704572 | P37: =$D$27/P15 -> 4.4573675 | Q37: =$D$27/Q15 -> 4.0579476 | R37: =$D$27/R15 -> 3.8700795 | S37: =$D$27/S15 -> 3.459052 | T37: =$D$27/T15 -> 3.1569128
C38: P/E | N38: =$D$25/N19 -> 52.396198 | O38: =$D$25/O19 -> 54.362735 | P38: =$D$25/P19 -> 35.946679 | Q38: =$D$25/Q19 -> 30.898884 | R38: =$D$25/R19 -> 64.408965 | S38: =$D$25/S19 -> 24.203452 | T38: =$D$25/T19 -> 20.984163

Sheet MW-Cache
A1: $H$2
A2: SBUX.O,mscalc:targetPrice,,,,USD | B2: 72 | C2: SBUX.O,mscalc:targetPrice | D2: 72 | E2: SBUX.O,mscalc:closePriceCurrencyCalc | F2: USD | G2: SBUX.O,mscalc:sedolCodeCalc | H2: 2842255

Sheet IS
DN1: =DN50 -> 0.64852084 | DO1: =DO50 -> 0.52698176 | DP1: =DP50 -> 0.64379562 | DQ1: =DQ50 -> 0.66246771 | DR1: =DR50 -> 2.4812693 | DS1: =DS50 -> 0.67247901 | DT1: =DT50 -> 0.61722872 | DU1: =DU50 -> 0.74597878 | ... EB1: =EB50 -> 3.1873226
A2: John S. Glass (617) 856-8752 | DN2: 0.64852084 | DO2: 0.52016469 | DP2: 0.65157087 | DQ2: 0.66341236 | DR2: 2.4831099 | DS2: 0.68881118 | DT2: 0.60692769 | DU2: 0.75202038 | DV2: 0.76120858 | DW2: 2.8079115 | DX2: 0.78196693 | DY2: 0.69287111 | DZ2: 0.85548958 | EA2: 0.86543689 | EB2: 3.1945656
A3: Chris Carril (617) 856-8750 | DN3: =+DN1-DN2 -> 0 | DO3: =+DO1-DO2 -> 0.0068170701 | DP3: =+DP1-DP2 -> -0.0077752446 | DQ3: =+DQ1-DQ2 -> -0.00094464993 | DR3: =+DR1-DR2 -> -0.0018406624 | DS3: =+DS1-DS2 -> -0.016332169 | DT3: =+DT1-DT2 -> 0.010301031 | DU3: =+DU1-DU2 -> -0.0060416025 | ... EB3: =+EB1-EB2 -> -0.0072429998
A5: STARBUCKS CORPORATION: INCOME STATEMENT | CB5: =CC5/BX17-1 -> 0.087971974 | CC5: =CC17*13/14 -> 2635.2857 | DO5: =1040*0.07/4 -> 18.2 | FD5: STARBUCKS CORPORATION: INCOME STATEMENT
A7: Fiscal Year Ends: September | B7: FY 1994 | C7: 34669 | D7: 34759 | E7: 34851 | F7: 34943 | G7: FY 1995 | H7: 35034 | I7: 35125 | J7: 35217 | K7: 35309 | L7: FY 1996 | M7: Dec-96R | N7: Mar-97R | O7: Jun-97R | P7: Sep-97R | Q7: FY 1997 R | R7: Dec-97 | S7: Mar-98 | T7: Jun-98 | U7: Sep-98 | V7: FY 1998 | W7: Dec-98 | X7: Mar-99 | Y7: Jun-99 | Z7: Sep-99 | AA7: FY 1999 | AB7: Dec-99 | AC7: Mar-00 | AD7: Jun-00 | AE7: Sep-00 | AF7: FY 2000A | AG7: Dec-00A | AH7: Mar-01A | AI7: Jun-01A | AJ7: Sep-01A | AK7: FY 2001 | AL7: Dec-01A | AM7: Mar-02A | AN7: Jun-02A | AO7: Sep-02A | AP7: FY 2002A | AQ7: Dec-02A | AR7: Mar-03A | AS7: Jun-03A | AT7: Sep-03A | AU7: FY 2003A | AV7: Dec-03A | AW7: Mar-04A | AX7: Jun-04A | AY7: Sep-04A | AZ7: FY 2004A | BA7: Dec-04A | BB7: Mar-05A | BC7: Jun-05A | BD7: Sep-05A | BE7: FY 2005A | BF7: Dec-05A | BG7: Mar-06A | BH7: Jun-06A | BI7: Sep-06A | BJ7: FY 2006A | BK7: Dec-06A | BL7: Mar-07A | BM7: Jun-07A | BN7: Sep-07A | BO7: FY 2007A | BP7: Dec-07A | BQ7: Mar-08A | BR7: Jun-08A | BS7: Sep-08A | BT7: FY 2008A | BU7: Dec-08A | BV7: Mar-09A | BW7: Jun-09A | BX7: Sep-09A | BY7: FY 2009A | BZ7: Dec-09A | CA7: Mar-10A | CB7: Jun-10A | CC7: Sep-10A | CD7: FY 2010A | CE7: Dec-10A | CF7: Mar-11A | CG7: Jun-11A | CH7: Sep-11A | CI7: FY 2011A | CJ7: Dec-11A | CK7: Mar-12A | CL7: Jun-12A | CM7: Sep-12A | CN7: FY 2012A | CO7: Dec-12A | CP7: Mar-13A | CQ7: Jun-13A | CR7: Sep-13A | CS7: FY2013A | CT7: Dec-13A | CU7: Mar-14A | CV7: Jun-14A | CW7: Sep-14A | CX7: FY2014A | CY7: Dec-14A | CZ7: Mar-15A | DA7: Jun-15A | DB7: Sep-15A | DC7: FY2015A | DD7: Dec-15A | DE7: Mar-16A | DF7: Jun-16A | DG7: Sep-16A | DH7: FY2016A | DI7: Dec-16A | DJ7: Mar-17A | DK7: Jun-17A | DL7: Sep-17A | DM7: FY2017A | DN7: Dec-17A | DO7: Mar-18E | DP7: Jun-18E | DQ7: Sep-18E | DR7: FY2018E | DS7: Dec-18E | DT7: Mar-19E | DU7: Jun-19E | DV7: Sep-19E | DW7: FY2019E | DX7: Dec-19E | DY7: Mar-20E | DZ7: Jun-20E | EA7: Sep-20E | EB7: FY2020E | EG7: CY 1998 | EH7: CY 1999 | EI7: CY 2000 | EJ7: CY 2001 | EK7: CY 2002 | EL7: CY 2003 | EM7: CY 2004 | EN7: CY 2005 | EO7: CY 2006 | EP7: CY 2007 | EQ7: CY 2008 | ER7: CY 2009 | ES7: CY 2010 | ET7: CY 2011 | EU7: CY 2012 | EV7: CY 2013 | EW7: CY 2014 | EX7: CY 2015 | EY7: CY 2016 | EZ7: CY 2017 | FA7: CY 2018 | FB7: CY 2019 | FD7: Fiscal Year Ends: September | FE7: =DN7 -> Dec-17A | FF7: Dec-17E | FG7: A vs. E | FH7: =DI7 -> Dec-16A | FI7: Y/Y
A8: $ in millions, quarters 4,4,5 | AA8: 53 weeks | AK8: restated | AP8: restated | AQ8: restated | AR8: restated | AU8: restated | AV8: restated | AW8: restated | AX8: restated | AY8: restated | AZ8: 53 weeks | BA8: restated | BB8: restated | BC8: restated | BD8: restated | BE8: 52 weeks | CD8: 53 weeks | CE8: restated | CF8: restated | CG8: restated | CH8: restated | FD8: dollars in millions, quarters 4,4,5
A9: SYSTEMWIDE SALES | V9: 1190 | W9: 382 | X9: 365 | Y9: 410 | Z9: 476 | AA9: 1633 | AB9: 520 | AC9: 521 | AD9: 584 | AE9: 625 | AF9: 2250 | AG9: 722 | AH9: 679 | AI9: 755 | AJ9: 795 | AK9: =SUM(AG9:AJ9) -> 2951 | AL9: 910 | AM9: 895 | AN9: 972 | AO9: 1019 | AP9: 3796 | AQ9: 1144
A10: Company Store Sales | B10: 248.495 | C10: 98.113 | D10: 86.894 | E10: 103.719 | F10: 113.929 | G10: =SUM(C10:F10) -> 402.655 | H10: 145.732 | I10: =132.301 -> 132.301 | J10: 153.212 | K10: 168.824 | L10: =SUM(H10:K10) -> 600.069 | M10: =205.338+1.012 -> 206.35 | N10: =185.061+1.355 -> 186.416 | O10: =209.993+2.051 -> 212.044 | P10: 231.482 | Q10: =SUM(M10:P10) -> 836.292 | R10: 274.973 | S10: =247.8+5.637 -> 253.437 | T10: 283.47 | U10: 290.922 | V10: 1102.574 | W10: 342.788 | X10: 318.728 | Y10: 355.951 | Z10: 405.9 | AA10: =SUM(W10:Z10) -> 1423.367 | AB10: 440.785 | AC10: 429.031 | AD10: 466.7 | AE10: 487.074 | AF10: =SUM(AB10:AE10) -> 1823.59 | AG10: 562.407 | AH10: 523.277 | AI10: 558.92 | AJ10: 584.99 | AK10: =SUM(AG10:AJ10) -> 2229.594 | AL10: 682.265 | AM10: 664.262 | AN10: 711.834 | AO10: 734.543 | AP10: =SUM(AL10:AO10) -> 2792.904 | AQ10: 849.486 | AR10: 809.317 | AS10: 877.754 | AT10: 913.066 | AU10: =SUM(AQ10:AT10) -> 3449.623 | AV10: 1080.495 | AW10: 1050.481 | AX10: 1108.055 | AY10: 1218.347 | AZ10: =SUM(AV10:AY10) -> 4457.378 | BA10: 1358.661 | BB10: 1283.947 | BC10: 1356.605 | BD10: 1392.714 | BE10: =SUM(BA10:BD10) -> 5391.927 | BF10: 1627.983 | BG10: 1599.844 | BH10: 1660.977 | BI10: 1694.294 | BJ10: =SUM(BF10:BI10) -> 6583.098 | BK10: 2006.811 | BL10: 1922.705 | BM10: 2010.772 | BN10: 2057.977 | BO10: =SUM(BK10:BN10) -> 7998.265 | BP10: 2351.5 | BQ10: 2142.9 | BR10: 2180.2 | BS10: 2097.3 | BT10: =SUM(BP10:BS10) -> 8771.9 | BU10: 2176.2 | BV10: 1961.8 | BW10: 2013.8 | BX10: 2028.4 | BY10: =SUM(BU10:BX10) -> 8180.2 | BZ10: 2292.9 | CA10: 2128.9 | CB10: 2186.7 | CC10: 2355 | CD10: =SUM(BZ10:CC10) -> 8963.5 | CE10: 2451.3 | CF10: 2293.5 | CG10: 2417.3 | CH10: 2470.4 | CI10: =SUM(CE10:CH10) -> 9632.5 | CJ10: 2731.8 | CK10: 2521.2 | CL10: 2615.6 | CM10: 2665.9 | CN10: =SUM(CJ10:CM10) -> 10534.5 | CO10: 2989.6 | CP10: 2807.7 | CQ10: 2986.3 | CR10: 3009.6 | CS10: =SUM(CO10:CR10) -> 11793.2 | CT10: 3343.8 | CU10: 3068 | CV10: 3290.5 | CW10: 3275.7 | CX10: =SUM(CT10:CW10) -> 12978 | CY10: 3772.8 | CZ10: 3622.9 | DA10: 3915 | DB10: 3886.6 | DC10: =SUM(CY10:DB10) -> 15197.3 | DD10: 4210.6 | DE10: 3944.2 | DF10: 4181.6 | DG10: 4507.8 | DH10: =SUM(DD10:DG10) -> 16844.2 | DI10: 4469.3 | DJ10: 4195.4 | DK10: 4509 | DL10: 4477 | DM10: =SUM(DI10:DL10) -> 17650.7 | DN10: 4741.8 | DO10: 4804.0164 | DP10: 5143.8377 | DQ10: 5129.744 | DR10: =SUM(DN10:DQ10) -> 19819.398 | DS10: 5287.1458 | DT10: 5254.1083 | DU10: 5635.8366 | DV10: 5622.9826 | DW10: =SUM(DS10:DV10) -> 21800.073 | DX10: 5778.283 | DY10: 5753.3039 | DZ10: 6164.7196 | EA10: 6142.8339 | EB10: =SUM(DX10:EA10) -> 23839.14 | EL10: =AZ10+BA10+BB10+BD10 -> 8492.7 | EM10: =SUM(BE10:BG10,BI10) -> 10314.048 | EN10: =BB10+BC10+BD10+BF10 -> 5661.249 | EO10: =SUM(BG10:BI10,BK10) -> 6961.926 | EP10: =SUM(BL10:BN10,BP10) -> 8342.954 | EQ10: =SUM(BQ10:BS10,BU10) -> 8596.6 | ER10: =SUM(BV10:BX10,BZ10) -> 8296.9 | ES10: =SUM(CA10:CC10,CE10) -> 9121.9 | ET10: =SUM(CF10:CH10,CJ10) -> 9913 | EU10: =SUM(CK10,CL10,CM10,CO10) -> 10792.3 | EV10: =SUM(CT10,CR10,CQ10,CP10) -> 12147.4 | EW10: =CU10+CV10+CW10+CY10 -> 13407 | EX10: =CZ10+DA10+DB10+DD10 -> 15635.1 | EY10: =DE10+DF10+DG10+DI10 -> 17102.9 | EZ10: =DJ10+DK10+DL10+DN10 -> 17923.2 | FA10: =DO10+DP10+DQ10+DS10 -> 20364.744 | FB10: =DT10+DU10+DV10+DX10 -> 22291.21 | FD10: Company Store Sales | FE10: =DN10 -> 4741.8 | FF10: 4834.8299 | FG10: =FE10-FF10 -> -93.029924 | FH10: =DI10 -> 4469.3 | FI10: =FE10/FH10-1 -> 0.060971517
A11: Licensing | AL11: 72.976 | AM11: 73.823 | AN11: 79.39 | AO11: 85.743 | AP11: =SUM(AL11:AO11) -> 311.932 | AQ11: 98.972 | AR11: 92.269 | AS11: 104.34 | AT11: 113.97 | AU11: =SUM(AQ11:AT11) -> 409.551 | AV11: 133.499 | AW11: 122.517 | AX11: 145.021 | AY11: 164.761 | AZ11: =SUM(AV11:AY11) -> 565.798 | BA11: 157.213 | BB11: 161.292 | BC11: 170.33 | BD11: 184.18 | BE11: =SUM(BA11:BD11) -> 673.015 | BF11: 219.15 | BG11: 202.354 | BH11: 216.267 | BI11: 222.905 | BJ11: =SUM(BF11:BI11) -> 860.676 | BK11: 253.922 | BL11: 234.807 | BM11: 254.904 | BN11: 282.705 | BO11: =SUM(BK11:BN11) -> 1026.338 | BP11: 304.8 | BQ11: 274.4 | BR11: 281.3 | BS11: 311.1 | BT11: =SUM(BP11:BS11) -> 1171.6 | BU11: 334.3 | BV11: 282.8 | BW11: 301 | BX11: 304.2 | BY11: =SUM(BU11:BX11) -> 1222.3 | BZ11: 326.1 | CA11: 310.4 | CB11: 330.6 | CC11: 373.8 | CD11: =SUM(BZ11:CC11) -> 1340.9 | CE11: 378.8 | CF11: =CF13 -> 237.8 | EL11: =AZ11+BA11+BB11+BD11 -> 1068.483 | EM11: =SUM(BE11:BG11,BI11) -> 1317.424 | EN11: =BB11+BC11+BD11+BF11 -> 734.952 | EO11: =SUM(BG11:BI11,BK11) -> 895.448 | EP11: =SUM(BL11:BN11,BP11) -> 1077.216 | EQ11: =SUM(BQ11:BS11,BU11) -> 1201.1 | ER11: =SUM(BV11:BX11,BZ11) -> 1214.1 | ES11: =SUM(CA11:CC11,CE11) -> 1393.6 | ET11: =SUM(CF11:CH11,CJ11) -> 237.8 | EU11: =SUM(CK11,CL11,CM11,CO11) -> 0 | EV11: =SUM(CT11,CR11,CQ11,CP11) -> 0 | EW11: =CU11+CV11+CW11+CY11 -> 0 | EX11: =CZ11+DA11+DB11+DD11 -> 0 | EY11: =DE11+DF11+DG11+DI11 -> 0 | EZ11: =DJ11+DK11+DL11+DN11 -> 0 | FA11: =DO11+DP11+DQ11+DS11 -> 0 | FB11: =DT11+DU11+DV11+DX11 -> 0 | FE11: =DN11 -> 0 | FF11: 0 | FH11: =DI11 -> 0
A12: Food Service and Other | AL12: 50.094 | AM12: 45.132 | AN12: 43.934 | AO12: 44.912 | AP12: =SUM(AL12:AO12) -> 184.072 | AQ12: 55.068 | AR12: 52.62 | AS12: 54.682 | AT12: 53.977 | AU12: =SUM(AQ12:AT12) -> 216.347 | AV12: 67.197 | AW12: 68.07 | AX12: 65.615 | AY12: 70.189 | AZ12: =SUM(AV12:AY12) -> 271.071 | BA12: 73.67 | BB12: 73.477 | BC12: 74.864 | BD12: 82.347 | BE12: =SUM(BA12:BD12) -> 304.358 | BF12: 86.959 | BG12: 83.624 | BH12: 86.429 | BI12: 86.156 | BJ12: =SUM(BF12:BI12) -> 343.168 | BK12: 94.99 | BL12: 98.082 | BM12: 93.569 | BN12: 100.253 | BO12: =SUM(BK12:BN12) -> 386.894 | BP12: 111.3 | BQ12: 108.7 | BR12: 112.5 | BS12: 107 | BT12: =SUM(BP12:BS12) -> 439.5 | BU12: 104.7 | BV12: 88.7 | BW12: 89.1 | BX12: 89.6 | BY12: =SUM(BU12:BX12) -> 372.1 | BZ12: 103.7 | CA12: 95.4 | CB12: 94.7 | CC12: 109.2 | CD12: =SUM(BZ12:CC12) -> 403 | CE12: 120.7 | CF12: =CF14 -> 254.4 | EL12: =AZ12+BA12+BB12+BD12 -> 500.565 | EM12: =SUM(BE12:BG12,BI12) -> 561.097 | EN12: =BB12+BC12+BD12+BF12 -> 317.647 | EO12: =SUM(BG12:BI12,BK12) -> 351.199 | EP12: =SUM(BL12:BN12,BP12) -> 403.204 | EQ12: =SUM(BQ12:BS12,BU12) -> 432.9 | ER12: =SUM(BV12:BX12,BZ12) -> 371.1 | ES12: =SUM(CA12:CC12,CE12) -> 420 | ET12: =SUM(CF12:CH12,CJ12) -> 254.4 | EU12: =SUM(CK12,CL12,CM12,CO12) -> 0 | EV12: =SUM(CT12,CR12,CQ12,CP12) -> 0 | EW12: =CU12+CV12+CW12+CY12 -> 0 | EX12: =CZ12+DA12+DB12+DD12 -> 0 | EY12: =DE12+DF12+DG12+DI12 -> 0 | EZ12: =DJ12+DK12+DL12+DN12 -> 0 | FA12: =DO12+DP12+DQ12+DS12 -> 0 | FB12: =DT12+DU12+DV12+DX12 -> 0 | FE12: =DN12 -> 0 | FF12: 0 | FH12: =DI12 -> 0
A13: Licensed stores | BP13: 204.2 | BQ13: 178.1 | BR13: 190.5 | BS13: 206.2 | BT13: =SUM(BP13:BS13) -> 779 | BU13: 219.9 | BV13: 188 | BW13: 194.7 | BX13: 192.4 | BY13: =SUM(BU13:BX13) -> 795 | BZ13: 216.5 | CA13: 210.9 | CB13: 213.5 | CC13: 234.3 | CD13: =SUM(BZ13:CC13) -> 875.2 | CE13: 254.2 | CF13: 237.8 | CG13: 248.7 | CH13: 266.8 | CI13: =SUM(CE13:CH13) -> 1007.5 | CJ13: 306.6 | CK13: 290.3 | CL13: 308.2 | CM13: 305.3 | CN13: =SUM(CJ13:CM13) -> 1210.4 | CO13: 350.2 | CP13: 322.1 | CQ13: 342 | CR13: 346.3 | CS13: =SUM(CO13:CR13) -> 1360.6 | CT13: 401.8 | CU13: 356.2 | CV13: 408.1 | CW13: 422.6 | CX13: =SUM(CT13:CW13) -> 1588.7 | CY13: 483.9 | CZ13: 421.3 | DA13: 475.2 | DB13: 481.4 | DC13: =SUM(CY13:DB13) -> 1861.8 | DD13: 540.6 | DE13: 493.1 | DF13: 527.2 | DG13: 593.2 | DH13: =SUM(DD13:DG13) -> 2154.1 | DI13: 602.4 | DJ13: 546.7 | DK13: 588.3 | DL13: 617.6 | DM13: =SUM(DI13:DL13) -> 2355 | DN13: 682.4 | DO13: 579.99657 | DP13: 617.85616 | DQ13: 665.97631 | DR13: =SUM(DN13:DQ13) -> 2546.229 | DS13: 753.76952 | DT13: 657.82113 | DU13: 699.79354 | DV13: 753.0606 | DW13: =SUM(DS13:DV13) -> 2864.4448 | DX13: 850.99726 | DY13: 741.36197 | DZ13: 787.61404 | EA13: 846.09414 | EB13: =SUM(DX13:EA13) -> 3226.0674 | ET13: =SUM(CF13:CH13,CJ13) -> 1059.9 | EU13: =SUM(CK13,CL13,CM13,CO13) -> 1254 | EV13: =SUM(CT13,CR13,CQ13,CP13) -> 1412.2 | EW13: =CU13+CV13+CW13+CY13 -> 1670.8 | EX13: =CZ13+DA13+DB13+DD13 -> 1918.5 | EY13: =DE13+DF13+DG13+DI13 -> 2215.9 | EZ13: =DJ13+DK13+DL13+DN13 -> 2435 | FA13: =DO13+DP13+DQ13+DS13 -> 2617.5986 | FB13: =DT13+DU13+DV13+DX13 -> 2961.6725 | FD13: Licensed stores | FE13: =DN13 -> 682.4 | FF13: 680.32312 | FG13: =FE13-FF13 -> 2.0768775 | FH13: =DI13 -> 602.4 | FI13: =FE13/FH13-1 -> 0.13280212
A14: CPG, foodservice and other | BP14: 211.9 | BQ14: 205 | BR14: 203.2 | BS14: 212 | BT14: =SUM(BP14:BS14) -> 832.1 | BU14: 219.1 | BV14: 183.5 | BW14: 195.4 | BX14: 201.4 | BY14: =SUM(BU14:BX14) -> 799.4 | BZ14: 213.3 | CA14: 194.9 | CB14: 211.8 | CC14: 248.7 | CD14: =SUM(BZ14:CC14) -> 868.7 | CE14: 245.3 | CF14: 254.4 | CG14: 266.2 | CH14: 294.7 | CI14: =SUM(CE14:CH14) -> 1060.6 | CJ14: 391.6 | CK14: 378.7 | CL14: 374.4 | CM14: 387.3 | CN14: =SUM(CJ14:CM14) -> 1532 | CO14: 453.4 | CP14: 419.8 | CQ14: 407 | CR14: 432.9 | CS14: =SUM(CO14:CR14) -> 1713.1 | CT14: 494 | CU14: 449.6 | CV14: 455.1 | CW14: 482.5 | CX14: =SUM(CT14:CW14) -> 1881.2 | CY14: 546.5 | CZ14: 519.3 | DA14: 491 | DB14: 546.8 | DC14: =SUM(CY14:DB14) -> 2103.6 | DD14: 622.3 | DE14: 555.9 | DF14: 529.2 | DG14: 610.2 | DH14: =SUM(DD14:DG14) -> 2317.6 | DI14: 661.2 | DJ14: 551.9 | DK14: 564.2 | DL14: 603.7 | DM14: =SUM(DI14:DL14) -> 2381 | DN14: 649.5 | DO14: 566.825 | DP14: 571.988 | DQ14: 611.767 | DR14: =SUM(DN14:DQ14) -> 2400.08 | DS14: 695.21025 | DT14: 603.53343 | DU14: 609.3798 | DV14: 651.97585 | DW14: =SUM(DS14:DV14) -> 2560.0993 | DX14: 744.01481 | DY14: 642.82706 | DZ14: 650.5343 | EA14: 697.0373 | EB14: =SUM(DX14:EA14) -> 2734.4135 | ET14: =SUM(CF14:CH14,CJ14) -> 1206.9 | EU14: =SUM(CK14,CL14,CM14,CO14) -> 1593.8 | EV14: =SUM(CT14,CR14,CQ14,CP14) -> 1753.7 | EW14: =CU14+CV14+CW14+CY14 -> 1933.7 | EX14: =CZ14+DA14+DB14+DD14 -> 2179.4 | EY14: =DE14+DF14+DG14+DI14 -> 2356.5 | EZ14: =DJ14+DK14+DL14+DN14 -> 2369.3 | FA14: =DO14+DP14+DQ14+DS14 -> 2445.7902 | FB14: =DT14+DU14+DV14+DX14 -> 2608.9039 | FD14: CPG, foodservice and other | FE14: =DN14 -> 649.5 | FF14: 705.3975 | FG14: =FE14-FF14 -> -55.8975 | FH14: =DI14 -> 661.2 | FI14: =FE14/FH14-1 -> -0.0176951
A15: Specialty Sales | B15: 26.542 | C15: 11.54 | D15: 11.439 | E15: 12.376 | F15: 12.787 | G15: =SUM(C15:F15) -> 48.142 | H15: 16.616 | I15: 18.024 | J15: 19.855 | K15: 24.159 | L15: =SUM(H15:K15)+17.8 -> 96.454 | M15: 25.022 | N15: 25.498 | O15: 27.9 | P15: 39.441 | Q15: =SUM(M15:P15)+21.2 -> 139.061 | R15: 38.779 | S15: 37.787 | T15: 47 | U15: 66.783 | V15: 206.128 | W15: 62.85 | X15: 57.094 | Y15: 67.841 | Z15: 68.97 | AA15: =SUM(W15:Z15) -> 256.755 | AB15: =86.197+2.35 -> 88.547 | AC15: =75.667+1.97 -> 77.637 | AD15: =88.8+1.97 -> 90.77 | AE15: =94.918+2.106 -> 97.024 | AF15: =SUM(AB15:AE15) -> 353.978 | AG15: 104.98 | AH15: 106.011 | AI15: 103.849 | AJ15: 104.546 | AK15: =SUM(AG15:AJ15) -> 419.386 | AL15: =AL11+AL12 -> 123.07 | AM15: =AM11+AM12 -> 118.955 | AN15: =AN11+AN12 -> 123.324 | AO15: =AO11+AO12 -> 130.655 | AP15: =SUM(AL15:AO15) -> 496.004 | AQ15: =AQ11+AQ12 -> 154.04 | AR15: =AR11+AR12 -> 144.889 | AS15: =AS11+AS12 -> 159.022 | AT15: =AT11+AT12 -> 167.947 | AU15: =SUM(AQ15:AT15) -> 625.898 | AV15: =AV11+AV12 -> 200.696 | AW15: =AW11+AW12 -> 190.587 | AX15: =AX11+AX12 -> 210.636 | AY15: =AY11+AY12 -> 234.95 | AZ15: =AZ11+AZ12 -> 836.869 | BA15: =BA11+BA12 -> 230.883 | BB15: =BB11+BB12 -> 234.769 | BC15: =BC11+BC12 -> 245.194 | ... BO15: =BO11+BO12 -> 1413.232 | BP15: =BP13+BP14 -> 416.1 | BQ15: =BQ13+BQ14 -> 383.1 | BR15: =BR13+BR14 -> 393.7 | BS15: =BS13+BS14 -> 418.2 | BT15: =BT11+BT12 -> 1611.1 | BU15: =BU13+BU14 -> 439 | BV15: =BV13+BV14 -> 371.5 | BW15: =BW13+BW14 -> 390.1 | BX15: =BX13+BX14 -> 393.8 | BY15: =BY13+BY14 -> 1594.4 | BZ15: =BZ13+BZ14 -> 429.8 | CA15: =CA13+CA14 -> 405.8 | CB15: =CB13+CB14 -> 425.3 | ... CD15: =CD13+CD14 -> 1743.9 | CE15: =CE14+CE13 -> 499.5 | CF15: =CF14+CF13 -> 492.2 | CG15: =CG14+CG13 -> 514.9 | CH15: =CH14+CH13 -> 561.5 | CI15: =CI14+CI13 -> 2068.1 | CJ15: =CJ14+CJ13 -> 698.2 | CK15: =CK14+CK13 -> 669 | CL15: =CL14+CL13 -> 682.6 | CM15: =CM14+CM13 -> 692.6 | CN15: =SUM(CJ15:CM15) -> 2742.4 | CO15: =CO14+CO13 -> 803.6 | CP15: =CP14+CP13 -> 741.9 | CQ15: =CQ14+CQ13 -> 749 | CR15: =CR14+CR13 -> 779.2 | CS15: =CS14+CS13 -> 3073.7 | CT15: =CT14+CT13 -> 895.8 | CU15: =CU14+CU13 -> 805.8 | CV15: =CV14+CV13 -> 863.2 | ... EB15: =EB14+EB13 -> 5960.4809 | EL15: =AZ15+BA15+BB15+BD15 -> 1569.048 | EM15: =SUM(BE15:BG15,BI15) -> 1878.521 | EN15: =BB15+BC15+BD15+BF15 -> 1052.599 | EO15: =SUM(BG15:BI15,BK15) -> 1246.647 | EP15: =SUM(BL15:BN15,BP15) -> 1480.42 | EQ15: =SUM(BQ15:BS15,BU15) -> 1634 | ER15: =SUM(BV15:BX15,BZ15) -> 1585.2 | ES15: =SUM(CA15:CC15,CE15) -> 1813.6 | ET15: =SUM(CF15:CH15,CJ15) -> 2266.8 | EU15: =SUM(CK15,CL15,CM15,CO15) -> 2847.8 | EV15: =SUM(CT15,CR15,CQ15,CP15) -> 3165.9 | EW15: =CU15+CV15+CW15+CY15 -> 3604.5 | EX15: =CZ15+DA15+DB15+DD15 -> 4097.9 | EY15: =DE15+DF15+DG15+DI15 -> 4572.4 | EZ15: =DJ15+DK15+DL15+DN15 -> 4804.3 | FA15: =DO15+DP15+DQ15+DS15 -> 5063.3888 | FB15: =DT15+DU15+DV15+DX15 -> 5570.5764 | FD15: Specialty Sales | FE15: =DN15 -> 1331.9 | FF15: 1385.7206 | FG15: =FE15-FF15 -> -53.820623 | FH15: =DI15 -> 1263.6 | FI15: =FE15/FH15-1 -> 0.054051915
A16: Mail Order (2) | B16: 9.886 | C16: 5.892 | D16: 2.78 | E16: 3.079 | F16: 2.664 | G16: =SUM(C16:F16) -> 14.415 | H16: 7.189 | I16: 3.284 | J16: 3.883 | K16: 3.402 | L16: =SUM(H16:K16) -> 17.758 | M16: 8.782 | N16: 4.356 | O16: 4.297 | P16: 3.802 | Q16: =SUM(M16:P16) -> 21.237 | R16: 7.573 | S16: 4.019 | T16: 3.959 | U16: 0 | V16: =SUM(R16:U16) -> 15.551 | FE16: =DN16 -> 0 | FF16: 0 | FH16: =DI16 -> 0
A17: Net Sales | B17: 284.923 | C17: =SUM(C10:C16) -> 115.545 | D17: =SUM(D10:D16) -> 101.113 | E17: =SUM(E10:E16) -> 119.174 | F17: =SUM(F10:F16) -> 129.38 | G17: =SUM(G10:G16) -> 465.212 | H17: =SUM(H10:H16) -> 169.537 | I17: =SUM(I10:I16) -> 153.609 | J17: =SUM(J10:J16) -> 176.95 | K17: =SUM(K10:K16) -> 196.385 | L17: =SUM(L10:L15) -> 696.523 | M17: =SUM(M10:M16) -> 240.154 | N17: =SUM(N10:N16) -> 216.27 | O17: =SUM(O10:O16) -> 244.241 | P17: =SUM(P10:P16) -> 274.725 | Q17: =SUM(Q10:Q15) -> 975.353 | R17: =SUM(R10:R16) -> 321.325 | S17: =SUM(S10:S16) -> 295.243 | T17: =SUM(T10:T16) -> 334.429 | U17: =SUM(U10:U16) -> 357.705 | V17: =SUM(V10:V15) -> 1308.702 | W17: =SUM(W10:W16) -> 405.638 | X17: =SUM(X10:X16) -> 375.822 | Y17: =SUM(Y10:Y16) -> 423.792 | Z17: =SUM(Z10:Z16) -> 474.87 | AA17: =SUM(W17:Z17) -> 1680.122 | AB17: =SUM(AB10:AB16) -> 529.332 | AC17: =SUM(AC10:AC16) -> 506.668 | AD17: =SUM(AD10:AD16) -> 557.47 | AE17: =SUM(AE10:AE16) -> 584.098 | AF17: =SUM(AB17:AE17) -> 2177.568 | AG17: =SUM(AG10:AG16) -> 667.387 | AH17: =SUM(AH10:AH16) -> 629.288 | AI17: =SUM(AI10:AI16) -> 662.769 | AJ17: =SUM(AJ10:AJ16) -> 689.536 | AK17: =SUM(AG17:AJ17) -> 2648.98 | AL17: =AL10+AL15 -> 805.335 | AM17: =AM10+AM15 -> 783.217 | AN17: =AN10+AN15 -> 835.158 | AO17: =AO10+AO15 -> 865.198 | AP17: =SUM(AL17:AO17) -> 3288.908 | AQ17: =AQ10+AQ15 -> 1003.526 | AR17: =AR10+AR15 -> 954.206 | AS17: =AS10+AS15 -> 1036.776 | AT17: =AT10+AT15 -> 1081.013 | AU17: =SUM(AQ17:AT17) -> 4075.521 | AV17: =AV10+AV15 -> 1281.191 | AW17: =AW10+AW15 -> 1241.068 | AX17: =AX10+AX15 -> 1318.691 | AY17: =AY10+AY15 -> 1453.297 | AZ17: =SUM(AV17:AY17) -> 5294.247 | BA17: =BA10+BA15 -> 1589.544 | BB17: =BB10+BB15 -> 1518.716 | BC17: =BC10+BC15 -> 1601.799 | BD17: =BD10+BD15 -> 1659.241 | BE17: =BE10+BE15 -> 6369.3 | BF17: =BF10+BF15 -> 1934.092 | BG17: =BG10+BG15 -> 1885.822 | BH17: =BH10+BH15 -> 1963.673 | ... EB17: =EB10+EB15 -> 29799.621 | EG17: =S17+T17+U17+W17 -> 1393.015 | EH17: =X17+Y17+Z17+AB17 -> 1803.816 | EI17: =AC17+AD17+AE17+AG17 -> 2315.623 | EJ17: =AH17+AI17+AJ17+AL17 -> 2786.928 | EK17: =AM17+AN17+AO17+AQ17 -> 3487.099 | EL17: =AR17+AS17+AT17+AV17 -> 4353.186 | EM17: =AW17+AX17+AY17+BA17 -> 5602.6 | EN17: =BB17+BC17+BD17+BF17 -> 6713.848 | EO17: =SUM(BG17:BI17,BK17) -> 8208.573 | EP17: =SUM(BL17:BN17,BP17) -> 9823.374 | EQ17: =SUM(BQ17:BS17,BU17) -> 10230.6 | ER17: =SUM(BV17:BX17,BZ17) -> 9882.1 | ES17: =SUM(CA17:CC17,CE17) -> 10935.5 | ET17: =SUM(CF17:CH17,CJ17) -> 12179.8 | EU17: =SUM(CK17,CL17,CM17,CO17) -> 13640.1 | EV17: =SUM(CT17,CR17,CQ17,CP17) -> 15313.3 | EW17: =CU17+CV17+CW17+CY17 -> 17011.5 | EX17: =CZ17+DA17+DB17+DD17 -> 19733 | EY17: =DE17+DF17+DG17+DI17 -> 21675.3 | EZ17: =DJ17+DK17+DL17+DN17 -> 22727.5 | FA17: =DO17+DP17+DQ17+DS17 -> 25428.133 | FB17: =DT17+DU17+DV17+DX17 -> 27861.787 | FD17: Net Sales | FE17: =DN17 -> 6073.7 | FF17: 6220.5505 | FG17: =FE17-FF17 -> -146.85055 | FH17: =DI17 -> 5732.9 | FI17: =FE17/FH17-1 -> 0.059446354
A19: Cost of sales | BP19: 910.5 | BQ19: 819.6 | BR19: 860.7 | BS19: 878.3 | BT19: 3469.2 | BU19: 915.3 | BV19: 772.7 | BW19: 766.5 | BX19: 754 | BY19: 3208.5 | BZ19: 859.5 | CA19: 788.4 | CB19: 796.8 | CC19: 881.1 | CD19: 3325.8 | CH19: 169.3 | CI19: 595.5 | EQ19: =SUM(BQ19:BS19,BU19) -> 3473.9 | ER19: =SUM(BV19:BX19,BZ19) -> 3152.7 | ES19: =SUM(CA19:CC19,CE19) -> 2466.3 | ET19: =SUM(CF19:CH19,CJ19) -> 169.3 | EU19: =SUM(CK19,CL19,CM19,CO19) -> 0 | EV19: =SUM(CT19,CR19,CQ19,CP19) -> 0 | EW19: =CU19+CV19+CW19+CY19 -> 0 | EX19: =CZ19+DA19+DB19+DD19 -> 0 | EY19: =DE19+DF19+DG19+DI19 -> 0 | EZ19: =DJ19+DK19+DL19+DN19 -> 0 | FA19: =DO19+DP19+DQ19+DS19 -> 0 | FB19: =DT19+DU19+DN19+DP19 -> 0 | FH19: =CP19 -> 0
A20: Occupancy costs | BP20: 275.5 | BQ20: 287.1 | BR20: 302.4 | BS20: 311 | BT20: 1176.1 | BU20: 281.6 | BV20: 270.7 | BW20: 276.9 | BX20: 287.2 | BY20: 1116.4 | BZ20: 286.1 | CA20: 275.7 | CB20: 279.2 | CC20: 291.5 | CD20: 1132.5 | CH20: 0 | CI20: 0 | FH20: =CP20 -> 0
A21: Cost of Sales and Related Occupancy Costs | B21: 130.324 | C21: 51.983 | D21: 45.639 | E21: 53.723 | F21: 59.935 | G21: =SUM(C21:F21) -> 211.28 | H21: 86.663 | I21: 76.938 | J21: 83.164 | K21: 89.181 | L21: =SUM(H21:K21) -> 335.946 | M21: 116.101 | N21: =216.071-M21 -> 99.97 | O21: =319.906-N21-M21 -> 103.835 | P21: =436.942-O21-N21-M21 -> 117.036 | Q21: =SUM(M21:P21) -> 436.942 | R21: 146.235 | S21: 133.501 | T21: 143.313 | U21: 153.666 | V21: =SUM(R21:U21) -> 576.715 | W21: 186.3 | X21: 169.957 | Y21: 185.02 | Z21: 199.734 | AA21: =SUM(W21:Z21) -> 741.011 | AB21: 240.714 | AC21: 225.24 | AD21: 243.066 | AE21: 252.865 | AF21: =SUM(AB21:AE21) -> 961.885 | AG21: 292.22 | AH21: 271.178 | AI21: 271.35 | AJ21: 278.037 | AK21: =SUM(AG21:AJ21) -> 1112.785 | AL21: 337.029 | AM21: 320.081 | AN21: 337.401 | AO21: 355.5 | AP21: =SUM(AL21:AO21) -> 1350.011 | AQ21: 419.161 | AR21: 392.098 | AS21: 425.709 | AT21: 448.96 | AU21: =SUM(AQ21:AT21) -> 1685.928 | AV21: 528.709 | AW21: 508.268 | AX21: 540.175 | AY21: 614.288 | AZ21: =SUM(AV21:AY21) -> 2191.44 | BA21: 647.755 | BB21: 628.74 | BC21: 649.831 | BD21: 678.886 | BE21: =SUM(BA21:BD21) -> 2605.212 | BF21: 778.038 | BG21: 760.873 | BH21: 804.889 | BI21: 834.991 | BJ21: =SUM(BF21:BI21) -> 3178.791 | BK21: 984.823 | BL21: 944.746 | BM21: 1003.881 | BN21: 1065.674 | BO21: =SUM(BK21:BN21) -> 3999.124 | BP21: 1186 | BQ21: 1106.7 | BR21: 1163.1 | BS21: 1189.5 | BT21: =SUM(BP21:BS21) -> 4645.3 | BU21: 1196.8 | BV21: 1043.5 | BW21: 1043.4 | BX21: 1041.2 | BY21: =SUM(BU21:BX21) -> 4324.9 | BZ21: 1145.7 | CA21: 1064.1 | CB21: 1076.2 | CC21: 1172.6 | CD21: =SUM(BZ21:CC21) -> 4458.6 | CE21: 1192.3 | CF21: 1171.2 | CG21: 1237.5 | CH21: 1314.5 | CI21: =SUM(CE21:CH21) -> 4915.5 | CJ21: 1496.1 | CK21: 1411.9 | CL21: 1446.1 | CM21: 1459.2 | CN21: =SUM(CJ21:CM21) -> 5813.3 | CO21: 1620.7 | CP21: 1530.4 | CQ21: 1597.6 | CR21: 1633.7 | CS21: =SUM(CO21:CR21) -> 6382.4 | CT21: 1795.1 | CU21: 1629.2 | CV21: 1711.5 | CW21: 1723.2 | CX21: =SUM(CT21:CW21) -> 6859 | CY21: 1991.2 | CZ21: 1859.8 | DA21: 1953.9 | DB21: 1982.6 | DC21: =SUM(CY21:DB21) -> 7787.5 | DD21: 2186.2 | DE21: 2010.3 | DF21: 2060.3 | DG21: 2254.2 | DH21: =SUM(DD21:DG21) -> 8511 | DI21: 2295 | DJ21: 2141.2 | DK21: 2249.1 | DL21: 2352.9 | DM21: =SUM(DI21:DL21) -> 9038.2 | DN21: 2502.9 | DO21: 2454.3139 | DP21: 2561.7893 | DQ21: 2607.6475 | DR21: =SUM(DN21:DQ21) -> 10126.651 | DS21: 2747.1685 | DT21: 2649.7999 | DU21: 2771.8859 | DV21: 2826.0405 | DW21: =SUM(DS21:DV21) -> 10994.895 | DX21: 2981.4779 | DY21: 2878.0754 | DZ21: 3008.3822 | EA21: 3064.8763 | EB21: =SUM(DX21:EA21) -> 11932.812 | EG21: =S21+T21+U21+W21 -> 616.78 | EH21: =X21+Y21+Z21+AB21 -> 795.425 | EI21: =AC21+AD21+AE21+AG21 -> 1013.391 | EJ21: =AH21+AI21+AJ21+AL21 -> 1157.594 | EK21: =AM21+AN21+AO21+AQ21 -> 1432.143 | EL21: =AR21+AS21+AT21+AV21 -> 1795.476 | EM21: =AW21+AX21+AY21+BA21 -> 2310.486 | EN21: =BB21+BC21+BD21+BF21 -> 2735.495 | EO21: =SUM(BG21:BI21,BK21) -> 3385.576 | EP21: =SUM(BL21:BN21,BP21) -> 4200.301 | EQ21: =SUM(BQ21:BS21,BU21) -> 4656.1 | ER21: =SUM(BV21:BX21,BZ21) -> 4273.8 | ES21: =SUM(CA21:CC21,CE21) -> 4505.2 | ET21: =SUM(CF21:CH21,CJ21) -> 5219.3 | EU21: =SUM(CK21,CL21,CM21,CO21) -> 5937.9 | EV21: =SUM(CT21,CR21,CQ21,CP21) -> 6556.8 | EW21: =CU21+CV21+CW21+CY21 -> 7055.1 | EX21: =CZ21+DA21+DB21+DD21 -> 7982.5 | EY21: =DE21+DF21+DG21+DI21 -> 8619.8 | EZ21: =DJ21+DK21+DL21+DN21 -> 9246.1 | FA21: =DO21+DP21+DQ21+DS21 -> 10370.919 | FB21: =DT21+DU21+DV21+DX21 -> 11229.204 | FD21: Cost of Sales and Related Occupancy Costs | FE21: =DN21 -> 2502.9 | FF21: 2476.039 | FG21: =FE21-FF21 -> 26.860957 | FH21: =DI21 -> 2295 | FI21: =FE21/FH21-1 -> 0.090588235
A22: Store Operating Expenses | B22: 90.094 | C22: 35.461 | D22: 33.882 | E22: 39.304 | F22: 40.109 | G22: =SUM(C22:F22) -> 148.756 | H22: 47.1 | I22: 47 | J22: 54.8 | K22: 61.7 | L22: =SUM(H22:K22) -> 210.6 | M22: 71.016 | N22: 70.057 | O22: 82.664 | P22: 90.327 | Q22: =SUM(M22:P22) -> 314.064 | R22: 98.101 | S22: 95.026 | T22: 106.869 | U22: 113.617 | V22: =SUM(R22:U22) -> 413.613 | W22: 122.601 | X22: 121.845 | Y22: 137.625 | Z22: 161.498 | AA22: =SUM(W22:Z22) -> 543.569 | AB22: 164.2 | AC22: 169.257 | AD22: 185.515 | AE22: 185.927 | AF22: =SUM(AB22:AE22) -> 704.899 | AG22: 209.69 | AH22: 208.608 | AI22: 226.614 | AJ22: 230.561 | AK22: 867.957 | AL22: 260.49 | AM22: 270.986 | AN22: 291.445 | AO22: 298.187 | AP22: 1109.782 | AQ22: 320.287 | AR22: 329.153 | AS22: 361.835 | AT22: 373.663 | AU22: 1379.574 | AV22: 405.821 | AW22: 425.976 | AX22: 448.029 | AY22: 510.342 | AZ22: =SUM(AV22:AY22) -> 1790.168 | BA22: 521.006 | BB22: 532.944 | BC22: 546.008 | BD22: 565.953 | BE22: =SUM(BA22:BD22) -> 2165.911 | BF22: 622.166 | BG22: 665.273 | BH22: 686.602 | BI22: 713.774 | BJ22: =SUM(BF22:BI22) -> 2687.815 | BK22: 771.967 | BL22: 780.985 | BM22: 819.212 | BN22: 843.725 | BO22: =SUM(BK22:BN22) -> 3215.889 | BP22: 927.3 | BQ22: 927.14 | BR22: 958.3 | BS22: 932.4 | BT22: =SUM(BP22:BS22) -> 3745.14 | BU22: =936.6 -> 936.6 | BV22: 819.6 | BW22: 821.4 | BX22: 847.5 | BY22: =SUM(BU22:BX22) -> 3425.1 | BZ22: 896.1 | CA22: 828 | CB22: 888.9 | CC22: 938.4 | CD22: =SUM(BZ22:CC22) -> 3551.4 | CE22: 888 | CF22: 867.2 | CG22: 917.1 | CH22: 922.9 | CI22: =SUM(CE22:CH22) -> 3595.2 | CJ22: 995.7 | CK22: 956.5 | CL22: 976 | CM22: 989.9 | CN22: =SUM(CJ22:CM22) -> 3918.1 | CO22: 1089.5 | CP22: 1038.4 | CQ22: 1084.1 | CR22: 1073.9 | CS22: =SUM(CO22:CR22) -> 4285.9 | CT22: 1175.1 | CU22: 1134.5 | CV22: 1176.5 | CW22: 1152.1 | CX22: =SUM(CT22:CW22) -> 4638.2 | CY22: 1315.5 | CZ22: 1324.6 | DA22: 1392.4 | DB22: 1378.6 | DC22: =SUM(CY22:DB22) -> 5411.1 | DD22: 1506.2 | DE22: 1466.4 | DF22: 1529.4 | DG22: 1562.3 | DH22: =SUM(DD22:DG22) -> 6064.3 | DI22: 1638.2 | DJ22: 1586.4 | DK22: 1628.9 | DL22: 1639.8 | DM22: =SUM(DI22:DL22) -> 6493.3 | DN22: 1737 | DO22: 1797.7155 | DP22: 1851.537 | DQ22: 1880.2069 | DR22: =SUM(DN22:DQ22) -> 7266.4594 | DS22: 1942.8655 | DT22: 1959.8978 | DU22: 2026.602 | DV22: 2058.1218 | DW22: =SUM(DS22:DV22) -> 7987.4871 | DX22: 2118.931 | DY22: 2137.2304 | DZ22: 2207.0311 | EA22: 2239.1097 | EB22: =SUM(DX22:EA22) -> 8702.3021 | EG22: =S22+T22+U22+W22 -> 438.113 | EH22: =X22+Y22+Z22+AB22 -> 585.168 | EI22: =AC22+AD22+AE22+AG22 -> 750.389 | EJ22: =AH22+AI22+AJ22+AL22 -> 926.273 | EK22: =AM22+AN22+AO22+AQ22 -> 1180.905 | EL22: =AR22+AS22+AT22+AV22 -> 1470.472 | EM22: =AW22+AX22+AY22+BA22 -> 1905.353 | EN22: =BB22+BC22+BD22+BF22 -> 2267.071 | EO22: =SUM(BG22:BI22,BK22) -> 2837.616 | EP22: =SUM(BL22:BN22,BP22) -> 3371.222 | EQ22: =SUM(BQ22:BS22,BU22) -> 3754.44 | ER22: =SUM(BV22:BX22,BZ22) -> 3384.6 | ES22: =SUM(CA22:CC22,CE22) -> 3543.3 | ET22: =SUM(CF22:CH22,CJ22) -> 3702.9 | EU22: =SUM(CK22,CL22,CM22,CO22) -> 4011.9 | EV22: =SUM(CT22,CR22,CQ22,CP22) -> 4371.5 | EW22: =CU22+CV22+CW22+CY22 -> 4778.6 | EX22: =CZ22+DA22+DB22+DD22 -> 5601.8 | EY22: =DE22+DF22+DG22+DI22 -> 6196.3 | EZ22: =DJ22+DK22+DL22+DN22 -> 6592.1 | FA22: =DO22+DP22+DQ22+DS22 -> 7472.3249 | FB22: =DT22+DU22+DV22+DX22 -> 8163.5525 | FD22: Store Operating Expenses | FE22: =DN22 -> 1737 | FF22: 1796.1314 | FG22: =FE22-FF22 -> -59.131385 | FH22: =DI22 -> 1638.2 | FI22: =FE22/FH22-1 -> 0.060310096
A23: Other Op. Expenses | B23: 8.696 | C23: 3.726 | D23: 2.875 | E23: =9.433-E24 -> 3.515 | F23: 3.817 | G23: =SUM(C23:F23) -> 13.933 | H23: 5.8 | I23: 3.8 | J23: 4.9 | K23: 5.3 | L23: =SUM(H23:K23) -> 19.8 | M23: 7.779 | N23: 6.931 | O23: 7.159 | P23: 6.37 | Q23: =SUM(M23:P23) -> 28.239 | R23: 9.674 | S23: 8.634 | T23: 12.221 | U23: 12.952 | V23: =SUM(R23:U23) -> 43.481 | W23: =13.308+W27 -> 13.028 | X23: =11.142+X27 -> 11.087 | Y23: =13.04+Y27 -> 13.4 | Z23: =13.883+Z27 -> 17.049 | AA23: =SUM(W23:Z23) -> 54.564 | AB23: 17.745 | AC23: 20.202 | AD23: 17.659 | AE23: 22.829 | AF23: =SUM(AB23:AE23) -> 78.435 | AG23: 21.786 | AH23: 23.785 | AI23: 22.695 | AJ23: 25.06 | AK23: 72.406 | AL23: 30.325 | AM23: 33.543 | AN23: 29.269 | AO23: 34.041 | AP23: 106.084 | AQ23: 31.516 | AR23: 36.521 | AS23: 41.946 | AT23: 43.658 | AU23: 141.346 | AV23: 43.698 | AW23: 40.802 | AX23: 44.259 | AY23: 42.889 | AZ23: =SUM(AV23:AY23) -> 171.648 | BA23: 44.281 | BB23: 46.347 | BC23: 48.464 | BD23: 57.932 | BE23: =SUM(BA23:BD23) -> 197.024 | BF23: 59.148 | BG23: 63.648 | BH23: 69.478 | BI23: 67.813 | BJ23: =SUM(BF23:BI23) -> 260.087 | BK23: 72.538 | BL23: 75.661 | BM23: 76.507 | BN23: 74.51 | BO23: =SUM(BK23:BN23) -> 299.216 | BP23: 85.7 | BQ23: 82.8 | BR23: 79.6 | BS23: 82 | BT23: =SUM(BP23:BS23) -> 330.1 | BU23: 72.6 | BV23: 64 | BW23: 69.2 | BX23: 58.6 | BY23: =SUM(BU23:BX23) -> 264.4 | BZ23: 71.9 | CA23: 61.8 | CB23: 77.2 | CC23: 82.3 | CD23: =SUM(BZ23:CC23) -> 293.2 | CE23: 90.1 | CF23: 98.9 | CG23: 100 | CH23: 103.7 | CI23: =SUM(CE23:CH23) -> 392.7 | CJ23: 100.8 | CK23: 99.6 | CL23: 100.5 | CM23: 106.2 | CN23: =SUM(CJ23:CM23) -> 407.1 | CO23: 126.1 | CP23: 105.8 | CQ23: 98.9 | CR23: 101.1 | CS23: =SUM(CO23:CR23) -> 431.9 | CT23: 114.9 | CU23: 110.9 | CV23: 120.6 | CW23: 111 | CX23: =SUM(CT23:CW23) -> 457.4 | CY23: 129.4 | CZ23: 133.5 | DA23: 131.6 | DB23: 127.9 | DC23: =SUM(CY23:DB23) -> 522.4 | DD23: 146.2 | DE23: 139.6 | DF23: 137.5 | DG23: 122.1 | DH23: =SUM(DD23:DG23) -> 545.4 | DI23: 145.4 | DJ23: 134.7 | DK23: 142.5 | DL23: 131.1 | DM23: =SUM(DI23:DL23) -> 553.7 | DN23: 141.6 | DO23: 146.19318 | DP23: 148.07814 | DQ23: 136.50251 | DR23: =SUM(DN23:DQ23) -> 572.37383 | DS23: 148.16902 | DT23: 150.34351 | DU23: 155.39241 | DV23: 144.27414 | DW23: =SUM(DS23:DV23) -> 598.17908 | DX23: 161.84502 | DY23: 158.82909 | DZ23: 164.11428 | EA23: 152.43131 | EB23: =SUM(DX23:EA23) -> 637.2197 | EG23: =S23+T23+U23+W23 -> 46.835 | EH23: =X23+Y23+Z23+AB23 -> 59.281 | EI23: =AC23+AD23+AE23+AG23 -> 82.476 | EJ23: =AH23+AI23+AJ23+AL23 -> 101.865 | EK23: =AM23+AN23+AO23+AQ23 -> 128.369 | EL23: =AR23+AS23+AT23+AV23 -> 165.823 | EM23: =AW23+AX23+AY23+BA23 -> 172.231 | EN23: =BB23+BC23+BD23+BF23 -> 211.891 | EO23: =SUM(BG23:BI23,BK23) -> 273.477 | EP23: =SUM(BL23:BN23,BP23) -> 312.378 | EQ23: =SUM(BQ23:BS23,BU23) -> 317 | ER23: =SUM(BV23:BX23,BZ23) -> 263.7 | ES23: =SUM(CA23:CC23,CE23) -> 311.4 | ET23: =SUM(CF23:CH23,CJ23) -> 403.4 | EU23: =SUM(CK23,CL23,CM23,CO23) -> 432.4 | EV23: =SUM(CT23,CR23,CQ23,CP23) -> 420.7 | EW23: =CU23+CV23+CW23+CY23 -> 471.9 | EX23: =CZ23+DA23+DB23+DD23 -> 539.2 | EY23: =DE23+DF23+DG23+DI23 -> 544.6 | EZ23: =DJ23+DK23+DL23+DN23 -> 549.9 | FA23: =DO23+DP23+DQ23+DS23 -> 578.94285 | FB23: =DT23+DU23+DV23+DX23 -> 611.85508 | FD23: Other Op. Expenses | FE23: =DN23 -> 141.6 | FF23: 153.44303 | FG23: =FE23-FF23 -> -11.84303 | FH23: =DI23 -> 145.4 | FI23: =FE23/FH23-1 -> -0.026134801
A24: Depreciation & Amortization | B24: 12.535 | C24: 4.464 | D24: 5.152 | E24: =22.486-D24-C24-F24 -> 5.918 | F24: 6.952 | G24: =SUM(C24:F24) -> 22.486 | H24: 7.6 | I24: 8.6 | J24: 9.5 | K24: 10.3 | L24: 35.9 | M24: 11.576 | N24: 12.494 | O24: 13.829 | P24: 14.902 | Q24: =SUM(M24:P24) -> 52.801 | R24: 16.051 | S24: 17.435 | T24: 18.928 | U24: 20.127 | V24: =SUM(R24:U24) -> 72.541 | W24: 21.893 | X24: 23.74 | Y24: 25.214 | Z24: 26.9 | AA24: =SUM(W24:Z24) -> 97.747 | AB24: 29.29 | AC24: 31.951 | AD24: 33.26 | AE24: 35.731 | AF24: =SUM(AB24:AE24) -> 130.232 | AG24: 37.562 | AH24: 38.597 | AI24: 41.884 | AJ24: 45.458 | AK24: 163.501 | AL24: 50.301 | AM24: 49.972 | AN24: 50.873 | AO24: 54.411 | AP24: 205.557 | AQ24: 57.385 | AR24: 57.961 | AS24: 59.764 | AT24: 62.697 | AU24: 237.807 | AV24: 67.929 | AW24: 74.225 | AX24: 72.886 | AY24: 74.142 | AZ24: =SUM(AV24:AY24) -> 289.182 | BA24: 78.559 | BB24: 87.772 | BC24: 85.363 | BD24: 88.475 | BE24: =SUM(BA24:BD24) -> 340.169 | BF24: 91.288 | BG24: 94.508 | BH24: 98.539 | BI24: 102.876 | BJ24: =SUM(BF24:BI24) -> 387.211 | BK24: 110.196 | BL24: 113.385 | BM24: 119.409 | BN24: 124.17 | BO24: =SUM(BK24:BN24) -> 467.16 | BP24: 133.2 | BQ24: 138.1 | BR24: 139.8 | BS24: 138.2 | BT24: =SUM(BP24:BS24) -> 549.3 | BU24: 134.3 | BV24: 134.1 | BW24: 133.7 | BX24: 132.6 | BY24: =SUM(BU24:BX24) -> 534.7 | BZ24: 130.6 | CA24: 128.5 | CB24: 125.2 | CC24: 126.1 | CD24: =SUM(BZ24:CC24) -> 510.4 | CE24: 127.8 | CF24: 129 | CG24: 129.5 | CH24: 137.1 | CI24: =SUM(CE24:CH24) -> 523.4 | CJ24: 134.8 | CK24: 137.1 | CL24: 136.7 | CM24: 141.7 | CN24: =SUM(CJ24:CM24) -> 550.3 | CO24: 148.9 | CP24: 153.1 | CQ24: 153.3 | CR24: 166.1 | CS24: =SUM(CO24:CR24) -> 621.4 | CT24: 169.7 | CU24: 174.4 | CV24: 180.1 | CW24: 185.4 | CX24: =SUM(CT24:CW24) -> 709.6 | CY24: 206 | CZ24: 217.1 | DA24: 236.5 | DB24: 234.3 | DC24: =SUM(CY24:DB24) -> 893.9 | DD24: 235.5 | DE24: 247.8 | DF24: 247.6 | DG24: 249.9 | DH24: =SUM(DD24:DG24) -> 980.8 | DI24: 249.7 | DJ24: 253.6 | DK24: 252.6 | DL24: 255.4 | DM24: =SUM(DI24:DL24) -> 1011.3 | DN24: 258.8 | DO24: 286.77687 | DP24: 285.37228 | DQ24: 285.95236 | DR24: =SUM(DN24:DQ24) -> 1116.9015 | DS24: 289.85017 | DT24: 301.88127 | DU24: 300.30162 | DV24: 302.28179 | DW24: =SUM(DS24:DV24) -> 1194.3148 | DX24: 310.58494 | DY24: 325.29515 | DZ24: 323.51993 | EA24: 325.71797 | EB24: =SUM(DX24:EA24) -> 1285.118 | EG24: =S24+T24+U24+W24 -> 78.383 | EH24: =X24+Y24+Z24+AB24 -> 105.144 | EI24: =AC24+AD24+AE24+AG24 -> 138.504 | EJ24: =AH24+AI24+AJ24+AL24 -> 176.24 | EK24: =AM24+AN24+AO24+AQ24 -> 212.641 | EL24: =AR24+AS24+AT24+AV24 -> 248.351 | EM24: =AW24+AX24+AY24+BA24 -> 299.812 | EN24: =BB24+BC24+BD24+BF24 -> 352.898 | EO24: =SUM(BG24:BI24,BK24) -> 406.119 | EP24: =SUM(BL24:BN24,BP24) -> 490.164 | EQ24: =SUM(BQ24:BS24,BU24) -> 550.4 | ER24: =SUM(BV24:BX24,BZ24) -> 531 | ES24: =SUM(CA24:CC24,CE24) -> 507.6 | ET24: =SUM(CF24:CH24,CJ24) -> 530.4 | EU24: =SUM(CK24,CL24,CM24,CO24) -> 564.4 | EV24: =SUM(CT24,CR24,CQ24,CP24) -> 642.2 | EW24: =CU24+CV24+CW24+CY24 -> 745.9 | EX24: =CZ24+DA24+DB24+DD24 -> 923.4 | EY24: =DE24+DF24+DG24+DI24 -> 995 | EZ24: =DJ24+DK24+DL24+DN24 -> 1020.4 | FA24: =DO24+DP24+DQ24+DS24 -> 1147.9517 | FB24: =DT24+DU24+DV24+DX24 -> 1215.0496 | FD24: Depreciation & Amortization | FE24: =DN24 -> 258.8 | FF24: 264.28621 | FG24: =FE24-FF24 -> -5.4862067 | FH24: =DI24 -> 249.7 | FI24: =FE24/FH24-1 -> 0.036443732
A25: General & Admin. Expense | B25: 19.973 | C25: 5.747 | D25: 6.489 | E25: 6.407 | F25: 9.999 | G25: =SUM(C25:F25) -> 28.642 | H25: 6.6 | I25: 9.7 | J25: 10 | K25: 10.9 | L25: 37.3 | M25: 12.92 | N25: 13.236 | O25: 14.186 | P25: 16.801 | Q25: =SUM(M25:P25) -> 57.143 | R25: 17.783 | S25: 19.307 | T25: 20.588 | U25: 19.897 | V25: =SUM(R25:U25) -> 77.575 | W25: 20.359 | X25: 22.371 | Y25: 24.679 | Z25: 22.276 | AA25: =SUM(W25:Z25) -> 89.685 | AB25: 26.145 | AC25: 28.622 | AD25: 28.049 | AE25: 27.385 | AF25: =SUM(AB25:AE25) -> 110.201 | AG25: 34.877 | AH25: 42.433 | AI25: 35.651 | AJ25: 38.455 | AK25: 179.852 | AL25: 41.129 | AM25: =67.314-18 -> 49.314 | AN25: 46.997 | AO25: 46.721 | AP25: 234.581 | AQ25: 60.943 | AR25: 59.552 | AS25: 49.325 | AT25: 57.071 | AU25: 244.55 | AV25: 70.417 | AW25: 79.982 | AX25: 73.357 | AY25: 80.537 | AZ25: =SUM(AV25:AY25) -> 304.293 | BA25: 83.599 | BB25: 81.929 | BC25: 90.637 | BD25: 100.949 | BE25: =SUM(BA25:BD25) -> 357.114 | BF25: =123.325 -> 123.325 | BG25: 119.611 | BH25: 115.258 | BI25: 114.829 | BJ25: =SUM(BF25:BI25) -> 473.023 | BK25: =115.228 -> 115.228 | BL25: 126.104 | BM25: 119.525 | BN25: 123.312 | BO25: =SUM(BK25:BN25) -> 484.169 | BP25: 125.9 | BQ25: 117.6 | BR25: 116.1 | BS25: 96.4 | BT25: =SUM(BP25:BS25) -> 456 | BU25: 105.2 | BV25: 104.3 | BW25: 110.3 | BX25: 133.2 | BY25: =SUM(BU25:BX25) -> 453 | BZ25: 136.9 | CA25: 139 | CB25: 132.7 | CC25: 160.9 | CD25: =SUM(BZ25:CC25) -> 569.5 | CE25: 185.2 | CF25: 181.6 | CG25: 190.2 | CH25: 192.3 | CI25: =SUM(CE25:CH25) -> 749.3 | CJ25: 191.5 | CK25: 206.9 | CL25: 199 | CM25: 203.8 | CN25: =SUM(CJ25:CM25) -> 801.2 | CO25: 231.9 | CP25: 230.3 | CQ25: 249.6 | CR25: 226.1 | CS25: =SUM(CO25:CR25) -> 937.9 | CT25: 242.6 | CU25: 240.6 | CV25: 269.4 | CW25: 238.6 | CX25: =SUM(CT25:CW25) -> 991.2 | CY25: 298.4 | CZ25: 305.9 | DA25: 288.5 | DB25: 303.9 | DC25: =SUM(CY25:DB25) -> 1196.7 | DD25: 305.5 | DE25: 330.5 | DF25: 323.4 | DG25: 401.2 | DH25: =SUM(DD25:DG25) -> 1360.6 | DI25: 356.4 | DJ25: 326.8 | DK25: 325 | DL25: 385.2 | DM25: =SUM(DI25:DL25) -> 1393.4 | DN25: 379.1 | DO25: 339.38957 | DP25: 359.16032 | DQ25: 360.9425 | DR25: =SUM(DN25:DQ25) -> 1438.5924 | DS25: 429.27432 | DT25: 380.66902 | DU25: 403.33093 | DV25: 404.83433 | DW25: =SUM(DS25:DV25) -> 1618.1086 | DX25: 477.95394 | DY25: 424.11722 | DZ25: 449.24173 | EA25: 450.15661 | EB25: =SUM(DX25:EA25) -> 1801.4695 | EG25: =S25+T25+U25+W25 -> 80.151 | EH25: =X25+Y25+Z25+AB25 -> 95.471 | EI25: =AC25+AD25+AE25+AG25 -> 118.933 | EJ25: =AH25+AI25+AJ25+AL25 -> 157.668 | EK25: =AM25+AN25+AO25+AQ25 -> 203.975 | EL25: =AR25+AS25+AT25+AV25 -> 236.365 | EM25: =AW25+AX25+AY25+BA25 -> 317.475 | EN25: =BB25+BC25+BD25+BF25 -> 396.84 | EO25: =SUM(BG25:BI25,BK25) -> 464.926 | EP25: =SUM(BL25:BN25,BP25) -> 494.841 | EQ25: =SUM(BQ25:BS25,BU25) -> 435.3 | ER25: =SUM(BV25:BX25,BZ25) -> 484.7 | ES25: =SUM(CA25:CC25,CE25) -> 617.8 | ET25: =SUM(CF25:CH25,CJ25) -> 755.6 | EU25: =SUM(CK25,CL25,CM25,CO25) -> 841.6 | EV25: =SUM(CT25,CR25,CQ25,CP25) -> 948.6 | EW25: =CU25+CV25+CW25+CY25 -> 1047 | EX25: =CZ25+DA25+DB25+DD25 -> 1203.8 | EY25: =DE25+DF25+DG25+DI25 -> 1411.5 | EZ25: =DJ25+DK25+DL25+DN25 -> 1416.1 | FA25: =DO25+DP25+DQ25+DS25 -> 1488.7667 | FB25: =DT25+DU25+DV25+DX25 -> 1666.7882 | FD25: General & Admin. Expense | FE25: =DN25 -> 379.1 | FF25: 414.95759 | FG25: =FE25-FF25 -> -35.857591 | FH25: =DI25 -> 356.4 | FI25: =FE25/FH25-1 -> 0.06369248
A26: Restructuring/Other one-time | BR26: 167.7 | BS26: 99.2 | BT26: =SUM(BP26:BS26) -> 266.9 | BU26: 75.5 | BV26: 152.1 | BW26: 51.6 | BX26: 53.2 | BY26: =SUM(BU26:BX26) -> 332.4 | BZ26: 18.3 | CA26: 7.9 | CB26: 20.4 | CC26: 6.4 | CD26: =SUM(BZ26:CC26) -> 53 | CE26: 0 | CF26: 0 | CG26: 0 | CH26: -30.2 | CI26: =SUM(CE26:CH26) -> -30.2 | CJ26: 0 | CK26: 0 | CL26: 0 | CM26: 0 | CN26: =SUM(CJ26:CM26) -> 0 | CO26: 0 | CP26: 0 | CQ26: 0 | CR26: 2784.1 | CS26: =SUM(CO26:CR26) -> 2784.1 | CT26: -20.2 | CU26: 0 | CV26: 0 | CW26: 0 | CX26: =SUM(CT26:CW26) -> -20.2 | CY26: 0 | CZ26: 0 | DA26: 0 | DB26: 0 | DC26: =SUM(CY26:DB26) -> 0 | DD26: 0 | DE26: 0 | DF26: 0 | DG26: 0 | DH26: =SUM(DD26:DG26) -> 0 | DI26: 0 | DJ26: 0 | DK26: 120.2 | DL26: 33.3 | DM26: =SUM(DI26:DL26) -> 153.5 | DN26: 27.6 | DO26: 0 | DP26: 0 | DQ26: 0 | DR26: =SUM(DN26:DQ26) -> 27.6 | DS26: 0 | DT26: 0 | DU26: 0 | DV26: 0 | DW26: =SUM(DS26:DV26) -> 0 | DX26: 0 | DY26: 0 | DZ26: 0 | EA26: 0 | EB26: =SUM(DX26:EA26) -> 0 | EQ26: =SUM(BQ26:BS26,BU26) -> 342.4 | ER26: =SUM(BV26:BX26,BZ26) -> 275.2 | ES26: =SUM(CA26:CC26,CE26) -> 34.7 | ET26: =SUM(CF26:CH26,CJ26) -> -30.2 | EU26: =SUM(CK26,CL26,CM26,CO26) -> 0 | EV26: =SUM(CT26,CR26,CQ26,CP26) -> 2763.9 | EW26: =CU26+CV26+CW26+CY26 -> 0 | EX26: =CZ26+DA26+DB26+DD26 -> 0 | EY26: =DE26+DF26+DG26+DI26 -> 0 | EZ26: =DJ26+DK26+DL26+DN26 -> 181.1 | FA26: =DO26+DP26+DQ26+DS26 -> 0 | FB26: =DT26+DU26+DV26+DX26 -> 0 | FD26: Restructuring | FE26: =DN26 -> 27.6 | FF26: 0 | FG26: =FE26-FF26 -> 27.6 | FH26: =DI26 -> 0
A27: Income from Equity Investees (loss) | W27: -0.28 | X27: -0.055 | Y27: 0.36 | Z27: 3.166 | AA27: =SUM(W27:Z27) -> 3.191 | AB27: 3.395 | AC27: 3.821 | AD27: 4.339 | AE27: 8.745 | AF27: =SUM(AB27:AE27) -> 20.3 | AG27: 4.805 | AH27: 6.167 | AI27: 6.732 | AJ27: 10.911 | AK27: 27.74 | AL27: =6.585-0.635 -> 5.95 | AM27: =7.459-0.354 -> 7.105 | AN27: =8.536-0.506 -> 8.03 | AO27: =13.252-0.779 -> 12.473 | AP27: 33.445 | AQ27: 6.601 | AR27: 6.573 | AS27: =7.917-0.0959 -> 7.8211 | AT27: 17.401 | AU27: 38.396 | AV27: 10.044 | AW27: 11.944 | AX27: 13.163 | AY27: 24.15 | AZ27: 59.071 | BA27: 12.847 | BB27: 16.294 | BC27: 18.074 | BD27: 29.469 | BE27: 76.745 | BF27: 19.754 | BG27: 19.985 | BH27: 25.666 | BI27: 28.566 | BJ27: =SUM(BF27:BI27) -> 93.971 | BK27: 18.753 | BL27: 26.261 | BM27: 24.503 | BN27: 38.489 | BO27: =SUM(BK27:BN27) -> 108.006 | BP27: 23.6 | BQ27: 24.5 | BR27: 29 | BS27: 36.5 | BT27: =SUM(BP27:BS27) -> 113.6 | BU27: 23.5 | BV27: 25.2 | BW27: 29.7 | BX27: 43.5 | BY27: =SUM(BU27:BX27) -> 121.9 | BZ27: 29.4 | CA27: 34.4 | CB27: 36.3 | CC27: 48 | CD27: =SUM(BZ27:CC27) -> 148.1 | CE27: 34.5 | CF27: 38.3 | CG27: 44.3 | CH27: 56.7 | CI27: =SUM(CE27:CH27) -> 173.8 | CJ27: 44.9 | CK27: 52.2 | CL27: 51.7 | CM27: 61.9 | CN27: =SUM(CJ27:CM27) -> 210.7 | CO27: 54.5 | CP27: 52.5 | CQ27: 63.4 | CR27: 81 | CS27: =SUM(CO27:CR27) -> 251.4 | CT27: 51.1 | CU27: 59.9 | CV27: 72.9 | CW27: 84.4 | CX27: =SUM(CT27:CW27) -> 268.3 | CY27: 52.8 | CZ27: 54.9 | DA27: 60.3 | DB27: 81.9 | DC27: =SUM(CY27:DB27) -> 249.9 | DD27: 64.1 | DE27: 65.6 | DF27: 82.5 | DG27: 106 | DH27: =SUM(DD27:DG27) -> 318.2 | DI27: 84.4 | DJ27: 84.1 | DK27: 101 | DL27: 121.9 | DM27: =SUM(DI27:DL27) -> 391.4 | DN27: 89.4 | DO27: 79.423456 | DP27: 92.356542 | DQ27: 112.53091 | DR27: =SUM(DN27:DQ27) -> 373.71091 | DS27: 85.130545 | DT27: 85.546605 | DU27: 101.91586 | DV27: 120.34192 | DW27: =SUM(DS27:DV27) -> 392.93492 | DX27: 93.404502 | DY27: 93.355598 | DZ27: 111.35828 | EA27: 131.68323 | EB27: =SUM(DX27:EA27) -> 429.80161 | EK27: =AM27+AN27+AO27+AQ27 -> 34.209 | EL27: =AR27+AS27+AT27+AV27 -> 41.8391 | EM27: =AW27+AX27+AY27+BA27 -> 62.104 | EN27: =BB27+BC27+BD27+BF27 -> 83.591 | EO27: =SUM(BG27:BI27,BK27) -> 92.97 | EP27: =SUM(BL27:BN27,BP27) -> 112.853 | EQ27: =SUM(BQ27:BS27,BU27) -> 113.5 | ER27: =SUM(BV27:BX27,BZ27) -> 127.8 | ES27: =SUM(CA27:CC27,CE27) -> 153.2 | ET27: =SUM(CF27:CH27,CJ27) -> 184.2 | EU27: =SUM(CK27,CL27,CM27,CO27) -> 220.3 | EV27: =SUM(CT27,CR27,CQ27,CP27) -> 248 | EW27: =CU27+CV27+CW27+CY27 -> 270 | EX27: =CZ27+DA27+DB27+DD27 -> 261.2 | EY27: =DE27+DF27+DG27+DI27 -> 338.5 | EZ27: =DJ27+DK27+DL27+DN27 -> 396.4 | FA27: =DO27+DP27+DQ27+DS27 -> 369.44145 | FB27: =DT27+DU27+DV27+DX27 -> 401.20888 | FD27: Income from Equity Investees (loss) | FE27: =DN27 -> 89.4 | FF27: 102.51205 | FG27: =FE27-FF27 -> -13.112046 | FH27: =DI27 -> 84.4 | FI27: =FE27/FH27-1 -> 0.059241706
A29: OPERATING INCOME | B29: 23.301 | C29: =C17-C21-C22-C23-C24-C25-C27 -> 14.164 | D29: =D17-D21-D22-D23-D24-D25-D27 -> 7.076 | E29: =E17-E21-E22-E23-E24-E25-E27 -> 10.307 | F29: =F17-F21-F22-F23-F24-F25-F27 -> 8.568 | G29: =G17-G21-G22-G23-G24-G25-G27 -> 40.115 | H29: =H17-H21-H22-H23-H24-H25-H27 -> 15.774 | I29: =I17-I21-I22-I23-I24-I25-I27 -> 7.571 | J29: =J17-J21-J22-J23-J24-J25-J27 -> 14.586 | ... V29: =V17-V21-V22-V23-V24-V25-V27 -> 124.777 | W29: =W17-W21-W22-W23-W24-W25+W27 -> 41.177 | X29: =X17-X21-X22-X23-X24-X25+X27 -> 26.767 | Y29: =Y17-Y21-Y22-Y23-Y24-Y25+Y27 -> 38.214 | Z29: =Z17-Z21-Z22-Z23-Z24-Z25+Z27 -> 50.579 | AA29: =AA17-AA21-AA22-AA23-AA24-AA25+AA27 -> 156.737 | AB29: =AB17-AB21-AB22-AB23-AB24-AB25+AB27 -> 54.633 | AC29: =AC17-AC21-AC22-AC23-AC24-AC25+AC27 -> 35.217 | AD29: =AD17-AD21-AD22-AD23-AD24-AD25+AD27 -> 54.26 | ... AY29: =AY17-AY21-AY22-AY23-AY24-AY25+AY27 -> 155.249 | AZ29: =SUM(AV29:AY29) -> 606.817 | BA29: =BA17-BA21-BA22-BA23-BA24-BA25+BA27 -> 227.191 | BB29: =BB17-BB21-BB22-BB23-BB24-BB25+BB27 -> 157.278 | BC29: =BC17-BC21-BC22-BC23-BC24-BC25+BC27 -> 199.57 | BD29: =BD17-BD21-BD22-BD23-BD24-BD25+BD27 -> 196.515 | BE29: =BE17-BE21-BE22-BE23-BE24-BE25+BE27 -> 780.615 | BF29: =BF17-BF21-BF22-BF23-BF24-BF25+BF27 -> 279.881 | BG29: =BG17-BG21-BG22-BG23-BG24-BG25+BG27 -> 201.894 | BH29: =BH17-BH21-BH22-BH23-BH24-BH25+BH27 -> 214.573 | BI29: =BI17-BI21-BI22-BI23-BI24-BI25+BI27 -> 197.638 | BJ29: =SUM(BF29:BI29) -> 893.986 | BK29: =BK17-BK21-BK22-BK23-BK24-BK25+BK27 -> 319.724 | BL29: =BL17-BL21-BL22-BL23-BL24-BL25+BL27 -> 240.974 | BM29: =BM17-BM21-BM22-BM23-BM24-BM25+BM27 -> 245.214 | BN29: =BN17-BN21-BN22-BN23-BN24-BN25+BN27 -> 248.033 | BO29: =SUM(BK29:BN29) -> 1053.945 | BP29: =BP17-BP21-BP22-BP23-BP24-BP25+BP27 -> 333.1 | BQ29: =BQ17-BQ21-BQ22-BQ23-BQ24-BQ25+BQ27 -> 178.16 | BR29: =BR17-BR21-BR22-BR23-BR24-BR25+BR27-BR26 -> -21.7 | BS29: =BS17-BS21-BS22-BS23-BS24-BS25+BS27-BS26 -> 14.3 | BT29: =SUM(BP29:BS29) -> 503.86 | BU29: =BU17-BU21-BU22-BU23-BU24-BU25+BU27-BU26 -> 117.7 | BV29: =BV17-BV21-BV22-BV23-BV24-BV25+BV27-BV26 -> 40.9 | BW29: =BW17-BW21-BW22-BW23-BW24-BW25+BW27-BW26 -> 204 | BX29: =BX17-BX21-BX22-BX23-BX24-BX25+BX27-BX26 -> 199.4 | BY29: =BY17-BY21-BY22-BY23-BY24-BY25+BY27-BY26 -> 562 | BZ29: =BZ17-BZ21-BZ22-BZ23-BZ24-BZ25+BZ27-BZ26 -> 352.6 | CA29: =CA17-CA21-CA22-CA23-CA24-CA25+CA27-CA26 -> 339.8 | CB29: =CB17-CB21-CB22-CB23-CB24-CB25+CB27-CB26 -> 327.7 | ... CX29: =CX17-CX21-CX22-CX23-CX24-CX25+CX27-CX26 -> 3081 | CY29: =CY17-CY21-CY22-CY23-CY24-CY25+CY27 -> 915.5 | CZ29: =CZ17-CZ21-CZ22-CZ23-CZ24-CZ25+CZ27-CZ26 -> 777.5 | DA29: =DA17-DA21-DA22-DA23-DA24-DA25+DA27-DA26 -> 938.6 | DB29: =DB17-DB21-DB22-DB23-DB24-DB25+DB27-DB26 -> 969.4 | DC29: =DC17-DC21-DC22-DC23-DC24-DC25+DC27 -> 3601 | DD29: =DD17-DD21-DD22-DD23-DD24-DD25+DD27-DD26 -> 1058 | DE29: =DE17-DE21-DE22-DE23-DE24-DE25+DE27-DE26 -> 864.2 | DF29: =DF17-DF21-DF22-DF23-DF24-DF25+DF27-DF26 -> 1022.3 | DG29: =DG17-DG21-DG22-DG23-DG24-DG25+DG27-DG26 -> 1227.5 | DH29: =DH17-DH21-DH22-DH23-DH24-DH25+DH27-DH26 -> 4172 | DI29: =DI17-DI21-DI22-DI23-DI24-DI25+DI27-DI26 -> 1132.6 | DJ29: =DJ17-DJ21-DJ22-DJ23-DJ24-DJ25+DJ27-DJ26 -> 935.4 | DK29: =DK17-DK21-DK22-DK23-DK24-DK25+DK27-DK26 -> 1044.2 | ... EB29: =EB17-EB21-EB22-EB23-EB24-EB25+EB27-EB26 -> 5870.5019 | EG29: =S29+T29+U29+W29 -> 132.473 | EH29: =X29+Y29+Z29+AB29 -> 170.193 | EI29: =AC29+AD29+AE29+AG29 -> 233.64 | EJ29: =AH29+AI29+AJ29+AL29 -> 297.048 | EK29: =AM29+AN29+AO29+AQ29 -> 363.275 | EL29: =AR29+AS29+AT29+AV29 -> 478.5381 | EM29: =AW29+AX29+AY29+BA29 -> 659.347 | EN29: =BB29+BC29+BD29+BF29 -> 833.244 | EO29: =SUM(BG29:BI29,BK29) -> 933.829 | EP29: =SUM(BL29:BN29,BP29) -> 1067.321 | EQ29: =SUM(BQ29:BS29,BU29) -> 288.46 | ER29: =SUM(BV29:BX29,BZ29) -> 796.9 | ES29: =SUM(CA29:CC29,CE29) -> 1568.7 | ET29: =ET17-ET21-ET22-ET23-ET24-ET25+ET27 -> 1752.4 | EU29: =EU17-EU21-EU22-EU23-EU24-EU25+EU27 -> 2072.2 | EV29: =EV17-EV21-EV22-EV23-EV24-EV25+EV27 -> 2621.5 | EW29: =EW17-EW21-EW22-EW23-EW24-EW25+EW27 -> 3183 | EX29: =EX17-EX21-EX22-EX23-EX24-EX25+EX27 -> 3743.5 | EY29: =EY17-EY21-EY22-EY23-EY24-EY25+EY27 -> 4246.6 | EZ29: =EZ17-EZ21-EZ22-EZ23-EZ24-EZ25+EZ27-EZ26 -> 4118.2 | FA29: =FA17-FA21-FA22-FA23-FA24-FA25+FA27 -> 4738.6687 | FB29: =FB17-FB21-FB22-FB23-FB24-FB25+FB27 -> 5376.5461 | FD29: OPERATING INCOME | FE29: =DN29 -> 1116.1 | FF29: 1218.2053 | FG29: =FE29-FF29 -> -102.10534 | FH29: =DI29 -> 1132.6 | FI29: =FE29/FH29-1 -> -0.01456825
A30: Operating income before charges | B30: =B29+B26 -> 23.301 | C30: =C29+C26 -> 14.164 | D30: =D29+D26 -> 7.076 | E30: =E29+E26 -> 10.307 | F30: =F29+F26 -> 8.568 | G30: =G29+G26 -> 40.115 | H30: =H29+H26 -> 15.774 | I30: =I29+I26 -> 7.571 | ... BP30: =BP29+BP26 -> 333.1 | BQ30: =BQ29+BQ26+35.1 -> 213.26 | BR30: =BR29+BR26 -> 146 | BS30: =BS29+BS26 -> 113.5 | BT30: =SUM(BP30:BS30) -> 805.86 | BU30: =BU29+BU26 -> 193.2 | BV30: =BV29+BV26 -> 193 | BW30: =BW29+BW26 -> 255.6 | BX30: =BX29+BX26 -> 252.6 | BY30: =BY29+BY26 -> 894.4 | BZ30: =BZ29+BZ26 -> 370.9 | CA30: =CA29+CA26 -> 347.7 | CB30: =CB29+CB26 -> 348.1 | ... CV30: =CV29+CV26 -> 768.5 | CW30: =CW29+2.4 -> 857.3 | CX30: =CX29+CX26 -> 3060.8 | CY30: =CY29+19.3 -> 934.8 | CZ30: =CZ29-(CZ45/(1-CZ66)) -> 789.4 | DA30: =DA29-(DA45/(1-DA66)) -> 950.1 | DB30: =DB29+11.9 -> 981.3 | DC30: =SUM(CY30:DB30) -> 3655.6 | DD30: =DD29+12.3 -> 1070.3 | DE30: =DE29+13.9 -> 878.1 | DF30: =DF29+14.5+2.8 -> 1039.6 | DG30: =DG29+16.7 -> 1244.2 | DH30: =DH29-(DH45/(1-DH66)) -> 4197.8122 | DI30: =DI29-(DI45/(1-DI66)) -> 1146.6 | DJ30: =DJ29-(DJ45/(1-DJ66)) -> 949.2 | DK30: 1178.4 | DL30: 1138.3 | DM30: =SUM(DI30:DL30) -> 4412.5 | DN30: 1167.5 | DO30: =DO29-(DO45/(1-DO66)) -> 1020.2835 | DP30: =DP29-(DP45/(1-DP66)) -> 1234.4113 | DQ30: =DQ29-(DQ45/(1-DQ66)) -> 1262.9778 | DR30: =SUM(DN30:DQ30) -> 4685.1725 | DS30: =DS29-(DS45/(1-DS66)) -> 1278.0581 | DT30: =DT29-(DT45/(1-DT66)) -> 1172.4725 | DU30: =DU29-(DU45/(1-DU66)) -> 1403.3845 | DV30: =DV29-(DV45/(1-DV66)) -> 1426.699 | DW30: =SUM(DS30:DV30) -> 5280.614 | DX30: =DX29-(DX45/(1-DX66)) -> 1429.7445 | DY30: =DY29-(DY45/(1-DY66)) -> 1321.1031 | DZ30: =DZ29-(DZ45/(1-DZ66)) -> 1575.6648 | EA30: =EA29-(EA45/(1-EA66)) -> 1598.9828 | EB30: =SUM(DX30:EA30) -> 5925.4951 | EQ30: =SUM(BQ30:BS30,BU30) -> 665.96 | ER30: =SUM(BV30:BX30,BZ30) -> 1072.1 | ES30: =SUM(CA30:CC30,CE30) -> 1603.4 | ET30: =SUM(CF30:CH30,CJ30) -> 1752.4 | EU30: =SUM(CK30,CL30,CM30,CO30) -> 2072.2 | EV30: =SUM(CT30,CR30,CQ30,CP30) -> 2621.5 | EW30: =CU30+CV30+CW30+CY30 -> 3204.7 | EX30: =CZ30+DA30+DB30+DD30 -> 3791.1 | EY30: =DE30+DF30+DG30+DI30 -> 4308.5 | EZ30: =DJ30+DK30+DL30+DN30 -> 4433.4 | FA30: =DO30+DP30+DQ30+DS30 -> 4795.7306 | FB30: =DT30+DU30+DV30+DX30 -> 5432.3004 | FD30: Operating income before charges | FE30: =DN30 -> 1167.5 | FF30: 1234.2503 | FG30: =FE30-FF30 -> -66.750345 | FH30: =DI30 -> 1146.6 | FI30: =FE30/FH30-1 -> 0.018227804
A31: EBITDA | B31: =B29+B24 -> 35.836 | C31: =C29+C24 -> 18.628 | D31: =D29+D24 -> 12.228 | E31: =E29+E24 -> 16.225 | F31: =F29+F24 -> 15.52 | G31: =G29+G24 -> 62.601 | H31: =H29+H24 -> 23.374 | I31: =I29+I24 -> 16.171 | ... Q31: =Q29+Q24 -> 138.965 | R31: =R29+CF!R12 -> 51.241 | S31: =S29+CF!S12 -> 40.734 | T31: =T29+CF!T12 -> 53.668 | U31: =U29+CF!U12 -> 60.035 | V31: =V29+CF!V12 -> 205.678 | W31: =W29+CF!W12 -> 65.815 | X31: =X29+CF!X12 -> 52.759 | Y31: =Y29+CF!Y12 -> 65.923 | ... BT31: =BT29+CF!BT12 -> 1108.36 | BU31: =BU29+BU24 -> 252 | BV31: =BV29+BV24 -> 175 | BW31: =BW29+BW24 -> 337.7 | BX31: =BX29+BX24 -> 332 | BY31: =BY29+BY24 -> 1096.7 | BZ31: =BZ29+BZ24 -> 483.2 | CA31: =CA29+CA24 -> 468.3 | CB31: =CB29+CB24 -> 452.9 | ... EB31: =EB29+EB24 -> 7155.6198 | EG31: =S31+T31+U31+W31 -> 220.252 | EH31: =X31+Y31+Z31+AB31 -> 285.043 | EI31: =AC31+AD31+AE31+AG31 -> 384.499 | EJ31: =AH31+AI31+AJ31+AL31 -> 487.495 | EK31: =AM31+AN31+AO31+AQ31 -> 591.954 | EL31: =AR31+AS31+AT31+AV31 -> 748.2751 | EM31: =AW31+AX31+AY31+BA31 -> 986.698 | EN31: =BB31+BC31+BD31+BF31 -> 1212.863 | EO31: =SUM(BG31:BI31,BK31) -> 1364.832 | EP31: =SUM(BL31:BN31,BP31) -> 1582.337 | EQ31: =EQ30+EQ24 -> 1216.36 | ER31: =SUM(BV31:BX31,BZ31) -> 1327.9 | ES31: =ES29+ES24 -> 2076.3 | ET31: =ET29+ET24 -> 2282.8 | EU31: =EU29+EU24 -> 2636.6 | EV31: =EV29+EV24 -> 3263.7 | EW31: =EW29+EW24 -> 3928.9 | EX31: =EX29+EX24 -> 4666.9 | EY31: =EY29+EY24 -> 5241.6 | EZ31: =EZ29+EZ24 -> 5138.6 | ... FB31: =FB29+FB24 -> 6591.5957 | FD31: EBITDA | FE31: =DN31 -> 1374.9 | FF31: 1482.4915 | FG31: =FE31-FF31 -> -107.59154 | FH31: =DI31 -> 1382.3 | FI31: =FE31/FH31-1 -> -0.0053533965
A32: EBITDA before charges | BP32: =BP31+BP26 -> 473 | BQ32: =BQ31+BQ26 -> 324.56 | BR32: =BR31+BR26 -> 291.1 | BS32: =BS31+BS26 -> 286.6 | BT32: =SUM(BP32:BS32) -> 1375.26 | BU32: =BU31+BU26 -> 327.5 | BV32: =BV31+BV26 -> 327.1 | BW32: =BW31+BW26 -> 389.3 | BX32: =BX31+BX26 -> 385.2 | BY32: =SUM(BU32:BX32) -> 1429.1 | BZ32: =BZ31+BZ26 -> 501.5 | CA32: =CA31+CA26 -> 476.2 | CB32: =CB31+CB26 -> 473.3 | CC32: =CC31+CC26 -> 531.8 | CD32: =CD31+CD26 -> 1982.8 | CE32: =CE31+CE26 -> 629.7 | CF32: =CF31+CF26 -> 505.1 | CG32: =CG31+CG26 -> 531.7 | ... CV32: =CV31+CV26 -> 948.6 | CW32: =CW31+CW26+2.4 -> 1042.7 | CX32: =CX31+CX26 -> 3770.4 | CY32: =CY30+CY24 -> 1140.8 | CZ32: =CZ30+CZ24 -> 1006.5 | DA32: =DA30+DA24 -> 1186.6 | DB32: =DB30+DB24 -> 1215.6 | DC32: =DC30+DC24 -> 4549.5 | DD32: =DD30+DD24 -> 1305.8 | DE32: =DE30+DE24 -> 1125.9 | DF32: =DF30+DF24 -> 1287.2 | ... EB32: =EB30+EB24 -> 7210.6131 | EQ32: =SUM(BQ32:BS32,BU32) -> 1229.76 | ER32: =SUM(BV32:BX32,BZ32) -> 1603.1 | ES32: =SUM(CA32:CC32,CE32) -> 2111 | ET32: =ET31 -> 2282.8 | EU32: =SUM(CK32,CL32,CM32,CO32) -> 2636.6 | EV32: =SUM(CT32,CR32,CQ32,CP32) -> 3263.7 | EW32: =CU32+CV32+CW32+CY32 -> 3950.6 | EX32: =CZ32+DA32+DB32+DD32 -> 4714.5 | EY32: =DE32+DF32+DG32+DI32 -> 5303.5 | EZ32: =DJ32+DK32+DL32+DN32 -> 5453.8 | FA32: =DO32+DP32+DQ32+DS32 -> 5943.6823 | FB32: =DT32+DU32+DV32+DX32 -> 6647.35 | FD32: EBITDA before charges | FE32: =DN32 -> 1426.3 | FF32: 1498.5366 | FG32: =FE32-FF32 -> -72.236552 | FH32: =DI32 -> 1396.3 | FI32: =FE32/FH32-1 -> 0.021485354
A33: Interest income & other, net | BK33: 13.5 | BP33: 10.7 | BQ33: 0.2 | BR33: 0.9 | BS33: -2.8 | BT33: =SUM(BP33:BS33) -> 9 | BU33: -6.4 | BV33: 3 | BW33: 18.6 | BX33: 21.4 | BY33: =SUM(BU33:BX33) -> 36.6 | BZ33: 25.1 | CA33: 4.7 | CB33: -1.4 | CC33: 21.9 | CD33: =SUM(BZ33:CC33) -> 50.3 | CE33: 14.4 | CF33: 19.9 | CG33: 16 | CH33: 65.7 | CI33: =SUM(CE33:CH33) -> 116 | CJ33: 23.2 | CK33: 35.3 | CL33: 9.7 | CM33: 26.3 | CN33: =SUM(CJ33:CM33) -> 94.5 | CO33: -2.9 | CP33: 50.8 | CQ33: 3.5 | CR33: 72.1 | CS33: =SUM(CO33:CR33) -> 123.5 | CT33: 19.8 | CU33: 17.8 | CV33: 19.4 | CW33: 85.7 | CX33: =SUM(CT33:CW33) -> 142.7 | CY33: 9.7 | CZ33: 1.3 | DA33: 25.5 | DB33: 6.4 | DC33: =SUM(CY33:DB33) -> 42.9 | DD33: 8.1 | DE33: 14.5 | DF33: 72.9 | DG33: 12.5 | DH33: =SUM(DD33:DG33) -> 108 | DI33: 24.1 | DJ33: 67.9 | DK33: 31.7 | DL33: 151.6 | DM33: =SUM(DI33:DL33) -> 275.3 | DN33: 88.2 | DO33: =DO148 -> 26.25 | DP33: =DP148 -> 26.25 | DQ33: =DQ148 -> 26.25 | DR33: =SUM(DN33:DQ33) -> 166.95 | DS33: =DS148 -> 27.5 | DT33: =DT148 -> 27.5 | DU33: =DU148 -> 27.5 | DV33: =DV148 -> 27.5 | DW33: =SUM(DS33:DV33) -> 110 | DX33: =DX148 -> 27.5 | DY33: =DY148 -> 27.5 | DZ33: =DZ148 -> 27.5 | EA33: =EA148 -> 27.5 | EB33: =SUM(DX33:EA33) -> 110 | ER33: =SUM(BZ33:CB33,CD33) -> 78.7 | ES33: =SUM(CA33:CC33,CE33) -> 39.6 | ET33: =SUM(CF33:CH33,CJ33) -> 124.8 | EU33: =SUM(CK33,CL33,CM33,CO33) -> 68.4 | EV33: =SUM(CT33,CR33,CQ33,CP33) -> 146.2 | EW33: =CU33+CV33+CW33+CY33 -> 132.6 | EX33: =CZ33+DA33+DB33+DD33 -> 41.3 | EY33: =DE33+DF33+DG33+DI33 -> 124 | EZ33: =DJ33+DK33+DL33+DN33 -> 339.4 | FA33: =DO33+DP33+DQ33+DS33 -> 106.25 | FB33: =DT33+DU33+DV33+DX33 -> 110 | FD33: Interest income & other, net | FE33: =DN33 -> 88.2 | FF33: 26.25 | FG33: =FE33-FF33 -> 61.95 | FH33: =DI33 -> 24.1 | FI33: =FE33/FH33-1 -> 2.659751
A34: Interest Expense | BK34: 7 | BP34: 17.1 | BQ34: 11.2 | BR34: 12.5 | BS34: 12.6 | BT34: =SUM(BP34:BS34) -> 53.4 | BU34: 13 | BV34: 8.9 | BW34: 8.6 | BX34: 8.6 | BY34: =SUM(BU34:BX34) -> 39.1 | BZ34: 8.2 | CA34: 8 | CB34: 7.9 | CC34: 8.6 | CD34: =SUM(BZ34:CC34) -> 32.7 | CE34: 7.9 | CF34: 7.1 | CG34: 8.5 | CH34: 9.8 | CI34: =SUM(CE34:CH34) -> 33.3 | CJ34: 8.6 | CK34: 8.8 | CL34: 8.9 | CM34: 6.4 | CN34: =SUM(CJ34:CM34) -> 32.7 | CO34: 6.6 | CP34: 6.1 | CQ34: 6.3 | CR34: 9.1 | CS34: =SUM(CO34:CR34) -> 28.1 | CT34: 14.5 | CU34: 16.7 | CV34: 16.4 | CW34: 16.4 | CX34: =SUM(CT34:CW34) -> 64 | CY34: 16.3 | CZ34: 16.9 | DA34: 19.1 | DB34: 18.2 | DC34: =SUM(CY34:DB34) -> 70.5 | DD34: 16.5 | DE34: 18.3 | DF34: 21.8 | DG34: 24.7 | DH34: =SUM(DD34:DG34) -> 81.3 | DI34: 23.8 | DJ34: 22.9 | DK34: 23.5 | DL34: 22.3 | DM34: =SUM(DI34:DL34) -> 92.5 | DN34: 25.9 | DO34: =DO145 -> 33.95375 | DP34: =DP145 -> 32.308263 | DQ34: =DQ145 -> 33.95375 | DR34: =SUM(DN34:DQ34) -> 126.11576 | DS34: =DS145 -> 38.64125 | DT34: =DT145 -> 43.32875 | DU34: =DU145 -> 41.228926 | DV34: =DV145 -> 43.32875 | DW34: =SUM(DS34:DV34) -> 166.52768 | DX34: =DX145 -> 46.45375 | DY34: =DY145 -> 49.57875 | DZ34: =DZ145 -> 47.176034 | EA34: =EA145 -> 49.57875 | EB34: =SUM(DX34:EA34) -> 192.78728 | ER34: =SUM(BZ34:CB34,CD34) -> 56.8 | ES34: =SUM(CA34:CC34,CE34) -> 32.4 | ET34: =SUM(CF34:CH34,CJ34) -> 34 | EU34: =SUM(CK34,CL34,CM34,CO34) -> 30.7 | EV34: =SUM(CT34,CR34,CQ34,CP34) -> 36 | EW34: =CU34+CV34+CW34+CY34 -> 65.8 | EX34: =CZ34+DA34+DB34+DD34 -> 70.7 | EY34: =DE34+DF34+DG34+DI34 -> 88.6 | EZ34: =DJ34+DK34+DL34+DN34 -> 94.6 | FA34: =DO34+DP34+DQ34+DS34 -> 138.85701 | FB34: =DT34+DU34+DV34+DX34 -> 174.34018 | FD34: Interest Expense | FE34: =DN34 -> 25.9 | FF34: 29.26625 | FG34: =FE34-FF34 -> -3.36625 | FH34: =DI34 -> 23.8 | FI34: =FE34/FH34-1 -> 0.088235294
A35: Interest/Other Expense (Income) | B35: 1.738 | C35: =949-985 -> -36 | D35: =-2.371+9.26 -> 6.889 | E35: =-1.917+0.907 -> -1.01 | F35: =1.519-0.962 -> 0.557 | G35: =-6.792+3.765 -> -3.027 | H35: =2.25-2.258 -> -0.008 | I35: =-2.857+2.709 -> -0.148 | J35: =-2.829+1.96 -> -0.869 | K35: =-3.085-0.017+1.82 -> -1.282 | L35: =SUM(H35:K35) -> -2.307 | M35: =1.804-3.936 -> -2.132 | N35: =1.834-3.531 -> -1.697 | O35: =1.823-2.605 -> -0.782 | P35: =1.821-2.321 -> -0.5 | Q35: =SUM(M35:P35) -> -5.111 | R35: =0.845-2.157 -> -1.312 | S35: =0.235-2.329 -> -2.094 | T35: =-2.176+0.114 -> -2.062 | U35: -1.665 | V35: =SUM(R35:U35) -> -7.133 | W35: =0.183-2.124 -> -1.941 | X35: =0.234-2.431 -> -2.197 | Y35: =-1.954+0.434 -> -1.52 | Z35: =-2.169+0.512 -> -1.657 | AA35: =SUM(W35:Z35) -> -7.315 | AB35: =-1.414 -> -1.414 | AC35: =-2.242 -> -2.242 | AD35: =-1.55 -> -1.55 | AE35: -1.899 | AF35: =SUM(AB35:AE35) -> -7.105 | AG35: -1.713 | AH35: -1.56 | AI35: -2.91 | AJ35: -1.645 | AK35: -10.768 | AL35: -2.493 | AM35: -2.135 | AN35: -1.456 | AO35: -3.216 | AP35: =SUM(AL35:AO35) -> -9.3 | AQ35: -4.496 | AR35: -1.239 | AS35: -5.115 | AT35: -0.772 | AU35: =SUM(AQ35:AT35) -> -11.622 | AV35: -3.208 | AW35: -3.685 | AX35: -4.424 | AY35: -2.823 | AZ35: =SUM(AV35:AY35) -> -14.14 | BA35: -5.122 | BB35: -4.014 | BC35: -3.235 | BD35: -3.458 | BE35: =SUM(BA35:BD35) -> -15.829 | BF35: -0.348 | BG35: -3.063 | BH35: -5.028 | BI35: -3.852 | BJ35: =SUM(BF35:BI35) -> -12.291 | BK35: =BK34-BK33 -> -6.5 | BL35: 0.592 | BM35: 2.241 | BN35: 1.187 | BO35: =SUM(BK35:BN35) -> -2.48 | BP35: =BP34-BP33 -> 6.4 | BQ35: =BQ34-BQ33 -> 11 | BR35: =BR34-BR33 -> 11.6 | BS35: =BS34-BS33 -> 15.4 | BT35: =SUM(BP35:BS35) -> 44.4 | BU35: =BU34-BU33 -> 19.4 | BV35: =BV34-BV33 -> 5.9 | BW35: =BW34-BW33 -> -10 | BX35: =BX34-BX33 -> -12.8 | BY35: =SUM(BU35:BX35) -> 2.5 | BZ35: =BZ34-BZ33 -> -16.9 | CA35: =CA34-CA33 -> 3.3 | CB35: =CB34-CB33 -> 9.3 | CC35: =CC34-CC33 -> -13.3 | CD35: =SUM(BZ35:CC35) -> -17.6 | CE35: =CE34-CE33 -> -6.5 | CF35: =CF34-CF33 -> -12.8 | CG35: =CG34-CG33 -> -7.5 | CH35: =CH34-CH33 -> -55.9 | CI35: =SUM(CE35:CH35) -> -82.7 | CJ35: =CJ34-CJ33 -> -14.6 | CK35: =CK34-CK33 -> -26.5 | CL35: =CL34-CL33 -> -0.8 | CM35: =CM34-CM33 -> -19.9 | CN35: =SUM(CJ35:CM35) -> -61.8 | CO35: =CO34-CO33 -> 9.5 | CP35: =CP34-CP33 -> -44.7 | CQ35: =CQ34-CQ33 -> 2.8 | CR35: =CR34-CR33 -> -63 | CS35: =SUM(CO35:CR35) -> -95.4 | CT35: =CT34-CT33 -> -5.3 | CU35: =CU34-CU33 -> -1.1 | CV35: =CV34-CV33 -> -3 | CW35: =CW34-CW33 -> -69.3 | CX35: =SUM(CT35:CW35) -> -78.7 | CY35: =CY34-CY33 -> 6.6 | CZ35: =CZ34-CZ33 -> 15.6 | DA35: =DA34-DA33 -> -6.4 | DB35: =DB34-DB33 -> 11.8 | DC35: =SUM(CY35:DB35) -> 27.6 | DD35: =DD34-DD33 -> 8.4 | DE35: =DE34-DE33 -> 3.8 | DF35: =DF34-DF33 -> -51.1 | DG35: =DG34-DG33 -> 12.2 | DH35: =SUM(DD35:DG35) -> -26.7 | DI35: =DI34-DI33 -> -0.3 | DJ35: =DJ34-DJ33 -> -45 | DK35: =DK34-DK33 -> -8.2 | DL35: =DL34-DL33 -> -129.3 | DM35: =SUM(DI35:DL35) -> -182.8 | DN35: =DN34-DN33 -> -62.3 | DO35: =DO34-DO33 -> 7.70375 | DP35: =DP34-DP33 -> 6.0582627 | DQ35: =DQ34-DQ33 -> 7.70375 | DR35: =SUM(DN35:DQ35) -> -40.834237 | DS35: =DS34-DS33 -> 11.14125 | DT35: =DT34-DT33 -> 15.82875 | DU35: =DU34-DU33 -> 13.728926 | DV35: =DV34-DV33 -> 15.82875 | DW35: =SUM(DS35:DV35) -> 56.527676 | DX35: =DX34-DX33 -> 18.95375 | DY35: =DY34-DY33 -> 22.07875 | DZ35: =DZ34-DZ33 -> 19.676034 | EA35: =EA34-EA33 -> 22.07875 | EB35: =SUM(DX35:EA35) -> 82.787284 | EG35: =S35+T35+U35+W35 -> -7.762 | EH35: =X35+Y35+Z35+AB35 -> -6.788 | EI35: =AC35+AD35+AE35+AG35 -> -7.404 | EJ35: =AH35+AI35+AJ35+AL35 -> -8.608 | EK35: =AM35+AN35+AO35+AQ35 -> -11.303 | EL35: =AR35+AS35+AT35+AV35 -> -10.334 | EM35: =AW35+AX35+AY35+BA35 -> -16.054 | EN35: =BB35+BC35+BD35+BF35 -> -11.055 | EO35: =SUM(BG35:BI35,BK35) -> -18.443 | EP35: =SUM(BL35:BN35,BP35) -> 10.42 | EQ35: =SUM(BQ35:BS35,BU35) -> 57.4 | ER35: =SUM(BV35:BX35,BZ35) -> -33.8 | ES35: =SUM(CA35:CC35,CE35) -> -7.2 | ET35: =SUM(CF35:CH35,CJ35) -> -90.8 | EU35: =SUM(CK35,CL35,CM35,CO35) -> -37.7 | EV35: =SUM(CT35,CR35,CQ35,CP35) -> -110.2 | EW35: =CU35+CV35+CW35+CY35 -> -66.8 | EX35: =CZ35+DA35+DB35+DD35 -> 29.4 | EY35: =DE35+DF35+DG35+DI35 -> -35.4 | EZ35: =DJ35+DK35+DL35+DN35 -> -244.8 | FA35: =DO35+DP35+DQ35+DS35 -> 32.607013 | FB35: =DT35+DU35+DV35+DX35 -> 64.340176 | FD35: Interest/Other Expense (Income) | FE35: =DN35 -> -62.3 | FF35: 3.01625 | FG35: =FE35-FF35 -> -65.31625 | FH35: =DI35 -> -0.3
A36: Internet related investment losses | AK36: 2.94 | ER36: =SUM(BV36:BX36,BZ36) -> 0 | ES36: =SUM(CA36:CC36,CE36) -> 0 | ET36: =SUM(CF36:CH36,CJ36) -> 0 | EU36: =SUM(CK36,CL36,CM36,CO36) -> 0 | EV36: =SUM(CT36,CR36,CQ36,CP36) -> 0 | EW36: =CU36+CV36+CW36+CY36 -> 0 | EX36: =CZ36+DA36+DB36+DD36 -> 0 | EY36: =DE36+DF36+DG36+DI36 -> 0 | EZ36: =DJ36+DK36+DL36+DN36 -> 0 | FA36: =DO36+DP36+DQ36+DS36 -> 0 | FB36: =DT36+DU36+DV36+DX36 -> 0 | FD36: Internet related investment losses | FE36: =DN36 -> 0 | FF36: 0 | FG36: =FE36-FF36 -> 0 | FH36: =DI36 -> 0
A37: Loss on extinguishment of debt | DB37: -61.1 | DC37: =SUM(CY37:DB37) -> -61.1 | FB37: =DT37+DU37+DV37+DX37 -> 0
A38: Gain on sale of investment | AP38: 13.361 | CY38: 390.6 | DC38: =SUM(CY38:DB38) -> 390.6 | DN38: =501.2+1326.3 -> 1827.5 | DR38: =SUM(DN38:DQ38) -> 1827.5 | ER38: =SUM(BV38:BX38,BZ38) -> 0 | ES38: =SUM(CA38:CC38,CE38) -> 0 | ET38: =SUM(CF38:CH38,CJ38) -> 0 | EU38: =SUM(CK38,CL38,CM38,CO38) -> 0 | EV38: =SUM(CT38,CR38,CQ38,CP38) -> 0 | EW38: =CU38+CV38+CW38+CY38 -> 390.6 | EX38: =CZ38+DA38+DB38+DD38 -> 0 | EY38: =DE38+DF38+DG38+DI38 -> 0 | EZ38: =DJ38+DK38+DL38+DN38 -> 1827.5 | FA38: =DO38+DP38+DQ38+DS38 -> 0 | FB38: =DT38+DU38+DV38+DX38 -> 0 | FD38: Gain on sale of investment | FE38: =DN38 -> 1827.5 | FF38: 0 | FG38: =FE38-FF38 -> 1827.5 | FH38: =DI38 -> 0
A39: Earnings Before Taxes | B39: 21.563 | C39: =C29-C35 -> 50.164 | D39: =D29-D35 -> 0.187 | E39: =E29-E35 -> 11.317 | F39: =F29+F35 -> 9.125 | G39: =G29-G35 -> 43.142 | H39: =H29-H35 -> 15.782 | I39: =I29-I35 -> 7.719 | J39: =J29-J35 -> 15.455 | K39: =K29-K35 -> 20.286 | L39: =L29-L35 -> 59.284 | M39: =M29-M35 -> 22.894 | N39: =38.17-M39 -> 15.276 | O39: =61.521-N39-M39 -> 23.351 | P39: =P29-P35 -> 29.789 | Q39: 91.31 | R39: =R29-R35 -> 34.793 | S39: =S29-S35 -> 23.434 | T39: =T29-T35 -> 34.572 | U39: =U29-U35 -> 39.111 | V39: =V29-V35 -> 131.91 | W39: =W29-W35 -> 43.118 | X39: =X29-X35 -> 28.964 | Y39: =Y29-Y35 -> 39.734 | ... AJ39: =AJ29-AJ35 -> 84.521 | AK39: =AK29-AK35-AK36 -> 288.047 | AL39: =AL29-AL35 -> 94.504 | AM39: =AM29-AM35 -> 68.561 | AN39: =AN29-AN35 -> 88.659 | AO39: =AO29-AO35 -> 92.027 | AP39: =AP29-AP35+AP38 -> 338.999 | AQ39: =AQ29-AQ35 -> 125.331 | AR39: =AR29-AR35 -> 86.733 | AS39: =AS29-AS35 -> 111.1331 | AT39: =AT29-AT35 -> 113.137 | AU39: =AU29-AU35 -> 436.334 | AV39: =AV29-AV35 -> 177.869 | AW39: =AW29-AW35 -> 127.444 | AX39: =AX29-AX35 -> 157.572 | ... CX39: =CX29-CX35 -> 3159.7 | CY39: =CY29+CY38-CY35 -> 1299.5 | CZ39: =CZ29-CZ35+CZ38 -> 761.9 | DA39: =DA29-DA35+DA38 -> 945 | DB39: =DB29-DB35+DB38+DB37 -> 896.5 | DC39: =DC29-DC35+DC38+DC37 -> 3902.9 | DD39: =DD29-DD35+DD38 -> 1049.6 | DE39: =DE29-DE35 -> 860.4 | DF39: =DF29-DF35 -> 1073.4 | DG39: =DG29-DG35 -> 1215.3 | DH39: =DH29-DH35 -> 4198.7 | DI39: =DI29-DI35 -> 1132.9 | DJ39: =DJ29-DJ35 -> 980.4 | DK39: =DK29-DK35 -> 1052.4 | DL39: =DL29-DL35 -> 1151.8 | DM39: =DM29-DM35 -> 4317.5 | DN39: =DN29+DN38-DN35 -> 3005.9 | DO39: =DO29+DO38-DO35 -> 998.16871 | DP39: =DP29+DP38-DP35 -> 1214.0431 | DQ39: =DQ29+DQ38-DQ35 -> 1241.0627 | DR39: =DR29+DR38-DR35 -> 6459.1745 | DS39: =DS29-DS35 -> 1252.7872 | DT39: =DT29-DT35 -> 1142.5892 | DU39: =DU29-DU35 -> 1375.6841 | DV39: =DV29-DV35 -> 1396.9795 | DW39: =DW29-DW35 -> 5168.0401 | DX39: =DX29-DX35 -> 1396.9531 | DY39: =DY29-DY35 -> 1285.2225 | DZ39: =DZ29-DZ35 -> 1542.261 | ... EB39: =EB29-EB35 -> 5787.7146 | EG39: =S39+T39+U39+W39 -> 140.235 | EH39: =X39+Y39+Z39+AB39 -> 176.981 | EI39: =AC39+AD39+AE39+AG39 -> 241.044 | EJ39: =AH39+AI39+AJ39+AL39 -> 305.656 | EK39: =AM39+AN39+AO39+AQ39 -> 374.578 | EL39: =AR39+AS39+AT39+AV39 -> 488.8721 | EM39: =AW39+AX39+AY39+BA39 -> 675.401 | EN39: =BB39+BC39+BD39+BF39 -> 844.299 | EO39: =SUM(BG39:BI39,BK39) -> 952.272 | EP39: =SUM(BL39:BN39,BP39) -> 1056.901 | EQ39: =SUM(BQ39:BS39,BU39) -> 231.06 | ER39: =SUM(BV39:BX39,BZ39) -> 830.7 | ES39: =ES29+ES33-ES34 -> 1575.9 | ET39: =ET29+ET33-ET34 -> 1843.2 | EU39: =EU29+EU33-EU34 -> 2109.9 | EV39: =EV29+EV33-EV34 -> 2731.7 | EW39: =EW29+EW33-EW34 -> 3249.8 | EX39: =EX29+EX33-EX34 -> 3714.1 | EY39: =EY29+EY33-EY34 -> 4282 | EZ39: =EZ29+EZ33-EZ34 -> 4363 | ... FB39: =FB29+FB33-FB34 -> 5312.2059 | FD39: Earnings Before Taxes | FE39: =DN39 -> 3005.9 | FF39: 1215.1891 | FG39: =FE39-FF39 -> 1790.7109 | FH39: =DI39 -> 1132.9 | FI39: =FE39/FH39-1 -> 1.6532792
A40: Income Taxes | B40: 8.478406 | C40: 5.58 | D40: 3.391 | E40: 4.472 | F40: 3.599 | G40: =SUM(C40:F40) -> 17.042 | H40: 6.246 | I40: =I39*0.385 -> 2.971815 | J40: 6.043 | K40: 7.571 | L40: 22.826 | M40: 9.008 | N40: =15.043-M40 -> 6.035 | O40: =24.194-N40-M40 -> 9.151 | P40: =Q40-SUM(M40:O40) -> 11.905 | Q40: 36.099 | R40: 13.838 | S40: =23.31-R40 -> 9.472 | T40: 13.691 | U40: 13.557 | V40: =SUM(R40:U40) -> 50.558 | W40: 16.385 | X40: 11.007 | Y40: 15.099 | Z40: 19.843 | AA40: =SUM(W40:Z40) -> 62.334 | AB40: 21.298 | AC40: 14.043 | AD40: 20.948 | AE40: 26.3 | AF40: =SUM(AB40:AE40) -> 82.589 | AG40: 28.775 | AH40: 20.204 | AI40: 27.46 | AJ40: 31.273 | AK40: 107.712 | AL40: =AL39*AL66 -> 34.96648 | AM40: =AM39*AM66 -> 25.36757 | AN40: 32.991 | AO40: 34.339 | AP40: 126.3131 | AQ40: 46.968 | AR40: 34.702 | AS40: =42.815-0.037 -> 42.778 | AT40: =AT39*AT66 -> 43.541566 | AU40: =SUM(AQ40:AT40) -> 167.98957 | AV40: 67.734 | AW40: 48.559 | AX40: 59.992 | AY40: 55.469 | AZ40: =SUM(AV40:AY40) -> 231.754 | BA40: 87.603 | BB40: 60.831 | BC40: 77.292 | BD40: 76.251 | BE40: =SUM(BA40:BD40) -> 301.977 | BF40: 106.039 | BG40: 77.641 | BH40: 74.103 | BI40: 66.987 | BJ40: =SUM(BF40:BI40) -> 324.77 | BK40: 121.211 | BL40: 89.542 | BM40: 84.63 | BN40: 88.343 | BO40: =SUM(BK40:BN40) -> 383.726 | BP40: 118.6 | BQ40: 58.5 | BR40: -26.5 | BS40: -6.6 | BT40: =SUM(BP40:BS40) -> 144 | BU40: 34 | BV40: 9.9 | BW40: 65.8 | BX40: 58.7 | BY40: =SUM(BU40:BX40) -> 168.4 | BZ40: 126 | CA40: 118.7 | CB40: 109.9 | CC40: 134.1 | CD40: =SUM(BZ40:CC40) -> 488.7 | CE40: 160.8 | CF40: 126.5 | CG40: 129.9 | CH40: 145.9 | CI40: =SUM(CE40:CH40) -> 563.1 | CJ40: 188.4 | CK40: 146.8 | CL40: 159.1 | CM40: 180.2 | CN40: =SUM(CJ40:CM40) -> 674.5 | CO40: 188.7 | CP40: 198.1 | CQ40: 194.6 | CR40: =250.9-(2784.1-1713.1) -> -820.1 | CS40: =SUM(CO40:CR40) -> -238.7 | CT40: 278.1 | CU40: 218.3 | CV40: 259 | CW40: 336.6 | CX40: =SUM(CT40:CW40) -> 1092 | CY40: 315 | CZ40: 266.3 | DA40: 318.5 | DB40: 244 | DC40: =SUM(CY40:DB40) -> 1143.8 | DD40: 361.9 | DE40: 285.4 | DF40: 318.9 | DG40: 413.5 | DH40: =SUM(DD40:DG40) -> 1379.7 | DI40: 381.4 | DJ40: 327.6 | DK40: 361.1 | DL40: 362.5 | DM40: =SUM(DI40:DL40) -> 1432.6 | DN40: 755.8 | DO40: =DO39*DO66 -> 259.52386 | DP40: =DP39*DP66 -> 315.65121 | DQ40: =DQ39*DQ66 -> 322.67629 | DR40: =SUM(DN40:DQ40) -> 1653.6514 | DS40: =DS39*DS66 -> 325.72468 | DT40: =DT39*DT66 -> 297.0732 | DU40: =DU39*DU66 -> 357.67786 | DV40: =DV39*DV66 -> 363.21468 | DW40: =SUM(DS40:DV40) -> 1343.6904 | DX40: =DX39*DX66 -> 363.2078 | DY40: =DY39*DY66 -> 334.15785 | DZ40: =DZ39*DZ66 -> 400.98786 | EA40: =EA39*EA66 -> 406.45228 | EB40: =SUM(DX40:EA40) -> 1504.8058 | EG40: =S40+T40+U40+W40 -> 53.105 | EH40: =X40+Y40+Z40+AB40 -> 67.247 | EI40: =AC40+AD40+AE40+AG40 -> 90.066 | EJ40: =AH40+AI40+AJ40+AL40 -> 113.90348 | EK40: =AM40+AN40+AO40+AQ40 -> 139.66557 | EL40: =AR40+AS40+AT40+AV40 -> 188.75557 | EM40: =AW40+AX40+AY40+BA40 -> 251.623 | EN40: =BB40+BC40+BD40+BF40 -> 320.413 | EO40: =SUM(BG40:BI40,BK40) -> 339.942 | EP40: =SUM(BL40:BN40,BP40) -> 381.115 | EQ40: =SUM(BQ40:BS40,BU40) -> 59.4 | ER40: =SUM(BV40:BX40,BZ40) -> 260.4 | ES40: =SUM(CA40:CC40,CE40) -> 523.5 | ET40: =SUM(CF40:CH40,CJ40) -> 590.7 | EU40: =SUM(CK40,CL40,CM40,CO40) -> 674.8 | EV40: =SUM(CT40,CR40,CQ40,CP40) -> -149.3 | EW40: =CU40+CV40+CW40+CY40 -> 1128.9 | EX40: =CZ40+DA40+DB40+DD40 -> 1190.7 | EY40: =DE40+DF40+DG40+DI40 -> 1399.2 | EZ40: =DJ40+DK40+DL40+DN40 -> 1807 | FA40: =DO40+DP40+DQ40+DS40 -> 1223.576 | FB40: =DT40+DU40+DV40+DX40 -> 1381.1735 | FD40: Income Taxes | FE40: =DN40 -> 755.8 | FF40: 401.0124 | FG40: =FE40-FF40 -> 354.7876 | FH40: =DI40 -> 381.4 | FI40: =FE40/FH40-1 -> 0.98164657
A41: Net Income | B41: 13.084594 | C41: =C39-C40 -> 44.584 | D41: =D39-D40 -> -3.204 | E41: =E39-E40 -> 6.845 | F41: =F39-F40 -> 5.526 | G41: =G39-G40 -> 26.1 | H41: =H39-H40 -> 9.536 | I41: =I39-I40 -> 4.747185 | J41: =J39-J40 -> 9.412 | ... AK41: =AK39-AK40 -> 180.335 | AL41: =AL39-AL40-0.011 -> 59.52652 | AM41: =AM39-AM40+0.018 -> 43.21143 | AN41: =AN39-AN40-0.112 -> 55.556 | AO41: =AO39-AO40 -> 57.688 | AP41: =AP39-AP40 -> 212.6859 | AQ41: =AQ39-AQ40 -> 78.363 | AR41: =AR39-AR40 -> 52.031 | AS41: =AS39-AS40 -> 68.3551 | AT41: =AT39-AT40 -> 69.595434 | AU41: =AU39-AU40 -> 268.34443 | AV41: =AV39-AV40 -> 110.135 | ... EB41: =EB39-EB40 -> 4282.9088 | EG41: =S41+T41+U41+W41 -> 87.13 | EH41: =X41+Y41+Z41+AB41 -> 109.734 | EI41: =AC41+AD41+AE41+AG41 -> 150.978 | EJ41: =AH41+AI41+AJ41+AL41 -> 191.74152 | EK41: =AM41+AN41+AO41+AQ41 -> 234.81843 | EL41: =AR41+AS41+AT41+AV41 -> 300.11653 | EM41: =AW41+AX41+AY41+BA41 -> 423.778 | EN41: =BB41+BC41+BD41+BF41 -> 523.886 | EO41: =SUM(BG41:BI41,BK41) -> 612.33 | EP41: =SUM(BL41:BN41,BP41) -> 675.786 | EQ41: =SUM(BQ41:BS41,BU41) -> 171.66 | ER41: =ER39-ER40 -> 570.3 | ES41: =ES39-ES40 -> 1052.4 | ET41: =ET39-ET40 -> 1252.5 | EU41: =EU39-EU40 -> 1435.1 | EV41: =EV39-EV40 -> 2881 | EW41: =EW39-EW40 -> 2120.9 | EX41: =EX39-EX40 -> 2523.4 | EY41: =EY39-EY40 -> 2882.8 | ... FB41: =FB39-FB40 -> 3931.0324 | FD41: Net Income | FE41: =DN41 -> 2250.1 | FF41: 814.17669 | FG41: =FE41-FF41 -> 1435.9233 | FH41: =DI41 -> 751.5 | FI41: =FE41/FH41-1 -> 1.994145
A42: Cumulative changes in accting | BF42: 0 | BG42: 0 | BH42: 0 | BI42: 17.214 | BJ42: =SUM(BF42:BI42) -> 17.214 | EQ42: =SUM(BQ42:BS42,BU42) -> 0 | ER42: =SUM(BV42:BX42,BZ42) -> 0 | ES42: =SUM(CA42:CC42,CE42) -> 0 | ET42: =SUM(CF42:CH42,CJ42) -> 0 | EU42: =SUM(CK42,CL42,CM42,CO42) -> 0 | EV42: =SUM(CT42,CR42,CQ42,CP42) -> 0 | EW42: =CU42+CV42+CW42+CY42 -> 0 | EX42: =CZ42+DA42+DB42+DD42 -> 0 | EY42: =DE42+DF42+DG42+DI42 -> 0 | EZ42: =DJ42+DK42+DL42+DN42 -> 0 | FA42: =DO42+DP42+DQ42+DS42 -> 0 | FB42: =DT42+DU42+DV42+DX42 -> 0 | FD42: Cumulative changes in accting | FE42: =DN42 -> 0 | FF42: 0 | FG42: =FE42-FF42 -> 0 | FH42: =DI42 -> 0
A43: Net earnings attributable to Non-controlling interests | BU43: 0.4 | BV43: 0.1 | BW43: -3.3 | BX43: 3.5 | BY43: =SUM(BU43:BX43) -> 0.7 | BZ43: 2 | CA43: 0.5 | CB43: 0.6 | CC43: -0.4 | CD43: =SUM(BZ43:CC43) -> 2.7 | CE43: 1 | CF43: 0.8 | CG43: 0.7 | CH43: -0.2 | CI43: =SUM(CE43:CH43) -> 2.3 | CJ43: 0.1 | CK43: 0.2 | CL43: 0.2 | CM43: 0.3 | CN43: =SUM(CJ43:CM43) -> 0.8 | CO43: 0.2 | CP43: 0.3 | CQ43: 0 | CR43: -0.1 | CZ43: 0.7 | DB43: 0 | DC43: =SUM(CY43:DB43) -> 0.7 | DD43: 0.1 | DE43: -0.1 | DF43: 0.4 | DG43: 0.8 | DH43: =SUM(DD43:DG43) -> 1.2 | DI43: -0.3 | DJ43: 0 | DK43: -0.3 | DL43: 0.8 | DM43: =SUM(DI43:DL43) -> 0.2 | DN43: -0.1 | DR43: =SUM(DN43:DQ43) -> -0.1 | ER43: =SUM(BV43:BX43,BZ43) -> 2.3 | ES43: =SUM(CA43:CC43,CE43) -> 1.7 | ET43: =SUM(CF43:CH43,CJ43) -> 1.4 | EU43: =SUM(CK43,CL43,CM43,CO43) -> 0.9 | EV43: =SUM(CT43,CR43,CQ43,CP43) -> 0.2 | EW43: =CU43+CV43+CW43+CY43 -> 0 | EX43: =CZ43+DA43+DB43+DD43 -> 0.8 | EY43: =DE43+DF43+DG43+DI43 -> 0.8 | EZ43: =DJ43+DK43+DL43+DN43 -> 0.4 | FA43: =DO43+DP43+DQ43+DS43 -> 0 | FB43: =DT43+DU43+DV43+DX43 -> 0 | FD43: Net earnings attributable to Non-controlling interests | FE43: =DN43 -> -0.1 | FF43: 0 | FG43: =FE43-FF43 -> -0.1 | FH43: =DI43 -> -0.3
A44: Net earnings attributable to Starbucks | BU44: =BU41-BU43 -> 63.9 | BV44: =BV41-BV43 -> 25 | BW44: =BW41-BW43 -> 151.5 | BX44: =BX41-BX43 -> 150 | BY44: =SUM(BU44:BX44) -> 390.4 | BZ44: =BZ41-BZ43 -> 241.5 | CA44: =CA41-CA43 -> 217.3 | CB44: =CB41-CB43 -> 207.9 | CC44: =CC41-CC43 -> 278.9 | CD44: =SUM(BZ44:CC44) -> 945.6 | CE44: =CE41-CE43 -> 346.6 | CF44: =CF41-CF43 -> 261.6 | CG44: =CG41-CG43 -> 279.1 | CH44: =CH41-CH43 -> 358.5 | CI44: =SUM(CE44:CH44) -> 1245.8 | CJ44: =CJ41-CJ43 -> 382.1 | CK44: =CK41-CK43 -> 309.9 | CL44: =CL41-CL43 -> 333.1 | CM44: =CM41-CM43 -> 359 | CN44: =CN41-CN43 -> 1384.1 | CO44: =CO41-CO43 -> 432.2 | CP44: =CP41-CP43 -> 390.4 | CQ44: =CQ41-CQ43 -> 417.8 | ... EB44: =EB41-EB43 -> 4282.9088 | EG44: =EG41-EG43 -> 87.13 | EH44: =EH41-EH43 -> 109.734 | EI44: =EI41-EI43 -> 150.978 | EJ44: =EJ41-EJ43 -> 191.74152 | EK44: =EK41-EK43 -> 234.81843 | EL44: =EL41-EL43 -> 300.11653 | EM44: =EM41-EM43 -> 423.778 | EN44: =EN41-EN43 -> 523.886 | ... FB44: =FB41-FB43 -> 3931.0324 | FD44: Net earnings attributable to Starbucks | FE44: =DN44 -> 2250.2 | FF44: 814.17669 | FG44: =FE44-FF44 -> 1436.0233 | FH44: =DI44 -> 751.8 | FI44: =FE44/FH44-1 -> 1.9930833
A45: Non-recurring (charges)/gains | BQ45: -22.179 | BR45: =-(BR26*(1-0.27)) -> -122.421 | BS45: -65.6 | BT45: =SUM(BP45:BS45) -> -210.2 | BU45: =-(BU26*(1-0.4)) -> -45.3 | BV45: -96.1 | BW45: -28.4 | BX45: =-(BX26*(1-0.35)) -> -34.58 | BY45: =SUM(BU45:BX45) -> -204.38 | BZ45: -12.8 | CA45: -5.8 | CB45: -13.8 | CC45: =-(CC26*(1-CC66)) -> -4.3199224 | CD45: =SUM(BZ45:CC45) -> -36.719922 | CE45: =-(CE26*(1-CE66)) -> 0 | CF45: =-(CF26*(1-CF66)) -> 0 | CG45: =-(CG26*(1-CG66)) -> 0 | CH45: 76.85 | CI45: =SUM(CE45:CH45) -> 76.85 | CN45: =SUM(CJ45:CM45) -> 0 | CP45: 25 | CQ45: 0 | CR45: =25-1713.1 -> -1688.1 | CS45: =SUM(CO45:CR45) -> -1663.1 | CT45: =-CT26*(1-CT66) -> 13.339204 | CU45: =-CU26*(1-CU66) -> 0 | CW45: =CW54*0.03 -> 45.648 | CX45: =SUM(CT45:CW45) -> 58.987204 | CY45: =CY38-19.3*(1-0.342) -> 377.9006 | CZ45: =-11.9*(1-CZ66) -> -7.7407009 | DA45: =-11.5*(1-DA66) -> -7.6240741 | DB45: 0 | DC45: =SUM(CY45:DB45) -> 362.53583 | DD45: =-12.3*(1-DD66) -> -8.0589844 | DE45: =-13.9*(1-DE66) -> -9.2892841 | DF45: =DF54*0.02 -> 29.586 | DG45: =DG54*-0.02 -> -29.568 | DH45: =SUM(DD45:DG45) -> -17.330268 | DI45: =-14*(1-DI66) -> -9.2867861 | DJ45: =-13.8*(1-DJ66) -> -9.1887393 | DK45: =(-120.2+-14)*(1-0.2) -> -107.36 | DL45: =DL54*-0.01 -> -14.512 | DM45: =SUM(DI45:DL45) -> -140.34753 | DN45: =DN54*-(-0.92+-0.11+-0.24+0.02+0.01+0.1+0.22) -> 1319.832 | DO45: =-0.0075*DO54 -> -10.66416 | DP45: =-0.0075*DP54 -> -10.589322 | DQ45: =-0.0075*DQ54 -> -10.516393 | DR45: =SUM(DN45:DQ45) -> 1288.0621 | DS45: =-0.0075*DS54 -> -10.455923 | DT45: =-0.0075*DT54 -> -10.400314 | DU45: =-0.0075*DU54 -> -10.338884 | DV45: =-0.0075*DV54 -> -10.2791 | DW45: =SUM(DS45:DV45) -> -41.474222 | DX45: =-0.0075*DX54 -> -10.23984 | DY45: =-0.0075*DY54 -> -10.213347 | DZ45: =-0.0075*DZ54 -> -10.158529 | EA45: =-0.0075*EA54 -> -10.083291 | EB45: =SUM(DX45:EA45) -> -40.695007 | EQ45: =SUM(BQ45:BS45,BU45) -> -255.5 | ER45: =SUM(BV45:BX45,BZ45) -> -171.88 | ES45: =SUM(CA45:CC45,CE45) -> -23.919922 | ET45: =SUM(CF45:CH45,CJ45) -> 76.85 | EU45: =SUM(CK45,CL45,CM45,CO45) -> 0 | EV45: =SUM(CT45,CR45,CQ45,CP45) -> -1649.7608 | EW45: =CU45+CV45+CW45+CY45 -> 423.5486 | EX45: =CZ45+DA45+DB45+DD45 -> -23.423759 | EY45: =DE45+DF45+DG45+DI45 -> -18.55807 | EZ45: =DJ45+DK45+DL45+DN45 -> 1188.7713 | FA45: =DO45+DP45+DQ45+DS45 -> -42.225797 | FB45: =DT45+DU45+DV45+DX45 -> -41.258138 | FD45: Non-recurring charges | FE45: =DN45 -> 1319.832 | FF45: -10.750155 | FG45: =FE45-FF45 -> 1330.5822 | FH45: =DI45 -> -9.2867861
A47: Net Income adjusted for consensus | AZ47: =AZ41-AZ45 -> 389.203 | BA47: =BA41-BA45 -> 144.71 | BB47: =BB41-BB45 -> 100.461 | BC47: =BC41-BC45 -> 125.513 | BD47: =BD41-BD45 -> 123.722 | BE47: =BE41-BE45 -> 494.467 | BF47: =BF41-BF45 -> 174.19 | BG47: =BG41-BG45 -> 127.316 | ... BY47: =BY41-BY45 -> 595.48 | BZ47: =BZ44-BZ45 -> 254.3 | CA47: =CA44-CA45 -> 223.1 | CB47: =CB44-CB45 -> 221.7 | CC47: =CC44-CC45 -> 283.21992 | CD47: =CD44-CD45 -> 982.31992 | CE47: =CE44-CE45 -> 346.6 | CF47: =CF44-CF45 -> 261.6 | CG47: =CG44-CG45 -> 279.1 | ... CP47: =CP44-CP45 -> 365.4 | CQ47: =CQ41-CQ45 -> 417.8 | CR47: =CR41-CR45 -> 456 | CS47: =CS41-CS45 -> 1671.9 | CT47: =CT41-CT45 -> 527.3608 | CU47: =CU41-CU45 -> 426.9 | CV47: =CV41-CV45 -> 512.5 | CW47: =CW41-CW45 -> 541.952 | CX47: =CX41-CX45 -> 2008.7128 | ... DC47: =DC41-DC45 -> 2396.5642 | DD47: =DD41-(DD45/(1-DD66)) -> 700 | DE47: =DE41-(DE45/(1-DE66)) -> 588.9 | DF47: =DF41-(DF45/(1-DF66)) -> 712.40906 | DG47: =DG41-(DG45/(1-DG66)) -> 846.61665 | DH47: =DH41-(DH45/(1-DH66)) -> 2844.8122 | DI47: =DI41-(DI45/(1-DI66)) -> 765.5 | DJ47: =DJ41-(DJ45/(1-DJ66)) -> 666.6 | DK47: =DK41-(DK45/(1-DK66)) -> 854.73941 | ... EB47: =EB41-(EB45/(1-EB66)) -> 4337.902 | EQ47: =EQ41-EQ45 -> 427.16 | ER47: =ER44-ER45 -> 739.88 | ES47: =ES44-ES45 -> 1074.6199 | ET47: =ET44-ET45 -> 1174.25 | EU47: =EU44-EU45 -> 1434.2 | EV47: =EV44-EV45 -> 4530.5608 | EW47: =EW44-EW45 -> 1697.3514 | EX47: =EX44-EX45 -> 2546.0238 | EY47: =EY44-EY45 -> 2900.5581 | ... FB47: =FB44-FB45 -> 3972.2905 | FD47: Net Income adjusted for consensus | FE47: =DN47 -> 486.94147 | FF47: 830.2217 | FG47: =FE47-FF47 -> -343.28023 | FH47: =DI47 -> 765.5 | FI47: =FE47/FH47-1 -> -0.36389096
A48: FX Impact on EPS | BO48: -0.00011336429 | BP48: 0.0011552636 | BQ48: 0.00046232079 | BR48: 0.00043345453 | BS48: 0.055460506 | BT48: -0.0051459049 | BU48: 0.0021128758 | BV48: -0.0053947294 | BW48: -0.0020008575 | BX48: -0.0021736456 | BY48: -0.024424013 | BZ48: 0 | CA48: 0 | CB48: 0 | CC48: 0 | CD48: 0.0093784752 | CE48: 0.00090751977 | CF48: 0.00075027042 | CG48: 0.00087691377 | CH48: 0.00075575441 | CI48: 0.0040889041 | CJ48: -0.0013621479 | CK48: -0.00010122921 | CL48: -0.001627189 | CM48: -0.00033691623 | CN48: -0.0034617691 | CO48: 0.0010381129 | CP48: 0.00024489899 | CQ48: 0.00012297646 | CR48: -0.0011877102 | CS48: -0.00017693644 | CT48: -0.0021462485 | CU48: -0.003399157 | CV48: -0.0019527053 | CW48: -0.0011631687 | CX48: -0.0087115872 | CY48: -0.0047140801 | CZ48: -0.0050324919 | DA48: -0.0065622689 | DB48: -0.012559245 | DC48: -0.026813486 | DD48: -0.0095149919 | DE48: -0.0061006747 | DF48: -0.0038492764 | DG48: -0.000428066 | DH48: =SUM(DD48:DG48) -> -0.019893009 | DI48: -0.0017564977 | DJ48: 0.0015292461 | DK48: -0.00028808723 | DL48: 0.0018488439 | DM48: 0.0011292826 | DN48: 0.0035020903 | DO48: 0.0075561045 | DP48: 0.0083691458 | DQ48: 0.0022553708 | DR48: 0.022312931 | DS48: 0.0016348629 | DT48: 0.0017433944 | DU48: 0.00097430725 | DV48: 0.00078397913 | DW48: 0.0051461074 | DX48: 0.0018029111 | DY48: 0.001917334 | DZ48: 0.0010709336 | EA48: 0.00086313961 | EB48: 0.0056642149 | FD48: FX Impact on EPS | FE48: =DN48 -> 0.0035020903 | FF48: 0.0044027878 | FG48: =FE48-FF48 -> -0.00090069748 | FH48: =DI48 -> -0.0017564977 | FI48: =FE48/FH48-1 -> -2.9937915
A50: EPS Operating | B50: 0.02 | C50: =(C41+1.111)/C54 -> 0.04295418 | D50: =(D41+1.111)/(D54) -> -0.0018087011 | E50: =(E41+1.111)/(E54) -> 0.0067735081 | F50: =(F41+1.111)/F54 -> 0.0056320602 | G50: =G41/G54 -> 0.022685 | H50: =(H41+1.111)/H54 -> 0.0089853561 | I50: =(I41+1.111)/(I54) -> 0.0049192729 | J50: =(J41+1.111)/(J54) -> 0.0081664804 | K50: =(K41+1.111)/K54 -> 0.010661497 | L50: =SUM(H50:K50) -> 0.032732606 | M50: =(M41+1.111)/M54 -> 0.010446387 | N50: =(N41+1.111)/(N54) -> 0.0072031351 | O50: =(O41+1.111)/(O54) -> 0.010648256 | P50: =(P41+1.111)/P54 -> 0.013059507 | Q50: =SUM(M50:P50) -> 0.041357285 | R50: =(R41+0.5555)/R54 -> 0.014670198 | S50: =S41/S54 -> 0.0095311561 | T50: =T41/T54 -> 0.014097506 | U50: =U41/U54 -> 0.01728509 | V50: =V41/V54 -> 0.055335323 | W50: =W41/W54 -> 0.018017453 | X50: =X41/X54 -> 0.01191734 | Y50: =Y41/Y54 -> 0.016094112 | Z50: =Z41/Z54 -> 0.021518212 | ... BN50: =BN41/BN54 -> 0.10440014 | BO50: =BO53 -> 0.43688973 | BP50: =BP41/BP54 -> 0.13968318 | BQ50: =(BQ41-BQ45)/BQ54 -> 0.088488435 | BR50: =(BR41-BR45)/BR54 -> 0.079008473 | BS50: =(BS41-BS45)/BS54 -> 0.047917509 | BT50: =(BT41-BT45)/BT54 -> 0.35543985 | BU50: =(BU41-BU45)/BU54 -> 0.074144229 | BV50: =(BV41-BV45)/BV54 -> 0.08190296 | BW50: =(BW41-BW45)/BW54 -> 0.11825365 | BX50: =(BX41-BX45)/BX54 -> 0.12407969 | BY50: =(BY41-BY45)/BY54 -> 0.39916879 | BZ50: =(BZ44-BZ45)/BZ54 -> 0.16666667 | CA50: =(CA44-CA45)/CA54 -> 0.14545573 | CB50: =(CB44-CB45)/CB54 -> 0.14458067 | CC50: =(CC44-CC45)/CC54 -> 0.1861085 | CD50: =(CD41-CD45)/CD54 -> 0.64447783 | CE50: =(CE44-CE45)/CE54 -> 0.22603365 | CF50: =(CF44-CF45)/CF54 -> 0.16947396 | CG50: 0.36 | CH50: =(CH44-CH45)/CH54 -> 0.18324658 | CI50: =(CI44-CI45)/CI54 -> 0.75935429 | CJ50: =(CJ44-CJ45)/CJ54 -> 0.24860117 | CK50: =(CK44-CK45)/CK54 -> 0.20037502 | CL50: =(CL44-CL45)/CL54 -> 0.21440525 | CM50: =(CM44-CM45)/CM54 -> 0.23206206 | CN50: =(CN44-CN45)/CN54 -> 0.89527814 | CO50: =(CO44-CO45)/CO54 -> 0.28385656 | ... EB50: =(EB44-EB45)/EB54 -> 3.1873226 | EG50: =EG41/EG54 -> 0.058989441 | EH50: =EH41/EH54 -> 0.072460667 | EI50: =EI41/EI54 -> 0.096976899 | EJ50: =EJ41/EJ54 -> 0.12168294 | EK50: =EK41/EK54 -> 0.14699147 | EL50: =EL41/EL54 -> 0.18589617 | EM50: =EM41/EM54 -> 0.25643845 | EN50: =EN41/EN54 -> 0.32499222 | ... EP50: =EP41/EP54 -> 0.44435823 | EQ50: =EQ47/EQ54 -> 0.28940379 | ER50: =ER47/ER54 -> 0.49203964 | ES50: =ES47/ES54 -> 0.70209063 | ET50: =ET47/ET54 -> 0.76232674 | EU50: =EU47/EU54 -> 0.92981944 | EV50: =CP50+CQ50+CR50+CT50 -> 1.1567633 | EW50: =EW47/EW54 -> 1.1149182 | EX50: =EX47/EX54 -> 1.6861084 | EY50: =EY47/EY54 -> 1.9615595 | EZ50: =EZ47/EZ54 -> 0.94101806 | FA50: =FA47/FA54 -> 2.5041882 | FB50: =FB47/FB54 -> 2.8883687 | FD50: EPS (FD) | FE50: =DN50 -> 0.64852084 | FF50: 0.57552205 | FG50: =FE50-FF50 -> 0.072998794 | FH50: =DI50 -> 0.51757007 | FI50: =FE50/FH50-1 -> 0.25301072
A51: Stock-Based Compensation Expense | AP51: =37.447/AP54 -> 0.023551572 | AU51: =37.436/AU54 -> 0.023301498 | AV51: =8.332/AV54 -> 0.0051098382 | AW51: =12.407/AW54 -> 0.0075365865 | AX51: =11.299/AX54 -> 0.0068513834 | AY51: =(13.018)/AY54 -> 0.0078729586 | AZ51: =45.056/AZ54 -> 0.027375354 | BA51: =12.074/BA54 -> 0.0072677586 | BB51: =15.983/BB54 -> 0.0096508474 | BC51: =15.276/BC54 -> 0.0094525257 | BD51: =15.409/BD54 -> 0.0096919021 | BE51: =58.742/BE54 -> 0.036019607 | BF51: =15.097/BF54 -> 0.0095195277 | BG51: =18/BG54 -> 0.011326268 | BH51: =17/BH54 -> 0.010648173 | BI51: =18.2236/BI54 -> 0.011619289 | BJ51: =SUM(BF51:BI51) -> 0.043113258 | EN51: =BB51+BC51+BD51+BF51 -> 0.038314803 | FD51: Stock-Based Compensation Expense | FE51: =DN51 -> 0 | FF51: 0 | FG51: =FE51-FF51 -> 0 | FH51: =DI51 -> 0
A52: Non-recurring charges | BI52: =BI42/BI54 -> 0.010975572 | BJ52: =BJ42/BJ54 -> 0.01086051 | BK52: =BK45/BK54 -> 0 | BL52: =BL45/BL54 -> 0 | BM52: =BM45/BM54 -> 0 | BN52: =BN45/BN54 -> 0 | BO52: =BO45/BO54 -> 0 | BP52: =BP45/BP54 -> 0 | BQ52: =BQ45/BQ54 -> -0.015 | BR52: =BR45/BR54 -> -0.083655187 | ... DG52: =DG45/DG54 -> -0.02 | DH52: =SUM(DD52:DG52) -> -0.01160954 | DI52: =DI45/DI54 -> -0.0063153935 | DJ52: =DJ45/DJ54 -> -0.0062730334 | DK52: =DK45/DK54 -> -0.073564479 | DL52: =DL45/DL54 -> -0.01 | DM52: =DM45/DM54 -> -0.096031424 | DN52: =DN45/DN54 -> 0.92 | DO52: =DO45/DO54 -> -0.0075 | DP52: =DP45/DP54 -> -0.0075 | ... EB52: =EB45/EB54 -> -0.03 | FD52: Non-recurring charges | FE52: =DN52 -> 0.92 | FF52: -0.0075 | FG52: =FE52-FF52 -> 0.9275 | FH52: =DI52 -> -0.0063153935
A53: EPS Reported (GAAP) | AK53: =AK50-AK51 -> 0.11432449 | AP53: =AP50-AP51 -> 0.11021314 | AU53: =AU50-AU51 -> 0.14372562 | AV53: =AV50-AV51 -> 0.062433613 | AW53: =AW50-AW51 -> 0.040381816 | AX53: =AX50-AX51 -> 0.052318277 | AY53: =AY50-AY51 -> 0.054178752 | AZ53: =AZ50-AZ51 -> 0.20909859 | BA53: =BA50-BA51 -> 0.0798382 | BB53: =BB50-BB51 -> 0.051009465 | ... BE53: =BE50-BE51 -> 0.26717925 | BF53: =(BF41-BF42)/BF54 -> 0.10983682 | BG53: =(BG41-BG42)/BG54 -> 0.080111954 | BH53: =(BH41-BH42)/BH54 -> 0.091134582 | BI53: =(BI41-BI42)/BI54 -> 0.074782962 | BJ53: =(BJ41-BJ42)/BJ54 -> 0.35601891 | BK53: =BK41/BK54 -> 0.13095454 | BL53: =BL41/BL54 -> 0.097434937 | BM53: =BM41/BM54 -> 0.10368747 | BN53: =BN41/BN54 -> 0.10440014 | BO53: =BO41/BO54 -> 0.43688973 | BP53: =BP41/BP54 -> 0.13968318 | BQ53: =BQ41/BQ54 -> 0.073488435 | BR53: =BR41/BR54 -> -0.0046467131 | ... BT53: =BT41/BT54 -> 0.21330719 | BU53: =BU44/BU54 -> 0.043228251 | BV53: =BV44/BV54 -> 0.016894175 | BW53: =BW44/BW54 -> 0.10144636 | BX53: =BX44/BX54 -> 0.098957646 | BY53: =BY44/BY54 -> 0.26169728 | BZ53: =BZ44/BZ54 -> 0.15827762 | CA53: =CA44/CA54 -> 0.14167427 | CB53: =CB44/CB54 -> 0.13558106 | ... EB53: =EB44/EB54 -> 3.1573226 | EN53: =EN50-EN51 -> 0.28667742 | EO53: =EO50-EO51 -> 0.38757124 | EP53: =EP50-EP51 -> 0.44435823 | EQ53: =EQ41/EQ54 -> 0.11630081 | ER53: =ER41/ER54 -> 0.37926448 | ES53: =ES41/ES54 -> 0.6875735 | ET53: =ET41/ET54 -> 0.81312689 | EU53: =EU41/EU54 -> 0.93040293 | EV53: =EV41/EV54 -> 1.8870149 | EW53: =EW41/EW54 -> 1.3931293 | EX53: =EX41/EX54 -> 1.6711258 | ... FB53: =FB41/FB54 -> 2.8583687 | FD53: EPS including One-time charges | FE53: =DN53 -> 1.5685208 | FF53: 0.56802205 | FG53: =FE53-FF53 -> 1.0004988 | FH53: =DI53 -> 0.51125468 | FI53: =FE53/FH53-1 -> 2.0679834
A54: Avg. Shs. Outs. (FD) | B54: =(239.03*2)*2 -> 956.12 | C54: =(66.488*2*2*2)*2 -> 1063.808 | D54: =(72.324*2*2*2)*2 -> 1157.184 | E54: =(73.411*2*2*2)*2 -> 1174.576 | F54: =(73.652*2*2*2)*2 -> 1178.432 | G54: =(287.635*2)*2 -> 1150.54 | H54: =(74.058*2*2*2)*2 -> 1184.928 | I54: =(74.429*2*2*2)*2 -> 1190.864 | J54: =(80.535*2*2*2)*2 -> 1288.56 | K54: =(81.051*2*2*2)*2 -> 1296.816 | L54: =(2*323.665)*2 -> 1294.66 | M54: =(89.726*2*2*2)*2 -> 1435.616 | N54: =(89.822*2*2*2)*2 -> 1437.152 | O54: =(89.868*2*2*2)*2 -> 1437.888 | P54: =(90.906*2*2*2)*2 -> 1454.496 | Q54: =(2*360.635)*2 -> 1442.54 | R54: =((89.825+1.817)*2*2*2)*2 -> 1466.272 | S54: =((89.738+1.817)*2*2*2)*2 -> 1464.88 | T54: =(92.574*2*2*2)*2 -> 1481.184 | U54: =(92.399*2*2*2)*2 -> 1478.384 | V54: =(2*367.541)*2 -> 1470.164 | W54: =(370.932*2)*2 -> 1483.728 | X54: =(2*376.699)*2 -> 1506.796 | Y54: =(2*382.671)*2 -> 1530.684 | Z54: =(2*376.344)*2 -> 1505.376 | AA54: =(2*377.062)*2 -> 1508.248 | AB54: =(2*378.68)*2 -> 1514.72 | AC54: =(2*384.835)*2 -> 1539.34 | AD54: =(2*387.762)*2 -> 1551.048 | AE54: =(2*390.588)*2 -> 1562.352 | AF54: =(2*385.999)*2 -> 1543.996 | AG54: =(2*393.66)*2 -> 1574.64 | AH54: =(2*395.701)*2 -> 1582.804 | AI54: =(2*394.482)*2 -> 1577.928 | AJ54: =(2*393.565)*2 -> 1574.26 | AK54: =(2*394.349)*2 -> 1577.396 | AL54: =(2*391.999)*2 -> 1567.996 | AM54: =(2*397.861)*2 -> 1591.444 | AN54: =(2*401.191)*2 -> 1604.764 | AO54: =(2*399.227)*2 -> 1596.908 | AP54: =(2*397.5)*2 -> 1590 | AQ54: =(2*399.218)*2 -> 1596.872 | AR54: =(2*399.622)*2 -> 1598.488 | AS54: =(2*402.664)*2 -> 1610.656 | AT54: =(2*404.5)*2 -> 1618 | AU54: =(2*401.648)*2 -> 1606.592 | AV54: =(2*407.645)*2 -> 1630.58 | AW54: =(2*411.559)*2 -> 1646.236 | AX54: =(2*412.289)*2 -> 1649.156 | AY54: 1653.508 | AZ54: 1645.86 | BA54: 1661.31 | BB54: =(2*414.031)*2 -> 1656.124 | BC54: =(2*404.019)*2 -> 1616.076 | BD54: 1589.884 | BE54: 1630.834 | BF54: 1585.898 | BG54: 1589.226 | BH54: 1596.518 | BI54: 1568.392 | BJ54: =(AVERAGE(BF54:BI54)) -> 1585.0085 | BK54: 1565.528 | BL54: 1548.11 | BM54: 1527.118 | BN54: 1518.226 | BO54: =(AVERAGE(BK54:BN54)) -> 1539.7455 | BP54: 1489.8 | BQ54: 1478.6 | BR54: 1463.4 | BS54: 1483.8 | BT54: =(AVERAGE(BP54:BS54)) -> 1478.9 | BU54: 1478.2 | BV54: 1479.8 | BW54: 1493.4 | BX54: 1515.8 | BY54: =(AVERAGE(BU54:BX54)) -> 1491.8 | BZ54: 1525.8 | CA54: 1533.8 | CB54: 1533.4 | CC54: 1521.8 | CD54: 1528.4 | CE54: 1533.4 | CF54: 1543.6 | CG54: 1543.8 | CH54: 1537 | CI54: =769.7*2 -> 1539.4 | CJ54: 1537 | CK54: 1546.6 | CL54: 1553.6 | CM54: 1547 | CN54: =773*2 -> 1546 | CO54: 1522.6 | CP54: 1522.6 | CQ54: 1523.8 | CR54: 1528.2 | CS54: =762.3*2 -> 1524.6 | CT54: 1532.4 | CU54: 1529.2 | CV54: 1522 | CW54: 1521.6 | CX54: =763.1*2 -> 1526.2 | CY54: 1516.8 | CZ54: 1516.5 | DA54: 1515.7 | DB54: 1504.5 | DC54: =AVERAGE(CY54:DB54) -> 1513.375 | DD54: 1503.3 | DE54: 1486.6 | DF54: 1479.3 | DG54: 1478.4 | DH54: =AVERAGE(DD54:DG54) -> 1486.9 | DI54: 1470.5 | DJ54: 1464.8 | DK54: 1459.4 | DL54: 1451.2 | DM54: =AVERAGE(DI54:DL54) -> 1461.475 | DN54: 1434.6 | DO54: =DO124 -> 1421.8879 | DP54: =DP124 -> 1411.9096 | DQ54: =DQ124 -> 1402.1857 | DR54: =AVERAGE(DN54:DQ54) -> 1417.6458 | DS54: =DS124 -> 1394.123 | DT54: =DT124 -> 1386.7086 | DU54: =DU124 -> 1378.5179 | DV54: =DV124 -> 1370.5467 | DW54: =AVERAGE(DS54:DV54) -> 1382.4741 | DX54: =DX124 -> 1365.3119 | DY54: =DY124 -> 1361.7797 | DZ54: =DZ124 -> 1354.4705 | EA54: =EA124 -> 1344.4388 | EB54: =AVERAGE(DX54:EA54) -> 1356.5002 | EG54: =AVERAGE(S54,T54,U54,W54) -> 1477.044 | EH54: =AVERAGE(X54,Y54,Z54,AB54) -> 1514.394 | EI54: =AVERAGE(AC54,AD54,AE54,AG54) -> 1556.845 | EJ54: =AVERAGE(AH54:AJ54,AL54) -> 1575.747 | EK54: =AVERAGE(AM54:AO54,AQ54) -> 1597.497 | EL54: =AVERAGE(AR54:AT54,AV54) -> 1614.431 | EM54: =AVERAGE(AW54:AY54,BA54) -> 1652.5525 | EN54: =AVERAGE(BB54:BD54,BF54) -> 1611.9955 | EO54: =AVERAGE(BG54:BI54,BK54) -> 1579.916 | EP54: =AVERAGE(BL54,BM54,BN54,BP54) -> 1520.8135 | EQ54: =AVERAGE(BQ54,BR54,BS54,BU54) -> 1476 | ER54: =AVERAGE(BV54,BW54,BX54,BZ54) -> 1503.7 | ES54: =AVERAGE(CA54,CB54,CC54,CE54) -> 1530.6 | ET54: =AVERAGE(CF54,CG54,CH54,CJ54) -> 1540.35 | EU54: =AVERAGE(CO54,CM54,CL54,CK54) -> 1542.45 | EV54: =AVERAGE(CT54,CR54,CQ54,CP54) -> 1526.75 | EW54: =AVERAGE(CY54,CW54,CV54,CU54) -> 1522.4 | EX54: =AVERAGE(DD54,DB54,DA54,CZ54) -> 1510 | EY54: =AVERAGE(DI54,DG54,DF54,DE54) -> 1478.7 | EZ54: =AVERAGE(DN54,DL54,DK54,DJ54) -> 1452.5 | FA54: =AVERAGE(DS54,DQ54,DP54,DO54) -> 1407.5266 | FB54: =AVERAGE(DV54,DX54,DU54,DT54) -> 1375.2713 | FD54: Avg. Shs. Outs. (FD) | FE54: =DN54 -> 1434.6 | FF54: 1433.354 | FG54: =FE54-FF54 -> 1.2459745 | FH54: =DI54 -> 1470.5 | FI54: =FE54/FH54-1 -> -0.024413465 | FJ54: =FE54/FF54-1 -> 0.00086927199
A55: Margin Analysis | BC55: =BC54/BB54-1 -> -0.024181764 | FD55: Margin Analysis
A56: Cost of sales | BP56: =BP19/BP17 -> 0.3289854 | BQ56: =BQ19/BQ17 -> 0.32446556 | BR56: =BR19/BR17 -> 0.33439528 | BS56: =BS19/BS17 -> 0.34915524 | BT56: =BT19/BT17 -> 0.33412309 | BU56: =BU19/BU17 -> 0.34999235 | BV56: =BV19/BV17 -> 0.33116187 | BW56: =BW19/BW17 -> 0.31885686 | ... EB56: =EB19/EB17 -> 0
A57: Occupancy costs | BP57: =BP20/BP17 -> 0.099544732 | BQ57: =BQ20/BQ17 -> 0.11365796 | BR57: =BR20/BR17 -> 0.11748708 | BS57: =BS20/BS17 -> 0.12363347 | BT57: =BT20/BT17 -> 0.11327169 | BU57: =BU20/BU17 -> 0.10767819 | BV57: =BV20/BV17 -> 0.11601594 | BW57: =BW20/BW17 -> 0.11518782 | ... EB57: =EB20/EB17 -> 0
A58: Cost of Sales and Related Occupancy Costs | B58: =B21/B17 -> 0.45740077 | C58: =C21/C17 -> 0.44989398 | D58: =D21/D17 -> 0.45136629 | E58: =E21/E17 -> 0.45079464 | F58: =F21/F17 -> 0.4632478 | G58: =G21/G17 -> 0.45415853 | H58: =H21/H17 -> 0.51117455 | I58: =I21/I17 -> 0.50086909 | ... EB58: =EB21/EB17 -> 0.40043501 | EN58: =EN21/EN17 -> 0.40744071 | EO58: =EO21/EO17 -> 0.41244392 | EP58: =EP21/EP17 -> 0.42758232 | EQ58: =EQ21/EQ17 -> 0.45511505 | ER58: =ER21/ER17 -> 0.43247893 | ES58: =ES21/ES17 -> 0.41197933 | ET58: =ET21/ET17 -> 0.42852099 | EU58: =EU21/EU17 -> 0.43532672 | ... FB58: =FB21/FB17 -> 0.40303245 | FD58: Cost of Sales and Related Occupancy Costs | FE58: =DN58 -> 0.41208818 | FF58: 0.39804178 | FG58: =FE58-FF58 -> 0.014046398 | FH58: =DI58 -> 0.40032095 | FI58: =FE58-FH58 -> 0.011767229
A59: Store Expense % Of Retail Sales | B59: 0.3625586 | C59: 0.36143019 | D59: 0.38992335 | E59: 0.37894696 | F59: 0.35205259 | G59: 0.36943786 | H59: =H22/H10 -> 0.323196 | I59: =I22/I10 -> 0.35525053 | J59: =J22/J10 -> 0.35767433 | K59: =K22/K10 -> 0.36546936 | L59: =L22/L10 -> 0.35095964 | M59: =M22/M10 -> 0.34415314 | N59: =N23/N10 -> 0.037180285 | O59: =O22/O10 -> 0.38984362 | P59: =P22/P10 -> 0.39021177 | Q59: =Q22/Q10 -> 0.37554347 | R59: =R22/R10 -> 0.35676594 | S59: =S22/S10 -> 0.3749492 | T59: =T22/T10 -> 0.37700286 | U59: =U22/U10 -> 0.39054111 | V59: =V22/V10 -> 0.375134 | ... EB59: =EB22/EB10 -> 0.36504261 | EN59: =EN22/EN10 -> 0.40045421 | EO59: =EO22/EO10 -> 0.40759066 | EP59: =EP22/EP10 -> 0.40408014 | EQ59: =EQ22/EQ10 -> 0.43673545 | ER59: =ER22/ER10 -> 0.40793549 | ES59: =ES22/ES10 -> 0.38843881 | ET59: =ET22/ET10 -> 0.3735398 | EU59: =EU22/EU10 -> 0.37173726 | ... FB59: =FB22/FB10 -> 0.36622294 | FD59: Store Expense % Of Store Sales | FE59: =DN59 -> 0.36631659 | FF59: 0.37149836 | FG59: =FE59-FF59 -> -0.0051817708 | FH59: =DI59 -> 0.3665451 | FI59: =FE59-FH59 -> -0.00022850791
A60: Other Op Expense % Of Spec. Sales | B60: =B23/B15 -> 0.32763168 | C60: =C23/C15 -> 0.32287695 | D60: =D23/D15 -> 0.25133316 | E60: =E23/E15 -> 0.28401745 | F60: =F23/F15 -> 0.2985063 | G60: =G23/G15 -> 0.28941465 | H60: =H23/H15 -> 0.34906115 | I60: =I23/I15 -> 0.21083 | ... EB60: =EB23/EB15 -> 0.10690743 | EN60: =EN23/EN15 -> 0.20130268 | EO60: =EO23/EO15 -> 0.21937004 | EP60: =EP23/EP15 -> 0.21100634 | EQ60: =EQ23/EQ15 -> 0.19400245 | ER60: =ER23/ER15 -> 0.16635125 | ES60: =ES23/ES15 -> 0.17170269 | ET60: =ET23/ET15 -> 0.17796012 | EU60: =EU23/EU15 -> 0.15183651 | ... FB60: =FB23/FB15 -> 0.10983694 | FD60: Other Op Expense % Of Spec. Sales | FE60: =DN60 -> 0.10631429 | FF60: 0.11073158 | FG60: =FE60-FF60 -> -0.0044172894 | FH60: =DI60 -> 0.11506806 | FI60: =FE60-FH60 -> -0.0087537717
A61: D&A | B61: =B24/B17 -> 0.043994342 | C61: =C24/C17 -> 0.038634298 | D61: =D24/D17 -> 0.050952894 | E61: =E24/E17 -> 0.049658483 | F61: =F24/F17 -> 0.053733189 | G61: =G24/G17 -> 0.048334953 | H61: =H24/H17 -> 0.044827973 | I61: =I24/I17 -> 0.055986303 | ... EB61: =EB24/EB17 -> 0.043125313 | EN61: =EN24/EN17 -> 0.052562703 | EO61: =EO24/EO17 -> 0.049474982 | EP61: =EP24/EP17 -> 0.049897724 | EQ61: =EQ24/EQ17 -> 0.053799386 | ER61: =ER24/ER17 -> 0.053733518 | ES61: =ES24/ES17 -> 0.046417631 | ET61: =ET24/ET17 -> 0.043547513 | EU61: =EU24/EU17 -> 0.041377996 | ... FB61: =FB24/FB17 -> 0.043609896 | FD61: D&A | FE61: =DN61 -> 0.042609941 | FF61: 0.042485983 | FG61: =FE61-FF61 -> 0.00012395791 | FH61: =DI61 -> 0.043555618 | FI61: =FE61-FH61 -> -0.00094567635
A62: General & Administrative Exp. | B62: 0.070099641 | C62: 0.049738197 | D62: 0.064175724 | E62: 0.053761727 | F62: 0.07728397 | G62: 0.061567629 | H62: =H25/H17 -> 0.038929555 | I62: =I25/I17 -> 0.063147342 | J62: =J25/J17 -> 0.056513139 | K62: =K25/K17 -> 0.055503221 | L62: =L25/L17 -> 0.053551713 | M62: =M25/M17 -> 0.053798812 | N62: =N25/N17 -> 0.061201276 | O62: =O25/O17 -> 0.058081976 | ... EB62: =EB25/EB17 -> 0.060452765 | EN62: =ES66 -> 0.33219113 | EO62: =EO25/EO17 -> 0.056639077 | EP62: =EP25/EP17 -> 0.050373833 | EQ62: =EQ25/EQ17 -> 0.042548824 | ER62: =ER25/ER17 -> 0.049048279 | ES62: =ES25/ES17 -> 0.056494902 | ET62: =ET25/ET17 -> 0.062037143 | EU62: =EU25/EU17 -> 0.061700427 | EV62: =EV25/EV17 -> 0.061946151 | ... FB62: =FB25/FB17 -> 0.05982345 | FD62: General & Administrative Exp. | FE62: =DN62 -> 0.062416649 | FF62: 0.066707535 | FG62: =FE62-FF62 -> -0.0042908858 | FH62: =DI62 -> 0.062167489 | FI62: =FE62-FH62 -> 0.00024915943
A63: Operating Margin | B63: =B29/B17 -> 0.08177999 | C63: =C29/C17 -> 0.12258427 | D63: =D29/D17 -> 0.06998111 | E63: =E29/E17 -> 0.086486985 | F63: =F29/F17 -> 0.066223528 | G63: 0.086229504 | H63: =H29/H17 -> 0.093041637 | I63: =I29/I17 -> 0.049287477 | J63: =J29/J17 -> 0.082430065 | K63: =K29/K17 -> 0.096769102 | L63: =L29/L17 -> 0.081802037 | M63: =M29/M17 -> 0.086452859 | N63: =N29/N17 -> 0.062801128 | O63: =O29/O17 -> 0.092400539 | ... EB63: =EB29/EB17 -> 0.19699921 | EN63: =EN29/EN17 -> 0.12410826 | EO63: =EO29/EO17 -> 0.11376265 | EP63: =EP29/EP17 -> 0.10865116 | EQ63: =EQ29/EQ17 -> 0.028195805 | ER63: =ER29/ER17 -> 0.080640754 | ES63: =ES29/ES17 -> 0.14345023 | ET63: =ET29/ET17 -> 0.14387757 | EU63: =EU29/EU17 -> 0.15191971 | ... FB63: =FB29/FB17 -> 0.19297205 | FD63: Operating Profit | FE63: =DN63 -> 0.18375949 | FF63: 0.19583561 | FG63: =FE63-FF63 -> -0.012076127 | FH63: =DI63 -> 0.19756144 | FI63: =FE63-FH63 -> -0.013801956
A64: Operating margin before charges/gains | B64: =B30/B17 -> 0.08177999 | C64: =C30/C17 -> 0.12258427 | D64: =D30/D17 -> 0.06998111 | E64: =E30/E17 -> 0.086486985 | F64: =F30/F17 -> 0.066223528 | G64: =G30/G17 -> 0.086229504 | H64: =H30/H17 -> 0.093041637 | I64: =I30/I17 -> 0.049287477 | ... EB64: =EB30/EB17 -> 0.19884465 | EQ64: =EQ30/EQ17 -> 0.065094911 | ER64: =ER30/ER17 -> 0.10848909 | ES64: =ES30/ES17 -> 0.14662338 | ET64: =ET30/ET17 -> 0.14387757 | EU64: =EU30/EU17 -> 0.15191971 | EV64: =EV30/EV17 -> 0.17119106 | EW64: =EW30/EW17 -> 0.18838433 | EX64: =EX30/EX17 -> 0.1921198 | ... FB64: =FB30/FB17 -> 0.19497315 | FD64: Operating profit before charges | FE64: =DN64 -> 0.1922222 | FF64: 0.19841497 | FG64: =FE64-FF64 -> -0.0061927653 | FH64: =DI64 -> 0.20000349 | FI64: =FE64-FH64 -> -0.0077812847
A65: EBITDA | B65: =B31/B17 -> 0.12577433 | C65: =C31/C17 -> 0.16121857 | D65: =D31/D17 -> 0.120934 | E65: =E31/E17 -> 0.13614547 | F65: =F31/F17 -> 0.11995672 | G65: =G31/G17 -> 0.13456446 | H65: =H31/H17 -> 0.13786961 | I65: =I31/I17 -> 0.10527378 | ... EB65: =EB31/EB17 -> 0.24012452 | EN65: =EN31/EN17 -> 0.18065095 | EO65: =EO31/EO17 -> 0.16626909 | EP65: =EP31/EP17 -> 0.16107877 | EQ65: =EQ31/EQ17 -> 0.1188943 | ER65: =ER31/ER17 -> 0.13437427 | ES65: =ES31/ES17 -> 0.18986786 | ET65: =ET31/ET17 -> 0.18742508 | EU65: =EU31/EU17 -> 0.1932977 | ... FB65: =FB31/FB17 -> 0.23658195 | FD65: EBITDA | FE65: =DN65 -> 0.22636943 | FF65: 0.2383216 | FG65: =FE65-FF65 -> -0.011952169 | FH65: =DI65 -> 0.24111706 | FI65: =FE65-FH65 -> -0.014747632
A66: Tax Rate | B66: 0.39319232 | C66: 0.39295775 | D66: 0.39795799 | E66: 0.39515773 | F66: 0.39441096 | G66: 0.39502109 | H66: =H40/H39 -> 0.39576733 | I66: =I40/I39 -> 0.385 | J66: =J40/J39 -> 0.39100615 | K66: =K40/K39 -> 0.37321305 | L66: =L40/L39 -> 0.385028 | M66: =M40/M39 -> 0.39346554 | N66: =N40/N39 -> 0.39506415 | O66: =O40/O39 -> 0.391889 | ... AK66: =AK40/AK39 -> 0.37393898 | AL66: 0.37 | AM66: 0.37 | AN66: 0.37 | AO66: 0.37 | AP66: =AP40/AP39 -> 0.37260611 | AQ66: =AQ40/AQ39 -> 0.37475166 | AR66: =AR40/AR39 -> 0.40010146 | AS66: =AS40/AS39 -> 0.38492582 | AT66: 0.384857 | AU66: =AU40/AU39 -> 0.38500224 | AV66: =AV40/AV39 -> 0.38080835 | AW66: =AW40/AW39 -> 0.38102225 | AX66: =AX40/AX39 -> 0.38072754 | AY66: =AY40/AY39 -> 0.35090971 | AZ66: =AZ40/AZ39 -> 0.37322069 | BA66: =BA40/BA39 -> 0.37709039 | BB66: =BB40/BB39 -> 0.37714828 | ... CR66: =CR40/CR39 -> 0.39961992 | CS66: 0.326 | CT66: =CT40/CT39 -> 0.33964338 | CU66: =CU40/CU39 -> 0.3383447 | CV66: =CV40/CV39 -> 0.33570966 | CW66: =CW40/CW39 -> 0.36420688 | CX66: =CX40/CX39 -> 0.34560243 | CY66: =CY40/CY39 -> 0.24240092 | CZ66: =CZ40/CZ39 -> 0.34952093 | DA66: =DA40/DA39 -> 0.33703704 | ... DN66: =DN40/DN39 -> 0.25143884 | DO66: 0.26 | DP66: 0.26 | DQ66: 0.26 | DR66: =DR40/DR39 -> 0.2560159 | DS66: 0.26 | DT66: 0.26 | DU66: 0.26 | DV66: 0.26 | DW66: =DW40/DW39 -> 0.26 | DX66: =DS66 -> 0.26 | DY66: =DT66 -> 0.26 | DZ66: =DU66 -> 0.26 | EA66: =DV66 -> 0.26 | EB66: =EB40/EB39 -> 0.26 | EN66: =EN40/EN39 -> 0.37950181 | EO66: =EO40/EO39 -> 0.35697994 | EP66: =EP40/EP39 -> 0.36059669 | EQ66: =EQ40/EQ39 -> 0.25707608 | ER66: =ER40/ER39 -> 0.31347057 | ES66: =ES40/ES39 -> 0.33219113 | ET66: =ET40/ET39 -> 0.32047526 | EU66: =EU40/EU39 -> 0.31982558 | ... FB66: =FB40/FB39 -> 0.26 | FD66: Tax Rate | FE66: =DN66 -> 0.25143884 | FF66: 0.33 | FG66: =FE66-FF66 -> -0.078561163 | FH66: =DI66 -> 0.33665813 | FI66: =FE66-FH66 -> -0.085219297 | FK66: =(FE66-FF66)*FE39/FE54 -> -0.16460825
A67: Net Income | B67: 0.045923263 | C67: 0.074602969 | D67: 0.050735316 | E67: 0.057437025 | F67: 0.042711393 | G67: 0.056103454 | H67: =H41/H17 -> 0.056247309 | I67: =I41/I17 -> 0.030904342 | J67: =J41/J17 -> 0.053190167 | K67: =K41/K17 -> 0.064745271 | L67: =L41/L17 -> 0.052342852 | M67: =M41/M17 -> 0.057821231 | N67: =N41/N17 -> 0.042728996 | O67: =O41/O17 -> 0.058139297 | ... BX67: =BX41/BX17 -> 0.063372141 | BY67: =BY41/BY40 -> 2.3224466 | BZ67: =BZ41/BZ17 -> 0.089433283 | CA67: =CA41/CA17 -> 0.085927329 | CB67: =CB41/CB17 -> 0.07982389 | CC67: =CC41/CC17 -> 0.098132488 | CD67: =CD41/CD17 -> 0.088564918 | CE67: =CE41/CE17 -> 0.11779856 | CF67: =CF41/CF17 -> 0.094195355 | CG67: =CG41/CG17 -> 0.095423232 | ... EB67: =EB41/EB17 -> 0.1437236 | EN67: =EN41/EN17 -> 0.078030661 | EO67: =EO41/EO17 -> 0.074596401 | EP67: =EP41/EP17 -> 0.068793675 | EQ67: =EQ41/EQ17 -> 0.016779075 | ER67: =ER41/ER17 -> 0.057710406 | ES67: =ES41/ES17 -> 0.096237026 | ET67: =ET41/ET17 -> 0.1028342 | EU67: =EU41/EU17 -> 0.10521184 | ... FB67: =FB41/FB17 -> 0.14109046 | FD67: Net Income | FE67: =DN67 -> 0.37046611 | FF67: 0.13088499 | FG67: =FE67-FF67 -> 0.23958112 | FH67: =DI67 -> 0.13108549 | FI67: =FE67-FH67 -> 0.23938062
A68: Year-Over-Year % Change: | FD68: Year-Over-Year % Change:
A69: Retail Sales | L69: =(L10-G10)/G10 -> 0.49028076 | Q69: =(Q10-L10)/L10 -> 0.39365973 | R69: =(R10-M10)/M10 -> 0.33255634 | S69: =(S10-N10)/N10 -> 0.35952386 | T69: =(T10-O10)/O10 -> 0.33684518 | U69: =(U10-P10)/P10 -> 0.25678022 | V69: =(V10-Q10)/Q10 -> 0.31840792 | W69: =(W10-R10)/R10 -> 0.24662421 | X69: =(X10-S10)/S10 -> 0.25762221 | ... EB69: =(EB10-DW10)/DW10 -> 0.093534872 | EM69: =EM10/EL10-1 -> 0.21446042 | EN69: =EN10/EM10-1 -> -0.45111279 | EO69: =EO10/EN10-1 -> 0.22975089 | EP69: =EP10/EO10-1 -> 0.19836867 | EQ69: =EQ10/EP10-1 -> 0.030402421 | ER69: =ER10/EQ10-1 -> -0.03486262 | ES69: =ES10/ER10-1 -> 0.099434729 | ET69: =ET10/ES10-1 -> 0.086725353 | ... FB69: =FB10/FA10-1 -> 0.094598126 | FD69: Retail Sales | FE69: =DN69 -> 0.060971517 | FF69: 0.08178684 | FG69: =FE69-FF69 -> -0.020815323 | FH69: =DI69 -> 0.061440175
A70: Licensed stores | BU70: =BU13/BP13-1 -> 0.076885406 | BV70: =BV13/BQ13-1 -> 0.055586749 | BW70: =BW13/BR13-1 -> 0.022047244 | BX70: =BX13/BS13-1 -> -0.066925315 | BY70: =BY13/BT13-1 -> 0.020539153 | BZ70: =BZ13/BU13-1 -> -0.015461573 | CA70: =CA13/BV13-1 -> 0.12180851 | CB70: =CB13/BW13-1 -> 0.096558808 | ... EB70: =EB13/DW13-1 -> 0.12624528 | FD70: Licensed stores | FE70: =DN70 -> 0.13280212 | FF70: 0.12935445 | FG70: =FE70-FF70 -> 0.0034476717 | FH70: =DI70 -> 0.11431743
A71: CPG, foodservice and other | BU71: =BU14/BP14-1 -> 0.033978292 | BV71: =BV14/BQ14-1 -> -0.10487805 | BW71: =BW14/BR14-1 -> -0.038385827 | BX71: =BX14/BS14-1 -> -0.05 | BY71: =BY14/BT14-1 -> -0.039298161 | BZ71: =BZ14/BU14-1 -> -0.026471931 | CA71: =CA14/BV14-1 -> 0.062125341 | CB71: =CB14/BW14-1 -> 0.083930399 | ... EB71: =EB14/DW14-1 -> 0.068088821 | FD71: CPG, foodservice and other | FE71: =DN71 -> -0.0176951 | FF71: 0.066844374 | FG71: =FE71-FF71 -> -0.084539474 | FH71: =DI71 -> 0.062510043
A72: Specialty Sales | L72: =((L15+L16)-(G15+G16))/(G15+G16) -> 0.82572694 | Q72: =((Q15+Q16)-(L15+L16))/(L15+L16) -> 0.40351277 | R72: =((R15+R16)-(M15+M16))/(M15+M16) -> 0.37119867 | S72: =((S15+S16)-(N15+N16))/(N15+N16) -> 0.40034836 | T72: =((T15+T16)-(O15+O16))/(O15+O16) -> 0.5827251 | U72: =((U15+U16)-(P15+P16))/(P15+P16) -> 0.54436556 | V72: =((V15+V16)-(Q15+Q16))/(Q15+Q16) -> 0.38291807 | W72: =((W15+W16)-(R15+R16))/(R15+R16) -> 0.35592855 | X72: =((X15+X16)-(S15+S16))/(S15+S16) -> 0.36568914 | ... AK72: =((AK15+AK16)-(AF15+AF16))/(AF15+AF16) -> 0.18477985 | AL72: =(AL15-AG15)/AG15 -> 0.17231854 | AM72: =(AM15-AH15)/AH15 -> 0.12210054 | AN72: =(AN15-AI15)/AI15 -> 0.1875319 | AO72: =(AO15-AJ15)/AJ15 -> 0.24973696 | AP72: =((AP15+AP16)-(AK15+AK16))/(AK15+AK16) -> 0.18269089 | AQ72: =(AQ15-AL15)/AL15 -> 0.25164541 | AR72: =(AR15-AM15)/AM15 -> 0.21801522 | AS72: =(AS15-AN15)/AN15 -> 0.28946515 | AT72: =(AT15-AO15)/AO15 -> 0.28542344 | AU72: =((AU15+AU16)-(AP15+AP16))/(AP15+AP16) -> 0.26188095 | AV72: =(AV15-AQ15)/AQ15 -> 0.30288237 | AW72: =(AW15-AR15)/AR15 -> 0.31540006 | AX72: =(AX15-AS15)/AS15 -> 0.32457144 | AY72: =(AY15-AT15)/AT15 -> 0.39895324 | AZ72: =((AZ15+AZ16)-(AU15+AU16))/(AU15+AU16) -> 0.3370693 | BA72: =(BA15-AV15)/AV15 -> 0.15041157 | BB72: =(BB15-AW15)/AW15 -> 0.23182064 | BC72: =(BC15-AX15)/AX15 -> 0.16406502 | BD72: =(BD15-AY15)/AY15 -> 0.13439881 | BE72: =((BE15+BE16)-(AZ15+AZ16))/(AZ15+AZ16) -> 0.16789247 | BF72: =(BF15-BA15)/BA15 -> 0.3258187 | BG72: =(BG15-BB15)/BB15 -> 0.21812505 | BH72: =(BH15-BC15)/BC15 -> 0.23451634 | BI72: =(BI15-BD15)/BD15 -> 0.15958608 | BJ72: =((BJ15+BJ16)-(BE15+BE16))/(BE15+BE16) -> 0.23171399 | BK72: =(BK15-BF15)/BF15 -> 0.13982928 | BL72: =(BL15-BG15)/BG15 -> 0.16403709 | BM72: =(BM15-BH15)/BH15 -> 0.15123094 | BN72: =(BN15-BI15)/BI15 -> 0.23910167 | BO72: =((BO15+BO16)-(BJ15+BJ16))/(BJ15+BJ16) -> 0.17393284 | BP72: =(BP15-BK15)/BK15 -> 0.19256431 | BQ72: =(BQ15-BL15)/BL15 -> 0.15083406 | BR72: =(BR15-BM15)/BM15 -> 0.12978624 | BS72: =(BS15-BN15)/BN15 -> 0.092025757 | BT72: =((BT15+BT16)-(BO15+BO16))/(BO15+BO16) -> 0.14001098 | BU72: =(BU15-BP15)/BP15 -> 0.055034847 | BV72: =(BV15-BQ15)/BQ15 -> -0.0302793 | BW72: =(BW15-BR15)/BR15 -> -0.0091440183 | BX72: =(BX15-BS15)/BS15 -> -0.058345289 | BY72: =((BY15+BY16)-(BT15+BT16))/(BT15+BT16) -> -0.010365589 | BZ72: =(BZ15-BU15)/BU15 -> -0.02095672 | CA72: =(CA15-BV15)/BV15 -> 0.092328398 | CB72: =(CB15-BW15)/BW15 -> 0.090233274 | CC72: =(CC15-BX15)/BX15 -> 0.22651092 | CD72: =((CD15+CD16)-(BY15+BY16))/(BY15+BY16) -> 0.09376568 | CE72: =(CE15-BZ15)/BZ15 -> 0.16216845 | CF72: =(CF15-CA15)/CA15 -> 0.21291276 | CG72: =(CG15-CB15)/CB15 -> 0.21067482 | CH72: =(CH15-CC15)/CC15 -> 0.16252588 | CI72: =((CI15+CI16)-(CD15+CD16))/(CD15+CD16) -> 0.18590516 | CJ72: =(CJ15-CE15)/CE15 -> 0.3977978 | CK72: =(CK15-CF15)/CF15 -> 0.35920358 | CL72: =(CL15-CG15)/CG15 -> 0.32569431 | CM72: =(CM15-CH15)/CH15 -> 0.23348175 | CN72: =((CN15+CN16)-(CI15+CI16))/(CI15+CI16) -> 0.32604806 | CO72: =(CO15-CJ15)/CJ15 -> 0.15095961 | CP72: =(CP15-CK15)/CK15 -> 0.10896861 | CQ72: =(CQ15-CL15)/CL15 -> 0.097275125 | CR72: =(CR15-CM15)/CM15 -> 0.1250361 | CS72: =((CS15+CS16)-(CN15+CN16))/(CN15+CN16) -> 0.12080659 | CT72: =(CT15-CO15)/CO15 -> 0.1147337 | CU72: =(CU15-CP15)/CP15 -> 0.086130206 | CV72: =(CV15-CQ15)/CQ15 -> 0.15246996 | CW72: =(CW15-CR15)/CR15 -> 0.16157598 | CX72: =((CX15+CX16)-(CS15+CS16))/(CS15+CS16) -> 0.12890002 | CY72: =(CY15-CT15)/CT15 -> 0.15025675 | CZ72: =(CZ15-CU15)/CU15 -> 0.16728717 | DA72: =(DA15-CV15)/CV15 -> 0.11932345 | DB72: =(DB15-CW15)/CW15 -> 0.13600707 | DC72: =((DC15+DC16)-(CX15+CX16))/(CX15+CX16) -> 0.1427995 | DD72: =(DD15-CY15)/CY15 -> 0.12859084 | DE72: =(DE15-CZ15)/CZ15 -> 0.11524559 | DF72: =(DF15-DA15)/DA15 -> 0.093355413 | DG72: =(DG15-DB15)/DB15 -> 0.17039486 | DH72: =((DH15+DH16)-(DC15+DC16))/(DC15+DC16) -> 0.12767943 | DI72: =(DI15-DD15)/DD15 -> 0.08659386 | DJ72: =(DJ15-DE15)/DE15 -> 0.047283127 | DK72: =(DK15-DF15)/DF15 -> 0.09096933 | DL72: =(DL15-DG15)/DG15 -> 0.014874522 | DM72: =((DM15+DM16)-(DH15+DH16))/(DH15+DH16) -> 0.059105038 | DN72: =(DN15-DI15)/DI15 -> 0.054051915 | DO72: =(DO15-DJ15)/DJ15 -> 0.043893657 | DP72: =(DP15-DK15)/DK15 -> 0.032402744 | DQ72: =(DQ15-DL15)/DL15 -> 0.046215765 | DR72: =((DR15+DR16)-(DM15+DM16))/(DM15+DM16) -> 0.044406471 | DS72: =(DS15-DN15)/DN15 -> 0.087904323 | DT72: =(DT15-DO15)/DO15 -> 0.099869924 | DU72: =(DU15-DP15)/DP15 -> 0.10028975 | DV72: =(DV15-DQ15)/DQ15 -> 0.099623403 | DW72: =((DW15+DW16)-(DR15+DR16))/(DR15+DR16) -> 0.096685237 | DX72: =(DX15-DS15)/DS15 -> 0.10078284 | DY72: =(DY15-DT15)/DT15 -> 0.097382986 | DZ72: =(DZ15-DU15)/DU15 -> 0.09851637 | EA72: =(EA15-DV15)/DV15 -> 0.098285699 | EB72: =((EB15+EB16)-(DW15+DW16))/(DW15+DW16) -> 0.09879849 | EM72: =EM15/EL15-1 -> 0.19723616 | EN72: =EN15/EM15-1 -> -0.4396661 | EO72: =EO15/EN15-1 -> 0.18435131 | EP72: =EP15/EO15-1 -> 0.18752141 | EQ72: =EQ15/EP15-1 -> 0.10374083 | ER72: =ER15/EQ15-1 -> -0.029865361 | ES72: =ES15/ER15-1 -> 0.14408277 | ET72: =ET15/ES15-1 -> 0.24988972 | ... FB72: =FB15/FA15-1 -> 0.10016762 | FD72: Specialty Sales | FE72: =DN72 -> 0.054051915 | FF72: 0.096645 | FG72: =FE72-FF72 -> -0.042593085 | FH72: =DI72 -> 0.08659386
A73: Net Sales | B73: 0.61392885 | C73: 0.6382855 | D73: 0.65514814 | E73: 0.6332141 | F73: 0.61048596 | G73: 0.63276394 | H73: =H17/C17-1 -> 0.46728115 | I73: =I17/D17-1 -> 0.51918151 | J73: =J17/E17-1 -> 0.48480373 | K73: =K17/F17-1 -> 0.51789303 | L73: =L17/G17-1 -> 0.49721632 | M73: =M17/H17-1 -> 0.41652855 | N73: =N17/I17-1 -> 0.40792532 | O73: =O17/J17-1 -> 0.38028257 | ... EB73: =EB17/DW17-1 -> 0.094583655 | EM73: =EM17/EL17-1 -> 0.2870114 | EN73: =EN17/EM17-1 -> 0.19834505 | EO73: =EO17/EN17-1 -> 0.22263313 | EP73: =EP17/EO17-1 -> 0.19672128 | EQ73: =EQ17/EP17-1 -> 0.0414548 | ER73: =ER17/EQ17-1 -> -0.034064473 | ES73: =ES17/ER17-1 -> 0.10659678 | ET73: =ET17/ES17-1 -> 0.11378538 | ... FB73: =FB17/FA17-1 -> 0.095707154 | FD73: Net Sales | FE73: =DN73 -> 0.059446354 | FF73: 0.085061757 | FG73: =FE73-FF73 -> -0.025615403 | FH73: =DI73 -> 0.066883782
A74: Revenues Three-Year CAGR | AZ74: =(AZ17/AK17)^(1/3)-1 -> 0.25962665 | BA74: =(BA17/AL17)^(1/3)-1 -> 0.2543883 | BB74: =(BB17/AM17)^(1/3)-1 -> 0.24699531 | BC74: =(BC17/AN17)^(1/3)-1 -> 0.24245249 | BD74: =(BD17/AO17)^(1/3)-1 -> 0.24240919 | BE74: =(BE17/AP17)^(1/3)-1 -> 0.24646473 | BF74: =(BF17/AQ17)^(1/3)-1 -> 0.24446542 | BG74: =(BG17/AR17)^(1/3)-1 -> 0.25493005 | ... EB74: =(EB17/DM17)^(1/3)-1 -> 0.10003597 | FD74: Revenues Three-Year CAGR | FE74: =DN74 -> 0.081369764 | FF74: 0.09001561 | FG74: =FE74-FF74 -> -0.0086458465 | FH74: =DI74 -> 0.10581674
A75: Income from equity investees | AZ75: =AZ27/AU27-1 -> 0.53846755 | BA75: =BA27/AV27-1 -> 0.27907208 | BB75: =BB27/AW27-1 -> 0.3641996 | BC75: =BC27/AX27-1 -> 0.37309124 | BD75: =BD27/AY27-1 -> 0.22024845 | BE75: =BE27/AZ27-1 -> 0.29919927 | BF75: =BF27/BA27-1 -> 0.53763525 | BG75: =BG27/BB27-1 -> 0.2265251 | ... EB75: =EB27/DW27-1 -> 0.093823909 | EM75: =EM27/EL27-1 -> 0.48435315 | EN75: =EN27/EM27-1 -> 0.34598416 | EO75: =EO27/EN27-1 -> 0.11220107 | EP75: =EP27/EO27-1 -> 0.21386469 | EQ75: =EQ27/EP27-1 -> 0.0057331218 | ER75: =ER27/EQ27-1 -> 0.12599119 | ES75: =ES27/ER27-1 -> 0.19874804 | ET75: =ET27/ES27-1 -> 0.20234987 | ... FB75: =FB27/FA27-1 -> 0.085987716 | FD75: Income from equity investees | FE75: =DN75 -> 0.059241706 | FF75: 0.21459771 | FG75: =FE75-FF75 -> -0.155356 | FH75: =DI75 -> 0.31669267
A76: G&A | BJ76: =BJ25/BE25-1 -> 0.32457143 | BK76: =BK25/BF25-1 -> -0.065655788 | BL76: =BL25/BG25-1 -> 0.054284305 | BM76: =BM25/BH25-1 -> 0.037021291 | BN76: =BN25/BI25-1 -> 0.073875066 | BO76: =BO25/BJ25-1 -> 0.023563336 | BP76: =BP25/BK25-1 -> 0.092616378 | BQ76: =BQ25/BL25-1 -> -0.067436402 | ... EB76: =EB25/DW25-1 -> 0.11331804 | FD76: G&A | FE76: =DN76 -> 0.06369248 | FF76: 0.164303 | FG76: =FE76-FF76 -> -0.10061052 | FH76: =DI76 -> 0.16661211
A77: Operating Profit | B77: 0.84679401 | C77: 0.76476452 | D77: NM | E77: 0.83594585 | F77: 0.17145201 | G77: 0.72159993 | H77: =H29/C29-1 -> 0.11366846 | I77: =I29/D29-1 -> 0.069954777 | J77: =J29/E29-1 -> 0.41515475 | K77: =K29/F29-1 -> 1.2180205 | L77: =L29/G29-1 -> 0.42034152 | M77: =M29/H29-1 -> 0.31621656 | N77: =N29/I29-1 -> 0.7939506 | O77: =O29/J29-1 -> 0.54723708 | ... EB77: =EB29/DW29-1 -> 0.12363397 | EM77: =EM29/EL29-1 -> 0.37783595 | EN77: =EN29/EM29-1 -> 0.26374125 | EO77: =EO29/EN29-1 -> 0.12071494 | EP77: =EP29/EO29-1 -> 0.14295123 | EQ77: =EQ29/EP29-1 -> -0.72973454 | ER77: =ER29/EQ29-1 -> 1.7626014 | ES77: =ES29/ER29-1 -> 0.96850295 | ET77: =ET29/ES29-1 -> 0.11710333 | ... FB77: =FB29/FA29-1 -> 0.13461109 | FD77: Operating Profit | FE77: =DN77 -> -0.01456825 | FF77: 0.075583028 | FG77: =FE77-FF77 -> -0.090151278 | FH77: =DI77 -> 0.070510397
A78: Operating profit before charges/gains | BZ78: =BZ30/BU30-1 -> 0.91977226 | CA78: =CA30/BV30-1 -> 0.8015544 | CB78: =CB30/BW30-1 -> 0.36189358 | CC78: =CC30/BX30-1 -> 0.6060966 | CD78: =CD30/BY30-1 -> 0.64624329 | CE78: =CE30/BZ30-1 -> 0.35319493 | CF78: =CF30/CA30-1 -> 0.081679609 | CG78: =CG30/CB30-1 -> 0.15541511 | ... EB78: =EB30/DW30-1 -> 0.12212236 | FE78: =DN78 -> 0.018227804 | FF78: 0 | FH78: =DI78 -> 0.071288424
A79: EBITDA Growth | AB79: =AB31/W31-1 -> 0.31594621 | AC79: =AC31/X31-1 -> 0.34261453 | AD79: =AD31/Y31-1 -> 0.33364683 | AE79: =AE31/Z31-1 -> 0.36705036 | AF79: =AF31/AA31-1 -> 0.34111009 | AG79: =AG31/AB31-1 -> 0.34767749 | AH79: =AH31/AC31-1 -> 0.31173855 | AI79: =AI31/AD31-1 -> 0.32737323 | ... EB79: =EB31/DW31-1 -> 0.11477655 | EM79: =EM31/EL31-1 -> 0.31863001 | EN79: =EN31/EM31-1 -> 0.229214 | EO79: =EO31/EN31-1 -> 0.12529775 | EP79: =EP31/EO31-1 -> 0.15936394 | EQ79: =EQ31/EP31-1 -> -0.23128891 | ER79: =ER31/EQ31-1 -> 0.091699826 | ES79: =ES31/ER31-1 -> 0.56359666 | ET79: =ET31/ES31-1 -> 0.099455763 | ... FB79: =FB31/FA31-1 -> 0.11975892 | FD79: EBITDA Growth | FE79: =DN79 -> -0.0053533965 | FF79: 0.072481765 | FG79: =FE79-FF79 -> -0.077835162 | FH79: =DI79 -> 0.068650947
A80: Net Income | B80: 0.58007415 | C80: 0.84424476 | D80: NM | E80: 1.1726062 | F80: 0.37977528 | G80: 0.99471225 | H80: =H41/C41-1 -> -0.78611161 | I80: =I41/D41-1 -> -2.4816433 | J80: =J41/E41-1 -> 0.37501826 | K80: =K41/F41-1 -> 1.300941 | L80: =L41/G41-1 -> 0.39685824 | M80: =M41/H41-1 -> 0.45616611 | N80: =N41/I41-1 -> 0.94662732 | O80: =O41/J41-1 -> 0.50871228 | ... EB80: =EB41/DW41-1 -> 0.11990512 | EM80: =EM41/EL41-1 -> 0.41204483 | EN80: =EN41/EM41-1 -> 0.23622746 | EO80: =EO41/EN41-1 -> 0.16882299 | EP80: =EP41/EO41-1 -> 0.1036304 | EQ80: =EQ41/EP41-1 -> -0.74598468 | ER80: =ER41/EQ41-1 -> 2.3222649 | ES80: =ES41/ER41-1 -> 0.84534456 | ET80: =ET41/ES41-1 -> 0.19013683 | ... FB80: =FB41/FA41-1 -> 0.12880074 | FD80: Net Income | FE80: =DN80 -> 1.994145 | FF80: 0.083402114 | FG80: =FE80-FF80 -> 1.9107429 | FH80: =DI80 -> 0.092773011
A81: EPS - Operating | G81: =G50/B50-1 -> 0.13425 | H81: =H50/C50-1 -> -0.79081533 | I81: =I50/D50-1 -> -3.7197821 | J81: =J50/E50-1 -> 0.20565006 | K81: =K50/F50-1 -> 0.89300125 | L81: =L50/G50-1 -> 0.44291851 | M81: =M50/H50-1 -> 0.16260131 | N81: =N50/I50-1 -> 0.46426824 | ... BE81: =BE50/AZ50-1 -> 0.28216603 | BF81: =BF50/BA53-1 -> 0.37574274 | BG81: =BG50/BB53-1 -> 0.57053114 | BH81: =BH50/BC53-1 -> 0.33603427 | BI81: =BI50/BD53-1 -> 0.25881586 | BJ81: =BJ53/BE53-1 -> 0.3325096 | BK81: =BK53/BF50-1 -> 0.19226445 | BL81: =BL53/BG50-1 -> 0.21623468 | BM81: =BM53/BH50-1 -> 0.13774011 | BN81: =BN53/BI50-1 -> 0.21737312 | BO81: =BO53/BJ50-1 -> 0.19082649 | BP81: =BP50/BK50-1 -> 0.066653957 | BQ81: =BQ50/BL50-1 -> -0.091820266 | BR81: =BR50/BM50-1 -> -0.23801329 | BS81: =BS50/BN50-1 -> -0.54102062 | BT81: =BT50/BO50-1 -> -0.1864312 | BU81: =BU50/BP50-1 -> -0.46919715 | BV81: =BV50/BQ50-1 -> -0.074421874 | BW81: =BW50/BR50-1 -> 0.4967211 | ... EB81: =EB50/DW50-1 -> 0.13983225 | EM81: =EM50/EL50-1 -> 0.37947142 | EN81: =EN50/EM50-1 -> 0.26733032 | EO81: =EO50/EN50-1 -> 0.19255543 | EP81: =EP50/EO50-1 -> 0.14652015 | EQ81: =EQ50/EP50-1 -> -0.34871513 | ER81: =ER50/EQ50-1 -> 0.70018378 | ES81: =ES50/ER50-1 -> 0.42689853 | ET81: =ET50/ES50-1 -> 0.085795349 | ... FB81: =FB50/FA50-1 -> 0.15341518 | FD81: EPS | FE81: =DN81 -> 0.25301072 | FF81: 0.11196934 | FG81: =FE81-FF81 -> 0.14104138 | FH81: =DI81 -> 0.11845473
A82: EPS - Reported | CJ82: =CJ53/CE53-1 -> 0.099841419 | CK82: =CK53/CF53-1 -> 0.18233515 | CL82: =CL53/CG53-1 -> 0.18595066 | CM82: =CM53/CH53-1 -> -0.0050784395 | CN82: =CN53/CI53-1 -> 0.10627 | CO82: =CO53/CJ53-1 -> 0.14181506 | CP82: =CP53/CK53-1 -> 0.27961821 | CQ82: =CQ53/CL53-1 -> 0.27880712 | ... CW82: =CW53/CR53-1 -> -1.4790168 | CX82: NM | CY82: =CY53/CT53-1 -> 0.83951433 | CZ82: =CZ53/CU53-1 -> 0.1689964 | DA82: =DA53/CV53-1 -> 0.22752009 | DB82: =DB53/CW53-1 -> 0.12307054 | DC82: =DC53/CX53-1 -> 0.34534792 | DD82: =DD53/CY53-1 -> -0.29530237 | DE82: =DE53/CZ53-1 -> 0.18542532 | DF82: =DF53/DA53-1 -> 0.233289 | ... EB82: =EB53/DW53-1 -> 0.1413487 | FE82: =DN82 -> 2.0679834 | FF82: 0.11103541 | FH82: =DI82 -> 0.11775619
A83: EPS Three Year CAGR | AZ83: =(AZ50/AK50)^(1/3)-1 -> 0.27413271 | BA83: =(BA50/AL50)^(1/3)-1 -> 0.31894729 | BB83: =(BB50/AM50)^(1/3)-1 -> 0.30727149 | BC83: =(BC50/AN50)^(1/3)-1 -> 0.30908861 | BD83: =(BD50/AO50)^(1/3)-1 -> 0.29149274 | BE83: =(BE50/AP50)^(1/3)-1 -> 0.31359653 | BF83: =(BF50/AQ50)^(1/3)-1 -> 0.30808412 | BG83: =(BG50/AR50)^(1/3)-1 -> 0.35014841 | ... EB83: =(EB50/DM50)^(1/3)-1 -> 0.15476887 | FD83: EPS Three Year CAGR | FE83: =CU83 -> 0.18100834 | FF83: 0.18100834 | FG83: =FE83-FF83 -> 0 | FH83: =CP83 -> 0.18163667
A84: Avg. Shs. Outs. (FD) | G84: =G54/B54-1 -> 0.20334268 | H84: =H54/C54-1 -> 0.11385513 | I84: =I54/D54-1 -> 0.029105138 | J84: =J54/E54-1 -> 0.097042678 | K84: =K54/F54-1 -> 0.10045891 | L84: =L54/G54-1 -> 0.12526292 | M84: =M54/H54-1 -> 0.21156391 | N84: =N54/I54-1 -> 0.20681455 | ... EB84: =EB54/DW54-1 -> -0.01878793
A85: Unit Summary | FD85: UNIT SUMMARY
A86: Total Stores | FD86: Total Stores
A87: The Americas | BU87: 12899 | BV87: 12832 | BW87: 12656 | BX87: 12546 | BY87: 12546 | BZ87: 12623 | CA87: 12570 | CB87: 12596 | CC87: 12624 | CD87: 12624 | CE87: 12682 | CF87: 12471 | CG87: 12523 | CH87: 12399 | CI87: 12399 | CJ87: 12494 | CK87: 12570 | CL87: 12653 | CM87: 12903 | CN87: 12903 | CO87: 12900 | CP87: 12995 | CQ87: 13153 | CR87: 13493 | CS87: 13493 | CT87: 13635 | CU87: 13763 | CV87: 13912 | CW87: 14191 | CX87: 14191 | CY87: 14401 | CZ87: 14399 | DA87: 14570 | DB87: 14803 | DC87: 14803 | DD87: 14974 | DE87: 15106 | DF87: 15300 | DG87: 15607 | DH87: 15607 | DI87: 15858 | DJ87: 16058 | DK87: 16302 | DL87: 16559 | DM87: 16559 | DN87: 16837 | DO87: 16992 | DP87: 17221 | DQ87: 17463 | DR87: 17463 | DS87: 17729 | DT87: 17872 | DU87: 18089 | DV87: 18319 | DW87: 18319 | DX87: 18573 | DY87: 18704 | DZ87: 18909 | EA87: 19127 | EB87: 19127 | ET87: =CJ87 -> 12494 | EU87: =CO87 -> 12900 | EV87: =CT87 -> 13635 | EW87: =CY87 -> 14401 | EX87: =DD87 -> 14974 | EY87: =DI87 -> 15858 | EZ87: =DN87 -> 16837 | FA87: =DS87 -> 17729 | FB87: =DX87 -> 18573 | FD87: The Americas | FE87: =DN87 -> 16837 | FF87: 16782 | FG87: =FE87-FF87 -> 55 | FH87: =DI87 -> 15858 | FI87: =FE87/FH87-1 -> 0.061735402
A88: EMEA | BU88: 1572 | BV88: 1596 | BW88: 1617 | BX88: 1618 | BY88: 1618 | BZ88: 1595 | CA88: 1593 | CB88: 1615 | CC88: 1654 | CD88: 1654 | CE88: 1685 | CF88: 1694 | CG88: 1730 | CH88: 1758 | CI88: 1758 | CJ88: 1783 | CK88: 1800 | CL88: 1836 | CM88: 1869 | CN88: 1869 | CO88: 1876 | CP88: 1898 | CQ88: 1941 | CR88: 1969 | CS88: 1969 | CT88: 2033 | CU88: 2065 | CV88: 2102 | CW88: 2140 | CX88: 2140 | CY88: 2198 | CZ88: 2233 | DA88: 2291 | DB88: 2362 | DC88: 2362 | DD88: 2441 | DE88: 2488 | DF88: 2565 | DG88: 2642 | DH88: 2642 | DI88: 2737 | DJ88: 2783 | DK88: 2870 | DL88: 2974 | DM88: 2974 | DN88: 3097 | DO88: 3124 | DP88: 3191 | DQ88: 3280 | DR88: 3280 | DS88: 3407 | DT88: 3438 | DU88: 3509 | DV88: 3602 | DW88: 3602 | DX88: 3729 | DY88: 3760 | DZ88: 3831 | EA88: 3924 | EB88: 3924 | ET88: =CJ88 -> 1783 | EU88: =CO88 -> 1876 | EV88: =CT88 -> 2033 | EW88: =CY88 -> 2198 | EX88: =DD88 -> 2441 | EY88: =DI88 -> 2737 | EZ88: =DN88 -> 3097 | FA88: =DS88 -> 3407 | FB88: =DX88 -> 3729 | FD88: EMEA | FE88: =DN88 -> 3097 | FF88: 3074 | FG88: =FE88-FF88 -> 23 | FH88: =DI88 -> 2737 | FI88: =FE87/FH87-1 -> 0.061735402
A89: China Asia Pacific | BU89: 2404 | BV89: 2434 | BW89: 2456 | BX89: 2471 | BY89: 2471 | BZ89: 2488 | CA89: 2501 | CB89: 2526 | CC89: 2580 | CD89: 2580 | CE89: 2642 | CF89: 2698 | CG89: 2765 | CH89: 2846 | CI89: 2846 | CJ89: 2967 | CK89: 3050 | CL89: 3162 | CM89: 3294 | CN89: 3294 | CO89: 3419 | CP89: 3566 | CQ89: 3685 | CR89: 3882 | CS89: 3882 | CT89: 4091 | CU89: 4265 | CV89: 4425 | CW89: 4624 | CX89: 4624 | CY89: 4858 | CZ89: 5034 | DA89: 5239 | DB89: 5462 | DC89: 5462 | DD89: 5743 | DE89: 5918 | DF89: 6127 | DG89: 6443 | DH89: 6443 | DI89: 6746 | DJ89: 6933 | DK89: 7183 | DL89: 7479 | DM89: 7479 | DN89: 7779 | DO89: 7951 | DP89: 8171 | DQ89: 8575 | DR89: 8575 | DS89: 8895 | DT89: 9087 | DU89: 9327 | DV89: 9751 | DW89: 9751 | DX89: 10091 | DY89: 10303 | DZ89: 10563 | EA89: 11007 | EB89: 11007 | ET89: =CJ89 -> 2967 | EU89: =CO89 -> 3419 | EV89: =CT89 -> 4091 | EW89: =CY89 -> 4858 | EX89: =DD89 -> 5743 | EY89: =DI89 -> 6746 | EZ89: =DN89 -> 7779 | FA89: =DS89 -> 8895 | FB89: =DX89 -> 10091 | FD89: China Asia Pacific | FE89: =DN89 -> 7779 | FF89: 7752 | FG89: =FE89-FF89 -> 27 | FH89: =DI89 -> 6746 | FI89: =FE89/FH89-1 -> 0.15312778
A90: Total | B90: 425 | C90: 482 | D90: 539 | E90: 607 | F90: 676 | G90: 676 | H90: 743 | I90: 828 | J90: 899 | K90: 1006 | L90: 1006 | M90: 1121 | N90: 1205 | O90: 1306 | P90: 1412 | Q90: 1412 | R90: 1568 | S90: 1665 | T90: 1778 | U90: 1886 | V90: 1886 | W90: 2030 | X90: 2192 | Y90: 2312 | Z90: 2498 | AA90: 2498 | AB90: 2674 | AC90: 2885 | AD90: 3215 | AE90: 3501 | AF90: 3501 | AG90: 3817 | AH90: 4135 | AI90: 4435 | AJ90: 4709 | AK90: 4709 | AL90: 5104 | AM90: 5368 | AN90: 5608 | AO90: 5886 | AP90: 5886 | AQ90: 6193 | AR90: 6458 | AS90: 6741 | AT90: 7225 | AU90: 7225 | AV90: 7567 | AW90: 7834 | AX90: 8119 | AY90: 8569 | AZ90: 8569 | BA90: 8949 | BB90: 9261 | BC90: 9671 | BD90: 10241 | BE90: 10241 | BF90: 10801 | BG90: 11225 | BH90: 11784 | BI90: 12440 | BJ90: 12440 | BK90: 13168 | BL90: 13728 | BM90: 14396 | BN90: 15011 | BO90: 15011 | BP90: 15756 | BQ90: 16226 | BR90: 16548 | BS90: 16680 | BT90: 16680 | BU90: 16875 | BV90: 16862 | BW90: 16729 | BX90: 16635 | BY90: 16635 | BZ90: 16706 | CA90: 16664 | CB90: 16737 | CC90: 16858 | CD90: 16858 | CE90: 17009 | CF90: 16863 | CG90: 17018 | CH90: 17003 | CI90: 17003 | CJ90: 17244 | CK90: 17420 | CL90: 17651 | CM90: 18066 | CN90: 18066 | CO90: 18278 | CP90: 18868 | CQ90: 19209 | CR90: 19767 | CS90: 19767 | CT90: 20184 | CU90: 20519 | CV90: 20863 | CW90: 21366 | CX90: 21366 | CY90: 21878 | CZ90: 22088 | DA90: 22519 | DB90: 23043 | DC90: 23043 | DD90: 23571 | DE90: 23921 | DF90: 24395 | DG90: 25085 | DH90: 25085 | DI90: 25734 | DJ90: 26161 | DK90: 26736 | DL90: 27339 | DM90: 27339 | DN90: 28039 | DO90: 28293 | DP90: 28709 | DQ90: 29357 | DR90: 29357 | DS90: 30070 | DT90: 30436 | DU90: 30964 | DV90: 31711 | DW90: 31711 | DX90: 32432 | DY90: 32806 | DZ90: 33342 | EA90: 34097 | EB90: 34097 | ET90: =SUM(ET87:ET89) -> 17244 | EU90: =SUM(EU87:EU89) -> 18195 | EV90: =SUM(EV87:EV89) -> 19759 | EW90: =SUM(EW87:EW89) -> 21457 | EX90: =SUM(EX87:EX89) -> 23158 | EY90: =SUM(EY87:EY89) -> 25341 | EZ90: =SUM(EZ87:EZ89) -> 27713 | FA90: =SUM(FA87:FA89) -> 30031 | FB90: =SUM(FB87:FB89) -> 32393 | FD90: Total | FE90: =DN90 -> 28039 | FF90: 27798 | FG90: =FE90-FF90 -> 241 | FH90: =DI90 -> 25734 | FI90: =FE90/FH90-1 -> 0.089570218
A91: Y/Y Growth | FD91: Y/Y Growth
A92: The Americas | CD92: =CD87/BY87-1 -> 0.006217121 | CE92: =CE87/BZ87-1 -> 0.0046740078 | CF92: =CF87/CA87-1 -> -0.007875895 | CG92: =CG87/CB87-1 -> -0.0057954906 | CH92: =CH87/CC87-1 -> -0.017823194 | CI92: =CI87/CD87-1 -> -0.017823194 | CJ92: =CJ87/CE87-1 -> -0.01482416 | CK92: =CK87/CF87-1 -> 0.0079384171 | ... EB92: =EB87/DW87-1 -> 0.044107211 | EU92: =EU87/ET87-1 -> 0.032495598 | EV92: =EV87/EU87-1 -> 0.056976744 | EW92: =EW87/EV87-1 -> 0.056178951 | EX92: =EX87/EW87-1 -> 0.039788904 | EY92: =EY87/EX87-1 -> 0.059035662 | EZ92: =EZ87/EY87-1 -> 0.061735402 | FA92: =FA87/EZ87-1 -> 0.052978559 | FB92: =FB87/FA87-1 -> 0.047605618 | FD92: The Americas | FE92: =DN92 -> 0.061735402 | FF92: 0.058267121 | FG92: =FE92-FF92 -> 0.003468281 | FH92: =DI92 -> 0.059035662
A93: EMEA | CD93: =CD88/BY88-1 -> 0.022249691 | CE93: =CE88/BZ88-1 -> 0.056426332 | CF93: =CF88/CA88-1 -> 0.063402385 | CG93: =CG88/CB88-1 -> 0.07120743 | CH93: =CH88/CC88-1 -> 0.062877872 | CI93: =CI88/CD88-1 -> 0.062877872 | CJ93: =CJ88/CE88-1 -> 0.058160237 | CK93: =CK88/CF88-1 -> 0.06257379 | ... EB93: =EB88/DW88-1 -> 0.089394781 | EU93: =EU88/ET88-1 -> 0.052159282 | EV93: =EV88/EU88-1 -> 0.083688699 | EW93: =EW88/EV88-1 -> 0.081160846 | EX93: =EX88/EW88-1 -> 0.11055505 | EY93: =EY88/EX88-1 -> 0.12126178 | EZ93: =EZ88/EY88-1 -> 0.13153087 | FA93: =FA88/EZ88-1 -> 0.10009687 | FB93: =FB88/FA88-1 -> 0.0945113 | FD93: EMEA | FE93: =DN93 -> 0.13153087 | FF93: 0.12312751 | FG93: =FE93-FF93 -> 0.0084033613 | FH93: =DI93 -> 0.12126178
A94: China Asia Pacific | CD94: =CD89/BY89-1 -> 0.044111696 | CE94: =CE89/BZ89-1 -> 0.061897106 | CF94: =CF89/CA89-1 -> 0.078768493 | CG94: =CG89/CB89-1 -> 0.094615994 | CH94: =CH89/CC89-1 -> 0.10310078 | CI94: =CI89/CD89-1 -> 0.10310078 | CJ94: =CJ89/CE89-1 -> 0.12301287 | CK94: =CK89/CF89-1 -> 0.13046701 | ... EB94: =EB89/DW89-1 -> 0.1288073 | EU94: =EU89/ET89-1 -> 0.15234243 | EV94: =EV89/EU89-1 -> 0.1965487 | EW94: =EW89/EV89-1 -> 0.18748472 | EX94: =EX89/EW89-1 -> 0.18217373 | EY94: =EY89/EX89-1 -> 0.1746474 | EZ94: =EZ89/EY89-1 -> 0.15312778 | FA94: =FA89/EZ89-1 -> 0.14346317 | FB94: =FB89/FA89-1 -> 0.13445756 | FD94: China Asia Pacific | FE94: =DN94 -> 0.15312778 | FF94: 0.14912541 | FG94: =FE94-FF94 -> 0.0040023718 | FH94: =DI94 -> 0.1746474
A95: Total | AZ95: =AZ90/AU90-1 -> 0.18602076 | BA95: =BA90/AV90-1 -> 0.18263513 | BB95: =BB90/AW90-1 -> 0.18215471 | BC95: =BC90/AX90-1 -> 0.19115655 | BD95: =BD90/AY90-1 -> 0.19512195 | BE95: =BE90/AZ90-1 -> 0.19512195 | BF95: =BF90/BA90-1 -> 0.2069505 | BG95: =BG90/BB90-1 -> 0.21207213 | ... EB95: =EB90/DW90-1 -> 0.07524203 | EU95: =EU90/ET90-1 -> 0.055149617 | EV95: =EV90/EU90-1 -> 0.085957681 | EW95: =EW90/EV90-1 -> 0.085935523 | EX95: =EX90/EW90-1 -> 0.079274829 | EY95: =EY90/EX90-1 -> 0.094265481 | EZ95: =EZ90/EY90-1 -> 0.093603252 | FA95: =FA90/EZ90-1 -> 0.083643056 | FB95: =FB90/FA90-1 -> 0.07865206 | FD95: Total | FE95: =DN95 -> 0.089570218 | FF95: 0.080205176 | FG95: =FE95-FF95 -> 0.0093650424 | FH95: =DI95 -> 0.091765305
A96: Same-Store Sales | FD96: Same-Store Sales
A97: The Americas | BU97: -0.1 | BV97: -0.08 | BW97: -0.06 | BX97: -0.01 | BY97: -0.06 | BZ97: 0.04 | CA97: 0.07 | CB97: 0.09 | CC97: 0.07 | CD97: 0.07 | CE97: 0.07 | CF97: 0.06 | CG97: 0.07 | CH97: 0.1 | CI97: 0.08 | CJ97: 0.09 | CK97: 0.08 | CL97: 0.07 | CM97: 0.07 | CN97: 0.0775 | CO97: 0.07 | CP97: 0.06 | CQ97: 0.09 | CR97: 0.08 | CS97: 0.07 | CT97: 0.05 | CU97: 0.06 | CV97: 0.06 | CW97: 0.05 | CX97: 0.0525 | CY97: 0.05 | CZ97: 0.07 | DA97: 0.08 | DB97: 0.08 | DC97: 0.075 | DD97: 0.09 | DE97: 0.07 | DF97: 0.04 | DG97: 0.05 | DH97: 0.06 | DI97: 0.03 | DJ97: 0.03 | DK97: 0.05 | DL97: 0.03 | DM97: 0.035 | DN97: 0.02 | DO97: 0.02 | DP97: 0.02 | DQ97: 0.03 | DR97: 0.0225 | DS97: 0.04 | DT97: 0.04 | DU97: 0.04 | DV97: 0.04 | DW97: 0.04 | DX97: 0.04 | DY97: 0.04 | DZ97: 0.04 | EA97: 0.04 | EB97: 0.04 | EU97: =AVERAGE(CK97,CL97,CM97,CO97) -> 0.0725 | EV97: =AVERAGE(CP97,CQ97,CR97,CT97) -> 0.07 | EW97: =AVERAGE(CU97,CV97,CW97,CY97) -> 0.055 | EX97: =AVERAGE(CZ97,DA97,DB97,DD97) -> 0.08 | EY97: =AVERAGE(DE97,DF97,DG97,DI97) -> 0.0475 | EZ97: =AVERAGE(DJ97,DK97,DL97,DN97) -> 0.0325 | FA97: =AVERAGE(DO97,DP97,DQ97,DS97) -> 0.0275 | FB97: =AVERAGE(DT97,DU97,DV97,DX97) -> 0.04 | FD97: The Americas | FE97: =DN97 -> 0.02 | FF97: 0.03 | FG97: =FE97-FF97 -> -0.01 | FH97: =DI97 -> 0.03 | FI97: =FE97-FH97 -> -0.01
A98: EMEA | BU98: -0.05 | BV98: -0.04 | BW98: -0.02 | BX98: 0 | BY98: -0.03 | BZ98: 0.03 | CA98: 0.04 | CB98: 0.05 | CC98: 0.07 | CD98: 0.05 | CE98: 0.03 | CF98: 0.04 | CG98: 0.03 | CH98: 0.01 | CI98: 0.03 | CJ98: 0.02 | CK98: -0.008 | CL98: 0 | CM98: -0.01 | CN98: 0.003 | CO98: -0.01 | CP98: -0.02 | CQ98: 0.02 | CR98: 0.02 | CS98: 0 | CT98: 0.05 | CU98: 0.06 | CV98: 0.04 | CW98: 0.05 | CX98: 0.045 | CY98: 0.04 | CZ98: 0.02 | DA98: 0.03 | DB98: 0.05 | DC98: 0.04 | DD98: 0.01 | DE98: 0.01 | DF98: -0.01 | DG98: -0.01 | DH98: 0 | DI98: -0.01 | DJ98: -0.01 | DK98: 0.02 | DL98: 0.01 | DM98: 0.0025 | DN98: -0.01 | DO98: 0 | DP98: -0.01 | DQ98: 0.02 | DR98: 0 | DS98: 0.03 | DT98: 0.03 | DU98: 0.03 | DV98: 0.03 | DW98: 0.03 | DX98: 0.03 | DY98: 0.03 | DZ98: 0.03 | EA98: 0.03 | EB98: 0.03 | EU98: =AVERAGE(CK98,CL98,CM98,CO98) -> -0.007 | EV98: =AVERAGE(CP98,CQ98,CR98,CT98) -> 0.0175 | EW98: =AVERAGE(CU98,CV98,CW98,CY98) -> 0.0475 | EX98: =AVERAGE(CZ98,DA98,DB98,DD98) -> 0.0275 | EY98: =AVERAGE(DE98,DF98,DG98,DI98) -> -0.005 | EZ98: =AVERAGE(DJ98,DK98,DL98,DN98) -> 0.0025 | FA98: =AVERAGE(DO98,DP98,DQ98,DS98) -> 0.01 | FB98: =AVERAGE(DT98,DU98,DV98,DX98) -> 0.03 | FD98: EMEA | FE98: =DN98 -> -0.01 | FF98: 0.02 | FG98: =FE98-FF98 -> -0.03 | FH98: =DI98 -> -0.01 | FI98: =FE98-FH98 -> 0
A99: China Asia Pacific | BU99: 0.02 | BV99: 0.02 | BW99: 0.03 | BX99: 0.03 | BY99: 0.02 | BZ99: 0.06 | CA99: 0.12 | CB99: 0.11 | CC99: 0.17 | CD99: 0.11 | CE99: 0.19 | CF99: 0.18 | CG99: 0.26 | CH99: 0.27 | CI99: 0.22 | CJ99: 0.2 | CK99: 0.18 | CL99: 0.12 | CM99: 0.1 | CN99: 0.1475 | CO99: 0.11 | CP99: 0.08 | CQ99: 0.09 | CR99: 0.08 | CS99: 0.09 | CT99: 0.08 | CU99: 0.07 | CV99: 0.07 | CW99: 0.05 | CX99: 0.0675 | CY99: 0.08 | CZ99: 0.12 | DA99: 0.11 | DB99: 0.06 | DC99: 0.0875 | DD99: 0.05 | DE99: 0.03 | DF99: 0.03 | DG99: 0.01 | DH99: 0.03 | DI99: 0.05 | DJ99: 0.03 | DK99: 0.01 | DL99: 0.02 | DM99: 0.025 | DN99: 0.01 | DO99: 0.03 | DP99: 0.03 | DQ99: 0.02 | DR99: 0.0225 | DS99: 0.03 | DT99: 0.03 | DU99: 0.03 | DV99: 0.03 | DW99: 0.03 | DX99: 0.05 | DY99: 0.05 | DZ99: 0.05 | EA99: 0.05 | EB99: 0.05 | EU99: =AVERAGE(CK99,CL99,CM99,CO99) -> 0.1275 | EV99: =AVERAGE(CP99,CQ99,CR99,CT99) -> 0.0825 | EW99: =AVERAGE(CU99,CV99,CW99,CY99) -> 0.0675 | EX99: =AVERAGE(CZ99,DA99,DB99,DD99) -> 0.085 | EY99: =AVERAGE(DE99,DF99,DG99,DI99) -> 0.03 | EZ99: =AVERAGE(DJ99,DK99,DL99,DN99) -> 0.0175 | FA99: =AVERAGE(DO99,DP99,DQ99,DS99) -> 0.0275 | FB99: =AVERAGE(DT99,DU99,DV99,DX99) -> 0.035 | FD99: China Asia Pacific | FE99: =DN99 -> 0.01 | FF99: 0 | FG99: =FE99-FF99 -> 0.01 | FH99: =DI99 -> 0.05 | FI99: =FE99-FH99 -> -0.04
A100: Total Company SSS | BU100: -0.09 | BV100: -0.08 | BW100: -0.052042509 | BX100: -0.01 | BY100: -0.06 | BZ100: 0.04 | CA100: 0.07 | CB100: 0.09 | CC100: 0.08 | CD100: 0.07 | CE100: 0.07 | CF100: 0.07 | CG100: 0.08 | CH100: 0.09 | CI100: 0.08 | CJ100: 0.09 | CK100: 0.07 | CL100: 0.06 | CM100: 0.06 | CN100: 0.07 | CO100: 0.06 | CP100: 0.06 | CQ100: 0.08 | CR100: 0.07 | CS100: 0.07 | CT100: 0.05 | CU100: 0.06 | CV100: 0.06 | CW100: 0.05 | CX100: 0.06 | CY100: 0.05 | CZ100: 0.07 | DA100: 0.07 | DB100: 0.08 | DC100: 0.07 | DD100: 0.08 | DE100: 0.06 | DF100: 0.04 | DG100: 0.04 | DH100: 0.05 | DI100: 0.03 | DJ100: 0.03 | DK100: 0.04 | DL100: 0.02 | DM100: 0.03 | DN100: 0.02 | DO100: 0.020816132 | DP100: 0.020596585 | DQ100: 0.027686174 | DR100: 0.022274723 | DS100: 0.037602387 | DT100: 0.037137914 | DU100: 0.037244663 | DV100: 0.037296492 | DW100: 0.037320364 | DX100: 0.041585598 | DY100: 0.042176791 | DZ100: 0.042197274 | EA100: 0.042178656 | EB100: 0.04203458 | EU100: =AVERAGE(CK100,CL100,CM100,CO100) -> 0.0625 | EV100: =AVERAGE(CP100,CQ100,CR100,CT100) -> 0.065 | EW100: =AVERAGE(CU100,CV100,CW100,CY100) -> 0.055 | EX100: =AVERAGE(CZ100,DA100,DB100,DD100) -> 0.075 | EY100: =AVERAGE(DE100,DF100,DG100,DI100) -> 0.0425 | EZ100: =AVERAGE(DJ100,DK100,DL100,DN100) -> 0.0275 | FA100: =AVERAGE(DO100,DP100,DQ100,DS100) -> 0.026675319 | FB100: =AVERAGE(DT100,DU100,DV100,DX100) -> 0.038316167 | FD100: Total Company SSS | FE100: =DN100 -> 0.02 | FF100: 0.024555971 | FG100: =FE100-FF100 -> -0.0045559707 | FH100: =DI100 -> 0.03 | FI100: =FE100-FH100 -> -0.01
A101: Balance Sheet Data | FD101: Balance Sheet Data
A102: Cash and equivalents | AZ102: =BS!AZ9 -> 145.053 | BA102: =BS!BA9 -> 643.548 | BB102: =BS!BB9 -> 177.142 | BC102: =BS!BC9 -> 130.112 | BD102: =BS!BD9 -> 173.809 | BE102: =BS!BE9 -> 173.809 | BF102: =BS!BF9 -> 251.435 | BG102: =BS!BG9 -> 202.671 | ... DR102: =BS!DR9 -> 3197.7168 | DS102: could insrt this | DT102: =BS!DT9 -> 3849.1138 | DU102: =BS!DU9 -> 3558.4988 | DV102: =BS!DV9 -> 3207.1224 | DW102: =BS!DW9 -> 3207.1224 | DX102: =BS!DX9 -> 4266.3009 | DY102: =BS!DY9 -> 3817.2383 | DZ102: =BS!DZ9 -> 3380.9122 | EA102: =BS!EA9 -> 2916.4022 | EB102: =BS!EB9 -> 2916.4022 | FD102: Cash and equivalents | FE102: =DN102 -> 4859.3241 | FF102: 3402.5932 | FG102: =FE102-FF102 -> 1456.7308 | FH102: =DI102 -> 2034.6 | FI102: =FE102/FH102-1 -> 1.3883437
A103: Long-Term Debt | AZ103: =BS!AZ45 -> 3.618 | BA103: =BS!BA45 -> 3.433 | BB103: =BS!BB45 -> 3.246 | BC103: =BS!BC45 -> 3.058 | BD103: =BS!BD45 -> 2.87 | BE103: =BS!BE45 -> 2.87 | BF103: =BS!BF45 -> 2.681 | BG103: =BS!BG45 -> 2.491 | ... EB103: =BS!EB45 -> 7932.6 | FD103: Long-Term Debt | FE103: =DN103 -> 5432.6 | FF103: 5432.6 | FG103: =FE103-FF103 -> 0 | FH103: =DI103 -> 3185.7 | FI103: =FE103/FH103-1 -> 0.7053081
A104: Net Debt/LTM EBITDA | AZ104: =BS!AZ68 -> 0 | BA104: =BS!BA68 -> 0 | BB104: =BS!BB68 -> 0 | BC104: =BS!BC68 -> 0 | BD104: =BS!BD68 -> 0 | BE104: =BS!BE68 -> 0 | BF104: =BS!BF68 -> 0 | BG104: =BS!BG68 -> 0 | ... EB104: =BS!EB68 -> 0.70101514 | FD104: Net Debt/LTM EBITDA | FE104: =DN104 -> 0.11156267 | FF104: 0.38694865 | FG104: =FE104-FF104 -> -0.27538599 | FH104: =DI104 -> 0.21960852 | FI104: =FE104/FH104-1 -> -0.49199299
A105: Cash Flow Data | FD105: Cash Flow Data
A106: Cash from operations | AZ106: =CF!AZ39 -> 858.537 | BA106: =CF!BA39 -> 407.915 | BB106: =CF!BB39 -> 158.578 | BC106: =CF!BC39 -> 192.437 | BD106: =CF!BD39 -> 164.678 | BE106: =CF!BE39 -> 923.608 | BF106: =CF!BF39 -> 609.317 | BG106: =CF!BG39 -> 152.675 | ... EB106: =CF!EB39 -> 5661.8129 | FD106: Cash from operations | FE106: =DN106 -> 2720.6878 | FF106: 1274.6006 | FG106: =FE106-FF106 -> 1446.0872 | FH106: =DI106 -> 1495.7 | FI106: =FE106/FH106-1 -> 0.81900634
...

Sheet BS
A2: John S. Glass (617) 856-8752
A3: Chris Carril (617) 856-8750 | BZ3: =BZ7-BY7 -> 91 | CA3: =CA7-BZ7 -> 91 | CB3: =CB7-CA7 -> 91 | CC3: =CC7-CB7 -> 98 | CE3: =CE7-CD7 -> 91 | CF3: =CF7-CE7 -> 91 | CG3: =CG7-CF7 -> 91 | CH3: =CH7-CG7 -> 91
A5: STARBUCKS CORPORATION: BALANCE SHEET
A6: Fiscal Year Ends: September | B6: FY 1994 | C6: 34669 | D6: 34759 | E6: 34851 | F6: 34943 | G6: FY 1995 | H6: 35034 | I6: 35125 | J6: 35217 | K6: 35309 | L6: FY 1996 | M6: Dec-96R | N6: Mar-97R | O6: Jun-97R | P6: Sep-97R | Q6: FY 1997 | R6: Dec-97R | S6: Mar-98R | T6: 35947 | U6: 36039 | V6: FY 1998 | W6: 36130 | X6: 36220 | Y6: 36312 | Z6: 36404 | AA6: FY 1999 | AB6: 36495 | AC6: 36586 | AD6: 36678 | AE6: 36770 | AF6: FY 2000A | AG6: 36861 | AH6: 36951 | AI6: 37043 | AJ6: 37135 | AK6: FY 2001 | AL6: 37226 | AM6: 37316 | AN6: 37408 | AO6: 37500 | AP6: FY 2002 | AQ6: 37591 | AR6: 37681 | AS6: 37773 | AT6: 37865 | AU6: FY 2003 | AV6: 37956 | AW6: 38047 | AX6: 38139 | AY6: 38231 | AZ6: FY 2004 | BA6: 38322 | BB6: 38412 | BC6: 38504 | BD6: 38596 | BE6: FY 2005 | BF6: 38687 | BG6: 38777 | BH6: 38869 | BI6: 38961 | BJ6: FY 2006 | BK6: 39052 | BL6: 39142 | BM6: 39234 | BN6: 39326 | BO6: FY 2007 | BP6: 39417 | BQ6: 39508 | BR6: 39600 | BS6: 39692 | BT6: FY 2008 | BU6: 39783 | BV6: 39873 | BW6: 39965 | BX6: 40057 | BY6: FY 2009 | BZ6: 40148 | CA6: 40238 | CB6: 40330 | CC6: 40422 | CD6: FY 2010 | CE6: 40513 | CF6: 40603 | CG6: 40695 | CH6: 40787 | CI6: FY 2011 | CJ6: 40878 | CK6: 40969 | CL6: 41061 | CM6: 41153 | CN6: FY 2012 | CO6: 41244 | CP6: 41334 | CQ6: 41426 | CR6: 41518 | CS6: FY 2013 | CT6: 41609 | CU6: 41699 | CV6: 41791 | CW6: 41883 | CX6: FY 2014 | CY6: 41974 | CZ6: 42064 | DA6: 42156 | DB6: 42248 | DC6: FY 2015 | DD6: 42339 | DE6: 42430 | DF6: 42522 | DG6: 42614 | DH6: FY 2016 | DI6: 42705 | DJ6: 42795 | DK6: 42887 | DL6: 42979 | DM6: FY 2017 | DN6: 43070 | DO6: 43160 | DP6: 43252 | DQ6: 43344 | DR6: FY 2018 | DS6: Dec-18E | DT6: Mar-19E | DU6: Jun-19E | DV6: Sep-19E | DW6: FY2019E | DX6: Dec-19E | DY6: Mar-20E | DZ6: Jun-20E | EA6: Sep-20E | EB6: FY2020E
A7: ASSETS | BW7: 39992 | BX7: 40083 | BY7: =BX7 -> 40083 | BZ7: 40174 | CA7: 40265 | CB7: 40356 | CC7: 40454 | CD7: =CC7 -> 40454 | CE7: 40545 | CF7: 40636 | CG7: 40727 | CH7: 40818 | CI7: =CH7 -> 40818 | CJ7: =CI7+91 -> 40909 | CK7: =CJ7+91 -> 41000 | CL7: =CK7+91 -> 41091 | CM7: =CL7+91 -> 41182 | CN7: =CM7 -> 41182 | CO7: 41273 | CP7: 41364 | CQ7: 41455 | CR7: 41546 | CS7: =CR7 -> 41546 | CT7: 41637 | CU7: =CT7+13*7 -> 41728 | CV7: =CU7+13*7 -> 41819 | CW7: =CV7+13*7 -> 41910 | CX7: =CW7 -> 41910 | CY7: =CX7+13*7 -> 42001 | CZ7: =CY7+13*7 -> 42092 | DA7: =CZ7+13*7 -> 42183 | DB7: =DA7+13*7 -> 42274 | DC7: =DB7 -> 42274 | DD7: =DC7+13*7 -> 42365 | DE7: =DD7+13*7 -> 42456 | DF7: =DE7+13*7 -> 42547 | DG7: =DF7+14*7 -> 42645 | DH7: =DG7 -> 42645 | DI7: =DH7+13*7 -> 42736 | DJ7: =DI7+13*7 -> 42827 | DK7: =DJ7+13*7 -> 42918 | DL7: =DK7+13*7 -> 43009 | DM7: =DL7 -> 43009 | DN7: =DM7+13*7 -> 43100 | DO7: =DN7+13*7 -> 43191 | DP7: =DO7+13*7 -> 43282 | DQ7: =DP7+13*7 -> 43373 | DR7: =DQ7 -> 43373 | DS7: =DR7+13*7 -> 43464 | DT7: =DS7+13*7 -> 43555 | DU7: =DT7+13*7 -> 43646 | DV7: =DU7+13*7 -> 43737 | DW7: =DV7 -> 43737 | DX7: =DW7+13*7 -> 43828 | DY7: =DX7+13*7 -> 43919 | DZ7: =DY7+13*7 -> 44010 | EA7: =DZ7+13*7 -> 44101 | EB7: =EA7 -> 44101
A8: Current Assets
A9: Cash and equivalents | Q9: 70.126 | U9: 101.663 | V9: =U9 -> 101.663 | W9: 128.385 | X9: 127.474 | Y9: 90.946 | Z9: 66.419 | AA9: =Z9 -> 66.419 | AB9: 77.368 | AC9: 85.258 | AD9: 67.436 | AE9: 70.817 | AF9: =AE9 -> 70.817 | AG9: 177.441 | AH9: 215.18 | AI9: 151.991 | AJ9: 113.237 | AK9: =AJ9 -> 113.237 | AL9: 226.833 | AM9: 161.844 | AN9: 209.143 | AO9: 99.677 | AP9: =AO9 -> 99.677 | AQ9: 251.461 | AR9: 250.401 | AS9: 263.638 | AT9: 200.907 | AU9: =AT9 -> 200.907 | AV9: 448.676 | AW9: 370.081 | AX9: 383.373 | AY9: 145.053 | AZ9: =AY9 -> 145.053 | BA9: 643.548 | BB9: 177.142 | BC9: 130.112 | BD9: 173.809 | BE9: =BD9 -> 173.809 | BF9: 251.435 | BG9: 202.671 | BH9: 215.739 | BI9: 312.606 | BJ9: =BI9 -> 312.606 | BK9: 270.873 | BL9: 200.179 | BM9: 172.789 | BN9: 281.261 | BO9: =BN9 -> 281.261 | BP9: 349.3 | BQ9: 303.4 | BR9: 297 | BS9: 269.8 | BT9: =BS9 -> 269.8 | BU9: 356.8 | BV9: 253.2 | BW9: 292 | BX9: 599.8 | BY9: =BX9 -> 599.8 | BZ9: 1306.3 | CA9: 1086 | CB9: 1125.2 | CC9: 1164 | CD9: =CC9 -> 1164 | CE9: 1792 | CF9: 1645.2 | CG9: 1720.8 | CH9: 1148.1 | CI9: =CH9 -> 1148.1 | CJ9: 1569.6 | CK9: 1432.2 | CL9: 1501.3 | CM9: 1188.6 | CN9: =CM9 -> 1188.6 | CO9: 1852.1 | CP9: 1223.2 | CQ9: 1430.8 | CR9: 2575.7 | CS9: =CR9 -> 2575.7 | CT9: 1545.8 | CU9: 1190.3 | CV9: 1019.4 | CW9: 1708.4 | CX9: =CW9 -> 1708.4 | CY9: 1857 | CZ9: 1750.4 | DA9: 2080.5 | DB9: 1530.1 | DC9: =DB9 -> 1530.1 | DD9: 2263.5 | DE9: 1294.4 | DF9: 2141.8 | DG9: 2128.8 | DH9: =DG9 -> 2128.8 | DI9: 2034.6 | DJ9: 2163.9 | DK9: 2716.2 | DL9: 2462.3 | DM9: =DL9 -> 2462.3 | DN9: =CF!DN78 -> 4859.3241 | DO9: =CF!DO78 -> 4064.8269 | DP9: =CF!DP78 -> 3677.0444 | DQ9: =CF!DQ78 -> 3197.7168 | DR9: =DQ9 -> 3197.7168 | DS9: =CF!DS78 -> 4526.9099 | DT9: =CF!DT78 -> 3849.1138 | DU9: =CF!DU78 -> 3558.4988 | DV9: =CF!DV78 -> 3207.1224 | DW9: =DV9 -> 3207.1224 | DX9: =CF!DX78 -> 4266.3009 | DY9: =CF!DY78 -> 3817.2383 | DZ9: =CF!DZ78 -> 3380.9122 | EA9: =CF!EA78 -> 2916.4022 | EB9: =EA9 -> 2916.4022
A10: Available-for-sale securities | Q10: 83.504 | U10: 21.874 | V10: =U10 -> 21.874 | W10: 56.079 | X10: 38.223 | Y10: 58.461 | Z10: 51.367 | AA10: =Z10 -> 51.367 | AB10: 72.808 | AC10: 42.926 | AD10: 56.127 | AE10: 57.573 | AF10: =AE10 -> 57.573 | AG10: 44.593 | AH10: 45.649 | AI10: 115.654 | AJ10: 101.399 | AK10: =AJ10 -> 101.399 | AL10: 72.771 | AM10: 151.537 | AN10: 206.827 | AO10: 217.302 | AP10: =AO10 -> 217.302 | AQ10: 191.134 | AR10: 240.111 | AS10: 282.879 | AT10: 128.905 | AU10: =AT10 -> 128.905 | AV10: 190.329 | AW10: 258.409 | AX10: 311.847 | AY10: 483.157 | AZ10: =AY10 -> 483.157 | BA10: 303.285 | BB10: 490.379 | BC10: 183.782 | BD10: 95.379 | BE10: =BD10 -> 95.379 | BF10: 240.25 | BG10: 193.231 | BH10: 175.851 | BI10: 87.542 | BJ10: =BI10 -> 87.542 | BK10: 103.184 | BL10: 77.872 | BM10: 85.956 | BN10: 83.845 | BO10: =BN10 -> 83.845 | BP10: 113.2 | BQ10: 0 | BR10: 0 | BS10: 3 | BT10: =BS10 -> 3 | BU10: 3 | BV10: 7.8 | BW10: 5.6 | BX10: 21.5 | BY10: =BX10 -> 21.5 | BZ10: 2.5 | CA10: 158.3 | CB10: 223.9 | CC10: 236.5 | CD10: =CC10 -> 236.5 | CE10: 204.5 | CF10: 224.8 | CG10: 173.6 | CH10: 855 | CI10: =CH10 -> 855 | CJ10: 703.6 | CK10: 802.1 | CL10: 996.3 | CM10: 848.4 | CN10: =CM10 -> 848.4 | CO10: 607.6 | CP10: 474.5 | CQ10: 613.5 | CR10: 658.1 | CS10: =CR10 -> 658.1 | CT10: 157 | CU10: 299.2 | CV10: 176.9 | CW10: 135.4 | CX10: =CW10 -> 135.4 | CY10: 96.1 | CZ10: 99.4 | DA10: 94.7 | DB10: 81.3 | DC10: =DB10 -> 81.3 | DD10: 116.4 | DE10: 123.2 | DF10: 174.5 | DG10: 134.4 | DH10: =DG10 -> 134.4 | DI10: 140.8 | DJ10: 231 | DK10: 289.9 | DL10: 228.6 | DM10: =DL10 -> 228.6 | DN10: =DM10-CF!DN42-CF!DN44 -> 228.6 | DO10: =DN10-CF!DO42-CF!DO44 -> 228.6 | DP10: =DO10-CF!DP42-CF!DP44 -> 228.6 | DQ10: =DP10-CF!DQ42-CF!DQ44 -> 228.6 | DR10: =DQ10 -> 228.6 | DS10: =DR10-CF!DS42-CF!DS44 -> 228.6 | DT10: =DS10-CF!DT42-CF!DT44 -> 228.6 | DU10: =DT10-CF!DU42-CF!DU44 -> 228.6 | DV10: =DU10-CF!DV42-CF!DV44 -> 228.6 | DW10: =DV10 -> 228.6 | DX10: =DW10-CF!DX42-CF!DX44 -> 228.6 | DY10: =DX10-CF!DY42-CF!DY44 -> 228.6 | DZ10: =DY10-CF!DZ42-CF!DZ44 -> 228.6 | EA10: =DZ10-CF!EA42-CF!EA44 -> 228.6 | EB10: =EA10 -> 228.6
A11: Trading securities | Q11: 0 | U11: 0 | V11: =U11 -> 0 | W11: 0 | X11: 0 | Y11: 0 | Z11: 0 | AA11: =Z11 -> 0 | AB11: 0 | AC11: 0 | AD11: 0 | AE11: 3.763 | AF11: =AE11 -> 3.763 | AG11: 5.695 | AH11: 5.34 | AI11: 6.322 | AJ11: 5.913 | AK11: =AJ11 -> 5.913 | AL11: 9.06 | AM11: 9.909 | AN11: 10.446 | AO11: 10.36 | AP11: =AO11 -> 10.36 | AQ11: 14.316 | AR11: 15.875 | AS11: 18.789 | AT11: 20.199 | AU11: =AT11 -> 20.199 | AV11: 26.388 | AW11: 29.144 | AX11: 23.893 | AY11: 24.799 | AZ11: =AY11 -> 24.799 | BA11: 31.587 | BB11: 33.083 | BC11: 34.647 | BD11: 37.848 | BE11: =BD11 -> 37.848 | BF11: 46.845 | BG11: 49.546 | BH11: 50.389 | BI11: 53.496 | BJ11: =BI11 -> 53.496 | BK11: 62.413 | BL11: 65.78 | BM11: 71.278 | BN11: 73.588 | BO11: =BN11 -> 73.588 | BP11: 72.9 | BQ11: 68.1 | BR11: 52.7 | BS11: 49.5 | BT11: =BS11 -> 49.5 | BU11: 35.7 | BV11: 33.5 | BW11: 39.1 | BX11: 44.8 | BY11: =BX11 -> 44.8 | BZ11: 47.9 | CA11: 49.6 | CB11: 46 | CC11: 49.2 | CD11: =CC11 -> 49.2 | CE11: 54.1 | CF11: 57.5 | CG11: 58.1 | CH11: 47.6 | CI11: =CH11 -> 47.6 | CJ11: 0 | CK11: 0 | CL11: 0 | CM11: 0 | CN11: =CM11 -> 0 | CO11: 0 | CP11: 0 | CQ11: 0 | CR11: 0 | CS11: =CR11 -> 0 | CT11: 0 | CU11: 0 | CV11: 0 | CW11: =CV11 -> 0 | CX11: =CW11 -> 0 | CY11: =CX11 -> 0 | CZ11: 0 | DA11: 0 | DB11: =DA11 -> 0 | DC11: =DB11 -> 0 | DD11: =DC11 -> 0 | DE11: 0 | DF11: 0 | DG11: 0 | DH11: =DG11 -> 0 | DI11: 0 | DJ11: 0 | DK11: 0 | DL11: =DK11 -> 0 | DM11: =DL11 -> 0 | DN11: =DM11 -> 0 | DO11: =DN11 -> 0 | DP11: =DO11 -> 0 | DQ11: =DP11 -> 0 | DR11: =DQ11 -> 0 | DS11: =DR11 -> 0 | ... EB11: =EA11 -> 0
A12: Accounts receivable (Net) | Q12: 31.231 | U12: 50.972 | V12: =U12 -> 50.972 | W12: 45.02 | X12: 37.971 | Y12: 41.468 | Z12: 47.646 | AA12: =Z12 -> 47.646 | AB12: 48.567 | AC12: 58.599 | AD12: 63.149 | AE12: 76.385 | AF12: =AE12 -> 76.385 | AG12: 78.349 | AH12: 75.982 | AI12: 95.943 | AJ12: 90.425 | AK12: =AJ12 -> 90.425 | AL12: 89.713 | AM12: 85.971 | AN12: 93.77 | AO12: 97.573 | AP12: =AO12 -> 97.573 | AQ12: 111.249 | AR12: 103.142 | AS12: 107.472 | AT12: 114.448 | AU12: =AT12 -> 114.448 | AV12: 122.072 | AW12: 118.587 | AX12: 122.76 | AY12: 140.226 | AZ12: =AY12 -> 140.226 | BA12: 149.406 | BB12: 151.638 | BC12: 148.982 | BD12: 190.762 | BE12: =BD12 -> 190.762 | BF12: 197.765 | BG12: 190.452 | BH12: 184.941 | BI12: 224.271 | BJ12: =BI12 -> 224.271 | BK12: 227.823 | BL12: 240.775 | BM12: 250.866 | BN12: 287.925 | BO12: =BN12 -> 287.925 | BP12: 316.2 | BQ12: 300.3 | BR12: 284.1 | BS12: 329.5 | BT12: =BS12 -> 329.5 | BU12: 332 | BV12: 309.3 | BW12: 295.2 | BX12: 271 | BY12: =BX12 -> 271 | BZ12: 263.4 | CA12: 299.7 | CB12: 282.5 | CC12: 302.7 | CD12: =CC12 -> 302.7 | CE12: 316.1 | CF12: 355.7 | CG12: 361.5 | CH12: 386.5 | CI12: =CH12 -> 386.5 | CJ12: 431 | CK12: 437.4 | CL12: 433 | CM12: 485.9 | CN12: =CM12 -> 485.9 | CO12: 469.2 | CP12: 520 | CQ12: 506.8 | CR12: 561.4 | CS12: =CR12 -> 561.4 | CT12: 589.8 | CU12: 590 | CV12: 580.9 | CW12: 631 | CX12: =CW12 -> 631 | CY12: 664.9 | CZ12: 655.6 | DA12: 672.7 | DB12: 719 | DC12: =DB12 -> 719 | DD12: 764.4 | DE12: 743.7 | DF12: 747.3 | DG12: 768.8 | DH12: =DG12 -> 768.8 | DI12: 865.1 | DJ12: 791 | DK12: 791.1 | DL12: 870.4 | DM12: =DL12 -> 870.4 | DN12: =DN80*DN85/365 -> 916.52704 | DO12: =DO80*DO85/365 -> 889.14107 | DP12: =DP80*DP85/365 -> 885.02619 | DQ12: =DQ80*DQ85/365 -> 862.5291 | DR12: =DQ12 -> 862.5291 | DS12: =DS80*DS85/365 -> 1016.4877 | DT12: =DT80*DT85/365 -> 973.50418 | DU12: =DU80*DU85/365 -> 970.44906 | DV12: =DV80*DV85/365 -> 946.06055 | DW12: =DV12 -> 946.06055 | DX12: =DX80*DX85/365 -> 1112.6372 | DY12: =DY80*DY85/365 -> 1066.4444 | DZ12: =DZ80*DZ85/365 -> 1062.3737 | EA12: =EA80*EA85/365 -> 1034.6285 | EB12: =EA12 -> 1034.6285
A13: Inventory | Q13: 119.767 | U13: 143.11 | V13: =U13 -> 143.11 | W13: 117.95 | X13: 129.184 | Y13: 166.579 | Z13: 180.886 | AA13: =Z13 -> 180.886 | AB13: 157.232 | AC13: 151.948 | AD13: 181.986 | AE13: 201.656 | AF13: =AE13 -> 201.656 | AG13: 168.438 | AH13: 151.368 | AI13: 189.889 | AJ13: 221.253 | AK13: =AJ13 -> 221.253 | AL13: 176.972 | AM13: 172.306 | AN13: 218.99 | AO13: 263.174 | AP13: =AO13 -> 263.174 | AQ13: 210.114 | AR13: 203.212 | AS13: 280.239 | AT13: 342.944 | AU13: =AT13 -> 342.944 | AV13: 305.529 | AW13: 307.215 | AX13: 385.284 | AY13: 422.663 | AZ13: =AY13 -> 422.663 | BA13: 379.475 | BB13: 406.073 | BC13: 495.542 | BD13: 546.299 | BE13: =BD13 -> 546.299 | BF13: 452.65 | BG13: 456.215 | BH13: 557.359 | BI13: 636.222 | BJ13: =BI13 -> 636.222 | BK13: 547.277 | BL13: 578.877 | BM13: 657.466 | BN13: 691.658 | BO13: =BN13 -> 691.658 | BP13: 580.9 | BQ13: 607.3 | BR13: 662.7 | BS13: 692.8 | BT13: =BS13 -> 692.8 | BU13: 590.4 | BV13: 627.8 | BW13: 703.6 | BX13: 664.9 | BY13: =BX13 -> 664.9 | BZ13: 544.9 | CA13: 488.7 | CB13: 496.6 | CC13: 543.3 | CD13: =CC13 -> 543.3 | CE13: 620.5 | CF13: 772.4 | CG13: 856.7 | CH13: 965.8 | CI13: =CH13 -> 965.8 | CJ13: 1124 | CK13: 1205 | CL13: 1249.2 | CM13: 1241.5 | CN13: =CM13 -> 1241.5 | CO13: 1093.2 | CP13: 1124.5 | CQ13: 1173.8 | CR13: 1111.2 | CS13: =CR13 -> 1111.2 | CT13: 943.3 | CU13: 954.7 | CV13: 1025.8 | CW13: 1090.9 | CX13: =CW13 -> 1090.9 | CY13: 1018.3 | CZ13: 1061.1 | DA13: 1166 | DB13: 1306.4 | DC13: =DB13 -> 1306.4 | DD13: 1242.6 | DE13: 1293.1 | DF13: 1325.1 | DG13: 1378.5 | DH13: =DG13 -> 1378.5 | DI13: 1218.7 | DJ13: 1323.6 | DK13: 1357.3 | DL13: 1364 | DM13: =DL13 -> 1364 | DN13: =DN81*DN86/365 -> 1329.0999 | DO13: =DO81*DO86/365 -> 1517.1539 | DP13: =DP81*DP86/365 -> 1546.0036 | DQ13: =DQ81*DQ86/365 -> 1594.642 | DR13: =DQ13 -> 1594.642 | DS13: =DS81*DS86/365 -> 1458.8123 | DT13: =DT81*DT86/365 -> 1637.9951 | DU13: =DU81*DU86/365 -> 1672.7939 | DV13: =DV81*DV86/365 -> 1728.1949 | DW13: =DV13 -> 1728.1949 | DX13: =DX81*DX86/365 -> 1583.2362 | DY13: =DY81*DY86/365 -> 1779.1055 | DZ13: =DZ81*DZ86/365 -> 1815.516 | EA13: =EA81*EA86/365 -> 1874.2489 | EB13: =EA13 -> 1874.2489
A14: Prepaid expenses and other | Q14: 8.763 | U14: 11.205 | V14: =U14 -> 11.205 | W14: 11.643 | X14: 15.883 | Y14: 19.967 | Z14: 19.049 | AA14: =Z14 -> 19.049 | AB14: 17.549 | AC14: 26.866 | AD14: 21.248 | AE14: 20.321 | AF14: =AE14 -> 20.321 | AG14: 22.417 | AH14: 29.43 | AI14: 29.567 | AJ14: 29.829 | AK14: =AJ14 -> 29.829 | AL14: 36.53 | AM14: 39.544 | AN14: 38.467 | AO14: 42.351 | AP14: =AO14 -> 42.351 | AQ14: 42.892 | AR14: 50.608 | AS14: 62.291 | AT14: 55.173 | AU14: =AT14 -> 55.173 | AV14: 59.825 | AW14: 59.656 | AX14: 64.758 | AY14: 71.347 | AZ14: =AY14 -> 71.347 | BA14: 71.718 | BB14: 83.175 | BC14: 80.77 | BD14: 94.429 | BE14: =BD14 -> 94.429 | BF14: 87.518 | BG14: 87.163 | BH14: 95.424 | BI14: 126.874 | BJ14: =BI14 -> 126.874 | BK14: 121.32 | BL14: 124.957 | BM14: 128.37 | BN14: 148.757 | BO14: =BN14 -> 148.757 | BP14: 144.7 | BQ14: 145.8 | BR14: 145.4 | BS14: 169.2 | BT14: =BS14 -> 169.2 | BU14: 159.7 | BV14: 159.6 | BW14: 145.1 | BX14: 147.2 | BY14: =BX14 -> 147.2 | BZ14: 141 | CA14: 136.1 | CB14: 156 | CC14: 156.5 | CD14: =CC14 -> 156.5 | CE14: 151 | CF14: 226.7 | CG14: 152.8 | CH14: 161.5 | CI14: =CH14 -> 161.5 | CJ14: 180.1 | CK14: 259.6 | CL14: 172.9 | CM14: 196.5 | CN14: =CM14 -> 196.5 | CO14: 178.3 | CP14: 256.7 | CQ14: 302 | CR14: 287.7 | CS14: =CR14 -> 287.7 | CT14: 271.1 | CU14: 286.1 | CV14: 289.4 | CW14: 285.6 | CX14: =CW14 -> 285.6 | CY14: 600.5 | CZ14: 355.1 | DA14: 413.8 | DB14: 334.2 | DC14: =DB14 -> 334.2 | DD14: 340.8 | DE14: 429.1 | DF14: 467.5 | DG14: 350 | DH14: =DG14 -> 350 | DI14: 357 | DJ14: 409.9 | DK14: 354.8 | DL14: 358.1 | DM14: =DL14 -> 358.1 | DN14: =DM14 -> 358.1 | DO14: =DN14 -> 358.1 | DP14: =DO14 -> 358.1 | DQ14: =DP14 -> 358.1 | DR14: =DQ14 -> 358.1 | DS14: =DR14 -> 358.1 | DT14: =DS14 -> 358.1 | ... EB14: =EA14 -> 358.1
A15: Deferred income taxes | Q15: 4.164 | U15: 8.448 | V15: =U15 -> 8.448 | W15: 9.023 | X15: 8.536 | Y15: 9.059 | Z15: 21.133 | AA15: =Z15 -> 21.133 | AB15: 25.093 | AC15: 26.369 | AD15: 26.146 | AE15: 29.304 | AF15: =AE15 -> 29.304 | AG15: 30.358 | AH15: 35.074 | AI15: 35.428 | AJ15: 31.869 | AK15: =AJ15 -> 31.869 | AL15: 38.824 | AM15: 40.691 | AN15: 41.043 | AO15: 42.206 | AP15: =AO15 -> 42.206 | AQ15: 47.876 | AR15: 43.621 | AS15: 47.584 | AT15: 61.453 | AU15: =AT15 -> 61.453 | AV15: 71.528 | AW15: 78.196 | AX15: 79.776 | AY15: 63.65 | AZ15: =AY15 -> 63.65 | BA15: 73.701 | BB15: 70.967 | BC15: 66.54 | BD15: 70.808 | BE15: =BD15 -> 70.808 | BF15: 77.046 | BG15: 87.477 | BH15: 89.969 | BI15: 88.777 | BJ15: =BI15 -> 88.777 | BK15: 96.646 | BL15: 96.422 | BM15: 101.071 | BN15: 129.453 | BO15: =BN15 -> 129.453 | BP15: 160.4 | BQ15: 154.3 | BR15: 215.4 | BS15: 234.2 | BT15: =BS15 -> 234.2 | BU15: 216.3 | BV15: 212.9 | BW15: 237.1 | BX15: 286.6 | BY15: =BX15 -> 286.6 | BZ15: 277.9 | CA15: 272 | CB15: 280.7 | CC15: 304.2 | CD15: =CC15 -> 304.2 | CE15: 262.2 | CF15: 258 | CG15: 263.5 | CH15: 230.4 | CI15: =CH15 -> 230.4 | CJ15: 228.8 | CK15: 215.2 | CL15: 216.9 | CM15: 238.7 | CN15: =CM15 -> 238.7 | CO15: 215.6 | CP15: 211.3 | CQ15: 212.8 | CR15: 277.3 | CS15: =CR15 -> 277.3 | CT15: 252.4 | CU15: 258.7 | CV15: 264.5 | CW15: 317.4 | CX15: =CW15 -> 317.4 | CY15: 309.3 | CZ15: 323.8 | DA15: 333 | DB15: 0 | DC15: =DB15 -> 0 | DD15: 0 | DE15: 0 | DF15: 0 | DG15: 0 | DH15: =DG15 -> 0 | DI15: 0 | DJ15: =DI15 -> 0 | DK15: 0 | DL15: =DK15 -> 0 | DM15: =DL15 -> 0 | DN15: =DM15 -> 0 | DO15: =DN15 -> 0 | DP15: =DO15 -> 0 | DQ15: =DP15 -> 0 | DR15: =DQ15 -> 0 | DS15: =DR15 -> 0 | ... EB15: =EA15 -> 0
A16: Total Current Assets | B16: 84.58 | C16: =SUM(C9:C14) -> 0 | D16: =SUM(D9:D14) -> 0 | E16: =SUM(E9:E14) -> 0 | F16: =SUM(F9:F14) -> 0 | G16: 205.35 | H16: =SUM(H9:H14) -> 0 | I16: =SUM(I9:I14) -> 0 | J16: =SUM(J9:J14) -> 0 | K16: =SUM(K9:K14) -> 0 | L16: 339.5 | M16: =SUM(M9:M14) -> 0 | N16: =SUM(N9:N14) -> 0 | O16: =SUM(O9:O14) -> 0 | P16: =SUM(P9:P14) -> 0 | Q16: =SUM(Q9:Q15) -> 317.555 | R16: =SUM(R9:R14) -> 0 | S16: =SUM(S9:S14) -> 0 | T16: =SUM(T9:T14) -> 0 | U16: =SUM(U9:U15) -> 337.272 | V16: =SUM(V9:V15) -> 337.272 | W16: =SUM(W9:W15) -> 368.1 | X16: =SUM(X9:X15) -> 357.271 | Y16: =SUM(Y9:Y15) -> 386.48 | Z16: =SUM(Z9:Z15) -> 386.5 | AA16: =SUM(AA9:AA15) -> 386.5 | AB16: =SUM(AB9:AB15) -> 398.617 | ... EB16: =SUM(EB9:EB15) -> 6411.9795
A18: Long-term investments - available for sale securities | AT18: 136.159 | AU18: =AT18 -> 136.159 | AV18: 178.867 | AW18: 195.508 | AX18: 158.962 | AY18: 135.179 | AZ18: 135.179 | BA18: 164.586 | BB18: 142.782 | BC18: 83.894 | BD18: 60.475 | BE18: 60.475 | BF18: 55.659 | BG18: 37.639 | BH18: 24.045 | BI18: 5.811 | BJ18: 5.811 | BK18: 23.28 | BL18: 20.994 | BM18: 15.98 | BN18: 21.022 | BO18: =BN18 -> 21.022 | BP18: 0 | BQ18: 70.5 | BR18: 77.6 | BS18: 71.4 | BT18: =BS18 -> 71.4 | BU18: 80 | BV18: 77.2 | BW18: 68.1 | BX18: 71.2 | BY18: 71.2 | BZ18: 78 | CA18: 270 | CB18: 263.9 | CC18: 191.8 | CD18: =CC18 -> 191.8 | CE18: 130.6 | CF18: 93.5 | CG18: 89.6 | CH18: 107 | CI18: =CH18 -> 107 | CJ18: 146.1 | CK18: 145.9 | CL18: 140.1 | CM18: 116 | CN18: =CM18 -> 116 | CO18: 80 | CP18: 44.4 | CQ18: 45.4 | CR18: 58.3 | CS18: =CR18 -> 58.3 | CT18: 480 | CU18: 449.8 | CV18: 832.7 | CW18: 318.4 | CX18: =CW18 -> 318.4 | CY18: 307.5 | CZ18: 325.1 | DA18: 390.1 | DB18: 312.5 | DC18: =DB18 -> 312.5 | DD18: 366.9 | DE18: 605 | DF18: 819.5 | DG18: 1141.7 | DH18: =DG18 -> 1141.7 | DI18: 1278.3 | DJ18: 1070.1 | DK18: 708.3 | DL18: 542.3 | DM18: =DL18 -> 542.3 | DN18: =DM18 -> 542.3 | DO18: =DN18 -> 542.3 | DP18: =DO18 -> 542.3 | DQ18: =DP18 -> 542.3 | DR18: =DQ18 -> 542.3 | DS18: =DR18 -> 542.3 | DT18: =DS18 -> 542.3 | ... EB18: =EA18 -> 542.3
A19: Equity and other investments (JV's) | Q19: 34.464 | U19: 38.917 | V19: =U19 -> 38.917 | W19: 43.559 | X19: 48.527 | Y19: 55.078 | Z19: 68.06 | AA19: =Z19 -> 68.06 | AB19: 82.424 | AC19: 104.988 | AD19: 108.794 | AE19: =52.051+3.788 -> 55.839 | AF19: =AE19 -> 55.839 | AG19: =63.898+3.832 -> 67.73 | AH19: =60.348+1.948 -> 62.296 | AI19: =56.363+1.948 -> 58.311 | AJ19: 63.097 | AK19: =AJ19 -> 63.097 | AL19: 98.023 | AM19: 98.581 | AN19: 108.249 | AO19: 102.929 | AP19: =AO19 -> 102.929 | AQ19: 107.575 | AR19: 111.275 | AS19: 119.339 | AT19: 144.257 | AU19: =AT19 -> 144.257 | AV19: 150.462 | AW19: 164.786 | AX19: 162.246 | AY19: 168.177 | AZ19: 167.74 | BA19: 184.635 | BB19: 189.115 | BC19: 182.067 | BD19: 201.089 | BE19: 201.089 | BF19: 207.47 | BG19: 214.78 | BH19: 217.306 | BI19: 219.093 | BJ19: 219.093 | BK19: 224.918 | BL19: 230.594 | BM19: 242.46 | BN19: 258.846 | BO19: =BN19 -> 258.846 | BP19: 270.3 | BQ19: 305.6 | BR19: 311.1 | BS19: 302.6 | BT19: =BS19 -> 302.6 | BU19: 311.1 | BV19: 310.2 | BW19: 340.3 | BX19: 352.3 | BY19: 352.3 | BZ19: 315.4 | CA19: 318.8 | CB19: 328.9 | CC19: 341.5 | CD19: =CC19 -> 341.5 | CE19: 352.9 | CF19: 354 | CG19: 384.1 | CH19: 372.3 | CI19: =CH19 -> 372.3 | CJ19: 382 | CK19: 393.8 | CL19: 414.3 | CM19: 459.9 | CN19: =CM19 -> 459.9 | CO19: 454.3 | CP19: 424.5 | CQ19: 443.4 | CR19: 496.5 | CS19: =CR19 -> 496.5 | CT19: 489.3 | CU19: 512.8 | CV19: 541.5 | CW19: 514.9 | CX19: =CW19 -> 514.9 | CY19: 320.9 | CZ19: 337 | DA19: 359.4 | DB19: 352 | DC19: =DB19 -> 352 | DD19: 289.6 | DE19: 332.4 | DF19: 352.6 | DG19: 354.5 | DH19: =DG19 -> 354.5 | DI19: 373.7 | DJ19: 391.2 | DK19: 430.2 | DL19: 481.6 | DM19: =DL19 -> 481.6 | DN19: =DM19-CF!DN18+CF!DN20 -> 481.6 | DO19: =DN19-CF!DO18+CF!DO20 -> 481.6 | DP19: =DO19-CF!DP18+CF!DP20 -> 481.6 | DQ19: =DP19-CF!DQ18+CF!DQ20 -> 481.6 | DR19: =DQ19 -> 481.6 | DS19: =DR19-CF!DS18+CF!DS20 -> 481.6 | DT19: =DS19-CF!DT18+CF!DT20 -> 481.6 | DU19: =DT19-CF!DU18+CF!DU20 -> 481.6 | DV19: =DU19-CF!DV18+CF!DV20 -> 481.6 | DW19: =DV19 -> 481.6 | DX19: =DW19-CF!DX18+CF!DX20 -> 481.6 | DY19: =DX19-CF!DY18+CF!DY20 -> 481.6 | DZ19: =DY19-CF!DZ18+CF!DZ20 -> 481.6 | EA19: =DZ19-CF!EA18+CF!EA20 -> 481.6 | EB19: =EA19 -> 481.6
A20: Property, plant & equipment, net | Q20: 483.8 | U20: 600.79 | V20: =U20 -> 600.79 | W20: 628.2 | X20: 654.224 | Y20: 691.7 | Z20: 760.289 | AA20: =Z20 -> 760.289 | AB20: 796.55 | AC20: 840.944 | AD20: 882.475 | AE20: 930.759 | AF20: =AE20 -> 930.759 | AG20: 960.383 | AH20: 997.585 | AI20: 1048.139 | AJ20: 1135.784 | AK20: =AJ20 -> 1135.784 | AL20: 1159.462 | AM20: 1195.397 | AN20: 1224.154 | AO20: 1265.756 | AP20: =AO20 -> 1265.756 | AQ20: 1303.892 | AR20: 1329.905 | AS20: 1346.525 | AT20: 1384.902 | AU20: =AT20 -> 1384.902 | AV20: 1377.716 | AW20: 1372.003 | AX20: 1383.058 | AY20: 1551.416 | AZ20: 1551.416 | BA20: 1655.121 | BB20: 1698.803 | BC20: 1738.83 | BD20: 1842.019 | BE20: 1842.019 | BF20: 1870.793 | BG20: 1963.701 | BH20: 2090.903 | BI20: 2287.899 | BJ20: 2287.899 | BK20: 2396.801 | BL20: 2523.87 | BM20: 2686.969 | BN20: 2890.433 | BO20: =BN20 -> 2890.433 | BP20: 2993 | BQ20: 3052.3 | BR20: 2947.4 | BS20: 2956.4 | BT20: =BS20 -> 2956.4 | BU20: 2822.5 | BV20: 2658 | BW20: 2594.2 | BX20: 2536.4 | BY20: 2536.4 | BZ20: 2482.7 | CA20: 2414.6 | CB20: 2361.5 | CC20: 2416.5 | CD20: =CC20 -> 2416.5 | CE20: 2393.6 | CF20: 2378.5 | CG20: 2384.8 | CH20: 2355 | CI20: =CH20 -> 2355 | CJ20: 2347.3 | CK20: 2382.5 | CL20: 2444.2 | CM20: 2658.9 | CN20: =CM20 -> 2658.9 | CO20: 2711.1 | CP20: 2845.3 | CQ20: 2987.1 | CR20: 3200.5 | CS20: =CR20 -> 3200.5 | CT20: 3233 | CU20: 3278.1 | CV20: 3373.7 | CW20: 3519 | CX20: =CW20 -> 3519 | CY20: 3822.3 | CZ20: 3897.7 | DA20: 3977.7 | DB20: 4088.3 | DC20: =DB20 -> 4088.3 | DD20: 4122.5 | DE20: 4246.9 | DF20: 4359.2 | DG20: 4533.8 | DH20: =DG20 -> 4533.8 | DI20: 4478.5 | DJ20: 4564.5 | DK20: 4699.8 | DL20: 4919.5 | DM20: =DL20 -> 4919.5 | DN20: =DM20-CF!DN50-CF!DN12 -> 5116.2275 | DO20: =DN20-CF!DO50-CF!DO12 -> 5275.7635 | DP20: =DO20-CF!DP50-CF!DP12 -> 5465.4173 | DQ20: =DP20-CF!DQ50-CF!DQ12 -> 5820.2137 | DR20: =DQ20 -> 5820.2137 | DS20: =DR20-CF!DS50-CF!DS12 -> 6001.8923 | DT20: =DS20-CF!DT50-CF!DT12 -> 6156.0934 | DU20: =DT20-CF!DU50-CF!DU12 -> 6341.9425 | DV20: =DU20-CF!DV50-CF!DV12 -> 6672.1824 | DW20: =DV20 -> 6672.1824 | DX20: =DW20-CF!DX50-CF!DX12 -> 6840.8617 | DY20: =DX20-CF!DY50-CF!DY12 -> 6979.5036 | DZ20: =DY20-CF!DZ50-CF!DZ12 -> 7150.1701 | EA20: =DZ20-CF!EA50-CF!EA12 -> 7439.3293 | EB20: =EA20 -> 7439.3293
A21: Deferred Income taxes, net | Q21: 0 | U21: 0 | V21: =U21 -> 0 | W21: 0 | X21: 0 | Y21: 0 | Z21: 0 | AA21: 0 | AB21: 0 | AC21: 0 | AD21: 0 | AE21: 0 | AF21: =AE21 -> 0 | AG21: 0 | AH21: 0 | AI21: 0 | AJ21: 0 | AK21: =AJ21 -> 0 | AP21: =AO21 | AQ21: 0 | AR21: 0 | AS21: 0 | AT21: 0 | AU21: =AT21 -> 0 | AV21: 0 | AW21: 0 | AX21: 0 | AY21: 0 | AZ21: 0 | BA21: 0 | BB21: 0 | BC21: 11.884 | BD21: 0 | BE21: 0 | BF21: 0 | BG21: 0 | BH21: 0 | BI21: 0 | BJ21: 0 | BK21: 0 | BL21: 0 | BM21: 0 | BN21: 0 | BO21: =BN21 -> 0 | BP21: 0 | BQ21: 0 | BR21: 0 | BS21: 0 | BT21: =BS21 -> 0 | BU21: 0 | BV21: 0 | BW21: 0 | BX21: 0 | BY21: 0 | BZ21: 0 | CA21: 0 | CB21: 0 | CC21: 0 | CD21: =CC21 -> 0 | CE21: 0 | CF21: 0 | CG21: 0 | CH21: 0 | CI21: =CH21 -> 0 | CJ21: 0 | CK21: 0 | CL21: 0 | CM21: 0 | CN21: =CM21 -> 0 | CO21: 0 | CP21: 0 | CQ21: 0 | CR21: 967 | CS21: =CR21 -> 967 | CT21: 949 | CU21: 943.4 | CV21: 947.1 | CW21: 903.3 | CX21: =CW21 -> 903.3 | CY21: 831.7 | CZ21: 851.1 | DA21: 851.2 | DB21: 1180.8 | DC21: =DB21 -> 1180.8 | DD21: 938.5 | DE21: 910.2 | DF21: 822.8 | DG21: 885.4 | DH21: =DG21 -> 885.4 | DI21: 806.1 | DJ21: 811.2 | DK21: 805.9 | DL21: 795.4 | DM21: =DL21 -> 795.4 | DN21: =DM21 -> 795.4 | DO21: =DN21 -> 795.4 | DP21: =DO21 -> 795.4 | DQ21: =DP21 -> 795.4 | DR21: =DQ21 -> 795.4 | DS21: =DR21 -> 795.4 | DT21: =DS21 -> 795.4 | ... EB21: =EA21 -> 795.4
A22: Other assets | Q22: 16.342 | U22: 15.764 | V22: =U22 -> 15.764 | W22: 16.594 | X22: 20.654 | Y22: 21.688 | Z22: 23.474 | AA22: =Z22 -> 23.474 | AB22: 27.582 | AC22: 27.367 | AD22: 27.141 | AE22: 25.403 | AF22: =AE22 -> 25.403 | AG22: 23.366 | AH22: 27.78 | AI22: 29.562 | AJ22: 36.388 | AK22: =AJ22 -> 36.388 | AL22: 35.22 | AM22: 42.855 | AN22: 44.129 | AO22: 43.691 | AP22: =AO22 -> 43.691 | AQ22: 43.113 | AR22: 42.071 | AS22: 44.167 | AT22: 52.113 | AU22: =AT22 -> 52.113 | AV22: 53.071 | AW22: 53.066 | AX22: 59.076 | AY22: 85.561 | AZ22: 85.561 | BA22: 62.584 | BB22: 58.978 | BC22: 63.49 | BD22: 72.893 | BE22: 72.893 | BF22: 97.375 | BG22: 125.171 | BH22: 147.648 | BI22: 186.917 | BJ22: 186.917 | BK22: 205.724 | BL22: 228.128 | BM22: 235.107 | BN22: 219.422 | BO22: =BN22 -> 219.422 | BP22: 247 | BQ22: 245 | BR22: 258.3 | BS22: 261.1 | BT22: =BS22 -> 261.1 | BU22: 294.2 | BV22: 303.4 | BW22: 287.9 | BX22: 253.8 | BY22: 253.8 | BZ22: 310.5 | CA22: 319 | CB22: 311.1 | CC22: 346.5 | CD22: =CC22 -> 346.5 | CE22: 317.9 | CF22: 323.4 | CG22: 312.1 | CH22: 297.7 | CI22: =CH22 -> 297.7 | CJ22: 386 | CK22: 392.1 | CL22: 404 | CM22: 385.7 | CN22: =CM22 -> 385.7 | CO22: 428.5 | CP22: 514.8 | CQ22: 485.8 | CR22: 274.8 | CS22: =CR22 -> 274.8 | CT22: 276.1 | CU22: 195.9 | CV22: 193 | CW22: 198.9 | CX22: =CW22 -> 198.9 | CY22: 382.2 | CZ22: 395.2 | DA22: 443.3 | DB22: 415.9 | DC22: =DB22 -> 415.9 | DD22: 416.9 | DE22: 401.2 | DF22: 391.1 | DG22: 417.7 | DH22: =DG22 -> 417.7 | DI22: 394.9 | DJ22: 368 | DK22: 365.3 | DL22: 362.8 | DM22: =DL22 -> 362.8 | DN22: =DM22 -> 362.8 | DO22: =DN22 -> 362.8 | DP22: =DO22 -> 362.8 | DQ22: =DP22 -> 362.8 | DR22: =DQ22 -> 362.8 | DS22: =DR22 -> 362.8 | DT22: =DS22 -> 362.8 | ... EB22: =EA22 -> 362.8
A23: Other intangible assets | Q23: 0 | V23: =U23 -> 0 | W23: 0 | X23: 0 | Y23: 0 | Z23: 0 | AA23: =Z23 -> 0 | AB23: 0 | AC23: 0 | AD23: 0 | AE23: 0 | AF23: =AE23 -> 0 | AG23: 0 | AH23: 0 | AI23: 0 | AJ23: 0 | AK23: =AJ23 -> 0 | AO23: 9.862 | AP23: =AO23 -> 9.862 | AQ23: 0 | AR23: 0 | AS23: 0 | AT23: 24.942 | AU23: =AT23 -> 24.942 | AV23: 25.27 | AW23: 25.628 | AX23: 25.948 | AY23: 26.8 | AZ23: 26.8 | BA23: 27.726 | BB23: 29.62 | BC23: 34.898 | BD23: 35.409 | BE23: 35.409 | BF23: 35.937 | BG23: 36.657 | BH23: 36.821 | BI23: 37.955 | BJ23: 37.955 | BK23: 39.469 | BL23: 39.942 | BM23: 40.392 | BN23: 42.043 | BO23: =BN23 -> 42.043 | BP23: 42.4 | BQ23: 58.1 | BR23: 65.8 | BS23: 66.6 | BT23: =BS23 -> 66.6 | BU23: 66.8 | BV23: 67.3 | BW23: 67.7 | BX23: 68.2 | BY23: 68.2 | BZ23: 68.6 | CA23: 69.1 | CB23: 69.7 | CC23: 70.8 | CD23: =CC23 -> 70.8 | CE23: 71.9 | CF23: 72.6 | CG23: 74.5 | CH23: 111.9 | CI23: =CH23 -> 111.9 | CJ23: 0 | CK23: 0 | CL23: 0 | CM23: 0 | CN23: =CM23 -> 0 | CO23: 0 | CP23: 0 | CQ23: 0 | CR23: 185.3 | CS23: =CR23 -> 185.3 | CT23: 205.8 | CU23: 277.2 | CV23: 278.7 | CW23: 273.5 | CX23: =CW23 -> 273.5 | CY23: 555.5 | CZ23: 547 | DA23: 525.8 | DB23: 520.4 | DC23: =DB23 -> 520.4 | DD23: 509.1 | DE23: 515.2 | DF23: 526.7 | DG23: 516.3 | DH23: =DG23 -> 516.3 | DI23: 470.6 | DJ23: 467.7 | DK23: 454.8 | DL23: 441.4 | DM23: =DL23 -> 441.4 | DN23: =DM23 -> 441.4 | DO23: =DN23 -> 441.4 | DP23: =DO23 -> 441.4 | DQ23: =DP23 -> 441.4 | DR23: =DQ23 -> 441.4 | DS23: =DR23 -> 441.4 | DT23: =DS23 -> 441.4 | ... EB23: =EA23 -> 441.4
A24: Goodwill | Q24: 0 | U24: 0 | V24: =U24 -> 0 | W24: 0 | X24: 13.663 | Y24: 13.56 | Z24: 14.191 | AA24: =Z24 -> 14.191 | AB24: 19.384 | AC24: 18.686 | AD24: 20.528 | AE24: 21.311 | AF24: =AE24 -> 21.311 | AG24: 23.078 | AH24: 22.585 | AI24: 22.036 | AJ24: 21.845 | AK24: =AJ24 -> 21.845 | AL24: 21.038 | AM24: 20.967 | AN24: 20.536 | AO24: 19.902 | AP24: =AO24 -> 19.902 | AQ24: 30.33 | AR24: 30.706 | AS24: 31.202 | AT24: 63.344 | AU24: =AT24 -> 63.344 | AV24: 63.374 | AW24: 63.376 | AX24: 63.311 | AY24: 68.95 | AZ24: 68.95 | BA24: 72.462 | BB24: 71.662 | BC24: 72.543 | BD24: 92.474 | BE24: 92.474 | BF24: 92.342 | BG24: 172.337 | BH24: 166.047 | BI24: 161.478 | BJ24: 161.478 | BK24: 207.906 | BL24: 208.485 | BM24: 215.219 | BN24: 215.625 | BO24: =BN24 -> 215.625 | BP24: 216.1 | BQ24: 223.4 | BR24: 234.8 | BS24: 266.5 | BT24: =BS24 -> 266.5 | BU24: 261.9 | BV24: 261.1 | BW24: 257.2 | BX24: 259.1 | BY24: 259.1 | BZ24: 262.5 | CA24: 262.8 | CB24: 260.9 | CC24: 262.4 | CD24: =CC24 -> 262.4 | CE24: 263.8 | CF24: 265.3 | CG24: 265.7 | CH24: 321.6 | CI24: =CH24 -> 321.6 | CJ24: 337.1 | CK24: 340.7 | CL24: 336.7 | CM24: 399.1 | CN24: =CM24 -> 399.1 | CO24: 400.2 | CP24: 863.6 | CQ24: 860.9 | CR24: 862.9 | CS24: =CR24 -> 862.9 | CT24: 862.6 | CU24: 860.8 | CV24: 861.7 | CW24: 856.2 | CX24: =CW24 -> 856.2 | CY24: 1584.9 | CZ24: 1592.2 | DA24: 1560.6 | DB24: 1575.4 | DC24: =DB24 -> 1575.4 | DD24: 1572.3 | DE24: 1625 | DF24: 1705.1 | DG24: 1719.6 | DH24: =DG24 -> 1719.6 | DI24: 1599 | DJ24: 1635.8 | DK24: 1549.1 | DL24: 1539.2 | DM24: =DL24 -> 1539.2 | DN24: =DM24 -> 1539.2 | DO24: =DN24 -> 1539.2 | DP24: =DO24 -> 1539.2 | DQ24: =DP24 -> 1539.2 | DR24: =DQ24 -> 1539.2 | DS24: =DR24 -> 1539.2 | DT24: =DS24 -> 1539.2 | ... EB24: =EA24 -> 1539.2
AU25: =AT25 -> 0 | BO25: =BN25 -> 0 | BT25: =BS25 -> 0 | CD25: =CC25 -> 0
A26: TOTAL ASSETS | B26: 231.421 | C26: 0 | D26: 0 | E26: 0 | F26: 0 | G26: 468.1 | H26: 0 | I26: 0 | J26: 0 | K26: 0 | L26: 726.7 | M26: 0 | N26: 0 | O26: 0 | P26: 0 | Q26: =Q16+Q19+Q20+Q22+Q24 -> 852.161 | R26: 0 | S26: 0 | T26: 0 | U26: =U16+U19+U20+U22+U24 -> 992.743 | V26: =U26 -> 992.743 | W26: =W16+W19+W20+W22+W24 -> 1056.453 | X26: =X16+X19+X20+X22+X24 -> 1094.339 | Y26: =Y16+Y19+Y20+Y22+Y24 -> 1168.506 | Z26: =Z16+Z19+Z20+Z22+Z24 -> 1252.514 | AA26: =Z26 -> 1252.514 | AB26: =AB16+AB19+AB20+AB22+AB24 -> 1324.557 | AC26: =AC16+AC19+AC20+AC22+AC24 -> 1383.951 | AD26: =AD16+AD19+AD20+AD22+AD24 -> 1455.03 | AE26: =AE16+AE19+AE20+AE22+AE24 -> 1493.131 | AF26: =AE26 -> 1493.131 | AG26: =AG16+AG19+AG20+AG22+AG24 -> 1601.848 | AH26: =AH16+AH19+AH20+AH22+AH24 -> 1668.269 | AI26: =AI16+AI19+AI20+AI22+AI24 -> 1782.842 | AJ26: =AJ16+AJ19+AJ20+AJ22+AJ24 -> 1851.039 | AK26: =AJ26 -> 1851.039 | AL26: =AL16+AL19+AL20+AL22+AL24 -> 1964.446 | AM26: =AM16+AM19+AM20+AM22+AM24 -> 2019.602 | AN26: =AN16+AN19+AN20+AN22+AN24 -> 2215.754 | AO26: =AO16+AO19+AO20+AO22+AO24+AO23 -> 2214.783 | AP26: =AO26 -> 2214.783 | AQ26: =AQ16+AQ19+AQ20+AQ22+AQ24+AQ23+AQ21 -> 2353.952 | AR26: =AR16+AR19+AR20+AR22+AR24+AR23+AR21 -> 2420.927 | AS26: =AS16+AS19+AS20+AS22+AS24+AS23+AS21 -> 2604.125 | AT26: =AT16+AT19+AT20+AT22+AT24+AT23+AT21+AT18 -> 2729.746 | AU26: =AT26 -> 2729.746 | AV26: =AV16+AV19+AV20+AV22+AV24+AV23+AV21+AV18 -> 3073.107 | AW26: =AW16+AW19+AW20+AW22+AW24+AW23+AW21+AW18 -> 3095.655 | AX26: =AX16+AX19+AX20+AX22+AX24+AX23+AX21+AX18 -> 3224.292 | AY26: =AY16+AY19+AY20+AY22+AY24+AY23+AY21+AY18 -> 3386.978 | AZ26: =AZ16+AZ19+AZ20+AZ22+AZ24+AZ23+AZ21+AZ18 -> 3386.541 | BA26: =BA16+BA19+BA20+BA22+BA24+BA23+BA21+BA18 -> 3819.834 | BB26: =BB16+BB19+BB20+BB22+BB24+BB23+BB21+BB18 -> 3603.417 | BC26: =BC16+BC19+BC20+BC22+BC24+BC23+BC21+BC18 -> 3327.981 | ... BJ26: =BJ16+BJ19+BJ20+BJ22+BJ24+BJ23+BJ21+BJ18 -> 4428.941 | BK26: =BK16+BK19+BK20+BK22+BK24+BK23+BK18 -> 4527.634 | BL26: =BL16+BL19+BL20+BL22+BL24+BL23+BL18 -> 4636.875 | BM26: =BM16+BM19+BM20+BM22+BM24+BM23+BM18 -> 4903.923 | BN26: =BN16+BN19+BN20+BN22+BN24+BN23+BN18 -> 5343.878 | BO26: =BN26 -> 5343.878 | BP26: =BP16+BP19+BP20+BP22+BP24+BP23+BP18 -> 5506.4 | BQ26: =BQ16+BQ19+BQ20+BQ22+BQ24+BQ23+BQ18 -> 5534.1 | BR26: =BR16+BR19+BR20+BR22+BR24+BR23+BR18 -> 5552.3 | BS26: =BS16+BS19+BS20+BS22+BS24+BS23+BS18 -> 5672.6 | BT26: =BS26 -> 5672.6 | BU26: =BU16+BU19+BU20+BU22+BU24+BU23+BU18 -> 5530.4 | BV26: =BV16+BV19+BV20+BV22+BV24+BV23+BV18 -> 5281.3 | BW26: =BW16+BW19+BW20+BW22+BW24+BW23+BW18 -> 5333.1 | BX26: =BX16+BX19+BX20+BX22+BX24+BX23+BX18 -> 5576.8 | BY26: =BY16+BY19+BY20+BY22+BY24+BY23+BY21+BY18 -> 5576.8 | BZ26: =BZ16+BZ19+BZ20+BZ22+BZ24+BZ23+BZ18 -> 6101.6 | CA26: =CA16+CA19+CA20+CA22+CA24+CA23+CA18 -> 6144.7 | CB26: =CB16+CB19+CB20+CB22+CB24+CB23+CB18 -> 6206.9 | CC26: =CC16+CC19+CC20+CC22+CC24+CC23+CC18 -> 6385.9 | CD26: =CC26 -> 6385.9 | CE26: =CE16+CE19+CE20+CE22+CE24+CE23+CE18 -> 6931.1 | CF26: =CF16+CF19+CF20+CF22+CF24+CF23+CF18 -> 7027.6 | CG26: =CG16+CG19+CG20+CG22+CG24+CG23+CG18 -> 7097.8 | CH26: =CH16+CH19+CH20+CH22+CH24+CH23+CH18 -> 7360.4 | CI26: =CH26 -> 7360.4 | CJ26: =CJ16+CJ19+CJ20+CJ22+CJ24+CJ23+CJ18 -> 7835.6 | CK26: =CK16+CK19+CK20+CK22+CK24+CK23+CK18 -> 8006.5 | CL26: =CL16+CL19+CL20+CL22+CL24+CL23+CL18 -> 8308.9 | CM26: =CM16+CM19+CM20+CM22+CM24+CM23+CM18 -> 8219.2 | CN26: =CM26 -> 8219.2 | CO26: =CO16+CO19+CO20+CO22+CO24+CO23+CO18 -> 8490.1 | CP26: =CP16+CP19+CP20+CP22+CP24+CP23+CP18 -> 8502.8 | CQ26: =CQ16+CQ19+CQ20+CQ22+CQ24+CQ23+CQ18 -> 9062.3 | CR26: =CR16+SUM(CR18:CR24) -> 11516.7 | CS26: =CR26 -> 11516.7 | CT26: =CT16+SUM(CT18:CT24) -> 10255.2 | CU26: =CU16+SUM(CU18:CU24) -> 10097 | CV26: =CV16+SUM(CV18:CV24) -> 10385.3 | CW26: =CW16+SUM(CW18:CW24) -> 10752.9 | CX26: =CX16+SUM(CX18:CX24) -> 10752.9 | CY26: =CY16+SUM(CY18:CY24) -> 12351.1 | CZ26: =CZ16+SUM(CZ18:CZ24) -> 12190.7 | DA26: =DA16+SUM(DA18:DA24) -> 12868.8 | ... EB26: =EB16+SUM(EB18:EB24) -> 18014.009
A28: LIABILITIES AND STOCKHOLDER'S EQUITY
A29: Current Liabilities
A30: Accounts Payable | Q30: 46.3 | U30: 54.446 | V30: =U30 -> 54.446 | W30: 53 | X30: 54.47 | Y30: 65.79 | Z30: 56.108 | AA30: =Z30 -> 56.108 | AB30: 63.803 | AC30: 65.13 | AD30: 75.225 | AE30: 73.653 | AF30: =AE30 -> 73.653 | AG30: 84.281 | AH30: 86.233 | AI30: 95.272 | AJ30: 127.905 | AK30: =AJ30 -> 127.905 | AL30: 84.525 | AM30: 99.6 | AN30: 121.993 | AO30: 135.994 | AP30: =AO30 -> 135.994 | AQ30: 124.616 | AR30: 144.831 | AS30: 180.499 | AT30: 168.984 | AU30: =AT30 -> 168.984 | AV30: 144.748 | AW30: 157.873 | AX30: 142.149 | AY30: 199.346 | AZ30: =AY30 -> 199.346 | BA30: 161.236 | BB30: 181.754 | BC30: 185.084 | BD30: 220.975 | BE30: 220.975 | BF30: 208.591 | BG30: 230.06 | BH30: 255.158 | BI30: 340.937 | BJ30: 340.937 | BK30: 275.691 | BL30: 279.96 | BM30: 314.583 | BN30: 390.836 | BO30: =BN30 -> 390.836 | BP30: 340.8 | BQ30: 313.4 | BR30: 329.4 | BS30: 324.9 | BT30: =BS30 -> 324.9 | BU30: 268.6 | BV30: 266.5 | BW30: 258.9 | BX30: =BY30 -> 267.1 | BY30: 267.1 | BZ30: 241.9 | CA30: 286.8 | CB30: 288.2 | CC30: 282.6 | CD30: =CC30 -> 282.6 | CE30: 296.8 | CF30: 330.2 | CG30: 339.9 | CH30: 540 | CI30: =CH30 -> 540 | CJ30: 365.9 | CK30: 388.3 | CL30: 402.2 | CM30: 398.1 | CN30: =CM30 -> 398.1 | CO30: 380.8 | CP30: 355.7 | CQ30: 415.2 | CR30: 491.7 | CS30: =CR30 -> 491.7 | CT30: 444.2 | CU30: 472.6 | CV30: 474.5 | CW30: 533.7 | CX30: =CW30 -> 533.7 | CY30: 547.7 | CZ30: 601.3 | DA30: 603.2 | DB30: 684.2 | DC30: =DB30 -> 684.2 | DD30: 648 | DE30: 662.7 | DF30: 675.7 | DG30: 730.6 | DH30: =DG30 -> 730.6 | DI30: 662.5 | DJ30: 686.9 | DK30: 702.2 | DL30: 782.5 | DM30: =DL30 -> 782.5 | DN30: =DN81*DN87/365 -> 722.51471 | DO30: =DO81*DO87/365 -> 787.34737 | DP30: =DP81*DP87/365 -> 799.82592 | DQ30: =DQ81*DQ87/365 -> 845.15449 | DR30: =DQ30 -> 845.15449 | DS30: =DS81*DS87/365 -> 793.02796 | DT30: =DT81*DT87/365 -> 850.05958 | DU30: =DU81*DU87/365 -> 865.42095 | DV30: =DV81*DV87/365 -> 915.93702 | DW30: =DV30 -> 915.93702 | DX30: =DX81*DX87/365 -> 860.66627 | DY30: =DY81*DY87/365 -> 923.29068 | DZ30: =DZ81*DZ87/365 -> 939.25835 | EA30: =EA81*EA87/365 -> 993.34513 | EB30: =EA30 -> 993.34513
A31: Checks drawn in excess | Q31: 28.582 | U31: 33.634 | V31: =U31 -> 33.634 | W31: 36.84 | X31: 34.388 | Y31: 39.364 | Z31: 63.811 | AA31: =Z31 -> 63.811 | AB31: 47.122 | AC31: 50.463 | AD31: 52.481 | AE31: 56.332 | AF31: =AE31 -> 56.332 | AG31: 58.301 | AH31: 52.637 | AI31: 65.992 | AJ31: 61.987 | AK31: =AJ31 -> 61.987 | AL31: 58.242 | AM31: 48.85 | AN31: 58.964 | AO31: 0 | AP31: =AO31 -> 0 | AQ31: 0 | AR31: 0 | AS31: 0 | AT31: 0 | AU31: =AT31 -> 0 | AV31: 0 | AW31: 0 | AX31: 0 | AY31: 0 | AZ31: =AY31 -> 0 | BB31: 0 | BC31: 0 | BD31: 0 | BE31: 0 | BF31: =BE31 -> 0 | BG31: =BF31 -> 0 | BH31: =BG31 -> 0 | BI31: =BH31 -> 0 | BJ31: =BI31 -> 0 | BK31: 0 | BL31: =BK31 -> 0 | BM31: =BL31 -> 0 | BN31: =BM31 -> 0 | BO31: =BN31 -> 0 | BP31: 0 | BQ31: 0 | BR31: 0 | BS31: 0 | BT31: =BS31 -> 0 | BU31: 0 | BV31: 0 | BW31: 0 | BX31: =BY31 -> 0 | BY31: 0 | BZ31: 0 | CA31: 0 | CB31: 0 | CC31: 0 | CD31: =CC31 -> 0 | CE31: 0 | CF31: 0 | CG31: 0 | CH31: 0 | CI31: =CH31 -> 0 | CJ31: 0 | CK31: 0 | CL31: 0 | CM31: 0 | CN31: =CM31 -> 0 | CO31: 0 | CP31: 0 | CQ31: 0 | CR31: =CQ31 -> 0 | CS31: =CR31 -> 0 | CT31: 0 | CU31: 0 | CV31: 0 | CW31: =CV31 -> 0 | CX31: =CW31 -> 0 | CY31: =CX31 -> 0 | CZ31: =CY31 -> 0 | DA31: =CZ31 -> 0 | DB31: =DA31 -> 0 | DC31: =DB31 -> 0 | DD31: =DC31 -> 0 | DE31: 0 | DF31: 0 | DG31: 0 | DH31: =DG31 -> 0 | DI31: 0 | DJ31: 0 | DK31: 0 | DL31: =DK31 -> 0 | DM31: =DL31 -> 0 | DN31: =DM31 -> 0 | DO31: =DN31 -> 0 | DP31: =DO31 -> 0 | DQ31: =DP31 -> 0 | DR31: =DQ31 -> 0 | DS31: =DR31 -> 0 | ... EB31: =EA31 -> 0
A32: Accrued compensation and related costs | Q32: 25.894 | U32: 35.941 | V32: =U32 -> 35.941 | W32: 36.177 | X32: 41.177 | Y32: 45.573 | Z32: 43.872 | AA32: =Z32 -> 43.872 | AB32: 51.193 | AC32: 62.185 | AD32: 71.295 | AE32: 75.25 | AF32: =AE32 -> 75.25 | AG32: 82.036 | AH32: 83.348 | AI32: 89.34 | AJ32: 81.458 | AK32: =AJ32 -> 81.458 | AL32: 85.886 | AM32: 91.408 | AN32: 107.594 | AO32: 105.899 | AP32: =AO32 -> 105.899 | AQ32: 109.556 | AR32: 117.601 | AS32: 136.094 | AT32: 152.608 | AU32: =AT32 -> 152.608 | AV32: 154.962 | AW32: 185.658 | AX32: 198.504 | AY32: 208.927 | AZ32: =AY32 -> 208.927 | BA32: 197.808 | BB32: 204.324 | BC32: 216.39 | BD32: 232.354 | BE32: 232.354 | BF32: 229.063 | BG32: 283.342 | BH32: 293.186 | BI32: 288.963 | BJ32: 288.963 | BK32: 289.005 | BL32: 301.05 | BM32: 324.915 | BN32: 332.331 | BO32: =BN32 -> 332.331 | BP32: 341.9 | BQ32: 329.2 | BR32: 325.3 | BS32: 253.6 | BT32: =BS32 -> 253.6 | BU32: 251.5 | BV32: 236.6 | BW32: 255.2 | BX32: =BY32 -> 307.5 | BY32: 307.5 | BZ32: 290.5 | CA32: 308.3 | CB32: 344.3 | CC32: 400 | CD32: =CC32 -> 400 | CE32: 306.6 | CF32: 328.2 | CG32: 351.9 | CH32: 364.4 | CI32: =CH32 -> 364.4 | CJ32: 0 | CK32: 0 | CL32: 0 | CM32: 0 | CN32: =CM32 -> 0 | CO32: 0 | CP32: 0 | CQ32: 0 | CR32: =CQ32 -> 0 | CS32: =CR32 -> 0 | CT32: 0 | CU32: 0 | CV32: 0 | CW32: =CV32 -> 0 | CX32: =CW32 -> 0 | CY32: =CX32 -> 0 | CZ32: =CY32 -> 0 | DA32: =CZ32 -> 0 | DB32: =DA32 -> 0 | DC32: =DB32 -> 0 | DD32: =DC32 -> 0 | DE32: 0 | DF32: 0 | DG32: 0 | DH32: =DG32 -> 0 | DI32: 0 | DJ32: 0 | DK32: 0 | DL32: =DK32 -> 0 | DM32: =DL32 -> 0 | DN32: =DM32 -> 0 | DO32: =DN32 -> 0 | DP32: =DO32 -> 0 | DQ32: =DP32 -> 0 | DR32: =DQ32 -> 0 | DS32: =DR32 -> 0 | ... EB32: =EA32 -> 0
A33: Accrued occupancy costs | Q33: 12.184 | U33: 17.526 | V33: =U33 -> 17.526 | W33: 19.356 | X33: 19.868 | Y33: 21.399 | Z33: 23.017 | AA33: =Z33 -> 23.017 | AB33: 25.608 | AC33: 26.005 | AD33: 27.47 | AE33: 29.117 | AF33: =AE33 -> 29.117 | AG33: 31.012 | AH33: 32.641 | AI33: 34.239 | AJ33: 35.835 | AK33: =AJ33 -> 35.835 | AL33: 36.966 | AM33: 42.037 | AN33: 42.525 | AO33: 51.195 | AP33: =AO33 -> 51.195 | AQ33: 45.583 | AR33: 46.064 | AS33: 53.943 | AT33: 56.179 | AU33: =AT33 -> 56.179 | AV33: 58.377 | AW33: 59.259 | AX33: 65.558 | AY33: 29.231 | AZ33: =AY33 -> 29.231 | BA33: 32.866 | BB33: 44.138 | BC33: 41.657 | BD33: 44.496 | BE33: 44.496 | BF33: 49.049 | BG33: 49.35 | BH33: 51.797 | BI33: 54.868 | BJ33: 54.868 | BK33: 68.033 | BL33: 68.006 | BM33: 75.916 | BN33: 74.591 | BO33: =BN33 -> 74.591 | BP33: 78.1 | BQ33: 82.4 | BR33: 88.4 | BS33: 136.1 | BT33: =BS33 -> 136.1 | BU33: 124.9 | BV33: 135.9 | BW33: 164.5 | BX33: =BY33 -> 188.1 | BY33: 188.1 | BZ33: 182 | CA33: 164.4 | CB33: 175.1 | CC33: 173.2 | CD33: =CC33 -> 173.2 | CE33: 163.7 | CF33: 153.3 | CG33: 150.5 | CH33: 148.3 | CI33: =CH33 -> 148.3 | CJ33: 0 | CK33: 0 | CL33: 0 | CM33: 0 | CN33: =CM33 -> 0 | CO33: 0 | CP33: 0 | CQ33: 0 | CR33: =CQ33 -> 0 | CS33: =CR33 -> 0 | CT33: 0 | CU33: 0 | CV33: 0 | CW33: =CV33 -> 0 | CX33: =CW33 -> 0 | CY33: =CX33 -> 0 | CZ33: =CY33 -> 0 | DA33: =CZ33 -> 0 | DB33: =DA33 -> 0 | DC33: =DB33 -> 0 | DD33: =DC33 -> 0 | DE33: 0 | DF33: 0 | DG33: 0 | DH33: =DG33 -> 0 | DI33: 0 | DJ33: 0 | DK33: 0 | DL33: =DK33 -> 0 | DM33: =DL33 -> 0 | DN33: =DM33 -> 0 | DO33: =DN33 -> 0 | DP33: =DO33 -> 0 | DQ33: =DP33 -> 0 | DR33: =DQ33 -> 0 | DS33: =DR33 -> 0 | ... EB33: =EA33 -> 0
A34: Accrued taxes | Q34: 0 | U34: 0 | V34: =U34 -> 0 | W34: 0 | X34: 0 | Y34: 24.579 | Z34: 30.752 | AA34: =Z34 -> 30.752 | AB34: 40.366 | AC34: 18.838 | AD34: 21.846 | AE34: 35.841 | AF34: =AE34 -> 35.841 | AG34: 46.738 | AH34: 28.186 | AI34: 47.518 | AJ34: 70.346 | AK34: =AJ34 -> 70.346 | AL34: 71.917 | AM34: 30.679 | AN34: 19.104 | AO34: 54.244 | AP34: =AO34 -> 54.244 | AQ34: 79.249 | AR34: 29.195 | AS34: 48.212 | AT34: 54.934 | AU34: =AT34 -> 54.934 | AV34: 113.891 | AW34: 49.663 | AX34: 49.99 | AY34: 62.959 | AZ34: =AY34 -> 62.959 | BA34: 87.857 | BB34: 76.124 | BC34: 96.514 | BD34: 78.293 | BE34: 78.293 | BF34: 181.585 | BG34: 100.108 | BH34: 70.543 | BI34: 94.01 | BJ34: 94.01 | BK34: 173.949 | BL34: 77.91 | BM34: 84.233 | BN34: 92.516 | BO34: =BN34 -> 92.516 | BP34: 187.6 | BQ34: 8.9 | BR34: 48.9 | BS34: 76.1 | BT34: =BS34 -> 76.1 | BU34: 112.3 | BV34: 101.6 | BW34: 131.9 | BX34: =BY34 -> 127.8 | BY34: 127.8 | BZ34: 188.8 | CA34: 66.1 | CB34: 69.1 | CC34: 100.2 | CD34: =CC34 -> 100.2 | CE34: 115.8 | CF34: 63.9 | CG34: 82.1 | CH34: 109.2 | CI34: =CH34 -> 109.2 | CJ34: 0 | CK34: 0 | CL34: 0 | CM34: 0 | CN34: =CM34 -> 0 | CO34: 0 | CP34: 0 | CQ34: 0 | CR34: =CQ34 -> 0 | CS34: =CR34 -> 0 | CT34: 0 | CU34: 0 | CV34: 0 | CW34: =CV34 -> 0 | CX34: =CW34 -> 0 | CY34: =CX34 -> 0 | CZ34: =CY34 -> 0 | DA34: =CZ34 -> 0 | DB34: =DA34 -> 0 | DC34: =DB34 -> 0 | DD34: =DC34 -> 0 | DE34: 0 | DF34: 0 | DG34: 0 | DH34: =DG34 -> 0 | DI34: 0 | DJ34: 0 | DK34: 0 | DL34: =DK34 -> 0 | DM34: =DL34 -> 0 | DN34: =DM34 -> 0 | DO34: =DN34 -> 0 | DP34: =DO34 -> 0 | DQ34: =DP34 -> 0 | DR34: =DQ34 -> 0 | DS34: =DR34 -> 0 | ... EB34: =EA34 -> 0
A35: Commercial paper and ST borrowings | AF35: =AE35 | AU35: =AT35 | AZ35: =AY35 | BD35: 277 | BE35: 277 | BF35: 105 | BG35: 95 | BH35: 200 | BI35: 700 | BJ35: 700 | BK35: 365 | BL35: 847 | BM35: 879.972 | BN35: 710.248 | BO35: =BN35 -> 710.248 | BP35: 529.5 | BQ35: 701.8 | BR35: 615.9 | BS35: 713 | BT35: =BS35 -> 713 | BU35: 290.2 | BV35: 226 | BW35: 0 | BX35: =BY35 -> 0 | BY35: 0 | BZ35: 0 | CA35: 0 | CB35: 0 | CC35: 0 | CD35: =CC35 -> 0 | CE35: 0 | CF35: 0 | CG35: 0 | CH35: 0 | CI35: =CH35 -> 0 | CJ35: 0 | CK35: 0 | CL35: 0 | CM35: 0 | CN35: =CM35 -> 0 | CO35: 0 | CP35: 0 | CQ35: 0 | CR35: =CQ35+CF!CR56+CF!CR57+CF!CR59+CF!CR62 -> 0 | CS35: =CR35 -> 0 | CT35: 0 | CU35: 0 | CV35: 0 | CW35: =CV35+CF!CW56+CF!CW57+CF!CW59+CF!CW62 -> 0 | CX35: =CW35 -> 0 | CY35: =CX35+CF!CY56+CF!CY57+CF!CY59+CF!CY62 -> 0 | CZ35: =CY35+CF!CZ56+CF!CZ57+CF!CZ59+CF!CZ62 -> 0 | DA35: =CZ35+CF!DA56+CF!DA57+CF!DA59+CF!DA62 -> 0 | DB35: =DA35+CF!DB56+CF!DB57+CF!DB59+CF!DB62 -> 0 | DC35: =DB35 -> 0 | DD35: 0 | DE35: 0 | DF35: 0 | DG35: 0 | DH35: =DG35 -> 0 | DI35: 0 | DJ35: 25 | DK35: 0 | DL35: =DK35+CF!DL56+CF!DL57+CF!DL59+CF!DL62 -> 0 | DM35: =DL35 -> 0 | DN35: =DM35+CF!DN56+CF!DN57+CF!DN59+CF!DN62 -> 0 | DO35: =DN35+CF!DO56+CF!DO57+CF!DO59+CF!DO62 -> 0 | DP35: =DO35+CF!DP56+CF!DP57+CF!DP59+CF!DP62 -> 0 | DQ35: =DP35+CF!DQ56+CF!DQ57+CF!DQ59+CF!DQ62 -> 0 | DR35: =DQ35 -> 0 | DS35: =DR35+CF!DS56+CF!DS57+CF!DS59+CF!DS62 -> 0 | DT35: =DS35+CF!DT56+CF!DT57+CF!DT59+CF!DT62 -> 0 | DU35: =DT35+CF!DU56+CF!DU57+CF!DU59+CF!DU62 -> 0 | DV35: =DU35+CF!DV56+CF!DV57+CF!DV59+CF!DV62 -> 0 | DW35: =DV35 -> 0 | DX35: =DW35+CF!DX56+CF!DX57+CF!DX59+CF!DX62 -> 0 | DY35: =DX35+CF!DY56+CF!DY57+CF!DY59+CF!DY62 -> 0 | DZ35: =DY35+CF!DZ56+CF!DZ57+CF!DZ59+CF!DZ62 -> 0 | EA35: =DZ35+CF!EA56+CF!EA57+CF!EA59+CF!EA62 -> 0 | EB35: =EA35 -> 0
A36: Other accrued expenses | Q36: 30.829 | U36: 37.928 | V36: =U36 -> 37.928 | W36: 50.873 | X36: 33.492 | Y36: 27.689 | Z36: 33.153 | AA36: =Z36 -> 33.153 | AB36: 31.103 | AC36: 50.552 | AD36: 40.34 | AE36: 35.053 | AF36: =AE36 -> 35.053 | AG36: 34.692 | AH36: 54.371 | AI36: 47.022 | AJ36: 40.117 | AK36: =AJ36 -> 40.117 | AL36: 51.49 | AM36: 59.298 | AN36: 65.609 | AO36: 72.289 | AP36: =AO36 -> 72.289 | AQ36: 79.863 | AR36: 87.585 | AS36: 104.403 | AT36: 101.8 | AU36: =AT36 -> 101.8 | AV36: 167.239 | AW36: 135.775 | AX36: 137.68 | AY36: 123.684 | AZ36: =AY36 -> 123.684 | BA36: 143.548 | BB36: 156.965 | BC36: 167.929 | BD36: 198.082 | BE36: 198.082 | BF36: 187.38 | BG36: 194.58 | BH36: 215.81 | BI36: 224.154 | BJ36: 224.154 | BK36: 209.146 | BL36: 244.558 | BM36: 233.313 | BN36: 257.369 | BO36: =BN36 -> 257.369 | BP36: 261.8 | BQ36: 266.7 | BR36: 279.8 | BS36: 164.4 | BT36: =BS36 -> 164.4 | BU36: 161.3 | BV36: 139.1 | BW36: 174.3 | BX36: =BY36 -> 147.3 | BY36: 147.3 | BZ36: 149.6 | CA36: 234.6 | CB36: 270.1 | CC36: 262.8 | CD36: =CC36 -> 262.8 | CE36: 151.3 | CF36: 286.1 | CG36: 298.7 | CH36: 319 | CI36: =CH36 -> 319 | CJ36: 0 | CK36: 0 | CL36: 0 | CM36: 0 | CN36: =CM36 -> 0 | CO36: 0 | CP36: 0 | CQ36: 0 | CR36: =CQ36 -> 0 | CS36: =CR36 -> 0 | CT36: 0 | CU36: 0 | CV36: 0 | CW36: =CV36 -> 0 | CX36: =CW36 -> 0 | CY36: =CX36 -> 0 | CZ36: =CY36 -> 0 | DA36: =CZ36 -> 0 | DB36: =DA36 -> 0 | DC36: =DB36 -> 0 | DD36: =DC36 -> 0 | DE36: 0 | DF36: 0 | DG36: 0 | DH36: =DG36 -> 0 | DI36: 0 | DJ36: 0 | DK36: 0 | DL36: =DK36 -> 0 | DM36: =DL36 -> 0 | DN36: =DM36 -> 0 | DO36: =DN36 -> 0 | DP36: =DO36 -> 0 | DQ36: =DP36 -> 0 | DR36: =DQ36 -> 0 | DS36: =DR36 -> 0 | ... EB36: =EA36 -> 0
A37: Deferred revenue | Q37: 0 | U37: 0 | V37: =U37 -> 0 | W37: 0 | X37: 0 | Y37: 0 | Z37: 0.484 | AA37: =Z37 -> 0.484 | AB37: 0 | AC37: 0 | AD37: 11.28 | AE37: 7.32 | AF37: =AE37 -> 7.32 | AG37: 3.449 | AH37: 1.766 | AI37: 13.547 | AJ37: 26.919 | AK37: =AJ37 -> 26.919 | AL37: 49.342 | AM37: 39.231 | AN37: 44.511 | AO37: 42.264 | AP37: =AO37 -> 42.264 | AQ37: 91.731 | AR37: 67.524 | AS37: 74.648 | AT37: 73.476 | AU37: =AT37 -> 73.476 | AV37: 146.151 | AW37: 105.315 | AX37: 124.374 | AY37: 121.377 | AZ37: =AY37 -> 121.377 | BA37: 222.344 | BB37: 168.61 | BC37: 172.976 | BD37: 175.048 | BE37: 175.048 | BF37: 310.868 | BG37: 233.269 | BH37: 235.528 | BI37: 231.926 | BJ37: 231.926 | BK37: 422.648 | BL37: 300.579 | BM37: 309.714 | BN37: 296.9 | BO37: =BN37 -> 296.9 | BP37: 512.7 | BQ37: 376.3 | BR37: 373.5 | BS37: 368.4 | BT37: =BS37 -> 368.4 | BU37: 598.3 | BV37: 431.4 | BW37: 419.7 | BX37: =BY37 -> 388.7 | BY37: 388.7 | BZ37: 569.9 | CA37: 433.9 | CB37: 434.3 | CC37: 414.1 | CD37: =CC37 -> 414.1 | CE37: 608.2 | CF37: 487 | CG37: 489.9 | CH37: 449.3 | CI37: =CH37 -> 449.3 | CJ37: 673.8 | CK37: 530.9 | CL37: 520.8 | CM37: 510.2 | CN37: =CM37 -> 510.2 | CO37: 785.5 | CP37: 667.9 | CQ37: 682 | CR37: 653.7 | CS37: =CR37 -> 653.7 | CT37: 1013.4 | CU37: 816.3 | CV37: 830.8 | CW37: 794.5 | CX37: =CW37 -> 794.5 | CY37: 1230.9 | CZ37: 1018.5 | DA37: 1024.6 | DB37: 983.8 | DC37: =DB37 -> 983.8 | DD37: 1448.8 | DE37: 1203.5 | DF37: 1216.6 | DG37: 1171.2 | DH37: =DG37 -> 1171.2 | DI37: 1578.3 | DJ37: 1339.7 | DK37: 1342.2 | DL37: 1288.5 | DM37: =DL37 -> 1288.5 | DN37: =DM37+225 -> 1513.5 | DO37: =DN37-200 -> 1313.5 | DP37: =DO37 -> 1313.5 | DQ37: =DP37 -> 1313.5 | DR37: =DQ37 -> 1313.5 | DS37: =DR37+225 -> 1538.5 | DT37: =DS37-200 -> 1338.5 | DU37: =DT37 -> 1338.5 | DV37: =DU37 -> 1338.5 | DW37: =DV37 -> 1338.5 | DX37: =DW37+225 -> 1563.5 | DY37: =DX37-200 -> 1363.5 | DZ37: =DY37 -> 1363.5 | EA37: =DZ37 -> 1363.5 | EB37: =EA37 -> 1363.5
A38: Current portion of long-term debt | Q38: 0 | U38: 0 | V38: =U38 -> 0 | W38: 0 | X38: 0 | Y38: 0 | Z38: 0 | AA38: =Z38 -> 0 | AB38: 0 | AC38: 0 | AD38: 0 | AE38: 0.694 | AF38: =AE38 -> 0.694 | AG38: 0.688 | AH38: 0.691 | AI38: 0.694 | AJ38: 0.697 | AK38: =AJ38 -> 0.697 | AL38: 0.7 | AM38: 0.703 | AN38: 0.706 | AO38: 0.71 | AP38: =AO38 -> 0.71 | AQ38: 0.713 | AR38: 0.716 | AS38: 0.719 | AT38: 0.722 | AU38: =AT38 -> 0.722 | AV38: 0.725 | AW38: 0.729 | AX38: 0.732 | AY38: 0.735 | AZ38: =AY38 -> 0.735 | BA38: 0.738 | BB38: 0.742 | BC38: 0.745 | BD38: 0.748 | BE38: 0.748 | BF38: 0.752 | BG38: 0.755 | BH38: 0.758 | BI38: 0.762 | BJ38: 0.762 | BK38: 0.765 | BL38: 0.769 | BM38: 0.772 | BN38: 0.775 | BO38: =BN38 -> 0.775 | BP38: 0.8 | BQ38: 0.7 | BR38: 0.7 | BS38: 0.7 | BT38: =BS38 -> 0.7 | BU38: 0.6 | BV38: 0.5 | BW38: 0.4 | BX38: =BY38 -> 0.2 | BY38: 0.2 | BZ38: 0.2 | CA38: 0 | CB38: 0 | CC38: 0 | CD38: =CC38 -> 0 | CE38: 0 | CF38: =CE38 -> 0 | CG38: 0 | CH38: 0 | CI38: =CH38 -> 0 | CJ38: =CI38 -> 0 | CK38: =CJ38 -> 0 | CL38: 0 | CM38: 0 | CN38: =CM38 -> 0 | CO38: 0 | CP38: 0 | CQ38: =CP38 -> 0 | CR38: =CQ38 -> 0 | CS38: =CR38 -> 0 | CT38: 0 | CU38: 0 | CV38: 0 | CW38: =CV38 -> 0 | CX38: =CW38 -> 0 | CY38: =CX38 -> 0 | CZ38: =CY38 -> 0 | DA38: 549.8 | DB38: 0 | DC38: =DB38 -> 0 | DD38: 399.8 | DE38: 399.8 | DF38: 399.8 | DG38: 400 | DH38: =DG38 -> 400 | DI38: 0 | DJ38: 0 | DK38: 0 | DL38: =DK38 -> 0 | DM38: =DL38 -> 0 | DN38: =DM38 -> 0 | DO38: =DN38 -> 0 | DP38: =DO38 -> 0 | DQ38: =DP38 -> 0 | DR38: =DQ38 -> 0 | DS38: =DR38 -> 0 | ... EB38: =EA38 -> 0
