Workbook
Name AdditionalInstructions: IndexInformation!$B$42
Name Address: ImportantDisclosures!$A$2:$A$2
Name ANA: ModPubIndex!$A$7
Name Authors: ImportantDisclosures!$A$7
Name Authors: IndexInformation!$B$18
Name BRO: ModPubIndex!$A$1
Name BS: [3]BS!$D$44:$GI$44
Name BSMethod: 2
Name Button_1: "TFT_report_data_share_prices_List"
Name cc_ReportCurrency: "NTD"
Name cc_ReportCurrencyUnit: "NT$"
Name cc_ReportCurrencyUnitFactor: 1
Name Conv_mark: 0
Name converting: {"Client Name or Project Name"}
Name CopyrightStamp: ImportantDisclosures!$A$27
Name COU: ModPubIndex!$A$5
Name CQEnd: IndexInformation!$B$31
Name Currency: IndexInformation!$B$24
Name CurrentStockPrice: IndexInformation!$B$23
Name CurrQtrEPS: IndexInformation!$B$29
Name CurrYearEPS: IndexInformation!$B$11
Name CurrYearTotalRevenue: IndexInformation!$B$10
Name CurrYearTotalRevenueActual: IndexInformation!$B$32
Name CUSIP: IndexInformation!$B$20
Name CYEnd: IndexInformation!$B$30
Name dataseries4: OFFSET([4]c1!$G$12,0,0,COUNTA([4]c1!$G$12:$G$31),1)
Name Date: ImportantDisclosures!$A$8
Name Dates: OFFSET('[5]Earnings Exhibits'!$A$3,0,COUNTA('[5]Earnings Exhibits'!$A$3:$IV$3)+2,1,-20)
Name Dates10: OFFSET('[5]Earnings Exhibits'!$A$3,0,COUNTA('[5]Earnings Exhibits'!$A$3:$IV$3)+2,1,-38)
Name DB: "WIREHKPROD"
Name Deleted: IndexInformation!$B$27
Name Description: IndexInformation!$B$7
Name Discipline: IndexInformation!$B$3
Name DISCIPLINE: ModPubIndex!$A$12
Name DisclosuresText: ImportantDisclosures!$A$22
Name Distribution: IndexInformation!$B$26
Name DistTable: ImportantDisclosures!#REF!
Name DistTablePreamble: ImportantDisclosures!#REF!
Name DOCDAT: ModPubIndex!$A$2
Name DOCTIME: ModPubIndex!$A$3
Name DocType: IndexInformation!$B$5
Name DummyEstYears: 3
Name EMAIL_ALERT: ModPubIndex!$A$10
Name EmailAlert: IndexInformation!$B$28
Name EurosFRF: 1
Name EurosITL: 1
Name FINCriteriaType: 1
Name FineUS: {"Client Name or Project Name"}
Name FiveYearGrowthRate: IndexInformation!$B$16
Name FollowingYearEPS: IndexInformation!$B$15
Name FollowingYearTotalRevenue: IndexInformation!$B$14
Name FollowingYearTotalRevenueActual: IndexInformation!$B$34
Name forest: {"Client Name or Project Name"}
Name forest2: {"Client Name or Project Name"}
Name FR_COM_ABBR: "1122.HK"
Name FR_COU_ABBR: "chn"
Name FR_END_DATE: "'31 Dec 2001"
Name FR_START_DATE: "'1 Jan 2001"
Name FR_SYBASE_SERVER: "PTKFBVDF01"
Name FR_TEMPLATE_KEY: "102119|1"

Sheet MW-Cache
A1: $IV$4
A2: STX.N,mstag:incomeLossFromInvestmentsAccountedForUnderTheEquityMethodOperatingIncomeStatement,2008Q4,,FYR,USD | B2: NA | C2: JAVA.O,mscalc:netOperatingAssets,2007Q4,,FYR,USD | D2: 2,984.671 | E2: STX.N,mscalc:operatingExpenses,2008Q1,,FYR,USD | F2: 2,859.87590849649 | G2: STX.N,mscalc:sharePrice,2007Q4,,FYR,USD | H2: 21.77 | I2: STX.N,mstag:tradeReceivables,2007Q1,,FYR,USD | J2: 1,331 | K2: JAVA.O,mscalc:consensusEps,2006Q3,,FYR,USD | L2: (0.0299999993294477) | M2: JAVA.O,mscalc:otheroperatingIncomeExpense,2007Q4,,FYR,USD | N2: NA | O2: STX.N,mscalc:consensusEps,2009Q3,,FYR,USD | P2: 0.685769021511078 | Q2: JAVA.O,mstag:researchAndDevelopment,2008Q2,,FYR,USD | R2: 492.153509172135 | S2: JAVA.O,mscalc:depreciationAndAmortization,2008Q4,,FYR,USD | T2: 212.596639218066 | U2: JAVA.O,mscalc:consensusEps,2008Q4,,FYR,USD | V2: 0.424109995365143 | W2: JAVA.O,mscalc:consensusEps,2006Q4,,FYR,USD | X2: 0.0199999995529652 | Y2: STX.N,mstag:costOfManufacturing,2008Q3,,FYR,USD | Z2: NA | AA2: STX.N,mscalc:taxExpenseFromOperations,2008Q3,,FYR,USD | AB2: 18.0256545986929 | AC2: STX.N,mstag:sellingGeneralAndAdministrativeExpenses,2008Q3,,FYR,USD | AD2: 144.488547365134 | AE2: JAVA.O,mstag:costOfManufacturing,2007Q4 | AF2: NA | AG2: STX.N,mstag:tradeAndOtherPayables,2008Q1,,FYR,USD | AH2: 1,551 | AI2: JAVA.O,mscalc:epsForConsensusForThomsonFeed,2007Q4,,FYR,USD | AJ2: 0.0847642622838515 | AK2: JAVA.O,mscalc:operatingExpenses,2008Q4,,FYR,USD | AL2: 3,677.11700350108 | AM2: JAVA.O,mstag:researchAndDevelopment,2008Q3,,FYR,USD | AN2: 478.661398865851 | AO2: STX.N,mscalc:epsForConsensusForThomsonFeed,2008Q1,,FYR,USD | AP2: 0.677315701983149 | AQ2: JAVA.O,mscalc:otheroperatingIncomeExpense,2008Q2,,FYR,USD | AR2: NA | AS2: JAVA.O,mscalc:netOperatingAssets,2008Q4,,FYR,USD | AT2: 2,154.76695786603 | AU2: JAVA.O,mscalc:netFinancialIncomeExpense,2008Q4,,FYR,USD | AV2: 25.937404376881 | AW2: STX.N,mscalc:consensusEps,2007Q1,,FYR,USD | AX2: 0.159999996423721 | AY2: STX.N,mscalc:otherIncomeExpense,2008Q1,,FYR,USD | AZ2: (4.443306415566) | BA2: JAVA.O,mscalc:sharePrice,2008Q1,,FYR,USD | BB2: 35.05 | BC2: JAVA.O,mscalc:netOperatingAssets,,,FYR,USD | BD2: NA | BE2: JAVA.O,mstag:costOfSalesWithoutDepreciation,2008Q1 | BF2: NA | BG2: STX.N,mstag:costOfSalesWithoutDepreciation,2008Q1 | BH2: NA | BI2: JAVA.O,mstag:costOfManufacturing,2008Q1 | BJ2: NA | BK2: STX.N,mscalc:mwAdjustmentsToEv,2008Q1,,FYR,USD | BL2: NA | BM2: STX.N,mstag:inventories,2008Q4,,FYR,USD | BN2: 861.742561596703 | BO2: JAVA.O,mscalc:consensusEps,2009Q3,,FYR,USD | BP2: 0.287961006164551 | BQ2: WDC.O,mscalc:targetPrice,,,,USD | BR2: 92 | BS2: JAVA.O,mstag:costOfSalesWithoutDepreciation,2008Q1,,FYR,USD | BT2: NA | BU2: STX.N,mscalc:consensusEps,2008Q2,,FYR,USD | BV2: 0.731366991996765 | BW2: STX.N,mstag:inventories,2008Q1,,FYR,USD | BX2: 763 | BY2: STX.N,mstag:employeeExpenses,2008Q1,,FYR,USD | BZ2: NA | CA2: JAVA.O,mstag:incomeLossFromInvestmentsAccountedForUnderTheEquityMethodOperatingIncomeStatement,2008Q4,,FYR,USD | CB2: NA | CC2: STX.N,mscalc:dilutedSharesOutstanding,2008Q2,,FYR | CD2: 562.067222377659 | CE2: JAVA.O,mstag:averageDilutedSharesOutstanding,2008Q4,,FYR | CF2: 3,261.61287817885 | CG2: JAVA.O,mstag:costOfSalesWithDepreciation,2008Q4,,FYR,USD | CH2: 2,184.73281192932 | CI2: JAVA.O,mstag:costOfSalesWithoutDepreciation,2008Q3,,FYR,USD | CJ2: NA | CK2: JAVA.O,mstag:costOfMaterials,2008Q4,,FYR,USD | CL2: NA | CM2: JAVA.O,mstag:inventories,2007Q1,,FYR,USD | CN2: 584 | CO2: STX.N,mscalc:netOperatingAssets,2008Q2,,FYR,USD | CP2: 5,970.77845385973 | CQ2: STX.N,mstag:costOfSalesWithoutDepreciation | CR2: NA | CS2: JAVA.O,mscalc:otheroperatingIncomeExpense,2008Q4,,FYR,USD | CT2: NA | CU2: JAVA.O,mstag:costOfMaterials,2008Q3,,FYR,USD | CV2: NA | CW2: STX.N,mscalc:otherIncomeExpense,2008Q2,,FYR,USD | CX2: 0.000000000000324100 | CY2: JAVA.O,mscalc:operatingRevenue,2008Q1,,FYR,USD | CZ2: 3,218.93093863074 | DA2: JAVA.O,mstag:averageDilutedSharesOutstanding,2008Q1,,FYR | DB2: 3,537 | DC2: JAVA.O,mstag:researchAndDevelopment,2007Q4,,FYR,USD | DD2: 514 | DE2: STX.N,mstag:costOfMaterials,2008Q1 | DF2: NA | DG2: STX.N,mscalc:operatingRevenue,2008Q3,,FYR,USD | DH2: 3,074.22441202413 | DI2: JAVA.O,mstag:costOfServicesSold,2008Q1 | DJ2: NA | DK2: JAVA.O,mscalc:consensusEps,2007Q4,,FYR,USD | DL2: 0.449912011623383 | DM2: STX.N,mscalc:operatingRevenue,2008Q2,,FYR,USD | DN2: 3,421.75749352828 | DO2: STX.N,mscalc:otheroperatingIncomeExpense,2008Q4,,FYR,USD | DP2: NA | DQ2: JAVA.O,mscalc:otherIncomeExpense,2008Q2,,FYR,USD | DR2: 26.9459299001817 | DS2: STX.N,mscalc:taxExpenseFromOperations,2008Q1,,FYR,USD | DT2: 21.2468473434805 | DU2: JAVA.O,mscalc:sharePrice,2007Q4,,FYR,USD | DV2: 5.26 | DW2: STX.N,mstag:inventories,2008Q3,,FYR,USD | DX2: 829.335997496634 | DY2: JAVA.O,mstag:costOfSalesWithoutDepreciation,2008Q3 | DZ2: NA | EA2: JAVA.O,mscalc:consensusEps,2007Q2,,FYR,USD | EB2: 0.159999996423721 | EC2: STX.N,mscalc:consensusEps,2007Q3,,FYR,USD | ED2: 0.469999998807907 | EE2: STX.N,mstag:costOfManufacturing,2008Q2,,FYR,USD | EF2: NA | EG2: JAVA.O,mscalc:epsForConsensusForThomsonFeed,2008Q1,,FYR,USD | EH2: 0.050972548256401 | EI2: JAVA.O,mscalc:netOperatingAssets,2008Q1,,FYR,USD | EJ2: 1,944 | EK2: JAVA.O,mstag:inventories,2008Q1,,FYR,USD | EL2: 571 | EM2: STX.N,mstag:averageDilutedSharesOutstanding,,,FYR | EN2: NA | EO2: JAVA.O,mscalc:taxExpenseFromOperations,2008Q4,,FYR,USD | EP2: 106.666794529249 | EQ2: JAVA.O,mstag:incomeLossFromInvestmentsAccountedForUnderTheEquityMethodOperatingIncomeStatement,2007Q4,,FYR,USD | ER2: NA | ES2: JAVA.O,mscalc:dilutedSharesOutstanding,2007Q4,,FYR | ET2: 3,710.66779184248 | EU2: WDC.N,mscalc:sedolCodeCalc | EV2: 2954699 | EW2: JAVA.O,mscalc:depreciationAndAmortization,2008Q3,,FYR,USD | EX2: 208.875834772559 | EY2: JAVA.O,mscalc:netFinancialIncomeExpense,2008Q2,,FYR,USD | EZ2: 29.0298250428817 | FA2: JAVA.O,mscalc:operatingExpenses,2007Q4,,FYR,USD | FB2: 3,534.06061219646 | FC2: STX.N,mstag:employeeExpenses,,,FYR,USD | FD2: NA | FE2: JAVA.O,mstag:employeeExpenses,,,FYR,USD | FF2: NA | FG2: JAVA.O,mstag:averageDilutedSharesOutstanding,,,FYR | FH2: NA | FI2: STX.N,mscalc:operatingExpenses,2008Q3,,FYR,USD | FJ2: 2,713.71132005027 | FK2: JAVA.O,mstag:costOfSalesWithoutDepreciation,2008Q4 | FL2: NA | FM2: JAVA.O,mstag:costOfManufacturing,2008Q2,,FYR,USD | FN2: NA | FO2: JAVA.O,mstag:researchAndDevelopment,2008Q4,,FYR,USD | FP2: 502.824862389408 | FQ2: STX.N,mstag:costOfManufacturing,2008Q1 | FR2: NA | FS2: STX.N,mscalc:netOperatingAssets,2008Q4,,FYR,USD | FT2: 6,321.46815512331 | FU2: JAVA.O,mstag:costOfSalesWithoutDepreciation,2007Q4 | FV2: NA | FW2: STX.N,mstag:sellingGeneralAndAdministrativeExpenses,2008Q4,,FYR,USD | FX2: 139.367913762653 | FY2: JAVA.O,mstag:costOfMaterials,2008Q1 | FZ2: NA | GA2: STX.N,mscalc:sharePrice,2007Q3,,FYR,USD | GB2: 23.3 | GC2: STX.N,mstag:tradeReceivables,2008Q2,,FYR,USD | GD2: 1,520.78110823479 | GE2: JAVA.O,mstag:tradeReceivables,2007Q1,,FYR,USD | GF2: 2,036 | GG2: JAVA.O,mstag:averageDilutedSharesOutstanding,2007Q4,,FYR | GH2: 3,632 | GI2: JAVA.O,mstag:sellingGeneralAndAdministrativeExpenses,2008Q2,,FYR,USD | GJ2: 927.245741918514 | GK2: STX.N,mstag:averageDilutedSharesOutstanding,2008Q2,,FYR | GL2: 550.722335034556 | GM2: STX.N,mstag:researchAndDevelopment,2008Q4,,FYR,USD | GN2: 226.472859864311 | GO2: JAVA.O,mscalc:operatingRevenue,2008Q3,,FYR,USD | GP2: 3,419.00999189894 | GQ2: STX.N,mstag:tradeAndOtherPayables,2007Q1,,FYR,USD | GR2: 1,448 | GS2: STX.N,mstag:costOfSalesWithoutDepreciation,2008Q4 | GT2: NA | GU2: JAVA.O,mstag:costOfSalesWithDepreciation,2008Q2,,FYR,USD | GV2: 1,916.05042456704 | GW2: JAVA.O,mscalc:operatingRevenue,,,FYR,USD | GX2: NA | GY2: JAVA.O,mstag:costOfManufacturing,2008Q1,,FYR,USD | GZ2: NA | HA2: JAVA.O,mstag:employeeExpenses,2007Q4,,FYR,USD | HB2: NA | HC2: JAVA.O,mscalc:taxExpenseFromOperations,2008Q1,,FYR,USD | HD2: 54.3218088729334 | HE2: STX.N,mscalc:depreciationAndAmortization,2008Q3,,FYR,USD | HF2: 225.17192187029 | HG2: STX.N,mstag:tradeReceivables,2008Q4,,FYR,USD | HH2: 1,516.27128399183 | HI2: STX.N,mscalc:otherIncomeExpense,2008Q3,,FYR,USD | HJ2: (0.000000000000149012) | HK2: JAVA.O,mstag:researchAndDevelopment,2008Q1,,FYR,USD | HL2: 446 | HM2: STX.N,mstag:researchAndDevelopment,2008Q3,,FYR,USD | HN2: 236.715279725858 | HO2: STX.N,mscalc:netFinancialIncomeExpense,2008Q1,,FYR,USD | HP2: (19.95) | HQ2: STX.N,mstag:costOfMaterials,2008Q3,,FYR,USD | HR2: NA | HS2: JAVA.O,mstag:costOfMaterials,2008Q2,,FYR,USD | HT2: NA | HU2: JAVA.O,mstag:employeeExpenses,2008Q2,,FYR,USD | HV2: NA | HW2: JAVA.O,mstag:inventories,2006Q4,,FYR,USD | HX2: 540 | HY2: STX.N,mstag:tradeAndOtherPayables,2008Q2,,FYR,USD | HZ2: 1,567.58235704186 | IA2: STX.N,mscalc:consensusEps,2008Q4,,FYR,USD | IB2: 0.550920009613037 | IC2: STX.N,mstag:costOfMaterials,2008Q2,,FYR,USD | ID2: NA | IE2: STX.N,mscalc:operatingRevenue,2008Q1,,FYR,USD | IF2: 3,284.8128553661 | IG2: JAVA.O,mstag:tradeReceivables,2008Q1,,FYR,USD | IH2: 2,203 | II2: JAVA.O,mscalc:netOperatingAssets,2008Q2,,FYR,USD | IJ2: 2,027.35625225519 | IK2: STX.N,mscalc:consensusEps,2007Q4,,FYR,USD | IL2: 0.4115070104599 | IM2: JAVA.O,mscalc:operatingExpenses,2008Q1,,FYR,USD | IN2: 3,042.98863544785 | IO2: JAVA.O,mstag:tradeAndOtherPayables,2008Q2,,FYR,USD | IP2: 1,368.60744611932 | IQ2: JAVA.O,mscalc:mwAdjustmentsToEv,2007Q4,,FYR,USD | IR2: NA | IS2: JAVA.O,mscalc:depreciationAndAmortization,2007Q4,,FYR,USD | IT2: 203 | IU2: JAVA.O,mscalc:operatingRevenue,2008Q2,,FYR,USD | IV2: 3,566.32977660967
A3: JAVA.O,mscalc:consensusEps,2009Q4,,FYR,USD | B3: 0.48369500041008 | C3: STX.N,mstag:costOfServicesSold,2008Q2,,FYR,USD | D3: NA | E3: STX.N,mstag:averageDilutedSharesOutstanding,2008Q1,,FYR | F3: 560 | G3: STX.N,mscalc:netOperatingAssets,,,FYR,USD | H3: NA | I3: STX.N,mscalc:taxExpenseFromOperations,2008Q4,,FYR,USD | J3: 16.0873992827918 | K3: JAVA.O,mscalc:otherIncomeExpense,2008Q4,,FYR,USD | L3: 47.3959541105269 | M3: JAVA.O,mscalc:operatingRevenue,2007Q4,,FYR,USD | N3: 3,835.14296185225 | O3: JAVA.O,mscalc:mwAdjustmentsToEv,2008Q1,,FYR,USD | P3: NA | Q3: JAVA.O,mscalc:consensusEps,2009Q2,,FYR,USD | R3: 0.369836002588272 | S3: STX.N,mstag:inventories,,,FYR,USD | T3: NA | U3: WDC.O,mscalc:sedolCodeCalc | V3: 2954699 | W3: STX.N,mstag:costOfManufacturing,2008Q4,,FYR,USD | X3: NA | Y3: JAVA.O,mscalc:otheroperatingIncomeExpense,2008Q1,,FYR,USD | Z3: NA | AA3: STX.N,mscalc:netFinancialIncomeExpense,2008Q2,,FYR,USD | AB3: (16.1293323045581) | AC3: STX.N,mscalc:operatingRevenue,,,FYR,USD | AD3: NA | AE3: STX.N,mscalc:consensusEps,2009Q2,,FYR,USD | AF3: 0.774507999420166 | AG3: STX.N,mstag:employeeExpenses,2008Q4,,FYR,USD | AH3: NA | AI3: JAVA.O,mstag:inventories,2008Q3,,FYR,USD | AJ3: 577.674010942396 | AK3: STX.N,mstag:costOfSalesWithDepreciation,2008Q4,,FYR,USD | AL3: 2,215.90944410581 | AM3: STX.N,mscalc:netFinancialIncomeExpense,2008Q3,,FYR,USD | AN3: (14.8950586097725) | AO3: STX.N,mscalc:epsForConsensusForThomsonFeed,2008Q4,,FYR,USD | AP3: 0.541713773410666 | AQ3: JAVA.O,mstag:employeeExpenses,2008Q3,,FYR,USD | AR3: NA | AS3: JAVA.O,mstag:tradeAndOtherPayables,2008Q1,,FYR,USD | AT3: 1,140 | AU3: STX.N,mscalc:sharePrice,2008Q1,,FYR,USD | AV3: 25.58 | AW3: JAVA.O,mscalc:epsForConsensusForThomsonFeed,2008Q3,,FYR,USD | AX3: 0.0532860260859363 | AY3: STX.N,mstag:sellingGeneralAndAdministrativeExpenses,2008Q1,,FYR,USD | AZ3: 153 | BA3: STX.N,mscalc:dilutedSharesOutstanding,2008Q4,,FYR | BB3: 562.067222377659 | BC3: JAVA.O,mscalc:operatingExpenses,2008Q2,,FYR,USD | BD3: 3,335.44967565769 | BE3: STX.N,mscalc:netOperatingAssets,2008Q1,,FYR,USD | BF3: 5,671 | BG3: JAVA.O,mstag:tradeReceivables,2008Q2,,FYR,USD | BH3: 2,468.99753765285 | BI3: JAVA.O,mstag:costOfSalesWithDepreciation,,,FYR,USD | BJ3: NA | BK3: JAVA.O,mstag:tradeReceivables,2007Q4,,FYR,USD | BL3: 2,964 | BM3: JAVA.O,mscalc:consensusEps,2006Q1,,FYR,USD | BN3: (0.0199999995529652) | BO3: STX.N,mscalc:nonMarketCapComponentsOfEv,2008Q1,,FYR,USD | BP3: 791 | BQ3: STX.N,mscalc:sharePrice,2007Q1,,FYR,USD | BR3: 23.09 | BS3: JAVA.O,mscalc:otherIncomeExpense,2007Q4,,FYR,USD | BT3: 71.5292064407504 | BU3: STX.N,mscalc:dilutiveSecurities,2008Q1,,FYR,USD | BV3: NA | BW3: STX.N,mstag:incomeLossFromInvestmentsAccountedForUnderTheEquityMethodOperatingIncomeStatement,2008Q3,,FYR,USD | BX3: NA | BY3: JAVA.O,mstag:costOfSalesWithDepreciation,2007Q4 | BZ3: 2,023.06061219646 | CA3: STX.N,mscalc:operatingExpenses,2008Q2,,FYR,USD | CB3: 2,986.01093777247 | CC3: ,mscalc:closePriceCurrencyCalc | CD3: NA | CE3: JAVA.O,mscalc:sharePrice,2006Q4,,FYR,USD | CF3: 4.15 | CG3: WDC.N,mscalc:targetPrice | CH3: NA | CI3: JAVA.O,mstag:averageDilutedSharesOutstanding,2008Q2,,FYR | CJ3: 3,326.86702900859 | CK3: JAVA.O,mstag:costOfManufacturing,2008Q3,,FYR,USD | CL3: NA | CM3: JAVA.O,mscalc:dilutiveSecurities,2007Q4,,FYR,USD | CN3: NA | CO3: ,mscalc:sedolCodeCalc | CP3: NA | CQ3: JAVA.O,mstag:tradeAndOtherPayables,2008Q4,,FYR,USD | CR3: 1,567.30832160147 | CS3: JAVA.O,mstag:tradeReceivables,2006Q4,,FYR,USD | CT3: 2,702 | CU3: JAVA.O,mscalc:epsForConsensusForThomsonFeed,2008Q2,,FYR,USD | CV3: 0.0647973357132661 | CW3: STX.N,mstag:sellingGeneralAndAdministrativeExpenses,2008Q2,,FYR,USD | CX3: 164.244359689357 | CY3: JAVA.O,mscalc:consensusEps,2008Q3,,FYR,USD | CZ3: 0.172246992588043 | DA3: STX.N,mscalc:otheroperatingIncomeExpense,2008Q1,,FYR,USD | DB3: NA | DC3: STX.N,mstag:tradeReceivables,2008Q1,,FYR,USD | DD3: 1,519 | DE3: JAVA.O,mscalc:nonMarketCapComponentsOfEv,2008Q1,,FYR,USD | DF3: (4,249) | DG3: JAVA.O,mstag:averageDilutedSharesOutstanding,2008Q3,,FYR | DH3: 3,293.88357427538 | DI3: JAVA.O,mstag:incomeLossFromInvestmentsAccountedForUnderTheEquityMethodOperatingIncomeStatement,2008Q1,,FYR,USD | DJ3: NA | DK3: JAVA.O,mstag:inventories,2008Q2,,FYR,USD | DL3: 589.553976789859 | DM3: JAVA.O,mstag:costOfServicesSold,2008Q3,,FYR,USD | DN3: NA | DO3: JAVA.O,mstag:costOfSalesWithDepreciation,2008Q3,,FYR,USD | DP3: 1,852.54079371182 | DQ3: STX.N,mscalc:sharePrice,2007Q2,,FYR,USD | DR3: 26.5 | DS3: STX.N,mscalc:dilutedSharesOutstanding,,,FYR | DT3: NA | DU3: JAVA.O,mscalc:netOperatingAssets,2008Q3,,FYR,USD | DV3: 2,148.23636549668 | DW3: STX.N,mscalc:dilutedSharesOutstanding,2008Q1,,FYR | DX3: 562.067222377659 | DY3: STX.N,mscalc:taxExpenseFromOperations,2008Q2,,FYR,USD | DZ3: 21.7873277877906 | EA3: JAVA.O,mscalc:sharePrice,2006Q2,,FYR,USD | EB3: 4.19 | EC3: WDC.N,mscalc:closePriceCurrencyCalc | ED3: USD | EE3: JAVA.O,mstag:incomeLossFromInvestmentsAccountedForUnderTheEquityMethodOperatingIncomeStatement,2008Q2,,FYR,USD | EF3: NA | EG3: JAVA.O,mscalc:netFinancialIncomeExpense,2007Q4,,FYR,USD | EH3: 38.8245728 | EI3: JAVA.O,mstag:employeeExpenses,2008Q1,,FYR,USD | EJ3: NA | EK3: JAVA.O,mstag:sellingGeneralAndAdministrativeExpenses,2008Q1,,FYR,USD | EL3: 939 | EM3: STX.N,mscalc:epsForConsensusForThomsonFeed,2008Q2,,FYR,USD | EN3: 0.722378357214259 | EO3: STX.N,mscalc:consensusEps,2008Q3,,FYR,USD | EP3: 0.601935982704163 | EQ3: JAVA.O,mscalc:netFinancialIncomeExpense,2008Q3,,FYR,USD | ER3: 26.0099560249537 | ES3: JAVA.O,mscalc:consensusEps,2007Q1,,FYR,USD | ET3: 0 | EU3: JAVA.O,mstag:costOfSalesWithDepreciation | EV3: NA | EW3: JAVA.O,mscalc:operatingExpenses,2008Q3,,FYR,USD | EX3: 3,237.23984043089 | EY3: STX.N,mstag:costOfMaterials,2008Q4,,FYR,USD | EZ3: NA | FA3: STX.N,mscalc:epsForConsensusForThomsonFeed,2008Q3,,FYR,USD | FB3: 0.601951352809964 | FC3: STX.N,mscalc:netOperatingAssets,2008Q3,,FYR,USD | FD3: 6,032.99133899868 | FE3: JAVA.O,mscalc:sharePrice,2007Q2,,FYR,USD | FF3: 5.42 | FG3: STX.N,mstag:costOfSalesWithDepreciation,2008Q2,,FYR,USD | FH3: 2,565.13476606849 | FI3: STX.N,mstag:costOfServicesSold,2008Q4,,FYR,USD | FJ3: NA | FK3: JAVA.O,mstag:tradeAndOtherPayables,2006Q4,,FYR,USD | FL3: 1,446 | FM3: JAVA.O,mscalc:dilutedSharesOutstanding,2008Q3,,FYR | FN3: 3,372.53215958779 | FO3: WDC.O,mscalc:targetPrice | FP3: NA | FQ3: WDC.O,mscalc:closePriceCurrencyCalc | FR3: USD | FS3: STX.N,mstag:researchAndDevelopment,2008Q1,,FYR,USD | FT3: 242 | FU3: STX.N,mscalc:consensusEps,2007Q2,,FYR,USD | FV3: 0.389999985694885 | FW3: ,mscalc:targetPrice,,,,USD | FX3: NA | FY3: JAVA.O,mscalc:netFinancialIncomeExpense,2008Q1,,FYR,USD | FZ3: 40.3329036020583 | GA3: JAVA.O,mscalc:otheroperatingIncomeExpense,2008Q3,,FYR,USD | GB3: NA | GC3: JAVA.O,mscalc:taxExpenseFromOperations,2007Q4,,FYR,USD | GD3: 103.572328281592 | GE3: JAVA.O,mstag:inventories,2007Q4,,FYR,USD | GF3: 524 | GG3: STX.N,mstag:tradeAndOtherPayables,2008Q4,,FYR,USD | GH3: 1,280.30323437225 | GI3: STX.N,mscalc:otherIncomeExpense,2008Q4,,FYR,USD | GJ3: (0.000000000000018626) | GK3: JAVA.O,mscalc:sharePrice,2006Q3,,FYR,USD | GL3: 5.13 | GM3: JAVA.O,mstag:costOfMaterials,2007Q4 | GN3: NA | GO3: JAVA.O,mstag:incomeLossFromInvestmentsAccountedForUnderTheEquityMethodOperatingIncomeStatement,2008Q3,,FYR,USD | GP3: NA | GQ3: STX.N,mscalc:consensusEps,2009Q4,,FYR,USD | GR3: 0.625940978527069 | GS3: JAVA.O,mstag:tradeAndOtherPayables,2007Q1,,FYR,USD | GT3: 1,292 | GU3: JAVA.O,mstag:costOfManufacturing,2008Q4,,FYR,USD | GV3: NA | GW3: JAVA.O,mscalc:otherIncomeExpense,2008Q3,,FYR,USD | GX3: 23.8590031054606 | GY3: JAVA.O,mscalc:dilutiveSecurities,2008Q1,,FYR,USD | GZ3: NA | HA3: JAVA.O,mstag:tradeAndOtherPayables,2008Q3,,FYR,USD | HB3: 1,294.7865762502 | HC3: STX.N,mstag:costOfServicesSold,2008Q1 | HD3: NA | HE3: JAVA.O,mscalc:dilutedSharesOutstanding,2008Q4,,FYR | HF3: 3,372.53215958779 | HG3: JAVA.O,mstag:tradeReceivables,2008Q3,,FYR,USD | HH3: 2,463.15773609923 | HI3: JAVA.O,mscalc:consensusEps,2008Q2,,FYR,USD | HJ3: 0.282489985227585 | HK3: WDC.N,mscalc:targetPrice,,,,USD | HL3: NA | HM3: JAVA.O,mstag:costOfSalesWithoutDepreciation,2008Q2,,FYR,USD | HN3: NA | HO3: STX.N,mscalc:operatingExpenses,2008Q4,,FYR,USD | HP3: 2,581.75021773277 | HQ3: STX.N,mscalc:depreciationAndAmortization,2008Q4,,FYR,USD | HR3: 225.17192187029 | HS3: JAVA.O,mstag:inventories,2008Q4,,FYR,USD | HT3: 546.18320298233 | HU3: JAVA.O,mscalc:consensusEps,2006Q2,,FYR,USD | HV3: (0.0299999993294477) | HW3: STX.N,mstag:employeeExpenses,2008Q3,,FYR,USD | HX3: NA | HY3: STX.N,mstag:costOfSalesWithoutDepreciation,2008Q2,,FYR,USD | HZ3: NA | IA3: JAVA.O,mscalc:consensusEps,2008Q1,,FYR,USD | IB3: 0.239999994635582 | IC3: STX.N,mstag:researchAndDevelopment,2008Q2,,FYR,USD | ID3: 256.631812014621 | IE3: JAVA.O,mscalc:sharePrice,2006Q1,,FYR,USD | IF3: 3.93 | IG3: JAVA.O,mscalc:consensusEps,2007Q3,,FYR,USD | IH3: 0.119999997317791 | II3: JAVA.O,mstag:tradeAndOtherPayables,2007Q4,,FYR,USD | IJ3: 1,428 | IK3: JAVA.O,mscalc:epsForConsensusForThomsonFeed,2008Q4,,FYR,USD | IL3: 0.0957037120072411 | IM3: STX.N,mscalc:consensusEps,2008Q1,,FYR,USD | IN3: 0.689000010490417 | IO3: STX.N,mstag:employeeExpenses,2008Q2,,FYR,USD | IP3: NA | IQ3: JAVA.O,mscalc:sharePrice,2007Q3,,FYR,USD | IR3: 6.01 | IS3: STX.N,mscalc:depreciationAndAmortization,2008Q2,,FYR,USD | IT3: 225.17192187029 | IU3: STX.N,mstag:costOfSalesWithDepreciation,2008Q3,,FYR,USD | IV3: 2,332.50749295928
A4: STX.N,mstag:inventories,2007Q1,,FYR,USD | B4: 939 | C4: JAVA.O,mscalc:sharePrice,,,FYR,USD | D4: NA | E4: JAVA.O,mscalc:dilutedSharesOutstanding,2008Q1,,FYR | F4: 3,372.53215958779 | G4: STX.N,mscalc:otheroperatingIncomeExpense,2008Q3,,FYR,USD | H4: NA | I4: JAVA.O,mstag:employeeExpenses,2008Q4,,FYR,USD | J4: NA | K4: JAVA.O,mstag:costOfMaterials,2008Q1,,FYR,USD | L4: NA | M4: STX.N,mstag:costOfSalesWithoutDepreciation,2008Q3,,FYR,USD | N4: NA | O4: STX.N,mscalc:depreciationAndAmortization,2008Q1,,FYR,USD | P4: 205 | Q4: STX.N,mstag:incomeLossFromInvestmentsAccountedForUnderTheEquityMethodOperatingIncomeStatement,2008Q2,,FYR,USD | R4: NA | S4: JAVA.O,mstag:costOfSalesWithoutDepreciation | T4: NA | U4: JAVA.O,mscalc:otherIncomeExpense,2008Q1,,FYR,USD | V4: 18.3365052708751 | W4: JAVA.O,mscalc:nonMarketCapComponentsOfEv,2007Q4,,FYR,USD | X4: (4,754) | Y4: STX.N,mstag:costOfSalesWithDepreciation | Z4: NA | AA4: STX.N,mscalc:otheroperatingIncomeExpense,2008Q2,,FYR,USD | AB4: NA | AC4: STX.N,mstag:tradeAndOtherPayables,2008Q3,,FYR,USD | AD4: 1,425.42124569734 | AE4: JAVA.O,mscalc:depreciationAndAmortization,2008Q2,,FYR,USD | AF4: 202.408164888305 | AG4: STX.N,mstag:tradeReceivables,2008Q3,,FYR,USD | AH4: 1,468.79610796709 | AI4: STX.N,mscalc:consensusEps,2009Q1,,FYR,USD | AJ4: 0.715201020240784 | AK4: JAVA.O,mscalc:depreciationAndAmortization,2008Q1,,FYR,USD | AL4: 193 | AM4: STX.N,mscalc:netFinancialIncomeExpense,2008Q4,,FYR,USD | AN4: (14.0015300805477) | AO4: JAVA.O,mstag:costOfSalesWithDepreciation,2008Q1,,FYR,USD | AP4: 1,814.135470455 | AQ4: JAVA.O,mstag:inventories,,,FYR,USD | AR4: NA | AS4: JAVA.O,mstag:sellingGeneralAndAdministrativeExpenses,2007Q4,,FYR,USD | AT4: 997 | AU4: JAVA.O,mscalc:dilutedSharesOutstanding,2008Q2,,FYR | AV4: 3,372.53215958779 | AW4: STX.N,mstag:costOfSalesWithDepreciation,,,FYR,USD | AX4: NA | AY4: JAVA.O,mstag:sellingGeneralAndAdministrativeExpenses,2008Q4,,FYR,USD | AZ4: 989.559329182354 | BA4: JAVA.O,mscalc:consensusEps,2009Q1,,FYR,USD | BB4: 0.233264997601509 | BC4: JAVA.O,mstag:costOfSalesWithDepreciation,2008Q1 | BD4: 1,657.98863544785 | BE4: JAVA.O,mscalc:taxExpenseFromOperations,2008Q3,,FYR,USD | BF4: 56.1211445355905 | BG4: JAVA.O,mstag:costOfServicesSold,2007Q4 | BH4: NA | BI4: STX.N,mstag:incomeLossFromInvestmentsAccountedForUnderTheEquityMethodOperatingIncomeStatement,2008Q1,,FYR,USD | BJ4: NA | BK4: STX.N,mstag:averageDilutedSharesOutstanding,2008Q4,,FYR | BL4: 538.400665827991 | BM4: JAVA.O,mstag:tradeReceivables,2008Q4,,FYR,USD | BN4: 3,016.94917433645 | BO4: JAVA.O,mstag:sellingGeneralAndAdministrativeExpenses,2008Q3,,FYR,USD | BP4: 906.037647853218 | BQ4: STX.N,mstag:costOfSalesWithDepreciation,2008Q1 | BR4: 2,464.87590849649 | BS4: JAVA.O,mscalc:dilutedSharesOutstanding,,,FYR | BT4: NA | BU4: STX.N,mscalc:dilutedSharesOutstanding,2008Q3,,FYR | BV4: 562.067222377659 | BW4: JAVA.O,mstag:costOfServicesSold,2008Q2,,FYR,USD | BX4: NA | BY4: JAVA.O,mstag:costOfServicesSold,2008Q1,,FYR,USD | BZ4: NA | CA4: JAVA.O,mstag:costOfServicesSold,2008Q4,,FYR,USD | CB4: NA | CC4: JAVA.O,mscalc:sharePrice,2007Q1,,FYR,USD | CD4: 4.95 | CE4: STX.N,mstag:averageDilutedSharesOutstanding,2008Q3,,FYR | CF4: 544.217364470004 | CG4: STX.N,mstag:costOfServicesSold,2008Q3,,FYR,USD | CH4: NA | CI4: JAVA.O,mscalc:taxExpenseFromOperations,2008Q2,,FYR,USD | CJ4: 71.2837361429788 | CK4: JAVA.O,mscalc:operatingRevenue,2008Q4,,FYR,USD | CL4: 4,022.59889911526 | CM4: STX.N,mscalc:sharePrice,,,FYR,USD | CN4: NA | CO4: STX.N,mscalc:operatingRevenue,2008Q4,,FYR,USD | CP4: 2,903.49820338861 | CQ4: STX.N,mstag:inventories,2008Q2,,FYR,USD | CR4: 912.047916824353

Sheet __FDSCACHE__
B1: This sheet contains Factset binary data for use with this workbook's =FDS codes. Modifying the worksheet's contents may damage the workbook's =FDS functionality.

Sheet ImportantDisclosures
A2: 1585 Broadway
A3: New York, NY 10036-8293
A4: United States
A5: Tel: +1 (1)212 761 4000
A7: Authors: Joseph Moore, Katy Huberty
A8: Date: 25 Jan 2018
A10: Ticker: WDC.O
A11: Stock Rating: Equal-Weight
A12: Industry: Semiconductors
A13: Industry View: In-Line
A14: Price as of 25 Jan 2018: 87.99
A15: Target Price: 92
... A107: Equal-weight and Not-Rated to hold and Underweight to sell recommendations, respectively.
B109: Coverage Universe | D109: Investment Banking Clients (IBC) | G109: Other Material Investment Services Clients (MISC)
A110: Stock Rating Category | B110: Count | C110: % of Total | D110: Count | E110: % of Total IBC | F110: % of Rating Category | G110: Count | H110: % of Total Other MISC
A111: Overweight/Buy | B111: 1142 | C111: 0.36 | D111: 320 | E111: 0.4 | F111: 0.28 | G111: 560 | H111: 0.38
A112: Equal-weight/Hold | B112: 1424 | C112: 0.44 | D112: 371 | E112: 0.47 | F112: 0.26 | G112: 674 | H112: 0.46
A113: Not-Rated/Hold | B113: 55 | C113: 0.02 | D113: 6 | E113: 0.01 | F113: 0.11 | G113: 9 | H113: 0.01
A114: Underweight/Sell | B114: 583 | C114: 0.18 | D114: 95 | E114: 0.12 | F114: 0.16 | G114: 237 | H114: 0.16
A115: Total | B115: 3204 | D115: 792 | G115: 1480
A117: Data include common stock and ADRs currently assigned ratings. Investment Banking Clients are companies
A118: from whom Morgan Stanley received investment banking compensation in the last 12 months. Due to rounding
A119: off of decimals, the percentages provided in the "% of total" column may not add up to exactly 100
A120: percent.
A122: Analyst Stock Ratings
A124: Overweight (O). The stock's total return is expected to exceed the average total return of the analyst's
A125: industry (or industry team's) coverage universe, on a risk-adjusted basis, over the next 12-18 months.
A127: Equal-weight (E). The stock's total return is expected to be in line with the average total return of
A128: the analyst's industry (or industry team's) coverage universe, on a risk-adjusted basis, over the next
A129: 12-18 months.
A131: Not-Rated (NR). Currently the analyst does not have adequate conviction about the stock's total return
A132: relative to the average total return of the analyst's industry (or industry team's) coverage universe,
... A378: © Copyright 2018 Morgan Stanley

Sheet IS
B5: Western Digital
B6: Income Statement
F8: F2001A | J8: F2002A | N8: F2003A | R8: F2004A | V8: F2005A | Z8: F2006A | AD8: F2007A | AH8: F2008A | AL8: F2009A | AP8: F2010A | AT8: F2011A | AX8: F2012A | BB8: F2013A | BF8: F2014A | BJ8: F2015A | BN8: F2016A | BR8: F2017A | BV8: F2018E | BZ8: F2019E | CR8: Fiscal Year | DS8: Calendarized
B9: ($ in millions) | F9: 36776 | G9: 36867 | H9: 36956 | I9: 37048 | J9: 37141 | K9: 37232 | L9: 37321 | M9: 37413 | N9: 37506 | O9: 37597 | P9: 37686 | Q9: 37778 | R9: 37871 | S9: 37962 | T9: 38052 | U9: 38144 | V9: 38237 | W9: 38328 | X9: 38417 | Y9: 38509 | Z9: 38602 | AA9: 38693 | AB9: 38782 | AC9: 38874 | AD9: 38967 | AE9: 39058 | AF9: 39147 | AG9: 39239 | AH9: 39331 | AI9: 39422 | AJ9: 39513 | AK9: 39605 | AL9: 39697 | AM9: 39788 | AN9: 39878 | AO9: 39970 | AP9: 40062 | AQ9: 40153 | AR9: 40243 | AS9: 40335 | AT9: 40451 | AU9: 40542 | AV9: 40632 | AW9: 40724 | AX9: 40816 | AY9: 40907 | AZ9: 40998 | BA9: 41090 | BB9: 41182 | BC9: 41273 | BD9: 41364 | BE9: 41455 | BF9: 41547 | BG9: 41638 | BH9: 41728 | BI9: 41820 | BJ9: 41912 | BK9: 42003 | BL9: 42093 | BM9: 42185 | BN9: 42277 | BO9: 42368 | BP9: 42459 | BQ9: 42551 | BR9: 42643 | BS9: 42735 | BT9: 42825 | BU9: 42916 | BV9: 43008 | BW9: 43100 | BX9: 43190 | BY9: 43281 | BZ9: 43373 | CA9: 43465 | CB9: 43555 | CC9: 43646 | CE9: 2001A | CF9: 2002A | CG9: 2003A | CH9: 2004A | CI9: 2005A | CJ9: 2006A | CK9: 2007A | CL9: 2008A | CM9: 2009A | CN9: 2010A | CO9: 2011A | CP9: 2012A | CQ9: 2013A | CR9: 2014A | CS9: 2015A | CT9: 2016A | CU9: 2017A | CV9: 2018E | CW9: 2019E | CX9: 2020E | CY9: 2021E | CZ9: 2022E | DA9: 2023E | DB9: 2024E | DC9: 2025E | DG9: 2001A | DH9: 2002A | DI9: 2003A | DJ9: 2004A | DK9: 2005A | DL9: 2006A | DM9: 2007A | DN9: 2008A | DO9: 2009A | DP9: 2010A | DQ9: 2011A | DR9: 2012A | DS9: 2013A | DT9: 2014A | DU9: 2015A | DV9: 2016A | DW9: 2017E | DX9: 2018E
BB10: FY13 and fwd restated for new segment reporting in 2H CY16 | BJ10: FY15 and fwd restated for SBC on 10/26/2016
A11: X | B11: Revenues | F11: 424.366 | G11: 561.57 | H11: 511.723 | I11: 455.733 | J11: =J395+J382 -> 440.943 | K11: =K395+K382 -> 574.67 | L11: =L395+L382 -> 594.86671 | M11: =M395+M382 -> 540.672 | N11: =N395+N382 -> 582.90928 | O11: =O395+O382 -> 749.4884 | P11: =P395+P382 -> 705.83853 | Q11: =Q395+Q382 -> 680.26237 | ... AO11: =AO395+AO382 -> 1928.1866 | AP11: =AP28+AP29+AP32+AP35 -> 2208 | AQ11: =AQ28+AQ29+AQ32+AQ35 -> 2619 | AR11: =AR28+AR29+AR32+AR35 -> 2641 | AS11: =AS28+AS29+AS32+AS35 -> 2382 | AT11: =AT28+AT29+AT32+AT35 -> 2447 | AU11: =AU28+AU29+AU32+AU35 -> 2475 | AV11: =AV28+AV29+AV32+AV35 -> 2252 | AW11: =AW28+AW29+AW32+AW35 -> 2403 | ... BA11: =BA28+BA29+BA32+BA35 -> 4754 | BB11: =SUM(BB12, BB13, BB14) -> 4035 | BC11: =SUM(BC12, BC13, BC14) -> 3824 | BD11: =SUM(BD12, BD13, BD14) -> 3764 | BE11: =SUM(BE12, BE13, BE14) -> 3728 | BF11: =SUM(BF12, BF13, BF14) -> 3804 | BG11: =SUM(BG12, BG13, BG14) -> 3972 | BH11: =SUM(BH12, BH13, BH14) -> 3703 | BI11: =SUM(BI12, BI13, BI14) -> 3651 | ... CC11: =SUM(CC12, CC13, CC14) -> 4386.1351 | CE11: =SUM(F11:I11) -> 1953.392 | CF11: =SUM(J11:M11) -> 2151.1517 | CG11: =SUM(N11:Q11) -> 2718.4986 | CH11: =SUM(R11:U11) -> 3046.7261 | CI11: =SUM(V11:Y11) -> 3638.7642 | CJ11: =SUM(Z11:AC11) -> 4341.263 | CK11: =SUM(AD11:AG11) -> 5468.7064 | CL11: =SUM(AH11:AK11) -> 8074.1839 | CM11: =SUM(AL11:AO11) -> 7451.8561 | CN11: =SUM(AP11:AS11) -> 9850 | CO11: =SUM(AT11:AW11) -> 9577 | CP11: =SUM(AX11:BA11) -> 12478 | CQ11: =SUM(CQ12, CQ13, CQ14) -> 15351 | CR11: =SUM(CR12, CR13, CR14) -> 15130 | CS11: =SUM(CS12, CS13, CS14) -> 14572 | CT11: =SUM(CT12, CT13, CT14) -> 12994 | CU11: =SUM(CU12, CU13, CU14) -> 19093 | CV11: =SUM(CV12, CV13, CV14) -> 20340.12 | CW11: =SUM(CW12, CW13, CW14) -> 19080.648 | CX11: =SUM(CX12, CX13, CX14) -> 20472.086 | ... DC11: =SUM(DC12, DC13, DC14) -> 25509.215 | DG11: =SUM(H11:K11) -> 1983.069 | DH11: =SUM(L11:O11) -> 2467.9364 | DI11: =SUM(P11:S11) -> 2935.1426 | DJ11: =SUM(T11:W11) -> 3276.186 | DK11: =SUM(X11:AA11) -> 3987.235 | DL11: =SUM(AB11:AE11) -> 4906.2595 | DM11: =SUM(AF11:AI11) -> 6746.8297 | DN11: =SUM(AJ11:AM11) -> 8035.8692 | DO11: =SUM(AN11:AQ11) -> 8347.0786 | DP11: =SUM(AR11:AU11) -> 9945 | DQ11: =SUM(AV11:AY11) -> 9344 | DR11: =SUM(AZ11:BC11) -> 15648 | DS11: =SUM(BD11:BG11) -> 15268 | DT11: =SUM(BH11:BK11) -> 15185 | DU11: =SUM(BL11:BO11) -> 13418 | DV11: =SUM(BP11:BS11) -> 15919 | DW11: =SUM(BT11:BW11) -> 20008 | DX11: =SUM(BX11:CA11) -> 19883.739 | DZ11: =CU11*(1+DZ28) -> 19665.79
C12: Client Devices | BB12: =BB241 -> 2650 | BC12: =BC241 -> 2259 | BD12: =BD241 -> 2168 | BE12: =BE241 -> 2109 | BF12: =BF241 -> 2198 | BG12: =BG241 -> 2226 | BH12: =BH241 -> 2126 | BI12: =BI241 -> 2170 | ... CC12: =CC241 -> 2114.1098 | CQ12: =CQ241 -> 9186 | CR12: =CR241 -> 8720 | CS12: =CS241 -> 7710 | CT12: =CT241 -> 6205 | CU12: =CU241 -> 9520 | CV12: =CV241 -> 10202.576 | CW12: =CW241 -> 9238.843 | CX12: =CX241 -> 9516.0082 | ... DC12: =DC241 -> 9311.6887 | DS12: =SUM(BD12:BG12) -> 8701 | DT12: =SUM(BH12:BK12) -> 8640 | DU12: =SUM(BL12:BO12) -> 6617 | DV12: =SUM(BP12:BS12) -> 7746 | DW12: =SUM(BT12:BW12) -> 10051 | DX12: =SUM(BX12:CA12) -> 9757.1691
C13: Client Solutions | BB13: =BB291 -> 500 | BC13: =BC291 -> 568 | BD13: =BD291 -> 500 | BE13: =BE291 -> 401 | BF13: =BF291 -> 455 | BG13: =BG291 -> 543 | BH13: =BH291 -> 479 | BI13: =BI291 -> 444 | ... CC13: =CC291 -> 1000.206 | CQ13: =CQ291 -> 1969 | CR13: =CR291 -> 1921 | CS13: =CS291 -> 1850 | CT13: =CT291 -> 1870 | CU13: =CU291 -> 4068 | CV13: =CV291 -> 4516.5835 | CW13: =CW291 -> 4249.3853 | CX13: =CX291 -> 4334.373 | ... DC13: =DC291 -> 4158.5538 | DS13: =SUM(BD13:BG13) -> 1899 | DT13: =SUM(BH13:BK13) -> 1955 | DU13: =SUM(BL13:BO13) -> 1676 | DV13: =SUM(BP13:BS13) -> 3064 | DW13: =SUM(BT13:BW13) -> 4407 | DX13: =SUM(BX13:CA13) -> 4348.7526
C14: Data Center Devices & Solutions | BB14: =BB317 -> 885 | BC14: =BC317 -> 997 | BD14: =BD317 -> 1096 | BE14: =BE317 -> 1218 | BF14: =BF317 -> 1151 | BG14: =BG317 -> 1203 | BH14: =BH317 -> 1098 | BI14: =BI317 -> 1037 | ... CC14: =CC317 -> 1271.8193 | CQ14: =CQ317 -> 4196 | CR14: =CR317 -> 4489 | CS14: =CS317 -> 5012 | CT14: =CT317 -> 4919 | CU14: =CU317 -> 5505 | CV14: =CV317 -> 5620.9601 | CW14: =CW317 -> 5592.4202 | CX14: =CX317 -> 6621.7051 | ... DC14: =DC317 -> 12038.972 | DS14: =SUM(BD14:BG14) -> 4668 | DT14: =SUM(BH14:BK14) -> 4590 | DU14: =SUM(BL14:BO14) -> 5125 | DV14: =SUM(BP14:BS14) -> 5109 | DW14: =SUM(BT14:BW14) -> 5550 | DX14: =SUM(BX14:CA14) -> 5777.817
B16: Cost of revenues | BB16: =SUM(BB17:BB19) -> 2804.1 | BC16: =SUM(BC17:BC19) -> 2726.9445 | BD16: =SUM(BD17:BD19) -> 2665.28 | BE16: =SUM(BE17:BE19) -> 2642.762 | BF16: =SUM(BF17:BF19) -> 2668.9298 | BG16: =SUM(BG17:BG19) -> 2776.176 | BH16: =SUM(BH17:BH19) -> 2587.992 | BI16: =SUM(BI17:BI19) -> 2572.69 | ... CC16: =SUM(CC17:CC19) -> 2832.7765 | CQ16: =SUM(CQ17:CQ19) -> 10839.086 | CR16: =SUM(CR17:CR19) -> 10605.788 | CS16: =SUM(CS17:CS19) -> 10161.024 | CT16: =SUM(CT17:CT19) -> 9183.5725 | CU16: =SUM(CU17:CU19) -> 11878.438 | CV16: =SUM(CV17:CV19) -> 11807.378 | CW16: =SUM(CW17:CW19) -> 12021.718 | CX16: =SUM(CX17:CX19) -> 12971.248 | ... DC16: =SUM(DC17:DC19) -> 16645.919 | DS16: =SUM(BD16:BG16) -> 10753.148 | DT16: =SUM(BH16:BK16) -> 10603.584 | DU16: =SUM(BL16:BO16) -> 9472.684 | DV16: =SUM(BP16:BS16) -> 10640.601 | DW16: =SUM(BT16:BW16) -> 11685.622 | DX16: =SUM(BX16:CA16) -> 12024.318
C17: Client Devices | BB17: =(1-BB516)*BB12 -> 1996.775 | BC17: =(1-BC516)*BC12 -> 1766.538 | BD17: =(1-BD516)*BD12 -> 1691.04 | BE17: =(1-BE516)*BE12 -> 1678.764 | BF17: =(1-BF516)*BF12 -> 1706.9668 | BG17: =(1-BG516)*BG12 -> 1736.28 | BH17: =(1-BH516)*BH12 -> 1643.398 | BI17: =(1-BI516)*BI12 -> 1675.24 | ... CC17: =(1-CC516)*CC12 -> 1522.159 | CQ17: =SUM(BB17:BE17) -> 7133.117 | CR17: =SUM(BF17:BI17) -> 6761.8848 | CS17: =SUM(BJ17:BM17) -> 6019.48 | CT17: =SUM(BN17:BQ17) -> 5015.9675 | CU17: =SUM(BR17:BU17) -> 6652.43 | CV17: =SUM(BV17:BY17) -> 6653.51 | CW17: =SUM(BZ17:CC17) -> 6494.9773 | CX17: =(1-CX516)*CX12 -> 6756.3659 | CY17: =(1-CY516)*CY12 -> 6781.6404 | CZ17: =(1-CZ516)*CZ12 -> 6759.082 | DA17: =(1-DA516)*DA12 -> 6849.5698 | DB17: =(1-DB516)*DB12 -> 6939.9841 | DC17: =(1-DC516)*DC12 -> 7030.325
C18: Client Solutions | BB18: =(1-BB517)*BB13 -> 325 | BC18: =(1-BC517)*BC13 -> 397.6 | BD18: =(1-BD517)*BD13 -> 355 | BE18: =(1-BE517)*BE13 -> 280.7 | BF18: =(1-BF517)*BF13 -> 313.95 | BG18: =(1-BG517)*BG13 -> 363.81 | BH18: =(1-BH517)*BH13 -> 320.93 | BI18: =(1-BI517)*BI13 -> 306.36 | ... CC18: =(1-CC517)*CC13 -> 700.14418 | CQ18: =SUM(BB18:BE18) -> 1358.3 | CR18: =SUM(BF18:BI18) -> 1305.05 | CS18: =SUM(BJ18:BM18) -> 1275.416 | CT18: =SUM(BN18:BQ18) -> 1292.145 | CU18: =SUM(BR18:BU18) -> 2568.908 | CV18: =SUM(BV18:BY18) -> 2771.4734 | CW18: =SUM(BZ18:CC18) -> 2930.1501 | CX18: =(1-CX517)*CX13 -> 2904.0299 | CY18: =(1-CY517)*CY13 -> 2946.1947 | CZ18: =(1-CZ517)*CZ13 -> 2959.0279 | DA18: =(1-DA517)*DA13 -> 2971.2929 | DB18: =(1-DB517)*DB13 -> 2982.9998 | DC18: =(1-DC517)*DC13 -> 2994.1587
C19: Data Center Devices and Solutions | BB19: =(1-BB518)*BB14 -> 482.325 | BC19: =(1-BC518)*BC14 -> 562.8065 | BD19: =(1-BD518)*BD14 -> 619.24 | BE19: =(1-BE518)*BE14 -> 683.298 | BF19: =(1-BF518)*BF14 -> 648.013 | BG19: =(1-BG518)*BG14 -> 676.086 | BH19: =(1-BH518)*BH14 -> 623.664 | BI19: =(1-BI518)*BI14 -> 591.09 | ... CC19: =(1-CC518)*CC14 -> 610.47327 | CQ19: =SUM(BB19:BE19) -> 2347.6695 | CR19: =SUM(BF19:BI19) -> 2538.853 | CS19: =SUM(BJ19:BM19) -> 2866.1275 | CT19: =SUM(BN19:BQ19) -> 2875.46 | CU19: =SUM(BR19:BU19) -> 2657.1 | CV19: =SUM(BV19:BY19) -> 2382.3946 | CW19: =SUM(BZ19:CC19) -> 2596.5902 | CX19: =(1-CX518)*CX14 -> 3310.8526 | CY19: =(1-CY518)*CY14 -> 3805.9575 | CZ19: =(1-CZ518)*CZ14 -> 4373.4183 | DA19: =(1-DA518)*DA14 -> 5023.6278 | DB19: =(1-DB518)*DB14 -> 5768.4517 | DC19: =(1-DC518)*DC14 -> 6621.4348
BV20: =AVERAGE(BR22:BW22) -> 0.3944032
B21: Gross Profit | BB21: =SUM(BB23, BB24, BB25) -> 1230.9 | BC21: =SUM(BC23, BC24, BC25) -> 1097.0555 | BD21: =SUM(BD23, BD24, BD25) -> 1098.72 | BE21: =SUM(BE23, BE24, BE25) -> 1085.238 | BF21: =SUM(BF23, BF24, BF25) -> 1135.0702 | BG21: =SUM(BG23, BG24, BG25) -> 1195.824 | BH21: =SUM(BH23, BH24, BH25) -> 1115.008 | BI21: =SUM(BI23, BI24, BI25) -> 1078.31 | ... CC21: =SUM(CC23, CC24, CC25) -> 1553.3586 | CQ21: =SUM(CQ23, CQ24, CQ25) -> 4511.9135 | CR21: =SUM(CR23, CR24, CR25) -> 4524.2122 | CS21: =SUM(CS23, CS24, CS25) -> 4410.9765 | CT21: =SUM(CT23, CT24, CT25) -> 3810.4275 | CU21: =SUM(CU23, CU24, CU25) -> 7214.562 | CV21: =SUM(CV23, CV24, CV25) -> 8532.7419 | CW21: =SUM(CW23, CW24, CW25) -> 7058.9308 | CX21: =SUM(CX23, CX24, CX25) -> 7500.838 | ... DC21: =SUM(DC23, DC24, DC25) -> 8863.2964 | DS21: =SUM(BD21:BG21) -> 4514.8522 | DT21: =SUM(BH21:BK21) -> 4581.416 | DU21: =SUM(BL21:BO21) -> 3945.316 | DV21: =SUM(BP21:BS21) -> 5278.399 | DW21: =SUM(BT21:BW21) -> 8322.378 | DX21: =SUM(BX21:CA21) -> 7859.4211
B22: Gross Margin | BB22: =BB21/BB11 -> 0.30505576 | BC22: =BC21/BC11 -> 0.2868869 | BD22: =BD21/BD11 -> 0.29190223 | BE22: =BE21/BE11 -> 0.29110461 | BF22: =BF21/BF11 -> 0.29838859 | BG22: =BG21/BG11 -> 0.30106344 | BH22: =BH21/BH11 -> 0.30110937 | BI22: =BI21/BI11 -> 0.29534648 | ... CC22: =CC21/CC11 -> 0.35415202 | CQ22: =CQ21/CQ11 -> 0.29391659 | CR22: =CR21/CR11 -> 0.29902262 | CS22: =CS21/CS11 -> 0.3027022 | CT22: =CT21/CT11 -> 0.29324515 | CU22: =CU21/CU11 -> 0.37786424 | CV22: =CV21/CV11 -> 0.41950303 | CW22: =CW21/CW11 -> 0.36995236 | CX22: =CX21/CX11 -> 0.36639343 | ... DC22: =DC21/DC11 -> 0.34745469 | DS22: =DS21/DS11 -> 0.29570685 | DT22: =DT21/DT11 -> 0.30170668 | DU22: =DU21/DU11 -> 0.2940316 | DV22: =DV21/DV11 -> 0.33157855 | DW22: =DW21/DW11 -> 0.41595252 | DX22: =DX21/DX11 -> 0.39526878
C23: Client Devices | BB23: =BB12-BB17 -> 653.225 | BC23: =BC12-BC17 -> 492.462 | BD23: =BD12-BD17 -> 476.96 | BE23: =BE12-BE17 -> 430.236 | BF23: =BF12-BF17 -> 491.0332 | BG23: =BG12-BG17 -> 489.72 | BH23: =BH12-BH17 -> 482.602 | BI23: =BI12-BI17 -> 494.76 | ... CC23: =CC12-CC17 -> 591.95073 | CQ23: =SUM(BB23:BE23) -> 2052.883 | CR23: =SUM(BF23:BI23) -> 1958.1152 | CS23: =SUM(BJ23:BM23) -> 1690.52 | CT23: =SUM(BN23:BQ23) -> 1189.0325 | CU23: =SUM(BR23:BU23) -> 2867.57 | CV23: =SUM(BV23:BY23) -> 3549.0664 | CW23: =CW12-CW17 -> 2743.8657 | CX23: =CX12-CX17 -> 2759.6424 | CY23: =CY12-CY17 -> 2637.3046 | CZ23: =CZ12-CZ17 -> 2563.7897 | DA23: =DA12-DA17 -> 2469.5728 | DB23: =DB12-DB17 -> 2375.4308 | DC23: =DC12-DC17 -> 2281.3637
C24: Client Solutions | BB24: =BB13-BB18 -> 175 | BC24: =BC13-BC18 -> 170.4 | BD24: =BD13-BD18 -> 145 | BE24: =BE13-BE18 -> 120.3 | BF24: =BF13-BF18 -> 141.05 | BG24: =BG13-BG18 -> 179.19 | BH24: =BH13-BH18 -> 158.07 | BI24: =BI13-BI18 -> 137.64 | ... CC24: =CC13-CC18 -> 300.06179 | CQ24: =SUM(BB24:BE24) -> 610.7 | CR24: =SUM(BF24:BI24) -> 615.95 | CS24: =SUM(BJ24:BM24) -> 574.584 | CT24: =SUM(BN24:BQ24) -> 577.855 | CU24: =SUM(BR24:BU24) -> 1499.092 | CV24: =SUM(BV24:BY24) -> 1745.11 | CW24: =CW13-CW18 -> 1319.2351 | CX24: =CX13-CX18 -> 1430.3431 | CY24: =CY13-CY18 -> 1386.4446 | CZ24: =CZ13-CZ18 -> 1329.4184 | DA24: =DA13-DA18 -> 1273.4112 | DB24: =DB13-DB18 -> 1218.4084 | DC24: =DC13-DC18 -> 1164.3951
C25: Data Center Devices and Solutions | BB25: =BB14-BB19 -> 402.675 | BC25: =BC14-BC19 -> 434.1935 | BD25: =BD14-BD19 -> 476.76 | BE25: =BE14-BE19 -> 534.702 | BF25: =BF14-BF19 -> 502.987 | BG25: =BG14-BG19 -> 526.914 | BH25: =BH14-BH19 -> 474.336 | BI25: =BI14-BI19 -> 445.91 | ... CC25: =CC14-CC19 -> 661.34605 | CQ25: =SUM(BB25:BE25) -> 1848.3305 | CR25: =SUM(BF25:BI25) -> 1950.147 | CS25: =SUM(BJ25:BM25) -> 2145.8725 | CT25: =SUM(BN25:BQ25) -> 2043.54 | CU25: =SUM(BR25:BU25) -> 2847.9 | CV25: =SUM(BV25:BY25) -> 3238.5655 | CW25: =CW14-CW19 -> 2995.83 | CX25: =CX14-CX19 -> 3310.8526 | CY25: =CY14-CY19 -> 3656.7042 | CZ25: =CZ14-CZ19 -> 4037.0015 | DA25: =DA14-DA19 -> 4454.9152 | DB25: =DB14-DB19 -> 4913.8663 | DC25: =DC14-DC19 -> 5417.5376
B27: OLD SEGMENT REPORTING
C28: Other - SSD | AP28: =AP382 -> 48.4382 | AQ28: =AQ382 -> 43.302 | AR28: =AR382 -> 34.241 | AS28: =AS382 -> 47.3835 | AT28: =AT382 -> 115.27873 | AU28: =AU382 -> 19.155 | AV28: =AV382 -> 10.72977 | AW28: =AW382 -> 33.820508 | ... BR28: =BR382 -> 244.59489 | CN28: =SUM(AP28:AS28) -> 173.3647 | CO28: =SUM(AT28:AW28) -> 178.98401 | CP28: =SUM(AX28:BA28) -> 226.44664 | CQ28: =SUM(BB28:BE28) -> 540.19275 | CR28: =SUM(BF28:BI28) -> 675.6603 | CS28: =SUM(BJ28:BM28) -> 905.21042 | CT28: =SUM(BN28:BQ28) -> 1102.2451 | CU28: =SUM(BR28:BU28) -> 244.59489 | DP28: =SUM(AR28:AU28) -> 216.05823 | DQ28: =SUM(AV28:AY28) -> 107.84546 | DR28: =SUM(AZ28:BC28) -> 475.3335 | DS28: =SUM(BD28:BG28) -> 587.38285 | DT28: =SUM(BH28:BK28) -> 729.71867 | DU28: =DU382 -> 1100.7101 | DV28: =DV382 -> 737.9098 | DW28: =DW382 -> 0 | DX28: =DX382 -> 0 | DZ28: 0.03
C29: Enterprise | AP29: =AP406 -> 155.217 | AQ29: =AQ406 -> 206.15 | AR29: =AR406 -> 223.82 | AS29: =AS406 -> 215.832 | AT29: =AT406 -> 211.029 | AU29: =AU406 -> 203.276 | AV29: =AV406 -> 197.01841 | AW29: =AW406 -> 209.34268 | ... BR29: =BR406 -> 770.31642 | CN29: =SUM(AP29:AS29) -> 801.019 | CO29: =SUM(AT29:AW29) -> 820.66609 | CP29: =SUM(AX29:BA29) -> 2046.7133 | CQ29: =SUM(BB29:BE29) -> 3610.479 | CR29: =SUM(BF29:BI29) -> 3663.3585 | CS29: =SUM(BJ29:BM29) -> 3737.5919 | CT29: =SUM(BN29:BQ29) -> 3174.0781 | CU29: =SUM(BR29:BU29) -> 770.31642 | DP29: =SUM(AR29:AU29) -> 853.957 | DQ29: =SUM(AV29:AY29) -> 840.33807 | DR29: =SUM(AZ29:BC29) -> 3302.3557 | DS29: =SUM(BD29:BG29) -> 3870.6433 | DT29: =SUM(BH29:BK29) -> 3633.7667 | DU29: =SUM(BL29:BO29) -> 3533.1208 | DV29: =SUM(BP29:BS29) -> 2228.6738 | DW29: =SUM(BT29:BW29) -> 0 | DX29: =SUM(BX29:CA29) -> 0
D30: Performance | AP30: =AP416 -> 0 | AQ30: =AQ416 -> 0 | AR30: =AR416 -> 0 | AS30: =AS416 -> 0 | AT30: =AT416 -> 0 | AU30: =AU416 -> 0 | AV30: =AV416 -> 0 | AW30: =AW416 -> 0 | ... BR30: =BR416 -> 301.05284 | CN30: =SUM(AP30:AS30) -> 0 | CO30: =SUM(AT30:AW30) -> 0 | CP30: =SUM(AX30:BA30) -> 706.7 | CQ30: =SUM(BB30:BE30) -> 1952.9766 | CR30: =SUM(BF30:BI30) -> 1896.5191 | CS30: =SUM(BJ30:BM30) -> 1891.4707 | CT30: =SUM(BN30:BQ30) -> 1460.9439 | CU30: =SUM(BR30:BU30) -> 301.05284 | DP30: =SUM(AR30:AU30) -> 0 | DQ30: =SUM(AV30:AY30) -> 0 | DR30: =SUM(AZ30:BC30) -> 1666.7949 | DS30: =SUM(BD30:BG30) -> 1999.8273 | DT30: =SUM(BH30:BK30) -> 1836.9771 | DU30: =SUM(BL30:BO30) -> 1780.5283 | DV30: =SUM(BP30:BS30) -> 925.53557 | DW30: =SUM(BT30:BW30) -> 0 | DX30: =SUM(BX30:CA30) -> 0
D31: Capacity | AP31: =AP426 -> 155.217 | AQ31: =AQ426 -> 206.15 | AR31: =AR426 -> 223.82 | AS31: =AS426 -> 215.832 | AT31: =AT426 -> 211.029 | AU31: =AU426 -> 203.276 | AV31: =AV426 -> 197.01841 | AW31: =AW426 -> 209.34268 | ... BR31: =BR426 -> 469.26358 | CN31: =SUM(AP31:AS31) -> 801.019 | CO31: =SUM(AT31:AW31) -> 820.66609 | CP31: =SUM(AX31:BA31) -> 1340.0133 | CQ31: =SUM(BB31:BE31) -> 1657.5024 | CR31: =SUM(BF31:BI31) -> 1766.8394 | CS31: =SUM(BJ31:BM31) -> 1846.1212 | CT31: =SUM(BN31:BQ31) -> 1713.1342 | CU31: =SUM(BR31:BU31) -> 469.26358 | DP31: =SUM(AR31:AU31) -> 853.957 | DQ31: =SUM(AV31:AY31) -> 840.33807 | DR31: =SUM(AZ31:BC31) -> 1635.5608 | DS31: =SUM(BD31:BG31) -> 1870.816 | DT31: =SUM(BH31:BK31) -> 1796.7896 | DU31: =SUM(BL31:BO31) -> 1752.5925 | DV31: =SUM(BP31:BS31) -> 1303.1382 | DW31: =SUM(BT31:BW31) -> 0 | DX31: =SUM(BX31:CA31) -> 0
C32: Compute | AP32: =AP437 -> 1499.7848 | AQ32: =AQ437 -> 1633.145 | AR32: =AR437 -> 1723.2545 | AS32: =AS437 -> 1514.5035 | AT32: =AT437 -> 1499.2298 | AU32: =AU437 -> 1529.9815 | AV32: =AV437 -> 1432.6053 | AW32: =AW437 -> 1545.3673 | ... BR32: =BR437 -> 1142.2333 | CN32: =SUM(AP32:AS32) -> 6370.6878 | CO32: =SUM(AT32:AW32) -> 6007.1838 | CP32: =SUM(AX32:BA32) -> 7881.0759 | CQ32: =SUM(BB32:BE32) -> 8008.2247 | CR32: =SUM(BF32:BI32) -> 7300.841 | CS32: =SUM(BJ32:BM32) -> 6372.9584 | CT32: =SUM(BN32:BQ32) -> 4589.9946 | CU32: =SUM(BR32:BU32) -> 1142.2333 | DP32: =SUM(AR32:AU32) -> 6266.9693 | DQ32: =SUM(AV32:AY32) -> 5957.2833 | DR32: =SUM(AZ32:BC32) -> 9044.4576 | DS32: =SUM(BD32:BG32) -> 7594.2701 | DT32: =SUM(BH32:BK32) -> 7145.2938 | DU32: =SUM(BL32:BO32) -> 5366.4428 | DV32: =SUM(BP32:BS32) -> 3165.5529 | DW32: =SUM(BT32:BW32) -> 0 | DX32: =SUM(BX32:CA32) -> 0
D33: Mobile | AP33: =AP447 -> 717.3152 | AQ33: =AQ447 -> 789.2075 | AR33: =AR447 -> 768.24 | AS33: =AS447 -> 693.0825 | AT33: =AT447 -> 667.4255 | AU33: =AU447 -> 708.43875 | AV33: =AV447 -> 644.71899 | AW33: =AW447 -> 670.14699 | ... BR33: =BR447 -> 710.60516 | CN33: =SUM(AP33:AS33) -> 2967.8452 | CO33: =SUM(AT33:AW33) -> 2690.7302 | CP33: =SUM(AX33:BA33) -> 4259.2349 | CQ33: =SUM(BB33:BE33) -> 4627.7609 | CR33: =SUM(BF33:BI33) -> 4216.9053 | CS33: =SUM(BJ33:BM33) -> 3726.1554 | CT33: =SUM(BN33:BQ33) -> 2622.6447 | CU33: =SUM(BR33:BU33) -> 710.60516 | DP33: =SUM(AR33:AU33) -> 2837.1867 | DQ33: =SUM(AV33:AY33) -> 2730.5716 | DR33: =SUM(AZ33:BC33) -> 5257.1111 | DS33: =SUM(BD33:BG33) -> 4359.0786 | DT33: =SUM(BH33:BK33) -> 4172.3651 | DU33: =SUM(BL33:BO33) -> 3080.04 | DV33: =SUM(BP33:BS33) -> 1879.0059 | DW33: =SUM(BT33:BW33) -> 0 | DX33: =SUM(BX33:CA33) -> 0
D34: Desktop | AP34: =AP457 -> 782.4696 | AQ34: =AQ457 -> 843.9375 | AR34: =AR457 -> 955.0145 | AS34: =AS457 -> 821.421 | AT34: =AT457 -> 831.80427 | AU34: =AU457 -> 821.54275 | AV34: =AV457 -> 787.88626 | AW34: =AW457 -> 875.22031 | ... BR34: =BR457 -> 431.62813 | CN34: =SUM(AP34:AS34) -> 3402.8426 | CO34: =SUM(AT34:AW34) -> 3316.4536 | CP34: =SUM(AX34:BA34) -> 3621.841 | CQ34: =SUM(BB34:BE34) -> 3380.4638 | CR34: =SUM(BF34:BI34) -> 3083.9357 | CS34: =SUM(BJ34:BM34) -> 2646.803 | CT34: =SUM(BN34:BQ34) -> 1967.35 | CU34: =SUM(BR34:BU34) -> 431.62813 | DP34: =SUM(AR34:AU34) -> 3429.7825 | DQ34: =SUM(AV34:AY34) -> 3226.7116 | DR34: =SUM(AZ34:BC34) -> 3787.3464 | DS34: =SUM(BD34:BG34) -> 3235.1915 | DT34: =SUM(BH34:BK34) -> 2972.9287 | DU34: =SUM(BL34:BO34) -> 2286.4029 | DV34: =SUM(BP34:BS34) -> 1286.547 | DW34: =SUM(BT34:BW34) -> 0 | DX34: =SUM(BX34:CA34) -> 0
C35: Non-Compute | AP35: =AP468 -> 504.56 | AQ35: =AQ468 -> 736.403 | AR35: =AR468 -> 659.6845 | AS35: =AS468 -> 604.281 | AT35: =AT468 -> 621.4625 | AU35: =AU468 -> 722.5875 | AV35: =AV468 -> 611.64656 | AW35: =AW468 -> 614.4695 | ... BR35: =BR468 -> 1009.9831 | CN35: =SUM(AP35:AS35) -> 2504.9285 | CO35: =SUM(AT35:AW35) -> 2570.1661 | CP35: =SUM(AX35:BA35) -> 2323.7642 | CQ35: =SUM(BB35:BE35) -> 3192.1036 | CR35: =SUM(BF35:BI35) -> 3490.1401 | CS35: =SUM(BJ35:BM35) -> 3556.2393 | CT35: =SUM(BN35:BQ35) -> 3386.2748 | CU35: =SUM(BR35:BU35) -> 1009.9831 | DP35: =SUM(AR35:AU35) -> 2608.0155 | DQ35: =SUM(AV35:AY35) -> 2438.5332 | DR35: =SUM(AZ35:BC35) -> 2825.8532 | DS35: =SUM(BD35:BG35) -> 3215.7037 | DT35: =SUM(BH35:BK35) -> 3676.2208 | DU35: =SUM(BL35:BO35) -> 3417.7263 | DV35: =SUM(BP35:BS35) -> 2610.5838 | DW35: =SUM(BT35:BW35) -> 0 | DX35: =SUM(BX35:CA35) -> 0
D36: Consumer Electronics | AP36: =AP478 -> 122.56 | AQ36: =AQ478 -> 167.403 | AR36: =AR478 -> 192.6845 | AS36: =AS478 -> 204.281 | AT36: =AT478 -> 196.4625 | AU36: =AU478 -> 176.5875 | AV36: =AV478 -> 170.64656 | AW36: =AW478 -> 232.4695 | ... BR36: =BR478 -> 573.14902 | CN36: =SUM(AP36:AS36) -> 686.9285 | CO36: =SUM(AT36:AW36) -> 776.16606 | CP36: =SUM(AX36:BA36) -> 781.89498 | CQ36: =SUM(BB36:BE36) -> 1190.3894 | CR36: =SUM(BF36:BI36) -> 1525.4404 | CS36: =SUM(BJ36:BM36) -> 1582.7408 | CT36: =SUM(BN36:BQ36) -> 1635.0614 | CU36: =SUM(BR36:BU36) -> 573.14902 | DP36: =SUM(AR36:AU36) -> 770.0155 | DQ36: =SUM(AV36:AY36) -> 798.5332 | DR36: =SUM(AZ36:BC36) -> 1030.256 | DS36: =SUM(BD36:BG36) -> 1264.6914 | DT36: =SUM(BH36:BK36) -> 1641.7578 | DU36: =SUM(BL36:BO36) -> 1593.6396 | DV36: =SUM(BP36:BS36) -> 1362.914 | DW36: =SUM(BT36:BW36) -> 0 | DX36: =SUM(BX36:CA36) -> 0
D37: Branded | AP37: =AP488 -> 382 | AQ37: =AQ488 -> 569 | AR37: =AR488 -> 467 | AS37: =AS488 -> 400 | AT37: =AT488 -> 425 | AU37: =AU488 -> 546 | AV37: =AV488 -> 441 | AW37: =AW488 -> 382 | ... BR37: =BR488 -> 436.83408 | CN37: =SUM(AP37:AS37) -> 1818 | CO37: =SUM(AT37:AW37) -> 1794 | CP37: =SUM(AX37:BA37) -> 1541.8692 | CQ37: =SUM(BB37:BE37) -> 2001.7142 | CR37: =SUM(BF37:BI37) -> 1964.6997 | CS37: =SUM(BJ37:BM37) -> 1973.4985 | CT37: =SUM(BN37:BQ37) -> 1751.2134 | CU37: =SUM(BR37:BU37) -> 436.83408 | DP37: =SUM(AR37:AU37) -> 1838 | DQ37: =SUM(AV37:AY37) -> 1640 | DR37: =SUM(AZ37:BC37) -> 1795.5972 | DS37: =SUM(BD37:BG37) -> 1951.0124 | DT37: =SUM(BH37:BK37) -> 2034.463 | DU37: =SUM(BL37:BO37) -> 1824.0868 | DV37: =SUM(BP37:BS37) -> 1247.6698 | DW37: =SUM(BT37:BW37) -> 0 | DX37: =SUM(BX37:CA37) -> 0
C38: SanDisk | BQ38: =BQ500*BQ499 -> 741.40741 | BR38: =BR500 -> 1546.8723 | CT38: =SUM(BN38:BQ38) -> 741.40741 | CU38: =SUM(BR38:BU38) -> 1546.8723
B40: Cost of revenues | F40: 398.43 | G40: 494.029 | H40: 448.428 | I40: 404.767 | J40: 384.936 | K40: 504.112 | L40: 513.849 | M40: 466.654 | N40: 499.266 | O40: 605.409 | P40: 583.819 | Q40: 568.585 | R40: 618 | S40: 693.0168 | T40: 626.3 | U40: 647.89325 | V40: 710.4765 | W40: 804.7 | X40: 752.9 | Y40: 780.9 | Z40: 831.6 | AA40: 888.8 | AB40: 910.9 | AC40: 894.1 | AD40: 1046 | AE40: 1173 | AF40: 1188 | AG40: 1162 | AH40: 1443 | AI40: 1690.8 | AJ40: 1634.42 | AK40: 1568 | AL40: 1685 | AM40: 1533 | AN40: 1339 | AO40: 1558 | AP40: =AP41+AP42+AP45+AP48 -> 1693.0511 | AQ40: =AQ41+AQ42+AQ45+AQ48 -> 1931.0599 | AR40: =AR41+AR42+AR45+AR48 -> 1975.1607 | AS40: =AS41+AS42+AS45+AS48 -> 1845.4347 | AT40: =AT41+AT42+AT45+AT48 -> 2000.0287 | AU40: =AU41+AU42+AU45+AU48 -> 1999.4178 | AV40: =AV41+AV42+AV45+AV48 -> 1841.9469 | AW40: =AW41+AW42+AW45+AW48 -> 1933.6861 | ... BP40: =BP41+BP42+BP45+BP48 -> 2025.971 | BQ40: =BQ41+BQ42+BQ45+BQ48+BQ51 -> 2403.1182 | BR40: =BR41+BR42+BR45+BR48+BR51 -> 3115.082 | CE40: =SUM(F40:I40) -> 1745.654 | CF40: =SUM(J40:M40) -> 1869.551 | CG40: =SUM(N40:Q40) -> 2257.079 | CH40: =SUM(R40:U40) -> 2585.2101 | CI40: =SUM(V40:Y40) -> 3048.9765 | CJ40: =SUM(Z40:AC40) -> 3525.4 | CK40: =SUM(AD40:AG40) -> 4569 | CL40: =SUM(AH40:AK40) -> 6336.22 | CM40: =SUM(AL40:AO40) -> 6115 | CN40: =SUM(AP40:AS40) -> 7444.7065 | CO40: =SUM(AT40:AW40) -> 7775.0794 | CP40: =SUM(AX40:BA40) -> 8699.9145 | CQ40: =SUM(BB40:BE40) -> 10838.692 | CR40: =SUM(BF40:BI40) -> 10605.997 | CS40: =SUM(BJ40:BM40) -> 10160.306 | CT40: =SUM(BN40:BQ40) -> 9183.9886 | CU40: =SUM(BR40:BU40) -> 3115.082 | DG40: =SUM(H40:K40) -> 1742.243 | DH40: =SUM(L40:O40) -> 2085.178 | DI40: =SUM(P40:S40) -> 2463.4208 | DJ40: =SUM(T40:W40) -> 2789.3697 | DK40: =SUM(X40:AA40) -> 3254.2 | DL40: =SUM(AB40:AE40) -> 4024 | DM40: =SUM(AF40:AI40) -> 5483.8 | DN40: =SUM(AJ40:AM40) -> 6420.42 | DO40: =SUM(AN40:AQ40) -> 6521.1111 | DP40: =SUM(AR40:AU40) -> 7820.0419 | DQ40: =SUM(AV40:AY40) -> 7274.8197 | DR40: =SUM(AZ40:BC40) -> 10731.417 | DS40: =SUM(BD40:BG40) -> 10753 | DT40: =SUM(BH40:BK40) -> 10603.441 | DU40: =SUM(BL40:BO40) -> 9472.7635 | DV40: =SUM(BP40:BS40) -> 7544.1712 | DW40: =SUM(BT40:BW40) -> 0 | DX40: =SUM(BX40:CA40) -> 0
C41: Other - Media | AP41: =AP28*(1-AP523) -> 37.152099 | AQ41: =AQ28*(1-AQ523) -> 31.956876 | AR41: =AR28*(1-AR523) -> 25.612268 | AS41: =AS28*(1-AS523) -> 36.74111 | AT41: =AT28*(1-AT523) -> 94.298001 | AU41: =AU28*(1-AU523) -> 15.47724 | AV41: =AV28*(1-AV523) -> 8.7769521 | AW41: =AW28*(1-AW523) -> 27.225509 | ... BR41: =BR28*(1-BR523) -> 139.41909 | CR41: =SUM(BF41:BI41) -> 408.37803 | CS41: =SUM(BJ41:BM41) -> 515.96994 | CT41: =SUM(BN41:BQ41) -> 627.35096 | CU41: =SUM(BR41:BU41) -> 139.41909 | DP41: =SUM(AR41:AU41) -> 172.12862 | DQ41: =SUM(AV41:AY41) -> 82.801406 | DR41: =SUM(AZ41:BC41) -> 331.25046
C42: Enterprise | AP42: =AP43+AP44 -> 93.1302 | AQ42: =AQ43+AQ44 -> 121.6285 | AR42: =AR43+AR44 -> 134.292 | AS42: =AS43+AS44 -> 131.65752 | AT42: =AT43+AT44 -> 131.89312 | AU42: =AU43+AU44 -> 127.0475 | AV42: =AV43+AV44 -> 126.09178 | AW42: =AW43+AW44 -> 131.88589 | ... BR42: =BR43+BR44 -> 439.08036 | CN42: =SUM(AP42:AS42) -> 480.70822 | CO42: =SUM(AT42:AW42) -> 516.9183 | CP42: =SUM(AX42:BA42) -> 1087.1188 | CQ42: =SUM(BB42:BE42) -> 2012.4703 | CR42: =SUM(BF42:BI42) -> 2071.0797 | CS42: =SUM(BJ42:BM42) -> 2131.9047 | CT42: =SUM(BN42:BQ42) -> 1883.169 | CU42: =SUM(BR42:BU42) -> 439.08036 | DP42: =SUM(AR42:AU42) -> 524.89015 | DQ42: =SUM(AV42:AY42) -> 502.45148 | DR42: =SUM(AZ42:BC42) -> 1779.7584
D43: Performance | AP43: =AP30*(1-AP525) -> 0 | AQ43: =AQ30*(1-AQ525) -> 0 | AR43: =AR30*(1-AR525) -> 0 | AS43: =AS30*(1-AS525) -> 0 | AT43: =AT30*(1-AT525) -> 0 | AU43: =AU30*(1-AU525) -> 0 | AV43: =AV30*(1-AV525) -> 0 | AW43: =AW30*(1-AW525) -> 0 | ... BR43: =BR30*(1-BR525) -> 171.60012 | CN43: =SUM(AP43:AS43) -> 0 | CO43: =SUM(AT43:AW43) -> 0 | CP43: =SUM(AX43:BA43) -> 378.658 | CQ43: =SUM(BB43:BE43) -> 1079.2999 | CR43: =SUM(BF43:BI43) -> 1063.9812 | CS43: =SUM(BJ43:BM43) -> 1068.4706 | CT43: =SUM(BN43:BQ43) -> 863.86593 | CU43: =SUM(BR43:BU43) -> 171.60012 | DP43: =SUM(AR43:AU43) -> 0 | DQ43: =SUM(AV43:AY43) -> 0 | DR43: =SUM(AZ43:BC43) -> 906.90857
D44: Capacity | AP44: =AP31*(1-AP526) -> 93.1302 | AQ44: =AQ31*(1-AQ526) -> 121.6285 | AR44: =AR31*(1-AR526) -> 134.292 | AS44: =AS31*(1-AS526) -> 131.65752 | AT44: =AT31*(1-AT526) -> 131.89312 | AU44: =AU31*(1-AU526) -> 127.0475 | AV44: =AV31*(1-AV526) -> 126.09178 | AW44: =AW31*(1-AW526) -> 131.88589 | ... BR44: =BR31*(1-BR526) -> 267.48024 | CN44: =SUM(AP44:AS44) -> 480.70822 | CO44: =SUM(AT44:AW44) -> 516.9183 | CP44: =SUM(AX44:BA44) -> 708.46076 | CQ44: =SUM(BB44:BE44) -> 933.17037 | CR44: =SUM(BF44:BI44) -> 1007.0985 | CS44: =SUM(BJ44:BM44) -> 1063.4341 | CT44: =SUM(BN44:BQ44) -> 1019.303 | CU44: =SUM(BR44:BU44) -> 267.48024 | DP44: =SUM(AR44:AU44) -> 524.89015 | DQ44: =SUM(AV44:AY44) -> 502.45148 | DR44: =SUM(AZ44:BC44) -> 872.84982
C45: Compute | AP45: =AP46+AP47 -> 1208.0964 | AQ45: =AQ46+AQ47 -> 1266.1733 | AR45: =AR46+AR47 -> 1349.3294 | AS45: =AS46+AS47 -> 1237.6112 | AT45: =AT46+AT47 -> 1305.2548 | AU45: =AU46+AU47 -> 1324.5937 | AV45: =AV46+AV47 -> 1247.2121 | AW45: =AW46+AW47 -> 1309.9903 | ... BR45: =BR46+BR47 -> 902.3643 | CN45: =SUM(AP45:AS45) -> 5061.2104 | CO45: =SUM(AT45:AW45) -> 5187.0509 | CP45: =SUM(AX45:BA45) -> 5859.8725 | CQ45: =SUM(BB45:BE45) -> 6225.6753 | CR45: =SUM(BF45:BI45) -> 5693.79 | CS45: =SUM(BJ45:BM45) -> 5011.2741 | CT45: =SUM(BN45:BQ45) -> 3772.7545 | CU45: =SUM(BR45:BU45) -> 902.3643 | DP45: =SUM(AR45:AU45) -> 5216.7892 | DQ45: =SUM(AV45:AY45) -> 4906.7396 | DR45: =SUM(AZ45:BC45) -> 6701.7231
D46: Mobile | AP46: =AP33*(1-AP528) -> 581.02531 | AQ46: =AQ33*(1-AQ528) -> 615.58185 | AR46: =AR33*(1-AR528) -> 605.37312 | AS46: =AS33*(1-AS528) -> 569.71382 | AT46: =AT33*(1-AT528) -> 583.99731 | AU46: =AU33*(1-AU528) -> 616.34171 | AV46: =AV33*(1-AV528) -> 563.4844 | AW46: =AW33*(1-AW528) -> 570.42912 | ... BR46: =BR33*(1-BR528) -> 561.37808 | CN46: =SUM(AP46:AS46) -> 2371.6941 | CO46: =SUM(AT46:AW46) -> 2334.2525 | CP46: =SUM(AX46:BA46) -> 3180.897 | CQ46: =SUM(BB46:BE46) -> 3637.3236 | CR46: =SUM(BF46:BI46) -> 3342.0797 | CS46: =SUM(BJ46:BM46) -> 2972.1738 | CT46: =SUM(BN46:BQ46) -> 2169.7558 | CU46: =SUM(BR46:BU46) -> 561.37808 | DP46: =SUM(AR46:AU46) -> 2375.426 | DQ46: =SUM(AV46:AY46) -> 2254.243 | DR46: =SUM(AZ46:BC46) -> 3937.6188
D47: Desktop | AP47: =AP34*(1-AP529) -> 627.07114 | AQ47: =AQ34*(1-AQ529) -> 650.59142 | AR47: =AR34*(1-AR529) -> 743.9563 | AS47: =AS34*(1-AS529) -> 667.89742 | AT47: =AT34*(1-AT529) -> 721.25748 | AU47: =AU34*(1-AU529) -> 708.252 | AV47: =AV34*(1-AV529) -> 683.7277 | AW47: =AW34*(1-AW529) -> 739.56116 | ... BR47: =BR34*(1-BR529) -> 340.98622 | CN47: =SUM(AP47:AS47) -> 2689.5163 | CO47: =SUM(AT47:AW47) -> 2852.7983 | CP47: =SUM(AX47:BA47) -> 2678.9755 | CQ47: =SUM(BB47:BE47) -> 2588.3517 | CR47: =SUM(BF47:BI47) -> 2351.7103 | CS47: =SUM(BJ47:BM47) -> 2039.1002 | CT47: =SUM(BN47:BQ47) -> 1602.9986 | CU47: =SUM(BR47:BU47) -> 340.98622 | DP47: =SUM(AR47:AU47) -> 2841.3632 | DQ47: =SUM(AV47:AY47) -> 2652.4965 | DR47: =SUM(AZ47:BC47) -> 2764.1043
C48: Non-Compute | AP48: =AP49+AP50 -> 354.6724 | AQ48: =AQ49+AQ50 -> 511.30128 | AR48: =AR49+AR50 -> 465.92706 | AS48: =AS49+AS50 -> 439.4248 | AT48: =AT49+AT50 -> 468.58275 | AU48: =AU49+AU50 -> 532.29938 | AV48: =AV49+AV50 -> 459.86604 | AW48: =AW49+AW50 -> 464.58438 | ... BR48: =BR49+BR50 -> 726.76949 | CN48: =SUM(AP48:AS48) -> 1771.3255 | CO48: =SUM(AT48:AW48) -> 1925.3326 | CP48: =SUM(AX48:BA48) -> 1593.4012 | CQ48: =SUM(BB48:BE48) -> 2222.4113 | CR48: =SUM(BF48:BI48) -> 2432.7491 | CS48: =SUM(BJ48:BM48) -> 2501.1575 | CT48: =SUM(BN48:BQ48) -> 2454.3882 | CU48: =SUM(BR48:BU48) -> 726.76949 | DP48: =SUM(AR48:AU48) -> 1906.234 | DQ48: =SUM(AV48:AY48) -> 1782.8272 | DR48: =SUM(AZ48:BC48) -> 1918.6856
D49: Consumer Electronics | AP49: =AP36*(1-AP531) -> 96.8224 | AQ49: =AQ36*(1-AQ531) -> 127.22628 | AR49: =AR36*(1-AR531) -> 148.36707 | AS49: =AS36*(1-AS531) -> 163.4248 | AT49: =AT36*(1-AT531) -> 168.95775 | AU49: =AU36*(1-AU531) -> 150.09938 | AV49: =AV36*(1-AV531) -> 146.75604 | AW49: =AW36*(1-AW531) -> 195.27438 | ... BR49: =BR36*(1-BR531) -> 438.459 | CN49: =SUM(AP49:AS49) -> 535.84055 | CO49: =SUM(AT49:AW49) -> 661.08755 | CP49: =SUM(AX49:BA49) -> 592.29128 | CQ49: =SUM(BB49:BE49) -> 904.10438 | CR49: =SUM(BF49:BI49) -> 1140.4369 | CS49: =SUM(BJ49:BM49) -> 1194.4666 | CT49: =SUM(BN49:BQ49) -> 1281.0752 | CU49: =SUM(BR49:BU49) -> 438.459 | DP49: =SUM(AR49:AU49) -> 630.84899 | DQ49: =SUM(AV49:AY49) -> 658.86222 | DR49: =SUM(AZ49:BC49) -> 757.31906
D50: Branded | AP50: =AP37*(1-AP532) -> 257.85 | AQ50: =AQ37*(1-AQ532) -> 384.075 | AR50: =AR37*(1-AR532) -> 317.56 | AS50: =AS37*(1-AS532) -> 276 | AT50: =AT37*(1-AT532) -> 299.625 | AU50: =AU37*(1-AU532) -> 382.2 | AV50: =AV37*(1-AV532) -> 313.11 | AW50: =AW37*(1-AW532) -> 269.31 | ... BR50: =BR37*(1-BR532) -> 288.31049 | CN50: =SUM(AP50:AS50) -> 1235.485 | CO50: =SUM(AT50:AW50) -> 1264.245 | CP50: =SUM(AX50:BA50) -> 1001.11 | CQ50: =SUM(BB50:BE50) -> 1318.3069 | CR50: =SUM(BF50:BI50) -> 1292.3122 | CS50: =SUM(BJ50:BM50) -> 1306.6909 | CT50: =SUM(BN50:BQ50) -> 1173.313 | CU50: =SUM(BR50:BU50) -> 288.31049 | DP50: =SUM(AR50:AU50) -> 1275.385 | DQ50: =SUM(AV50:AY50) -> 1123.965 | DR50: =SUM(AZ50:BC50) -> 1161.3665
C51: SanDisk | BQ51: =BQ38*(1-BQ533) -> 446.32606 | BR51: =BR38*(1-BR533) -> 907.44875 | CT51: =SUM(BN51:BQ51) -> 446.32606 | CU51: =SUM(BR51:BU51) -> 907.44875
B53: Gross Profit | F53: =F11-F40 -> 25.936 | G53: =G11-G40 -> 67.541 | H53: =H11-H40 -> 63.295 | I53: =I11-I40 -> 50.966 | J53: =J11-J40 -> 56.007 | K53: =K11-K40 -> 70.558 | L53: =L11-L40 -> 81.017714 | M53: =M11-M40 -> 74.018 | ... BR53: =BR11-BR40 -> 1598.918 | CE53: =CE11-CE40 -> 207.738 | CF53: =CF11-CF40 -> 281.60071 | CG53: =CG11-CG40 -> 461.41958 | CH53: =CH11-CH40 -> 461.51604 | CI53: =CI11-CI40 -> 589.78768 | CJ53: =CJ11-CJ40 -> 815.86299 | CK53: =CK11-CK40 -> 899.70639 | CL53: =CL11-CL40 -> 1737.9639 | CM53: =CM11-CM40 -> 1336.8561 | CN53: =SUM(AP53:AS53) -> 2405.2935 | CO53: =SUM(AT53:AW53) -> 1801.9206 | CP53: =SUM(AX53:BA53) -> 3778.0855 | CQ53: =SUM(BB53:BE53) -> 4512.3082 | CR53: =SUM(BF53:BI53) -> 4524.0032 | CS53: =SUM(BJ53:BM53) -> 4411.6938 | CT53: =SUM(BN53:BQ53) -> 3810.0114 | CU53: =SUM(BR53:BU53) -> 1598.918 | DG53: =SUM(H53:K53) -> 240.826 | DH53: =SUM(L53:O53) -> 382.75839 | DI53: =SUM(P53:S53) -> 471.72178 | DJ53: =SUM(T53:W53) -> 486.81624 | DK53: =SUM(X53:AA53) -> 733.03497 | DL53: =SUM(AB53:AE53) -> 882.25946 | DM53: =SUM(AF53:AI53) -> 1263.0297 | DN53: =SUM(AJ53:AM53) -> 1615.4492 | DO53: =SUM(AN53:AQ53) -> 1825.9675 | DP53: =SUM(AR53:AU53) -> 2124.9581 | DQ53: =SUM(AV53:AY53) -> 2069.1803 | DR53: =SUM(AZ53:BC53) -> 4916.5825 | DS53: =SUM(BD53:BG53) -> 4514.9995 | DT53: =SUM(BH53:BK53) -> 4581.5595 | DU53: =SUM(BL53:BO53) -> 3945.2365 | DV53: =SUM(BP53:BS53) -> 3486.8288 | DW53: =SUM(BT53:BW53) -> 0 | DX53: =SUM(BX53:CA53) -> 0 | DZ53: =DZ54*DZ11 -> 1843.5435
C54: Gross Margin | F54: =F53/F11 -> 0.061117055 | G54: =G53/G11 -> 0.12027174 | H54: =H53/H11 -> 0.12368997 | I54: =I53/I11 -> 0.11183303 | J54: =J53/J11 -> 0.12701642 | K54: =K53/K11 -> 0.12278003 | L54: =L53/L11 -> 0.13619473 | M54: =M53/M11 -> 0.13690001 | ... BR54: =BR53/BR11 -> 0.33918498 | CE54: =CE53/CE11 -> 0.10634732 | CF54: =CF53/CF11 -> 0.13090695 | CG54: =CG53/CG11 -> 0.16973324 | CH54: =CH53/CH11 -> 0.15147934 | CI54: =CI53/CI11 -> 0.16208461 | CJ54: =CJ53/CJ11 -> 0.18793217 | CK54: =CK53/CK11 -> 0.16451905 | CL54: =CL53/CL11 -> 0.21524949 | ... CU54: =CU53/CU11 -> 0.083743677 | DL54: =DL53/DL11 -> 0.17982324 | DM54: =DM53/DM11 -> 0.18720344 | DN54: =DN53/DN11 -> 0.20102981 | DO54: =DO53/DO11 -> 0.21875528 | DP54: =DP53/DP11 -> 0.213671 | DQ54: =DQ53/DQ11 -> 0.22144481 | DR54: =DR53/DR11 -> 0.31419878 | DS54: =DS53/DS11 -> 0.2957165 | ... DX54: =DX53/DX11 -> 0 | DZ54: =CU54+1% -> 0.093743677
C55: Other - Media | AP55: =AP28-AP41 -> 11.286101 | AQ55: =AQ28-AQ41 -> 11.345124 | AR55: =AR28-AR41 -> 8.628732 | AS55: =AS28-AS41 -> 10.64239 | AT55: =AT28-AT41 -> 20.980729 | AU55: =AU28-AU41 -> 3.67776 | AV55: =AV28-AV41 -> 1.9528182 | AW55: =AW28-AW41 -> 6.5949991 | ... BR55: =BR28-BR41 -> 105.1758 | CN55: =SUM(AP55:AS55) -> 41.902346 | CO55: =SUM(AT55:AW55) -> 33.206306 | CP55: =SUM(AX55:BA55) -> 66.924658 | CQ55: =SUM(BB55:BE55) -> 162.05782 | CR55: =SUM(BF55:BI55) -> 267.28227 | CS55: =SUM(BJ55:BM55) -> 389.24048 | CT55: =SUM(BN55:BQ55) -> 474.89412 | CU55: =SUM(BR55:BU55) -> 105.1758 | DP55: =SUM(AR55:AU55) -> 43.929611 | DQ55: =SUM(AV55:AY55) -> 25.044052 | DR55: =SUM(AZ55:BC55) -> 144.08303 | DS55: =SUM(BD55:BG55) -> 200.07876 | DT55: =SUM(BH55:BK55) -> 313.38184 | DU55: =SUM(BL55:BO55) -> 474.23408 | DV55: =SUM(BP55:BS55) -> 317.30121 | DW55: =SUM(BT55:BW55) -> 0 | DX55: =SUM(BX55:CA55) -> 0
C56: Enterprise | AP56: =AP29-AP42 -> 62.0868 | AQ56: =AQ29-AQ42 -> 84.5215 | AR56: =AR29-AR42 -> 89.528 | AS56: =AS29-AS42 -> 84.17448 | AT56: =AT29-AT42 -> 79.135875 | AU56: =AU29-AU42 -> 76.2285 | AV56: =AV29-AV42 -> 70.926628 | AW56: =AW29-AW42 -> 77.456793 | ... BR56: =BR29-BR42 -> 331.23606 | CN56: =SUM(AP56:AS56) -> 320.31078 | CO56: =SUM(AT56:AW56) -> 303.7478 | CP56: =SUM(AX56:BA56) -> 959.59457 | CQ56: =SUM(BB56:BE56) -> 1598.0087 | CR56: =SUM(BF56:BI56) -> 1592.2789 | CS56: =SUM(BJ56:BM56) -> 1605.6872 | CT56: =SUM(BN56:BQ56) -> 1290.9091 | CU56: =SUM(BR56:BU56) -> 331.23606 | DP56: =SUM(AR56:AU56) -> 329.06685 | DQ56: =SUM(AV56:AY56) -> 337.88659 | DR56: =SUM(AZ56:BC56) -> 1522.5973 | DS56: =SUM(BD56:BG56) -> 1696.4966 | DT56: =SUM(BH56:BK56) -> 1573.9242 | DU56: =SUM(BL56:BO56) -> 1473.4149 | DV56: =SUM(BP56:BS56) -> 921.77826 | DW56: =SUM(BT56:BW56) -> 0 | DX56: =SUM(BX56:CA56) -> 0
D57: Performance | AP57: =AP30-AP43 -> 0 | AQ57: =AQ30-AQ43 -> 0 | AR57: =AR30-AR43 -> 0 | AS57: =AS30-AS43 -> 0 | AT57: =AT30-AT43 -> 0 | AU57: =AU30-AU43 -> 0 | AV57: =AV30-AV43 -> 0 | AW57: =AW30-AW43 -> 0 | ... BR57: =BR30-BR43 -> 129.45272 | CN57: =SUM(AP57:AS57) -> 0 | CO57: =SUM(AT57:AW57) -> 0 | CP57: =SUM(AX57:BA57) -> 328.042 | CQ57: =SUM(BB57:BE57) -> 873.67667 | CR57: =SUM(BF57:BI57) -> 832.53791 | CS57: =SUM(BJ57:BM57) -> 823.00003 | CT57: =SUM(BN57:BQ57) -> 597.07793 | CU57: =SUM(BR57:BU57) -> 129.45272 | DP57: =SUM(AR57:AU57) -> 0 | DQ57: =SUM(AV57:AY57) -> 0 | DR57: =SUM(AZ57:BC57) -> 759.88629 | DS57: =SUM(BD57:BG57) -> 887.40577 | DT57: =SUM(BH57:BK57) -> 803.82207 | DU57: =SUM(BL57:BO57) -> 750.47691 | DV57: =SUM(BP57:BS57) -> 382.19623 | DW57: =SUM(BT57:BW57) -> 0 | DX57: =SUM(BX57:CA57) -> 0
D58: Capacity | AP58: =AP31-AP44 -> 62.0868 | AQ58: =AQ31-AQ44 -> 84.5215 | AR58: =AR31-AR44 -> 89.528 | AS58: =AS31-AS44 -> 84.17448 | AT58: =AT31-AT44 -> 79.135875 | AU58: =AU31-AU44 -> 76.2285 | AV58: =AV31-AV44 -> 70.926628 | AW58: =AW31-AW44 -> 77.456793 | ... BR58: =BR31-BR44 -> 201.78334 | CN58: =SUM(AP58:AS58) -> 320.31078 | CO58: =SUM(AT58:AW58) -> 303.7478 | CP58: =SUM(AX58:BA58) -> 631.55257 | CQ58: =SUM(BB58:BE58) -> 724.33199 | CR58: =SUM(BF58:BI58) -> 759.74095 | CS58: =SUM(BJ58:BM58) -> 782.68712 | CT58: =SUM(BN58:BQ58) -> 693.83119 | CU58: =SUM(BR58:BU58) -> 201.78334 | DP58: =SUM(AR58:AU58) -> 329.06685 | DQ58: =SUM(AV58:AY58) -> 337.88659 | DR58: =SUM(AZ58:BC58) -> 762.71101 | DS58: =SUM(BD58:BG58) -> 809.09079 | DT58: =SUM(BH58:BK58) -> 770.10218 | DU58: =SUM(BL58:BO58) -> 722.93798 | DV58: =SUM(BP58:BS58) -> 539.58203 | DW58: =SUM(BT58:BW58) -> 0 | DX58: =SUM(BX58:CA58) -> 0
C59: Compute | AP59: =AP32-AP45 -> 291.68835 | AQ59: =AQ32-AQ45 -> 366.97173 | AR59: =AR32-AR45 -> 373.92508 | AS59: =AS32-AS45 -> 276.89227 | AT59: =AT32-AT45 -> 193.97497 | AU59: =AU32-AU45 -> 205.38778 | AV59: =AV32-AV45 -> 185.39316 | AW59: =AW32-AW45 -> 235.37702 | ... BR59: =BR32-BR45 -> 239.86899 | CN59: =SUM(AP59:AS59) -> 1309.4774 | CO59: =SUM(AT59:AW59) -> 820.13294 | CP59: =SUM(AX59:BA59) -> 2021.2034 | CQ59: =SUM(BB59:BE59) -> 1782.5494 | CR59: =SUM(BF59:BI59) -> 1607.051 | CS59: =SUM(BJ59:BM59) -> 1361.6843 | CT59: =SUM(BN59:BQ59) -> 817.24015 | CU59: =SUM(BR59:BU59) -> 239.86899 | DP59: =SUM(AR59:AU59) -> 1050.1801 | DQ59: =SUM(AV59:AY59) -> 1050.5437 | DR59: =SUM(AZ59:BC59) -> 2342.7345 | DS59: =SUM(BD59:BG59) -> 1643.1512 | DT59: =SUM(BH59:BK59) -> 1584.6774 | DU59: =SUM(BL59:BO59) -> 1037.7167 | DV59: =SUM(BP59:BS59) -> 591.54396 | DW59: =SUM(BT59:BW59) -> 0 | DX59: =SUM(BX59:CA59) -> 0
D60: Mobile | AP60: =AP33-AP46 -> 136.28989 | AQ60: =AQ33-AQ46 -> 173.62565 | AR60: =AR33-AR46 -> 162.86688 | AS60: =AS33-AS46 -> 123.36868 | AT60: =AT33-AT46 -> 83.428188 | AU60: =AU33-AU46 -> 92.097038 | AV60: =AV33-AV46 -> 81.234593 | AW60: =AW33-AW46 -> 99.717873 | ... BR60: =BR33-BR46 -> 149.22708 | CN60: =SUM(AP60:AS60) -> 596.1511 | CO60: =SUM(AT60:AW60) -> 356.47769 | CP60: =SUM(AX60:BA60) -> 1078.3379 | CQ60: =SUM(BB60:BE60) -> 990.43736 | CR60: =SUM(BF60:BI60) -> 874.82562 | CS60: =SUM(BJ60:BM60) -> 753.98151 | CT60: =SUM(BN60:BQ60) -> 452.88882 | CU60: =SUM(BR60:BU60) -> 149.22708 | DP60: =SUM(AR60:AU60) -> 461.76079 | DQ60: =SUM(AV60:AY60) -> 476.32863 | DR60: =SUM(AZ60:BC60) -> 1319.4924 | DS60: =SUM(BD60:BG60) -> 893.61111 | DT60: =SUM(BH60:BK60) -> 871.17452 | DU60: =SUM(BL60:BO60) -> 572.51632 | DV60: =SUM(BP60:BS60) -> 347.5278 | DW60: =SUM(BT60:BW60) -> 0 | DX60: =SUM(BX60:CA60) -> 0
D61: Desktop | AP61: =AP34-AP47 -> 155.39846 | AQ61: =AQ34-AQ47 -> 193.34608 | AR61: =AR34-AR47 -> 211.0582 | AS61: =AS34-AS47 -> 153.52358 | AT61: =AT34-AT47 -> 110.54679 | AU61: =AU34-AU47 -> 113.29075 | AV61: =AV34-AV47 -> 104.15856 | AW61: =AW34-AW47 -> 135.65915 | ... BR61: =BR34-BR47 -> 90.641908 | CN61: =SUM(AP61:AS61) -> 713.32633 | CO61: =SUM(AT61:AW61) -> 463.65524 | CP61: =SUM(AX61:BA61) -> 942.8655 | CQ61: =SUM(BB61:BE61) -> 792.11209 | CR61: =SUM(BF61:BI61) -> 732.22538 | CS61: =SUM(BJ61:BM61) -> 607.70277 | CT61: =SUM(BN61:BQ61) -> 364.35133 | CU61: =SUM(BR61:BU61) -> 90.641908 | DP61: =SUM(AR61:AU61) -> 588.41932 | DQ61: =SUM(AV61:AY61) -> 574.21508 | DR61: =SUM(AZ61:BC61) -> 1023.2421 | DS61: =SUM(BD61:BG61) -> 749.54008 | DT61: =SUM(BH61:BK61) -> 713.50288 | DU61: =SUM(BL61:BO61) -> 465.20035 | DV61: =SUM(BP61:BS61) -> 244.01616 | DW61: =SUM(BT61:BW61) -> 0 | DX61: =SUM(BX61:CA61) -> 0
C62: Non-Compute | AP62: =AP35-AP48 -> 149.8876 | AQ62: =AQ35-AQ48 -> 225.10172 | AR62: =AR35-AR48 -> 193.75744 | AS62: =AS35-AS48 -> 164.8562 | AT62: =AT35-AT48 -> 152.87975 | AU62: =AU35-AU48 -> 190.28812 | AV62: =AV35-AV48 -> 151.78052 | AW62: =AW35-AW48 -> 149.88512 | ... BR62: =BR35-BR48 -> 283.2136 | CN62: =SUM(AP62:AS62) -> 733.60296 | CO62: =SUM(AT62:AW62) -> 644.83351 | CP62: =SUM(AX62:BA62) -> 730.36292 | CQ62: =SUM(BB62:BE62) -> 969.69229 | CR62: =SUM(BF62:BI62) -> 1057.391 | CS62: =SUM(BJ62:BM62) -> 1055.0819 | CT62: =SUM(BN62:BQ62) -> 931.88663 | CU62: =SUM(BR62:BU62) -> 283.2136 | DP62: =SUM(AR62:AU62) -> 701.78151 | DQ62: =SUM(AV62:AY62) -> 655.70598 | DR62: =SUM(AZ62:BC62) -> 907.16768 | DS62: =SUM(BD62:BG62) -> 975.27303 | DT62: =SUM(BH62:BK62) -> 1109.576 | DU62: =SUM(BL62:BO62) -> 959.87084 | DV62: =SUM(BP62:BS62) -> 721.70046 | DW62: =SUM(BT62:BW62) -> 0 | DX62: =SUM(BX62:CA62) -> 0
D63: Consumer Electronics | AP63: =AP36-AP49 -> 25.7376 | AQ63: =AQ36-AQ49 -> 40.17672 | AR63: =AR36-AR49 -> 44.317435 | AS63: =AS36-AS49 -> 40.8562 | AT63: =AT36-AT49 -> 27.50475 | AU63: =AU36-AU49 -> 26.488125 | AV63: =AV36-AV49 -> 23.890519 | AW63: =AW36-AW49 -> 37.19512 | ... BR63: =BR36-BR49 -> 134.69002 | CN63: =SUM(AP63:AS63) -> 151.08795 | CO63: =SUM(AT63:AW63) -> 115.07851 | CP63: =SUM(AX63:BA63) -> 189.6037 | CQ63: =SUM(BB63:BE63) -> 286.28503 | CR63: =SUM(BF63:BI63) -> 385.00348 | CS63: =SUM(BJ63:BM63) -> 388.27422 | CT63: =SUM(BN63:BQ63) -> 353.98621 | CU63: =SUM(BR63:BU63) -> 134.69002 | DP63: =SUM(AR63:AU63) -> 139.16651 | DQ63: =SUM(AV63:AY63) -> 139.67098 | DR63: =SUM(AZ63:BC63) -> 272.93696 | DS63: =SUM(BD63:BG63) -> 307.30585 | DT63: =SUM(BH63:BK63) -> 420.14645 | DU63: =SUM(BL63:BO63) -> 353.26697 | DV63: =SUM(BP63:BS63) -> 305.60109 | DW63: =SUM(BT63:BW63) -> 0 | DX63: =SUM(BX63:CA63) -> 0
D64: Branded | AP64: =AP37-AP50 -> 124.15 | AQ64: =AQ37-AQ50 -> 184.925 | AR64: =AR37-AR50 -> 149.44 | AS64: =AS37-AS50 -> 124 | AT64: =AT37-AT50 -> 125.375 | AU64: =AU37-AU50 -> 163.8 | AV64: =AV37-AV50 -> 127.89 | AW64: =AW37-AW50 -> 112.69 | ... BR64: =BR37-BR50 -> 148.52359 | CN64: =SUM(AP64:AS64) -> 582.515 | CO64: =SUM(AT64:AW64) -> 529.755 | CP64: =SUM(AX64:BA64) -> 540.75921 | CQ64: =SUM(BB64:BE64) -> 683.40725 | CR64: =SUM(BF64:BI64) -> 672.38756 | CS64: =SUM(BJ64:BM64) -> 666.80765 | CT64: =SUM(BN64:BQ64) -> 577.90043 | CU64: =SUM(BR64:BU64) -> 148.52359 | DP64: =SUM(AR64:AU64) -> 562.615 | DQ64: =SUM(AV64:AY64) -> 516.035 | DR64: =SUM(AZ64:BC64) -> 634.23072 | DS64: =SUM(BD64:BG64) -> 667.96718 | DT64: =SUM(BH64:BK64) -> 689.42955 | DU64: =SUM(BL64:BO64) -> 606.60387 | DV64: =SUM(BP64:BS64) -> 416.09937 | DW64: =SUM(BT64:BW64) -> 0 | DX64: =SUM(BX64:CA64) -> 0
C65: SanDisk | BQ65: =BQ38-BQ51 -> 295.08135 | BR65: =BR38-BR51 -> 639.42356 | CT65: =SUM(BN65:BQ65) -> 295.08135 | CU65: =SUM(BR65:BU65) -> 639.42356
B67: Operating Expenses | F67: =SUM(F68:F69) -> 61.524 | G67: =SUM(G68:G69) -> 65.542 | H67: =SUM(H68:H69) -> 62.31 | I67: =SUM(I68:I69) -> 39.838 | J67: =SUM(J68:J69) -> 56.213 | K67: =SUM(K68:K69) -> 57.706 | L67: =SUM(L68:L69) -> 62.966 | M67: =SUM(M68:M69) -> 56.789 | ... CC67: =SUM(CC68:CC69) -> 719.32615 | CE67: =SUM(CE68:CE69) -> 229.214 | CF67: =SUM(CF68:CF69) -> 233.674 | CG67: =SUM(CG68:CG69) -> 256.1 | CH67: =SUM(CH68:CH69) -> 306.6 | CI67: =SUM(CI68:CI69) -> 373.9 | CJ67: =SUM(CJ68:CJ69) -> 462 | CK67: =SUM(CK68:CK69) -> 485 | CL67: =SUM(CL68:CL69) -> 683 | ... DC67: =SUM(DC68:DC69) -> 3800.873 | DG67: =SUM(H67:K67) -> 216.067 | DH67: =SUM(L67:O67) -> 246.151 | DI67: =SUM(P67:S67) -> 291.504 | DJ67: =SUM(T67:W67) -> 320.3 | DK67: =SUM(X67:AA67) -> 432.8 | DL67: =SUM(AB67:AE67) -> 479.6 | DM67: =SUM(AF67:AI67) -> 553 | DN67: =SUM(AJ67:AM67) -> 736 | DO67: =SUM(AN67:AQ67) -> 767 | DP67: =SUM(AR67:AU67) -> 900 | DQ67: =SUM(AV67:AY67) -> 1038 | DR67: =SUM(AZ67:BC67) -> 2048 | DS67: =SUM(BD67:BG67) -> 2313 | DT67: =SUM(BH67:BK67) -> 2378 | DU67: =SUM(BL67:BO67) -> 2140 | DV67: =SUM(BP67:BS67) -> 2750 | DW67: =SUM(BT67:BW67) -> 3307 | DX67: =SUM(BX67:CA67) -> 3269.7154 | DZ67: =(CU67/CU11)*DZ11 -> 3381.49
C68: Product development | F68: 32.001 | G68: 33.617 | H68: 32.085 | I68: =113.382-SUM(F68:H68) -> 15.679 | J68: 28.845 | K68: 29.212 | L68: 33.206 | M68: 30.628 | N68: 31.914 | O68: 34.41 | P68: 34.726 | Q68: =134.7-SUM(N68:P68) -> 33.65 | R68: =63.7 -> 63.7 | S68: 44 | T68: 46.5 | U68: 46.8 | V68: 54 | W68: 59.7 | X68: 60.7 | Y68: 64.1 | Z68: 70 | AA68: 76.2 | AB68: 78.7 | AC68: 71.6 | AD68: 75 | AE68: 77 | AF68: 75 | AG68: 79 | AH68: 91 | AI68: 122 | AJ68: 123 | AK68: 128 | AL68: 133 | AM68: =119+16 -> 135 | AN68: =125 -> 125 | AO68: 132 | AP68: 142 | AQ68: 154 | AR68: 160 | AS68: 154 | AT68: 167 | AU68: 169 | AV68: =179 -> 179 | AW68: 188 | AX68: 193 | AY68: =191 -> 191 | AZ68: 265 | BA68: 406 | BB68: =396 -> 396 | BC68: =378 -> 378 | BD68: =396 -> 396 | BE68: =402 -> 402 | BF68: =401 -> 401 | BG68: =421 -> 421 | BH68: =426-8 -> 418 | BI68: =429 -> 429 | BJ68: =437 -> 437 | BK68: 426 | BL68: 402 | BM68: 381 | BN68: 385 | BO68: 389 | BP68: 359 | BQ68: 494 | BR68: 639 | BS68: 585 | BT68: 613 | BU68: 604 | BV68: 592 | BW68: 629 | BX68: =BX540 -> 598.91004 | BY68: =BY540 -> 594.59657 | BZ68: =BZ540 -> 583.1088 | CA68: =CA540 -> 573.86236 | CB68: =CB540 -> 579.23682 | CC68: =CC540 -> 526.33621 | CE68: =SUM(F68:I68) -> 113.382 | CF68: =SUM(J68:M68) -> 121.891 | CG68: =SUM(N68:Q68) -> 134.7 | CH68: =SUM(R68:U68) -> 201 | CI68: =SUM(V68:Y68) -> 238.5 | CJ68: =SUM(Z68:AC68) -> 296.5 | CK68: =SUM(AD68:AG68) -> 306 | CL68: =SUM(AH68:AK68) -> 464 | CM68: =SUM(AL68:AO68) -> 525 | CN68: =SUM(AP68:AS68) -> 610 | CO68: =SUM(AT68:AW68) -> 703 | CP68: =SUM(AX68:BA68) -> 1055 | CQ68: =SUM(BB68:BE68) -> 1572 | CR68: =SUM(BF68:BI68) -> 1669 | CS68: =SUM(BJ68:BM68) -> 1646 | CT68: =SUM(BN68:BQ68) -> 1627 | CU68: =SUM(BR68:BU68) -> 2441 | CV68: =SUM(BV68:BY68) -> 2414.5066 | CW68: =SUM(BZ68:CC68) -> 2262.5442 | CX68: =CX540 -> 2354.2899 | CY68: =CY540 -> 2482.0668 | CZ68: =CZ540 -> 2532.4998 | DA68: =DA540 -> 2603.79 | DB68: =DB540 -> 2686.1047 | DC68: =DC540 -> 2780.5044 | DL68: =SUM(AB68:AE68) -> 302.3 | DM68: =SUM(AF68:AI68) -> 367 | DN68: =SUM(AJ68:AM68) -> 519 | DO68: =SUM(AN68:AQ68) -> 553 | DP68: =SUM(AR68:AU68) -> 650 | DQ68: =SUM(AV68:AY68) -> 751 | DR68: =SUM(AZ68:BC68) -> 1445 | DS68: =SUM(BD68:BG68) -> 1620 | DT68: =SUM(BH68:BK68) -> 1710 | DU68: =SUM(BL68:BO68) -> 1557 | DV68: =SUM(BP68:BS68) -> 2077 | DW68: =SUM(BT68:BW68) -> 2438 | DX68: =SUM(BX68:CA68) -> 2350.4778
C69: SG&A | F69: 29.523 | G69: 31.925 | H69: 30.225 | I69: =115.832-SUM(F69:H69) -> 24.159 | J69: 27.368 | K69: 28.494 | L69: 29.76 | M69: 26.161 | N69: 26.444 | O69: 33.628 | P69: 30.205 | Q69: =121.4-SUM(N69:P69) -> 31.123 | R69: 27.6 | S69: 26.5 | T69: 27.2 | U69: 24.3 | V69: 27.9 | W69: 33.9 | X69: 35.6 | Y69: =57-19 -> 38 | Z69: 40.4 | AA69: 47.8 | AB69: 38.5 | AC69: 38.8 | AD69: 44 | AE69: 56 | AF69: 32 | AG69: 47 | AH69: 48 | AI69: 59 | AJ69: 56 | AK69: 56 | AL69: 57 | AM69: =42+6 -> 48 | AN69: =49 -> 49 | AO69: 52 | AP69: 53 | AQ69: 60 | AR69: 64 | AS69: =88-27 -> 61 | AT69: 59 | AU69: 66 | AV69: =73-10 -> 63 | AW69: =109-35 -> 74 | AX69: =89-21 -> 68 | AY69: =96-14 -> 82 | AZ69: =155-34-3 -> 118 | BA69: =178-12 -> 166 | BB69: =179-11 -> 168 | BC69: =162-11 -> 151 | BD69: =185-11-11 -> 163 | BE69: =180-11-7 -> 162 | BF69: =132+65-11-13 -> 173 | BG69: =229-11-11-12 -> 195 | BH69: =202-40+13+8 -> 183 | BI69: =202-8-25 -> 169 | BJ69: =220-7-35-15 -> 163 | BK69: =164+37-7-35-6 -> 153 | BL69: =199-7-3-33+6 -> 162 | BM69: =190-8-38+2 -> 146 | BN69: =192-8-2-36 -> 146 | BO69: =207-8-15-27-31+3 -> 129 | BP69: =166-6-24-16-32+2 -> 90 | BQ69: =400-73-30-116+26-60 -> 147 | BR69: =396-40-86-10-33-3 -> 224 | BS69: =358-39-85-5-15-2 -> 212 | BT69: =346-40-85-2-22+1 -> 198 | BU69: =345-40-77-16-4 -> 208 | BV69: =364-40-84-4-9-0 -> 227 | BW69: =381-41-6-12-86 -> 236 | BX69: =BX541 -> 245.45493 | BY69: =BY541 -> 226.04498 | BZ69: =BZ541 -> 228.17301 | CA69: =CA541 -> 219.56473 | CB69: =CB541 -> 213.15915 | CC69: =CC541 -> 192.98994 | CE69: =SUM(F69:I69) -> 115.832 | CF69: =SUM(J69:M69) -> 111.783 | CG69: =SUM(N69:Q69) -> 121.4 | CH69: =SUM(R69:U69) -> 105.6 | CI69: =SUM(V69:Y69) -> 135.4 | CJ69: =SUM(Z69:AC69) -> 165.5 | CK69: =SUM(AD69:AG69) -> 179 | CL69: =SUM(AH69:AK69) -> 219 | CM69: =SUM(AL69:AO69) -> 206 | CN69: =SUM(AP69:AS69) -> 238 | CO69: =SUM(AT69:AW69) -> 262 | CP69: =SUM(AX69:BA69) -> 434 | CQ69: =SUM(BB69:BE69) -> 644 | CR69: =SUM(BF69:BI69) -> 720 | CS69: =SUM(BJ69:BM69) -> 624 | CT69: =SUM(BN69:BQ69) -> 512 | CU69: =SUM(BR69:BU69) -> 842 | CV69: =SUM(BV69:BY69) -> 934.49991 | CW69: =SUM(BZ69:CC69) -> 853.88683 | CX69: =CX541 -> 921.24389 | CY69: =CY541 -> 890.99833 | CZ69: =CZ541 -> 902.89125 | DA69: =DA541 -> 921.69559 | DB69: =DB541 -> 967.96564 | DC69: =DC541 -> 1020.3686 | DL69: =SUM(AB69:AE69) -> 177.3 | DM69: =SUM(AF69:AI69) -> 186 | DN69: =SUM(AJ69:AM69) -> 217 | DO69: =SUM(AN69:AQ69) -> 214 | DP69: =SUM(AR69:AU69) -> 250 | DQ69: =SUM(AV69:AY69) -> 287 | DR69: =SUM(AZ69:BC69) -> 603 | DS69: =SUM(BD69:BG69) -> 693 | DT69: =SUM(BH69:BK69) -> 668 | DU69: =SUM(BL69:BO69) -> 583 | DV69: =SUM(BP69:BS69) -> 673 | DW69: =SUM(BT69:BW69) -> 869 | DX69: =SUM(BX69:CA69) -> 919.23765
B71: Income from Operations (PTOP) | F71: =F53-F67 -> -35.588 | G71: =G53-G67 -> 1.999 | H71: =H53-H67 -> 0.985 | I71: =I53-I67 -> 11.128 | J71: =J53-J67 -> -0.206 | K71: =K53-K67 -> 12.852 | L71: =L53-L67 -> 18.051714 | M71: =M53-M67 -> 17.229 | ... BA71: =BA53-BA67 -> 939.10029 | BB71: =BB21-BB67 -> 666.9 | BC71: =BC21-BC67 -> 568.0555 | BD71: =BD21-BD67 -> 539.72 | BE71: =BE21-BE67 -> 521.238 | BF71: =BF21-BF67 -> 561.0702 | BG71: =BG21-BG67 -> 579.824 | BH71: =BH21-BH67 -> 514.008 | BI71: =BI21-BI67 -> 480.31 | ... CC71: =CC21-CC67 -> 834.03242 | CE71: =CE53-CE67 -> -21.476 | CF71: =CF53-CF67 -> 47.926714 | CG71: =CG53-CG67 -> 205.31958 | CH71: =CH53-CH67 -> 154.91604 | CI71: =CI53-CI67 -> 215.88768 | CJ71: =CJ53-CJ67 -> 353.86299 | CK71: =CK53-CK67 -> 414.70639 | CL71: =CL53-CL67 -> 1054.9639 | ... CP71: =CP53-CP67 -> 2289.0855 | CQ71: =CQ21-CQ67 -> 2295.9135 | CR71: =CR21-CR67 -> 2135.2122 | CS71: =CS21-CS67 -> 2140.9765 | CT71: =CT21-CT67 -> 1671.4275 | CU71: =CU21-CU67 -> 3931.562 | CV71: =CV21-CV67 -> 5183.7354 | CW71: =CW21-CW67 -> 3942.4998 | CX71: =CX21-CX67 -> 4225.3042 | ... DC71: =DC21-DC67 -> 5062.4234 | DG71: =SUM(H71:K71) -> 24.759 | DH71: =SUM(L71:O71) -> 136.60739 | DI71: =SUM(P71:S71) -> 180.21778 | DJ71: =SUM(T71:W71) -> 166.51624 | DK71: =SUM(X71:AA71) -> 300.23497 | DL71: =SUM(AB71:AE71) -> 402.65946 | DM71: =SUM(AF71:AI71) -> 710.02973 | DN71: =SUM(AJ71:AM71) -> 879.44925 | DO71: =SUM(AN71:AQ71) -> 1058.9675 | DP71: =SUM(AR71:AU71) -> 1224.9581 | DQ71: =SUM(AV71:AY71) -> 1031.1803 | DR71: =SUM(AZ71:BC71) -> 2868.2278 | DS71: =SUM(BD71:BG71) -> 2201.8522 | DT71: =SUM(BH71:BK71) -> 2203.416 | DU71: =SUM(BL71:BO71) -> 1805.316 | DV71: =SUM(BP71:BS71) -> 2528.399 | DW71: =SUM(BT71:BW71) -> 5015.378 | DX71: =SUM(BX71:CA71) -> 4589.7057 | DZ71: =DZ53-DZ67 -> -1537.9465
C72: PTOP Margin | F72: =F71/F11 -> -0.083861572 | G72: =G71/G11 -> 0.0035596631 | H72: =H71/H11 -> 0.0019248695 | I72: =I71/I11 -> 0.024417806 | J72: =J71/J11 -> -0.00046718057 | K72: =K71/K11 -> 0.022364139 | L72: =L71/L11 -> 0.030345813 | M72: =M71/M11 -> 0.0318659 | ... CC72: =CC71/CC11 -> 0.19015202 | CE72: =CE71/CE11 -> -0.010994209 | CF72: =CF71/CF11 -> 0.02227956 | CG72: =CG71/CG11 -> 0.07552683 | CH72: =CH71/CH11 -> 0.050846725 | CI72: =CI71/CI11 -> 0.059329944 | CJ72: =CJ71/CJ11 -> 0.081511531 | CK72: =CK71/CK11 -> 0.075832631 | CL72: =CL71/CL11 -> 0.13065889 | ... DC72: =DC71/DC11 -> 0.19845469 | DG72: =DG71/DG11 -> 0.012485193 | DH72: =DH71/DH11 -> 0.055352883 | DI72: =DI71/DI11 -> 0.06140001 | DJ72: =DJ71/DJ11 -> 0.050826248 | DK72: =DK71/DK11 -> 0.075299042 | DL72: =DL71/DL11 -> 0.08207056 | DM72: =DM71/DM11 -> 0.10523902 | DN72: =DN71/DN11 -> 0.10944046 | ... DX72: =DX71/DX11 -> 0.23082709 | DZ72: =DZ71/DZ11 -> -0.078204158
DM73: =SUM(AF73:AI73) -> 0 | DN73: =SUM(AJ73:AM73) -> 0 | DO73: =SUM(AN73:AQ73) -> 0 | DP73: =SUM(AR73:AU73) -> 0
B74: Total Interest Income (expense), net | F74: =F75+F76 -> -1.632 | G74: =G75+G76 -> 0.839 | H74: =H75+H76 -> 0.052 | I74: =I75+I76 -> -52.454 | J74: =J75+J76 -> -0.351 | K74: =K75+K76 -> 2.593 | L74: =L75+L76 -> -0.492 | M74: =M75+M76 -> -0.537 | ... BU74: =BU75+BU76 -> -197 | BV74: =-195-5 -> -200 | BW74: =-181-1+2 -> -180 | BX74: =BX75+BX76 -> -180.63025 | BY74: =BY75+BY76 -> -174.19729 | BZ74: =BZ75+BZ76 -> -141.39158 | CA74: =CA75+CA76 -> -138.04809 | CB74: =CB75+CB76 -> -134.62761 | CC74: =CC75+CC76 -> -131.5053 | CE74: =CE75+CE76 -> -53.195 | CF74: =CF75+CF76 -> 1.213 | CG74: =CG75+CG76 -> -2.165 | CH74: =CH75+CH76 -> 0.3 | CI74: =CI75+CI76 -> 5.4 | CJ74: =CJ75+CJ76 -> 15.8 | CK74: =CK75+CK76 -> 36 | CL74: =CL75+CL76 -> -25 | ... DC74: =DC75+DC76 -> -192.99385 | DL74: =SUM(AB74:AE74) -> 27.5 | DM74: =SUM(AF74:AI74) -> 6 | DN74: =SUM(AJ74:AM74) -> -25 | DO74: =SUM(AN74:AQ74) -> -9 | DP74: =SUM(AR74:AU74) -> -2.8 | DQ74: =SUM(AV74:AY74) -> -3 | DR74: =SUM(AZ74:BC74) -> -35 | DS74: =SUM(BD74:BG74) -> -41 | DT74: =SUM(BH74:BK74) -> -35 | DU74: =SUM(BL74:BO74) -> -32 | DV74: =SUM(BP74:BS74) -> -665 | DW74: =SUM(BT74:BW74) -> -783 | DX74: =SUM(BX74:CA74) -> -634.26721 | DZ74: =CU74 -> -851
C75: Interest and Other Income | AD75: 7 | AE75: 8 | AF75: 8 | AG75: 9 | AH75: 9 | AI75: 8 | AJ75: 6 | AK75: 4 | AL75: 4 | AM75: 2 | AN75: 1 | AO75: =9-SUM(AL75:AN75) -> 2 | AP75: 1 | AQ75: 1 | AR75: 1 | AS75: 0.6 | AT75: 2 | AU75: 2 | AV75: 2 | AW75: =9-SUM(AT75:AV75) -> 3 | AX75: 3 | AY75: 3 | AZ75: 3 | BA75: =12-SUM(AX75:AZ75) -> 3 | BB75: 2 | BC75: 3 | BD75: 3 | BE75: =11-SUM(BB75:BD75) -> 3 | BF75: 3 | BG75: 3 | BH75: 4 | BI75: =17-SUM(BF75:BH75) -> 7 | BJ75: 3 | BK75: 4 | BL75: 3 | BM75: =15-SUM(BJ75:BL75) -> 5 | BN75: 5 | BO75: =5+1 -> 6 | BP75: 6 | BQ75: =26-SUM(BN75:BP75) -> 9 | BR75: 5 | BS75: 5 | BT75: 7 | BU75: =26-SUM(BR75:BT75) -> 9 | BV75: 5 | BW75: 3 | BX75: =BX545 -> 3.1475 | BY75: =BY545 -> 2.8177142 | BZ75: =BZ545 -> 2.9959191 | CA75: =CA545 -> 3.2144077 | CB75: =CB545 -> 3.5098919 | CC75: =CC545 -> 3.5071992 | CE75: =SUM(F75:I75) -> 0 | CF75: =SUM(J75:M75) -> 0 | CG75: =SUM(N75:Q75) -> 0 | CH75: =SUM(R75:U75) -> 0 | CI75: =SUM(V75:Y75) -> 0 | CJ75: =SUM(Z75:AC75) -> 0 | CK75: =SUM(AD75:AG75) -> 32 | CL75: =SUM(AH75:AK75) -> 27 | CM75: =SUM(AL75:AO75) -> 9 | CN75: =SUM(AP75:AS75) -> 3.6 | CO75: =SUM(AT75:AW75) -> 9 | CP75: =SUM(AX75:BA75) -> 12 | CQ75: =SUM(BB75:BE75) -> 11 | CR75: =SUM(BF75:BI75) -> 17 | CS75: =SUM(BJ75:BM75) -> 15 | CT75: =SUM(BN75:BQ75) -> 26 | CU75: =SUM(BR75:BU75) -> 26 | CV75: =SUM(BV75:BY75) -> 13.965214 | CW75: =SUM(BZ75:CC75) -> 13.227418 | CX75: =CX545 -> 17.328829 | CY75: =CY545 -> 20.739888 | CZ75: =CZ545 -> 23.853684 | DA75: =DA545 -> 27.451979 | DB75: =DB545 -> 30.651726 | DC75: =DC545 -> 34.556147 | DL75: =SUM(AB75:AE75) -> 15 | DM75: =SUM(AF75:AI75) -> 34 | DN75: =SUM(AJ75:AM75) -> 16 | DO75: =SUM(AN75:AQ75) -> 5 | DP75: =SUM(AR75:AU75) -> 5.6 | DQ75: =SUM(AV75:AY75) -> 11 | DR75: =SUM(AZ75:BC75) -> 11 | DS75: =SUM(BD75:BG75) -> 12 | DT75: =SUM(BH75:BK75) -> 18 | DU75: =SUM(BL75:BO75) -> 19 | DV75: =SUM(BP75:BS75) -> 25 | DW75: =SUM(BT75:BW75) -> 24 | DX75: =SUM(BX75:CA75) -> 12.175541
C76: Interest and Other Expense | F76: -1.632 | G76: 0.839 | H76: 0.052 | I76: -52.454 | J76: -0.351 | K76: 2.593 | L76: -0.492 | M76: -0.537 | N76: -1.269 | O76: -0.78 | P76: -0.316 | Q76: 0.2 | R76: =0.3 -> 0.3 | S76: 0 | T76: 0.1 | U76: -0.1 | V76: 0 | W76: 0.8 | X76: 1.9 | Y76: 2.7 | Z76: 2.5 | AA76: 2.8 | AB76: 4.8 | AC76: 5.7 | AD76: 0 | AE76: 2 | AF76: 1 | AG76: 1 | AH76: -6 | AI76: -24 | AJ76: -14 | AK76: -8 | AL76: -8 | AM76: -11 | AN76: -4 | AO76: =-27-SUM(AL76:AN76) -> -4 | AP76: -3 | AQ76: -3 | AR76: -2 | AS76: -1.4 | AT76: -2 | AU76: -3 | AV76: -1 | AW76: =-10-SUM(AT76:AV76) -> -4 | AX76: -4 | AY76: -5 | AZ76: -7 | BA76: =-26-SUM(AX76:AZ76) -> -10 | BB76: -16 | BC76: -13 | BD76: -14 | BE76: =-55-SUM(BB76:BD76) -> -12 | BF76: -13 | BG76: -14 | BH76: -17 | BI76: =-56-SUM(BF76:BH76) -> -12 | BJ76: -12 | BK76: -12 | BL76: -12 | BM76: =-49-SUM(BJ76:BL76) -> -13 | BN76: -13 | BO76: -13 | BP76: -14 | BQ76: =(-266+-73)-SUM(BN76:BP76)+58+18+5 -> -218 | BR76: =-236-272+5+267+4 -> -232 | BS76: =-205-24+1+2 -> -226 | BT76: =-205-23+(221-206) -> -213 | BU76: =(-847+-364)-SUM(BR76:BT76)+6+274+54 -> -206 | BV76: =BV74-BV75 -> -205 | BW76: =BW74-BW75 -> -183 | BX76: =BX550 -> -183.77775 | BY76: =BY550 -> -177.015 | BZ76: =BZ550 -> -144.3875 | CA76: =CA550 -> -141.2625 | CB76: =CB550 -> -138.1375 | CC76: =CC550 -> -135.0125 | CE76: =SUM(F76:I76) -> -53.195 | CF76: =SUM(J76:M76) -> 1.213 | CG76: =SUM(N76:Q76) -> -2.165 | CH76: =SUM(R76:U76) -> 0.3 | CI76: =SUM(V76:Y76) -> 5.4 | CJ76: =SUM(Z76:AC76) -> 15.8 | CK76: =SUM(AD76:AG76) -> 4 | CL76: =SUM(AH76:AK76) -> -52 | CM76: =SUM(AL76:AO76) -> -27 | CN76: =SUM(AP76:AS76) -> -9.4 | CO76: =SUM(AT76:AW76) -> -10 | CP76: =SUM(AX76:BA76) -> -26 | CQ76: =SUM(BB76:BE76) -> -55 | CR76: =SUM(BF76:BI76) -> -56 | CS76: =SUM(BJ76:BM76) -> -49 | CT76: =SUM(BN76:BQ76) -> -258 | CU76: =SUM(BR76:BU76) -> -877 | CV76: =SUM(BV76:BY76) -> -748.79275 | CW76: =SUM(BZ76:CC76) -> -558.8 | CX76: =CX550 -> -496.652 | CY76: =CY550 -> -427.55 | CZ76: =CZ550 -> -377.55 | DA76: =DA550 -> -327.55 | DB76: =DB550 -> -277.55 | DC76: =DC550 -> -227.55 | DL76: =SUM(AB76:AE76) -> 12.5 | DM76: =SUM(AF76:AI76) -> -28 | DN76: =SUM(AJ76:AM76) -> -41 | DO76: =SUM(AN76:AQ76) -> -14 | DP76: =SUM(AR76:AU76) -> -8.4 | DQ76: =SUM(AV76:AY76) -> -14 | DR76: =SUM(AZ76:BC76) -> -46 | DS76: =SUM(BD76:BG76) -> -53 | DT76: =SUM(BH76:BK76) -> -53 | DU76: =SUM(BL76:BO76) -> -51 | DV76: =SUM(BP76:BS76) -> -690 | DW76: =SUM(BT76:BW76) -> -807 | DX76: =SUM(BX76:CA76) -> -646.44275
B78: Operating Income Before Taxes | F78: =F71+F74 -> -37.22 | G78: =G71+G74 -> 2.838 | H78: =H71+H74 -> 1.037 | I78: =I71+I74 -> -41.326 | J78: =J71+J74 -> -0.557 | K78: =K71+K74 -> 15.445 | L78: =L71+L74 -> 17.559714 | M78: =M71+M74 -> 16.692 | ... CC78: =CC71+CC74 -> 702.52712 | CE78: =CE71+CE74 -> -74.671 | CF78: =CF71+CF74 -> 49.139714 | CG78: =CG71+CG74 -> 203.15458 | CH78: =CH71+CH74 -> 155.21604 | CI78: =CI71+CI74 -> 221.28768 | CJ78: =CJ71+CJ74 -> 369.66299 | CK78: =CK71+CK74 -> 450.70639 | CL78: =CL71+CL74 -> 1029.9639 | ... DC78: =DC71+DC74 -> 4869.4295 | DL78: =SUM(AB78:AE78) -> 430.15946 | DM78: =SUM(AF78:AI78) -> 716.02973 | DN78: =SUM(AJ78:AM78) -> 854.44925 | DO78: =SUM(AN78:AQ78) -> 1049.9675 | DP78: =SUM(AR78:AU78) -> 1222.1581 | DQ78: =SUM(AV78:AY78) -> 1028.1803 | DR78: =SUM(AZ78:BC78) -> 2833.2278 | DS78: =SUM(BD78:BG78) -> 2160.8522 | DT78: =SUM(BH78:BK78) -> 2168.416 | DU78: =SUM(BL78:BO78) -> 1773.316 | DV78: =SUM(BP78:BS78) -> 1863.399 | DW78: =SUM(BT78:BW78) -> 4232.378 | DX78: =SUM(BX78:CA78) -> 3955.4384 | DZ78: =DZ71+DZ74 -> -2388.9465
B80: GAAP Income Tax Provision | F80: 0 | G80: 0 | H80: 0 | I80: 0 | J80: 0 | K80: 0 | L80: -1.624 | M80: 0.484 | N80: 1.801 | O80: 2.223 | P80: 2.271 | Q80: 2.033 | R80: 0.2 | S80: 2.5 | T80: 1.1 | U80: 0.1 | V80: 0.8 | W80: 1.4 | X80: 1.8 | Y80: 0 | Z80: 1.6 | AA80: 2.8 | AB80: 2.6 | AC80: -20.2 | AD80: 3 | AE80: 0 | AF80: 1 | AG80: -146 | AH80: 69 | AI80: 11 | AJ80: 10 | AK80: 24 | AL80: 19 | AM80: -7 | AN80: 8 | AO80: 11 | AP80: 29 | AQ80: 42 | AR80: 40 | AS80: 27 | AT80: 14 | AU80: 14 | AV80: 13 | AW80: 12 | AX80: 19 | AY80: 15 | AZ80: 55 | BA80: 56 | BB80: 59 | BC80: =133 -> 133 | BD80: 15 | BE80: 35 | BF80: 37 | BG80: 37 | BH80: 31 | BI80: 30 | BJ80: 37 | BK80: 20 | BL80: 28 | BM80: 27 | BN80: 31 | BO80: =-7 -> -7 | BP80: =6 -> 6 | BQ80: =-119 -> -119 | BR80: 95 | BS80: 86 | BT80: 56 | BU80: 135 | BV80: 29 | BW80: 1597 | BX80: =BX78*BX82 -> 58.366458 | BY80: =BY78*BY82 -> 52.441098 | BZ80: =BZ78*BZ82 -> 55.709558 | CA80: =CA78*CA82 -> 51.032 | CB80: =CB78*CB82 -> 41.450447 | CC80: =CC78*CC82 -> 38.638992 | CE80: =SUM(F80:I80) -> 0 | CF80: =SUM(J80:M80) -> -1.14 | CG80: =SUM(N80:Q80) -> 8.328 | CH80: =SUM(R80:U80) -> 3.9 | CI80: =SUM(V80:Y80) -> 4 | CJ80: =SUM(Z80:AC80) -> -13.2 | CK80: =SUM(AD80:AG80) -> -142 | CL80: =SUM(AH80:AK80) -> 114 | CM80: =SUM(AL80:AO80) -> 31 | CN80: =SUM(AP80:AS80) -> 138 | CO80: =SUM(AT80:AW80) -> 53 | CP80: =SUM(AX80:BA80) -> 145 | CQ80: =SUM(BB80:BE80) -> 242 | CR80: =SUM(BF80:BI80) -> 135 | CS80: =SUM(BJ80:BM80) -> 112 | CT80: =SUM(BN80:BQ80) -> -89 | CU80: =SUM(BR80:BU80) -> 372 | CV80: =SUM(BV80:BY80) -> 1736.8076 | CW80: =SUM(BZ80:CC80) -> 186.831 | CX80: =CX78*CX82 -> 206.02896 | CY80: =CY78*CY82 -> 214.5318 | CZ80: =CZ78*CZ82 -> 227.76172 | DA80: =DA78*DA82 -> 437.23156 | DB80: =DB78*DB82 -> 460.67369 | DC80: =DC78*DC82 -> 486.94295 | DL80: =SUM(AB80:AE80) -> -14.6 | DM80: =SUM(AF80:AI80) -> -65 | DN80: =SUM(AJ80:AM80) -> 46 | DO80: =SUM(AN80:AQ80) -> 90 | DP80: =SUM(AR80:AU80) -> 95 | DQ80: =SUM(AV80:AY80) -> 59 | DR80: =SUM(AZ80:BC80) -> 303 | DS80: =SUM(BD80:BG80) -> 124 | DT80: =SUM(BH80:BK80) -> 118 | DU80: =SUM(BL80:BO80) -> 79 | DV80: =SUM(BP80:BS80) -> 68 | DW80: =SUM(BT80:BW80) -> 1817 | DX80: =SUM(BX80:CA80) -> 217.54911
B81: Recurring Tax Provision | F81: =F80-F96 -> 0 | G81: =G80-G96 -> 0 | H81: =H80-H96 -> 0 | I81: =I80-I96 -> 0 | J81: =J80-J96 -> 0 | K81: =K80-K96 -> 0 | L81: =L80-L96 -> 0 | M81: =M80-M96 -> 0.484 | ... CC81: =CC80-CC96 -> 38.638992 | CE81: =SUM(F81:I81) -> 0 | CF81: =SUM(J81:M81) -> 0.484 | CG81: =SUM(N81:Q81) -> 8.328 | CH81: =SUM(R81:U81) -> 3.9 | CI81: =SUM(V81:Y81) -> 4 | CJ81: =SUM(Z81:AC81) -> 8.8 | CK81: =SUM(AD81:AG81) -> 4.8697643 | CL81: =SUM(AH81:AK81) -> 39.340312 | CM81: =SUM(AL81:AO81) -> 44 | CN81: =SUM(AP81:AS81) -> 138 | CO81: =SUM(AT81:AW81) -> 53 | CP81: =SUM(AX81:BA81) -> 165 | CQ81: =SUM(BB81:BE81) -> 154 | CR81: =SUM(BF81:BI81) -> 135 | CS81: =SUM(BJ81:BM81) -> 104 | CT81: =SUM(BN81:BQ81) -> 38 | CU81: =SUM(BR81:BU81) -> 361 | CV81: =SUM(BV81:BY81) -> 247.80756 | CW81: =SUM(BZ81:CC81) -> 186.831 | CX81: =CX80-CX96 -> 206.02896 | CY81: =CY80-CY96 -> 214.5318 | CZ81: =CZ80-CZ96 -> 227.76172 | DA81: =DA80-DA96 -> 437.23156 | DB81: =DB80-DB96 -> 460.67369 | DC81: =DC80-DC96 -> 486.94295 | DL81: =SUM(AB81:AE81) -> 7.4 | DM81: =SUM(AF81:AI81) -> 22.210076 | DN81: =SUM(AJ81:AM81) -> 44 | DO81: =SUM(AN81:AQ81) -> 90 | DP81: =SUM(AR81:AU81) -> 95 | DQ81: =SUM(AV81:AY81) -> 59 | DR81: =SUM(AZ81:BC81) -> 235 | DS81: =SUM(BD81:BG81) -> 124 | DT81: =SUM(BH81:BK81) -> 113 | DU81: =SUM(BL81:BO81) -> 95 | DV81: =SUM(BP81:BS81) -> 155 | DW81: =SUM(BT81:BW81) -> 338 | DX81: =SUM(BX81:CA81) -> 217.54911 | DZ81: =DZ82*DZ78 -> -279.95207
C82: Effective Tax Rate | F82: =F81/F78 -> 0 | G82: =G81/G78 -> 0 | H82: =H81/H78 -> 0 | I82: =I81/I78 -> 0 | J82: =J81/J78 -> 0 | K82: =K81/K78 -> 0 | L82: =L81/L78 -> 0 | M82: =M81/M78 -> 0.028995926 | ... BW82: =BW81/BW78 -> 0.042018139 | BX82: 0.055 | BY82: =BX82 -> 0.055 | BZ82: =BY82 -> 0.055 | CA82: =BZ82 -> 0.055 | CB82: =CA82 -> 0.055 | CC82: =CB82 -> 0.055 | CE82: =CE81/CE78 -> 0 | CF82: =CF81/CF78 -> 0.0098494671 | CG82: =CG81/CG78 -> 0.040993415 | CH82: =CH81/CH78 -> 0.025126268 | CI82: =CI81/CI78 -> 0.018076018 | CJ82: =CJ81/CJ78 -> 0.023805466 | CK82: =CK81/CK78 -> 0.010804738 | CL82: =CL81/CL78 -> 0.038195814 | ... CW82: =CW81/CW78 -> 0.055 | CX82: =CW82 -> 0.055 | CY82: =CX82 -> 0.055 | CZ82: =CY82 -> 0.055 | DA82: 0.1 | DB82: 0.1 | DC82: 0.1 | DL82: =SUM(AB82:AE82) -> 0.073710068 | DM82: =DM81/DM78 -> 0.031018371 | DN82: =DN81/DN78 -> 0.051495159 | DO82: =DO81/DO78 -> 0.085716938 | DP82: =DP81/DP78 -> 0.077731352 | DQ82: =DQ81/DQ78 -> 0.057382929 | DR82: =DR81/DR78 -> 0.082944267 | DS82: =DS81/DS78 -> 0.057384767 | DT82: =DT81/DT78 -> 0.052111772 | ... DX82: =DX81/DX78 -> 0.055 | DZ82: =CU82 -> 0.11718641
C83: Statutory Tax Rate | F83: =F557 -> 0.32 | G83: =G557 -> 0.32 | H83: =H557 -> 0.32 | I83: =I557 -> 0.32 | J83: =J557 -> 0.32 | K83: =K557 -> 0.32 | L83: =L557 -> 0.32 | M83: =M557 -> 0.32 | ... BW83: =BW557 -> 0.32 | BX83: 0.2 | BY83: 0.2 | BZ83: 0.2 | CA83: 0.2 | CB83: 0.2 | CC83: 0.2 | CE83: =CE557 -> 0.32 | CF83: =CF557 -> 0.32 | CG83: =CG557 -> 0.32 | CH83: =CH557 -> 0.32 | CI83: =CI557 -> 0.32 | CJ83: =CJ557 -> 0.32 | CK83: =CK557 -> 0.32 | CL83: =CL557 -> 0.32 | ... CV83: =CV557 -> 0.32 | CW83: 0.2 | CX83: 0.2 | CY83: =CY557 -> 0.32 | CZ83: =CZ557 -> 0.32 | DA83: =DA557 -> 0.32 | DB83: =DB557 -> 0.32 | DC83: =DC557 -> 0.32 | DL83: =SUM(AB83:AE83) -> 1.28 | DM83: 0.32 | DN83: =DM83 -> 0.32 | DO83: =DN83 -> 0.32 | DP83: =DO83 -> 0.32 | DQ83: =DP83 -> 0.32 | DR83: =DQ83 -> 0.32 | DS83: =DR83 -> 0.32 | DT83: =DS83 -> 0.32 | DU83: =DT83 -> 0.32 | DV83: 0.2 | DW83: 0.2 | DX83: 0.2
B85: Operating Net Income | F85: =F78-F81 -> -37.22 | G85: =G78-G81 -> 2.838 | H85: =H78-H81 -> 1.037 | I85: =I78-I81 -> -41.326 | J85: =J78-J81 -> -0.557 | K85: =K78-K81 -> 15.445 | L85: =L78-L81 -> 17.559714 | M85: =M78-M81 -> 16.208 | ... CC85: =CC78-CC81 -> 663.88813 | CE85: =CE78-CE81 -> -74.671 | CF85: =CF78-CF81 -> 48.655714 | CG85: =CG78-CG81 -> 194.82658 | CH85: =CH78-CH81 -> 151.31604 | CI85: =CI78-CI81 -> 217.28768 | CJ85: =CJ78-CJ81 -> 360.86299 | CK85: =CK78-CK81 -> 445.83663 | CL85: =CL78-CL81 -> 990.62363 | ... DC85: =DC78-DC81 -> 4382.4866 | DL85: =DL78-DL81 -> 422.75946 | DM85: =DM78-DM81 -> 693.81965 | DN85: =DN78-DN81 -> 810.44925 | DO85: =DO78-DO81 -> 959.96751 | DP85: =DP78-DP81 -> 1127.1581 | DQ85: =DQ78-DQ81 -> 969.18034 | DR85: =DR78-DR81 -> 2598.2278 | DS85: =DS78-DS81 -> 2036.8522 | ... DX85: =DX78-DX81 -> 3737.8893 | DZ85: =DZ78-DZ81 -> -2108.9945
C86: Operating Net Income Margin | F86: =F85/F11 -> -0.087707309 | G86: =G85/G11 -> 0.0050536888 | H86: =H85/H11 -> 0.002026487 | I86: =I85/I11 -> -0.090680289 | J86: =J85/J11 -> -0.0012632018 | K86: =K85/K11 -> 0.026876294 | L86: =L85/L11 -> 0.029518737 | M86: =M85/M11 -> 0.029977509 | ... CC86: =CC85/CC11 -> 0.15136062 | CE86: =CE85/CE11 -> -0.038226326 | CF86: =CF85/CF11 -> 0.022618449 | CG86: =CG85/CG11 -> 0.071666979 | CH86: =CH85/CH11 -> 0.049665129 | CI86: =CI85/CI11 -> 0.05971469 | CJ86: =CJ85/CJ11 -> 0.083123965 | CK86: =CK85/CK11 -> 0.081525062 | CL86: =CL85/CL11 -> 0.12269025 | ... DC86: =DC85/DC11 -> 0.17180013 | DL86: =DL85/DL11 -> 0.086167367 | DM86: =DM85/DM11 -> 0.1028364 | DN86: =DN85/DN11 -> 0.10085396 | DO86: =DO85/DO11 -> 0.11500641 | DP86: =DP85/DP11 -> 0.11333917 | DQ86: =DQ85/DQ11 -> 0.10372221 | DR86: =DR85/DR11 -> 0.16604216 | DS86: =DS85/DS11 -> 0.13340662 | ... DX86: =DX85/DX11 -> 0.18798725 | DZ86: =DZ85/DZ11 -> -0.10724179
B88: One-Time Charges/ Adjustments | F88: =F89+F96 -> 0 | G88: =G89+G96 -> -0.749 | H88: =H89+H96 -> 6.785 | I88: =I89+I96 -> 17.116 | J88: =J89+J96 -> -21.075 | K88: =K89+K96 -> 2.851 | L88: =L89+L96 -> -1.638 | M88: =M89+M96 -> 3.09 | ... CC88: =CC89+CC96 -> 316.75 | CE88: =CE89+CE96 -> 23.152 | CF88: =CF89+CF96 -> -16.772 | CG88: =CG89+CG96 -> 12.73 | CH88: =CH89+CH96 -> 0 | CI88: =CI89+CI96 -> 19 | CJ88: =CJ89+CJ96 -> -35 | CK88: =CK89+CK96 -> -146.86976 | CL88: =CL89+CL96 -> 123.65969 | ... CP88: =CP89+CP96 -> 497 | CQ88: =SUM(BB88:BE88) -> 1118 | CR88: =SUM(BF88:BI88) -> 344 | CS88: =SUM(BJ88:BM88) -> 540.5 | CT88: =SUM(BN88:BQ88) -> 1175.9 | CU88: =SUM(BR88:BU88) -> 2323 | CV88: =SUM(BV88:BY88) -> 3288.5 | CW88: =SUM(BZ88:CC88) -> 1264.75 | CX88: =CX89+CX96 -> 1264.75 | CY88: =CY89+CY96 -> 1264.75 | CZ88: =CZ89+CZ96 -> 1264.75 | DA88: =DA89+DA96 -> 1264.75 | DB88: =DB89+DB96 -> 1264.75 | DC88: =DC89+DC96 -> 1264.75 | DL88: =SUM(AB88:AE88) -> -35 | DM88: =SUM(AF88:AI88) -> -38.210076 | DN88: =SUM(AJ88:AM88) -> 93 | DO88: =SUM(AN88:AQ88) -> -5 | DP88: =SUM(AR88:AU88) -> 27 | DQ88: =SUM(AV88:AY88) -> 279 | DR88: =SUM(AZ88:BC88) -> 516 | DS88: =SUM(BD88:BG88) -> 986 | DT88: =SUM(BH88:BK88) -> 489 | DU88: =SUM(BL88:BO88) -> 565.5 | DV88: =SUM(BP88:BS88) -> 2138.9 | DW88: =SUM(BT88:BW88) -> 3508 | DX88: =SUM(BX88:CA88) -> 1483.5
C89: Total One-time, gross | F89: =SUM(F90:F95) -> 0 | G89: =SUM(G90:G95) -> -0.749 | H89: =SUM(H90:H95) -> 6.785 | I89: =SUM(I90:I95) -> 17.116 | J89: =SUM(J90:J95) -> -21.075 | K89: =SUM(K90:K95) -> 2.851 | L89: =SUM(L90:L95) -> -0.014 | M89: =SUM(M90:M95) -> 3.09 | ... CC89: =SUM(CC90:CC95) -> 316.75 | CE89: =SUM(CE90:CE95) -> 23.152 | CF89: =SUM(CF90:CF95) -> -15.148 | CG89: =SUM(CG90:CG95) -> 12.73 | CH89: =SUM(CH90:CH95) -> 0 | CI89: =SUM(CI90:CI95) -> 19 | CJ89: =SUM(CJ90:CJ95) -> -13 | CK89: =SUM(CK90:CK95) -> 0 | CL89: =SUM(CL90:CL95) -> 49 | ... CP89: =SUM(CP90:CP95) -> 517 | CQ89: =SUM(BB89:BE89) -> 1030 | CR89: =SUM(BF89:BI89) -> 344 | CS89: =SUM(BJ89:BM89) -> 532.5 | CT89: =SUM(BN89:BQ89) -> 1302.9 | CU89: =SUM(BR89:BU89) -> 2312 | CV89: =SUM(BV89:BY89) -> 1799.5 | CW89: =SUM(BZ89:CC89) -> 1264.75 | CX89: =SUM(CX90:CX95) -> 1264.75 | CY89: =SUM(CY90:CY95) -> 1264.75 | CZ89: =SUM(CZ90:CZ95) -> 1264.75 | DA89: =SUM(DA90:DA95) -> 1264.75 | DB89: =SUM(DB90:DB95) -> 1264.75 | DC89: =SUM(DC90:DC95) -> 1264.75 | DL89: =SUM(AB89:AE89) -> -13 | DM89: =SUM(AF89:AI89) -> 49 | DN89: =SUM(AJ89:AM89) -> 91 | DO89: =SUM(AN89:AQ89) -> -5 | DP89: =SUM(AR89:AU89) -> 27 | DQ89: =SUM(AV89:AY89) -> 279 | DR89: =SUM(AZ89:BC89) -> 448 | DS89: =SUM(BD89:BG89) -> 986 | DT89: =SUM(BH89:BK89) -> 484 | DU89: =SUM(BL89:BO89) -> 581.5 | DV89: =SUM(BP89:BS89) -> 2225.9 | DW89: =SUM(BT89:BW89) -> 2029 | DX89: =SUM(BX89:CA89) -> 1483.5
D90: Amortization | F90: 0 | G90: 0 | H90: 0 | I90: 0 | J90: 0 | K90: 0 | L90: 0 | M90: 0 | N90: 0 | O90: 0 | P90: 0 | Q90: 0 | R90: 0 | S90: 0 | T90: 0 | U90: 0 | V90: 0 | W90: 0 | X90: 0 | Y90: 0 | Z90: 0 | AA90: 0 | AB90: 0 | AC90: 0 | AD90: 0 | AE90: 0 | AF90: 0 | AG90: 0 | AH90: 0 | AI90: 0 | AJ90: 0 | AK90: 0 | AL90: 0 | AM90: 0 | AN90: 0 | AO90: 0 | AP90: 0 | AQ90: 0 | AR90: 0 | AS90: 0 | AT90: 0 | AU90: 0 | AV90: 0 | AW90: 0 | AX90: 0 | AY90: 0 | AZ90: 12 | BA90: 51 | BB90: 49 | BC90: 49 | BD90: 49 | BE90: 46 | BF90: 47 | BG90: 51 | BH90: 50 | BI90: 47 | BJ90: =46 -> 46 | BK90: 45 | BL90: 44 | BM90: 28 | BN90: 25 | BO90: 24 | BP90: 22 | BQ90: 187 | BR90: 242 | BS90: 259 | BT90: 303 | BU90: 319 | BV90: 319 | BW90: 315 | BX90: =AVERAGE(BT90:BW90) -> 314 | BY90: =AVERAGE(BU90:BX90) -> 316.75 | BZ90: =BV90 -> 319 | CA90: =BW90 -> 315 | CB90: =BX90 -> 314 | CC90: =BY90 -> 316.75 | CE90: =SUM(F90:I90) -> 0 | CF90: =SUM(J90:M90) -> 0 | CG90: =SUM(N90:Q90) -> 0 | CH90: =SUM(R90:U90) -> 0 | CI90: =SUM(V90:Y90) -> 0 | CJ90: =SUM(Z90:AC90) -> 0 | CK90: =SUM(AD90:AG90) -> 0 | CL90: =SUM(AH90:AK90) -> 0 | CM90: =SUM(AL90:AO90) -> 0 | CN90: =SUM(AP90:AS90) -> 0 | CO90: =SUM(AT90:AW90) -> 0 | CP90: =SUM(AX90:BA90) -> 63 | CQ90: =SUM(BB90:BE90) -> 193 | CR90: =SUM(BF90:BI90) -> 195 | CS90: =SUM(BJ90:BM90) -> 163 | CT90: =SUM(BN90:BQ90) -> 258 | CU90: =SUM(BR90:BU90) -> 1123 | CV90: =SUM(BV90:BY90) -> 1264.75 | CW90: =SUM(BZ90:CC90) -> 1264.75 | CX90: =CW90 -> 1264.75 | CY90: =CX90 -> 1264.75 | CZ90: =CY90 -> 1264.75 | DA90: =CZ90 -> 1264.75 | DB90: =DA90 -> 1264.75 | DC90: =DB90 -> 1264.75 | DL90: =SUM(AB90:AE90) -> 0 | DM90: =SUM(AF90:AI90) -> 0 | DN90: =SUM(AJ90:AM90) -> 0 | DO90: =SUM(AN90:AQ90) -> 0 | DP90: =SUM(AR90:AU90) -> 0 | DQ90: =SUM(AV90:AY90) -> 0 | DR90: =SUM(AZ90:BC90) -> 161 | DS90: =SUM(BD90:BG90) -> 193 | DT90: =SUM(BH90:BK90) -> 188 | DU90: =SUM(BL90:BO90) -> 121 | DV90: =SUM(BP90:BS90) -> 710 | DW90: =SUM(BT90:BW90) -> 1256 | DX90: =SUM(BX90:CA90) -> 1264.75
D91: Restructuring Charge | F91: 0 | G91: 0 | H91: 0 | I91: 0 | J91: 0 | K91: 0 | L91: 0 | M91: 0 | N91: 0 | O91: 0 | P91: 0 | Q91: 0 | R91: 0 | S91: 0 | T91: 0 | U91: 0 | V91: 0 | W91: 0 | X91: 0 | Y91: 0 | Z91: 0 | AA91: 0 | AB91: 0 | AC91: 0 | AD91: 0 | AE91: 0 | AF91: 0 | AG91: 0 | AH91: 0 | AI91: 0 | AJ91: 0 | AK91: 0 | AL91: 0 | AM91: 113 | AN91: 4 | AO91: -23 | AP91: 0 | AQ91: 0 | AR91: 0 | AS91: 0 | AT91: 0 | AU91: 0 | AV91: 0 | AW91: 0 | AX91: 0 | AY91: 0 | AZ91: 0 | BA91: =80 -> 80 | BB91: 26 | BC91: 0 | BD91: 63 | BE91: 8 | BF91: 0 | BG91: 0 | BH91: 28 | BI91: 10 | BJ91: 0 | BK91: 0 | BL91: 0 | BM91: 0 | BN91: 0 | BO91: 0 | BP91: 0 | BQ91: 0 | BR91: 0 | BS91: 0 | BT91: 0 | BU91: 0 | BV91: 0 | BW91: 0 | BX91: 0 | BY91: 0 | BZ91: 0 | CA91: 0 | CB91: 0 | CC91: 0 | CE91: =SUM(F91:I91) -> 0 | CF91: =SUM(J91:M91) -> 0 | CG91: =SUM(N91:Q91) -> 0 | CH91: =SUM(R91:U91) -> 0 | CI91: =SUM(V91:Y91) -> 0 | CJ91: =SUM(Z91:AC91) -> 0 | CK91: =SUM(AD91:AG91) -> 0 | CL91: =SUM(AH91:AK91) -> 0 | CM91: =SUM(AL91:AO91) -> 94 | CN91: =SUM(AP91:AS91) -> 0 | CO91: =SUM(AT91:AW91) -> 0 | CP91: =SUM(AX91:BA91) -> 80 | CQ91: =SUM(BB91:BE91) -> 97 | CR91: =SUM(BF91:BI91) -> 38 | CS91: =SUM(BJ91:BM91) -> 0 | CT91: =SUM(BN91:BQ91) -> 0 | CU91: =SUM(BR91:BU91) -> 0 | CV91: =SUM(BV91:BY91) -> 0 | CW91: =SUM(BZ91:CC91) -> 0 | CX91: 0 | CY91: 0 | CZ91: 0 | DA91: 0 | DB91: 0 | DC91: 0 | DL91: =SUM(AB91:AE91) -> 0 | DM91: =SUM(AF91:AI91) -> 0 | DN91: =SUM(AJ91:AM91) -> 113 | DO91: =SUM(AN91:AQ91) -> -19 | DP91: =SUM(AR91:AU91) -> 0 | DQ91: =SUM(AV91:AY91) -> 0 | DR91: =SUM(AZ91:BC91) -> 106 | DS91: =SUM(BD91:BG91) -> 71 | DT91: =SUM(BH91:BK91) -> 38 | DU91: =SUM(BL91:BO91) -> 0 | DV91: =SUM(BP91:BS91) -> 0 | DW91: =SUM(BT91:BW91) -> 0 | DX91: =SUM(BX91:CA91) -> 0
D92: Deferred Compensation Expense | F92: 0 | G92: 0 | H92: 0 | I92: 0 | J92: 0 | K92: 0 | L92: 0 | M92: 0 | N92: 0 | O92: 0 | P92: 0 | Q92: 0 | R92: 0 | S92: 0 | T92: 0 | U92: 0 | V92: 0 | W92: 0 | X92: 0 | Y92: 0 | Z92: 0 | AA92: 0 | AB92: 0 | AC92: 0 | AD92: 0 | AE92: 0 | AF92: 0 | AG92: 0 | AH92: 0 | AI92: 0 | AJ92: 0 | AK92: 0 | AL92: 0 | AM92: 0 | AN92: 0 | AO92: 0 | AP92: 0 | AQ92: 0 | AR92: 0 | AS92: 0 | AT92: 0 | AU92: 0 | AV92: 0 | AW92: 0 | AX92: 0 | AY92: 0 | AZ92: 0 | BA92: 0 | BB92: 0 | BC92: 0 | BD92: 0 | BE92: 0 | BF92: 0 | BG92: 0 | BH92: 0 | BI92: 0 | BJ92: 0 | BK92: 0 | BL92: 0 | BM92: 0 | BN92: 0 | BO92: 0 | BP92: 0 | BQ92: 0 | BR92: 0 | BS92: 0 | BT92: 0 | BU92: 0 | BV92: 0 | BW92: 0 | BX92: 0 | BY92: 0 | BZ92: 0 | CA92: 0 | CB92: 0 | CC92: 0 | CE92: =SUM(F92:I92) -> 0 | CF92: =SUM(J92:M92) -> 0 | CG92: =SUM(N92:Q92) -> 0 | CH92: =SUM(R92:U92) -> 0 | CI92: =SUM(V92:Y92) -> 0 | CJ92: =SUM(Z92:AC92) -> 0 | CK92: =SUM(AD92:AG92) -> 0 | CL92: =SUM(AH92:AK92) -> 0 | CM92: =SUM(AL92:AO92) -> 0 | CN92: =SUM(AP92:AS92) -> 0 | CO92: =SUM(AT92:AW92) -> 0 | CP92: =SUM(AX92:BA92) -> 0 | CQ92: =SUM(BB92:BE92) -> 0 | CR92: =SUM(BF92:BI92) -> 0 | CS92: =SUM(BJ92:BM92) -> 0 | CT92: =SUM(BN92:BQ92) -> 0 | CU92: =SUM(BR92:BU92) -> 0 | CV92: =SUM(BV92:BY92) -> 0 | CW92: =SUM(BZ92:CC92) -> 0 | CX92: 0 | CY92: 0 | CZ92: 0 | DA92: 0 | DB92: 0 | DC92: 0 | DL92: =SUM(AB92:AE92) -> 0 | DM92: =SUM(AF92:AI92) -> 0 | DN92: =SUM(AJ92:AM92) -> 0 | DO92: =SUM(AN92:AQ92) -> 0 | DP92: =SUM(AR92:AU92) -> 0 | DQ92: =SUM(AV92:AY92) -> 0 | DR92: =SUM(AZ92:BC92) -> 0 | DS92: =SUM(BD92:BG92) -> 0 | DT92: =SUM(BH92:BK92) -> 0 | DU92: =SUM(BL92:BO92) -> 0 | DV92: =SUM(BP92:BS92) -> 0 | DW92: =SUM(BT92:BW92) -> 0 | DX92: =SUM(BX92:CA92) -> 0
D93: Stock Based Comp | F93: 0 | G93: 0 | H93: 0 | I93: 0 | J93: 0 | K93: 0 | L93: 0 | M93: 0 | N93: 0 | O93: 0 | P93: 0 | Q93: 0 | R93: 0 | S93: 0 | T93: 0 | U93: 0 | V93: 0 | W93: 0 | X93: 0 | Y93: 0 | Z93: 0 | AA93: 0 | AB93: 0 | AC93: 0 | AD93: 0 | AE93: 0 | AF93: 0 | AG93: 0 | AH93: 0 | AI93: 0 | AJ93: 0 | AK93: 0 | AL93: 0 | AM93: 0 | AN93: 0 | AO93: 0 | AP93: 0 | AQ93: 0 | AR93: 0 | AS93: 0 | AT93: 0 | AU93: 0 | AV93: 0 | AW93: 0 | AX93: 0 | AY93: 0 | AZ93: 0 | BA93: 0 | BB93: 0 | BC93: 0 | BD93: 0 | BE93: 0 | BF93: 0 | BG93: 0 | BH93: 0 | BI93: 0 | BJ93: 39 | BK93: 40 | BL93: 37 | BM93: 42 | BN93: 41 | BO93: 35 | BP93: 36 | BQ93: 68 | BR93: 99 | BS93: 191 | BT93: 187 | BU93: 89 | BV93: 97 | BW93: 99 | BX93: =AVERAGE(BT93:BW93) -> 118 | BY93: =AVERAGE(BU93:BX93) -> 100.75 | BZ93: 0 | CA93: 0 | CB93: 0 | CC93: 0 | CE93: =SUM(F93:I93) -> 0 | CF93: =SUM(J93:M93) -> 0 | CG93: =SUM(N93:Q93) -> 0 | CH93: =SUM(R93:U93) -> 0 | CI93: =SUM(V93:Y93) -> 0 | CJ93: =SUM(Z93:AC93) -> 0 | CK93: =SUM(AD93:AG93) -> 0 | CL93: =SUM(AH93:AK93) -> 0 | CM93: =SUM(AL93:AO93) -> 0 | CN93: =SUM(AP93:AS93) -> 0 | CO93: =SUM(AT93:AW93) -> 0 | CP93: =SUM(AX93:BA93) -> 0 | CQ93: =SUM(BB93:BE93) -> 0 | CR93: =SUM(BF93:BI93) -> 0 | CS93: =SUM(BJ93:BM93) -> 158 | CT93: =SUM(BN93:BQ93) -> 180 | CU93: =SUM(BR93:BU93) -> 566 | CV93: =SUM(BV93:BY93) -> 414.75 | CW93: =SUM(BZ93:CC93) -> 0 | CX93: 0 | CY93: 0 | CZ93: 0 | DA93: 0 | DB93: 0 | DC93: 0 | DL93: =SUM(AB93:AE93) -> 0 | DM93: =SUM(AF93:AI93) -> 0 | DN93: =SUM(AJ93:AM93) -> 0 | DO93: =SUM(AN93:AQ93) -> 0 | DP93: =SUM(AR93:AU93) -> 0 | DQ93: =SUM(AV93:AY93) -> 0 | DR93: =SUM(AZ93:BC93) -> 0 | DS93: =SUM(BD93:BG93) -> 0 | DT93: =SUM(BH93:BK93) -> 79 | DU93: =SUM(BL93:BO93) -> 155 | DV93: =SUM(BP93:BS93) -> 394 | DW93: =SUM(BT93:BW93) -> 472 | DX93: =SUM(BX93:CA93) -> 218.75
D94: Debt Refinancing Costs | F94: 0 | G94: 0 | H94: 0 | I94: -22.4 | J94: 0 | K94: 0 | L94: 0 | M94: 0 | N94: 0 | O94: 0 | P94: 0 | Q94: 0 | R94: 0 | S94: 0 | T94: 0 | U94: 0 | V94: 0 | W94: 0 | X94: 0 | Y94: 0 | Z94: 0 | AA94: 0 | AB94: 0 | AC94: 0 | AD94: 0 | AE94: 0 | AF94: 0 | AG94: 0 | AH94: 0 | AI94: 0 | AJ94: 0 | AK94: 0 | AL94: 0 | AM94: 0 | AN94: 0 | AO94: 0 | AP94: 0 | AQ94: 0 | AR94: 0 | AS94: 0 | AT94: 0 | AU94: 0 | AV94: 0 | AW94: 0 | AX94: 0 | AY94: 0 | AZ94: 0 | BA94: 0 | BB94: 0 | BC94: 0 | BD94: 0 | BE94: 0 | BF94: 0 | BG94: 0 | BH94: 4 | BI94: 0 | BJ94: 0 | BK94: 0 | BL94: 0 | BM94: 0 | BN94: 0 | BO94: 0 | BP94: 0 | BQ94: 0 | BR94: 0 | BS94: 0 | BT94: 0 | BU94: 0 | BV94: 0 | BW94: 0 | BX94: 0 | BY94: 0 | BZ94: 0 | CA94: 0 | CB94: 0 | CC94: 0 | CE94: =SUM(F94:I94) -> -22.4 | CF94: =SUM(J94:M94) -> 0 | CG94: =SUM(N94:Q94) -> 0 | CH94: =SUM(R94:U94) -> 0 | CI94: =SUM(V94:Y94) -> 0 | CJ94: =SUM(Z94:AC94) -> 0 | CK94: =SUM(AD94:AG94) -> 0 | CL94: =SUM(AH94:AK94) -> 0 | CM94: =SUM(AL94:AO94) -> 0 | CN94: =SUM(AP94:AS94) -> 0 | CO94: =SUM(AT94:AW94) -> 0 | CP94: =SUM(AX94:BA94) -> 0 | CQ94: =SUM(BB94:BE94) -> 0 | CR94: =SUM(BF94:BI94) -> 4 | CS94: =SUM(BJ94:BM94) -> 0 | CT94: =SUM(BN94:BQ94) -> 0 | CU94: =SUM(BR94:BU94) -> 0 | CV94: =SUM(BV94:BY94) -> 0 | CW94: =SUM(BZ94:CC94) -> 0 | CX94: 0 | CY94: 0 | CZ94: 0 | DA94: 0 | DB94: 0 | DC94: 0 | DL94: =SUM(AB94:AE94) -> 0 | DM94: =SUM(AF94:AI94) -> 0 | DN94: =SUM(AJ94:AM94) -> 0 | DO94: =SUM(AN94:AQ94) -> 0 | DP94: =SUM(AR94:AU94) -> 0 | DQ94: =SUM(AV94:AY94) -> 0 | DR94: =SUM(AZ94:BC94) -> 0 | DS94: =SUM(BD94:BG94) -> 0 | DT94: =SUM(BH94:BK94) -> 4 | DU94: =SUM(BL94:BO94) -> 0 | DV94: =SUM(BP94:BS94) -> 0 | DW94: =SUM(BT94:BW94) -> 0 | DX94: =SUM(BX94:CA94) -> 0
D95: Other | F95: 0 | G95: =9.827-10.576 -> -0.749 | H95: =7.156-0.371 -> 6.785 | I95: =38.012+1.504 -> 39.516 | J95: -21.075 | K95: 2.851 | L95: -0.014 | M95: 3.09 | O95: -1.32 | P95: 0 | Q95: =18.5-3.4-1.05 -> 14.05 | R95: 0 | S95: 0 | T95: 0 | U95: 0 | V95: 0 | W95: 0 | X95: 0 | Y95: 19 | Z95: 0 | AA95: 0 | AB95: 0 | AC95: -13 | AD95: 0 | AE95: 0 | AF95: 0 | AG95: 0 | AH95: 49 | AI95: 0 | AJ95: 0 | AK95: 0 | AL95: 0 | AM95: =-16-6 -> -22 | AN95: 14 | AO95: 0 | AP95: 0 | AQ95: 0 | AR95: 0 | AS95: 27 | AT95: 0 | AU95: 0 | AV95: 10 | AW95: 35 | AX95: 21 | AY95: =199+14 -> 213 | AZ95: 140 | BA95: 0 | BB95: 0 | BC95: =41 -> 41 | BD95: 11 | BE95: =7+681 -> 688 | BF95: =13+13+11-65 -> -28 | BG95: =13+26+12 -> 51 | BH95: =13 -> 13 | BI95: =13+36+22 -> 71 | BJ95: =9+14+12 -> 35 | BK95: =53+1-37+39 -> 56 | BL95: =10+3 -> 13 | BM95: =104+3.5 -> 107.5 | BN95: =56+2 -> 58 | BO95: =27+37+32+27+4 -> 127 | BP95: =140+49+16+2 -> 207 | BQ95: =122+58+57+238.4-2.5 -> 472.9 | BR95: =27+63+68+5+267+9 -> 439 | BS95: 3 | BT95: 15 | BU95: =80-1+40+47 -> 166 | BV95: =4-4+52+0+0-5 -> 47 | BW95: =48+6+18+2-1 -> 73 | BX95: 0 | BY95: 0 | BZ95: 0 | CA95: 0 | CB95: 0 | CC95: 0 | CE95: =SUM(F95:I95) -> 45.552 | CF95: =SUM(J95:M95) -> -15.148 | CG95: =SUM(N95:Q95) -> 12.73 | CH95: =SUM(R95:U95) -> 0 | CI95: =SUM(V95:Y95) -> 19 | CJ95: =SUM(Z95:AC95) -> -13 | CK95: =SUM(AD95:AG95) -> 0 | CL95: =SUM(AH95:AK95) -> 49 | CM95: =SUM(AL95:AO95) -> -8 | CN95: =SUM(AP95:AS95) -> 27 | CO95: =SUM(AT95:AW95) -> 45 | CP95: =SUM(AX95:BA95) -> 374 | CQ95: =SUM(BB95:BE95) -> 740 | CR95: =SUM(BF95:BI95) -> 107 | CS95: =SUM(BJ95:BM95) -> 211.5 | CT95: =SUM(BN95:BQ95) -> 864.9 | CU95: =SUM(BR95:BU95) -> 623 | CV95: =SUM(BV95:BY95) -> 120 | CW95: =SUM(BZ95:CC95) -> 0 | CX95: 0 | CY95: 0 | CZ95: 0 | DA95: 0 | DB95: 0 | DC95: 0 | DL95: =SUM(AB95:AE95) -> -13 | DM95: =SUM(AF95:AI95) -> 49 | DN95: =SUM(AJ95:AM95) -> -22 | DO95: =SUM(AN95:AQ95) -> 14 | DP95: =SUM(AR95:AU95) -> 27 | DQ95: =SUM(AV95:AY95) -> 279 | DR95: =SUM(AZ95:BC95) -> 181 | DS95: =SUM(BD95:BG95) -> 722 | DT95: =SUM(BH95:BK95) -> 175 | DU95: =SUM(BL95:BO95) -> 305.5 | DV95: =SUM(BP95:BS95) -> 1121.9 | DW95: =SUM(BT95:BW95) -> 301 | DX95: =SUM(BX95:CA95) -> 0
C96: Less: One-time Tax Impact | F96: 0 | G96: 0 | H96: 0 | I96: 0 | J96: 0 | K96: 0 | L96: -1.624 | M96: 0 | N96: 0 | O96: 0 | P96: 0 | Q96: 0 | R96: 0 | S96: 0 | T96: 0 | U96: 0 | V96: 0 | W96: 0 | X96: 0 | Y96: 0 | Z96: 0 | AA96: 0 | AB96: 0 | AC96: =-22 -> -22 | AD96: 0 | AE96: 0 | AF96: 0 | AG96: -146.86976 | AH96: 59.659688 | AI96: 0 | AJ96: 0 | AK96: 15 | AL96: 0 | AM96: -13 | AN96: 0 | AO96: 0 | AP96: 0 | AQ96: 0 | AR96: 0 | AS96: 0 | AT96: 0 | AU96: 0 | AV96: 0 | AW96: 0 | AX96: 0 | AY96: 0 | AZ96: -16 | BA96: -4 | BB96: 0 | BC96: 88 | BD96: 0 | BE96: 0 | BF96: 0 | BG96: 0 | BH96: 0 | BI96: 0 | BJ96: 2 | BK96: 3 | BL96: 2 | BM96: 1 | BN96: 5 | BO96: -24 | BP96: -16 | BQ96: -92 | BR96: 34 | BS96: -13 | BT96: -37 | BU96: 27 | BV96: -55 | BW96: 1544 | BX96: 0 | BY96: 0 | BZ96: 0 | CA96: 0 | CB96: 0 | CC96: 0 | CE96: =SUM(F96:I96) -> 0 | CF96: =SUM(J96:M96) -> -1.624 | CG96: =SUM(N96:Q96) -> 0 | CH96: =SUM(R96:U96) -> 0 | CI96: =SUM(V96:Y96) -> 0 | CJ96: =SUM(Z96:AC96) -> -22 | CK96: =SUM(AD96:AG96) -> -146.86976 | CL96: =SUM(AH96:AK96) -> 74.659688 | CM96: =SUM(AL96:AO96) -> -13 | CN96: =SUM(AP96:AS96) -> 0 | CO96: =SUM(AT96:AW96) -> 0 | CP96: =SUM(AX96:BA96) -> -20 | CQ96: =SUM(BB96:BE96) -> 88 | CR96: =SUM(BF96:BI96) -> 0 | CS96: =SUM(BJ96:BM96) -> 8 | CT96: =SUM(BN96:BQ96) -> -127 | CU96: =SUM(BR96:BU96) -> 11 | CV96: =SUM(BV96:BY96) -> 1489 | CW96: =SUM(BZ96:CC96) -> 0 | CX96: 0 | CY96: 0 | CZ96: 0 | DA96: 0 | DB96: 0 | DC96: 0 | DL96: =SUM(AB96:AE96) -> -22 | DM96: =SUM(AF96:AI96) -> -87.210076 | DN96: =SUM(AJ96:AM96) -> 2 | DO96: =SUM(AN96:AQ96) -> 0 | DP96: =SUM(AR96:AU96) -> 0 | DQ96: =SUM(AV96:AY96) -> 0 | DR96: =SUM(AZ96:BC96) -> 68 | DS96: =SUM(BD96:BG96) -> 0 | DT96: =SUM(BH96:BK96) -> 5 | DU96: =SUM(BL96:BO96) -> -16 | DV96: =SUM(BP96:BS96) -> -87 | DW96: =SUM(BT96:BW96) -> 1479 | DX96: =SUM(BX96:CA96) -> 0
B98: Reported Income Before Taxes | F98: =F100+F80 -> -37.22 | G98: =G100+G80 -> 3.587 | H98: =H100+H80 -> -5.748 | I98: =I100+I80 -> -58.442 | J98: =J100+J80 -> 20.518 | K98: =K100+K80 -> 12.594 | L98: =L100+L80 -> 17.573714 | M98: =M100+M80 -> 13.602 | ... CC98: =CC100+CC80 -> 385.77712 | CE98: =(CE78-CE90-CE92-CE94-CE95) -> -97.823 | CF98: =(CF78-CF90-CF92-CF94-CF95) -> 64.287714 | CG98: =(CG78-CG90-CG92-CG94-CG95) -> 190.42458 | CH98: =(CH78-CH90-CH92-CH94-CH95) -> 155.21604 | CI98: =(CI78-CI90-CI92-CI94-CI95) -> 202.28768 | CJ98: =(CJ78-CJ90-CJ92-CJ94-CJ95) -> 382.66299 | CK98: =(CK78-CK90-CK92-CK94-CK95) -> 450.70639 | CL98: =(CL78-CL90-CL92-CL94-CL95) -> 980.96394 | ... CR98: =(CR78-CR90-CR92-CR94-CR95) -> 1790.2122 | CS98: =CS100+CS80 -> 1574.4765 | CT98: =CT100+CT80 -> 136.5275 | CU98: =CU100+CU80 -> 768.562 | CV98: =CV100+CV80 -> 2649.4078 | CW98: =CW100+CW80 -> 2132.1772 | CX98: =CX100+CX80 -> 2481.2311 | CY98: =CY100+CY80 -> 2635.8282 | CZ98: =CZ100+CZ80 -> 2876.3721 | ... DC98: =DC100+DC80 -> 3604.6795 | DL98: =SUM(AB98:AE98) -> 443.15946 | DM98: =SUM(AF98:AI98) -> 667.02973 | DN98: =SUM(AJ98:AM98) -> 763.44925 | DO98: =SUM(AN98:AQ98) -> 1054.9675 | DP98: =SUM(AR98:AU98) -> 1195.1581 | DQ98: =SUM(AV98:AY98) -> 749.18034 | DR98: =SUM(AZ98:BC98) -> 2385.2278 | DS98: =SUM(BD98:BG98) -> 1174.8522 | DT98: =SUM(BE98:BH98) -> 1175.1402 | DU98: =SUM(BF98:BI98) -> 1752.2122 | DV98: =SUM(BJ98:BM98) -> 1574.4765 | DW98: =SUM(BN98:BQ98) -> 136.5275 | DX98: =SUM(BR98:BU98) -> 768.562
B100: GAAP Net Income | F100: =F85-F88 -> -37.22 | G100: =G85-G88 -> 3.587 | H100: =H85-H88 -> -5.748 | I100: =I85-I88 -> -58.442 | J100: =J85-J88 -> 20.518 | K100: =K85-K88 -> 12.594 | L100: =L85-L88 -> 19.197714 | M100: =M85-M88 -> 13.118 | ... CC100: =CC85-CC88 -> 347.13813 | CE100: =CE85-CE88 -> -97.823 | CF100: =CF85-CF88 -> 65.427714 | CG100: =CG85-CG88 -> 182.09658 | CH100: =CH85-CH88 -> 151.31604 | CI100: =CI85-CI88 -> 198.28768 | CJ100: =CJ85-CJ88 -> 395.86299 | CK100: =CK85-CK88 -> 592.70639 | CL100: =CL85-CL88 -> 866.96394 | ... DC100: =DC85-DC88 -> 3117.7366 | DL100: =SUM(AB100:AE100) -> 457.75946 | DM100: =SUM(AF100:AI100) -> 732.02973 | DN100: =SUM(AJ100:AM100) -> 717.44925 | DO100: =SUM(AN100:AQ100) -> 964.96751 | DP100: =SUM(AR100:AU100) -> 1100.1581 | DQ100: =SUM(AV100:AY100) -> 690.18034 | DR100: =SUM(AZ100:BC100) -> 2082.2278 | DS100: =SUM(BD100:BG100) -> 1050.8522 | DT100: =SUM(BH100:BK100) -> 1566.416 | DU100: =SUM(BL100:BO100) -> 1112.816 | DV100: =SUM(BP100:BS100) -> -430.501 | DW100: =SUM(BT100:BW100) -> 386.378 | DX100: =SUM(BX100:CA100) -> 2254.3893
B102: Stock Option Expense | F102: =CF!F19 -> 0 | G102: =CF!G19 -> 0 | H102: =CF!H19 -> 0 | I102: =CF!I19 -> 0 | J102: =CF!J19 -> 0 | K102: =CF!K19 -> 0 | L102: =CF!L19 -> 0 | M102: =CF!M19 -> 0 | ... BW102: =CF!BW19 -> 99 | BX102: =BX11*BX554 -> 91.079604 | BY102: =BY11*BY554 -> 91.170935 | BZ102: =BZ11*BZ554 -> 94.07433 | CA102: =CA11*CA554 -> 92.582579 | CB102: =CB11*CB554 -> 85.973681 | CC102: =CC11*CC554 -> 81.376943 | CE102: =SUM(F102:I102) -> 0 | CF102: =SUM(J102:M102) -> 0 | CG102: =SUM(N102:Q102) -> 0 | CH102: =SUM(R102:U102) -> 0 | CI102: =SUM(V102:Y102) -> 0 | CJ102: =SUM(Z102:AC102) -> 37 | CK102: =SUM(AD102:AG102) -> 48 | CL102: =SUM(AH102:AK102) -> 37 | CM102: =SUM(AL102:AO102) -> 47 | CN102: =SUM(AP102:AS102) -> 60 | CO102: =SUM(AT102:AW102) -> 69 | CP102: =SUM(AX102:BA102) -> 92 | CQ102: =SUM(BB102:BE102) -> 137 | CR102: =SUM(BF102:BI102) -> 156 | CS102: =SUM(BJ102:BM102) -> 162 | CT102: =SUM(BN102:BQ102) -> 191 | CU102: =SUM(BR102:BU102) -> 394 | CV102: =SUM(BV102:BY102) -> 378.25054 | CW102: =SUM(BZ102:CC102) -> 354.00753 | CX102: =CX11*CX554 -> 379.82319 | CY102: =CY11*CY554 -> 393.59264 | CZ102: =CZ11*CZ554 -> 408.57422 | DA102: =DA11*DA554 -> 427.5106 | DB102: =DB11*DB554 -> 448.97207 | DC102: =DC11*DC554 -> 473.27816 | DL102: =SUM(AB102:AE102) -> 42.2 | DM102: =SUM(AF102:AI102) -> 44 | DN102: =SUM(AJ102:AM102) -> 41 | DO102: =SUM(AN102:AQ102) -> 53 | DP102: =SUM(AR102:AU102) -> 70 | DQ102: =SUM(AV102:AY102) -> 73 | DR102: =SUM(AZ102:BC102) -> 122 | DS102: =SUM(BD102:BG102) -> 150 | DT102: =SUM(BH102:BK102) -> 152 | DU102: =SUM(BL102:BO102) -> 161 | DV102: =SUM(BP102:BS102) -> 313 | DW102: =SUM(BT102:BW102) -> 389 | DX102: =SUM(BX102:CA102) -> 368.90745
B103: Tax Benefit on Stock Option Expense | F103: =F102*F82 -> 0 | G103: =G102*G82 -> 0 | H103: =H102*H82 -> 0 | I103: =I102*I82 -> 0 | J103: =J102*J82 -> 0 | K103: =K102*K82 -> 0 | L103: =L102*L82 -> 0 | M103: =M102*M82 -> 0 | ... Y103: =Y102*Y82 -> 0 | Z103: =Z102-4.6 -> 2.3 | AA103: =AA102-4.2 -> 4.7 | AB103: =0.32*AB102 -> 2.784 | AC103: =0.32*AC102 -> 4 | AD103: =0.32*AD102 -> 2.88 | AE103: =0.32*AE102 -> 3.84 | AF103: =0.32*AF102 -> 4.16 | AG103: =0.32*AG102 -> 4.48 | AH103: =0.32*AH102 -> 2.56 | AI103: =0.32*AI102 -> 2.88 | ... CC103: =0.32*CC102 -> 26.040622 | CE103: =SUM(F103:I103) -> 0 | CF103: =SUM(J103:M103) -> 0 | CG103: =SUM(N103:Q103) -> 0 | CH103: =SUM(R103:U103) -> 0 | CI103: =SUM(V103:Y103) -> 0 | CJ103: =SUM(Z103:AC103) -> 13.784 | CK103: =SUM(AD103:AG103) -> 15.36 | CL103: =SUM(AH103:AK103) -> 11.84 | CM103: =SUM(AL103:AO103) -> 15.04 | CN103: =SUM(AP103:AS103) -> 19.2 | CO103: =SUM(AT103:AW103) -> 22.08 | CP103: =SUM(AX103:BA103) -> 29.44 | CQ103: =SUM(BB103:BE103) -> 43.84 | CR103: =SUM(BF103:BI103) -> 49.92 | CS103: =SUM(BJ103:BM103) -> 51.84 | CT103: =SUM(BN103:BQ103) -> 61.12 | CU103: =SUM(BR103:BU103) -> 126.08 | CV103: =SUM(BV103:BY103) -> 121.04017 | CW103: =SUM(BZ103:CC103) -> 113.28241 | CX103: =0.32*CX102 -> 121.54342 | CY103: =0.32*CY102 -> 125.94965 | CZ103: =0.32*CZ102 -> 130.74375 | DA103: =0.32*DA102 -> 136.80339 | DB103: =0.32*DB102 -> 143.67106 | DC103: =0.32*DC102 -> 151.44901 | DL103: =SUM(AB103:AE103) -> 13.504 | DM103: =SUM(AF103:AI103) -> 14.08 | DN103: =SUM(AJ103:AM103) -> 13.12 | DO103: =SUM(AN103:AQ103) -> 16.96 | DP103: =SUM(AR103:AU103) -> 22.4 | DQ103: =SUM(AV103:AY103) -> 23.36 | DR103: =SUM(AZ103:BC103) -> 39.04 | DS103: =SUM(BD103:BG103) -> 48 | DT103: =SUM(BH103:BK103) -> 48.64 | DU103: =SUM(BL103:BO103) -> 51.52 | DV103: =SUM(BP103:BS103) -> 100.16 | DW103: =SUM(BT103:BW103) -> 124.48 | DX103: =SUM(BX103:CA103) -> 118.05038
B104: Stock Option Expense Per Share | F104: =F116-F114 -> 0 | G104: =G116-G114 -> 0 | H104: =H116-H114 -> 0 | I104: =I116-I114 -> 0 | J104: =J116-J114 -> 0 | K104: =K116-K114 -> 0 | L104: =L116-L114 -> 0 | M104: =M116-M114 -> 0 | ... CC104: =CC116-CC114 -> 0.17588278 | CE104: =CE116-CE114 -> 0 | CF104: =CF116-CF114 -> 0 | CG104: =CG116-CG114 -> 0 | CH104: =CH116-CH114 -> 0 | CI104: =CI116-CI114 -> 0 | CJ104: =CJ116-CJ114 -> 0.10364286 | CK104: =CK116-CK114 -> 0.14442478 | CL104: =CL116-CL114 -> 0.11132743 | ... DC104: =DC116-DC114 -> 0.88280269 | DL104: =SUM(AB104:AE104) -> 0.12715185 | DM104: =SUM(AF104:AI104) -> 0.13279152 | DN104: =SUM(AJ104:AM104) -> 0.12339325 | DO104: =SUM(AN104:AQ104) -> 0.15751379 | DP104: =SUM(AR104:AU104) -> 0.202986 | DQ104: =SUM(AV104:AY104) -> 0.20965816 | DR104: =SUM(AZ104:BC104) -> 0.33005486 | DS104: =SUM(BD104:BG104) -> 0.41941638 | DT104: =SUM(BH104:BK104) -> 0.43031835 | DU104: =SUM(BL104:BO104) -> 0.46639559 | DV104: =SUM(BP104:BS104) -> 0.77109617 | DW104: =SUM(BT104:BW104) -> 0.8731102 | DX104: =SUM(BX104:CA104) -> 0.81232288
B106: Operating Net Income (pre-stock options) | F106: =F85+F102-F103 -> -37.22 | G106: =G85+G102-G103 -> 2.838 | H106: =H85+H102-H103 -> 1.037 | I106: =I85+I102-I103 -> -41.326 | J106: =J85+J102-J103 -> -0.557 | K106: =K85+K102-K103 -> 15.445 | L106: =L85+L102-L103 -> 17.559714 | M106: =M85+M102-M103 -> 16.208 | ... CC106: =CC85+CC102-CC103 -> 719.22445 | CE106: =CE85+CE102-CE103 -> -74.671 | CF106: =CF85+CF102-CF103 -> 48.655714 | CG106: =CG85+CG102-CG103 -> 194.82658 | CH106: =CH85+CH102-CH103 -> 151.31604 | CI106: =CI85+CI102-CI103 -> 217.28768 | CJ106: =CJ85+CJ102-CJ103 -> 384.07899 | CK106: =CK85+CK102-CK103 -> 478.47663 | CL106: =CL85+CL102-CL103 -> 1015.7836 | ... DC106: =DC85+DC102-DC103 -> 4704.3157 | DL106: =SUM(AB106:AE106) -> 451.45546 | DM106: =SUM(AF106:AI106) -> 723.73965 | DN106: =SUM(AJ106:AM106) -> 838.32925 | DO106: =SUM(AN106:AQ106) -> 996.00751 | DP106: =SUM(AR106:AU106) -> 1174.7581 | DQ106: =SUM(AV106:AY106) -> 1018.8203 | DR106: =SUM(AZ106:BC106) -> 2681.1878 | DS106: =SUM(BD106:BG106) -> 2138.8522 | DT106: =SUM(BH106:BK106) -> 2158.776 | DU106: =SUM(BL106:BO106) -> 1787.796 | DV106: =DV85+DV102-DV103 -> 1921.239 | DW106: =DW85+DW102-DW103 -> 4158.898 | DX106: =DX85+DX102-DX103 -> 3988.7464
B108: Basic EPS
C109: EPS - ModelWare | F109: =F85/F122 -> -0.25141174 | G109: =G85/G122 -> 0.016579524 | H109: =H85/H122 -> 0.0058836879 | I109: =I85/I122 -> -0.2303683 | J109: =J85/J122 -> -0.0029844349 | K109: =K85/K122 -> 0.082289508 | L109: =L85/L122 -> 0.092375306 | M109: =M85/M122 -> 0.084600408 | ... CC109: =CC85/CC122 -> 2.1811911 | CE109: =CE85/CE122 -> -0.44258661 | CF109: =CF85/CF122 -> 0.25745399 | CG109: =CG85/CG122 -> 0.99604592 | CH109: =CH85/CH122 -> 0.73561519 | CI109: =CI85/CI122 -> 1.0446523 | CJ109: =CJ85/CJ122 -> 1.6784325 | CK109: =CK85/CK122 -> 2.0357837 | CL109: =CL85/CL122 -> 4.4824599 | ... DC109: =DC85/DC122 -> 12.645725 | DL109: =SUM(AB109:AE109) -> 1.9351498 | DM109: =SUM(AF109:AI109) -> 3.159236 | DN109: =SUM(AJ109:AM109) -> 3.6506723 | DO109: =SUM(AN109:AQ109) -> 4.2592961 | DP109: =SUM(AR109:AU109) -> 4.9082977
C110: EPS - Reported | F110: =F100/F122 -> -0.25141174 | G110: =G100/G122 -> 0.020955163 | H110: =H100/H122 -> -0.032612766 | I110: =I100/I122 -> -0.32578 | J110: =J100/J122 -> 0.10993651 | K110: =K100/K122 -> 0.067099648 | L110: =L100/L122 -> 0.10099223 | M110: =M100/M122 -> 0.068471628 | ... CC110: =CC100/CC122 -> 1.1405154 | CE110: =CE100/CE122 -> -0.57981211 | CF110: =CF100/CF122 -> 0.34620036 | CG110: =CG100/CG122 -> 0.93096412 | CH110: =CH100/CH122 -> 0.73561519 | CI110: =CI100/CI122 -> 0.95330613 | CJ110: =CJ100/CJ122 -> 1.8412232 | CK110: =CK100/CK122 -> 2.7064219 | CL110: =CL100/CL122 -> 3.9229138 | ... DC110: =DC100/DC122 -> 8.9962713 | DL110: =SUM(AB110:AE110) -> 2.0959953 | DM110: =SUM(AF110:AI110) -> 3.3337112 | DN110: =SUM(AJ110:AM110) -> 3.2317534 | DO110: =SUM(AN110:AQ110) -> 4.2817176 | DP110: =SUM(AR110:AU110) -> 4.7909064
C111: EPS - ModelWare excl. Stock Option Expense | F111: =F106/F122 -> -0.25141174 | G111: =G106/G122 -> 0.016579524 | H111: =H106/H122 -> 0.0058836879 | I111: =I106/I122 -> -0.2303683 | J111: =J106/J122 -> -0.0029844349 | K111: =K106/K122 -> 0.082289508 | L111: =L106/L122 -> 0.092375306 | M111: =M106/M122 -> 0.084600408 | ... CC111: =CC106/CC122 -> 2.3629975 | CE111: =CE106/CE122 -> -0.44258661 | CF111: =CF106/CF122 -> 0.25745399 | CG111: =CG106/CG122 -> 0.99604592 | CH111: =CH106/CH122 -> 0.73561519 | CI111: =CI106/CI122 -> 1.0446523 | CJ111: =CJ106/CJ122 -> 1.7864139 | CK111: =CK106/CK122 -> 2.1848248 | CL111: =CL106/CL122 -> 4.596306 | ... DC111: =DC106/DC122 -> 13.574367 | DL111: =SUM(AB111:AE111) -> 2.0665488 | DM111: =SUM(AF111:AI111) -> 3.2955465 | DN111: =SUM(AJ111:AM111) -> 3.7762579 | DO111: =SUM(AN111:AQ111) -> 4.4198058 | DP111: =SUM(AR111:AU111) -> 5.1154608
B113: Fully-diluted EPS
C114: EPS - ModelWare | F114: =(F85)/F124 -> -0.25141174 | G114: =(G85)/G124 -> 0.016579524 | H114: =(H85)/H124 -> 0.0058383722 | I114: =(I85)/I124 -> -0.23213854 | J114: =(J85)/J124 -> -0.0029844349 | K114: =(K85)/K124 -> 0.080600551 | L114: =(L85)/L124 -> 0.088526704 | M114: =(M85)/M124 -> 0.081976997 | ... CC114: =(CC85)/CC124 -> 2.1101238 | CE114: =(CE85)/CE124 -> -0.44258661 | CF114: =(CF85)/CF124 -> 0.25118072 | CG114: =(CG85)/CG124 -> 0.94806122 | CH114: =(CH85)/CH124 -> 0.69827432 | CI114: =(CI85)/CI124 -> 1.0013257 | CJ114: =(CJ85)/CJ124 -> 1.6109955 | CK114: =(CK85)/CK124 -> 1.9727284 | CL114: =(CL85)/CL124 -> 4.3832904 | ... DC114: =(DC85)/DC124 -> 12.021506 | DL114: =SUM(AB114:AE114) -> 1.8725394 | DM114: =SUM(AF114:AI114) -> 3.0787442 | DN114: =SUM(AJ114:AM114) -> 3.5797891 | DO114: =SUM(AN114:AQ114) -> 4.1728329 | DP114: =SUM(AR114:AU114) -> 4.8074705 | DQ114: =SUM(AV114:AY114) -> 4.0921586 | DR114: =SUM(AZ114:BC114) -> 10.313529 | DS114: =SUM(BD114:BG114) -> 8.3735919 | DT114: =SUM(BH114:BK114) -> 8.5610394 | DU114: =(DU85)/DU124 -> 7.1493759 | DV114: =(DV85)/DV124 -> 6.3215504 | DW114: =(DW85)/DW124 -> 12.852733 | DX114: =(DX85)/DX124 -> 12.104174 | DZ114: =(DZ85)/DZ124 -> -7.1249813
C115: EPS - Reported | F115: =F100/F124 -> -0.25141174 | G115: =G100/G124 -> 0.020955163 | H115: =H100/H124 -> -0.032361585 | I115: =I100/I124 -> -0.32828342 | J115: =J100/J124 -> 0.10993651 | K115: =K100/K124 -> 0.065722456 | L115: =L100/L124 -> 0.096784625 | M115: =M100/M124 -> 0.066348362 | ... BV115: =BV100/BV124 -> 2.225049 | BW115: =BW100/BW123 -> -2.7791892 | BX115: =BX100/BX124 -> 1.8517245 | BY115: =BY100/BY124 -> 1.5723755 | BZ115: =BZ100/BZ124 -> 2.0649134 | CA115: =CA100/CA124 -> 1.8101022 | CB115: =CB100/CB124 -> 1.2753297 | CC115: =CC100/CC124 -> 1.1033552 | CE115: =CE100/CE124 -> -0.57981211 | CF115: =CF100/CF124 -> 0.33776465 | CG115: =CG100/CG124 -> 0.88611475 | CH115: =CH100/CH124 -> 0.69827432 | CI115: =CI100/CI124 -> 0.91376809 | CJ115: =CJ100/CJ124 -> 1.7672455 | CK115: =CK100/CK124 -> 2.6225947 | CL115: =CL100/CL124 -> 3.8361236 | ... DC115: =DC100/DC124 -> 8.5521967 | DL115: =SUM(AB115:AE115) -> 2.0280259 | DM115: =SUM(AF115:AI115) -> 3.2464108 | DN115: =SUM(AJ115:AM115) -> 3.1654955 | DO115: =SUM(AN115:AQ115) -> 4.1945085 | DP115: =SUM(AR115:AU115) -> 4.6925769 | DQ115: =SUM(AV115:AY115) -> 2.9147646 | DR115: =SUM(AZ115:BC115) -> 8.2510252 | DS115: =SUM(BD115:BG115) -> 4.3197876 | DT115: =SUM(BH115:BK115) -> 6.5239817 | DU115: =DU100/DU124 -> 4.7404302 | DV115: =DV100/DV124 -> -1.5929732 | DW115: =DW100/DW124 -> 1.2751749 | DX115: =DX100/DX124 -> 7.3002484 | DZ115: =+DZ114*13 -> -92.624757
C116: EPS - ModelWare excl. Stock Option Expense | F116: =(F106)/F124 -> -0.25141174 | G116: =(G106)/G124 -> 0.016579524 | H116: =(H106)/H124 -> 0.0058383722 | I116: =(I106)/I124 -> -0.23213854 | J116: =(J106)/J124 -> -0.0029844349 | K116: =(K106)/K124 -> 0.080600551 | L116: =(L106)/L124 -> 0.088526704 | M116: =(M106)/M124 -> 0.081976997 | ... CC116: =(CC106)/CC124 -> 2.2860066 | CE116: =(CE106)/CE124 -> -0.44258661 | CF116: =(CF106)/CF124 -> 0.25118072 | CG116: =(CG106)/CG124 -> 0.94806122 | CH116: =(CH106)/CH124 -> 0.69827432 | CI116: =(CI106)/CI124 -> 1.0013257 | CJ116: =(CJ106)/CJ124 -> 1.7146384 | CK116: =(CK106)/CK124 -> 2.1171532 | CL116: =(CL106)/CL124 -> 4.4946178 | ... DC116: =(DC106)/DC124 -> 12.904308 | DL116: =SUM(AB116:AE116) -> 1.9996913 | DM116: =SUM(AF116:AI116) -> 3.2115357 | DN116: =SUM(AJ116:AM116) -> 3.7031824 | DO116: =SUM(AN116:AQ116) -> 4.3303467 | DP116: =SUM(AR116:AU116) -> 5.0104565 | DQ116: =SUM(AV116:AY116) -> 4.3018167 | DR116: =SUM(AZ116:BC116) -> 10.643583 | DS116: =SUM(BD116:BG116) -> 8.7930082 | DT116: =SUM(BH116:BK116) -> 8.9913578 | DU116: =(DU106)/DU124 -> 7.6157444 | DV116: =(DV106)/DV124 -> 7.1091175 | DW116: =(DW106)/DW124 -> 13.725736 | DX116: =(DX106)/DX124 -> 12.916509
B118: Dividend Payment | BB118: =CF!BB47 -> 0 | BC118: =CF!BC47 -> -121 | BD118: =CF!BD47 -> 0 | BE118: =CF!BE47 -> -60 | BF118: =CF!BF47 -> -59 | BG118: =CF!BG47 -> -59 | BH118: =CF!BH47 -> -71 | BI118: =CF!BI47 -> -70 | ... BP118: =CF!BP47 -> -116 | BQ118: =-BQ119*BQ121 -> -142 | BR118: =-BR119*BR121 -> -142.5 | BS118: =-BS119*BS121 -> -144 | BT118: =-BT119*BT121 -> -145.5 | BU118: =-BU119*BU121 -> -147 | BV118: =-BV119*BV121 -> -148.055 | BW118: =-BW119*BW121 -> -149.8068 | BX118: =-BX119*BX121 -> -150.36343 | ... CC118: =-CC119*CC121 -> -153.14722 | CQ118: =SUM(BB118:BE118) -> -181 | CR118: =SUM(BF118:BI118) -> -259 | CS118: =SUM(BJ118:BM118) -> -396 | CT118: =SUM(BN118:BQ118) -> -489 | CU118: =SUM(BR118:BU118) -> -579 | CV118: =SUM(BV118:BY118) -> -598.94755 | CW118: =SUM(BZ118:CC118) -> -606.06417 | CX118: =-CX119*CX121 -> -625.03105 | CY118: =-CY119*CY121 -> -638.80141 | CZ118: =-CZ119*CZ121 -> -653.67245 | DA118: =-DA119*DA121 -> -669.47363 | DB118: =-DB119*DB121 -> -685.22787 | DC118: =-DC119*DC121 -> -701.00713 | DL118: =SUM(AB118:AE118) -> 0 | DM118: =SUM(AF118:AI118) -> 0 | DN118: =SUM(AJ118:AM118) -> 0 | DO118: =SUM(AN118:AQ118) -> 0 | DP118: =SUM(AR118:AU118) -> 0 | DQ118: =SUM(AV118:AY118) -> 0 | DR118: =SUM(AZ118:BC118) -> -121 | DS118: =SUM(BD118:BG118) -> -178 | DT118: =SUM(BH118:BK118) -> -328 | DU118: =SUM(BI118:BL118) -> -350 | DV118: =SUM(BM118:BP118) -> -463 | DW118: =SUM(BQ118:BT118) -> -574 | DX118: =SUM(BU118:BX118) -> -595.22523
B119: Dividend Per Share | BB119: 0 | BC119: 0.5 | BD119: 0 | BE119: 0.25 | BF119: 0.25 | BG119: 0.25 | BH119: 0.3 | BI119: 0.3 | BJ119: 0.4 | BK119: 0.4 | BL119: 0.5 | BM119: 0.5 | BN119: 0.5 | BO119: 0.5 | BP119: =BO119 -> 0.5 | BQ119: 0.5 | BR119: 0.5 | BS119: 0.5 | BT119: 0.5 | BU119: 0.5 | BV119: =BU119 -> 0.5 | BW119: =BV119 -> 0.5 | BX119: =BW119 -> 0.5 | BY119: =BX119 -> 0.5 | BZ119: =BY119 -> 0.5 | CA119: =BZ119 -> 0.5 | CB119: =CA119 -> 0.5 | CC119: =CB119 -> 0.5 | CQ119: =SUM(BB119:BE119) -> 0.75 | CR119: =SUM(BF119:BI119) -> 1.1 | CS119: =SUM(BJ119:BM119) -> 1.8 | CT119: =SUM(BN119:BQ119) -> 2 | CU119: =SUM(BR119:BU119) -> 2 | CV119: =SUM(BV119:BY119) -> 2 | CW119: =SUM(BZ119:CC119) -> 2 | CX119: =CW119 -> 2 | CY119: =CX119 -> 2 | CZ119: =CY119 -> 2 | DA119: =CZ119 -> 2 | DB119: =DA119 -> 2 | DC119: =DB119 -> 2 | DL119: =SUM(AB119:AE119) -> 0 | DM119: =SUM(AF119:AI119) -> 0 | DN119: =SUM(AJ119:AM119) -> 0 | DO119: =SUM(AN119:AQ119) -> 0 | DP119: =SUM(AR119:AU119) -> 0 | DQ119: =SUM(AV119:AY119) -> 0 | DR119: =SUM(AZ119:BC119) -> 0.5 | DS119: =SUM(BD119:BG119) -> 0.75 | DT119: =SUM(BH119:BK119) -> 1.4 | DU119: =SUM(BI119:BL119) -> 1.6 | DV119: =SUM(BM119:BP119) -> 2 | DW119: =SUM(BQ119:BT119) -> 2 | DX119: =SUM(BU119:BX119) -> 2
B121: Period Ending Outstanding Shares | F121: 168.455 | G121: 183.191 | H121: 183.532 | I121: 192.8 | J121: 192.8 | K121: 194.346 | L121: 195.437 | M121: 195.438 | N121: 195.487 | O121: 195.505 | P121: 198.316 | Q121: 203.6 | R121: 206.2 | S121: 206.9 | T121: 208.2 | U121: 208.8 | V121: 208.8 | W121: 208.8 | X121: 212.4 | Y121: 214.6 | Z121: 215.7 | AA121: 217.5 | AB121: 220.6 | AC121: 221.7 | AD121: =AD573 -> 221.7 | AE121: =AE573 -> 222 | AF121: =AF573 -> 221.9 | AG121: =AG573 -> 219 | AH121: =AH573 -> 220.1 | AI121: =AI573 -> 222 | AJ121: =AJ573 -> 221.39674 | AK121: =AK573 -> 221.48571 | AL121: =AL573 -> 222 | AM121: =225-2 -> 223 | AN121: =225-1 -> 224 | AO121: 225 | AP121: 225 | AQ121: 228 | AR121: 229 | AS121: 231 | AT121: 230 | AU121: 232 | AV121: 232 | AW121: =233 -> 233 | AX121: =234 -> 234 | AY121: 235 | AZ121: 261 | BA121: 246 | BB121: 243 | BC121: 241 | BD121: 238 | BE121: 237 | BF121: 236 | BG121: 237 | BH121: =235 -> 235 | BI121: 234 | BJ121: 234 | BK121: 232 | BL121: 231 | BM121: 230 | BN121: 231 | BO121: 232 | BP121: 233 | BQ121: 284 | BR121: 285 | BS121: 288 | BT121: 291 | BU121: 294 | BV121: =BV573 -> 296.11 | BW121: =BW573 -> 299.6136 | BX121: =BX573 -> 300.72687 | BY121: =BY573 -> 301.44463 | BZ121: =BZ573 -> 301.44463 | CA121: =CA573 -> 301.94463 | CB121: =CB573 -> 302.44463 | CC121: =CC573 -> 306.29444 | CE121: 192.8 | CF121: 195.438 | CG121: =Q121 -> 203.6 | CH121: =U121 -> 208.8 | CI121: =Y121 -> 214.6 | CJ121: =AC121 -> 221.7 | CK121: =AG121 -> 219 | CL121: =AK121 -> 221.48571 | CM121: =AO121 -> 225 | CN121: =AS121 -> 231 | CO121: =AW121 -> 233 | CP121: =BA121 -> 246 | CQ121: =BE121 -> 237 | CR121: =BI121 -> 234 | CS121: =BM121 -> 230 | CT121: =BQ121 -> 284 | CU121: =CU573 -> 294 | CV121: =CV573 -> 301.44463 | CW121: =CW573 -> 306.29444 | CX121: =CX573 -> 312.51552 | CY121: =CY573 -> 319.4007 | CZ121: =CZ573 -> 326.83622 | DA121: =DA573 -> 334.73681 | DB121: =DB573 -> 342.61394 | DC121: =DC573 -> 350.50356 | DL121: =AVERAGE(AB121:AE121) -> 221.5 | DM121: =AVERAGE(AF121:AI121) -> 220.75 | DN121: =AVERAGE(AJ121:AM121) -> 221.97061 | DO121: =AVERAGE(AN121:AQ121) -> 225.5 | DP121: =AVERAGE(AR121:AU121) -> 230.5 | DQ121: =AVERAGE(AV121:AY121) -> 233.5 | DR121: =BC121 -> 241 | DS121: =BG121 -> 237 | DT121: =BK121 -> 232 | DU121: =BO121 -> 232 | DV121: =BS121 -> 288 | DW121: =BW121 -> 299.6136 | DX121: =CA121 -> 301.94463
B122: Avg Shares (Basic) | F122: 148.044 | G122: 171.175 | H122: 176.25 | I122: =168.715*4-SUM(F122:H122) -> 179.391 | J122: 186.635 | K122: 187.691 | L122: 190.091 | M122: 191.583 | N122: 192.464 | O122: 193.725 | P122: 196.258 | Q122: 199.953 | R122: 204.1 | S122: 205.4 | T122: 206.7 | U122: 206.5 | V122: 205.2 | W122: 205.1 | X122: 208.8 | Y122: 211.4 | Z122: 212.9 | AA122: 212.8 | AB122: 216.7 | AC122: 217.6 | AD122: 219 | AE122: 220 | AF122: 220 | AG122: 219 | AH122: 219 | AI122: 220 | AJ122: 222 | AK122: 222 | AL122: 222 | AM122: 222 | AN122: 223 | AO122: 223 | AP122: 225 | AQ122: 227 | AR122: 229 | AS122: 230 | AT122: 230 | AU122: 230 | AV122: 232 | AW122: 233 | AX122: 233 | AY122: 234 | AZ122: 241 | BA122: 254 | BB122: 246 | BC122: 242 | BD122: 239 | BE122: 236 | BF122: 236 | BG122: 236 | BH122: 235 | BI122: 234 | BJ122: 234 | BK122: 233 | BL122: 231 | BM122: 231 | BN122: 231 | BO122: 232 | BP122: 233 | BQ122: 261 | BR122: 285 | BS122: 286 | BT122: 289 | BU122: 292 | BV122: 295 | BW122: 296 | BX122: =BX575 -> 300.17023 | BY122: =BY575 -> 301.08575 | BZ122: =BZ575 -> 301.44463 | CA122: =CA575 -> 301.69463 | CB122: =CB575 -> 302.19463 | CC122: =CC575 -> 304.36953 | CE122: 168.715 | CF122: 188.988 | CG122: 195.6 | CH122: 205.7 | CI122: 208 | CJ122: 215 | CK122: 219 | CL122: 221 | CM122: 222 | CN122: 228 | CO122: 231 | CP122: 241 | CQ122: 241 | CR122: 235 | CS122: 232 | CT122: =AVERAGE(BN122:BQ122) -> 239.25 | CU122: =AVERAGE(BR122:BU122) -> 288 | CV122: =CV575 -> 297.72232 | CW122: =CW575 -> 303.86953 | CX122: =CX575 -> 309.40498 | CY122: =CY575 -> 315.95811 | CZ122: =CZ575 -> 323.11846 | DA122: =DA575 -> 330.78652 | DB122: =DB575 -> 338.67538 | DC122: =DC575 -> 346.55875 | DL122: =AVERAGE(AB122:AE122) -> 218.325 | DM122: =AVERAGE(AF122:AI122) -> 219.5 | DN122: =AVERAGE(AJ122:AM122) -> 222 | DO122: =AVERAGE(AN122:AQ122) -> 224.5 | DP122: =AVERAGE(AR122:AU122) -> 229.75 | DQ122: =AVERAGE(AV122:AY122) -> 233 | DR122: =AVERAGE(AZ122:BC122) -> 245.75 | DS122: =AVERAGE(BD122:BG122) -> 236.75 | DT122: =AVERAGE(BH122:BK122) -> 234 | DU122: =AVERAGE(BL122:BO122) -> 231.25 | DV122: =AVERAGE(BP122:BS122) -> 266.25 | DW122: =AVERAGE(BT122:BW122) -> 293 | DX122: =AVERAGE(BX122:CA122) -> 301.09881
B123: Avg Shares (Fully Diluted, GAAP) | F123: =F124 -> 148.044 | G123: =G124 -> 171.175 | H123: =H124 -> 177.618 | I123: =I124 -> 178.023 | J123: =J124 -> 186.635 | K123: =K124 -> 191.624 | L123: =L124 -> 198.355 | M123: =M124 -> 197.714 | ... BP123: =BP124 -> 234 | BQ123: 261 | BR123: 285 | BS123: 294 | BT123: 299 | BU123: 301 | BV123: 306 | BW123: 296 | BX123: =BX124 -> 308.27581 | BY123: =BY124 -> 307.51777 | BZ123: =BZ124 -> 309.06453 | CA123: =CA124 -> 310.38167 | CB123: =CB124 -> 312.22832 | CC123: =CC124 -> 314.62047
...

Sheet BS
B4: =IS!$B$5 -> Western Digital
B5: Balance Sheet
B7: ($ in millions) | F7: 2001A | J7: 2002A | N7: 2003A | R7: 2004A | V7: 2005A | Z7: 2006A | AD7: 2007A | AH7: 2008A | AL7: 2009A | AP7: 2010A | AT7: F2011A | AX7: F2012A | BB7: F2013A | BF7: F2014A | BJ7: F2015A | BN7: F2016A | BR7: F2017A | BV7: F2018E | BZ7: F2019E | CR7: Fiscal Year
F8: 36776 | G8: 36867 | H8: 36956 | I8: 37048 | J8: 37141 | K8: 37232 | L8: 37321 | M8: 37413 | N8: 37506 | O8: 37597 | P8: 37686 | Q8: 37778 | R8: 37871 | S8: 37962 | T8: 38052 | U8: 38144 | V8: 38237 | W8: 38328 | X8: 38417 | Y8: 38509 | Z8: 38602 | AA8: 38693 | AB8: 38782 | AC8: 38874 | AD8: 38967 | AE8: 39058 | AF8: 39147 | AG8: 39239 | AH8: 39331 | AI8: 39422 | AJ8: 39513 | AK8: 39605 | AL8: 39697 | AM8: 39788 | AN8: 39878 | AO8: 39970 | AP8: 40062 | AQ8: 40153 | AR8: 40243 | AS8: 40335 | AT8: 40451 | AU8: 40542 | AV8: 40632 | AW8: 40724 | AX8: 40816 | AY8: 40907 | AZ8: 40998 | BA8: 41090 | BB8: 41182 | BC8: 41273 | BD8: 41363 | BE8: 41455 | BF8: 41547 | BG8: 41638 | BH8: 41728 | BI8: 41820 | BJ8: 41912 | BK8: 42003 | BL8: 42093 | BM8: 42185 | BN8: 42277 | BO8: 42368 | BP8: 42459 | BQ8: 42551 | BR8: 42643 | BS8: 42734 | BT8: 42824 | BU8: 42916 | BV8: 43008 | BW8: 43100 | BX8: 43190 | BY8: 43281 | BZ8: 43373 | CA8: 43465 | CB8: 43555 | CC8: 43646 | CE8: 2001A | CF8: 2002A | CG8: 2003A | CH8: 2004A | CI8: 2005A | CJ8: 2006A | CK8: 2007A | CL8: 2008A | CM8: 2009A | CN8: 2010A | CO8: 2011A | CP8: 2012A | CQ8: 2013A | CR8: 2014A | CS8: 2015A | CT8: 2016A | CU8: 2017A | CV8: 2018E | CW8: 2019E | CX8: 2020E | CY8: 2021E | CZ8: 2022E | DA8: 2023E | DB8: 2024E | DC8: 2025E
B9: No. of Days in the Quarter | F9: 90 | G9: 91 | H9: 92 | I9: 92 | J9: 90 | K9: 91 | L9: 92 | M9: 92 | N9: 90 | O9: 91 | P9: 92 | Q9: 92 | R9: 90 | S9: 91 | T9: 93 | U9: 92 | V9: 91 | W9: 91 | X9: 92 | Y9: 92 | Z9: 90 | AA9: 91 | AB9: 92 | AC9: 92 | AD9: 90 | AE9: 91 | AF9: 92 | AG9: 92 | AH9: 90 | AI9: 91 | AJ9: 93 | AK9: 92 | AL9: 90 | AM9: 91 | AN9: 92 | AO9: 92 | AP9: 90 | AQ9: 91 | AR9: 92 | AS9: 92 | AT9: 90 | AU9: 91 | AV9: 92 | AW9: 92 | AX9: 90 | AY9: 91 | AZ9: 92 | BA9: 92 | BB9: 90 | BC9: 91 | BD9: 92 | BE9: 92 | BF9: 90 | BG9: 91 | BH9: 92 | BI9: 92 | BJ9: 90 | BK9: 91 | BL9: 92 | BM9: 92 | BN9: 92 | BO9: 92 | BP9: 92 | BQ9: 92 | BR9: 92 | BS9: 92 | BT9: 92 | BU9: 92 | BV9: 92 | BW9: 92 | BX9: 92 | BY9: 92 | BZ9: 92 | CA9: 92 | CB9: 92 | CC9: 92 | CE9: =SUM(F9:I9) -> 365 | CF9: =SUM(J9:M9) -> 365 | CG9: =SUM(N9:Q9) -> 365 | CH9: =SUM(R9:U9) -> 366 | CI9: =SUM(V9:Y9) -> 366 | CJ9: =SUM(Z9:AC9) -> 365 | CK9: =SUM(AD9:AG9) -> 365 | CL9: =SUM(AH9:AK9) -> 366 | CM9: =SUM(AL9:AO9) -> 365 | CN9: =SUM(AP9:AS9) -> 365 | CO9: 365 | CP9: 366 | CQ9: 365 | CR9: 365 | CS9: 365 | CT9: 366 | CU9: 366 | CV9: 366 | CW9: 366 | CX9: 366 | CY9: 366 | CZ9: 366 | DA9: 366 | DB9: 366 | DC9: 366
A11: X | B11: Assets
C12: Current Assets:
D13: Cash and cash equivalents | F13: 166.949 | G13: 179.383 | H13: 160.869 | I13: 167.582 | J13: 200.582 | K13: 193.317 | L13: 226.487 | M13: 223.728 | N13: 244.448 | O13: 326.944 | P13: 347.06 | Q13: 393.2 | R13: 285.8 | S13: 318.4 | T13: 359.9 | U13: =377.8-U14 -> 345.5 | V13: =405.2-V14 -> 372.9 | W13: =492.5-W14 -> 460.2 | X13: 461.1 | Y13: 485.2 | Z13: 506 | AA13: 550.2 | AB13: 543.4 | AC13: 550.7 | AD13: 603 | AE13: 676 | AF13: 704 | AG13: 700 | AH13: 651 | AI13: 917 | AJ13: 917 | AK13: 1104 | AL13: 1213 | AM13: 1376 | AN13: 1579 | AO13: 1794 | AP13: 2056 | AQ13: 2435 | AR13: 2826 | AS13: 2734 | AT13: 2858 | AU13: 3110 | AV13: 3230 | AW13: 3490 | AX13: 3675 | AY13: 3924 | AZ13: 3377 | BA13: 3208 | BB13: 3537 | BC13: 3816 | BD13: 4060 | BE13: 4309 | BF13: 4869 | BG13: 4655 | BH13: 4569 | BI13: 4804 | BJ13: 5159 | BK13: 4902 | BL13: 4812 | BM13: 5024 | BN13: 5081 | BO13: 5363 | BP13: 5887 | BQ13: 8151 | BR13: 4077 | BS13: 4940 | BT13: 5652 | BU13: 6354 | BV13: 6886 | BW13: 6272 | BX13: =CF!BX102 -> 5612.4284 | BY13: =CF!BY102 -> 5968.8382 | BZ13: =CF!BZ102 -> 6405.8155 | CA13: =CF!CA102 -> 6996.7837 | CB13: =CF!CB102 -> 6991.3984 | CC13: =CF!CC102 -> 6908.5314 | CE13: =I13 -> 167.582 | CF13: =M13 -> 223.728 | CG13: =Q13 -> 393.2 | CH13: =U13 -> 345.5 | CI13: =Y13 -> 485.2 | CJ13: =AC13 -> 550.7 | CK13: =AG13 -> 700 | CL13: =AK13 -> 1104 | CM13: =AO13 -> 1794 | CN13: =AS13 -> 2734 | CO13: =AW13 -> 3490 | CP13: =BA13 -> 3208 | CQ13: =BE13 -> 4309 | CR13: =BI13 -> 4804 | CS13: =BM13 -> 5024 | CT13: =BQ13 -> 8151 | CU13: =BU13 -> 6354 | CV13: =BY13 -> 5968.8382 | CW13: =CC13 -> 6908.5314 | CX13: =CF!CX102 -> 8272.9553 | CY13: =CF!CY102 -> 9518.4736 | CZ13: =CF!CZ102 -> 10957.792 | DA13: =CF!DA102 -> 12237.69 | DB13: =CF!DB102 -> 13799.459 | DC13: =CF!DC102 -> 15664.036
D14: Short-term investments | U14: 32.3 | V14: =U14 -> 32.3 | W14: =V14 -> 32.3 | X14: 113.2 | Y14: 113.2 | Z14: 75.3 | AA14: 94.5 | AB14: 130.7 | AC14: 148.1 | AD14: 148 | AE14: 154 | AF14: 171 | AG14: 207 | AH14: 200 | AI14: 50 | AJ14: 32 | AK14: 3 | AL14: 2 | AM14: 0 | AN14: 0 | AO14: 0 | AP14: 0 | AQ14: 0 | AR14: 0 | AS14: 0 | AT14: 0 | AU14: 0 | AV14: 0 | AW14: 0 | AX14: 0 | AY14: 0 | AZ14: 0 | BA14: 0 | BB14: 0 | BC14: 0 | BD14: 0 | BE14: 0 | BF14: 0 | BG14: 0 | BH14: 296 | BI14: 284 | BJ14: 222 | BK14: 241 | BL14: 228 | BM14: 262 | BN14: 347 | BO14: 497 | BP14: 146 | BQ14: 227 | BR14: 248 | BS14: 161 | BT14: 25 | BU14: 24 | BV14: 35 | BW14: 23 | BX14: =BW14+CF!BX35-CF!BX36 -> 23 | BY14: =BX14+CF!BY35-CF!BY36 -> 23 | BZ14: =BY14+CF!BZ35-CF!BZ36 -> 23 | CA14: =BZ14+CF!CA35-CF!CA36 -> 23 | CB14: =CA14+CF!CB35-CF!CB36 -> 23 | CC14: =CB14+CF!CC35-CF!CC36 -> 23 | CE14: =I14 -> 0 | CF14: =M14 -> 0 | CG14: =Q14 -> 0 | CH14: =U14 -> 32.3 | CI14: =Y14 -> 113.2 | CJ14: =AC14 -> 148.1 | CK14: =AG14 -> 207 | CL14: =AK14 -> 3 | CM14: =AO14 -> 0 | CN14: =AS14 -> 0 | CO14: =AW14 -> 0 | CP14: =BA14 -> 0 | CQ14: =BE14 -> 0 | CR14: =BI14 -> 284 | CS14: =BM14 -> 262 | CT14: =BQ14 -> 227 | CU14: =BU14 -> 24 | CV14: =BY14 -> 23 | CW14: =CC14 -> 23 | CX14: =CW14+CF!CX35-CF!CX36 -> 23 | CY14: =CX14+CF!CY35-CF!CY36 -> 23 | CZ14: =CY14+CF!CZ35-CF!CZ36 -> 23 | DA14: =CZ14+CF!DA35-CF!DA36 -> 23 | DB14: =DA14+CF!DB35-CF!DB36 -> 23 | DC14: =DB14+CF!DC35-CF!DC36 -> 23
D15: Accounts receivable, net | F15: 146.318 | G15: 173.966 | H15: 153.095 | I15: 127.767 | J15: 212.085 | K15: 222.822 | L15: 186.173 | M15: 218.832 | N15: 233.037 | O15: 246.304 | P15: 195.738 | Q15: 243.9 | R15: 328.7 | S15: 361.3 | T15: 308.3 | U15: 313.1 | V15: 400.7 | W15: 390.4 | X15: 398.6 | Y15: 402.9 | Z15: 470.4 | AA15: 428.3 | AB15: 483.2 | AC15: 481.5 | AD15: 614 | AE15: 668 | AF15: 715 | AG15: 697 | AH15: 985 | AI15: 1086 | AJ15: 1014 | AK15: 1010 | AL15: 1082 | AM15: 926 | AN15: 824 | AO15: 926 | AP15: 1131 | AQ15: 1365 | AR15: 1257 | AS15: 1256 | AT15: 1325 | AU15: 1250 | AV15: 1171 | AW15: 1206 | AX15: 1356 | AY15: 747 | AZ15: 2377 | BA15: 2364 | BB15: 1951 | BC15: 1732 | BD15: 1700 | BE15: 1793 | BF15: 1791 | BG15: 1959 | BH15: 1802 | BI15: 1989 | BJ15: 1915 | BK15: 1880 | BL15: 1696 | BM15: 1532 | BN15: 1616 | BO15: 1650 | BP15: 1254 | BQ15: 1461 | BR15: 2023 | BS15: 2004 | BT15: 1948 | BU15: 1948 | BV15: 2101 | BW15: 2052 | BX15: =IS!BX11*BS!BX118/BS!BX$9 -> 2027.6712 | BY15: =IS!BY11*BS!BY118/BS!BY$9 -> 1922.8779 | BZ15: =IS!BZ11*BS!BZ118/BS!BZ$9 -> 2094.3416 | CA15: =IS!CA11*BS!CA118/BS!CA$9 -> 2006.8911 | CB15: =IS!CB11*BS!CB118/BS!CB$9 -> 1913.9999 | CC15: =IS!CC11*BS!CC118/BS!CC$9 -> 1971.8538 | CE15: =I15 -> 127.767 | CF15: =M15 -> 218.832 | CG15: =Q15 -> 243.9 | CH15: =U15 -> 313.1 | CI15: =Y15 -> 402.9 | CJ15: =AC15 -> 481.5 | CK15: =AG15 -> 697 | CL15: =AK15 -> 1010 | CM15: =AO15 -> 926 | CN15: =AS15 -> 1256 | CO15: =AW15 -> 1206 | CP15: =BA15 -> 2364 | CQ15: =BE15 -> 1793 | CR15: =BI15 -> 1989 | CS15: =BM15 -> 1532 | CT15: =BQ15 -> 1461 | CU15: =BU15 -> 1948 | CV15: =BY15 -> 1922.8779 | CW15: =CC15 -> 1971.8538 | CX15: =IS!CX11*BS!CX118/BS!CX$9 -> 2293.3211 | CY15: =IS!CY11*BS!CY118/BS!CY$9 -> 2376.4592 | CZ15: =IS!CZ11*BS!CZ118/BS!CZ$9 -> 2466.916 | DA15: =IS!DA11*BS!DA118/BS!DA$9 -> 2581.2513 | DB15: =IS!DB11*BS!DB118/BS!DB$9 -> 2710.8327 | DC15: =IS!DC11*BS!DC118/BS!DC$9 -> 2857.5897
D16: Inventories | F16: 60.027 | G16: 78.177 | H16: 65.258 | I16: 78.905 | J16: 76.343 | K16: 96.441 | L16: 94.513 | M16: 73.395 | N16: 91.503 | O16: 105.792 | P16: 110.663 | Q16: 97.8 | R16: 122.9 | S16: 155.8 | T16: 149.1 | U16: 148.6 | V16: 144.3 | W16: 118.3 | X16: 135.5 | Y16: =SUM(Y17:Y19) -> 152.9 | Z16: =SUM(Z17:Z19) -> 172.8 | AA16: =SUM(AA17:AA19) -> 168.3 | AB16: =SUM(AB17:AB19) -> 177.6 | AC16: =SUM(AC17:AC19) -> 205.1 | AD16: =SUM(AD17:AD19) -> 216 | AE16: =SUM(AE17:AE19) -> 265 | AF16: =SUM(AF17:AF19) -> 243 | ... AV16: =SUM(AV17:AV19) -> 574 | AW16: 577 | AX16: =SUM(AX17:AX19) -> 645 | AY16: =SUM(AY17:AY19) -> 466 | AZ16: =SUM(AZ17:AZ19) -> 1282 | BA16: =SUM(BA17:BA19) -> 1210 | BB16: 1304 | BC16: =SUM(BC17:BC19) -> 1204 | BD16: =SUM(BD17:BD19) -> 1197 | BE16: =SUM(BE17:BE19) -> 1188 | BF16: 1244 | BG16: 1293 | BH16: 1277 | BI16: =SUM(BI17:BI19) -> 1226 | BJ16: =SUM(BJ17:BJ19) -> 1272 | BK16: =SUM(BK17:BK19) -> 1282 | BL16: =SUM(BL17:BL19) -> 1322 | BM16: =SUM(BM17:BM19) -> 1368 | BN16: =SUM(BN17:BN19) -> 1260 | BO16: =SUM(BO17:BO19) -> 1238 | BP16: =SUM(BP17:BP19) -> 1227 | ... BU16: =SUM(BU17:BU19) -> 2341 | BV16: 2302 | BW16: 2281 | BX16: =IS!BX16*BS!BX119/BX$9 -> 2239.9059 | BY16: =IS!BY16*BS!BY119/BY$9 -> 2320.9888 | BZ16: =IS!BZ16*BS!BZ119/BZ$9 -> 2497.4492 | CA16: =IS!CA16*BS!CA119/CA$9 -> 2518.2343 | CB16: =IS!CB16*BS!CB119/CB$9 -> 2343.321 | CC16: =IS!CC16*BS!CC119/CC$9 -> 2098.41 | CE16: =I16 -> 78.905 | CF16: =M16 -> 73.395 | CG16: =Q16 -> 97.8 | CH16: =U16 -> 148.6 | CI16: =Y16 -> 152.9 | CJ16: =AC16 -> 205.1 | CK16: =AG16 -> 259 | CL16: =AK16 -> 456 | CM16: =AO16 -> 376 | CN16: =AS16 -> 560 | CO16: =AW16 -> 577 | CP16: =BA16 -> 1210 | CQ16: =BE16 -> 1188 | CR16: =BI16 -> 1226 | CS16: =BM16 -> 1368 | CT16: =BQ16 -> 2129 | CU16: =BU16 -> 2341 | CV16: =BY16 -> 2320.9888 | CW16: =CC16 -> 2098.41 | CX16: =IS!CX16*BS!CX119/CX$9 -> 2339.0776 | CY16: =IS!CY16*BS!CY119/CY$9 -> 2477.4975 | CZ16: =IS!CZ16*BS!CZ119/CZ$9 -> 2579.5967 | DA16: =IS!DA16*BS!DA119/DA$9 -> 2717.4341 | DB16: =IS!DB16*BS!DB119/DB$9 -> 2872.4759 | DC16: =IS!DC16*BS!DC119/DC$9 -> 3047.2037
E17: Raw Materials and components | F17: -- | G17: -- | H17: -- | I17: 21.894 | J17: 9.75 | K17: 4.148 | L17: 12.924 | M17: 9.389 | N17: 7.259 | O17: 13.834 | P17: 12.917 | Q17: 11.8 | R17: 10.5 | S17: 18.6 | T17: 9 | U17: 26.4 | V17: 11 | W17: 12 | X17: 15 | Y17: 14.5 | Z17: 14 | AA17: 17.6 | AB17: 15.6 | AC17: 23.3 | AD17: 33 | AE17: 17 | AF17: 12 | AG17: 12 | AH17: 165 | AI17: 171 | AJ17: 153 | AK17: 144 | AL17: 129 | AM17: 124 | AN17: 104 | AO17: 97 | AP17: 96 | AQ17: 102 | AR17: 115 | AS17: 159 | AT17: 155 | AU17: 141 | AV17: 151 | AW17: 172 | AX17: 170 | AY17: 191 | AZ17: 329 | BA17: 245 | BB17: 237 | BC17: 193 | BD17: 191 | BE17: 167 | BF17: 208 | BG17: 201 | BH17: 204 | BI17: 168 | BJ17: 178 | BK17: 154 | BL17: 173 | BM17: 168 | BN17: 135 | BO17: 130 | BP17: 133 | BQ17: 569 | BR17: 610 | BS17: 586 | BT17: 581 | BU17: 646 | BV17: =BV$16*BV123 -> 635.23793 | BW17: =BW$16*BW123 -> 629.44297 | BX17: =BX$16*BX123 -> 618.10304 | BY17: =BY$16*BY123 -> 640.4779 | BZ17: =BZ$16*BZ123 -> 689.17224 | CA17: =CA$16*CA123 -> 694.90788 | CB17: =CB$16*CB123 -> 646.64048 | CC17: =CC$16*CC123 -> 579.05717 | CE17: =I17 -> 21.894 | CF17: =M17 -> 9.389 | CG17: =Q17 -> 11.8 | CH17: =U17 -> 26.4 | CI17: =Y17 -> 14.5 | CJ17: =AC17 -> 23.3 | CK17: =AG17 -> 12 | CL17: =AK17 -> 144 | CM17: =AO17 -> 97 | CN17: =AS17 -> 159 | CO17: =AW17 -> 172 | CP17: =BA17 -> 245 | CQ17: =BE17 -> 167 | CR17: =BI17 -> 168 | CS17: =BM17 -> 168 | CT17: =BQ17 -> 569 | CU17: =BU17 -> 646 | CV17: =BY17 -> 640.4779 | CW17: =CC17 -> 579.05717 | CX17: =CX$16*CX123 -> 645.4695 | CY17: =CY$16*CY123 -> 683.66656 | CZ17: =CZ$16*CZ123 -> 711.84086 | DA17: =DA$16*DA123 -> 749.87715 | DB17: =DB$16*DB123 -> 792.66102 | DC17: =DC$16*DC123 -> 840.87722
E18: Work-in-process | F18: -- | G18: -- | H18: -- | I18: 8.888 | J18: 27.141 | K18: 12.929 | L18: 14.091 | M18: 9.523 | N18: 16.708 | O18: 18.517 | P18: 17.088 | Q18: 19.6 | R18: 50.7 | S18: 58.6 | T18: 67 | U18: 51.6 | V18: 45 | W18: 50 | X18: 53 | Y18: 59.7 | Z18: 54 | AA18: 58.4 | AB18: 62.8 | AC18: 62.3 | AD18: 81 | AE18: 90 | AF18: 86 | AG18: 94 | AH18: 145 | AI18: 131 | AJ18: 131 | AK18: 145 | AL18: 168 | AM18: 159 | AN18: 152 | AO18: 154 | AP18: 173 | AQ18: 212 | AR18: 254 | AS18: 255 | AT18: 266 | AU18: 274 | AV18: 260 | AW18: 263 | AX18: 275 | AY18: 185 | AZ18: 667 | BA18: 552 | BB18: 559 | BC18: 581 | BD18: 583 | BE18: 575 | BF18: 579 | BG18: 581 | BH18: 519 | BI18: 493 | BJ18: 509 | BK18: 510 | BL18: 498 | BM18: 500 | BN18: 507 | BO18: 474 | BP18: 440 | BQ18: 589 | BR18: 680 | BS18: 617 | BT18: 627 | BU18: 632 | BV18: =BV$16*BV124 -> 621.47117 | BW18: =BW$16*BW124 -> 615.80179 | BX18: =BX$16*BX124 -> 604.70762 | BY18: =BY$16*BY124 -> 626.59758 | BZ18: =BZ$16*BZ124 -> 674.23661 | CA18: =CA$16*CA124 -> 679.84796 | CB18: =CB$16*CB124 -> 632.6266 | CC18: =CC$16*CC124 -> 566.50795 | CE18: =I18 -> 8.888 | CF18: =M18 -> 9.523 | CG18: =Q18 -> 19.6 | CH18: =U18 -> 51.6 | CI18: =Y18 -> 59.7 | CJ18: =AC18 -> 62.3 | CK18: =AG18 -> 94 | CL18: =AK18 -> 145 | CM18: =AO18 -> 154 | CN18: =AS18 -> 255 | CO18: =AW18 -> 263 | CP18: =BA18 -> 552 | CQ18: =BE18 -> 575 | CR18: =BI18 -> 493 | CS18: =BM18 -> 500 | CT18: =BQ18 -> 589 | CU18: =BU18 -> 632 | CV18: =BY18 -> 626.59758 | CW18: =CC18 -> 566.50795 | CX18: =CX$16*CX124 -> 631.481 | CY18: =CY$16*CY124 -> 668.85025 | CZ18: =CZ$16*CZ124 -> 696.41397 | DA18: =DA$16*DA124 -> 733.62594 | DB18: =DB$16*DB124 -> 775.48261 | DC18: =DC$16*DC124 -> 822.65387
E19: Finished goods | F19: -- | G19: -- | H19: -- | I19: 48.123 | J19: 39.452 | K19: 79.364 | L19: 67.498 | M19: 54.483 | N19: 67.536 | O19: 73.441 | P19: 80.658 | Q19: 66.4 | R19: 61.7 | S19: 78.6 | T19: 73 | U19: 70.6 | V19: 88 | W19: 56 | X19: 68 | Y19: 78.7 | Z19: 104.8 | AA19: 92.3 | AB19: 99.2 | AC19: 119.5 | AD19: 102 | AE19: 158 | AF19: 145 | AG19: 153 | AH19: 151 | AI19: 157 | AJ19: 171 | AK19: 167 | AL19: 180 | AM19: 163 | AN19: 129 | AO19: 125 | AP19: 126 | AQ19: 139 | AR19: 138 | AS19: 146 | AT19: 140 | AU19: 153 | AV19: 163 | AW19: 142 | AX19: 200 | AY19: 90 | AZ19: 286 | BA19: 413 | BB19: 508 | BC19: 430 | BD19: 423 | BE19: 446 | BF19: 457 | BG19: 511 | BH19: 554 | BI19: 565 | BJ19: 585 | BK19: 618 | BL19: 651 | BM19: 700 | BN19: 618 | BO19: 634 | BP19: 654 | BQ19: 971 | BR19: 819 | BS19: 882 | BT19: 1046 | BU19: 1063 | BV19: =BV$16*BV125 -> 1045.2909 | BW19: =BW$16*BW125 -> 1035.7552 | BX19: =BX$16*BX125 -> 1017.0952 | BY19: =BY$16*BY125 -> 1053.9133 | BZ19: =BZ$16*BZ125 -> 1134.0404 | CA19: =CA$16*CA125 -> 1143.4784 | CB19: =CB$16*CB125 -> 1064.0539 | CC19: =CC$16*CC125 -> 952.84485 | CE19: =I19 -> 48.123 | CF19: =M19 -> 54.483 | CG19: =Q19 -> 66.4 | CH19: =U19 -> 70.6 | CI19: =Y19 -> 78.7 | CJ19: =AC19 -> 119.5 | CK19: =AG19 -> 153 | CL19: =AK19 -> 167 | CM19: =AO19 -> 125 | CN19: =AS19 -> 146 | CO19: =AW19 -> 142 | CP19: =BA19 -> 413 | CQ19: =BE19 -> 446 | CR19: =BI19 -> 565 | CS19: =BM19 -> 700 | CT19: =BQ19 -> 971 | CU19: =BU19 -> 1063 | CV19: =BY19 -> 1053.9133 | CW19: =CC19 -> 952.84485 | CX19: =CX$16*CX125 -> 1062.1271 | CY19: =CY$16*CY125 -> 1124.9807 | CZ19: =CZ$16*CZ125 -> 1171.3419 | DA19: =DA$16*DA125 -> 1233.931 | DB19: =DB$16*DB125 -> 1304.3323 | DC19: =DC$16*DC125 -> 1383.6726
D20: Advances to Suppliers | AD20: 86 | AE20: 76 | AF20: 77 | AG20: 63 | AH20: 42 | AI20: 27 | AJ20: 36 | AK20: 36 | AL20: 0 | AM20: 0 | AN20: 0 | AO20: 0 | AP20: 0 | AQ20: 0 | AR20: 0 | AS20: 0 | AT20: 0 | AU20: 0 | AV20: 0 | AW20: 0 | AX20: 0 | AY20: 0 | AZ20: 0 | BA20: 0 | BB20: 0 | BC20: 0 | BD20: 0 | BE20: 0 | BF20: 0 | BG20: 0 | BH20: 0 | BI20: 0 | BJ20: 0 | BK20: 0 | BL20: 0 | BM20: 0 | BN20: 0 | BO20: 0 | BP20: 0 | BQ20: 0 | BR20: 0 | BS20: 0 | BT20: 0 | BU20: 0 | BV20: 0 | BW20: 0 | BX20: =BX15*BX128 -> 0 | BY20: =BY15*BY128 -> 0 | BZ20: =BZ15*BZ128 -> 0 | CA20: =CA15*CA128 -> 0 | CB20: =CB15*CB128 -> 0 | CC20: =CC15*CC128 -> 0 | CE20: =I20 -> 0 | CF20: =M20 -> 0 | CG20: =Q20 -> 0 | CH20: =U20 -> 0 | CI20: =Y20 -> 0 | CJ20: =AC20 -> 0 | CK20: =AG20 -> 63 | CL20: =AK20 -> 36 | CM20: =AO20 -> 0 | CN20: =AS20 -> 0 | CO20: =AW20 -> 0 | CP20: =BA20 -> 0 | CQ20: =BE20 -> 0 | CR20: =BI20 -> 0 | CS20: =BM20 -> 0 | CT20: =BQ20 -> 0 | CU20: =BU20 -> 0 | CV20: =BY20 -> 0 | CW20: =CC20 -> 0 | CX20: =CX15*CX128 -> 0 | CY20: =CY15*CY128 -> 0 | CZ20: =CZ15*CZ128 -> 0 | DA20: =DA15*DA128 -> 0 | DB20: =DB15*DB128 -> 0 | DC20: =DC15*DC128 -> 0
D21: Other current assets | F21: 25.567 | G21: 10.341 | H21: 18.054 | I21: 11.455 | J21: 11.107 | K21: 6.165 | L21: 17.388 | M21: 13.205 | N21: 8.981 | O21: 14.139 | P21: 13.374 | Q21: 9.2 | R21: 12.6 | S21: 9.9 | T21: 19 | U21: 17.8 | V21: 17.4 | W21: 17.6 | X21: 18.3 | Y21: 27 | Z21: 47.6 | AA21: 83.3 | AB21: 82.8 | AC21: 106.8 | AD21: 30 | AE21: 27 | AF21: 23 | AG21: 103 | AH21: 108 | AI21: 114 | AJ21: 175 | AK21: 122 | AL21: 174 | AM21: 147 | AN21: 134 | AO21: 134 | AP21: 168 | AQ21: 163 | AR21: 188 | AS21: 170 | AT21: 217 | AU21: 192 | AV21: 178 | AW21: 214 | AX21: 250 | AY21: 261 | AZ21: 409 | BA21: 359 | BB21: 394 | BC21: 423 | BD21: 383 | BE21: 308 | BF21: 357 | BG21: 381 | BH21: 362 | BI21: 417 | BJ21: 422 | BK21: 355 | BL21: 371 | BM21: 331 | BN21: 351 | BO21: 200 | BP21: 226 | BQ21: 616 | BR21: 666 | BS21: 416 | BT21: 434 | BU21: 389 | BV21: 496 | BW21: 485 | BX21: =IS!BX11*BX129 -> 392.72789 | BY21: =IS!BY11*BY129 -> 491.40213 | BZ21: =IS!BZ11*BZ129 -> 557.75625 | CA21: =IS!CA11*CA129 -> 399.2086 | CB21: =IS!CB11*CB129 -> 370.71156 | CC21: =IS!CC11*CC129 -> 442.99964 | CE21: =I21 -> 11.455 | CF21: =M21 -> 13.205 | CG21: =Q21 -> 9.2 | CH21: =U21 -> 17.8 | CI21: =Y21 -> 27 | CJ21: =AC21 -> 106.8 | CK21: =AG21 -> 103 | CL21: =AK21 -> 122 | CM21: =AO21 -> 134 | CN21: =AS21 -> 170 | CO21: =AW21 -> 214 | CP21: =BA21 -> 359 | CQ21: =BE21 -> 308 | CR21: =BI21 -> 417 | CS21: =BM21 -> 331 | CT21: =BQ21 -> 616 | CU21: =BU21 -> 389 | CV21: =BY21 -> 491.40213 | CW21: =CC21 -> 442.99964 | CX21: =IS!CX11*CX129 -> 475.30496 | CY21: =IS!CY11*CY129 -> 492.53584 | CZ21: =IS!CZ11*CZ129 -> 511.28356 | DA21: =IS!DA11*DA129 -> 534.98027 | DB21: =IS!DB11*DB129 -> 561.83682 | DC21: =IS!DC11*DC129 -> 592.25309
C22: Total Current Assets | F22: =SUM(F13:F16,F20:F21) -> 398.861 | G22: =SUM(G13:G16,G20:G21) -> 441.867 | H22: =SUM(H13:H16,H20:H21) -> 397.276 | I22: =SUM(I13:I16,I20:I21) -> 385.709 | J22: =SUM(J13:J16,J20:J21) -> 500.117 | K22: =SUM(K13:K16,K20:K21) -> 518.745 | L22: =SUM(L13:L16,L20:L21) -> 524.561 | M22: =SUM(M13:M16,M20:M21) -> 529.16 | ... CC22: =SUM(CC13:CC16,CC20:CC21) -> 11444.795 | CE22: =SUM(CE13:CE16,CE20:CE21) -> 385.709 | CF22: =SUM(CF13:CF16,CF20:CF21) -> 529.16 | CG22: =SUM(CG13:CG16,CG20:CG21) -> 744.1 | CH22: =SUM(CH13:CH16,CH20:CH21) -> 857.3 | CI22: =SUM(CI13:CI16,CI20:CI21) -> 1181.2 | CJ22: =SUM(CJ13:CJ16,CJ20:CJ21) -> 1492.2 | CK22: =SUM(CK13:CK16,CK20:CK21) -> 2029 | CL22: =SUM(CL13:CL16,CL20:CL21) -> 2731 | ... DC22: =SUM(DC13:DC16,DC20:DC21) -> 22184.082
CE23: =I23 -> 0 | CF23: =M23 -> 0 | CG23: =Q23 -> 0 | CH23: =U23 -> 0 | CI23: =Y23 -> 0 | CJ23: =AC23 -> 0 | CK23: =AG23 -> 0 | CL23: =AK23 -> 0 | CM23: =AO23 -> 0 | CN23: =AS23 -> 0 | CS23: =BM23 -> 0 | CT23: =BQ23 -> 0 | CU23: =BU23 -> 0
C24: Property, equipment and leasehold improvements, Gross | F24: =SUM(F25:F28) -> 393.61192 | G24: =SUM(G25:G28) -> 411.82545 | H24: =SUM(H25:H28) -> 419.92953 | I24: =SUM(I25:I28) -> 378.063 | J24: =SUM(J25:J28) -> 383.73576 | K24: =SUM(K25:K28) -> 396.94015 | L24: =SUM(L25:L28) -> 394.35839 | M24: =SUM(M25:M28) -> 367.443 | ... AC24: =SUM(AC25:AC28) -> 1143 | AD24: =-AD29+AD30 -> 1237 | AE24: =-AE29+AE30 -> 1325 | AF24: =-AF29+AF30 -> 1415 | AG24: =SUM(AG25:AG28) -> 1517 | AH24: =-AH29+AH30 -> 2370 | AI24: =-AI29+AI30 -> 2525 | AJ24: =-AJ29+AJ30 -> 2605 | AK24: =SUM(AK25:AK28) -> 2814 | AL24: =-AL29+AL30 -> 2937 | AM24: =-AM29+AM30 -> 3005 | AN24: =-AN29+AN30 -> 3074 | AO24: =SUM(AO25:AO28) -> 3175 | AP24: =-AP29+AP30 -> 3337 | AQ24: =-AQ29+AQ30 -> 3534 | AR24: =-AR29+AR30 -> 3723 | AS24: =SUM(AS25:AS28) -> 4223 | AT24: =-AT29+AT30 -> 4459 | AU24: =-AU29+AU30 -> 4642 | AV24: =-AV29+AV30 -> 4765 | AW24: =SUM(AW25:AW28) -> 4837 | AX24: =-AX29+AX30 -> 4980 | AY24: =-AY29+AY30 -> 5002 | AZ24: =-AZ29+AZ30 -> 7270 | BA24: =SUM(BA25:BA28) -> 7173 | BB24: =-BB29+BB30 -> 7446 | BC24: 7490 | BD24: 7561 | BE24: =SUM(BE25:BE28) -> 7616 | BF24: 7764 | BG24: 7879 | BH24: 7991 | BI24: =SUM(BI25:BI28) -> 8123 | BJ24: 8244 | BK24: 8353 | BL24: 8520 | BM24: =SUM(BM25:BM28) -> 8604 | BN24: 8635 | BO24: 8716 | BP24: 8778 | BQ24: =SUM(BQ25:BQ28) -> 9632 | BR24: =SUM(BR25:BR28) -> 9587 | BS24: =SUM(BS25:BS28) -> 9594 | BT24: =SUM(BT25:BT28) -> 9544 | BU24: =SUM(BU25:BU28) -> 9526 | BV24: 10255.424 | BW24: 10255.424 | BX24: =BX83 -> 10599.061 | BY24: =BY83 -> 10943.043 | BZ24: =BZ83 -> 11272.626 | CA24: =CA83 -> 11596.983 | CB24: =CB83 -> 11875.016 | CC24: =CC83 -> 12138.185 | CE24: =I24 -> 378.063 | CF24: =M24 -> 367.443 | CG24: =Q24 -> 420.2 | CH24: =U24 -> 648.5 | CI24: =Y24 -> 845.1 | CJ24: =AC24 -> 1143 | CK24: =AG24 -> 1517 | CL24: =AK24 -> 2814 | CM24: =AO24 -> 3175 | CN24: =AS24 -> 4223 | CO24: =AW24 -> 4837 | CP24: =BA24 -> 7173 | CQ24: =BE24 -> 7616 | CR24: =BI24 -> 8123 | CS24: =BM24 -> 8604 | CT24: =BQ24 -> 9632 | CU24: =BU24 -> 9526 | CV24: =BY24 -> 10943.043 | CW24: =CC24 -> 12138.185 | CX24: =CX83 -> 13468.87 | CY24: =CY83 -> 14847.796 | CZ24: =CZ83 -> 16389.318 | DA24: =DA83 -> 18002.285 | DB24: =DB83 -> 19696.225 | DC24: =DC83 -> 21481.87
D25: Machinery & Equipment | E25: Land and Buildings | F25: 53.99329 | G25: 56.491711 | H25: 57.603379 | I25: 54.06 | J25: 54.87116 | K25: 56.759283 | L25: 56.390111 | M25: 59.097 | N25: 60.008299 | O25: 62.311828 | P25: 64.396603 | Q25: 59.4 | R25: 103.96216 | S25: 114.85946 | T25: 116.46486 | U25: 73 | V25: 80.786312 | W25: 87.722242 | X25: 92.266473 | Y25: 77.5 | Z25: 82.498169 | AA25: 86.401529 | AB25: 94.899315 | AC25: 163 | AD25: =AD107*AD$24 -> 176.40507 | AE25: =AE107*AE$24 -> 188.95451 | AF25: =AF107*AF$24 -> 201.78915 | AG25: 189 | AH25: =AH107*AH$24 -> 295.27357 | AI25: =AI$24*AI107 -> 314.58471 | AJ25: =AJ$24*AJ107 -> 324.55175 | AK25: 478 | AL25: =AL$24*AL107 -> 498.89339 | AM25: =AM$24*AM107 -> 510.44421 | AN25: =AN$24*AN107 -> 522.16489 | AO25: 522 | AP25: =AP$24*AP107 -> 548.63433 | AQ25: =AQ$24*AQ107 -> 581.02299 | AR25: =AR$24*AR107 -> 612.09638 | AS25: 675 | AT25: =AT$24*AT107 -> 712.722 | AU25: =AU$24*AU107 -> 741.97253 | AV25: =AV$24*AV107 -> 761.63273 | AW25: 750 | AX25: =AX$24*AX107 -> 772.17283 | AY25: =AY$24*AY107 -> 775.58404 | AZ25: =AZ$24*AZ107 -> 1127.2483 | BA25: 1222 | BB25: =BB$24*BB107 -> 1268.5086 | BC25: =BC$24*BC107 -> 1276.0045 | BD25: =BD$24*BD107 -> 1288.1001 | BE25: 1231 | BF25: =BF$24*BF107 -> 1254.9217 | BG25: =BG$24*BG107 -> 1273.5096 | BH25: =BH$24*BH107 -> 1291.6125 | BI25: 1364 | BJ25: =BJ$24*BJ107 -> 1384.3181 | BK25: =BK$24*BK107 -> 1402.6212 | BL25: =BL$24*BL107 -> 1430.6635 | BM25: 1441 | BN25: =BN$24*BN107 -> 1446.1919 | BO25: =BO$24*BO107 -> 1459.7578 | BP25: =BP$24*BP107 -> 1470.1416 | BQ25: 1900 | BR25: 1920 | BS25: 1871 | BT25: 1883 | BU25: 1855 | BV25: =BV$24*BV107 -> 1997.0409 | BW25: =BW$24*BW107 -> 1997.0409 | BX25: =BX$24*BX107 -> 2063.9574 | BY25: =BY$24*BY107 -> 2130.941 | BZ25: =BZ$24*BZ107 -> 2195.1208 | CA25: =CA$24*CA107 -> 2258.2829 | CB25: =CB$24*CB107 -> 2312.4245 | CC25: =CC$24*CC107 -> 2363.6712 | CE25: =I25 -> 54.06 | CF25: =M25 -> 59.097 | CG25: =Q25 -> 59.4 | CH25: =U25 -> 73 | CI25: =Y25 -> 77.5 | CJ25: =AC25 -> 163 | CK25: =AG25 -> 189 | CL25: =AK25 -> 478 | CM25: =AO25 -> 522 | CN25: =AS25 -> 675 | CO25: =AW25 -> 750 | CP25: =BA25 -> 1222 | CQ25: =BE25 -> 1231 | CR25: =BI25 -> 1364 | CS25: =BM25 -> 1441 | CT25: =BQ25 -> 1900 | CU25: =BU25 -> 1855 | CV25: =BY25 -> 2130.941 | CW25: =CC25 -> 2363.6712 | CX25: =CX$24*CX107 -> 2622.7959 | CY25: =CY$24*CY107 -> 2891.3145 | CZ25: =CZ$24*CZ107 -> 3191.4953 | DA25: =DA$24*DA107 -> 3505.5888 | DB25: =DB$24*DB107 -> 3835.4501 | DC25: =DC$24*DC107 -> 4183.1691
D26: Furniture & Fixtures | E26: Machinery, equipment and software | F26: 313.28814 | G26: 327.78486 | H26: 334.23515 | I26: 305.966 | J26: 310.55696 | K26: 321.24326 | L26: 319.15384 | M26: 290.477 | N26: 294.95627 | O26: 306.27871 | P26: 316.52591 | Q26: 342.4 | R26: 599.27011 | S26: 662.0855 | T26: 671.33956 | U26: 539.7 | V26: 597.26538 | W26: 648.54376 | X26: 682.13993 | Y26: 730.8 | Z26: 777.93112 | AA26: 814.73854 | AB26: 894.86993 | AC26: =906+38 -> 944 | AD26: =AD108*AD$24 -> 1021.6343 | AE26: =AE108*AE$24 -> 1094.3132 | AF26: =AF108*AF$24 -> 1168.6439 | AG26: =1203+60 -> 1263 | AH26: =AH108*AH$24 -> 1973.1773 | AI26: =AI$24*AI108 -> 2102.2248 | AJ26: =AJ$24*AJ108 -> 2168.8299 | AK26: =2166+58 -> 2224 | AL26: =AL$24*AL108 -> 2276.175 | AM26: =AM$24*AM108 -> 2328.875 | AN26: =AN$24*AN108 -> 2382.35 | AO26: =2533+58 -> 2591 | AP26: =AP$24*AP108 -> 2723.2022 | AQ26: =AQ$24*AQ108 -> 2883.9666 | AR26: =AR$24*AR108 -> 3038.2025 | AS26: 3470 | AT26: =AT$24*AT108 -> 3663.919 | AU26: =AU$24*AU108 -> 3814.2884 | AV26: =AV$24*AV108 -> 3915.3564 | AW26: 3963 | AX26: =AX$24*AX108 -> 4080.1613 | AY26: =AY$24*AY108 -> 4098.1861 | AZ26: =AZ$24*AZ108 -> 5956.38 | BA26: 5211 | BB26: =BB$24*BB108 -> 5409.3275 | BC26: =BC$24*BC108 -> 5441.2923 | BD26: =BD$24*BD108 -> 5492.872 | BE26: 5738 | BF26: =BF$24*BF108 -> 5849.5053 | BG26: =BG$24*BG108 -> 5936.1478 | BH26: =BH$24*BH108 -> 6020.5302 | BI26: 6109 | BJ26: =BJ$24*BJ108 -> 6199.9995 | BK26: =BK$24*BK108 -> 6281.9743 | BL26: =BL$24*BL108 -> 6407.5686 | BM26: 6520 | BN26: =BN$24*BN108 -> 6543.4914 | BO26: =BO$24*BO108 -> 6604.8722 | BP26: =BP$24*BP108 -> 6651.855 | BQ26: 7070 | BR26: 7155 | BS26: =7064+174 -> 7238 | BT26: =7008+181 -> 7189 | BU26: =6868+284 -> 7152 | BV26: =BV$24*BV108 -> 7699.6424 | BW26: =BW$24*BW108 -> 7699.6424 | BX26: =BX$24*BX108 -> 7957.6406 | BY26: =BY$24*BY108 -> 8215.8976 | BZ26: =BZ$24*BZ108 -> 8463.3445 | CA26: =CA$24*CA108 -> 8706.8676 | CB26: =CB$24*CB108 -> 8915.6117 | CC26: =CC$24*CC108 -> 9113.195 | CE26: =I26 -> 305.966 | CF26: =M26 -> 290.477 | CG26: =Q26 -> 342.4 | CH26: =U26 -> 539.7 | CI26: =Y26 -> 730.8 | CJ26: =AC26 -> 944 | CK26: =AG26 -> 1263 | CL26: =AK26 -> 2224 | CM26: =AO26 -> 2591 | CN26: =AS26 -> 3470 | CO26: =AW26 -> 3963 | CP26: =BA26 -> 5211 | CQ26: =BE26 -> 5738 | CR26: =BI26 -> 6109 | CS26: =BM26 -> 6520 | CT26: =BQ26 -> 7070 | CU26: =BU26 -> 7152 | CV26: =BY26 -> 8215.8976 | CW26: =CC26 -> 9113.195 | CX26: =CX$24*CX108 -> 10112.257 | CY26: =CY$24*CY108 -> 11147.537 | CZ26: =CZ$24*CZ108 -> 12304.892 | DA26: =DA$24*DA108 -> 13515.887 | DB26: =DB$24*DB108 -> 14787.676 | DC26: =DC$24*DC108 -> 16128.316
D27: Leasehold Improvements | E27: Furniture and fixtures | F27: 9.2765719 | G27: 9.7058248 | H27: 9.8968202 | I27: 7.219 | J27: 7.3273197 | K27: 7.5794536 | L27: 7.5301556 | M27: 6.674 | N27: 6.7769157 | O27: 7.0370601 | P27: 7.2724999 | Q27: 6.8 | R27: 11.901392 | S27: 13.148894 | T27: 13.332678 | U27: 7 | V27: 7.7466327 | W27: 8.4117219 | X27: 8.84747 | Y27: 7.6 | Z27: 8.090143 | AA27: 8.4729241 | AB27: 9.3062554 | AC27: 8 | AD27: =AD109*AD$24 -> 8.6579178 | AE27: =AE109*AE$24 -> 9.2738408 | AF27: =AF109*AF$24 -> 9.903762 | AG27: 12 | AH27: =AH109*AH$24 -> 18.747528 | AI27: =AI$24*AI109 -> 19.973632 | AJ27: =AJ$24*AJ109 -> 20.60646 | AK27: 10 | AL27: =AL$24*AL109 -> 10.4371 | AM27: =AM$24*AM109 -> 10.678749 | AN27: =AN$24*AN109 -> 10.923952 | AO27: 9 | AP27: =AP$24*AP109 -> 9.4592126 | AQ27: =AQ$24*AQ109 -> 10.017638 | AR27: =AR$24*AR109 -> 10.553386 | AS27: 9 | AT27: =AT$24*AT109 -> 9.50296 | AU27: =AU$24*AU109 -> 9.8929671 | AV27: =AV$24*AV109 -> 10.155103 | AW27: 9 | AX27: =AX$24*AX109 -> 9.266074 | AY27: =AY$24*AY109 -> 9.3070085 | AZ27: =AZ$24*AZ109 -> 13.52698 | BA27: 15 | BB27: =BB$24*BB109 -> 15.570891 | BC27: =BC$24*BC109 -> 15.662903 | BD27: =BD$24*BD109 -> 15.811376 | BE27: =39 -> 39 | BF27: =BF$24*BF109 -> 39.757878 | BG27: =BG$24*BG109 -> 40.34677 | BH27: =BH$24*BH109 -> 40.920299 | BI27: 54 | BJ27: =BJ$24*BJ109 -> 54.804383 | BK27: =BK$24*BK109 -> 55.528992 | BL27: =BL$24*BL109 -> 56.639173 | BM27: 71 | BN27: =BN$24*BN109 -> 71.255811 | BO27: =BO$24*BO109 -> 71.924221 | BP27: =BP$24*BP109 -> 72.435844 | BQ27: 110 | BR27: 50 | BS27: 52 | BT27: 52 | BU27: 116 | BV27: =BV$24*BV109 -> 124.88234 | BW27: =BW$24*BW109 -> 124.88234 | BX27: =BX$24*BX109 -> 129.06688 | BY27: =BY$24*BY109 -> 133.25561 | BZ27: =BZ$24*BZ109 -> 137.26901 | CA27: =CA$24*CA109 -> 141.21877 | CB27: =CB$24*CB109 -> 144.60444 | CC27: =CC$24*CC109 -> 147.80909 | CE27: =I27 -> 7.219 | CF27: =M27 -> 6.674 | CG27: =Q27 -> 6.8 | CH27: =U27 -> 7 | CI27: =Y27 -> 7.6 | CJ27: =AC27 -> 8 | CK27: =AG27 -> 12 | CL27: =AK27 -> 10 | CM27: =AO27 -> 9 | CN27: =AS27 -> 9 | CO27: =AW27 -> 9 | CP27: =BA27 -> 15 | CQ27: =BE27 -> 39 | CR27: =BI27 -> 54 | CS27: =BM27 -> 71 | CT27: =BQ27 -> 110 | CU27: =BU27 -> 116 | CV27: =BY27 -> 133.25561 | CW27: =CC27 -> 147.80909 | CX27: =CX$24*CX109 -> 164.01312 | CY27: =CY$24*CY109 -> 180.80457 | CZ27: =CZ$24*CZ109 -> 199.57599 | DA27: =DA$24*DA109 -> 219.21741 | DB27: =DB$24*DB109 -> 239.84486 | DC27: =DC$24*DC109 -> 261.58901
D28: Land & Buildings | E28: Leashold Improvements | F28: 17.05392 | G28: 17.843053 | H28: 18.194176 | I28: 10.818 | J28: 10.980322 | K28: 11.358156 | L28: 11.284281 | M28: 11.195 | N28: 11.367631 | O28: 11.803999 | P28: 12.198927 | Q28: 11.6 | R28: 20.302375 | S28: 22.430467 | T28: 22.74398 | U28: 28.8 | V28: 31.87186 | W28: 34.608227 | X28: 36.401019 | Y28: 29.2 | Z28: 31.083181 | AA28: 32.553866 | AB28: 35.755613 | AC28: 28 | AD28: =AD110*AD$24 -> 30.302712 | AE28: =AE110*AE$24 -> 32.458443 | AF28: =AF110*AF$24 -> 34.663167 | AG28: 53 | AH28: =AH110*AH$24 -> 82.801582 | AI28: =AI$24*AI110 -> 88.216875 | AJ28: =AJ$24*AJ110 -> 91.011866 | AK28: 102 | AL28: =AL$24*AL110 -> 106.45842 | AM28: =AM$24*AM110 -> 108.92324 | AN28: =AN$24*AN110 -> 111.42431 | AO28: 53 | AP28: =AP$24*AP110 -> 55.704252 | AQ28: =AQ$24*AQ110 -> 58.992756 | AR28: =AR$24*AR110 -> 62.147717 | AS28: 69 | AT28: =AT$24*AT110 -> 72.856027 | AU28: =AU$24*AU110 -> 75.846081 | AV28: =AV$24*AV110 -> 77.85579 | AW28: 115 | AX28: =AX$24*AX110 -> 118.39983 | AY28: =AY$24*AY110 -> 118.92289 | AZ28: =AZ$24*AZ110 -> 172.84474 | BA28: =128+597 -> 725 | BB28: =BB$24*BB110 -> 752.59306 | BC28: =BC$24*BC110 -> 757.04029 | BD28: =BD$24*BD110 -> 764.21651 | BE28: =233+375 -> 608 | BF28: =BF$24*BF110 -> 619.81513 | BG28: =BG$24*BG110 -> 628.9958 | BH28: =BH$24*BH110 -> 637.93697 | BI28: =254+342 -> 596 | BJ28: =BJ$24*BJ110 -> 604.878 | BK28: =BK$24*BK110 -> 612.87554 | BL28: =BL$24*BL110 -> 625.12865 | BM28: =296+276 -> 572 | BN28: =BN$24*BN110 -> 574.0609 | BO28: =BO$24*BO110 -> 579.44584 | BP28: =BP$24*BP110 -> 583.56764 | BQ28: =307+245 -> 552 | BR28: =313+149 -> 462 | BS28: =314+119 -> 433 | BT28: =305+115 -> 420 | BU28: =259+144 -> 403 | BV28: =BV$24*BV110 -> 433.85848 | BW28: =BW$24*BW110 -> 433.85848 | BX28: =BX$24*BX110 -> 448.39614 | BY28: =BY$24*BY110 -> 462.94837 | BZ28: =BZ$24*BZ110 -> 476.89147 | CA28: =CA$24*CA110 -> 490.61348 | CB28: =CB$24*CB110 -> 502.37577 | CC28: =CC$24*CC110 -> 513.50917 | CE28: =I28 -> 10.818 | CF28: =M28 -> 11.195 | CG28: =Q28 -> 11.6 | CH28: =U28 -> 28.8 | CI28: =Y28 -> 29.2 | CJ28: =AC28 -> 28 | CK28: =AG28 -> 53 | CL28: =AK28 -> 102 | CM28: =AO28 -> 53 | CN28: =AS28 -> 69 | CO28: =AW28 -> 115 | CP28: =BA28 -> 725 | CQ28: =BE28 -> 608 | CR28: =BI28 -> 596 | CS28: =BM28 -> 572 | CT28: =BQ28 -> 552 | CU28: =BU28 -> 403 | CV28: =BY28 -> 462.94837 | CW28: =CC28 -> 513.50917 | CX28: =CX$24*CX110 -> 569.80419 | CY28: =CY$24*CY110 -> 628.14002 | CZ28: =CZ$24*CZ110 -> 693.35451 | DA28: =DA$24*DA110 -> 761.59153 | DB28: =DB$24*DB110 -> 833.25411 | DC28: =DC$24*DC110 -> 908.7963
C29: Less: Accumulated Depreciation and Amortization | F29: -293.50992 | G29: -307.09145 | H29: -313.13453 | I29: -271.897 | J29: -275.97676 | K29: -285.47315 | L29: -283.61639 | M29: -259.923 | N29: -263.93111 | O29: -274.0626 | P29: -283.23194 | Q29: -298.1 | R29: -521.73604 | S29: -576.42432 | T29: -584.48108 | U29: -373.8 | V29: -413.67019 | W29: -449.18595 | X29: -472.4549 | Y29: -450.1 | Z29: -481.80261 | AA29: -508.46686 | AB29: -538.43111 | AC29: -594 | AD29: =AD91 -> -639 | AE29: =AE91 -> -688 | AF29: =AF91 -> -743 | AG29: -776 | AH29: =AH91 -> -854 | AI29: =AI91 -> -965 | AJ29: =AJ91 -> -1076 | AK29: -1146 | AL29: =AL91 -> -1263 | AM29: =AM91 -> -1385 | AN29: =AN91 -> -1504 | AO29: -1591 | AP29: =AP91 -> -1712 | AQ29: =AQ91 -> -1838 | AR29: =AR91 -> -1967 | AS29: -2064 | AT29: =AT91 -> -2214 | AU29: =AU91 -> -2365 | AV29: =AV91 -> -2516 | AW29: -2613 | AX29: =AX91 -> -2771 | AY29: =AY91 -> -2911 | AZ29: =AZ91 -> -3099 | BA29: -3106 | BB29: =BB91 -> -3419 | BC29: -3552 | BD29: -3758 | BE29: -3916 | BF29: -4126 | BG29: -4370 | BH29: -4585 | BI29: -4830 | BJ29: -5042 | BK29: -5254 | BL29: -5469 | BM29: -5639 | BN29: -5745 | BO29: -5915 | BP29: -6091 | BQ29: -6129 | BR29: -6228 | BS29: -6356 | BT29: -6445 | BU29: -6493 | BV29: =BV30-BV24 -> -7207.4241 | BW29: =BW30-BW24 -> -7201.4241 | BX29: =BX91 -> -7577.1395 | BY29: =BY91 -> -7961.8199 | BZ29: =BZ91 -> -8358.5283 | CA29: =CA91 -> -8766.9142 | CB29: =CB91 -> -9186.057 | CC29: =CC91 -> -9619.8215 | CE29: =I29 -> -271.897 | CF29: =M29 -> -259.923 | CG29: =Q29 -> -298.1 | CH29: =U29 -> -373.8 | CI29: =Y29 -> -450.1 | CJ29: =AC29 -> -594 | CK29: =AG29 -> -776 | CL29: =AK29 -> -1146 | CM29: =AO29 -> -1591 | CN29: =AS29 -> -2064 | CO29: =AW29 -> -2613 | CP29: =BA29 -> -3106 | CQ29: =BE29 -> -3916 | CR29: =BI29 -> -4830 | CS29: =BM29 -> -5639 | CT29: =BQ29 -> -6129 | CU29: =BU29 -> -6493 | CV29: =BY29 -> -7961.8199 | CW29: =CC29 -> -9619.8215 | CX29: =CX91 -> -11448.897 | CY29: =CY91 -> -12864.73 | CZ29: =CZ91 -> -14426.586 | DA29: =DA91 -> -15859.569 | DB29: =DB91 -> -17430.341 | DC29: =DC91 -> -19146.094
C30: Property, equipment and leasehold improvements, net | F30: 100.102 | G30: 104.734 | H30: 106.795 | I30: 106.166 | J30: 107.759 | K30: 111.467 | L30: 110.742 | M30: 107.52 | N30: 109.178 | O30: 113.369 | P30: 117.162 | Q30: 122.1 | R30: 213.7 | S30: 236.1 | T30: 239.4 | U30: 274.7 | V30: 304 | W30: 330.1 | X30: 347.2 | Y30: 395 | Z30: 417.8 | AA30: 433.7 | AB30: 496.4 | AC30: 548.6 | AD30: 598 | AE30: 637 | AF30: 672 | AG30: 741 | AH30: 1516 | AI30: 1560 | AJ30: 1529 | AK30: 1668 | AL30: 1674 | AM30: 1620 | AN30: 1570 | AO30: 1584 | AP30: 1625 | AQ30: 1696 | AR30: 1756 | AS30: 2159 | AT30: 2245 | AU30: 2277 | AV30: 2249 | AW30: 2224 | AX30: 2209 | AY30: 2091 | AZ30: 4171 | BA30: 4067 | BB30: 4027 | BC30: 3938 | BD30: 3803 | BE30: 3700 | BF30: 3638 | BG30: 3509 | BH30: 3406 | BI30: 3293 | BJ30: 3202 | BK30: 3099 | BL30: 3051 | BM30: 2965 | BN30: 2890 | BO30: 2801 | BP30: 2687 | BQ30: 3503 | BR30: 3359 | BS30: 3238 | BT30: 3099 | BU30: 3033 | BV30: 3048 | BW30: 3054 | BX30: =BX24+BX29 -> 3021.9215 | BY30: =BY24+BY29 -> 2981.2226 | BZ30: =BZ24+BZ29 -> 2914.0975 | CA30: =CA24+CA29 -> 2830.0686 | CB30: =CB24+CB29 -> 2688.9594 | CC30: =CC24+CC29 -> 2518.3631 | CE30: =I30 -> 106.166 | CF30: =CF24+CF29 -> 107.52 | CG30: =CG24+CG29 -> 122.1 | CH30: =CH24+CH29 -> 274.7 | CI30: =CI24+CI29 -> 395 | CJ30: =AC30 -> 548.6 | CK30: =CK24+CK29 -> 741 | CL30: =CL24+CL29 -> 1668 | CM30: =CM24+CM29 -> 1584 | CN30: =CN24+CN29 -> 2159 | CO30: =AW30 -> 2224 | CP30: =BA30 -> 4067 | CQ30: =BE30 -> 3700 | CR30: =BI30 -> 3293 | CS30: =BM30 -> 2965 | CT30: =BQ30 -> 3503 | CU30: =BU30 -> 3033 | CV30: =BY30 -> 2981.2226 | CW30: =CC30 -> 2518.3631 | CX30: =CX24+CX29 -> 2019.9733 | CY30: =CY24+CY29 -> 1983.066 | CZ30: =CZ24+CZ29 -> 1962.732 | DA30: =DA24+DA29 -> 2142.7158 | DB30: =DB24+DB29 -> 2265.8844 | DC30: =DC24+DC29 -> 2335.7755
C31: Goodwill and Other Intangible assets | I31: 0 | J31: 0 | K31: 0 | L31: 0 | M31: 0 | N31: 0 | O31: 0 | P31: 0 | Q31: 0 | R31: 0 | S31: 32.9 | T31: 31.4 | U31: 0 | V31: 0 | W31: 0 | X31: 0 | Y31: 0 | Z31: 0 | AA31: 0 | AB31: 0 | AC31: 0 | AD31: 0 | AE31: 0 | AF31: 0 | AG31: 0 | AH31: 187 | AI31: 174 | AJ31: 187 | AK31: =116+81 -> 197 | AL31: =116+78 -> 194 | AM31: =116+70 -> 186 | AN31: =138+93 -> 231 | AO31: =139+89 -> 228 | AP31: =139+86 -> 225 | AQ31: =139+83 -> 222 | AR31: =139+80 -> 219 | AS31: =146+88 -> 234 | AT31: =150+83 -> 233 | AU31: =151+79 -> 230 | AV31: =151+75 -> 226 | AW31: =151+71 -> 222 | AX31: =151+67 -> 218 | AY31: 151 | AZ31: =1851+840 -> 2691 | BA31: 1975 | BB31: 1944 | BC31: 1907 | BD31: 1954 | BE31: 1954 | BF31: 2051 | BG31: 2555 | BH31: 2558 | BI31: 2559 | BJ31: 2559 | BK31: 2566 | BL31: 2745 | BM31: 2766 | BN31: 2766 | BO31: 2766 | BP31: 2766 | BQ31: =9951+5034 -> 14985 | BR31: =9967+4791 -> 14758 | BS31: 10005 | BT31: 10012 | BU31: 10014 | BV31: 10073 | BW31: 10076 | BX31: =BW31 -> 10076 | BY31: =BX31 -> 10076 | BZ31: =BY31 -> 10076 | CA31: =BZ31 -> 10076 | CB31: =CA31 -> 10076 | CC31: =CB31 -> 10076 | CE31: =I31 -> 0 | CF31: =M31 -> 0 | CG31: =Q31 -> 0 | CH31: =U31 -> 0 | CI31: =Y31 -> 0 | CJ31: =AC31 -> 0 | CK31: =AG31 -> 0 | CL31: =AK31 -> 197 | CM31: =AO31 -> 228 | CN31: =AS31 -> 234 | CO31: =AW31 -> 222 | CP31: =BA31 -> 1975 | CQ31: =BE31 -> 1954 | CR31: =BI31 -> 2559 | CS31: =BM31 -> 2766 | CT31: =BQ31 -> 14985 | CU31: =BU31 -> 10014 | CV31: =BY31 -> 10076 | CW31: =CC31 -> 10076 | CX31: =CW31 -> 10076 | CY31: =CX31 -> 10076 | CZ31: =CY31 -> 10076 | DA31: =CZ31 -> 10076 | DB31: =DA31 -> 10076 | DC31: =DB31 -> 10076
C32: Other Assets, net | F32: 63.764 | G32: 44.336 | H32: 41.07 | I32: 15.777 | J32: 11.569 | K32: 5.437 | L32: 2.155 | M32: 0 | N32: 1.24 | O32: 0.863 | P32: 0.543 | Q32: 0 | R32: 37.9 | S32: 1.4 | T32: 0 | U32: 27.2 | V32: 23.4 | W32: 19.8 | X32: 16.2 | Y32: 12.4 | Z32: 10.6 | AA32: 20.1 | AB32: 17.6 | AC32: 32.5 | AD32: 30 | AE32: 37 | AF32: 48 | AG32: 131 | AH32: 224 | AI32: 213 | AJ32: 198 | AK32: 279 | AL32: 276 | AM32: 270 | AN32: 269 | AO32: 249 | AP32: 249 | AQ32: 251 | AR32: 247 | AS32: 215 | AT32: 216 | AU32: 216 | AV32: 211 | AW32: 185 | AX32: 114 | AY32: =63+104 -> 167 | AZ32: 203 | BA32: =224+799 -> 1023 | BB32: =746+269 -> 1015 | BC32: =709+200 -> 909 | BD32: =656+174 -> 830 | BE32: =605+179 -> 784 | BF32: =616+240 -> 856 | BG32: =607+323 -> 930 | BH32: =539+523 -> 1062 | BI32: =454+473 -> 927 | BJ32: =406+495 -> 901 | BK32: =359+455 -> 814 | BL32: =400+551 -> 951 | BM32: =332+601 -> 933 | BN32: =319+631 -> 950 | BO32: =292+659 -> 951 | BP32: =268+486 -> 754 | BQ32: =1171+619 -> 1790 | BR32: =1217+553 -> 1770 | BS32: =4469+575+1082 -> 6126 | BT32: =1291+4144+589 -> 6024 | BU32: =1340+3823+594 -> 5757 | BV32: =1462+3545+557 -> 5564 | BW32: =1845+3230+522 -> 5597 | BX32: =BW32 -> 5597 | BY32: =BX32 -> 5597 | BZ32: =BY32 -> 5597 | CA32: =BZ32 -> 5597 | CB32: =CA32 -> 5597 | CC32: =CB32 -> 5597 | CE32: =I32 -> 15.777 | CF32: =M32 -> 0 | CG32: =Q32 -> 0 | CH32: =U32 -> 27.2 | CI32: =Y32 -> 12.4 | CJ32: =AC32 -> 32.5 | CK32: =AG32 -> 131 | CL32: =AK32 -> 279 | CM32: =AO32 -> 249 | CN32: =AS32 -> 215 | CO32: =AW32 -> 185 | CP32: =BA32 -> 1023 | CQ32: =BE32 -> 784 | CR32: =BI32 -> 927 | CS32: =BM32 -> 933 | CT32: =BQ32 -> 1790 | CU32: =BU32 -> 5757 | CV32: =BY32 -> 5597 | CW32: =CC32 -> 5597 | CX32: =CW32 -> 5597 | CY32: =CX32 -> 5597 | CZ32: =CY32 -> 5597 | DA32: =CZ32 -> 5597 | DB32: =DA32 -> 5597 | DC32: =DB32 -> 5597
B33: Total Assets | F33: =SUM(F30:F32,F22) -> 562.727 | G33: =SUM(G30:G32,G22) -> 590.937 | H33: =SUM(H30:H32,H22) -> 545.141 | I33: =SUM(I30:I32,I22) -> 507.652 | J33: =SUM(J30:J32,J22) -> 619.445 | K33: =SUM(K30:K32,K22) -> 635.649 | L33: =SUM(L30:L32,L22) -> 637.458 | M33: =SUM(M30:M32,M22) -> 636.68 | ... CC33: =SUM(CC30:CC32,CC22) -> 29636.158 | CE33: =SUM(CE30:CE32,CE22) -> 507.652 | CF33: =SUM(CF30:CF32,CF22) -> 636.68 | CG33: =SUM(CG30:CG32,CG22) -> 866.2 | CH33: =SUM(CH30:CH32,CH22) -> 1159.2 | CI33: =SUM(CI30:CI32,CI22) -> 1588.6 | CJ33: =SUM(CJ30:CJ32,CJ22) -> 2073.3 | CK33: =SUM(CK30:CK32,CK22) -> 2901 | CL33: =SUM(CL30:CL32,CL22) -> 4875 | ... DC33: =SUM(DC30:DC32,DC22) -> 40192.858
CE34: =I34 -> 0 | CF34: =M34 -> 0 | CG34: =Q34 -> 0 | CH34: =U34 -> 0 | CI34: =Y34 -> 0 | CJ34: =AC34 -> 0 | CK34: =AG34 -> 0 | CL34: =AK34 -> 0 | CM34: =AO34 -> 0 | CN34: =AS34 -> 0 | CS34: =BM34 -> 0 | CT34: =BN34 -> 0 | CU34: =BO34 -> 0
B35: Liabilities
C36: Current Liabilities:
D37: Accounts payable | F37: 236.471 | G37: 263.001 | H37: 234.851 | I37: 224.544 | J37: 319.015 | K37: 323.33 | L37: 316.932 | M37: 302.998 | N37: 344.389 | O37: 352.249 | P37: 348.332 | Q37: 352.3 | R37: 402.6 | S37: 471.7 | T37: 420.5 | U37: 434.9 | V37: 535.6 | W37: 521.5 | X37: 551 | Y37: 569.1 | Z37: 648.1 | AA37: 580.2 | AB37: 597.4 | AC37: 631.8 | AD37: 750 | AE37: 816 | AF37: 851 | AG37: 882 | AH37: 1106 | AI37: 1216 | AJ37: 1144 | AK37: 1181 | AL37: 1215 | AM37: 1075 | AN37: 1001 | AO37: 1101 | AP37: 1342 | AQ37: 1507 | AR37: 1508 | AS37: 1507 | AT37: 1703 | AU37: 1628 | AV37: 1486 | AW37: 1545 | AX37: 1708 | AY37: 883 | AZ37: 2774 | BA37: 2773 | BB37: 2545 | BC37: 2185 | BD37: 2037 | BE37: 1990 | BF37: 2061 | BG37: 2106 | BH37: 1902 | BI37: 1971 | BJ37: 2016 | BK37: 2071 | BL37: 2020 | BM37: 1881 | BN37: 1799 | BO37: =1806+32 -> 1838 | BP37: 1571 | BQ37: =1888+168 -> 2056 | BR37: =1946+190 -> 2136 | BS37: =2012+175 -> 2187 | BT37: =2185+194 -> 2379 | BU37: =2144+206 -> 2350 | BV37: =2066+226 -> 2292 | BW37: =1921+250 -> 2171 | BX37: =IS!BX16*BS!BX120/BS!BX$9 -> 2270.5895 | BY37: =IS!BY16*BS!BY120/BS!BY$9 -> 2385.4607 | BZ37: =IS!BZ16*BS!BZ120/BS!BZ$9 -> 2531.1985 | CA37: =IS!CA16*BS!CA120/BS!CA$9 -> 2552.2645 | CB37: =IS!CB16*BS!CB120/BS!CB$9 -> 2375.4213 | CC37: =IS!CC16*BS!CC120/BS!CC$9 -> 2066.0794 | CE37: =I37 -> 224.544 | CF37: =M37 -> 302.998 | CG37: =Q37 -> 352.3 | CH37: =U37 -> 434.9 | CI37: =Y37 -> 569.1 | CJ37: =AC37 -> 631.8 | CK37: =AG37 -> 882 | CL37: =AK37 -> 1181 | CM37: =AO37 -> 1101 | CN37: =AS37 -> 1507 | CO37: =AW37 -> 1545 | CP37: =BA37 -> 2773 | CQ37: =BE37 -> 1990 | CR37: =BI37 -> 1971 | CS37: =BM37 -> 1881 | CT37: =BQ37 -> 2056 | CU37: =BU37 -> 2350 | CV37: =BY37 -> 2385.4607 | CW37: =CC37 -> 2066.0794 | CX37: =IS!CX16*BS!CX120/BS!CX$9 -> 2268.1964 | CY37: =IS!CY16*BS!CY120/BS!CY$9 -> 2403.5424 | CZ37: =IS!CZ16*BS!CZ120/BS!CZ$9 -> 2502.5938 | DA37: =IS!DA16*BS!DA120/BS!DA$9 -> 2636.3166 | DB37: =IS!DB16*BS!DB120/BS!DB$9 -> 2786.7304 | DC37: =IS!DC16*BS!DC120/BS!DC$9 -> 2956.2424
D38: Customer Advances | AH38: 59 | AI38: 51 | AJ38: 28 | AK38: 0 | AL38: 0 | AM38: 0 | AN38: 0 | AO38: 0 | AP38: 0 | AQ38: 0 | AR38: 0 | AS38: 0 | AT38: 0 | AU38: 0 | AV38: 0 | AW38: 0 | AX38: 0 | AY38: 0 | AZ38: 0 | BA38: 0 | BB38: 0 | BC38: 0 | BD38: 0 | BE38: 0 | BF38: 0 | BG38: 0 | BH38: 0 | BI38: 0 | BJ38: 0 | BK38: =BJ38 -> 0 | BL38: 0 | BM38: 0 | BN38: 0 | BO38: 0 | BP38: 0 | BQ38: 0 | BR38: 0 | BS38: 0 | BT38: =BS38 -> 0 | BU38: 0 | BV38: 0 | BW38: 0 | BX38: =BW38 -> 0 | BY38: =BX38 -> 0 | BZ38: =BY38 -> 0 | CA38: =BZ38 -> 0 | CB38: =CA38 -> 0 | CC38: =CB38 -> 0 | CE38: =I38 -> 0 | CF38: =M38 -> 0 | CG38: =Q38 -> 0 | CH38: =U38 -> 0 | CI38: =Y38 -> 0 | CJ38: =AC38 -> 0 | CK38: =AG38 -> 0 | CL38: =AK38 -> 0 | CM38: =AO38 -> 0 | CN38: =AS38 -> 0 | CO38: =AW38 -> 0 | CP38: =BA38 -> 0 | CQ38: =BE38 -> 0 | CR38: =BI38 -> 0 | CS38: =BM38 -> 0 | CT38: =BQ38 -> 0 | CU38: =BU38 -> 0 | CV38: =BY38 -> 0 | CW38: =CC38 -> 0 | CX38: =CW38 -> 0 | CY38: =CX38 -> 0 | CZ38: =CY38 -> 0 | DA38: =CZ38 -> 0 | DB38: =DA38 -> 0 | DC38: =DB38 -> 0
D39: Accrued expenses | F39: 113.459 | G39: 109.577 | H39: 95.133 | I39: 82.741 | J39: 111.24 | K39: 114.585 | L39: 73.132 | M39: 103.474 | N39: 115.891 | O39: 142.048 | P39: 132.108 | Q39: 112.4 | R39: 181.1 | S39: 149.7 | T39: 139 | U39: 136.8 | V39: 160.3 | W39: 184.8 | X39: 188.1 | Y39: 229.3 | Z39: 110.1 | AA39: 135.3 | AB39: 137.9 | AC39: 131 | AD39: 128 | AE39: 140 | AF39: 125 | AG39: 163 | AH39: 211 | AI39: 234 | AJ39: 226 | AK39: 266 | AL39: 243 | AM39: 243 | AN39: 252 | AO39: 247 | AP39: 218 | AQ39: 288 | AR39: 225 | AS39: 281 | AT39: 227 | AU39: 262 | AV39: 250 | AW39: 349 | AX39: 348 | AY39: 364 | AZ39: 837 | BA39: 858 | BB39: 774 | BC39: 722 | BD39: 837 | BE39: =480+453+706 -> 1639 | BF39: =406+388+719 -> 1513 | BG39: =732+479+456 -> 1667 | BH39: =745+455+409 -> 1609 | BI39: =412+460+758 -> 1630 | BJ39: =772+433+438 -> 1643 | BK39: =496+451 -> 947 | BL39: =0+503+398 -> 901 | BM39: =470+330 -> 800 | BN39: =528+336 -> 864 | BO39: =505+315 -> 820 | BP39: =579+282 -> 861 | BQ39: =995+392 -> 1387 | BR39: =983+552 -> 1535 | BS39: =1001+581 -> 1582 | BT39: =1073+480 -> 1553 | BU39: =1069+506 -> 1575 | BV39: =1271+468 -> 1739 | BW39: =1191+523 -> 1714 | BX39: =(IS!BX16+IS!BX67)*BS!BX130-BX40 -> 1588.1751 | BY39: =(IS!BY16+IS!BY67)*BS!BY130-BY40 -> 1647.4737 | BZ39: =(IS!BZ16+IS!BZ67)*BS!BZ130-BZ40 -> 1900.3947 | CA39: =(IS!CA16+IS!CA67)*BS!CA130-CA40 -> 1908.8073 | CB39: =(IS!CB16+IS!CB67)*BS!CB130-CB40 -> 1641.1165 | CC39: =(IS!CC16+IS!CC67)*BS!CC130-CC40 -> 1602.0514 | CE39: =I39 -> 82.741 | CF39: =M39 -> 103.474 | CG39: =Q39 -> 112.4 | CH39: =U39 -> 136.8 | CI39: =Y39 -> 229.3 | CJ39: =AC39 -> 131 | CK39: =AG39 -> 163 | CL39: =AK39 -> 266 | CM39: =AO39 -> 247 | CN39: =AS39 -> 281 | CO39: =AW39 -> 349 | CP39: =BA39 -> 858 | CQ39: =BE39 -> 1639 | CR39: =BI39 -> 1630 | CS39: =BM39 -> 800 | CT39: =BQ39 -> 1387 | CU39: =BU39 -> 1575 | CV39: =BY39 -> 1647.4737 | CW39: =CC39 -> 1602.0514 | CX39: =(IS!CX16+IS!CX67)*BS!CX130-CX40 -> 1719.4455 | CY39: =(IS!CY16+IS!CY67)*BS!CY130-CY40 -> 1790.343 | CZ39: =(IS!CZ16+IS!CZ67)*BS!CZ130-CZ40 -> 1855.6622 | DA39: =(IS!DA16+IS!DA67)*BS!DA130-DA40 -> 1945.3689 | DB39: =(IS!DB16+IS!DB67)*BS!DB130-DB40 -> 2049.4534 | DC39: =(IS!DC16+IS!DC67)*BS!DC130-DC40 -> 2166.9067
D40: Accrued warranty | F40: 30.989 | G40: 35.752 | H40: 33.856 | I40: 30.943 | L40: 28.471 | Q40: 41 | Z40: 78.1 | AA40: 76.6 | AB40: 78.2 | AC40: 71.6 | AD40: 74 | AE40: 72 | AF40: 74 | AG40: 73 | AH40: 76 | AI40: 80 | AJ40: 85 | AK40: 90 | AL40: 93 | AM40: 94 | AN40: 93 | AO40: 95 | AP40: 101 | AQ40: 118 | AR40: 124 | AS40: 129 | AT40: 131 | AU40: 135 | AV40: 134 | AW40: 132 | AX40: 135 | AY40: 124 | AZ40: 194 | BA40: 171 | BB40: 146 | BC40: 131 | BD40: 122 | BE40: 114 | BF40: 123 | BG40: 117 | BH40: 111 | BI40: 119 | BJ40: 134 | BK40: 146 | BL40: 156 | BM40: 150 | BN40: 141 | BO40: 144 | BP40: 146 | BQ40: 172 | BR40: 170 | BS40: 190 | BT40: 196 | BU40: 186 | BV40: 180 | BW40: 194 | BX40: =IS!BX11*BS!BX131 -> 245.45493 | BY40: =IS!BY11*BS!BY131 -> 245.70106 | BZ40: =IS!BZ11*BS!BZ131 -> 253.52557 | CA40: =IS!CA11*BS!CA131 -> 249.50537 | CB40: =IS!CB11*BS!CB131 -> 231.69473 | CC40: =IS!CC11*BS!CC131 -> 221.45596 | CE40: =I40 -> 30.943 | CF40: =M40 -> 0 | CG40: =Q40 -> 41 | CH40: =U40 -> 0 | CI40: =Y40 -> 0 | CJ40: =AC40 -> 71.6 | CK40: =AG40 -> 73 | CL40: =AK40 -> 90 | CM40: =AO40 -> 95 | CN40: =AS40 -> 129 | CO40: =AW40 -> 132 | CP40: =BA40 -> 171 | CQ40: =BE40 -> 114 | CR40: =BI40 -> 119 | CS40: =BM40 -> 150 | CT40: =BQ40 -> 172 | CU40: =BU40 -> 186 | CV40: =BY40 -> 245.70106 | CW40: =CC40 -> 221.45596 | CX40: =IS!CX11*BS!CX131 -> 237.60542 | CY40: =IS!CY11*BS!CY131 -> 246.21916 | CZ40: =IS!CZ11*BS!CZ131 -> 255.59116 | DA40: =IS!DA11*BS!DA131 -> 267.43716 | DB40: =IS!DB11*BS!DB131 -> 280.86278 | DC40: =IS!DC11*BS!DC131 -> 296.06791
D41: Short-term debt | AH41: 999 | AI41: 760 | AJ41: 0 | AK41: 0 | AL41: 0 | AM41: 0 | AN41: 0 | AO41: 0 | AP41: 0 | AQ41: 0 | AR41: 0 | AS41: 0 | AT41: 0 | AU41: 0 | AV41: 0 | AW41: 0 | AX41: 0 | AY41: 0 | AZ41: 500 | BA41: 0 | BB41: 0 | BC41: 0 | BD41: 0 | BE41: 0 | BF41: 500 | BG41: 500 | BH41: 0 | BI41: 0 | BJ41: 0 | BK41: 0 | BL41: 0 | BM41: 255 | BN41: 255 | BO41: 255 | BP41: 0 | BQ41: 0 | BR41: 0 | BS41: 0 | BT41: 0 | BU41: 0 | BV41: 0 | BW41: 0 | BX41: =BW41+CF!BX35-CF!BX36 -> 0 | BY41: =BX41+CF!BY35-CF!BY36 -> 0 | BZ41: =BY41+CF!BZ35-CF!BZ36 -> 0 | CA41: =BZ41+CF!CA35-CF!CA36 -> 0 | CB41: =CA41+CF!CB35-CF!CB36 -> 0 | CC41: =CB41+CF!CC35-CF!CC36 -> 0 | CE41: =I41 -> 0 | CF41: =M41 -> 0 | CG41: =Q41 -> 0 | CH41: =U41 -> 0 | CI41: =Y41 -> 0 | CJ41: =AC41 -> 0 | CK41: =AG41 -> 0 | CL41: =AK41 -> 0 | CM41: =AO41 -> 0 | CN41: =AS41 -> 0 | CO41: =AW41 -> 0 | CP41: =BA41 -> 0 | CQ41: =BE41 -> 0 | CR41: =BI41 -> 0 | CS41: =BM41 -> 255 | CT41: =BQ41 -> 0 | CU41: =BU41 -> 0 | CV41: =BY41 -> 0 | CW41: =CC41 -> 0 | CX41: =CW41+CF!CX35-CF!CX36 -> 0 | CY41: =CX41+CF!CY35-CF!CY36 -> 0 | CZ41: =CY41+CF!CZ35-CF!CZ36 -> 0 | DA41: =CZ41+CF!DA35-CF!DA36 -> 0 | DB41: =DA41+CF!DB35-CF!DB36 -> 0 | DC41: =DB41+CF!DC35-CF!DC36 -> 0
D42: Current portion of long-term debt | I42: 2.118 | J42: 0 | K42: 0 | L42: 0 | M42: 0 | N42: 0 | O42: 0 | P42: 0 | Q42: 0 | R42: 0 | S42: 3.1 | T42: 6.3 | U42: 15.2 | V42: 19.8 | W42: 19.9 | X42: 19.9 | Y42: 20.1 | Z42: 22.2 | AA42: 24.9 | AB42: 25 | AC42: 24.6 | AD42: 30 | AE42: 28 | AF42: 14 | AG42: 12 | AH42: 12 | AI42: 11 | AJ42: 11 | AK42: 27 | AL42: 45 | AM42: 60 | AN42: 77 | AO42: 82 | AP42: 88 | AQ42: 94 | AR42: 100 | AS42: 106 | AT42: 113 | AU42: 119 | AV42: 125 | AW42: 144 | AX42: 163 | AY42: 181 | AZ42: 230 | BA42: 230 | BB42: 230 | BC42: 288 | BD42: 230 | BE42: 230 | BF42: 230 | BG42: 230 | BH42: 125 | BI42: 125 | BJ42: 125 | BK42: 125 | BL42: 141 | BM42: 156 | BN42: 172 | BO42: 188 | BP42: 203 | BQ42: =339+2995 -> 3334 | BR42: 78 | BS42: 129 | BT42: 181 | BU42: 233 | BV42: 258 | BW42: 274 | BX42: =BW42+CF!BX42 -> 274 | BY42: =BX42+CF!BY42 -> 274 | BZ42: =BY42+CF!BZ42 -> 274 | CA42: =BZ42+CF!CA42 -> 274 | CB42: =CA42+CF!CB42 -> 274 | CC42: =CB42+CF!CC42 -> 274 | CE42: =I42 -> 2.118 | CF42: =M42 -> 0 | CG42: =Q42 -> 0 | CH42: =U42 -> 15.2 | CI42: =Y42 -> 20.1 | CJ42: =AC42 -> 24.6 | CK42: =AG42 -> 12 | CL42: =AK42 -> 27 | CM42: =AO42 -> 82 | CN42: =AS42 -> 106 | CO42: =AW42 -> 144 | CP42: =BA42 -> 230 | CQ42: =BE42 -> 230 | CR42: =BI42 -> 125 | CS42: =BM42 -> 156 | CT42: =BQ42 -> 3334 | CU42: =BU42 -> 233 | CV42: =BY42 -> 274 | CW42: =CC42 -> 274 | CX42: =CW42 -> 274 | CY42: =CX42 -> 274 | CZ42: =CY42 -> 274 | DA42: =CZ42 -> 274 | DB42: =DA42 -> 274 | DC42: =DB42 -> 274
C43: Total Current Liabilities | F43: =SUM(F37:F42) -> 380.919 | G43: =SUM(G37:G42) -> 408.33 | H43: =SUM(H37:H42) -> 363.84 | I43: =SUM(I37:I42) -> 340.346 | J43: =SUM(J37:J42) -> 430.255 | K43: =SUM(K37:K42) -> 437.915 | L43: =SUM(L37:L42) -> 418.535 | M43: =SUM(M37:M42) -> 406.472 | ... CC43: =SUM(CC37:CC42) -> 4163.5868 | CE43: =SUM(CE37:CE42) -> 340.346 | CF43: =SUM(CF37:CF42) -> 406.472 | CG43: =SUM(CG37:CG42) -> 505.7 | CH43: =SUM(CH37:CH42) -> 586.9 | CI43: =SUM(CI37:CI42) -> 818.5 | CJ43: =SUM(CJ37:CJ42) -> 859 | CK43: =SUM(CK37:CK42) -> 1130 | CL43: =SUM(CL37:CL42) -> 1564 | ... DC43: =SUM(DC37:DC42) -> 5693.217
CE44: =I44 -> 0 | CF44: =M44 -> 0 | CG44: =Q44 -> 0 | CH44: =U44 -> 0 | CI44: =Y44 -> 0 | CJ44: =AC44 -> 0 | CK44: =AG44 -> 0 | CL44: =AK44 -> 0 | CM44: =AO44 -> 0 | CN44: =AS44 -> 0 | CS44: =BM44 -> 0 | CT44: =BN44 -> 0 | CU44: =BO44 -> 0
C45: Long Term Liabilities
D46: Other liabilities | F46: 46.844 | G46: 44.467 | H46: 41.556 | I46: 38.629 | J46: 47.561 | K46: 46.436 | L46: 39.968 | M46: 41.142 | N46: 27.657 | O46: 29.588 | P46: 28.016 | Q46: 33.1 | R46: 23.6 | S46: 27.5 | T46: 26.6 | U46: 32 | V46: 24.1 | W46: 31.5 | X46: 30.6 | Y46: 35.4 | Z46: 31.5 | AA46: 35.5 | AB46: 40 | AC46: 37.6 | AD46: 42 | AE46: 38 | AF46: 40 | AG46: 45 | AH46: 117 | AI46: 117 | AJ46: 129 | AK46: 133 | AL46: 147 | AM46: 134 | AN46: 152 | AO46: 174 | AP46: 202 | AQ46: 237 | AR46: 287 | AS46: 302 | AT46: 308 | AU46: 309 | AV46: 328 | AW46: 310 | AX46: 290 | AY46: 282 | AZ46: 546 | BA46: 550 | BB46: 542 | BC46: 516 | BD46: 495 | BE46: 445 | BF46: 458 | BG46: 473 | BH46: 473 | BI46: 499 | BJ46: 490 | BK46: 518 | BL46: 529 | BM46: 564 | BN46: 585 | BO46: 602 | BP46: 557 | BQ46: 1108 | BR46: 1261 | BS46: 1211 | BT46: 1201 | BU46: 1180 | BV46: 1104 | BW46: 2438 | BX46: =(IS!BX16+IS!BX67)*BS!BX134 -> 1301.8773 | BY46: =(IS!BY16+IS!BY67)*BS!BY134 -> 1344.1541 | BZ46: =(IS!BZ16+IS!BZ67)*BS!BZ134 -> 1390.2576 | CA46: =(IS!CA16+IS!CA67)*BS!CA134 -> 1393.0927 | CB46: =(IS!CB16+IS!CB67)*BS!CB134 -> 1329.696 | CC46: =(IS!CC16+IS!CC67)*BS!CC134 -> 1294.7414 | CE46: =I46 -> 38.629 | CF46: =M46 -> 41.142 | CG46: =Q46 -> 33.1 | CH46: =U46 -> 32 | CI46: =Y46 -> 35.4 | CJ46: =AC46 -> 37.6 | CK46: =AG46 -> 45 | CL46: =AK46 -> 133 | CM46: =AO46 -> 174 | CN46: =AS46 -> 302 | CO46: =AW46 -> 310 | CP46: =BA46 -> 550 | CQ46: =BE46 -> 445 | CR46: =BI46 -> 499 | CS46: =BM46 -> 564 | CT46: =BQ46 -> 1108 | CU46: =BU46 -> 1180 | CV46: =BY46 -> 1344.1541 | CW46: =CC46 -> 1294.7414 | CX46: =(IS!CX16+IS!CX67)*BS!CX134 -> 1389.561 | CY46: =(IS!CY16+IS!CY67)*BS!CY134 -> 1446.0162 | CZ46: =(IS!CZ16+IS!CZ67)*BS!CZ134 -> 1499.0491 | DA46: =(IS!DA16+IS!DA67)*BS!DA134 -> 1571.1544 | DB46: =(IS!DB16+IS!DB67)*BS!DB134 -> 1654.5899 | DC46: =(IS!DC16+IS!DC67)*BS!DC134 -> 1748.7811
D47: Long-term debt, less current portion | F47: 178.512 | G47: 113.203 | H47: 112.611 | I47: 112.491 | J47: 113.974 | K47: 102.404 | L47: 89.517 | M47: 86.204 | N47: 72.599 | O47: 73.556 | P47: 0 | Q47: 0 | R47: 50 | S47: 46.9 | T47: 43.8 | U47: 52.7 | V47: 47.7 | W47: 42.7 | X47: 37.7 | Y47: 32.6 | Z47: 33.8 | AA47: 31.9 | AB47: 25.2 | AC47: 19.5 | AD47: 29 | AE47: 21 | AF47: 13 | AG47: 10 | AH47: 7 | AI47: 4 | AJ47: 503 | AK47: 482 | AL47: 462 | AM47: 444 | AN47: 425 | AO47: 400 | AP47: 375 | AQ47: 350 | AR47: 325 | AS47: 294 | AT47: 262 | AU47: 231 | AV47: 200 | AW47: 150 | AX47: 100 | AY47: 50 | AZ47: 2013 | BA47: 1955 | BB47: 1898 | BC47: 1840 | BD47: 1783 | BE47: 1725 | BF47: 1668 | BG47: 1610 | BH47: 2344 | BI47: 2313 | BJ47: 2281 | BK47: 2250 | BL47: 2203 | BM47: 2156 | BN47: 2109 | BO47: 2062 | BP47: 2000 | BQ47: 13660 | BR47: 13055 | BS47: 12944 | BT47: 12907 | BU47: 12918 | BV47: 12873 | BW47: 11777 | BX47: =BW47+CF!BX41+CF!BX46 -> 11527 | BY47: =BX47+CF!BY41+CF!BY46 -> 11277 | BZ47: =BY47+CF!BZ41+CF!BZ46 -> 11027 | CA47: =BZ47+CF!CA41+CF!CA46 -> 10777 | CB47: =CA47+CF!CB41+CF!CB46 -> 10527 | CC47: =CB47+CF!CC41+CF!CC46 -> 10277 | CE47: =I47 -> 112.491 | CF47: =M47 -> 86.204 | CG47: =Q47 -> 0 | CH47: =U47 -> 52.7 | CI47: =Y47 -> 32.6 | CJ47: =AC47 -> 19.5 | CK47: =AG47 -> 10 | CL47: =AK47 -> 482 | CM47: =AO47 -> 400 | CN47: =AS47 -> 294 | CO47: =AW47 -> 150 | CP47: =BA47 -> 1955 | CQ47: =BE47 -> 1725 | CR47: =BI47 -> 2313 | CS47: =BM47 -> 2156 | CT47: =BQ47 -> 13660 | CU47: =BU47 -> 12918 | CV47: =BY47 -> 11277 | CW47: =CC47 -> 10277 | CX47: =CW47+CF!CX41+CF!CX46 -> 9277 | CY47: =CX47+CF!CY41+CF!CY46 -> 8277 | CZ47: =CY47+CF!CZ41+CF!CZ46 -> 7277 | DA47: =CZ47+CF!DA41+CF!DA46 -> 6277 | DB47: =DA47+CF!DB41+CF!DB46 -> 5277 | DC47: =DB47+CF!DC41+CF!DC46 -> 4277
D48: Minority Interest | F48: 9.644 | G48: 9.251 | H48: 8.998 | I48: 9.383 | CE48: =I48 -> 9.383 | CF48: =M48 -> 0 | CG48: =Q48 -> 0 | CH48: =U48 -> 0 | CI48: =Y48 -> 0 | CJ48: =AC48 -> 0 | CK48: =AG48 -> 0 | CL48: =AK48 -> 0 | CM48: =AO48 -> 0 | CN48: =AS48 -> 0 | CO48: =AW48 -> 0 | CP48: =BA48 -> 0
C49: Total Long Term Liabilities | F49: =SUM(F46:F48) -> 235 | G49: =SUM(G46:G48) -> 166.921 | H49: =SUM(H46:H48) -> 163.165 | I49: =SUM(I46:I48) -> 160.503 | J49: =SUM(J46:J48) -> 161.535 | K49: =SUM(K46:K48) -> 148.84 | L49: =SUM(L46:L48) -> 129.485 | M49: =SUM(M46:M48) -> 127.346 | ... CC49: =SUM(CC46:CC48) -> 11571.741 | CE49: =SUM(CE46:CE48) -> 160.503 | CF49: =SUM(CF46:CF48) -> 127.346 | CG49: =SUM(CG46:CG48) -> 33.1 | CH49: =SUM(CH46:CH48) -> 84.7 | CI49: =SUM(CI46:CI48) -> 68 | CJ49: =SUM(CJ46:CJ48) -> 57.1 | CK49: =SUM(CK46:CK48) -> 55 | CL49: =SUM(CL46:CL48) -> 615 | ... DC49: =SUM(DC46:DC48) -> 6025.7811
CS50: =BM50 -> 0 | CT50: =BN50 -> 0 | CU50: =BO50 -> 0
B51: Total Liabilities | F51: =F43+F49 -> 615.919 | G51: =G43+G49 -> 575.251 | H51: =H43+H49 -> 527.005 | I51: =I43+I49 -> 500.849 | J51: =J43+J49 -> 591.79 | K51: =K43+K49 -> 586.755 | L51: =L43+L49 -> 548.02 | M51: =M43+M49 -> 533.818 | ... CC51: =CC43+CC49 -> 15735.328 | CE51: =SUM(CE49,CE43) -> 500.849 | CF51: =SUM(CF49,CF43) -> 533.818 | CG51: =SUM(CG49,CG43) -> 538.8 | CH51: =SUM(CH49,CH43) -> 671.6 | CI51: =SUM(CI49,CI43) -> 886.5 | CJ51: =SUM(CJ49,CJ43) -> 916.1 | CK51: =SUM(CK49,CK43) -> 1185 | CL51: =SUM(CL49,CL43) -> 2179 | ... CN51: =SUM(CN49,CN43) -> 2619 | CO51: =CO43+CO49 -> 2630 | CP51: =CP43+CP49 -> 6537 | CQ51: =CQ43+CQ49 -> 6143 | CR51: =CR43+CR49 -> 6657 | CS51: =CS43+CS49 -> 5962 | CT51: =CT43+CT49 -> 21717 | CU51: =CU43+CU49 -> 18442 | CV51: =CV43+CV49 -> 17173.79 | ... DC51: =DC43+DC49 -> 11718.998
CE52: =I52 -> 0 | CF52: =M52 -> 0 | CG52: =Q52 -> 0 | CH52: =U52 -> 0 | CI52: =Y52 -> 0 | CJ52: =AC52 -> 0 | CK52: =AG52 -> 0 | CL52: =AK52 -> 0 | CM52: =AO52 -> 0 | CN52: =AS52 -> 0 | CS52: =BM52 -> 0 | CT52: =BN52 -> 0 | CU52: =BO52 -> 0
B53: Stockholder's Equity:
C54: Common shares | F54: 1.685 | G54: 1.832 | H54: 1.835 | I54: 1.928 | J54: 1.928 | K54: 1.944 | L54: 1.955 | M54: 1.954 | N54: 1.955 | O54: 1.955 | P54: 1.983 | Q54: 2 | R54: 2.1 | S54: 2.1 | T54: 2.1 | U54: 2.1 | V54: 2.1 | W54: 2.1 | X54: 2.1 | Y54: 2.1 | Z54: 2.2 | AA54: 2.2 | AB54: 2.2 | AC54: 2.2 | AD54: 2 | AE54: 2 | AF54: 2 | AG54: 2 | AH54: 2 | AI54: 2 | AJ54: 2 | AK54: 2 | AL54: 2 | AM54: 2 | AN54: 2 | AO54: 2 | AP54: 2 | AQ54: 2 | AR54: 2 | AS54: 2 | AT54: 2 | AU54: 2 | AV54: 2 | AW54: 2 | AX54: 2 | AY54: 2 | AZ54: 3 | BA54: 3 | BB54: 3 | BC54: 3 | BD54: 3 | BE54: 3 | BF54: 3 | BG54: 3 | BH54: 3 | BI54: 3 | BJ54: 3 | BK54: 3 | BL54: 3 | BM54: 3 | BN54: 3 | BO54: 3 | BP54: 3 | BQ54: 3 | BR54: 3 | BS54: 3 | BT54: 3 | BU54: 3 | BV54: =BU54 -> 3 | BW54: =BV54 -> 3 | BX54: =BW54 -> 3 | BY54: =BX54 -> 3 | BZ54: =BY54 -> 3 | CA54: =BZ54 -> 3 | CB54: =CA54 -> 3 | CC54: =CB54 -> 3 | CE54: =I54 -> 1.928 | CF54: =M54 -> 1.954 | CG54: =Q54 -> 2 | CH54: =U54 -> 2.1 | CI54: =Y54 -> 2.1 | CJ54: =AC54 -> 2.2 | CK54: =AG54 -> 2 | CL54: =AK54 -> 2 | CM54: =AO54 -> 2 | CN54: =AS54 -> 2 | CO54: =AW54 -> 2 | CP54: =BA54 -> 3 | CQ54: =BE54 -> 3 | CR54: =BI54 -> 3 | CS54: =BM54 -> 3 | CT54: =BQ54 -> 3 | CU54: =BU54 -> 3 | CV54: =BY54 -> 3 | CW54: =CC54 -> 3 | CX54: =CW54 -> 3 | CY54: =CX54 -> 3 | CZ54: =CY54 -> 3 | DA54: =CZ54 -> 3 | DB54: =DA54 -> 3 | DC54: =DB54 -> 3
C55: Additional paid-in capital | F55: 624.086 | G55: 708.398 | H55: 694.567 | I55: 735.439 | J55: 729.32 | K55: 731.064 | L55: 719.019 | M55: 710.945 | N55: 684.995 | O55: 640.13 | P55: 651.514 | Q55: 676.6 | R55: 687.2 | S55: 691.3 | T55: 695.3 | U55: 698.7 | V55: 684.7 | W55: 674.6 | X55: 700.1 | Y55: 711.1 | Z55: 705.4 | AA55: 704 | AB55: 752.8 | AC55: 775.3 | AD55: 782 | AE55: 802 | AF55: 807 | AG55: 811 | AH55: 811 | AI55: 818 | AJ55: 821 | AK55: 906 | AL55: 920 | AM55: 909 | AN55: 913 | AO55: 896 | AP55: 932 | AQ55: 976 | AR55: 997 | AS55: 1022 | AT55: 1038 | AU55: 1040 | AV55: 1064 | AW55: 1091 | AX55: 1106 | AY55: 1151 | AZ55: 2150 | BA55: 2223 | BB55: 2224 | BC55: 2224 | BD55: 2232 | BE55: 2188 | BF55: 2205 | BG55: 2262 | BH55: 2314 | BI55: 2331 | BJ55: 2285 | BK55: 2318 | BL55: 2369 | BM55: 2428 | BN55: 2407 | BO55: 2421 | BP55: 2454 | BQ55: 4429 | BR55: 4492 | BS55: 4574 | BT55: 4477 | BU55: 4506 | BV55: =BV60-SUM(BV54, BV56:BV59) -> 4613.135 | BW55: =BW60-SUM(BW54, BW56:BW59) -> 4796.775 | BX55: =BW55+CF!BX19+CF!BX43 -> 4887.8546 | BY55: =BX55+CF!BY19+CF!BY43 -> 4979.0255 | BZ55: =BY55+CF!BZ19+CF!BZ43 -> 5073.0999 | CA55: =BZ55+CF!CA19+CF!CA43 -> 5165.6824 | CB55: =CA55+CF!CB19+CF!CB43 -> 5251.6561 | CC55: =CB55+CF!CC19+CF!CC43 -> 5333.0331 | CE55: =I55 -> 735.439 | CF55: =M55 -> 710.945 | CG55: =Q55 -> 676.6 | CH55: =U55 -> 698.7 | CI55: =Y55 -> 711.1 | CJ55: =AC55 -> 775.3 | CK55: =AG55 -> 811 | CL55: =AK55 -> 906 | CM55: =AO55 -> 896 | CN55: =AS55 -> 1022 | CO55: =AW55 -> 1091 | CP55: =BA55 -> 2223 | CQ55: =BE55 -> 2188 | CR55: =BI55 -> 2331 | CS55: =BM55 -> 2428 | CT55: =BQ55 -> 4429 | CU55: =BU55 -> 4506 | CV55: =BY55 -> 4979.0255 | CW55: =CC55 -> 5333.0331 | CX55: =CW55+CF!CX19+CF!CX43 -> 5712.8563 | CY55: =CX55+CF!CY19+CF!CY43 -> 6106.4489 | CZ55: =CY55+CF!CZ19+CF!CZ43 -> 6515.0231 | DA55: =CZ55+CF!DA19+CF!DA43 -> 6942.5337 | DB55: =DA55+CF!DB19+CF!DB43 -> 7391.5058 | DC55: =DB55+CF!DC19+CF!DC43 -> 7864.784
C56: Accumulated other comprehensive income | F56: 8.915 | G56: -10.032 | H56: -9.447 | I56: 3.112 | J56: 1.581 | K56: 2.179 | L56: 4.094 | M56: 2.559 | N56: 1.24 | O56: 1.85 | P56: 3.248 | Q56: 0 | U56: 0.2 | Y56: -0.3 | Z56: 0 | AA56: 0 | AB56: 0 | AC56: 1 | AD56: 1 | AE56: 0 | AF56: 5 | AG56: -1 | AH56: 2 | AI56: 5 | AJ56: 43 | AK56: -12 | AL56: -14 | AM56: -11 | AN56: -3 | AO56: 2 | AP56: 9 | AQ56: 4 | AR56: 22 | AS56: 11 | AT56: 39 | AU56: 21 | AV56: 8 | AW56: -5 | AX56: -24 | AY56: -14 | AZ56: -4 | BA56: -15 | BB56: 14 | BC56: 8 | BD56: 20 | BE56: -35 | BF56: -19 | BG56: -49 | BH56: -4 | BI56: 12 | BJ56: -14 | BK56: -32 | BL56: -3 | BM56: -20 | BN56: -44 | BO56: -8 | BP56: 32 | BQ56: 103 | BR56: 115 | BS56: -197 | BT56: -96 | BU56: -58 | BV56: =BU56 -> -58 | BW56: =BV56 -> -58 | BX56: =BW56 -> -58 | BY56: =BX56 -> -58 | BZ56: =BY56 -> -58 | CA56: =BZ56 -> -58 | CB56: =CA56 -> -58 | CC56: =CB56 -> -58 | CE56: =I56 -> 3.112 | CF56: =M56 -> 2.559 | CG56: =Q56 -> 0 | CH56: =U56 -> 0.2 | CI56: =Y56 -> -0.3 | CJ56: =AC56 -> 1 | CK56: =AG56 -> -1 | CL56: =AK56 -> -12 | CM56: =AO56 -> 2 | CN56: =AS56 -> 11 | CO56: =AW56 -> -5 | CP56: =BA56 -> -15 | CQ56: =BE56 -> -35 | CR56: =BI56 -> 12 | CS56: =BM56 -> -20 | CT56: =BQ56 -> 103 | CU56: =BU56 -> -58 | CV56: =BY56 -> -58 | CW56: =CC56 -> -58 | CX56: =CW56 -> -58 | CY56: =CX56 -> -58 | CZ56: =CY56 -> -58 | DA56: =CZ56 -> -58 | DB56: =DA56 -> -58 | DC56: =DB56 -> -58
C57: Deferred stock compensation | I57: -3.745 | Q57: -1.2 | U57: -1.3 | X57: -13.5 | Y57: -14.6 | Z57: 0 | AA57: 0 | AB57: 0 | AC57: 0 | AD57: 0 | AE57: 0 | AF57: 0 | AG57: 0 | AH57: 0 | AI57: 0 | AJ57: 0 | AK57: 0 | AL57: 0 | AM57: 0 | AN57: 0 | AO57: 0 | AP57: 0 | AQ57: 0 | AR57: 0 | AS57: 0 | AT57: 0 | AU57: 0 | AV57: 0 | AW57: 0 | AX57: 0 | AY57: 0 | AZ57: 0 | BA57: 0 | BB57: 0 | BC57: 0 | BD57: 0 | BE57: =BD57 -> 0 | BF57: 0 | BG57: 0 | BH57: 0 | BI57: =BH57 -> 0 | BJ57: 0 | BK57: 0 | BL57: 0 | BM57: =BL57 -> 0 | BN57: 0 | BO57: 0 | BP57: 0 | BQ57: 0 | BR57: 0 | BS57: 0 | BT57: 0 | BU57: 0 | BV57: =BU57 -> 0 | BW57: =BV57 -> 0 | BX57: =BW57 -> 0 | BY57: =BX57 -> 0 | BZ57: =BY57 -> 0 | CA57: =BZ57 -> 0 | CB57: =CA57 -> 0 | CC57: =CB57 -> 0 | CE57: =I57 -> -3.745 | CF57: =M57 -> 0 | CG57: =Q57 -> -1.2 | CH57: =U57 -> -1.3 | CI57: =Y57 -> -14.6 | CJ57: =AC57 -> 0 | CK57: =AG57 -> 0 | CL57: =AK57 -> 0 | CM57: =AO57 -> 0 | CN57: =AS57 -> 0 | CO57: =AW57 -> 0 | CP57: =BA57 -> 0 | CQ57: =BE57 -> 0 | CR57: =BI57 -> 0 | CS57: =BM57 -> 0 | CT57: =BQ57 -> 0 | CU57: =BU57 -> 0 | CV57: =BY57 -> 0 | CW57: =CC57 -> 0 | CX57: =CW57 -> 0 | CY57: =CX57 -> 0 | CZ57: =CY57 -> 0 | DA57: =CZ57 -> 0 | DB57: =DA57 -> 0 | DC57: =DB57 -> 0
C58: Retained earnings | F58: -516.377 | G58: -514.589 | H58: -517.636 | I58: -581.72 | J58: -561.202 | K58: -548.608 | L58: -529.41 | M58: -516.292 | N58: -494.077 | O58: -419.717 | P58: -365.215 | Q58: -334.2 | R58: -329.2 | S58: -260.4 | T58: -212.5 | U58: -182.9 | V58: -152.5 | W58: -96.5 | X58: -25.7 | Y58: 15.5 | Z58: 84.3 | AA58: 188.6 | AB58: 291.5 | AC58: 390.5 | AD58: 494 | AE58: 622 | AF58: 742 | AG58: 955 | AH58: 1023 | AI58: 1329 | AJ58: 1609 | AK58: 1822 | AL58: 2033 | AM58: 2047 | AN58: 2096 | AO58: 2292 | AP58: 2580 | AQ58: 3009 | AR58: 3410 | AS58: 3674 | AT58: 3871 | AU58: 4096 | AV58: 4242 | AW58: 4400 | AX58: 4639 | AY58: 4784 | AZ58: 5267 | BA58: 6012 | BB58: 6470 | BC58: 6744 | BD58: 7073 | BE58: 6749 | BF58: 7183 | BG58: 7541 | BH58: 7845 | BI58: 8066 | BJ58: 8394 | BK58: 8738 | BL58: 9004 | BM58: 9107 | BN58: 9273 | BO58: 9407 | BP58: 9363 | BQ58: 8848 | BR58: 8329 | BS58: 8411 | BT58: 8507 | BU58: 8633 | BV58: =BU58+IS!BV100+CF!BV47 -> 9166.865 | BW58: =BV58+IS!BW100+CF!BW47 -> 8196.225 | BX58: =BW58+IS!BX100+CF!BX47 -> 8616.7034 | BY58: =BX58+IS!BY100+CF!BY47 -> 8949.5145 | BZ58: =BY58+IS!BZ100+CF!BZ47 -> 9436.9837 | CA58: =BZ58+IS!CA100+CF!CA47 -> 9847.8339 | CB58: =CA58+IS!CB100+CF!CB47 -> 10094.806 | CC58: =CB58+IS!CC100+CF!CC47 -> 10288.797 | CE58: =I58 -> -581.72 | CF58: =M58 -> -516.292 | CG58: =Q58 -> -334.2 | CH58: =U58 -> -182.9 | CI58: =Y58 -> 15.5 | CJ58: =AC58 -> 390.5 | CK58: =AG58 -> 955 | CL58: =AK58 -> 1822 | CM58: =AO58 -> 2292 | CN58: =AS58 -> 3674 | CO58: =AW58 -> 4400 | CP58: =BA58 -> 6012 | CQ58: =BE58 -> 6749 | CR58: =BI58 -> 8066 | CS58: =BM58 -> 9107 | CT58: =BQ58 -> 8848 | CU58: =BU58 -> 8633 | CV58: =BY58 -> 8949.5145 | CW58: =CC58 -> 10288.797 | CX58: =CW58+IS!CX100+CF!CX47 -> 11938.968 | CY58: =CX58+IS!CY100+CF!CY47 -> 13721.463 | CZ58: =CY58+IS!CZ100+CF!CZ47 -> 15716.401 | DA58: =CZ58+IS!DA100+CF!DA47 -> 17717.261 | DB58: =DA58+IS!DB100+CF!DB47 -> 19913.346 | DC58: =DB58+IS!DC100+CF!DC47 -> 22330.076
