Workbook
Name _1H_96: "assumpt"
Name _scenchg_count: 1
Name aaaa: {13}
Name aaaa: {13}
Name aaaaaa: {"BMC"}
Name aaaaaa: {"BMC"}
Name AdditionalInstructions: IndexInformation!$B$42
Name Address: ImportantDisclosures!$A$2:$A$2
Name AllTables: {1}
Name AllTables: {1}
Name AllTables: {9}
Name ANA: ModPubIndex!$A$7
Name asfadsg: {1}
Name asfadsg: {1}
Name asfadsg: {1}
Name Authors: ImportantDisclosures!$A$7
Name Authors: IndexInformation!$B$18
Name AxesFormat: 'debt schedule'!AxesFormat
Name biovailvaluation: {"Client Name or Project Name"}
Name biovailvaluation: {"Client Name or Project Name"}
Name BRO: ModPubIndex!$A$1
Name Cell_Errors: OFFSET('debt schedule'!File_Name,0,5,1,1)
Name CF_OP_GR: "'=BackSheet!$D$239:$AG$239"
Name CF_PR_DV: "'=BackSheet!$D$241:$AG$241"
Name chart_1: "Chart 1"
Name chart_2: "Chart 2"
Name Choices_Wrapper: 'debt schedule'!Choices_Wrapper
Name Company_Name: "Project Knit"
Name converting: {"Client Name or Project Name"}
Name converting: {"Client Name or Project Name"}
Name CopyrightStamp: ImportantDisclosures!$A$27
Name COU: ModPubIndex!$A$5
Name CQEnd: IndexInformation!$B$31
Name Currency: IndexInformation!$B$24
Name Currency_ISOcode: OPEB!$AQ$174
Name Currency_ISOcode: Pension!$AQ$186
Name currentFY: Pension!$AZ$18
Name CurrentStockPrice: IndexInformation!$B$23
Name CurrQtrEPS: IndexInformation!$B$29
Name CurrYearEPS: IndexInformation!$B$11
Name CurrYearTotalRevenue: IndexInformation!$B$10
Name CurrYearTotalRevenueActual: IndexInformation!$B$32
Name CUSIP: IndexInformation!$B$20
Name CYEnd: IndexInformation!$B$30
Name darvon: {"Client Name or Project Name"}
Name darvon: {"Client Name or Project Name"}
Name Date: ImportantDisclosures!$A$8
Name DB: "WIREUK"
Name dd: {"Client Name or Project Name"}
Name dd: {"Client Name or Project Name"}
Name ddd: {13}
Name ddd: {13}
Name ddddd: {"BMC"}
Name ddddd: {"BMC"}
Name Deleted: IndexInformation!$B$27
Name Description: IndexInformation!$B$7
Name DEVELOPMENT: 5
Name dfasd: {"Project PPaids"}
Name dfasd: {"Project PPaids"}
Name Discipline: IndexInformation!$B$3

Sheet ImportantDisclosures
A2: 1585 Broadway
A3: New York, NY 10036-8293
A4: United States
A5: Tel: +1 (1)212 761 4000
A7: Authors: Piyush Sood, Lynn Bernabei, Serena Rocha Calejon
A8: Date: 17 Apr 2018
A10: Ticker: X.N
A11: Stock Rating: Overweight
A12: Industry: Steel
A13: Industry View: In-Line
A14: Price as of 17 Apr 2018: 35.75
A15: Target Price: 44
... A129: Equal-weight and Not-Rated to hold and Underweight to sell recommendations, respectively.
B131: Coverage Universe | D131: Investment Banking Clients (IBC) | G131: Other Material Investment Services Clients (MISC)
A132: Stock Rating Category | B132: Count | C132: % of Total | D132: Count | E132: % of Total IBC | F132: % of Rating Category | G132: Count | H132: % of Total Other MISC
A133: Overweight/Buy | B133: 1189 | C133: 0.38 | D133: 315 | E133: 0.41 | F133: 0.26 | G133: 555 | H133: 0.39
A134: Equal-weight/Hold | B134: 1355 | C134: 0.43 | D134: 364 | E134: 0.47 | F134: 0.27 | G134: 644 | H134: 0.45
A135: Not-Rated/Hold | B135: 53 | C135: 0.02 | D135: 4 | E135: 0.01 | F135: 0.08 | G135: 7 | H135: 0
A136: Underweight/Sell | B136: 545 | C136: 0.17 | D136: 84 | E136: 0.11 | F136: 0.15 | G136: 214 | H136: 0.15
A137: Total | B137: 3142 | D137: 767 | G137: 1420
A139: Data include common stock and ADRs currently assigned ratings. Investment Banking Clients are companies
A140: from whom Morgan Stanley received investment banking compensation in the last 12 months. Due to rounding
A141: off of decimals, the percentages provided in the "% of total" column may not add up to exactly 100
A142: percent.
A144: Analyst Stock Ratings
A146: Overweight (O). The stock's total return is expected to exceed the average total return of the analyst's
A147: industry (or industry team's) coverage universe, on a risk-adjusted basis, over the next 12-18 months.
A149: Equal-weight (E). The stock's total return is expected to be in line with the average total return of
A150: the analyst's industry (or industry team's) coverage universe, on a risk-adjusted basis, over the next
A151: 12-18 months.
A153: Not-Rated (NR). Currently the analyst does not have adequate conviction about the stock's total return
A154: relative to the average total return of the analyst's industry (or industry team's) coverage universe,
... A400: © Copyright 2018 Morgan Stanley

Sheet Summary
B2: US Steel Corp.
B3: Summary Information
B5: Key Assumptions | J5: Income Statement
B6: Year End December | C6: 2014 | D6: 2015 | E6: 2016 | F6: 2017 | G6: 2018e | H6: 2019e | J6: Year End December (US$M) | K6: =C6 -> 2014 | L6: =D6 -> 2015 | M6: =E6 -> 2016 | N6: =F6 -> 2017 | O6: =G6 -> 2018e | P6: =H6 -> 2019e
B7: Realizations, $/t | J7: Sales | K7: =Financials!$BM$14 -> 17507 | L7: =Financials!$BR$14 -> 11574 | M7: =Financials!$BW$14 -> 10261 | N7: =Financials!$CB$14 -> 12250 | O7: =Financials!$CG$14 -> 14096.401 | P7: =Financials!$CL$14 -> 15045.003
B8: Flat Rolled | C8: =Operations!$BM$51 -> 771.57902 | D8: =Operations!$BR$51 -> 694.76614 | E8: =Operations!$BW$51 -> 665.14959 | F8: =Operations!$CB$51 -> 726.63052 | G8: =Operations!$CG$51 -> 791.74194 | H8: =Operations!$CL$51 -> 818.44807 | J8: COGS | K8: =Financials!$BM$18 -> 15461 | L8: =Financials!$BR$18 -> 10916 | M8: =Financials!$BW$18 -> 9398 | N8: =Financials!$CB$18 -> 10744 | O8: =Financials!$CG$18 -> 11894.968 | P8: =Financials!$CL$18 -> 12623.285
B9: Tubular | C9: =Operations!$BM$116 -> 1538.1009 | D9: =Operations!$BR$116 -> 1464.3491 | E9: =Operations!$BW$116 -> 1070.7325 | F9: =Operations!$CB$116 -> 1306.4477 | G9: =Operations!$CG$116 -> 1584.0876 | H9: =Operations!$CL$116 -> 1584.0876 | J9: D&A | K9: =Financials!$BM$25 -> 627 | L9: =Financials!$BR$25 -> 547 | M9: =Financials!$BW$25 -> 507 | N9: =Financials!$CB$25 -> 501 | O9: =Financials!$CG$25 -> 495 | P9: =Financials!$CL$25 -> 495
B10: USSE | C10: =Operations!$BM$155 -> 668 | D10: =Operations!$BR$155 -> 514 | E10: =Operations!$BW$155 -> 482.5 | F10: =Operations!$CB$155 -> 621.75 | G10: =Operations!$CG$155 -> 719.38232 | H10: =Operations!$CL$155 -> 719.38232 | J10: SG&A | K10: =Financials!$BM$23 -> 523 | L10: =Financials!$BR$23 -> 415 | M10: =Financials!$BW$23 -> 255 | N10: =Financials!$CB$23 -> 375 | O10: =Financials!$CG$23 -> 422.89203 | P10: =Financials!$CL$23 -> 451.3501
B11: Blended | C11: =Operations!$BM$196 -> 817.16207 | D11: =Operations!$BR$196 -> 672.34909 | E11: =Operations!$BW$196 -> 621.19891 | F11: =Operations!$CB$196 -> 721.22399 | G11: =Operations!$CG$196 -> 809.66506 | H11: =Operations!$CL$196 -> 827.98195 | J11: EBITDA | K11: =Financials!$BM$101 -> 1678 | L11: =Financials!$BR$101 -> 202 | M11: =Financials!$BW$101 -> 510 | N11: =Financials!$CB$101 -> 1087 | O11: =Financials!$CG$101 -> 1738.5413 | P11: =Financials!$CL$101 -> 1930.3678
J12: EBIT | K12: =Financials!$BM$39 -> 1051 | L12: =Financials!$BR$39 -> -345 | M12: =Financials!$BW$39 -> 3 | N12: =Financials!$CB$39 -> 586 | O12: =Financials!$CG$39 -> 1243.5413 | P12: =Financials!$CL$39 -> 1435.3678
B13: Shipments, kt | J13: Pre-Tax Income | K13: =Financials!$BM$48 -> 808 | L13: =Financials!$BR$48 -> -566 | M13: =Financials!$BW$48 -> -224 | N13: =Financials!$CB$48 -> 336 | O13: =Financials!$CG$48 -> 972.27649 | P13: =Financials!$CL$48 -> 1167.1162
B14: Flat Rolled | C14: =Operations!$BM$34 -> 13908 | D14: =Operations!$BR$34 -> 10596 | E14: =Operations!$BW$34 -> 10094 | F14: =Operations!$CB$34 -> 9887 | G14: =Operations!$CG$34 -> 10483.45 | H14: =Operations!$CL$34 -> 11255.274 | J14: Tax | K14: =Financials!$BM$51 -> 145 | L14: =Financials!$BR$51 -> 183 | M14: =Financials!$BW$51 -> 24 | N14: =Financials!$CB$51 -> -5 | O14: =Financials!$CG$51 -> 77.880788 | P14: =Financials!$CL$51 -> 85.039629
B15: Tubular | C15: =Operations!$BM$100 -> 1744 | D15: =Operations!$BR$100 -> 593 | E15: =Operations!$BW$100 -> 400 | F15: =Operations!$CB$100 -> 688 | G15: =Operations!$CG$100 -> 777.15 | H15: =Operations!$CL$100 -> 800.4645 | J15: Minority Interest and Others | K15: =Financials!$BM$54 -> 0 | L15: =Financials!$BR$54 -> 0 | M15: =Financials!$BW$54 -> 0 | N15: =Financials!$CB$54 -> 0 | O15: =Financials!$CG$54 -> 0 | P15: =Financials!$CL$54 -> 0
B16: USSE | C16: =Operations!$BM$141 -> 4179 | D16: =Operations!$BR$141 -> 4466 | E16: =Operations!$BW$141 -> 4495 | F16: =Operations!$CB$141 -> 4585 | G16: =Operations!$CG$141 -> 4585 | H16: =Operations!$CL$141 -> 4585 | J16: Adj. Net Income | K16: =Financials!$BM$59 -> 663 | L16: =Financials!$BR$59 -> -749 | M16: =Financials!$BW$59 -> -248 | N16: =Financials!$CB$59 -> 341 | O16: =Financials!$CG$59 -> 894.3957 | P16: =Financials!$CL$59 -> 1082.0766
B17: Total | C17: =Operations!$BM$195 -> 19831 | D17: =Operations!$BR$195 -> 15655 | E17: =Operations!$BW$195 -> 14989 | F17: =Operations!$CB$195 -> 15160 | G17: =Operations!$CG$195 -> 15845.6 | H17: =Operations!$CL$195 -> 16640.738 | J17: Adj. EPS | K17: =Financials!$BM$64 -> 4.4608261 | L17: =Financials!$BR$64 -> -5.1268361 | M17: =Financials!$BW$64 -> -1.5834706 | N17: =Financials!$CB$64 -> 1.9292632 | O17: =Financials!$CG$64 -> 5.1109942 | P17: =Financials!$CL$64 -> 6.1834904
B18: NA Capacity Utilization | C18: =Operations!$BM$37 -> 0.79852905 | D18: =Operations!$BR$37 -> 0.60374361 | E18: =Operations!$BW$37 -> 0.62967381 | F18: =Operations!$CB$37 -> 0.63738308 | G18: =Operations!$CG$37 -> 0.67834088 | H18: =Operations!$CL$37 -> 0.72828243 | J18: Reported EPS | K18: =Financials!$BM$94 -> 0.68628094 | L18: =Financials!$BR$94 -> -11.239339 | M18: =Financials!$BW$94 -> -2.8093833 | N18: =Financials!$CB$94 -> 2.1895157 | O18: =Financials!$CG$94 -> 5.1109942 | P18: =Financials!$CL$94 -> 6.1834904
B20: Segment EBIT | J20: Balance Sheet
B21: =+J6 -> Year End December (US$M) | C21: =+C6 -> 2014 | D21: =+D6 -> 2015 | E21: =+E6 -> 2016 | F21: =+F6 -> 2017 | G21: =+G6 -> 2018e | H21: =+H6 -> 2019e | J21: =+$J$6 -> Year End December (US$M) | K21: =+K6 -> 2014 | L21: =+L6 -> 2015 | M21: =+M6 -> 2016 | N21: =+N6 -> 2017 | O21: =+O6 -> 2018e | P21: =+P6 -> 2019e
B22: Flat rolled Segment- Steel | C22: =Financials!$BM$32 -> 709 | D22: =Financials!$BR$32 -> -237 | E22: =Financials!$BW$32 -> -3 | F22: =Financials!$CB$32 -> 380 | G22: =Financials!$CG$32 -> 762.3697 | H22: =Financials!$CL$32 -> 925.0848 | J22: Cash and Equivalents | K22: =Financials!$BM$121 -> 1354 | L22: =Financials!$BR$121 -> 755 | M22: =Financials!$BW$121 -> 1515 | N22: =Financials!$CB$121 -> 1553 | O22: =Financials!$CG$121 -> 1799.9354 | P22: =Financials!$CL$121 -> 2142.9895
B23: Tubular | C23: =Financials!$BM$34 -> 261 | D23: =Financials!$BR$34 -> -179 | E23: =Financials!$BW$34 -> -304 | F23: =Financials!$CB$34 -> -99 | G23: =Financials!$CG$34 -> 64.310698 | H23: =Financials!$CL$34 -> 59.332384 | J23: Receivables | K23: =+Financials!BM122+Financials!BM123 -> 1927 | L23: =+Financials!BR122+Financials!BR123 -> 1063 | M23: =+Financials!BW122+Financials!BW123 -> 1248 | N23: =+Financials!CB122+Financials!CB123 -> 1379 | O23: =+Financials!CG122+Financials!CG123 -> 1697.6643 | P23: =+Financials!CL122+Financials!CL123 -> 1876.2989
B24: USSE | C24: =Financials!$BM$33 -> 116 | D24: =Financials!$BR$33 -> 81 | E24: =Financials!$BW$33 -> 185 | F24: =Financials!$CB$33 -> 327 | G24: =Financials!$CG$33 -> 370.8609 | H24: =Financials!$CL$33 -> 404.95061 | J24: Inventories | K24: =Financials!$BM$124 -> 2496 | L24: =Financials!$BR$124 -> 2074 | M24: =Financials!$BW$124 -> 1573 | N24: =Financials!$CB$124 -> 1738 | O24: =Financials!$CG$124 -> 2132.5494 | P24: =Financials!$CL$124 -> 2118.039
B25: Others | C25: =+Financials!BM35+Financials!BM36+Financials!BM37 -> -35 | D25: =+Financials!BR35+Financials!BR36+Financials!BR37 -> -10 | E25: =+Financials!BW35+Financials!BW36+Financials!BW37 -> 125 | F25: =+Financials!CB35+Financials!CB36+Financials!CB37 -> -22 | G25: =+Financials!CG35+Financials!CG36+Financials!CG37 -> 46 | H25: =+Financials!CL35+Financials!CL36+Financials!CL37 -> 46 | J25: Goodwill and Intangibles | K25: =Financials!BM134+Financials!BM135 -> 204 | L25: =Financials!BR134+Financials!BR135 -> 196 | M25: =Financials!BW134+Financials!BW135 -> 175 | N25: =Financials!CB134+Financials!CB135 -> 167 | O25: =Financials!CG134+Financials!CG135 -> 167 | P25: =Financials!CL134+Financials!CL135 -> 167
J26: Net PP&E | K26: =Financials!$BM$132 -> 4574 | L26: =Financials!$BR$132 -> 4411 | M26: =Financials!$BW$132 -> 3979 | N26: =Financials!$CB$132 -> 4280 | O26: =Financials!$CG$132 -> 4635 | P26: =Financials!$CL$132 -> 5290
B27: Quarterly Data | J27: Deferred Tax Asset | K27: =Financials!BM125+Financials!BM136 -> 648 | L27: =Financials!BR125+Financials!BR136 -> 15 | M27: =Financials!BW125+Financials!BW136 -> 6 | N27: =Financials!CB125+Financials!CB136 -> 0 | O27: =Financials!CG125+Financials!CG136 -> 0 | P27: =Financials!CL125+Financials!CL136 -> 0
B28: =+B6 -> Year End December | C28: =ROUNDUP(MONTH(C60)/3,0)&"Q"&(YEAR(C60)-2000) -> 3Q17 | D28: =ROUNDUP(MONTH(D60)/3,0)&"Q"&(YEAR(D60)-2000) -> 4Q17 | E28: =ROUNDUP(MONTH(E60)/3,0)&"Q"&(YEAR(E60)-2000)&"e" -> 1Q18e | F28: =ROUNDUP(MONTH(F60)/3,0)&"Q"&(YEAR(F60)-2000)&"e" -> 2Q18e | G28: =ROUNDUP(MONTH(G60)/3,0)&"Q"&(YEAR(G60)-2000)&"e" -> 3Q18e | H28: =ROUNDUP(MONTH(H60)/3,0)&"Q"&(YEAR(H60)-2000)&"e" -> 4Q18e | J28: Other Assets | K28: =K29-SUM(K22:K27) -> 1111 | L28: =L29-SUM(L22:L27) -> 676 | M28: =M29-SUM(M22:M27) -> 664 | N28: =N29-SUM(N22:N27) -> 745 | O28: =O29-SUM(O22:O27) -> 745 | P28: =P29-SUM(P22:P27) -> 745
B29: Quarterly Operating Data | J29: Total Assets | K29: =Financials!$BM$139 -> 12314 | L29: =Financials!$BR$139 -> 9190 | M29: =Financials!$BW$139 -> 9160 | N29: =Financials!$CB$139 -> 9862 | O29: =Financials!$CG$139 -> 11177.149 | P29: =Financials!$CL$139 -> 12339.327
B30: Blended Realization | C30: =Operations!BZ196 -> 737.34194 | D30: =Operations!CA196 -> 722.5213 | E30: =Operations!CC196 -> 764.05569 | F30: =Operations!CD196 -> 818.65936 | G30: =Operations!CE196 -> 834.13264 | H30: =Operations!CF196 -> 816.83856
B31: Total Shipments | C31: =Operations!BZ195 -> 3796 | D31: =Operations!CA195 -> 3873 | E31: =Operations!CC195 -> 3688.24 | F31: =Operations!CD195 -> 3894.97 | G31: =Operations!CE195 -> 4087.4 | H31: =Operations!CF195 -> 4174.99 | J31: Short Term debt | K31: =Financials!$BM$149 -> 378 | L31: =Financials!$BR$149 -> 45 | M31: =Financials!$BW$149 -> 50 | N31: =Financials!$CB$149 -> 3 | O31: =Financials!$CG$149 -> 0 | P31: =Financials!$CL$149 -> 0
B32: NA Capacity Utilization | C32: =Operations!BZ37 -> 0.66 | D32: =Operations!CA37 -> 0.6 | E32: =Operations!CC37 -> 0.62843388 | F32: =Operations!CD37 -> 0.65274518 | G32: =Operations!CE37 -> 0.72429176 | H32: =Operations!CF37 -> 0.70789271 | J32: Long Term debt | K32: =Financials!$BM$154 -> 3120 | L32: =Financials!$BR$154 -> 3116 | M32: =Financials!$BW$154 -> 2981 | N32: =Financials!$CB$154 -> 2700 | O32: =Financials!$CG$154 -> 2703 | P32: =Financials!$CL$154 -> 2703
B33: Quarterly Financial Data | J33: Payables | K33: =Financials!BM142+Financials!BM143 -> 2002 | L33: =Financials!BR142+Financials!BR143 -> 1493 | M33: =Financials!BW142+Financials!BW143 -> 1668 | N33: =Financials!CB142+Financials!CB143 -> 2170 | O33: =Financials!CG142+Financials!CG143 -> 2492.5651 | P33: =Financials!CL142+Financials!CL143 -> 2475.0856
B34: Sales | C34: =Financials!BZ14 -> 3248 | D34: =Financials!CA14 -> 3133 | E34: =Financials!CC14 -> 3135.5207 | F34: =Financials!CD14 -> 3506.1536 | G34: =Financials!CE14 -> 3726.9338 | H34: =Financials!CF14 -> 3727.7928 | J34: Deferred Tax Liability | K34: =+Financials!BM147+Financials!BM155 -> 0 | L34: =+Financials!BR147+Financials!BR155 -> 29 | M34: =+Financials!BW147+Financials!BW155 -> 28 | N34: =+Financials!CB147+Financials!CB155 -> 6 | O34: =+Financials!CG147+Financials!CG155 -> 52.691575 | P34: =+Financials!CL147+Financials!CL155 -> 99.70986
B35: EBITDA | C35: =Financials!BZ101 -> 342 | D35: =Financials!CA101 -> 309 | E35: =Financials!CC101 -> 259.78647 | F35: =Financials!CD101 -> 460.24419 | G35: =Financials!CE101 -> 542.18315 | H35: =Financials!CF101 -> 476.32747 | J35: Other Liabilities | K35: =K37-K36-SUM(K31:K34) -> 3015 | L35: =L37-L36-SUM(L31:L34) -> 2071 | M35: =M37-M36-SUM(M31:M34) -> 2159 | N35: =N37-N36-SUM(N31:N34) -> 1663 | O35: =O37-O36-SUM(O31:O34) -> 1589.5955 | P35: =P37-P36-SUM(P31:P34) -> 1515.2575
B36: EBIT | C36: =Financials!BZ98 -> 224 | D36: =Financials!CA98 -> 184 | E36: =Financials!CC98 -> 127.78647 | F36: =Financials!CD98 -> 336.24419 | G36: =Financials!CE98 -> 418.18315 | H36: =Financials!CF98 -> 361.32747 | J36: Shareholders' Equity | K36: =Financials!$BM$172-Financials!$BM$170 -> 3799 | L36: =Financials!$BR$172-Financials!$BR$170 -> 2436 | M36: =Financials!$BW$172-Financials!$BW$170 -> 2274 | N36: =Financials!$CB$172-Financials!$CB$170 -> 3320 | O36: =Financials!$CG$172-Financials!$CG$170 -> 4339.2968 | P36: =Financials!$CL$172-Financials!$CL$170 -> 5546.2745
B37: Adj. EPS | C37: =Financials!BZ64 -> 0.912264 | D37: =Financials!CA64 -> 0.76745105 | E37: =Financials!CC64 -> 0.22229559 | F37: =Financials!CD64 -> 1.4474911 | G37: =Financials!CE64 -> 1.9108477 | H37: =Financials!CF64 -> 1.5303598 | J37: Liabilities & Equity | K37: =K29 -> 12314 | L37: =L29 -> 9190 | M37: =M29 -> 9160 | N37: =N29 -> 9862 | O37: =O29 -> 11177.149 | P37: =P29 -> 12339.327
B38: Reported EPS | C38: =Financials!BZ94 -> 0.8329367 | D38: =Financials!CA94 -> 0.89724056 | E38: =Financials!CC94 -> 0.22229559 | F38: =Financials!CD94 -> 1.4474911 | G38: =Financials!CE94 -> 1.9108477 | H38: =Financials!CF94 -> 1.5303598
J39: Cashflow Statement
B40: Important Ratios | J40: =+$J$6 -> Year End December (US$M) | K40: =+K21 -> 2014 | L40: =+L21 -> 2015 | M40: =+M21 -> 2016 | N40: =+N21 -> 2017 | O40: =+O21 -> 2018e | P40: =+P21 -> 2019e
B41: =+$B$28 -> Year End December | C41: =+C21 -> 2014 | D41: =+D21 -> 2015 | E41: =+E21 -> 2016 | F41: =+F21 -> 2017 | G41: =+G21 -> 2018e | H41: =+H21 -> 2019e | J41: Net Income | K41: =Financials!$BM$217 -> 102 | L41: =Financials!$BR$217 -> -1642 | M41: =Financials!$BW$217 -> -440 | N41: =Financials!$CB$217 -> 387 | O41: =Financials!$CG$217 -> 894.3957 | P41: =Financials!$CL$217 -> 1082.0766
B42: Diluted Shares Out (m) | C42: =Financials!$BM$67 -> 148.62718 | D42: =Financials!$BR$67 -> 146.094 | E42: =Financials!$BW$67 -> 156.618 | F42: =Financials!$CB$67 -> 176.75142 | G42: =Financials!$CG$67 -> 174.99446 | H42: =Financials!$CL$67 -> 174.99446 | J42: D&A | K42: =K9 -> 627 | L42: =L9 -> 547 | M42: =M9 -> 507 | N42: =N9 -> 501 | O42: =O9 -> 495 | P42: =P9 -> 495
B43: Adj. EPS | C43: =K17 -> 4.4608261 | D43: =L17 -> -5.1268361 | E43: =M17 -> -1.5834706 | F43: =N17 -> 1.9292632 | G43: =O17 -> 5.1109942 | H43: =P17 -> 6.1834904 | J43: Others | K43: =K45-K44-K42-K41 -> 397 | L43: =L45-L44-L42-L41 -> 897 | M43: =M45-M44-M42-M41 -> 54 | N43: =N45-N44-N42-N41 -> -106 | O43: =O45-O44-O42-O41 -> 133.18707 | P43: =P45-P44-P42-P41 -> 132.58033
B44: EPS Growth YoY | C44: =Financials!$BM$65 -> -6.9121992 | D44: =Financials!$BR$65 -> -2.1493019 | E44: =Financials!$BW$65 -> -0.69114078 | F44: =Financials!$CB$65 -> -2.2183764 | G44: =Financials!$CG$65 -> 1.6491949 | H44: =Financials!$CL$65 -> 0.209841 | J44: (Increase) in Working Capital | K44: =Financials!$BM$228 -> 366 | L44: =Financials!$BR$228 -> 557 | M44: =Financials!$BW$228 -> 606 | N44: =Financials!$CB$228 -> 20 | O44: =Financials!$CG$228 -> -390.64852 | P44: =Financials!$CL$228 -> -181.60387
B45: P/E | C45: =C61/C43 -> 7.9604089 | D45: =D61/D43 -> -6.926299 | E45: =E61/E43 -> -22.425424 | F45: =F61/F43 -> 18.405991 | G45: =G61/G43 -> 6.9477676 | H45: =H61/H43 -> 5.7427113 | J45: Net Cash from Operations | K45: =Financials!$BM$233 -> 1492 | L45: =Financials!$BR$233 -> 359 | M45: =Financials!$BW$233 -> 727 | N45: =Financials!$CB$233 -> 802 | O45: =Financials!$CG$233 -> 1131.9343 | P45: =Financials!$CL$233 -> 1528.053
B46: P/B | C46: =C61/(K36/C42) -> 1.3892475 | D46: =D61/(L36/D42) -> 2.1296379 | E46: =E61/(M36/E42) -> 2.4456927 | F46: =F61/(N36/F42) -> 1.8904948 | G46: =G61/(O36/G42) -> 1.4320416 | H46: =H61/(P36/H42) -> 1.1204013
B47: EV | C47: =(C42*C61)+C54+Financials!BM170 -> 7422.7511 | D47: =(D42*D61)+D54+Financials!BR170 -> 7594.7979 | E47: =(E42*E61)+E54+Financials!BW170 -> 7078.5052 | F47: =(F42*F61)+F54+Financials!CB170 -> 7427.4428 | G47: =(G42*G61)+G54+Financials!CG170 -> 7118.1181 | H47: =(H42*H61)+H54+Financials!CL170 -> 6775.0639 | J47: Acquisitions | K47: =Financials!$BM$238 -> 0 | L47: =Financials!$BR$238 -> -25 | M47: =Financials!$BW$238 -> 0 | N47: =Financials!$CB$238 -> 0 | O47: =Financials!$CG$238 -> 0 | P47: =Financials!$CL$238 -> 0
B48: EV/EBITDA | C48: =C47/K11 -> 4.4235704 | D48: =D47/L11 -> 37.59801 | E48: =E47/M11 -> 13.879422 | F48: =F47/N11 -> 6.8329741 | G48: =G47/O11 -> 4.0943049 | H48: =H47/P11 -> 3.509727 | J48: Capex | K48: =Financials!$BM$236 -> -419 | L48: =Financials!$BR$236 -> -500 | M48: =Financials!$BW$236 -> -306 | N48: =Financials!$CB$236 -> -505 | O48: =Financials!$CG$236 -> -850 | P48: =Financials!$CL$236 -> -1150
B49: Dividend Per Share | C49: =Financials!$BM$69 -> 0.2 | D49: =Financials!$BR$69 -> 0.2 | E49: =Financials!$BW$69 -> 0.2 | F49: =Financials!$CB$69 -> 0.2 | G49: =Financials!$CG$69 -> 0.2 | H49: =Financials!$CL$69 -> 0.2 | J49: Others | K49: =K50-K48-K47 -> 53 | L49: =L50-L48-L47 -> 15 | M49: =M50-M48-M47 -> -12 | N49: =N50-N48-N47 -> 116 | O49: =O50-O48-O47 -> 0 | P49: =P50-P48-P47 -> 0
B50: Payout ratio | C50: =C49/C43 -> 0.044834745 | D50: =D49/D43 -> -0.039010414 | E50: =E49/E43 -> -0.12630484 | F50: =F49/F43 -> 0.10366652 | G50: =G49/G43 -> 0.03913133 | H50: =H49/H43 -> 0.032344192 | J50: Net Cash used in Investing | K50: =Financials!$BM$243 -> -366 | L50: =Financials!$BR$243 -> -510 | M50: =Financials!$BW$243 -> -318 | N50: =Financials!$CB$243 -> -389 | O50: =Financials!$CG$243 -> -850 | P50: =Financials!$CL$243 -> -1150
B51: Div Yield | C51: =+C49/C61 -> 0.0056322163 | D51: =+D49/D61 -> 0.0056322163 | E51: =+E49/E61 -> 0.0056322163 | F51: =+F49/F61 -> 0.0056322163 | G51: =+G49/G61 -> 0.0056322163 | H51: =+H49/H61 -> 0.0056322163
B52: ROE | C52: =K16/Financials!BH172 -> 0.19796954 | D52: =L16/K36 -> -0.19715715 | E52: =M16/L36 -> -0.10180624 | F52: =N16/M36 -> 0.14995602 | G52: =O16/N36 -> 0.26939629 | H52: =P16/O36 -> 0.24936681 | J52: Proceeds from Equity | K52: =Financials!BM246+Financials!BM247+Financials!BM248 -> 0 | L52: =Financials!BR246+Financials!BR247+Financials!BR248 -> 0 | M52: =Financials!BW246+Financials!BW247+Financials!BW248 -> 517 | N52: =Financials!CB246+Financials!CB247+Financials!CB248 -> 20 | O52: =Financials!CG246+Financials!CG247+Financials!CG248 -> 0 | P52: =Financials!CL246+Financials!CL247+Financials!CL248 -> 0
B53: ROIC | C53: =(Financials!BM39*(1-Financials!BM52)/(Financials!BH149+Financials!BH154+Financials!BH172-Financials!BH170-Financials!BH121)) -> 0.12904269 | D53: =(Financials!BR39*(1-Financials!BR52)/(Financials!BM149+Financials!BM154+Financials!BM172-Financials!BM170-Financials!BM121)) -> -0.076820787 | E53: =(Financials!BW39*(1-Financials!BW52)/(Financials!BR149+Financials!BR154+Financials!BR172-Financials!BR170-Financials!BR121)) -> 0.00068596212 | F53: =(Financials!CB39*(1-Financials!CB52)/(Financials!BW149+Financials!BW154+Financials!BW172-Financials!BW170-Financials!BW121)) -> 0.15691827 | G53: =(Financials!CG39*(1-Financials!CG52)/(Financials!CB149+Financials!CB154+Financials!CB172-Financials!CB170-Financials!CB121)) -> 0.25591315 | H53: =(Financials!CL39*(1-Financials!CL52)/(Financials!CG149+Financials!CG154+Financials!CG172-Financials!CG170-Financials!CG121)) -> 0.25385173 | J53: Proceeds from Debt | K53: =Financials!BM249+Financials!BM250+Financials!BM251+Financials!BM252 -> -325 | L53: =Financials!BR249+Financials!BR250+Financials!BR251+Financials!BR252 -> -379 | M53: =Financials!BW249+Financials!BW250+Financials!BW251+Financials!BW252 -> -112 | N53: =Financials!CB249+Financials!CB250+Financials!CB251+Financials!CB252 -> -367 | O53: =Financials!CG249+Financials!CG250+Financials!CG251+Financials!CG252 -> 0 | P53: =Financials!CL249+Financials!CL250+Financials!CL251+Financials!CL252 -> 0
B54: Net Debt | C54: =K32+K31-K22 -> 2144 | D54: =L32+L31-L22 -> 2406 | E54: =M32+M31-M22 -> 1516 | F54: =N32+N31-N22 -> 1150 | G54: =O32+O31-O22 -> 903.06464 | H54: =P32+P31-P22 -> 560.01049 | J54: Others
B55: Leverage (Net Debt/Captital) | C55: =C54/(C54+K36) -> 0.36076056 | D55: =D54/(D54+L36) -> 0.49690211 | E55: =E54/(E54+M36) -> 0.4 | F55: =F54/(F54+N36) -> 0.25727069 | G55: =G54/(G54+O36) -> 0.17226295 | H55: =H54/(H54+P36) -> 0.091710507 | J55: Net Cash used in Financing | K55: =Financials!$BM$257 -> -341 | L55: =Financials!$BR$257 -> -407 | M55: =Financials!$BW$257 -> 359 | N55: =Financials!$CB$257 -> -392 | O55: =Financials!$CG$257 -> -34.998893 | P55: =Financials!$CL$257 -> -34.998893
B56: Leverage (Net Debt/EBITDA) | C56: =C54/K11 -> 1.2777116 | D56: =D54/L11 -> 11.910891 | E56: =E54/M11 -> 2.972549 | F56: =F54/N11 -> 1.0579577 | G56: =G54/O11 -> 0.51943813 | H56: =H54/P11 -> 0.29010559
B57: FCF Per Share | C57: =Financials!$BM$268 -> 7.3918053 | D57: =Financials!$BR$268 -> -0.96513204 | E57: =Financials!$BW$268 -> 2.6880691 | F57: =Financials!$CB$268 -> 1.6991843 | G57: =Financials!$CG$268 -> 1.6111038 | H57: =Financials!$CL$268 -> 2.1603714 | J57: Net Cash Inflow | K57: =Financials!$BM$261 -> 750 | L57: =Financials!$BR$261 -> -599 | M57: =Financials!$BW$261 -> 760 | N57: =Financials!$CB$261 -> 38 | O57: =Financials!$CG$261 -> 246.93536 | P57: =Financials!$CL$261 -> 343.05415
B58: FCF Yield | C58: =(C57)/C61 -> 0.20816123 | D58: =(D57)/D61 -> -0.027179162 | E58: =(E57)/E61 -> 0.075698932 | F58: =(F57)/F61 -> 0.047850868 | G58: =(G57)/G61 -> 0.045370426 | H58: =(H57)/H61 -> 0.060838396 | J58: Closing Cash Balance | K58: =Financials!$BM$263 -> 1354 | L58: =Financials!$BR$263 -> 755 | M58: =Financials!$BW$263 -> 1515 | N58: =Financials!$CB$263 -> 1553 | O58: =Financials!$CG$263 -> 1799.9354 | P58: =Financials!$CL$263 -> 2142.9895
B60: For Lookups | C60: 43008 | D60: =DATE(YEAR(C60),MONTH(C60)+4,DAY(C69)) -> 43100 | E60: =DATE(YEAR(D60),MONTH(D60)+4,DAY(D69)) -> 43190 | F60: =DATE(YEAR(E60),MONTH(E60)+4,DAY(E69)) -> 43281 | G60: =DATE(YEAR(F60),MONTH(F60)+4,DAY(F69)) -> 43373 | H60: =DATE(YEAR(G60),MONTH(G60)+4,DAY(G69)) -> 43465
B61: Stock Price | C61: =D61 -> 35.51 | D61: =E61 -> 35.51 | E61: =F61 -> 35.51 | F61: =G61 -> 35.51 | G61: =H61 -> 35.51 | H61: 35.51

Sheet Operations
A1: =Financials!A2 -> US Steel Corporation
A2: Key Model Drivers
A3: (Input Fields in Blue)
D4: =Operations!D25 -> 2001 | E4: =Operations!E25 -> 2002 | F4: =Operations!F25 -> 1Q | G4: =Operations!G25 -> 2Q | H4: =Operations!H25 -> 3Q | I4: =Operations!I25 -> 4Q | J4: 2003 | K4: 1Q | L4: 2Q | M4: 3Q | N4: 4Q | O4: 2004 | P4: 1Q | Q4: 2Q | R4: 3Q | S4: 4Q | T4: 2005 | U4: 1Q | V4: 2Q | W4: 3Q | X4: 4Q | Y4: 2006 | Z4: 1Q | AA4: 2Q | AB4: 3Q | AC4: 4Q | AD4: 2007 | AE4: 1Q | AF4: 2Q | AG4: 3Q | AH4: 4Q | AI4: 2008 | AJ4: 1Q | AK4: 2Q | AL4: 3Q | AM4: 4Q | AN4: 2009 | AO4: 1Q | AP4: 2Q | AQ4: 3Q | AR4: 4Q | AS4: 2010 | AT4: 1Q | AU4: 2Q | AV4: 3Q | AW4: 4Q | AX4: 2011 | AY4: 1Q | AZ4: 2Q | BA4: 3Q | BB4: 4Q | BC4: 2012 | BD4: 1Q | BE4: 2Q | BF4: 3Q | BG4: 4Q | BH4: 2013 | BI4: 1Q | BJ4: 2Q | BK4: 3Q | BL4: 4Q | BM4: 2014 | BN4: 1Q | BO4: 2Q | BP4: 3Q | BQ4: 4Q | BR4: 2015 | BS4: 1Q | BT4: 2Q | BU4: 3Q | BV4: 4Q | BW4: 2016 | BX4: 1Q | BY4: 2Q | BZ4: 3Q | CA4: 4Q | CB4: 2017 | CC4: 1QE | CD4: 2QE | CE4: 3QE | CF4: 4QE | CG4: 2018E | CH4: 1QE | CI4: 2QE | CJ4: 3QE | CK4: 4QE | CL4: 2019E | CM4: 1QE | CN4: 2QE | CO4: 3QE | CP4: 4QE | CQ4: 2020E
AE5: 39538 | AF5: 39629 | AG5: 39721 | AH5: 39813 | AI5: FY8 | AJ5: 39903 | AK5: 39994 | AL5: 40086 | AM5: 40178 | AN5: FY9 | AO5: 40268 | AP5: 40359 | AQ5: 40451 | AR5: 40543 | AS5: FY10 | AT5: 40633 | AU5: 40724 | AV5: 40816 | AW5: 40908 | AX5: FY11 | AY5: 40999 | AZ5: 41090 | BA5: 41182 | BB5: 41274 | BC5: FY12 | BD5: 41364 | BE5: 41455 | BF5: 41547 | BG5: 41639 | BH5: FY13 | BI5: 41729 | BJ5: 41820 | BK5: 41912 | BL5: 42004 | BM5: FY14 | BN5: 42094 | BO5: 42185 | BP5: 42277 | BQ5: 42369 | BR5: FY15 | BS5: 42460 | BT5: 42551 | BU5: 42643 | BV5: 42735 | BW5: FY16 | BX5: 42825 | BY5: 42916 | BZ5: 43008 | CA5: 43100 | CB5: FY17 | CC5: 43190 | CD5: 43281 | CE5: 43373 | CF5: 43465 | CG5: FY18 | CH5: 43555 | CI5: 43646 | CJ5: 43738 | CK5: 43830 | CL5: FY19 | CM5: 43921 | CN5: 44012 | CO5: 44104 | CP5: 44196 | CQ5: FY20
A6: Price Assumptions
B7: Flat-Rolled Segment ($ per ton)
C8: Hot-rolled Sheets | J8: 290.5 | K8: 462.33333 | L8: 610 | M8: 703.33333 | N8: 658.33333 | O8: =AVERAGE(K8:N8) -> 608.5 | P8: 631.66667 | Q8: 532.5 | R8: 461.66667 | S8: 550 | T8: =AVERAGE(P8:S8) -> 543.95833 | U8: 550 | V8: 591.66667 | W8: 621.66667 | X8: 563.33333 | Y8: =AVERAGE(U8:X8) -> 581.66667 | Z8: 518.33333 | AA8: 553.33333 | AB8: 516.66667 | AC8: 535 | AD8: =AVERAGE(Z8:AC8) -> 530.83333 | AE8: 691.66667 | AF8: 976.66667 | AG8: 1051.6667 | AH8: 714 | AI8: =AVERAGE(AE8:AH8) -> 858.5 | AJ8: 508.66667 | AK8: 399 | AL8: 491.33333 | AM8: 528 | AN8: =AVERAGE(AJ8:AM8) -> 481.75 | AO8: 592 | AP8: 682 | AQ8: 582.66667 | AR8: 557 | AS8: =AVERAGE(AO8:AR8) -> 603.41667 | AT8: 795.66667 | AU8: 813 | AV8: 687.66782 | AW8: 657.66667 | AX8: =AVERAGE(AT8:AW8) -> 738.50029 | AY8: 720.66667 | AZ8: 660 | BA8: 625.66667 | BB8: 619.99869 | BC8: =AVERAGE(AY8:BB8) -> 656.58301 | BD8: 616.66667 | BE8: 592.33333 | BF8: 643.66667 | BG8: 658.99708 | BH8: =AVERAGE(BD8:BG8) -> 627.91594 | BI8: 654.66667 | BJ8: 671 | BK8: 667.66667 | BL8: 634.33333 | BM8: =AVERAGE(BI8:BL8) -> 656.91667 | BN8: 536.33333 | BO8: 453.66667 | BP8: 459 | BQ8: 387 | BR8: =AVERAGE(BN8:BQ8) -> 459 | BS8: 398.33333 | BT8: 561.66667 | BU8: 592 | BV8: 521 | BW8: =AVERAGE(BS8:BV8) -> 518.25 | BX8: 622.66667 | BY8: 623.5942 | BZ8: 621.41848 | CA8: 618.09489 | CB8: =AVERAGE(BX8:CA8) -> 621.44356 | CC8: 741.07743 | CD8: 885 | CE8: 830 | CF8: 785 | CG8: =AVERAGE(CC8:CF8) -> 810.26936 | CH8: 800 | CI8: 770 | CJ8: 760 | CK8: 715 | CL8: =AVERAGE(CH8:CK8) -> 761.25 | CM8: 660 | CN8: 675 | CO8: 645 | CP8: 645 | CQ8: =AVERAGE(CM8:CP8) -> 656.25
C9: Cold-rolled Sheets | J9: 386.25 | K9: 538.77778 | L9: 696.66667 | M9: 796.66667 | N9: 750 | O9: =AVERAGE(K9:N9) -> 695.52778 | P9: 710 | Q9: 617.5 | R9: 556.66667 | S9: 640 | T9: =AVERAGE(P9:S9) -> 631.04167 | U9: 640 | V9: 685 | W9: 716.66667 | X9: 658.33333 | Y9: =AVERAGE(U9:X9) -> 675 | Z9: 610 | AA9: 628.33333 | AB9: 606.66667 | AC9: 625 | AD9: =AVERAGE(Z9:AC9) -> 617.5 | AE9: 786.66667 | AF9: 1073.3333 | AG9: 1145 | AH9: 806.66667 | AI9: =AVERAGE(AE9:AH9) -> 952.91667 | AJ9: 596 | AK9: 479.66667 | AL9: 599 | AM9: 638.33333 | AN9: =AVERAGE(AJ9:AM9) -> 578.25 | AO9: 715 | AP9: 792 | AQ9: 701 | AR9: 664.66667 | AS9: =AVERAGE(AO9:AR9) -> 718.16667 | AT9: 904.33333 | AU9: 915.66667 | AV9: 800.66528 | AW9: 768 | AX9: =AVERAGE(AT9:AW9) -> 847.16632 | AY9: 824.33333 | AZ9: 766.66667 | BA9: 735.66667 | BB9: 729.33333 | BC9: =AVERAGE(AY9:BB9) -> 764 | BD9: 725 | BE9: 701.66667 | BF9: 752.33333 | BG9: 770.9966 | BH9: =AVERAGE(BD9:BG9) -> 737.49915 | BI9: 776.66667 | BJ9: 800.33333 | BK9: 794.33333 | BL9: 760.66667 | BM9: =AVERAGE(BI9:BL9) -> 783 | BN9: 674 | BO9: 574.66667 | BP9: 588 | BQ9: 515.33333 | BR9: =AVERAGE(BN9:BQ9) -> 588 | BS9: 551.66667 | BT9: 748.66667 | BU9: 809 | BV9: 743.66667 | BW9: =AVERAGE(BS9:BV9) -> 713.25 | BX9: 827.66667 | BY9: 825.34783 | BZ9: 798.1917 | CA9: 803.08744 | CB9: =AVERAGE(BX9:CA9) -> 813.57341 | CC9: 887.71308 | CD9: 1015 | CE9: 970 | CF9: 935 | CG9: =AVERAGE(CC9:CF9) -> 951.92827 | CH9: 950 | CI9: 920 | CJ9: 910 | CK9: 865 | CL9: =AVERAGE(CH9:CK9) -> 911.25 | CM9: 810 | CN9: 825 | CO9: 795 | CP9: 795 | CQ9: =AVERAGE(CM9:CP9) -> 806.25
C10: Coated Sheets | J10: 396.75 | K10: 548.77778 | L10: 720 | M10: 863.33333 | N10: 805 | O10: =AVERAGE(K10:N10) -> 734.27778 | P10: 756.66667 | Q10: 655 | R10: 603.33333 | S10: 695 | T10: =AVERAGE(P10:S10) -> 677.5 | U10: 703.33333 | V10: 783.33333 | W10: 826.66667 | X10: 765 | Y10: =AVERAGE(U10:X10) -> 769.58333 | Z10: 716.66667 | AA10: 726.66667 | AB10: 703.33333 | AC10: 702 | AD10: =AVERAGE(Z10:AC10) -> 712.16667 | AE10: 857 | AF10: 1153 | AG10: 1207.3333 | AH10: 865 | AI10: =AVERAGE(AE10:AH10) -> 1020.5833 | AJ10: 642.66667 | AK10: 519.66667 | AL10: 662 | AM10: 699 | AN10: =AVERAGE(AJ10:AM10) -> 630.83333 | AO10: 779.66667 | AP10: 848 | AQ10: 756 | AR10: 718 | AS10: =AVERAGE(AO10:AR10) -> 775.41667 | AT10: 956.33333 | AU10: 980 | AV10: 867.00064 | AW10: 837 | AX10: =AVERAGE(AT10:AW10) -> 910.08349 | AY10: 888 | AZ10: 823.66667 | BA10: 796 | BB10: 778.99833 | BC10: =AVERAGE(AY10:BB10) -> 821.66625 | BD10: 781.66667 | BE10: 757.33333 | BF10: 807.66667 | BG10: 827.66301 | BH10: =AVERAGE(BD10:BG10) -> 793.58242 | BI10: 826.33333 | BJ10: 853 | BK10: 851.66667 | BL10: 829 | BM10: =AVERAGE(BI10:BL10) -> 840 | BN10: 740.33333 | BO10: 652.66667 | BP10: 653.66667 | BQ10: 568.66667 | BR10: =AVERAGE(BN10:BQ10) -> 653.83333 | BS10: 610 | BT10: 803 | BU10: 864.66667 | BV10: 799.66667 | BW10: =AVERAGE(BS10:BV10) -> 769.33333 | BX10: 905 | BY10: 910.37681 | BZ10: 885.73946 | CA10: 878.6011 | CB10: =AVERAGE(BX10:CA10) -> 894.92934 | CC10: 929.99058 | CD10: 1120 | CE10: 1080 | CF10: 1040 | CG10: =AVERAGE(CC10:CF10) -> 1042.4976 | CH10: 1050 | CI10: 1015 | CJ10: 1005 | CK10: 960 | CL10: =AVERAGE(CH10:CK10) -> 1007.5 | CM10: 900 | CN10: 915 | CO10: 885 | CP10: 885 | CQ10: =AVERAGE(CM10:CP10) -> 896.25
C11: Tin Mill Products | J11: 474.98704 | K11: 662.47822 | L11: 856.14736 | M11: 957.56237 | N11: 910.10136 | O11: =AVERAGE(K11:N11) -> 846.57233 | P11: 856.0277 | Q11: 760.99291 | R11: 683.96655 | S11: 756.56204 | T11: =AVERAGE(P11:S11) -> 764.3873 | U11: 777.71175 | V11: 841.18516 | W11: 872.63419 | X11: 843.21742 | Y11: =AVERAGE(U11:X11) -> 833.68713 | Z11: 836.27189 | AA11: 882.09743 | AB11: 878.06193 | AC11: 923.48105 | AD11: =AVERAGE(Z11:AC11) -> 879.97808 | AE11: 1110.0963 | AF11: 1479.3705 | AG11: 1557.0173 | AH11: 1214.783 | AI11: =AVERAGE(AE11:AH11) -> 1340.3168 | AJ11: 1003.1487 | AK11: 885.99888 | AL11: 1004.5157 | AM11: 1043.8491 | AN11: =AVERAGE(AJ11:AM11) -> 984.3781 | AO11: 1023.446 | AP11: 1118.5899 | AQ11: =AQ9+AQ$13/1.1023*1000*0.02 -> 1073.7038 | AR11: =AR9+AR$13/1.1023*1000*0.02 -> 1134.7103 | AS11: =AVERAGE(AO11:AR11) -> 1087.6125 | AT11: =AT9+AT$13/1.1023*1000*0.02 -> 1447.139 | AU11: =AU9+AU$13/1.1023*1000*0.02 -> 1434.3107 | AV11: =AV9+AV$13/1.1023*1000*0.02 -> 1247.3338 | AW11: =AW9+AW$13/1.1023*1000*0.02 -> 1146.8285 | AX11: =AVERAGE(AT11:AW11) -> 1318.903 | AY11: =AY9+AY$13/1.1023*1000*0.02 -> 1240.6014 | AZ11: =AZ9+AZ$13/1.1023*1000*0.02 -> 1139.3767 | BA11: =BA9+BA$13/1.1023*1000*0.02 -> 1085.5857 | BB11: =BB9+BB$13/1.1023*1000*0.02 -> 1120.2169 | BC11: =AVERAGE(AY11:BB11) -> 1146.4452 | BD11: =BD9+BD$13/1.1023*1000*0.02 -> 1161.4589 | BE11: =BE9+BE$13/1.1023*1000*0.02 -> 1080.6785 | BF11: =BF9+BF$13/1.1023*1000*0.02 -> 1138.0428 | BG11: =BG9+BG$13/1.1023*1000*0.02 -> 1186.5851 | BH11: =AVERAGE(BD11:BG11) -> 1141.6913 | BI11: =BI9+BI$13/1.1023*1000*0.02 -> 1187.155 | BJ11: =BJ9+BJ$13/1.1023*1000*0.02 -> 1220.1763 | BK11: =BK9+BK$13/1.1023*1000*0.02 -> 1191.9221 | BL11: =BL9+BL$13/1.1023*1000*0.02 -> 1121.1414 | BM11: =AVERAGE(BI11:BL11) -> 1180.0987 | BN11: =BN9+BN$13/1.1023*1000*0.02 -> 1007.371 | BO11: =BO9+BO$13/1.1023*1000*0.02 -> 857.96419 | BP11: =BP9+BP$13/1.1023*1000*0.02 -> 864.08805 | BQ11: =BQ9+BQ$13/1.1023*1000*0.02 -> 791.42139 | BR11: =AVERAGE(BN11:BQ11) -> 880.21116 | BS11: =BS9+BS$13/1.1023*1000*0.02 -> 833.0852 | BT11: =BT9+BT$13/1.1023*1000*0.02 -> 1055.3173 | BU11: =BU9+BU$13/1.1023*1000*0.02 -> 1146.4827 | BV11: =BV9+BV$13/1.1023*1000*0.02 -> 1121.4507 | BW11: =AVERAGE(BS11:BV11) -> 1039.084 | BX11: =BX9+BX$13/1.1023*1000*0.02 -> 1191.0411 | BY11: =BY9+BY$13/1.1023*1000*0.02 -> 1186.7604 | BZ11: =BZ9+BZ$13/1.1023*1000*0.02 -> 1170.388 | CA11: =CA9+CA$13/1.1023*1000*0.02 -> 1175.2837 | CB11: =AVERAGE(BX11:CA11) -> 1180.8683 | CC11: =CC9+CC$13/1.1023*1000*0.02 -> 1259.9094 | CD11: =CD9+CD$13/1.1023*1000*0.02 -> 1399 | CE11: =CE9+CE$13/1.1023*1000*0.02 -> 1350 | CF11: =CF9+CF$13/1.1023*1000*0.02 -> 1315 | CG11: =AVERAGE(CC11:CF11) -> 1330.9773 | CH11: =CH9+CH$13/1.1023*1000*0.02 -> 1330 | CI11: =CI9+CI$13/1.1023*1000*0.02 -> 1300 | CJ11: =CJ9+CJ$13/1.1023*1000*0.02 -> 1290 | CK11: =CK9+CK$13/1.1023*1000*0.02 -> 1245 | CL11: =AVERAGE(CH11:CK11) -> 1291.25 | CM11: =CM9+CM$13/1.1023*1000*0.02 -> 1230 | CN11: =CN9+CN$13/1.1023*1000*0.02 -> 1245 | CO11: =CO9+CO$13/1.1023*1000*0.02 -> 1235 | CP11: =CP9+CP$13/1.1023*1000*0.02 -> 1235 | CQ11: =AVERAGE(CM11:CP11) -> 1236.25
C12: Semi-finished and Plates | J12: 224.07693 | K12: 349.26971 | L12: 465.69295 | M12: 480.81285 | N12: 498.95673 | O12: =AVERAGE(K12:N12) -> 448.68306 | P12: 492.90877 | Q12: 438.47712 | R12: 334.14981 | S12: 362.87762 | T12: =AVERAGE(P12:S12) -> 407.10333 | U12: 359.85364 | V12: 438.47712 | W12: 495.93275 | X12: 456.621 | Y12: =AVERAGE(U12:X12) -> 437.72113 | Z12: 441.5011 | AA12: 501.98071 | AB12: 489.88479 | AC12: 489.88479 | AD12: =AVERAGE(Z12:AC12) -> 480.81285 | AE12: 544.31643 | AF12: 816.47464 | AG12: 946.50579 | AH12: 559.43633 | AI12: =AVERAGE(AE12:AH12) -> 716.6833 | AJ12: 323.68747 | AK12: 118.3 | AL12: 293.44767 | AM12: 387.06946 | AN12: =AVERAGE(AJ12:AM12) -> 280.62615 | AO12: 456.621 | AP12: 547.34041 | AQ12: 492.90877 | AR12: 483.83683 | AS12: =AVERAGE(AO12:AR12) -> 495.17675 | AT12: 613.86797 | AU12: 669.81161 | AV12: 650.15573 | AW12: 666.78763 | AX12: =AVERAGE(AT12:AW12) -> 650.15573 | AY12: 622.93991 | AZ12: 559.50951 | BA12: 530 | BB12: 496.33333 | BC12: =AVERAGE(AY12:BB12) -> 552.19569 | BD12: 524.35816 | BE12: 506.45015 | BF12: 544.92123 | BG12: 549.75959 | BH12: =AVERAGE(BD12:BG12) -> 531.37228 | BI12: 539.17411 | BJ12: 524.6558 | BK12: 511.04801 | BL12: 472.03902 | BM12: =AVERAGE(BI12:BL12) -> 511.72924 | BN12: 399.16538 | BO12: 353.80568 | BP12: 328.10185 | BQ12: 306.93399 | BR12: =AVERAGE(BN12:BQ12) -> 347.00172 | BS12: 297.86205 | BT12: 382.53349 | BU12: 361.36563 | BV12: 390.09344 | BW12: =AVERAGE(BS12:BV12) -> 357.96365 | BX12: 452.08503 | BY12: 453.16667 | BZ12: 460.66667 | CA12: 468.09489 | CB12: =AVERAGE(BX12:CA12) -> 458.50332 | CC12: 591.07743 | CD12: 695 | CE12: 680 | CF12: 635 | CG12: =AVERAGE(CC12:CF12) -> 650.26936 | CH12: 650 | CI12: 620 | CJ12: 610 | CK12: 565 | CL12: =AVERAGE(CH12:CK12) -> 611.25 | CM12: 510 | CN12: 525 | CO12: 495 | CP12: 495 | CQ12: =AVERAGE(CM12:CP12) -> 506.25
C13: LME Tin ($k/t) | AO13: 17.205558 | AP13: 17.804716 | AQ13: 20.541567 | AR13: 25.906452 | AS13: =AVERAGE(AO13:AR13) -> 20.364573 | AT13: 29.916737 | AU13: 28.585066 | AV13: 24.618134 | AW13: 20.879132 | AX13: =AVERAGE(AT13:AW13) -> 25.999767 | AY13: 22.942616 | AZ13: 20.541914 | BA13: 19.285786 | BB13: 21.543547 | BC13: =AVERAGE(AY13:BB13) -> 21.078466 | BD13: 24.055435 | BE13: 20.889238 | BF13: 21.258376 | BG13: 22.905159 | BH13: =AVERAGE(BD13:BG13) -> 22.277052 | BI13: 22.624065 | BJ13: 23.139643 | BK13: 21.913105 | BL13: 19.867562 | BM13: =AVERAGE(BI13:BL13) -> 21.886094 | BN13: 18.373743 | BO13: 15.613943 | BP13: 15.216593 | BQ13: 15.216593 | BR13: =AVERAGE(BN13:BQ13) -> 16.105218 | BS13: 15.510382 | BT13: 16.901051 | BU13: 18.600358 | BV13: 20.821565 | BW13: =AVERAGE(BS13:BV13) -> 17.958339 | BX13: 20.02738 | BY13: 19.919255 | BZ13: 20.513598 | CA13: 20.513598 | CB13: =AVERAGE(BX13:CA13) -> 20.243458 | CC13: 20.513598 | CD13: 21.16416 | CE13: 20.9437 | CF13: 20.9437 | CG13: =AVERAGE(CC13:CF13) -> 20.89129 | CH13: 20.9437 | CI13: 20.9437 | CJ13: 20.9437 | CK13: 20.9437 | CL13: =AVERAGE(CH13:CK13) -> 20.9437 | CM13: 23.1483 | CN13: 23.1483 | CO13: 24.2506 | CP13: 24.2506 | CQ13: =AVERAGE(CM13:CP13) -> 23.69945
B14: Tubular Segment ($ per ton)
C15: Seamless | J15: 882.66667 | K15: 929.33333 | L15: 1297.3333 | M15: 1454.6667 | N15: 1480.3333 | O15: =AVERAGE(K15:N15) -> 1290.4167 | P15: 1527 | Q15: 1569.6667 | R15: 1556 | S15: 1553.6667 | T15: =AVERAGE(P15:S15) -> 1551.5833 | U15: 1569.3333 | V15: 1565 | W15: 1576 | X15: 1536 | Y15: =AVERAGE(U15:X15) -> 1561.5833 | Z15: 1517.3333 | AA15: 1467.6667 | AB15: 1472.3333 | AC15: 1470 | AD15: =AVERAGE(Z15:AC15) -> 1481.8333 | AE15: 1499 | AF15: 2108 | AG15: 3196 | AH15: 3086.6667 | AI15: =AVERAGE(AE15:AH15) -> 2472.4167 | AJ15: 2260 | AK15: 1563 | AL15: 1477 | AM15: 1503.3333 | AN15: =AVERAGE(AJ15:AM15) -> 1700.8333 | AO15: 1616.6667 | AP15: 1779 | AQ15: 1829 | AR15: 1767 | AS15: =AVERAGE(AO15:AR15) -> 1747.9167 | AT15: 1757.6667 | AU15: 1926.3333 | AV15: 1996.6667 | AW15: 2040.6667 | AX15: =AVERAGE(AT15:AW15) -> 1930.3333 | AY15: 2028.3333 | AZ15: 2000.3333 | BA15: 1927 | BB15: 1888.6667 | BC15: =AVERAGE(AY15:BB15) -> 1961.0833 | BD15: 1837.6667 | BE15: 1759.3333 | BF15: 1725.3333 | BG15: 1723 | BH15: =AVERAGE(BD15:BG15) -> 1761.3333 | BI15: 1691.6667 | BJ15: 1705.3333 | BK15: 1792.3333 | BL15: 1929.6667 | BM15: =AVERAGE(BI15:BL15) -> 1779.75 | BN15: 1768 | BO15: 1593.3333 | BP15: 1445 | BQ15: 1304.3333 | BR15: =AVERAGE(BN15:BQ15) -> 1527.6667 | BS15: 1213.3333 | BT15: 1171.6667 | BU15: 1198.3333 | BV15: 1182.3333 | BW15: =AVERAGE(BS15:BV15) -> 1191.4167 | BX15: 1312.3333 | BY15: 1504.6667 | BZ15: 1509.6667 | CA15: 1524 | CB15: =AVERAGE(BX15:CA15) -> 1462.6667 | CC15: 1584.6667 | CD15: 1780 | CE15: 1760 | CF15: 1745 | CG15: =AVERAGE(CC15:CF15) -> 1717.4167 | CH15: 1755 | CI15: 1760 | CJ15: 1755 | CK15: 1735 | CL15: =AVERAGE(CH15:CK15) -> 1751.25 | CM15: 1705 | CN15: 1710 | CO15: 1705 | CP15: 1685 | CQ15: =AVERAGE(CM15:CP15) -> 1701.25
C16: Welded | J16: 789.66667 | K16: 831 | L16: 1259.3333 | M16: 1315.6667 | N16: 1318.3333 | O16: =AVERAGE(K16:N16) -> 1181.0833 | P16: 1358.3333 | Q16: 1330.3333 | R16: 1352 | S16: 1358.3333 | T16: =AVERAGE(P16:S16) -> 1349.75 | U16: 1352.3333 | V16: 1369.6667 | W16: 1385 | X16: 1360.6667 | Y16: =AVERAGE(U16:X16) -> 1366.9167 | Z16: 1332.3333 | AA16: 1305.3333 | AB16: 1276.3333 | AC16: 1289 | AD16: =AVERAGE(Z16:AC16) -> 1300.75 | AE16: 1321.3333 | AF16: 1921 | AG16: 2941.6667 | AH16: 2769 | AI16: =AVERAGE(AE16:AH16) -> 2238.25 | AJ16: 2164 | AK16: 1602 | AL16: 1430 | AM16: 1376.3333 | AN16: =AVERAGE(AJ16:AM16) -> 1643.0833 | AO16: 1540 | AP16: 1683.6667 | AQ16: 1744.3333 | AR16: 1677.3333 | AS16: =AVERAGE(AO16:AR16) -> 1661.3333 | AT16: 1691.3333 | AU16: 1749.6667 | AV16: 1780 | AW16: 1759.3333 | AX16: =AVERAGE(AT16:AW16) -> 1745.0833 | AY16: 1699.3333 | AZ16: 1624 | BA16: 1584 | BB16: 1518.6667 | BC16: =AVERAGE(AY16:BB16) -> 1606.5 | BD16: 1475.6667 | BE16: 1441.3333 | BF16: 1397.3333 | BG16: 1406.3333 | BH16: =AVERAGE(BD16:BG16) -> 1430.1667 | BI16: 1395.6667 | BJ16: 1436.3333 | BK16: 1557.3333 | BL16: 1606.6667 | BM16: =AVERAGE(BI16:BL16) -> 1499 | BN16: 1466.6667 | BO16: 1296 | BP16: 1184.6667 | BQ16: 1088 | BR16: =AVERAGE(BN16:BQ16) -> 1258.8333 | BS16: 1034.3333 | BT16: 995 | BU16: 1011.6667 | BV16: 1000.3333 | BW16: =AVERAGE(BS16:BV16) -> 1010.3333 | BX16: 1117 | BY16: 1316.3333 | BZ16: 1308.6667 | CA16: 1302.6667 | CB16: =AVERAGE(BX16:CA16) -> 1261.1667 | CC16: 1352.6667 | CD16: 1535 | CE16: 1505 | CF16: 1485 | CG16: =AVERAGE(CC16:CF16) -> 1469.4167 | CH16: 1500 | CI16: 1470 | CJ16: 1460 | CK16: 1415 | CL16: =AVERAGE(CH16:CK16) -> 1461.25 | CM16: 1360 | CN16: 1375 | CO16: 1345 | CP16: 1345 | CQ16: =AVERAGE(CM16:CP16) -> 1356.25
B17: USSE Segment ($ per ton)
C18: Hot-rolled Sheets | J18: 238.96704 | K18: 389.6987 | L18: 474.88933 | M18: 531.44784 | N18: 603.82082 | O18: 499.96417 | P18: 617.43983 | Q18: 543.11764 | R18: 438.69405 | S18: 435.04539 | T18: 508.57423 | U18: 451.02379 | V18: 540.27772 | W18: 561.92697 | X18: 561.66809 | Y18: 528.72414 | Z18: 555.71914 | AA18: 602.18398 | AB18: 618.37054 | AC18: 649.6949 | AD18: 606.49214 | AE18: 717.65749 | AF18: 916.51131 | AG18: 1054.3847 | AH18: 673.85413 | AI18: 840.60191 | AJ18: 490.69393 | AK18: 465.05467 | AL18: 547.80209 | AM18: 560.813 | AN18: 516.09092 | AO18: 522.60667 | AP18: 680.03766 | AQ18: 655.595 | AR18: 629.96 | AS18: =AVERAGE(AO18:AR18) -> 622.04983 | AT18: 771.78833 | AU18: 772.87667 | AV18: 689.85667 | AW18: 620.28833 | AX18: =AVERAGE(AT18:AW18) -> 713.7025 | AY18: 651.60667 | AZ18: 633.90667 | BA18: 573.92167 | BB18: 560.94167 | BC18: =AVERAGE(AY18:BB18) -> 605.09417 | BD18: 598.68333 | BE18: 545.82667 | BF18: 528.89667 | BG18: 557.005 | BH18: =AVERAGE(BD18:BG18) -> 557.60292 | BI18: 558.54 | BJ18: 531.265 | BK18: 503.755 | BL18: 467.42667 | BM18: =AVERAGE(BI18:BL18) -> 515.24667 | BN18: 419.26667 | BO18: 402.66333 | BP18: 378.15 | BQ18: 328.42667 | BR18: =AVERAGE(BN18:BQ18) -> 382.12667 | BS18: 329.17333 | BT18: 422.82 | BU18: 431.88333 | BV18: 487.82667 | BW18: =AVERAGE(BS18:BV18) -> 417.92583 | BX18: 549.59833 | BY18: 520.825 | BZ18: 550.50794 | CA18: 574.73968 | CB18: =AVERAGE(BX18:CA18) -> 548.91774 | CC18: 625.47905 | CD18: 625 | CE18: 590 | CF18: 560 | CG18: =AVERAGE(CC18:CF18) -> 600.11976 | CH18: 550 | CI18: 550 | CJ18: 520 | CK18: 520 | CL18: =AVERAGE(CH18:CK18) -> 535 | CM18: 520 | CN18: 530 | CO18: 515 | CP18: 515 | CQ18: =AVERAGE(CM18:CP18) -> 520
C19: Cold-rolled Sheets | J19: 408.24865 | K19: 472.69352 | L19: 562.22536 | M19: 634.01865 | N19: 715.14145 | O19: 596.01975 | P19: 734.66926 | Q19: 668.23738 | R19: 549.33089 | S19: 542.90125 | T19: 623.7847 | U19: 560.15029 | V19: 655.39747 | W19: 676.60595 | X19: 666.19101 | Y19: 639.58618 | Z19: 654.82692 | AA19: 685.89392 | AB19: 699.57071 | AC19: 735.00838 | AD19: 693.82498 | AE19: 799.10473 | AF19: 1001.6109 | AG19: 1108.4557 | AH19: 722.14233 | AI19: 907.82842 | AJ19: 537.79823 | AK19: 509.69773 | AL19: 600.38851 | AM19: 614.6484 | AN19: 565.63322 | AO19: 572.77444 | AP19: 745.31807 | AQ19: =AP19*AQ18/AP18 -> 718.52903 | AR19: =AQ19*AR18/AQ18 -> 690.43319 | AS19: =AVERAGE(AO19:AR19) -> 681.76368 | AT19: =AR19*AT18/AR18 -> 845.87637 | AU19: =AT19*AU18/AT18 -> 847.06918 | AV19: =AU19*AV18/AU18 -> 756.07965 | AW19: =AV19*AW18/AV18 -> 679.83309 | AX19: =AVERAGE(AT19:AW19) -> 782.21457 | AY19: =AW19*AY18/AW18 -> 714.15783 | AZ19: =AY19*AZ18/AY18 -> 694.75872 | BA19: =AZ19*BA18/AZ18 -> 629.01544 | BB19: =BA19*BB18/BA18 -> 614.78942 | BC19: =AVERAGE(AY19:BB19) -> 663.18035 | BD19: =BB19*BD18/BB18 -> 656.15411 | BE19: =BD19*BE18/BD18 -> 598.22345 | BF19: =BE19*BF18/BE18 -> 579.66825 | BG19: =BF19*BG18/BF18 -> 610.47485 | BH19: =AVERAGE(BD19:BG19) -> 611.13017 | BI19: =BG19*BI18/BG18 -> 612.15721 | BJ19: =BI19*BJ18/BI18 -> 582.26393 | BK19: =BJ19*BK18/BJ18 -> 552.1131 | BL19: =BK19*BL18/BK18 -> 512.29742 | BM19: =AVERAGE(BI19:BL19) -> 564.70792 | BN19: =BN18*1.16 -> 486.34933 | BO19: =BN19*BO18/BN18 -> 467.08947 | BP19: =BO19*BP18/BO18 -> 438.654 | BQ19: =BP19*BQ18/BP18 -> 380.97493 | BR19: =AVERAGE(BN19:BQ19) -> 443.26693 | BS19: =BS18*1.16 -> 381.84107 | BT19: =BS19*BT18/BS18 -> 490.4712 | BU19: =BT19*BU18/BT18 -> 500.98467 | BV19: =BU19*BV18/BU18 -> 565.87893 | BW19: =AVERAGE(BS19:BV19) -> 484.79397 | BX19: =BX18*1.16 -> 637.53407 | BY19: =BY18*1.16 -> 604.157 | BZ19: =BZ18*1.16 -> 638.58921 | CA19: =CA18*1.16 -> 666.69803 | CB19: =AVERAGE(BX19:CA19) -> 636.74458 | CC19: =CA19*CC18/CA18 -> 725.5557 | CD19: =CC19*CD18/CC18 -> 725 | CE19: =CD19*CE18/CD18 -> 684.4 | CF19: =CE19*CF18/CE18 -> 649.6 | CG19: =AVERAGE(CC19:CF19) -> 696.13893 | CH19: =CF19*CH18/CF18 -> 638 | CI19: =CH19*CI18/CH18 -> 638 | CJ19: =CI19*CJ18/CI18 -> 603.2 | CK19: =CJ19*CK18/CJ18 -> 603.2 | CL19: =AVERAGE(CH19:CK19) -> 620.6 | CM19: =CK19*CM18/CK18 -> 603.2 | CN19: =CM19*CN18/CM18 -> 614.8 | CO19: =CN19*CO18/CN18 -> 597.4 | CP19: =CO19*CP18/CO18 -> 597.4 | CQ19: =AVERAGE(CM19:CP19) -> 603.2
C20: Coated Sheets | J20: 424.50056 | K20: 483.99985 | L20: 573.14235 | M20: 645.20978 | N20: 726.85941 | O20: 607.30285 | P20: 744.56162 | Q20: 670.06126 | R20: 554.90836 | S20: 560.85045 | T20: 632.59542 | U20: 578.27319 | V20: 756.46867 | W20: 802.75282 | X20: 797.93745 | Y20: 733.85803 | Z20: 797.69825 | AA20: 828.8176 | AB20: 824.39696 | AC20: 813.75927 | AD20: 816.16802 | AE20: 839.43882 | AF20: 1048.9066 | AG20: 1189.5622 | AH20: 794.57464 | AI20: 968.12058 | AJ20: 608.4508 | AK20: 576.65863 | AL20: 679.2638 | AM20: 695.39706 | AN20: 639.94257 | AO20: 648.02197 | AP20: 843.2333 | AQ20: =AP20*AQ19/AP19 -> 812.92488 | AR20: =AQ20*AR19/AQ19 -> 781.13798 | AS20: =AVERAGE(AO20:AR20) -> 771.32953 | AT20: =AR20*AT19/AR19 -> 957.00232 | AU20: =AT20*AU19/AT19 -> 958.35183 | AV20: =AU20*AV19/AU19 -> 855.40867 | AW20: =AV20*AW19/AV19 -> 769.14531 | AX20: =AVERAGE(AT20:AW20) -> 884.97703 | AY20: =AW20*AY19/AW19 -> 807.97942 | AZ20: =AY20*AZ19/AY19 -> 786.03177 | BA20: =AZ20*BA19/AZ19 -> 711.65155 | BB20: =BA20*BB19/BA19 -> 695.55661 | BC20: =AVERAGE(AY20:BB20) -> 750.30484 | BD20: =BB20*BD19/BB19 -> 742.35553 | BE20: =BC20*BE19/BC19 -> 676.81431 | BF20: =BE20*BF19/BE19 -> 655.82144 | BG20: =BF20*BG19/BF19 -> 690.67522 | BH20: =AVERAGE(BD20:BG20) -> 691.41663 | BI20: =BG20*BI19/BG19 -> 692.57859 | BJ20: =BI20*BJ19/BI19 -> 658.75813 | BK20: =BJ20*BK19/BJ19 -> 624.64627 | BL20: =BK20*BL19/BK19 -> 579.59985 | BM20: =AVERAGE(BI20:BL20) -> 638.89571 | BN20: =BN18*1.19 -> 498.92733 | BO20: =BN20*BO19/BN19 -> 479.16937 | BP20: =BO20*BP19/BO19 -> 449.9985 | BQ20: =BP20*BQ19/BP19 -> 390.82773 | BR20: =AVERAGE(BN20:BQ20) -> 454.73073 | BS20: =BS18*1.19 -> 391.71627 | BT20: =BS20*BT19/BS19 -> 503.1558 | BU20: =BT20*BU19/BT19 -> 513.94117 | BV20: =BU20*BV19/BU19 -> 580.51373 | BW20: =AVERAGE(BS20:BV20) -> 497.33174 | BX20: =BX18*1.19 -> 654.02202 | BY20: =BY18*1.19 -> 619.78175 | BZ20: =BZ18*1.19 -> 655.10444 | CA20: =CA18*1.19 -> 683.94022 | CB20: =AVERAGE(BX20:CA20) -> 653.21211 | CC20: =CA20*CC19/CA19 -> 744.32007 | CD20: =CC20*CD19/CC19 -> 743.75 | CE20: =CD20*CE19/CD19 -> 702.1 | CF20: =CE20*CF19/CE19 -> 666.4 | CG20: =AVERAGE(CC20:CF20) -> 714.14252 | CH20: =CF20*CH19/CF19 -> 654.5 | CI20: =CH20*CI19/CH19 -> 654.5 | CJ20: =CI20*CJ19/CI19 -> 618.8 | CK20: =CJ20*CK19/CJ19 -> 618.8 | CL20: =AVERAGE(CH20:CK20) -> 636.65 | CM20: =CK20*CM19/CK19 -> 618.8 | CN20: =CM20*CN19/CM19 -> 630.7 | CO20: =CN20*CO19/CN19 -> 612.85 | CP20: =CO20*CP19/CO19 -> 612.85 | CQ20: =AVERAGE(CM20:CP20) -> 618.8
C21: Tin Mill Products | J21: 496.9857 | K21: 596.39397 | L21: 721.70605 | M21: 794.91436 | N21: 875.24282 | O21: 747.0643 | P21: 880.69696 | Q21: 811.73029 | R21: 676.63078 | S21: 659.46328 | T21: 757.13033 | U21: 697.86205 | V21: 811.58263 | W21: 832.57347 | X21: 851.0751 | Y21: 798.27331 | Z21: 881.09881 | AA21: 939.65802 | AB21: 970.96597 | AC21: 1033.4894 | AD21: 956.30306 | AE21: 1122.5344 | AF21: 1407.648 | AG21: 1520.473 | AH21: 921.72502 | AI21: 1296.2038 | AJ21: 719.23704 | AK21: 691.13654 | AL21: 818.11508 | AM21: 886.80662 | AN21: 972.97847 | AO21: =AO19+AO$13/1.1023*1000*0.02 -> 884.95004 | AP21: =AP19+AP$13/1.1023*1000*0.02 -> 1068.3647 | AQ21: =AQ19+AQ$13/1.1023*1000*0.02 -> 1091.2328 | AR21: =AR19+AR$13/1.1023*1000*0.02 -> 1160.4768 | AS21: =AVERAGE(AO21:AR21) -> 1051.2561 | AT21: =AT19+AT$13/1.1023*1000*0.02 -> 1388.6821 | AU21: =AU19+AU$13/1.1023*1000*0.02 -> 1365.7132 | AV21: =AV19+AV$13/1.1023*1000*0.02 -> 1202.7482 | AW21: =AW19+AW$13/1.1023*1000*0.02 -> 1058.6616 | AX21: =AVERAGE(AT21:AW21) -> 1253.9513 | AY21: =AY19+AY$13/1.1023*1000*0.02 -> 1130.4259 | AZ21: =AZ19+AZ$13/1.1023*1000*0.02 -> 1067.4688 | BA21: =BA19+BA$13/1.1023*1000*0.02 -> 978.93444 | BB21: =BB19+BB$13/1.1023*1000*0.02 -> 1005.673 | BC21: =AVERAGE(AY21:BB21) -> 1045.6255 | BD21: =BD19+BD$13/1.1023*1000*0.02 -> 1092.6131 | BE21: =BE19+BE$13/1.1023*1000*0.02 -> 977.2353 | BF21: =BF19+BF$13/1.1023*1000*0.02 -> 965.3777 | BG21: =BG19+BG$13/1.1023*1000*0.02 -> 1026.0633 | BH21: =AVERAGE(BD21:BG21) -> 1015.3223 | BI21: =BI19+BI$13/1.1023*1000*0.02 -> 1022.6455 | BJ21: =BJ19+BJ$13/1.1023*1000*0.02 -> 1002.1069 | BK21: =BK19+BK$13/1.1023*1000*0.02 -> 949.70187 | BL21: =BL19+BL$13/1.1023*1000*0.02 -> 872.77211 | BM21: =AVERAGE(BI21:BL21) -> 961.80659 | BN21: =BN19+BN$13/1.1023*1000*0.02 -> 819.72035 | BO21: =BO19+BO$13/1.1023*1000*0.02 -> 750.38699 | BP21: =BP19+BP$13/1.1023*1000*0.02 -> 714.74205 | BQ21: =BQ19+BQ$13/1.1023*1000*0.02 -> 657.06299 | BR21: =AVERAGE(BN21:BQ21) -> 735.47809 | BS21: =BS19+BS$13/1.1023*1000*0.02 -> 663.2596 | BT21: =BT19+BT$13/1.1023*1000*0.02 -> 797.12185 | BU21: =BU19+BU$13/1.1023*1000*0.02 -> 838.46734 | BV21: =BV19+BV$13/1.1023*1000*0.02 -> 943.66293 | BW21: =AVERAGE(BS21:BV21) -> 810.62793 | BX21: =BX19+BX$13/1.1023*1000*0.02 -> 1000.9085 | BY21: =BY19+BY$13/1.1023*1000*0.02 -> 965.5696 | BZ21: =BZ19+BZ$13/1.1023*1000*0.02 -> 1010.7855 | CA21: =CA19+CA$13/1.1023*1000*0.02 -> 1038.8943 | CB21: =AVERAGE(BX21:CA21) -> 1004.0395 | CC21: =CC19+CC$13/1.1023*1000*0.02 -> 1097.752 | CD21: =CD19+CD$13/1.1023*1000*0.02 -> 1109 | CE21: =CE19+CE$13/1.1023*1000*0.02 -> 1064.4 | CF21: =CF19+CF$13/1.1023*1000*0.02 -> 1029.6 | CG21: =AVERAGE(CC21:CF21) -> 1075.188 | CH21: =CH19+CH$13/1.1023*1000*0.02 -> 1018 | CI21: =CI19+CI$13/1.1023*1000*0.02 -> 1018 | CJ21: =CJ19+CJ$13/1.1023*1000*0.02 -> 983.2 | CK21: =CK19+CK$13/1.1023*1000*0.02 -> 983.2 | CL21: =AVERAGE(CH21:CK21) -> 1000.6 | CM21: =CM19+CM$13/1.1023*1000*0.02 -> 1023.2 | CN21: =CN19+CN$13/1.1023*1000*0.02 -> 1034.8 | CO21: =CO19+CO$13/1.1023*1000*0.02 -> 1037.4 | CP21: =CP19+CP$13/1.1023*1000*0.02 -> 1037.4 | CQ21: =AVERAGE(CM21:CP21) -> 1033.2
C22: Tubular | J22: 789.66667 | K22: 831 | L22: 1259.3333 | M22: 1315.6667 | N22: 1318.3333 | O22: 1181.0833 | P22: 1358.3333 | Q22: 1330.3333 | R22: 1352 | S22: 1358.3333 | T22: 1349.75 | U22: 1352.3333 | V22: 1369.6667 | W22: 1385 | X22: 1360.6667 | Y22: 1366.9167 | Z22: 1332.3333 | AA22: 1305.3333 | AB22: 1276.3333 | AC22: 1289 | AD22: 1300.75 | AE22: 1321.3333 | AF22: 1921 | AG22: 2941.6667 | AH22: 2769 | AI22: 2238.25 | AJ22: 2164 | AK22: 1602 | AL22: 1430 | AM22: 1376.3333 | AN22: 1643.0833 | AO22: 1540 | AP22: 1683.6667 | AQ22: =AQ16 -> 1744.3333 | AR22: =AR16 -> 1677.3333 | AS22: =AVERAGE(AO22:AR22) -> 1661.3333 | AT22: =AT16 -> 1691.3333 | AU22: =AU16 -> 1749.6667 | AV22: =AV16 -> 1780 | AW22: =AW108 -> 1891.56 | AX22: =AVERAGE(AT22:AW22) -> 1778.14 | AY22: =AY108 -> 1853.9633 | AZ22: =AZ108 -> 1800.8767 | BA22: =BA108 -> 1745.21 | BB22: =BB108 -> 1692.5667 | BC22: =AVERAGE(AY22:BB22) -> 1773.1542 | BD22: =BD108 -> 1645.8067 | BE22: =BE108 -> 1590.7933 | BF22: =BF108 -> 1551.4933 | BG22: =BG108 -> 1555.1667 | BH22: =AVERAGE(BD22:BG22) -> 1585.815 | BI22: =BI108 -> 1534.7867 | BJ22: =BJ108 -> 1562.7633 | BK22: =BK108 -> 1667.7833 | BL22: =BL108 -> 1758.4767 | BM22: =AVERAGE(BI22:BL22) -> 1630.9525 | BN22: =BN108 -> 1608.2933 | BO22: =BO108 -> 1435.7467 | BP22: =BP108 -> 1307.0233 | BQ22: =BQ108 -> 1189.6767 | BR22: =AVERAGE(BN22:BQ22) -> 1385.185 | BS22: =BS108 -> 1118.4633 | BT22: =BT108 -> 1078.0333 | BU22: =BU108 -> 1099.4 | BV22: =BV108 -> 1085.8733 | BW22: =AVERAGE(BS22:BV22) -> 1095.4425 | BX22: =BX108 -> 1208.8067 | BY22: =BY108 -> 1404.85 | BZ22: =BZ108 -> 1403.1367 | CA22: =CA108 -> 1406.6933 | CB22: =AVERAGE(BX22:CA22) -> 1355.8717 | CC22: =CC108 -> 1461.7067 | CD22: =CD108 -> 1650.15 | CE22: =CE108 -> 1624.85 | CF22: =CF108 -> 1607.2 | CG22: =AVERAGE(CC22:CF22) -> 1585.9767 | CH22: =CH108 -> 1619.85 | CI22: =CI108 -> 1606.3 | CJ22: =CJ108 -> 1598.65 | CK22: =CK108 -> 1565.4 | CL22: =AVERAGE(CH22:CK22) -> 1597.55 | CM22: =CM108 -> 1522.15 | CN22: =CN108 -> 1532.45 | CO22: =CO108 -> 1514.2 | CP22: =CP108 -> 1504.8 | CQ22: =AVERAGE(CM22:CP22) -> 1518.4
C23: Semi-finished and Plates | J23: 317.21785 | K23: 389.6987 | L23: 474.88933 | M23: 531.44784 | N23: 603.82082 | O23: 499.96417 | P23: 617.43983 | Q23: 543.11764 | R23: 438.69405 | S23: 435.04539 | T23: 508.57423 | U23: 451.02379 | V23: 540.27772 | W23: 561.92697 | X23: 561.66809 | Y23: 528.72414 | Z23: 555.71914 | AA23: 602.18398 | AB23: 618.37054 | AC23: 649.6949 | AD23: 606.49214 | AE23: 717.65749 | AF23: 916.51131 | AG23: 1054.3847 | AH23: 673.85413 | AI23: 840.60191 | AJ23: 490.69393 | AK23: 465.05467 | AL23: 547.80209 | AM23: 560.813 | AN23: 516.09092 | AO23: 522.60667 | AP23: 680.03766 | AQ23: =AP23*AQ18/AP18 -> 655.595 | AR23: =AQ23*AR18/AQ18 -> 629.96 | AS23: =AVERAGE(AO23:AR23) -> 622.04983 | AT23: =AR23*AT18/AR18 -> 771.78833 | AU23: =AT23*AU18/AT18 -> 772.87667 | AV23: =AU23*AV18/AU18 -> 689.85667 | AW23: =AV23*AW18/AV18 -> 620.28833 | AX23: =AVERAGE(AT23:AW23) -> 713.7025 | AY23: =AW23*AY18/AW18 -> 651.60667 | AZ23: =AY23*AZ18/AY18 -> 633.90667 | BA23: =AZ23*BA18/AZ18 -> 573.92167 | BB23: =BA23*BB18/BA18 -> 560.94167 | BC23: =AVERAGE(AY23:BB23) -> 605.09417 | BD23: =BB23*BD18/BB18 -> 598.68333 | BE23: =BC23*BE18/BC18 -> 545.82667 | BF23: =BE23*BF18/BE18 -> 528.89667 | BG23: =BF23*BG18/BF18 -> 557.005 | BH23: =AVERAGE(BD23:BG23) -> 557.60292 | BI23: =BI18 -> 558.54 | BJ23: =BJ18 -> 531.265 | BK23: =BK18 -> 503.755 | BL23: =BL18 -> 467.42667 | BM23: =AVERAGE(BI23:BL23) -> 515.24667 | BN23: =BN18*1.05 -> 440.23 | BO23: =BN23*BO18/BN18 -> 422.7965 | BP23: =BO23*BP18/BO18 -> 397.0575 | BQ23: =BP23*BQ18/BP18 -> 344.848 | BR23: =AVERAGE(BN23:BQ23) -> 401.233 | BS23: =BS18*1.05 -> 345.632 | BT23: =BS23*BT18/BS18 -> 443.961 | BU23: =BT23*BU18/BT18 -> 453.4775 | BV23: =BU23*BV18/BU18 -> 512.218 | BW23: =AVERAGE(BS23:BV23) -> 438.82213 | BX23: =BX18*1.05 -> 577.07825 | BY23: =BY18*1.05 -> 546.86625 | BZ23: =BZ18*1.05 -> 578.03333 | CA23: =CA18*1.05 -> 603.47667 | CB23: =AVERAGE(BX23:CA23) -> 576.36362 | CC23: =CA23*CC18/CA18 -> 656.75301 | CD23: =CC23*CD18/CC18 -> 656.25 | CE23: =CD23*CE18/CD18 -> 619.5 | CF23: =CE23*CF18/CE18 -> 588 | CG23: =AVERAGE(CC23:CF23) -> 630.12575 | CH23: =CF23*CH18/CF18 -> 577.5 | CI23: =CH23*CI18/CH18 -> 577.5 | CJ23: =CI23*CJ18/CI18 -> 546 | CK23: =CJ23*CK18/CJ18 -> 546 | CL23: =AVERAGE(CH23:CK23) -> 561.75 | CM23: =CK23*CM18/CK18 -> 546 | CN23: =CM23*CN18/CM18 -> 556.5 | CO23: =CN23*CO18/CN18 -> 540.75 | CP23: =CO23*CP18/CO18 -> 540.75 | CQ23: =AVERAGE(CM23:CP23) -> 546
A25: Flat Rolled Steel | D25: 2001 | E25: 2002 | F25: 1Q | G25: 2Q | H25: 3Q | I25: 4Q | J25: =J4 -> 2003 | K25: =Operations!K4 -> 1Q | L25: =Operations!L4 -> 2Q | M25: =Operations!M4 -> 3Q | N25: =Operations!N4 -> 4Q | O25: =Operations!O4 -> 2004 | P25: =Operations!P4 -> 1Q | Q25: =Operations!Q4 -> 2Q | R25: =Operations!R4 -> 3Q | ... CQ25: =Operations!CQ4 -> 2020E
B26: Volume Growth | E26: =Operations!E34/Operations!D34-1 -> 0.12769108 | J26: =Operations!J34/Operations!E34-1 -> 0.36535354 | K26: =Operations!K34/Operations!F34-1 -> 0.70812808 | L26: =Operations!L34/Operations!G34-1 -> 0.24359775 | M26: =Operations!M34/Operations!H34-1 -> -0.041954464 | N26: =Operations!N34/Operations!I34-1 -> -0.056171285 | O26: =Operations!O34/Operations!J34-1 -> 0.15669157 | P26: =Operations!P34/Operations!K34-1 -> -0.1504446 | Q26: =Operations!Q34/Operations!L34-1 -> -0.1903566 | ... CB26: =Operations!CB34/Operations!BW34-1 -> -0.020507232 | CC26: 0.01 | CD26: 0.01 | CE26: 0.1 | CF26: 0.12 | CG26: =Operations!CG34/Operations!CB34-1 -> 0.060326692 | CH26: 0.13 | CI26: 0.137 | CJ26: 0.02 | CK26: 0.02 | CL26: =Operations!CL34/Operations!CG34-1 -> 0.073623081 | CM26: 0 | CN26: 0 | CO26: 0 | CP26: 0 | CQ26: =Operations!CQ34/Operations!CL34-1 -> 0
B28: SHIPMENTS (in '000 tons) | BZ28: =300/BZ34 -> 0.11792453
B29: Hot-rolled Sheets | F29: =$J29/$J$34*F$34 -> 810.07768 | G29: =$J29/$J$34*G$34 -> 1064.8065 | H29: =$J29/$J$34*H$34 -> 1299.9153 | I29: =$J29/$J$34*I$34 -> 1320.2005 | J29: 4495 | K29: =$O29/$O$34*K$34 -> 1374.3143 | L29: =$O29/$O$34*L$34 -> 1315.1933 | M29: =$O29/$O$34*M$34 -> 1236.9159 | N29: =$O29/$O$34*N$34 -> 1237.5765 | O29: 5164 | P29: =$T29/$T$34*P$34 -> 1004.7206 | Q29: =$T29/$T$34*Q$34 -> 916.32792 | R29: =$T29/$T$34*R$34 -> 906.94863 | S29: =$T29/$T$34*S$34 -> 951.00286 | T29: 3779 | U29: =$Y29/$Y$34*U$34 -> 1044.0166 | V29: =$Y29/$Y$34*V$34 -> 1147.2645 | W29: =$Y29/$Y$34*W$34 -> 1093.1259 | X29: =$Y29/$Y$34*X$34 -> 910.59309 | Y29: 4195 | Z29: =$AD29/$AD$34*Z$34 -> 1071.9524 | AA29: =$AD29/$AD$34*AA$34 -> 1210.1495 | AB29: =$AD29/$AD$34*AB$34 -> 1210.822 | AC29: =$AD29/$AD$34*AC$34 -> 1394.0761 | AD29: 4887 | AE29: =$AD29/$AD$34*AE$34 -> 1580.6927 | AF29: =$AD29/$AD$34*AF$34 -> 1630.4571 | AG29: =$AD29/$AD$34*AG$34 -> 1514.7884 | AH29: =$AD29/$AD$34*AH$34 -> 938.12646 | AI29: 6474 | AJ29: =AJ$34*($AN29/$AN$34) -> 683.12331 | AK29: =AK$34*($AN29/$AN$34) -> 584.01734 | AL29: =AL$34*($AN29/$AN$34) -> 875.86513 | AM29: =AM$34*($AN29/$AN$34) -> 1029.9942 | AN29: 3173 | AO29: =AO$34*($AS29/$AS$34) -> 1158.6064 | AP29: =AP$34*($AS29/$AS$34) -> 1317.2174 | AQ29: =AQ$34*($AS29/$AS$34) -> 1236.4523 | AR29: =AR$34*($AS29/$AS$34) -> 1250.724 | AS29: 4963 | AT29: =AT$34*($AX29/$AX$34) -> 1382.0771 | AU29: =AU$34*($AX29/$AX$34) -> 1375.7854 | AV29: =AV$34*($AX29/$AX$34) -> 1340.482 | AW29: =AW$34*($AX29/$AX$34) -> 1322.6555 | AX29: 5421 | AY29: =AY$34*($BC29/$BC$34) -> 1468.6012 | AZ29: =AZ$34*($BC29/$BC$34) -> 1430.5583 | BA29: =BA$34*($BC29/$BC$34) -> 1425.5337 | BB29: =BB$34*($BC29/$BC$34) -> 1408.3067 | BC29: 5733 | BD29: =BD$34*($BH29/$BH$34) -> 1379.5755 | BE29: =BE$34*($BH29/$BH$34) -> 1280.0044 | BF29: =BF$34*($BH29/$BH$34) -> 1176.9997 | BG29: =BG$34*($BH29/$BH$34) -> 1191.4204 | BH29: 5028 | BI29: =BI$34*($BM29/$BM$34) -> 1296.7836 | BJ29: =BJ$34*($BM29/$BM$34) -> 1244.8981 | BK29: =BK$34*($BM29/$BM$34) -> 1303.1369 | BL29: =BL$34*($BM29/$BM$34) -> 1064.1814 | BM29: 4909 | BN29: =BN$34*($BR29/$BR$34) -> 810.83532 | BO29: =BO$34*($BR29/$BR$34) -> 840.26954 | BP29: =BP$34*($BR29/$BR$34) -> 829.11552 | BQ29: =BQ$34*($BR29/$BR$34) -> 802.77963 | BR29: 3283 | BS29: =BS$34*($BW29/$BW$34) -> 688.96691 | BT29: =BT$34*($BW29/$BW$34) -> 742.47355 | BU29: =BU$34*($BW29/$BW$34) -> 699.17179 | BV29: =BV$34*($BW29/$BW$34) -> 653.38776 | BW29: 2784 | BX29: =BX$34*0.25 -> 601 | BY29: =BY$34*0.25 -> 624.25 | BZ29: =BZ$34*0.25 -> 636 | CA29: =CA$34*0.25 -> 610.5 | CB29: =SUM(BX29:CA29) -> 2471.75 | CC29: =CC$34*0.25 -> 607.01 | CD29: =CD$34*0.25 -> 630.4925 | CE29: =CE$34*0.28 -> 783.552 | CF29: =CF$34*0.28 -> 765.8112 | CG29: =SUM(CC29:CF29) -> 2786.8657 | CH29: =CH$34*0.28 -> 768.23186 | CI29: =CI$34*0.28 -> 802.89437 | CJ29: =CJ$34*0.28 -> 799.22304 | CK29: =CK$34*0.28 -> 781.12742 | CL29: =SUM(CH29:CK29) -> 3151.4767 | CM29: =CM$34*0.28 -> 768.23186 | CN29: =CN$34*0.28 -> 802.89437 | CO29: =CO$34*0.28 -> 799.22304 | CP29: =CP$34*0.28 -> 781.12742 | CQ29: =SUM(CM29:CP29) -> 3151.4767 | CS29: 642.36 | CT29: 616.605 | DC29: 619.1502 | DD29: 643.10235 | DE29: =CS29-DF29 -> -1904.0368 | DF29: 2546.3969
B30: Cold-rolled Sheets | F30: =$J30/$J$34*F$34 -> 733.84568 | G30: =$J30/$J$34*G$34 -> 964.60339 | H30: =$J30/$J$34*H$34 -> 1177.5873 | I30: =$J30/$J$34*I$34 -> 1195.9636 | J30: 4072 | K30: =$O30/$O$34*K$34 -> 1220.7552 | L30: =$O30/$O$34*L$34 -> 1168.2401 | M30: =$O30/$O$34*M$34 -> 1098.709 | N30: =$O30/$O$34*N$34 -> 1099.2957 | O30: 4587 | P30: =$T30/$T$34*P$34 -> 1154.671 | Q30: =$T30/$T$34*Q$34 -> 1053.086 | R30: =$T30/$T$34*R$34 -> 1042.3069 | S30: =$T30/$T$34*S$34 -> 1092.9361 | T30: 4343 | U30: =$Y30/$Y$34*U$34 -> 1114.6961 | V30: =$Y30/$Y$34*V$34 -> 1224.9339 | W30: =$Y30/$Y$34*W$34 -> 1167.1301 | X30: =$Y30/$Y$34*X$34 -> 972.23992 | Y30: 4479 | Z30: =$AD30/$AD$34*Z$34 -> 929.59571 | AA30: =$AD30/$AD$34*AA$34 -> 1049.4401 | AB30: =$AD30/$AD$34*AB$34 -> 1050.0233 | AC30: =$AD30/$AD$34*AC$34 -> 1208.941 | AD30: 4238 | AE30: =$AD30/$AD$34*AE$34 -> 1370.7746 | AF30: =$AD30/$AD$34*AF$34 -> 1413.9302 | AG30: =$AD30/$AD$34*AG$34 -> 1313.6225 | AH30: =$AD30/$AD$34*AH$34 -> 813.54204 | AI30: 4489 | AJ30: =AJ$34*($AN30/$AN$34) -> 678.60217 | AK30: =AK$34*($AN30/$AN$34) -> 580.15211 | AL30: =AL$34*($AN30/$AN$34) -> 870.06835 | AM30: =AM$34*($AN30/$AN$34) -> 1023.1774 | AN30: 3152 | AO30: =AO$34*($AS30/$AS$34) -> 1013.1678 | AP30: =AP$34*($AS30/$AS$34) -> 1151.8685 | AQ30: =AQ$34*($AS30/$AS$34) -> 1081.2417 | AR30: =AR$34*($AS30/$AS$34) -> 1093.722 | AS30: 4340 | AT30: =AT$34*($AX30/$AX$34) -> 1099.084 | AU30: =AU$34*($AX30/$AX$34) -> 1094.0806 | AV30: =AV$34*($AX30/$AX$34) -> 1066.0059 | AW30: =AW$34*($AX30/$AX$34) -> 1051.8295 | AX30: 4311 | AY30: =AY$34*($BC30/$BC$34) -> 1146.6002 | AZ30: =AZ$34*($BC30/$BC$34) -> 1116.8985 | BA30: =BA$34*($BC30/$BC$34) -> 1112.9756 | BB30: =BB$34*($BC30/$BC$34) -> 1099.5257 | BC30: 4476 | BD30: =BD$34*($BH30/$BH$34) -> 1192.7237 | BE30: =BE$34*($BH30/$BH$34) -> 1106.6386 | BF30: =BF$34*($BH30/$BH$34) -> 1017.5851 | BG30: =BG$34*($BH30/$BH$34) -> 1030.0526 | BH30: 4347 | BI30: =BI$34*($BM30/$BM$34) -> 1111.3401 | BJ30: =BJ$34*($BM30/$BM$34) -> 1066.8744 | BK30: =BK$34*($BM30/$BM$34) -> 1116.7849 | BL30: =BL$34*($BM30/$BM$34) -> 912.00065 | BM30: 4207 | BN30: =BN$34*($BR30/$BR$34) -> 866.15883 | BO30: =BO$34*($BR30/$BR$34) -> 897.60136 | BP30: =BP$34*($BR30/$BR$34) -> 885.6863 | BQ30: =BQ$34*($BR30/$BR$34) -> 857.55351 | BR30: 3507 | BS30: =BS$34*($BW30/$BW$34) -> 934.21339 | BT30: =BT$34*($BW30/$BW$34) -> 1006.7664 | BU30: =BU$34*($BW30/$BW$34) -> 948.05082 | BV30: =BV$34*($BW30/$BW$34) -> 885.96939 | BW30: 3775 | BX30: =BX$34*0.35 -> 841.4 | BY30: =BY$34*0.35 -> 873.95 | BZ30: =BZ$34*0.35 -> 890.4 | CA30: =CA$34*0.35 -> 854.7 | CB30: =SUM(BX30:CA30) -> 3460.45 | CC30: =CC$34*0.35 -> 849.814 | CD30: =CD$34*0.35 -> 882.6895 | CE30: =CE$34*0.32 -> 895.488 | CF30: =CF$34*0.32 -> 875.2128 | CG30: =SUM(CC30:CF30) -> 3503.2043 | CH30: =CH$34*0.32 -> 877.97926 | CI30: =CI$34*0.32 -> 917.59356 | CJ30: =CJ$34*0.32 -> 913.39776 | CK30: =CK$34*0.32 -> 892.71706 | CL30: =SUM(CH30:CK30) -> 3601.6876 | CM30: =CM$34*0.32 -> 877.97926 | CN30: =CN$34*0.32 -> 917.59356 | CO30: =CO$34*0.32 -> 913.39776 | CP30: =CP$34*0.32 -> 892.71706 | CQ30: =SUM(CM30:CP30) -> 3601.6876 | CS30: 899.304 | CT30: 863.247 | DC30: 866.81028 | DD30: 900.34329 | DE30: =CS30-DF30 -> -2665.6516 | DF30: 3564.9556
B31: Coated Sheets | F31: =$J31/$J$34*F$34 -> 579.39927 | G31: =$J31/$J$34*G$34 -> 761.59133 | H31: =$J31/$J$34*H$34 -> 929.75031 | I31: =$J31/$J$34*I$34 -> 944.25908 | J31: 3215 | K31: =$O31/$O$34*K$34 -> 1140.6489 | L31: =$O31/$O$34*L$34 -> 1091.5799 | M31: =$O31/$O$34*M$34 -> 1026.6114 | N31: =$O31/$O$34*N$34 -> 1027.1597 | O31: 4286 | P31: =$T31/$T$34*P$34 -> 972.28452 | Q31: =$T31/$T$34*Q$34 -> 886.74549 | R31: =$T31/$T$34*R$34 -> 877.669 | S31: =$T31/$T$34*S$34 -> 920.30099 | T31: 3657 | U31: =$Y31/$Y$34*U$34 -> 1016.1429 | V31: =$Y31/$Y$34*V$34 -> 1116.6343 | W31: =$Y31/$Y$34*W$34 -> 1063.9411 | X31: =$Y31/$Y$34*X$34 -> 886.28166 | Y31: 4083 | Z31: =$AD31/$AD$34*Z$34 -> 821.01858 | AA31: =$AD31/$AD$34*AA$34 -> 926.86507 | AB31: =$AD31/$AD$34*AB$34 -> 927.38014 | AC31: =$AD31/$AD$34*AC$34 -> 1067.7362 | AD31: 3743 | AE31: =$AD31/$AD$34*AE$34 -> 1210.6676 | AF31: =$AD31/$AD$34*AF$34 -> 1248.7826 | AG31: =$AD31/$AD$34*AG$34 -> 1160.1909 | AH31: =$AD31/$AD$34*AH$34 -> 718.52002 | AI31: 3554 | AJ31: =AJ$34*($AN31/$AN$34) -> 405.18061 | AK31: =AK$34*($AN31/$AN$34) -> 346.39793 | AL31: =AL$34*($AN31/$AN$34) -> 519.50147 | AM31: =AM$34*($AN31/$AN$34) -> 610.91999 | AN31: 1882 | AO31: =AO$34*($AS31/$AS$34) -> 675.36736 | AP31: =AP$34*($AS31/$AS$34) -> 767.82387 | AQ31: =AQ$34*($AS31/$AS$34) -> 720.74479 | AR31: =AR$34*($AS31/$AS$34) -> 729.06398 | AS31: 2893 | AT31: =AT$34*($AX31/$AX$34) -> 799.51925 | AU31: =AU$34*($AX31/$AX$34) -> 795.87955 | AV31: =AV$34*($AX31/$AX$34) -> 775.45683 | AW31: =AW$34*($AX31/$AX$34) -> 765.14437 | AX31: 3136 | AY31: =AY$34*($BC31/$BC$34) -> 894.02028 | AZ31: =AZ$34*($BC31/$BC$34) -> 870.8614 | BA31: =BA$34*($BC31/$BC$34) -> 867.80268 | BB31: =BB$34*($BC31/$BC$34) -> 857.31564 | BC31: 3490 | BD31: =BD$34*($BH31/$BH$34) -> 987.48853 | BE31: =BE$34*($BH31/$BH$34) -> 916.21633 | BF31: =BF$34*($BH31/$BH$34) -> 842.48648 | BG31: =BG$34*($BH31/$BH$34) -> 852.80866 | BH31: 3599 | BI31: =BI$34*($BM31/$BM$34) -> 875.96951 | BJ31: =BJ$34*($BM31/$BM$34) -> 840.9212 | BK31: =BK$34*($BM31/$BM$34) -> 880.26114 | BL31: =BL$34*($BM31/$BM$34) -> 718.84814 | BM31: 3316 | BN31: =BN$34*($BR31/$BR$34) -> 620.16676 | BO31: =BO$34*($BR31/$BR$34) -> 642.6795 | BP31: =BP$34*($BR31/$BR$34) -> 634.14836 | BQ31: =BQ$34*($BR31/$BR$34) -> 614.00538 | BR31: 2511 | BS31: =BS$34*($BW31/$BW$34) -> 657.0428 | BT31: =BT$34*($BW31/$BW$34) -> 708.07014 | BU31: =BU$34*($BW31/$BW$34) -> 666.77482 | BV31: =BV$34*($BW31/$BW$34) -> 623.11224 | BW31: 2655 | BX31: =BX$34*0.3 -> 721.2 | BY31: =BY$34*0.3 -> 749.1 | BZ31: =BZ$34*0.3 -> 763.2 | CA31: =CA$34*0.3 -> 732.6 | CB31: =SUM(BX31:CA31) -> 2966.1 | CC31: =CC$34*0.3 -> 728.412 | CD31: =CD$34*0.3 -> 756.591 | CE31: =CE$34*0.275 -> 769.56 | CF31: =CF$34*0.275 -> 752.136 | CG31: =SUM(CC31:CF31) -> 3006.699 | CH31: =CH$34*0.275 -> 754.51343 | CI31: =CI$34*0.275 -> 788.55697 | CJ31: =CJ$34*0.275 -> 784.9512 | CK31: =CK$34*0.275 -> 767.17872 | CL31: =SUM(CH31:CK31) -> 3095.2003 | CM31: =CM$34*0.275 -> 754.51343 | CN31: =CN$34*0.275 -> 788.55697 | CO31: =CO$34*0.275 -> 784.9512 | CP31: =CP$34*0.275 -> 767.17872 | CQ31: =SUM(CM31:CP31) -> 3095.2003 | CS31: 770.832 | CT31: 739.926 | DC31: 742.98024 | DD31: 771.72282 | DE31: =CS31-DF31 -> -2284.8442 | DF31: 3055.6762
B32: Tin Mill Products | F32: =$J32/$J$34*F$34 -> 199.14034 | G32: =$J32/$J$34*G$34 -> 261.76001 | H32: =$J32/$J$34*H$34 -> 319.55648 | I32: =$J32/$J$34*I$34 -> 324.54317 | J32: 1105 | K32: =$O32/$O$34*K$34 -> 384.03089 | L32: =$O32/$O$34*L$34 -> 367.51046 | M32: =$O32/$O$34*M$34 -> 345.63703 | N32: =$O32/$O$34*N$34 -> 345.82162 | O32: 1443 | P32: =$T32/$T$34*P$34 -> 369.02677 | Q32: =$T32/$T$34*Q$34 -> 336.56077 | R32: =$T32/$T$34*R$34 -> 333.11582 | S32: =$T32/$T$34*S$34 -> 349.29663 | T32: 1388 | U32: =$Y32/$Y$34*U$34 -> 328.01283 | V32: =$Y32/$Y$34*V$34 -> 360.45162 | W32: =$Y32/$Y$34*W$34 -> 343.44217 | X32: =$Y32/$Y$34*X$34 -> 286.09337 | Y32: 1318 | Z32: =$AD32/$AD$34*Z$34 -> 282.51988 | AA32: =$AD32/$AD$34*AA$34 -> 318.94262 | AB32: =$AD32/$AD$34*AB$34 -> 319.11986 | AC32: =$AD32/$AD$34*AC$34 -> 367.41764 | AD32: 1288 | AE32: =$AD32/$AD$34*AE$34 -> 416.60162 | AF32: =$AD32/$AD$34*AF$34 -> 429.71735 | AG32: =$AD32/$AD$34*AG$34 -> 399.23215 | AH32: =$AD32/$AD$34*AH$34 -> 247.24921 | AI32: 1387 | AJ32: =AJ$34*($AN32/$AN$34) -> 269.76159 | AK32: =AK$34*($AN32/$AN$34) -> 230.62519 | AL32: =AL$34*($AN32/$AN$34) -> 345.87425 | AM32: =AM$34*($AN32/$AN$34) -> 406.73897 | AN32: 1253 | AO32: =AO$34*($AS32/$AS$34) -> 312.82138 | AP32: =AP$34*($AS32/$AS$34) -> 355.64604 | AQ32: =AQ$34*($AS32/$AS$34) -> 333.83962 | AR32: =AR$34*($AS32/$AS$34) -> 337.69296 | AS32: 1340 | AT32: =AT$34*($AX32/$AX$34) -> 300.07467 | AU32: =AU$34*($AX32/$AX$34) -> 298.70862 | AV32: =AV$34*($AX32/$AX$34) -> 291.04359 | AW32: =AW$34*($AX32/$AX$34) -> 287.17313 | AX32: 1177 | AY32: =AY$34*($BC32/$BC$34) -> 312.52285 | AZ32: =AZ$34*($BC32/$BC$34) -> 304.42719 | BA32: =BA$34*($BC32/$BC$34) -> 303.35796 | BB32: =BB$34*($BC32/$BC$34) -> 299.692 | BC32: 1220 | BD32: =BD$34*($BH32/$BH$34) -> 330.35182 | BE32: =BE$34*($BH32/$BH$34) -> 306.5086 | BF32: =BF$34*($BH32/$BH$34) -> 281.84321 | BG32: =BG$34*($BH32/$BH$34) -> 285.29637 | BH32: 1204 | BI32: =BI$34*($BM32/$BM$34) -> 311.71412 | BJ32: =BJ$34*($BM32/$BM$34) -> 299.24216 | BK32: =BK$34*($BM32/$BM$34) -> 313.2413 | BL32: =BL$34*($BM32/$BM$34) -> 255.80242 | BM32: 1180 | BN32: =BN$34*($BR32/$BR$34) -> 228.95045 | BO32: =BO$34*($BR32/$BR$34) -> 237.26161 | BP32: =BP$34*($BR32/$BR$34) -> 234.11212 | BQ32: =BQ$34*($BR32/$BR$34) -> 226.67582 | BR32: 927 | BS32: =BS$34*($BW32/$BW$34) -> 205.65068 | BT32: =BT$34*($BW32/$BW$34) -> 221.62195 | BU32: =BU$34*($BW32/$BW$34) -> 208.69675 | BV32: =BV$34*($BW32/$BW$34) -> 195.03061 | BW32: 831 | BX32: =BX$34*0.08 -> 192.32 | BY32: =BY$34*0.08 -> 199.76 | BZ32: =BZ$34*0.08 -> 203.52 | CA32: =CA$34*0.08 -> 195.36 | CB32: =SUM(BX32:CA32) -> 790.96 | CC32: =CC$34*0.08 -> 194.2432 | CD32: =CD$34*0.08 -> 201.7576 | CE32: =CE$34*0.073 -> 204.2832 | CF32: =CF$34*0.073 -> 199.65792 | CG32: =SUM(CC32:CF32) -> 799.94192 | CH32: =CH$34*0.073 -> 200.28902 | CI32: =CI$34*0.073 -> 209.32603 | CJ32: =CJ$34*0.073 -> 208.36886 | CK32: =CK$34*0.073 -> 203.65108 | CL32: =SUM(CH32:CK32) -> 821.63499 | CM32: =CM$34*0.073 -> 200.28902 | CN32: =CN$34*0.073 -> 209.32603 | CO32: =CO$34*0.073 -> 208.36886 | CP32: =CP$34*0.073 -> 203.65108 | CQ32: =SUM(CM32:CP32) -> 821.63499 | CS32: 205.5552 | CT32: 197.3136 | DC32: 198.12806 | DD32: 205.79275 | DE32: =CS32-DF32 -> -609.29179 | DF32: 814.84699
B33: Semi-finished and Plates | F33: =$J33/$J$34*F$34 -> 113.53703 | G33: =$J33/$J$34*G$34 -> 149.23874 | H33: =$J33/$J$34*H$34 -> 182.19057 | I33: =$J33/$J$34*I$34 -> 185.03366 | J33: 630 | K33: =$O33/$O$34*K$34 -> 41.25072 | L33: =$O33/$O$34*L$34 -> 39.476175 | M33: =$O33/$O$34*M$34 -> 37.126639 | N33: =$O33/$O$34*N$34 -> 37.146466 | O33: 155 | P33: =$T33/$T$34*P$34 -> 34.297157 | Q33: =$T33/$T$34*Q$34 -> 31.279783 | R33: =$T33/$T$34*R$34 -> 30.959612 | S33: =$T33/$T$34*S$34 -> 32.463448 | T33: 129 | U33: =$Y33/$Y$34*U$34 -> 26.131523 | V33: =$Y33/$Y$34*V$34 -> 28.715797 | W33: =$Y33/$Y$34*W$34 -> 27.360719 | X33: =$Y33/$Y$34*X$34 -> 22.791961 | Y33: 105 | Z33: =$AD33/$AD$34*Z$34 -> 82.913444 | AA33: =$AD33/$AD$34*AA$34 -> 93.602725 | AB33: =$AD33/$AD$34*AB$34 -> 93.654741 | AC33: =$AD33/$AD$34*AC$34 -> 107.82909 | AD33: 378 | AE33: =$AD33/$AD$34*AE$34 -> 122.26352 | AF33: =$AD33/$AD$34*AF$34 -> 126.1127 | AG33: =$AD33/$AD$34*AG$34 -> 117.16596 | AH33: =$AD33/$AD$34*AH$34 -> 72.562268 | AI33: 941 | AJ33: =AJ$34*($AN33/$AN$34) -> 86.332319 | AK33: =AK$34*($AN33/$AN$34) -> 73.807423 | AL33: =AL$34*($AN33/$AN$34) -> 110.6908 | AM33: =AM$34*($AN33/$AN$34) -> 130.16946 | AN33: 401 | AO33: =AO$34*($AS33/$AS$34) -> 412.03712 | AP33: =AP$34*($AS33/$AS$34) -> 468.44422 | AQ33: =AQ$34*($AS33/$AS$34) -> 439.72159 | AR33: =AR$34*($AS33/$AS$34) -> 444.79707 | AS33: 1765 | AT33: =AT$34*($AX33/$AX$34) -> 373.24495 | AU33: =AU$34*($AX33/$AX$34) -> 371.54581 | AV33: =AV$34*($AX33/$AX$34) -> 362.01174 | AW33: =AW$34*($AX33/$AX$34) -> 357.1975 | AX33: 1464 | AY33: =AY$34*($BC33/$BC$34) -> 270.25542 | AZ33: =AZ$34*($BC33/$BC$34) -> 263.25466 | BA33: =BA$34*($BC33/$BC$34) -> 262.33004 | BB33: =BB$34*($BC33/$BC$34) -> 259.15988 | BC33: 1055 | BD33: =BD$34*($BH33/$BH$34) -> 127.86042 | BE33: =BE$34*($BH33/$BH$34) -> 118.63207 | BF33: =BF$34*($BH33/$BH$34) -> 109.0855 | BG33: =BG$34*($BH33/$BH$34) -> 110.42202 | BH33: 466 | BI33: =BI$34*($BM33/$BM$34) -> 78.192695 | BJ33: =BJ$34*($BM33/$BM$34) -> 75.064136 | BK33: =BK$34*($BM33/$BM$34) -> 78.575784 | BL33: =BL$34*($BM33/$BM$34) -> 64.167386 | BM33: =165+131 -> 296 | BN33: =BN$34*($BR33/$BR$34) -> 90.641657 | BO33: =BO$34*($BR33/$BR$34) -> 93.93205 | BP33: =BP$34*($BR33/$BR$34) -> 92.685164 | BQ33: =BQ$34*($BR33/$BR$34) -> 89.741129 | BR33: =47+320 -> 367 | BS33: =BS$34*($BW33/$BW$34) -> 12.126214 | BT33: =BT$34*($BW33/$BW$34) -> 13.067961 | BU33: =BU$34*($BW33/$BW$34) -> 12.305825 | BV33: =BV$34*($BW33/$BW$34) -> 11.5 | BW33: =23+26 -> 49 | BX33: =BX34-SUM(BX29:BX32) -> 48.08 | BY33: =BY34-SUM(BY29:BY32) -> 49.94 | BZ33: =BZ34-SUM(BZ29:BZ32) -> 50.88 | CA33: =CA34-SUM(CA29:CA32) -> 48.84 | CB33: =SUM(BX33:CA33) -> 197.74 | CC33: =CC34-SUM(CC29:CC32) -> 48.5608 | CD33: =CD34-SUM(CD29:CD32) -> 50.4394 | CE33: =CE34-SUM(CE29:CE32) -> 145.5168 | CF33: =CF34-SUM(CF29:CF32) -> 142.22208 | CG33: =SUM(CC33:CF33) -> 386.73908 | CH33: =CH34-SUM(CH29:CH32) -> 142.67163 | CI33: =CI34-SUM(CI29:CI32) -> 149.10895 | CJ33: =CJ34-SUM(CJ29:CJ32) -> 148.42714 | CK33: =CK34-SUM(CK29:CK32) -> 145.06652 | CL33: =SUM(CH33:CK33) -> 585.27424 | CM33: =CM34-SUM(CM29:CM32) -> 142.67163 | CN33: =CN34-SUM(CN29:CN32) -> 149.10895 | CO33: =CO34-SUM(CO29:CO32) -> 148.42714 | CP33: =CP34-SUM(CP29:CP32) -> 145.06652 | CQ33: =SUM(CM33:CP33) -> 585.27424 | CS33: 51.3888 | CT33: 49.3284 | DC33: 49.532016 | DD33: 51.448188 | DE33: =CS33-DF33 -> -152.32295 | DF33: 203.71175
B34: Total Flat Steel | D34: 8779 | E34: =7682+2218 -> 9900 | F34: 2436 | G34: 3202 | H34: 3909 | I34: 3970 | J34: =SUM(J29:J33) -> 13517 | K34: 4161 | L34: 3982 | M34: 3745 | N34: 3747 | O34: =SUM(O29:O33) -> 15635 | P34: 3535 | Q34: 3224 | R34: 3191 | S34: 3346 | T34: =SUM(T29:T33) -> 13296 | U34: 3529 | V34: 3878 | W34: 3695 | X34: 3078 | Y34: =SUM(U34:X34) -> 14180 | Z34: 3188 | AA34: 3599 | AB34: 3601 | AC34: 4146 | AD34: =SUM(Z34:AC34) -> 14534 | AE34: 4701 | AF34: 4849 | AG34: 4505 | AH34: 2790 | AI34: =SUM(AE34:AH34) -> 16845 | AJ34: 2123 | AK34: 1815 | AL34: 2722 | AM34: 3201 | AN34: =SUM(AJ34:AM34) -> 9861 | AO34: 3572 | AP34: 4061 | AQ34: 3812 | AR34: 3856 | AS34: =SUM(AO34:AR34) -> 15301 | AT34: 3954 | AU34: 3936 | AV34: 3835 | AW34: 3784 | AX34: =SUM(AT34:AW34) -> 15509 | AY34: 4092 | AZ34: 3986 | BA34: 3972 | BB34: 3924 | BC34: =SUM(AY34:BB34) -> 15974 | BD34: 4018 | BE34: 3728 | BF34: 3428 | BG34: 3470 | BH34: =SUM(BD34:BG34) -> 14644 | BI34: 3674 | BJ34: 3527 | BK34: 3692 | BL34: 3015 | BM34: =SUM(BI34:BL34) -> 13908 | BN34: 2617 | BO34: 2712 | BP34: 2676 | BQ34: 2591 | BR34: =SUM(BN34:BQ34) -> 10596 | BS34: 2498 | BT34: 2692 | BU34: 2535 | BV34: 2369 | BW34: =SUM(BS34:BV34) -> 10094 | BX34: 2404 | BY34: 2497 | BZ34: 2544 | CA34: 2442 | CB34: =SUM(BX34:CA34) -> 9887 | CC34: =BX34*(1+CC26) -> 2428.04 | CD34: =BY34*(1+CD26) -> 2521.97 | CE34: =BZ34*(1+CE26) -> 2798.4 | CF34: =CA34*(1+CF26) -> 2735.04 | CG34: =SUM(CC34:CF34) -> 10483.45 | CH34: =CC34*(1+CH26) -> 2743.6852 | CI34: =CD34*(1+CI26) -> 2867.4799 | CJ34: =CE34*(1+CJ26) -> 2854.368 | CK34: =CF34*(1+CK26) -> 2789.7408 | CL34: =SUM(CH34:CK34) -> 11255.274 | CM34: =CH34*(1+CM26) -> 2743.6852 | CN34: =CI34*(1+CN26) -> 2867.4799 | CO34: =CJ34*(1+CO26) -> 2854.368 | CP34: =CK34*(1+CP26) -> 2789.7408 | CQ34: =SUM(CM34:CP34) -> 11255.274 | CS34: 2569.44 | CT34: 2466.42 | DC34: 2476.6008 | DD34: 2572.4094 | DE34: =CS34-DF34 -> -7616.1474 | DF34: =SUM(DF29:DF33) -> 10185.587
B36: Raw Steel Production (in '000 tons) | D36: =2160+2689+2621+2623 -> 10093 | E36: 11535 | F36: 2895 | G36: 3338 | H36: 4396 | I36: 4285 | J36: =SUM(F36:I36) -> 14914 | K36: 4479 | L36: 4230 | M36: 4293 | N36: 4264 | O36: =SUM(K36:N36) -> 17266 | P36: 4303 | Q36: 3597 | R36: 3514 | S36: 3929 | T36: =SUM(P36:S36) -> 15343 | U36: 4141 | V36: 4585 | W36: 4359 | X36: 3270 | Y36: =SUM(U36:X36) -> 16355 | Z36: 3713 | AA36: 4116 | AB36: 4328 | AC36: 4681 | AD36: =SUM(Z36:AC36) -> 16838 | AE36: 5558 | AF36: 5614 | AG36: 5282 | AH36: 2736 | AI36: =SUM(AE36:AH36) -> 19190 | AJ36: 2279 | AK36: 1964 | AL36: 3548 | AM36: 3932 | AN36: =SUM(AJ36:AM36) -> 11723 | AO36: 4383 | AP36: 4979 | AQ36: 4694 | AR36: 4387 | AS36: =SUM(AO36:AR36) -> 18443 | AT36: 4598 | AU36: 4894 | AV36: 4516 | AW36: 4593 | AX36: =SUM(AT36:AW36) -> 18601 | AY36: 5043 | AZ36: 4688 | BA36: 4699 | BB36: 4686 | BC36: =SUM(AY36:BB36) -> 19116 | BD36: 4920 | BE36: 4212 | BF36: 4261 | BG36: 4474 | BH36: =SUM(BD36:BG36) -> 17867 | BI36: 4491 | BJ36: 4132 | BK36: 4675 | BL36: 3664 | BM36: =SUM(BI36:BL36) -> 16962 | BN36: 2868 | BO36: 2808 | BP36: 3240 | BQ36: 2421 | BR36: =SUM(BN36:BQ36) -> 11337 | BS36: 2779 | BT36: 2735 | BU36: 2734 | BV36: 2458 | BW36: =SUM(BS36:BV36) -> 10706 | BX36: 2714 | BY36: 2711 | BZ36: 2821 | CA36: 2575 | CB36: =SUM(BX36:CA36) -> 10821 | CC36: =Operations!CC41 -> 2670.844 | CD36: =Operations!CD41 -> 2774.167 | CE36: =Operations!CE41 -> 3078.24 | CF36: =Operations!CF41 -> 3008.544 | CG36: =SUM(CC36:CF36) -> 11531.795 | CH36: =Operations!CH41 -> 3018.0537 | CI36: =Operations!CI41 -> 3154.2279 | CJ36: =Operations!CJ41 -> 3139.8048 | CK36: =Operations!CK41 -> 3068.7149 | CL36: =SUM(CH36:CK36) -> 12380.801 | CM36: =Operations!CM41 -> 3018.0537 | CN36: =Operations!CN41 -> 3154.2279 | CO36: =Operations!CO41 -> 3139.8048 | CP36: =Operations!CP41 -> 3068.7149 | CQ36: =SUM(CM36:CP36) -> 12380.801 | CS36: =CE34-CS34 -> 228.96 | CT36: =CF34-CT34 -> 268.62 | DC36: =CO34-DC34 -> 377.7672 | DD36: =CP34-DD34 -> 217.3314
B37: % Capacity Utilization | D37: =D36/D38 -> 0.78851563 | E37: =E36/E38 -> 0.90117187 | F37: 0.917 | G37: 0.854 | H37: 0.899 | I37: 0.876 | J37: =J36/J38 -> 0.88525469 | K37: 0.917 | L37: 0.875 | M37: 0.878 | N37: 0.872 | O37: =O36/O38 -> 0.88552121 | P37: 0.9 | Q37: 0.744 | R37: 0.719 | S37: 0.803 | T37: =T36/T38 -> 0.79103802 | U37: 0.866 | V37: 0.948 | W37: 0.891 | X37: 0.669 | Y37: =Y36/Y38 -> 0.84311071 | Z37: 0.776 | AA37: 0.851 | AB37: 0.885 | AC37: 0.82 | AD37: =AD36/AD38 -> 0.83272386 | AE37: 0.917 | AF37: 0.927 | AG37: 0.862 | AH37: 0.447 | AI37: =AI36/AI38 -> 0.78758645 | AJ37: 0.38 | AK37: 0.324 | AL37: 0.579 | AM37: 0.642 | AN37: =AN36/AN38 -> 0.4821995 | AO37: 0.73 | AP37: 0.82 | AQ37: 0.77 | AR37: 0.72 | AS37: =AS36/AS38 -> 0.76005904 | AT37: 0.77 | AU37: 0.81 | AV37: 0.74 | AW37: 0.75 | AX37: =AX36/AX38 -> 0.76736461 | AY37: 0.83 | AZ37: 0.77 | BA37: 0.77 | BB37: 0.77 | BC37: =BC36/BC38 -> 0.78496987 | BD37: 0.82 | BE37: 0.7 | BF37: 0.7 | BG37: 0.73 | BH37: =BH36/BH38 -> 0.73729877 | BI37: 0.83 | BJ37: 0.75 | BK37: 0.86 | BL37: 0.75 | BM37: =BM36/BM38 -> 0.79852905 | BN37: 0.6 | BO37: 0.58 | BP37: 0.66 | BQ37: 0.57 | BR37: =BR36/BR38 -> 0.60374361 | BS37: 0.66 | BT37: 0.65 | BU37: 0.64 | BV37: 0.57 | BW37: =BW36/BW38 -> 0.62967381 | BX37: 0.65 | BY37: 0.64 | BZ37: 0.66 | CA37: 0.6 | CB37: =CB36/CB38 -> 0.63738308 | CC37: =CC36/CC38 -> 0.62843388 | CD37: =CD36/CD38 -> 0.65274518 | CE37: =CE36/CE38 -> 0.72429176 | CF37: =CF36/CF38 -> 0.70789271 | CG37: =CG36/CG38 -> 0.67834088 | CH37: =CH36/CH38 -> 0.71013029 | CI37: =CI36/CI38 -> 0.74217127 | ... CQ37: =CQ36/CQ38 -> 0.72828243 | CS37: =CE29-CS29 -> 141.192 | CT37: =CF29-CT29 -> 149.2062 | DC37: =CO29-DC29 -> 180.07284 | DD37: =CP29-DD29 -> 138.02507
B38: Capacity | D38: 12800 | E38: 12800 | F38: =F36/F37 -> 3157.0338 | G38: =G36/G37 -> 3908.6651 | H38: =H36/H37 -> 4889.8776 | I38: =I36/I37 -> 4891.5525 | J38: =SUM(F38:I38) -> 16847.129 | K38: =K36/K37 -> 4884.4057 | L38: =L36/L37 -> 4834.2857 | M38: =M36/M37 -> 4889.5216 | N38: =N36/N37 -> 4889.9083 | O38: =SUM(K38:N38) -> 19498.121 | P38: =P36/P37 -> 4781.1111 | Q38: =Q36/Q37 -> 4834.6774 | R38: =R36/R37 -> 4887.3435 | S38: =S36/S37 -> 4892.9016 | T38: =SUM(P38:S38) -> 19396.034 | U38: =U36/U37 -> 4781.7552 | V38: =V36/V37 -> 4836.4979 | W38: =W36/W37 -> 4892.2559 | X38: =X36/X37 -> 4887.8924 | Y38: =SUM(U38:X38) -> 19398.401 | Z38: =Z36/Z37 -> 4784.7938 | AA38: =AA36/AA37 -> 4836.6627 | AB38: =AB36/AB37 -> 4890.3955 | AC38: =AC36/AC37 -> 5708.5366 | AD38: =SUM(Z38:AC38) -> 20220.389 | AE38: =AE36/AE37 -> 6061.0687 | AF38: =AF36/AF37 -> 6056.0949 | AG38: =AG36/AG37 -> 6127.6102 | AH38: =AH36/AH37 -> 6120.8054 | AI38: =SUM(AE38:AH38) -> 24365.579 | AJ38: =AJ36/AJ37 -> 5997.3684 | AK38: =AK36/AK37 -> 6061.7284 | AL38: =AL36/AL37 -> 6127.8066 | AM38: =AM36/AM37 -> 6124.6106 | AN38: =SUM(AJ38:AM38) -> 24311.514 | AO38: =AO36/AO37 -> 6004.1096 | AP38: =AP36/AP37 -> 6071.9512 | AQ38: =AQ36/AQ37 -> 6096.1039 | AR38: =AR36/AR37 -> 6093.0556 | AS38: =SUM(AO38:AR38) -> 24265.22 | AT38: =AT36/AT37 -> 5971.4286 | AU38: =AU36/AU37 -> 6041.9753 | AV38: =AV36/AV37 -> 6102.7027 | AW38: =AW36/AW37 -> 6124 | AX38: =SUM(AT38:AW38) -> 24240.107 | AY38: =AY36/AY37 -> 6075.9036 | AZ38: =AZ36/AZ37 -> 6088.3117 | BA38: =BA36/BA37 -> 6102.5974 | BB38: =BB36/BB37 -> 6085.7143 | BC38: =SUM(AY38:BB38) -> 24352.527 | BD38: =BD36/BD37 -> 6000 | BE38: =BE36/BE37 -> 6017.1429 | BF38: =BF36/BF37 -> 6087.1429 | BG38: =BG36/BG37 -> 6128.7671 | BH38: =SUM(BD38:BG38) -> 24233.053 | BI38: =BI36/BI37 -> 5410.8434 | BJ38: =BJ36/BJ37 -> 5509.3333 | BK38: =BK36/BK37 -> 5436.0465 | BL38: =BL36/BL37 -> 4885.3333 | BM38: =SUM(BI38:BL38) -> 21241.557 | BN38: =BN36/BN37 -> 4780 | BO38: =BO36/BO37 -> 4841.3793 | BP38: =BP36/BP37 -> 4909.0909 | BQ38: =BQ36/BQ37 -> 4247.3684 | BR38: =SUM(BN38:BQ38) -> 18777.839 | BS38: =BS36/BS37 -> 4210.6061 | BT38: =BT36/BT37 -> 4207.6923 | BU38: =BU36/BU37 -> 4271.875 | BV38: =BV36/BV37 -> 4312.2807 | BW38: =SUM(BS38:BV38) -> 17002.454 | BX38: =BX36/BX37 -> 4175.3846 | BY38: =BY36/BY37 -> 4235.9375 | BZ38: =BZ36/BZ37 -> 4274.2424 | CA38: =CA36/CA37 -> 4291.6667 | CB38: =SUM(BX38:CA38) -> 16977.231 | CC38: =Operations!CC40 -> 4250 | CD38: =Operations!CD40 -> 4250 | CE38: =Operations!CE40 -> 4250 | CF38: =Operations!CF40 -> 4250 | CG38: =SUM(CC38:CF38) -> 17000 | CH38: =Operations!CH40 -> 4250 | CI38: =Operations!CI40 -> 4250 | CJ38: =Operations!CJ40 -> 4250 | CK38: =Operations!CK40 -> 4250 | CL38: =SUM(CH38:CK38) -> 17000 | CM38: =Operations!CM40 -> 4250 | CN38: =Operations!CN40 -> 4250 | CO38: =Operations!CO40 -> 4250 | CP38: =Operations!CP40 -> 4250 | CQ38: =SUM(CM38:CP38) -> 17000 | CS38: =CE33-CS33 -> 94.128 | CT38: =CF33-CT33 -> 92.89368 | DC38: =CO33-DC33 -> 98.89512 | DD38: =CP33-DD33 -> 93.618334
C40: Domestic Capacity | J40: =Operations!J38 -> 16847.129 | K40: =Operations!K38 -> 4884.4057 | L40: =Operations!L38 -> 4834.2857 | M40: =Operations!M38 -> 4889.5216 | N40: =Operations!N38 -> 4889.9083 | O40: =Operations!O38 -> 19498.121 | P40: =Operations!P38 -> 4781.1111 | Q40: =Operations!Q38 -> 4834.6774 | ... X40: =Operations!X38 -> 4887.8924 | Y40: =SUM(U40:X40) -> 19398.401 | Z40: =Operations!Z38 -> 4784.7938 | AA40: =Operations!AA38 -> 4836.6627 | AB40: =Operations!AB38 -> 4890.3955 | AC40: =Operations!AC38 -> 5708.5366 | AD40: =SUM(Z40:AC40) -> 20220.389 | AE40: =Operations!AE38 -> 6061.0687 | AF40: =Operations!AF38 -> 6056.0949 | AG40: =Operations!AG38 -> 6127.6102 | AH40: =Operations!AH38 -> 6120.8054 | AI40: =SUM(AE40:AH40) -> 24365.579 | AJ40: =Operations!AJ38 -> 5997.3684 | AK40: =Operations!AK38 -> 6061.7284 | AL40: =Operations!AL38 -> 6127.8066 | AM40: =Operations!AM38 -> 6124.6106 | AN40: =SUM(AJ40:AM40) -> 24311.514 | AO40: =Operations!AO38 -> 6004.1096 | AP40: =Operations!AP38 -> 6071.9512 | AQ40: =Operations!AQ38 -> 6096.1039 | AR40: =Operations!AR38 -> 6093.0556 | AS40: =SUM(AO40:AR40) -> 24265.22 | AT40: =Operations!AT38 -> 5971.4286 | AU40: =Operations!AU38 -> 6041.9753 | AV40: =Operations!AV38 -> 6102.7027 | AW40: =Operations!AW38 -> 6124 | AX40: =SUM(AT40:AW40) -> 24240.107 | AY40: =Operations!AY38 -> 6075.9036 | AZ40: =Operations!AZ38 -> 6088.3117 | BA40: =Operations!BA38 -> 6102.5974 | BB40: =Operations!BB38 -> 6085.7143 | BC40: =SUM(AY40:BB40) -> 24352.527 | BD40: =Operations!BD38 -> 6000 | BE40: =Operations!BE38 -> 6017.1429 | BF40: =Operations!BF38 -> 6087.1429 | BG40: =Operations!BG38 -> 6128.7671 | BH40: =SUM(BD40:BG40) -> 24233.053 | BI40: =Operations!BI38 -> 5410.8434 | BJ40: =Operations!BJ38 -> 5509.3333 | BK40: =Operations!BK38 -> 5436.0465 | BL40: =Operations!BL38 -> 4885.3333 | BM40: =SUM(BI40:BL40) -> 21241.557 | BN40: =Operations!BN38 -> 4780 | BO40: =Operations!BO38 -> 4841.3793 | BP40: =Operations!BP38 -> 4909.0909 | BQ40: =Operations!BQ38 -> 4247.3684 | BR40: =SUM(BN40:BQ40) -> 18777.839 | BS40: =Operations!BS38 -> 4210.6061 | BT40: =Operations!BT38 -> 4207.6923 | BU40: =Operations!BU38 -> 4271.875 | BV40: =Operations!BV38 -> 4312.2807 | BW40: =Operations!BW38 -> 17002.454 | BX40: =Operations!BX38 -> 4175.3846 | BY40: =Operations!BY38 -> 4235.9375 | BZ40: =Operations!BZ38 -> 4274.2424 | CA40: =Operations!CA38 -> 4291.6667 | CB40: =SUM(BX40:CA40) -> 16977.231 | CC40: =17000/4 -> 4250 | CD40: =17000/4 -> 4250 | CE40: =17000/4 -> 4250 | CF40: =17000/4 -> 4250 | CG40: =SUM(CC40:CF40) -> 17000 | CH40: =17000/4 -> 4250 | CI40: =17000/4 -> 4250 | CJ40: =17000/4 -> 4250 | CK40: =17000/4 -> 4250 | CL40: =SUM(CH40:CK40) -> 17000 | CM40: =17000/4 -> 4250 | CN40: =17000/4 -> 4250 | CO40: =17000/4 -> 4250 | CP40: =17000/4 -> 4250 | CQ40: =SUM(CM40:CP40) -> 17000
C41: Raw Steel Production | J41: =Operations!J36 -> 14914 | K41: =Operations!K36 -> 4479 | L41: =Operations!L36 -> 4230 | M41: =Operations!M36 -> 4293 | N41: =Operations!N36 -> 4264 | O41: =Operations!O36 -> 17266 | P41: =Operations!P36 -> 4303 | Q41: =Operations!Q36 -> 3597 | ... X41: =Operations!X36 -> 3270 | Y41: =SUM(U41:X41) -> 16355 | Z41: =Operations!Z36 -> 3713 | AA41: =Operations!AA36 -> 4116 | AB41: =Operations!AB36 -> 4328 | AC41: =Operations!AC36 -> 4681 | AD41: =SUM(Z41:AC41) -> 16838 | AE41: =Operations!AE36 -> 5558 | AF41: =Operations!AF36 -> 5614 | AG41: =Operations!AG36 -> 5282 | AH41: =Operations!AH36 -> 2736 | AI41: =SUM(AE41:AH41) -> 19190 | AJ41: =Operations!AJ36 -> 2279 | AK41: =Operations!AK36 -> 1964 | AL41: =Operations!AL36 -> 3548 | AM41: =Operations!AM36 -> 3932 | AN41: =SUM(AJ41:AM41) -> 11723 | AO41: =Operations!AO36 -> 4383 | AP41: =Operations!AP36 -> 4979 | AQ41: =Operations!AQ36 -> 4694 | AR41: =Operations!AR36 -> 4387 | AS41: =SUM(AO41:AR41) -> 18443 | AT41: =Operations!AT36 -> 4598 | AU41: =Operations!AU36 -> 4894 | AV41: =Operations!AV36 -> 4516 | AW41: =Operations!AW36 -> 4593 | AX41: =SUM(AT41:AW41) -> 18601 | AY41: =Operations!AY36 -> 5043 | AZ41: =Operations!AZ36 -> 4688 | BA41: =Operations!BA36 -> 4699 | BB41: =Operations!BB36 -> 4686 | BC41: =SUM(AY41:BB41) -> 19116 | BD41: =Operations!BD36 -> 4920 | BE41: =Operations!BE36 -> 4212 | BF41: =Operations!BF36 -> 4261 | BG41: =Operations!BG36 -> 4474 | BH41: =SUM(BD41:BG41) -> 17867 | BI41: =Operations!BI36 -> 4491 | BJ41: =Operations!BJ36 -> 4132 | BK41: =Operations!BK36 -> 4675 | BL41: =Operations!BL36 -> 3664 | BM41: =SUM(BI41:BL41) -> 16962 | BN41: =Operations!BN36 -> 2868 | BO41: =Operations!BO36 -> 2808 | BP41: =Operations!BP36 -> 3240 | BQ41: =Operations!BQ36 -> 2421 | BR41: =SUM(BN41:BQ41) -> 11337 | BS41: =Operations!BS36 -> 2779 | BT41: =Operations!BT36 -> 2735 | BU41: =Operations!BU36 -> 2734 | BV41: =Operations!BV36 -> 2458 | BW41: =SUM(BS41:BV41) -> 10706 | BX41: =Operations!BX36 -> 2714 | BY41: =Operations!BY36 -> 2711 | BZ41: =Operations!BZ36 -> 2821 | CA41: =Operations!CA36 -> 2575 | CB41: =SUM(BX41:CA41) -> 10821 | CC41: =CC34*1.1 -> 2670.844 | CD41: =CD34*1.1 -> 2774.167 | CE41: =CE34*1.1 -> 3078.24 | CF41: =CF34*1.1 -> 3008.544 | CG41: =SUM(CC41:CF41) -> 11531.795 | CH41: =CH34*1.1 -> 3018.0537 | CI41: =CI34*1.1 -> 3154.2279 | CJ41: =CJ34*1.1 -> 3139.8048 | CK41: =CK34*1.1 -> 3068.7149 | CL41: =SUM(CH41:CK41) -> 12380.801 | CM41: =CM34*1.1 -> 3018.0537 | CN41: =CN34*1.1 -> 3154.2279 | CO41: =CO34*1.1 -> 3139.8048 | CP41: =CP34*1.1 -> 3068.7149 | CQ41: =SUM(CM41:CP41) -> 12380.801
C42: Capacity utilization | J42: =J41/J40 -> 0.88525469 | K42: =K41/K40 -> 0.917 | L42: =L41/L40 -> 0.875 | M42: =M41/M40 -> 0.878 | N42: =N41/N40 -> 0.872 | O42: =O41/O40 -> 0.88552121 | P42: =P41/P40 -> 0.9 | Q42: =Q41/Q40 -> 0.744 | ... CQ42: =CQ41/CQ40 -> 0.72828243
B44: Average Spot Price, $/st | J44: =(J8*J29+J9*J30+J10*J31+J11*J32+J12*J33)/J34 -> 356.6019 | K44: =(K8*K29+K9*K30+K10*K31+K11*K32+K12*K33)/K34 -> 525.8086 | L44: =(L8*L29+L9*L30+L10*L31+L11*L32+L12*L33)/L34 -> 686.86748 | M44: =(M8*M29+M9*M30+M10*M31+M11*M32+M12*M33)/M34 -> 795.83361 | N44: =(N8*N29+N9*N30+N10*N31+N11*N32+N12*N33)/N34 -> 747.08845 | O44: =(O8*O29+O9*O30+O10*O31+O11*O32+O12*O33)/O34 -> 688.89953 | P44: =(P8*P29+P9*P30+P10*P31+P11*P32+P12*P33)/P34 -> 713.70939 | Q44: =(Q8*Q29+Q9*Q30+Q10*Q31+Q11*Q32+Q12*Q33)/Q34 -> 616.89807 | ... CQ44: =(CQ8*CQ29+CQ9*CQ30+CQ10*CQ31+CQ11*CQ32+CQ12*CQ33)/CQ34 -> 804.79
B45: Other Revenue/ton | F45: =+F46-F51 -> 12.087028 | G45: =+G46-G51 -> 16.289819 | H45: =+H46-H51 -> 41.592223 | I45: =+I46-I51 -> 113.27204 | J45: =+J46-J51 -> 51.551824 | K45: =+K46-K51 -> 32.570296 | L45: =+L46-L51 -> 47.336514 | M45: =+M46-M51 -> 65.923899 | ... CB45: =+CB46-CB51 -> 132.17397 | CL45: 865
B46: Total Revenue per ton | F46: =+F48/F34*1000 -> 433.08703 | G46: =+G48/G34*1000 -> 436.28982 | H46: =+H48/H34*1000 -> 465.59222 | I46: =+I48/I34*1000 -> 536.27204 | J46: =+J48/J34*1000 -> 473.55182 | K46: =+K48/K34*1000 -> 507.5703 | L46: =+L48/L34*1000 -> 630.33651 | M46: =+M48/M34*1000 -> 692.9239 | ... CB46: =+CB48/CB34*1000 -> 858.80449 | CL46: =CL44-CL45 -> 42.85875 | CM46: =CL46*CL36 -> 530625.67
B48: Flat rolled Segment Revenue | F48: =Financials!F9 -> 1055 | G48: =Financials!G9 -> 1397 | H48: =Financials!H9 -> 1820 | I48: =Financials!I9 -> 2129 | J48: =Financials!J9 -> 6401 | K48: =Financials!K9 -> 2112 | L48: =Financials!L9 -> 2510 | M48: =Financials!M9 -> 2595 | ... T48: =Financials!T9 -> 8813 | U48: 2324 | V48: 2581 | W48: 2545 | X48: =Y48-W48-V48-U48 -> 2157 | Y48: 9607 | Z48: 2189 | AA48: 2509 | AB48: 2439 | AC48: 2747 | AD48: =AD49+AD50 -> 9884 | AE48: 3155 | AF48: 4010 | AG48: 4303 | AH48: 2363 | AI48: =AI49+AI50 -> 13831 | AJ48: 1592 | AK48: 1310 | AL48: 1745 | AM48: 2167 | AN48: =AN49+AN50 -> 6814 | AO48: 2455 | AP48: 2963 | AQ48: 2763 | AR48: 2667 | AS48: =AS49+AS50 -> 10848 | AT48: 2969 | AU48: 3304 | AV48: 3136 | AW48: 2958 | AX48: =AX49+AX50 -> 12367 | AY48: 3300 | AZ48: 3356 | BA48: 3142 | BB48: 3110 | BC48: =BC49+BC50 -> 12908 | BD48: 3103 | BE48: 2876 | BF48: 2731 | BG48: 2862 | BH48: =BH49+BH50 -> 11572 | BI48: 3025 | BJ48: 2938 | BK48: 3125 | BL48: 2619 | BM48: =BM49+BM50 -> 11707 | BN48: 2194 | BO48: 2125 | BP48: 2070 | BQ48: =8293-SUM(BN48:BP48) -> 1904 | BR48: =BR49+BR50 -> 8293 | BS48: 1748 | BT48: 1926 | BU48: 1986 | BV48: 1873 | BW48: =BW49+BW50 -> 7533 | BX48: 1886 | BY48: 2243 | BZ48: 2291 | CA48: 2071 | CB48: =CB49+CB50 -> 8491 | CC48: =CC49+CC50 -> 2017.3163 | CD48: =CD49+CD50 -> 2212.8619 | CE48: =CE49+CE50 -> 2502.5213 | CF48: =CF49+CF50 -> 2467.4876 | CG48: =CG49+CG50 -> 9200.1871 | CH48: =CH49+CH50 -> 2497.4003 | CI48: =CI49+CI50 -> 2589.6386 | ... CQ48: =CQ49+CQ50 -> 9331.1817
B49: STEEL REVENUE | D49: =D48-D50 -> 3485.263 | E49: =E48-E50 -> 4059 | F49: =F48-F50 -> 1025.556 | G49: =G48-G50 -> 1344.84 | H49: =H48-H50 -> 1657.416 | I49: =I48-I50 -> 1679.31 | J49: =J48-J50 -> 5704.174 | K49: =K48-K50 -> 1976.475 | ... N49: =N48-N50 -> 2328.394 | O49: =SUM(K49:N49) -> 8974.49 | P49: =P48-P50 -> 2297.75 | Q49: =Q48-Q50 -> 2040.792 | R49: =R48-R50 -> 1869.926 | S49: =S48-S50 -> 1997.562 | T49: =SUM(P49:S49) -> 8206.03 | U49: =U48-U50 -> 2173.864 | V49: =V48-V50 -> 2419.872 | W49: =W48-W50 -> 2405.445 | X49: =X48-X50 -> 1994.544 | Y49: =SUM(U49:X49) -> 8993.725 | Z49: =Z48-Z50 -> 2072.2 | AA49: =AA48-AA50 -> 2346.548 | AB49: =AB48-AB50 -> 2315.443 | AC49: =AC48-AC50 -> 2599.542 | AD49: =SUM(Z49:AC49) -> 9333.733 | AE49: =AE48-AE50 -> 3036.846 | AF49: =AF48-AF50 -> 3767.673 | AG49: =AG48-AG50 -> 4086.035 | AH49: =AH48-AH50 -> 2245.95 | AI49: =SUM(AE49:AH49) -> 13136.504 | AJ49: =AJ48-AJ50 -> 1517.945 | AK49: =AK48-AK50 -> 1228.755 | AL49: =AL48-AL50 -> 1646.81 | AM49: =AM48-AM50 -> 2026.233 | AN49: =SUM(AJ49:AM49) -> 6419.743 | AO49: =AO48-AO50 -> 2336.088 | AP49: =AP48-AP50 -> 2842.7 | AQ49: =AQ48-AQ50 -> 2622.656 | AR49: =AR48-AR50 -> 2533.392 | AS49: =SUM(AO49:AR49) -> 10334.836 | AT49: =AT48-AT50 -> 2846.88 | AU49: =AU48-AU50 -> 3160.608 | AV49: =AV48-AV50 -> 2964.455 | AW49: =AW48-AW50 -> 2803.944 | AX49: =SUM(AT49:AW49) -> 11775.887 | AY49: =AY48-AY50 -> 3126.288 | AZ49: =AZ48-AZ50 -> 3077.192 | BA49: =BA48-BA50 -> 2943.252 | BB49: =BB48-BB50 -> 2829.204 | BC49: =SUM(AY49:BB49) -> 11975.936 | BD49: =BD48-BD50 -> 2888.942 | BE49: =BE48-BE50 -> 2702.8 | BF49: =BF48-BF50 -> 2577.856 | BG49: =BG48-BG50 -> 2602.5 | BH49: =SUM(BD49:BG49) -> 10772.098 | BI49: =BI48-BI50 -> 2795.914 | BJ49: =BJ48-BJ50 -> 2729.898 | BK49: =BK48-BK50 -> 2868.684 | BL49: =BL48-BL50 -> 2336.625 | BM49: =SUM(BI49:BL49) -> 10731.121 | BN49: =BN48-BN50 -> 2009.856 | BO49: =BO48-BO50 -> 1884.84 | BP49: =BP48-BP50 -> 1803.624 | BQ49: =BQ48-BQ50 -> 1663.422 | BR49: =SUM(BN49:BQ49) -> 7361.742 | BS49: =BS48-BS50 -> 1526.278 | BT49: =BT48-BT50 -> 1728.264 | BU49: =BU48-BU50 -> 1820.13 | BV49: =BV48-BV50 -> 1639.348 | BW49: =SUM(BS49:BV49) -> 6714.02 | BX49: =BX48-BX50 -> 1728.476 | BY49: =BY48-BY50 -> 1852.774 | BZ49: =BZ48-BZ50 -> 1852.032 | CA49: =CA48-CA50 -> 1750.914 | CB49: =SUM(BX49:CA49) -> 7184.196 | CC49: =+CC51*CC34/1000 -> 1792.3163 | CD49: =+CD51*CD34/1000 -> 1987.8619 | CE49: =+CE51*CE34/1000 -> 2277.5213 | CF49: =+CF51*CF34/1000 -> 2242.4876 | CG49: =SUM(CC49:CF49) -> 8300.1871 | CH49: =+CH51*CH34/1000 -> 2272.4003 | CI49: =+CI51*CI34/1000 -> 2364.6386 | CJ49: =+CJ51*CJ34/1000 -> 2338.0913 | CK49: =+CK51*CK34/1000 -> 2236.727 | CL49: =SUM(CH49:CK49) -> 9211.8571 | CM49: =+CM51*CM34/1000 -> 2122.4631 | CN49: =+CN51*CN34/1000 -> 2174.5528 | CO49: =+CO51*CO34/1000 -> 2109.7372 | CP49: =+CP51*CP34/1000 -> 2024.4287 | CQ49: =SUM(CM49:CP49) -> 8431.1817
B50: Other revenue ( $ in millions) | D50: =D48-D51*D34/1000 -> -3485.263 | E50: =E48-E51*E34/1000 -> -4059 | F50: =F48-F51*F34/1000 -> 29.444 | G50: =G48-G51*G34/1000 -> 52.16 | H50: =H48-H51*H34/1000 -> 162.584 | I50: =I48-I51*I34/1000 -> 449.69 | J50: =J48-J51*J34/1000 -> 696.826 | K50: =K48-K51*K34/1000 -> 135.525 | ... X50: =X48-X51*X34/1000 -> 162.456 | Y50: =SUM(U50:X50) -> 613.275 | Z50: =Z48-Z51*Z34/1000 -> 116.8 | AA50: =AA48-AA51*AA34/1000 -> 162.452 | AB50: =AB48-AB51*AB34/1000 -> 123.557 | AC50: =AC48-AC51*AC34/1000 -> 147.458 | AD50: =SUM(Z50:AC50) -> 550.267 | AE50: =AE48-AE51*AE34/1000 -> 118.154 | AF50: =AF48-AF51*AF34/1000 -> 242.327 | AG50: =AG48-AG51*AG34/1000 -> 216.965 | AH50: =AH48-AH51*AH34/1000 -> 117.05 | AI50: =SUM(AE50:AH50) -> 694.496 | AJ50: =AJ48-AJ51*AJ34/1000 -> 74.055 | AK50: =AK48-AK51*AK34/1000 -> 81.245 | AL50: =AL48-AL51*AL34/1000 -> 98.19 | AM50: =AM48-AM51*AM34/1000 -> 140.767 | AN50: =SUM(AJ50:AM50) -> 394.257 | AO50: =AO48-AO51*AO34/1000 -> 118.912 | AP50: =AP48-AP51*AP34/1000 -> 120.3 | AQ50: =AQ48-AQ51*AQ34/1000 -> 140.344 | AR50: =AR48-AR51*AR34/1000 -> 133.608 | AS50: =SUM(AO50:AR50) -> 513.164 | AT50: =AT48-AT51*AT34/1000 -> 122.12 | AU50: =AU48-AU51*AU34/1000 -> 143.392 | AV50: =AV48-AV51*AV34/1000 -> 171.545 | AW50: =AW48-AW51*AW34/1000 -> 154.056 | AX50: =SUM(AT50:AW50) -> 591.113 | AY50: =AY48-AY51*AY34/1000 -> 173.712 | AZ50: =AZ48-AZ51*AZ34/1000 -> 278.808 | BA50: =BA48-BA51*BA34/1000 -> 198.748 | BB50: =BB48-BB51*BB34/1000 -> 280.796 | BC50: =SUM(AY50:BB50) -> 932.064 | BD50: =BD48-BD51*BD34/1000 -> 214.058 | BE50: =BE48-BE51*BE34/1000 -> 173.2 | BF50: =BF48-BF51*BF34/1000 -> 153.144 | BG50: =BG48-BG51*BG34/1000 -> 259.5 | BH50: =SUM(BD50:BG50) -> 799.902 | BI50: =BI48-BI51*BI34/1000 -> 229.086 | BJ50: =BJ48-BJ51*BJ34/1000 -> 208.102 | BK50: =BK48-BK51*BK34/1000 -> 256.316 | BL50: =BL48-BL51*BL34/1000 -> 282.375 | BM50: =SUM(BI50:BL50) -> 975.879 | BN50: =BN48-BN51*BN34/1000 -> 184.144 | BO50: =BO48-BO51*BO34/1000 -> 240.16 | BP50: =BP48-BP51*BP34/1000 -> 266.376 | BQ50: =BQ48-BQ51*BQ34/1000 -> 240.578 | BR50: =SUM(BN50:BQ50) -> 931.258 | BS50: =BS48-BS51*BS34/1000 -> 221.722 | BT50: =BT48-BT51*BT34/1000 -> 197.736 | BU50: =BU48-BU51*BU34/1000 -> 165.87 | BV50: =BV48-BV51*BV34/1000 -> 233.652 | BW50: =SUM(BS50:BV50) -> 818.98 | BX50: =BX48-BX51*BX34/1000 -> 157.524 | BY50: =BY48-BY51*BY34/1000 -> 390.226 | BZ50: =BZ48-BZ51*BZ34/1000 -> 438.968 | CA50: =CA48-CA51*CA34/1000 -> 320.086 | CB50: =SUM(BX50:CA50) -> 1306.804 | CC50: 225 | CD50: =CC50 -> 225 | CE50: =CD50 -> 225 | CF50: =CE50 -> 225 | CG50: =SUM(CC50:CF50) -> 900 | CH50: 225 | CI50: =CH50 -> 225 | CJ50: =CI50 -> 225 | CK50: =CJ50 -> 225 | CL50: =SUM(CH50:CK50) -> 900 | CM50: 225 | CN50: =CM50 -> 225 | CO50: =CN50 -> 225 | CP50: =CO50 -> 225 | CQ50: =SUM(CM50:CP50) -> 900
B51: Average realized steel price per ton | D51: 397 | E51: 410 | F51: 421 | G51: 420 | H51: 424 | I51: 423 | J51: 422 | K51: =P51-175 -> 475 | L51: =Q51-50 -> 583 | M51: =R51+41 -> 627 | N51: =((O51*O34)-K51*K34-L34*L51-M51*M34)/N34 -> 621.40219 | O51: 574 | P51: 650 | Q51: 633 | R51: 586 | S51: 597 | T51: 617 | U51: 616 | V51: 624 | W51: 651 | X51: 648 | Y51: =(U51*U34+V34*V51+W51*W34+X34*X51)/Y34 -> 634.25423 | Z51: 650 | AA51: 652 | AB51: 643 | AC51: 627 | AD51: =(Z51*Z34+AA34*AA51+AB51*AB34+AC34*AC51)/AD34 -> 642.19988 | AE51: 646 | AF51: 777 | AG51: 907 | AH51: 805 | AI51: =(AE51*AE34+AF34*AF51+AG51*AG34+AH34*AH51)/AI34 -> 779.84589 | AJ51: 715 | AK51: 677 | AL51: 605 | AM51: 633 | AN51: =(AJ51*AJ34+AK34*AK51+AL51*AL34+AM34*AM51)/AN34 -> 651.02353 | AO51: 654 | AP51: 700 | AQ51: 688 | AR51: 657 | AS51: =(AO51*AO34+AP34*AP51+AQ51*AQ34+AR34*AR51)/AS34 -> 675.43533 | AT51: 720 | AU51: 803 | AV51: 773 | AW51: 741 | AX51: =(AT51*AT34+AU34*AU51+AV51*AV34+AW34*AW51)/AX34 -> 759.29376 | AY51: 764 | AZ51: 772 | BA51: 741 | BB51: 721 | BC51: =(AY51*AY34+AZ34*AZ51+BA51*BA34+BB34*BB51)/BC34 -> 749.71429 | BD51: 719 | BE51: 725 | BF51: 752 | BG51: 750 | BH51: =(BD51*BD34+BE34*BE51+BF51*BF34+BG34*BG51)/BH34 -> 735.59806 | BI51: 761 | BJ51: 774 | BK51: 777 | BL51: 775 | BM51: =(BI51*BI34+BJ34*BJ51+BK51*BK34+BL34*BL51)/BM34 -> 771.57902 | BN51: 768 | BO51: 695 | BP51: 674 | BQ51: 642 | BR51: =(BN51*BN34+BO34*BO51+BP51*BP34+BQ34*BQ51)/BR34 -> 694.76614 | BS51: 611 | BT51: 642 | BU51: 718 | BV51: 692 | BW51: =(BS51*BS34+BT34*BT51+BU51*BU34+BV34*BV51)/BW34 -> 665.14959 | BX51: 719 | BY51: 742 | BZ51: 728 | CA51: 717 | CB51: =(BX51*BX34+BY34*BY51+BZ51*BZ34+CA34*CA51)/CB34 -> 726.63052 | CC51: ='Price Relationships'!$C$69 -> 738.17412 | CD51: ='Price Relationships'!$C$70 -> 788.21789 | CE51: ='Price Relationships'!$C$71 -> 813.86552 | CF51: ='Price Relationships'!$C$72 -> 819.91036 | CG51: =(CC51*CC34+CD34*CD51+CE51*CE34+CF34*CF51)/CG34 -> 791.74194 | CH51: ='Price Relationships'!$C$73 -> 828.22925 | CI51: ='Price Relationships'!$C$74 -> 824.63998 | CJ51: ='Price Relationships'!$C$75 -> 819.12748 | CK51: ='Price Relationships'!$C$76 -> 801.76874 | CL51: =(CH51*CH34+CI34*CI51+CJ51*CJ34+CK34*CK51)/CL34 -> 818.44807 | CM51: ='Price Relationships'!$C$77 -> 773.58112 | CN51: ='Price Relationships'!$C$78 -> 758.34978 | CO51: ='Price Relationships'!$C$79 -> 739.12585 | CP51: ='Price Relationships'!$C$80 -> 725.66909 | CQ51: =(CM51*CM34+CN34*CN51+CO51*CO34+CP34*CP51)/CQ34 -> 749.0872
B53: Costs
B54: Coking Coal ($ per ton) | Z54: 110 | AA54: 110 | AB54: 110 | AC54: 110 | AD54: 110 | AE54: 130 | AF54: 130 | AG54: 130 | AH54: 130 | AI54: 130 | AJ54: 143.24 | AK54: 155.56 | AL54: 161.43 | AM54: 146.39 | AN54: =AVERAGE(AJ54:AM54) -> 151.655 | AO54: 152.61 | AP54: 148.87 | AQ54: 150 | AR54: 200 | AS54: =AVERAGE(AO54:AR54) -> 162.87 | AT54: 172.8 | AU54: 194.51 | AV54: 193.7 | AW54: 205.2 | AX54: =AVERAGE(AT54:AW54) -> 191.5525 | AY54: 189 | AZ54: 189 | BA54: 189 | BB54: 189 | BC54: =AVERAGE(AY54:BB54) -> 189 | BD54: 145 | BE54: 145 | BF54: 145 | BG54: 145 | BH54: =AVERAGE(BD54:BG54) -> 145 | BI54: 133 | BJ54: 133 | BK54: 133 | BL54: 133 | BM54: =AVERAGE(BI54:BL54) -> 133 | BN54: 110 | BO54: 110 | BP54: 110 | BQ54: 110 | BR54: =AVERAGE(BN54:BQ54) -> 110 | BS54: 115 | BT54: 115 | BU54: 115 | BV54: 115 | BW54: =AVERAGE(BS54:BV54) -> 115 | BX54: =+BW54+19 -> 134 | BY54: =BX54 -> 134 | BZ54: =BY54 -> 134 | CA54: =BZ54 -> 134 | CB54: =AVERAGE(BX54:CA54) -> 134 | CC54: 145 | CD54: 145 | CE54: 145 | CF54: 145 | CG54: =AVERAGE(CC54:CF54) -> 145 | CH54: 135 | CI54: 135 | CJ54: 135 | CK54: 135 | CL54: =AVERAGE(CH54:CK54) -> 135 | CM54: 135 | CN54: 135 | CO54: 135 | CP54: 135 | CQ54: =AVERAGE(CM54:CP54) -> 135
B55: Coke ($ per ton) | K55: 348.33333 | L55: 415 | M55: 257.66667 | N55: 245 | O55: 316.5 | P55: 233 | Q55: 220 | R55: 161 | S55: 124.33333 | T55: 184.58333 | U55: 132 | V55: 148.33333 | W55: 163.33333 | X55: 165 | Y55: 152.16667 | Z55: 181.66667 | AA55: 219.66667 | AB55: 262.33333 | AC55: 376.66667 | AD55: 260.08333 | AE55: 470 | AF55: 500 | AG55: 700 | AH55: 500 | AI55: 542.5 | AJ55: 310.9 | AK55: =AK54*1.6*1.35 -> 336.0096 | AL55: 360.03 | AM55: 328.18 | AN55: =AVERAGE(AJ55:AM55) -> 333.7799 | AO55: 330.08 | AP55: 339.4 | AQ55: 320 | AR55: 325 | AS55: =AVERAGE(AO55:AR55) -> 328.62 | AT55: 397.45 | AU55: 453.08 | AV55: 437.12 | AW55: 438.5 | AX55: =AVERAGE(AT55:AW55) -> 431.5375 | AY55: 402.71 | AZ55: 388.87 | BA55: 392.99 | BB55: 401.58 | BC55: =AVERAGE(AY55:BB55) -> 396.5375 | BD55: 364.97 | BE55: 331.26 | BF55: 330.18 | BG55: 329.47 | BH55: =AVERAGE(BD55:BG55) -> 338.97 | BI55: 143 | BJ55: 308.6 | BK55: 343.18 | BL55: 322 | BM55: =AVERAGE(BI55:BL55) -> 279.195 | BN55: 298.54 | BO55: 289.82 | BP55: 289.44 | BQ55: 289.88 | BR55: =AVERAGE(BN55:BQ55) -> 291.92 | BS55: 227.76 | BT55: 201.78 | BU55: 197.52 | BV55: 203.86 | BW55: =AVERAGE(BS55:BV55) -> 207.73 | BX55: 310 | BY55: 310 | BZ55: 310 | CA55: 310 | CB55: =AVERAGE(BX55:CA55) -> 310 | CC55: =CC54*2 -> 290 | CD55: =CD54*2 -> 290 | CE55: =CE54*2 -> 290 | CF55: =CF54*2 -> 290 | CG55: =AVERAGE(CC55:CF55) -> 290 | CH55: =CH54*2 -> 270 | CI55: =CI54*2 -> 270 | CJ55: =CJ54*2 -> 270 | CK55: =CK54*2 -> 270 | CL55: =AVERAGE(CH55:CK55) -> 270 | CM55: =CM54*2 -> 270 | CN55: =CN54*2 -> 270 | CO55: =CO54*2 -> 270 | CP55: =CP54*2 -> 270 | CQ55: =AVERAGE(CM55:CP55) -> 270
B56: Scrap ($ per gross ton) | F56: 123.47333 | G56: 127.24 | H56: 137 | I56: 162.09333 | J56: =AVERAGE(F56:I56) -> 137.45167 | K56: 244.5 | L56: 201.46667 | M56: 265.48333 | N56: 287.01667 | O56: 249.61667 | P56: 246.37667 | Q56: 203.84667 | R56: 220.79667 | S56: 246.94 | T56: 229.49 | U56: 241.68333 | V56: 267.78 | W56: 254.14667 | X56: 228.62 | Y56: 248.0575 | Z56: 299.89 | AA56: 286.15333 | AB56: 278.87 | AC56: 295.4 | AD56: 290.07833 | AE56: 392.54 | AF56: 547.20667 | AG56: 513.71333 | AH56: 193.66333 | AI56: 411.78083 | AJ56: 213.37333 | AK56: 191.80667 | AL56: 269.50667 | AM56: 265.71333 | AN56: 235.1 | AO56: 358.61667 | AP56: 368.89333 | AQ56: 339.70667 | AR56: 367.51667 | AS56: =AVERAGE(AO56:AR56) -> 358.68333 | AT56: 456.45667 | AU56: 447.39333 | AV56: 450 | AW56: 429.87 | AX56: =AVERAGE(AT56:AW56) -> 445.93 | AY56: 449.5 | AZ56: 414.82667 | BA56: 373.72 | BB56: 369.33 | BC56: =AVERAGE(AY56:BB56) -> 401.84417 | BD56: 390.07333 | BE56: 374.86667 | BF56: 366.60333 | BG56: 383.98333 | BH56: =AVERAGE(BD56:BG56) -> 378.88167 | BI56: 412.41333 | BJ56: 383.64333 | BK56: 374.24333 | BL56: 338.38333 | BM56: =AVERAGE(BI56:BL56) -> 377.17083 | BN56: 277.58667 | BO56: 249.18333 | BP56: 244.09 | BQ56: 171.85667 | BR56: =AVERAGE(BN56:BQ56) -> 235.67917 | BS56: 194.21667 | BT56: 260.70667 | BU56: 235.08 | BV56: 227.43667 | BW56: =AVERAGE(BS56:BV56) -> 229.36 | BX56: 301.52667 | BY56: 292.27333 | BZ56: 289.08667 | CA56: 272.81667 | CB56: =AVERAGE(BX56:CA56) -> 288.92583 | CC56: 332.51333 | CD56: 375 | CE56: 360 | CF56: 345 | CG56: =AVERAGE(CC56:CF56) -> 353.12833 | CH56: 355 | CI56: 360 | CJ56: 350 | CK56: 335 | CL56: =AVERAGE(CH56:CK56) -> 350 | CM56: 305 | CN56: 310 | CO56: 300 | CP56: 285 | CQ56: =AVERAGE(CM56:CP56) -> 300
B57: Nat Gas ($ per mcf) | K57: 5.43 | L57: 5.97 | M57: 5.34 | N57: 6.5 | O57: 5.81 | P57: 6.27 | Q57: 6.73 | R57: 9 | S57: 12.97 | T57: 8.7425 | U57: 8.98 | V57: 6.79 | W57: 6.58 | X57: 6.57 | Y57: 7.23 | Z57: 6.77 | AA57: 7.55 | AB57: 6.16 | AC57: 6.95 | AD57: 6.8575 | AE57: 8.11 | AF57: 10 | AG57: 8 | AH57: 6 | AI57: 8.0275 | AJ57: 6 | AK57: 4 | AL57: 4 | AM57: 5 | AN57: 4.75 | AO57: 4.8 | AP57: 4.2 | AQ57: 4.5 | AR57: 3 | AS57: =AVERAGE(AO57:AR57) -> 4.125 | AT57: 4.3 | AU57: 4.3 | AV57: 4 | AW57: 3.5 | AX57: =AVERAGE(AT57:AW57) -> 4.025 | AY57: 3.5 | AZ57: 2.89 | BA57: 3.89 | BB57: 3.55 | BC57: =AVERAGE(AY57:BB57) -> 3.4575 | BD57: 3.5 | BE57: 3.5 | BF57: 3.5 | BG57: 3.5 | BH57: =AVERAGE(BD57:BG57) -> 3.5 | BI57: 6 | BJ57: 4 | BK57: 4 | BL57: 4 | BM57: =AVERAGE(BI57:BL57) -> 4.5 | BN57: 3.5 | BO57: 3 | BP57: 2.75 | BQ57: 2.11 | BR57: =AVERAGE(BN57:BQ57) -> 2.84 | BS57: 2.3 | BT57: 2.4 | BU57: 2.8 | BV57: 3.1 | BW57: =AVERAGE(BS57:BV57) -> 2.65 | BX57: 3 | BY57: 3 | BZ57: 3 | CA57: 3 | CB57: =AVERAGE(BX57:CA57) -> 3 | CC57: 3 | CD57: 3 | CE57: 3 | CF57: 3 | CG57: =AVERAGE(CC57:CF57) -> 3 | CH57: 3 | CI57: 3 | CJ57: 3 | CK57: 3 | CL57: =AVERAGE(CH57:CK57) -> 3 | CM57: 3 | CN57: 3 | CO57: 3 | CP57: 3 | CQ57: =AVERAGE(CM57:CP57) -> 3
B58: Iron Ore (delivered) | F58: =G58 -> 26.931126 | G58: =H58 -> 26.931126 | H58: =I58 -> 26.931126 | I58: =J58 -> 26.931126 | J58: 26.931126 | K58: =L58 -> 37.451472 | L58: =M58 -> 37.451472 | M58: =N58 -> 37.451472 | N58: =O58 -> 37.451472 | O58: 37.451472 | P58: =Q58 -> 42.710846 | Q58: =R58 -> 42.710846 | R58: =S58 -> 42.710846 | S58: =T58 -> 42.710846 | T58: 42.710846 | U58: =V58 -> 47.271846 | V58: =W58 -> 47.271846 | W58: =X58 -> 47.271846 | X58: =Y58 -> 47.271846 | Y58: 47.271846 | Z58: =AA58 -> 47.920037 | AA58: =AB58 -> 47.920037 | AB58: =AC58 -> 47.920037 | AC58: =AD58 -> 47.920037 | AD58: 47.920037 | AE58: =AF58 -> 55 | AF58: =AG58 -> 55 | AG58: =AH58 -> 55 | AH58: =AI58 -> 55 | AI58: =40+15 -> 55 | AJ58: =AK58 -> 60 | AK58: =AL58 -> 60 | AL58: =AM58 -> 60 | AM58: =AN58 -> 60 | AN58: =45+15 -> 60 | AO58: =AP58 -> 60.6 | AP58: =AQ58 -> 60.6 | AQ58: =AR58 -> 60.6 | AR58: =AS58 -> 60.6 | AS58: =AN58*1.01 -> 60.6 | AT58: =AU58 -> 61.206 | AU58: =AV58 -> 61.206 | AV58: =AW58 -> 61.206 | AW58: =AX58 -> 61.206 | AX58: =AS58*1.01 -> 61.206 | AY58: =AZ58 -> 61.81806 | AZ58: =BA58 -> 61.81806 | BA58: =BB58 -> 61.81806 | BB58: =BC58 -> 61.81806 | BC58: =AX58*1.01 -> 61.81806 | BD58: =BE58 -> 62.436241 | BE58: =BF58 -> 62.436241 | BF58: =BG58 -> 62.436241 | BG58: =BH58 -> 62.436241 | BH58: =BC58*1.01 -> 62.436241 | BI58: =BJ58 -> 63.060603 | BJ58: =BK58 -> 63.060603 | BK58: =BL58 -> 63.060603 | BL58: =BM58 -> 63.060603 | BM58: =BH58*1.01 -> 63.060603 | BN58: =BO58 -> 63.691209 | BO58: =BP58 -> 63.691209 | BP58: =BQ58 -> 63.691209 | BQ58: =BR58 -> 63.691209 | BR58: =BM58*1.01 -> 63.691209 | BS58: =BT58 -> 64.328121 | BT58: =BU58 -> 64.328121 | BU58: =BV58 -> 64.328121 | BV58: =BW58 -> 64.328121 | BW58: =BR58*1.01 -> 64.328121 | BX58: =BY58 -> 64.971402 | BY58: =BZ58 -> 64.971402 | BZ58: =CA58 -> 64.971402 | CA58: =CB58 -> 64.971402 | CB58: =BW58*1.01 -> 64.971402 | CC58: =CD58 -> 65.621116 | CD58: =CE58 -> 65.621116 | CE58: =CF58 -> 65.621116 | CF58: =CG58 -> 65.621116 | CG58: =CB58*1.01 -> 65.621116 | CH58: =CI58 -> 66.277328 | CI58: =CJ58 -> 66.277328 | CJ58: =CK58 -> 66.277328 | CK58: =CL58 -> 66.277328 | CL58: =CG58*1.01 -> 66.277328 | CM58: =CN58 -> 66 | CN58: =CO58 -> 66 | CO58: =CP58 -> 66 | CP58: =CQ58 -> 66 | CQ58: 66
B60: Iron Ore (delivered) | F60: 123 | G60: =AVERAGE(F58:G58) -> 26.931126 | H60: =AVERAGE(G58:H58) -> 26.931126 | I60: =AVERAGE(H58:I58) -> 26.931126 | J60: =AVERAGE(F60:I60) -> 50.948345 | K60: =AVERAGE(I58,K58) -> 32.191299 | L60: =AVERAGE(K58,L58) -> 37.451472 | M60: =AVERAGE(L58,M58) -> 37.451472 | N60: =AVERAGE(M58,N58) -> 37.451472 | O60: =AVERAGE(K60:N60) -> 36.136429 | P60: =AVERAGE(N58,P58) -> 40.081159 | Q60: =AVERAGE(P58,Q58) -> 42.710846 | R60: =AVERAGE(Q58,R58) -> 42.710846 | S60: =AVERAGE(R58,S58) -> 42.710846 | T60: =AVERAGE(P60:S60) -> 42.053424 | U60: =AVERAGE(S58,U58) -> 44.991346 | V60: =AVERAGE(U58,V58) -> 47.271846 | W60: =AVERAGE(V58,W58) -> 47.271846 | X60: =AVERAGE(W58,X58) -> 47.271846 | Y60: =AVERAGE(U60:X60) -> 46.701721 | Z60: =AVERAGE(X58,Z58) -> 47.595941 | AA60: =AVERAGE(Z58,AA58) -> 47.920037 | AB60: =AVERAGE(AA58,AB58) -> 47.920037 | AC60: =AVERAGE(AB58,AC58) -> 47.920037 | AD60: =AVERAGE(Z60:AC60) -> 47.839013 | AE60: =AVERAGE(AC58,AE58) -> 51.460018 | AF60: =AVERAGE(AE58,AF58) -> 55 | AG60: =AVERAGE(AF58,AG58) -> 55 | AH60: =AVERAGE(AG58,AH58) -> 55 | AI60: =AVERAGE(AE60:AH60) -> 54.115005 | AJ60: =AVERAGE(AH58,AJ58) -> 57.5 | AK60: =AVERAGE(AJ58,AK58) -> 60 | AL60: =AVERAGE(AK58,AL58) -> 60 | AM60: =AVERAGE(AL58,AM58) -> 60 | AN60: =AVERAGE(AJ60:AM60) -> 59.375 | AO60: =AVERAGE(AM58,AO58) -> 60.3 | AP60: =AVERAGE(AO58,AP58) -> 60.6 | AQ60: =AVERAGE(AP58,AQ58) -> 60.6 | AR60: =AVERAGE(AQ58,AR58) -> 60.6 | AS60: =AVERAGE(AO60:AR60) -> 60.525 | AT60: =AVERAGE(AR58,AT58) -> 60.903 | AU60: =AVERAGE(AT58,AU58) -> 61.206 | AV60: =AVERAGE(AU58,AV58) -> 61.206 | AW60: =AVERAGE(AV58,AW58) -> 61.206 | AX60: =AVERAGE(AT60:AW60) -> 61.13025 | AY60: =AVERAGE(AW58,AY58) -> 61.51203 | AZ60: =AVERAGE(AY58,AZ58) -> 61.81806 | BA60: =AVERAGE(AZ58,BA58) -> 61.81806 | BB60: =AVERAGE(BA58,BB58) -> 61.81806 | BC60: =AVERAGE(AY60:BB60) -> 61.741553 | BD60: =AVERAGE(BB58,BD58) -> 62.12715 | BE60: =AVERAGE(BD58,BE58) -> 62.436241 | BF60: =AVERAGE(BE58,BF58) -> 62.436241 | BG60: =AVERAGE(BF58,BG58) -> 62.436241 | BH60: =AVERAGE(BD60:BG60) -> 62.358968 | BI60: =AVERAGE(BG58,BI58) -> 62.748422 | BJ60: =AVERAGE(BI58,BJ58) -> 63.060603 | BK60: =AVERAGE(BJ58,BK58) -> 63.060603 | BL60: =AVERAGE(BK58,BL58) -> 63.060603 | BM60: =AVERAGE(BI60:BL60) -> 62.982558 | BN60: =AVERAGE(BL58,BN58) -> 63.375906 | BO60: =AVERAGE(BN58,BO58) -> 63.691209 | BP60: =AVERAGE(BO58,BP58) -> 63.691209 | BQ60: =AVERAGE(BP58,BQ58) -> 63.691209 | BR60: =AVERAGE(BN60:BQ60) -> 63.612383 | BS60: =AVERAGE(BQ58,BS58) -> 64.009665 | BT60: =AVERAGE(BS58,BT58) -> 64.328121 | BU60: =AVERAGE(BT58,BU58) -> 64.328121 | BV60: =AVERAGE(BU58,BV58) -> 64.328121 | BW60: =AVERAGE(BS60:BV60) -> 64.248507 | BX60: =AVERAGE(BV58,BX58) -> 64.649762 | BY60: =AVERAGE(BX58,BY58) -> 64.971402 | BZ60: =AVERAGE(BY58,BZ58) -> 64.971402 | CA60: =AVERAGE(BZ58,CA58) -> 64.971402 | CB60: =AVERAGE(BX60:CA60) -> 64.890992 | CC60: =AVERAGE(CA58,CC58) -> 65.296259 | CD60: =AVERAGE(CC58,CD58) -> 65.621116 | CE60: =AVERAGE(CD58,CE58) -> 65.621116 | CF60: =AVERAGE(CE58,CF58) -> 65.621116 | CG60: =AVERAGE(CC60:CF60) -> 65.539902 | CH60: =AVERAGE(CF58,CH58) -> 65.949222 | CI60: =AVERAGE(CH58,CI58) -> 66.277328 | CJ60: =AVERAGE(CI58,CJ58) -> 66.277328 | CK60: =AVERAGE(CJ58,CK58) -> 66.277328 | CL60: =AVERAGE(CH60:CK60) -> 66.195301 | CM60: =AVERAGE(CK58,CM58) -> 66.138664 | CN60: =AVERAGE(CM58,CN58) -> 66 | CO60: =AVERAGE(CN58,CO58) -> 66 | CP60: =AVERAGE(CO58,CP58) -> 66 | CQ60: =AVERAGE(CM60:CP60) -> 66.034666
B61: Coking Coal | Z61: =AVERAGE(X54,Z54) -> 110 | AA61: =AVERAGE(Z54,AA54) -> 110 | AB61: =AVERAGE(AA54,AB54) -> 110 | AC61: =AVERAGE(AB54,AC54) -> 110 | AD61: =AVERAGE(Z61:AC61) -> 110 | AE61: =AVERAGE(AC54,AE54) -> 120 | AF61: =AVERAGE(AE54,AF54) -> 130 | AG61: =AVERAGE(AF54,AG54) -> 130 | AH61: =AVERAGE(AG54,AH54) -> 130 | AI61: =AVERAGE(AE61:AH61) -> 127.5 | AJ61: =AVERAGE(AH54,AJ54) -> 136.62 | AK61: =AVERAGE(AJ54,AK54) -> 149.4 | AL61: =AVERAGE(AK54,AL54) -> 158.495 | AM61: =AVERAGE(AL54,AM54) -> 153.91 | AN61: =AVERAGE(AJ61:AM61) -> 149.60625 | AO61: =AVERAGE(AM54,AO54) -> 149.5 | AP61: =AVERAGE(AO54,AP54) -> 150.74 | AQ61: =AVERAGE(AP54,AQ54) -> 149.435 | AR61: =AVERAGE(AQ54,AR54) -> 175 | AS61: =AVERAGE(AO61:AR61) -> 156.16875 | AT61: =AVERAGE(AR54,AT54) -> 186.4 | AU61: =AVERAGE(AT54,AU54) -> 183.655 | AV61: =AVERAGE(AU54,AV54) -> 194.105 | AW61: =AVERAGE(AV54,AW54) -> 199.45 | AX61: =AVERAGE(AT61:AW61) -> 190.9025 | AY61: =AVERAGE(AW54,AY54) -> 197.1 | AZ61: =AVERAGE(AY54,AZ54) -> 189 | BA61: =AVERAGE(AZ54,BA54) -> 189 | BB61: =AVERAGE(BA54,BB54) -> 189 | BC61: =AVERAGE(AY61:BB61) -> 191.025 | BD61: =BB54*0.67+BD54*0.33 -> 174.48 | BE61: =AVERAGE(BD54,BE54) -> 145 | BF61: =AVERAGE(BE54,BF54) -> 145 | BG61: =AVERAGE(BF54,BG54) -> 145 | BH61: =AVERAGE(BD61:BG61) -> 152.37 | BI61: =BG61 -> 145 | BJ61: =AVERAGE(BI54,BJ54) -> 133 | BK61: =AVERAGE(BJ54,BK54) -> 133 | BL61: =AVERAGE(BK54,BL54) -> 133 | BM61: =AVERAGE(BI61:BL61) -> 136 | BN61: =BL54*0.67+BN54*0.33 -> 125.41 | BO61: =AVERAGE(BN54,BO54) -> 110 | BP61: =AVERAGE(BO54,BP54) -> 110 | BQ61: =AVERAGE(BP54,BQ54) -> 110 | BR61: =AVERAGE(BN61:BQ61) -> 113.8525 | BS61: =BQ54*0.67+BS54*0.33 -> 111.65 | BT61: =AVERAGE(BS54,BT54) -> 115 | BU61: =AVERAGE(BT54,BU54) -> 115 | BV61: =AVERAGE(BU54,BV54) -> 115 | BW61: =AVERAGE(BS61:BV61) -> 114.1625 | BX61: =AVERAGE(BV54,BX54) -> 124.5 | BY61: =AVERAGE(BX54,BY54) -> 134 | BZ61: =AVERAGE(BY54,BZ54) -> 134 | CA61: =AVERAGE(BZ54,CA54) -> 134 | CB61: =AVERAGE(BX61:CA61) -> 131.625 | CC61: =CA54*0.67+CC54*0.33 -> 137.63 | CD61: =CC54*0.67+CD54*0.33 -> 145 | CE61: =CD54*0.67+CE54*0.33 -> 145 | CF61: =CE54*0.67+CF54*0.33 -> 145 | CG61: =AVERAGE(CC61:CF61) -> 143.1575 | CH61: =CF54*0.67+CH54*0.33 -> 141.7 | CI61: =CH54*0.67+CI54*0.33 -> 135 | CJ61: =CI54*0.67+CJ54*0.33 -> 135 | CK61: =CJ54*0.67+CK54*0.33 -> 135 | CL61: =AVERAGE(CH61:CK61) -> 136.675 | CM61: =CK54*0.67+CM54*0.33 -> 135 | CN61: =CM54*0.67+CN54*0.33 -> 135 | CO61: =CN54*0.67+CO54*0.33 -> 135 | CP61: =CO54*0.67+CP54*0.33 -> 135 | CQ61: =AVERAGE(CM61:CP61) -> 135
B62: Coke | F62: 123 | G62: =AVERAGE(F63:G63) -> 124.17833 | H62: =AVERAGE(G63:H63) -> 128.73833 | I62: =AVERAGE(H63:I63) -> 140.83333 | J62: =AVERAGE(F62:I62) -> 129.1875 | K62: =AVERAGE(K63,I63) -> 176.42167 | L62: =AVERAGE(K63:L63) -> 213.14 | M62: =AVERAGE(L63:M63) -> 228.22917 | N62: =AVERAGE(M63:N63) -> 254.8625 | O62: =AVERAGE(K62:N62) -> 218.16333 | P62: =AVERAGE(P63,N63) -> 271.47333 | Q62: =AVERAGE(P63:Q63) -> 245.90417 | R62: =AVERAGE(Q63:R63) -> 218.71667 | S62: =AVERAGE(R63:S63) -> 223.095 | T62: =AVERAGE(P62:S62) -> 239.79729 | U62: =AVERAGE(U63,S63) -> 239.09 | V62: =AVERAGE(U63:V63) -> 249.52167 | W62: =AVERAGE(V63:W63) -> 257.8475 | X62: =AVERAGE(W63:X63) -> 251.17333 | Y62: =AVERAGE(U62:X62) -> 249.40812 | Z62: =AVERAGE(Z63,X63) -> 252.81917 | AA62: =AVERAGE(Z63:AA63) -> 278.63833 | AB62: =AVERAGE(AA63:AB63) -> 287.76667 | AC62: =AVERAGE(AB63:AC63) -> 284.82333 | AD62: =AVERAGE(Z62:AC62) -> 276.01187 | AE62: =AVERAGE(AE63,AC63) -> 315.5525 | AF62: =AVERAGE(AE63:AF63) -> 406.92167 | AG62: =AVERAGE(AF63:AG63) -> 500.16667 | AH62: =AVERAGE(AG63:AH63) -> 442.07417 | AI62: =AVERAGE(AE62:AH62) -> 416.17875 | AJ62: =AVERAGE(AJ63,AH63) -> 278.60333 | AK62: =AVERAGE(AJ63:AK63) -> 203.05417 | AL62: =AVERAGE(AK63:AL63) -> 216.62333 | AM62: =AVERAGE(AL63:AM63) -> 249.13333 | AN62: =AVERAGE(AJ62:AM62) -> 236.85354 | AO62: =AVERAGE(AO63,AM63) -> 289.8875 | AP62: =AVERAGE(AO63:AP63) -> 337.96 | AQ62: =AVERAGE(AP63:AQ63) -> 359.0275 | AR62: =AVERAGE(AQ63:AR63) -> 353.95583 | AS62: =AVERAGE(AO62:AR62) -> 335.20771 | AT62: =AVERAGE(AT63,AR63) -> 382.79917 | AU62: =AVERAGE(AT63:AU63) -> 431.95583 | AV62: =AVERAGE(AU63:AV63) -> 450.31083 | AW62: =AVERAGE(AV63:AW63) -> 444.31583 | AX62: =AVERAGE(AT62:AW62) -> 427.34542 | AY62: =AVERAGE(AY63,AW63) -> 439.81 | AZ62: =AVERAGE(AY63:AZ63) -> 435.92417 | BA62: =AVERAGE(AZ63:BA63) -> 413.21833 | BB62: =AVERAGE(BA63:BB63) -> 382.89917 | BC62: =AVERAGE(AY62:BB62) -> 417.96292 | BD62: =AVERAGE(BD63,BB63) -> 375.61333 | BE62: =AVERAGE(BD63:BE63) -> 381.08583 | BF62: =AVERAGE(BE63:BF63) -> 376.6025 | BG62: =AVERAGE(BF63:BG63) -> 373.01417 | BH62: =AVERAGE(BD62:BG62) -> 376.57896 | BI62: =AVERAGE(BI63,BG63) -> 386.74583 | BJ62: =AVERAGE(BI63:BJ63) -> 398.11333 | BK62: =AVERAGE(BJ63:BK63) -> 388.48583 | BL62: =AVERAGE(BK63:BL63) -> 367.62833 | BM62: =AVERAGE(BI62:BL62) -> 385.24333 | BN62: =AVERAGE(BN63,BL63) -> 332.14917 | BO62: =AVERAGE(BN63:BO63) -> 285.685 | BP62: =AVERAGE(BO63:BP63) -> 255.01083 | BQ62: =AVERAGE(BP63:BQ63) -> 227.305 | BR62: =AVERAGE(BN62:BQ62) -> 275.0375 | BS62: =AVERAGE(BS63,BQ63) -> 195.505 | BT62: =AVERAGE(BS63:BT63) -> 205.24917 | BU62: =AVERAGE(BT63:BU63) -> 237.6775 | BV62: =AVERAGE(BU63:BV63) -> 239.57583 | BW62: =AVERAGE(BS62:BV62) -> 219.50188 | BX62: =AVERAGE(BX63,BV63) -> 247.87 | BY62: =AVERAGE(BX63:BY63) -> 280.69083 | BZ62: =AVERAGE(BY63:BZ63) -> 293.79 | CA62: =AVERAGE(BZ63:CA63) -> 285.81583 | CB62: =AVERAGE(BX62:CA62) -> 277.04167 | CC62: =AVERAGE(CC63,CA63) -> 291.80833 | CD62: =AVERAGE(CC63:CD63) -> 328.21083 | CE62: =AVERAGE(CD63:CE63) -> 360.62833 | CF62: =AVERAGE(CE63:CF63) -> 360 | CG62: =AVERAGE(CC62:CF62) -> 335.16188 | CH62: =AVERAGE(CH63,CF63) -> 351.25 | CI62: =AVERAGE(CH63:CI63) -> 353.75 | CJ62: =AVERAGE(CI63:CJ63) -> 356.25 | CK62: =AVERAGE(CJ63:CK63) -> 348.75 | CL62: =AVERAGE(CH62:CK62) -> 352.5 | CM62: =AVERAGE(CM63,CK63) -> 331.25 | CN62: =AVERAGE(CM63:CN63) -> 313.75 | CO62: =AVERAGE(CN63:CO63) -> 306.25 | CP62: =AVERAGE(CO63:CP63) -> 298.75 | CQ62: =AVERAGE(CM62:CP62) -> 312.5
B63: Scrap ($/gross ton) | F63: 123 | G63: =AVERAGE(F56:G56) -> 125.35667 | H63: =AVERAGE(G56:H56) -> 132.12 | I63: =AVERAGE(H56:I56) -> 149.54667 | J63: =AVERAGE(F63:I63) -> 132.50583 | K63: =AVERAGE(I56,K56) -> 203.29667 | L63: =AVERAGE(K56,L56) -> 222.98333 | M63: =AVERAGE(L56,M56) -> 233.475 | N63: =AVERAGE(M56,N56) -> 276.25 | O63: =AVERAGE(K63:N63) -> 234.00125 | P63: =AVERAGE(N56,P56) -> 266.69667 | Q63: =AVERAGE(P56,Q56) -> 225.11167 | R63: =AVERAGE(Q56,R56) -> 212.32167 | S63: =AVERAGE(R56,S56) -> 233.86833 | T63: =AVERAGE(P63:S63) -> 234.49958 | U63: =AVERAGE(S56,U56) -> 244.31167 | V63: =AVERAGE(U56,V56) -> 254.73167 | W63: =AVERAGE(V56,W56) -> 260.96333 | X63: =AVERAGE(W56,X56) -> 241.38333 | Y63: =AVERAGE(U63:X63) -> 250.3475 | Z63: =AVERAGE(X56,Z56) -> 264.255 | AA63: =AVERAGE(Z56,AA56) -> 293.02167 | AB63: =AVERAGE(AA56,AB56) -> 282.51167 | AC63: =AVERAGE(AB56,AC56) -> 287.135 | AD63: =AVERAGE(Z63:AC63) -> 281.73083 | AE63: =AVERAGE(AC56,AE56) -> 343.97 | AF63: =AVERAGE(AE56,AF56) -> 469.87333 | AG63: =AVERAGE(AF56,AG56) -> 530.46 | AH63: =AVERAGE(AG56,AH56) -> 353.68833 | AI63: =AVERAGE(AE63:AH63) -> 424.49792 | AJ63: =AVERAGE(AH56,AJ56) -> 203.51833 | AK63: =AVERAGE(AJ56,AK56) -> 202.59 | AL63: =AVERAGE(AK56,AL56) -> 230.65667 | AM63: =AVERAGE(AL56,AM56) -> 267.61 | AN63: =AVERAGE(AJ63:AM63) -> 226.09375 | AO63: =AVERAGE(AM56,AO56) -> 312.165 | AP63: =AVERAGE(AO56,AP56) -> 363.755 | AQ63: =AVERAGE(AP56,AQ56) -> 354.3 | AR63: =AVERAGE(AQ56,AR56) -> 353.61167 | AS63: =AVERAGE(AO63:AR63) -> 345.95792 | AT63: =AVERAGE(AR56,AT56) -> 411.98667 | AU63: =AVERAGE(AT56,AU56) -> 451.925 | AV63: =AVERAGE(AU56,AV56) -> 448.69667 | AW63: =AVERAGE(AV56,AW56) -> 439.935 | AX63: =AVERAGE(AT63:AW63) -> 438.13583 | AY63: =AVERAGE(AW56,AY56) -> 439.685 | AZ63: =AVERAGE(AY56,AZ56) -> 432.16333 | BA63: =AVERAGE(AZ56,BA56) -> 394.27333 | BB63: =AVERAGE(BA56,BB56) -> 371.525 | BC63: =AVERAGE(AY63:BB63) -> 409.41167 | BD63: =AVERAGE(BB56,BD56) -> 379.70167 | BE63: =AVERAGE(BD56,BE56) -> 382.47 | BF63: =AVERAGE(BE56,BF56) -> 370.735 | BG63: =AVERAGE(BF56,BG56) -> 375.29333 | BH63: =AVERAGE(BD63:BG63) -> 377.05 | BI63: =AVERAGE(BG56,BI56) -> 398.19833 | BJ63: =AVERAGE(BI56,BJ56) -> 398.02833 | BK63: =AVERAGE(BJ56,BK56) -> 378.94333 | BL63: =AVERAGE(BK56,BL56) -> 356.31333 | BM63: =AVERAGE(BI63:BL63) -> 382.87083 | BN63: =AVERAGE(BL56,BN56) -> 307.985 | BO63: =AVERAGE(BN56,BO56) -> 263.385 | BP63: =AVERAGE(BO56,BP56) -> 246.63667 | BQ63: =AVERAGE(BP56,BQ56) -> 207.97333 | BR63: =AVERAGE(BN63:BQ63) -> 256.495 | BS63: =AVERAGE(BQ56,BS56) -> 183.03667 | BT63: =AVERAGE(BS56,BT56) -> 227.46167 | BU63: =AVERAGE(BT56,BU56) -> 247.89333 | BV63: =AVERAGE(BU56,BV56) -> 231.25833 | BW63: =AVERAGE(BS63:BV63) -> 222.4125 | BX63: =AVERAGE(BV56,BX56) -> 264.48167 | BY63: =AVERAGE(BX56,BY56) -> 296.9 | BZ63: =AVERAGE(BY56,BZ56) -> 290.68 | CA63: =AVERAGE(BZ56,CA56) -> 280.95167 | CB63: =AVERAGE(BX63:CA63) -> 283.25333 | CC63: =AVERAGE(CA56,CC56) -> 302.665 | CD63: =AVERAGE(CC56,CD56) -> 353.75667 | CE63: =AVERAGE(CD56,CE56) -> 367.5 | CF63: =AVERAGE(CE56,CF56) -> 352.5 | CG63: =AVERAGE(CC63:CF63) -> 344.10542 | CH63: =AVERAGE(CF56,CH56) -> 350 | CI63: =AVERAGE(CH56,CI56) -> 357.5 | CJ63: =AVERAGE(CI56,CJ56) -> 355 | CK63: =AVERAGE(CJ56,CK56) -> 342.5 | CL63: =AVERAGE(CH63:CK63) -> 351.25 | CM63: =AVERAGE(CK56,CM56) -> 320 | CN63: =AVERAGE(CM56,CN56) -> 307.5 | CO63: =AVERAGE(CN56,CO56) -> 305 | CP63: =AVERAGE(CO56,CP56) -> 292.5 | CQ63: =AVERAGE(CM63:CP63) -> 306.25
B64: Natural Gas ($/mcf) | K64: =Operations!K57 -> 5.43 | L64: =Operations!L57 -> 5.97 | M64: =Operations!M57 -> 5.34 | N64: =Operations!N57 -> 6.5 | O64: =Operations!O57 -> 5.81 | P64: =Operations!P57 -> 6.27 | Q64: =Operations!Q57 -> 6.73 | R64: =Operations!R57 -> 9 | ... CQ64: =Operations!CQ57 -> 3
B66: Costs Per ton of Finished Steel
C67: Iron Ore | F67: =F60*1/0.65*0.8 -> 151.38462 | G67: =G60*1/0.65*0.8 -> 33.146001 | H67: =H60*1/0.65*0.8 -> 33.146001 | I67: =I60*1/0.65*0.8 -> 33.146001 | J67: =J60*1/0.65*0.8 -> 62.705655 | K67: =K60*1/0.65*0.8 -> 39.620061 | L67: =L60*1/0.65*0.8 -> 46.09412 | M67: =M60*1/0.65*0.8 -> 46.09412 | ... CQ67: =CQ60*1/0.65*0.8 -> 81.273435
C68: Coking Coal | Z68: =Z61*0.6*0.8 -> 52.8 | AA68: =AA61*0.6*0.8 -> 52.8 | AB68: =AB61*0.6*0.8 -> 52.8 | AC68: =AC61*0.6*0.8 -> 52.8 | AD68: =AD61*0.56*0.8 -> 49.28 | AE68: =AE61*0.6*0.8 -> 57.6 | AF68: =AF61*0.6*0.8 -> 62.4 | AG68: =AG61*0.6*0.8 -> 62.4 | AH68: =AH61*0.6*0.8 -> 62.4 | AI68: =AI61*0.56*0.8 -> 57.12 | AJ68: =AJ61*0.6*0.8 -> 65.5776 | AK68: =AK61*0.6*0.8 -> 71.712 | AL68: =AL61*0.6*0.8 -> 76.0776 | AM68: =AM61*0.6*0.8 -> 73.8768 | AN68: =AN61*0.56*0.8 -> 67.0236 | AO68: =AO61*0.6*0.8 -> 71.76 | AP68: =AP61*0.6*0.8 -> 72.3552 | AQ68: =AQ61*0.6*0.8 -> 71.7288 | AR68: =AR61*0.6*0.8 -> 84 | AS68: =AS61*0.56*0.8 -> 69.9636 | AT68: =AT61*0.6*0.8 -> 89.472 | AU68: =AU61*0.6*0.8 -> 88.1544 | AV68: =AV61*0.6*0.8 -> 93.1704 | AW68: =AW61*0.6*0.8 -> 95.736 | AX68: =AX61*0.56*0.8 -> 85.52432 | AY68: =AY61*0.6*0.8 -> 94.608 | AZ68: =AZ61*0.6*0.8 -> 90.72 | BA68: =BA61*0.6*0.8 -> 90.72 | BB68: =BB61*0.6*0.8 -> 90.72 | BC68: =BC61*0.56*0.8 -> 85.5792 | BD68: =BD61*0.6*0.8 -> 83.7504 | BE68: =BE61*0.6*0.8 -> 69.6 | BF68: =BF61*0.6*0.8 -> 69.6 | BG68: =BG61*0.6*0.8 -> 69.6 | BH68: =BH61*0.56*0.8 -> 68.26176 | BI68: =BI61*0.6*0.8 -> 69.6 | BJ68: =BJ61*0.6*0.8 -> 63.84 | BK68: =BK61*0.6*0.8 -> 63.84 | BL68: =BL61*0.6*0.8 -> 63.84 | BM68: =BM61*0.56*0.8 -> 60.928 | BN68: =BN61*0.6*0.8 -> 60.1968 | BO68: =BO61*0.6*0.8 -> 52.8 | BP68: =BP61*0.6*0.8 -> 52.8 | BQ68: =BQ61*0.6*0.8 -> 52.8 | BR68: =BR61*0.56*0.8 -> 51.00592 | BS68: =BS61*0.6*0.8 -> 53.592 | BT68: =BT61*0.6*0.8 -> 55.2 | BU68: =BU61*0.6*0.8 -> 55.2 | BV68: =BV61*0.6*0.8 -> 55.2 | BW68: =BW61*0.6*0.8 -> 54.798 | BX68: =BX61*0.6*0.8 -> 59.76 | BY68: =BY61*0.6*0.8 -> 64.32 | BZ68: =BZ61*0.6*0.8 -> 64.32 | CA68: =CA61*0.6*0.8 -> 64.32 | CB68: =CB61*0.56*0.8 -> 58.968 | CC68: =CC61*0.6*0.8 -> 66.0624 | CD68: =CD61*0.6*0.8 -> 69.6 | CE68: =CE61*0.6*0.8 -> 69.6 | CF68: =CF61*0.6*0.8 -> 69.6 | CG68: =CG61*0.56*0.8 -> 64.13456 | CH68: =CH61*0.6*0.8 -> 68.016 | CI68: =CI61*0.6*0.8 -> 64.8 | CJ68: =CJ61*0.6*0.8 -> 64.8 | CK68: =CK61*0.6*0.8 -> 64.8 | CL68: =CL61*0.56*0.8 -> 61.2304 | CM68: =CM61*0.6*0.8 -> 64.8 | CN68: =CN61*0.6*0.8 -> 64.8 | CO68: =CO61*0.6*0.8 -> 64.8 | CP68: =CP61*0.6*0.8 -> 64.8 | CQ68: =CQ61*0.56*0.8 -> 60.48
C69: Coke | F69: =F62*0.4*0.2 -> 9.84 | G69: =G62*0.4*0.2 -> 9.9342667 | H69: =H62*0.4*0.2 -> 10.299067 | I69: =I62*0.4*0.2 -> 11.266667 | J69: =J62*0.4*0.2 -> 10.335 | K69: =K62*0.4*0.2 -> 14.113733 | L69: =L62*0.4*0.2 -> 17.0512 | M69: =M62*0.4*0.2 -> 18.258333 | ... CQ69: =CQ62*0.4*0.2 -> 25
C70: Scrap ($/gross ton) | K70: =K63*0.2 -> 40.659333 | L70: =L63*0.2 -> 44.596667 | M70: =M63*0.2 -> 46.695 | N70: =N63*0.2 -> 55.25 | O70: =O63*0.2 -> 46.80025 | P70: =P63*0.2 -> 53.339333 | Q70: =Q63*0.2 -> 45.022333 | R70: =R63*0.2 -> 42.464333 | ... CQ70: =CQ63*0.2 -> 61.25
C71: Natural Gas ($/mcf) | K71: =K64*4.5 -> 24.435 | L71: =L64*4.5 -> 26.865 | M71: =M64*4.5 -> 24.03 | N71: =N64*4.5 -> 29.25 | O71: =O64*4.5 -> 26.145 | P71: =P64*4.5 -> 28.215 | Q71: =Q64*4.5 -> 30.285 | R71: =R64*4.5 -> 40.5 | ... AT71: =AT64*4.5 -> 19.35 | AU71: =AU64*5 -> 21.5 | AV71: =AV64*5.5 -> 22 | AW71: =AW64*6 -> 21 | AX71: =AX64*4.5 -> 18.1125 | AY71: =AY64*6 -> 21 | AZ71: =AZ64*6 -> 17.34 | BA71: =BA64*6 -> 23.34 | BB71: =BB64*6 -> 21.3 | BC71: =BC64*6 -> 20.745 | BD71: =BD64*6 -> 21 | BE71: =BE64*6 -> 21 | BF71: =BF64*6 -> 21 | ... CQ71: =CQ64*6 -> 18
C73: Realized Cost per ton | D73: =+D51-D87 -> 372.50974 | E73: =+E51-E87 -> 385.35354 | F73: =+F51-F87 -> 403.14286 | G73: =+G51-G87 -> 415.47158 | H73: =+H51-H87 -> 415.94167 | I73: =+I51-I87 -> 396.1738 | J73: =+J51-J87 -> 407.49974 | K73: =+K51-K87 -> 431.74117 | ... CA73: =+CA51-CA87 -> 642.88043 | CB73: =AVERAGE(BX73:CA73) -> 653.21853 | CC73: =+CC75+CC74 -> 691.9711 | CD73: =+CD75+CD74 -> 657.17273 | CE73: =+CE75+CE74 -> 672.66626 | CF73: =+CF75+CF74 -> 713.30754 | CG73: =AVERAGE(CC73:CF73) -> 683.77941 | CH73: =+CH75+CH74 -> 752.43302 | CI73: =+CI75+CI74 -> 693.28434 | CJ73: =+CJ75+CJ74 -> 686.81399 | CK73: =+CK75+CK74 -> 683.55248 | CL73: =AVERAGE(CH73:CK73) -> 704.02096 | CM73: =+CM75+CM74 -> 690.17592 | CN73: =+CN75+CN74 -> 654.01545 | CO73: =+CO75+CO74 -> 644.1403 | CP73: =+CP75+CP74 -> 643.71709 | CQ73: =AVERAGE(CM73:CP73) -> 658.01219
C74: Other Costs | BI74: =+BI73-BI75 -> -12.328058 | BJ74: =+BJ73-BJ75 -> 33.611742 | BK74: =+BK73-BK75 -> -47.217669 | BL74: =+BL73-BL75 -> -40.548332 | BM74: =AVERAGE(BI74:BL74) -> -16.620579 | BN74: =+BN73-BN75 -> 64.533004 | BO74: =+BO73-BO75 -> -16.675383 | BP74: =+BP73-BP75 -> -17.504247 | BQ74: =+BQ73-BQ75 -> 7.7794135 | BR74: =AVERAGE(BN74:BQ74) -> 9.5331967 | BS74: =+BS73-BS75 -> 7.4124439 | BT74: =+BT73-BT75 -> -14.779502 | BU74: =+BU73-BU75 -> 10.126199 | BV74: =+BV73-BV75 -> -29.412638 | BW74: =AVERAGE(BS74:BV74) -> -6.6633743 | BX74: =+BX73-BX75 -> 79.027553 | BY74: =+BY73-BY75 -> -64.917732 | BZ74: =+BZ73-BZ75 -> -0.89555966 | CA74: =+CA73-CA75 -> -11.188608 | CB74: =AVERAGE(BX74:CA74) -> 0.5064135 | CC74: 39 | CD74: -15 | CE74: 40 | CF74: 40 | CG74: =AVERAGE(CC74:CF74) -> 26 | CH74: 60 | CI74: -10 | CJ74: 10 | CK74: 5 | CL74: =AVERAGE(CH74:CK74) -> 16.25 | CM74: =+(CM81-CK81)/CM34*1000+30 -> 11.776335 | CN74: -17 | CO74: -15 | CP74: -15 | CQ74: =AVERAGE(CM74:CP74) -> -8.8059163
C75: Calculated Costs per ton | Z75: =1.693*Z67+1.39*Z68-0.7836*Z70+3.507*Z71-215.15*(Z34/X34-1)+0.6349*X73 -> 623.77477 | AA75: =1.693*AA67+1.39*AA68-0.7836*AA70+3.507*AA71-215.15*(AA34/Z34-1)+0.6349*Z73 -> 603.93511 | AB75: =1.693*AB67+1.39*AB68-0.7836*AB70+3.507*AB71-215.15*(AB34/AA34-1)+0.6349*AA73 -> 612.49668 | AC75: =1.693*AC67+1.39*AC68-0.7836*AC70+3.507*AC71-215.15*(AC34/AB34-1)+0.6349*AB73 -> 571.993 | AD75: =AVERAGE(Z75:AC75) -> 603.04989 | AE75: =1.693*AE67+1.39*AE68-0.7836*AE70+3.507*AE71-215.15*(AE34/AC34-1)+0.6349*AC73 -> 608.44864 | AF75: =1.693*AF67+1.39*AF68-0.7836*AF70+3.507*AF71-215.15*(AF34/AE34-1)+0.6349*AE73 -> 658.36469 | AG75: =1.693*AG67+1.39*AG68-0.7836*AG70+3.507*AG71-215.15*(AG34/AF34-1)+0.6349*AF73 -> 676.44144 | AH75: =1.693*AH67+1.39*AH68-0.7836*AH70+3.507*AH71-215.15*(AH34/AG34-1)+0.6349*AG73 -> 767.00849 | AI75: =AVERAGE(AE75:AH75) -> 677.56582 | AJ75: =1.693*AJ67+1.39*AJ68-0.7836*AJ70+3.507*AJ71-215.15*(AJ34/AH34-1)+0.6349*AH73 -> 819.44914 | AK75: =1.693*AK67+1.39*AK68-0.7836*AK70+3.507*AK71-215.15*(AK34/AJ34-1)+0.6349*AJ73 -> 834.55036 | AL75: =1.693*AL67+1.39*AL68-0.7836*AL70+3.507*AL71-215.15*(AL34/AK34-1)+0.6349*AK73 -> 667.86006 | AM75: =1.693*AM67+1.39*AM68-0.7836*AM70+3.507*AM71-215.15*(AM34/AL34-1)+0.6349*AL73 -> 643.43324 | AN75: =AVERAGE(AJ75:AM75) -> 741.3232 | AO75: =1.693*AO67+1.39*AO68-0.7836*AO70+3.507*AO71-215.15*(AO34/AM34-1)+0.6349*AM73 -> 632.42815 | AP75: =1.693*AP67+1.39*AP68-0.7836*AP70+3.507*AP71-215.15*(AP34/AO34-1)+0.6349*AO73 -> 580.62524 | AQ75: =1.693*AQ67+1.39*AQ68-0.7836*AQ70+3.507*AQ71-215.15*(AQ34/AP34-1)+0.6349*AP73 -> 665.63062 | AR75: =1.693*AR67+1.39*AR68-0.7836*AR70+3.507*AR71-215.15*(AR34/AQ34-1)+0.6349*AQ73 -> 639.25656 | AS75: =AVERAGE(AO75:AR75) -> 629.48514 | AT75: =1.693*AT67+1.39*AT68-0.7836*AT70+3.507*AT71-215.15*(AT34/AR34-1)+0.6349*AR73 -> 633.68712 | AU75: =1.693*AU67+1.39*AU68-0.7836*AU70+3.507*AU71-215.15*(AU34/AT34-1)+0.6349*AT73 -> 699.26333 | AV75: =1.693*AV67+1.39*AV68-0.7836*AV70+3.507*AV71-215.15*(AV34/AU34-1)+0.6349*AU73 -> 699.53605 | AW75: =1.693*AW67+1.39*AW68-0.7836*AW70+3.507*AW71-215.15*(AW34/AV34-1)+0.6349*AV73 -> 705.30725 | AX75: =AVERAGE(AT75:AW75) -> 684.44844 | AY75: =1.693*AY67+1.39*AY68-0.7836*AY70+3.507*AY71-215.15*(AY34/AW34-1)+0.6349*AW73 -> 708.64068 | AZ75: =1.693*AZ67+1.39*AZ68-0.7836*AZ70+3.507*AZ71-215.15*(AZ34/AY34-1)+0.6349*AY73 -> 691.77301 | BA75: =1.693*BA67+1.39*BA68-0.7836*BA70+3.507*BA71-215.15*(BA34/AZ34-1)+0.6349*AZ73 -> 718.24649 | BB75: =1.693*BB67+1.39*BB68-0.7836*BB70+3.507*BB71-215.15*(BB34/BA34-1)+0.6349*BA73 -> 720.30879 | BC75: =AVERAGE(AY75:BB75) -> 709.74224 | BD75: =1.693*BD67+1.39*BD68-0.7836*BD70+3.507*BD71-215.15*(BD34/BB34-1)+0.6349*BB73 -> 689.96414 | BE75: =1.693*BE67+1.39*BE68-0.7836*BE70+3.507*BE71-215.15*(BE34/BD34-1)+0.6349*BD73 -> 694.2402 | BF75: =1.693*BF67+1.39*BF68-0.7836*BF70+3.507*BF71-215.15*(BF34/BE34-1)+0.6349*BE73 -> 706.88985 | BG75: =1.693*BG67+1.39*BG68-0.7836*BG70+3.507*BG71-215.15*(BG34/BF34-1)+0.6349*BF73 -> 676.84677 | BH75: =AVERAGE(BD75:BG75) -> 691.98524 | BI75: =1.693*BI67+1.39*BI68-0.7836*BI70+3.507*BI71-215.15*(BI34/BG34-1)+0.6349*BG73 -> 716.44183 | BJ75: =1.693*BJ67+1.39*BJ68-0.7836*BJ70+3.507*BJ71-215.15*(BJ34/BI34-1)+0.6349*BI73 -> 697.57567 | BK75: =1.693*BK67+1.39*BK68-0.7836*BK70+3.507*BK71-215.15*(BK34/BJ34-1)+0.6349*BJ73 -> 699.08224 | BL75: =1.693*BL67+1.39*BL68-0.7836*BL70+3.507*BL71-215.15*(BL34/BK34-1)+0.6349*BK73 -> 701.78382 | BM75: =AVERAGE(BI75:BL75) -> 703.72089 | BN75: =1.693*BN67+1.39*BN68-0.7836*BN70+3.507*BN71-215.15*(BN34/BL34-1)+0.6349*BL73 -> 689.32867 | BO75: =1.693*BO67+1.39*BO68-0.7836*BO70+3.507*BO71-215.15*(BO34/BN34-1)+0.6349*BN73 -> 698.76978 | BP75: =1.693*BP67+1.39*BP68-0.7836*BP70+3.507*BP71-215.15*(BP34/BO34-1)+0.6349*BO73 -> 661.23519 | BQ75: =1.693*BQ67+1.39*BQ68-0.7836*BQ70+3.507*BQ71-215.15*(BQ34/BP34-1)+0.6349*BP73 -> 633.44868 | BR75: =AVERAGE(BN75:BQ75) -> 670.69558 | BS75: =1.693*BS67+1.39*BS68-0.7836*BS70+3.507*BS71-215.15*(BS34/BQ34-1)+0.6349*BQ73 -> 642.41862 | BT75: =1.693*BT67+1.39*BT68-0.7836*BT70+3.507*BT71-215.15*(BT34/BS34-1)+0.6349*BS73 -> 621.48975 | BU75: =1.693*BU67+1.39*BU68-0.7836*BU70+3.507*BU71-215.15*(BU34/BT34-1)+0.6349*BT73 -> 628.58386 | BV75: =1.693*BV67+1.39*BV68-0.7836*BV70+3.507*BV71-215.15*(BV34/BU34-1)+0.6349*BU73 -> 659.36114 | BW75: =AVERAGE(BS75:BV75) -> 637.96334 | BX75: =1.693*BX67+1.39*BX68-0.7836*BX70+3.507*BX71-215.15*(BX34/BV34-1)+0.6349*BV73 -> 636.22869 | BY75: =1.693*BY67+1.39*BY68-0.7836*BY70+3.507*BY71-215.15*(BY34/BX34-1)+0.6349*BX73 -> 687.17404 | BZ75: =1.693*BZ67+1.39*BZ68-0.7836*BZ70+3.507*BZ71-215.15*(BZ34/BY34-1)+0.6349*BY73 -> 633.37669 | CA75: =1.693*CA67+1.39*CA68-0.7836*CA70+3.507*CA71-215.15*(CA34/BZ34-1)+0.6349*BZ73 -> 654.06903 | CB75: =AVERAGE(BX75:CA75) -> 652.71211 | CC75: =1.693*CC67+1.39*CC68-0.7836*CC70+3.507*CC71-215.15*(CC34/CA34-1)+0.6349*CA73 -> 652.9711 | CD75: =1.693*CD67+1.39*CD68-0.7836*CD70+3.507*CD71-215.15*(CD34/CC34-1)+0.6349*CC73 -> 672.17273 | CE75: =1.693*CE67+1.39*CE68-0.7836*CE70+3.507*CE71-215.15*(CE34/CD34-1)+0.6349*CD73 -> 632.66626 | CF75: =1.693*CF67+1.39*CF68-0.7836*CF70+3.507*CF71-215.15*(CF34/CE34-1)+0.6349*CE73 -> 673.30754 | CG75: =AVERAGE(CC75:CF75) -> 657.77941 | CH75: =1.693*CH67+1.39*CH68-0.7836*CH70+3.507*CH71-215.15*(CH34/CF34-1)+0.6349*CF73 -> 692.43302 | CI75: =1.693*CI67+1.39*CI68-0.7836*CI70+3.507*CI71-215.15*(CI34/CH34-1)+0.6349*CH73 -> 703.28434 | CJ75: =1.693*CJ67+1.39*CJ68-0.7836*CJ70+3.507*CJ71-215.15*(CJ34/CI34-1)+0.6349*CI73 -> 676.81399 | CK75: =1.693*CK67+1.39*CK68-0.7836*CK70+3.507*CK71-215.15*(CK34/CJ34-1)+0.6349*CJ73 -> 678.55248 | CL75: =AVERAGE(CH75:CK75) -> 687.77096 | CM75: =1.693*CM67+1.39*CM68-0.7836*CM70+3.507*CM71-215.15*(CM34/CK34-1)+0.6349*CK73 -> 678.39959 | CN75: =1.693*CN67+1.39*CN68-0.7836*CN70+3.507*CN71-215.15*(CN34/CM34-1)+0.6349*CM73 -> 671.01545 | CO75: =1.693*CO67+1.39*CO68-0.7836*CO70+3.507*CO71-215.15*(CO34/CN34-1)+0.6349*CN73 -> 659.1403 | CP75: =1.693*CP67+1.39*CP68-0.7836*CP70+3.507*CP71-215.15*(CP34/CO34-1)+0.6349*CO73 -> 658.71709 | CQ75: =AVERAGE(CM75:CP75) -> 666.81811
C76: Calculated Costs per ton, Alternative | Z76: =2.172*Z67+1.568*Z68-0.986*Z70+3.877*Z71-219*(Z34/X34-1)+0.57257*X73 -> 623.04215 | AA76: =2.172*AA67+1.568*AA68-0.986*AA70+3.877*AA71-219*(AA34/Z34-1)+0.57257*Z73 -> 603.98071 | AB76: =2.172*AB67+1.568*AB68-0.986*AB70+3.877*AB71-219*(AB34/AA34-1)+0.57257*AA73 -> 611.02653 | AC76: =2.172*AC67+1.568*AC68-0.986*AC70+3.877*AC71-219*(AC34/AB34-1)+0.57257*AB73 -> 573.0147 | AD76: =AVERAGE(Z76:AC76) -> 602.76602 | AE76: =2.172*AE67+1.568*AE68-0.986*AE70+3.877*AE71-219*(AE34/AC34-1)+0.57257*AC73 -> 611.20196 | AF76: =2.172*AF67+1.568*AF68-0.986*AF70+3.877*AF71-219*(AF34/AE34-1)+0.57257*AE73 -> 662.13616 | AG76: =2.172*AG67+1.568*AG68-0.986*AG70+3.877*AG71-219*(AG34/AF34-1)+0.57257*AF73 -> 671.18266 | AH76: =2.172*AH67+1.568*AH68-0.986*AH70+3.877*AH71-219*(AH34/AG34-1)+0.57257*AG73 -> 764.04025 | AI76: =AVERAGE(AE76:AH76) -> 677.14026 | AJ76: =2.172*AJ67+1.568*AJ68-0.986*AJ70+3.877*AJ71-219*(AJ34/AH34-1)+0.57257*AH73 -> 819.16995 | AK76: =2.172*AK67+1.568*AK68-0.986*AK70+3.877*AK71-219*(AK34/AJ34-1)+0.57257*AJ73 -> 827.97903 | AL76: =2.172*AL67+1.568*AL68-0.986*AL70+3.877*AL71-219*(AL34/AK34-1)+0.57257*AK73 -> 661.35611 | AM76: =2.172*AM67+1.568*AM68-0.986*AM70+3.877*AM71-219*(AM34/AL34-1)+0.57257*AL73 -> 647.86985 | AN76: =AVERAGE(AJ76:AM76) -> 739.09373 | AO76: =2.172*AO67+1.568*AO68-0.986*AO70+3.877*AO71-219*(AO34/AM34-1)+0.57257*AM73 -> 635.8859 | AP76: =2.172*AP67+1.568*AP68-0.986*AP70+3.877*AP71-219*(AP34/AO34-1)+0.57257*AO73 -> 584.259 | AQ76: =2.172*AQ67+1.568*AQ68-0.986*AQ70+3.877*AQ71-219*(AQ34/AP34-1)+0.57257*AP73 -> 667.16444 | AR76: =2.172*AR67+1.568*AR68-0.986*AR70+3.877*AR71-219*(AR34/AQ34-1)+0.57257*AQ73 -> 640.636 | AS76: =AVERAGE(AO76:AR76) -> 631.98634 | AT76: =2.172*AT67+1.568*AT68-0.986*AT70+3.877*AT71-219*(AT34/AR34-1)+0.57257*AR73 -> 638.14569 | AU76: =2.172*AU67+1.568*AU68-0.986*AU70+3.877*AU71-219*(AU34/AT34-1)+0.57257*AT73 -> 697.16326 | AV76: =2.172*AV67+1.568*AV68-0.986*AV70+3.877*AV71-219*(AV34/AU34-1)+0.57257*AU73 -> 700.05115 | AW76: =2.172*AW67+1.568*AW68-0.986*AW70+3.877*AW71-219*(AW34/AV34-1)+0.57257*AV73 -> 705.52904 | AX76: =AVERAGE(AT76:AW76) -> 685.22229 | AY76: =2.172*AY67+1.568*AY68-0.986*AY70+3.877*AY71-219*(AY34/AW34-1)+0.57257*AW73 -> 706.0728 | AZ76: =2.172*AZ67+1.568*AZ68-0.986*AZ70+3.877*AZ71-219*(AZ34/AY34-1)+0.57257*AY73 -> 690.36685 | BA76: =2.172*BA67+1.568*BA68-0.986*BA70+3.877*BA71-219*(BA34/AZ34-1)+0.57257*AZ73 -> 720.08468 | BB76: =2.172*BB67+1.568*BB68-0.986*BB70+3.877*BB71-219*(BB34/BA34-1)+0.57257*BA73 -> 721.97228 | BC76: =AVERAGE(AY76:BB76) -> 709.62415 | BD76: =2.172*BD67+1.568*BD68-0.986*BD70+3.877*BD71-219*(BD34/BB34-1)+0.57257*BB73 -> 691.08938 | BE76: =2.172*BE67+1.568*BE68-0.986*BE70+3.877*BE71-219*(BE34/BD34-1)+0.57257*BD73 -> 692.98725 | BF76: =2.172*BF67+1.568*BF68-0.986*BF70+3.877*BF71-219*(BF34/BE34-1)+0.57257*BE73 -> 705.25783 | BG76: =2.172*BG67+1.568*BG68-0.986*BG70+3.877*BG71-219*(BG34/BF34-1)+0.57257*BF73 -> 675.59401 | BH76: =AVERAGE(BD76:BG76) -> 691.23212 | BI76: =2.172*BI67+1.568*BI68-0.986*BI70+3.877*BI71-219*(BI34/BG34-1)+0.57257*BG73 -> 719.82246 | BJ76: =2.172*BJ67+1.568*BJ68-0.986*BJ70+3.877*BJ71-219*(BJ34/BI34-1)+0.57257*BI73 -> 695.15028 | BK76: =2.172*BK67+1.568*BK68-0.986*BK70+3.877*BK71-219*(BK34/BJ34-1)+0.57257*BJ73 -> 695.40776 | BL76: =2.172*BL67+1.568*BL68-0.986*BL70+3.877*BL71-219*(BL34/BK34-1)+0.57257*BK73 -> 704.85568 | BM76: =AVERAGE(BI76:BL76) -> 703.80905 | BN76: =2.172*BN67+1.568*BN68-0.986*BN70+3.877*BN71-219*(BN34/BL34-1)+0.57257*BL73 -> 692.00242 | BO76: =2.172*BO67+1.568*BO68-0.986*BO70+3.877*BO71-219*(BO34/BN34-1)+0.57257*BN73 -> 694.58681 | BP76: =2.172*BP67+1.568*BP68-0.986*BP70+3.877*BP71-219*(BP34/BO34-1)+0.57257*BO73 -> 661.83932 | BQ76: =2.172*BQ67+1.568*BQ68-0.986*BQ70+3.877*BQ71-219*(BQ34/BP34-1)+0.57257*BP73 -> 636.65948 | BR76: =AVERAGE(BN76:BQ76) -> 671.27201 | BS76: =2.172*BS67+1.568*BS68-0.986*BS70+3.877*BS71-219*(BS34/BQ34-1)+0.57257*BQ73 -> 647.56127 | BT76: =2.172*BT67+1.568*BT68-0.986*BT70+3.877*BT71-219*(BT34/BS34-1)+0.57257*BS73 -> 624.55664 | BU76: =2.172*BU67+1.568*BU68-0.986*BU70+3.877*BU71-219*(BU34/BT34-1)+0.57257*BT73 -> 634.92292 | BV76: =2.172*BV67+1.568*BV68-0.986*BV70+3.877*BV71-219*(BV34/BU34-1)+0.57257*BU73 -> 665.07262 | BW76: =AVERAGE(BS76:BV76) -> 643.02836 | BX76: =2.172*BX67+1.568*BX68-0.986*BX70+3.877*BX71-219*(BX34/BV34-1)+0.57257*BV73 -> 641.6117 | BY76: =2.172*BY67+1.568*BY68-0.986*BY70+3.877*BY71-219*(BY34/BX34-1)+0.57257*BX73 -> 686.83677 | BZ76: =2.172*BZ67+1.568*BZ68-0.986*BZ70+3.877*BZ71-219*(BZ34/BY34-1)+0.57257*BY73 -> 639.16436 | CA76: =2.172*CA67+1.568*CA68-0.986*CA70+3.877*CA71-219*(CA34/BZ34-1)+0.57257*BZ73 -> 659.84003 | CB76: =AVERAGE(BX76:CA76) -> 656.86321 | CC76: =2.172*CC67+1.568*CC68-0.986*CC70+3.877*CC71-219*(CC34/CA34-1)+0.57257*CA73 -> 657.58426 | CD76: =2.172*CD67+1.568*CD68-0.986*CD70+3.877*CD71-219*(CD34/CC34-1)+0.57257*CC73 -> 672.30814 | CE76: =2.172*CE67+1.568*CE68-0.986*CE70+3.877*CE71-219*(CE34/CD34-1)+0.57257*CD73 -> 634.14126 | CF76: =2.172*CF67+1.568*CF68-0.986*CF70+3.877*CF71-219*(CF34/CE34-1)+0.57257*CE73 -> 674.9332 | CG76: =AVERAGE(CC76:CF76) -> 659.74172 | CH76: =2.172*CH67+1.568*CH68-0.986*CH70+3.877*CH71-219*(CH34/CF34-1)+0.57257*CF73 -> 691.43884 | CI76: =2.172*CI67+1.568*CI68-0.986*CI70+3.877*CI71-219*(CI34/CH34-1)+0.57257*CH73 -> 699.00732 | CJ76: =2.172*CJ67+1.568*CJ68-0.986*CJ70+3.877*CJ71-219*(CJ34/CI34-1)+0.57257*CI73 -> 676.51621 | CK76: =2.172*CK67+1.568*CK68-0.986*CK70+3.877*CK71-219*(CK34/CJ34-1)+0.57257*CJ73 -> 679.23357 | CL76: =AVERAGE(CH76:CK76) -> 686.54898 | CM76: =2.172*CM67+1.568*CM68-0.986*CM70+3.877*CM71-219*(CM34/CK34-1)+0.57257*CK73 -> 680.08941 | CN76: =2.172*CN67+1.568*CN68-0.986*CN70+3.877*CN71-219*(CN34/CM34-1)+0.57257*CM73 -> 672.47941 | CO76: =2.172*CO67+1.568*CO68-0.986*CO70+3.877*CO71-219*(CO34/CN34-1)+0.57257*CN73 -> 663.15066 | CP76: =2.172*CP67+1.568*CP68-0.986*CP70+3.877*CP71-219*(CP34/CO34-1)+0.57257*CO73 -> 663.91853 | CQ76: =AVERAGE(CM76:CP76) -> 669.9095
C78: Sustainable Changes in Cost, $/t | BN78: =(BN80+BN79)/BN34*1000 -> 92.09018 | BO78: =(BO80+BO79)/BO34*1000 -> 0 | BP78: =(BP80+BP79)/BP34*1000 -> 0 | BQ78: =(BQ80+BQ79)/BQ34*1000 -> 0 | BR78: =AVERAGE(BN78:BQ78) -> 23.022545 | BS78: =(BS80+BS79)/BS34*1000 -> -1.4011209 | BT78: =(BT80+BT79)/BT34*1000 -> 0 | BU78: =(BU80+BU79)/BU34*1000 -> 0 | BV78: =(BV80+BV79)/BV34*1000 -> 0 | BW78: =AVERAGE(BS78:BV78) -> -0.35028022 | BX78: =(BX80+BX79)/BX34*1000 -> 35.565724 | BY78: =(BY80+BY79)/BY34*1000 -> -63.275931 | BZ78: =(BZ80+BZ79)/BZ34*1000 -> -24.764151 | CA78: =(CA80+CA79)/CA34*1000 -> -48.321048 | CB78: =AVERAGE(BX78:CA78) -> -25.198852 | CC78: =(CC80+CC79)/CC34*1000 -> -1.2355645 | CD78: =(CD80+CD79)/CD34*1000 -> -6.6085904 | CE78: =(CE80+CE79)/CE34*1000 -> 0 | CF78: =(CF80+CF79)/CF34*1000 -> 0 | CG78: =AVERAGE(CC78:CF78) -> -1.9610387 | CH78: =(CH80+CH79)/CH34*1000 -> -12.14911 | CI78: =(CI80+CI79)/CI34*1000 -> 0 | CJ78: =(CJ80+CJ79)/CJ34*1000 -> 0 | CK78: =(CK80+CK79)/CK34*1000 -> 0 | CL78: =AVERAGE(CH78:CK78) -> -3.0372775 | CM78: =(CM80+CM79)/CM34*1000 -> -18.223665 | CN78: =(CN80+CN79)/CN34*1000 -> 0 | CO78: =(CO80+CO79)/CO34*1000 -> 0 | CP78: =(CP80+CP79)/CP34*1000 -> 0 | CQ78: =AVERAGE(CM78:CP78) -> -4.5559163
C79: Accounting Change, $mn | BN79: 0 | BO79: 0 | BP79: 0 | BQ79: 0 | BR79: =SUM(BN79:BQ79) -> 0 | BS79: 0 | BT79: 0 | BU79: 0 | BV79: 0 | BW79: =SUM(BS79:BV79) -> 0 | BX79: -17 | BY79: =-118 -> -118 | BZ79: -95 | CA79: -139 | CB79: =SUM(BX79:CA79) -> -369 | CC79: 0 | CD79: 0 | CE79: 0 | CF79: 0 | CG79: =SUM(CC79:CF79) -> 0 | CH79: 0 | CI79: 0 | CJ79: 0 | CK79: 0 | CL79: =SUM(CH79:CK79) -> 0 | CM79: 0 | CN79: 0 | CO79: 0 | CP79: 0 | CQ79: =SUM(CM79:CP79) -> 0
C80: Additional Maintenance, $mn | BN80: =+BN81-BL81 -> 241 | BO80: =+BO81-BN81 -> 0 | BP80: =+BP81-BO81 -> 0 | BQ80: =+BQ81-BP81 -> 0 | BR80: =SUM(BN80:BQ80) -> 241 | BS80: =+BS81-BQ81 -> -3.5 | BT80: =+BT81-BS81 -> 0 | BU80: =+BU81-BT81 -> 0 | BV80: =+BV81-BU81 -> 0 | BW80: =SUM(BS80:BV80) -> -3.5 | BX80: =+BX81-BV81 -> 102.5 | BY80: =+BY81-BX81 -> -40 | BZ80: =+BZ81-BY81 -> 32 | CA80: =+CA81-BZ81 -> 21 | CB80: =SUM(BX80:CA80) -> 115.5 | CC80: =+CC81-CA81 -> -3 | CD80: =+CD81-CC81 -> -16.666667 | CE80: =+CE81-CD81 -> 0 | CF80: =+CF81-CE81 -> 0 | CG80: =SUM(CC80:CF80) -> -19.666667 | CH80: =+CH81-CF81 -> -33.333333 | CI80: =+CI81-CH81 -> 0 | CJ80: =+CJ81-CI81 -> 0 | CK80: =+CK81-CJ81 -> 0 | CL80: =SUM(CH80:CK80) -> -33.333333 | CM80: =+CM81-CK81 -> -50 | CN80: =+CN81-CM81 -> 0 | CO80: =+CO81-CN81 -> 0 | CP80: =+CP81-CO81 -> 0 | CQ80: =SUM(CM80:CP80) -> -50
C81: Maintenance, $mn | BN81: =BR81/4 -> 241 | BO81: =+BN81 -> 241 | BP81: =+BO81 -> 241 | BQ81: =+BP81 -> 241 | BR81: 964 | BS81: =BW81/4 -> 237.5 | BT81: =+BS81 -> 237.5 | BU81: =+BT81 -> 237.5 | BV81: =+BU81 -> 237.5 | BW81: 950 | BX81: 340 | BY81: =640-BX81 -> 300 | BZ81: =972-BX81-BY81 -> 332 | CA81: =+CB81-BX81-BY81-BZ81 -> 353 | CB81: 1325 | CC81: 350 | CD81: =+(CG81-CC81)/3 -> 333.33333 | CE81: =+(CG81-CC81-CD81)/2 -> 333.33333 | CF81: =+CG81-CC81-CD81-CE81 -> 333.33333 | CG81: 1350 | CH81: =CL81/4 -> 300 | CI81: =+CH81 -> 300 | CJ81: =+CI81 -> 300 | CK81: =+CJ81 -> 300 | CL81: 1200 | CM81: =CQ81/4 -> 250 | CN81: =+CM81 -> 250 | CO81: =+CN81 -> 250 | CP81: =+CO81 -> 250 | CQ81: 1000
C82: Maintenance, $/t | BN82: =+BN81/BN34*1000 -> 92.09018 | BO82: =+BO81/BO34*1000 -> 88.864307 | BP82: =+BP81/BP34*1000 -> 90.059791 | BQ82: =+BQ81/BQ34*1000 -> 93.01428 | BR82: =+BR81/BR34*1000 -> 90.977727 | BS82: =+BS81/BS34*1000 -> 95.076061 | BT82: =+BT81/BT34*1000 -> 88.224368 | BU82: =+BU81/BU34*1000 -> 93.688363 | ... CQ82: =+CQ81/CQ34*1000 -> 88.847238
B84: SEGMENT PROFIT (EBIT) | F84: =Financials!F32 -> -19 | G84: =Financials!G32 -> -48 | H84: =Financials!H32 -> -31 | I84: =Financials!I32 -> 44 | J84: =Financials!J32 -> -54 | K84: =Financials!K32 -> 113 | L84: =Financials!L32 -> 335 | M84: =Financials!M32 -> 362 | ... T84: =Financials!T32 -> 602 | U84: 127 | V84: 212 | W84: 230 | X84: =31 -> 31 | Y84: =SUM(U84:X84) -> 600 | Z84: 75 | AA84: 92 | AB84: 170 | AC84: 53 | AD84: =SUM(Z84:AC84) -> 390 | AE84: 120 | AF84: 478 | AG84: 835 | AH84: -2 | AI84: =SUM(AE84:AH84) -> 1431 | AJ84: -422 | AK84: -362 | AL84: -370 | AM84: -284 | AN84: =SUM(AJ84:AM84) -> -1438 | AO84: -80 | AP84: 98 | AQ84: -174 | AR84: -156 | AS84: =SUM(AO84:AR84) -> -312 | AT84: -36 | AU84: 374 | AV84: 203 | AW84: -72 | AX84: =SUM(AT84:AW84) -> 469 | AY84: 183 | AZ84: 177 | BA84: 29 | BB84: 11 | BC84: =SUM(AY84:BB84) -> 400 | BD84: -13 | BE84: -51 | BF84: 82 | BG84: 87 | BH84: =SUM(BD84:BG84) -> 105 | BI84: 85 | BJ84: 30 | BK84: 347 | BL84: 247 | BM84: =SUM(BI84:BL84) -> 709 | BN84: -67 | BO84: -64 | BP84: -18 | BQ84: =-237-SUM(BN84:BP84) -> -88 | BR84: =SUM(BN84:BQ84) -> -237 | BS84: -188 | BT84: 6 | BU84: 114 | BV84: 65 | BW84: =SUM(BS84:BV84) -> -3 | BX84: -90 | BY84: 218 | BZ84: 160 | CA84: 92 | CB84: =SUM(BX84:CA84) -> 380 | CC84: =+CC86-CC85 -> 12.182774 | CD84: =+CD86-CD85 -> 238.49194 | CE84: =+CE86-CE85 -> 303.13201 | CF84: =+CF86-CF85 -> 208.56297 | CG84: =SUM(CC84:CF84) -> 762.3697 | CH84: =+CH86-CH85 -> 107.96101 | CI84: =+CI86-CI85 -> 284.65964 | CJ84: =+CJ86-CJ85 -> 285.67142 | CK84: =+CK86-CK85 -> 246.79273 | CL84: =SUM(CH84:CK84) -> 925.0848 | CM84: =+CM86-CM85 -> 128.8376 | CN84: =+CN86-CN85 -> 207.17661 | CO84: =+CO86-CO85 -> 179.12371 | CP84: =+CP86-CP85 -> 145.62485 | CQ84: =SUM(CM84:CP84) -> 660.76277
C85: Depreciation and Amortization | D85: 215 | E85: 244 | F85: =G85 -> 62.5 | G85: =H85 -> 62.5 | H85: =I85 -> 62.5 | I85: =J85/4 -> 62.5 | J85: 250 | K85: =O85/4 -> 67 | L85: =O85/4 -> 67 | M85: =O85/4 -> 67 | N85: =O85/4 -> 67 | O85: 268 | P85: 64 | Q85: 56 | R85: 55 | S85: 57 | T85: 232 | U85: 66 | V85: 72 | W85: 69 | X85: =Y85-W85-V85-U85 -> 56 | Y85: 263 | Z85: 63 | AA85: 64 | AB85: 66 | AC85: 92 | AD85: =SUM(Z85:AC85) -> 285 | AE85: 106 | AF85: 107 | AG85: 97 | AH85: 76 | AI85: =SUM(AE85:AH85) -> 386 | AJ85: 110 | AK85: 111 | AL85: =AL63 -> 230.65667 | AM85: =AM63 -> 267.61 | AN85: =AN63 -> 226.09375 | AO85: =AO63 -> 312.165 | AP85: 116 | AQ85: =AQ63 -> 354.3 | AR85: =AR63 -> 353.61167 | AS85: =AS63 -> 345.95792 | AT85: 120 | AU85: 120 | AV85: 121 | AW85: 124 | AX85: =AX63 -> 438.13583 | AY85: 119 | AZ85: 122 | BA85: 122 | BB85: 129 | BC85: =BC63 -> 409.41167 | BD85: 129 | BE85: 128 | BF85: 132 | BG85: 123 | BH85: =SUM(BD85:BG85) -> 512 | BI85: 124 | BJ85: 121 | BK85: 115 | BL85: 96 | BM85: =SUM(BI85:BL85) -> 456 | BN85: 104 | BO85: 99 | BP85: 99 | BQ85: 90 | BR85: =SUM(BN85:BQ85) -> 392 | BS85: 91 | BT85: 89 | BU85: 87 | BV85: 82 | BW85: =SUM(BS85:BV85) -> 349 | BX85: 99 | BY85: 81 | BZ85: 83 | CA85: 89 | CB85: =SUM(BX85:CA85) -> 352 | CC85: 100 | CD85: 92 | CE85: 92 | CF85: 83 | CG85: =SUM(CC85:CF85) -> 367 | CH85: 100 | CI85: 92 | CJ85: 92 | CK85: 83 | CL85: =SUM(CH85:CK85) -> 367 | CM85: 100 | CN85: 92 | CO85: 92 | CP85: 83 | CQ85: =SUM(CM85:CP85) -> 367
C86: EBITDA | D86: =D84+D85 -> 215 | E86: =E84+E85 -> 244 | F86: =F84+F85 -> 43.5 | G86: =G84+G85 -> 14.5 | H86: =H84+H85 -> 31.5 | I86: =I84+I85 -> 106.5 | J86: =J84+J85 -> 196 | K86: =K84+K85 -> 180 | ... CA86: =CA84+CA85 -> 181 | CB86: =SUM(BX86:CA86) -> 732 | CC86: =+CC87*CC34/1000 -> 112.18277 | CD86: =+CD87*CD34/1000 -> 330.49194 | CE86: =+CE87*CE34/1000 -> 395.13201 | CF86: =+CF87*CF34/1000 -> 291.56297 | CG86: =SUM(CC86:CF86) -> 1129.3697 | CH86: =+CH87*CH34/1000 -> 207.96101 | CI86: =+CI87*CI34/1000 -> 376.65964 | CJ86: =+CJ87*CJ34/1000 -> 377.67142 | CK86: =+CK87*CK34/1000 -> 329.79273 | CL86: =SUM(CH86:CK86) -> 1292.0848 | CM86: =+CM87*CM34/1000 -> 228.8376 | CN86: =+CN87*CN34/1000 -> 299.17661 | CO86: =+CO87*CO34/1000 -> 271.12371 | CP86: =+CP87*CP34/1000 -> 228.62485 | CQ86: =SUM(CM86:CP86) -> 1027.7628
C87: EBITDA per Ton | D87: =D86/D34*1000 -> 24.490261 | E87: =E86/E34*1000 -> 24.646465 | F87: =F86/F34*1000 -> 17.857143 | G87: =G86/G34*1000 -> 4.5284197 | H87: =H86/H34*1000 -> 8.0583269 | I87: =I86/I34*1000 -> 26.826196 | J87: =J86/J34*1000 -> 14.500259 | K87: =K86/K34*1000 -> 43.258832 | ... CA87: =CA86/CA34*1000 -> 74.119574 | CB87: =CB51-CB73 -> 73.411999 | CC87: =CC51-CC73 -> 46.203017 | CD87: =CD51-CD73 -> 131.04515 | CE87: =CE51-CE73 -> 141.19926 | CF87: =CF51-CF73 -> 106.60282 | CG87: =CG51-CG73 -> 107.96253 | CH87: =CH51-CH73 -> 75.796237 | CI87: =CI51-CI73 -> 131.35564 | ... CQ87: =CQ51-CQ73 -> 91.075016
A89: Pension and OPEB Expense | F89: =G89 -> -12 | G89: =H89 -> -12 | H89: =I89 -> -12 | I89: =J89/4 -> -12 | J89: =-155-Financials!J36 -> -48 | K89: =L89 -> -37 | L89: =M89 -> -37 | M89: =N89 -> -37 | N89: =O89/4 -> -37 | O89: =-360-Financials!O36 -> -148 | P89: =Q89 -> -30.5 | Q89: =R89 -> -30.5 | R89: =S89 -> -30.5 | S89: =T89/4 -> -30.5 | T89: =-389-Financials!T36 -> -122 | U89: =V89 -> -17.25 | V89: =W89 -> -17.25 | W89: =X89 -> -17.25 | X89: =Y89/4 -> -17.25 | Y89: =-312-Financials!Y36 -> -69 | Z89: =AA89 -> -41.25 | AA89: =AB89 -> -41.25 | AB89: =AC89 -> -41.25 | AC89: =AD89/4 -> -41.25 | AD89: =-265-Financials!AD36 -> -165 | AE89: =AF89 -> -51.25 | AF89: =AG89 -> -51.25 | AG89: =AH89 -> -51.25 | AH89: =AI89/4 -> -51.25 | AI89: =-227-Financials!AI36 -> -205 | AJ89: =AK89 -> -82 | AK89: =AL89 -> -82 | AL89: =AM89 -> -82 | AM89: =AN89/4 -> -82 | AN89: =-462-Financials!AN36 -> -328 | AO89: =AP89 -> -60 | AP89: =AQ89 -> -60 | AQ89: =AR89 -> -60 | AR89: =AS89/4 -> -60 | AS89: =-428-Financials!AS36 -> -240 | AT89: =AU89 -> -54 | AU89: =AV89 -> -54 | AV89: =AW89 -> -54 | AW89: =AX89/4 -> -54 | AX89: =-Pension!J25-OPEB!J25-Financials!AX36 -> -216 | AY89: =AZ89 -> -53.75 | AZ89: =BA89 -> -53.75 | BA89: =BB89 -> -53.75 | BB89: =BC89/4 -> -53.75 | BC89: =-Pension!K25-OPEB!K25-Financials!BC36 -> -215 | BD89: =BE89 -> -57.5 | BE89: =BF89 -> -57.5 | BF89: =BG89 -> -57.5 | BG89: =BH89/4 -> -57.5 | BH89: =-Pension!L25-OPEB!L25-Financials!BH36 -> -230 | BI89: =BJ89 -> -54.25 | BJ89: =BK89 -> -54.25 | BK89: =BL89 -> -54.25 | BL89: =BM89/4 -> -54.25 | BM89: =-Pension!M25-OPEB!M25-Financials!BM36 -> -217 | BN89: =BO89 -> -53 | BO89: =BP89 -> -53 | BP89: =BQ89 -> -53 | BQ89: =BR89/4 -> -53 | BR89: =-Pension!N25-OPEB!N25-Financials!BR36 -> -212 | BS89: =BT89 -> -41 | BT89: =BU89 -> -41 | BU89: =BV89 -> -41 | BV89: =BW89/4 -> -41 | BW89: =-Pension!O25-OPEB!O25-Financials!BW36 -> -164 | BX89: =BY89 -> -30.25 | BY89: =BZ89 -> -30.25 | BZ89: =CA89 -> -30.25 | CA89: =CB89/4 -> -30.25 | CB89: =-Pension!P25-OPEB!P25-Financials!CB36 -> -121 | CC89: =CD89 -> -27.148875 | CD89: =CE89 -> -27.148875 | CE89: =CF89 -> -27.148875 | CF89: =CG89/4 -> -27.148875 | CG89: =-Pension!Q25-OPEB!Q25-Financials!CG36 -> -108.5955 | CH89: =CI89 -> -26.91551 | CI89: =CJ89 -> -26.91551 | CJ89: =CK89 -> -26.91551 | CK89: =CL89/4 -> -26.91551 | CL89: =-Pension!R25-OPEB!R25-Financials!CL36 -> -107.66204 | CM89: =CN89 -> -26.507146 | CN89: =CO89 -> -26.507146 | CO89: =CP89 -> -26.507146 | CP89: =CQ89/4 -> -26.507146 | CQ89: =-Pension!S25-OPEB!S25-Financials!CQ36 -> -106.02859
B91: Capital Expenditures | D91: 144 | E91: 47 | F91: 11 | G91: 21 | H91: 23 | I91: =J91-SUM(F91:H91) -> 46 | J91: 101 | K91: 21 | L91: 37 | M91: 109 | N91: =O91-SUM(K91:M91) -> 86 | O91: 253 | P91: 59 | Q91: 78 | R91: 83 | S91: =T91-SUM(P91:R91) -> 157 | T91: 377 | U91: 69 | V91: 32 | W91: 46 | X91: 127 | Y91: =SUM(U91:X91) -> 274 | Z91: 50 | AA91: 69 | AB91: 121 | AC91: 79 | AD91: =SUM(Z91:AC91) -> 319 | AE91: 83 | AF91: 145 | AG91: 192 | AH91: 175 | AI91: =SUM(AE91:AH91) -> 595 | AJ91: 98 | AK91: 65 | AL91: 68 | AM91: 107 | AN91: =SUM(AJ91:AM91) -> 338 | AO91: 80 | AP91: 74 | AQ91: 151 | AR91: 194 | AS91: =SUM(AO91:AR91) -> 499 | AT91: 125 | AU91: 142 | AV91: 160 | AW91: 189 | AX91: =SUM(AT91:AW91) -> 616 | AY91: 119 | AZ91: 151 | BA91: 89 | BB91: 141 | BC91: =SUM(AY91:BB91) -> 500 | BD91: 96 | BE91: 80 | BF91: 72 | BG91: 101 | BH91: =SUM(BD91:BG91) -> 349 | BI91: 55 | BJ91: 47 | BK91: 56 | BL91: 103 | BM91: =SUM(BI91:BL91) -> 261 | BN91: 132 | BO91: 56 | BP91: 63 | BQ91: 84 | BR91: =SUM(BN91:BQ91) -> 335 | BS91: 46 | BT91: 28 | BU91: 23 | BV91: 14 | BW91: =SUM(BS91:BV91) -> 111 | BX91: 25 | BY91: 47 | BZ91: 134 | CA91: 182 | CB91: =SUM(BX91:CA91) -> 388 | CC91: =CD91 -> 175 | CD91: =CE91 -> 175 | CE91: =CG91/4 -> 175 | CF91: =CG91-SUM(CC91:CE91) -> 175 | CG91: 700 | CH91: =CI91 -> 250 | CI91: =CJ91 -> 250 | CJ91: =CL91/4 -> 250 | CK91: =CL91-SUM(CH91:CJ91) -> 250 | CL91: =250+(2000-200-300)/2 -> 1000 | CM91: =CN91 -> 250 | CN91: =CO91 -> 250 | CO91: =CQ91/4 -> 250 | CP91: =CQ91-SUM(CM91:CO91) -> 250 | CQ91: =250+(2000-200-300)/2 -> 1000
B92: Capex per ton | D92: =D91/D34*1000 -> 16.402779 | E92: =E91/E34*1000 -> 4.7474747 | F92: =F91/F34*1000 -> 4.5155993 | G92: =G91/G34*1000 -> 6.558401 | H92: =H91/H34*1000 -> 5.8838578 | I92: =I91/I34*1000 -> 11.586902 | J92: =J91/J34*1000 -> 7.4720722 | K92: =K91/K34*1000 -> 5.0468637 | ... CQ92: =CQ91/CQ34*1000 -> 88.847238
A94: Tubular Segment
C95: Volume Growth | E95: =Operations!E100/Operations!D100-1 -> -0.24363992 | J95: =Operations!J100/Operations!E100-1 -> 0.14100906 | K95: =Operations!K100/Operations!F100-1 -> 0.32038835 | L95: =Operations!L100/Operations!G100-1 -> 0.27488152 | M95: =Operations!M100/Operations!H100-1 -> 0.15151515 | N95: =Operations!N100/Operations!I100-1 -> 0.21794872 | O95: =Operations!O100/Operations!J100-1 -> 0.23809524 | P95: =Operations!P100/Operations!K100-1 -> 0.11397059 | Q95: =Operations!Q100/Operations!L100-1 -> 0.10408922 | ... CB95: =Operations!CB100/Operations!BW100-1 -> 0.72 | CC95: 0.05 | CD95: 0.2 | CE95: 0.2 | CF95: 0.05 | CG95: =Operations!CG100/Operations!CB100-1 -> 0.12957849 | CH95: 0.03 | CI95: 0.03 | CJ95: 0.03 | CK95: 0.03 | CL95: =Operations!CL100/Operations!CG100-1 -> 0.03 | CM95: 0.03 | CN95: 0.03 | CO95: 0.03 | CP95: 0.03 | CQ95: =Operations!CQ100/Operations!CL100-1 -> 0.03
A97: Volume Mix
B98: Seamless | D98: =D100 -> 1022 | E98: =E100 -> 773 | F98: =F100 -> 206 | G98: =G100 -> 211 | H98: =H100 -> 231 | I98: =I100 -> 234 | J98: =J100 -> 882 | K98: =K100 -> 272 | ... AA98: =AA100 -> 289 | AB98: =0.47*AB100 -> 222.31 | AC98: =0.47*AC100 -> 200.69 | AD98: =SUM(Z98:AC98) -> 959 | AE98: =0.47*AE100 -> 203.51 | AF98: =0.47*AF100 -> 235 | AG98: =0.47*AG100 -> 243.93 | AH98: =0.47*AH100 -> 235 | AI98: =SUM(AE98:AH98) -> 917.44 | AJ98: =0.47*AJ100 -> 97.29 | AK98: =0.47*AK100 -> 43.24 | AL98: =0.47*AL100 -> 70.97 | AM98: =0.47*AM100 -> 97.29 | AN98: =SUM(AJ98:AM98) -> 308.79 | AO98: =0.47*AO100 -> 145.7 | AP98: =0.47*AP100 -> 203.51 | AQ98: =0.47*AQ100 -> 198.34 | AR98: =0.47*AR100 -> 181.42 | AS98: =SUM(AO98:AR98) -> 728.97 | AT98: =0.47*AT100 -> 199.75 | AU98: =0.47*AU100 -> 199.28 | AV98: =0.47*AV100 -> 226.07 | AW98: =0.47*AW100 -> 226.54 | AX98: =SUM(AT98:AW98) -> 851.64 | AY98: =0.47*AY100 -> 248.63 | AZ98: =0.47*AZ100 -> 231.71 | BA98: =0.47*BA100 -> 214.79 | BB98: =0.47*BB100 -> 191.29 | BC98: =SUM(AY98:BB98) -> 886.42 | BD98: =0.47*BD100 -> 201.16 | BE98: =0.47*BE100 -> 214.32 | BF98: =0.47*BF100 -> 215.73 | BG98: =0.47*BG100 -> 194.58 | BH98: =SUM(BD98:BG98) -> 825.79 | BI98: =0.47*BI100 -> 196.93 | BJ98: =0.47*BJ100 -> 211.03 | BK98: =0.47*BK100 -> 201.16 | BL98: =0.47*BL100 -> 210.56 | BM98: =SUM(BI98:BL98) -> 819.68 | BN98: =0.47*BN100 -> 103.4 | BO98: =0.47*BO100 -> 43.24 | BP98: =0.47*BP100 -> 72.38 | BQ98: =0.47*BQ100 -> 59.69 | BR98: =SUM(BN98:BQ98) -> 278.71 | BS98: =0.47*BS100 -> 41.83 | BT98: =0.47*BT100 -> 32.9 | BU98: =0.47*BU100 -> 48.41 | BV98: =0.47*BV100 -> 64.86 | BW98: =SUM(BS98:BV98) -> 188 | BX98: =0.47*BX100 -> 67.68 | BY98: =0.47*BY100 -> 84.6 | BZ98: =0.47*BZ100 -> 86.95 | CA98: =0.47*CA100 -> 84.13 | CB98: =SUM(BX98:CA98) -> 323.36 | CC98: =0.47*CC100 -> 71.064 | CD98: =0.47*CD100 -> 101.52 | CE98: =0.47*CE100 -> 104.34 | CF98: =0.47*CF100 -> 88.3365 | CG98: =SUM(CC98:CF98) -> 365.2605 | CH98: =0.47*CH100 -> 73.19592 | CI98: =0.47*CI100 -> 104.5656 | CJ98: =0.47*CJ100 -> 107.4702 | CK98: =0.47*CK100 -> 90.986595 | CL98: =SUM(CH98:CK98) -> 376.21831 | CM98: =0.47*CM100 -> 75.391798 | CN98: =0.47*CN100 -> 107.70257 | CO98: =0.47*CO100 -> 110.69431 | CP98: =0.47*CP100 -> 93.716193 | CQ98: =SUM(CM98:CP98) -> 387.50486
B99: Welded | AB99: =AB100-AB98 -> 250.69 | AC99: =AC100-AC98 -> 226.31 | AD99: =SUM(Z99:AC99) -> 477 | AE99: =AE100-AE98 -> 229.49 | AF99: =AF100-AF98 -> 265 | AG99: =AG100-AG98 -> 275.07 | AH99: =AH100-AH98 -> 265 | AI99: =SUM(AE99:AH99) -> 1034.56 | AJ99: =AJ100-AJ98 -> 109.71 | AK99: =AK100-AK98 -> 48.76 | AL99: =AL100-AL98 -> 80.03 | AM99: =AM100-AM98 -> 109.71 | AN99: =SUM(AJ99:AM99) -> 348.21 | AO99: =AO100-AO98 -> 164.3 | AP99: =AP100-AP98 -> 229.49 | AQ99: =AQ100-AQ98 -> 223.66 | AR99: =AR100-AR98 -> 204.58 | AS99: =SUM(AO99:AR99) -> 822.03 | AT99: =AT100-AT98 -> 225.25 | AU99: =AU100-AU98 -> 224.72 | AV99: =AV100-AV98 -> 254.93 | AW99: =AW100-AW98 -> 255.46 | AX99: =SUM(AT99:AW99) -> 960.36 | AY99: =AY100-AY98 -> 280.37 | AZ99: =AZ100-AZ98 -> 261.29 | BA99: =BA100-BA98 -> 242.21 | BB99: =BB100-BB98 -> 215.71 | BC99: =SUM(AY99:BB99) -> 999.58 | BD99: =BD100-BD98 -> 226.84 | BE99: =BE100-BE98 -> 241.68 | BF99: =BF100-BF98 -> 243.27 | BG99: =BG100-BG98 -> 219.42 | BH99: =SUM(BD99:BG99) -> 931.21 | BI99: =BI100-BI98 -> 222.07 | BJ99: =BJ100-BJ98 -> 237.97 | BK99: =BK100-BK98 -> 226.84 | BL99: =BL100-BL98 -> 237.44 | BM99: =SUM(BI99:BL99) -> 924.32 | BN99: =BN100-BN98 -> 116.6 | BO99: =BO100-BO98 -> 48.76 | BP99: =BP100-BP98 -> 81.62 | BQ99: =BQ100-BQ98 -> 67.31 | BR99: =SUM(BN99:BQ99) -> 314.29 | BS99: =BS100-BS98 -> 47.17 | BT99: =BT100-BT98 -> 37.1 | BU99: =BU100-BU98 -> 54.59 | BV99: =BV100-BV98 -> 73.14 | BW99: =SUM(BS99:BV99) -> 212 | BX99: =BX100-BX98 -> 76.32 | BY99: =BY100-BY98 -> 95.4 | BZ99: =BZ100-BZ98 -> 98.05 | CA99: =CA100-CA98 -> 94.87 | CB99: =SUM(BX99:CA99) -> 364.64 | CC99: =CC100-CC98 -> 80.136 | CD99: =CD100-CD98 -> 114.48 | CE99: =CE100-CE98 -> 117.66 | CF99: =CF100-CF98 -> 99.6135 | CG99: =SUM(CC99:CF99) -> 411.8895 | CH99: =CH100-CH98 -> 82.54008 | CI99: =CI100-CI98 -> 117.9144 | CJ99: =CJ100-CJ98 -> 121.1898 | CK99: =CK100-CK98 -> 102.60191 | CL99: =SUM(CH99:CK99) -> 424.24619 | CM99: =CM100-CM98 -> 85.016282 | CN99: =CN100-CN98 -> 121.45183 | CO99: =CO100-CO98 -> 124.82549 | CP99: =CP100-CP98 -> 105.67996 | CQ99: =SUM(CM99:CP99) -> 436.97357
C100: Tubular Shipments | D100: 1022 | E100: 773 | F100: 206 | G100: 211 | H100: 231 | I100: 234 | J100: 882 | K100: 272 | L100: 269 | M100: 266 | N100: 285 | O100: 1092 | P100: 303 | Q100: 297 | R100: 264 | S100: 292 | T100: 1156 | U100: 319 | V100: 298 | W100: 303 | X100: 271 | Y100: =SUM(U100:X100) -> 1191 | Z100: 247 | AA100: 289 | AB100: 473 | AC100: 427 | AD100: =SUM(Z100:AC100) -> 1436 | AE100: 433 | AF100: 500 | AG100: 519 | AH100: 500 | AI100: =SUM(AE100:AH100) -> 1952 | AJ100: 207 | AK100: 92 | AL100: 151 | AM100: 207 | AN100: =SUM(AJ100:AM100) -> 657 | AO100: 310 | AP100: 433 | AQ100: 422 | AR100: 386 | AS100: =SUM(AO100:AR100) -> 1551 | AT100: 425 | AU100: 424 | AV100: 481 | AW100: 482 | AX100: =SUM(AT100:AW100) -> 1812 | AY100: 529 | AZ100: 493 | BA100: 457 | BB100: 407 | BC100: =SUM(AY100:BB100) -> 1886 | BD100: 428 | BE100: 456 | BF100: 459 | BG100: 414 | BH100: =SUM(BD100:BG100) -> 1757 | BI100: 419 | BJ100: 449 | BK100: 428 | BL100: 448 | BM100: =SUM(BI100:BL100) -> 1744 | BN100: 220 | BO100: 92 | BP100: 154 | BQ100: 127 | BR100: =SUM(BN100:BQ100) -> 593 | BS100: 89 | BT100: 70 | BU100: 103 | BV100: 138 | BW100: =SUM(BS100:BV100) -> 400 | BX100: 144 | BY100: 180 | BZ100: 185 | CA100: 179 | CB100: =SUM(BX100:CA100) -> 688 | CC100: =BX100*(1+CC95) -> 151.2 | CD100: =BY100*(1+CD95) -> 216 | CE100: =BZ100*(1+CE95) -> 222 | CF100: =CA100*(1+CF95) -> 187.95 | CG100: =SUM(CC100:CF100) -> 777.15 | CH100: =CC100*(1+CH95) -> 155.736 | CI100: =CD100*(1+CI95) -> 222.48 | CJ100: =CE100*(1+CJ95) -> 228.66 | CK100: =CF100*(1+CK95) -> 193.5885 | CL100: =SUM(CH100:CK100) -> 800.4645 | CM100: =CH100*(1+CM95) -> 160.40808 | CN100: =CI100*(1+CN95) -> 229.1544 | CO100: =CJ100*(1+CO95) -> 235.5198 | CP100: =CK100*(1+CP95) -> 199.39616 | CQ100: =SUM(CM100:CP100) -> 824.47844
C102: Rolling Capacity | J102: =Operations!J110 -> 1800 | K102: =Operations!K110 -> 448.76712 | L102: =Operations!L110 -> 448.76712 | M102: =Operations!M110 -> 453.69863 | N102: =Operations!N110 -> 453.69863 | O102: =Operations!O110 -> 1804.9315 | P102: =Operations!P110 -> 443.83562 | Q102: =Operations!Q110 -> 448.76712 | ... CQ102: =Operations!CQ110 -> 2800
C103: Shipments / Capacity | J103: =Operations!J111 -> 0.49 | K103: =Operations!K111 -> 0.60610501 | L103: =Operations!L111 -> 0.59942002 | M103: =Operations!M111 -> 0.58629227 | N103: =Operations!N111 -> 0.62817029 | O103: =Operations!O111 -> 0.60500911 | P103: =Operations!P111 -> 0.68268519 | Q103: =Operations!Q111 -> 0.66181319 | ... CQ103: =Operations!CQ111 -> 0.29445658
A105: Spot Prices
B106: Seamless | F106: 877.33333 | G106: 882.66667 | H106: 882.66667 | I106: 888 | J106: 882.66667 | K106: =Operations!K15 -> 929.33333 | L106: =Operations!L15 -> 1297.3333 | M106: =Operations!M15 -> 1454.6667 | N106: =Operations!N15 -> 1480.3333 | O106: =Operations!O15 -> 1290.4167 | P106: =Operations!P15 -> 1527 | Q106: =Operations!Q15 -> 1569.6667 | R106: =Operations!R15 -> 1556 | ... CQ106: =Operations!CQ15 -> 1701.25
B107: Welded | F107: 776 | G107: 783.66667 | H107: 797 | I107: 802 | J107: 789.66667 | K107: =Operations!K16 -> 831 | L107: =Operations!L16 -> 1259.3333 | M107: =Operations!M16 -> 1315.6667 | N107: =Operations!N16 -> 1318.3333 | O107: =Operations!O16 -> 1181.0833 | P107: =Operations!P16 -> 1358.3333 | Q107: =Operations!Q16 -> 1330.3333 | R107: =Operations!R16 -> 1352 | ... CQ107: =Operations!CQ16 -> 1356.25
C108: Blended Average | F108: =(F106*F98+F107*F99)/SUM(F98:F99) -> 877.33333 | G108: =(G106*G98+G107*G99)/SUM(G98:G99) -> 882.66667 | H108: =(H106*H98+H107*H99)/SUM(H98:H99) -> 882.66667 | I108: =(I106*I98+I107*I99)/SUM(I98:I99) -> 888 | J108: =(J106*J98+J107*J99)/SUM(J98:J99) -> 882.66667 | K108: =(K106*K98+K107*K99)/SUM(K98:K99) -> 929.33333 | L108: =(L106*L98+L107*L99)/SUM(L98:L99) -> 1297.3333 | M108: =(M106*M98+M107*M99)/SUM(M98:M99) -> 1454.6667 | ... CQ108: =(CQ106*CQ98+CQ107*CQ99)/SUM(CQ98:CQ99) -> 1518.4
A110: Rolling Capacity | D110: 1800 | E110: 1800 | F110: =1800/365*90 -> 443.83562 | G110: =1800/365*91 -> 448.76712 | H110: =1800/365*92 -> 453.69863 | I110: =1800/365*92 -> 453.69863 | J110: =SUM(F110:I110) -> 1800 | K110: =1800/365*91 -> 448.76712 | L110: =1800/365*91 -> 448.76712 | M110: =1800/365*92 -> 453.69863 | N110: =1800/365*92 -> 453.69863 | O110: =SUM(K110:N110) -> 1804.9315 | P110: =1800/365*90 -> 443.83562 | Q110: =1800/365*91 -> 448.76712 | R110: =1800/365*92 -> 453.69863 | S110: =1800/365*92 -> 453.69863 | T110: =SUM(P110:S110) -> 1800 | U110: =1800/365*90 -> 443.83562 | V110: =1800/365*91 -> 448.76712 | W110: =1800/365*92 -> 453.69863 | X110: =1800/365*92 -> 453.69863 | Y110: =SUM(U110:X110) -> 1800 | Z110: =1800/365*90 -> 443.83562 | AA110: =1800/365*91 -> 448.76712 | AB110: =2800/365*92 -> 705.75342 | AC110: =2800/365*92 -> 705.75342 | AD110: =SUM(Z110:AC110) -> 2304.1096 | AE110: =2800/365*91 -> 698.08219 | AF110: =2800/365*91 -> 698.08219 | AG110: =2800/365*92 -> 705.75342 | AH110: =2800/365*92 -> 705.75342 | AI110: =SUM(AE110:AH110) -> 2807.6712 | AJ110: =2800/365*90 -> 690.41096 | AK110: =2800/365*91 -> 698.08219 | AL110: =2800/365*92 -> 705.75342 | AM110: =2800/365*92 -> 705.75342 | AN110: =SUM(AJ110:AM110) -> 2800 | AO110: =2800/365*90 -> 690.41096 | AP110: =2800/365*91 -> 698.08219 | AQ110: =2800/365*92 -> 705.75342 | AR110: =2800/365*92 -> 705.75342 | AS110: =SUM(AO110:AR110) -> 2800 | AT110: =2800/365*90 -> 690.41096 | AU110: =2800/365*91 -> 698.08219 | AV110: =2800/365*91 -> 698.08219 | AW110: =2800/365*92 -> 705.75342 | AX110: =SUM(AT110:AW110) -> 2792.3288 | AY110: =2800/365*91 -> 698.08219 | AZ110: =2800/365*91 -> 698.08219 | BA110: =2800/365*92 -> 705.75342 | BB110: =2800/365*92 -> 705.75342 | BC110: =SUM(AY110:BB110) -> 2807.6712 | BD110: =2800/365*91 -> 698.08219 | BE110: =2800/365*92 -> 705.75342 | BF110: =2800/365*92 -> 705.75342 | BG110: =2800/365*92 -> 705.75342 | BH110: =SUM(BD110:BG110) -> 2815.3425 | BI110: =2800/365*92 -> 705.75342 | BJ110: =2800/365*92 -> 705.75342 | BK110: 610 | BL110: 566 | BM110: =SUM(BI110:BL110) -> 2587.5068 | BN110: =2800/4 -> 700 | BO110: =2800/4 -> 700 | BP110: =2800/4 -> 700 | BQ110: =2800/4 -> 700 | BR110: =SUM(BN110:BQ110) -> 2800 | BS110: =2800/4 -> 700 | BT110: =2800/4 -> 700 | BU110: =2800/4 -> 700 | BV110: =2800/4 -> 700 | BW110: =SUM(BS110:BV110) -> 2800 | BX110: =2800/4 -> 700 | BY110: =2800/4 -> 700 | BZ110: =2800/4 -> 700 | CA110: =2800/4 -> 700 | CB110: =SUM(BX110:CA110) -> 2800 | CC110: =2800/4 -> 700 | CD110: =2800/4 -> 700 | CE110: =2800/4 -> 700 | CF110: =2800/4 -> 700 | CG110: =SUM(CC110:CF110) -> 2800 | CH110: =2800/4 -> 700 | CI110: =2800/4 -> 700 | CJ110: =2800/4 -> 700 | CK110: =2800/4 -> 700 | CL110: =SUM(CH110:CK110) -> 2800 | CM110: =2800/4 -> 700 | CN110: =2800/4 -> 700 | CO110: =2800/4 -> 700 | CP110: =2800/4 -> 700 | CQ110: =SUM(CM110:CP110) -> 2800
B111: Shipments / Capacity | D111: =D100/D110 -> 0.56777778 | E111: =E100/E110 -> 0.42944444 | F111: =F100/F110 -> 0.4641358 | G111: =G100/G110 -> 0.47017705 | H111: =H100/H110 -> 0.50914855 | I111: =I100/I110 -> 0.51576087 | J111: =J100/J110 -> 0.49 | K111: =K100/K110 -> 0.60610501 | ... CQ111: =CQ100/CQ110 -> 0.29445658
B113: Tubular Segment revenue | F113: =Financials!F11 -> 136 | G113: =Financials!G11 -> 140 | H113: =Financials!H11 -> 149 | I113: =Financials!I11 -> 148 | J113: =Financials!J11 -> 573 | K113: =Financials!K11 -> 190 | L113: =Financials!L11 -> 198 | M113: =Financials!M11 -> 246 | ... T113: =Financials!T11 -> 1546 | U113: 485 | V113: 444 | W113: 455 | X113: =Y113-W113-V113-U113 -> 414 | Y113: 1798 | Z113: 356 | AA113: 405 | AB113: 637 | AC113: 587 | AD113: =SUM(Z113:AC113) -> 1985 | AE113: 621 | AF113: 912 | AG113: 1333 | AH113: 1386 | AI113: =AI114+AI115 -> 4252 | AJ113: 515 | AK113: 157 | AL113: 234 | AM113: 310 | AN113: =AN114+AN115 -> 1216 | AO113: 445 | AP113: 679 | AQ113: 680 | AR113: 599 | AS113: =AS114+AS115 -> 2403 | AT113: 642 | AU113: 695 | AV113: 846 | AW113: 851 | AX113: =AX114+AX115 -> 3034 | AY113: 946 | AZ113: 871 | BA113: 787 | BB113: 679 | BC113: =BC114+BC115 -> 3283 | BD113: 686 | BE113: 709 | BF113: 731 | BG113: 646 | BH113: =BH114+BH115 -> 2772 | BI113: 643 | BJ113: 686 | BK113: 700 | BL113: 743 | BM113: =BM114+BM115 -> 2772 | BN113: 371 | BO113: 160 | BP113: 199 | BQ113: =898-SUM(BN113:BP113) -> 168 | BR113: =BR114+BR115 -> 898 | BS113: 108 | BT113: 83 | BU113: 114 | BV113: 145 | BW113: =BW114+BW115 -> 450 | BX113: 171 | BY113: 234 | BZ113: 276 | CA113: 264 | CB113: =SUM(BX113:CA113) -> 945 | CC113: =+CC114+CC115 -> 232.61791 | CD113: =+CD114+CD115 -> 355.15913 | CE113: =+CE114+CE115 -> 376.23134 | CF113: =+CF114+CF115 -> 317.06531 | CG113: =SUM(CC113:CF113) -> 1281.0737 | CH113: =+CH114+CH115 -> 239.22145 | CI113: =+CI114+CI115 -> 365.43891 | CJ113: =+CJ114+CJ115 -> 387.14328 | CK113: =+CK114+CK115 -> 326.20227 | CL113: =SUM(CH113:CK113) -> 1318.0059 | CM113: =+CM114+CM115 -> 246.02309 | CN113: =+CN114+CN115 -> 376.02707 | CO113: =+CO114+CO115 -> 398.38258 | CP113: =+CP114+CP115 -> 335.61334 | CQ113: =SUM(CM113:CP113) -> 1356.0461
B114: STEEL REVENUE | D114: =D113 -> 0 | E114: =E113-E115 -> 503.223 | F114: =F113-F115 -> 131.428 | G114: =G113-G115 -> 135.884 | H114: =H113-H115 -> 144.375 | I114: =I113-I115 -> 143.973 | J114: =J113-J115 -> 555.66 | K114: =K113-K115 -> 182.784 | L114: =L113-L115 -> 209.551 | ... X114: =X113-X115 -> 412.733 | Y114: =SUM(U114:X114) -> 1785.662 | Z114: =Z113-Z115 -> 354.445 | AA114: =AA113-AA115 -> 401.421 | AB114: =AB113-AB115 -> 606.386 | AC114: =AC113-AC115 -> 554.673 | AD114: =SUM(Z114:AC114) -> 1916.925 | AE114: =AE113-AE115 -> 561.601 | AF114: =AF113-AF115 -> 845 | AG114: =AG113-AG115 -> 1240.41 | AH114: =AH113-AH115 -> 1337.5 | AI114: =SUM(AE114:AH114) -> 3984.511 | AJ114: =AJ113-AJ115 -> 487.071 | AK114: =AK113-AK115 -> 140.392 | AL114: =AL113-AL115 -> 222.574 | AM114: =AM113-AM115 -> 302.634 | AN114: =SUM(AJ114:AM114) -> 1152.671 | AO114: =AO113-AO115 -> 430.59 | AP114: =AP113-AP115 -> 647.768 | AQ114: =AQ113-AQ115 -> 657.898 | AR114: =AR113-AR115 -> 580.544 | AS114: =SUM(AO114:AR114) -> 2316.8 | AT114: =AT113-AT115 -> 614.975 | AU114: =AU113-AU115 -> 663.56 | AV114: =AV113-AV115 -> 817.219 | AW114: =AW113-AW115 -> 824.702 | AX114: =SUM(AT114:AW114) -> 2920.456 | AY114: =AY113-AY115 -> 913.583 | AZ114: =AZ113-AZ115 -> 841.058 | BA114: =BA113-BA115 -> 765.932 | BB114: =BB113-BB115 -> 660.968 | BC114: =SUM(AY114:BB114) -> 3181.541 | BD114: =BD113-BD115 -> 665.968 | BE114: =BE113-BE115 -> 688.56 | BF114: =BF113-BF115 -> 708.237 | BG114: =BG113-BG115 -> 624.726 | BH114: =SUM(BD114:BG114) -> 2687.491 | BI114: =BI113-BI115 -> 619.701 | BJ114: =BJ113-BJ115 -> 664.071 | BK114: =BK113-BK115 -> 670.676 | BL114: =BL113-BL115 -> 728 | BM114: =SUM(BI114:BL114) -> 2682.448 | BN114: =BN113-BN115 -> 360.14 | BO114: =BO113-BO115 -> 151.892 | BP114: =BP113-BP115 -> 194.656 | BQ114: =BQ113-BQ115 -> 161.671 | BR114: =SUM(BN114:BQ114) -> 868.359 | BS114: =BS113-BS115 -> 105.02 | BT114: =BT113-BT115 -> 73.5 | BU114: =BU113-BU115 -> 108.047 | BV114: =BV113-BV115 -> 141.726 | BW114: =SUM(BS114:BV114) -> 428.293 | BX114: =BX113-BX115 -> 157.968 | BY114: =BY113-BY115 -> 222.12 | BZ114: =BZ113-BZ115 -> 265.105 | CA114: =CA113-CA115 -> 253.643 | CB114: =SUM(BX114:CA114) -> 898.836 | CC114: =CC116*CC100/1000 -> 220.11791 | CD114: =CD116*CD100/1000 -> 342.65913 | CE114: =CE116*CE100/1000 -> 363.73134 | CF114: =CF116*CF100/1000 -> 304.56531 | CG114: =SUM(CC114:CF114) -> 1231.0737 | CH114: =CH116*CH100/1000 -> 226.72145 | CI114: =CI116*CI100/1000 -> 352.93891 | CJ114: =CJ116*CJ100/1000 -> 374.64328 | CK114: =CK116*CK100/1000 -> 313.70227 | CL114: =SUM(CH114:CK114) -> 1268.0059 | CM114: =CM116*CM100/1000 -> 233.52309 | CN114: =CN116*CN100/1000 -> 363.52707 | CO114: =CO116*CO100/1000 -> 385.88258 | CP114: =CP116*CP100/1000 -> 323.11334 | CQ114: =SUM(CM114:CP114) -> 1306.0461
B115: Other revenue ( $ in millions) | D115: =D113-D116*D100/1000 -> -700.07 | E115: =E113-E116*E100/1000 -> -503.223 | F115: =F113-F116*F100/1000 -> 4.572 | G115: =G113-G116*G100/1000 -> 4.116 | H115: =H113-H116*H100/1000 -> 4.625 | I115: =I113-I116*I100/1000 -> 4.027 | J115: =J113-J116*J100/1000 -> 17.34 | K115: =K113-K116*K100/1000 -> 7.216 | ... X115: =X113-X116*X100/1000 -> 1.267 | Y115: =SUM(U115:X115) -> 12.338 | Z115: =Z113-Z116*Z100/1000 -> 1.555 | AA115: =AA113-AA116*AA100/1000 -> 3.579 | AB115: =AB113-AB116*AB100/1000 -> 30.614 | AC115: =AC113-AC116*AC100/1000 -> 32.327 | AD115: =SUM(Z115:AC115) -> 68.075 | AE115: =AE113-AE116*AE100/1000 -> 59.399 | AF115: =AF113-AF116*AF100/1000 -> 67 | AG115: =AG113-AG116*AG100/1000 -> 92.59 | AH115: =AH113-AH116*AH100/1000 -> 48.5 | AI115: =SUM(AE115:AH115) -> 267.489 | AJ115: =AJ113-AJ116*AJ100/1000 -> 27.929 | AK115: =AK113-AK116*AK100/1000 -> 16.608 | AL115: =AL113-AL116*AL100/1000 -> 11.426 | AM115: =AM113-AM116*AM100/1000 -> 7.366 | AN115: =SUM(AJ115:AM115) -> 63.329 | AO115: =AO113-AO116*AO100/1000 -> 14.41 | AP115: =AP113-AP116*AP100/1000 -> 31.232 | AQ115: =AQ113-AQ116*AQ100/1000 -> 22.102 | AR115: =AR113-AR116*AR100/1000 -> 18.456 | AS115: =SUM(AO115:AR115) -> 86.2 | AT115: =AT113-AT116*AT100/1000 -> 27.025 | AU115: =AU113-AU116*AU100/1000 -> 31.44 | AV115: =AV113-AV116*AV100/1000 -> 28.781 | AW115: =AW113-AW116*AW100/1000 -> 26.298 | AX115: =SUM(AT115:AW115) -> 113.544 | AY115: =AY113-AY116*AY100/1000 -> 32.417 | AZ115: =AZ113-AZ116*AZ100/1000 -> 29.942 | BA115: =BA113-BA116*BA100/1000 -> 21.068 | BB115: =BB113-BB116*BB100/1000 -> 18.032 | BC115: =SUM(AY115:BB115) -> 101.459 | BD115: =BD113-BD116*BD100/1000 -> 20.032 | BE115: =BE113-BE116*BE100/1000 -> 20.44 | BF115: =BF113-BF116*BF100/1000 -> 22.763 | BG115: =BG113-BG116*BG100/1000 -> 21.274 | BH115: =SUM(BD115:BG115) -> 84.509 | BI115: =BI113-BI116*BI100/1000 -> 23.299 | BJ115: =BJ113-BJ116*BJ100/1000 -> 21.929 | BK115: =BK113-BK116*BK100/1000 -> 29.324 | BL115: =BL113-BL116*BL100/1000 -> 15 | BM115: =SUM(BI115:BL115) -> 89.552 | BN115: =BN113-BN116*BN100/1000 -> 10.86 | BO115: =BO113-BO116*BO100/1000 -> 8.108 | BP115: =BP113-BP116*BP100/1000 -> 4.344 | BQ115: =BQ113-BQ116*BQ100/1000 -> 6.329 | BR115: =SUM(BN115:BQ115) -> 29.641 | BS115: =BS113-BS116*BS100/1000 -> 2.98 | BT115: =BT113-BT116*BT100/1000 -> 9.5 | BU115: =BU113-BU116*BU100/1000 -> 5.953 | BV115: =BV113-BV116*BV100/1000 -> 3.274 | BW115: =SUM(BS115:BV115) -> 21.707 | BX115: =BX113-BX116*BX100/1000 -> 13.032 | BY115: =BY113-BY116*BY100/1000 -> 11.88 | BZ115: =BZ113-BZ116*BZ100/1000 -> 10.895 | CA115: =CA113-CA116*CA100/1000 -> 10.357 | CB115: =SUM(BX115:CA115) -> 46.164 | CC115: =CD115 -> 12.5 | CD115: =CE115 -> 12.5 | CE115: =CG115/4 -> 12.5 | CF115: =CG115-SUM(CC115:CE115) -> 12.5 | CG115: 50 | CH115: =CI115 -> 12.5 | CI115: =CJ115 -> 12.5 | CJ115: =CL115/4 -> 12.5 | CK115: =CL115-SUM(CH115:CJ115) -> 12.5 | CL115: 50 | CM115: =CN115 -> 12.5 | CN115: =CO115 -> 12.5 | CO115: =CQ115/4 -> 12.5 | CP115: =CQ115-SUM(CM115:CO115) -> 12.5 | CQ115: 50
B116: Revenue Per Ton ( Steel only) $ per ton | D116: 685 | E116: 651 | F116: 638 | G116: 644 | H116: 625 | I116: =((J116*J100)-F116*F100-G100*G116-H116*H100)/I100 -> 615.26923 | J116: 630 | K116: 672 | L116: 779 | M116: 907 | N116: =((O116*O100)-K116*K100-L100*L116-M116*M100)/N100 -> 1083.5053 | O116: 863 | P116: 1165 | Q116: 1302 | R116: 1393 | S116: =((T116*T100)-P116*P100-Q100*Q116-R116*R100)/S100 -> 1456.9007 | T116: 1326 | U116: 1506 | V116: 1479 | W116: 1491 | X116: 1523 | Y116: =(U116*U100+V100*V116+W116*W100+X100*X116)/Y100 -> 1499.2964 | Z116: 1435 | AA116: 1389 | AB116: 1282 | AC116: 1299 | AD116: =(Z116*Z100+AA100*AA116+AB116*AB100+AC100*AC116)/AD100 -> 1334.906 | AE116: 1297 | AF116: 1690 | AG116: 2390 | AH116: 2675 | AI116: =(AE116*AE100+AF100*AF116+AG116*AG100+AH100*AH116)/AI100 -> 2041.2454 | AJ116: 2353 | AK116: 1526 | AL116: 1474 | AM116: 1462 | AN116: =(AJ116*AJ100+AK100*AK116+AL116*AL100+AM100*AM116)/AN100 -> 1754.446 | AO116: 1389 | AP116: 1496 | AQ116: 1559 | AR116: 1504 | AS116: =(AO116*AO100+AP100*AP116+AQ116*AQ100+AR100*AR116)/AS100 -> 1493.746 | AT116: 1447 | AU116: 1565 | AV116: 1699 | AW116: 1711 | AX116: =(AT116*AT100+AU100*AU116+AV116*AV100+AW100*AW116)/AX100 -> 1611.7307 | AY116: 1727 | AZ116: 1706 | BA116: 1676 | BB116: 1624 | BC116: =(AY116*AY100+AZ100*AZ116+BA116*BA100+BB100*BB116)/BC100 -> 1686.9252 | BD116: 1556 | BE116: 1510 | BF116: 1543 | BG116: 1509 | BH116: =(BD116*BD100+BE100*BE116+BF116*BF100+BG100*BG116)/BH100 -> 1529.5908 | BI116: 1479 | BJ116: 1479 | BK116: 1567 | BL116: 1625 | BM116: =(BI116*BI100+BJ100*BJ116+BK116*BK100+BL100*BL116)/BM100 -> 1538.1009 | BN116: 1637 | BO116: 1651 | BP116: 1264 | BQ116: 1273 | BR116: =(BN116*BN100+BO100*BO116+BP116*BP100+BQ100*BQ116)/BR100 -> 1464.3491 | BS116: 1180 | BT116: 1050 | BU116: 1049 | BV116: 1027 | BW116: =(BS116*BS100+BT100*BT116+BU116*BU100+BV100*BV116)/BW100 -> 1070.7325 | BX116: 1097 | BY116: 1234 | BZ116: 1433 | CA116: 1417 | CB116: =(BX116*BX100+BY100*BY116+BZ116*BZ100+CA100*CA116)/CB100 -> 1306.4477 | CC116: ='Price Relationships'!$E$69 -> 1455.8063 | CD116: ='Price Relationships'!$E$70 -> 1586.3849 | CE116: ='Price Relationships'!$E$71 -> 1638.4295 | CF116: ='Price Relationships'!$E$72 -> 1620.4592 | CG116: =(CC116*CC100+CD100*CD116+CE116*CE100+CF100*CF116)/CG100 -> 1584.0876 | CH116: ='Price Relationships'!$E$69 -> 1455.8063 | CI116: ='Price Relationships'!$E$70 -> 1586.3849 | CJ116: ='Price Relationships'!$E$71 -> 1638.4295 | CK116: ='Price Relationships'!$E$72 -> 1620.4592 | CL116: =(CH116*CH100+CI100*CI116+CJ116*CJ100+CK100*CK116)/CL100 -> 1584.0876 | CM116: ='Price Relationships'!$E$69 -> 1455.8063 | CN116: ='Price Relationships'!$E$70 -> 1586.3849 | CO116: ='Price Relationships'!$E$71 -> 1638.4295 | CP116: ='Price Relationships'!$E$72 -> 1620.4592 | CQ116: =(CM116*CM100+CN100*CN116+CO116*CO100+CP100*CP116)/CQ100 -> 1584.0876
C118: Realized Cost per ton | D118: =+D116-D127/D100*1000 -> 674.46848 | E118: =+E116-E127/E100*1000 -> 634.26441 | F118: =+F116-F127/F100*1000 -> 667.45612 | G118: =+G116-G127/G100*1000 -> 649.61533 | H118: =+H116-H127/H100*1000 -> 742.12674 | I118: =+I116-I127/I100*1000 -> 656.36062 | J118: =+J116-J127/J100*1000 -> 642.85473 | K118: =+K116-K127/K100*1000 -> 577.38495 | ... CA118: =+CA116-CA127/CA100*1000 -> 1229.7399 | CB118: =AVERAGE(BX118:CA118) -> 1849.0391 | CC118: =+CC119+CC120 -> 1355 | CD118: =+CD119+CD120 -> 1460 | CE118: =+CE119+CE120 -> 1460 | CF118: =+CF119+CF120 -> 1460 | CG118: =AVERAGE(CC118:CF118) -> 1433.75 | CH118: =+CH119+CH120 -> 1450 | CI118: =+CI119+CI120 -> 1450 | CJ118: =+CJ119+CJ120 -> 1450 | CK118: =+CK119+CK120 -> 1450 | CL118: =AVERAGE(CH118:CK118) -> 1450 | CM118: =+CM119+CM120 -> 1450 | CN118: =+CN119+CN120 -> 1450 | CO118: =+CO119+CO120 -> 1450 | CP118: =+CP119+CP120 -> 1450 | CQ118: =AVERAGE(CM118:CP118) -> 1450
C119: Other Costs | CC119: -45 | CD119: 60 | CE119: 60 | CF119: 60 | CG119: =AVERAGE(CC119:CF119) -> 33.75 | CH119: 50 | CI119: 50 | CJ119: 50 | CK119: 50 | CL119: =AVERAGE(CH119:CK119) -> 50 | CM119: 50 | CN119: 50 | CO119: 50 | CP119: 50 | CQ119: =AVERAGE(CM119:CP119) -> 50
C120: Calculated Costs per ton | BX120: =0.9555*BV118-7677*(BX100/BV100-1)+3700*(BX8/BV8-1) -> 4881.6547 | BY120: =0.9555*BX118-7677*(BY100/BX100-1)+3700*(BY8/BX8-1) -> 1069.775 | BZ120: =0.9555*BY118-7677*(BZ100/BY100-1)+3700*(BZ8/BY8-1) -> 1424.7795 | CA120: =0.9555*BZ118-7677*(CA100/BZ100-1)+3700*(CA8/BZ8-1) -> 1486.7535 | CB120: =AVERAGE(BX120:CA120) -> 2215.7407 | CC120: 1400 | CD120: 1400 | CE120: 1400 | CF120: 1400 | CG120: =AVERAGE(CC120:CF120) -> 1400 | CH120: 1400 | CI120: 1400 | CJ120: 1400 | CK120: 1400 | CL120: =AVERAGE(CH120:CK120) -> 1400 | CM120: 1400 | CN120: 1400 | CO120: 1400 | CP120: 1400 | CQ120: =AVERAGE(CM120:CP120) -> 1400
C121: Substrate Costs | K121: =AVERAGE(K8,E8) -> 462.33333 | L121: =AVERAGE(L8,K8) -> 536.16667 | M121: =AVERAGE(M8,L8) -> 656.66667 | N121: =AVERAGE(N8,M8) -> 680.83333 | O121: =AVERAGE(K121:N121) -> 584 | P121: =AVERAGE(P8,N8) -> 645 | Q121: =AVERAGE(Q8,P8) -> 582.08333 | R121: =AVERAGE(R8,Q8) -> 497.08333 | S121: =AVERAGE(S8,R8) -> 505.83333 | T121: =AVERAGE(P121:S121) -> 557.5 | U121: =AVERAGE(U8,S8) -> 550 | V121: =AVERAGE(V8,U8) -> 570.83333 | W121: =AVERAGE(W8,V8) -> 606.66667 | X121: =AVERAGE(X8,W8) -> 592.5 | Y121: =AVERAGE(U121:X121) -> 580 | Z121: =AVERAGE(Z8,X8) -> 540.83333 | AA121: =AVERAGE(AA8,Z8) -> 535.83333 | AB121: =AVERAGE(AB8,AA8) -> 535 | AC121: =AVERAGE(AC8,AB8) -> 525.83333 | AD121: =AVERAGE(Z121:AC121) -> 534.375 | AE121: =AVERAGE(AE8,AC8) -> 613.33333 | AF121: =AVERAGE(AF8,AE8) -> 834.16667 | AG121: =AVERAGE(AG8,AF8) -> 1014.1667 | AH121: =AVERAGE(AH8,AG8) -> 882.83333 | AI121: =AVERAGE(AE121:AH121) -> 836.125 | AJ121: =AVERAGE(AJ8,AH8) -> 611.33333 | AK121: =AVERAGE(AK8,AJ8) -> 453.83333 | AL121: =AVERAGE(AL8,AK8) -> 445.16667 | AM121: =AVERAGE(AM8,AL8) -> 509.66667 | AN121: =AVERAGE(AJ121:AM121) -> 505 | AO121: =AVERAGE(AO8,AM8) -> 560 | AP121: =AVERAGE(AP8,AO8) -> 637 | AQ121: =AVERAGE(AQ8,AP8) -> 632.33333 | AR121: =AVERAGE(AR8,AQ8) -> 569.83333 | AS121: =AVERAGE(AO121:AR121) -> 599.79167 | AT121: =AVERAGE(AT8,AR8) -> 676.33333 | AU121: =AVERAGE(AU8,AT8) -> 804.33333 | AV121: =AVERAGE(AV8,AU8) -> 750.33391 | AW121: =AVERAGE(AW8,AV8) -> 672.66724 | AX121: =AVERAGE(AT121:AW121) -> 725.91695 | AY121: =AVERAGE(AY8,AW8) -> 689.16667 | AZ121: =AVERAGE(AZ8,AY8) -> 690.33333 | BA121: =AVERAGE(BA8,AZ8) -> 642.83333 | BB121: =AVERAGE(BB8,BA8) -> 622.83268 | BC121: =AVERAGE(AY121:BB121) -> 661.2915 | BD121: =AVERAGE(BD8,BB8) -> 618.33268 | BE121: =AVERAGE(BE8,BD8) -> 604.5 | BF121: =AVERAGE(BF8,BE8) -> 618 | BG121: =AVERAGE(BG8,BF8) -> 651.33187 | BH121: =AVERAGE(BD121:BG121) -> 623.04114 | BI121: =AVERAGE(BI8,BG8) -> 656.83187 | BJ121: =AVERAGE(BJ8,BI8) -> 662.83333 | BK121: =AVERAGE(BK8,BJ8) -> 669.33333 | BL121: =AVERAGE(BL8,BK8) -> 651 | BM121: =AVERAGE(BI121:BL121) -> 659.99964 | BN121: =AVERAGE(BN8,BL8) -> 585.33333 | BO121: =AVERAGE(BO8,BN8) -> 495 | BP121: =AVERAGE(BP8,BO8) -> 456.33333 | BQ121: =AVERAGE(BQ8,BP8) -> 423 | BR121: =AVERAGE(BN121:BQ121) -> 489.91667 | BS121: =AVERAGE(BS8,BQ8) -> 392.66667 | BT121: =AVERAGE(BT8,BS8) -> 480 | BU121: =AVERAGE(BU8,BT8) -> 576.83333 | BV121: =AVERAGE(BV8,BU8) -> 556.5 | BW121: =AVERAGE(BS121:BV121) -> 501.5 | BX121: =AVERAGE(BX8,BV8) -> 571.83333 | BY121: =AVERAGE(BY8,BX8) -> 623.13043 | BZ121: =AVERAGE(BZ8,BY8) -> 622.50634 | CA121: =AVERAGE(CA8,BZ8) -> 619.75669 | CB121: =AVERAGE(BX121:CA121) -> 609.3067 | CC121: =AVERAGE(CC8,CA8) -> 679.58616 | CD121: =AVERAGE(CD8,CC8) -> 813.03872 | CE121: =AVERAGE(CE8,CD8) -> 857.5 | CF121: =AVERAGE(CF8,CE8) -> 807.5 | CG121: =AVERAGE(CC121:CF121) -> 789.40622 | CH121: =AVERAGE(CH8,CF8) -> 792.5 | CI121: =AVERAGE(CI8,CH8) -> 785 | CJ121: =AVERAGE(CJ8,CI8) -> 765 | CK121: =AVERAGE(CK8,CJ8) -> 737.5 | CL121: =AVERAGE(CH121:CK121) -> 770 | CM121: =AVERAGE(CM8,CK8) -> 687.5 | CN121: =AVERAGE(CN8,CM8) -> 667.5 | CO121: =AVERAGE(CO8,CN8) -> 660 | CP121: =AVERAGE(CP8,CO8) -> 645 | CQ121: =AVERAGE(CM121:CP121) -> 665
...

Sheet Financials
A2: US Steel Corporation
A3: Quarterly Income Statement
AE4: =Operations!AE5 -> 39538 | AF4: =Operations!AF5 -> 39629 | AG4: =Operations!AG5 -> 39721 | AH4: =Operations!AH5 -> 39813 | AI4: =Operations!AI5 -> FY8 | AJ4: =Operations!AJ5 -> 39903 | AK4: =Operations!AK5 -> 39994 | AL4: =Operations!AL5 -> 40086 | ... BH4: =Operations!BH5 -> FY13 | BI4: 41729 | BJ4: 41820 | BK4: =Operations!BK5 -> 41912 | BL4: =Operations!BL5 -> 42004 | BM4: =Operations!BM5 -> FY14 | BN4: =Operations!BN5 -> 42094 | BO4: =Operations!BO5 -> 42185 | BP4: =Operations!BP5 -> 42277 | BQ4: =Operations!BQ5 -> 42369 | BR4: =Operations!BR5 -> FY15 | ... CQ4: =Operations!CQ5 -> FY20
F6: 2003 | K6: =O7 -> 2004 | P6: =T7 -> 2005 | U6: =Y7 -> 2006 | Z6: =AD7 -> 2007 | AE6: =AI7 -> 2008 | AJ6: =AN7 -> 2009 | AO6: =AS7 -> 2010 | AT6: =AX7 -> 2011 | AY6: =BC7 -> 2012 | BD6: =BH7 -> 2013 | BI6: =BM7 -> 2014 | BN6: =BR7 -> 2015 | BS6: =BW7 -> 2016 | BX6: =CB7 -> 2017 | CC6: =CG7 -> 2018E | CH6: =CL7 -> 2019E | CM6: =CQ7 -> 2020E
A7: ($ Millions Except Per Share Data) | F7: 1Q | G7: 2Q | H7: 3Q | I7: 4Q | J7: =Operations!J4 -> 2003 | K7: =Operations!K4 -> 1Q | L7: =Operations!L4 -> 2Q | M7: =Operations!M4 -> 3Q | N7: =Operations!N4 -> 4Q | O7: =Operations!O4 -> 2004 | P7: =Operations!P4 -> 1Q | Q7: =Operations!Q4 -> 2Q | ... CQ7: =Operations!CQ4 -> 2020E
A8: Revenues | AT8: 40633 | AU8: 40724 | AV8: 40816 | AW8: 40908 | AY8: 40999 | AZ8: 41090 | BA8: 41182 | BB8: 41274 | BD8: 41364 | BE8: 41455 | BF8: 41547 | BG8: 41639 | BI8: 41729 | BJ8: 41820 | BK8: 41912 | BL8: 42004 | BN8: 42094 | BO8: 42185 | BP8: 42277 | BQ8: 42369 | BS8: 42460 | BT8: 42551 | BU8: 42643 | BV8: 42735 | BX8: 42825 | BY8: 42916 | BZ8: 43008 | CA8: 43100 | CC8: 43190 | CD8: 43281 | CE8: 43373 | CF8: 43465 | CH8: 43555 | CI8: 43646 | CJ8: 43738 | CK8: 43830
B9: Flat rolled Segment | F9: 1055 | G9: 1397 | H9: 1820 | I9: =J9-F9-G9-H9 -> 2129 | J9: 6401 | K9: 2112 | L9: 2510 | M9: 2595 | N9: =O9-K9-L9-M9 -> 2603 | O9: 9820 | P9: 2444 | Q9: 2207 | R9: 2005 | S9: =T9-P9-Q9-R9 -> 2157 | T9: 8813 | U9: =Operations!U49+Operations!U50 -> 2324 | V9: =Operations!V49+Operations!V50 -> 2581 | W9: =Operations!W49+Operations!W50 -> 2545 | X9: =Operations!X49+Operations!X50 -> 2157 | Y9: =SUM(U9:X9) -> 9607 | Z9: =Operations!Z48 -> 2189 | AA9: =Operations!AA48 -> 2509 | AB9: =Operations!AB48 -> 2439 | AC9: =Operations!AC48 -> 2747 | AD9: =SUM(Z9:AC9) -> 9884 | AE9: =Operations!AE48 -> 3155 | AF9: =Operations!AF48 -> 4010 | AG9: =Operations!AG48 -> 4303 | AH9: =Operations!AH48 -> 2363 | AI9: =SUM(AE9:AH9) -> 13831 | AJ9: =Operations!AJ48 -> 1592 | AK9: =Operations!AK48 -> 1310 | AL9: =Operations!AL48 -> 1745 | AM9: =Operations!AM48 -> 2167 | AN9: =SUM(AJ9:AM9) -> 6814 | AO9: =Operations!AO48 -> 2455 | AP9: =Operations!AP48 -> 2963 | AQ9: =Operations!AQ48 -> 2763 | AR9: =Operations!AR48 -> 2667 | AS9: =SUM(AO9:AR9) -> 10848 | AT9: =Operations!AT48 -> 2969 | AU9: =Operations!AU48 -> 3304 | AV9: =Operations!AV48 -> 3136 | AW9: =Operations!AW48 -> 2958 | AX9: =SUM(AT9:AW9) -> 12367 | AY9: =Operations!AY48 -> 3300 | AZ9: =Operations!AZ48 -> 3356 | BA9: =Operations!BA48 -> 3142 | BB9: =Operations!BB48 -> 3110 | BC9: =SUM(AY9:BB9) -> 12908 | BD9: =Operations!BD48 -> 3103 | BE9: =Operations!BE48 -> 2876 | BF9: =Operations!BF48 -> 2731 | BG9: =Operations!BG48 -> 2862 | BH9: =SUM(BD9:BG9) -> 11572 | BI9: =Operations!BI48 -> 3025 | BJ9: =Operations!BJ48 -> 2938 | BK9: =Operations!BK48 -> 3125 | BL9: =Operations!BL48 -> 2619 | BM9: =SUM(BI9:BL9) -> 11707 | BN9: =Operations!BN48 -> 2194 | BO9: =Operations!BO48 -> 2125 | BP9: =Operations!BP48 -> 2070 | BQ9: =Operations!BQ48 -> 1904 | BR9: =SUM(BN9:BQ9) -> 8293 | BS9: =Operations!BS48 -> 1748 | BT9: =Operations!BT48 -> 1926 | BU9: =Operations!BU48 -> 1986 | BV9: =Operations!BV48 -> 1873 | BW9: =SUM(BS9:BV9) -> 7533 | BX9: =Operations!BX48 -> 1886 | BY9: =Operations!BY48 -> 2243 | BZ9: =Operations!BZ48 -> 2291 | CA9: =Operations!CA48 -> 2071 | CB9: =SUM(BX9:CA9) -> 8491 | CC9: =Operations!CC48 -> 2017.3163 | CD9: =Operations!CD48 -> 2212.8619 | CE9: =Operations!CE48 -> 2502.5213 | CF9: =Operations!CF48 -> 2467.4876 | CG9: =SUM(CC9:CF9) -> 9200.1871 | CH9: =Operations!CH48 -> 2497.4003 | CI9: =Operations!CI48 -> 2589.6386 | CJ9: =Operations!CJ48 -> 2563.0913 | CK9: =Operations!CK48 -> 2461.727 | CL9: =SUM(CH9:CK9) -> 10111.857 | CM9: =Operations!CM48 -> 2347.4631 | CN9: =Operations!CN48 -> 2399.5528 | CO9: =Operations!CO48 -> 2334.7372 | CP9: =Operations!CP48 -> 2249.4287 | CQ9: =SUM(CM9:CP9) -> 9331.1817
B10: USSE Segment | F10: 426 | G10: 467 | H10: 440 | I10: =J10-F10-G10-H10 -> 484 | J10: 1817 | K10: 514 | L10: 654 | M10: 780 | N10: =O10-K10-L10-M10 -> 885 | O10: 2833 | P10: 901 | Q10: 893 | R10: 725 | S10: =T10-P10-Q10-R10 -> 817 | T10: 3336 | U10: =Operations!U152 -> 854 | V10: =Operations!V152 -> 1003 | W10: =Operations!W152 -> 1036 | X10: =Operations!X152 -> 1075 | Y10: =SUM(U10:X10) -> 3968 | Z10: =Operations!Z152 -> 1160 | AA10: =Operations!AA152 -> 1239 | AB10: =Operations!AB152 -> 1167 | AC10: =Operations!AC152 -> 1101 | AD10: =SUM(Z10:AC10) -> 4667 | AE10: =Operations!AE152 -> 1356 | AF10: =Operations!AF152 -> 1760 | AG10: =Operations!AG152 -> 1598 | AH10: =Operations!AH152 -> 773 | AI10: =SUM(AE10:AH10) -> 5487 | AJ10: =Operations!AJ152 -> 622 | AK10: =Operations!AK152 -> 645 | AL10: =Operations!AL152 -> 822 | AM10: =Operations!AM152 -> 855 | AN10: =SUM(AJ10:AM10) -> 2944 | AO10: =Operations!AO152 -> 964 | AP10: =Operations!AP152 -> 985 | AQ10: =Operations!AQ152 -> 1034 | AR10: =Operations!AR152 -> 1006 | AS10: =SUM(AO10:AR10) -> 3989 | AT10: =Operations!AT152 -> 1223 | AU10: =Operations!AU152 -> 1096 | AV10: =Operations!AV152 -> 1072 | AW10: =Operations!AW152 -> 915 | AX10: =SUM(AT10:AW10) -> 4306 | AY10: =Operations!AY152 -> 815 | AZ10: =Operations!AZ152 -> 763 | BA10: =Operations!BA152 -> 696 | BB10: =Operations!BB152 -> 675 | BC10: =SUM(AY10:BB10) -> 2949 | BD10: =Operations!BD152 -> 783 | BE10: =Operations!BE152 -> 778 | BF10: =Operations!BF152 -> 643 | BG10: =Operations!BG152 -> 737 | BH10: =SUM(BD10:BG10) -> 2941 | BI10: =Operations!BI152 -> 759 | BJ10: =Operations!BJ152 -> 757 | BK10: =Operations!BK152 -> 687 | BL10: =Operations!BL152 -> 688 | BM10: =SUM(BI10:BL10) -> 2891 | BN10: =Operations!BN152 -> 691 | BO10: =Operations!BO152 -> 600 | BP10: =Operations!BP152 -> 546 | BQ10: =Operations!BQ152 -> 486 | BR10: =SUM(BN10:BQ10) -> 2323 | BS10: =Operations!BS152 -> 477 | BT10: =Operations!BT152 -> 566 | BU10: =Operations!BU152 -> 576 | BV10: =Operations!BV152 -> 628 | BW10: =SUM(BS10:BV10) -> 2247 | BX10: =Operations!BX152 -> 686 | BY10: =Operations!BY152 -> 752 | BZ10: =Operations!BZ152 -> 711 | CA10: =Operations!CA152 -> 826 | CB10: =SUM(BX10:CA10) -> 2975 | CC10: =Operations!CC152 -> 835.58653 | CD10: =Operations!CD152 -> 888.13265 | CE10: =Operations!CE152 -> 798.18114 | CF10: =Operations!CF152 -> 893.23986 | CG10: =SUM(CC10:CF10) -> 3415.1402 | CH10: =Operations!CH152 -> 835.58653 | CI10: =Operations!CI152 -> 888.13265 | CJ10: =Operations!CJ152 -> 798.18114 | CK10: =Operations!CK152 -> 893.23986 | CL10: =SUM(CH10:CK10) -> 3415.1402 | CM10: =Operations!CM152 -> 835.58653 | CN10: =Operations!CN152 -> 888.13265 | CO10: =Operations!CO152 -> 798.18114 | CP10: =Operations!CP152 -> 893.23986 | CQ10: =SUM(CM10:CP10) -> 3415.1402
B11: Tubular Segment | F11: 136 | G11: 140 | H11: 149 | I11: =J11-F11-G11-H11 -> 148 | J11: 573 | K11: 190 | L11: 198 | M11: 246 | N11: =O11-K11-L11-M11 -> 314 | O11: 948 | P11: 357 | Q11: 396 | R11: 368 | S11: =T11-P11-Q11-R11 -> 425 | T11: 1546 | U11: =Operations!U113 -> 485 | V11: =Operations!V113 -> 444 | W11: =Operations!W113 -> 455 | X11: =Operations!X113 -> 414 | Y11: =SUM(U11:X11) -> 1798 | Z11: =Operations!Z113 -> 356 | AA11: =Operations!AA113 -> 405 | AB11: =Operations!AB113 -> 637 | AC11: =Operations!AC113 -> 587 | AD11: =SUM(Z11:AC11) -> 1985 | AE11: =Operations!AE113 -> 621 | AF11: =Operations!AF113 -> 912 | AG11: =Operations!AG113 -> 1333 | AH11: =Operations!AH113 -> 1386 | AI11: =SUM(AE11:AH11) -> 4252 | AJ11: =Operations!AJ113 -> 515 | AK11: =Operations!AK113 -> 157 | AL11: =Operations!AL113 -> 234 | AM11: =Operations!AM113 -> 310 | AN11: =SUM(AJ11:AM11) -> 1216 | AO11: =Operations!AO113 -> 445 | AP11: =Operations!AP113 -> 679 | AQ11: =Operations!AQ113 -> 680 | AR11: =Operations!AR113 -> 599 | AS11: =SUM(AO11:AR11) -> 2403 | AT11: =Operations!AT113 -> 642 | AU11: =Operations!AU113 -> 695 | AV11: =Operations!AV113 -> 846 | AW11: =Operations!AW113 -> 851 | AX11: =SUM(AT11:AW11) -> 3034 | AY11: =Operations!AY113 -> 946 | AZ11: =Operations!AZ113 -> 871 | BA11: =Operations!BA113 -> 787 | BB11: =Operations!BB113 -> 679 | BC11: =SUM(AY11:BB11) -> 3283 | BD11: =Operations!BD113 -> 686 | BE11: =Operations!BE113 -> 709 | BF11: =Operations!BF113 -> 731 | BG11: =Operations!BG113 -> 646 | BH11: =SUM(BD11:BG11) -> 2772 | BI11: =Operations!BI113 -> 643 | BJ11: =Operations!BJ113 -> 686 | BK11: =Operations!BK113 -> 700 | BL11: =Operations!BL113 -> 743 | BM11: =SUM(BI11:BL11) -> 2772 | BN11: =Operations!BN113 -> 371 | BO11: =Operations!BO113 -> 160 | BP11: =Operations!BP113 -> 199 | BQ11: =Operations!BQ113 -> 168 | BR11: =SUM(BN11:BQ11) -> 898 | BS11: =Operations!BS113 -> 108 | BT11: =Operations!BT113 -> 83 | BU11: =Operations!BU113 -> 114 | BV11: =Operations!BV113 -> 145 | BW11: =SUM(BS11:BV11) -> 450 | BX11: =Operations!BX113 -> 171 | BY11: =Operations!BY113 -> 234 | BZ11: =Operations!BZ113 -> 276 | CA11: =Operations!CA113 -> 264 | CB11: =SUM(BX11:CA11) -> 945 | CC11: =Operations!CC113 -> 232.61791 | CD11: =Operations!CD113 -> 355.15913 | CE11: =Operations!CE113 -> 376.23134 | CF11: =Operations!CF113 -> 317.06531 | CG11: =SUM(CC11:CF11) -> 1281.0737 | CH11: =Operations!CH113 -> 239.22145 | CI11: =Operations!CI113 -> 365.43891 | CJ11: =Operations!CJ113 -> 387.14328 | CK11: =Operations!CK113 -> 326.20227 | CL11: =SUM(CH11:CK11) -> 1318.0059 | CM11: =Operations!CM113 -> 246.02309 | CN11: =Operations!CN113 -> 376.02707 | CO11: =Operations!CO113 -> 398.38258 | CP11: =Operations!CP113 -> 335.61334 | CQ11: =SUM(CM11:CP11) -> 1356.0461
B12: Other Businesses | F12: =25+27+229 -> 281 | G12: =35+24+248 -> 307 | H12: =36+19+42 -> 97 | I12: =J12-F12-G12-H12 -> -148 | J12: =87+138+312 -> 537 | K12: =15+75 -> 90 | L12: =10+76 -> 86 | M12: =11+75 -> 86 | N12: =O12-K12-L12-M12 -> 106 | O12: =47+321 -> 368 | P12: =59 -> 59 | Q12: =86 -> 86 | R12: =102 -> 102 | S12: =T12-P12-Q12-R12 -> 97 | T12: =344 -> 344 | U12: =63 -> 63 | V12: =79 -> 79 | W12: =70 -> 70 | X12: =Y12-SUM(U12:W12) -> 130 | Y12: 342 | Z12: 51 | AA12: 75 | AB12: =4354-AB9-AB10-AB11 -> 111 | AC12: 100 | AD12: =SUM(Z12:AC12) -> 337 | AE12: =5196-AE9-AE10-AE11 -> 64 | AF12: =6744-AF11-AF10-AF9 -> 62 | AG12: =7312-AG11-AG10-AG9 -> 78 | AH12: =4565-AH11-AH10-AH9 -> 43 | AI12: =SUM(AE12:AH12) -> 247 | AJ12: =2750-AJ11-AJ10-AJ9 -> 21 | AK12: =2127-AK11-AK10-AK9 -> 15 | AL12: =AL14-AL9-AL10-AL11 -> 16 | AM12: =AM14-AM9-AM10-AM11 -> 22 | AN12: =SUM(AJ12:AM12) -> 74 | AO12: =AO14-AO9-AO10-AO11 -> 32 | AP12: =AP14-AP9-AP10-AP11 -> 54 | AQ12: =AQ14-AQ9-AQ10-AQ11 -> 20 | AR12: =AR14-AR9-AR10-AR11 -> 28 | AS12: =SUM(AO12:AR12) -> 134 | AT12: =AT14-AT9-AT10-AT11 -> 30 | AU12: =AU14-AU9-AU10-AU11 -> 25 | AV12: =AV14-AV9-AV10-AV11 -> 27 | AW12: =AW14-AW9-AW10-AW11 -> 95 | AX12: =SUM(AT12:AW12) -> 177 | AY12: =AY14-AY9-AY10-AY11 -> 111 | AZ12: =AZ14-AZ9-AZ10-AZ11 -> 27 | BA12: =BA14-BA9-BA10-BA11 -> 27 | BB12: =BB14-BB9-BB10-BB11 -> 23 | BC12: =SUM(AY12:BB12) -> 188 | BD12: =BD14-BD9-BD10-BD11 -> 23 | BE12: =BE14-BE9-BE10-BE11 -> 66 | BF12: =BF14-BF9-BF10-BF11 -> 26 | BG12: =BG14-BG9-BG10-BG11 -> 24 | BH12: =SUM(BD12:BG12) -> 139 | BI12: =BI14-BI9-BI10-BI11 -> 21 | BJ12: =BJ14-BJ9-BJ10-BJ11 -> 19 | BK12: =BK14-BK9-BK10-BK11 -> 75 | BL12: =BL14-BL9-BL10-BL11 -> 22 | BM12: =SUM(BI12:BL12) -> 137 | BN12: =BN14-BN9-BN10-BN11 -> 16 | BO12: =BO14-BO9-BO10-BO11 -> 15 | BP12: =BP14-BP9-BP10-BP11 -> 15 | BQ12: =BQ14-BQ9-BQ10-BQ11 -> 14 | BR12: =SUM(BN12:BQ12) -> 60 | BS12: =BS14-BS9-BS10-BS11 -> 8 | BT12: =BT14-BT9-BT10-BT11 -> 9 | BU12: =BU14-BU9-BU10-BU11 -> 10 | BV12: =BV14-BV9-BV10-BV11 -> 4 | BW12: =SUM(BS12:BV12) -> 31 | BX12: =BX14-BX9-BX10-BX11 -> -18 | BY12: =BY14-BY9-BY10-BY11 -> -85 | BZ12: =BZ14-BZ9-BZ10-BZ11 -> -30 | CA12: =CA14-CA9-CA10-CA11 -> -28 | CB12: =SUM(BX12:CA12) -> -161 | CC12: 50 | CD12: =CC12 -> 50 | CE12: =CD12 -> 50 | CF12: =CE12 -> 50 | CG12: =SUM(CC12:CF12) -> 200 | CH12: 50 | CI12: =CH12 -> 50 | CJ12: =CI12 -> 50 | CK12: =CJ12 -> 50 | CL12: =SUM(CH12:CK12) -> 200 | CM12: 50 | CN12: =CM12 -> 50 | CO12: =CN12 -> 50 | CP12: =CO12 -> 50 | CQ12: =SUM(CM12:CP12) -> 200
N13: =O13-K13-L13-M13 -> 0
C14: Total Net Sales | F14: =SUM(F9:F12) -> 1898 | G14: =SUM(G9:G12) -> 2311 | H14: =SUM(H9:H12) -> 2506 | I14: =SUM(I9:I12) -> 2613 | J14: =SUM(J9:J12) -> 9328 | K14: =SUM(K9:K12) -> 2906 | L14: =SUM(L9:L12) -> 3448 | M14: =SUM(M9:M12) -> 3707 | ... R14: =SUM(R9:R12) -> 3200 | S14: =T14-P14-Q14-R14 -> 3496 | T14: =SUM(T9:T12) -> 14039 | U14: =SUM(U9:U12) -> 3726 | V14: =SUM(V9:V13) -> 4107 | W14: =SUM(W9:W12) -> 4106 | X14: =SUM(X9:X12) -> 3776 | Y14: =SUM(Y9:Y12) -> 15715 | Z14: =3756 -> 3756 | AA14: 4228 | AB14: =SUM(AB9:AB12) -> 4354 | AC14: =SUM(AC9:AC12) -> 4535 | AD14: =SUM(AD9:AD12) -> 16873 | AE14: =SUM(AE9:AE13) -> 5196 | AF14: =SUM(AF9:AF13) -> 6744 | AG14: =SUM(AG9:AG12) -> 7312 | AH14: =SUM(AH9:AH12) -> 4565 | AI14: =SUM(AI9:AI12) -> 23817 | AJ14: =SUM(AJ9:AJ12) -> 2750 | AK14: =SUM(AK9:AK13) -> 2127 | AL14: 2817 | AM14: 3354 | AN14: =SUM(AN9:AN12) -> 11048 | AO14: 3896 | AP14: 4681 | AQ14: 4497 | AR14: 4300 | AS14: =SUM(AS9:AS12) -> 17374 | AT14: 4864 | AU14: 5120 | AV14: 5081 | AW14: 4819 | AX14: =SUM(AX9:AX12) -> 19884 | AY14: 5172 | AZ14: 5017 | BA14: 4652 | BB14: 4487 | BC14: =SUM(BC9:BC12) -> 19328 | BD14: 4595 | BE14: 4429 | BF14: 4131 | BG14: 4269 | BH14: =SUM(BH9:BH12) -> 17424 | BI14: 4448 | BJ14: 4400 | BK14: 4587 | BL14: 4072 | BM14: =SUM(BM9:BM12) -> 17507 | BN14: 3272 | BO14: 2900 | BP14: 2830 | BQ14: =11574-SUM(BN14:BP14) -> 2572 | BR14: =SUM(BR9:BR12) -> 11574 | BS14: 2341 | BT14: 2584 | BU14: 2686 | BV14: 2650 | BW14: =SUM(BW9:BW12) -> 10261 | BX14: 2725 | BY14: 3144 | BZ14: 3248 | CA14: 3133 | CB14: =SUM(CB9:CB12) -> 12250 | CC14: =SUM(CC9:CC13) -> 3135.5207 | CD14: =SUM(CD9:CD13) -> 3506.1536 | CE14: =SUM(CE9:CE12) -> 3726.9338 | CF14: =SUM(CF9:CF12) -> 3727.7928 | CG14: =SUM(CG9:CG12) -> 14096.401 | CH14: =SUM(CH9:CH13) -> 3622.2083 | CI14: =SUM(CI9:CI13) -> 3893.2101 | CJ14: =SUM(CJ9:CJ12) -> 3798.4157 | CK14: =SUM(CK9:CK12) -> 3731.1691 | CL14: =SUM(CL9:CL12) -> 15045.003 | CM14: =SUM(CM9:CM13) -> 3479.0727 | CN14: =SUM(CN9:CN13) -> 3713.7125 | CO14: =SUM(CO9:CO12) -> 3581.3009 | CP14: =SUM(CP9:CP12) -> 3528.2819 | CQ14: =SUM(CQ9:CQ12) -> 14302.368
C15: Annual Growth % | K15: =K14/F14-1 -> 0.53108535 | L15: =L14/G14-1 -> 0.49199481 | M15: =M14/H14-1 -> 0.4792498 | N15: =N14/I14-1 -> 0.49559893 | O15: =O14/J14-1 -> 0.49753431 | P15: =P14/K14-1 -> 0.29421886 | Q15: =Q14/L14-1 -> 0.038863109 | R15: =R14/M14-1 -> -0.13676828 | ... CQ15: =CQ14/CL14-1 -> -0.049360927
C16: Seq. Growth % | G16: =G14/F14-1 -> 0.21759747 | H16: =H14/G14-1 -> 0.084379057 | I16: =I14/H14-1 -> 0.042697526 | K16: =K14/I14-1 -> 0.11213165 | L16: =L14/K14-1 -> 0.18651067 | M16: =M14/L14-1 -> 0.075116009 | N16: =N14/M14-1 -> 0.054221743 | P16: =P14/N14-1 -> -0.037615148 | Q16: =Q14/P14-1 -> -0.047593725 | R16: =R14/Q14-1 -> -0.10664433 | S16: =S14/R14-1 -> 0.0925 | U16: =U14/S14-1 -> 0.065789474 | V16: =V14/U14-1 -> 0.10225443 | W16: =W14/V14-1 -> -0.00024348673 | X16: =X14/W14-1 -> -0.08037019 | Z16: =Z14/X14-1 -> -0.0052966102 | AA16: =AA14/Z14-1 -> 0.1256656 | AB16: =AB14/AA14-1 -> 0.029801325 | AC16: =AC14/AB14-1 -> 0.041570969 | AE16: =AE14/AC14-1 -> 0.14575524 | AF16: =AF14/AE14-1 -> 0.29792148 | AG16: =AG14/AF14-1 -> 0.084223013 | AH16: =AH14/AG14-1 -> -0.37568381 | AJ16: =AJ14/AH14-1 -> -0.39759036 | AK16: =AK14/AJ14-1 -> -0.22654545 | AL16: =AL14/AK14-1 -> 0.32440056 | AM16: =AM14/AL14-1 -> 0.19062833 | AO16: =AO14/AM14-1 -> 0.16159809 | AP16: =AP14/AO14-1 -> 0.20148871 | AQ16: =AQ14/AP14-1 -> -0.03930784 | AR16: =AR14/AQ14-1 -> -0.043806982 | AT16: =AT14/AR14-1 -> 0.13116279 | AU16: =AU14/AT14-1 -> 0.052631579 | AV16: =AV14/AU14-1 -> -0.0076171875 | AW16: =AW14/AV14-1 -> -0.051564653 | AY16: =AY14/AW14-1 -> 0.073251712 | AZ16: =AZ14/AY14-1 -> -0.029969064 | BA16: =BA14/AZ14-1 -> -0.072752641 | BB16: =BB14/BA14-1 -> -0.035468616 | BD16: =BD14/BB14-1 -> 0.024069534 | BE16: =BE14/BD14-1 -> -0.036126224 | BF16: =BF14/BE14-1 -> -0.067283811 | BG16: =BG14/BF14-1 -> 0.033405955 | BI16: =BI14/BG14-1 -> 0.041930194 | BJ16: =BJ14/BI14-1 -> -0.010791367 | BK16: =BK14/BJ14-1 -> 0.0425 | BL16: =BL14/BK14-1 -> -0.11227382 | BN16: =BN14/BL14-1 -> -0.19646365 | BO16: =BO14/BN14-1 -> -0.11369193 | BP16: =BP14/BO14-1 -> -0.024137931 | BQ16: =BQ14/BP14-1 -> -0.091166078 | BS16: =BS14/BQ14-1 -> -0.089813375 | BT16: =BT14/BS14-1 -> 0.10380179 | BU16: =BU14/BT14-1 -> 0.039473684 | BV16: =BV14/BU14-1 -> -0.013402829 | BX16: =BX14/BV14-1 -> 0.028301887 | BY16: =BY14/BX14-1 -> 0.15376147 | BZ16: =BZ14/BY14-1 -> 0.03307888 | CA16: =CA14/BZ14-1 -> -0.035406404 | CC16: =CC14/CA14-1 -> 0.00080457737 | CD16: =CD14/CC14-1 -> 0.11820458 | CE16: =CE14/CD14-1 -> 0.06296932 | CF16: =CF14/CE14-1 -> 0.00023049968 | CH16: =CH14/CF14-1 -> -0.028323591 | CI16: =CI14/CH14-1 -> 0.074816728 | CJ16: =CJ14/CI14-1 -> -0.024348649 | CK16: =CK14/CJ14-1 -> -0.017703858 | CM16: =CM14/CK14-1 -> -0.06756499 | CN16: =CN14/CM14-1 -> 0.067443196 | CO16: =CO14/CN14-1 -> -0.035654775 | CP16: =CP14/CO14-1 -> -0.014804401
