Workbook
Name __FDS_USED_FOR_REUSING_RANGE_IDS_RECYCLE: {2371,2371,2371,2371,2371,2371,2371,2371,2371,2371,2371,2371,2371,2371,2371,2371,2371,2371,2371,2371,2371,2371,2371,2371,2371,2371,2371,2371,2371,2371,2371,2371,2371,2371}
Name _Switch: DCF!$B$5
Name _Toggle: DCF!$A$5
Name actual_start_year: 1992
Name AdditionalInstructions: IndexInformation!$B$42
Name Address: ImportantDisclosures!$A$2:$A$2
Name admin: 1
Name AllTables: {1}
Name ANA: ModPubIndex!$A$7
Name AssetsCurrentDeferredIncomeTaxes: 0
Name AssetsCurrentShortTermInvestments: 0
Name AssetsIntangiblesAccumulatedAmortization: 0
Name AssetsIntangiblesGross: 0
Name AssetsOtherAccumulatedAmortization: 0
Name AssetsOtherGross: 0
Name AssetsOtherNet: 0
Name Authors: ImportantDisclosures!$A$7
Name Authors: IndexInformation!$B$18
Name BRO: ModPubIndex!$A$1
Name case_num: 1
Name CashFlowCapitalExpenditureCellular: 0
Name CashFlowCapitalExpenditureOther: 0
Name CashFlowCapitalExpenditurePaging: 0
Name CashFlowCapitalExpenditureTelephone: 0
Name CashFlowCapitalExpenditureWireless: 0
Name CashFlowDividendPaidPreferredStock: 0
Name chart: "Chart 1"
Name Class_B: 68.45
Name cm: 1
Name CopyrightStamp: ImportantDisclosures!$A$29
Name COU: ModPubIndex!$A$5
Name CQEnd: IndexInformation!$B$31
Name Currency: IndexInformation!$B$24
Name CurrentStockPrice: IndexInformation!$B$23
Name CurrQtrEPS: IndexInformation!$B$29
Name CurrYearEPS: IndexInformation!$B$11
Name CurrYearTotalRevenue: IndexInformation!$B$10
Name CurrYearTotalRevenueActual: IndexInformation!$B$32
Name CUSIP: IndexInformation!$B$20
Name CYEnd: IndexInformation!$B$30
Name Date: ImportantDisclosures!$A$8
Name DB: "WIRENYPROD"
Name dd: {"Jan","Feb","Mar","Apr","May","Jun","Jul","Aug","Sep","Oct","Nov","Dec";"January","February","March","April","May","June","July","August","September","October","November","December"}
Name Deleted: IndexInformation!$B$27
Name Description: IndexInformation!$B$7
Name DEVELOPMENT: 5
Name Discipline: IndexInformation!$B$3
Name DISCIPLINE: ModPubIndex!$A$12
Name DisclosuresText: ImportantDisclosures!$A$24
Name Distribution: IndexInformation!$B$26
Name DistTable: ImportantDisclosures!#REF!
Name DistTablePreamble: ImportantDisclosures!#REF!
Name DOCDAT: ModPubIndex!$A$2
Name DOCTIME: ModPubIndex!$A$3
Name DocType: IndexInformation!$B$5
Name EMAIL_ALERT: ModPubIndex!$A$10
Name EmailAlert: IndexInformation!$B$28
Name EquityAdjustments: 0
Name EquityEmployeeStockOwnershipPlan: 0
Name EquityPaidInCapital: 0

Sheet ImportantDisclosures
A2: 1585 Broadway
A3: New York, NY 10036-8293
A4: United States
A5: Tel: +1 (1)212 761 4000
A7: Authors: James Faucette, Vasundhara Govil, Brian Nowak, Priscilla Russo
A8: Date: 26 Apr 2018
A10: Ticker: PYPL.O
A11: Stock Rating: Overweight
A12: Industry: Payments and Processing
A13: Industry View: In-Line
A14: Price as of 26 Apr 2018: 74.00
A15: Target Price: 89
... A125: Equal-weight and Not-Rated to hold and Underweight to sell recommendations, respectively.
B127: Coverage Universe | D127: Investment Banking Clients (IBC) | G127: Other Material Investment Services Clients (MISC)
A128: Stock Rating Category | B128: Count | C128: % of Total | D128: Count | E128: % of Total IBC | F128: % of Rating Category | G128: Count | H128: % of Total Other MISC
A129: Overweight/Buy | B129: 1189 | C129: 0.38 | D129: 315 | E129: 0.41 | F129: 0.26 | G129: 555 | H129: 0.39
A130: Equal-weight/Hold | B130: 1355 | C130: 0.43 | D130: 364 | E130: 0.47 | F130: 0.27 | G130: 644 | H130: 0.45
A131: Not-Rated/Hold | B131: 53 | C131: 0.02 | D131: 4 | E131: 0.01 | F131: 0.08 | G131: 7 | H131: 0
A132: Underweight/Sell | B132: 545 | C132: 0.17 | D132: 84 | E132: 0.11 | F132: 0.15 | G132: 214 | H132: 0.15
A133: Total | B133: 3142 | D133: 767 | G133: 1420
A135: Data include common stock and ADRs currently assigned ratings. Investment Banking Clients are companies
A136: from whom Morgan Stanley received investment banking compensation in the last 12 months. Due to rounding
A137: off of decimals, the percentages provided in the "% of total" column may not add up to exactly 100
A138: percent.
A140: Analyst Stock Ratings
A142: Overweight (O). The stock's total return is expected to exceed the average total return of the analyst's
A143: industry (or industry team's) coverage universe, on a risk-adjusted basis, over the next 12-18 months.
A145: Equal-weight (E). The stock's total return is expected to be in line with the average total return of
A146: the analyst's industry (or industry team's) coverage universe, on a risk-adjusted basis, over the next
A147: 12-18 months.
A149: Not-Rated (NR). Currently the analyst does not have adequate conviction about the stock's total return
A150: relative to the average total return of the analyst's industry (or industry team's) coverage universe,
... A396: © Copyright 2018 Morgan Stanley

Sheet Portfolio Manager's Snapshot
B2: James Faucette | H2: Vasu Govil | L2: Priscilla Russo
B3: Executive Director | H3: Vice President | L3: Associate
B4: 212-296-5771 | H4: 212-761-3609 | L4: 212-296-4563
B5: james.faucette@morganstanley.com | H5: vasundhara.govil@morganstanley.com | L5: priscilla.russo@morganstanley.com
B7: Scenario:
B9: PayPal Holdings, Inc. (PYPL)
B11: Financials (FY ended December) | H11: MS Estimates vs. Guidance (YoY % change)
C12: 2016A | D12: 2017A | E12: 2018E | F12: 2019E | H12: F18 | I12: MS | J12: Guidance
B13: Revenue
B14: ='Segment Detail'!B45 -> Transaction Revenue | C14: =+'Segment Detail'!BE45 -> 9585 | D14: =+'Segment Detail'!BJ45 -> 11501 | E14: =+'Segment Detail'!BO45 -> 13995.271 | F14: =+'Segment Detail'!BT45 -> 16676.021 | H14: TPV Growth | I14: ='Segment Detail'!BO7 -> 0.28803568
B15: ='Segment Detail'!B49 -> Other Value-Added Services Revenue | C15: =+'Segment Detail'!BE49 -> 1257 | D15: =+'Segment Detail'!BJ49 -> 1593 | E15: =+'Segment Detail'!BO49 -> 1413.9363 | F15: =+'Segment Detail'!BT49 -> 1078.7399
H16: Revenue Growth | I16: ='Quarterly Model'!BO15 -> 0.18032993 | J16: 16-18%
B17: Net Revenue | C17: =+C14+C15 -> 10842 | D17: =+D14+D15 -> 13094 | E17: =+E14+E15 -> 15409.207 | F17: =+F14+F15 -> 17754.761
B18: YoY % change | C18: =+'Segment Detail'!BE58 -> 0.17236159 | D18: =+'Segment Detail'!BJ58 -> 0.20771075 | E18: =+'Segment Detail'!BO58 -> 0.17681436 | F18: =+'Segment Detail'!BT58 -> 0.15221767 | H18: Non-GAAP Operating Margin | I18: ='Quarterly Model'!BO78 -> 0.22288082
B20: EBITDA (MS method) | C20: =+'Quarterly Model'!BE88 -> 2439 | D20: =+'Quarterly Model'!BJ88 -> 2788 | E20: =+'Quarterly Model'!BO88 -> 2989.6504 | F20: =+'Quarterly Model'!BT88 -> 3599.2249 | H20: Adj. Net Income | I20: ='Quarterly Model'!BO104 -> 2835.8217
B21: EBITDA Margin | C21: =+'Quarterly Model'!BE89 -> 0.10212381 | D21: =+'Quarterly Model'!BJ89 -> 0.14309143 | E21: =+'Quarterly Model'!BO89 -> 0.072327963 | F21: =+'Quarterly Model'!BT89 -> 0.20389492
H22: Adj. EPS | I22: ='Quarterly Model'!BO105 -> 2.3370818 | J22: $2.31-2.34
B23: Operating Income | C23: ='Quarterly Model'!BE76 -> 2174 | D23: ='Quarterly Model'!BJ76 -> 2755 | E23: ='Quarterly Model'!BO76 -> 3434.4167 | F23: ='Quarterly Model'!BT76 -> 4085.5105
B24: Operating Margin | C24: ='Quarterly Model'!BE78 -> 0.20051651 | D24: ='Quarterly Model'!BJ78 -> 0.21103026 | E24: ='Quarterly Model'!BO78 -> 0.22288082 | F24: ='Quarterly Model'!BT78 -> 0.23010789
B26: GAAP Net Income | C26: ='Quarterly Model'!BE137 -> 1402 | D26: ='Quarterly Model'!BJ137 -> 1795 | E26: ='Quarterly Model'!BO137 -> 1935.0938 | F26: ='Quarterly Model'!BT137 -> 2338.5776
B27: YoY % change | C27: 0.15581204 | D27: =D26/C26-1 -> 0.28031384 | E27: =E26/D26-1 -> 0.078046677 | F27: =F26/E26-1 -> 0.20850869
B29: Adjusted Net Income (PayPal Method) | C29: ='Quarterly Model'!BE104 -> 1825 | D29: ='Quarterly Model'!BJ104 -> 2318 | E29: ='Quarterly Model'!BO104 -> 2835.8217 | F29: ='Quarterly Model'!BT104 -> 3288.836
B30: YoY % change | C30: 0.16297345 | D30: =D29/C29-1 -> 0.27013699 | E30: =E29/D29-1 -> 0.22339158 | F30: =F29/E29-1 -> 0.1597471
B32: Adjusted EPS (PayPal Method) | C32: ='Quarterly Model'!BE105 -> 1.4989733 | D32: ='Quarterly Model'!BJ105 -> 1.8992216 | E32: ='Quarterly Model'!BO105 -> 2.3370818 | F32: ='Quarterly Model'!BT105 -> 2.7298345
B33: YoY % change | C33: 0.1725256 | D33: =D32/C32-1 -> 0.26701498 | E33: =E32/D32-1 -> 0.23054716 | F33: =F32/E32-1 -> 0.16805261
B35: Capex | C35: =+'Quarterly Model'!BE180 -> -669 | D35: =+'Quarterly Model'!BJ180 -> -667 | E35: =+'Quarterly Model'!BO180 -> -852.14191 | F35: =+'Quarterly Model'!BT180 -> -976.51184
B36: Capex % of sales | C36: =+'Portfolio Manager''s Snapshot'!C35/'Portfolio Manager''s Snapshot'!C17 -> -0.061704483 | D36: =+'Portfolio Manager''s Snapshot'!D35/'Portfolio Manager''s Snapshot'!D17 -> -0.050939362 | E36: =+'Portfolio Manager''s Snapshot'!E35/'Portfolio Manager''s Snapshot'!E17 -> -0.055300828 | F36: =+'Portfolio Manager''s Snapshot'!F35/'Portfolio Manager''s Snapshot'!F17 -> -0.055
B37: FCFF | C37: =+DCF!G72 -> 1577.3339 | D37: =+DCF!H72 -> 811.77489 | E37: =+DCF!I72 -> 853.5269 | F37: =+DCF!J72 -> 1944.5126
B39: Total assets | C39: =+'Quarterly Model'!BE235 -> 33103 | D39: =+'Quarterly Model'!BJ235 -> 40774 | E39: =+'Quarterly Model'!BO235 -> 43675.527 | F39: =+'Quarterly Model'!BT235 -> 45355.89
B40: Total cash | C40: ='Quarterly Model'!BE220 -> 1590 | D40: ='Quarterly Model'!BJ220 -> 2883 | E40: ='Quarterly Model'!BO220 -> 10141.845 | F40: ='Quarterly Model'!BT220 -> 12035.811
B42: Total liabilities | C42: =+'Quarterly Model'!BE247 -> 18391 | D42: =+'Quarterly Model'!BJ247 -> 24780 | E42: =+'Quarterly Model'!BO247 -> 28043.667 | F42: =+'Quarterly Model'!BT247 -> 27920.167
B43: Total debt | C43: =+'Quarterly Model'!BE259 -> 0 | D43: =+'Quarterly Model'!BJ259 -> 1000 | E43: =+'Quarterly Model'!BO259 -> 3000 | F43: =+'Quarterly Model'!BT259 -> 3000
B44: Total shareholder's equity | C44: =+'Quarterly Model'!BE254 -> 14712 | D44: =+'Quarterly Model'!BJ254 -> 15994 | E44: =+'Quarterly Model'!BO254 -> 15631.86 | F44: =+'Quarterly Model'!BT254 -> 17435.723

Sheet Quarterly Model
B2: Scenario:
C3: 1Q06A | D3: 2Q06A | E3: 3Q06A | F3: 4Q06A | G3: 2006A | H3: 1Q07A | I3: 2Q07A | J3: 3Q07A | K3: 4Q07A | L3: 2007A | M3: 1Q08A | N3: 2Q08A | O3: 3Q08A | P3: 4Q08A | Q3: 2008A | R3: 1Q09A | S3: 2Q09A | T3: 3Q09A | U3: 4Q09A | V3: 2009A | W3: 1Q10A | X3: 2Q10A | Y3: 3Q10A | Z3: 4Q10A | AA3: 2010A | AB3: 1Q11A | AC3: 2Q11A | AD3: 3Q11A | AE3: 4Q11A | AF3: 2011A | AG3: 1Q12A | AH3: 2Q12A | AI3: 3Q12A | AJ3: 4Q12A | AK3: 2012A | AL3: 1Q13A | AM3: 2Q13A | AN3: 3Q13A | AO3: 4Q13A | AP3: 2013A | AQ3: 1Q14A | AR3: 2Q14A | AS3: 3Q14A | AT3: 4Q14A | AU3: 2014A | AV3: 1Q15A | AW3: 2Q15A | AX3: 3Q15A | AY3: 4Q15A | AZ3: 2015A | BA3: 1Q16A | BB3: 2Q16A | BC3: 3Q16A | BD3: 4Q16A | BE3: 2016A | BF3: 1Q17A | BG3: 2Q17A | BH3: 3Q17A | BI3: 4Q17A | BJ3: 2017A | BK3: 1Q18A | BL3: 2Q18E | BM3: 3Q18E | BN3: 4Q18E | BO3: 2018E | BP3: 1Q19E | BQ3: 2Q19E | BR3: 3Q19E | BS3: 4Q19E | BT3: 2019E | BU3: 1Q20E | BV3: 2Q20E | BW3: 3Q20E | BX3: 4Q20E | BY3: 2020E | BZ3: 1Q21E | CA3: 2Q21E | CB3: 3Q21E | CC3: 4Q21E | CD3: 2021E
B4: Income Statement
B5: Fiscal Year End: December ($ in millions, except per share data)
B8: Transaction Revenue | AK8: ='Segment Detail'!AK45 -> 5028 | AP8: ='Segment Detail'!AP45 -> 5992 | AQ8: ='Segment Detail'!AQ45 -> 1671 | AR8: ='Segment Detail'!AR45 -> 1710 | AS8: ='Segment Detail'!AS45 -> 1750 | AT8: ='Segment Detail'!AT45 -> 1963 | AU8: ='Segment Detail'!AU45 -> 7094 | AV8: ='Segment Detail'!AV45 -> 1911 | AW8: ='Segment Detail'!AW45 -> 1966 | ... CD8: ='Segment Detail'!CD45 -> 22411.783
B9: YoY % change | AP9: =IF(ISERROR((AP8/AK8-1)),"NM",(AP8/AK8-1)) -> 0.19172633 | AQ9: =IF(ISERROR((AQ8/AL8-1)),"NM",(AQ8/AL8-1)) -> NM | AU9: =IF(ISERROR((AU8/AP8-1)),"NM",(AU8/AP8-1)) -> 0.18391188 | AV9: =IF(ISERROR((AV8/AQ8-1)),"NM",(AV8/AQ8-1)) -> 0.14362657 | AW9: =IF(ISERROR((AW8/AR8-1)),"NM",(AW8/AR8-1)) -> 0.1497076 | AX9: =IF(ISERROR((AX8/AS8-1)),"NM",(AX8/AS8-1)) -> 0.14514286 | AY9: =IF(ISERROR((AY8/AT8-1)),"NM",(AY8/AT8-1)) -> 0.16454407 | AZ9: =IF(ISERROR((AZ8/AU8-1)),"NM",(AZ8/AU8-1)) -> 0.15830279 | BA9: =IF(ISERROR((BA8/AV8-1)),"NM",(BA8/AV8-1)) -> 0.1826269 | BB9: =IF(ISERROR((BB8/AW8-1)),"NM",(BB8/AW8-1)) -> 0.19379451 | ... CD9: =IF(ISERROR((CD8/BY8-1)),"NM",(CD8/BY8-1)) -> 0.1556825
B11: Other Value-added Services | AK11: ='Segment Detail'!AK49 -> 634 | AP11: ='Segment Detail'!AP49 -> 735 | AQ11: ='Segment Detail'!AQ49 -> 200 | AR11: ='Segment Detail'!AR49 -> 271 | AS11: ='Segment Detail'!AS49 -> 221 | AT11: ='Segment Detail'!AT49 -> 226 | AU11: ='Segment Detail'!AU49 -> 918 | AV11: ='Segment Detail'!AV49 -> 223 | AW11: ='Segment Detail'!AW49 -> 327 | ... BH11: ='Segment Detail'!BH49 -> 381 | BI11: ='Segment Detail'!BI49-39 -> 461 | BJ11: ='Segment Detail'!BJ49-39 -> 1554 | BK11: ='Segment Detail'!BK49 -> 488 | BL11: ='Segment Detail'!BL49 -> 452.98511 | BM11: ='Segment Detail'!BM49 -> 173.69852 | BN11: ='Segment Detail'!BN49 -> 299.25267 | BO11: ='Segment Detail'!BO49 -> 1413.9363 | BP11: ='Segment Detail'!BP49 -> 283.4 | BQ11: ='Segment Detail'!BQ49 -> 237.2575 | BR11: ='Segment Detail'!BR49 -> 204.96425 | ... CD11: ='Segment Detail'!CD49 -> 1439.039
B12: YoY % change | AP12: =IF(ISERROR((AP11/AK11-1)),"NM",(AP11/AK11-1)) -> 0.15930599 | AQ12: =IF(ISERROR((AQ11/AL11-1)),"NM",(AQ11/AL11-1)) -> NM | AU12: =IF(ISERROR((AU11/AP11-1)),"NM",(AU11/AP11-1)) -> 0.24897959 | AV12: =IF(ISERROR((AV11/AQ11-1)),"NM",(AV11/AQ11-1)) -> 0.115 | AW12: =IF(ISERROR((AW11/AR11-1)),"NM",(AW11/AR11-1)) -> 0.20664207 | AX12: =IF(ISERROR((AX11/AS11-1)),"NM",(AX11/AS11-1)) -> 0.14932127 | AY12: =IF(ISERROR((AY11/AT11-1)),"NM",(AY11/AT11-1)) -> 0.19469027 | AZ12: =IF(ISERROR((AZ11/AU11-1)),"NM",(AZ11/AU11-1)) -> 0.12309368 | BA12: =IF(ISERROR((BA11/AV11-1)),"NM",(BA11/AV11-1)) -> 0.2735426 | BB12: =IF(ISERROR((BB11/AW11-1)),"NM",(BB11/AW11-1)) -> -0.073394495 | ... CD12: =IF(ISERROR((CD11/BY11-1)),"NM",(CD11/BY11-1)) -> 0.15
B14: Net Revenue | AK14: =IF(ISERROR(AK11+AK8),"NM",AK11+AK8) -> 5662 | AL14: =IF(ISERROR(AL11+AL8),"NM",AL11+AL8) -> 0 | AM14: =IF(ISERROR(AM11+AM8),"NM",AM11+AM8) -> 0 | AN14: =IF(ISERROR(AN11+AN8),"NM",AN11+AN8) -> 0 | AO14: =IF(ISERROR(AO11+AO8),"NM",AO11+AO8) -> 0 | AP14: =IF(ISERROR(AP11+AP8),"NM",AP11+AP8) -> 6727 | AQ14: =IF(ISERROR(AQ11+AQ8),"NM",AQ11+AQ8) -> 1871 | AR14: =IF(ISERROR(AR11+AR8),"NM",AR11+AR8) -> 1981 | ... CD14: =IF(ISERROR(CD11+CD8),"NM",CD11+CD8) -> 23850.822 | CE14: =(BY14/BE14)^0.25-1 -> 0.17468444
B15: YoY % change | AP15: =IF(ISERROR((AP14/AK14-1)),"NM",(AP14/AK14-1)) -> 0.18809608 | AQ15: =IF(ISERROR(AQ14/AL14-1), "NM", (AQ14/AL14-1)) -> NM | AR15: =IF(ISERROR(AR14/AM14-1), "NM", (AR14/AM14-1)) -> NM | AS15: =IF(ISERROR(AS14/AN14-1), "NM", (AS14/AN14-1)) -> NM | AT15: =IF(ISERROR(AT14/AO14-1), "NM", (AT14/AO14-1)) -> NM | AU15: =IF(ISERROR((AU14/AP14-1)),"NM",(AU14/AP14-1)) -> 0.19102126 | AV15: =IF(ISERROR(AV14/AQ14-1), "NM", (AV14/AQ14-1)) -> 0.14056654 | AW15: =IF(ISERROR(AW14/AR14-1), "NM", (AW14/AR14-1)) -> 0.15749621 | AX15: =IF(ISERROR(AX14/AS14-1), "NM", (AX14/AS14-1)) -> 0.14561136 | AY15: =IF(ISERROR(AY14/AT14-1), "NM", (AY14/AT14-1)) -> 0.16765646 | AZ15: =IF(ISERROR(AZ14/AU14-1), "NM", (AZ14/AU14-1)) -> 0.1542686 | BA15: =IF(ISERROR(BA14/AV14-1), "NM", (BA14/AV14-1)) -> 0.19212746 | BB15: =IF(ISERROR(BB14/AW14-1), "NM", (BB14/AW14-1)) -> 0.15569123 | BC15: =IF(ISERROR(BC14/AX14-1), "NM", (BC14/AX14-1)) -> 0.18113375 | ... CD15: =IF(ISERROR(CD14/BY14-1), "NM", (CD14/BY14-1)) -> 0.15533806
B16: YoY % change (FX neutral) | AV16: 0.17 | AW16: 0.19 | AX16: 0.19 | AY16: 0.21 | AZ16: 0.19 | BA16: 0.23 | BB16: 0.19 | BC16: 0.21 | BD16: 0.19 | BF16: 0.19 | BG16: 0.2 | BH16: 0.22 | BK16: 0.22
B18: Transaction Expense | AK18: 1518 | AP18: 1835 | AQ18: 514 | AR18: 525 | AS18: 537 | AT18: 594 | AU18: =SUM(AQ18:AT18) -> 2170 | AV18: 575 | AW18: 634 | AX18: 651 | AY18: 750 | AZ18: =SUM(AV18:AY18) -> 2610 | BA18: 752 | BB18: 810 | BC18: 830 | BD18: 954 | BE18: =SUM(BA18:BD18) -> 3346 | BF18: 987 | BG18: 1064 | BH18: 1102 | BI18: 1266 | BJ18: =SUM(BF18:BI18) -> 4419 | BK18: 1275 | BL18: =BL20*'Segment Detail'!BL6 -> 1363.6012 | BM18: =BM20*'Segment Detail'!BM6 -> 1430.3215 | BN18: =BN20*'Segment Detail'!BN6 -> 1634.1717 | BO18: =SUM(BK18:BN18) -> 5703.0945 | BP18: =BP20*'Segment Detail'!BP6 -> 1588.3017 | BQ18: =BQ20*'Segment Detail'!BQ6 -> 1691.7633 | BR18: =BR20*'Segment Detail'!BR6 -> 1774.4938 | BS18: =BS20*'Segment Detail'!BS6 -> 2027.3427 | BT18: =SUM(BP18:BS18) -> 7081.9015 | BU18: =BU20*'Segment Detail'!BU6 -> 1926.433 | BV18: =BV20*'Segment Detail'!BV6 -> 2052.9003 | BW18: =BW20*'Segment Detail'!BW6 -> 2118.4087 | BX18: =BX20*'Segment Detail'!BX6 -> 2421.4055 | BY18: =SUM(BU18:BX18) -> 8519.1475 | BZ18: =BZ20*'Segment Detail'!BZ6 -> 2281.2991 | CA18: =CA20*'Segment Detail'!CA6 -> 2430.9746 | CB18: =CB20*'Segment Detail'!CB6 -> 2508.4568 | CC18: =CC20*'Segment Detail'!CC6 -> 2867.1394 | CD18: =SUM(BZ18:CC18) -> 10087.87
B19: YoY % change | AP19: =IF(ISERROR((AP18/AK18-1)),"NM",(AP18/AK18-1)) -> 0.2088274 | AQ19: =IF(ISERROR((AQ18/AL18-1)),"NM",(AQ18/AL18-1)) -> NM | AR19: =IF(ISERROR((AR18/AM18-1)),"NM",(AR18/AM18-1)) -> NM | AS19: =IF(ISERROR((AS18/AN18-1)),"NM",(AS18/AN18-1)) -> NM | AT19: =IF(ISERROR((AT18/AO18-1)),"NM",(AT18/AO18-1)) -> NM | AU19: =IF(ISERROR((AU18/AP18-1)),"NM",(AU18/AP18-1)) -> 0.18256131 | AV19: =IF(ISERROR(AV18/AQ18-1), "NM", (AV18/AQ18-1)) -> 0.11867704 | AW19: =IF(ISERROR(AW18/AR18-1), "NM", (AW18/AR18-1)) -> 0.20761905 | AX19: =IF(ISERROR(AX18/AS18-1), "NM", (AX18/AS18-1)) -> 0.2122905 | AY19: =IF(ISERROR(AY18/AT18-1), "NM", (AY18/AT18-1)) -> 0.26262626 | AZ19: =IF(ISERROR(AZ18/AU18-1), "NM", (AZ18/AU18-1)) -> 0.20276498 | BA19: =IF(ISERROR(BA18/AV18-1), "NM", (BA18/AV18-1)) -> 0.30782609 | BB19: =IF(ISERROR(BB18/AW18-1), "NM", (BB18/AW18-1)) -> 0.27760252 | BC19: =IF(ISERROR(BC18/AX18-1), "NM", (BC18/AX18-1)) -> 0.2749616 | ... CD19: =IF(ISERROR(CD18/BY18-1), "NM", (CD18/BY18-1)) -> 0.18414079
B20: As a % of TPV | AK20: =AK18/'Segment Detail'!AK$6 -> 0.010115549 | AP20: =AP18/'Segment Detail'!AP$6 -> 0.0098865338 | AQ20: =AQ18/'Segment Detail'!AQ$6 -> 0.0095759744 | AR20: =AR18/'Segment Detail'!AR$6 -> 0.0092533841 | AS20: =AS18/'Segment Detail'!AS$6 -> 0.0092293414 | AT20: =AT18/'Segment Detail'!AT$6 -> 0.008994685 | AU20: =AU18/'Segment Detail'!AU$6 -> 0.0092484071 | AV20: =AV18/'Segment Detail'!AV$6 -> 0.0091239428 | AW20: =AW18/'Segment Detail'!AW$6 -> 0.009395098 | ... AY20: =AY18/'Segment Detail'!AY$6 -> 0.0090250535 | AZ20: =AZ18/'Segment Detail'!AZ6 -> 0.0090613044 | BA20: =BA18/'Segment Detail'!BA$6 -> 0.0091086375 | BB20: =BB18/'Segment Detail'!BB$6 -> 0.0092294019 | BC20: =BC18/'Segment Detail'!BC$6 -> 0.0093368581 | BD20: =BD18/'Segment Detail'!BD$6 -> 0.0094726495 | BE20: =BE18/'Segment Detail'!BE6 -> 0.0092963037 | BF20: =BF18/'Segment Detail'!BF$6 -> 0.0098073312 | BG20: =BG18/'Segment Detail'!BG$6 -> 0.0098701299 | BH20: =BH18/'Segment Detail'!BH$6 -> 0.0095639797 | BI20: =BI18/'Segment Detail'!BI$6 -> 0.0095536354 | BJ20: =BJ18/'Segment Detail'!BJ6 -> 0.0096870081 | BK20: =BK18/'Segment Detail'!BK$6 -> 0.0096325285 | BL20: =CHOOSE(_Switch,BL21,BL22,BL23) -> 0.0097011117 | BM20: =CHOOSE(_Switch,BM21,BM22,BM23) -> 0.0097261117 | BN20: =CHOOSE(_Switch,BN21,BN22,BN23) -> 0.0097511117 | BO20: =BO18/'Segment Detail'!BO6 -> 0.0097061799 | BP20: =CHOOSE(_Switch,BP21,BP22,BP23) -> 0.0097761117 | BQ20: =CHOOSE(_Switch,BQ21,BQ22,BQ23) -> 0.0098011117 | BR20: =CHOOSE(_Switch,BR21,BR22,BR23) -> 0.0098261117 | BS20: =CHOOSE(_Switch,BS21,BS22,BS23) -> 0.0098511117 | BT20: =BT18/'Segment Detail'!BT6 -> 0.0098160022 | BU20: =CHOOSE(_Switch,BU21,BU22,BU23) -> 0.0098811117 | BV20: =CHOOSE(_Switch,BV21,BV22,BV23) -> 0.0099111117 | BW20: =CHOOSE(_Switch,BW21,BW22,BW23) -> 0.0099411117 | BX20: =CHOOSE(_Switch,BX21,BX22,BX23) -> 0.0099711117 | BY20: =BY18/'Segment Detail'!BY6 -> 0.0099287271 | BZ20: =CHOOSE(_Switch,BZ21,BZ22,BZ23) -> 0.010001112 | CA20: =CHOOSE(_Switch,CA21,CA22,CA23) -> 0.010031112 | CB20: =CHOOSE(_Switch,CB21,CB22,CB23) -> 0.010061112 | CC20: =CHOOSE(_Switch,CC21,CC22,CC23) -> 0.010091112 | CD20: =CD18/'Segment Detail'!CD6 -> 0.010048727
B21: Bull | BL21: =+BL22-0.0001 -> 0.0096011117 | BM21: =+BM22-0.0001 -> 0.0096261117 | BN21: =+BN22-0.0001 -> 0.0096511117 | BP21: =+BP22-0.0001 -> 0.0096761117 | BQ21: =+BQ22-0.0001 -> 0.0097011117 | BR21: =+BR22-0.0001 -> 0.0097261117 | BS21: =+BS22-0.0001 -> 0.0097511117 | BU21: =+BU22-0.0001 -> 0.0097811117 | BV21: =+BV22-0.0001 -> 0.0098111117 | BW21: =+BW22-0.0001 -> 0.0098411117 | BX21: =+BX22-0.0001 -> 0.0098711117 | BZ21: =+BZ22-0.0001 -> 0.0099011117 | CA21: =+CA22-0.0001 -> 0.0099311117 | CB21: =+CB22-0.0001 -> 0.0099611117 | CC21: =+CC22-0.0001 -> 0.0099911117
B22: Base | BL22: 0.0097011117 | BM22: =+BL22+0.000025 -> 0.0097261117 | BN22: =+BM22+0.000025 -> 0.0097511117 | BP22: =+BN22+0.000025 -> 0.0097761117 | BQ22: =+BP22+0.000025 -> 0.0098011117 | BR22: =+BQ22+0.000025 -> 0.0098261117 | BS22: =+BR22+0.000025 -> 0.0098511117 | BU22: =+BS22+0.00003 -> 0.0098811117 | BV22: =+BU22+0.00003 -> 0.0099111117 | BW22: =+BV22+0.00003 -> 0.0099411117 | BX22: =+BW22+0.00003 -> 0.0099711117 | BZ22: =+BX22+0.00003 -> 0.010001112 | CA22: =+BZ22+0.00003 -> 0.010031112 | CB22: =+CA22+0.00003 -> 0.010061112 | CC22: =+CB22+0.00003 -> 0.010091112
B23: Bear | BL23: =BL22+0.01% -> 0.0098011117 | BM23: =BM22+0.01% -> 0.0098261117 | BN23: =BN22+0.01% -> 0.0098511117 | BP23: =BP22+0.01% -> 0.0098761117 | BQ23: =BQ22+0.01% -> 0.0099011117 | BR23: =BR22+0.01% -> 0.0099261117 | BS23: =BS22+0.01% -> 0.0099511117 | BU23: =BU22+0.01% -> 0.0099811117 | BV23: =BV22+0.01% -> 0.010011112 | BW23: =BW22+0.01% -> 0.010041112 | BX23: =BX22+0.01% -> 0.010071112 | BZ23: =BZ22+0.01% -> 0.010101112 | CA23: =CA22+0.01% -> 0.010131112 | CB23: =CB22+0.01% -> 0.010161112 | CC23: =CC22+0.01% -> 0.010191112
B25: Transaction and Loan Losses | AK25: 365 | AP25: 502 | AQ25: =129+12 -> 141 | AR25: =144+10 -> 154 | AS25: =180+10 -> 190 | AT25: =193+11 -> 204 | AU25: =SUM(AQ25:AT25) -> 689 | AV25: =178+10 -> 188 | AW25: =185+12 -> 197 | AX25: 201 | AY25: 245 | AZ25: =SUM(AV25:AY25) -> 831 | BA25: 255 | BB25: 255 | BC25: 271 | BD25: 307 | BE25: =SUM(BA25:BD25) -> 1088 | BF25: 300 | BG25: 308 | BH25: 363 | BI25: 40 | BJ25: =SUM(BF25:BI25) -> 1011 | BK25: 305 | BL25: =BL27*'Segment Detail'!BL$6 -> 323.29108 | BM25: =BM27*'Segment Detail'!BM$6 -> 338.2379 | BN25: =BN27*'Segment Detail'!BN$6 -> 385.45297 | BO25: =SUM(BK25:BN25) -> 1351.9819 | BP25: =BP27*'Segment Detail'!BP$6 -> 369.61386 | BQ25: =BQ27*'Segment Detail'!BQ$6 -> 392.68621 | BR25: =BR27*'Segment Detail'!BR$6 -> 410.84139 | BS25: =BS27*'Segment Detail'!BS$6 -> 468.19129 | BT25: =SUM(BP25:BS25) -> 1641.3328 | BU25: =BU27*'Segment Detail'!BU$6 -> 443.53664 | BV25: =BV27*'Segment Detail'!BV$6 -> 471.22345 | BW25: =BW27*'Segment Detail'!BW$6 -> 484.79285 | BX25: =BX27*'Segment Detail'!BX$6 -> 552.46572 | BY25: =SUM(BU25:BX25) -> 1952.0187 | BZ25: =BZ27*'Segment Detail'!BZ$6 -> 518.93786 | CA25: =CA27*'Segment Detail'!CA$6 -> 551.33144 | CB25: =CB27*'Segment Detail'!CB$6 -> 567.20763 | CC25: =CC27*'Segment Detail'!CC$6 -> 646.38489 | CD25: =SUM(BZ25:CC25) -> 2283.8618
B26: YoY % change | AP26: =IF(ISERROR(AP25/AK25-1), "NM", (AP25/AK25-1)) -> 0.37534247 | AQ26: =IF(ISERROR(AQ25/AL25-1), "NM", (AQ25/AL25-1)) -> NM | AR26: =IF(ISERROR(AR25/AM25-1), "NM", (AR25/AM25-1)) -> NM | AS26: =IF(ISERROR(AS25/AN25-1), "NM", (AS25/AN25-1)) -> NM | AT26: =IF(ISERROR(AT25/AO25-1), "NM", (AT25/AO25-1)) -> NM | AU26: =IF(ISERROR(AU25/AP25-1), "NM", (AU25/AP25-1)) -> 0.37250996 | AV26: =IF(ISERROR(AV25/AQ25-1), "NM", (AV25/AQ25-1)) -> 0.33333333 | AW26: =IF(ISERROR(AW25/AR25-1), "NM", (AW25/AR25-1)) -> 0.27922078 | ... CD26: =IF(ISERROR(CD25/BY25-1), "NM", (CD25/BY25-1)) -> 0.17
B27: As a % of TPV | AK27: =AK25/'Segment Detail'!AK$6 -> 0.0024322631 | AP27: =AP25/'Segment Detail'!AP$6 -> 0.0027046539 | AQ27: =AQ25/'Segment Detail'!AQ$6 -> 0.0026268723 | AR27: =AR25/'Segment Detail'!AR$6 -> 0.002714326 | AS27: =AS25/'Segment Detail'!AS$6 -> 0.0032655025 | AT27: =AT25/'Segment Detail'!AT$6 -> 0.0030890837 | AU27: =AU25/'Segment Detail'!AU$6 -> 0.0029364758 | AV27: =AV25/'Segment Detail'!AV$6 -> 0.0029831326 | AW27: =AW25/'Segment Detail'!AW$6 -> 0.002919297 | ... BK27: =BK25/'Segment Detail'!BK$6 -> 0.0023042519 | BL27: =CHOOSE(_Switch,BL28,BL29,BL30) -> 0.0023 | BM27: =CHOOSE(_Switch,BM28,BM29,BM30) -> 0.0023 | BN27: =CHOOSE(_Switch,BN28,BN29,BN30) -> 0.0023 | BO27: =BO25/'Segment Detail'!BO$6 -> 0.0023009578 | BP27: =CHOOSE(_Switch,BP28,BP29,BP30) -> 0.002275 | BQ27: =CHOOSE(_Switch,BQ28,BQ29,BQ30) -> 0.002275 | BR27: =CHOOSE(_Switch,BR28,BR29,BR30) -> 0.002275 | BS27: =CHOOSE(_Switch,BS28,BS29,BS30) -> 0.002275 | BT27: =BT25/'Segment Detail'!BT$6 -> 0.002275 | BU27: =CHOOSE(_Switch,BU28,BU29,BU30) -> 0.002275 | BV27: =CHOOSE(_Switch,BV28,BV29,BV30) -> 0.002275 | BW27: =CHOOSE(_Switch,BW28,BW29,BW30) -> 0.002275 | BX27: =CHOOSE(_Switch,BX28,BX29,BX30) -> 0.002275 | BY27: =BY25/'Segment Detail'!BY$6 -> 0.002275 | BZ27: =CHOOSE(_Switch,BZ28,BZ29,BZ30) -> 0.002275 | CA27: =CHOOSE(_Switch,CA28,CA29,CA30) -> 0.002275 | CB27: =CHOOSE(_Switch,CB28,CB29,CB30) -> 0.002275 | CC27: =CHOOSE(_Switch,CC28,CC29,CC30) -> 0.002275 | CD27: =CD25/'Segment Detail'!CD$6 -> 0.002275
B28: Bull | BL28: =BL29-0.005% -> 0.00225 | BM28: =BM29-0.005% -> 0.00225 | BN28: =BN29-0.005% -> 0.00225 | BP28: =BP29-0.005% -> 0.002225 | BQ28: =BQ29-0.005% -> 0.002225 | BR28: =BR29-0.005% -> 0.002225 | BS28: =BS29-0.005% -> 0.002225 | BU28: =BU29-0.005% -> 0.002225 | BV28: =BV29-0.005% -> 0.002225 | BW28: =BW29-0.005% -> 0.002225 | BX28: =BX29-0.005% -> 0.002225 | BZ28: =BZ29-0.005% -> 0.002225 | CA28: =CA29-0.005% -> 0.002225 | CB28: =CB29-0.005% -> 0.002225 | CC28: =CC29-0.005% -> 0.002225
B29: Base | BL29: 0.0023 | BM29: =BL29 -> 0.0023 | BN29: =BM29 -> 0.0023 | BP29: =BN29-0.000025 -> 0.002275 | BQ29: =BP29 -> 0.002275 | BR29: =BQ29 -> 0.002275 | BS29: =BR29 -> 0.002275 | BU29: =BS29 -> 0.002275 | BV29: =BU29 -> 0.002275 | BW29: =BV29 -> 0.002275 | BX29: =BW29 -> 0.002275 | BZ29: =BX29 -> 0.002275 | CA29: =BZ29 -> 0.002275 | CB29: =CA29 -> 0.002275 | CC29: =CB29 -> 0.002275 | CE29: =(CD18+CD25+CD37+CD44+CD51+CD58+CD72)/'Take Rate Drivers'!BY6 -> 0.020806383
B30: Bear | BL30: =BL29+0.015% -> 0.00245 | BM30: =BM29+0.015% -> 0.00245 | BN30: =BN29+0.015% -> 0.00245 | BP30: =BP29+0.015% -> 0.002425 | BQ30: =BQ29+0.015% -> 0.002425 | BR30: =BR29+0.015% -> 0.002425 | BS30: =BS29+0.015% -> 0.002425 | BU30: =BU29+0.015% -> 0.002425 | BV30: =BV29+0.015% -> 0.002425 | BW30: =BW29+0.015% -> 0.002425 | BX30: =BX29+0.015% -> 0.002425 | BZ30: =BZ29+0.015% -> 0.002425 | CA30: =CA29+0.015% -> 0.002425 | CB30: =CB29+0.015% -> 0.002425 | CC30: =CC29+0.015% -> 0.002425
B31: Loan Losses (included in above) | AK31: 134 | AP31: 194 | AQ31: 49 | AU31: 239 | AV31: 71
B33: Gross Profit | AK33: =AK14-AK18-AK25 -> 3779 | AL33: =AL14-AL18-AL25 -> 0 | AM33: =AM14-AM18-AM25 -> 0 | AN33: =AN14-AN18-AN25 -> 0 | AO33: =AO14-AO18-AO25 -> 0 | AP33: =AP14-AP18-AP25 -> 4390 | AQ33: =AQ14-AQ18-AQ25 -> 1216 | AR33: =AR14-AR18-AR25 -> 1302 | ... CD33: =CD14-CD18-CD25 -> 11479.09
B34: Gross Profit Margin ("Transaction Margin") | AK34: =AK33/AK14 -> 0.667432 | AP34: =AP33/AP14 -> 0.65259402 | AQ34: =AQ33/AQ14 -> 0.64991983 | AR34: =AR33/AR14 -> 0.65724382 | AS34: =AS33/AS14 -> 0.6311517 | AT34: =AT33/AT14 -> 0.63544998 | AU34: =AU33/AU14 -> 0.64316026 | AV34: =AV33/AV14 -> 0.64245548 | AW34: =AW33/AW14 -> 0.63759267 | ... CD34: =CD33/CD14 -> 0.48128698
B35: As a % of TPV | AU35: =+AU33/'Segment Detail'!AU6 -> 0.02196177 | AV35: =+AV33/'Segment Detail'!AV6 -> 0.021754653 | AW35: =+AW33/'Segment Detail'!AW6 -> 0.021665037 | AX35: =+AX33/'Segment Detail'!AX6 -> 0.019714795 | AY35: =+AY33/'Segment Detail'!AY6 -> 0.018784145 | AZ35: =+AZ33/'Segment Detail'!AZ6 -> 0.020160534 | BA35: =+BA33/'Segment Detail'!BA6 -> 0.018616989 | BB35: =+BB33/'Segment Detail'!BB6 -> 0.018060003 | ... CD35: =+CD33/'Segment Detail'!CD6 -> 0.011434549
B37: Customer Support and Operations | AK37: =814-49 -> 765 | AP37: =950-74 -> 876 | AQ37: =237-15+2 -> 224 | AR37: =246-12+2 -> 236 | AS37: =244-12+4 -> 236 | AT37: =264-13+5 -> 256 | AU37: =SUM(AQ37:AT37) -> 952 | AV37: =249-14+3 -> 238 | AW37: =278+5-17 -> 266 | AX37: =284-16 -> 268 | AY37: =299-18 -> 281 | AZ37: =SUM(AV37:AY37) -> 1053 | BA37: =296-18 -> 278 | BB37: =318-22 -> 296 | BC37: =325-21 -> 304 | BD37: =328-24 -> 304 | BE37: =SUM(BA37:BD37) -> 1182 | BF37: =317-30 -> 287 | BG37: =335-34 -> 301 | BH37: =346-38 -> 308 | BI37: =366-40 -> 326 | BJ37: =SUM(BF37:BI37) -> 1222 | BK37: =351-38 -> 313 | BL37: =BL39*BL$14 -> 328.52405 | BM37: =BM39*BM$14 -> 302.4296 | BN37: =BN39*BN$14 -> 341.40268 | BO37: =SUM(BK37:BN37) -> 1285.3563 | BP37: =BP39*BP$14 -> 341.26929 | BQ37: =BQ39*BQ$14 -> 335.22471 | BR37: =BR39*BR$14 -> 330.08756 | BS37: =BS39*BS$14 -> 371.94023 | BT37: =SUM(BP37:BS37) -> 1378.5218 | BU37: =BU39*BU$14 -> 365.56097 | BV37: =BV39*BV$14 -> 358.44768 | BW37: =BW39*BW$14 -> 345.35737 | BX37: =BX39*BX$14 -> 389.39483 | BY37: =SUM(BU37:BX37) -> 1458.7608 | BZ37: =BZ39*BZ$14 -> 373.49579 | CA37: =CA39*CA$14 -> 363.91453 | CB37: =CB39*CB$14 -> 350.65045 | CC37: =CC39*CC$14 -> 394.20011 | CD37: =SUM(BZ37:CC37) -> 1482.2609
B38: YoY % change | AP38: =IF(ISERROR(AP37/AK37-1), "NM", (AP37/AK37-1)) -> 0.14509804 | AQ38: =IF(ISERROR(AQ37/AL37-1), "NM", (AQ37/AL37-1)) -> NM | AR38: =IF(ISERROR(AR37/AM37-1), "NM", (AR37/AM37-1)) -> NM | AS38: =IF(ISERROR(AS37/AN37-1), "NM", (AS37/AN37-1)) -> NM | AT38: =IF(ISERROR(AT37/AO37-1), "NM", (AT37/AO37-1)) -> NM | AU38: =IF(ISERROR(AU37/AP37-1), "NM", (AU37/AP37-1)) -> 0.086757991 | AV38: =IF(ISERROR(AV37/AQ37-1), "NM", (AV37/AQ37-1)) -> 0.0625 | AW38: =IF(ISERROR(AW37/AR37-1), "NM", (AW37/AR37-1)) -> 0.12711864 | ... CD38: =IF(ISERROR(CD37/BY37-1), "NM", (CD37/BY37-1)) -> 0.016109584
B39: as a % of net revenue | AK39: =AK37/AK$14 -> 0.13511127 | AP39: =AP37/AP$14 -> 0.1302215 | AQ39: =AQ37/AQ$14 -> 0.11972207 | AR39: =AR37/AR$14 -> 0.11913175 | AS39: =AS37/AS$14 -> 0.11973617 | AT39: =AT37/AT$14 -> 0.11694838 | AU39: =AU37/AU$14 -> 0.11882177 | AV39: =AV37/AV$14 -> 0.11152765 | AW39: =AW37/AW$14 -> 0.11600523 | ... BK39: =BK37/BK$14 -> 0.084938942 | BL39: =CHOOSE(_Switch,BL40,BL41,BL42) -> 0.085982143 | BM39: =CHOOSE(_Switch,BM40,BM41,BM42) -> 0.082591077 | BN39: =CHOOSE(_Switch,BN40,BN41,BN42) -> 0.080489204 | BO39: =BO37/BO$14 -> 0.083414825 | BP39: =CHOOSE(_Switch,BP40,BP41,BP42) -> 0.083592334 | BQ39: =CHOOSE(_Switch,BQ40,BQ41,BQ42) -> 0.078982143 | BR39: =CHOOSE(_Switch,BR40,BR41,BR42) -> 0.075591077 | BS39: =CHOOSE(_Switch,BS40,BS41,BS42) -> 0.073489204 | BT39: =BT37/BT$14 -> 0.077642375 | BU39: =CHOOSE(_Switch,BU40,BU41,BU42) -> 0.076592334 | BV39: =CHOOSE(_Switch,BV40,BV41,BV42) -> 0.071982143 | BW39: =CHOOSE(_Switch,BW40,BW41,BW42) -> 0.068591077 | BX39: =CHOOSE(_Switch,BX40,BX41,BX42) -> 0.066489204 | BY39: =BY37/BY$14 -> 0.070662635 | BZ39: =CHOOSE(_Switch,BZ40,BZ41,BZ42) -> 0.068092334 | CA39: =CHOOSE(_Switch,CA40,CA41,CA42) -> 0.063482143 | CB39: =CHOOSE(_Switch,CB40,CB41,CB42) -> 0.060091077 | CC39: =CHOOSE(_Switch,CC40,CC41,CC42) -> 0.057989204 | CD39: =CD37/CD$14 -> 0.062147161
B40: Bull | BL40: =BL41-0.005 -> 0.080982143 | BM40: =BM41-0.005 -> 0.077591077 | BN40: =BN41-0.005 -> 0.075489204 | BP40: =BP41-0.0035 -> 0.080092334 | BQ40: =BQ41-0.0035 -> 0.075482143 | BR40: =BR41-0.0035 -> 0.072091077 | BS40: =BS41-0.0035 -> 0.069989204 | BU40: =BU41-0.0035 -> 0.073092334 | BV40: =BV41-0.0035 -> 0.068482143 | BW40: =BW41-0.0035 -> 0.065091077 | BX40: =BX41-0.0035 -> 0.062989204 | BZ40: =BZ41-0.0035 -> 0.064592334 | CA40: =CA41-0.0035 -> 0.059982143 | CB40: =CB41-0.0035 -> 0.056591077 | CC40: =CC41-0.0035 -> 0.054489204
B41: Base | BL41: =+BG39-0.01 -> 0.085982143 | BM41: =+BH39-0.0125 -> 0.082591077 | BN41: =+BI39-0.0075 -> 0.080489204 | BP41: =+BK38-0.007 -> 0.083592334 | BQ41: =+BL41-0.007 -> 0.078982143 | BR41: =+BM41-0.007 -> 0.075591077 | BS41: =+BN41-0.007 -> 0.073489204 | BU41: =+BP41-0.007 -> 0.076592334 | BV41: =+BQ41-0.007 -> 0.071982143 | BW41: =+BR41-0.007 -> 0.068591077 | BX41: =+BS41-0.007 -> 0.066489204 | BZ41: =+BU41-0.0085 -> 0.068092334 | CA41: =+BV41-0.0085 -> 0.063482143 | CB41: =+BW41-0.0085 -> 0.060091077 | CC41: =+BX41-0.0085 -> 0.057989204
B42: Bear | BL42: =+BL41*0.98 -> 0.0842625 | BM42: =+BM41*0.98 -> 0.080939256 | BN42: =+BN41*0.98 -> 0.07887942 | BP42: =+BP41*0.98 -> 0.081920488 | BQ42: =+BQ41*0.98 -> 0.0774025 | BR42: =+BR41*0.98 -> 0.074079256 | BS42: =+BS41*0.98 -> 0.07201942 | BU42: =+BU41*0.98 -> 0.075060488 | BV42: =+BV41*0.98 -> 0.0705425 | BW42: =+BW41*0.98 -> 0.067219256 | BX42: =+BX41*0.98 -> 0.06515942 | BZ42: =+BZ41*0.98 -> 0.066730488 | CA42: =+CA41*0.98 -> 0.0622125 | CB42: =+CB41*0.98 -> 0.058889256 | CC42: =+CC41*0.98 -> 0.05682942
B44: Sales and Marketing | AK44: =662-43 -> 619 | AP44: =791-46 -> 745 | AQ44: =202-12-17 -> 173 | AR44: =239-14-15 -> 210 | AS44: =255-14-13 -> 228 | AT44: =258-19-15 -> 224 | AU44: =SUM(AQ44:AT44) -> 835 | AV44: =222-13-13 -> 196 | AW44: =234-11-12 -> 211 | AX44: =226-18 -> 208 | AY44: =255-10 -> 245 | AZ44: =SUM(AV44:AY44) -> 860 | BA44: =233-16 -> 217 | BB44: =250-22 -> 228 | BC44: =233-21 -> 212 | BD44: =253-25 -> 228 | BE44: =SUM(BA44:BD44) -> 885 | BF44: =238-28 -> 210 | BG44: =284-33 -> 251 | BH44: =278-36 -> 242 | BI44: =328-43 -> 285 | BJ44: =SUM(BF44:BI44) -> 988 | BK44: =285-44 -> 241 | BL44: =BL46*BL$14 -> 286.70924 | BM44: =BM46*BM$14 -> 255.27823 | BN44: =BN46*BN$14 -> 305.06863 | BO44: =SUM(BK44:BN44) -> 1088.0561 | BP44: =BP46*BP$14 -> 246.5867 | BQ44: =BQ46*BQ$14 -> 297.26412 | BR44: =BR46*BR$14 -> 282.59188 | BS44: =BS46*BS$14 -> 338.70805 | BT44: =SUM(BP44:BS44) -> 1165.1507 | BU44: =BU46*BU$14 -> 264.41519 | BV44: =BV46*BV$14 -> 323.86943 | BW44: =BW46*BW$14 -> 300.66322 | BX44: =BX46*BX$14 -> 362.65325 | BY44: =SUM(BU44:BX44) -> 1251.6011 | BZ44: =BZ46*BZ$14 -> 276.4524 | CA44: =CA46*CA$14 -> 344.17233 | CB44: =CB46*CB$14 -> 319.27594 | CC44: =CC46*CC$14 -> 386.95277 | CD44: =SUM(BZ44:CC44) -> 1326.8534
B45: YoY % change | AP45: =IF(ISERROR(AP44/AK44-1), "NM", (AP44/AK44-1)) -> 0.20355412 | AQ45: =IF(ISERROR(AQ44/AL44-1), "NM", (AQ44/AL44-1)) -> NM | AR45: =IF(ISERROR(AR44/AM44-1), "NM", (AR44/AM44-1)) -> NM | AS45: =IF(ISERROR(AS44/AN44-1), "NM", (AS44/AN44-1)) -> NM | AT45: =IF(ISERROR(AT44/AO44-1), "NM", (AT44/AO44-1)) -> NM | AU45: =IF(ISERROR(AU44/AP44-1), "NM", (AU44/AP44-1)) -> 0.12080537 | AV45: =IF(ISERROR(AV44/AQ44-1), "NM", (AV44/AQ44-1)) -> 0.13294798 | AW45: =IF(ISERROR(AW44/AR44-1), "NM", (AW44/AR44-1)) -> 0.0047619048 | ... CD45: =IF(ISERROR(CD44/BY44-1), "NM", (CD44/BY44-1)) -> 0.060124867
B46: as a % of net revenue | AK46: =AK44/AK$14 -> 0.10932533 | AP46: =AP44/AP$14 -> 0.11074773 | AQ46: =AQ44/AQ$14 -> 0.092463923 | AR46: =AR44/AR$14 -> 0.10600707 | AS46: =AS44/AS$14 -> 0.11567732 | AT46: =AT44/AT$14 -> 0.10232983 | AU46: =AU44/AU$14 -> 0.10421867 | AV46: =AV44/AV$14 -> 0.091846298 | AW46: =AW44/AW$14 -> 0.092019189 | ... BK46: =BK44/BK$14 -> 0.065400271 | BL46: =CHOOSE(_Switch,BL47,BL48,BL49) -> 0.075038265 | BM46: =CHOOSE(_Switch,BM47,BM48,BM49) -> 0.069714418 | BN46: =CHOOSE(_Switch,BN47,BN48,BN49) -> 0.071923077 | BO46: =BO44/BO$14 -> 0.070610777 | BP46: =CHOOSE(_Switch,BP47,BP48,BP49) -> 0.060400271 | BQ46: =CHOOSE(_Switch,BQ47,BQ48,BQ49) -> 0.070038265 | BR46: =CHOOSE(_Switch,BR47,BR48,BR49) -> 0.064714418 | BS46: =CHOOSE(_Switch,BS47,BS48,BS49) -> 0.066923077 | BT46: =BT44/BT$14 -> 0.065624694 | BU46: =CHOOSE(_Switch,BU47,BU48,BU49) -> 0.055400271 | BV46: =CHOOSE(_Switch,BV47,BV48,BV49) -> 0.065038265 | BW46: =CHOOSE(_Switch,BW47,BW48,BW49) -> 0.059714418 | BX46: =CHOOSE(_Switch,BX47,BX48,BX49) -> 0.061923077 | BY46: =BY44/BY$14 -> 0.060627779 | BZ46: =CHOOSE(_Switch,BZ47,BZ48,BZ49) -> 0.050400271 | CA46: =CHOOSE(_Switch,CA47,CA48,CA49) -> 0.060038265 | CB46: =CHOOSE(_Switch,CB47,CB48,CB49) -> 0.054714418 | CC46: =CHOOSE(_Switch,CC47,CC48,CC49) -> 0.056923077 | CD46: =CD44/CD$14 -> 0.055631351
B47: Bull | BL47: =BL48-0.002 -> 0.073038265 | BM47: =BM48-0.002 -> 0.067714418 | BN47: =BN48-0.002 -> 0.069923077 | BP47: =BP48-0.0005 -> 0.059900271 | BQ47: =BQ48-0.0005 -> 0.069538265 | BR47: =BR48-0.0005 -> 0.064214418 | BS47: =BS48-0.0005 -> 0.066423077 | BU47: =BU48-0.0005 -> 0.054900271 | BV47: =BV48-0.0005 -> 0.064538265 | BW47: =BW48-0.0005 -> 0.059214418 | BX47: =BX48-0.0005 -> 0.061423077 | BZ47: =BZ48-0.0005 -> 0.049900271 | CA47: =CA48-0.0005 -> 0.059538265 | CB47: =CB48-0.0005 -> 0.054214418 | CC47: =CC48-0.0005 -> 0.056423077
B48: Base | BL48: =+BG46-0.5% -> 0.075038265 | BM48: =+BH46-0.5% -> 0.069714418 | BN48: =+BI46-0.5% -> 0.071923077 | BP48: =+BK46-0.5% -> 0.060400271 | BQ48: =+BL48-0.5% -> 0.070038265 | BR48: =+BM48-0.5% -> 0.064714418 | BS48: =+BN48-0.5% -> 0.066923077 | BU48: =+BP48-0.5% -> 0.055400271 | BV48: =+BQ48-0.5% -> 0.065038265 | BW48: =+BR48-0.5% -> 0.059714418 | BX48: =+BS48-0.5% -> 0.061923077 | BZ48: =+BU48-0.5% -> 0.050400271 | CA48: =+BV48-0.5% -> 0.060038265 | CB48: =+BW48-0.5% -> 0.054714418 | CC48: =+BX48-0.5% -> 0.056923077
B49: Bear | BL49: =BL48+0.003 -> 0.078038265 | BM49: =BM48+0.003 -> 0.072714418 | BN49: =BN48+0.003 -> 0.074923077 | BP49: =BP48+0.003 -> 0.063400271 | BQ49: =BQ48+0.003 -> 0.073038265 | BR49: =BR48+0.003 -> 0.067714418 | BS49: =BS48+0.003 -> 0.069923077 | BU49: =BU48+0.003 -> 0.058400271 | BV49: =BV48+0.003 -> 0.068038265 | BW49: =BW48+0.003 -> 0.062714418 | BX49: =BX48+0.003 -> 0.064923077 | BZ49: =BZ48+0.003 -> 0.053400271 | CA49: =CA48+0.003 -> 0.063038265 | CB49: =CB48+0.003 -> 0.057714418 | CC49: =CC48+0.003 -> 0.059923077
B51: Product Development | AK51: =677-60 -> 617 | AP51: =727-87 -> 640 | AQ51: =165-24 -> 141 | AR51: =189-28 -> 161 | AS51: =192-28 -> 164 | AT51: =201-28 -> 173 | AU51: =SUM(AQ51:AT51) -> 639 | AV51: =185-29 -> 156 | AW51: =202-35 -> 167 | AX51: =197-33 -> 164 | AY51: =208-35 -> 173 | AZ51: =SUM(AV51:AY51) -> 660 | BA51: =195-33 -> 162 | BB51: =209-35 -> 174 | BC51: =215-34 -> 181 | BD51: =215-37 -> 178 | BE51: =SUM(BA51:BD51) -> 695 | BF51: =214-45 -> 169 | BG51: =232-59 -> 173 | BH51: =240-64 -> 176 | BI51: =267-72 -> 195 | BJ51: =SUM(BF51:BI51) -> 713 | BK51: =258-64 -> 194 | BL51: =BL53*BL$14 -> 195.49642 | BM51: =BM53*BM$14 -> 180.66357 | BN51: =BN53*BN$14 -> 202.03391 | BO51: =SUM(BK51:BN51) -> 772.1939 | BP51: =BP53*BP$14 -> 195.00618 | BQ51: =BQ53*BQ$14 -> 196.45136 | BR51: =BR53*BR$14 -> 194.13605 | BS51: =BS53*BS$14 -> 216.37236 | BT51: =SUM(BP51:BS51) -> 801.96595 | BU51: =BU53*BU$14 -> 208.88632 | BV51: =BV53*BV$14 -> 210.56963 | BW51: =BW53*BW$14 -> 203.70558 | BX51: =BX53*BX$14 -> 226.94909 | BY51: =SUM(BU51:BX51) -> 850.11061 | BZ51: =BZ53*BZ$14 -> 215.37863 | CA51: =CA53*CA$14 -> 216.60907 | CB51: =CB53*CB$14 -> 209.8249 | CC51: =CC53*CC$14 -> 232.83603 | CD51: =SUM(BZ51:CC51) -> 874.64863
B52: YoY % change | AP52: =IF(ISERROR(AP51/AK51-1), "NM", (AP51/AK51-1)) -> 0.037277147 | AQ52: =IF(ISERROR(AQ51/AL51-1), "NM", (AQ51/AL51-1)) -> NM | AR52: =IF(ISERROR(AR51/AM51-1), "NM", (AR51/AM51-1)) -> NM | AS52: =IF(ISERROR(AS51/AN51-1), "NM", (AS51/AN51-1)) -> NM | AT52: =IF(ISERROR(AT51/AO51-1), "NM", (AT51/AO51-1)) -> NM | AU52: =IF(ISERROR(AU51/AP51-1), "NM", (AU51/AP51-1)) -> -0.0015625 | AV52: =IF(ISERROR(AV51/AQ51-1), "NM", (AV51/AQ51-1)) -> 0.10638298 | AW52: =IF(ISERROR(AW51/AR51-1), "NM", (AW51/AR51-1)) -> 0.037267081 | ... CD52: =IF(ISERROR(CD51/BY51-1), "NM", (CD51/BY51-1)) -> 0.028864499
B53: as a % of net revenue | AK53: =AK51/AK$14 -> 0.10897209 | AP53: =AP51/AP$14 -> 0.095138992 | AQ53: =AQ51/AQ$14 -> 0.07536077 | AR53: =AR51/AR$14 -> 0.081272085 | AS53: =AS51/AS$14 -> 0.083206494 | AT53: =AT51/AT$14 -> 0.079031521 | AU53: =AU51/AU$14 -> 0.079755367 | AV53: =AV51/AV$14 -> 0.073102156 | AW53: =AW51/AW$14 -> 0.072830353 | ... BK53: =BK51/BK$14 -> 0.052645862 | BL53: =CHOOSE(_Switch,BL54,BL55,BL56) -> 0.051165816 | BM53: =CHOOSE(_Switch,BM54,BM55,BM56) -> 0.049337759 | BN53: =CHOOSE(_Switch,BN54,BN55,BN56) -> 0.047631579 | BO53: =BO51/BO$14 -> 0.0501125 | BP53: =CHOOSE(_Switch,BP54,BP55,BP56) -> 0.047765862 | BQ53: =CHOOSE(_Switch,BQ54,BQ55,BQ56) -> 0.046285816 | BR53: =CHOOSE(_Switch,BR54,BR55,BR56) -> 0.044457759 | BS53: =CHOOSE(_Switch,BS54,BS55,BS56) -> 0.042751579 | BT53: =BT51/BT$14 -> 0.045169065 | BU53: =CHOOSE(_Switch,BU54,BU55,BU56) -> 0.043765862 | BV53: =CHOOSE(_Switch,BV54,BV55,BV56) -> 0.042285816 | BW53: =CHOOSE(_Switch,BW54,BW55,BW56) -> 0.040457759 | BX53: =CHOOSE(_Switch,BX54,BX55,BX56) -> 0.038751579 | BY53: =BY51/BY$14 -> 0.041179509 | BZ53: =CHOOSE(_Switch,BZ54,BZ55,BZ56) -> 0.039265862 | CA53: =CHOOSE(_Switch,CA54,CA55,CA56) -> 0.037785816 | CB53: =CHOOSE(_Switch,CB54,CB55,CB56) -> 0.035957759 | CC53: =CHOOSE(_Switch,CC54,CC55,CC56) -> 0.034251579 | CD53: =CD51/CD$14 -> 0.036671635
B54: Bull | BL54: =+BL55-0.5% -> 0.046165816 | BM54: =+BM55-0.5% -> 0.044337759 | BN54: =+BN55-0.5% -> 0.042631579 | BP54: =+BP55-0.5% -> 0.042765862 | BQ54: =+BQ55-0.5% -> 0.041285816 | BR54: =+BR55-0.5% -> 0.039457759 | BS54: =+BS55-0.5% -> 0.037751579 | BU54: =+BU55-0.5% -> 0.038765862 | BV54: =+BV55-0.5% -> 0.037285816 | BW54: =+BW55-0.5% -> 0.035457759 | BX54: =+BX55-0.5% -> 0.033751579 | BZ54: =+BZ55-0.5% -> 0.034265862 | CA54: =+CA55-0.5% -> 0.032785816 | CB54: =+CB55-0.5% -> 0.030957759 | CC54: =+CC55-0.5% -> 0.029251579
B55: Base | BL55: =+BG53-0.4% -> 0.051165816 | BM55: =+BH53-0.5% -> 0.049337759 | BN55: =+BI53-0.5% -> 0.047631579 | BP55: =+BK53-0.5%+0.00012 -> 0.047765862 | BQ55: =+BL55-0.5%+0.00012 -> 0.046285816 | BR55: =+BM55-0.5%+0.00012 -> 0.044457759 | BS55: =+BN55-0.5%+0.00012 -> 0.042751579 | BU55: =+BP55-0.4% -> 0.043765862 | BV55: =+BQ55-0.4% -> 0.042285816 | BW55: =+BR55-0.4% -> 0.040457759 | BX55: =+BS55-0.4% -> 0.038751579 | BZ55: =+BU55-0.45% -> 0.039265862 | CA55: =+BV55-0.45% -> 0.037785816 | CB55: =+BW55-0.45% -> 0.035957759 | CC55: =+BX55-0.45% -> 0.034251579
B56: Bear | BL56: =BL55+0.001 -> 0.052165816 | BM56: =BM55+0.001 -> 0.050337759 | BN56: =BN55+0.001 -> 0.048631579 | BP56: =BP55+0.001 -> 0.048765862 | BQ56: =BQ55+0.001 -> 0.047285816 | BR56: =BR55+0.001 -> 0.045457759 | BS56: =BS55+0.001 -> 0.043751579 | BU56: =BU55+0.001 -> 0.044765862 | BV56: =BV55+0.001 -> 0.043285816 | BW56: =BW55+0.001 -> 0.041457759 | BX56: =BX55+0.001 -> 0.039751579 | BZ56: =BZ55+0.001 -> 0.040265862 | CA56: =CA55+0.001 -> 0.038785816 | CB56: =CB55+0.001 -> 0.036957759 | CC56: =CC55+0.001 -> 0.035251579
B58: General and Administrative | AK58: =345-38-(210-190) -> 287 | AP58: =378-27+4-(269-234) -> 320 | AQ58: =179-16-5+1 -> 159 | AR58: =185-20-4+1 -> 162 | AS58: =166-20-1+2 -> 147 | AT58: =203-19-2+2 -> 184 | AU58: =SUM(AQ58:AT58) -> 652 | AV58: =217-22-3-4+1 -> 189 | AW58: =215-21-5-7-3+2 -> 181 | AX58: =216-25-1-3-2 -> 185 | AY58: =225-26-5+2-1+1 -> 196 | AZ58: =SUM(AV58:AY58) -> 751 | BA58: =231-27-1 -> 203 | BB58: =261-33-(122-113) -> 219 | BC58: =261-31-(110-109) -> 229 | BD58: =275-39 -> 236 | BE58: =SUM(BA58:BD58) -> 887 | BF58: =265-42+40-40-2 -> 221 | BG58: =282-51-15-(192-180) -> 204 | BH58: =293-54-2 -> 237 | BI58: =315-63 -> 252 | BJ58: =SUM(BF58:BI58) -> 914 | BK58: =339-59 -> 280 | BL58: =BL60*BL$14 -> 227.53495 | BM58: =BM60*BM$14 -> 245.96383 | BN58: =BN60*BN$14 -> 263.04763 | BO58: =SUM(BK58:BN58) -> 1016.5464 | BP58: =BP60*BP$14 -> 289.79407 | BQ58: =BQ60*BQ$14 -> 231.53145 | BR58: =BR60*BR$14 -> 271.48423 | BS58: =BS60*BS$14 -> 288.56778 | BT58: =SUM(BP58:BS58) -> 1081.3775 | BU58: =BU60*BU$14 -> 314.92802 | BV58: =BV60*BV$14 -> 246.74798 | BW58: =BW60*BW$14 -> 287.85571 | BX58: =BX60*BX$14 -> 304.63347 | BY58: =SUM(BU58:BX58) -> 1154.1652 | BZ58: =BZ60*BZ$14 -> 331.76148 | CA58: =CA60*CA$14 -> 252.52466 | CB58: =CB60*CB$14 -> 301.51507 | CC58: =CC60*CC$14 -> 316.20866 | CD58: =SUM(BZ58:CC58) -> 1202.0099
B59: YoY % change | AP59: =IF(ISERROR(AP58/AK58-1), "NM", (AP58/AK58-1)) -> 0.11498258 | AQ59: =IF(ISERROR(AQ58/AL58-1), "NM", (AQ58/AL58-1)) -> NM | AR59: =IF(ISERROR(AR58/AM58-1), "NM", (AR58/AM58-1)) -> NM | AS59: =IF(ISERROR(AS58/AN58-1), "NM", (AS58/AN58-1)) -> NM | AT59: =IF(ISERROR(AT58/AO58-1), "NM", (AT58/AO58-1)) -> NM | AU59: =IF(ISERROR(AU58/AP58-1), "NM", (AU58/AP58-1)) -> 1.0375 | AV59: =IF(ISERROR(AV58/AQ58-1), "NM", (AV58/AQ58-1)) -> 0.18867925 | AW59: =IF(ISERROR(AW58/AR58-1), "NM", (AW58/AR58-1)) -> 0.11728395 | ... CD59: =IF(ISERROR(CD58/BY58-1), "NM", (CD58/BY58-1)) -> 0.041453942
B60: as a % of net revenue | AK60: =AK58/AK$14 -> 0.050688803 | AP60: =AP58/AP$14 -> 0.047569496 | AQ60: =AQ58/AQ$14 -> 0.084981293 | AR60: =AR58/AR$14 -> 0.08177688 | AS60: =AS58/AS$14 -> 0.074581431 | AT60: =AT58/AT$14 -> 0.084056647 | AU60: =AU58/AU$14 -> 0.081377933 | AV60: =AV58/AV$14 -> 0.088566073 | AW60: =AW58/AW$14 -> 0.078935892 | ... BK60: =BK58/BK$14 -> 0.075983718 | BL60: =CHOOSE(_Switch,BL61,BL62,BL63) -> 0.05955102 | BM60: =CHOOSE(_Switch,BM61,BM62,BM63) -> 0.067170732 | BN60: =CHOOSE(_Switch,BN61,BN62,BN63) -> 0.062016194 | BO60: =BO58/BO$14 -> 0.065970066 | BP60: =CHOOSE(_Switch,BP61,BP62,BP63) -> 0.070983718 | BQ60: =CHOOSE(_Switch,BQ61,BQ62,BQ63) -> 0.05455102 | BR60: =CHOOSE(_Switch,BR61,BR62,BR63) -> 0.062170732 | BS60: =CHOOSE(_Switch,BS61,BS62,BS63) -> 0.057016194 | BT60: =BT58/BT$14 -> 0.060906342 | BU60: =CHOOSE(_Switch,BU61,BU62,BU63) -> 0.065983718 | BV60: =CHOOSE(_Switch,BV61,BV62,BV63) -> 0.04955102 | BW60: =CHOOSE(_Switch,BW61,BW62,BW63) -> 0.057170732 | BX60: =CHOOSE(_Switch,BX61,BX62,BX63) -> 0.052016194 | BY60: =BY58/BY$14 -> 0.055907966 | BZ60: =CHOOSE(_Switch,BZ61,BZ62,BZ63) -> 0.060483718 | CA60: =CHOOSE(_Switch,CA61,CA62,CA63) -> 0.04405102 | CB60: =CHOOSE(_Switch,CB61,CB62,CB63) -> 0.051670732 | CC60: =CHOOSE(_Switch,CC61,CC62,CC63) -> 0.046516194 | CD60: =CD58/CD$14 -> 0.050397
B61: Bull | BL61: =BL62-0.0025 -> 0.05705102 | BM61: =BM62-0.0025 -> 0.064670732 | BN61: =BN62-0.0025 -> 0.059516194 | BP61: =BP62-0.0025 -> 0.068483718 | BQ61: =BQ62-0.0025 -> 0.05205102 | BR61: =BR62-0.0025 -> 0.059670732 | BS61: =BS62-0.0025 -> 0.054516194 | BU61: =BU62-0.0025 -> 0.063483718 | BV61: =BV62-0.0025 -> 0.04705102 | BW61: =BW62-0.0025 -> 0.054670732 | BX61: =BX62-0.0025 -> 0.049516194 | BZ61: =BZ62-0.0025 -> 0.057983718 | CA61: =CA62-0.0025 -> 0.04155102 | CB61: =CB62-0.0025 -> 0.049170732 | CC61: =CC62-0.0025 -> 0.044016194
B62: Base | BL62: =+BG60-0.55% -> 0.05955102 | BM62: =+BH60-0.6% -> 0.067170732 | BN62: =+BI60-0.6% -> 0.062016194 | BP62: =+BK60-0.5% -> 0.070983718 | BQ62: =+BL62-0.5% -> 0.05455102 | BR62: =+BM62-0.5% -> 0.062170732 | BS62: =+BN62-0.5% -> 0.057016194 | BU62: =+BP62-0.5% -> 0.065983718 | BV62: =+BQ62-0.5% -> 0.04955102 | BW62: =+BR62-0.5% -> 0.057170732 | BX62: =+BS62-0.5% -> 0.052016194 | BZ62: =+BU62-0.55% -> 0.060483718 | CA62: =+BV62-0.55% -> 0.04405102 | CB62: =+BW62-0.55% -> 0.051670732 | CC62: =+BX62-0.55% -> 0.046516194
B63: Bear | BL63: =+BL62 -> 0.05955102 | BM63: =+BM62 -> 0.067170732 | BN63: =+BN62 -> 0.062016194 | BP63: =+BP62 -> 0.070983718 | BQ63: =+BQ62 -> 0.05455102 | BR63: =+BR62 -> 0.062170732 | BS63: =+BS62 -> 0.057016194 | BU63: =+BU62 -> 0.065983718 | BV63: =+BV62 -> 0.04955102 | BW63: =+BW62 -> 0.057170732 | BX63: =+BX62 -> 0.052016194 | BZ63: =+BZ62 -> 0.060483718 | CA63: =+CA62 -> 0.04405102 | CB63: =+CB62 -> 0.051670732 | CC63: =+CC62 -> 0.046516194
B65: Charge-offs | BI65: =317+92-39 -> 370 | BJ65: =SUM(BF65:BI65) -> 370 | BK65: =153-BK122 -> 128 | BL65: =BL67*'Segment Detail'!BL6 -> 140.56134 | BO65: =SUM(BK65:BN65) -> 268.56134
B66: YoY % change | BJ66: =IF(ISERROR(BJ65/BE65-1), "NM", (BJ65/BE65-1)) -> NM | BK66: =IF(ISERROR(BK65/BF65-1), "NM", (BK65/BF65-1)) -> NM | BL66: =IF(ISERROR(BL65/BG65-1), "NM", (BL65/BG65-1)) -> NM | BO66: =IF(ISERROR(BO65/BJ65-1), "NM", (BO65/BJ65-1)) -> -0.27415855
B67: as a % of TPV | BK67: =+BK65/'Segment Detail'!BK6 -> 0.00096703031 | BL67: =CHOOSE(_Switch,BL68,BL69,BL70) -> 0.001
B68: Bull | BL68: 0.0013
B69: Base | BL69: 0.001
B70: Bear | BL70: 0.0009
B72: Depreciation (ex-amortization of intangibles) | AK72: =382-58 -> 324 | AP72: =453-55 -> 398 | AQ72: 112 | AR72: =125-1-16+4 -> 112 | AS72: =129-1-16+4 -> 116 | AT72: =132-1-17+4 -> 118 | AU72: =SUM(AQ72:AT72) -> 458 | AV72: =141-2-16+4 -> 127 | AW72: =150-20-2+4 -> 132 | AX72: =153-2-20 -> 131 | AY72: =164-1-29 -> 134 | AZ72: =SUM(AV72:AY72) -> 524 | BA72: =175-1-34 -> 140 | BB72: =176-35-1 -> 140 | BC72: =184-32-2 -> 150 | BD72: =189-2-32 -> 155 | BE72: =SUM(BA72:BD72) -> 585 | BF72: =183-2-23 -> 158 | BG72: =201-3-22 -> 176 | BH72: =194-BH123-3 -> 165 | BI72: =227-4-BI123-(223-222) -> 164 | BJ72: =SUM(BF72:BI72) -> 663 | BK72: =185-4-BK123-(241-209) -> 120 | BL72: =+BK72+1.5 -> 121.5 | BM72: =+BL72+1.5 -> 123 | BN72: =+BM72+1.5 -> 124.5 | BO72: =SUM(BK72:BN72) -> 489 | BP72: =+BN72+3 -> 127.5 | BQ72: =+BP72+1.5 -> 129 | BR72: =+BQ72+1.5 -> 130.5 | BS72: =+BR72+1.5 -> 132 | BT72: =SUM(BP72:BS72) -> 519 | BU72: =+BS72+5 -> 137 | BV72: =+BU72+1.5 -> 138.5 | BW72: =+BV72+1.5 -> 140 | BX72: =+BW72+1.5 -> 141.5 | BY72: =SUM(BU72:BX72) -> 557 | BZ72: =+BX72+5 -> 146.5 | CA72: =+BZ72+1.5 -> 148 | CB72: =+CA72+1.5 -> 149.5 | CC72: =+CB72+1.5 -> 151 | CD72: =SUM(BZ72:CC72) -> 595
B73: YoY % change | AP73: =IF(ISERROR(AP72/AK72-1), "NM", (AP72/AK72-1)) -> 0.22839506 | AQ73: =IF(ISERROR(AQ72/AL72-1), "NM", (AQ72/AL72-1)) -> NM | AR73: =IF(ISERROR(AR72/AM72-1), "NM", (AR72/AM72-1)) -> NM | AS73: =IF(ISERROR(AS72/AN72-1), "NM", (AS72/AN72-1)) -> NM | AT73: =IF(ISERROR(AT72/AO72-1), "NM", (AT72/AO72-1)) -> NM | AU73: =IF(ISERROR(AU72/AP72-1), "NM", (AU72/AP72-1)) -> 0.15075377 | AV73: =IF(ISERROR(AV72/AQ72-1), "NM", (AV72/AQ72-1)) -> 0.13392857 | AW73: =IF(ISERROR(AW72/AR72-1), "NM", (AW72/AR72-1)) -> 0.17857143 | ... CD73: =IF(ISERROR(CD72/BY72-1), "NM", (CD72/BY72-1)) -> 0.068222621
B74: as a % of net revenue | AK74: =AK72/AK$14 -> 0.057223596 | AP74: =AP72/AP$14 -> 0.059164561 | AQ74: =AQ72/AQ$14 -> 0.059861037 | AR74: =AR72/AR$14 -> 0.056537102 | AS74: =AS72/AS$14 -> 0.058853374 | AT74: =AT72/AT$14 -> 0.053905893 | AU74: =AU72/AU$14 -> 0.057164254 | AV74: =AV72/AV$14 -> 0.059512652 | AW74: =AW72/AW$14 -> 0.057566507 | ... CD74: =CD72/CD$14 -> 0.024946729
B76: Operating Income (PayPal method) | AK76: =AK33-AK37-AK44-AK51-AK58-AK72 -> 1167 | AL76: =AL33-AL37-AL44-AL51-AL58-AL72 -> 0 | AM76: =AM33-AM37-AM44-AM51-AM58-AM72 -> 0 | AN76: =AN33-AN37-AN44-AN51-AN58-AN72 -> 0 | AO76: =AO33-AO37-AO44-AO51-AO58-AO72 -> 0 | AP76: =AP33-AP37-AP44-AP51-AP58-AP72 -> 1411 | AQ76: =AQ33-AQ37-AQ44-AQ51-AQ58-AQ72 -> 407 | AR76: =AR33-AR37-AR44-AR51-AR58-AR72 -> 421 | ... BH76: =BH33-BH37-BH44-BH51-BH58-BH72 -> 646 | BI76: =BI33-BI37-BI44-BI51-BI58-BI72-BI65 -> 807 | BJ76: =BJ33-BJ37-BJ44-BJ51-BJ58-BJ72-BJ65 -> 2755 | BK76: =BK33-BK37-BK44-BK51-BK58-BK72-BK65 -> 829 | BL76: =BL33-BL37-BL44-BL51-BL58-BL72-BL65 -> 833.62213 | BM76: =BM33-BM37-BM44-BM51-BM58-BM72-BM65 -> 785.87622 | BN76: =BN33-BN37-BN44-BN51-BN58-BN72-BN65 -> 985.91834 | BO76: =BO33-BO37-BO44-BO51-BO58-BO72-BO65 -> 3434.4167 | BP76: =BP33-BP37-BP44-BP51-BP58-BP72 -> 924.47107 | BQ76: =BQ33-BQ37-BQ44-BQ51-BQ58-BQ72 -> 970.38907 | BR76: =BR33-BR37-BR44-BR51-BR58-BR72 -> 972.61806 | BS76: =BS33-BS37-BS44-BS51-BS58-BS72 -> 1218.0323 | BT76: =BT33-BT37-BT44-BT51-BT58-BT72 -> 4085.5105 | BU76: =BU33-BU37-BU44-BU51-BU58-BU72 -> 1112.0539 | BV76: =BV33-BV37-BV44-BV51-BV58-BV72 -> 1177.4166 | BW76: =BW33-BW37-BW44-BW51-BW58-BW72 -> 1154.2354 | ... CD76: =CD33-CD37-CD44-CD51-CD58-CD72 -> 5998.3173
B77: YoY% change | AP77: =IF(ISERROR(AP76/AK76-1), "NM", (AP76/AK76-1)) -> 0.20908312 | AQ77: =IF(ISERROR(AQ76/AL76-1), "NM", (AQ76/AL76-1)) -> NM | AR77: =IF(ISERROR(AR76/AM76-1), "NM", (AR76/AM76-1)) -> NM | AS77: =IF(ISERROR(AS76/AN76-1), "NM", (AS76/AN76-1)) -> NM | AT77: =IF(ISERROR(AT76/AO76-1), "NM", (AT76/AO76-1)) -> NM | AU77: =IF(ISERROR(AU76/AP76-1), "NM", (AU76/AP76-1)) -> 0.14599575 | AV77: =+AV76/AQ76-1 -> 0.14250614 | AW77: =+AW76/AR76-1 -> 0.19952494 | AX77: =+AX76/AS76-1 -> 0.27478754 | AY77: =+AY76/AT76-1 -> 0.22018349 | AZ77: =+AZ76/AU76-1 -> 0.21150278 | BA77: =+BA76/AV76-1 -> 0.15483871 | BB77: =+BB76/AW76-1 -> 0.045544554 | BC77: =+BC76/AX76-1 -> 0.088888889 | ... CD77: =+CD76/BY76-1 -> 0.22384264
B78: Operating Margin | AK78: =AK76/AK14 -> 0.20611091 | AP78: =AP76/AP14 -> 0.20975175 | AQ78: =AQ76/AQ14 -> 0.21753073 | AR78: =AR76/AR14 -> 0.21251893 | AS78: =AS76/AS14 -> 0.17909691 | AT78: =AT76/AT14 -> 0.19917771 | AU78: =AU76/AU14 -> 0.20182227 | AV78: =AV76/AV14 -> 0.21790066 | AW78: =AW76/AW14 -> 0.2202355 | ... CD78: =CD76/CD14 -> 0.25149311
B80: Stock-based compensation expense | AK80: 210 | AP80: 269 | AQ80: =15+12+24+16+1+5 -> 73 | AR80: =12+14+28+20+1+4 -> 79 | AS80: =12+14+28+20+1+1 -> 76 | AT80: =13+19+28+19+1+1 -> 81 | AU80: =+SUM(AQ80:AT80) -> 309 | AV80: =13+13+29+22+2+3 -> 82 | AW80: 89 | AX80: =16+18+33+25+2 -> 94 | AY80: 90 | AZ80: =+SUM(AV80:AY80) -> 355 | BA80: 95 | BB80: 122 | BC80: 109 | BD80: 127 | BE80: =+SUM(BA80:BD80) -> 453 | BF80: 147 | BG80: 192 | BH80: 197 | BI80: 223 | BJ80: =+SUM(BF80:BI80) -> 759 | BK80: 241 | BL80: =+BL82*BL14 -> 249.884 | BM80: =+BM82*BM14 -> 239.48081 | BN80: =+BN82*BN14 -> 277.40152 | BO80: =+SUM(BK80:BN80) -> 1007.7663 | BP80: =+BP82*BP14 -> 244.95257 | BQ80: =+BQ82*BQ14 -> 254.65861 | BR80: =+BR82*BR14 -> 262.00518 | BS80: =+BS82*BS14 -> 303.66929 | BT80: =+SUM(BP80:BS80) -> 1065.2856 | BU80: =+BU82*BU14 -> 293.52806 | BV80: =+BV82*BV14 -> 306.25002 | BW80: =+BW82*BW14 -> 309.65366 | BX80: =+BX82*BX14 -> 360.17549 | BY80: =+SUM(BU80:BX80) -> 1269.6072 | BZ80: =+BZ82*BZ14 -> 318.13795 | CA80: =+CA82*CA14 -> 332.48788 | CB80: =+CB82*CB14 -> 338.44835 | CC80: =+CC82*CC14 -> 394.2735 | CD80: =+SUM(BZ80:CC80) -> 1383.3477
B81: YoY % change | AP81: =IF(ISERROR(AP80/AK80-1), "NM", (AP80/AK80-1)) -> 0.28095238 | AQ81: =IF(ISERROR(AQ80/AL80-1), "NM", (AQ80/AL80-1)) -> NM | AR81: =IF(ISERROR(AR80/AM80-1), "NM", (AR80/AM80-1)) -> NM | AS81: =IF(ISERROR(AS80/AN80-1), "NM", (AS80/AN80-1)) -> NM | AT81: =IF(ISERROR(AT80/AO80-1), "NM", (AT80/AO80-1)) -> NM | AU81: =IF(ISERROR(AU80/AP80-1), "NM", (AU80/AP80-1)) -> 0.14869888 | AV81: =IF(ISERROR(AV80/AQ80-1), "NM", (AV80/AQ80-1)) -> 0.12328767 | AW81: =IF(ISERROR(AW80/AR80-1), "NM", (AW80/AR80-1)) -> 0.12658228 | ... CD81: =IF(ISERROR(CD80/BY80-1), "NM", (CD80/BY80-1)) -> 0.089587109
B82: as a % of net revenue | AP82: =+AP80/AP14 -> 0.039988108 | AQ82: =+AQ80/AQ14 -> 0.039016569 | AR82: =+AR80/AR14 -> 0.039878849 | AS82: =+AS80/AS14 -> 0.038559107 | AT82: =+AT80/AT14 -> 0.037003198 | AU82: =+AU80/AU14 -> 0.038567149 | AV82: =+AV80/AV14 -> 0.038425492 | AW82: =+AW80/AW14 -> 0.038813781 | ... BC82: =+BC80/BC14 -> 0.040869891 | BD82: 0.0385 | BE82: =+BE80/BE14 -> 0.041781959 | BF82: =+BF80/BF14 -> 0.049411765 | BG82: 0.059 | BH82: 0.054 | BI82: 0.0575 | BJ82: =+BJ80/BJ14 -> 0.058138644 | BK82: =+BK80/BK14 -> 0.065400271 | BL82: =+BK82 -> 0.065400271 | BM82: =+BL82 -> 0.065400271 | BN82: =+BM82 -> 0.065400271 | BO82: =+BO80/BO14 -> 0.065400271 | BP82: 0.06 | BQ82: =+BP82 -> 0.06 | BR82: =+BQ82 -> 0.06 | BS82: =+BR82 -> 0.06 | BT82: =+BT80/BT14 -> 0.06 | BU82: 0.0615 | BV82: =+BU82 -> 0.0615 | BW82: =+BV82 -> 0.0615 | BX82: =+BW82 -> 0.0615 | BY82: =+BY80/BY14 -> 0.0615 | BZ82: 0.058 | CA82: =+BZ82 -> 0.058 | CB82: =+CA82 -> 0.058 | CC82: =+CB82 -> 0.058 | CD82: =+CD80/CD14 -> 0.058
B84: Operating Income (SBC Burdened) | AK84: =+AK76-AK80 -> 957 | AL84: =+AL76-AL80 -> 0 | AM84: =+AM76-AM80 -> 0 | AN84: =+AN76-AN80 -> 0 | AO84: =+AO76-AO80 -> 0 | AP84: =+AP76-AP80 -> 1142 | AQ84: =+AQ76-AQ80 -> 334 | AR84: =+AR76-AR80 -> 342 | ... CD84: =+CD76-CD80 -> 4614.9697 | CE84: =(BY84/BE84)^0.25-1 -> 0.20525669
B85: YoY% change | AP85: =IF(ISERROR(AP84/AK84-1), "NM", (AP84/AK84-1)) -> 0.19331243 | AQ85: =IF(ISERROR(AQ84/AL84-1), "NM", (AQ84/AL84-1)) -> NM | AR85: =IF(ISERROR(AR84/AM84-1), "NM", (AR84/AM84-1)) -> NM | AS85: =IF(ISERROR(AS84/AN84-1), "NM", (AS84/AN84-1)) -> NM | AT85: =IF(ISERROR(AT84/AO84-1), "NM", (AT84/AO84-1)) -> NM | AU85: =IF(ISERROR(AU84/AP84-1), "NM", (AU84/AP84-1)) -> 0.14535902 | AV85: =IF(ISERROR(AV84/AQ84-1), "NM", (AV84/AQ84-1)) -> 0.14670659 | AW85: =IF(ISERROR(AW84/AR84-1), "NM", (AW84/AR84-1)) -> 0.21637427 | ... CD85: =IF(ISERROR(CD84/BY84-1), "NM", (CD84/BY84-1)) -> 0.27077825
B86: Operating Margin | AK86: =AK84/AK14 -> 0.16902155 | AP86: =AP84/AP14 -> 0.16976364 | AQ86: =AQ84/AQ14 -> 0.17851416 | AR86: =AR84/AR14 -> 0.17264008 | AS86: =AS84/AS14 -> 0.1405378 | AT86: =AT84/AT14 -> 0.16217451 | AU86: =AU84/AU14 -> 0.16325512 | AV86: =AV84/AV14 -> 0.17947516 | AW86: =AW84/AW14 -> 0.18142172 | ... CD86: =CD84/CD14 -> 0.19349311
B88: EBITDA (MS method) | AK88: =AK84+AK72+AK123 -> 1281 | AP88: =AP84+AP72+AP123 -> 1540 | AQ88: =AQ84+AQ72 -> 446 | AR88: =AR84+AR72 -> 454 | AS88: =AS84+AS72 -> 393 | AT88: =AT84+AT72 -> 473 | AU88: =AU84+AU72+AU123 -> 1836 | AV88: =AV84+AV72 -> 510 | AW88: =AW84+AW72 -> 548 | AX88: =AX84+AX72 -> 487 | AY88: =AY84+AY72 -> 576 | AZ88: =AZ84+AZ72+AZ123 -> 2213 | BA88: =BA84+BA72 -> 582 | BB88: =BB84+BB72 -> 546 | BC88: =BC84+BC72 -> 531 | BD88: =BD84+BD72 -> 647 | BE88: =BE84+BE72+BE123 -> 2439 | BF88: =BF84+BF72 -> 654 | BG88: =BG84+BG72 -> 643 | BH88: =BH84+BH72 -> 614 | BI88: =BI84+BI72 -> 748 | BJ88: =BJ84+BJ72+BJ123 -> 2788 | BK88: =BK84+BK72 -> 708 | BL88: =BL84+BL72 -> 705.23813 | BM88: =BM84+BM72 -> 669.39541 | BN88: =BN84+BN72 -> 833.01682 | BO88: =BO84+BO72+BO123 -> 2989.6504 | BP88: =BP84+BP72 -> 807.01849 | BQ88: =BQ84+BQ72 -> 844.73046 | BR88: =BR84+BR72 -> 841.11288 | BS88: =BS84+BS72 -> 1046.363 | BT88: =BT84+BT72+BT123 -> 3599.2249 | BU88: =BU84+BU72 -> 955.52588 | BV88: =BV84+BV72 -> 1009.6665 | BW88: =BW84+BW72 -> 984.58172 | BX88: =BX84+BX72 -> 1238.8348 | BY88: =BY84+BY72+BY123 -> 4248.609 | BZ88: =BZ84+BZ72 -> 1169.6738 | CA88: =CA84+CA72 -> 1240.5351 | CB88: =CB84+CB72 -> 1239.9372 | CC88: =CC84+CC72 -> 1559.8235 | CD88: =CD84+CD72+CD123 -> 5269.9697
B89: YoY % change | AP89: =IF(ISERROR(AP88/AK88-1), "NM", (AP88/AK88-1)) -> 0.20218579 | AQ89: =IF(ISERROR(AQ88/AL88-1), "NM", (AQ88/AL88-1)) -> NM | AR89: =IF(ISERROR(AR88/AM88-1), "NM", (AR88/AM88-1)) -> NM | AS89: =IF(ISERROR(AS88/AN88-1), "NM", (AS88/AN88-1)) -> NM | AT89: =IF(ISERROR(AT88/AO88-1), "NM", (AT88/AO88-1)) -> NM | AU89: =IF(ISERROR(AU88/AP88-1), "NM", (AU88/AP88-1)) -> 0.19220779 | AV89: =IF(ISERROR(AV88/AQ88-1), "NM", (AV88/AQ88-1)) -> 0.14349776 | AW89: =IF(ISERROR(AW88/AR88-1), "NM", (AW88/AR88-1)) -> 0.20704846 | ... CD89: =IF(ISERROR(CD88/BY88-1), "NM", (CD88/BY88-1)) -> 0.24039885
B90: EBITDA Margin on Net Revenue | AK90: =AK88/AK$14 -> 0.22624514 | AP90: =AP88/AP$14 -> 0.2289282 | AQ90: =AQ88/AQ$14 -> 0.2383752 | AR90: =AR88/AR$14 -> 0.22917718 | AS90: =AS88/AS$14 -> 0.19939117 | AT90: =AT88/AT$14 -> 0.2160804 | AU90: =AU88/AU$14 -> 0.22915627 | AV90: =AV88/AV$14 -> 0.23898782 | AW90: =AW88/AW$14 -> 0.23898823 | ... CD90: =CD88/CD$14 -> 0.22095547
B92: EBITDA (Cons method ex SBC) | AK92: =AK88+AK80 -> 1491 | AL92: =AL88+AL80 -> 0 | AM92: =AM88+AM80 -> 0 | AN92: =AN88+AN80 -> 0 | AO92: =AO88+AO80 -> 0 | AP92: =AP88+AP80 -> 1809 | AQ92: =AQ88+AQ80 -> 519 | AR92: =AR88+AR80 -> 533 | ... CD92: =CD88+CD80 -> 6653.3173
B93: YoY % change | AP93: =IF(ISERROR(AP92/AK92-1), "NM", (AP92/AK92-1)) -> 0.21327968 | AQ93: =IF(ISERROR(AQ92/AL92-1), "NM", (AQ92/AL92-1)) -> NM | AR93: =IF(ISERROR(AR92/AM92-1), "NM", (AR92/AM92-1)) -> NM | AS93: =IF(ISERROR(AS92/AN92-1), "NM", (AS92/AN92-1)) -> NM | AT93: =IF(ISERROR(AT92/AO92-1), "NM", (AT92/AO92-1)) -> NM | AU93: =IF(ISERROR(AU92/AP92-1), "NM", (AU92/AP92-1)) -> 0.18573798 | AV93: =IF(ISERROR(AV92/AQ92-1), "NM", (AV92/AQ92-1)) -> 0.14065511 | AW93: =IF(ISERROR(AW92/AR92-1), "NM", (AW92/AR92-1)) -> 0.19512195 | ... CD93: =IF(ISERROR(CD92/BY92-1), "NM", (CD92/BY92-1)) -> 0.20570074
B94: EBITDA Margin on Net Revenue | AK94: =AK92/AK$14 -> 0.26333451 | AP94: =AP92/AP$14 -> 0.26891631 | AQ94: =AQ92/AQ$14 -> 0.27739177 | AR94: =AR92/AR$14 -> 0.26905603 | AS94: =AS92/AS$14 -> 0.23795028 | AT94: =AT92/AT$14 -> 0.2530836 | AU94: =AU92/AU$14 -> 0.26772341 | AV94: =AV92/AV$14 -> 0.27741331 | AW94: =AW92/AW$14 -> 0.27780201 | ... CD94: =CD92/CD$14 -> 0.27895547
B96: Other Income (Expense), net | AK96: 11 | AP96: =-7+7 -> 0 | AQ96: -4 | AR96: -3 | AS96: 1 | AT96: -1 | AU96: =-7 -> -7 | AV96: -1 | AW96: 1 | AX96: =20-12 -> 8 | AY96: 7 | AZ96: =SUM(AV96:AY96) -> 15 | BA96: 15 | BB96: 9 | BC96: 12 | BD96: 9 | BE96: =SUM(BA96:BD96) -> 45 | BF96: 7 | BG96: 17 | BH96: 28 | BI96: 21 | BJ96: =SUM(BF96:BI96) -> 73 | BK96: 14 | BL96: 3 | BM96: 3 | BN96: =+BM96 -> 3 | BO96: =SUM(BK96:BN96) -> 23 | BP96: 0 | BQ96: 0 | BR96: 0 | BS96: 0 | BT96: =SUM(BP96:BS96) -> 0 | BU96: 0 | BV96: 0 | BW96: 0 | BX96: 0 | BY96: =SUM(BU96:BX96) -> 0 | BZ96: 0 | CA96: 0 | CB96: 0 | CC96: 0 | CD96: =SUM(BZ96:CC96) -> 0
B98: Income before income taxes (PayPal method) | AK98: =AK76+AK96 -> 1178 | AP98: =AP76+AP96 -> 1411 | AQ98: =AQ76+AQ96 -> 403 | AR98: =AR76+AR96 -> 418 | AS98: =AS76+AS96 -> 354 | AT98: =AT76+AT96 -> 435 | AU98: =AU76+AU96 -> 1610 | AV98: =AV76+AV96 -> 464 | AW98: =AW76+AW96 -> 506 | ... CD98: =CD76+CD96 -> 5998.3173
B99: as a % of net revenue | AK99: =AK98/AK$14 -> 0.20805369 | AP99: =AP98/AP$14 -> 0.20975175 | AQ99: =AQ98/AQ$14 -> 0.21539284 | AR99: =AR98/AR$14 -> 0.21100454 | AS99: =AS98/AS$14 -> 0.17960426 | AT99: =AT98/AT$14 -> 0.19872088 | AU99: =AU98/AU$14 -> 0.20094858 | AV99: =AV98/AV$14 -> 0.21743205 | AW99: =AW98/AW$14 -> 0.22067161 | ... CD99: =CD98/CD$14 -> 0.25149311
B101: Income tax expense/(benefit) | AK101: =113+104 -> 217 | AP101: =129+96 -> 225 | AQ101: =0.173697270471464*AQ98 -> 70 | AR101: 72 | AS101: 66 | AT101: 87 | AU101: =SUM(AQ101:AT101) -> 295 | AV101: 111 | AW101: =+(94+19)/(399+122)*AW98 -> 109.74664 | AX101: =49+32 -> 81 | AY101: =51+45 -> 96 | AZ101: =SUM(AV101:AY101) -> 397.74664 | BA101: =57+43 -> 100 | BB101: =57+44 -> 101 | BC101: =37+40 -> 77 | BD101: =79+37 -> 116 | BE101: =SUM(BA101:BD101) -> 394 | BF101: =54+62 -> 116 | BG101: =36+86 -> 122 | BH101: =71+66-23 -> 114 | BI101: =244+115-201 -> 158 | BJ101: =SUM(BF101:BI101) -> 510 | BK101: =37+117-3 -> 151 | BL101: =BL98*BL102 -> 150.59198 | BM101: =BM98*BM102 -> 141.99772 | BN101: =BN98*BN102 -> 178.0053 | BO101: =SUM(BK101:BN101) -> 621.59501 | BP101: =BP98*BP102 -> 180.27186 | BQ101: =BQ98*BQ102 -> 189.22587 | BR101: =BR98*BR102 -> 189.66052 | BS101: =BS98*BS102 -> 237.5163 | BT101: =SUM(BP101:BS101) -> 796.67455 | BU101: =BU98*BU102 -> 222.41079 | BV101: =BV98*BV102 -> 235.48331 | BW101: =BW98*BW102 -> 230.84708 | BX101: =BX98*BX102 -> 291.50206 | BY101: =SUM(BU101:BX101) -> 980.24324 | BZ101: =BZ98*BZ102 -> 274.96891 | CA101: =CA98*CA102 -> 292.12971 | CB101: =CB98*CB102 -> 292.92154 | CC101: =CC98*CC102 -> 369.63489 | CD101: =SUM(BZ101:CC101) -> 1229.6551
B102: Effective Tax Rate | AK102: =AK101/AK98 -> 0.18421053 | AP102: =AP101/AP98 -> 0.15946137 | AQ102: =AQ101/AQ98 -> 0.17369727 | AR102: =AR101/AR98 -> 0.1722488 | AS102: =AS101/AS98 -> 0.18644068 | AT102: =AT101/AT98 -> 0.2 | AU102: =AU101/AU98 -> 0.18322981 | AV102: =AV101/AV98 -> 0.23922414 | AW102: =AW101/AW98 -> 0.2168906 | ... BK102: =BK101/BK98 -> 0.17912218 | BL102: 0.18 | BM102: =+BL102 -> 0.18 | BN102: =+BM102 -> 0.18 | BO102: =BO101/BO98 -> 0.17978597 | BP102: 0.195 | BQ102: =BP102 -> 0.195 | BR102: =BQ102 -> 0.195 | BS102: =BR102 -> 0.195 | BT102: =BT101/BT98 -> 0.195 | BU102: 0.2 | BV102: =BU102 -> 0.2 | BW102: =BV102 -> 0.2 | BX102: =BW102 -> 0.2 | BY102: =BY101/BY98 -> 0.2 | BZ102: 0.205 | CA102: =BZ102 -> 0.205 | CB102: =CA102 -> 0.205 | CC102: =CB102 -> 0.205 | CD102: =CD101/CD98 -> 0.205
B104: Adjusted Net Income (PayPal Method) | AK104: =AK98-AK101 -> 961 | AP104: =AP98-AP101 -> 1186 | AQ104: =AQ98-AQ101 -> 333 | AR104: =AR98-AR101 -> 346 | AS104: =AS98-AS101 -> 288 | AT104: =AT98-AT101 -> 348 | AU104: =AU98-AU101 -> 1315 | AV104: =AV98-AV101 -> 353 | AW104: =AW98-AW101 -> 396.25336 | ... CD104: =CD98-CD101 -> 4768.6623
B105: Adjusted EPS (PayPal Method) | AK105: =IF(ISERROR(AK104/AK143),"NM",AK104/AK143) -> NM | AP105: =IF(ISERROR(AP104/AP143),"NM",AP104/AP143) -> 0.90327494 | AQ105: =AQ104/AQ143 -> 0.26097179 | AR105: =AR104/AR143 -> 0.27308603 | AS105: =AS104/AS143 -> 0.23021583 | AT105: =AT104/AT143 -> 0.28041902 | AU105: =AU104/AU143 -> 1.0596293 | AV105: =AV104/AV143 -> 0.28722539 | AW105: =AW104/AW143 -> 0.3237364 | AX105: =AX104/AX143 -> 0.30725346 | ... CD105: =CD104/CD143 -> 4.0158854 | CE105: =+(BO105/AZ105)^(0.33333)-1 -> 0.22092484
B106: YoY % change | AP106: =IF(ISERROR(AP105/AK105-1), "NM", (AP105/AK105-1)) -> NM | AQ106: =IF(ISERROR(AQ105/AL105-1), "NM", (AQ105/AL105-1)) -> NM | AR106: =IF(ISERROR(AR105/AM105-1), "NM", (AR105/AM105-1)) -> NM | AS106: =IF(ISERROR(AS105/AN105-1), "NM", (AS105/AN105-1)) -> NM | AT106: =IF(ISERROR(AT105/AO105-1), "NM", (AT105/AO105-1)) -> NM | AU106: =IF(ISERROR(AU105/AP105-1), "NM", (AU105/AP105-1)) -> 0.17309723 | AV106: =IF(ISERROR(AV105/AQ105-1), "NM", (AV105/AQ105-1)) -> 0.10059938 | AW106: =IF(ISERROR(AW105/AR105-1), "NM", (AW105/AR105-1)) -> 0.18547406 | ... CD106: =IF(ISERROR(CD105/BY105-1), "NM", (CD105/BY105-1)) -> 0.22468522 | CE106: =+(CD105/BJ105)^(1/4)-1 -> 0.20587257
B108: Income before income taxes (MS method) | AP108: =+AP84+AP96 -> 1142 | AQ108: =+AQ84+AQ96 -> 330 | AR108: =+AR84+AR96 -> 339 | AS108: =+AS84+AS96 -> 278 | AT108: =+AT84+AT96 -> 354 | AU108: =+AU84+AU96 -> 1301 | AV108: =+AV84+AV96 -> 382 | AW108: =+AW84+AW96 -> 417 | ... AY108: =+AY84+AY96 -> 449 | AZ108: =+SUM(AV108:AY108) -> 1612 | BA108: =+BA84+BA96 -> 457 | BB108: =+BB84+BB96 -> 415 | BC108: =+BC84+BC96 -> 393 | BD108: =+BD84+BD96 -> 501 | BE108: =+SUM(BA108:BD108) -> 1766 | BF108: =+BF84+BF96 -> 503 | BG108: =+BG84+BG96 -> 484 | BH108: =+BH84+BH96 -> 477 | BI108: =+BI84+BI96 -> 605 | BJ108: =+SUM(BF108:BI108) -> 2069 | BK108: =+BK84+BK96 -> 602 | BL108: =+BL84+BL96 -> 586.73813 | BM108: =+BM84+BM96 -> 549.39541 | BN108: =+BN84+BN96 -> 711.51682 | BO108: =+SUM(BK108:BN108) -> 2449.6504 | BP108: =+BP84+BP96 -> 679.51849 | BQ108: =+BQ84+BQ96 -> 715.73046 | BR108: =+BR84+BR96 -> 710.61288 | BS108: =+BS84+BS96 -> 914.36304 | BT108: =+SUM(BP108:BS108) -> 3020.2249 | BU108: =+BU84+BU96 -> 818.52588 | BV108: =+BV84+BV96 -> 871.16655 | BW108: =+BW84+BW96 -> 844.58172 | BX108: =+BX84+BX96 -> 1097.3348 | BY108: =+SUM(BU108:BX108) -> 3631.609 | BZ108: =+BZ84+BZ96 -> 1023.1738 | CA108: =+CA84+CA96 -> 1092.5351 | CB108: =+CB84+CB96 -> 1090.4372 | CC108: =+CC84+CC96 -> 1408.8235 | CD108: =+SUM(BZ108:CC108) -> 4614.9697
B109: as a % of net revenue | AV109: =+AV108/AV14 -> 0.17900656 | AW109: =+AW108/AW14 -> 0.18185783 | AX109: =+AX108/AX14 -> 0.16120461 | AY109: =+AY108/AY14 -> 0.1756651 | AZ109: =+AZ108/AZ14 -> 0.17430796 | BA109: =+BA108/BA14 -> 0.17963836 | BB109: =+BB108/BB14 -> 0.15660377 | BC109: =+BC108/BC14 -> 0.14735658 | ... CD109: =+CD108/CD14 -> 0.19349311
B111: Income tax expense/(benefit) | AP111: =+AP108*AP102 -> 182.10489 | AQ111: =+AQ108*AQ102 -> 57.320099 | AR111: =+AR108*AR102 -> 58.392344 | AS111: =+AS108*AS102 -> 51.830508 | AT111: =+AT108*AT102 -> 70.8 | AU111: =+SUM(AQ111:AT111) -> 238.34295 | AV111: =+AV108*AV102 -> 91.383621 | AW111: =+AW108*AW102 -> 90.443378 | AX111: =+AX108*AX102 -> 64.375546 | AY111: =+AY108*AY102 -> 79.970315 | AZ111: =+SUM(AV111:AY111) -> 326.17286 | BA111: =+BA108*BA102 -> 82.789855 | BB111: =+BB108*BB102 -> 78.054004 | BC111: =+BC108*BC102 -> 60.280876 | BD111: =+BD108*BD102 -> 92.541401 | BE111: =+SUM(BA111:BD111) -> 313.66614 | BF111: =+BF108*BF102 -> 89.766154 | BG111: =+BG108*BG102 -> 87.349112 | BH111: =+BH108*BH102 -> 80.679525 | BI111: =+BI108*BI102 -> 115.44686 | BJ111: =+SUM(BF111:BI111) -> 373.24165 | BK111: =+BK108*BK102 -> 107.83155 | BL111: =+BL108*BL102 -> 105.61286 | BM111: =+BM108*BM102 -> 98.891173 | BN111: =+BN108*BN102 -> 128.07303 | BO111: =+SUM(BK111:BN111) -> 440.40862 | BP111: =+BP108*BP102 -> 132.50611 | BQ111: =+BQ108*BQ102 -> 139.56744 | BR111: =+BR108*BR102 -> 138.56951 | BS111: =+BS108*BS102 -> 178.30079 | BT111: =+SUM(BP111:BS111) -> 588.94385 | BU111: =+BU108*BU102 -> 163.70518 | BV111: =+BV108*BV102 -> 174.23331 | BW111: =+BW108*BW102 -> 168.91634 | BX111: =+BX108*BX102 -> 219.46696 | BY111: =+SUM(BU111:BX111) -> 726.32179 | BZ111: =+BZ108*BZ102 -> 209.75063 | CA111: =+CA108*CA102 -> 223.96969 | CB111: =+CB108*CB102 -> 223.53963 | CC111: =+CC108*CC102 -> 288.80882 | CD111: =+SUM(BZ111:CC111) -> 946.06878
B112: Effective Tax Rate | AP112: =+AP111/AP108 -> 0.15946137 | AQ112: =+AQ111/AQ108 -> 0.17369727 | AR112: =+AR111/AR108 -> 0.1722488 | AS112: =+AS111/AS108 -> 0.18644068 | AT112: =+AT111/AT108 -> 0.2 | AU112: =+AU111/AU108 -> 0.18319981 | AV112: =+AV111/AV108 -> 0.23922414 | AW112: =+AW111/AW108 -> 0.2168906 | ... CD112: =+CD111/CD108 -> 0.205
B114: Adjusted Net Income (SBC Burdened) | AP114: =+AP108-AP111 -> 959.89511 | AQ114: =+AQ108-AQ111 -> 272.6799 | AR114: =+AR108-AR111 -> 280.60766 | AS114: =+AS108-AS111 -> 226.16949 | AT114: =+AT108-AT111 -> 283.2 | AU114: =+AU108-AU111 -> 1062.657 | AV114: =+AV108-AV111 -> 290.61638 | AW114: =+AW108-AW111 -> 326.55662 | ... CD114: =+CD108-CD111 -> 3668.9009
B115: Adjusted EPS (SBC Burdened) | AP115: =+AP114/AP143 -> 0.73107015 | AQ115: =+AQ114/AQ143 -> 0.21369898 | AR115: =+AR114/AR143 -> 0.22147408 | AS115: =+AS114/AS143 -> 0.18079096 | AT115: =+AT114/AT143 -> 0.22820306 | AU115: =+AU114/AU143 -> 0.85629093 | AV115: =+AV114/AV143 -> 0.23646573 | AW115: =+AW114/AW143 -> 0.26679463 | ... CD115: =+CD114/CD143 -> 3.0897314 | CE115: =(BY115/BE115)^0.25-1 -> 0.19464437
B116: YoY % change | AQ116: =IF(ISERROR(AQ115/AL115-1), "NM", (AQ115/AL115-1)) -> NM | AR116: =IF(ISERROR(AR115/AM115-1), "NM", (AR115/AM115-1)) -> NM | AS116: =IF(ISERROR(AS115/AN115-1), "NM", (AS115/AN115-1)) -> NM | AT116: =IF(ISERROR(AT115/AO115-1), "NM", (AT115/AO115-1)) -> NM | AU116: =IF(ISERROR(AU115/AP115-1), "NM", (AU115/AP115-1)) -> 0.17128422 | AV116: =IF(ISERROR(AV115/AQ115-1), "NM", (AV115/AQ115-1)) -> 0.10653652 | AW116: =IF(ISERROR(AW115/AR115-1), "NM", (AW115/AR115-1)) -> 0.20463139 | AX116: =IF(ISERROR(AX115/AS115-1), "NM", (AX115/AS115-1)) -> 0.35069092 | AY116: =IF(ISERROR(AY115/AT115-1), "NM", (AY115/AT115-1)) -> 0.3147244 | AZ116: =+AZ115/AU115-1 -> 0.22331906 | BA116: =IF(ISERROR(BA115/AV115-1), "NM", (BA115/AV115-1)) -> 0.29184754 | BB116: =IF(ISERROR(BB115/AW115-1), "NM", (BB115/AW115-1)) -> 0.039457998 | BC116: =IF(ISERROR(BC115/AX115-1), "NM", (BC115/AX115-1)) -> 0.12234502 | BD116: =IF(ISERROR(BD115/AY115-1), "NM", (BD115/AY115-1)) -> 0.11958811 | BE116: =+BE115/AZ115-1 -> 0.13877102 | BF116: =IF(ISERROR(BF115/BA115-1), "NM", (BF115/BA115-1)) -> 0.112456 | BG116: =IF(ISERROR(BG115/BB115-1), "NM", (BG115/BB115-1)) -> 0.17719424 | BH116: =IF(ISERROR(BH115/BC115-1), "NM", (BH115/BC115-1)) -> 0.18239062 | BI116: =IF(ISERROR(BI115/BD115-1), "NM", (BI115/BD115-1)) -> 0.18682587 | BJ116: =+BJ115/BE115-1 -> 0.16473918 | BK116: =IF(ISERROR(BK115/BF115-1), "NM", (BK115/BF115-1)) -> 0.19487403 | BL116: =IF(ISERROR(BL115/BG115-1), "NM", (BL115/BG115-1)) -> 0.21342232 | BM116: =IF(ISERROR(BM115/BH115-1), "NM", (BM115/BH115-1)) -> 0.14704672 | BN116: =IF(ISERROR(BN115/BI115-1), "NM", (BN115/BI115-1)) -> 0.20943873 | BO116: =+BO115/BJ115-1 -> 0.19179348 | BP116: =IF(ISERROR(BP115/BK115-1), "NM", (BP115/BK115-1)) -> 0.11543566 | BQ116: =IF(ISERROR(BQ115/BL115-1), "NM", (BQ115/BL115-1)) -> 0.2064455 | BR116: =IF(ISERROR(BR115/BM115-1), "NM", (BR115/BM115-1)) -> 0.27865403 | BS116: =IF(ISERROR(BS115/BN115-1), "NM", (BS115/BN115-1)) -> 0.26982735 | BT116: =+BT115/BO115-1 -> 0.21871478 | BU116: =IF(ISERROR(BU115/BP115-1), "NM", (BU115/BP115-1)) -> 0.20541283 | BV116: =IF(ISERROR(BV115/BQ115-1), "NM", (BV115/BQ115-1)) -> 0.21849555 | BW116: =IF(ISERROR(BW115/BR115-1), "NM", (BW115/BR115-1)) -> 0.19032923 | BX116: =IF(ISERROR(BX115/BS115-1), "NM", (BX115/BS115-1)) -> 0.2023711 | BY116: =+BY115/BT115-1 -> 0.20398975 | BZ116: =IF(ISERROR(BZ115/BU115-1), "NM", (BZ115/BU115-1)) -> 0.25174856 | CA116: =IF(ISERROR(CA115/BV115-1), "NM", (CA115/BV115-1)) -> 0.25526546 | CB116: =IF(ISERROR(CB115/BW115-1), "NM", (CB115/BW115-1)) -> 0.2916834 | CC116: =IF(ISERROR(CC115/BX115-1), "NM", (CC115/BX115-1)) -> 0.28384551 | CD116: =+CD115/BY115-1 -> 0.27165315 | CE116: =+(BT115/BE115)^(1/3)-1 -> 0.19154539
B118: Adjusted Net Income (PayPal Method Incl SBC) | AK118: =AK112-AK115 -> 0 | AP118: =AP112-AP115 -> -0.57160878 | AQ118: =AQ104-AQ80*(1-AQ102) -> 272.6799 | AR118: =AR104-AR80*(1-AR102) -> 280.60766 | AS118: =AS104-AS80*(1-AS102) -> 226.16949 | AT118: =AT104-AT80*(1-AT102) -> 283.2 | AU118: =SUM(AQ118:AT118) -> 1062.657 | AV118: =AV104-AV80*(1-AV102) -> 290.61638 | AW118: =AW104-AW80*(1-AW102) -> 326.55662 | AX118: =AX104-AX80*(1-AX102) -> 299.62445 | AY118: =AY104-AY80*(1-AY102) -> 369.02968 | AZ118: =SUM(AV118:AY118) -> 1285.8271 | BA118: =BA104-BA80*(1-BA102) -> 374.21014 | BB118: =BB104-BB80*(1-BB102) -> 336.946 | BC118: =BC104-BC80*(1-BC102) -> 332.71912 | BD118: =BD104-BD80*(1-BD102) -> 408.4586 | BE118: =SUM(BA118:BD118) -> 1452.3339 | BF118: =BF104-BF80*(1-BF102) -> 413.23385 | BG118: =BG104-BG80*(1-BG102) -> 396.65089 | BH118: =BH104-BH80*(1-BH102) -> 396.32047 | BI118: =BI104-BI80*(1-BI102) -> 489.55314 | BJ118: =SUM(BF118:BI118) -> 1695.7583 | BK118: =BK104-BK80*(1-BK102) -> 494.16845 | BL118: =BL104-BL80*(1-BL102) -> 481.12527 | BM118: =BM104-BM80*(1-BM102) -> 450.50423 | BN118: =BN104-BN80*(1-BN102) -> 583.44379 | BO118: =SUM(BK118:BN118) -> 2009.2417 | BP118: =BP104-BP80*(1-BP102) -> 547.01239 | BQ118: =BQ104-BQ80*(1-BQ102) -> 576.16302 | BR118: =BR104-BR80*(1-BR102) -> 572.04337 | BS118: =BS104-BS80*(1-BS102) -> 736.06225 | BT118: =SUM(BP118:BS118) -> 2431.281 | BU118: =BU104-BU80*(1-BU102) -> 654.8207 | BV118: =BV104-BV80*(1-BV102) -> 696.93324 | BW118: =BW104-BW80*(1-BW102) -> 675.66538 | BX118: =BX104-BX80*(1-BX102) -> 877.86784 | BY118: =SUM(BU118:BX118) -> 2905.2872 | BZ118: =BZ104-BZ80*(1-BZ102) -> 813.42319 | CA118: =CA104-CA80*(1-CA102) -> 868.56539 | CB118: =CB104-CB80*(1-CB102) -> 866.8976 | CC118: =CC104-CC80*(1-CC102) -> 1120.0147 | CD118: =SUM(BZ118:CC118) -> 3668.9009
AQ119: =AQ118/AQ143 -> 0.21369898 | AR119: =AR118/AR143 -> 0.22147408 | AS119: =AS118/AS143 -> 0.18079096 | AT119: =AT118/AT143 -> 0.22820306 | AU119: =AU118/AU143 -> 0.85629093 | AV119: =AV118/AV143 -> 0.23646573 | AW119: =AW118/AW143 -> 0.26679463 | AX119: =AX118/AX143 -> 0.24419271 | ... CD119: =CD118/CD143 -> 3.0897314
BI120: =740-620 -> 120
B121: Reconcilation to Net Income (GAAP)
B122: Other income adjustment / amortization | AK122: 58 | AP122: =55+7 -> 62 | AQ122: 2 | AR122: 1 | AS122: =1-4 -> -3 | AT122: 0 | AU122: =SUM(AQ122:AT122) -> 0 | AV122: 0 | AW122: 0 | AX122: =-12+1 -> -11 | AY122: 0 | AZ122: 0 | BA122: 0 | BB122: 0 | BC122: 1 | BD122: 0 | BE122: =SUM(BA122:BD122) -> 1 | BF122: 2 | BG122: 15 | BH122: 0 | BI122: =-317 -> -317 | BJ122: =SUM(BF122:BI122) -> -300 | BK122: 25 | BL122: 0 | BM122: 0 | BN122: 0 | BO122: =SUM(BK122:BN122) -> 25 | BP122: 0 | BQ122: 0 | BR122: 0 | BS122: 0 | BT122: =SUM(BP122:BS122) -> 0 | BU122: 0 | BV122: 0 | BW122: 0 | BX122: 0 | BY122: =SUM(BU122:BX122) -> 0 | BZ122: 0 | CA122: 0 | CB122: 0 | CC122: 0 | CD122: =SUM(BZ122:CC122) -> 0
B123: Amortization of acquired intangibles | AQ123: 21 | AR123: 16 | AS123: 16 | AT123: 17 | AU123: =+SUM(AQ123:AT123) -> 70 | AV123: 16 | AW123: 20 | AX123: 20 | AY123: 29 | AZ123: =+SUM(AV123:AY123) -> 85 | BA123: 34 | BB123: 35 | BC123: 32 | BD123: =BC123 -> 32 | BE123: =+SUM(BA123:BD123) -> 133 | BF123: 23 | BG123: 22 | BH123: 26 | BI123: 58 | BJ123: =+SUM(BF123:BI123) -> 129 | BK123: 29 | BL123: 15 | BM123: 15 | BN123: 15 | BO123: =+SUM(BK123:BN123) -> 74 | BP123: 15 | BQ123: 15 | BR123: 15 | BS123: 15 | BT123: =+SUM(BP123:BS123) -> 60 | BU123: 15 | BV123: 15 | BW123: 15 | BX123: 15 | BY123: =+SUM(BU123:BX123) -> 60 | BZ123: 15 | CA123: 15 | CB123: 15 | CC123: 15 | CD123: =+SUM(BZ123:CC123) -> 60
B124: Restructuring | AK124: 19 | AP124: -4 | AQ124: 0 | AR124: 0 | AS124: 0 | AT124: 1 | AU124: =SUM(AQ124:AT124) -> 1 | AV124: 48 | AW124: 1 | AX124: 0 | AY124: 1 | AZ124: =SUM(AV124:AY124) -> 50 | BA124: 0 | BB124: 0 | BC124: 0 | BD124: 0 | BE124: =SUM(BA124:BD124) -> 0 | BF124: 40 | BG124: 0 | BH124: 0 | BI124: 0 | BJ124: =SUM(BF124:BI124) -> 40 | BK124: 0 | BL124: 0 | BM124: 0 | BN124: 0 | BO124: =SUM(BK124:BN124) -> 0 | BP124: 0 | BQ124: 0 | BR124: 0 | BS124: 0 | BT124: =SUM(BP124:BS124) -> 0 | BU124: 0 | BV124: 0 | BW124: 0 | BX124: 0 | BY124: =SUM(BU124:BX124) -> 0 | BZ124: 0 | CA124: 0 | CB124: 0 | CC124: 0 | CD124: =SUM(BZ124:CC124) -> 0
B125: Separation related | AK125: 0 | AP125: 0 | AQ125: 0 | AR125: 0 | AS125: 0 | AT125: 0 | AU125: =SUM(AQ125:AT125) -> 0 | AV125: =4+1 -> 5 | AW125: 9 | AX125: =3 -> 3 | AY125: 2 | AZ125: =SUM(AV125:AY125) -> 19 | BA125: 0 | BB125: 0 | BC125: 0 | BD125: 0 | BE125: =SUM(BA125:BD125) -> 0 | BF125: 0 | BG125: 0 | BH125: 0 | BI125: 0 | BJ125: =SUM(BF125:BI125) -> 0 | BK125: 0 | BL125: 0 | BM125: 0 | BN125: 0 | BO125: =SUM(BK125:BN125) -> 0 | BP125: 0 | BQ125: 0 | BR125: 0 | BS125: 0 | BT125: =SUM(BP125:BS125) -> 0 | BU125: 0 | BV125: 0 | BW125: 0 | BX125: 0 | BY125: =SUM(BU125:BX125) -> 0 | BZ125: 0 | CA125: 0 | CB125: 0 | CC125: 0 | CD125: =SUM(BZ125:CC125) -> 0
B126: Lower Transaction revenues | AK126: 0 | AL126: 0 | AM126: 0 | AN126: 0 | AO126: 0 | AP126: 0 | AQ126: -3 | AR126: -2 | AS126: -4 | AT126: -4 | AU126: =SUM(AQ126:AT126) -> -13 | AV126: -3 | AW126: 0 | AX126: 0 | AY126: 0 | AZ126: =SUM(AV126:AY126) -> -3 | BA126: 0 | BB126: 0 | BC126: 0 | BD126: 0 | BE126: =SUM(BA126:BD126) -> 0 | BF126: 0 | BG126: 0 | BH126: 0 | BI126: 0 | BJ126: =SUM(BF126:BI126) -> 0 | BK126: 0 | BL126: 0 | BM126: 0 | BN126: 0 | BO126: =SUM(BK126:BN126) -> 0 | BP126: 0 | BQ126: 0 | BR126: 0 | BS126: 0 | BT126: =SUM(BP126:BS126) -> 0 | BU126: 0 | BV126: 0 | BW126: 0 | BX126: 0 | BY126: =SUM(BU126:BX126) -> 0 | BZ126: 0 | CA126: 0 | CB126: 0 | CC126: 0 | CD126: =SUM(BZ126:CC126) -> 0
B127: Protection programme related adjustment | AK127: 0 | AL127: 0 | AM127: 0 | AN127: 0 | AO127: 0 | AP127: 0 | AQ127: =-12-2-1 -> -15 | AR127: =-10-2-1 -> -13 | AS127: =-10-4-2 -> -16 | AT127: =-11-5-2 -> -18 | AU127: =SUM(AQ127:AT127) -> -62 | AV127: =-10-3-1 -> -14 | AW127: =-12-5 -> -17 | AX127: 0 | AY127: 0 | AZ127: =SUM(AV127:AY127) -> -31 | BA127: 0 | BB127: 0 | BC127: 0 | BD127: 0 | BE127: =SUM(BA127:BD127) -> 0 | BF127: 0 | BG127: 0 | BH127: 0 | BI127: 0 | BJ127: =SUM(BF127:BI127) -> 0 | BK127: 0 | BL127: 0 | BM127: 0 | BN127: 0 | BO127: =SUM(BK127:BN127) -> 0 | BP127: 0 | BQ127: 0 | BR127: 0 | BS127: 0 | BT127: =SUM(BP127:BS127) -> 0 | BU127: 0 | BV127: 0 | BW127: 0 | BX127: 0 | BY127: =SUM(BU127:BX127) -> 0 | BZ127: 0 | CA127: 0 | CB127: 0 | CC127: 0 | CD127: =SUM(BZ127:CC127) -> 0
...

Sheet Segment Detail
B1: Segment Detail
B2: Fiscal Year End: December ($ in millions, except per share data)
B3: Scenario:
C4: 1Q06A | D4: 2Q06A | E4: 3Q06A | F4: 4Q06A | G4: 2006A | H4: 1Q07A | I4: 2Q07A | J4: 3Q07A | K4: 4Q07A | L4: 2007A | M4: 1Q08A | N4: 2Q08A | O4: 3Q08A | P4: 4Q08A | Q4: 2008A | R4: 1Q09A | S4: 2Q09A | T4: 3Q09A | U4: 4Q09A | V4: 2009A | W4: 1Q10A | X4: 2Q10A | Y4: 3Q10A | Z4: 4Q10A | AA4: 2010A | AB4: 1Q11A | AC4: 2Q11A | AD4: 3Q11A | AE4: 4Q11A | AF4: 2011A | AG4: 1Q12A | AH4: 2Q12A | AI4: 3Q12A | AJ4: 4Q12A | AK4: ='Quarterly Model'!AK3 -> 2012A | AL4: 1Q13A | AM4: 2Q13A | AN4: 3Q13A | AO4: 4Q13A | AP4: ='Quarterly Model'!AP3 -> 2013A | AQ4: ='Quarterly Model'!AQ3 -> 1Q14A | AR4: ='Quarterly Model'!AR3 -> 2Q14A | AS4: ='Quarterly Model'!AS3 -> 3Q14A | AT4: ='Quarterly Model'!AT3 -> 4Q14A | AU4: ='Quarterly Model'!AU3 -> 2014A | AV4: ='Quarterly Model'!AV3 -> 1Q15A | AW4: ='Quarterly Model'!AW3 -> 2Q15A | ... CD4: ='Quarterly Model'!CD3 -> 2021E
B5: Revenue Drivers
B6: TPV | AK6: 150066 | AP6: 185606 | AQ6: 53676 | AR6: 56736 | AS6: 58184 | AT6: 66039 | AU6: 234635 | AV6: 63021 | AW6: 67482 | AX6: 71317 | AY6: 83102 | AZ6: 288038 | BA6: 82559 | BB6: 87763 | BC6: 88895 | BD6: 100711 | BE6: =SUM(BA6:BD6) -> 359928 | BF6: 100639 | BG6: 107800 | BH6: 115224 | BI6: 132515 | BJ6: =SUM(BF6:BI6) -> 456178 | BK6: 132364 | BL6: =+BG6*(1+BL7) -> 140561.34 | BM6: =+BH6*(1+BM7) -> 147059.95 | BN6: =+BI6*(1+BN7) -> 167588.25 | BO6: =SUM(BK6:BN6) -> 587573.54 | BP6: =+BK6*(1+BP7) -> 162467.63 | BQ6: =+BL6*(1+BQ7) -> 172609.32 | BR6: =+BM6*(1+BR7) -> 180589.62 | BS6: =+BN6*(1+BS7) -> 205798.37 | BT6: =SUM(BP6:BS6) -> 721464.95 | BU6: =+BP6*(1+BU7) -> 194961.16 | BV6: =+BQ6*(1+BV7) -> 207131.19 | BW6: =+BR6*(1+BW7) -> 213095.76 | BX6: =+BS6*(1+BX7) -> 242842.07 | BY6: =SUM(BU6:BX6) -> 858030.18 | BZ6: =+BU6*(1+BZ7) -> 228104.56 | CA6: =+BV6*(1+CA7) -> 242343.49 | CB6: =+BW6*(1+CB7) -> 249322.04 | CC6: =+BX6*(1+CC7) -> 284125.23 | CD6: =SUM(BZ6:CC6) -> 1003895.3 | CE6: =+(BO6/AZ6)^(0.33333)-1 -> 0.26824487
B7: YoY % change | AP7: =IF(ISERROR(AP6/AK6-1), "NM", (AP6/AK6-1)) -> 0.23682913 | AU7: =IF(ISERROR(AU6/AP6-1), "NM", (AU6/AP6-1)) -> 0.26415633 | AV7: =IF(ISERROR(AV6/AQ6-1), "NM", (AV6/AQ6-1)) -> 0.17410016 | AW7: =IF(ISERROR(AW6/AR6-1), "NM", (AW6/AR6-1)) -> 0.18940355 | AX7: =IF(ISERROR(AX6/AS6-1), "NM", (AX6/AS6-1)) -> 0.22571497 | AY7: =IF(ISERROR(AY6/AT6-1), "NM", (AY6/AT6-1)) -> 0.25837763 | AZ7: =+AZ6/AU6-1 -> 0.22760032 | BA7: =IF(ISERROR(BA6/AV6-1), "NM", (BA6/AV6-1)) -> 0.31002364 | BB7: =IF(ISERROR(BB6/AW6-1), "NM", (BB6/AW6-1)) -> 0.3005394 | BC7: =IF(ISERROR(BC6/AX6-1), "NM", (BC6/AX6-1)) -> 0.246477 | BD7: =IF(ISERROR(BD6/AY6-1), "NM", (BD6/AY6-1)) -> 0.21189622 | BE7: =IF(ISERROR(BE6/AZ6-1), "NM", (BE6/AZ6-1)) -> 0.24958512 | BF7: =IF(ISERROR(BF6/BA6-1), "NM", (BF6/BA6-1)) -> 0.2189949 | BG7: =IF(ISERROR(BG6/BB6-1), "NM", (BG6/BB6-1)) -> 0.22830806 | BH7: =IF(ISERROR(BH6/BC6-1), "NM", (BH6/BC6-1)) -> 0.29618089 | ... BK7: =IF(ISERROR(BK6/BF6-1), "NM", (BK6/BF6-1)) -> 0.31523564 | BL7: =+BL8+BL12 -> 0.30390851 | BM7: =+BM8+BM12 -> 0.27629621 | BN7: =+BN8+BN12 -> 0.2646738 | BO7: =IF(ISERROR(BO6/BJ6-1), "NM", (BO6/BJ6-1)) -> 0.28803568 | BP7: =+BP8+BP12 -> 0.22743066 | BQ7: =+BQ8+BQ12 -> 0.228 | BR7: =+BR8+BR12 -> 0.228 | BS7: =+BS8+BS12 -> 0.228 | BT7: =IF(ISERROR(BT6/BO6-1), "NM", (BT6/BO6-1)) -> 0.22787174 | BU7: =+BU8+BU12 -> 0.2 | BV7: =+BV8+BV12 -> 0.2 | BW7: =+BW8+BW12 -> 0.18 | BX7: =+BX8+BX12 -> 0.18 | BY7: =IF(ISERROR(BY6/BT6-1), "NM", (BY6/BT6-1)) -> 0.18928879 | BZ7: =+BZ8+BZ12 -> 0.17 | CA7: =+CA8+CA12 -> 0.17 | CB7: =+CB8+CB12 -> 0.17 | CC7: =+CC8+CC12 -> 0.17 | CD7: =IF(ISERROR(CD6/BY6-1), "NM", (CD6/BY6-1)) -> 0.17
B8: YoY % change (ex-FX) | AR8: 0.26 | AS8: 0.27 | AT8: 0.26 | AV8: 0.25 | AW8: 0.27 | AX8: 0.27 | AY8: 0.29 | AZ8: =+AZ7-AZ179 -> 0.28433401 | BA8: 0.31 | BB8: 0.29 | BC8: 0.27 | BD8: 0.25 | BE8: 0.28 | BF8: 0.24 | BG8: 0.25 | BH8: 0.28 | BI8: 0.29 | BJ8: 0.27 | BK8: 0.27 | BL8: =CHOOSE(_Switch,BL9,BL10,BL11) -> 0.2575 | BM8: =CHOOSE(_Switch,BM9,BM10,BM11) -> 0.2475 | BN8: =CHOOSE(_Switch,BN9,BN10,BN11) -> 0.24 | BO8: =+BO7-BO179 -> 0.25099666 | BP8: =CHOOSE(_Switch,BP9,BP10,BP11) -> 0.228 | BQ8: =CHOOSE(_Switch,BQ9,BQ10,BQ11) -> 0.228 | BR8: =CHOOSE(_Switch,BR9,BR10,BR11) -> 0.228 | BS8: =CHOOSE(_Switch,BS9,BS10,BS11) -> 0.228 | BT8: =+BT7-BT179 -> 0.228 | BU8: =CHOOSE(_Switch,BU9,BU10,BU11) -> 0.2 | BV8: =CHOOSE(_Switch,BV9,BV10,BV11) -> 0.2 | BW8: =CHOOSE(_Switch,BW9,BW10,BW11) -> 0.18 | BX8: =CHOOSE(_Switch,BX9,BX10,BX11) -> 0.18 | BY8: =+BY7-BY179 -> 0.18928879 | BZ8: =CHOOSE(_Switch,BZ9,BZ10,BZ11) -> 0.17 | CA8: =CHOOSE(_Switch,CA9,CA10,CA11) -> 0.17 | CB8: =CHOOSE(_Switch,CB9,CB10,CB11) -> 0.17 | CC8: =CHOOSE(_Switch,CC9,CC10,CC11) -> 0.17 | CD8: =+CD7-CD179 -> 0.17 | CE8: =((1+BJ8)*(1+BO8)*(1+BT8))^0.333-1 -> 0.24926909
B9: Bull | BL9: =BL10+3% -> 0.2875 | BM9: =BM10+3% -> 0.2775 | BN9: =BN10+3% -> 0.27 | BP9: =BP10+1% -> 0.238 | BQ9: =BQ10+1% -> 0.238 | BR9: =BR10+1% -> 0.238 | BS9: =BS10+1% -> 0.238 | BU9: =BU10+3% -> 0.23 | BV9: =BV10+3% -> 0.23 | BW9: =BW10+3% -> 0.21 | BX9: =BX10+3% -> 0.21 | BZ9: =BZ10+3% -> 0.2 | CA9: =CA10+3% -> 0.2 | CB9: =CB10+3% -> 0.2 | CC9: =CC10+3% -> 0.2
B10: Base | BL10: 0.2575 | BM10: =+BL10-1% -> 0.2475 | BN10: =+BM10-0.75% -> 0.24 | BP10: =23.5%-0.7% -> 0.228 | BQ10: =+BP10 -> 0.228 | BR10: =+BQ10 -> 0.228 | BS10: =+BR10 -> 0.228 | BU10: 0.2 | BV10: =BU10 -> 0.2 | BW10: =20%-0.02 -> 0.18 | BX10: =BW10 -> 0.18 | BZ10: =19%-0.02 -> 0.17 | CA10: =BZ10 -> 0.17 | CB10: =CA10 -> 0.17 | CC10: =CB10 -> 0.17
B11: Bear | BL11: =BL10-3% -> 0.2275 | BM11: =BM10-3% -> 0.2175 | BN11: =BN10-3% -> 0.21 | BP11: =BP10-4% -> 0.188 | BQ11: =BQ10-4% -> 0.188 | BR11: =BR10-4% -> 0.188 | BS11: =BS10-4% -> 0.188 | BU11: =BU10-4% -> 0.16 | BV11: =BV10-4% -> 0.16 | BW11: =BW10-4% -> 0.14 | BX11: =BX10-4% -> 0.14 | BZ11: =BZ10-4% -> 0.13 | CA11: =CA10-4% -> 0.13 | CB11: =CB10-4% -> 0.13 | CC11: =CC10-4% -> 0.13
B12: Estimated FX Impact on TPV | BL12: =BL179 -> 0.046408515 | BM12: =BM179 -> 0.02879621 | BN12: =BN179 -> 0.024673796 | BP12: =BP179 -> -0.00056933849 | BQ12: =BQ179 -> 0 | BR12: =BR179 -> 0 | BS12: =BS179 -> 0 | BU12: =BU179 -> 0 | BV12: =BV179 -> 0 | BW12: =BW179 -> 0 | BX12: =BX179 -> 0 | BZ12: =BZ179 -> 0 | CA12: =CA179 -> 0 | CB12: =CB179 -> 0 | CC12: =CC179 -> 0
B14: TPV from large merchants | AP14: =+AP16*AP6 -> 72386.34 | AQ14: =+AQ6*AQ16 -> 21470.4 | AR14: =+AR6*AR16 -> 24396.48 | AS14: =+AS6*AS16 -> 25019.12 | AT14: =+AT6*AT16 -> 28396.77 | AU14: =+AU16*AU6 -> 98546.7 | AV14: =+AV6*AV16 -> 26468.82 | AW14: =+AW6*AW16 -> 31041.72 | AX14: =+AX6*AX16 -> 32805.82 | AY14: =AY6*AY16 -> 38226.92 | AZ14: =SUM(AV14:AY14) -> 128543.28 | BA14: =BA6*BA16 -> 37151.55 | BB14: =BB6*BB16 -> 42126.24 | BC14: =BC6*BC16 -> 42669.6 | BD14: =BD6*BD16 -> 48341.28 | BE14: =SUM(BA14:BD14) -> 170288.67 | BF14: =BF6*BF16 -> 48306.72 | BG14: =BG6*BG16 -> 52283 | BH14: =BH6*BH16 -> 56459.76 | BI14: =BI6*BI16 -> 65594.925 | BJ14: =SUM(BF14:BI14) -> 222644.41 | BK14: =BK6*BK16 -> 66049.636 | BL14: =BL6*BL16 -> 70702.353 | BM14: =BM6*BM16 -> 74559.397 | BN14: =BN6*BN16 -> 85637.595 | BO14: =SUM(BK14:BN14) -> 296948.98 | BP14: =BP6*BP16 -> 83345.895 | BQ14: =BQ6*BQ16 -> 88893.801 | BR14: =BR6*BR16 -> 93364.836 | BS14: =BS6*BS16 -> 106809.35 | BT14: =SUM(BP14:BS14) -> 372413.89 | BU14: =BU6*BU16 -> 101574.76 | BV14: =BV6*BV16 -> 108329.61 | BW14: =BW6*BW16 -> 111875.27 | BX14: =BX6*BX16 -> 127977.77 | BY14: =SUM(BU14:BX14) -> 449757.42 | BZ14: =BZ6*BZ16 -> 120667.31 | CA14: =CA6*CA16 -> 128684.39 | CB14: =CB6*CB16 -> 132888.64 | CC14: =CC6*CC16 -> 152007 | CD14: =SUM(BZ14:CC14) -> 534247.34
B15: YoY % change | AU15: =+AU14/AP14-1 -> 0.36139913 | AV15: =+AV14/AQ14-1 -> 0.23280516 | AW15: =+AW14/AR14-1 -> 0.2723852 | AX15: =+AX14/AS14-1 -> 0.31122997 | AY15: =AY14/AT14-1 -> 0.34617141 | AZ15: =+AZ14/AU14-1 -> 0.30438949 | BA15: =BA14/AV14-1 -> 0.40359676 | BB15: =BB14/AW14-1 -> 0.35708459 | BC15: =BC14/AX14-1 -> 0.30067165 | BD15: =BD14/AY14-1 -> 0.26458736 | BE15: =BE14/AZ14-1 -> 0.32475747 | BF15: =BF14/BA14-1 -> 0.30026123 | BG15: =BG14/BB14-1 -> 0.24110293 | BH15: =BH14/BC14-1 -> 0.32318466 | ... CD15: =CD14/BY14-1 -> 0.18785665
B16: % of total TPV | AP16: 0.39 | AQ16: 0.4 | AR16: 0.43 | AS16: 0.43 | AT16: 0.43 | AU16: 0.42 | AV16: 0.42 | AW16: 0.46 | AX16: 0.46 | AY16: 0.46 | AZ16: =AZ14/AZ6 -> 0.44627195 | BA16: 0.45 | BB16: 0.48 | BC16: 0.48 | BD16: =+BC16 -> 0.48 | BE16: =BE14/BE6 -> 0.47311871 | BF16: 0.48 | BG16: 0.485 | BH16: 0.49 | BI16: 0.495 | BJ16: =BJ14/BJ6 -> 0.48806476 | BK16: 0.499 | BL16: =CHOOSE(_Switch,BL17,BL18,BL19) -> 0.503 | BM16: =CHOOSE(_Switch,BM17,BM18,BM19) -> 0.507 | BN16: =CHOOSE(_Switch,BN17,BN18,BN19) -> 0.511 | BO16: =BO14/BO6 -> 0.50538181 | BP16: =CHOOSE(_Switch,BP17,BP18,BP19) -> 0.513 | BQ16: =CHOOSE(_Switch,BQ17,BQ18,BQ19) -> 0.515 | BR16: =CHOOSE(_Switch,BR17,BR18,BR19) -> 0.517 | BS16: =CHOOSE(_Switch,BS17,BS18,BS19) -> 0.519 | BT16: =BT14/BT6 -> 0.51619124 | BU16: =CHOOSE(_Switch,BU17,BU18,BU19) -> 0.521 | BV16: =CHOOSE(_Switch,BV17,BV18,BV19) -> 0.523 | BW16: =CHOOSE(_Switch,BW17,BW18,BW19) -> 0.525 | BX16: =CHOOSE(_Switch,BX17,BX18,BX19) -> 0.527 | BY16: =BY14/BY6 -> 0.52417436 | BZ16: =CHOOSE(_Switch,BZ17,BZ18,BZ19) -> 0.529 | CA16: =CHOOSE(_Switch,CA17,CA18,CA19) -> 0.531 | CB16: =CHOOSE(_Switch,CB17,CB18,CB19) -> 0.533 | CC16: =CHOOSE(_Switch,CC17,CC18,CC19) -> 0.535 | CD16: =CD14/CD6 -> 0.53217436
B17: Bull | BL17: =+BL18+1.5% -> 0.518 | BM17: =+BM18+1.5% -> 0.522 | BN17: =+BN18+1.5% -> 0.526 | BP17: =+BP18+1.5% -> 0.528 | BQ17: =+BQ18+1.5% -> 0.53 | BR17: =+BR18+1.5% -> 0.532 | BS17: =+BS18+1.5% -> 0.534 | BU17: =+BU18+1.5% -> 0.536 | BV17: =+BV18+1.5% -> 0.538 | BW17: =+BW18+1.5% -> 0.54 | BX17: =+BX18+1.5% -> 0.542 | BZ17: =+BZ18+1.5% -> 0.544 | CA17: =+CA18+1.5% -> 0.546 | CB17: =+CB18+1.5% -> 0.548 | CC17: =+CC18+1.5% -> 0.55
B18: Base | BL18: 0.503 | BM18: =BL18+0.004 -> 0.507 | BN18: =BM18+0.004 -> 0.511 | BP18: =BN18+0.002 -> 0.513 | BQ18: =BP18+0.002 -> 0.515 | BR18: =BQ18+0.002 -> 0.517 | BS18: =BR18+0.002 -> 0.519 | BU18: =BS18+0.002 -> 0.521 | BV18: =BU18+0.002 -> 0.523 | BW18: =BV18+0.002 -> 0.525 | BX18: =BW18+0.002 -> 0.527 | BZ18: =BX18+0.002 -> 0.529 | CA18: =BZ18+0.002 -> 0.531 | CB18: =CA18+0.002 -> 0.533 | CC18: =CB18+0.002 -> 0.535
B19: Bear | BL19: =BL18-0.5% -> 0.498 | BM19: =BM18-0.5% -> 0.502 | BN19: =BN18-0.5% -> 0.506 | BP19: =BP18-0.5% -> 0.508 | BQ19: =BQ18-0.5% -> 0.51 | BR19: =BR18-0.5% -> 0.512 | BS19: =BS18-0.5% -> 0.514 | BU19: =BU18-0.5% -> 0.516 | BV19: =BV18-0.5% -> 0.518 | BW19: =BW18-0.5% -> 0.52 | BX19: =BX18-0.5% -> 0.522 | BZ19: =BZ18-0.5% -> 0.524 | CA19: =CA18-0.5% -> 0.526 | CB19: =CB18-0.5% -> 0.528 | CC19: =CC18-0.5% -> 0.53
B21: TPV from small merchants | AP21: =+AP6-AP14 -> 113219.66 | AQ21: =+AQ6-AQ14 -> 32205.6 | AR21: =+AR6-AR14 -> 32339.52 | AS21: =+AS6-AS14 -> 33164.88 | AT21: =+AT6-AT14 -> 37642.23 | AU21: =+AU6-AU14 -> 136088.3 | AV21: =+AV6-AV14 -> 36552.18 | AW21: =+AW6-AW14 -> 36440.28 | ... CD21: =+CD6-CD14 -> 469647.96
B22: YoY % change | AU22: =+AU21/AP21-1 -> 0.20198471 | AV22: =AV21/AQ21-1 -> 0.13496348 | AW22: =AW21/AR21-1 -> 0.12680337 | AX22: =AX21/AS21-1 -> 0.16120366 | AY22: =AY21/AT21-1 -> 0.19214722 | AZ22: =+AZ21/AU21-1 -> 0.17199436 | BA22: =BA21/AV21-1 -> 0.2422638 | BB22: =BB21/AW21-1 -> 0.25237128 | BC22: =BC21/AX21-1 -> 0.20031118 | BD22: =BD21/AY21-1 -> 0.16701118 | BE22: =+BE21/AZ21-1 -> 0.18900068 | BF22: =BF21/BA21-1 -> 0.15250427 | BG22: =BG21/BB21-1 -> 0.2164974 | BH22: =BH21/BC21-1 -> 0.27125433 | BI22: =BI21/BD21-1 -> 0.27783908 | BJ22: =+BJ21/BE21-1 -> 0.23146182 | BK22: =BK21/BF21-1 -> 0.26717896 | BL22: =BL21/BG21-1 -> 0.25833501 | BM22: =BM21/BH21-1 -> 0.233753 | BN22: =BN21/BI21-1 -> 0.22460492 | BO22: =+BO21/BJ21-1 -> 0.24446575 | BP22: =BP21/BK21-1 -> 0.1931312 | BQ22: =BQ21/BL21-1 -> 0.1983501 | BR22: =BR21/BM21-1 -> 0.20309128 | BS22: =BS21/BN21-1 -> 0.20791002 | BT22: =+BT21/BO21-1 -> 0.20103773 | BU22: =BU21/BP21-1 -> 0.18028747 | BV22: =BV21/BQ21-1 -> 0.18020619 | BW22: =BW21/BR21-1 -> 0.16045549 | BX22: =BX21/BS21-1 -> 0.16037422 | BY22: =+BY21/BT21-1 -> 0.16966485 | BZ22: =BZ21/BU21-1 -> 0.15045929 | CA22: =CA21/BV21-1 -> 0.15037736 | CB22: =CB21/BW21-1 -> 0.15029474 | CC22: =CC21/BX21-1 -> 0.15021142 | CD22: =+CD21/BY21-1 -> 0.15032893
B23: % of total TPV | AP23: =+AP21/AP6 -> 0.61 | AQ23: =+AQ21/AQ6 -> 0.6 | AR23: =+AR21/AR6 -> 0.57 | AS23: =+AS21/AS6 -> 0.57 | AT23: =+AT21/AT6 -> 0.57 | AU23: =+AU21/AU6 -> 0.58 | AV23: =+AV21/AV6 -> 0.58 | AW23: =+AW21/AW6 -> 0.54 | ... CD23: =+CD21/CD6 -> 0.46782564
B25: Transaction Revenue Take Rate | AK25: =AK45/AK6 -> 0.033505258 | AP25: =AP45/AP6 -> 0.032283439 | AQ25: =+AQ45/AQ6 -> 0.031131232 | AR25: =+AR45/AR6 -> 0.030139594 | AS25: =+AS45/AS6 -> 0.030076997 | AT25: =+AT45/AT6 -> 0.02972486 | AU25: =AU45/AU6 -> 0.030234194 | AV25: =AV45/AV6 -> 0.030323226 | AW25: =AW45/AW6 -> 0.029133695 | AX25: =AX45/AX6 -> 0.028099892 | AY25: =AY45/AY6 -> 0.027508363 | AZ25: =AZ45/AZ6 -> 0.028527486 | BA25: =BA45/BA6 -> 0.027374363 | BB25: =BB45/BB6 -> 0.026742477 | ... BK25: =BK45/BK6 -> 0.024153093 | BL25: =+BL30*BL23+BL35*BL16+BL43 -> 0.02396004 | BM25: =+BM30*BM23+BM35*BM16+BM43 -> 0.02371871 | BN25: =+BN30*BN23+BN35*BN16+BN43 -> 0.023523984 | BO25: =BO45/BO6 -> 0.023818756 | BP25: =+BP30*BP23+BP35*BP16+BP43 -> 0.023383999 | BQ25: =+BQ30*BQ23+BQ35*BQ16+BQ43 -> 0.023214579 | BR25: =+BR30*BR23+BR35*BR16+BR43 -> 0.023045558 | BS25: =+BS30*BS23+BS35*BS16+BS43 -> 0.022876938 | BT25: =BT45/BT6 -> 0.023114111 | BU25: =+BU30*BU23+BU35*BU16+BU43 -> 0.022794643 | BV25: =+BV30*BV23+BV35*BV16+BV43 -> 0.022712448 | BW25: =+BW30*BW23+BW35*BW16+BW43 -> 0.022512228 | BX25: =+BX30*BX23+BX35*BX16+BX43 -> 0.022429783 | BY25: =BY45/BY6 -> 0.022601398 | BZ25: =+BZ30*BZ23+BZ35*BZ16+BZ43 -> 0.022389213 | CA25: =+CA30*CA23+CA35*CA16+CA43 -> 0.022348643 | CB25: =+CB30*CB23+CB35*CB16+CB43 -> 0.022308073 | CC25: =+CC30*CC23+CC35*CC16+CC43 -> 0.022267503 | CD25: =CD45/CD6 -> 0.022324821
B26: % Change | AU26: =AU25/AP25-1 -> -0.063476681 | AV26: =AV25/AQ25-1 -> -0.025954843 | AW26: =AW25/AR25-1 -> -0.03337467 | AX26: =AX25/AS25-1 -> -0.06573479 | AY26: =AY25/AT25-1 -> -0.074567092 | AZ26: =AZ25/AU25-1 -> -0.056449582 | BA26: =BA25/AV25-1 -> -0.097247669 | BB26: =BB25/AW25-1 -> -0.082077403 | ... CD26: =CD25/BY25-1 -> -0.012237179
B27: Bps Change | AU27: =(AU25-AP25)*10000 -> -20.492456 | AV27: =(AV25-AQ25)*10000 -> -8.0800624 | AW27: =(AW25-AR25)*10000 -> -10.05899 | AX27: =(AX25-AS25)*10000 -> -19.771051 | AY27: =(AY25-AT25)*10000 -> -22.164963 | AZ27: =(AZ25-AU25)*10000 -> -17.067076 | BA27: =(BA25-AV25)*10000 -> -29.48863 | BB27: =(BB25-AW25)*10000 -> -23.91218 | ... CD27: =(CD25-BY25)*10000 -> -2.7657737
AV28: =AV27-AV42*10000 -> -23.733732 | AW28: =AW27-AW42*10000 -> -24.159385 | AX28: =AX27-AX42*10000 -> -29.223821 | AY28: =AY27-AY42*10000 -> -25.950605 | AZ28: =AZ27-AZ42*10000 -> -25.260439 | BA28: =BA27-BA42*10000 -> -27.308371 | BB28: =BB27-BB42*10000 -> -19.126564 | BC28: =BC27-BC42*10000 -> -16.979572 | ... BJ28: =BJ27-BJ42*10000 -> -12.060399 | BO28: =BO27-BO42*10000 -> -11.818562 | BT28: =BT27-BT42*10000 -> -8.4602419 | BY28: =BY27-BY42*10000 -> -5.1271276 | CD28: =CD27-CD42*10000 -> -2.7657737
B29: Take rate derivation (All assumptions)
B30: Small merchant take rate | AQ30: 0.0375 | AR30: 0.037 | AS30: 0.037 | AT30: 0.03506 | AU30: =SUMPRODUCT(AQ30:AT30,AQ6:AT6)/SUM(AQ6:AT6) -> 0.036568361 | AV30: 0.0345 | AW30: 0.0335 | AX30: 0.0333 | AY30: 0.0327 | AZ30: =SUMPRODUCT(AV30:AY30,AV6:AY6)/SUM(AV6:AY6) -> 0.033437794 | BA30: 0.0325 | BB30: 0.0324 | BC30: 0.032 | BD30: 0.0316 | BE30: =SUMPRODUCT(BA30:BD30,BA6:BD6)/SUM(BA6:BD6) -> 0.032100299 | BF30: 0.03125 | BG30: 0.031 | BH30: 0.0307 | BI30: 0.0302 | BJ30: =SUMPRODUCT(BF30:BI30,BF6:BI6)/SUM(BF6:BI6) -> 0.030746986 | BK30: 0.02995 | BL30: =CHOOSE(_Switch,BL31,BL32,BL33) -> 0.0296 | BM30: =CHOOSE(_Switch,BM31,BM32,BM33) -> 0.0292 | BN30: =CHOOSE(_Switch,BN31,BN32,BN33) -> 0.02895 | BO30: =SUMPRODUCT(BK30:BN30,BK6:BN6)/SUM(BK6:BN6) -> 0.029393338 | BP30: =CHOOSE(_Switch,BP31,BP32,BP33) -> 0.02875 | BQ30: =CHOOSE(_Switch,BQ31,BQ32,BQ33) -> 0.02855 | BR30: =CHOOSE(_Switch,BR31,BR32,BR33) -> 0.02835 | BS30: =CHOOSE(_Switch,BS31,BS32,BS33) -> 0.02815 | BT30: =SUMPRODUCT(BP30:BS30,BP6:BS6)/SUM(BP6:BS6) -> 0.028430876 | BU30: =CHOOSE(_Switch,BU31,BU32,BU33) -> 0.028075 | BV30: =CHOOSE(_Switch,BV31,BV32,BV33) -> 0.028 | BW30: =CHOOSE(_Switch,BW31,BW32,BW33) -> 0.027925 | BX30: =CHOOSE(_Switch,BX31,BX32,BX33) -> 0.02785 | BY30: =SUMPRODUCT(BU30:BX30,BU6:BX6)/SUM(BU6:BX6) -> 0.027955961 | BZ30: =CHOOSE(_Switch,BZ31,BZ32,BZ33) -> 0.02783 | CA30: =CHOOSE(_Switch,CA31,CA32,CA33) -> 0.02781 | CB30: =CHOOSE(_Switch,CB31,CB32,CB33) -> 0.02779 | CC30: =CHOOSE(_Switch,CC31,CC32,CC33) -> 0.02777 | CD30: =SUMPRODUCT(BZ30:CC30,BZ6:CC6)/SUM(BZ6:CC6) -> 0.027798256
B31: Bull | BL31: =+BL32+0.06% -> 0.0302 | BM31: =+BM32+0.06% -> 0.0298 | BN31: =+BN32+0.06% -> 0.02955 | BP31: =+BP32+0.06% -> 0.02935 | BQ31: =+BQ32+0.06% -> 0.02915 | BR31: =+BR32+0.06% -> 0.02895 | BS31: =+BS32+0.06% -> 0.02875 | BU31: =+BU32+0.06% -> 0.028675 | BV31: =+BV32+0.06% -> 0.0286 | BW31: =+BW32+0.06% -> 0.028525 | BX31: =+BX32+0.06% -> 0.02845 | BZ31: =+BZ32+0.06% -> 0.02843 | CA31: =+CA32+0.06% -> 0.02841 | CB31: =+CB32+0.06%+CB29/CB23*0.002 -> 0.02839 | CC31: =+CB31-0.005% -> 0.02834
B32: Base | BL32: 0.0296 | BM32: =+BL32-0.04% -> 0.0292 | BN32: =+BM32-0.025% -> 0.02895 | BP32: =+BN32-0.02% -> 0.02875 | BQ32: =+BP32-0.02% -> 0.02855 | BR32: =+BQ32-0.02% -> 0.02835 | BS32: =+BR32-0.02% -> 0.02815 | BU32: =+BS32-0.0075% -> 0.028075 | BV32: =+BU32-0.0075% -> 0.028 | BW32: =+BV32-0.0075% -> 0.027925 | BX32: =+BW32-0.0075% -> 0.02785 | BZ32: =+BX32-0.002% -> 0.02783 | CA32: =+BZ32-0.002% -> 0.02781 | CB32: =+CA32-0.002% -> 0.02779 | CC32: =+CB32-0.002% -> 0.02777
B33: Bear | BL33: =+BL32-0.06% -> 0.029 | BM33: =+BM32-0.06% -> 0.0286 | BN33: =+BN32-0.06% -> 0.02835 | BP33: =+BP32-0.06% -> 0.02815 | BQ33: =+BQ32-0.06% -> 0.02795 | BR33: =+BR32-0.06% -> 0.02775 | BS33: =+BS32-0.06% -> 0.02755 | BU33: =+BU32-0.0625% -> 0.02745 | BV33: =+BV32-0.0625% -> 0.027375 | BW33: =+BW32-0.0625% -> 0.0273 | BX33: =+BX32-0.0625% -> 0.027225 | BZ33: =+BZ32-0.0625% -> 0.027205 | CA33: =+CA32-0.0625% -> 0.027185 | CB33: =+CB32-0.0625%-CB29/CB23*0.002 -> 0.027165 | CC33: =+CB33-0.005% -> 0.027115
B35: Large merchant take rate | AQ35: =+(AQ25-(AQ30*AQ23)-AQ43)/AQ16 -> 0.022369867 | AR35: =+(AR25-(AR30*AR23)-AR43)/AR16 -> 0.021988326 | AS35: =+(AS25-(AS30*AS23)-AS43)/AS16 -> 0.021539504 | AT35: =+(AT25-(AT30*AT23)-AT43)/AT16 -> 0.021948391 | AU35: =SUMPRODUCT(AQ35:AT35,AQ6:AT6)/SUM(AQ6:AT6) -> 0.021953072 | AV35: =+(AV25-(AV30*AV23)-AV43)/AV16 -> 0.022666284 | AW35: =+(AW25-(AW30*AW23)-AW43)/AW16 -> 0.02201072 | AX35: =+(AX25-(AX30*AX23)-AX43)/AX16 -> 0.020837086 | AY35: =+(AY25-(AY30*AY23)-AY43)/AY16 -> 0.020576727 | AZ35: =SUMPRODUCT(AV35:AY35,AV6:AY6)/SUM(AV6:AY6) -> 0.021443711 | BA35: =+(BA25-(BA30*BA23)-BA43)/BA16 -> 0.020248358 | BB35: =+(BB25-(BB30*BB23)-BB43)/BB16 -> 0.02013873 | BC35: =+(BC25-(BC30*BC23)-BC43)/BC16 -> 0.019446801 | BD35: =+(BD25-(BD30*BD23)-BD43)/BD16 -> 0.0195923 | BE35: =SUMPRODUCT(BA35:BD35,BA6:BD6)/SUM(BA6:BD6) -> 0.019840087 | BF35: =+(BF25-(BF30*BF23)-BF43)/BF16 -> 0.019637356 | BG35: =+(BG25-(BG30*BG23)-BG43)/BG16 -> 0.019489566 | BH35: =+(BH25-(BH30*BH23)-BH43)/BH16 -> 0.018897314 | BI35: =+(BI25-(BI30*BI23)-BI43)/BI16 -> 0.019254748 | BJ35: =SUMPRODUCT(BF35:BI35,BF6:BI6)/SUM(BF6:BI6) -> 0.019304364 | BK35: =+(BK25-(BK30*BK23)-BK43)/BK16 -> 0.019089958 | BL35: =CHOOSE(_Switch,BL36,BL37,BL38) -> 0.018839958 | BM35: =CHOOSE(_Switch,BM36,BM37,BM38) -> 0.018589958 | BN35: =CHOOSE(_Switch,BN36,BN37,BN38) -> 0.018389958 | BO35: =SUMPRODUCT(BK35:BN35,BK6:BN6)/SUM(BK6:BN6) -> 0.018705356 | BP35: =CHOOSE(_Switch,BP36,BP37,BP38) -> 0.018289958 | BQ35: =CHOOSE(_Switch,BQ36,BQ37,BQ38) -> 0.018189958 | BR35: =CHOOSE(_Switch,BR36,BR37,BR38) -> 0.018089958 | BS35: =CHOOSE(_Switch,BS36,BS37,BS38) -> 0.017989958 | BT35: =SUMPRODUCT(BP35:BS35,BP6:BS6)/SUM(BP6:BS6) -> 0.018130396 | BU35: =CHOOSE(_Switch,BU36,BU37,BU38) -> 0.017939958 | BV35: =CHOOSE(_Switch,BV36,BV37,BV38) -> 0.017889958 | BW35: =CHOOSE(_Switch,BW36,BW37,BW38) -> 0.017614958 | BX35: =CHOOSE(_Switch,BX36,BX37,BX38) -> 0.017564958 | BY35: =SUMPRODUCT(BU35:BX35,BU6:BX6)/SUM(BU6:BX6) -> 0.017741039 | BZ35: =CHOOSE(_Switch,BZ36,BZ37,BZ38) -> 0.017544958 | CA35: =CHOOSE(_Switch,CA36,CA37,CA38) -> 0.017524958 | CB35: =CHOOSE(_Switch,CB36,CB37,CB38) -> 0.017504958 | CC35: =CHOOSE(_Switch,CC36,CC37,CC38) -> 0.017484958 | CD35: =SUMPRODUCT(BZ35:CC35,BZ6:CC6)/SUM(BZ6:CC6) -> 0.017513215
B36: Bull | BL36: =+BL37+0.045% -> 0.019289958 | BM36: =+BM37+0.045% -> 0.019039958 | BN36: =+BN37+0.045% -> 0.018839958 | BP36: =+BP37+0.05% -> 0.018789958 | BQ36: =+BQ37+0.05% -> 0.018689958 | BR36: =+BR37+0.05% -> 0.018589958 | BS36: =+BS37+0.05% -> 0.018489958 | BU36: =+BU37+0.05% -> 0.018439958 | BV36: =+BV37+0.05% -> 0.018389958 | BW36: =+BW37+0.05% -> 0.018114958 | BX36: =+BX37+0.05% -> 0.018064958 | BZ36: =+BZ37+0.05% -> 0.018044958 | CA36: =+CA37+0.05% -> 0.018024958 | CB36: =+CB37+0.05% -> 0.018004958 | CC36: =+CC37+0.05% -> 0.017984958
B37: Base | BL37: =+BK35-0.025% -> 0.018839958 | BM37: =+BL37-0.025% -> 0.018589958 | BN37: =+BM37-0.02% -> 0.018389958 | BP37: =+BN37-0.01% -> 0.018289958 | BQ37: =+BP37-0.01% -> 0.018189958 | BR37: =+BQ37-0.01% -> 0.018089958 | BS37: =+BR37-0.01% -> 0.017989958 | BU37: =+BS37-0.005% -> 0.017939958 | BV37: =+BU37-0.005% -> 0.017889958 | BW37: =+BV37-0.005%-0.003*0.075 -> 0.017614958 | BX37: =+BW37-0.005% -> 0.017564958 | BZ37: =+BX37-0.002% -> 0.017544958 | CA37: =+BZ37-0.002% -> 0.017524958 | CB37: =+CA37-0.002% -> 0.017504958 | CC37: =+CB37-0.002% -> 0.017484958
B38: Bear | BL38: =+BL37-0.04% -> 0.018439958 | BM38: =+BM37-0.04% -> 0.018189958 | BN38: =+BN37-0.04% -> 0.017989958 | BP38: =+BP37-0.035% -> 0.017939958 | BQ38: =+BQ37-0.035% -> 0.017839958 | BR38: =+BR37-0.035% -> 0.017739958 | BS38: =+BS37-0.035% -> 0.017639958 | BU38: =+BU37-0.0375% -> 0.017564958 | BV38: =+BV37-0.0375% -> 0.017514958 | BW38: =+BW37-0.0375% -> 0.017239958 | BX38: =+BX37-0.0375% -> 0.017189958 | BZ38: =+BZ37-0.0375% -> 0.017169958 | CA38: =+CA37-0.0375% -> 0.017149958 | CB38: =+CB37-0.0375% -> 0.017129958 | CC38: =+CC37-0.0375% -> 0.017109958
B40: Absolute Hedge Gain/Loss Recognized in Period | AQ40: =-40+23 -> -17 | AR40: -23 | AS40: -16 | AT40: 20 | AU40: =SUM(AQ40:AT40) -> -36 | AV40: =112-62 -> 50 | AW40: 62 | AX40: 38 | AY40: =182-AX40-AW40-AV40 -> 32 | AZ40: =SUM(AV40:AY40) -> 182 | BA40: 32 | BB40: 20 | BC40: 28 | BD40: =119-BC40-BB40-BA40 -> 39 | BE40: =SUM(BA40:BD40) -> 119 | BF40: 40 | BG40: 35 | BH40: -13 | BI40: -40 | BJ40: =SUM(BF40:BI40) -> 22 | BK40: -50 | BL40: -32 | BM40: -15 | BN40: -5 | BO40: =SUM(BK40:BN40) -> -102 | BP40: 0 | BQ40: 0 | BR40: 0 | BS40: 0 | BT40: =SUM(BP40:BS40) -> 0 | BU40: 0 | BV40: 0 | BW40: 0 | BX40: 0 | BY40: =SUM(BU40:BX40) -> 0 | BZ40: 0 | CA40: 0 | CB40: 0 | CC40: 0 | CD40: =SUM(BZ40:CC40) -> 0
B41: YoY Hedge Benefit (Headwind) | AV41: =AV40-AQ40 -> 67 | AW41: =AW40-AR40 -> 85 | AX41: =AX40-AS40 -> 54 | AY41: 30 | AZ41: =SUM(AV41:AY41) -> 236 | BA41: =BA40-AV40 -> -18 | BB41: =BB40-AW40 -> -42 | BC41: =BC40-AX40 -> -10 | BD41: =BD40-AY40 -> 7 | BE41: =SUM(BA41:BD41) -> -63 | BF41: =BF40-BA40 -> 8 | BG41: =BG40-BB40 -> 15 | BH41: =BH40-BC40 -> -41 | BI41: =BI40-BD40 -> -79 | BJ41: =SUM(BF41:BI41) -> -97 | BK41: =BK40-BF40 -> -90 | BL41: =BL40-BG40 -> -67 | BM41: =BM40-BH40 -> -2 | BN41: =BN40-BI40 -> 35 | BO41: =SUM(BK41:BN41) -> -124 | BP41: =BP40-BK40 -> 50 | BQ41: =BQ40-BL40 -> 32 | BR41: =BR40-BM40 -> 15 | BS41: =BS40-BN40 -> 5 | BT41: =SUM(BP41:BS41) -> 102 | BU41: =BU40-BP40 -> 0 | BV41: =BV40-BQ40 -> 0 | BW41: =BW40-BR40 -> 0 | BX41: =BX40-BS40 -> 0 | BY41: =SUM(BU41:BX41) -> 0 | BZ41: =BZ40-BU40 -> 0 | CA41: =CA40-BV40 -> 0 | CB41: =CB40-BW40 -> 0 | CC41: =CC40-BX40 -> 0 | CD41: =SUM(BZ41:CC41) -> 0
B42: YoY Take Rate Benefit / (Impact) from FX hedges | AQ42: =0.03*(1+AQ187)-0.03 -> -0.00045697644 | AR42: =0.03*(1+AR187)-0.03 -> -0.00080299148 | AS42: =0.03*(1+AS187)-0.03 -> -0.00050155078 | AT42: =0.03*(1+AT187)-0.03 -> 0.00096165557 | AV42: =+AQ25*(1+AV187)-AQ25 -> 0.0015653669 | AW42: =80/AR6 -> 0.0014100395 | AX42: =55/AS6 -> 0.00094527705 | AY42: =25/AT6 -> 0.00037856418 | AZ42: =AZ41/AZ6 -> 0.00081933634 | BA42: =BA41/BA6 -> -0.0002180259 | BB42: =BB41/BB6 -> -0.00047856158 | BC42: =BC41/BC6 -> -0.00011249227 | BD42: =BD41/BD6 -> 6.9505814e-05 | BE42: =BE41/BE6 -> -0.00017503501 | BF42: =BF41/BF6 -> 7.9492046e-05 | BG42: =BG41/BG6 -> 0.00013914657 | ... CD42: =CD41/CD6 -> 0
B43: Abs. Take Rate Benefit / (Impact) from FX hedges | AQ43: =AQ40/AQ6 -> -0.00031671511 | AR43: =AR40/AR6 -> -0.00040538635 | AS43: =AS40/AS6 -> -0.00027498969 | AT43: =AT40/AT6 -> 0.00030285135 | AU43: =AU40/AU6 -> -0.0001534298 | AV43: =AV40/AV6 -> 0.00079338633 | AW43: =AW40/AW6 -> 0.00091876352 | AX43: =AX40/AX6 -> 0.00053283228 | ... CD43: =CD40/CD6 -> 0
B45: Transaction Revenue | AK45: 5028 | AP45: 5992 | AQ45: =1674-3 -> 1671 | AR45: =1712-2 -> 1710 | AS45: =1754-4 -> 1750 | AT45: =1967-4 -> 1963 | AU45: =7107-13 -> 7094 | AV45: =1914-3 -> 1911 | AW45: =1970-4 -> 1966 | AX45: 2004 | AY45: 2286 | AZ45: 8217 | BA45: 2260 | BB45: 2347 | BC45: 2337 | BD45: 2641 | BE45: =SUM(BA45:BD45) -> 9585 | BF45: 2624 | BG45: 2775 | BH45: 2858 | BI45: 3244 | BJ45: =SUM(BF45:BI45) -> 11501 | BK45: 3197 | BL45: =BL6*BL25 -> 3367.8553 | BM45: =BM6*BM25 -> 3488.0724 | BN45: =BN6*BN25 -> 3942.3432 | BO45: =SUM(BK45:BN45) -> 13995.271 | BP45: =BP6*BP25 -> 3799.1429 | BQ45: =BQ6*BQ25 -> 4007.0527 | BR45: =BR6*BR25 -> 4161.7887 | BS45: =BS6*BS25 -> 4708.0366 | BT45: =SUM(BP45:BS45) -> 16676.021 | BU45: =BU6*BU25 -> 4444.0701 | BV45: =BV6*BV25 -> 4704.4564 | BW45: =BW6*BW25 -> 4797.2603 | BX45: =BX6*BX25 -> 5446.8951 | BY45: =SUM(BU45:BX45) -> 19392.682 | BZ45: =BZ6*BZ25 -> 5107.0815 | CA45: =CA6*CA25 -> 5416.0481 | CB45: =CB6*CB25 -> 5561.8941 | CC45: =CC6*CC25 -> 6326.7593 | CD45: =SUM(BZ45:CC45) -> 22411.783
B46: YoY % change | AP46: =IF(ISERROR(AP45/AK45-1), "NM", (AP45/AK45-1)) -> 0.19172633 | AU46: =IF(ISERROR(AU45/AP45-1), "NM", (AU45/AP45-1)) -> 0.18391188 | AV46: =IF(ISERROR(AV45/AQ45-1), "NM", (AV45/AQ45-1)) -> 0.14362657 | AW46: =IF(ISERROR(AW45/AR45-1), "NM", (AW45/AR45-1)) -> 0.1497076 | AX46: =IF(ISERROR(AX45/AS45-1), "NM", (AX45/AS45-1)) -> 0.14514286 | AY46: =IF(ISERROR(AY45/AT45-1), "NM", (AY45/AT45-1)) -> 0.16454407 | AZ46: =IF(ISERROR(AZ45/AU45-1), "NM", (AZ45/AU45-1)) -> 0.15830279 | BA46: =IF(ISERROR(BA45/AV45-1), "NM", (BA45/AV45-1)) -> 0.1826269 | BB46: =IF(ISERROR(BB45/AW45-1), "NM", (BB45/AW45-1)) -> 0.19379451 | ... CD46: =IF(ISERROR(CD45/BY45-1), "NM", (CD45/BY45-1)) -> 0.1556825
B47: YoY % change (ex-FX) | AV47: =+AV46-AV183 -> 0.17306003 | AW47: =+AW46-AW183 -> 0.18221139 | AX47: 0.18 | AY47: 0.15026309 | AZ47: =+AZ46-AZ183 -> 0.19570169 | BA47: =+BA46-BA183 -> 0.22049944 | BB47: =+BB46-BB183 -> 0.22810327 | BC47: 0.2 | BE47: =+BE46-BE183 -> 0.19733511 | BF47: =+BF46-BF183 -> 0.18164371 | BG47: =+BG46-BG183 -> 0.20854107 | BH47: =+BH46-BH183 -> 0.22015024 | BI47: =+BI46-BI183 -> 0.20204002 | BJ47: =+BJ46-BJ183 -> 0.20321261 | BK47: =+BK46-BK183 -> 0.17619134 | BL47: =+BL46-BL183 -> 0.17883518 | ... CD47: =+CD46-CD183 -> 0.1556825
B49: Other Value-Added Services Revenue | AK49: 634 | AP49: 735 | AQ49: 200 | AR49: 271 | AS49: 221 | AT49: 226 | AU49: =SUM(AQ49:AT49) -> 918 | AV49: 223 | AW49: 327 | AX49: 254 | AY49: 270 | AZ49: 1031 | BA49: 284 | BB49: 303 | BC49: 330 | BD49: 340 | BE49: =SUM(BA49:BD49) -> 1257 | BF49: 351 | BG49: 361 | BH49: 381 | BI49: 500 | BJ49: =SUM(BF49:BI49) -> 1593 | BK49: 488 | BL49: =BG49*(1+BL50) -> 452.98511 | BM49: =BH49*(1+BM50) -> 173.69852 | BN49: =BI49*(1+BN50) -> 299.25267 | BO49: =SUM(BK49:BN49) -> 1413.9363 | BP49: =BK49*(1+BP50) -> 283.4 | BQ49: =BL49*(1+BQ50) -> 237.2575 | BR49: =BM49*(1+BR50) -> 204.96425 | BS49: =BN49*(1+BS50) -> 353.11815 | BT49: =SUM(BP49:BS49) -> 1078.7399 | BU49: =BP49*(1+BU50) -> 328.744 | BV49: =BQ49*(1+BV50) -> 275.2187 | BW49: =BR49*(1+BW50) -> 237.75853 | BX49: =BS49*(1+BX50) -> 409.61706 | BY49: =SUM(BU49:BX49) -> 1251.3383 | BZ49: =BU49*(1+BZ50) -> 378.0556 | CA49: =BV49*(1+CA50) -> 316.5015 | CB49: =BW49*(1+CB50) -> 273.42231 | CC49: =BX49*(1+CC50) -> 471.05962 | CD49: =SUM(BZ49:CC49) -> 1439.039
B50: YoY % change | AP50: =IF(ISERROR(AP49/AK49-1), "NM", (AP49/AK49-1)) -> 0.15930599 | AU50: =IF(ISERROR(AU49/AP49-1), "NM", (AU49/AP49-1)) -> 0.24897959 | AV50: =AV49/AQ49-1 -> 0.115 | AW50: =AW49/AR49-1 -> 0.20664207 | AX50: =AX49/AS49-1 -> 0.14932127 | AY50: =AY49/AT49-1 -> 0.19469027 | AZ50: =IF(ISERROR(AZ49/AU49-1), "NM", (AZ49/AU49-1)) -> 0.12309368 | BA50: =BA49/AV49-1 -> 0.2735426 | BB50: =BB49/AW49-1 -> -0.073394495 | BC50: =BC49/AX49-1 -> 0.2992126 | BD50: =BD49/AY49-1 -> 0.25925926 | BE50: =IF(ISERROR(BE49/AZ49-1), "NM", (BE49/AZ49-1)) -> 0.21920466 | BF50: =BF49/BA49-1 -> 0.23591549 | BG50: =BG49/BB49-1 -> 0.19141914 | BH50: =BH49/BC49-1 -> 0.15454545 | BI50: =BI49/BD49-1 -> 0.47058824 | BJ50: =IF(ISERROR(BJ49/BE49-1), "NM", (BJ49/BE49-1)) -> 0.2673031 | BK50: =BK49/BF49-1 -> 0.39031339 | BL50: =BL51+BL55 -> 0.25480639 | BM50: =BM51+BM55 -> -0.54409838 | BN50: =BN51+BN55 -> -0.40149465 | BO50: =IF(ISERROR(BO49/BJ49-1), "NM", (BO49/BJ49-1)) -> -0.11240659 | BP50: =BP51+BP55 -> -0.4192623 | BQ50: =BQ51+BQ55 -> -0.47623554 | BR50: =BR51+BR55 -> 0.18 | BS50: =BS51+BS55 -> 0.18 | BT50: =IF(ISERROR(BT49/BO49-1), "NM", (BT49/BO49-1)) -> -0.23706612 | BU50: =BU51+BU55 -> 0.16 | BV50: =BV51+BV55 -> 0.16 | BW50: =BW51+BW55 -> 0.16 | BX50: =BX51+BX55 -> 0.16 | BY50: =IF(ISERROR(BY49/BT49-1), "NM", (BY49/BT49-1)) -> 0.16 | BZ50: =BZ51+BZ55 -> 0.15 | CA50: =CA51+CA55 -> 0.15 | CB50: =CB51+CB55 -> 0.15 | CC50: =CC51+CC55 -> 0.15 | CD50: =IF(ISERROR(CD49/BY49-1), "NM", (CD49/BY49-1)) -> 0.15
B51: YoY % change (ex-FX) | AU51: =+AU50-AU183 -> 0.24897959 | AV51: =AV50-AV55 -> 0.14443346 | AW51: =AW50-AW55 -> 0.23914585 | AX51: =AX50-AX55 -> 0.1937099 | AY51: =AY50-AY55 -> 0.2370338 | AZ51: =+AZ50-AZ183 -> 0.16049258 | BA51: =BA50-BA55 -> 0.31141514 | BB51: =BB50-BB55 -> -0.03908573 | BC51: 0.28 | BE51: =+BE50-BE183 -> 0.25005565 | BF51: =BF50-BF55 -> 0.25649725 | BG51: =BG50-BG55 -> 0.21759975 | BH51: =BH50-BH55 -> 0.15176031 | BI51: =BI50-BI55 -> 0.44430565 | BJ51: =+BJ50-BJ183 -> 0.27062004 | BK51: =BK50-BK55 -> 0.34813583 | BL51: =CHOOSE(_Switch,BL52,BL53,BL54) -> 0.22 | BM51: =CHOOSE(_Switch,BM52,BM53,BM54) -> -0.56569554 | BN51: =CHOOSE(_Switch,BN52,BN53,BN54) -> -0.42 | BO51: =+BO50-BO183 -> -0.14095924 | BP51: =CHOOSE(_Switch,BP52,BP53,BP54) -> -0.4192623 | BQ51: =CHOOSE(_Switch,BQ52,BQ53,BQ54) -> -0.47623554 | BR51: =CHOOSE(_Switch,BR52,BR53,BR54) -> 0.18 | BS51: =CHOOSE(_Switch,BS52,BS53,BS54) -> 0.18 | BT51: =+BT50-BT183 -> -0.23706612 | BU51: =CHOOSE(_Switch,BU52,BU53,BU54) -> 0.16 | BV51: =CHOOSE(_Switch,BV52,BV53,BV54) -> 0.16 | BW51: =CHOOSE(_Switch,BW52,BW53,BW54) -> 0.16 | BX51: =CHOOSE(_Switch,BX52,BX53,BX54) -> 0.16 | BY51: =+BY50-BY183 -> 0.16 | BZ51: =CHOOSE(_Switch,BZ52,BZ53,BZ54) -> 0.15 | CA51: =CHOOSE(_Switch,CA52,CA53,CA54) -> 0.15 | CB51: =CHOOSE(_Switch,CB52,CB53,CB54) -> 0.15 | CC51: =CHOOSE(_Switch,CC52,CC53,CC54) -> 0.15 | CD51: =+CD50-CD183 -> 0.15
B52: Bull | BD52: =BD53+3.5% -> 0.26 | BL52: =BL53+3.5% -> 0.255 | BM52: =BM53+3.5% -> -0.53069554 | BN52: =BN53+3.5% -> -0.385 | BP52: =BP53+3.5% -> -0.3842623 | BQ52: =BQ53+3.5% -> -0.44123554 | BR52: =BR53+3.5% -> 0.215 | BS52: =BS53+3.5% -> 0.215 | BU52: =BU53+3.5% -> 0.195 | BV52: =BV53+3.5% -> 0.195 | BW52: =BW53+3.5% -> 0.195 | BX52: =BX53+3.5% -> 0.195 | BZ52: =BZ53+3.5% -> 0.185 | CA52: =CA53+3.5% -> 0.185 | CB52: =CB53+3.5% -> 0.185 | CC52: =CC53+3.5% -> 0.185
B53: Base | BD53: 0.225 | BL53: 0.22 | BM53: =0.12-1200/4/BH49+155/4/BH49 -> -0.56569554 | BN53: =0.11-1200/4/BI49+140/4/BI49 -> -0.42 | BP53: =0.175-1300/4/BK49+140/4/BK49 -> -0.4192623 | BQ53: =0.175-1300/4/BL49+120/4/BL49 -> -0.47623554 | BR53: 0.18 | BS53: =+BR53 -> 0.18 | BU53: 0.16 | BV53: =+BU53 -> 0.16 | BW53: =+BV53 -> 0.16 | BX53: =+BW53 -> 0.16 | BZ53: 0.15 | CA53: =+BZ53 -> 0.15 | CB53: =+CA53 -> 0.15 | CC53: =+CB53 -> 0.15
B54: Bear | BD54: =BD53-2% -> 0.205 | BL54: =BL53-2% -> 0.2 | BM54: =BM53-2% -> -0.58569554 | BN54: =BN53-2% -> -0.44 | BP54: =BP53-2% -> -0.4392623 | BQ54: =BQ53-2% -> -0.49623554 | BR54: =BR53-2% -> 0.16 | BS54: =BS53-2% -> 0.16 | BU54: =BU53-2% -> 0.14 | BV54: =BV53-2% -> 0.14 | BW54: =BW53-2% -> 0.14 | BX54: =BX53-2% -> 0.14 | BZ54: =BZ53-2% -> 0.13 | CA54: =CA53-2% -> 0.13 | CB54: =CB53-2% -> 0.13 | CC54: =CC53-2% -> 0.13
B55: Estimated FX Impact on Value Added Services Rev | AV55: =AV183 -> -0.029433458 | AW55: =AW183 -> -0.032503786 | AX55: =AX183 -> -0.044388635 | AY55: =AY183 -> -0.042343536 | BA55: =BA183 -> -0.03787254 | BB55: =BB183 -> -0.034308766 | BC55: =BC183 -> -0.028866253 | BD55: =BD183 -> -0.02372457 | BF55: =BF183 -> -0.020581761 | BG55: =BG183 -> -0.026180609 | BH55: =BH183 -> 0.0027851454 | BI55: =BI183 -> 0.02628259 | BK55: =BK183 -> 0.042177564 | BL55: =BL183 -> 0.034806386 | BM55: =BM183 -> 0.021597158 | BN55: =BN183 -> 0.018505347 | BP55: =BP183 -> 0 | BQ55: =BQ183 -> 0 | BR55: =BR183 -> 0 | BS55: =BS183 -> 0 | BU55: =BU183 -> 0 | BV55: =BV183 -> 0 | BW55: =BW183 -> 0 | BX55: =BX183 -> 0 | BZ55: =BZ183 -> 0 | CA55: =CA183 -> 0 | CB55: =CB183 -> 0 | CC55: =CC183 -> 0
B57: Total Net Revenue | AK57: =IF(ISERROR(AK49+AK45),"NM",AK49+AK45) -> 5662 | AL57: =IF(ISERROR(AL49+AL45),"NM",AL49+AL45) -> 0 | AM57: =IF(ISERROR(AM49+AM45),"NM",AM49+AM45) -> 0 | AN57: =IF(ISERROR(AN49+AN45),"NM",AN49+AN45) -> 0 | AO57: =IF(ISERROR(AO49+AO45),"NM",AO49+AO45) -> 0 | AP57: =IF(ISERROR(AP49+AP45),"NM",AP49+AP45) -> 6727 | AQ57: =IF(ISERROR(AQ49+AQ45),"NM",AQ49+AQ45) -> 1871 | AR57: =IF(ISERROR(AR49+AR45),"NM",AR49+AR45) -> 1981 | ... CD57: =IF(ISERROR(CD49+CD45),"NM",CD49+CD45) -> 23850.822
B58: YoY % change | AP58: =IF(ISERROR(AP57/AK57-1), "NM", (AP57/AK57-1)) -> 0.18809608 | AU58: =IF(ISERROR(AU57/AP57-1), "NM", (AU57/AP57-1)) -> 0.19102126 | AV58: =IF(ISERROR(AV57/AQ57-1), "NM", (AV57/AQ57-1)) -> 0.14056654 | AW58: =IF(ISERROR(AW57/AR57-1), "NM", (AW57/AR57-1)) -> 0.15749621 | AX58: =IF(ISERROR(AX57/AS57-1), "NM", (AX57/AS57-1)) -> 0.14561136 | AY58: =IF(ISERROR(AY57/AT57-1), "NM", (AY57/AT57-1)) -> 0.16765646 | AZ58: =IF(ISERROR(AZ57/AU57-1), "NM", (AZ57/AU57-1)) -> 0.1542686 | BA58: =IF(ISERROR(BA57/AV57-1), "NM", (BA57/AV57-1)) -> 0.19212746 | BB58: =IF(ISERROR(BB57/AW57-1), "NM", (BB57/AW57-1)) -> 0.15569123 | ... CD58: =IF(ISERROR(CD57/BY57-1), "NM", (CD57/BY57-1)) -> 0.15533806
B59: YoY % change (calc'd, ex-FX) | AV59: =+AV58-AV183 -> 0.17 | AW59: =+AW58-AW183 -> 0.19 | AX59: =+AX58-AX183 -> 0.19 | AY59: =+AY58-AY183 -> 0.21 | AZ59: =+AZ58-AZ183 -> 0.1916675 | BA59: =+BA58-BA183 -> 0.23 | BB59: =+BB58-BB183 -> 0.19 | BC59: =+BC58-BC183 -> 0.21 | ... CD59: =+CD58-CD183 -> 0.15533806
B61: Check | AK61: =IF(ISERROR(AK57-'Quarterly Model'!AK14),"NM",AK57-'Quarterly Model'!AK14) -> 0 | AP61: =IF(ISERROR(AP57-'Quarterly Model'!AP14),"NM",AP57-'Quarterly Model'!AP14) -> 0 | AU61: =IF(ISERROR(AU57-'Quarterly Model'!AU14),"NM",AU57-'Quarterly Model'!AU14) -> 0 | AV61: =IF(ISERROR(AV57-'Quarterly Model'!AV14),"NM",AV57-'Quarterly Model'!AV14) -> 0 | AW61: =IF(ISERROR(AW57-'Quarterly Model'!AW14),"NM",AW57-'Quarterly Model'!AW14) -> 0 | AX61: =IF(ISERROR(AX57-'Quarterly Model'!AX14),"NM",AX57-'Quarterly Model'!AX14) -> 0 | AY61: =IF(ISERROR(AY57-'Quarterly Model'!AY14),"NM",AY57-'Quarterly Model'!AY14) -> 0 | AZ61: =IF(ISERROR(AZ57-'Quarterly Model'!AZ14),"NM",AZ57-'Quarterly Model'!AZ14) -> 0 | BA61: =IF(ISERROR(BA57-'Quarterly Model'!BA14),"NM",BA57-'Quarterly Model'!BA14) -> 0 | BB61: =IF(ISERROR(BB57-'Quarterly Model'!BB14),"NM",BB57-'Quarterly Model'!BB14) -> 0 | ... BJ61: =IF(ISERROR(BJ57-'Quarterly Model'!BJ14),"NM",BJ57-'Quarterly Model'!BJ14) -> 39 | BK61: =IF(ISERROR(BK57-'Quarterly Model'!CE14),"NM",BK57-'Quarterly Model'!CE14) -> 3684.8253 | BL61: =IF(ISERROR(BL57-'Quarterly Model'!CF14),"NM",BL57-'Quarterly Model'!CF14) -> 3820.8404 | BM61: =IF(ISERROR(BM57-'Quarterly Model'!CG14),"NM",BM57-'Quarterly Model'!CG14) -> 3661.7709 | BN61: =IF(ISERROR(BN57-'Quarterly Model'!CH14),"NM",BN57-'Quarterly Model'!CH14) -> 4241.5959 | BO61: =IF(ISERROR(BO57-'Quarterly Model'!CI14),"NM",BO57-'Quarterly Model'!CI14) -> 15409.207 | BP61: =IF(ISERROR(BP57-'Quarterly Model'!CJ14),"NM",BP57-'Quarterly Model'!CJ14) -> 4082.5429 | BQ61: =IF(ISERROR(BQ57-'Quarterly Model'!CK14),"NM",BQ57-'Quarterly Model'!CK14) -> 4244.3102 | BR61: =IF(ISERROR(BR57-'Quarterly Model'!CL14),"NM",BR57-'Quarterly Model'!CL14) -> 4366.753 | ... CD61: =IF(ISERROR(CD57-'Quarterly Model'!CX14),"NM",CD57-'Quarterly Model'!CX14) -> 23850.822
B62: Total Revenue Take Rate | AK62: =AK57/AK6 -> 0.037730065 | AL62: =AL57/AL6 -> #DIV/0! | AM62: =AM57/AM6 -> #DIV/0! | AN62: =AN57/AN6 -> #DIV/0! | AO62: =AO57/AO6 -> #DIV/0! | AP62: =AP57/AP6 -> 0.03624344 | AQ62: =AQ57/AQ6 -> 0.034857292 | AR62: =AR57/AR6 -> 0.034916103 | ... CD62: =CD57/CD6 -> 0.023758276
B66: Usage Stats
B68: Active Customer Accounts | AK68: 123 | AP68: 143 | AQ68: 148 | AR68: 152 | AS68: 157 | AT68: 162 | AU68: 162 | AV68: 165 | AW68: 169 | AX68: 175 | AY68: 181 | AZ68: =+AY68 -> 181 | BA68: 186 | BB68: 189 | BC68: 194 | BD68: 199 | BE68: =+BD68 -> 199 | BF68: 205 | BG68: 212 | BH68: 220 | BI68: 229 | BK68: 237 | BL68: =+BK68+6 -> 243 | BM68: =+BL68+6 -> 249 | BN68: =+BM68+6 -> 255 | BP68: =+BN68+5 -> 260 | BQ68: =+BP68+5 -> 265 | BR68: =+BQ68+5 -> 270 | BS68: =+BR68+5 -> 275 | BT68: =+BS68 -> 275
B69: YoY % change | AP69: =IF(ISERROR(AP68/AK68-1), "NM", (AP68/AK68-1)) -> 0.16260163 | AU69: =IF(ISERROR(AU68/AP68-1), "NM", (AU68/AP68-1)) -> 0.13286713 | AV69: =AV68/AQ68-1 -> 0.11486486 | AW69: =AW68/AR68-1 -> 0.11184211 | AX69: =AX68/AS68-1 -> 0.11464968 | AY69: =AY68/AT68-1 -> 0.11728395 | BA69: =BA68/AV68-1 -> 0.12727273 | BB69: =BB68/AW68-1 -> 0.1183432 | BC69: =BC68/AX68-1 -> 0.10857143 | BD69: =BD68/AY68-1 -> 0.099447514 | BF69: =BF68/BA68-1 -> 0.10215054 | BG69: =BG68/BB68-1 -> 0.12169312 | BH69: =BH68/BC68-1 -> 0.13402062 | BI69: =BI68/BD68-1 -> 0.15075377 | BK69: =BK68/BF68-1 -> 0.15609756
B71: TPV per account | AQ71: =+AQ6/AQ68 -> 362.67568 | AR71: =+AR6/AR68 -> 373.26316 | AS71: =+AS6/AS68 -> 370.59873 | AT71: =+AT6/AT68 -> 407.64815 | AU71: =+AU6/AU68 -> 1448.3642 | AV71: =+AV6/AV68 -> 381.94545 | AW71: =+AW6/AW68 -> 399.30178 | AX71: =+AX6/AX68 -> 407.52571 | AY71: =+AY6/AY68 -> 459.12707 | BA71: =+BA6/BA68 -> 443.86559 | BB71: =+BB6/BB68 -> 464.3545 | BC71: =+BC6/BC68 -> 458.22165 | BD71: =+BD6/BD68 -> 506.08543 | BF71: =+BF6/BF68 -> 490.92195 | BG71: =+BG6/BG68 -> 508.49057 | BH71: =+BH6/BH68 -> 523.74545 | BI71: =+BI6/BI68 -> 578.66812 | BK71: =+BK6/BK68 -> 558.49789
B72: YoY % change | AV72: =+AV71/AQ71-1 -> 0.053132262 | AW72: =+AW71/AR71-1 -> 0.069759409 | AX72: =+AX71/AS71-1 -> 0.099641433 | AY72: =+AY71/AT71-1 -> 0.12628274 | BA72: =+BA71/AV71-1 -> 0.16211775 | BB72: =+BB71/AW71-1 -> 0.16291619 | BC72: =+BC71/AX71-1 -> 0.12439935 | BD72: =+BD71/AY71-1 -> 0.10227747 | BF72: =+BF71/BA71-1 -> 0.10601489 | BG72: =+BG71/BB71-1 -> 0.095048221 | BH72: =+BH71/BC71-1 -> 0.14299587 | BI72: =+BI71/BD71-1 -> 0.14341985 | BK72: =+BK71/BF71-1 -> 0.13765108
B74: Number of Payment Transactions | AK74: 2663 | AP74: 3261 | AQ74: 918 | AR74: 930 | AS74: 972 | AT74: 1144 | AU74: 3964 | AV74: 1123 | AW74: 1161 | AX74: 1257 | AY74: 1469 | AZ74: =SUM(AV74:AY74) -> 5010 | BA74: 1453 | BB74: 1491 | BC74: 1555 | BD74: 1796 | BE74: =SUM(BA74:BD74) -> 6295 | BF74: 1771 | BG74: 1817 | BH74: 1941 | BI74: 2240 | BJ74: =SUM(BF74:BI74) -> 7769 | BK74: 2214 | BL74: =BG74/BG68*BL68 -> 2082.6934 | BM74: =BH74/BH68*BM68 -> 2196.8591 | BN74: =BI74/BI68*BN68 -> 2494.3231 | BP74: =BK74/BK68*BP68 -> 2428.8608 | BQ74: =BL74/BL68*BQ68 -> 2271.25 | BR74: =BM74/BM68*BR68 -> 2382.1364 | BS74: =BN74/BN68*BS68 -> 2689.9563
B75: YoY % change | AP75: =IF(ISERROR(AP74/AK74-1), "NM", (AP74/AK74-1)) -> 0.22455877 | AU75: =IF(ISERROR(AU74/AP74-1), "NM", (AU74/AP74-1)) -> 0.21557804 | AV75: =IF(ISERROR(AV74/AQ74-1), "NM", (AV74/AQ74-1)) -> 0.22331155 | AW75: =IF(ISERROR(AW74/AR74-1), "NM", (AW74/AR74-1)) -> 0.2483871 | AX75: =IF(ISERROR(AX74/AS74-1), "NM", (AX74/AS74-1)) -> 0.29320988 | AY75: =IF(ISERROR(AY74/AT74-1), "NM", (AY74/AT74-1)) -> 0.28409091 | AZ75: =IF(ISERROR(AZ74/AU74-1), "NM", (AZ74/AU74-1)) -> 0.26387487 | BA75: =IF(ISERROR(BA74/AV74-1), "NM", (BA74/AV74-1)) -> 0.29385574 | BB75: =IF(ISERROR(BB74/AW74-1), "NM", (BB74/AW74-1)) -> 0.28423773 | ... BD75: =IF(ISERROR(BD74/AY74-1), "NM", (BD74/AY74-1)) -> 0.22260041 | BF75: =IF(ISERROR(BF74/BA74-1), "NM", (BF74/BA74-1)) -> 0.21885754 | BG75: =IF(ISERROR(BG74/BB74-1), "NM", (BG74/BB74-1)) -> 0.2186452 | BH75: =IF(ISERROR(BH74/BC74-1), "NM", (BH74/BC74-1)) -> 0.24823151 | BI75: =IF(ISERROR(BI74/BD74-1), "NM", (BI74/BD74-1)) -> 0.24721604 | BK75: =IF(ISERROR(BK74/BF74-1), "NM", (BK74/BF74-1)) -> 0.25014116
B77: Transaction per Active Customer Account | AK77: =IF(ISERROR(AK74/AK68),"NM",AK74/AK68) -> 21.650407 | AP77: =IF(ISERROR(AP74/AP68),"NM",AP74/AP68) -> 22.804196 | AQ77: =IF(ISERROR(AQ74/AQ68),"NM",AQ74/AQ68) -> 6.2027027 | AR77: =IF(ISERROR(AR74/AR68),"NM",AR74/AR68) -> 6.1184211 | AS77: =IF(ISERROR(AS74/AS68),"NM",AS74/AS68) -> 6.1910828 | AT77: =IF(ISERROR(AT74/AT68),"NM",AT74/AT68) -> 7.0617284 | AU77: =IF(ISERROR(AU74/AU68),"NM",AU74/AU68) -> 24.469136 | AV77: =IF(ISERROR(AV74/AV68),"NM",AV74/AV68) -> 6.8060606 | AW77: =IF(ISERROR(AW74/AW68),"NM",AW74/AW68) -> 6.8698225 | ... BI77: =IF(ISERROR(BI74/BI68),"NM",BI74/BI68) -> 9.7816594 | BJ77: =+BE77*1.12 -> 35.429146 | BK77: =IF(ISERROR(BK74/BK68),"NM",BK74/BK68) -> 9.3417722 | BO77: =+BJ77*1.12 -> 39.680643 | BT77: =+BO77*1.12 -> 44.44232
B78: YoY % change | AP78: =IF(ISERROR(AP77/AK77-1), "NM", (AP77/AK77-1)) -> 0.053291808 | AU78: =IF(ISERROR(AU77/AP77-1), "NM", (AU77/AP77-1)) -> 0.073010248 | AV78: =AV77/AQ77-1 -> 0.097273387 | AW78: =AW77/AR77-1 -> 0.1228097 | AX78: =AX77/AS77-1 -> 0.160194 | AY78: =AY77/AT77-1 -> 0.14929684 | BA78: =BA77/AV77-1 -> 0.14777526 | BB78: =BB77/AW77-1 -> 0.14833955 | BC78: =BC77/AX77-1 -> 0.11591582 | BD78: =BD77/AY77-1 -> 0.11201344 | BE78: =+BE77/AZ77-1 -> 0.14283493 | BF78: =BF77/BA77-1 -> 0.10589025 | BG78: =BG77/BB77-1 -> 0.086433697 | BH78: =BH77/BC77-1 -> 0.10071324 | BI78: =BI77/BD77-1 -> 0.083825289 | BJ78: =+BJ77/BE77-1 -> 0.12 | BK78: =BK77/BF77-1 -> 0.081345732
B79: Per week
B80: Per year
B81: Transaction per Account per year (PYPL Disclosure) | AW81: 26.1 | AX81: 27.5 | AY81: 28.1 | BA81: 29 | BB81: 29.9 | BC81: 30.8 | BD81: 31.6 | BF81: 32.2 | BG81: 32.8 | BH81: 33.3 | BI81: 34 | BK81: 34.7
B83: One Touch Merchants (millions) | AX83: 1 | BC83: 4 | BD83: 5 | BF83: 5 | BG83: 5.6 | BH83: 6 | BI83: 8 | BK83: 8.6
B84: One Touch Consumer Opt Ins (millions) | AX84: 7 | BC84: 32 | BD84: 40 | BF84: 53 | BG84: 61 | BH84: 70 | BI84: 80 | BK84: 92
B86: Product & Platform Mix Stats | AY86: .
B88: Percent of TPV from cross-border payments | BC88: 0.22 | BH88: 0.21
B89: Percent of TPV from large merchants | AK89: 0.36 | AP89: 0.39 | AQ89: 0.4 | AR89: 0.43 | AS89: 0.43 | AU89: 0.42 | AV89: 0.42 | AW89: 0.46 | AX89: 0.46 | BA89: 0.47
B90: Percent of TPV from PayPal credit | AK90: 0.02 | AP90: 0.02 | AQ90: 0.02 | AR90: 0.02 | AS90: 0.02 | AU90: 0.02 | AV90: 0.02 | AW90: 0.02 | AX90: 0.02
B91: Percent of Net Revenue From eBay marketplace | AP91: 0.32 | AU91: 0.29 | AZ91: 0.26 | BE91: 0.22
B92: Mobile Payment Volume | AK92: 13000 | AP92: 27000 | AU92: 46000 | AY92: 20bn | AZ92: 66000 | BG92: 36000 | BI92: 48000 | BK92: 49000
B93: % of TPV from Mobile | AK93: =AK92/AK6 -> 0.08662855 | AP93: =AP92/AP6 -> 0.14546944 | AU93: =AU92/AU6 -> 0.19604918 | AZ93: =AZ92/AZ6 -> 0.22913643 | BC93: 0.3 | BD93: 0.31 | BG93: 0.34 | BH93: 0.35
B94: % of Transactions from Mobile | AK94: 0.13 | AP94: 0.2 | AU94: 0.25 | AZ94: 0.28
B96: Braintree TPV | AT96: 3118.38
B97: YoY % change
B98: Venmo TPV | AQ98: 314 | AR98: 468 | AS98: 700 | AT98: 906 | AU98: =SUM(AQ98:AT98) -> 2388 | AV98: 1300 | AW98: =AR98*(1+AW99) -> 1623.96 | AX98: 2110 | AY98: =AT98*(1+AY99) -> 2482.44 | AZ98: =SUM(AV98:AY98) -> 7516.4 | BA98: 3200 | BB98: 3900 | BC98: 4900 | BD98: 5600 | BE98: =SUM(BA98:BD98) -> 17600 | BF98: 6800 | BG98: 8000 | BH98: 9400 | BI98: 10400 | BJ98: =SUM(BF98:BI98) -> 34600 | BK98: 12000
B99: YoY % change | AU99: 6 | AV99: =AV98/AQ98-1 -> 3.1401274 | AW99: 2.47 | AX99: =AX98/AS98-1 -> 2.0142857 | AY99: 1.74 | BA99: 1.5 | BB99: 1.41 | BC99: 1.31 | BD99: 1.26 | BF99: =BF98/BA98-1 -> 1.125 | BG99: 1.03 | BH99: 0.93 | BI99: 0.86 | BJ99: 0.97 | BK99: 0.8
B100: Ex Venmo ex FX TPV Growth | AV100: =(AQ6*(1+AV8)-AV98)/(AQ6-AQ98)-1 -> 0.23299352 | AW100: =(AR6*(1+AW8)-AW98)/(AR6-AR98)-1 -> 0.25170186 | AX100: =(AS6*(1+AX8)-AX98)/(AS6-AS98)-1 -> 0.24875931 | AY100: =(AT6*(1+AY8)-AY98)/(AT6-AT98)-1 -> 0.2698305 | BA100: =(AV6*(1+BA8)-BA98)/(AV6-AV98)-1 -> 0.28574569 | BB100: =(AW6*(1+BB8)-BB98)/(AW6-AW98)-1 -> 0.26259117 | BC100: =(AX6*(1+BC8)-BC98)/(AX6-AX98)-1 -> 0.23791799 | BD100: =(AY6*(1+BD8)-BD98)/(AY6-AY98)-1 -> 0.21902799 | BF100: =(BA6*(1+BF8)-BF98)/(BA6-BA98)-1 -> 0.20431407 | BG100: =(BB6*(1+BG8)-BG98)/(BB6-BB98)-1 -> 0.21273684 | BH100: =(BC6*(1+BH8)-BH98)/(BC6-BC98)-1 -> 0.24275969 | BI100: =(BD6*(1+BI8)-BI98)/(BD6-BD98)-1 -> 0.25660744 | BK100: 0.20197743
B101: Merchant Services TPV | AY101: =AY6*0.81 -> 67312.62 | BB101: =BB6*0.83 -> 72843.29 | BC101: 73000 | BD101: =BD6*0.84 -> 84597.24 | BF101: 84000 | BG101: =BG6*0.86 -> 92708
B102: YoY % change ex FX | AX102: 0.34 | AY102: 0.36 | BA102: 0.39 | BB102: 0.36 | BC102: 0.34 | BD102: 0.3 | BF102: 0.3 | BG102: 0.3
B104: EBAY as a % of total TPV | BA104: 0.18 | BD104: 0.16 | BF104: 0.15 | BG104: 0.14 | BH104: 0.135 | BI104: 0.13 | BK104: =17000/BK6 -> 0.12843371
B106: P2P | BE106: 64000 | BG106: =BG6*0.21 -> 22638 | BH106: 24000 | BI106: 27000 | BK106: 30000
B107: YoY Growth | BH107: 0.44 | BI107: 0.5 | BK107: 0.5
B109: PayPal Working Capital | AX109: $1bn to date
B111: Geographic Data
B112: TPV by Geography
B113: US TPV | AP113: =+AP6-AP118 -> 96515.12 | AQ113: =+AQ6-AQ118 -> 27911.52 | AR113: =+AR6-AR118 -> 28935.36 | AS113: =+AS6-AS118 -> 30043 | AT113: 34325 | AU113: =+AU6-AU118 -> 122010.2 | AV113: 34132 | AW113: 36864 | AX113: 38570 | AY113: 44320 | AZ113: =SUM(AV113:AY113) -> 153886 | BA113: 44453 | BB113: 46848 | BC113: 48380 | BD113: 54719 | BE113: =SUM(BA113:BD113) -> 194400
B114: YoY % change | AR114: 0.25 | AS114: 0.27 | AT114: 0.25 | AU114: =+AU113/AP113-1 -> 0.26415633 | AV114: 0.23 | AW114: 0.26 | AX114: 0.28 | AY114: =AY113/AT113-1 -> 0.29118718 | BA114: =BA113/AV113-1 -> 0.30238486 | BB114: =BB113/AW113-1 -> 0.27083333 | BC114: =BC113/AX113-1 -> 0.25434275 | BD114: =BD113/AY113-1 -> 0.23463448 | BH114: 0.31
B115: YoY % change ex Venmo | AV115: =(AV113-AV98)/(AQ113-AQ98)-1 -> 0.18967212 | AW115: =(AW113-AW98)/(AR113-AR98)-1 -> 0.23791036 | AX115: =(AX113-AX98)/(AS113-AS98)-1 -> 0.24254507 | AY115: =(AY113-AY98)/(AT113-AT98)-1 -> 0.25190939 | BB115: 0.27 | BC115: 0.25
B116: Take Rate
B118: International TPV | AP118: =+AP123*AP6 -> 89090.88 | AQ118: =+AQ123*AQ6 -> 25764.48 | AR118: =+AR123*AR6 -> 27800.64 | AS118: 28141 | AT118: 31714 | AU118: =+AU123*AU6 -> 112624.8 | AV118: 28889 | AW118: 30618 | AX118: 31168 | AY118: 37203 | BA118: 36603 | BB118: 39360 | BC118: 39023 | BD118: 44629 | BE118: =SUM(BA118:BD118) -> 159615
B119: YoY % change | AU119: =AU118/AP118-1 -> 0.26415633 | AV119: =AV118/AQ118-1 -> 0.12127239 | AW119: =AW118/AR118-1 -> 0.10134155 | AX119: =AX118/AS118-1 -> 0.10756547 | AY119: =AY118/AT118-1 -> 0.17307814 | BA119: =BA118/AV118-1 -> 0.26702205 | BB119: =BB118/AW118-1 -> 0.28551832 | BC119: =BC118/AX118-1 -> 0.2520213 | BD119: =BD118/AY118-1 -> 0.19960756 | BH119: 0.27
B120: YoY % change ex-FX | AR120: 0.27 | AS120: 0.28 | AT120: 0.27 | AV120: 0.27 | AW120: 0.28 | AX120: 0.25 | AY120: 0.28 | BA120: 0.32 | BB120: 0.31 | BC120: 0.3 | BD120: 0.27
B121: Take Rate
B123: Percent of TPV from Intl (as reported) | AK123: 0.46 | AP123: 0.48 | AQ123: 0.48 | AR123: 0.49 | AS123: 0.48 | AU123: 0.48 | AV123: 0.46 | AW123: 0.45 | AX123: 0.45 | AY123: 0.45 | AZ123: 0.45 | BA123: 0.45 | BB123: 0.45 | BC123: 0.45 | BG123: 0.44 | BH123: 0.44
AT124: =AT118/(AT118+AT113) -> 0.48023138 | AV124: =AV118/(AV118+AV113) -> 0.45840275 | AW124: =AW118/(AW118+AW113) -> 0.45372099 | AX124: =AX118/(AX118+AX113) -> 0.44692994 | AY124: =AY118/(AY118+AY113) -> 0.45634974 | BA124: =BA118/(BA118+BA113) -> 0.45157669
B125: Percent of TPV from cross-border | AK125: 0.24 | AP125: 0.24 | AQ125: 0.24 | AR125: 0.24 | AS125: 0.24 | AU125: 0.24 | AV125: 0.23 | AW125: 0.22 | AX125: 0.21
B127: Revenue by Geography
...

Sheet DCF
B1: PayPal Holdings, Inc: DCF Analysis
A2: 1=Bull | B2: FYE: Dec ($ in mn, except per share data) | W2: To adjust discounting:
A3: 2=Base | B3: Scenario: | C3: =IF(C4<$V$3,"",IF(C4=$V$3,0.25*(4-$V$4)/2,MAX(0,C4-$V$3+0.5-0.25*$V$4))) | D3: =IF(D4<$V$3,"",IF(D4=$V$3,0.25*(4-$V$4)/2,MAX(0,D4-$V$3+0.5-0.25*$V$4))) | E3: =IF(E4<$V$3,"",IF(E4=$V$3,0.25*(4-$V$4)/2,MAX(0,E4-$V$3+0.5-0.25*$V$4))) | F3: =IF(F4<$V$3,"",IF(F4=$V$3,0.25*(4-$V$4)/2,MAX(0,F4-$V$3+0.5-0.25*$V$4))) | G3: =IF(G4<$V$3,"",IF(G4=$V$3,0.25*(4-$V$4)/2,MAX(0,G4-$V$3+0.5-0.25*$V$4))) | H3: =IF(H4<$V$3,"",IF(H4=$V$3,0.25*(4-$V$4)/2,MAX(0,H4-$V$3+0.5-0.25*$V$4))) | I3: =IF(I4<$V$3,"",IF(I4=$V$3,0.25*(4-$V$4)/2,MAX(0,I4-$V$3+0.5-0.25*$V$4))) | J3: =IF(J4<$V$3,"",IF(J4=$V$3,0.25*(4-$V$4)/2,MAX(0,J4-$V$3+0.5-0.25*$V$4))) -> 0.375 | ... T3: =IF(T4<$V$3,"",IF(T4=$V$3,0.25*(4-$V$4)/2,MAX(0,T4-$V$3+0.5-0.25*$V$4))) -> 10.25 | V3: 2019 | W3: <-Enter current fiscal year+1
A4: 3=Bear | C4: =LEFT(C5,4)+0 -> 2012 | D4: =+C4+1 -> 2013 | E4: =+D4+1 -> 2014 | F4: =+E4+1 -> 2015 | G4: =+F4+1 -> 2016 | H4: =+G4+1 -> 2017 | I4: =+H4+1 -> 2018 | J4: =+I4+1 -> 2019 | K4: =+J4+1 -> 2020 | ... T4: =+S4+1 -> 2029 | V4: 1 | W4: <-Enter most recent Q reported (0-3, 0 means YE)
A5: 2=Base | B5: =IF(A5="1=Bull",1,IF(A5="2=Base",2,3)) -> 2 | C5: ='Quarterly Model'!AK3 -> 2012A | D5: ='Quarterly Model'!AP3 -> 2013A | E5: ='Quarterly Model'!AU3 -> 2014A | F5: ='Quarterly Model'!AZ3 -> 2015A | G5: ='Quarterly Model'!BE3 -> 2016A | H5: ='Quarterly Model'!BJ3 -> 2017A | I5: =I4&"E" -> 2018E | J5: =J4&"E" -> 2019E | K5: =K4&"E" -> 2020E | L5: =L4&"E" -> 2021E | M5: =M4&"E" -> 2022E | N5: =N4&"E" -> 2023E | O5: =O4&"E" -> 2024E | P5: =P4&"E" -> 2025E
B6: TPV | C6: ='Segment Detail'!AK6 -> 150066 | D6: ='Segment Detail'!AP6 -> 185606 | E6: ='Segment Detail'!AU6 -> 234635 | F6: ='Segment Detail'!AZ6 -> 288038 | G6: ='Segment Detail'!BE6 -> 359928 | H6: ='Segment Detail'!BJ6 -> 456178 | I6: ='Segment Detail'!BO6 -> 587573.54 | J6: ='Segment Detail'!BT6 -> 721464.95 | K6: ='Segment Detail'!BY6 -> 858030.18 | L6: ='Segment Detail'!CD6 -> 1003895.3 | M6: =(1+M7)*L6 -> 1166024.4 | N6: =(1+N7)*M6 -> 1335506 | O6: =(1+O7)*N6 -> 1485984.2 | P6: =(1+P7)*O6 -> 1604862.9
B7: YoY % change | D7: =D6/C6-1 -> 0.23682913 | E7: =E6/D6-1 -> 0.26415633 | F7: =F6/E6-1 -> 0.22760032 | G7: =G6/F6-1 -> 0.24958512 | H7: =H6/G6-1 -> 0.26741459 | I7: =I6/H6-1 -> 0.28803568 | J7: =J6/I6-1 -> 0.22787174 | K7: =K6/J6-1 -> 0.18928879 | L7: =L6/K6-1 -> 0.17 | M7: =IF(_Toggle="2=Base",0.95*L7,IF(_Toggle="1=Bull",0.8*L7,0.9*L7)) -> 0.1615 | N7: =M7*0.9 -> 0.14535 | O7: =N7-($N7-$P7)/2 -> 0.112675 | P7: 0.08
B9: Net revenue | C9: ='Quarterly Model'!AK14 -> 5662 | D9: ='Quarterly Model'!AP14 -> 6727 | E9: ='Quarterly Model'!AU14 -> 8012 | F9: ='Quarterly Model'!AZ14 -> 9248 | G9: ='Quarterly Model'!BE14 -> 10842 | H9: ='Quarterly Model'!BJ14 -> 13055 | I9: ='Quarterly Model'!BO14 -> 15409.207 | J9: ='Quarterly Model'!BT14 -> 17754.761 | K9: ='Quarterly Model'!BY14 -> 20644.02 | L9: ='Quarterly Model'!CD14 -> 23850.822 | M9: =M6*M11 -> 27246.825 | N9: =N6*N11 -> 30940.05 | O9: =O6*O11 -> 34391.794 | P9: =P6*P11 -> 37105.994
B10: YoY % change | D10: =+D9/C9-1 -> 0.18809608 | E10: =+E9/D9-1 -> 0.19102126 | F10: =+F9/E9-1 -> 0.1542686 | G10: =+G9/F9-1 -> 0.17236159 | H10: =+H9/G9-1 -> 0.20411363 | I10: =+I9/H9-1 -> 0.18032993 | J10: =+J9/I9-1 -> 0.15221767 | K10: =+K9/J9-1 -> 0.16273152 | ... P10: =+P9/O9-1 -> 0.07892
B11: Total Take Rate | C11: =C9/C6 -> 0.037730065 | D11: =D9/D6 -> 0.03624344 | E11: =E9/E6 -> 0.034146653 | F11: =F9/F6 -> 0.032106875 | G11: =G9/G6 -> 0.030122691 | H11: =H9/H6 -> 0.028618215 | I11: =I9/I6 -> 0.026225155 | J11: =J9/J6 -> 0.024609319 | ... L11: =L9/L6 -> 0.023758276 | M11: =IF(_Toggle="2=Base",L11-0.0002,IF(_Toggle="1=Bull",L11-0.00015,L11-0.0003))-0.0190990659010806% -> 0.023367286 | N11: =IF(_Toggle="2=Base",M11-0.0002,IF(_Toggle="1=Bull",M11-0.00015,M11-0.0003)) -> 0.023167286 | O11: =N11*0.999 -> 0.023144118 | P11: =O11*0.999 -> 0.023120974
B13: Transaction expense and loan losses | C13: ='Quarterly Model'!AK18+'Quarterly Model'!AK25 -> 1883 | D13: ='Quarterly Model'!AP18+'Quarterly Model'!AP25 -> 2337 | E13: ='Quarterly Model'!AU18+'Quarterly Model'!AU25 -> 2859 | F13: ='Quarterly Model'!AZ18+'Quarterly Model'!AZ25 -> 3441 | G13: ='Quarterly Model'!BE18+'Quarterly Model'!BE25 -> 4434 | H13: ='Quarterly Model'!BJ18+'Quarterly Model'!BJ25 -> 5430 | I13: ='Quarterly Model'!BO18+'Quarterly Model'!BO25 -> 7055.0764 | J13: ='Quarterly Model'!BT18+'Quarterly Model'!BT25 -> 8723.2343 | K13: ='Quarterly Model'!BY18+'Quarterly Model'!BY25 -> 10471.166 | L13: ='Quarterly Model'!CD18+'Quarterly Model'!CD25 -> 12371.732 | M13: =M6*M14 -> 14398.917 | N13: =N6*N14 -> 16525.187 | O13: =O6*O14 -> 18424.312 | P13: =P6*P14 -> 19938.379
B14: % of TPV | C14: =C13/C6 -> 0.012547812 | D14: =D13/D6 -> 0.012591188 | E14: =E13/E6 -> 0.012184883 | F14: =F13/F6 -> 0.01194634 | G14: =G13/G6 -> 0.01231913 | H14: =H13/H6 -> 0.011903248 | I14: =I13/I6 -> 0.012007138 | J14: =J13/J6 -> 0.012091002 | ... L14: =L13/L6 -> 0.012323727 | M14: =L14+0.000025 -> 0.012348727 | N14: =M14+0.000025 -> 0.012373727 | O14: =N14+0.000025 -> 0.012398727 | P14: =O14+0.000025 -> 0.012423727
B16: Customer Support and Operations | C16: ='Quarterly Model'!AK37 -> 765 | D16: ='Quarterly Model'!AP37 -> 876 | E16: ='Quarterly Model'!AU37 -> 952 | F16: ='Quarterly Model'!AZ37 -> 1053 | G16: ='Quarterly Model'!BE37 -> 1182 | H16: ='Quarterly Model'!BJ37 -> 1222 | I16: ='Quarterly Model'!BO37 -> 1285.3563 | J16: ='Quarterly Model'!BT37 -> 1378.5218 | K16: ='Quarterly Model'!BY37 -> 1458.7608 | L16: ='Quarterly Model'!CD37 -> 1482.2609 | M16: =M17*M9 -> 1666.066 | N16: =N17*N9 -> 1860.9562 | O16: =O17*O9 -> 2034.177 | P16: =P17*P9 -> 2157.6082
B17: % of revenues | C17: =C16/C9 -> 0.13511127 | D17: =D16/D9 -> 0.1302215 | E17: =E16/E9 -> 0.11882177 | F17: =F16/F9 -> 0.11386246 | G17: =G16/G9 -> 0.10902048 | H17: =H16/H9 -> 0.093603983 | I17: =I16/I9 -> 0.083414825 | J17: =J16/J9 -> 0.077642375 | ... L17: =L16/L9 -> 0.062147161 | M17: =L17-0.001 -> 0.061147161 | N17: =M17-0.001 -> 0.060147161 | O17: =N17-0.001 -> 0.059147161 | P17: =O17-0.001 -> 0.058147161
B19: ='Quarterly Model'!B44 -> Sales and Marketing | C19: ='Quarterly Model'!AK44 -> 619 | D19: ='Quarterly Model'!AP44 -> 745 | E19: ='Quarterly Model'!AU44 -> 835 | F19: ='Quarterly Model'!AZ44 -> 860 | G19: ='Quarterly Model'!BE44 -> 885 | H19: ='Quarterly Model'!BJ44 -> 988 | I19: ='Quarterly Model'!BO44 -> 1088.0561 | J19: ='Quarterly Model'!BT44 -> 1165.1507 | K19: ='Quarterly Model'!BY44 -> 1251.6011 | L19: ='Quarterly Model'!CD44 -> 1326.8534 | M19: =M20*M9 -> 1488.5309 | N19: =N20*N9 -> 1659.3567 | O19: =O20*O9 -> 1810.0866 | P19: =P20*P9 -> 1915.8326
B20: % of revenues | C20: =C19/C9 -> 0.10932533 | D20: =D19/D9 -> 0.11074773 | E20: =E19/E9 -> 0.10421867 | F20: =F19/F9 -> 0.09299308 | G20: =G19/G9 -> 0.081627006 | H20: =H19/H9 -> 0.075679816 | I20: =I19/I9 -> 0.070610777 | J20: =J19/J9 -> 0.065624694 | ... L20: =L19/L9 -> 0.055631351 | M20: =L20-0.001 -> 0.054631351 | N20: =M20-0.001 -> 0.053631351 | O20: =N20-0.001 -> 0.052631351 | P20: =O20-0.001 -> 0.051631351
B22: General and administrative | C22: ='Quarterly Model'!AK58 -> 287 | D22: ='Quarterly Model'!AP58 -> 320 | E22: ='Quarterly Model'!AU58 -> 652 | F22: ='Quarterly Model'!AZ58 -> 751 | G22: ='Quarterly Model'!BE58 -> 887 | H22: ='Quarterly Model'!BJ58 -> 914 | I22: ='Quarterly Model'!BO58 -> 1016.5464 | J22: ='Quarterly Model'!BT58 -> 1081.3775 | K22: ='Quarterly Model'!BY58 -> 1154.1652 | L22: ='Quarterly Model'!CD58 -> 1202.0099 | M22: =M23*M9 -> 1352.7231 | N22: =N23*N9 -> 1512.8756 | O22: =O23*O9 -> 1655.8617 | P22: =P23*P9 -> 1758.7128
B23: % of revenues | C23: =C22/C9 -> 0.050688803 | D23: =D22/D9 -> 0.047569496 | E23: =E22/E9 -> 0.081377933 | F23: =F22/F9 -> 0.081206747 | G23: =G22/G9 -> 0.081811474 | H23: =H22/H9 -> 0.07001149 | I23: =I22/I9 -> 0.065970066 | J23: =J22/J9 -> 0.060906342 | ... L23: =L22/L9 -> 0.050397 | M23: =L23-0.00075 -> 0.049647 | N23: =M23-0.00075 -> 0.048897 | O23: =N23-0.00075 -> 0.048147 | P23: =O23-0.00075 -> 0.047397
B25: Product development | C25: ='Quarterly Model'!AK51 -> 617 | D25: ='Quarterly Model'!AP51 -> 640 | E25: ='Quarterly Model'!AU51 -> 639 | F25: ='Quarterly Model'!AZ51 -> 660 | G25: ='Quarterly Model'!BE51 -> 695 | H25: ='Quarterly Model'!BJ51 -> 713 | I25: ='Quarterly Model'!BO51 -> 772.1939 | J25: ='Quarterly Model'!BT51 -> 801.96595 | K25: ='Quarterly Model'!BY51 -> 850.11061 | L25: ='Quarterly Model'!CD51 -> 874.64863 | M25: =M26*M9 -> 971.93879 | N25: =N26*N9 -> 1103.6822 | O25: =O26*O9 -> 1226.8115 | P25: =P26*P9 -> 1323.6315
B26: % of revenues | C26: =C25/C9 -> 0.10897209 | D26: =D25/D9 -> 0.095138992 | E26: =E25/E9 -> 0.079755367 | F26: =F25/F9 -> 0.071366782 | G26: =G25/G9 -> 0.064102564 | H26: =H25/H9 -> 0.05461509 | I26: =I25/I9 -> 0.0501125 | J26: =J25/J9 -> 0.045169065 | ... L26: =L25/L9 -> 0.036671635 | M26: =L26-0.001 -> 0.035671635 | N26: =M26 -> 0.035671635 | O26: =N26 -> 0.035671635 | P26: =O26 -> 0.035671635
B28: Depreciation (ex-Amortization of Int) | C28: ='Quarterly Model'!AK72 -> 324 | D28: ='Quarterly Model'!AP72 -> 398 | E28: ='Quarterly Model'!AU72 -> 458 | F28: ='Quarterly Model'!AZ72 -> 524 | G28: ='Quarterly Model'!BE72 -> 585 | H28: ='Quarterly Model'!BJ72 -> 663 | I28: ='Quarterly Model'!BO72 -> 489 | J28: ='Quarterly Model'!BT72 -> 519 | K28: ='Quarterly Model'!BY72 -> 557 | L28: ='Quarterly Model'!CD72 -> 595 | M28: =M29*M9 -> 826.53372 | N28: =N29*N9 -> 1105.2827 | O28: =O29*O9 -> 1413.9045 | P28: =P29*P9 -> 1725.4287
B29: % of revenues | C29: =C28/C9 -> 0.057223596 | D29: =D28/D9 -> 0.059164561 | E29: =E28/E9 -> 0.057164254 | F29: =F28/F9 -> 0.0566609 | G29: =G28/G9 -> 0.053956835 | H29: =H28/H9 -> 0.05078514 | I29: =I28/I9 -> 0.031734274 | J29: =J28/J9 -> 0.029231596 | ... L29: =L28/L9 -> 0.024946729 | M29: =L29-($L29-$P29)/4 -> 0.030335047 | N29: =M29-($L29-$P29)/4 -> 0.035723365 | O29: =N29-($L29-$P29)/4 -> 0.041111682 | P29: =-P62 -> 0.0465
B31: Stock Based Comp | C31: =+'Quarterly Model'!AK80 -> 210 | D31: =+'Quarterly Model'!AP80 -> 269 | E31: =+'Quarterly Model'!AU80 -> 309 | F31: =+'Quarterly Model'!AZ80 -> 355 | G31: =+'Quarterly Model'!BE80 -> 453 | H31: =+'Quarterly Model'!BJ80 -> 759 | I31: =+'Quarterly Model'!BO80 -> 1007.7663 | J31: =+'Quarterly Model'!BT80 -> 1065.2856 | K31: =+'Quarterly Model'!BY80 -> 1269.6072 | L31: =+'Quarterly Model'!CD80 -> 1383.3477 | M31: =M32*M9 -> 1580.3159 | N31: =N32*N9 -> 1794.5229 | O31: =O32*O9 -> 1994.724 | P31: =P32*P9 -> 2152.1477
B32: % of revenues | C32: =C31/C9 -> 0.037089368 | D32: =D31/D9 -> 0.039988108 | E32: =E31/E9 -> 0.038567149 | F32: =F31/F9 -> 0.038386678 | G32: =G31/G9 -> 0.041781959 | H32: =H31/H9 -> 0.058138644 | I32: =I31/I9 -> 0.065400271 | J32: =J31/J9 -> 0.06 | ... L32: =L31/L9 -> 0.058 | M32: =L32 -> 0.058 | N32: =M32 -> 0.058 | O32: =N32 -> 0.058 | P32: =O32 -> 0.058
B34: Operating Income (MS Method) | C34: =C9-C13-C22-C25-C28-C19-C16-C31 -> 957 | D34: =D9-D13-D22-D25-D28-D19-D16-D31 -> 1142 | E34: =E9-E13-E22-E25-E28-E19-E16-E31 -> 1308 | F34: =F9-F13-F22-F25-F28-F19-F16-F31 -> 1604 | G34: =G9-G13-G22-G25-G28-G19-G16-G31 -> 1721 | H34: =H9-H13-H22-H25-H28-H19-H16-H31 -> 2366 | I34: =I9-I13-I22-I25-I28-I19-I16-I31 -> 2695.2117 | J34: =J9-J13-J22-J25-J28-J19-J16-J31 -> 3020.2249 | ... P34: =P9-P13-P22-P25-P28-P19-P16-P31 -> 6134.2537
B35: Operating Margin | C35: =C34/C9 -> 0.16902155 | D35: =D34/D9 -> 0.16976364 | E35: =E34/E9 -> 0.16325512 | F35: =F34/F9 -> 0.17344291 | G35: =G34/G9 -> 0.15873455 | H35: =H34/H9 -> 0.18123324 | I35: =I34/I9 -> 0.17490917 | J35: =J34/J9 -> 0.17010789 | ... P35: =P34/P9 -> 0.16531705
B36: Operating Margin (ex SBC) | C36: =(C34+C31)/C9 -> 0.20611091 | D36: =(D34+D31)/D9 -> 0.20975175 | E36: =(E34+E31)/E9 -> 0.20182227 | F36: =(F34+F31)/F9 -> 0.21182958 | G36: =(G34+G31)/G9 -> 0.20051651 | H36: =(H34+H31)/H9 -> 0.23937189 | I36: =(I34+I31)/I9 -> 0.24030945 | J36: =(J34+J31)/J9 -> 0.23010789 | ... P36: =(P34+P31)/P9 -> 0.22331705
B37: YoY change in margin (bps) | D37: =(D35-C35)*10000 -> 7.4209191 | E37: =(E35-D35)*10000 -> -65.085217 | F37: =(F35-E35)*10000 -> 101.87789 | G37: =(G35-F35)*10000 -> -147.08356 | H37: =(H35-G35)*10000 -> 224.98693 | I37: =(I35-H35)*10000 -> -63.240703 | J37: =(J35-I35)*10000 -> -48.012851 | K37: =(K35-J35)*10000 -> 58.078947 | ... P37: =(P35-O35)*10000 -> -42.558415
B39: Amortization of Intangibles | C39: ='Quarterly Model'!AK123 -> 0 | D39: ='Quarterly Model'!AP123 -> 0 | E39: ='Quarterly Model'!AU123 -> 70 | F39: ='Quarterly Model'!AZ123 -> 85 | G39: ='Quarterly Model'!BE123 -> 133 | H39: ='Quarterly Model'!BJ123 -> 129 | I39: ='Quarterly Model'!BO123 -> 74 | J39: ='Quarterly Model'!BT123 -> 60 | K39: ='Quarterly Model'!BY123 -> 60 | L39: ='Quarterly Model'!CD123 -> 60 | M39: =M40*M25 -> 66.431021 | N39: =N40*N25 -> 75.159624 | O39: =O40*O25 -> 83.237904 | P39: =P40*P25 -> 89.476131
B40: % of revenues | C40: =C39/C25 -> 0 | D40: =D39/D25 -> 0 | E40: =E39/E25 -> 0.10954617 | F40: =F39/F25 -> 0.12878788 | G40: =G39/G25 -> 0.19136691 | H40: =H39/H25 -> 0.18092567 | I40: =I39/I25 -> 0.095830853 | J40: =J39/J25 -> 0.074816144 | ... L40: =L39/L25 -> 0.068598976 | M40: =L40-0.00025 -> 0.068348976 | N40: =M40-0.00025 -> 0.068098976 | O40: =N40-0.00025 -> 0.067848976 | P40: =O40-0.00025 -> 0.067598976
B42: EBITDA (MS Method) | C42: =C34+C28+C39 -> 1281 | D42: =D34+D28+D39 -> 1540 | E42: =E34+E28+E39 -> 1836 | F42: =F34+F28+F39 -> 2213 | G42: =G34+G28+G39 -> 2439 | H42: =H34+H28+H39 -> 3158 | I42: =I34+I28+I39 -> 3258.2117 | J42: =J34+J28+J39 -> 3599.2249 | ... P42: =P34+P28+P39 -> 7949.1585
B43: EBITDA margin | C43: =C42/C9 -> 0.22624514 | D43: =D42/D9 -> 0.2289282 | E43: =E42/E9 -> 0.22915627 | F43: =F42/F9 -> 0.23929498 | G43: =G42/G9 -> 0.22495849 | H43: =H42/H9 -> 0.24189966 | I43: =I42/I9 -> 0.21144577 | J43: =J42/J9 -> 0.20271886 | ... P43: =P42/P9 -> 0.21422842
B44: YoY change in margin (bps) | D44: =(D43-C43)*10000 -> 26.830567 | E44: =(E43-D43)*10000 -> 2.2806581 | F44: =(F43-E43)*10000 -> 101.38717 | G44: =(G43-F43)*10000 -> -143.36488 | H44: =(H43-G43)*10000 -> 169.41161 | I44: =(I43-H43)*10000 -> -304.53884 | J44: =(J43-I43)*10000 -> -87.26911 | K44: =(K43-J43)*10000 -> 30.845128 | ... P44: =(P43-O43)*10000 -> 11.235582
B46: Other | C46: =+'Quarterly Model'!AK96 -> 11 | D46: =+'Quarterly Model'!AP96 -> 0 | E46: =+'Quarterly Model'!AU96 -> -7 | F46: =+'Quarterly Model'!AZ96 -> 15 | G46: =+'Quarterly Model'!BE96 -> 45 | H46: =+'Quarterly Model'!BJ96 -> 73 | I46: =+'Quarterly Model'!BO96 -> 23 | J46: =+'Quarterly Model'!BT96 -> 0 | K46: =+'Quarterly Model'!BY96 -> 0 | L46: =+'Quarterly Model'!CD96 -> 0 | M46: =M47*M9 -> 0 | N46: =N47*N9 -> 0 | O46: =O47*O9 -> 0 | P46: =P47*P9 -> 0
B47: % of revenues | C47: =C46/C9 -> 0.0019427764 | D47: =D46/D9 -> 0 | E47: =E46/E9 -> -0.00087368947 | F47: =F46/F9 -> 0.0016219723 | G47: =G46/G9 -> 0.0041505257 | H47: =H46/H9 -> 0.0055917273 | I47: =I46/I9 -> 0.0014926141 | J47: =J46/J9 -> 0 | ... L47: =L46/L9 -> 0 | M47: 0 | N47: 0 | O47: 0 | P47: 0
B49: EBT | C49: =C34+C46 -> 968 | D49: =D34+D46 -> 1142 | E49: =E34+E46 -> 1301 | F49: =F34+F46 -> 1619 | G49: =G34+G46 -> 1766 | H49: =H34+H46 -> 2439 | I49: =I34+I46 -> 2718.2117 | J49: =J34+J46 -> 3020.2249 | ... P49: =P34+P46 -> 6134.2537
B51: Tax exp/(benefit) | C51: =+'Quarterly Model'!AK111 -> 0 | D51: =+'Quarterly Model'!AP111 -> 182.10489 | E51: =+'Quarterly Model'!AU111 -> 238.34295 | F51: =+'Quarterly Model'!AZ111 -> 326.17286 | G51: =+'Quarterly Model'!BE111 -> 313.66614 | H51: =+'Quarterly Model'!BJ111 -> 373.24165 | I51: =+'Quarterly Model'!BO111 -> 440.40862 | J51: =+'Quarterly Model'!BT111 -> 588.94385 | K51: =+'Quarterly Model'!BY111 -> 726.32179 | L51: =+'Quarterly Model'!CD111 -> 946.06878 | M51: =M49*M52 -> 1041.9779 | N51: =N49*N52 -> 1156.3101 | O51: =O49*O52 -> 1283.0215 | P51: =P49*P52 -> 1380.2071
B52: Tax rate | C52: =+C51/C49 -> 0 | D52: =+D51/D49 -> 0.15946137 | E52: =+E51/E49 -> 0.18319981 | F52: =+F51/F49 -> 0.20146563 | G52: =+G51/G49 -> 0.17761389 | H52: =+H51/H49 -> 0.15303061 | I52: =+I51/I49 -> 0.16202146 | J52: =+J51/J49 -> 0.195 | ... L52: =+L51/L49 -> 0.205 | M52: =L52+0.005 -> 0.21 | N52: =M52+0.005 -> 0.215 | O52: =N52+0.005 -> 0.22 | P52: =O52+0.005 -> 0.225
B54: Net income(adjusted) | C54: =C49-C51 -> 968 | D54: =D49-D51 -> 959.89511 | E54: =E49-E51 -> 1062.657 | F54: =F49-F51 -> 1292.8271 | G54: =G49-G51 -> 1452.3339 | H54: =H49-H51 -> 2065.7583 | I54: =I49-I51 -> 2277.8031 | J54: =J49-J51 -> 2431.281 | ... P54: =P49-P51 -> 4754.0466
B56: Check | C56: =C54-'Quarterly Model'!AK137 -> 941 | D56: =D54-'Quarterly Model'!AP137 -> -220.10489 | E56: =E54-'Quarterly Model'!AU137 -> 643.65705 | F56: =F54-'Quarterly Model'!AZ137 -> 79.82714 | G56: =G54-'Quarterly Model'!BE137 -> 50.333863 | H56: =H54-'Quarterly Model'!BJ137 -> 270.75835 | I56: =I54-'Quarterly Model'!BO137 -> 342.70929 | J56: =J54-'Quarterly Model'!BT137 -> 92.703373 | K56: =K54-'Quarterly Model'!BY137 -> 83.71609 | L56: =L54-'Quarterly Model'!CD137 -> 70.474848
B58: Other Cash Impacts
B59: Depreciation (ex-Amort of Intangibles) | C59: =C28 -> 324 | D59: =D28 -> 398 | E59: =E28 -> 458 | F59: =F28 -> 524 | G59: =G28 -> 585 | H59: =H28 -> 663 | I59: =I28 -> 489 | J59: =J28 -> 519 | ... P59: =P28 -> 1725.4287
B60: % of revenues | C60: =C59/C9 -> 0.057223596 | D60: =D59/D9 -> 0.059164561 | E60: =E59/E9 -> 0.057164254 | F60: =F59/F9 -> 0.0566609 | G60: =G59/G9 -> 0.053956835 | H60: =H59/H9 -> 0.05078514 | I60: =I59/I9 -> 0.031734274 | J60: =J59/J9 -> 0.029231596 | ... P60: =P59/P9 -> 0.0465
B61: Capital Expenditure | C61: ='Quarterly Model'!AK180 -> -511 | D61: ='Quarterly Model'!AP180 -> -391 | E61: ='Quarterly Model'!AU180 -> -492 | F61: ='Quarterly Model'!AZ180 -> -696 | G61: ='Quarterly Model'!BE180 -> -669 | H61: ='Quarterly Model'!BJ180 -> -667 | I61: ='Quarterly Model'!BO180 -> -852.14191 | J61: ='Quarterly Model'!BT180 -> -976.51184 | K61: ='Quarterly Model'!BY180 -> -1083.8111 | L61: ='Quarterly Model'!CD180 -> -1252.1682 | M61: =M62*M9 -> -1389.5881 | N61: =N62*N9 -> -1531.5325 | O61: =O62*O9 -> -1650.8061 | P61: =P62*P9 -> -1725.4287
B62: Capex % of revenues | C62: =C61/C9 -> -0.090250795 | D62: =D61/D9 -> -0.058123978 | E62: =E61/E9 -> -0.061407888 | F62: =F61/F9 -> -0.075259516 | G62: =G61/G9 -> -0.061704483 | H62: =H61/H9 -> -0.051091536 | I62: =I61/I9 -> -0.055300828 | J62: =J61/J9 -> -0.055 | ... L62: =L61/L9 -> -0.0525 | M62: =+L62+0.15% -> -0.051 | N62: =+M62+0.15% -> -0.0495 | O62: =+N62+0.15% -> -0.048 | P62: =+O62+0.15% -> -0.0465
B63: Change in Net working capital | C63: =SUM('Quarterly Model'!AK169:AK176) -> -154 | D63: =SUM('Quarterly Model'!AP169:AP176) -> -146 | E63: =SUM('Quarterly Model'!AU169:AU176) -> -299 | F63: =SUM('Quarterly Model'!AZ169:AZ176) -> -506 | G63: =SUM('Quarterly Model'!BE169:BE176) -> -481 | H63: =SUM('Quarterly Model'!BJ169:BJ176) -> -581 | I63: =SUM('Quarterly Model'!BO169:BO176) -> -1994.6377 | J63: =SUM('Quarterly Model'!BT169:BT176) -> -1052.0724 | K63: =SUM('Quarterly Model'!BY169:BY176) -> -619.40584 | L63: =SUM('Quarterly Model'!CD169:CD176) -> -772.38024 | M63: =+M64*M9 -> -923.22596 | N63: =+N64*N9 -> -1094.7765 | O63: =+O64*O9 -> -1268.5 | P63: =+P64*P9 -> -1424.269
B64: NWC % of revenues | C64: =+C63/C9 -> -0.02719887 | D64: =+D63/D9 -> -0.021703583 | E64: =+E63/E9 -> -0.037319021 | F64: =+F63/F9 -> -0.054714533 | G64: =+G63/G9 -> -0.044364508 | H64: =+H63/H9 -> -0.044504021 | I64: =+I63/I9 -> -0.12944454 | J64: =+J63/J9 -> -0.059255794 | ... L64: =+L63/L9 -> -0.0323838 | M64: =L64-0.0015 -> -0.0338838 | N64: =M64-0.0015 -> -0.0353838 | O64: =N64-0.0015 -> -0.0368838 | P64: =O64-0.0015 -> -0.0383838
B65: Add back Transaction/Loan Provision | C65: ='Quarterly Model'!AK162 -> 365 | D65: ='Quarterly Model'!AP162 -> 502 | E65: ='Quarterly Model'!AU162 -> 646 | F65: ='Quarterly Model'!AZ162 -> 809 | G65: ='Quarterly Model'!BE162 -> 1088 | H65: ='Quarterly Model'!BJ162 -> 1011 | I65: ='Quarterly Model'!BO162 -> 1351.9819 | J65: ='Quarterly Model'!BT162 -> 1641.3328 | K65: ='Quarterly Model'!BY162 -> 1952.0187 | L65: ='Quarterly Model'!CD162 -> 2283.8618 | M65: =M66*M9 -> 2540.9328 | N65: =N66*N9 -> 2807.9984 | O65: =O66*O9 -> 3035.2858 | P65: =P66*P9 -> 3182.0655
B66: Provision as a % of revenues | C66: =C65/C9 -> 0.064464853 | D66: =D65/D9 -> 0.074624647 | E66: =E65/E9 -> 0.080629056 | F66: =F65/F9 -> 0.087478374 | G66: =G65/G9 -> 0.10035049 | H66: =H65/H9 -> 0.077441593 | I66: =I65/I9 -> 0.087738579 | J66: =J65/J9 -> 0.092444656 | ... L66: =L65/L9 -> 0.095756105 | M66: =L66-0.0025 -> 0.093256105 | N66: =M66-0.0025 -> 0.090756105 | O66: =N66-0.0025 -> 0.088256105 | P66: =O66-0.0025 -> 0.085756105
B67: Subtract Estimated Loan NCOs | C67: =C65*C68 -> -155.24757 | D67: =-232+14 -> -218 | E67: =-297+28 -> -269 | F67: =-335+24 -> -311 | G67: =-438+28 -> -410 | H67: =H65*H68 -> -380.98346 | I67: =I65*I68 -> -509.47849 | J67: =J65*J68 -> -618.51694 | K67: =K65*K68 -> -735.59526 | L67: =L65*L68 -> -860.64646 | M67: =M65*M68 -> -957.52063 | N67: =N65*N68 -> -1058.1612 | O67: =O65*O68 -> -1143.8117 | P67: =P65*P68 -> -1199.124
B68: As a % of Provisions | C68: =AVERAGE(D68:E68) -> -0.42533581 | D68: =D67/D65 -> -0.43426295 | E68: =E67/E65 -> -0.41640867 | F68: =F67/F65 -> -0.38442522 | G68: =G67/G65 -> -0.37683824 | H68: =G68 -> -0.37683824 | I68: =H68 -> -0.37683824 | J68: =I68 -> -0.37683824 | K68: =J68 -> -0.37683824 | L68: =K68 -> -0.37683824 | M68: =L68 -> -0.37683824 | N68: =M68 -> -0.37683824 | O68: =N68 -> -0.37683824 | P68: =O68 -> -0.37683824
B69: Other non-cash items | C69: =SUM('Quarterly Model'!AK165:AK166) -> -11 | D69: =SUM('Quarterly Model'!AP165:AP166) -> -24 | E69: =SUM('Quarterly Model'!AU165:AU166) -> 639 | F69: =SUM('Quarterly Model'!AZ165:AZ166) -> 101 | G69: =SUM('Quarterly Model'!BE165:BE166) -> 12 | H69: =SUM('Quarterly Model'!BJ165:BJ166) -> -1299 | I69: =SUM('Quarterly Model'!BO165:BO166) -> 91 | J69: =SUM('Quarterly Model'!BT165:BT166) -> 0 | K69: =SUM('Quarterly Model'!BY165:BY166) -> 0 | L69: =SUM('Quarterly Model'!CD165:CD166) -> 0 | M69: =+M70*M9 -> 0 | N69: =+N70*N9 -> 0 | O69: =+O70*O9 -> 0 | P69: =+P70*P9 -> 0
B70: Other % of revenues | C70: =+C69/C9 -> -0.0019427764 | D70: =+D69/D9 -> -0.0035677122 | E70: =+E69/E9 -> 0.079755367 | F70: =+F69/F9 -> 0.01092128 | G70: =+G69/G9 -> 0.0011068069 | H70: =+H69/H9 -> -0.099502106 | I70: =+I69/I9 -> 0.0059055601 | J70: =+J69/J9 -> 0 | ... L70: =+L69/L9 -> 0 | M70: =+L70 -> 0 | N70: =+M70 -> 0 | O70: =+N70 -> 0 | P70: =+O70 -> 0
B71: Add back after tax interest exp | C71: 0 | D71: 0 | E71: 0 | F71: 0 | G71: 0 | H71: 0 | I71: 0 | J71: 0 | K71: 0 | L71: 0 | M71: 0 | N71: 0 | O71: 0 | P71: 0
B72: Free cash flow to firm | C72: =C54+C59+C61+C63+C69+C71+C65+C67 -> 825.75243 | D72: =D54+D59+D61+D63+D69+D71+D65+D67 -> 1080.8951 | E72: =E54+E59+E61+E63+E69+E71+E65+E67 -> 1745.657 | F72: =F54+F59+F61+F63+F69+F71+F65+F67 -> 1213.8271 | G72: =G54+G59+G61+G63+G69+G71+G65+G67 -> 1577.3339 | H72: =H54+H59+H61+H63+H69+H71+H65+H67 -> 811.77489 | I72: =I54+I59+I61+I63+I69+I71+I65+I67 -> 853.5269 | J72: =J54+J59+J61+J63+J69+J71+J65+J67 -> 1944.5126 | ... P72: =P54+P59+P61+P63+P69+P71+P65+P67 -> 5312.7191
B73: YoY % change | D73: =+D72/C72-1 -> 0.30898205 | E73: =+E72/D72-1 -> 0.61501059 | F73: =+F72/E72-1 -> -0.30465887 | G73: =+G72/F72-1 -> 0.29947157 | H73: =+H72/G72-1 -> -0.48534999 | I73: =+I72/H72-1 -> 0.051432984 | J73: =+J72/I72-1 -> 1.2782089 | K73: =+K72/J72-1 -> 0.53020029 | ... P73: =+P72/O72-1 -> 0.07654604
B75: PV factor | C75: =IF(C$4<$V$3,"",(1+$C$81)^C$3) | D75: =IF(D$4<$V$3,"",(1+$C$81)^D$3) | F75: =IF(F$4<$V$3,"",(1+$C$81)^F$3) | G75: =IF(G$4<$V$3,"",(1+$C$81)^G$3) | H75: =IF(H$4<$V$3,"",(1+$C$81)^H$3) | I75: =IF(I$4<$V$3,"",(1+$C$81)^I$3) | J75: =IF(J$4<$V$3,"",(1+$C$81)^J$3) -> 1.0319555 | K75: =IF(K$4<$V$3,"",(1+$C$81)^K$3) -> 1.1105461 | L75: =IF(L$4<$V$3,"",(1+$C$81)^L$3) -> 1.2077189 | M75: =IF(M$4<$V$3,"",(1+$C$81)^M$3) -> 1.3133943 | ... P75: =IF(P$4<$V$3,"",(1+$C$81)^P$3) -> 1.6892071
B76: PV of Free Cash Flows | C76: =IF(C$4<$V$3,"",IF(C$4=$V$3,(4-$V$4)/4*C72/C75,C72/C75)) | D76: =IF(D$4<$V$3,"",IF(D$4=$V$3,(4-$V$4)/4*D72/D75,D72/D75)) | F76: =IF(F$4<$V$3,"",IF(F$4=$V$3,(4-$V$4)/4*F72/F75,F72/F75)) | G76: =IF(G$4<$V$3,"",IF(G$4=$V$3,(4-$V$4)/4*G72/G75,G72/G75)) | H76: =IF(H$4<$V$3,"",IF(H$4=$V$3,(4-$V$4)/4*H72/H75,H72/H75)) | I76: =IF(I$4<$V$3,"",IF(I$4=$V$3,(4-$V$4)/4*I72/I75,I72/I75)) | J76: =IF(J$4<$V$3,"",IF(J$4=$V$3,(4-$V$4)/4*J72/J75,J72/J75)) -> 1413.2241 | K76: =IF(K$4<$V$3,"",IF(K$4=$V$3,(4-$V$4)/4*K72/K75,K72/K75)) -> 2679.3068 | L76: =IF(L$4<$V$3,"",IF(L$4=$V$3,(4-$V$4)/4*L72/L75,L72/L75)) -> 3032.6328 | M76: =IF(M$4<$V$3,"",IF(M$4=$V$3,(4-$V$4)/4*M72/M75,M72/M75)) -> 3058.4522 | ... P76: =IF(P$4<$V$3,"",IF(P$4=$V$3,(4-$V$4)/4*P72/P75,P72/P75)) -> 3145.0963
B78: Terminal Value | P78: =((P72*(1+C86)/(C81-C86))+(P72*C90/2*(C91-C86)/(C81-C86))) -> 109026.24
B80: Inputs | E80: Valuation | K80: DCF Sensitivity Analysis
B81: WACC | C81: 0.0875 | E81: PV of cash flows in years 2018-2020 | I81: =SUM(I76:K76) -> 4092.5309
B82: 2012-2016 rev growth rate | C82: =((G9/C9)^(1/4))-1 -> 0.17634547 | E82: PV of cash flows in years 2021-2025 | I82: =SUM(L76:P76) -> 15529.317 | M82: Discount Rate
B83: 2016-2025 rev growth rate | C83: =((P9/G9)^(1/9))-1 -> 0.14649065 | E83: PV of terminal value | I83: =P78/(1+C81)^P3 -> 64542.845 | L83: =I90 -> 79.567133 | M83: =O83-0.02 -> 0.0675 | N83: =O83-0.01 -> 0.0775 | O83: 0.0875 | P83: =O83+0.01 -> 0.0975 | Q83: =O83+0.02 -> 0.1075
B84: Terminal FCF multiple | C84: =P78/P72 -> 20.521739 | E84: Total PV of FCF | I84: =SUM(I81:I83) -> 84164.693 | K84: Terminal | L84: =L85-0.005 -> 0.02 | M84: 102.36476 | N84: 85.211344 | O84: 73.19305 | P84: 64.319078 | Q84: 57.508912
B85: Terminal EBITDA multiple | C85: =+P78/P42 -> 13.715444 | E85: Less: Debt | I85: 3000 | K85: Growth | L85: =L86-0.005 -> 0.025 | M85: 109.82537 | N85: 89.735303 | O85: 76.125128 | P85: 66.310632 | Q85: 58.909232
B86: Terminal Growth Rate | C86: =CHOOSE(_Switch,C87,C88,C89) -> 0.03 | E86: Plus: Cash & corp investments | I86: 14930.555 | K86: Rate | L86: =C88 -> 0.03 | M86: 119.27547 | N86: 95.211675 | O86: 79.567133 | P86: 68.597231 | Q86: 60.49024
B87: Bull | C87: 0.03 | E87: Less: Minority Interest | I87: 0 | L87: =L86+0.005 -> 0.035 | M87: 131.63329 | N87: 101.97661 | O87: 83.664758 | P87: 71.249685 | Q87: 62.289317
B88: Base | C88: 0.03 | E88: Equity value | I88: =I84-I85+I86-I87 -> 96095.248 | L88: =L87+0.005 -> 0.04 | M88: 148.48487 | N88: 110.54552 | O88: 88.625041 | P88: 74.363436 | Q88: 64.354925
B89: Bear | C89: 0.025 | E89: Diluted shares outstanding | I89: 1207.7254
B90: High Growth Years | C90: 10 | E90: Implied share price in one year | I90: =+I88/I89 -> 79.567133
B91: High Growth Starting Growth Rate | C91: 0.06
B94: WACC Calculation
B96: WACC = (equity/capital) x (WACE) + (LTD/capital) x (WACD)
B98: Current capital structure
F99: Weighted
C100: Value | D100: % | E100: Cost | F100: Cost
B101: Equity (market cap) | C101: 72000 | D101: =+C101/C103 -> 1 | E101: =+C118 -> 0.0885 | F101: =(C101/$C$103)*E101 -> 0.0885
B102: Debt | C102: ='Quarterly Model'!AY259 -> 0 | D102: =+C102/C103 -> 0 | E102: 0.06 | F102: =(C102/$C$103)*E102 -> 0
B103: WACC | C103: =+C101+C102 -> 72000 | D103: =+D101+D102 -> 1 | F103: =F102+F101 -> 0.0885
B107: Weighted Average cost of equity
B108: CAPM = Risk free rate + beta (expected market return - risk free rate)
B110: Risk free rate | C110: 0.0225 | D110: 10-yr avg of 10-yr Treasury Yield
B111: +
B112: Beta | C112: 1.1
B113: x
B114: Expected market return | C114: 0.0725
B115: -RFR | C115: =+C110 -> 0.0225
B116: Risk Premium | C116: 0.06
B117: + Alpha | C117: 0
B118: Cost of Equity (WACE) | C118: =+C110+(C112*C116)+C117 -> 0.0885

Sheet Take Rate Drivers
B1: Take Rate Drivers
B2: Fiscal Year End: December ($ in millions, except per share data)
C4: 1Q06A | D4: 2Q06A | E4: 3Q06A | F4: 4Q06A | G4: 2006A | H4: 1Q07A | I4: 2Q07A | J4: 3Q07A | K4: 4Q07A | L4: 2007A | M4: 1Q08A | N4: 2Q08A | O4: 3Q08A | P4: 4Q08A | Q4: 2008A | R4: 1Q09A | S4: 2Q09A | T4: 3Q09A | U4: 4Q09A | V4: 2009A | W4: 1Q10A | X4: 2Q10A | Y4: 3Q10A | Z4: 4Q10A | AA4: 2010A | AB4: 1Q11A | AC4: 2Q11A | AD4: 3Q11A | AE4: 4Q11A | AF4: 2011A | AG4: 1Q12A | AH4: 2Q12A | AI4: 3Q12A | AJ4: 4Q12A | AK4: ='Quarterly Model'!AK3 -> 2012A | AL4: 1Q13A | AM4: 2Q13A | AN4: 3Q13A | AO4: 4Q13A | AP4: ='Quarterly Model'!AP3 -> 2013A | AQ4: ='Quarterly Model'!AQ3 -> 1Q14A | AR4: ='Quarterly Model'!AR3 -> 2Q14A | AS4: ='Quarterly Model'!AS3 -> 3Q14A | AT4: ='Quarterly Model'!AT3 -> 4Q14A | AU4: ='Quarterly Model'!AU3 -> 2014A | AV4: ='Quarterly Model'!AV3 -> 1Q15A | AW4: ='Quarterly Model'!AW3 -> 2Q15A | ... CD4: ='Quarterly Model'!CD3 -> 2021E
B5: Revenue Drivers
B6: Total TPV | AK6: ='Segment Detail'!AK6 -> 150066 | AP6: ='Segment Detail'!AP6 -> 185606 | AQ6: ='Segment Detail'!AQ6 -> 53676 | AR6: ='Segment Detail'!AR6 -> 56736 | AS6: ='Segment Detail'!AS6 -> 58184 | AT6: ='Segment Detail'!AT6 -> 66039 | AU6: ='Segment Detail'!AU6 -> 234635 | AV6: ='Segment Detail'!AV6 -> 63021 | AW6: ='Segment Detail'!AW6 -> 67482 | ... CD6: ='Segment Detail'!CD6 -> 1003895.3
B7: YoY % change | AP7: =IF(ISERROR(AP6/AK6-1), "NM", (AP6/AK6-1)) -> 0.23682913 | AU7: =IF(ISERROR(AU6/AP6-1), "NM", (AU6/AP6-1)) -> 0.26415633 | AV7: =IF(ISERROR(AV6/AQ6-1), "NM", (AV6/AQ6-1)) -> 0.17410016 | AW7: =IF(ISERROR(AW6/AR6-1), "NM", (AW6/AR6-1)) -> 0.18940355 | AX7: =IF(ISERROR(AX6/AS6-1), "NM", (AX6/AS6-1)) -> 0.22571497 | AY7: =IF(ISERROR(AY6/AT6-1), "NM", (AY6/AT6-1)) -> 0.25837763 | AZ7: =+AZ6/AU6-1 -> 0.22760032 | BA7: =IF(ISERROR(BA6/AV6-1), "NM", (BA6/AV6-1)) -> 0.31002364 | BB7: =IF(ISERROR(BB6/AW6-1), "NM", (BB6/AW6-1)) -> 0.3005394 | BC7: =IF(ISERROR(BC6/AX6-1), "NM", (BC6/AX6-1)) -> 0.246477 | BD7: =IF(ISERROR(BD6/AY6-1), "NM", (BD6/AY6-1)) -> 0.21189622 | BE7: =IF(ISERROR(BE6/AZ6-1), "NM", (BE6/AZ6-1)) -> 0.24958512 | BF7: =IF(ISERROR(BF6/BA6-1), "NM", (BF6/BA6-1)) -> 0.2189949 | BG7: =IF(ISERROR(BG6/BB6-1), "NM", (BG6/BB6-1)) -> 0.22830806 | BH7: =IF(ISERROR(BH6/BC6-1), "NM", (BH6/BC6-1)) -> 0.29618089 | ... CD7: =IF(ISERROR(CD6/BY6-1), "NM", (CD6/BY6-1)) -> 0.17
B9: 1. Venmo P2P TPV (ex Pay With Venmo) | AQ9: 314 | AR9: 468 | AS9: 700 | AT9: 906 | AU9: =SUM(AQ9:AT9) -> 2388 | AV9: 1300 | AW9: =AR9*(1+AW10) -> 1623.96 | AX9: 2110 | AY9: =AT9*(1+AY10) -> 2482.44 | AZ9: =SUM(AV9:AY9) -> 7516.4 | BA9: ='Segment Detail'!BA98 -> 3200 | BB9: ='Segment Detail'!BB98 -> 3900 | BC9: ='Segment Detail'!BC98 -> 4900 | BD9: ='Segment Detail'!BD98 -> 5600 | BE9: =SUM(BA9:BD9) -> 17600 | BF9: ='Segment Detail'!BF98 -> 6800 | BG9: ='Segment Detail'!BG98 -> 8000 | BH9: ='Segment Detail'!BH98 -> 9400 | BI9: ='Segment Detail'!BI98 -> 10400 | BJ9: =SUM(BF9:BI9) -> 34600 | BK9: ='Segment Detail'!BK98 -> 12000 | BL9: =BG9*(1+BL10) -> 13200 | BM9: =BH9*(1+BM10) -> 15040 | BN9: =BI9*(1+BN10) -> 15600 | BO9: =SUM(BK9:BN9) -> 55840 | BP9: =BK9*(1+BP10) -> 16200 | BQ9: =BL9*(1+BQ10) -> 17820 | BR9: =BM9*(1+BR10) -> 20304 | BS9: =BN9*(1+BS10) -> 21060 | BT9: =SUM(BP9:BS9) -> 75384 | BU9: =BP9*(1+BU10) -> 21060 | BV9: =BQ9*(1+BV10) -> 23166 | BW9: =BR9*(1+BW10) -> 26395.2 | BX9: =BS9*(1+BX10) -> 27378 | BY9: =SUM(BU9:BX9) -> 97999.2 | BZ9: =BU9*(1+BZ10) -> 27378 | CA9: =BV9*(1+CA10) -> 30115.8 | CB9: =BW9*(1+CB10) -> 34313.76 | CC9: =BX9*(1+CC10) -> 35591.4 | CD9: =SUM(BZ9:CC9) -> 127398.96
B10: YoY % change | AU10: 6 | AV10: =AV9/AQ9-1 -> 3.1401274 | AW10: 2.47 | AX10: =AX9/AS9-1 -> 2.0142857 | AY10: 1.74 | AZ10: =AZ9/AU9-1 -> 2.1475712 | BA10: ='Segment Detail'!BA99 -> 1.5 | BB10: ='Segment Detail'!BB99 -> 1.41 | BC10: ='Segment Detail'!BC99 -> 1.31 | BD10: ='Segment Detail'!BD99 -> 1.26 | BE10: =BE9/AZ9-1 -> 1.3415465 | BF10: ='Segment Detail'!BF99 -> 1.125 | BG10: ='Segment Detail'!BG99 -> 1.03 | BH10: ='Segment Detail'!BH99 -> 0.93 | BI10: ='Segment Detail'!BI99 -> 0.86 | BJ10: =BJ9/BE9-1 -> 0.96590909 | BK10: ='Segment Detail'!BK99 -> 0.8 | BL10: 0.65 | BM10: 0.6 | BN10: 0.5 | BO10: =BO9/BJ9-1 -> 0.61387283 | BP10: 0.35 | BQ10: =+BP10 -> 0.35 | BR10: =+BQ10 -> 0.35 | BS10: =+BR10 -> 0.35 | BT10: =BT9/BO9-1 -> 0.35 | BU10: 0.3 | BV10: =+BU10 -> 0.3 | BW10: =+BV10 -> 0.3 | BX10: =+BW10 -> 0.3 | BY10: =BY9/BT9-1 -> 0.3 | BZ10: 0.3 | CA10: =+BZ10 -> 0.3 | CB10: =+CA10 -> 0.3 | CC10: =+CB10 -> 0.3 | CD10: =CD9/BY9-1 -> 0.3
B11: % of total TPV | AQ11: =AQ9/AQ$6 -> 0.0058499143 | AR11: =AR9/AR$6 -> 0.008248731 | AS11: =AS9/AS$6 -> 0.012030799 | AT11: =AT9/AT$6 -> 0.013719166 | AU11: =AU9/AU$6 -> 0.01017751 | AV11: =AV9/AV$6 -> 0.020628045 | AW11: =AW9/AW$6 -> 0.024065084 | AX11: =AX9/AX$6 -> 0.029586214 | ... CD11: =CD9/CD$6 -> 0.12690463
B12: Assumed Transaction Take Rate | AQ12: 0 | AR12: 0 | AS12: 0 | AT12: 0 | AU12: =SUMPRODUCT(AQ12:AT12,AQ9:AT9)/SUM(AQ9:AT9) -> 0 | AV12: 0 | AW12: 0 | AX12: 0 | AY12: 0 | AZ12: =SUMPRODUCT(AV12:AY12,AV9:AY9)/SUM(AV9:AY9) -> 0 | BA12: 0 | BB12: 0 | BC12: 0 | BD12: 0 | BE12: =SUMPRODUCT(BA12:BD12,BA9:BD9)/SUM(BA9:BD9) -> 0 | BF12: 0 | BG12: 0 | BH12: 0 | BI12: 0 | BJ12: =SUMPRODUCT(BF12:BI12,BF9:BI9)/SUM(BF9:BI9) -> 0 | BK12: 0 | BL12: 0 | BM12: 0 | BN12: 0 | BO12: =SUMPRODUCT(BK12:BN12,BK9:BN9)/SUM(BK9:BN9) -> 0 | BP12: 0 | BQ12: 0 | BR12: 0 | BS12: 0 | BT12: =SUMPRODUCT(BP12:BS12,BP9:BS9)/SUM(BP9:BS9) -> 0 | BU12: 0 | BV12: 0 | BW12: 0 | BX12: 0 | BY12: =SUMPRODUCT(BU12:BX12,BU9:BX9)/SUM(BU9:BX9) -> 0 | BZ12: 0 | CA12: 0 | CB12: 0 | CC12: 0 | CD12: =SUMPRODUCT(BZ12:CC12,BZ9:CC9)/SUM(BZ9:CC9) -> 0
B13: Assumed Transaction Expense Rate | AQ13: 0.003 | AR13: =AQ13 -> 0.003 | AS13: =AR13 -> 0.003 | AT13: =AS13 -> 0.003 | AU13: =SUMPRODUCT(AQ13:AT13,AQ9:AT9)/SUM(AQ9:AT9) -> 0.003 | AV13: =AT13 -> 0.003 | AW13: =AV13 -> 0.003 | AX13: =AW13 -> 0.003 | AY13: =AX13 -> 0.003 | AZ13: =SUMPRODUCT(AV13:AY13,AV9:AY9)/SUM(AV9:AY9) -> 0.003 | BA13: =AY13 -> 0.003 | BB13: =BA13 -> 0.003 | BC13: =BB13 -> 0.003 | BD13: =BC13 -> 0.003 | BE13: =SUMPRODUCT(BA13:BD13,BA9:BD9)/SUM(BA9:BD9) -> 0.003 | BF13: =BD13 -> 0.003 | BG13: =BE13 -> 0.003 | BH13: =BG13 -> 0.003 | BI13: =BH13 -> 0.003 | BJ13: =SUMPRODUCT(BF13:BI13,BF9:BI9)/SUM(BF9:BI9) -> 0.003 | BK13: =BI13 -> 0.003 | BL13: =BK13 -> 0.003 | BM13: =BL13 -> 0.003 | BN13: =BM13 -> 0.003 | BO13: =SUMPRODUCT(BK13:BN13,BK9:BN9)/SUM(BK9:BN9) -> 0.003 | BP13: =BN13 -> 0.003 | BQ13: =BP13 -> 0.003 | BR13: =BQ13 -> 0.003 | BS13: =BR13 -> 0.003 | BT13: =SUMPRODUCT(BP13:BS13,BP9:BS9)/SUM(BP9:BS9) -> 0.003 | BU13: =BS13 -> 0.003 | BV13: =BU13 -> 0.003 | BW13: =BV13 -> 0.003 | BX13: =BW13 -> 0.003 | BY13: =SUMPRODUCT(BU13:BX13,BU9:BX9)/SUM(BU9:BX9) -> 0.003 | BZ13: =BX13 -> 0.003 | CA13: =BZ13 -> 0.003 | CB13: =CA13 -> 0.003 | CC13: =CB13 -> 0.003 | CD13: =SUMPRODUCT(BZ13:CC13,BZ9:CC9)/SUM(BZ9:CC9) -> 0.003
B14: Implied Transaction Revenue | AQ14: =AQ9*AQ12 -> 0 | AR14: =AR9*AR12 -> 0 | AS14: =AS9*AS12 -> 0 | AT14: =AT9*AT12 -> 0 | AU14: =SUM(AQ14:AT14) -> 0 | AV14: =AV9*AV12 -> 0 | AW14: =AW9*AW12 -> 0 | AX14: =AX9*AX12 -> 0 | AY14: =AY9*AY12 -> 0 | AZ14: =SUM(AV14:AY14) -> 0 | BA14: =BA9*BA12 -> 0 | BB14: =BB9*BB12 -> 0 | BC14: =BC9*BC12 -> 0 | BD14: =BD9*BD12 -> 0 | BE14: =SUM(BA14:BD14) -> 0 | BF14: =BF9*BF12 -> 0 | BG14: =BG9*BG12 -> 0 | BH14: =BH9*BH12 -> 0 | BI14: =BI9*BI12 -> 0 | BJ14: =SUM(BF14:BI14) -> 0 | BK14: =BK9*BK12 -> 0 | BL14: =BL9*BL12 -> 0 | BM14: =BM9*BM12 -> 0 | BN14: =BN9*BN12 -> 0 | BO14: =SUM(BK14:BN14) -> 0 | BP14: =BP9*BP12 -> 0 | BQ14: =BQ9*BQ12 -> 0 | BR14: =BR9*BR12 -> 0 | BS14: =BS9*BS12 -> 0 | BT14: =SUM(BP14:BS14) -> 0 | BU14: =BU9*BU12 -> 0 | BV14: =BV9*BV12 -> 0 | BW14: =BW9*BW12 -> 0 | BX14: =BX9*BX12 -> 0 | BY14: =SUM(BU14:BX14) -> 0 | BZ14: =BZ9*BZ12 -> 0 | CA14: =CA9*CA12 -> 0 | CB14: =CB9*CB12 -> 0 | CC14: =CC9*CC12 -> 0 | CD14: =SUM(BZ14:CC14) -> 0
B15: Implied Transaction Expense | AQ15: =AQ9*AQ13 -> 0.942 | AR15: =AR9*AR13 -> 1.404 | AS15: =AS9*AS13 -> 2.1 | AT15: =AT9*AT13 -> 2.718 | AU15: =SUM(AQ15:AT15) -> 7.164 | AV15: =AV9*AV13 -> 3.9 | AW15: =AW9*AW13 -> 4.87188 | AX15: =AX9*AX13 -> 6.33 | AY15: =AY9*AY13 -> 7.44732 | AZ15: =SUM(AV15:AY15) -> 22.5492 | BA15: =BA9*BA13 -> 9.6 | BB15: =BB9*BB13 -> 11.7 | BC15: =BC9*BC13 -> 14.7 | BD15: =BD9*BD13 -> 16.8 | BE15: =SUM(BA15:BD15) -> 52.8 | BF15: =BF9*BF13 -> 20.4 | BG15: =BG9*BG13 -> 24 | BH15: =BH9*BH13 -> 28.2 | BI15: =BI9*BI13 -> 31.2 | BJ15: =SUM(BF15:BI15) -> 103.8 | BK15: =BK9*BK13 -> 36 | BL15: =BL9*BL13 -> 39.6 | BM15: =BM9*BM13 -> 45.12 | BN15: =BN9*BN13 -> 46.8 | BO15: =SUM(BK15:BN15) -> 167.52 | BP15: =BP9*BP13 -> 48.6 | BQ15: =BQ9*BQ13 -> 53.46 | BR15: =BR9*BR13 -> 60.912 | BS15: =BS9*BS13 -> 63.18 | BT15: =SUM(BP15:BS15) -> 226.152 | BU15: =BU9*BU13 -> 63.18 | BV15: =BV9*BV13 -> 69.498 | BW15: =BW9*BW13 -> 79.1856 | BX15: =BX9*BX13 -> 82.134 | BY15: =SUM(BU15:BX15) -> 293.9976 | BZ15: =BZ9*BZ13 -> 82.134 | CA15: =CA9*CA13 -> 90.3474 | CB15: =CB9*CB13 -> 102.94128 | CC15: =CC9*CC13 -> 106.7742 | CD15: =SUM(BZ15:CC15) -> 382.19688
B17: Take Rate ex Venmo P2P | AK17: =(AK55+AK30+AK38)/(AK6-AK9) -> 0.033505258 | AP17: =(AP55+AP30+AP38)/(AP6-AP9) -> 0.032283439 | AQ17: =(AQ55+AQ30+AQ38)/(AQ6-AQ9) -> 0.031314419 | AR17: =(AR55+AR30+AR38)/(AR6-AR9) -> 0.030390275 | AS17: =(AS55+AS30+AS38)/(AS6-AS9) -> 0.030443254 | AT17: =(AT55+AT30+AT38)/(AT6-AT9) -> 0.030138332 | AU17: =(AU55+AU30+AU38)/(AU6-AU9) -> 0.030545066 | AV17: =(AV55+AV30+AV38)/(AV6-AV9) -> 0.030961909 | AW17: =(AW55+AW30+AW38)/(AW6-AW9) -> 0.029852088 | ... CD17: =(CD55+CD30+CD38)/(CD6-CD9) -> 0.024306758
B18: Txn Expense Rate ex Venmo P2P | AK18: =(AK56+AK31+AK39)/(AK6-AK9) -> 0.010115549 | AP18: =(AP56+AP31+AP39)/(AP6-AP9) -> 0.0098865338 | AQ18: =(AQ56+AQ31+AQ39)/(AQ6-AQ9) -> 0.0096146696 | AR18: =(AR56+AR31+AR39)/(AR6-AR9) -> 0.0093053956 | AS18: =(AS56+AS31+AS39)/(AS6-AS9) -> 0.009305198 | AT18: =(AT56+AT31+AT39)/(AT6-AT9) -> 0.009078071 | AU18: =(AU56+AU31+AU39)/(AU6-AU9) -> 0.0093126542 | AV18: =(AV56+AV31+AV39)/(AV6-AV9) -> 0.0092529285 | AW18: =(AW56+AW31+AW39)/(AW6-AW9) -> 0.0095527914 | ... CD18: =(CD56+CD31+CD39)/(CD6-CD9) -> 0.01071241
B19: YoY Take Rate Degradation caused by Venmo P2P | AU19: =-((AU58-AP58)-(AU17-AP17))*10000 -> 3.1087271 | AV19: =-((AV58-AQ58)-(AV17-AQ17))*10000 -> 4.5549698 | AW19: =-((AW58-AR58)-(AW17-AR17))*10000 -> 4.677118 | AX19: =-((AX58-AS58)-(AX17-AS17))*10000 -> 4.9045974 | AY19: =-((AY58-AT58)-(AY17-AT17))*10000 -> 4.3356559 | AZ19: =-((AZ58-AU58)-(AZ17-AU17))*10000 -> 4.5350335 | BA19: =-((BA58-AV58)-(BA17-AV17))*10000 -> 4.6160694 | BB19: =-((BB58-AW58)-(BB17-AW17))*10000 -> 5.1523398 | ... CD19: =-((CD58-BY58)-(CD17-BY17))*10000 -> -1.3684464
B20: YoY Txn Expense benefit caused by Venmo P2P | AU20: =-((AU60-AP60)-(AU18-AP18))*10000 -> 0.642471 | AV20: =-((AV60-AQ60)-(AV18-AQ18))*10000 -> 0.90290438 | AW20: =-((AW60-AR60)-(AW18-AR18))*10000 -> 1.0568196 | AX20: =-((AX60-AS60)-(AX18-AS18))*10000 -> 1.1098328 | AY20: =-((AY60-AT60)-(AY18-AT18))*10000 -> 1.0213757 | AZ20: =-((AZ60-AU60)-(AZ18-AU18))*10000 -> 0.98161743 | BA20: =-((BA60-AV60)-(BA18-AV18))*10000 -> 1.1632537 | BB20: =-((BB60-AW60)-(BB18-AW18))*10000 -> 1.2913942 | ... CD20: =-((CD60-BY60)-(CD18-BY18))*10000 -> -0.02438799
B22: Gross Profit ex Venmo P2P | AK22: =('Quarterly Model'!AK33+'Take Rate Drivers'!AK15-'Take Rate Drivers'!AK14)/('Quarterly Model'!AK14-'Take Rate Drivers'!AK14) -> 0.667432 | AP22: =('Quarterly Model'!AP33+'Take Rate Drivers'!AP15-'Take Rate Drivers'!AP14)/('Quarterly Model'!AP14-'Take Rate Drivers'!AP14) -> 0.65259402 | AQ22: =('Quarterly Model'!AQ33+'Take Rate Drivers'!AQ15-'Take Rate Drivers'!AQ14)/('Quarterly Model'!AQ14-'Take Rate Drivers'!AQ14) -> 0.6504233 | AR22: =('Quarterly Model'!AR33+'Take Rate Drivers'!AR15-'Take Rate Drivers'!AR14)/('Quarterly Model'!AR14-'Take Rate Drivers'!AR14) -> 0.65795255 | AS22: =('Quarterly Model'!AS33+'Take Rate Drivers'!AS15-'Take Rate Drivers'!AS14)/('Quarterly Model'!AS14-'Take Rate Drivers'!AS14) -> 0.63221715 | AT22: =('Quarterly Model'!AT33+'Take Rate Drivers'!AT15-'Take Rate Drivers'!AT14)/('Quarterly Model'!AT14-'Take Rate Drivers'!AT14) -> 0.63669164 | AU22: =('Quarterly Model'!AU33+'Take Rate Drivers'!AU15-'Take Rate Drivers'!AU14)/('Quarterly Model'!AU14-'Take Rate Drivers'!AU14) -> 0.64405442 | AV22: =('Quarterly Model'!AV33+'Take Rate Drivers'!AV15-'Take Rate Drivers'!AV14)/('Quarterly Model'!AV14-'Take Rate Drivers'!AV14) -> 0.64428304 | AW22: =('Quarterly Model'!AW33+'Take Rate Drivers'!AW15-'Take Rate Drivers'!AW14)/('Quarterly Model'!AW14-'Take Rate Drivers'!AW14) -> 0.63971735 | ... CD22: =('Quarterly Model'!CD33+'Take Rate Drivers'!CD15-'Take Rate Drivers'!CD14)/('Quarterly Model'!CD14-'Take Rate Drivers'!CD14) -> 0.49731146
B23: YoY Gross Profit Margin Degradation caused by Venmo P2P | AU23: =-(('Quarterly Model'!AU34-'Quarterly Model'!AP34)-(AU22-AP22))*10000 -> 8.9415876 | AV23: =-(('Quarterly Model'!AV34-'Quarterly Model'!AQ34)-(AV22-AQ22))*10000 -> 13.240798 | AW23: =-(('Quarterly Model'!AW34-'Quarterly Model'!AR34)-(AW22-AR22))*10000 -> 14.159421 | AX23: =-(('Quarterly Model'!AX34-'Quarterly Model'!AS34)-(AX22-AS22))*10000 -> 17.379168 | AY23: =-(('Quarterly Model'!AY34-'Quarterly Model'!AT34)-(AY22-AT22))*10000 -> 16.719991 | AZ23: =-(('Quarterly Model'!AZ34-'Quarterly Model'!AU34)-(AZ22-AU22))*10000 -> 15.441198 | BA23: =-(('Quarterly Model'!BA34-'Quarterly Model'!AV34)-(BA22-AV22))*10000 -> 19.46031 | BB23: =-(('Quarterly Model'!BB34-'Quarterly Model'!AW34)-(BB22-AW22))*10000 -> 22.904192 | ... CD23: =-(('Quarterly Model'!CD34-'Quarterly Model'!BY34)-(CD22-BY22))*10000 -> 17.831782
B25: 2. Braintree Full Stack TPV | AQ25: 500 | AR25: 1000 | AS25: 1500 | AT25: =3118.38-AT9 -> 2212.38 | AU25: =SUM(AQ25:AT25) -> 5212.38 | AV25: 3000 | AW25: 3500 | AX25: 4000 | AY25: 4500 | AZ25: =SUM(AV25:AY25) -> 15000 | BA25: =AV25*(1+BA26) -> 6000 | BB25: =AW25*(1+BB26) -> 6650 | BC25: =AX25*(1+BC26) -> 7200 | BD25: =AY25*(1+BD26) -> 7650 | BE25: =SUM(BA25:BD25) -> 27500 | BF25: =BA25*(1+BF26) -> 9900 | BG25: =BB25*(1+BG26) -> 10972.5 | BH25: =BC25*(1+BH26) -> 11160 | BI25: =BD25*(1+BI26) -> 11092.5 | BJ25: =SUM(BF25:BI25) -> 43125 | BK25: =BF25*(1+BK26) -> 13860 | BL25: =BG25*(1+BL26) -> 14812.875 | BM25: =BH25*(1+BM26) -> 14508 | BN25: =BI25*(1+BN26) -> 14420.25 | BO25: =SUM(BK25:BN25) -> 57601.125 | BP25: =BK25*(1+BP26) -> 17325 | BQ25: =BL25*(1+BQ26) -> 18516.094 | BR25: =BM25*(1+BR26) -> 18135 | BS25: =BN25*(1+BS26) -> 18025.312 | BT25: =SUM(BP25:BS25) -> 72001.406 | BU25: =BP25*(1+BU26) -> 20790 | BV25: =BQ25*(1+BV26) -> 22219.313 | BW25: =BR25*(1+BW26) -> 21762 | BX25: =BS25*(1+BX26) -> 21630.375 | BY25: =SUM(BU25:BX25) -> 86401.688 | BZ25: =BU25*(1+BZ26) -> 24948 | CA25: =BV25*(1+CA26) -> 26663.175 | CB25: =BW25*(1+CB26) -> 26114.4 | CC25: =BX25*(1+CC26) -> 25956.45 | CD25: =SUM(BZ25:CC25) -> 103682.02
B26: YoY % change | AY26: 1.74 | BA26: 1 | BB26: 0.9 | BC26: 0.8 | BD26: 0.7 | BE26: =BE25/AZ25-1 -> 0.83333333 | BF26: 0.65 | BG26: 0.65 | BH26: 0.55 | BI26: 0.45 | BJ26: =BJ25/BE25-1 -> 0.56818182 | BK26: 0.4 | BL26: 0.35 | BM26: 0.3 | BN26: 0.3 | BO26: =BO25/BJ25-1 -> 0.33567826 | BP26: 0.25 | BQ26: =+BP26 -> 0.25 | BR26: =+BQ26 -> 0.25 | BS26: =+BR26 -> 0.25 | BT26: =BT25/BO25-1 -> 0.25 | BU26: 0.2 | BV26: =+BU26 -> 0.2 | BW26: =+BV26 -> 0.2 | BX26: =+BW26 -> 0.2 | BY26: =BY25/BT25-1 -> 0.2 | BZ26: 0.2 | CA26: =+BZ26 -> 0.2 | CB26: =+CA26 -> 0.2 | CC26: =+CB26 -> 0.2 | CD26: =CD25/BY25-1 -> 0.2
B27: % of total TPV | AQ27: =AQ25/AQ$6 -> 0.0093151502 | AR27: =AR25/AR$6 -> 0.017625494 | AS27: =AS25/AS$6 -> 0.025780283 | AT27: =AT25/AT$6 -> 0.033501113 | AU27: =AU25/AU$6 -> 0.022214844 | AV27: =AV25/AV$6 -> 0.04760318 | AW27: =AW25/AW$6 -> 0.051865683 | AX27: =AX25/AX$6 -> 0.056087609 | ... CD27: =CD25/CD$6 -> 0.10327972
B28: Assumed Transaction Take Rate | AQ28: 0.028 | AR28: =AQ28 -> 0.028 | AS28: =AR28 -> 0.028 | AT28: =AS28 -> 0.028 | AU28: =SUMPRODUCT(AQ28:AT28,AQ25:AT25)/SUM(AQ25:AT25) -> 0.028 | AV28: =AT28-0.075% -> 0.02725 | AW28: =AV28 -> 0.02725 | AX28: =AW28 -> 0.02725 | AY28: =AX28 -> 0.02725 | AZ28: =SUMPRODUCT(AV28:AY28,AV25:AY25)/SUM(AV25:AY25) -> 0.02725 | BA28: =AY28-0.075% -> 0.0265 | BB28: =BA28 -> 0.0265 | BC28: =BB28 -> 0.0265 | BD28: =BC28 -> 0.0265 | BE28: =SUMPRODUCT(BA28:BD28,BA25:BD25)/SUM(BA25:BD25) -> 0.0265 | BF28: =BD28-0.05% -> 0.026 | BG28: =BE28-0.05% -> 0.026 | BH28: =BG28 -> 0.026 | BI28: =BH28 -> 0.026 | BJ28: =SUMPRODUCT(BF28:BI28,BF25:BI25)/SUM(BF25:BI25) -> 0.026 | BK28: =BI28-0.02% -> 0.0258 | BL28: =BK28 -> 0.0258 | BM28: =BL28 -> 0.0258 | BN28: =BM28 -> 0.0258 | BO28: =SUMPRODUCT(BK28:BN28,BK25:BN25)/SUM(BK25:BN25) -> 0.0258 | BP28: =BN28-0.02% -> 0.0256 | BQ28: =BP28 -> 0.0256 | BR28: =BQ28 -> 0.0256 | BS28: =BR28 -> 0.0256 | BT28: =SUMPRODUCT(BP28:BS28,BP25:BS25)/SUM(BP25:BS25) -> 0.0256 | BU28: =BS28-0.02% -> 0.0254 | BV28: =BU28 -> 0.0254 | BW28: =BV28 -> 0.0254 | BX28: =BW28 -> 0.0254 | BY28: =SUMPRODUCT(BU28:BX28,BU25:BX25)/SUM(BU25:BX25) -> 0.0254 | BZ28: =BX28-0.02% -> 0.0252 | CA28: =BZ28 -> 0.0252 | CB28: =CA28 -> 0.0252 | CC28: =CB28 -> 0.0252 | CD28: =SUMPRODUCT(BZ28:CC28,BZ25:CC25)/SUM(BZ25:CC25) -> 0.0252
B29: Assumed Transaction Expense Rate | AQ29: 0.018 | AR29: =AQ29 -> 0.018 | AS29: =AR29 -> 0.018 | AT29: =AS29 -> 0.018 | AU29: =SUMPRODUCT(AQ29:AT29,AQ25:AT25)/SUM(AQ25:AT25) -> 0.018 | AV29: =AT29 -> 0.018 | AW29: =AV29 -> 0.018 | AX29: =AW29 -> 0.018 | AY29: =AX29 -> 0.018 | AZ29: =SUMPRODUCT(AV29:AY29,AV25:AY25)/SUM(AV25:AY25) -> 0.018 | BA29: =AY29 -> 0.018 | BB29: =BA29 -> 0.018 | BC29: =BB29 -> 0.018 | BD29: =BC29 -> 0.018 | BE29: =SUMPRODUCT(BA29:BD29,BA25:BD25)/SUM(BA25:BD25) -> 0.018 | BF29: =BD29 -> 0.018 | BG29: =BE29 -> 0.018 | BH29: =BG29 -> 0.018 | BI29: =BH29 -> 0.018 | BJ29: =SUMPRODUCT(BF29:BI29,BF25:BI25)/SUM(BF25:BI25) -> 0.018 | BK29: =BI29 -> 0.018 | BL29: =BK29 -> 0.018 | BM29: =BL29 -> 0.018 | BN29: =BM29 -> 0.018 | BO29: =SUMPRODUCT(BK29:BN29,BK25:BN25)/SUM(BK25:BN25) -> 0.018 | BP29: =BN29 -> 0.018 | BQ29: =BP29 -> 0.018 | BR29: =BQ29 -> 0.018 | BS29: =BR29 -> 0.018 | BT29: =SUMPRODUCT(BP29:BS29,BP25:BS25)/SUM(BP25:BS25) -> 0.018 | BU29: =BS29 -> 0.018 | BV29: =BU29 -> 0.018 | BW29: =BV29 -> 0.018 | BX29: =BW29 -> 0.018 | BY29: =SUMPRODUCT(BU29:BX29,BU25:BX25)/SUM(BU25:BX25) -> 0.018 | BZ29: =BX29 -> 0.018 | CA29: =BZ29 -> 0.018 | CB29: =CA29 -> 0.018 | CC29: =CB29 -> 0.018 | CD29: =SUMPRODUCT(BZ29:CC29,BZ25:CC25)/SUM(BZ25:CC25) -> 0.018
B30: Implied Transaction Revenue | AQ30: =AQ25*AQ28 -> 14 | AR30: =AR25*AR28 -> 28 | AS30: =AS25*AS28 -> 42 | AT30: =AT25*AT28 -> 61.94664 | AU30: =SUM(AQ30:AT30) -> 145.94664 | AV30: =AV25*AV28 -> 81.75 | AW30: =AW25*AW28 -> 95.375 | AX30: =AX25*AX28 -> 109 | AY30: =AY25*AY28 -> 122.625 | AZ30: =SUM(AV30:AY30) -> 408.75 | BA30: =BA25*BA28 -> 159 | BB30: =BB25*BB28 -> 176.225 | BC30: =BC25*BC28 -> 190.8 | BD30: =BD25*BD28 -> 202.725 | BE30: =SUM(BA30:BD30) -> 728.75 | BF30: =BF25*BF28 -> 257.4 | BG30: =BG25*BG28 -> 285.285 | BH30: =BH25*BH28 -> 290.16 | BI30: =BI25*BI28 -> 288.405 | BJ30: =SUM(BF30:BI30) -> 1121.25 | BK30: =BK25*BK28 -> 357.588 | BL30: =BL25*BL28 -> 382.17218 | BM30: =BM25*BM28 -> 374.3064 | BN30: =BN25*BN28 -> 372.04245 | BO30: =SUM(BK30:BN30) -> 1486.109 | BP30: =BP25*BP28 -> 443.52 | BQ30: =BQ25*BQ28 -> 474.012 | BR30: =BR25*BR28 -> 464.256 | BS30: =BS25*BS28 -> 461.448 | BT30: =SUM(BP30:BS30) -> 1843.236 | BU30: =BU25*BU28 -> 528.066 | BV30: =BV25*BV28 -> 564.37054 | BW30: =BW25*BW28 -> 552.7548 | BX30: =BX25*BX28 -> 549.41153 | BY30: =SUM(BU30:BX30) -> 2194.6029 | BZ30: =BZ25*BZ28 -> 628.6896 | CA30: =CA25*CA28 -> 671.91201 | CB30: =CB25*CB28 -> 658.08288 | CC30: =CC25*CC28 -> 654.10254 | CD30: =SUM(BZ30:CC30) -> 2612.787
B31: Implied Transaction Expense | AQ31: =AQ25*AQ29 -> 9 | AR31: =AR25*AR29 -> 18 | AS31: =AS25*AS29 -> 27 | AT31: =AT25*AT29 -> 39.82284 | AU31: =SUM(AQ31:AT31) -> 93.82284 | AV31: =AV25*AV29 -> 54 | AW31: =AW25*AW29 -> 63 | AX31: =AX25*AX29 -> 72 | AY31: =AY25*AY29 -> 81 | AZ31: =SUM(AV31:AY31) -> 270 | BA31: =BA25*BA29 -> 108 | BB31: =BB25*BB29 -> 119.7 | BC31: =BC25*BC29 -> 129.6 | BD31: =BD25*BD29 -> 137.7 | BE31: =SUM(BA31:BD31) -> 495 | BF31: =BF25*BF29 -> 178.2 | BG31: =BG25*BG29 -> 197.505 | BH31: =BH25*BH29 -> 200.88 | BI31: =BI25*BI29 -> 199.665 | BJ31: =SUM(BF31:BI31) -> 776.25 | BK31: =BK25*BK29 -> 249.48 | BL31: =BL25*BL29 -> 266.63175 | BM31: =BM25*BM29 -> 261.144 | BN31: =BN25*BN29 -> 259.5645 | BO31: =SUM(BK31:BN31) -> 1036.8202 | BP31: =BP25*BP29 -> 311.85 | BQ31: =BQ25*BQ29 -> 333.28969 | BR31: =BR25*BR29 -> 326.43 | BS31: =BS25*BS29 -> 324.45562 | BT31: =SUM(BP31:BS31) -> 1296.0253 | BU31: =BU25*BU29 -> 374.22 | BV31: =BV25*BV29 -> 399.94763 | BW31: =BW25*BW29 -> 391.716 | BX31: =BX25*BX29 -> 389.34675 | BY31: =SUM(BU31:BX31) -> 1555.2304 | BZ31: =BZ25*BZ29 -> 449.064 | CA31: =CA25*CA29 -> 479.93715 | CB31: =CB25*CB29 -> 470.0592 | CC31: =CC25*CC29 -> 467.2161 | CD31: =SUM(BZ31:CC31) -> 1866.2764
B33: 3. Xoom TPV | AF33: 1706.659 | AT33: 1758.865 | AU33: 6859.3967 | AV33: 1761.447 | AW33: 1727.534 | AX33: 1930.646 | AY33: =AT33*(1+AY34)/2 -> 1011.3474 | AZ33: =AY33 -> 1011.3474 | BA33: =AV33*(1+BA34) -> 2025.664 | BB33: =AW33*(1+BB34) -> 1986.6641 | BC33: =AX33*(1+BC34) -> 2220.2429 | BD33: =AY33*2*(1+BD34) -> 2326.099 | BE33: =SUM(BA33:BD33) -> 8558.67 | BF33: =BA33*(1+BF34) -> 2329.5137 | BG33: =BB33*(1+BG34) -> 2284.6637 | BH33: =BC33*(1+BH34) -> 2553.2793 | BI33: =BD33*(1+BI34) -> 2675.0138 | BJ33: =SUM(BF33:BI33) -> 9842.4705 | BK33: =BF33*(1+BK34) -> 2678.9407 | BL33: =BG33*(1+BL34) -> 2627.3633 | BM33: =BH33*(1+BM34) -> 2936.2712 | BN33: =BI33*(1+BN34) -> 3076.2659 | BO33: =SUM(BK33:BN33) -> 11318.841 | BP33: =BK33*(1+BP34) -> 3080.7818 | BQ33: =BL33*(1+BQ34) -> 3021.4678 | BR33: =BM33*(1+BR34) -> 3376.7119 | BS33: =BN33*(1+BS34) -> 3537.7058 | BT33: =SUM(BP33:BS33) -> 13016.667 | BU33: =BP33*(1+BU34) -> 3542.8991 | BV33: =BQ33*(1+BV34) -> 3474.6879 | BW33: =BR33*(1+BW34) -> 3883.2187 | BX33: =BS33*(1+BX34) -> 4068.3616 | BY33: =SUM(BU33:BX33) -> 14969.167 | BZ33: =BU33*(1+BZ34) -> 4074.3339 | CA33: =BV33*(1+CA34) -> 3995.8911 | CB33: =BW33*(1+CB34) -> 4465.7015 | CC33: =BX33*(1+CC34) -> 4678.6159 | CD33: =SUM(BZ33:CC33) -> 17214.542
B34: YoY % change | AP34: 0.70688884 | AQ34: 0.49329466 | AR34: 0.12371466 | AS34: 0.13390588 | AT34: 0.28687991 | AU34: 0.23709644 | AV34: 0.11717981 | AW34: -0.043098759 | AX34: 0.12344901 | AY34: 0.15 | BA34: 0.15 | BB34: 0.15 | BC34: 0.15 | BD34: 0.15 | BF34: 0.15 | BG34: 0.15 | BH34: 0.15 | BI34: 0.15 | BJ34: =BJ33/BE33-1 -> 0.15 | BK34: 0.15 | BL34: 0.15 | BM34: 0.15 | BN34: 0.15 | BO34: =BO33/BJ33-1 -> 0.15 | BP34: 0.15 | BQ34: 0.15 | BR34: 0.15 | BS34: 0.15 | BT34: =BT33/BO33-1 -> 0.15 | BU34: 0.15 | BV34: 0.15 | BW34: 0.15 | BX34: 0.15 | BY34: =BY33/BT33-1 -> 0.15 | BZ34: 0.15 | CA34: 0.15 | CB34: 0.15 | CC34: 0.15 | CD34: =CD33/BY33-1 -> 0.15
B35: % of total TPV | AY35: =AY33/AY$6 -> 0.012169952 | AZ35: =AZ33/AZ6 -> 0.0035111596 | BA35: =BA33/BA6 -> 0.024535957 | BB35: =BB33/BB6 -> 0.022636693 | BC35: =BC33/BC6 -> 0.024976016 | BD35: =BD33/BD6 -> 0.023096772 | BE35: =BE33/BE6 -> 0.023778839 | BF35: =BF33/BF6 -> 0.023147226 | BG35: =BG33/BG6 -> 0.021193541 | ... CD35: =CD33/CD6 -> 0.017147747
B36: Assumed Transaction Take Rate | AK36: 0.024632002 | AP36: 0.022039928 | AQ36: 0.02279331 | AR36: 0.022070057 | AS36: 0.022936295 | AT36: 0.024951318 | AU36: 0.023192127 | AV36: 0.025216768 | AW36: 0.026816838 | AX36: 0.021977618 | AY36: 0.023 | AZ36: =AY36 -> 0.023 | BA36: =AY36 -> 0.023 | BB36: =BA36 -> 0.023 | BC36: =BB36 -> 0.023 | BD36: =BC36 -> 0.023 | BE36: =SUMPRODUCT(BA36:BD36,BA33:BD33)/SUM(BA33:BD33) -> 0.023 | BF36: =BD36 -> 0.023 | BG36: =BE36 -> 0.023 | BH36: =BG36 -> 0.023 | BI36: =BH36 -> 0.023 | BJ36: =SUMPRODUCT(BF36:BI36,BF33:BI33)/SUM(BF33:BI33) -> 0.023 | BK36: =BI36 -> 0.023 | BL36: =BK36 -> 0.023 | BM36: =BL36 -> 0.023 | BN36: =BM36 -> 0.023 | BO36: =SUMPRODUCT(BK36:BN36,BK33:BN33)/SUM(BK33:BN33) -> 0.023 | BP36: =BN36 -> 0.023 | BQ36: =BP36 -> 0.023 | BR36: =BQ36 -> 0.023 | BS36: =BR36 -> 0.023 | BT36: =SUMPRODUCT(BP36:BS36,BP33:BS33)/SUM(BP33:BS33) -> 0.023 | BU36: =BS36 -> 0.023 | BV36: =BU36 -> 0.023 | BW36: =BV36 -> 0.023 | BX36: =BW36 -> 0.023 | BY36: =SUMPRODUCT(BU36:BX36,BU33:BX33)/SUM(BU33:BX33) -> 0.023 | BZ36: =BX36 -> 0.023 | CA36: =BZ36 -> 0.023 | CB36: =CA36 -> 0.023 | CC36: =CB36 -> 0.023 | CD36: =SUMPRODUCT(BZ36:CC36,BZ33:CC33)/SUM(BZ33:CC33) -> 0.023
B37: Assumed Transaction Expense Rate | AK37: 0.0082436061 | AP37: 0.0068681123 | AQ37: 0.0060747489 | AR37: 0.0071881117 | AS37: 0.0064713451 | AT37: 0.0066741905 | AU37: 0.0066208447 | AV37: 0.0068313154 | AW37: 0.0077271996 | AX37: 0.0075384094 | AY37: 0.0075 | AZ37: =AY37 -> 0.0075 | BA37: =AY37 -> 0.0075 | BB37: =BA37 -> 0.0075 | BC37: =BB37 -> 0.0075 | BD37: =BC37 -> 0.0075 | BE37: =SUMPRODUCT(BA37:BD37,BA33:BD33)/SUM(BA33:BD33) -> 0.0075 | BF37: =BD37 -> 0.0075 | BG37: =BE37 -> 0.0075 | BH37: =BG37 -> 0.0075 | BI37: =BH37 -> 0.0075 | BJ37: =SUMPRODUCT(BF37:BI37,BF33:BI33)/SUM(BF33:BI33) -> 0.0075 | BK37: =BI37 -> 0.0075 | BL37: =BK37 -> 0.0075 | BM37: =BL37 -> 0.0075 | BN37: =BM37 -> 0.0075 | BO37: =SUMPRODUCT(BK37:BN37,BK33:BN33)/SUM(BK33:BN33) -> 0.0075 | BP37: =BN37 -> 0.0075 | BQ37: =BP37 -> 0.0075 | BR37: =BQ37 -> 0.0075 | BS37: =BR37 -> 0.0075 | BT37: =SUMPRODUCT(BP37:BS37,BP33:BS33)/SUM(BP33:BS33) -> 0.0075 | BU37: =BS37 -> 0.0075 | BV37: =BU37 -> 0.0075 | BW37: =BV37 -> 0.0075 | BX37: =BW37 -> 0.0075 | BY37: =SUMPRODUCT(BU37:BX37,BU33:BX33)/SUM(BU33:BX33) -> 0.0075 | BZ37: =BX37 -> 0.0075 | CA37: =BZ37 -> 0.0075 | CB37: =CA37 -> 0.0075 | CC37: =CB37 -> 0.0075 | CD37: =SUMPRODUCT(BZ37:CC37,BZ33:CC33)/SUM(BZ33:CC33) -> 0.0075
B38: Implied Transaction Revenue | AY38: =AY33*AY36 -> 23.26099 | AZ38: =SUM(AV38:AY38) -> 23.26099 | BA38: =BA33*BA36 -> 46.590273 | BB38: =BB33*BB36 -> 45.693274 | BC38: =BC33*BC36 -> 51.065587 | BD38: =BD33*BD36 -> 53.500276 | BE38: =SUM(BA38:BD38) -> 196.84941 | BF38: =BF33*BF36 -> 53.578814 | BG38: =BG33*BG36 -> 52.547265 | BH38: =BH33*BH36 -> 58.725425 | BI38: =BI33*BI36 -> 61.525318 | BJ38: =SUM(BF38:BI38) -> 226.37682 | BK38: =BK33*BK36 -> 61.615636 | BL38: =BL33*BL36 -> 60.429355 | BM38: =BM33*BM36 -> 67.534238 | BN38: =BN33*BN36 -> 70.754115 | BO38: =SUM(BK38:BN38) -> 260.33335 | BP38: =BP33*BP36 -> 70.857982 | BQ38: =BQ33*BQ36 -> 69.493759 | BR38: =BR33*BR36 -> 77.664374 | BS38: =BS33*BS36 -> 81.367232 | BT38: =SUM(BP38:BS38) -> 299.38335 | BU38: =BU33*BU36 -> 81.486679 | BV38: =BV33*BV36 -> 79.917822 | BW38: =BW33*BW36 -> 89.31403 | BX38: =BX33*BX36 -> 93.572317 | BY38: =SUM(BU38:BX38) -> 344.29085 | BZ38: =BZ33*BZ36 -> 93.709681 | CA38: =CA33*CA36 -> 91.905496 | CB38: =CB33*CB36 -> 102.71113 | CC38: =CC33*CC36 -> 107.60816 | CD38: =SUM(BZ38:CC38) -> 395.93448
B39: Implied Transaction Expense | AY39: =AY33*AY37 -> 7.5851053 | AZ39: =SUM(AV39:AY39) -> 7.5851053 | BA39: =BA33*BA37 -> 15.19248 | BB39: =BB33*BB37 -> 14.899981 | BC39: =BC33*BC37 -> 16.651822 | BD39: =BD33*BD37 -> 17.445742 | BE39: =SUM(BA39:BD39) -> 64.190025 | BF39: =BF33*BF37 -> 17.471352 | BG39: =BG33*BG37 -> 17.134978 | BH39: =BH33*BH37 -> 19.149595 | BI39: =BI33*BI37 -> 20.062604 | BJ39: =SUM(BF39:BI39) -> 73.818529 | BK39: =BK33*BK37 -> 20.092055 | BL39: =BL33*BL37 -> 19.705225 | BM39: =BM33*BM37 -> 22.022034 | BN39: =BN33*BN37 -> 23.071994 | BO39: =SUM(BK39:BN39) -> 84.891308 | BP39: =BP33*BP37 -> 23.105864 | BQ39: =BQ33*BQ37 -> 22.661008 | BR39: =BR33*BR37 -> 25.325339 | BS39: =BS33*BS37 -> 26.532793 | BT39: =SUM(BP39:BS39) -> 97.625004 | BU39: =BU33*BU37 -> 26.571743 | BV39: =BV33*BV37 -> 26.060159 | BW39: =BW33*BW37 -> 29.12414 | BX39: =BX33*BX37 -> 30.512712 | BY39: =SUM(BU39:BX39) -> 112.26876 | BZ39: =BZ33*BZ37 -> 30.557505 | CA39: =CA33*CA37 -> 29.969183 | CB39: =CB33*CB37 -> 33.492761 | CC39: =CC33*CC37 -> 35.089619 | CD39: =SUM(BZ39:CC39) -> 129.10907
B41: 4. Pay With Venmo TPV | BA41: 10 | BB41: 30 | BC41: 100 | BD41: 150 | BE41: =SUM(BA41:BD41) -> 290 | BF41: 50 | BG41: 100 | BH41: 150 | BI41: 250 | BJ41: =SUM(BF41:BI41) -> 550 | BK41: =+BK9*BK43 -> 360 | BL41: =+BL9*BL43 -> 594 | BM41: =+BM9*BM43 -> 902.4 | BN41: =+BN9*BN43 -> 1170 | BO41: =SUM(BK41:BN41) -> 3026.4 | BP41: =+BP9*BP43 -> 1458 | BQ41: =+BQ9*BQ43 -> 2049.3 | BR41: =+BR9*BR43 -> 2842.56 | BS41: =+BS9*BS43 -> 3474.9 | BT41: =SUM(BP41:BS41) -> 9824.76 | BU41: =+BU9*BU43 -> 3790.8 | BV41: =+BV9*BV43 -> 4749.03 | BW41: =+BW9*BW43 -> 6070.896 | BX41: =+BX9*BX43 -> 6981.39 | BY41: =SUM(BU41:BX41) -> 21592.116 | BZ41: =+BZ9*BZ43 -> 7392.06 | CA41: =+CA9*CA43 -> 8884.161 | CB41: =+CB9*CB43 -> 10980.403 | CC41: =+CC9*CC43 -> 12279.033 | CD41: =SUM(BZ41:CC41) -> 39535.657
B42: YoY % change | BA42: NM | BB42: NM | BC42: NM | BD42: NM | BE42: NM | BF42: =BF41/BA41-1 -> 4 | BG42: =BG41/BB41-1 -> 2.3333333 | BH42: =BH41/BC41-1 -> 0.5 | BI42: =BI41/BD41-1 -> 0.66666667 | BJ42: =BJ41/BE41-1 -> 0.89655172 | BK42: =+BK41/BF41-1 -> 6.2 | BL42: =+BL41/BG41-1 -> 4.94 | BM42: =+BM41/BH41-1 -> 5.016 | BN42: =+BN41/BI41-1 -> 3.68 | BO42: =BO41/BJ41-1 -> 4.5025455 | BP42: =+BP41/BK41-1 -> 3.05 | BQ42: =+BQ41/BL41-1 -> 2.45 | BR42: =+BR41/BM41-1 -> 2.15 | BS42: =+BS41/BN41-1 -> 1.97 | BT42: =BT41/BO41-1 -> 2.2463521 | BU42: =+BU41/BP41-1 -> 1.6 | BV42: =+BV41/BQ41-1 -> 1.3173913 | BW42: =+BW41/BR41-1 -> 1.1357143 | BX42: =+BX41/BS41-1 -> 1.0090909 | BY42: =BY41/BT41-1 -> 1.1977245 | BZ42: =+BZ41/BU41-1 -> 0.95 | CA42: =+CA41/BV41-1 -> 0.87073171 | CB42: =+CB41/BW41-1 -> 0.80869565 | CC42: =+CC41/BX41-1 -> 0.75882353 | CD42: =CD41/BY41-1 -> 0.83102282
B43: % of total Venmo TPV | BA43: =BA41/BA$6 -> 0.0001211255 | BB43: =BB41/BB$6 -> 0.0003418297 | BC43: =BC41/BC$6 -> 0.0011249227 | BD43: =BD41/BD$6 -> 0.0014894103 | BE43: =BE41/BE$6 -> 0.0008057167 | BF43: =BF41/BF$9 -> 0.0073529412 | BG43: =BG41/BG$9 -> 0.0125 | BH43: =BH41/BH$9 -> 0.015957447 | BI43: =BI41/BI$9 -> 0.024038462 | BJ43: =BJ41/BJ$6 -> 0.0012056697 | BK43: 0.03 | BL43: =+BK43+1.5% -> 0.045 | BM43: =+BL43+1.5% -> 0.06 | BN43: =+BM43+1.5% -> 0.075 | BO43: =BO41/BO$9 -> 0.054197708 | BP43: =+BN43+1.5% -> 0.09 | BQ43: =+BP43+2.5% -> 0.115 | BR43: =+BQ43+2.5% -> 0.14 | BS43: =+BR43+2.5% -> 0.165 | BT43: =BT41/BT$9 -> 0.13032951 | BU43: =+BS43+1.5% -> 0.18 | BV43: =+BU43+2.5% -> 0.205 | BW43: =+BV43+2.5% -> 0.23 | BX43: =+BW43+2.5% -> 0.255 | BY43: =BY41/BY$9 -> 0.22032951 | BZ43: =+BX43+1.5% -> 0.27 | CA43: =+BZ43+2.5% -> 0.295 | CB43: =+CA43+2.5% -> 0.32 | CC43: =+CB43+2.5% -> 0.345 | CD43: =CD41/CD$9 -> 0.31032951
B44: % of total TPV | BF44: =+BF41/BF6 -> 0.00049682529 | BG44: =+BG41/BG6 -> 0.00092764378 | BH44: =+BH41/BH6 -> 0.0013018121 | BI44: =+BI41/BI6 -> 0.0018865789 | BK44: =+BK41/BK6 -> 0.0027197727 | BL44: =+BL41/BL6 -> 0.0042259131 | BM44: =+BM41/BM6 -> 0.0061362728 | BN44: =+BN41/BN6 -> 0.0069813964 | BP44: =+BP41/BP6 -> 0.0089740952 | BQ44: =+BQ41/BQ6 -> 0.011872476 | BR44: =+BR41/BR6 -> 0.015740439 | BS44: =+BS41/BS6 -> 0.016884973 | BU44: =+BU41/BU6 -> 0.019443873 | BV44: =+BV41/BV6 -> 0.022927643 | BW44: =+BW41/BW6 -> 0.028489052 | BX44: =+BX41/BX6 -> 0.028748684 | BZ44: =+BZ41/BZ6 -> 0.032406455 | CA44: =+CA41/CA6 -> 0.036659376 | CB44: =+CB41/CB6 -> 0.044041046 | CC44: =+CC41/CC6 -> 0.043216975
B45: Assumed Transaction Take Rate | BA45: 0.028 | BB45: =BA45 -> 0.028 | BC45: =BB45 -> 0.028 | BD45: =BC45 -> 0.028 | BE45: =SUMPRODUCT(BA45:BD45,BA41:BD41)/SUM(BA41:BD41) -> 0.028 | BF45: =BD45 -> 0.028 | BG45: =BF45 -> 0.028 | BH45: =BG45 -> 0.028 | BI45: =BH45 -> 0.028 | BJ45: =SUMPRODUCT(BF45:BI45,BF41:BI41)/SUM(BF41:BI41) -> 0.028 | BK45: =+BI45 -> 0.028 | BL45: =BK45 -> 0.028 | BM45: =BL45 -> 0.028 | BN45: =BM45 -> 0.028 | BO45: =SUMPRODUCT(BK45:BN45,BK41:BN41)/SUM(BK41:BN41) -> 0.028 | BP45: =+BN45 -> 0.028 | BQ45: =BP45 -> 0.028 | BR45: =BQ45 -> 0.028 | BS45: =BR45 -> 0.028 | BT45: =SUMPRODUCT(BP45:BS45,BP41:BS41)/SUM(BP41:BS41) -> 0.028 | BU45: =+BS45 -> 0.028 | BV45: =BU45 -> 0.028 | BW45: =BV45 -> 0.028 | BX45: =BW45 -> 0.028 | BY45: =SUMPRODUCT(BU45:BX45,BU41:BX41)/SUM(BU41:BX41) -> 0.028 | BZ45: =+BX45 -> 0.028 | CA45: =BZ45 -> 0.028 | CB45: =CA45 -> 0.028 | CC45: =CB45 -> 0.028 | CD45: =SUMPRODUCT(BZ45:CC45,BZ41:CC41)/SUM(BZ41:CC41) -> 0.028
B46: Assumed Transaction Expense Rate | BA46: 0.008 | BB46: =BA46 -> 0.008 | BC46: =BB46 -> 0.008 | BD46: =BC46 -> 0.008 | BE46: =SUMPRODUCT(BA46:BD46,BA41:BD41)/SUM(BA41:BD41) -> 0.008 | BF46: =BD46 -> 0.008 | BG46: =BE46 -> 0.008 | BH46: =BG46 -> 0.008 | BI46: =BH46 -> 0.008 | BJ46: =SUMPRODUCT(BF46:BI46,BF41:BI41)/SUM(BF41:BI41) -> 0.008 | BK46: =BI46 -> 0.008 | BL46: =BK46 -> 0.008 | BM46: =BL46 -> 0.008 | BN46: =BM46 -> 0.008 | BO46: =SUMPRODUCT(BK46:BN46,BK41:BN41)/SUM(BK41:BN41) -> 0.008 | BP46: =BN46 -> 0.008 | BQ46: =BP46 -> 0.008 | BR46: =BQ46 -> 0.008 | BS46: =BR46 -> 0.008 | BT46: =SUMPRODUCT(BP46:BS46,BP41:BS41)/SUM(BP41:BS41) -> 0.008 | BU46: =BS46 -> 0.008 | BV46: =BU46 -> 0.008 | BW46: =BV46 -> 0.008 | BX46: =BW46 -> 0.008 | BY46: =SUMPRODUCT(BU46:BX46,BU41:BX41)/SUM(BU41:BX41) -> 0.008 | BZ46: =BX46 -> 0.008 | CA46: =BZ46 -> 0.008 | CB46: =CA46 -> 0.008 | CC46: =CB46 -> 0.008 | CD46: =SUMPRODUCT(BZ46:CC46,BZ41:CC41)/SUM(BZ41:CC41) -> 0.008
B47: Implied Transaction Revenue | BA47: =BA41*BA45 -> 0.28 | BB47: =BB41*BB45 -> 0.84 | BC47: =BC41*BC45 -> 2.8 | BD47: =BD41*BD45 -> 4.2 | BE47: =SUM(BA47:BD47) -> 8.12 | BF47: =BF41*BF45 -> 1.4 | BG47: =BG41*BG45 -> 2.8 | BH47: =BH41*BH45 -> 4.2 | BI47: =BI41*BI45 -> 7 | BJ47: =SUM(BF47:BI47) -> 15.4 | BK47: =BK41*BK45 -> 10.08 | BL47: =BL41*BL45 -> 16.632 | BM47: =BM41*BM45 -> 25.2672 | BN47: =BN41*BN45 -> 32.76 | BO47: =SUM(BK47:BN47) -> 84.7392 | BP47: =BP41*BP45 -> 40.824 | BQ47: =BQ41*BQ45 -> 57.3804 | BR47: =BR41*BR45 -> 79.59168 | BS47: =BS41*BS45 -> 97.2972 | BT47: =SUM(BP47:BS47) -> 275.09328 | BU47: =BU41*BU45 -> 106.1424 | BV47: =BV41*BV45 -> 132.97284 | BW47: =BW41*BW45 -> 169.98509 | BX47: =BX41*BX45 -> 195.47892 | BY47: =SUM(BU47:BX47) -> 604.57925 | BZ47: =BZ41*BZ45 -> 206.97768 | CA47: =CA41*CA45 -> 248.75651 | CB47: =CB41*CB45 -> 307.45129 | CC47: =CC41*CC45 -> 343.81292 | CD47: =SUM(BZ47:CC47) -> 1106.9984
B48: Implied Transaction Expense | BA48: =BA41*BA46 -> 0.08 | BB48: =BB41*BB46 -> 0.24 | BC48: =BC41*BC46 -> 0.8 | BD48: =BD41*BD46 -> 1.2 | BE48: =SUM(BA48:BD48) -> 2.32 | BF48: =BF41*BF46 -> 0.4 | BG48: =BG41*BG46 -> 0.8 | BH48: =BH41*BH46 -> 1.2 | BI48: =BI41*BI46 -> 2 | BJ48: =SUM(BF48:BI48) -> 4.4 | BK48: =BK41*BK46 -> 2.88 | BL48: =BL41*BL46 -> 4.752 | BM48: =BM41*BM46 -> 7.2192 | BN48: =BN41*BN46 -> 9.36 | BO48: =SUM(BK48:BN48) -> 24.2112 | BP48: =BP41*BP46 -> 11.664 | BQ48: =BQ41*BQ46 -> 16.3944 | BR48: =BR41*BR46 -> 22.74048 | BS48: =BS41*BS46 -> 27.7992 | BT48: =SUM(BP48:BS48) -> 78.59808 | BU48: =BU41*BU46 -> 30.3264 | BV48: =BV41*BV46 -> 37.99224 | BW48: =BW41*BW46 -> 48.567168 | BX48: =BX41*BX46 -> 55.85112 | BY48: =SUM(BU48:BX48) -> 172.73693 | BZ48: =BZ41*BZ46 -> 59.13648 | CA48: =CA41*CA46 -> 71.073288 | CB48: =CB41*CB46 -> 87.843226 | CC48: =CC41*CC46 -> 98.232264 | CD48: =SUM(BZ48:CC48) -> 316.28526
B50: 4. All Other TPV (Other Merch Svc and On-EBAY) | AK50: =AK6-AK9-AK41-AK25 -> 150066 | AP50: =AP6-AP9-AP41-AP25 -> 185606 | AQ50: =AQ6-AQ9-AQ41-AQ25 -> 52862 | AR50: =AR6-AR9-AR41-AR25 -> 55268 | AS50: =AS6-AS9-AS41-AS25 -> 55984 | AT50: =AT6-AT9-AT41-AT25 -> 62920.62 | AU50: =AU6-AU9-AU41-AU25-AU33 -> 220175.22 | AV50: =AV6-AV9-AV41-AV25 -> 58721 | AW50: =AW6-AW9-AW41-AW25 -> 62358.04 | AX50: =AX6-AX9-AX41-AX25 -> 65207 | AY50: =AY6-AY9-AY41-AY25-AY33 -> 75108.213 | AZ50: =AZ6-AZ9-AZ41-AZ25-AZ33 -> 264510.25 | BA50: =BA6-BA9-BA41-BA25-BA33 -> 71323.336 | BB50: =BB6-BB9-BB41-BB25-BB33 -> 75196.336 | BC50: =BC6-BC9-BC41-BC25-BC33 -> 74474.757 | BD50: =BD6-BD9-BD41-BD25-BD33 -> 84984.901 | BE50: =BE6-BE9-BE41-BE25-BE33 -> 305979.33 | BF50: =BF6-BF9-BF41-BF25-BF33 -> 81559.486 | ... CD50: =CD6-CD9-CD41-CD25-CD33 -> 716064.12
B51: YoY % change | AP51: =AP50/AK50-1 -> 0.23682913 | AU51: =AU50/AP50-1 -> 0.18625057 | AV51: =AV50/AQ50-1 -> 0.11083576 | AW51: =AW50/AR50-1 -> 0.12828472 | AX51: =AX50/AS50-1 -> 0.1647435 | AY51: =AY50/AT50-1 -> 0.19369791 | AZ51: =AZ50/AU50-1 -> 0.20136248 | BA51: =BA50/AV50-1 -> 0.21461378 | BB51: =BB50/AW50-1 -> 0.20588036 | ... CD51: =CD50/BY50-1 -> 0.1239995
B52: % of total TPV | AK52: =AK50/AK$6 -> 1 | AP52: =AP50/AP$6 -> 1 | AQ52: =AQ50/AQ$6 -> 0.98483494 | AR52: =AR50/AR$6 -> 0.97412578 | AS52: =AS50/AS$6 -> 0.96218892 | AT52: =AT50/AT$6 -> 0.95277972 | AU52: =AU50/AU$6 -> 0.93837332 | AV52: =AV50/AV$6 -> 0.93176878 | AW52: =AW50/AW$6 -> 0.92406923 | ... CD52: =CD50/CD$6 -> 0.71328566
B53: Implied Transaction Take Rate | AK53: ='Segment Detail'!AK25 -> 0.033505258 | AP53: ='Segment Detail'!AP25 -> 0.032283439 | AQ53: =AQ55/AQ50 -> 0.031345768 | AR53: =AR55/AR50 -> 0.030433524 | AS53: =AS55/AS50 -> 0.030508717 | AT53: =AT55/AT50 -> 0.030213519 | AU53: =AU55/AU50 -> 0.031556927 | AV53: =AV55/AV50 -> 0.031151547 | AW53: =AW55/AW50 -> 0.029998137 | AX53: =AX55/AX50 -> 0.029061297 | ... CD53: =CD55/CD50 -> 0.025550872 | CE53: <- Sanity Check
B54: Implied Transaction Expense Rate | AK54: ='Quarterly Model'!AK20 -> 0.010115549 | AP54: ='Quarterly Model'!AP20 -> 0.0098865338 | AQ54: =AQ56/AQ50 -> 0.0095353562 | AR54: =AR56/AR50 -> 0.0091480785 | AS54: =AS56/AS50 -> 0.0090722349 | AT54: =AT56/AT50 -> 0.0087643631 | AU54: =AU56/AU50 -> 0.0093971208 | AV54: =AV56/AV50 -> 0.0088060489 | AW54: =AW56/AW50 -> 0.0090786708 | AX54: =AX56/AX50 -> 0.0087823393 | ... CD54: =CD56/CD50 -> 0.010325894 | CE54: <- Sanity Check
B55: Implied Transaction Revenue | AK55: ='Segment Detail'!AK45 -> 5028 | AP55: ='Segment Detail'!AP45 -> 5992 | AQ55: ='Segment Detail'!AQ45-AQ14-AQ30-AQ38-AQ47 -> 1657 | AR55: ='Segment Detail'!AR45-AR14-AR30-AR38-AR47 -> 1682 | AS55: ='Segment Detail'!AS45-AS14-AS30-AS38-AS47 -> 1708 | AT55: ='Segment Detail'!AT45-AT14-AT30-AT38-AT47 -> 1901.0534 | AU55: ='Segment Detail'!AU45-AU14-AU30-AU38-AU47 -> 6948.0534 | AV55: ='Segment Detail'!AV45-AV14-AV30-AV38-AV47 -> 1829.25 | AW55: ='Segment Detail'!AW45-AW14-AW30-AW38-AW47 -> 1870.625 | AX55: ='Segment Detail'!AX45-AX14-AX30-AX38-AX47 -> 1895 | ... CD55: ='Segment Detail'!CD45-CD14-CD30-CD38-CD47 -> 18296.063
B56: Implied Transaction Expense | AK56: ='Quarterly Model'!AK18 -> 1518 | AP56: ='Quarterly Model'!AP18 -> 1835 | AQ56: ='Quarterly Model'!AQ18-AQ15-AQ31-AQ39-AQ48 -> 504.058 | AR56: ='Quarterly Model'!AR18-AR15-AR31-AR39-AR48 -> 505.596 | AS56: ='Quarterly Model'!AS18-AS15-AS31-AS39-AS48 -> 507.9 | AT56: ='Quarterly Model'!AT18-AT15-AT31-AT39-AT48 -> 551.45916 | AU56: ='Quarterly Model'!AU18-AU15-AU31-AU39-AU48 -> 2069.0132 | AV56: ='Quarterly Model'!AV18-AV15-AV31-AV39-AV48 -> 517.1 | AW56: ='Quarterly Model'!AW18-AW15-AW31-AW39-AW48 -> 566.12812 | AX56: ='Quarterly Model'!AX18-AX15-AX31-AX39-AX48 -> 572.67 | ... CD56: ='Quarterly Model'!CD18-CD15-CD31-CD39-CD48 -> 7394.0023
B58: Weighted Average Transaction Take Rate (From Model) | AP58: =SUM(AP55,AP47,AP38,AP30,AP14)/AP$6 -> 0.032283439 | AQ58: =SUM(AQ55,AQ47,AQ38,AQ30,AQ14)/AQ$6 -> 0.031131232 | AR58: =SUM(AR55,AR47,AR38,AR30,AR14)/AR$6 -> 0.030139594 | AS58: =SUM(AS55,AS47,AS38,AS30,AS14)/AS$6 -> 0.030076997 | AT58: =SUM(AT55,AT47,AT38,AT30,AT14)/AT$6 -> 0.02972486 | AU58: =SUM(AU55,AU47,AU38,AU30,AU14)/AU$6 -> 0.030234194 | AV58: =SUM(AV55,AV47,AV38,AV30,AV14)/AV$6 -> 0.030323226 | AW58: =SUM(AW55,AW47,AW38,AW30,AW14)/AW$6 -> 0.029133695 | ... CD58: =SUM(CD55,CD47,CD38,CD30,CD14)/CD$6 -> 0.022324821
B60: Weighted Average Transaction Expense Rate (From Model) | AP60: =SUM(AP56,AP48,AP39,AP31,AP15)/AP$6 -> 0.0098865338 | AQ60: =SUM(AQ56,AQ48,AQ39,AQ31,AQ15)/AQ$6 -> 0.0095759744 | AR60: =SUM(AR56,AR48,AR39,AR31,AR15)/AR$6 -> 0.0092533841 | AS60: =SUM(AS56,AS48,AS39,AS31,AS15)/AS$6 -> 0.0092293414 | AT60: =SUM(AT56,AT48,AT39,AT31,AT15)/AT$6 -> 0.008994685 | AU60: =SUM(AU56,AU48,AU39,AU31,AU15)/AU$6 -> 0.0092484071 | AV60: =SUM(AV56,AV48,AV39,AV31,AV15)/AV$6 -> 0.0091239428 | AW60: =SUM(AW56,AW48,AW39,AW31,AW15)/AW$6 -> 0.009395098 | ... CD60: =SUM(CD56,CD48,CD39,CD31,CD15)/CD$6 -> 0.010048727

Sheet PT
B2: PayPal Holdings Inc. PT Interpolation
B4: Scenario:
C8: Calculated | D8: Weighting
C9: $ | D9: %
B10: DCF Valuation | C10: =DCF!I90 -> 79.567133 | D10: 0.25
B11: PE | C11: =C20 -> 81.895035 | D11: =1-D10 -> 0.75
C12: =+C11 -> 81.895035
B14: PE Valuation | C14: PE Target | D14: Target Implied
B15: CY19 EPS (MS Method) | C15: ='Quarterly Model'!BT105 -> 2.7298345 | D15: =C15 -> 2.7298345
B16: Target Multiple | C16: =CHOOSE(_Switch,C17,C18,C19) -> 30 | D16: =D20/D15 -> 30
B17: Bull | C17: 31
B18: Base | C18: 30
B19: Bear | C19: 21
B20: Price Target (ex Cash) | C20: =C15*C16 -> 81.895035 | D20: =C12 -> 81.895035
B22: Cash per share (after tax) | C22: =('Quarterly Model'!BM220+'Quarterly Model'!BM221+'Quarterly Model'!BM230)*0.85 -> 12452.554
B23: Amount of "excess" | C23: =C22-4000 -> 8452.5539
B24: Value per share | C24: =C23/'Quarterly Model'!BM143 -> 6.9741331
B25: Price Target (Incl Cash) | C25: =C20+C24 -> 88.869168
B27: Current Price | C27: 77
B28: Target | C28: =C25 -> 88.869168
B29: Up/(Down)side | C29: =C28/C27-1 -> 0.15414504
B31: Current Trading Multiple | C31: =C27/C15 -> 28.206838
F36: .

Sheet Presentation
B1: PayPal Holdings, Inc. Financials - Presentation Format
B2: Fiscal Year End: December ($ in millions, except per share data)
B4: INCOME STATEMENT ($ in millions except per share data)
C5: ='Quarterly Model'!AG3 -> 1Q12A | D5: ='Quarterly Model'!AH3 -> 2Q12A | E5: ='Quarterly Model'!AI3 -> 3Q12A | F5: ='Quarterly Model'!AJ3 -> 4Q12A | G5: ='Quarterly Model'!AK3 -> 2012A | H5: ='Quarterly Model'!AL3 -> 1Q13A | I5: ='Quarterly Model'!AM3 -> 2Q13A | J5: ='Quarterly Model'!AN3 -> 3Q13A | ... AZ5: ='Quarterly Model'!CD3 -> 2021E
B7: TPV | G7: ='Segment Detail'!AK6 -> 150066 | H7: ='Segment Detail'!AL6 -> 0 | I7: ='Segment Detail'!AM6 -> 0 | J7: ='Segment Detail'!AN6 -> 0 | K7: ='Segment Detail'!AO6 -> 0 | L7: ='Segment Detail'!AP6 -> 185606 | M7: ='Segment Detail'!AQ6 -> 53676 | N7: ='Segment Detail'!AR6 -> 56736 | ... AZ7: ='Segment Detail'!CD6 -> 1003895.3
B8: YoY % change | H8: ='Segment Detail'!AL7 -> 0 | I8: ='Segment Detail'!AM7 -> 0 | J8: ='Segment Detail'!AN7 -> 0 | K8: ='Segment Detail'!AO7 -> 0 | L8: ='Segment Detail'!AP7 -> 0.23682913 | M8: ='Segment Detail'!AQ7 -> 0 | N8: ='Segment Detail'!AR7 -> 0 | O8: ='Segment Detail'!AS7 -> 0 | ... AZ8: ='Segment Detail'!CD7 -> 0.17
B9: Transaction Take Rate | G9: ='Segment Detail'!AK25 -> 0.033505258 | H9: ='Segment Detail'!AL25 -> 0 | I9: ='Segment Detail'!AM25 -> 0 | J9: ='Segment Detail'!AN25 -> 0 | K9: ='Segment Detail'!AO25 -> 0 | L9: ='Segment Detail'!AP25 -> 0.032283439 | M9: ='Segment Detail'!AQ25 -> 0.031131232 | N9: ='Segment Detail'!AR25 -> 0.030139594 | ... AZ9: ='Segment Detail'!CD25 -> 0.022324821
B10: Total Revenue Take Rate | G10: ='Segment Detail'!AK62 -> 0.037730065 | H10: ='Segment Detail'!AL62 -> #DIV/0! | I10: ='Segment Detail'!AM62 -> #DIV/0! | J10: ='Segment Detail'!AN62 -> #DIV/0! | K10: ='Segment Detail'!AO62 -> #DIV/0! | L10: ='Segment Detail'!AP62 -> 0.03624344 | M10: ='Segment Detail'!AQ62 -> 0.034857292 | N10: ='Segment Detail'!AR62 -> 0.034916103 | ... AZ10: ='Segment Detail'!CD62 -> 0.023758276
B12: ='Quarterly Model'!B8 -> Transaction Revenue | C12: ='Quarterly Model'!AG8 -> 0 | D12: ='Quarterly Model'!AH8 -> 0 | E12: ='Quarterly Model'!AI8 -> 0 | F12: ='Quarterly Model'!AJ8 -> 0 | G12: ='Quarterly Model'!AK8 -> 5028 | H12: ='Quarterly Model'!AL8 -> 0 | I12: ='Quarterly Model'!AM8 -> 0 | J12: ='Quarterly Model'!AN8 -> 0 | ... AZ12: ='Quarterly Model'!CD8 -> 22411.783
B13: ='Quarterly Model'!B9 -> YoY % change | C13: ='Quarterly Model'!AG9 -> 0 | D13: ='Quarterly Model'!AH9 -> 0 | E13: ='Quarterly Model'!AI9 -> 0 | F13: ='Quarterly Model'!AJ9 -> 0 | G13: ='Quarterly Model'!AK9 -> 0 | H13: ='Quarterly Model'!AL9 -> 0 | I13: ='Quarterly Model'!AM9 -> 0 | J13: ='Quarterly Model'!AN9 -> 0 | ... AZ13: ='Quarterly Model'!CD9 -> 0.1556825
