Workbook
Name AdditionalInstructions: IndexInformation!$B$42
Name Address: ImportantDisclosures!$A$2:$A$2
Name ANA: ModPubIndex!$A$7
Name Authors: ImportantDisclosures!$A$7
Name Authors: IndexInformation!$B$18
Name BRO: ModPubIndex!$A$1
Name Cap_IQ_Non_Trans: 'Op Metrics'!$239:$239
Name Cap_IQ_Trans: 'Op Metrics'!$235:$235
Name CashFlowCapitalExpenditureCellular: 0
Name CashFlowCapitalExpenditureOther: 0
Name CashFlowCapitalExpenditurePaging: 0
Name CashFlowCapitalExpenditureTelephone: 0
Name CashFlowCapitalExpenditureWireless: 0
Name CashFlowDividendPaidPreferredStock: 0
Name CopyrightStamp: ImportantDisclosures!$A$27
Name Corinthian_Colleges: '[10]Print '!$B$2:$M$71
Name COU: ModPubIndex!$A$5
Name CQEnd: IndexInformation!$B$31
Name Currency: IndexInformation!$B$24
Name CurrentStockPrice: IndexInformation!$B$23
Name CurrQtrEPS: IndexInformation!$B$29
Name CurrYearEPS: IndexInformation!$B$11
Name CurrYearTotalRevenue: IndexInformation!$B$10
Name CurrYearTotalRevenueActual: IndexInformation!$B$32
Name CUSIP: IndexInformation!$B$20
Name CYEnd: IndexInformation!$B$30
Name Date: ImportantDisclosures!$A$8
Name Deleted: IndexInformation!$B$27
Name Description: IndexInformation!$B$7
Name Discipline: IndexInformation!$B$3
Name DISCIPLINE: ModPubIndex!$A$12
Name DisclosuresText: ImportantDisclosures!$A$22
Name Distribution: IndexInformation!$B$26
Name DistTable: ImportantDisclosures!#REF!
Name DistTablePreamble: ImportantDisclosures!#REF!
Name DOCDAT: ModPubIndex!$A$2
Name DOCTIME: ModPubIndex!$A$3
Name DocType: IndexInformation!$B$5
Name EMAIL_ALERT: ModPubIndex!$A$10
Name EmailAlert: IndexInformation!$B$28
Name EquityAdjustments: 0
Name EquityEmployeeStockOwnershipPlan: 0
Name EquityPaidInCapital: 0
Name EquityTreasuryStock: 0
Name FiveYearGrowthRate: IndexInformation!$B$16
Name FollowingYearEPS: IndexInformation!$B$15
Name FollowingYearTotalRevenue: IndexInformation!$B$14
Name FollowingYearTotalRevenueActual: IndexInformation!$B$34
Name HL: ModPubIndex!$A$8
Name IncomeEPSFullyDiluted: 0
Name IncomeEPSPrimary: 0
Name IncomeEPSRegular: 0
Name IND: ModPubIndex!$A$9
Name Industry: ImportantDisclosures!$A$12
Name IndustryId: IndexInformation!$B$40
Name IndustryRating: ImportantDisclosures!$A$13
Name KeepVersions: IndexInformation!$B$8
Name LanguageCode: IndexInformation!$B$38
Name LastCell: ImportantDisclosures!$A$22
Name LiabilitiesCurrentAccruedLiabilities: 0

Sheet ImportantDisclosures
A2: 1585 Broadway
A3: New York, NY 10036-8293
A4: United States
A5: Tel: +1 (1)212 761 4000
A7: Authors: Toni Kaplan, Jeffrey Goldstein
A8: Date: 26 Apr 2018
A10: Ticker: SPGI.N
A11: Stock Rating: Equal-Weight
A12: Industry: Business & Education Services
A13: Industry View: In-Line
A14: Price as of 26 Apr 2018: 190.25
A15: Target Price: 205
... A126: Equal-weight and Not-Rated to hold and Underweight to sell recommendations, respectively.
B128: Coverage Universe | D128: Investment Banking Clients (IBC) | G128: Other Material Investment Services Clients (MISC)
A129: Stock Rating Category | B129: Count | C129: % of Total | D129: Count | E129: % of Total IBC | F129: % of Rating Category | G129: Count | H129: % of Total Other MISC
A130: Overweight/Buy | B130: 1189 | C130: 0.38 | D130: 315 | E130: 0.41 | F130: 0.26 | G130: 555 | H130: 0.39
A131: Equal-weight/Hold | B131: 1355 | C131: 0.43 | D131: 364 | E131: 0.47 | F131: 0.27 | G131: 644 | H131: 0.45
A132: Not-Rated/Hold | B132: 53 | C132: 0.02 | D132: 4 | E132: 0.01 | F132: 0.08 | G132: 7 | H132: 0
A133: Underweight/Sell | B133: 545 | C133: 0.17 | D133: 84 | E133: 0.11 | F133: 0.15 | G133: 214 | H133: 0.15
A134: Total | B134: 3142 | D134: 767 | G134: 1420
A136: Data include common stock and ADRs currently assigned ratings. Investment Banking Clients are companies
A137: from whom Morgan Stanley received investment banking compensation in the last 12 months. Due to rounding
A138: off of decimals, the percentages provided in the "% of total" column may not add up to exactly 100
A139: percent.
A141: Analyst Stock Ratings
A143: Overweight (O). The stock's total return is expected to exceed the average total return of the analyst's
A144: industry (or industry team's) coverage universe, on a risk-adjusted basis, over the next 12-18 months.
A146: Equal-weight (E). The stock's total return is expected to be in line with the average total return of
A147: the analyst's industry (or industry team's) coverage universe, on a risk-adjusted basis, over the next
A148: 12-18 months.
A150: Not-Rated (NR). Currently the analyst does not have adequate conviction about the stock's total return
A151: relative to the average total return of the analyst's industry (or industry team's) coverage universe,
... A401: © Copyright 2018 Morgan Stanley

Sheet MHFI
B1: 2001 | C1: 2002 | D1: 2003 | E1: 2004 | F1: 2005 | G1: 1Q06 | H1: 2Q06 | I1: 3Q06 | J1: 4Q06 | K1: 2006 | L1: 1Q07 | M1: 2Q07 | N1: 3Q07 | O1: 4Q07 | P1: 2007 | Q1: 1Q08 | R1: 2Q08 | S1: 3Q08 | T1: 4Q08 | U1: 2008 | V1: 1Q09 | W1: 2Q09 | X1: 3Q09 | Y1: 4Q09 | Z1: 2009 | AA1: 1Q10 | AB1: 2Q10 | AC1: 3Q10 | AD1: 4Q10 | AE1: 2010 | AF1: 1Q11 | AG1: 2Q11 | AH1: 3Q11 | AI1: 4Q11 | AJ1: 2011 | AK1: 1Q12 | AL1: 2Q12 | AM1: 3Q12 | AN1: 4Q12 | AO1: 2012 | AP1: 1Q13 | AQ1: 2Q13 | AR1: 3Q13 | AS1: 4Q13 | AT1: 2013 | AU1: 1Q14 | AV1: 2Q14 | AW1: 3Q14 | AX1: 4Q14 | AY1: 2014 | AZ1: 1Q15 | BA1: 2Q15 | BB1: 3Q15 | BC1: 4Q15 | BD1: 2015 | BE1: 1Q16 | BF1: 2Q16 | BG1: 3Q16 | BH1: 4Q16 | BI1: 2016 | BJ1: 1Q17 | BK1: 2Q17 | BL1: 3Q17 | BM1: 4Q17 | BN1: 2017 | BO1: 1Q18E | BP1: 2Q18E | BQ1: 3Q18E | BR1: 4Q18E | BS1: 2018E | BT1: 1Q19E | BU1: 2Q19E | BV1: 3Q19E | BW1: 4Q19E | BX1: 2019E | BY1: 2020E | BZ1: 2021E | CA1: 2022E
A3: 2
DK4: Do not Delete
A6: S&P Global, Inc | CD6: The McGraw-Hill Companies, Inc.
A7: Quarterly Income Statement | CD7: Annual Income Statement
A8: (Values in millions, except per-share amounts) | CB8: CAGR | CD8: (Values in millions, except per-share amounts)
B9: =B1 -> 2001 | C9: =C1 -> 2002 | D9: =D1 -> 2003 | E9: =E1 -> 2004 | F9: =F1 -> 2005 | G9: =G1 -> 1Q06 | H9: =H1 -> 2Q06 | I9: =I1 -> 3Q06 | ... CA9: =CA1 -> 2022E | CB9: 17-'22 | CD9: =A9 | CE9: =B9 -> 2001 | CF9: =C9 -> 2002 | CG9: =D9 -> 2003 | CH9: =E9 -> 2004 | CI9: =F9 -> 2005 | CJ9: =K9 -> 2006 | CK9: =P9 -> 2007 | CL9: =U9 -> 2008 | CM9: =Z9 -> 2009 | CN9: =AE9 -> 2010 | CO9: =AJ9 -> 2011 | CP9: =AO9 -> 2012 | CQ9: =AT9 -> 2013 | CR9: =AY9 -> 2014 | CS9: =BD9 -> 2015 | CT9: =BI9 -> 2016 | CU9: =BN9 -> 2017 | CV9: =BS9 -> 2018E | CW9: =BX9 -> 2019E | CX9: =BY9 -> 2020E | CY9: =BZ9 -> 2021E | CZ9: =CA9 -> 2022E | DB9: NTM
A10: Revenues | CD10: =A10 -> Revenues
A11: Product | B11: =B195 -> 2433.402 | C11: =C195 -> 2389.77 | D11: =D195 -> 2477.026 | E11: =E195 -> 2460.274 | F11: =F195 -> 2536.422 | G11: =G195 -> 302.619 | H11: 567.93 | I11: =I195 -> 1069.092 | J11: =J195 -> 503.142 | K11: =SUM(G11:J11) -> 2442.783 | L11: =L195 -> 312.369 | M11: =M195 -> 605.373 | N11: =N195 -> 1167.288 | O11: =O195 -> 519.402 | P11: =SUM(L11:O11) -> 2604.432 | Q11: =Q195 -> 317.643 | R11: =R195 -> 634.112 | S11: =S195 -> 1136.462 | T11: =T195 -> 494.336 | U11: =SUM(Q11:T11) -> 2582.553 | V11: =V195 -> 289.398 | W11: =W195 -> 525.813 | X11: =X195 -> 1013.213 | Y11: =Y195 -> 533.811 | Z11: =SUM(V11:Y11) -> 2362.235 | AA11: =AA195 -> 310.8 | AB11: =AB195 -> 545 | AC11: =AC195 -> 1058.4 | AD11: =AD195 -> 497.093 | AE11: =SUM(AA11:AD11) -> 2411.293 | AF11: =AF195 -> 298 | AG11: =AG195 -> 523 | AH11: =AH195 -> 940.5 | AI11: =AI195 -> 513.5 | AJ11: =SUM(AF11:AI11) -> 2275 | CD11: =A11 -> Product | CE11: =B11 -> 2433.402 | CF11: =C11 -> 2389.77 | CG11: =D11 -> 2477.026 | CH11: =E11 -> 2460.274 | CI11: =F11 -> 2536.422 | CJ11: =K11 -> 2442.783 | CK11: =P11 -> 2604.432 | CL11: =U11 -> 2582.553 | CM11: =Z11 -> 2362.235 | CN11: =AE11 -> 2411.293 | CO11: =AJ11 -> 2275
A12: Service | B12: =B198 -> 2212.133 | C12: =C198 -> 2250.414 | D12: =D198 -> 2413.294 | E12: =E198 -> 2790.264 | F12: =F198 -> 3467.22 | G12: =G198 -> 838.06 | H12: =H198 -> 959.613 | I12: =I198 -> 923.478 | J12: =J198 -> 1091.204 | K12: =SUM(G12:J12) -> 3812.355 | L12: =L198 -> 984.049 | M12: =M198 -> 1112.806 | N12: =N198 -> 1020.708 | O12: =O198 -> 1050.286 | P12: =SUM(L12:O12) -> 4167.849 | Q12: =Q198 -> 900.228 | R12: =R198 -> 1039.113 | S12: =S198 -> 912.079 | T12: =T198 -> 921.082 | U12: =SUM(Q12:T12) -> 3772.502 | V12: =V198 -> 858.809 | W12: =W198 -> 939.367 | X12: =X198 -> 862.69 | Y12: =Y198 -> 928.681 | Z12: =SUM(V12:Y12) -> 3589.547 | AA12: =AA198 -> 879.6 | AB12: =AB198 -> 929.1 | AC12: =AC198 -> 897.8 | AD12: =AD198 -> 1050.538 | AE12: =SUM(AA12:AD12) -> 3757.038 | AF12: =AF198 -> 963 | AG12: =AG198 -> 1034 | AH12: =AH198 -> 967.5 | AI12: =AI198 -> 1006.5 | AJ12: =SUM(AF12:AI12) -> 3971 | CD12: =A12 -> Service | CE12: =B12 -> 2212.133 | CF12: =C12 -> 2250.414 | CG12: =D12 -> 2413.294 | CH12: =E12 -> 2790.264 | CI12: =F12 -> 3467.22 | CJ12: =K12 -> 3812.355 | CK12: =P12 -> 4167.849 | CL12: =U12 -> 3772.502 | CM12: =Z12 -> 3589.547 | CN12: =AE12 -> 3757.038 | CO12: =AJ12 -> 3971
B13: ______ | C13: ______ | D13: ______ | E13: ______ | F13: ______ | G13: ______ | H13: ______ | I13: ______ | J13: ______ | K13: ______ | L13: ______ | M13: ______ | N13: ______ | O13: ______ | P13: ______ | Q13: ______ | R13: ______ | S13: ______ | T13: ______ | U13: ______ | V13: ______ | W13: ______ | X13: ______ | Y13: ______ | Z13: ______ | AA13: ______ | AB13: ______ | AC13: ______ | AD13: ______ | AE13: ______ | AF13: ______ | AG13: ______ | AH13: ______ | AI13: ______ | AJ13: ______ | AK13: ______ | AL13: ______ | AM13: ______ | AN13: ______ | AO13: ______ | AP13: ______ | AQ13: ______ | AR13: ______ | AS13: ______ | AT13: ______ | AU13: ______ | AV13: ______ | AW13: ______ | AX13: ______ | AY13: ______ | AZ13: ______ | BA13: ______ | BB13: ______ | BC13: ______ | BD13: ______ | BE13: ______ | BF13: ______ | BG13: ______ | BH13: ______ | BI13: ______ | BN13: ______ | BS13: ______ | BX13: ______ | BY13: ______ | BZ13: ______ | CA13: ______ | CE13: ______ | CF13: ______ | CG13: ______ | CH13: ______ | CI13: ______ | CJ13: ______ | CK13: ______ | CL13: ______ | CM13: ______ | CN13: ______ | CO13: ______ | CP13: ______ | CQ13: ______ | CR13: ______ | CS13: ______ | CT13: ______ | CU13: ______ | CV13: ______ | CW13: ______ | CX13: ______ | CY13: ______ | CZ13: ______
A14: Total Revenues | B14: =SUM(B11:B12) -> 4645.535 | C14: =SUM(C11:C12) -> 4640.184 | D14: =SUM(D11:D12) -> 4890.32 | E14: =SUM(E11:E12) -> 5250.538 | F14: =SUM(F11:F12) -> 6003.642 | G14: =SUM(G11:G12) -> 1140.679 | H14: =SUM(H11:H12) -> 1527.543 | I14: =SUM(I11:I12) -> 1992.57 | ... X14: =SUM(X11:X12) -> 1875.903 | Y14: 1462.492 | Z14: =SUM(Z11:Z12) -> 5951.782 | AA14: =SUM(AA11:AA12) -> 1190.4 | AB14: =SUM(AB11:AB12) -> 1474.1 | AC14: =SUM(AC11:AC12) -> 1956.2 | AD14: =SUM(AD11:AD12) -> 1547.631 | AE14: =SUM(AE11:AE12) -> 6168.331 | AF14: =AF210 -> 1261 | AG14: =AG210 -> 1557 | AH14: =AH210 -> 1908 | AI14: =AI210 -> 1004 | AJ14: =SUM(AJ11:AJ12) -> 6246 | AK14: =AK210 -> 1035 | AL14: =AL210 -> 1072 | AM14: =AM210 -> 1116 | AN14: =AN210 -> 1227 | AO14: =SUM(AK14:AN14) -> 4450 | AP14: =AP210 -> 1181 | AQ14: =AQ210 -> 1250 | AR14: =AR210 -> 1152 | AS14: =AS210 -> 1206 | AT14: =SUM(AP14:AS14) -> 4789 | AU14: =AU210 -> 1196 | AV14: =AV210 -> 1302 | AW14: =AW210 -> 1263 | AX14: =AX210 -> 1290 | AY14: =SUM(AU14:AX14) -> 5051 | AZ14: =AZ210 -> 1273 | BA14: =BA210 -> 1342 | BB14: =BB210 -> 1324 | BC14: =BC210 -> 1374 | BD14: =SUM(AZ14:BC14) -> 5313 | BE14: =BE210 -> 1341 | BF14: =BF210 -> 1482 | BG14: =BG210 -> 1439 | BH14: =BH210 -> 1399 | BI14: =SUM(BE14:BH14) -> 5661 | BJ14: =BJ210 -> 1453 | BK14: =BK210 -> 1509 | BL14: =BL210 -> 1513 | BM14: =BM210 -> 1589 | BN14: =SUM(BJ14:BM14) -> 6064 | BO14: =BO210 -> 1567 | BP14: ='Op Metrics'!BP30 -> 1640.3822 | BQ14: ='Op Metrics'!BQ30 -> 1623.3294 | BR14: ='Op Metrics'!BR30 -> 1671.1382 | BS14: =SUM(BO14:BR14) -> 6501.8499 | BT14: ='Op Metrics'!BT30 -> 1646.4317 | BU14: ='Op Metrics'!BU30 -> 1737.365 | BV14: ='Op Metrics'!BV30 -> 1721.2878 | BW14: ='Op Metrics'!BW30 -> 1770.9532 | BX14: =SUM(BT14:BW14) -> 6876.0376 | BY14: ='Op Metrics'!BY30 -> 7231.5258 | BZ14: ='Op Metrics'!BZ30 -> 7608.3789 | CA14: ='Op Metrics'!CA30 -> 7964.8548 | CB14: =(CA14/BN14)^(1/5)-1 -> 0.056048183 | CD14: =A14 -> Total Revenues | CE14: =B14 -> 4645.535 | CF14: =C14 -> 4640.184 | CG14: =D14 -> 4890.32 | CH14: =E14 -> 5250.538 | CI14: =F14 -> 6003.642 | CJ14: =K14 -> 6255.138 | CK14: =P14 -> 6772.281 | CL14: =U14 -> 6355.055 | CM14: =Z14 -> 5951.782 | CN14: =AE14 -> 6168.331 | CO14: =AJ14 -> 6246 | CP14: =AO14 -> 4450 | CQ14: =AT14 -> 4789 | CR14: =AY14 -> 5051 | CS14: =BD14 -> 5313 | CT14: =BI14 -> 5661 | CU14: =BN14 -> 6064 | CV14: =BS14 -> 6501.8499 | CW14: =BX14 -> 6876.0376 | CX14: =BY14 -> 7231.5258 | CY14: =BZ14 -> 7608.3789 | CZ14: =CA14 -> 7964.8548 | DB14: =SUM(BO14,BP14,BQ14,BR14) -> 6501.8499
A15: Annual Growth | C15: =C14/B14-1 -> -0.0011518587 | D15: =D14/C14-1 -> 0.053906483 | E15: =E14/D14-1 -> 0.073659392 | F15: =F14/E14-1 -> 0.14343368 | K15: =K14/F14-1 -> 0.041890572 | L15: =L14/G14-1 -> 0.13653184 | M15: =M14/H14-1 -> 0.12479911 | N15: =N14/I14-1 -> 0.098077357 | O15: =O14/J14-1 -> -0.015465903 | P15: =P14/K14-1 -> 0.082674915 | Q15: =Q14/L14-1 -> -0.060587712 | R15: =R14/M14-1 -> -0.026163747 | ... BX15: =BX14/BS14-1 -> 0.057550966 | BY15: =BY14/BX14-1 -> 0.051699566 | BZ15: =BZ14/BY14-1 -> 0.052112529 | CA15: =CA14/BZ14-1 -> 0.046853066 | CD15: =A15 -> Annual Growth | CE15: =B15 -> 0 | CF15: =C15 -> -0.0011518587 | CG15: =D15 -> 0.053906483 | CH15: =E15 -> 0.073659392 | CI15: =F15 -> 0.14343368 | CJ15: =K15 -> 0.041890572 | CK15: =P15 -> 0.082674915 | CL15: =U15 -> -0.061607898 | CM15: =Z15 -> -0.063457043 | CN15: =AE15 -> 0.036383893 | CO15: =AJ15 -> 0.012591575 | CP15: =AO15 -> -0.28754403 | CQ15: =AT15 -> 0.076179775 | CR15: =AY15 -> 0.054708707 | CS15: =BD15 -> 0.051870917 | CT15: =BI15 -> 0.065499718 | CU15: =BN15 -> 0.071188836 | CV15: =BS15 -> 0.072204798 | CW15: =BX15 -> 0.057550966 | CX15: =BY15 -> 0.051699566 | CY15: =BZ15 -> 0.052112529 | CZ15: =CA15 -> 0.046853066
A17: Operating-Related Expenses | CD17: =A17 -> Operating-Related Expenses
A18: Product | B18: =B214 -> 1223.658 | C18: =C214 -> 1166.888 | D18: =D214 -> 1189.573 | E18: =E214 -> 1120.842 | F18: =F214 -> 1092.159 | G18: =G214 -> 172.109 | H18: =H214 -> 261.889 | I18: =I214 -> 407.728 | J18: =J214 -> 250.583 | K18: =SUM(G18:J18) -> 1092.309 | L18: =L214 -> 170.978 | M18: =M214 -> 265.168 | N18: =N214 -> 439.928 | O18: =O214 -> 253.445 | P18: =SUM(L18:O18) -> 1129.519 | Q18: =Q214 -> 182.046 | R18: =R214 -> 278.22 | S18: =S214 -> 453.798 | T18: =T214 -> 267.258 | U18: =SUM(Q18:T18) -> 1181.322 | V18: =V214 -> 174.273 | W18: =W214 -> 268.235 | X18: =X214 -> 438.405 | Y18: =Y214 -> 251.389 | Z18: =SUM(V18:Y18) -> 1132.302 | AA18: =AA214 -> 173 | AB18: =AB214 -> 259.1 | AC18: =AC214 -> 408.4 | AD18: =AD214 -> 239.592 | AE18: =SUM(AA18:AD18) -> 1080.092 | AF18: =AF214 -> 173 | AG18: =AG214 -> 239 | AH18: =AH214 -> 374.5 | AI18: =AI214 -> 221.5 | AJ18: =SUM(AF18:AI18) -> 1008 | CD18: =A18 -> Product | CE18: =B18 -> 1223.658 | CF18: =C18 -> 1166.888 | CG18: =D18 -> 1189.573 | CH18: =E18 -> 1120.842 | CI18: =F18 -> 1092.159 | CJ18: =K18 -> 1092.309 | CK18: =P18 -> 1129.519 | CL18: =U18 -> 1181.322 | CM18: =Z18 -> 1132.302 | CN18: =AE18 -> 1080.092 | CO18: =AJ18 -> 1008
A19: Service | B19: =B217 -> 881.115 | C19: =C217 -> 814.423 | D19: =D217 -> 828.877 | E19: =E217 -> 925.803 | F19: =F217 -> 1224.175 | G19: =G217 -> 309.376 | H19: =H217 -> 324.587 | I19: =I217 -> 304.529 | J19: =J217 -> 356.446 | K19: =SUM(G19:J19) -> 1294.938 | L19: =L217 -> 333.404 | M19: =M217 -> 369.633 | N19: =N217 -> 326.963 | O19: =O217 -> 368.081 | P19: =SUM(L19:O19) -> 1398.081 | Q19: =Q217 -> 326.265 | R19: =R217 -> 368.934 | S19: =S217 -> 301.29 | T19: =T217 -> 340.619 | U19: =SUM(Q19:T19) -> 1337.108 | V19: =V217 -> 314.666 | W19: =W217 -> 314.27 | X19: =X217 -> 297.475 | Y19: =Y217 -> 327.294 | Z19: =SUM(V19:Y19) -> 1253.705 | AA19: =AA217 -> 303.2 | AB19: =AB217 -> 301.8 | AC19: =AC217 -> 299.6 | AD19: =AD217 -> 361.336 | AE19: =SUM(AA19:AD19) -> 1265.936 | AF19: =AF217 -> 330 | AG19: =AG217 -> 354 | AH19: =AH217 -> 336.6 | AI19: =AI217 -> 371.4 | AJ19: =SUM(AF19:AI19) -> 1392 | CD19: =A19 -> Service | CE19: =B19 -> 881.115 | CF19: =C19 -> 814.423 | CG19: =D19 -> 828.877 | CH19: =E19 -> 925.803 | CI19: =F19 -> 1224.175 | CJ19: =K19 -> 1294.938 | CK19: =P19 -> 1398.081 | CL19: =U19 -> 1337.108 | CM19: =Z19 -> 1253.705 | CN19: =AE19 -> 1265.936 | CO19: =AJ19 -> 1392
B20: ______ | C20: ______ | D20: ______ | E20: ______ | F20: ______ | G20: ______ | H20: ______ | I20: ______ | J20: ______ | K20: ______ | L20: ______ | M20: ______ | N20: ______ | O20: ______ | P20: ______ | Q20: ______ | R20: ______ | S20: ______ | T20: ______ | U20: ______ | V20: ______ | W20: ______ | X20: ______ | Y20: ______ | Z20: ______ | AA20: ______ | AB20: ______ | AC20: ______ | AD20: ______ | AE20: ______ | AF20: ______ | AG20: ______ | AH20: ______ | AI20: ______ | AJ20: ______ | AK20: ______ | AL20: ______ | AM20: ______ | AN20: ______ | AO20: ______ | AP20: ______ | AQ20: ______ | AR20: ______ | AS20: ______ | AT20: ______ | AU20: ______ | AV20: ______ | AW20: ______ | AX20: ______ | AY20: ______ | AZ20: ______ | BA20: ______ | BB20: ______ | BC20: ______ | BD20: ______ | BE20: ______ | BF20: ______ | BG20: ______ | BH20: ______ | BI20: ______ | BJ20: ______ | BK20: ______ | BL20: ______ | BM20: ______ | BN20: ______ | BO20: ______ | BP20: ______ | BQ20: ______ | BR20: ______ | BS20: ______ | BT20: ______ | BU20: ______ | BV20: ______ | BW20: ______ | BX20: ______ | BY20: ______ | BZ20: ______ | CA20: ______ | CE20: ______ | CF20: ______ | CG20: ______ | CH20: ______ | CI20: ______ | CJ20: ______ | CK20: ______ | CL20: ______ | CM20: ______ | CN20: ______ | CO20: ______ | CP20: ______ | CQ20: ______ | CR20: ______ | CS20: ______ | CT20: ______ | CU20: ______ | CV20: ______ | CW20: ______ | CX20: ______ | CY20: ______ | CZ20: ______
A21: Total Operating-Related Expenses | B21: =SUM(B18:B19) -> 2104.773 | C21: =SUM(C18:C19) -> 1981.311 | D21: =SUM(D18:D19) -> 2018.45 | E21: =SUM(E18:E19) -> 2046.645 | F21: =SUM(F18:F19) -> 2316.334 | G21: =SUM(G18:G19) -> 481.485 | H21: =SUM(H18:H19) -> 586.476 | I21: =SUM(I18:I19) -> 712.257 | ... AE21: =SUM(AE18:AE19) -> 2346.028 | AF21: =AF220 -> 503 | AG21: =AG220 -> 593 | AH21: =AH220 -> 711 | AI21: =AI220 -> 593 | AJ21: =SUM(AF21:AI21) -> 2400 | AK21: =AK220 -> 361 | AL21: =AL220 -> 351 | AM21: =AM220 -> 367 | AN21: =AN220 -> 407 | AO21: =SUM(AK21:AN21) -> 1486 | AP21: =AP220 -> 374 | AQ21: =AQ220 -> 395 | AR21: =AR220 -> 371 | AS21: =AS220 -> 424 | AT21: =SUM(AP21:AS21) -> 1564 | AU21: =AU220 -> 411 | AV21: =AV220 -> 420 | AW21: =AW220 -> 399 | AX21: =AX220 -> 397 | AY21: =SUM(AU21:AX21) -> 1627 | AZ21: =AZ220 -> 410 | BA21: =BA220 -> 406 | BB21: =BB220 -> 419 | BC21: =BC220 -> 437 | BD21: =SUM(AZ21:BC21) -> 1672 | BE21: =BE220 -> 457 | BF21: =BF220 -> 469 | BG21: =BG220 -> 438 | BH21: =BH220 -> 405 | BI21: =SUM(BE21:BH21) -> 1769 | BJ21: =BJ220 -> 411 | BK21: =BK220 -> 449 | BL21: =BL220 -> 421 | BM21: =BM220 -> 432 | BN21: =SUM(BJ21:BM21) -> 1713 | BO21: =BO220 -> 439 | BP21: =BP220 -> 488.09252 | BQ21: =BQ220 -> 451.69973 | BR21: =BR220 -> 454.33085 | BS21: =SUM(BO21:BR21) -> 1833.1231 | BT21: =BT220 -> 461.25305 | BU21: =BU220 -> 516.94955 | BV21: =BV220 -> 478.95713 | BW21: =BW220 -> 481.46745 | BX21: =SUM(BT21:BW21) -> 1938.6272 | BY21: =BY220 -> 2038.8534 | BZ21: =BZ220 -> 2145.1032 | CA21: =CA220 -> 2245.6078 | CD21: =A21 -> Total Operating-Related Expenses | CE21: =B21 -> 2104.773 | CF21: =C21 -> 1981.311 | CG21: =D21 -> 2018.45 | CH21: =E21 -> 2046.645 | CI21: =F21 -> 2316.334 | CJ21: =K21 -> 2387.247 | CK21: =P21 -> 2527.6 | CL21: =U21 -> 2518.43 | CM21: =Z21 -> 2386.007 | CN21: =AE21 -> 2346.028 | CO21: =AJ21 -> 2400 | CP21: =AO21 -> 1486 | CQ21: =AT21 -> 1564 | CR21: =AY21 -> 1627 | CS21: =BD21 -> 1672 | CT21: =BI21 -> 1769 | CU21: =BN21 -> 1713 | CV21: =BS21 -> 1833.1231 | CW21: =BX21 -> 1938.6272 | CX21: =BY21 -> 2038.8534 | CY21: =BZ21 -> 2145.1032 | CZ21: =CA21 -> 2245.6078 | DB21: =SUM(BO21,BP21,BQ21,BR21) -> 1833.1231
A22: % of Total Revenue | B22: =B21/B14 -> 0.4530744 | C22: =C21/C14 -> 0.42698975 | D22: =D21/D14 -> 0.41274395 | E22: =E21/E14 -> 0.3897972 | F22: =F21/F14 -> 0.38582147 | G22: =G21/G14 -> 0.42210385 | H22: =H21/H14 -> 0.3839342 | I22: =I21/I14 -> 0.35745645 | ... CA22: =CA21/CA14 -> 0.28193958 | CD22: =A22 -> % of Total Revenue | CE22: =B22 -> 0.4530744 | CF22: =C22 -> 0.42698975 | CG22: =D22 -> 0.41274395 | CH22: =E22 -> 0.3897972 | CI22: =F22 -> 0.38582147 | CJ22: =K22 -> 0.38164578 | CK22: =P22 -> 0.37322728 | CL22: =U22 -> 0.39628768 | CM22: =Z22 -> 0.40088952 | CN22: =AE22 -> 0.38033432 | CO22: =AJ22 -> 0.38424592 | CP22: =AO22 -> 0.33393258 | CQ22: =AT22 -> 0.32658175 | CR22: =AY22 -> 0.32211443 | CS22: =BD22 -> 0.31469979 | CT22: =BI22 -> 0.31248896 | CU22: =BN22 -> 0.28248681 | CV22: =BS22 -> 0.2819387 | CW22: =BX22 -> 0.28193958 | CX22: =BY22 -> 0.28193958 | CY22: =BZ22 -> 0.28193958 | CZ22: =CA22 -> 0.28193958 | DB22: =DB21/$DB$14 -> 0.2819387
A23: Selling and general expenses | B23: =B224 -> 1700.533 | C23: =C224 -> 1634.533 | D23: =D224 -> 1766.549 | E23: =E224 -> 1904.556 | F23: =F224 -> 2149.195 | G23: =G224 -> 480.23 | H23: =H224 -> 540.241 | I23: =I224 -> 609.679 | J23: =J224 -> 626.2 | K23: =SUM(G23:J23) -> 2256.35 | L23: =L224 -> 536.643 | M23: =M224 -> 587.687 | N23: =N224 -> 644.545 | O23: =O224 -> 625.309 | P23: =SUM(L23:O23) -> 2394.184 | Q23: =Q224 -> 516.773 | R23: =R224 -> 594.135 | S23: =S224 -> 573.548 | T23: =T224 -> 525.739 | U23: =SUM(Q23:T23) -> 2210.195 | V23: =V224 -> 491.311 | W23: =W224 -> 530.926 | X23: =X224 -> 546.961 | Y23: =Y224 -> 567.053 | Z23: =SUM(V23:Y23) -> 2136.251 | AA23: =AA224 -> 488 | AB23: =AB224 -> 547.7 | AC23: =AC224 -> 597.6 | AD23: =AD224 -> 602.703 | AE23: =SUM(AA23:AD23) -> 2236.003 | AF23: =AF224 -> 503 | AG23: =AG224 -> 580 | AH23: =AH224 -> 552.2 | AI23: =AI224 -> 128.9 | AJ23: =SUM(AF23:AI23) -> 1764.1 | AK23: =AK224 -> 332 | AL23: =AL224 -> 340 | AM23: =AM224 -> 354 | AN23: =AN224 -> 464 | AO23: =SUM(AK23:AN23) -> 1490 | AP23: =AP224 -> 373 | AQ23: =AQ224 -> 374 | AR23: =AR224 -> 388 | AS23: =AS224 -> 364 | AT23: =SUM(AP23:AS23) -> 1499 | AU23: =AU224 -> 331.5 | AV23: =AV224 -> 364.5 | AW23: =AW224 -> 355 | AX23: =AX224 -> 415 | AY23: =SUM(AU23:AX23) -> 1466 | AZ23: =772-'Op Metrics'!AZ140-AZ34-AZ21 -> 335 | BA23: =771-'Op Metrics'!BA140-BA34-BA21 -> 362 | BB23: =914-'Op Metrics'!BB140-BB34-BB21 -> 339 | BC23: =950-'Op Metrics'!BC140-BC34-BC21 -> 406 | BD23: =SUM(AZ23:BC23) -> 1442 | BE23: =829-'Op Metrics'!BE140-BE34-BE21 -> 315 | BF23: =831-'Op Metrics'!BF140-BF34-BF21 -> 339 | BG23: =813-'Op Metrics'!BG140-BG34-BG21-721 -> 340 | BH23: =921-'Op Metrics'!BH140-BH34-BH21-379 -> 383 | BI23: =SUM(BE23:BH23) -> 1377 | BJ23: =805-'Op Metrics'!BJ140-BJ34-BJ21 -> 334 | BK23: =832-'Op Metrics'!BK140-BK34-BK21 -> 325 | BL23: =855-'Op Metrics'!BL140-BL34-BL21 -> 369 | BM23: =961-'Op Metrics'!BM140-BM34-BM21 -> 384 | BN23: =SUM(BJ23:BM23) -> 1412 | BO23: =856-'Op Metrics'!BO140-BO34-BO21 -> 372 | BP23: =BP224 -> 359.36113 | BQ23: =BQ224 -> 397.53765 | BR23: =BR224 -> 413.21026 | BS23: =SUM(BO23:BR23) -> 1542.109 | BT23: =BT224 -> 370.06454 | BU23: =BU224 -> 353.38836 | BV23: =BV224 -> 394.31479 | BW23: =BW224 -> 408.23157 | BX23: =SUM(BT23:BW23) -> 1525.9992 | BY23: =BY224 -> 1563.2314 | BZ23: =BZ224 -> 1594.0943 | CA23: =CA224 -> 1624.7035 | CD23: =A23 -> Selling and general expenses | CE23: =B23 -> 1700.533 | CF23: =C23 -> 1634.533 | CG23: =D23 -> 1766.549 | CH23: =E23 -> 1904.556 | CI23: =F23 -> 2149.195 | CJ23: =K23 -> 2256.35 | CK23: =P23 -> 2394.184 | CL23: =U23 -> 2210.195 | CM23: =Z23 -> 2136.251 | CN23: =AE23 -> 2236.003 | CO23: =AJ23 -> 1764.1 | CP23: =AO23 -> 1490 | CQ23: =AT23 -> 1499 | CR23: =AY23 -> 1466 | CS23: =BD23 -> 1442 | CT23: =BI23 -> 1377 | CU23: =BN23 -> 1412 | CV23: =BS23 -> 1542.109 | CW23: =BX23 -> 1525.9992 | CX23: =BY23 -> 1563.2314 | CY23: =BZ23 -> 1594.0943 | CZ23: =CA23 -> 1624.7035 | DB23: =SUM(BO23,BP23,BQ23,BR23) -> 1542.109
A24: % of Total Revenue | B24: =B23/B14 -> 0.36605752 | C24: =C23/C14 -> 0.35225607 | D24: =D23/D14 -> 0.36123383 | E24: =E23/E14 -> 0.3627354 | F24: =F23/F14 -> 0.35798187 | G24: =G23/G14 -> 0.42100363 | H24: =H23/H14 -> 0.35366664 | I24: =I23/I14 -> 0.3059762 | ... CA24: =CA23/CA14 -> 0.20398408 | CD24: =A24 -> % of Total Revenue | CE24: =B24 -> 0.36605752 | CF24: =C24 -> 0.35225607 | CG24: =D24 -> 0.36123383 | CH24: =E24 -> 0.3627354 | CI24: =F24 -> 0.35798187 | CJ24: =K24 -> 0.36071946 | CK24: =P24 -> 0.35352697 | CL24: =U24 -> 0.34778535 | CM24: =Z24 -> 0.35892628 | CN24: =AE24 -> 0.36249725 | CO24: =AJ24 -> 0.28243676 | CP24: =AO24 -> 0.33483146 | CQ24: =AT24 -> 0.31300898 | CR24: =AY24 -> 0.29023956 | CS24: =BD24 -> 0.27140975 | CT24: =BI24 -> 0.24324324 | CU24: =BN24 -> 0.2328496 | CV24: =BS24 -> 0.23718004 | CW24: =BX24 -> 0.22193003 | CX24: =BY24 -> 0.21616896 | CY24: =BZ24 -> 0.20951826 | CZ24: =CA24 -> 0.20398408 | DB24: =DB23/$DB$14 -> 0.23718004
A26: Other Income/ (Expense) | B26: 10.256 | C26: =18.66+14.5 -> 33.16 | D26: =147.85-131.3 -> 16.55 | E26: 0 | F26: =1.236-1.236 -> 0 | G26: 0 | H26: 0 | I26: 0 | J26: =0-SUM(G26:I26) -> 0 | K26: =SUM(G26:J26) -> 0 | L26: =17.305-17.305 -> 0 | M26: 0 | N26: 0 | O26: =17.305-SUM(L26:N26) -> 17.305 | P26: =SUM(L26:O26) -> 17.305 | Q26: 0 | R26: 0 | S26: 0 | T26: =0-SUM(Q26:S26) -> 0 | U26: =SUM(Q26:T26) -> 0 | V26: 0 | W26: =-13.849+13.849 -> 0 | X26: 0 | Y26: =-3.304+(13.849-0.4)-SUM(V26:X26) -> 10.145 | Z26: =SUM(V26:Y26) -> 10.145 | AA26: 0 | AB26: 0 | AC26: =11.1-7.3-3.8 -> 0 | AD26: =11.058-11.058-SUM(AA26:AC26) -> 0 | AE26: =SUM(AA26:AD26) -> 0 | AF26: 0 | AG26: 13 | AH26: 0 | AI26: =13-SUM(AF26:AH26) -> 0 | AJ26: =SUM(AF26:AI26) -> 13 | AK26: 0 | AL26: 0 | AM26: 0 | AN26: =52-SUM(AK26:AM26) -> 52 | AO26: =SUM(AK26:AN26) -> 52 | AP26: 0 | AQ26: 0 | AR26: 24 | AS26: =-12-SUM(AP26:AR26) -> -36 | AT26: =SUM(AP26:AS26) -> -12 | AU26: 0 | AV26: -9 | AW26: 0 | AX26: 0 | AY26: =SUM(AU26:AX26) -> -9 | AZ26: 0 | BA26: =11 -> 11 | BB26: 0 | BC26: 0 | BD26: =SUM(AZ26:BC26) -> 11 | BE26: 0 | BF26: 0 | BG26: 0 | BH26: 0 | BI26: =SUM(BE26:BH26) -> 0 | BJ26: 0 | BK26: 0 | BL26: 0 | BM26: 0 | BN26: =SUM(BJ26:BM26) -> 0 | BO26: 0 | BP26: 0 | BQ26: 0 | BR26: 0 | BS26: =SUM(BO26:BR26) -> 0 | BT26: 0 | BU26: 0 | BV26: 0 | BW26: 0 | BX26: =SUM(BT26:BW26) -> 0 | BY26: 0 | BZ26: 0 | CA26: 0 | CD26: =A26 -> Other Income/ (Expense) | CE26: =B26 -> 10.256 | CF26: =C26 -> 33.16 | CG26: =D26 -> 16.55 | CH26: =E26 -> 0 | CI26: =F26 -> 0 | CJ26: =K26 -> 0 | CK26: =P26 -> 17.305 | CL26: =U26 -> 0 | CM26: =Z26 -> 10.145 | CN26: =AE26 -> 0 | CO26: =AJ26 -> 13 | CP26: =AO26 -> 52 | CQ26: =AT26 -> -12 | CR26: =AY26 -> -9 | CS26: =BD26 -> 11 | CT26: =BI26 -> 0 | CU26: =BN26 -> 0 | CV26: =BS26 -> 0 | CW26: =BX26 -> 0 | CX26: =BY26 -> 0 | CY26: =BZ26 -> 0 | CZ26: =CA26 -> 0 | DB26: =SUM(BO26,BP26,BQ26,BR26) -> 0
B27: ______ | C27: ______ | D27: ______ | E27: ______ | F27: ______ | G27: ______ | H27: ______ | I27: ______ | J27: ______ | K27: ______ | L27: ______ | M27: ______ | N27: ______ | O27: ______ | P27: ______ | Q27: ______ | R27: ______ | S27: ______ | T27: ______ | U27: ______ | V27: ______ | W27: ______ | X27: ______ | Y27: ______ | Z27: ______ | AA27: ______ | AB27: ______ | AC27: ______ | AD27: ______ | AE27: ______ | AF27: ______ | AG27: ______ | AH27: ______ | AI27: ______ | AJ27: ______ | AK27: ______ | AL27: ______ | AM27: ______ | AN27: ______ | AO27: ______ | AP27: ______ | AQ27: ______ | AR27: ______ | AS27: ______ | AT27: ______ | AU27: ______ | AV27: ______ | AW27: ______ | AX27: ______ | AY27: ______ | AZ27: ______ | BA27: ______ | BB27: ______ | BC27: ______ | BD27: ______ | BE27: ______ | BF27: ______ | BG27: ______ | BH27: ______ | BI27: ______ | BJ27: ______ | BK27: ______ | BL27: ______ | BM27: ______ | BN27: ______ | BO27: ______ | BP27: ______ | BQ27: ______ | BR27: ______ | BS27: ______ | BT27: ______ | BU27: ______ | BV27: ______ | BW27: ______ | BX27: ______ | BY27: ______ | BZ27: ______ | CA27: ______ | CE27: ______ | CF27: ______ | CG27: ______ | CH27: ______ | CI27: ______ | CJ27: ______ | CK27: ______ | CL27: ______ | CM27: ______ | CN27: ______ | CO27: ______ | CP27: ______ | CQ27: ______ | CR27: ______ | CS27: ______ | CT27: ______ | CU27: ______ | CV27: ______ | CW27: ______ | CX27: ______ | CY27: ______ | CZ27: ______
A28: Total Expenses | B28: =B23+B21-B26 -> 3795.05 | C28: =C23+C21-C26 -> 3582.684 | D28: =D23+D21-D26 -> 3768.449 | E28: =E23+E21-E26 -> 3951.201 | F28: =F23+F21-F26 -> 4465.529 | G28: =G23+G21-G26 -> 961.715 | H28: =H23+H21-H26 -> 1126.717 | I28: =I23+I21-I26 -> 1321.936 | ... AN28: =AN23+AN21-AN26 -> 819 | AO28: =SUM(AK28:AN28) -> 2924 | AP28: =AP23+AP21-AP26 -> 747 | AQ28: =AQ23+AQ21-AQ26 -> 769 | AR28: =AR23+AR21-AR26 -> 735 | AS28: =AS23+AS21-AS26 -> 824 | AT28: =SUM(AP28:AS28) -> 3075 | AU28: =AU23+AU21-AU26 -> 742.5 | AV28: =AV23+AV21-AV26 -> 793.5 | AW28: =AW23+AW21-AW26 -> 754 | AX28: =AX23+AX21-AX26 -> 812 | AY28: =SUM(AU28:AX28) -> 3102 | AZ28: =AZ23+AZ21-AZ26 -> 745 | BA28: =BA23+BA21-BA26 -> 757 | BB28: =BB23+BB21-BB26 -> 758 | BC28: =BC23+BC21-BC26 -> 843 | BD28: =SUM(AZ28:BC28) -> 3103 | BE28: =BE23+BE21-BE26 -> 772 | BF28: =BF23+BF21-BF26 -> 808 | BG28: =BG23+BG21-BG26 -> 778 | BH28: =BH23+BH21-BH26 -> 788 | BI28: =SUM(BE28:BH28) -> 3146 | BJ28: =BJ23+BJ21-BJ26 -> 745 | BK28: =BK23+BK21-BK26 -> 774 | BL28: =BL23+BL21-BL26 -> 790 | BM28: =BM23+BM21-BM26 -> 816 | BN28: =SUM(BJ28:BM28) -> 3125 | BO28: =BO23+BO21-BO26 -> 811 | BP28: =BP23+BP21-BP26 -> 847.45366 | BQ28: =BQ23+BQ21-BQ26 -> 849.23738 | BR28: =BR23+BR21-BR26 -> 867.54111 | BS28: =SUM(BO28:BR28) -> 3375.2321 | BT28: =BT23+BT21-BT26 -> 831.31759 | BU28: =BU23+BU21-BU26 -> 870.33791 | BV28: =BV23+BV21-BV26 -> 873.27192 | BW28: =BW23+BW21-BW26 -> 889.69902 | BX28: =SUM(BT28:BW28) -> 3464.6264 | BY28: =BY23+BY21-BY26 -> 3602.0848 | BZ28: =BZ23+BZ21-BZ26 -> 3739.1975 | CA28: =CA23+CA21-CA26 -> 3870.3114 | CD28: =A28 -> Total Expenses | CE28: =B28 -> 3795.05 | CF28: =C28 -> 3582.684 | CG28: =D28 -> 3768.449 | CH28: =E28 -> 3951.201 | CI28: =F28 -> 4465.529 | CJ28: =K28 -> 4643.597 | CK28: =P28 -> 4904.479 | CL28: =U28 -> 4728.625 | CM28: =Z28 -> 4512.113 | CN28: =AE28 -> 4582.031 | CO28: =AJ28 -> 4151.1 | CP28: =AO28 -> 2924 | CQ28: =AT28 -> 3075 | CR28: =AY28 -> 3102 | CS28: =BD28 -> 3103 | CT28: =BI28 -> 3146 | CU28: =BN28 -> 3125 | CV28: =BS28 -> 3375.2321 | CW28: =BX28 -> 3464.6264 | CX28: =BY28 -> 3602.0848 | CY28: =BZ28 -> 3739.1975 | CZ28: =CA28 -> 3870.3114 | DB28: =SUM(BO28,BP28,BQ28,BR28) -> 3375.2321
A30: EBITDA | B30: =B14-B28 -> 850.485 | C30: =C14-C28 -> 1057.5 | D30: =D14-D28 -> 1121.871 | E30: =E14-E28 -> 1299.337 | F30: =F14-F28 -> 1538.113 | G30: =G14-G28 -> 178.964 | H30: =H14-H28 -> 400.826 | I30: =I14-I28 -> 670.634 | ... M30: =M14-M28 -> 495.691 | N30: =N14-N28+N26+N42 -> 761.137 | O30: =O14-O28 -> 340.158 | P30: =P14-P28 -> 1867.802 | Q30: =Q14-Q28 -> 192.787 | R30: =R14-R28 -> 431.936 | S30: =S14-S28 -> 719.905 | T30: =U30-S30-R30-Q30 -> 281.802 | U30: =U14-U28 -> 1626.43 | V30: =V14-V28 -> 167.957 | W30: =W14-W28 -> 351.749 | X30: =X14-X28 -> 593.062 | Y30: =Y14-Y28 -> 326.901 | Z30: =Z14-Z28 -> 1439.669 | AA30: =AA14-AA28 -> 226.2 | AB30: =AB14-AB28 -> 365.5 | ... AJ30: =AJ14-AJ28 -> 2094.9 | AK30: =AK39+AK34 -> 342 | AL30: =AL39+AL34 -> 381 | AM30: =AM39+AM34 -> 395 | AN30: =AN39+AN34 -> 408 | AO30: =SUM(AK30:AN30) -> 1526 | AP30: =AP39+AP34 -> 434 | AQ30: =AQ39+AQ34 -> 481 | AR30: =AR39+AR34 -> 417 | AS30: =AS39+AS34 -> 382 | AT30: =SUM(AP30:AS30) -> 1714 | AU30: =AU39+AU34 -> 453.5 | AV30: =AV39+AV34 -> 508.5 | AW30: =AW39+AW34 -> 509 | AX30: =AX39+AX34 -> 478 | AY30: =SUM(AU30:AX30) -> 1949 | AZ30: =AZ39+AZ34 -> 528 | BA30: =BA39+BA34 -> 585 | BB30: =BB39+BB34 -> 566 | BC30: =BC39+BC34 -> 531 | BD30: =SUM(AZ30:BC30) -> 2210 | BE30: =BE39+BE34 -> 569 | BF30: =BF39+BF34 -> 674 | BG30: =BG39+BG34 -> 661 | BH30: =BH39+BH34 -> 611 | BI30: =SUM(BE30:BH30) -> 2515 | BJ30: =BJ39+BJ34 -> 708 | BK30: =BK39+BK34 -> 735 | BL30: =BL39+BL34 -> 723 | BM30: =BM39+BM34 -> 773 | BN30: =SUM(BJ30:BM30) -> 2939 | BO30: =BO39+BO34 -> 756 | BP30: =BP39+BP34 -> 792.92857 | BQ30: =BQ39+BQ34 -> 774.09206 | BR30: =BR39+BR34 -> 803.59713 | BS30: =SUM(BO30:BR30) -> 3126.6178 | BT30: =BT39+BT34 -> 815.11416 | BU30: =BU39+BU34 -> 867.02705 | BV30: =BV39+BV34 -> 848.01583 | BW30: =BW39+BW34 -> 881.25417 | BX30: =SUM(BT30:BW30) -> 3411.4112 | BY30: =BY39+BY34 -> 3629.441 | BZ30: =BZ39+BZ34 -> 3869.1814 | CA30: =CA39+CA34 -> 4094.5434 | CB30: =(CA30/BN30)^(1/5)-1 -> 0.068565574 | CD30: =A30 -> EBITDA | CE30: =CE14-CE28 -> 850.485 | CF30: =CF14-CF28 -> 1057.5 | CG30: =CG14-CG28 -> 1121.871 | CH30: =CH14-CH28 -> 1299.337 | CI30: =CI14-CI28 -> 1538.113 | CJ30: =CJ14-CJ28 -> 1611.541 | CK30: =CK14-CK28 -> 1867.802 | CL30: =CL14-CL28 -> 1626.43 | ... CO30: =CO14-CO28 -> 2094.9 | CP30: =AO30 -> 1526 | CQ30: =AT30 -> 1714 | CR30: =AY30 -> 1949 | CS30: =BD30 -> 2210 | CT30: =BI30 -> 2515 | CU30: =BN30 -> 2939 | CV30: =BS30 -> 3126.6178 | CW30: =BX30 -> 3411.4112 | CX30: =BY30 -> 3629.441 | CY30: =BZ30 -> 3869.1814 | CZ30: =CA30 -> 4094.5434 | DB30: =SUM(BO30,BP30,BQ30,BR30) -> 3126.6178
A31: EBITDA Margin | B31: =B30/B14 -> 0.18307579 | C31: =C30/C14 -> 0.22790045 | D31: =D30/D14 -> 0.22940646 | E31: =E30/E14 -> 0.2474674 | F31: =F30/F14 -> 0.25619666 | G31: =G30/G14 -> 0.15689252 | H31: =H30/H14 -> 0.26239916 | I31: =I30/I14 -> 0.33656735 | ... CA31: =CA30/CA14 -> 0.51407634 | CD31: =A31 -> EBITDA Margin | CE31: =B31 -> 0.18307579 | CF31: =C31 -> 0.22790045 | CG31: =D31 -> 0.22940646 | CH31: =E31 -> 0.2474674 | CI31: =F31 -> 0.25619666 | CJ31: =K31 -> 0.25763476 | CK31: =P31 -> 0.27580102 | CL31: =U31 -> 0.25592697 | CM31: =Z31 -> 0.24188873 | CN31: =AE31 -> 0.25716843 | CO31: =AJ31 -> 0.33539866 | CP31: =AO31 -> 0.34292135 | CQ31: =AT31 -> 0.35790353 | CR31: =AY31 -> 0.38586419 | CS31: =BD31 -> 0.41596085 | CT31: =BI31 -> 0.4442678 | CU31: =BN31 -> 0.48466359 | CV31: =BS31 -> 0.48088126 | CW31: =BX31 -> 0.49613039 | CX31: =BY31 -> 0.50189146 | CY31: =BZ31 -> 0.50854216 | CZ31: =CA31 -> 0.51407634 | DB31: =DB30/$DB$14 -> 0.48088126
A32: Year-over-Year Growth | C32: =C30/B30-1 -> 0.24340817 | D32: =D30/C30-1 -> 0.060870922 | E32: =E30/D30-1 -> 0.15818753 | F32: =F30/E30-1 -> 0.18376757 | K32: =K30/F30-1 -> 0.047739015 | L32: =L30/G30-1 -> 0.42706354 | M32: =M30/H30-1 -> 0.23667377 | N32: =N30/I30-1 -> 0.1349514 | O32: =O30/J30-1 -> -0.058039361 | P32: =P30/K30-1 -> 0.15901612 | Q32: =Q30/L30-1 -> -0.24513593 | R32: =R30/M30-1 -> -0.12861843 | ... BX32: =BX30/BS30-1 -> 0.091086751 | BY32: =BY30/BX30-1 -> 0.063911912 | BZ32: =BZ30/BY30-1 -> 0.066054363 | CA32: =CA30/BZ30-1 -> 0.058245385 | CD32: =A32 -> Year-over-Year Growth | CF32: =C32 -> 0.24340817 | CG32: =D32 -> 0.060870922 | CH32: =E32 -> 0.15818753 | CI32: =F32 -> 0.18376757 | CJ32: =K32 -> 0.047739015 | CK32: =P32 -> 0.15901612 | CL32: =U32 -> -0.12922783 | CM32: =Z32 -> -0.1148288 | CN32: =AE32 -> 0.10185049 | CO32: =AJ32 -> 0.32062031 | CP32: =AO32 -> -0.27156428 | CQ32: =AT32 -> 0.1231979 | CR32: =AY32 -> 0.13710618 | CS32: =BD32 -> 0.13391483 | CT32: =BI32 -> 0.13800905 | CU32: =BN32 -> 0.16858847 | CV32: =BS32 -> 0.063837275 | CW32: =BX32 -> 0.091086751 | CX32: =BY32 -> 0.063911912 | CY32: =BZ32 -> 0.066054363 | CZ32: =CA32 -> 0.058245385
A34: Depreciation and Amortization | B34: =B35+B36 -> 180.357 | C34: =C35+C36 -> 123.088 | D34: =D35+D36 -> 115.797 | E34: =E35+E36 -> 124.647 | F34: =F35+F36 -> 150.985 | G34: =G35+G36 -> 39.49 | H34: =H35+H36 -> 40.423 | I34: =I35+I36 -> 39.005 | ... AI34: =AI35+AI36 -> 40.1 | AJ34: =SUM(AF34:AI34) -> 156 | AK34: =AK35+AK36 -> 31 | AL34: =AL35+AL36 -> 34 | AM34: =AM35+AM36 -> 39 | AN34: =AN35+AN36 -> 37 | AO34: =SUM(AK34:AN34) -> 141 | AP34: =AP35+AP36 -> 35 | AQ34: =AQ35+AQ36 -> 35 | AR34: =AR35+AR36 -> 33 | AS34: =AS35+AS36 -> 34 | AT34: =SUM(AP34:AS34) -> 137 | AU34: =AU35+AU36 -> 33 | AV34: =AV35+AV36 -> 34 | AW34: =AW35+AW36 -> 33 | AX34: =AX35+AX36 -> 34 | AY34: =SUM(AU34:AX34) -> 134 | AZ34: =AZ35+AZ36 -> 33 | BA34: =BA35+BA36 -> 33 | BB34: =BB35+BB36 -> 38 | BC34: =BC35+BC36 -> 53 | BD34: =SUM(AZ34:BC34) -> 157 | BE34: =BE35+BE36 -> 42 | BF34: =BF35+BF36 -> 45 | BG34: =BG35+BG36 -> 47 | BH34: =BH35+BH36 -> 47 | BI34: =SUM(BE34:BH34) -> 181 | BJ34: =BJ35+BJ36 -> 43 | BK34: =BK35+BK36 -> 45 | BL34: =BL35+BL36 -> 46 | BM34: =BM35+BM36 -> 46 | BN34: =SUM(BJ34:BM34) -> 180 | BO34: =BO35+BO36 -> 45 | BP34: =BP37*BP14 -> 47.277577 | BQ34: =BQ37*BQ14 -> 47.731036 | BR34: =BR37*BR14 -> 46.706683 | BS34: =SUM(BO34:BR34) -> 186.7153 | BT34: =BT37*BT14 -> 46.100089 | BU34: =BU37*BU14 -> 48.646219 | BV34: =BV37*BV14 -> 48.196057 | BW34: =BW37*BW14 -> 49.586689 | BX34: =SUM(BT34:BW34) -> 192.52905 | BY34: =BY37*BY14 -> 195.2512 | BZ34: =BZ37*BZ14 -> 197.81785 | CA34: =CA37*CA14 -> 199.12137 | CD34: =A34 -> Depreciation and Amortization | CE34: =CE35+CE36 -> 180.357 | CF34: =CF35+CF36 -> 123.088 | CG34: =CG35+CG36 -> 115.797 | CH34: =CH35+CH36 -> 124.647 | CI34: =CI35+CI36 -> 150.985 | CJ34: =CJ35+CJ36 -> 161.587 | CK34: =CK35+CK36 -> 160.989 | CL34: =CL35+CL36 -> 178.346 | ... CO34: =CO35+CO36 -> 156 | CP34: =AO34 -> 141 | CQ34: =AT34 -> 137 | CR34: =AY34 -> 134 | CS34: =BD34 -> 157 | CT34: =BI34 -> 181 | CU34: =BN34 -> 180 | CV34: =BS34 -> 186.7153 | CW34: =BX34 -> 192.52905 | CX34: =BY34 -> 195.2512 | CY34: =BZ34 -> 197.81785 | CZ34: =CA34 -> 199.12137 | DB34: =SUM(BO34,BP34,BQ34,BR34) -> 186.7153
A35: Depreciation | B35: 88.802 | C35: 86.818 | D35: 82.826 | E35: 92.177 | F35: 106.75 | G35: 27.564 | H35: 28.316 | I35: 26.868 | J35: =113.2-SUM(G35:I35) -> 30.452 | K35: =SUM(G35:J35) -> 113.2 | L35: 28.905 | M35: 28.798 | N35: 26.199 | O35: =112.586-SUM(L35:N35) -> 28.684 | P35: =SUM(L35:O35) -> 112.586 | Q35: 27.527 | R35: 30.411 | S35: 29.952 | T35: =119.849-SUM(Q35:S35) -> 31.959 | U35: =SUM(Q35:T35) -> 119.849 | V35: 29.412 | W35: 28.782 | X35: 26.031 | Y35: =112.764-SUM(V35:X35) -> 28.539 | Z35: =SUM(V35:Y35) -> 112.764 | AA35: 25.9 | AB35: 26.2 | AC35: 23.3 | AD35: =104.504-SUM(AA35:AC35) -> 29.104 | AE35: =SUM(AA35:AD35) -> 104.504 | AF35: 25 | AG35: 25 | AH35: 23.1 | AI35: =98-SUM(AF35:AH35) -> 24.9 | AJ35: =SUM(AF35:AI35) -> 98 | AK35: 22 | AL35: 23 | AM35: 24 | AN35: =93-SUM(AK35:AM35) -> 24 | AO35: =SUM(AK35:AN35) -> 93 | AP35: 23 | AQ35: 22 | AR35: 20 | AS35: =86-SUM(AP35:AR35) -> 21 | AT35: =SUM(AP35:AS35) -> 86 | AU35: 21 | AV35: 22 | AW35: 21 | AX35: =86-SUM(AU35:AW35) -> 22 | AY35: =SUM(AU35:AX35) -> 86 | AZ35: 22 | BA35: =43-AZ35 -> 21 | BB35: =64-BA35-AZ35 -> 21 | BC35: =90-SUM(AZ35:BB35) -> 26 | BD35: =SUM(AZ35:BC35) -> 90 | BE35: 18 | BF35: =40-BE35 -> 22 | BG35: =63-BF35-BE35 -> 23 | BH35: =85-SUM(BE35:BG35) -> 22 | BI35: =SUM(BE35:BH35) -> 85 | BJ35: 19 | BK35: =39-BJ35 -> 20 | BL35: =61-BK35-BJ35 -> 22 | BM35: =82-SUM(BJ35:BL35) -> 21 | BN35: =SUM(BJ35:BM35) -> 82 | BO35: 21 | BP35: =BP34-BP36 -> 12.777577 | BQ35: =BQ34-BQ36 -> 13.231036 | BR35: =BR34-BR36 -> 12.206683 | BS35: =SUM(BO35:BR35) -> 59.215296 | BT35: =BT34-BT36 -> 15.975089 | BU35: =BU34-BU36 -> 18.521219 | BV35: =BV34-BV36 -> 18.071057 | BW35: =BW34-BW36 -> 19.461689 | BX35: =SUM(BT35:BW35) -> 72.029054 | BY35: =BY34-BY36 -> 80.751197 | BZ35: =BZ34-BZ36 -> 95.317851 | CA35: =CA34-CA36 -> 98.621369 | CD35: =A35 -> Depreciation | CE35: =B35 -> 88.802 | CF35: =C35 -> 86.818 | CG35: =D35 -> 82.826 | CH35: =E35 -> 92.177 | CI35: =F35 -> 106.75 | CJ35: =K35 -> 113.2 | CK35: =P35 -> 112.586 | CL35: =U35 -> 119.849 | CM35: =Z35 -> 112.764 | CN35: =AE35 -> 104.504 | CO35: =AJ35 -> 98 | CP35: =AO35 -> 93 | CQ35: =AT35 -> 86 | CR35: =AY35 -> 86 | CS35: =BD35 -> 90 | CT35: =BI35 -> 85 | CU35: =BN35 -> 82 | CV35: =BS35 -> 59.215296 | CW35: =BX35 -> 72.029054 | CX35: =BY35 -> 80.751197 | CY35: =BZ35 -> 95.317851 | CZ35: =CA35 -> 98.621369 | DB35: =SUM(BO35,BP35,BQ35,BR35) -> 59.215296
A36: Amortization | B36: =34.919+56.636 -> 91.555 | C36: 36.27 | D36: 32.971 | E36: 32.47 | F36: 44.235 | G36: 11.926 | H36: 12.107 | I36: 12.137 | J36: =48.387-SUM(G36:I36) -> 12.217 | K36: =SUM(G36:J36) -> 48.387 | L36: 11.612 | M36: 11.468 | N36: 11.709 | O36: =48.403-SUM(L36:N36) -> 13.614 | P36: =SUM(L36:O36) -> 48.403 | Q36: 14.2 | R36: 13.144 | S36: 13.637 | T36: =58.497-SUM(Q36:S36) -> 17.516 | U36: =SUM(Q36:T36) -> 58.497 | V36: 14.204 | W36: 11.44 | X36: 11.066 | Y36: =52.72-SUM(V36:X36) -> 16.01 | Z36: =SUM(V36:Y36) -> 52.72 | AA36: 10 | AB36: 13 | AC36: 8.4 | AD36: =45.595-SUM(AA36:AC36) -> 14.195 | AE36: =SUM(AA36:AD36) -> 45.595 | AF36: 14 | AG36: 14 | AH36: 14.8 | AI36: =58-SUM(AF36:AH36) -> 15.2 | AJ36: =SUM(AF36:AI36) -> 58 | AK36: 9 | AL36: 11 | AM36: 15 | AN36: =48-SUM(AK36:AM36) -> 13 | AO36: =SUM(AK36:AN36) -> 48 | AP36: 12 | AQ36: 13 | AR36: 13 | AS36: =51-SUM(AP36:AR36) -> 13 | AT36: =SUM(AP36:AS36) -> 51 | AU36: 12 | AV36: 12 | AW36: 12 | AX36: =48-SUM(AU36:AW36) -> 12 | AY36: =+SUM(AU36:AX36) -> 48 | AZ36: 11 | BA36: =23-AZ36 -> 12 | BB36: =40-BA36-AZ36 -> 17 | BC36: =67-SUM(AZ36:BB36) -> 27 | BD36: =+SUM(AZ36:BC36) -> 67 | BE36: 24 | BF36: =47-BE36 -> 23 | BG36: =71-BF36-BE36 -> 24 | BH36: =96-SUM(BE36:BG36) -> 25 | BI36: =+SUM(BE36:BH36) -> 96 | BJ36: 24 | BK36: =49-BJ36 -> 25 | BL36: =73-BK36-BJ36 -> 24 | BM36: =98-SUM(BJ36:BL36) -> 25 | BN36: =+SUM(BJ36:BM36) -> 98 | BO36: 24 | BP36: =($BS$36-$BO$36)/3 -> 34.5 | BQ36: =($BS$36-$BO$36)/3 -> 34.5 | BR36: =+BS36-SUM(BO36:BQ36) -> 34.5 | BS36: 127.5 | BT36: =+$BX$36/4 -> 30.125 | BU36: =+$BX$36/4 -> 30.125 | BV36: =+$BX$36/4 -> 30.125 | BW36: =+BX36-SUM(BT36:BV36) -> 30.125 | BX36: =88+32.5 -> 120.5 | BY36: =82+32.5 -> 114.5 | BZ36: =70+32.5 -> 102.5 | CA36: =68+32.5 -> 100.5 | CD36: =A36 -> Amortization | CE36: =B36 -> 91.555 | CF36: =C36 -> 36.27 | CG36: =D36 -> 32.971 | CH36: =E36 -> 32.47 | CI36: =F36 -> 44.235 | CJ36: =K36 -> 48.387 | CK36: =P36 -> 48.403 | CL36: =U36 -> 58.497 | CM36: =Z36 -> 52.72 | CN36: =AE36 -> 45.595 | CO36: =AJ36 -> 58 | CP36: =AO36 -> 48 | CQ36: =AT36 -> 51 | CR36: =AY36 -> 48 | CS36: =BD36 -> 67 | CT36: =BI36 -> 96 | CU36: =BN36 -> 98 | CV36: =BS36 -> 127.5 | CW36: =BX36 -> 120.5 | CX36: =BY36 -> 114.5 | CY36: =BZ36 -> 102.5 | CZ36: =CA36 -> 100.5 | DB36: =SUM(BO36,BP36,BQ36,BR36) -> 127.5
A37: % of Total Revenue | B37: =B34/B14 -> 0.038823731 | C37: =C34/C14 -> 0.026526534 | D37: =D34/D14 -> 0.023678819 | E37: =E34/E14 -> 0.023739853 | F37: =F34/F14 -> 0.025148901 | G37: =G34/G14 -> 0.034619731 | H37: =H34/H14 -> 0.026462758 | I37: =I34/I14 -> 0.019575222 | ... BO37: =BO34/BO14 -> 0.028717294 | BP37: =+BK37-0.001 -> 0.028821074 | BQ37: =+BL37-0.001 -> 0.029403173 | BR37: =+BM37-0.001 -> 0.027949025 | BS37: =BS34/BS14 -> 0.028717257 | BT37: 0.028 | BU37: 0.028 | BV37: 0.028 | BW37: 0.028 | BX37: =BX34/BX14 -> 0.028 | BY37: =BX37-0.1% -> 0.027 | BZ37: =BY37-0.1% -> 0.026 | CA37: =BZ37-0.1% -> 0.025 | CD37: =A37 -> % of Total Revenue | CE37: =B37 -> 0.038823731 | CF37: =C37 -> 0.026526534 | CG37: =D37 -> 0.023678819 | CH37: =E37 -> 0.023739853 | CI37: =F37 -> 0.025148901 | CJ37: =K37 -> 0.025832683 | CK37: =P37 -> 0.023771754 | CL37: =U37 -> 0.028063644 | CM37: =Z37 -> 0.02780411 | CN37: =AE37 -> 0.024333811 | CO37: =AJ37 -> 0.024975985 | CP37: =AO37 -> 0.031685393 | CQ37: =AT37 -> 0.028607225 | CR37: =AY37 -> 0.0265294 | CS37: =BD37 -> 0.02955016 | CT37: =BI37 -> 0.03197315 | CU37: =BN37 -> 0.029683377 | CV37: =BS37 -> 0.028717257 | CW37: =BX37 -> 0.028 | CX37: =BY37 -> 0.027 | CY37: =BZ37 -> 0.026 | CZ37: =CA37 -> 0.025 | DB37: =DB36/$DB$14 -> 0.019609804
A39: Operating Profit | B39: =B14-B28-B34 -> 670.128 | C39: =C14-C28-C34 -> 934.412 | D39: =D14-D28-D34 -> 1006.074 | E39: =E14-E28-E34 -> 1174.69 | F39: =F14-F28-F34 -> 1387.128 | G39: =G14-G28-G34 -> 139.474 | H39: =H14-H28-H34 -> 360.403 | I39: =I14-I28-I34 -> 631.629 | ... AI39: =AI14-AI28-AI34 -> 242 | AJ39: =SUM(AF39:AI39) -> 1422.9 | AK39: =AK14-AK28-AK34 -> 311 | AL39: =AL14-AL28-AL34 -> 347 | AM39: =AM14-AM28-AM34 -> 356 | AN39: =AN14-AN28-AN34 -> 371 | AO39: =SUM(AK39:AN39) -> 1385 | AP39: =AP14-AP28-AP34 -> 399 | AQ39: =AQ14-AQ28-AQ34 -> 446 | AR39: =AR14-AR28-AR34 -> 384 | AS39: =AS14-AS28-AS34 -> 348 | AT39: =SUM(AP39:AS39) -> 1577 | AU39: =AU14-AU28-AU34 -> 420.5 | AV39: =AV14-AV28-AV34 -> 474.5 | AW39: =AW14-AW28-AW34 -> 476 | AX39: =AX14-AX28-AX34 -> 444 | AY39: =SUM(AU39:AX39) -> 1815 | AZ39: =AZ14-AZ28-AZ34 -> 495 | BA39: =BA14-BA28-BA34 -> 552 | BB39: =BB14-BB28-BB34 -> 528 | BC39: =BC14-BC28-BC34 -> 478 | BD39: =SUM(AZ39:BC39) -> 2053 | BE39: =BE14-BE28-BE34 -> 527 | BF39: =BF14-BF28-BF34 -> 629 | BG39: =BG14-BG28-BG34 -> 614 | BH39: =BH14-BH28-BH34 -> 564 | BI39: =SUM(BE39:BH39) -> 2334 | BJ39: =BJ14-BJ28-BJ34 -> 665 | BK39: =BK14-BK28-BK34 -> 690 | BL39: =BL14-BL28-BL34 -> 677 | BM39: =BM14-BM28-BM34 -> 727 | BN39: =SUM(BJ39:BM39) -> 2759 | BO39: =BO14-BO28-BO34 -> 711 | BP39: ='Op Metrics'!BP142 -> 745.65099 | BQ39: ='Op Metrics'!BQ142 -> 726.36102 | BR39: ='Op Metrics'!BR142 -> 756.89044 | BS39: =SUM(BO39:BR39) -> 2939.9025 | BT39: ='Op Metrics'!BT142 -> 769.01407 | BU39: ='Op Metrics'!BU142 -> 818.38083 | BV39: ='Op Metrics'!BV142 -> 799.81978 | BW39: ='Op Metrics'!BW142 -> 831.66748 | BX39: =SUM(BT39:BW39) -> 3218.8822 | BY39: ='Op Metrics'!BY142 -> 3434.1898 | BZ39: ='Op Metrics'!BZ142 -> 3671.3636 | CA39: ='Op Metrics'!CA142 -> 3895.422 | CB39: =(CA39/BN39)^(1/5)-1 -> 0.071422008 | CD39: =A39 -> Operating Profit | CE39: =CE14-CE28-CE34 -> 670.128 | CF39: =CF14-CF28-CF34 -> 934.412 | CG39: =CG14-CG28-CG34 -> 1006.074 | CH39: =CH14-CH28-CH34 -> 1174.69 | CI39: =CI14-CI28-CI34 -> 1387.128 | CJ39: =CJ14-CJ28-CJ34 -> 1449.954 | CK39: =CK14-CK28-CK34 -> 1706.813 | CL39: =CL14-CL28-CL34 -> 1448.084 | ... CO39: =CO14-CO28-CO34 -> 1938.9 | CP39: =AO39 -> 1385 | CQ39: =AT39 -> 1577 | CR39: =AY39 -> 1815 | CS39: =BD39 -> 2053 | CT39: =BI39 -> 2334 | CU39: =BN39 -> 2759 | CV39: =BS39 -> 2939.9025 | CW39: =BX39 -> 3218.8822 | CX39: =BY39 -> 3434.1898 | CY39: =BZ39 -> 3671.3636 | CZ39: =CA39 -> 3895.422 | DB39: =SUM(BO39,BP39,BQ39,BR39) -> 2939.9025
A40: Operating Margin | B40: =B39/B14 -> 0.14425206 | C40: =C39/C14 -> 0.20137391 | D40: =D39/D14 -> 0.20572764 | E40: =E39/E14 -> 0.22372755 | F40: =F39/F14 -> 0.23104775 | G40: =G39/G14 -> 0.12227279 | H40: =H39/H14 -> 0.2359364 | I40: =I39/I14 -> 0.31699213 | ... CA40: =CA39/CA14 -> 0.48907634 | CD40: =A40 -> Operating Margin | CE40: =B40 -> 0.14425206 | CF40: =C40 -> 0.20137391 | CG40: =D40 -> 0.20572764 | CH40: =E40 -> 0.22372755 | CI40: =F40 -> 0.23104775 | CJ40: =K40 -> 0.23180208 | CK40: =P40 -> 0.25202926 | CL40: =U40 -> 0.22786333 | CM40: =Z40 -> 0.21408462 | CN40: =AE40 -> 0.23283462 | CO40: =AJ40 -> 0.2278098 | CP40: =AO40 -> 0.31123596 | CQ40: =AT40 -> 0.3292963 | CR40: =AY40 -> 0.35933479 | CS40: =BD40 -> 0.38641069 | CT40: =BI40 -> 0.41229465 | CU40: =BN40 -> 0.45498021 | CV40: =BS40 -> 0.452164 | CW40: =BX40 -> 0.46813039 | CX40: =BY40 -> 0.47489146 | CY40: =BZ40 -> 0.48254216 | CZ40: =CA40 -> 0.48907634 | DB40: =DB39/$DB$14 -> 0.452164
A42: Interest Expense, Net | B42: -55.07 | C42: -22.517 | D42: -7.097 | E42: -5.785 | F42: -5.202 | G42: 2.509 | H42: -8.555 | I42: -7.515 | J42: =-13.631-SUM(G42:I42) -> -0.07 | K42: =SUM(G42:J42) -> -13.631 | L42: -1.204 | M42: -12.099 | N42: -15.423 | O42: =-40.581-SUM(L42:N42) -> -11.855 | P42: =SUM(L42:O42) -> -40.581 | Q42: -17.83 | R42: -20.354 | S42: -22.002 | T42: =-75.624-SUM(Q42:S42) -> -15.438 | U42: =SUM(Q42:T42) -> -75.624 | V42: -20.591 | W42: -18.499 | X42: -17.827 | Y42: =-76.867-SUM(V42:X42) -> -19.95 | Z42: =SUM(V42:Y42) -> -76.867 | AA42: -22.1 | AB42: -20.9 | AC42: -19.3 | AD42: =-81.643-SUM(AA42:AC42) -> -19.343 | AE42: =SUM(AA42:AD42) -> -81.643 | AF42: -19 | AG42: -20 | AH42: -18.1 | AI42: -19 | AJ42: =SUM(AF42:AI42) -> -76.1 | AK42: -21 | AL42: -21 | AM42: -21 | AN42: =-81-SUM(AK42:AM42) -> -18 | AO42: =SUM(AK42:AN42) -> -81 | AP42: -15 | AQ42: -16 | AR42: -14 | AS42: =-59-SUM(AP42:AR42) -> -14 | AT42: =SUM(AP42:AS42) -> -59 | AU42: -14 | AV42: -14 | AW42: -12 | AX42: -19 | AY42: =SUM(AU42:AX42) -> -59 | AZ42: -16 | BA42: -16 | BB42: -30 | BC42: -40 | BD42: =SUM(AZ42:BC42) -> -102 | BE42: -40 | BF42: -42 | BG42: -39 | BH42: =-60+21 -> -39 | BI42: =SUM(BE42:BH42) -> -160 | BJ42: -37 | BK42: -37 | BL42: -37 | BM42: -39 | BN42: =SUM(BJ42:BM42) -> -150 | BO42: -34 | BP42: =-BP293 -> -37.128513 | BQ42: =-BQ293 -> -37.128513 | BR42: =-BR293 -> -37.128513 | BS42: =SUM(BO42:BR42) -> -145.38554 | BT42: =-BT293 -> -37.03875 | BU42: =-BU293 -> -37.03875 | BV42: =-BV293 -> -37.03875 | BW42: =-BW293 -> -37.03875 | BX42: =SUM(BT42:BW42) -> -148.155 | BY42: =-BY293 -> -148.155 | BZ42: =-BZ293 -> -148.155 | CA42: =-CA293 -> -148.155 | CD42: =A42 -> Interest Expense, Net | CE42: =B42 -> -55.07 | CF42: =C42 -> -22.517 | CG42: =D42 -> -7.097 | CH42: =E42 -> -5.785 | CI42: =F42 -> -5.202 | CJ42: =K42 -> -13.631 | CK42: =P42 -> -40.581 | CL42: =U42 -> -75.624 | CM42: =Z42 -> -76.867 | CN42: =AE42 -> -81.643 | CO42: =AJ42 -> -76.1 | CP42: =AO42 -> -81 | CQ42: =AT42 -> -59 | CR42: =AY42 -> -59 | CS42: =BD42 -> -102 | CT42: =BI42 -> -160 | CU42: =BN42 -> -150 | CV42: =BS42 -> -145.38554 | CW42: =BX42 -> -148.155 | CX42: =BY42 -> -148.155 | CY42: =BZ42 -> -148.155 | CZ42: =CA42 -> -148.155 | DB42: =SUM(BO42,BP42,BQ42,BR42) -> -145.38554
A43: Other income/ (expense), net | BO43: =4 -> 4 | BP43: 0 | BQ43: 0 | BR43: 0 | BS43: =SUM(BO43:BR43) -> 4 | BT43: 0 | BU43: 0 | BV43: 0 | BW43: 0 | BX43: =SUM(BT43:BW43) -> 0 | BY43: 0 | BZ43: 0 | CA43: 0 | CD43: =A43 -> Other income/ (expense), net | CO43: =AJ43 -> 0 | CP43: =AO43 -> 0 | CQ43: =AT43 -> 0 | CR43: =AY43 -> 0 | CS43: =BD43 -> 0 | CT43: =BI43 -> 0 | CU43: =BN43 -> 0 | CV43: =BS43 -> 4 | CW43: =BX43 -> 0 | CX43: =BY43 -> 0 | CY43: =BZ43 -> 0 | CZ43: =CA43 -> 0
A45: Pretax Income | B45: =B39+B42 -> 615.058 | C45: =C39+C42 -> 911.895 | D45: =D39+D42 -> 998.977 | E45: =E39+E42 -> 1168.905 | F45: =F39+F42 -> 1381.926 | G45: =G39+G42 -> 141.983 | H45: =H39+H42 -> 351.848 | I45: =I39+I42 -> 624.114 | ... BN45: =BN39+BN42 -> 2609 | BO45: =BO39+BO42+BO43 -> 681 | BP45: =BP39+BP42+BP43 -> 708.52248 | BQ45: =BQ39+BQ42+BQ43 -> 689.23251 | BR45: =BR39+BR42+BR43 -> 719.76193 | BS45: =BS39+BS42+BS43 -> 2798.5169 | BT45: =BT39+BT42+BT43 -> 731.97532 | BU45: =BU39+BU42+BU43 -> 781.34208 | BV45: =BV39+BV42+BV43 -> 762.78103 | ... CA45: =CA39+CA42+CA43 -> 3747.267 | CD45: =A45 -> Pretax Income | CE45: =CE39+CE42 -> 615.058 | CF45: =CF39+CF42 -> 911.895 | CG45: =CG39+CG42 -> 998.977 | CH45: =CH39+CH42 -> 1168.905 | CI45: =CI39+CI42 -> 1381.926 | CJ45: =CJ39+CJ42 -> 1436.323 | CK45: =CK39+CK42 -> 1666.232 | CL45: =CL39+CL42 -> 1372.46 | ... CO45: =CO39+CO42 -> 1862.8 | CP45: =AO45 -> 1304 | CQ45: =AT45 -> 1518 | CR45: =AY45 -> 1756 | CS45: =BD45 -> 1951 | CT45: =BI45 -> 2174 | CU45: =BN45 -> 2609 | CV45: =BS45 -> 2798.5169 | CW45: =BX45 -> 3070.7272 | CX45: =BY45 -> 3286.0348 | CY45: =BZ45 -> 3523.2086 | CZ45: =CA45 -> 3747.267 | DB45: =SUM(BO45,BP45,BQ45,BR45) -> 2798.5169
A46: Income Tax Benefit (Expense)- Reported | B46: -238.027 | C46: -325.429 | D46: -442.466 | E46: -412.495 | F46: -515.656 | G46: -43.963 | H46: -130.887 | I46: -226.441 | J46: =-522.592-SUM(G46:I46) -> -121.301 | K46: =SUM(G46:J46) -> -522.592 | L46: -87.139 | M46: -166.248 | N46: -271.211 | O46: =-608.973-SUM(L46:N46) -> -84.375 | P46: =SUM(L46:O46) -> -608.973 | Q46: -48.667 | R46: -127.377 | S46: -234.099 | T46: =-479.695-SUM(Q46:S46) -> -69.552 | U46: =SUM(Q46:T46) -> -479.695 | V46: -37.765 | W46: -96.088 | X46: -195.882 | Y46: =-429.108-SUM(V46:X46) -> -99.373 | Z46: =SUM(V46:Y46) -> -429.108 | AA46: -61.2 | AB46: -111.2 | AC46: -221.7 | AD46: =-487.547-SUM(AA46:AC46) -> -93.447 | AE46: =SUM(AA46:AD46) -> -487.547 | AF46: -72 | AG46: -122 | AH46: -213.7 | AI46: -68 | AJ46: =SUM(AF46:AI46) -> -475.7 | AK46: -98 | AL46: -107 | AM46: -82 | AN46: -117 | AO46: =SUM(AK46:AN46) -> -404 | AP46: -89 | AQ46: -147 | AR46: -123 | AS46: -75 | AT46: =SUM(AP46:AS46) -> -434 | AU46: =-141+(253-245)/2-1 -> -138 | AV46: =-156+(253-245)/2+1 -> -151 | AW46: -139 | AX46: 183 | AY46: =SUM(AU46:AX46) -> -245 | AZ46: -156 | BA46: -185 | BB46: -99 | BC46: -108 | BD46: =SUM(AZ46:BC46) -> -548 | BE46: -149 | BF46: -197 | BG46: -386 | BH46: -228 | BI46: =SUM(BE46:BH46) -> -960 | BJ46: -181 | BK46: -183 | BL46: -169 | BM46: -290 | BN46: =SUM(BJ46:BM46) -> -823 | BO46: -147 | BP46: =-BP45*BP249 -> -152.33233 | BQ46: =-BQ45*BQ249 -> -148.18499 | BR46: =-BR45*BR249 -> -154.74882 | BS46: =SUM(BO46:BR46) -> -602.26614 | BT46: =-BT45*BT249 -> -157.37469 | BU46: =-BU45*BU249 -> -167.98855 | BV46: =-BV45*BV249 -> -163.99792 | BW46: =-BW45*BW249 -> -170.84518 | BX46: =SUM(BT46:BW46) -> -660.20634 | BY46: =-BY45*BY249 -> -706.49749 | BZ46: =-BZ45*BZ249 -> -757.48985 | CA46: =-CA45*CA249 -> -805.66241 | CD46: =A46 -> Income Tax Benefit (Expense)- Reported | CE46: =B46 -> -238.027 | CF46: =C46 -> -325.429 | CG46: =D46 -> -442.466 | CH46: =E46 -> -412.495 | CI46: =F46 -> -515.656 | CJ46: =K46 -> -522.592 | CK46: =P46 -> -608.973 | CL46: =U46 -> -479.695 | CM46: =Z46 -> -429.108 | CN46: =AE46 -> -487.547 | CO46: =AJ46 -> -475.7 | CP46: =AO46 -> -404 | CQ46: =AT46 -> -434 | CR46: =AY46 -> -245 | CS46: =BD46 -> -548 | CT46: =BI46 -> -960 | CU46: =BN46 -> -823 | CV46: =BS46 -> -602.26614 | CW46: =BX46 -> -660.20634 | CX46: =BY46 -> -706.49749 | CY46: =BZ46 -> -757.48985 | CZ46: =CA46 -> -805.66241 | DB46: =SUM(BO46,BP46,BQ46,BR46) -> -602.26614
A47: Income Tax Benefit (Expense)- Extraordinary income (expenses) | B47: 0 | C47: =-14.5*C245 -> -5.6405 | D47: =131.3*D245 -> 51.0757 | E47: 0 | F47: =(-23.2+1.236)*F245 -> -7.841148 | G47: =-23.8*G245 -> -9.3296 | H47: 0 | I47: =-15.4*I245 -> -6.0368 | J47: =-31.5*J242-SUM(G47:I47) -> 14.983785 | K47: =SUM(G47:J47) -> -0.38261527 | L47: =17.305*L245 -> 6.835475 | M47: 0 | N47: 0 | O47: =-43.7*O245-SUM(L47:N47) -> -24.096975 | P47: =SUM(L47:O47) -> -17.2615 | Q47: 0 | R47: =-23.7*R245 -> -9.2904 | S47: =-23.4*(S245) -> -9.1728 | T47: =(-73.4*(T245))-SUM(Q47:S47) -> -10.3096 | U47: =SUM(Q47:T47) -> -28.7728 | V47: 0 | W47: =(-15.2-13.849)*(W245) -> -11.300061 | X47: 0 | Y47: =-6.7-SUM(V47:X47) -> 4.600061 | Z47: =SUM(V47:Y47) -> -6.7 | AA47: 0 | AB47: 0 | AC47: 4 | AD47: =-5.5-SUM(AA47:AC47) -> -9.5 | AE47: =SUM(AA47:AD47) -> -5.5 | AF47: 0 | AG47: 0 | AH47: 0 | AI47: -15 | AJ47: =SUM(AF47:AI47) -> -15 | AK47: -11 | AL47: -15 | AM47: -30 | AN47: -9 | AO47: =SUM(AK47:AN47) -> -65 | AP47: -46 | AQ47: -3 | AR47: -6 | AS47: -26 | AT47: =SUM(AP47:AS47) -> -81 | AU47: 0 | AV47: 0 | AW47: -17 | AX47: -319 | AY47: =SUM(AU47:AX47) -> -336 | AZ47: 2 | BA47: 12 | BB47: -45 | BC47: -18 | BD47: =SUM(AZ47:BC47) -> -49 | BE47: -5 | BF47: 9 | BG47: =206 -> 206 | BH47: 53 | BI47: =SUM(BE47:BH47) -> 263 | BJ47: -9 | BK47: -5 | BL47: -7 | BM47: 96 | BN47: =SUM(BJ47:BM47) -> 75 | BO47: 0 | BP47: 0 | BQ47: 0 | BR47: 0 | BS47: =SUM(BO47:BR47) -> 0 | BT47: 0 | BU47: 0 | BV47: 0 | BW47: 0 | BX47: =SUM(BT47:BW47) -> 0 | BY47: 0 | BZ47: 0 | CA47: 0 | CD47: =A47 -> Income Tax Benefit (Expense)- Extraordinary income (expenses) | CE47: =B47 -> 0 | CF47: =C47 -> -5.6405 | CG47: =D47 -> 51.0757 | CH47: =E47 -> 0 | CI47: =F47 -> -7.841148 | CJ47: =K47 -> -0.38261527 | CK47: =P47 -> -17.2615 | CL47: =U47 -> -28.7728 | CM47: =Z47 -> -6.7 | CN47: =AE47 -> -5.5 | CO47: =AJ47 -> -15 | CP47: =AO47 -> -65 | CQ47: =AT47 -> -81 | CR47: =AY47 -> -336 | CS47: =BD47 -> -49 | CT47: =BI47 -> 263 | CU47: =BN47 -> 75 | CV47: =BS47 -> 0 | CW47: =BX47 -> 0 | CX47: =BY47 -> 0 | CY47: =BZ47 -> 0 | CZ47: =CA47 -> 0 | DB47: =SUM(BO47,BP47,BQ47,BR47) -> 0
A48: Income Tax Benefit (Expense) | B48: =B46+B47 -> -238.027 | C48: =C46+C47 -> -331.0695 | D48: =D46+D47 -> -391.3903 | E48: =E46+E47 -> -412.495 | F48: =F46+F47 -> -523.49715 | G48: =G46+G47 -> -53.2926 | H48: =H46+H47 -> -130.887 | I48: =I46+I47 -> -232.4778 | ... CA48: =CA46+CA47 -> -805.66241 | CD48: =A48 -> Income Tax Benefit (Expense) | CE48: =B48 -> -238.027 | CF48: =C48 -> -331.0695 | CG48: =D48 -> -391.3903 | CH48: =E48 -> -412.495 | CI48: =F48 -> -523.49715 | CJ48: =K48 -> -522.97462 | CK48: =P48 -> -626.2345 | CL48: =U48 -> -508.4678 | CM48: =Z48 -> -435.808 | CN48: =AE48 -> -493.047 | CO48: =AJ48 -> -490.7 | CP48: =AO48 -> -469 | CQ48: =AT48 -> -515 | CR48: =AY48 -> -581 | CS48: =BD48 -> -597 | CT48: =BI48 -> -697 | CU48: =BN48 -> -748 | CV48: =BS48 -> -602.26614 | CW48: =BX48 -> -660.20634 | CX48: =BY48 -> -706.49749 | CY48: =BZ48 -> -757.48985 | CZ48: =CA48 -> -805.66241 | DB48: =SUM(BO48,BP48,BQ48,BR48) -> -602.26614
A49: Tax rate | K49: =-K48/K45 -> 0.36410655 | L49: =-L48/L45 -> 0.37582615 | M49: =-M48/M45 -> 0.37500169 | N49: =-N48/N45 -> 0.37500017 | O49: =-O48/O45 -> 0.37926601 | P49: =-P48/P45 -> 0.37583872 | Q49: =-Q48/Q45 -> 0.3652856 | R49: =-R48/R45 -> 0.37135156 | ... CA49: =-CA48/CA45 -> 0.215 | CD49: =A49 -> Tax rate | CG49: =-CG48/CG45 -> 0.3917911 | CH49: =-CH48/CH45 -> 0.3528901 | CI49: =-CI48/CI45 -> 0.37881706 | CJ49: =-CJ48/CJ45 -> 0.36410655 | CK49: =-CK48/CK45 -> 0.37583872 | CL49: =-CL48/CL45 -> 0.37047914 | CM49: =-CM48/CM45 -> 0.36398684 | CN49: =-CN48/CN45 -> 0.36399106 | ... CZ49: =-CZ48/CZ45 -> 0.215
B50: ______ | C50: ______ | D50: ______ | E50: ______ | F50: ______ | G50: ______ | H50: ______ | I50: ______ | J50: ______ | K50: ______ | L50: ______ | M50: ______ | N50: ______ | O50: ______ | P50: ______ | Q50: ______ | R50: ______ | S50: ______ | T50: ______ | U50: ______ | V50: ______ | W50: ______ | X50: ______ | Y50: ______ | Z50: ______ | AA50: ______ | AB50: ______ | AC50: ______ | AD50: ______ | AE50: ______ | AF50: ______ | AG50: ______ | AH50: ______ | AI50: ______ | AJ50: ______ | AK50: ______ | AL50: ______ | AM50: ______ | AN50: ______ | AO50: ______ | AP50: ______ | AQ50: ______ | AR50: ______ | AS50: ______ | AT50: ______ | AU50: ______ | AV50: ______ | AW50: ______ | AX50: ______ | AY50: ______ | AZ50: ______ | BA50: ______ | BB50: ______ | BC50: ______ | BD50: ______ | BE50: ______ | BF50: ______ | BG50: ______ | BH50: ______ | BI50: ______ | BJ50: ______ | BK50: ______ | BL50: ______ | BM50: ______ | BN50: ______ | BO50: ______ | BP50: ______ | BQ50: ______ | BR50: ______ | BS50: ______ | BT50: ______ | BU50: ______ | BV50: ______ | BW50: ______ | BX50: ______ | BY50: ______ | BZ50: ______ | CA50: ______ | CE50: ______ | CF50: ______ | CG50: ______ | CH50: ______ | CI50: ______ | CJ50: ______ | CK50: ______ | CL50: ______ | CM50: ______ | CN50: ______ | CO50: ______ | CP50: ______ | CQ50: ______ | CR50: ______ | CS50: ______ | CT50: ______ | CU50: ______ | CV50: ______ | CW50: ______ | CX50: ______ | CY50: ______ | CZ50: ______
A51: Income from Continuing Operations | B51: =B45+B48 -> 377.031 | C51: =C45+C48 -> 580.8255 | D51: =D45+D48 -> 607.5867 | E51: =E45+E48 -> 756.41 | F51: =F45+F48 -> 858.42885 | G51: =G45+G48 -> 88.6904 | H51: =H45+H48 -> 220.961 | I51: =I45+I48 -> 391.6362 | ... CA51: =CA45+CA48 -> 2941.6046 | CD51: =A51 -> Income from Continuing Operations | CE51: =CE45+CE48 -> 377.031 | CF51: =CF45+CF48 -> 580.8255 | CG51: =CG45+CG48 -> 607.5867 | CH51: =CH45+CH48 -> 756.41 | CI51: =CI45+CI48 -> 858.42885 | CJ51: =CJ45+CJ48 -> 913.34838 | CK51: =CK45+CK48 -> 1039.9975 | CL51: =CL45+CL48 -> 863.9922 | ... CO51: =CO45+CO48 -> 1372.1 | CP51: =AO51 -> 835 | CQ51: =AT51 -> 1003 | CR51: =AY51 -> 1175 | CS51: =BD51 -> 1354 | CT51: =BI51 -> 1477 | CU51: =BN51 -> 1861 | CV51: =BS51 -> 2196.2508 | CW51: =BX51 -> 2410.5208 | CX51: =BY51 -> 2579.5373 | CY51: =BZ51 -> 2765.7187 | CZ51: =CA51 -> 2941.6046 | DB51: =SUM(BO51,BP51,BQ51,BR51) -> 2196.2508
A53: Income (loss) from Discontinued Operations, net | B53: 0 | C53: =5.517-0.723 -> 4.794 | D53: -0.161 | E53: -0.587 | F53: 0 | G53: 0 | H53: 0 | I53: 0 | J53: =0-SUM(G53:I53) -> 0 | K53: =SUM(G53:J53) -> 0 | L53: 0 | M53: 0 | N53: 0 | O53: =0-SUM(L53:N53) -> 0 | P53: =SUM(L53:O53) -> 0 | Q53: 0 | R53: 0 | S53: 0 | T53: =0-SUM(Q53:S53) -> 0 | U53: =SUM(Q53:T53) -> 0 | V53: 0 | W53: 0 | X53: 0 | Y53: =0-SUM(V53:X53) -> 0 | Z53: =SUM(V53:Y53) -> 0 | AA53: 0 | AB53: 0 | AC53: 0.7 | AD53: =0-SUM(AA53:AC53) -> -0.7 | AE53: =SUM(AA53:AD53) -> 0 | AF53: -1 | AG53: 0 | AH53: -1.1 | AI53: =108 -> 108 | AJ53: =SUM(AF53:AI53) -> 105.9 | AK53: -36 | AL53: 40 | AM53: 165 | AN53: -404 | AO53: =SUM(AK53:AN53) -> -235 | AP53: =-31+612+1 -> 582 | AQ53: 4 | AR53: =7-20 -> -13 | AS53: 6 | AT53: =SUM(AP53:AS53) -> 579 | AU53: 7 | AV53: 6 | AW53: 2 | AX53: =3+160 -> 163 | AY53: =SUM(AU53:AX53) -> 178 | AZ53: 0 | BA53: 0 | BB53: 0 | BC53: 0 | BD53: =SUM(AZ53:BC53) -> 0 | BE53: 0 | BF53: 0 | BG53: 0 | BH53: 0 | BI53: =SUM(BE53:BH53) -> 0 | BJ53: 0 | BK53: 0 | BL53: 0 | BM53: 0 | BN53: =SUM(BJ53:BM53) -> 0 | BO53: 0 | BP53: 0 | BQ53: 0 | BR53: 0 | BS53: =SUM(BO53:BR53) -> 0 | BT53: 0 | BU53: 0 | BV53: 0 | BW53: 0 | BX53: =SUM(BT53:BW53) -> 0 | BY53: 0 | BZ53: 0 | CA53: 0 | CD53: =A53 -> Income (loss) from Discontinued Operations, net | CE53: =B53 -> 0 | CF53: =C53 -> 4.794 | CG53: =D53 -> -0.161 | CH53: =E53 -> -0.587 | CI53: =F53 -> 0 | CJ53: =K53 -> 0 | CK53: =P53 -> 0 | CL53: =U53 -> 0 | CM53: =Z53 -> 0 | CN53: =AE53 -> 0 | CO53: =AJ53 -> 105.9 | CP53: =AO53 -> -235 | CQ53: =AT53 -> 579 | CR53: =AY53 -> 178 | CS53: =BD53 -> 0 | CT53: =BI53 -> 0 | CU53: =BN53 -> 0 | CV53: =BS53 -> 0 | CW53: =BX53 -> 0 | CX53: =BY53 -> 0 | CY53: =BZ53 -> 0 | CZ53: =CA53 -> 0 | DB53: =SUM(BO53,BP53,BQ53,BR53) -> 0
A54: Extraordinary (charges) / gains | B54: 0 | C54: =-14.5*(1-C245) -> -8.8595 | D54: =131.3*(1-D245) -> 80.2243 | E54: 0 | F54: =(-23.2+1.236)*(1-F245) -> -14.122852 | G54: =-23.8*(1-G245) -> -14.4704 | H54: 0 | I54: =-15.4*(1-I245) -> -9.3632 | J54: =-31.5*(1-J242)-SUM(G54:I54) -> -7.2837847 | K54: =SUM(G54:J54) -> -31.117385 | L54: =17.305*(1-L245) -> 10.469525 | M54: 0 | N54: 0 | O54: =-43.7*(1-O245)-SUM(L54:N54) -> -36.908025 | P54: =SUM(L54:O54) -> -26.4385 | Q54: 0 | R54: =-23.7*(1-R245) -> -14.4096 | S54: =-23.4*(1-S245) -> -14.2272 | T54: =-73.4*(1-T245)-SUM(Q54:S54) -> -15.9904 | U54: =SUM(Q54:T54) -> -44.6272 | V54: 0 | W54: =(-15.2-13.849)*(1-W245) -> -17.748939 | X54: 0 | Y54: =-11.8-SUM(V54:X54) -> 5.948939 | Z54: =SUM(V54:Y54) -> -11.8 | AA54: 0 | AB54: 0 | AC54: =7.1-2.3 -> 4.8 | AD54: =-9.6-2.3-SUM(AA54:AC54) -> -16.7 | AE54: =SUM(AA54:AD54) -> -11.9 | AF54: 0 | AG54: 0 | AH54: 0 | AI54: =-'Op Metrics'!AI140-AI47 -> -27 | AJ54: =SUM(AF54:AI54) -> -27 | AK54: =-'Op Metrics'!AK140-AK47 -> -18 | AL54: =-'Op Metrics'!AL140-AL47 -> -24 | AM54: =-'Op Metrics'!AM140-AM47 -> -51 | AN54: =-'Op Metrics'!AN140-AN47 -> -16 | AO54: =SUM(AK54:AN54) -> -109 | AP54: =-'Op Metrics'!AP140-AP47 -> -75 | AQ54: =-'Op Metrics'!AQ140-AQ47 -> -7 | AR54: =-'Op Metrics'!AR140-AR47 -> 17 | AS54: =-'Op Metrics'!AS140-AS47 -> -51 | AT54: =SUM(AP54:AS54) -> -116 | AU54: =-'Op Metrics'!AU140-AU47 -> 0 | AV54: =-'Op Metrics'!AV140-AV47 -> 0 | AW54: =-'Op Metrics'!AW140-AW47 -> -93 | AX54: =-'Op Metrics'!AX140-AX47 -> -1273 | AY54: =SUM(AU54:AX54) -> -1366 | AZ54: =-'Op Metrics'!AZ140-AZ47 -> 4 | BA54: =-'Op Metrics'!BA140-BA47 -> 18 | BB54: =-'Op Metrics'!BB140-BB47 -> -73 | BC54: =-'Op Metrics'!BC140-BC47 -> -36 | BD54: =SUM(AZ54:BC54) -> -87 | BE54: =-'Op Metrics'!BE140-BE47 -> -10 | BF54: =-'Op Metrics'!BF140-BF47 -> 13 | BG54: =-'Op Metrics'!BG140-BG47 -> 527 | BH54: =-'Op Metrics'!BH140-BH47-21 -> 219 | BI54: =SUM(BE54:BH54) -> 749 | BJ54: =-'Op Metrics'!BJ140-BJ47 -> -8 | BK54: =-'Op Metrics'!BK140-BK47 -> -8 | BL54: =-'Op Metrics'!BL140-BL47 -> -12 | BM54: =-'Op Metrics'!BM140-BM47 -> -195 | BN54: =SUM(BJ54:BM54) -> -223 | BO54: =-'Op Metrics'!BO140-BO47 -> 0 | BP54: =-'Op Metrics'!BP140-BP47 -> -10.833333 | BQ54: =-'Op Metrics'!BQ140-BQ47 -> -10.833333 | BR54: =-'Op Metrics'!BR140-BR47 -> -10.833333 | BS54: =SUM(BO54:BR54) -> -32.5 | BT54: =-'Op Metrics'!BT140-BT47 -> 0 | BU54: =-'Op Metrics'!BU140-BU47 -> 0 | BV54: =-'Op Metrics'!BV140-BV47 -> 0 | BW54: =-'Op Metrics'!BW140-BW47 -> 0 | BX54: =SUM(BT54:BW54) -> 0 | BY54: 0 | BZ54: 0 | CA54: 0 | CD54: =A54 -> Extraordinary (charges) / gains | CE54: =B54 -> 0 | CF54: =C54 -> -8.8595 | CG54: =D54 -> 80.2243 | CH54: =E54 -> 0 | CI54: =F54 -> -14.122852 | CJ54: =K54 -> -31.117385 | CK54: =P54 -> -26.4385 | CL54: =U54 -> -44.6272 | CM54: =Z54 -> -11.8 | CN54: =AE54 -> -11.9 | CO54: =AJ54 -> -27 | CP54: =AO54 -> -109 | CQ54: =AT54 -> -116 | CR54: =AY54 -> -1366 | CS54: =BD54 -> -87 | CT54: =BI54 -> 749 | CU54: =BN54 -> -223 | CV54: =BS54 -> -32.5 | CW54: =BX54 -> 0 | CX54: =BY54 -> 0 | CY54: =BZ54 -> 0 | CZ54: =CA54 -> 0 | DB54: =SUM(BO54,BP54,BQ54,BR54) -> -32.5
B55: ______ | C55: ______ | D55: ______ | E55: ______ | F55: ______ | G55: ______ | H55: ______ | I55: ______ | J55: ______ | K55: ______ | L55: ______ | M55: ______ | N55: ______ | O55: ______ | P55: ______ | Q55: ______ | R55: ______ | S55: ______ | T55: ______ | U55: ______ | V55: ______ | W55: ______ | X55: ______ | Y55: ______ | Z55: ______ | AA55: ______ | AB55: ______ | AC55: ______ | AD55: ______ | AE55: ______ | AF55: ______ | AG55: ______ | AH55: ______ | AI55: ______ | AJ55: ______ | AK55: ______ | AL55: ______ | AM55: ______ | AN55: ______ | AO55: ______ | AP55: ______ | AQ55: ______ | AR55: ______ | AS55: ______ | AT55: ______ | AU55: ______ | AV55: ______ | AW55: ______ | AX55: ______ | AY55: ______ | AZ55: ______ | BA55: ______ | BB55: ______ | BC55: ______ | BD55: ______ | BE55: ______ | BF55: ______ | BG55: ______ | BH55: ______ | BI55: ______ | BJ55: ______ | BK55: ______ | BL55: ______ | BM55: ______ | BN55: ______ | BO55: ______ | BP55: ______ | BQ55: ______ | BR55: ______ | BS55: ______ | BT55: ______ | BU55: ______ | BV55: ______ | BW55: ______ | BX55: ______ | BY55: ______ | BZ55: ______ | CA55: ______ | CE55: ______ | CF55: ______ | CG55: ______ | CH55: ______ | CI55: ______ | CJ55: ______ | CK55: ______ | CL55: ______ | CM55: ______ | CN55: ______ | CO55: ______ | CP55: ______ | CQ55: ______ | CR55: ______ | CS55: ______ | CT55: ______ | CU55: ______ | CV55: ______ | CW55: ______ | CX55: ______ | CY55: ______ | CZ55: ______
A56: Net Income | B56: =SUM(B51:B54) -> 377.031 | C56: =SUM(C51:C54) -> 576.76 | D56: =SUM(D51:D54) -> 687.65 | E56: =SUM(E51:E54) -> 755.823 | F56: =SUM(F51:F54) -> 844.306 | G56: =SUM(G51:G54) -> 74.22 | H56: =SUM(H51:H54) -> 220.961 | I56: =SUM(I51:I54) -> 382.273 | ... CA56: =SUM(CA51:CA54) -> 2941.6046 | CD56: =A56 -> Net Income | CE56: =SUM(CE51:CE54) -> 377.031 | CF56: =SUM(CF51:CF54) -> 576.76 | CG56: =SUM(CG51:CG54) -> 687.65 | CH56: =SUM(CH51:CH54) -> 755.823 | CI56: =SUM(CI51:CI54) -> 844.306 | CJ56: =SUM(CJ51:CJ54) -> 882.231 | CK56: =SUM(CK51:CK54) -> 1013.559 | CL56: =SUM(CL51:CL54) -> 819.365 | ... CO56: =SUM(CO51:CO54) -> 1451 | CP56: =AO56 -> 491 | CQ56: =AT56 -> 1466 | CR56: =AY56 -> -13 | CS56: =BD56 -> 1267 | CT56: =BI56 -> 2226 | CU56: =BN56 -> 1638 | CV56: =BS56 -> 2163.7508 | CW56: =BX56 -> 2410.5208 | CX56: =BY56 -> 2579.5373 | CY56: =BZ56 -> 2765.7187 | CZ56: =CA56 -> 2941.6046 | DB56: =SUM(BO56,BP56,BQ56,BR56) -> 2163.7508
A58: Less: Net Income Attributable to Noncontrolling Interests | B58: 0 | C58: 0 | D58: 0 | E58: 0 | F58: 0 | G58: 0 | H58: 0 | I58: 0 | J58: 0 | K58: =SUM(G58:J58) -> 0 | L58: 0 | M58: 0 | N58: 0 | O58: 0 | P58: =SUM(L58:O58) -> 0 | Q58: -3.453 | R58: -4.656 | S58: -6.649 | T58: =-19.874-SUM(Q58:S58) -> -5.116 | U58: =SUM(Q58:T58) -> -19.874 | V58: -2.981 | W58: -3.798 | X58: -6.145 | Y58: =-19.259-SUM(V58:X58) -> -6.335 | Z58: =SUM(V58:Y58) -> -19.259 | AA58: -3.7 | AB58: -3.1 | AC58: =-9.8+2.3 -> -7.5 | AD58: =-23.806+2.3-SUM(AA58:AC58) -> -7.206 | AE58: =SUM(AA58:AD58) -> -21.506 | AF58: -4 | AG58: -5 | AH58: -8.3 | AI58: =+-5+-2 -> -7 | AJ58: =SUM(AF58:AI58) -> -24.3 | AK58: =+-5+1 -> -4 | AL58: =+-3-1 -> -4 | AM58: =+-21+-2 -> -23 | AN58: =-52-SUM(AK58:AM58) -> -21 | AO58: =SUM(AK58:AN58) -> -52 | AP58: -21 | AQ58: -23 | AR58: -30 | AS58: =-91-SUM(AP58:AR58) -> -17 | AT58: =SUM(AP58:AS58) -> -91 | AU58: -27.49 | AV58: -24 | AW58: -27 | AX58: -24 | AY58: =SUM(AU58:AX58) -> -102.49 | AZ58: -26 | BA58: -28.1 | BB58: -29 | BC58: -28 | BD58: =SUM(AZ58:BC58) -> -111.1 | BE58: -29 | BF58: -29 | BG58: -31 | BH58: -32 | BI58: =SUM(BE58:BH58) -> -121 | BJ58: -31 | BK58: -36 | BL58: -38 | BM58: -36 | BN58: =SUM(BJ58:BM58) -> -141 | BO58: -43 | BP58: =-'Op Metrics'!BP148 -> -39.912492 | BQ58: =-'Op Metrics'!BQ148 -> -39.461538 | BR58: =-'Op Metrics'!BR148 -> -40.996688 | BS58: =SUM(BO58:BR58) -> -163.37072 | BT58: =-'Op Metrics'!BT148 -> -44.879024 | BU58: =-'Op Metrics'!BU148 -> -43.962957 | BV58: =-'Op Metrics'!BV148 -> -43.886208 | BW58: =-'Op Metrics'!BW148 -> -45.416186 | BX58: =SUM(BT58:BW58) -> -178.14438 | BY58: =-'Op Metrics'!BY148 -> -193.66001 | BZ58: =-'Op Metrics'!BZ148 -> -210.29139 | CA58: =-'Op Metrics'!CA148 -> -227.13479 | CD58: =A58 -> Less: Net Income Attributable to Noncontrolling Interests | CE58: =B58 -> 0 | CF58: =C58 -> 0 | CG58: =D58 -> 0 | CH58: =E58 -> 0 | CI58: =F58 -> 0 | CJ58: =K58 -> 0 | CK58: =P58 -> 0 | CL58: =U58 -> -19.874 | CM58: =Z58 -> -19.259 | CN58: =AE58 -> -21.506 | CO58: =AJ58 -> -24.3 | CP58: =AO58 -> -52 | CQ58: =AT58 -> -91 | CR58: =AY58 -> -102.49 | CS58: =BD58 -> -111.1 | CT58: =BI58 -> -121 | CU58: =BN58 -> -141 | CV58: =BS58 -> -163.37072 | CW58: =BX58 -> -178.14438 | CX58: =BY58 -> -193.66001 | CY58: =BZ58 -> -210.29139 | CZ58: =CA58 -> -227.13479 | DB58: =SUM(BO58,BP58,BQ58,BR58) -> -163.37072
B59: ______ | C59: ______ | D59: ______ | E59: ______ | F59: ______ | G59: ______ | H59: ______ | I59: ______ | J59: ______ | K59: ______ | L59: ______ | M59: ______ | N59: ______ | O59: ______ | P59: ______ | Q59: ______ | R59: ______ | S59: ______ | T59: ______ | U59: ______ | V59: ______ | W59: ______ | X59: ______ | Y59: ______ | Z59: ______ | AA59: ______ | AB59: ______ | AC59: ______ | AD59: ______ | AE59: ______ | AF59: ______ | AG59: ______ | AH59: ______ | AI59: ______ | AJ59: ______ | AK59: ______ | AL59: ______ | AM59: ______ | AN59: ______ | AO59: ______ | AP59: ______ | AQ59: ______ | AR59: ______ | AS59: ______ | AT59: ______ | AU59: ______ | AV59: ______ | AW59: ______ | AX59: ______ | AY59: ______ | AZ59: ______ | BA59: ______ | BB59: ______ | BC59: ______ | BD59: ______ | BE59: ______ | BF59: ______ | BG59: ______ | BH59: ______ | BI59: ______ | BJ59: ______ | BK59: ______ | BL59: ______ | BM59: ______ | BN59: ______ | BO59: ______ | BP59: ______ | BQ59: ______ | BR59: ______ | BS59: ______ | BT59: ______ | BU59: ______ | BV59: ______ | BW59: ______ | BX59: ______ | BY59: ______ | BZ59: ______ | CA59: ______
A60: Net Income to The McGraw-Hill Companies, Inc. | B60: =SUM(B56:B58) -> 377.031 | C60: =SUM(C56:C58) -> 576.76 | D60: =SUM(D56:D58) -> 687.65 | E60: =SUM(E56:E58) -> 755.823 | F60: =SUM(F56:F58) -> 844.306 | G60: =SUM(G56:G58) -> 74.22 | H60: =SUM(H56:H58) -> 220.961 | I60: =SUM(I56:I58) -> 382.273 | ... CA60: =SUM(CA56:CA58) -> 2714.4698 | CD60: =A60 -> Net Income to The McGraw-Hill Companies, Inc. | CE60: =SUM(CE56:CE58) -> 377.031 | CF60: =SUM(CF56:CF58) -> 576.76 | CG60: =SUM(CG56:CG58) -> 687.65 | CH60: =SUM(CH56:CH58) -> 755.823 | CI60: =SUM(CI56:CI58) -> 844.306 | CJ60: =SUM(CJ56:CJ58) -> 882.231 | CK60: =SUM(CK56:CK58) -> 1013.559 | CL60: =SUM(CL56:CL58) -> 799.491 | ... CO60: =SUM(CO56:CO58) -> 1426.7 | CP60: =AO60 -> 439 | CQ60: =AT60 -> 1375 | CR60: =AY60 -> -115.49 | CS60: =BD60 -> 1155.9 | CT60: =BI60 -> 2105 | CU60: =BN60 -> 1497 | CV60: =BS60 -> 2000.3801 | CW60: =BX60 -> 2232.3764 | CX60: =BY60 -> 2385.8773 | CY60: =BZ60 -> 2555.4274 | CZ60: =CA60 -> 2714.4698 | DB60: =SUM(BO60,BP60,BQ60,BR60) -> 2000.3801
A61: Non-GAAP Adjustments | K61: =SUM(G61:J61) -> 0 | P61: =SUM(L61:O61) -> 0 | U61: =SUM(Q61:T61) -> 0 | Z61: =SUM(V61:Y61) -> 0 | AE61: =SUM(AA61:AD61) -> 0 | AF61: 0 | AG61: 0 | AH61: 0 | AI61: 0 | AJ61: =SUM(AF61:AI61) -> 0 | AK61: 0 | AL61: 0 | AM61: 0 | AN61: 0 | AO61: =SUM(AK61:AN61) -> 0 | AP61: 0 | AQ61: 0 | AR61: 0 | AS61: 0 | AT61: =SUM(AP61:AS61) -> 0 | AU61: 0 | AV61: 0 | AW61: 0 | AX61: 0 | AY61: =SUM(AU61:AX61) -> 0 | AZ61: 0 | BA61: 0 | BB61: 0 | BC61: 0 | BD61: =SUM(AZ61:BC61) -> 0 | BE61: 0 | BF61: 0 | BG61: 0 | BH61: 0 | BI61: =SUM(BE61:BH61) -> 0 | BJ61: 0 | BK61: 0 | BL61: 0 | BM61: 0 | BN61: =SUM(BJ61:BM61) -> 0 | BO61: 0 | BP61: 0 | BQ61: 0 | BR61: 0 | BS61: =SUM(BO61:BR61) -> 0 | BT61: 0 | BU61: 0 | BV61: 0 | BW61: 0 | BX61: =SUM(BT61:BW61) -> 0 | BY61: 0 | BZ61: 0 | CA61: 0 | CD61: =A61 -> Non-GAAP Adjustments | CE61: =B61 -> 0 | CF61: =C61 -> 0 | CG61: =D61 -> 0 | CH61: =E61 -> 0 | CI61: =F61 -> 0 | CJ61: =K61 -> 0 | CK61: =P61 -> 0 | CL61: =U61 -> 0 | CM61: =Z61 -> 0 | CN61: =AE61 -> 0 | CO61: =AJ61 -> 0 | CP61: =AO61 -> 0 | CQ61: =AT61 -> 0 | CR61: =AY61 -> 0 | CS61: =BD61 -> 0 | CT61: =BI61 -> 0 | CU61: =BN61 -> 0 | CV61: =BS61 -> 0 | CW61: =BX61 -> 0 | CX61: =BY61 -> 0 | CY61: =BZ61 -> 0 | CZ61: =CA61 -> 0 | DB61: =SUM(BC61,AZ61,BA61,BB61) -> 0
A63: Adjusted Net Income - Cont Ops plus adjustments | B63: =B51+B58 -> 377.031 | C63: =C51+C58 -> 580.8255 | D63: =D51+D58 -> 607.5867 | E63: =E51+E58 -> 756.41 | F63: =F51+F58 -> 858.42885 | G63: =G51+G58 -> 88.6904 | H63: =H51+H58 -> 220.961 | I63: =I51+I58 -> 391.6362 | ... CA63: =CA51+CA58 -> 2714.4698 | CB63: =(CA63/BN63)^(1/5)-1 -> 0.095547757 | CD63: =A63 -> Adjusted Net Income - Cont Ops plus adjustments | CE63: =CE51+CE58 -> 377.031 | CF63: =CF51+CF58 -> 580.8255 | CG63: =CG51+CG58 -> 607.5867 | CH63: =CH51+CH58 -> 756.41 | CI63: =CI51+CI58 -> 858.42885 | CJ63: =CJ51+CJ58 -> 913.34838 | CK63: =CK51+CK58 -> 1039.9975 | CL63: =CL51+CL58 -> 844.1182 | ... CO63: =CO51+CO58 -> 1347.8 | CP63: =AO63 -> 783 | CQ63: =AT63 -> 912 | CR63: =AY63 -> 1072.51 | CS63: =BD63 -> 1242.9 | CT63: =BI63 -> 1356 | CU63: =BN63 -> 1720 | CV63: =BS63 -> 2032.8801 | CW63: =BX63 -> 2232.3764 | CX63: =BY63 -> 2385.8773 | CY63: =BZ63 -> 2555.4274 | CZ63: =CA63 -> 2714.4698 | DB63: =SUM(BO63,BP63,BQ63,BR63) -> 2032.8801
A64: Adjusted Net Income | B64: =B63+B53 -> 377.031 | C64: =C63+C53 -> 585.6195 | D64: =D63+D53 -> 607.4257 | E64: =E63+E53 -> 755.823 | F64: =F63+F53 -> 858.42885 | G64: =G63+G53 -> 88.6904 | H64: =H63+H53 -> 220.961 | I64: =I63+I53 -> 391.6362 | ... CA64: =CA63+CA53 -> 2714.4698 | CB64: =(CA64/BN64)^(1/5)-1 -> 0.095547757 | CD64: =A64 -> Adjusted Net Income | CE64: =CE63+CE53 -> 377.031 | CF64: =CF63+CF53 -> 585.6195 | CG64: =CG63+CG53 -> 607.4257 | CH64: =CH63+CH53 -> 755.823 | CI64: =CI63+CI53 -> 858.42885 | CJ64: =CJ63+CJ53 -> 913.34838 | CK64: =CK63+CK53 -> 1039.9975 | CL64: =CL63+CL53 -> 844.1182 | ... CO64: =CO63+CO53 -> 1453.7 | CP64: =AO64 -> 548 | CQ64: =AT64 -> 1491 | CR64: =AY64 -> 1250.51 | CS64: =BD64 -> 1242.9 | CT64: =BI64 -> 1356 | CU64: =BN64 -> 1720 | CV64: =BS64 -> 2032.8801 | CW64: =BX64 -> 2232.3764 | CX64: =BY64 -> 2385.8773 | CY64: =BZ64 -> 2555.4274 | CZ64: =CA64 -> 2714.4698 | DB64: =SUM(BO64,BP64,BQ64,BR64) -> 2032.8801
A66: Basic Shares Outstanding | B66: =205.83891-12.620573 -> 193.21834 | C66: =205.853583-14.021056 -> 191.83253 | D66: =205.854086-15.45788 -> 190.39621 | E66: =411.709328-32.08241 -> 379.62692 | F66: =411.709328-39.011219 -> 372.69811 | G66: 357.8 | H66: 351.9 | I66: 354.2 | J66: =411.709328-57.750506 -> 353.95882 | K66: =J66 -> 353.95882 | L66: 343.2 | M66: 338.9 | N66: 329 | O66: =411.709328-89.341682 -> 322.36765 | P66: =O66 -> 322.36765 | Q66: 321.3 | R66: 317.6 | S66: 314.5 | T66: =411.709328-97.303901 -> 314.40543 | U66: =T66 -> 314.40543 | V66: 314.5 | W66: 314.8 | X66: 314.9 | Y66: =411.709328-96.368589 -> 315.34074 | Z66: =Y66 -> 315.34074 | AA66: 315.5 | AB66: 309.1 | AC66: 307 | AD66: =411.709328-104.087656 -> 307.62167 | AE66: =AD66 -> 307.62167 | AF66: 304.7 | AG66: 301.3 | AH66: 293.4 | AI66: 278 | AJ66: =AJ312 -> 278 | AK66: 279.7 | AL66: 280.2 | AM66: 277.7 | AN66: =412-133 -> 279 | AO66: =AO312 -> 279 | AP66: 274.1 | AQ66: 275.2 | AR66: 270.8 | AS66: 271 | AT66: =AT312 -> 271 | AU66: 272.2 | AV66: 270.9 | AW66: 271.4 | AX66: 272 | AY66: =AY312 -> 272 | AZ66: 273.7 | BA66: 272.5 | BB66: 270.3 | BC66: 265.2 | BD66: =BD312 -> 265.2 | BE66: 264.5 | BF66: 263.9 | BG66: 259.1 | BH66: 258.3 | BI66: =BI312 -> 258.3 | BJ66: 257.8 | BK66: 257 | BL66: 255 | BM66: 253.7 | BN66: =BN312 -> 253.7 | BO66: 249.4 | BP66: =BP312 -> 247.96147 | BQ66: =BQ312 -> 247.10466 | BR66: =BR312 -> 245.59456 | BS66: =BS312 -> 245.59456 | BT66: =BT312 -> 244.7081 | BU66: =BU312 -> 243.4103 | BV66: =BV312 -> 242.69119 | BW66: =BW312 -> 241.31584 | ... CA66: =CA312 -> 228.76751 | CD66: =A66 -> Basic Shares Outstanding | CE66: =B66 -> 193.21834 | CF66: =C66 -> 191.83253 | CG66: =D66 -> 190.39621 | CH66: =E66 -> 379.62692 | CI66: =F66 -> 372.69811 | CJ66: =K66 -> 353.95882 | CK66: =P66 -> 322.36765 | CL66: =U66 -> 314.40543 | CM66: =Z66 -> 315.34074 | CN66: =AE66 -> 307.62167 | CO66: =AJ66 -> 278 | CP66: =AO66 -> 279 | CQ66: =AT66 -> 271 | CR66: =AY66 -> 272 | CS66: =BD66 -> 265.2 | CT66: =BI66 -> 258.3 | CU66: =BN66 -> 253.7 | CV66: =BS66 -> 245.59456 | CW66: =BX66 -> 241.31584 | CX66: =BY66 -> 237.18463 | CY66: =BZ66 -> 233.00199 | CZ66: =CA66 -> 228.76751
A67: Average Basic Shares Outstanding | B67: 193.888 | C67: 192.888 | D67: 190.492 | E67: 379.688 | F67: 375.006 | G67: 367.456 | H67: 351.9 | I67: 351.139 | J67: 352.965 | K67: 356.467 | L67: 351.215 | M67: 340.183 | N67: 330.249 | O67: 324.35 | P67: 336.21 | Q67: 319.945 | R67: 317.746 | S67: 313.105 | T67: 311.215 | U67: 315.559 | V67: 312.017 | W67: 312.226 | X67: 312.471 | Y67: 312.687 | Z67: 312.223 | AA67: 313.4 | AB67: 311.2 | AC67: 307.2 | AD67: 305.928 | AE67: 309.379 | AF67: 305.2 | AG67: 303.6 | AH67: 297.8 | AI67: 286 | AJ67: 298 | AK67: 278 | AL67: 279.7 | AM67: =278.7 -> 278.7 | AN67: 277.9 | AO67: 278.6 | AP67: 280.5 | AQ67: 274.3 | AR67: 272.8 | AS67: 270.4 | AT67: 274.5 | AU67: 271.8 | AV67: 271.5 | AW67: =AVERAGE(AV66:AW66) -> 271.15 | AX67: =AVERAGE(AW66:AX66) -> 271.7 | AY67: =AVERAGE(AU67:AX67) -> 271.5375 | AZ67: 273.5 | BA67: 273.1 | BB67: 271.3 | BC67: 268.5 | BD67: =AVERAGE(AZ67:BC67) -> 271.6 | BE67: 265 | BF67: 264.5 | BG67: 262.9 | BH67: 258.9 | BI67: =AVERAGE(BE67:BH67) -> 262.825 | BJ67: 258.2 | BK67: 257.3 | BL67: 255.5 | BM67: 254.4 | BN67: =AVERAGE(BJ67:BM67) -> 256.35 | BO67: 252.4 | BP67: =AVERAGE(BO66:BP66) -> 248.68074 | BQ67: =AVERAGE(BP66:BQ66) -> 247.53307 | BR67: =AVERAGE(BQ66:BR66) -> 246.34961 | BS67: =AVERAGE(BO67:BR67) -> 248.74085 | BT67: =AVERAGE(BT66,BR66) -> 245.15133 | BU67: =AVERAGE(BT66:BU66) -> 244.0592 | BV67: =AVERAGE(BU66:BV66) -> 243.05074 | BW67: =AVERAGE(BV66:BW66) -> 242.00352 | BX67: =AVERAGE(BT67:BW67) -> 243.5662 | BY67: =AVERAGE(BX66:BY66) -> 239.25023 | BZ67: =AVERAGE(BY66:BZ66) -> 235.09331 | CA67: =AVERAGE(BZ66:CA66) -> 230.88475 | CD67: =A67 -> Average Basic Shares Outstanding | CE67: =B67 -> 193.888 | CF67: =C67 -> 192.888 | CG67: =D67 -> 190.492 | CH67: =E67 -> 379.688 | CI67: =F67 -> 375.006 | CJ67: =K67 -> 356.467 | CK67: =P67 -> 336.21 | CL67: =U67 -> 315.559 | CM67: =Z67 -> 312.223 | CN67: =AE67 -> 309.379 | CO67: =AJ67 -> 298 | CP67: =AO67 -> 278.6 | CQ67: =AT67 -> 274.5 | CR67: =AY67 -> 271.5375 | CS67: =BD67 -> 271.6 | CT67: =BI67 -> 262.825 | CU67: =BN67 -> 256.35 | CV67: =BS67 -> 248.74085 | CW67: =BX67 -> 243.5662 | CX67: =BY67 -> 239.25023 | CY67: =BZ67 -> 235.09331 | CZ67: =CA67 -> 230.88475
A68: Diluted Shares Outstanding | B68: 195.873 | C68: 194.573 | D68: 192.005 | E68: 385.824 | F68: 382.57 | G68: 377.333 | H68: 365.507 | I68: 360.935 | J68: 364.16 | K68: 366.878 | L68: 361.497 | M68: 350.298 | N68: 337.733 | O68: 330.765 | P68: 344.785 | Q68: 323.4 | R68: 321.087 | S68: 317.203 | T68: 312.834 | U68: 318.687 | V68: 312.017 | W68: 313.033 | X68: 313.642 | Y68: 314.482 | Z68: 313.296 | AA68: 316.3 | AB68: 313.2 | AC68: 309.3 | AD68: 310.323 | AE68: 312.22 | AF68: 309.6 | AG68: 309.2 | AH68: 303.6 | AI68: 292 | AJ68: 303.9 | AK68: 283.8 | AL68: 285.3 | AM68: 284.6 | AN68: 284.7 | AO68: 284.6 | AP68: 284.3 | AQ68: 278.3 | AR68: 278.8 | AS68: 278 | AT68: 279.8 | AU68: 277.2 | AV68: 276.1 | AW68: 275.4 | AX68: =+AW68-AW66+AX66 -> 276 | AY68: =AVERAGE(AU68:AX68) -> 276.175 | AZ68: 276.3 | BA68: 275.7 | BB68: 274.4 | BC68: 272.1 | BD68: =AVERAGE(AZ68:BC68) -> 274.625 | BE68: 267.2 | BF68: 266.7 | BG68: 265.3 | BH68: 261.6 | BI68: =AVERAGE(BE68:BH68) -> 265.2 | BJ68: 260.8 | BK68: 259.9 | BL68: 257.9 | BM68: 257 | BN68: =AVERAGE(BJ68:BM68) -> 258.9 | BO68: 254.4 | BP68: =BP67*BO68/BO67 -> 250.65127 | BQ68: =BQ67*BP68/BP67 -> 249.4945 | BR68: =BR67*BQ68/BQ67 -> 248.30167 | BS68: =AVERAGE(BO68:BR68) -> 250.71186 | BT68: =BT67*BR68/BR67 -> 247.09389 | BU68: =BU67*BT68/BT67 -> 245.9931 | BV68: =BV67*BU68/BU67 -> 244.97666 | BW68: =BW67*BV68/BV67 -> 243.92114 | BX68: =AVERAGE(BT68:BW68) -> 245.4962 | BY68: =BY67*BX68/BX67 -> 241.14604 | BZ68: =BZ67*BY68/BY67 -> 236.95617 | CA68: =CA67*BZ68/BZ67 -> 232.71427 | CD68: =A68 -> Diluted Shares Outstanding | CE68: =B68 -> 195.873 | CF68: =C68 -> 194.573 | CG68: =D68 -> 192.005 | CH68: =E68 -> 385.824 | CI68: =F68 -> 382.57 | CJ68: =K68 -> 366.878 | CK68: =P68 -> 344.785 | CL68: =U68 -> 318.687 | CM68: =Z68 -> 313.296 | CN68: =AE68 -> 312.22 | CO68: =AJ68 -> 303.9 | CP68: =AO68 -> 284.6 | CQ68: =AT68 -> 279.8 | CR68: =AY68 -> 276.175 | CS68: =BD68 -> 274.625 | CT68: =BI68 -> 265.2 | CU68: =BN68 -> 258.9 | CV68: =BS68 -> 250.71186 | CW68: =BX68 -> 245.4962 | CX68: =BY68 -> 241.14604 | CY68: =BZ68 -> 236.95617 | CZ68: =CA68 -> 232.71427
A69: Common Dividend Per Share | B69: 0.98 | C69: 1.02 | D69: 1.08 | E69: 0.6 | F69: 0.66 | G69: 0.1815 | H69: 0.1815 | I69: 0.1815 | J69: 0.1815 | K69: 0.726 | L69: 0.205 | M69: 0.205 | N69: 0.205 | O69: 0.205 | P69: 0.82 | Q69: 0.22 | R69: 0.22 | S69: 0.22 | T69: 0.22 | U69: 0.88 | V69: 0.225 | W69: 0.225 | X69: 0.225 | Y69: 0.225 | Z69: 0.9 | AA69: 0.235 | AB69: 0.235 | AC69: 0.235 | AD69: 0.235 | AE69: 0.94 | AF69: 0.25 | AG69: 0.25 | AH69: 0.25 | AI69: =1-SUM(AF69:AH69) -> 0.25 | AJ69: =SUM(AF69:AI69) -> 1 | AK69: 0.255 | AL69: 0.255 | AM69: 0.255 | AN69: 0.255 | AO69: =SUM(AK69:AN69) -> 1.02 | AP69: 0.28 | AQ69: 0.28 | AR69: 0.28 | AS69: 0.28 | AT69: =SUM(AP69:AS69) -> 1.12 | AU69: 0.3 | AV69: 0.3 | AW69: 0.3 | AX69: 0.3 | AY69: =SUM(AU69:AX69) -> 1.2 | AZ69: 0.33 | BA69: 0.33 | BB69: 0.33 | BC69: 0.33 | BD69: =SUM(AZ69:BC69) -> 1.32 | BE69: 0.36 | BF69: =-BF119/BF67 -> 0.35916824 | BG69: =-BG119/BG67 -> 0.36135413 | BH69: =-BH119/BH67 -> 0.36307455 | BI69: =SUM(BE69:BH69) -> 1.4435969 | BJ69: =-BJ119/BJ67 -> 0.41053447 | BK69: =-BK119/BK67 -> 0.41197046 | BL69: =-BL119/BL67 -> 0.40704501 | BM69: =-BM119/BM67 -> 0.41273585 | BN69: =SUM(BJ69:BM69) -> 1.6422858 | BO69: =-BO119/BO67 -> 0.50316957 | BP69: =-BP119/BP67 -> 0.5077493 | BQ69: =-BQ119/BQ67 -> 0.50834082 | BR69: =-BR119/BR67 -> 0.5076614 | BS69: =SUM(BO69:BR69) -> 2.0269211 | BT69: =-BT119/BT67 -> 0.88496737 | BU69: =-BU119/BU67 -> 0.8842131 | BV69: =-BV119/BV67 -> 0.88525876 | BW69: =-BW119/BW67 -> 0.88405104 | BX69: =SUM(BT69:BW69) -> 3.5384903 | BY69: =-BY119/BY67 -> 3.8692881 | BZ69: =-BZ119/BZ67 -> 4.2332439 | CA69: =-CA119/CA67 -> 4.5600643 | CD69: =A69 -> Common Dividend Per Share | CE69: =B69 -> 0.98 | CF69: =C69 -> 1.02 | CG69: =D69 -> 1.08 | CH69: =E69 -> 0.6 | CI69: =F69 -> 0.66 | CJ69: =K69 -> 0.726 | CK69: =P69 -> 0.82 | CL69: =U69 -> 0.88 | CM69: =Z69 -> 0.9 | CN69: =AE69 -> 0.94 | CO69: =AJ69 -> 1 | CP69: =AO69 -> 1.02 | CQ69: =AT69 -> 1.12 | CR69: =AY69 -> 1.2 | CS69: =BD69 -> 1.32 | CT69: =BI69 -> 1.4435969 | CU69: =BN69 -> 1.6422858 | CV69: =BS69 -> 2.0269211 | CW69: =BX69 -> 3.5384903 | CX69: =BY69 -> 3.8692881 | CY69: =BZ69 -> 4.2332439 | CZ69: =CA69 -> 4.5600643
A70: Avg. Diluted Shares Outstanding | B70: =B68 -> 195.873 | C70: =C68 -> 194.573 | D70: =D68 -> 192.005 | E70: =E68 -> 385.824 | F70: =F68 -> 382.57 | G70: =G68 -> 377.333 | H70: =H68 -> 365.507 | I70: =I68 -> 360.935 | ... AN70: =AN68 -> 284.7 | AO70: =AVERAGE(AK70:AN70) -> 284.6 | AP70: =AP68 -> 284.3 | AQ70: =AQ68 -> 278.3 | AR70: =AR68 -> 278.8 | AS70: =AS68 -> 278 | AT70: =AVERAGE(AP70:AS70) -> 279.85 | AU70: =AU68 -> 277.2 | AV70: =AV68 -> 276.1 | AW70: =AW68 -> 275.4 | AX70: 276.2 | AY70: =AVERAGE(AU70:AX70) -> 276.225 | AZ70: =AZ68 -> 276.3 | BA70: =BA68 -> 275.7 | BB70: =BB68 -> 274.4 | BC70: =BC68 -> 272.1 | BD70: =AVERAGE(AZ70:BC70) -> 274.625 | BE70: =BE68 -> 267.2 | BF70: =BF68 -> 266.7 | BG70: =BG68 -> 265.3 | BH70: =BH68 -> 261.6 | BI70: =AVERAGE(BE70:BH70) -> 265.2 | BJ70: =BJ68 -> 260.8 | BK70: =BK68 -> 259.9 | BL70: =BL68 -> 257.9 | BM70: =BM68 -> 257 | BN70: =AVERAGE(BJ70:BM70) -> 258.9 | BO70: =BO68 -> 254.4 | BP70: =BP68 -> 250.65127 | BQ70: =BQ68 -> 249.4945 | BR70: =BR68 -> 248.30167 | BS70: =AVERAGE(BO70:BR70) -> 250.71186 | BT70: =BT68 -> 247.09389 | BU70: =BU68 -> 245.9931 | BV70: =BV68 -> 244.97666 | BW70: =BW68 -> 243.92114 | BX70: =AVERAGE(BT70:BW70) -> 245.4962 | BY70: =BY68 -> 241.14604 | BZ70: =BZ68 -> 236.95617 | CA70: =CA68 -> 232.71427 | CD70: =A70 -> Avg. Diluted Shares Outstanding | CE70: =B70 -> 195.873 | CF70: =C70 -> 194.573 | CG70: =D70 -> 192.005 | CH70: =E70 -> 385.824 | CI70: =F70 -> 382.57 | CJ70: =K70 -> 366.878 | CK70: =P70 -> 344.785 | CL70: =U70 -> 318.687 | CM70: =Z70 -> 313.296 | CN70: =AE70 -> 312.22 | CO70: =AJ70 -> 303.9 | CP70: =AO70 -> 284.6 | CQ70: =AT70 -> 279.85 | CR70: =AY70 -> 276.225 | CS70: =BD70 -> 274.625 | CT70: =BI70 -> 265.2 | CU70: =BN70 -> 258.9 | CV70: =BS70 -> 250.71186 | CW70: =BX70 -> 245.4962 | CX70: =BY70 -> 241.14604 | CY70: =BZ70 -> 236.95617 | CZ70: =CA70 -> 232.71427
A71: Diluted GAAP EPS Reported | B71: =B60/B70 -> 1.9248748 | C71: =C60/C70 -> 2.9642345 | D71: =D60/D70 -> 3.5814172 | E71: =E60/E70 -> 1.9589839 | F71: =F60/F70 -> 2.2069321 | G71: =G60/G70 -> 0.19669629 | H71: =H60/H70 -> 0.60453288 | I71: =I60/I70 -> 1.0591187 | ... AW71: =AW60/AW70 -> 0.68990559 | AX71: =AX60/AX67 -> -3.1100478 | AY71: =AY60/AY70 -> -0.41810119 | AZ71: =AZ60/AZ70 -> 1.0966341 | BA71: =BA60/BA70 -> 1.2800145 | BB71: =BB60/BB70 -> 0.91836735 | BC71: =BC60/BC70 -> 0.91142962 | BD71: =BD60/BD70 -> 4.2090123 | BE71: =BE60/BE70 -> 1.1002994 | BF71: =BF60/BF70 -> 1.4360705 | ... CA71: =CA60/CA70 -> 11.664389 | CD71: =A71 -> Diluted GAAP EPS Reported | CE71: =B71 -> 1.9248748 | CF71: =C71 -> 2.9642345 | CG71: =D71 -> 3.5814172 | CH71: =E71 -> 1.9589839 | CI71: =F71 -> 2.2069321 | CJ71: =K71 -> 2.4046986 | CK71: =P71 -> 2.9396842 | CL71: =U71 -> 2.5087029 | CM71: =Z71 -> 2.3315044 | CN71: =AE71 -> 2.6523125 | CO71: =AJ71 -> 2.9967094 | CP71: =AO71 -> 1.5425158 | CQ71: =AT71 -> 4.9133464 | CR71: =AY71 -> -0.41810119 | CS71: =BD71 -> 4.2090123 | CT71: =BI71 -> 7.9374057 | CU71: =BN71 -> 5.7821553 | CV71: =BS71 -> 7.9788011 | CW71: =BX71 -> 9.0933239 | CX71: =BY71 -> 9.8939106 | CY71: =BZ71 -> 10.784388 | CZ71: =CA71 -> 11.664389
A72: Adj. Diluted EPS (MW), Cont | B72: =B63/B68 -> 1.9248748 | C72: =C63/C68 -> 2.985129 | D72: =D63/D68 -> 3.1644317 | E72: =E63/E68 -> 1.9605053 | F72: =F63/F68 -> 2.2438478 | G72: =G63/G68 -> 0.23504544 | H72: =H63/H68 -> 0.60453288 | I72: =I63/I68 -> 1.0850602 | ... AI72: =AI63/AI68 -> 0.45547945 | AJ72: =+SUM(AF72:AI72) -> 2.7368812 | AK72: =AK63/AK68 -> 0.62367865 | AL72: =AL63/AL68 -> 0.70101647 | AM72: =AM63/AM68 -> 0.70274069 | AN72: =AN63/AN68 -> 0.72356867 | AO72: =+SUM(AK72:AN72) -> 2.7510045 | AP72: =AP63/AP68 -> 0.80196975 | AQ72: =AQ63/AQ68 -> 0.92346389 | AR72: =AR63/AR68 -> 0.75681492 | AS72: =AS63/AS68 -> 0.77697842 | AT72: =+SUM(AP72:AS72) -> 3.259227 | AU72: =AU63/AU68 -> 0.86944444 | AV72: =AV63/AV68 -> 1.0340456 | AW72: =AW63/AW70 -> 1.0203341 | AX72: =AX63/AX70 -> 0.95944967 | AY72: =+SUM(AU72:AX72) -> 3.8832738 | AZ72: =AZ63/AZ70+0.004 -> 1.0861571 | BA72: =BA63/BA70 -> 1.2147262 | BB72: =BB63/BB70 -> 1.1844023 | BC72: =BC63/BC70 -> 1.0437339 | BD72: =BD63/BD68 -> 4.5258079 | BE72: =BE63/BE68 -> 1.1377246 | BF72: =BF63/BF68 -> 1.3873266 | BG72: =BG63/BG68 -> 1.3720317 | BH72: =BH63/BH68 -> 1.2155963 | BI72: =BI63/BI68 -> 5.1131222 | BJ72: =BJ63/BJ68 -> 1.5605828 | BK72: =BK63/BK68 -> 1.6506349 | ... CA72: =CA63/CA68 -> 11.664389 | CB72: =(CA72/BN72)^(1/5)-1 -> 0.11916243
A73: Adj. Diluted EPS | B73: =B63/B70 -> 1.9248748 | C73: =C63/C70 -> 2.985129 | D73: =D63/D70 -> 3.1644317 | E73: =E63/E70 -> 1.9605053 | F73: =F63/F70 -> 2.2438478 | G73: =G63/G70 -> 0.23504544 | H73: =H63/H70 -> 0.60453288 | I73: =I63/I70 -> 1.0850602 | J73: =J63/J70 -> 0.5823286 | K73: =K64/K70 -> 2.4895153 | L73: =L64/L70 -> 0.36893384 | M73: =M64/M70 -> 0.79097797 | N73: =N64/N70 -> 1.3383886 | O73: =O64/O70 -> 0.53673462 | P73: =P64/P70 -> 3.0163653 | Q73: =Q64/Q70 -> 0.25080396 | R73: =R64/R70 -> 0.70605039 | ... AE73: =AE64/AE70 -> 2.6904266 | AF73: =AF63/AF70 -> 0.39082687 | AG73: =AG63/AG70 -> 0.68240621 | AH73: =AH63/AH70 -> 1.2081686 | AI73: =AI63/AI70 -> 0.45547945 | AJ73: =+SUM(AF73:AI73) -> 2.7368812 | AK73: =AK63/AK70 -> 0.62367865 | AL73: =AL63/AL70 -> 0.70101647 | AM73: =AM63/AM70 -> 0.70274069 | AN73: =AN63/AN70 -> 0.72356867 | AO73: =+SUM(AK73:AN73) -> 2.7510045 | AP73: =AP63/AP70 -> 0.80196975 | AQ73: =AQ63/AQ70 -> 0.92346389 | AR73: =AR63/AR70 -> 0.75681492 | AS73: =AS63/AS70 -> 0.77697842 | AT73: =+SUM(AP73:AS73) -> 3.259227 | AU73: =AU64/AU70 -> 0.89469697 | AV73: =AV64/AV70 -> 1.0557769 | AW73: =AW63/AW70 -> 1.0203341 | AX73: =AX63/AX70 -> 0.95944967 | AY73: =+SUM(AU73:AX73) -> 3.9302576 | AZ73: =AZ63/AZ70 -> 1.0821571 | BA73: =BA63/BA70 -> 1.2147262 | BB73: =BB63/BB70 -> 1.1844023 | BC73: =BC63/BC70 -> 1.0437339 | BD73: =BD64/BD70 -> 4.5258079 | BE73: =BE64/BE70 -> 1.1377246 | BF73: =BF64/BF70 -> 1.3873266 | BG73: =BG64/BG70 -> 1.3720317 | BH73: =BH64/BH70 -> 1.2155963 | BI73: =BI64/BI70 -> 5.1131222 | BJ73: =BJ64/BJ70 -> 1.5605828 | BK73: =BK64/BK70 -> 1.6506349 | ... CA73: =CA64/CA70 -> 11.664389 | CB73: =(CA73/BN73)^(1/5)-1 -> 0.11916243 | CD73: =A73 -> Adj. Diluted EPS | CE73: =B73 -> 1.9248748 | CF73: =C73 -> 2.985129 | CG73: =D73 -> 3.1644317 | CH73: =E73 -> 1.9605053 | CI73: =F73 -> 2.2438478 | CJ73: =K73 -> 2.4895153 | CK73: =P73 -> 3.0163653 | CL73: =U73 -> 2.6487375 | CM73: =Z73 -> 2.3691685 | CN73: =AE73 -> 2.6904266 | CO73: =AJ73 -> 2.7368812 | CP73: =AO73 -> 2.7510045 | CQ73: =AT73 -> 3.259227 | CR73: =AY73 -> 3.9302576 | CS73: =BD73 -> 4.5258079 | CT73: =BI73 -> 5.1131222 | CU73: =BN73 -> 6.6434917 | CV73: =BS73 -> 8.108432 | CW73: =BX73 -> 9.0933239 | CX73: =BY73 -> 9.8939106 | CY73: =BZ73 -> 10.784388 | CZ73: =CA73 -> 11.664389 | DB73: =SUM(BO73,BP73,BQ73,BR73) -> 8.1105876
A75: Cash EPS (Ex-Amort) | CD75: =+A75 -> Cash EPS (Ex-Amort)
A76: Adjusted Net Income | B76: =+B63 -> 377.031 | C76: =+C63 -> 580.8255 | D76: =+D63 -> 607.5867 | E76: =+E63 -> 756.41 | F76: =+F63 -> 858.42885 | G76: =+G63 -> 88.6904 | H76: =+H63 -> 220.961 | I76: =+I63 -> 391.6362 | J76: =+J63 -> 212.06078 | K76: =+SUM(G76:J76) -> 913.34838 | L76: =+L63 -> 133.36848 | M76: =+M63 -> 277.078 | N76: =+N63 -> 452.018 | O76: =+O63 -> 177.53302 | P76: =+SUM(L76:O76) -> 1039.9975 | Q76: =+Q63 -> 81.11 | R76: =+R63 -> 226.7036 | S76: =+S63 -> 404.3932 | T76: =+T63 -> 131.9114 | U76: =+SUM(Q76:T76) -> 844.1182 | V76: =+V63 -> 63.004 | W76: =+W63 -> 181.84194 | X76: =+X63 -> 336.111 | Y76: =+Y63 -> 161.29406 | Z76: =+SUM(V76:Y76) -> 742.251 | AA76: =+AA63 -> 103.3 | AB76: =+AB63 -> 191.1 | AC76: =+AC63 -> 374.4 | AD76: =+AD63 -> 171.205 | AE76: =+SUM(AA76:AD76) -> 840.005 | AF76: =+AF63 -> 121 | AG76: =+AG63 -> 211 | AH76: =+AH63 -> 366.8 | AI76: =+AI63 -> 133 | AJ76: =+SUM(AF76:AI76) -> 831.8 | AK76: =+AK63 -> 177 | AL76: =+AL63 -> 200 | AM76: =+AM63 -> 200 | AN76: =+AN63 -> 206 | AO76: =+SUM(AK76:AN76) -> 783 | AP76: =+AP63 -> 228 | AQ76: =+AQ63 -> 257 | AR76: =+AR63 -> 211 | AS76: =+AS63 -> 216 | AT76: =+SUM(AP76:AS76) -> 912 | AU76: =+AU63 -> 241.01 | AV76: =+AV63 -> 285.5 | AW76: =+AW63 -> 281 | AX76: =+AX63 -> 265 | AY76: =+SUM(AU76:AX76) -> 1072.51 | AZ76: =+AZ63 -> 299 | BA76: =+BA63 -> 334.9 | BB76: =+BB63 -> 325 | BC76: =+BC63 -> 284 | BD76: =+SUM(AZ76:BC76) -> 1242.9 | BE76: =+BE63 -> 304 | BF76: =+BF63 -> 370 | BG76: =+BG63 -> 364 | BH76: =+BH63 -> 318 | BI76: =+SUM(BE76:BH76) -> 1356 | BJ76: =+BJ63 -> 407 | BK76: =+BK63 -> 429 | BL76: =+BL63 -> 426 | BM76: =+BM63 -> 458 | BN76: =+SUM(BJ76:BM76) -> 1720 | BO76: =+BO63 -> 491 | BP76: =+BP63 -> 516.27765 | BQ76: =+BQ63 -> 501.58598 | BR76: =+BR63 -> 524.01643 | BS76: =+SUM(BO76:BR76) -> 2032.8801 | BT76: =+BT63 -> 529.7216 | BU76: =+BU63 -> 569.39058 | BV76: =+BV63 -> 554.8969 | BW76: =+BW63 -> 578.36736 | BX76: =+SUM(BT76:BW76) -> 2232.3764 | BY76: =+BY63 -> 2385.8773 | BZ76: =+BZ63 -> 2555.4274 | CA76: =+CA63 -> 2714.4698 | CD76: =+A76 -> Adjusted Net Income | CE76: =B76 -> 377.031 | CF76: =C76 -> 580.8255 | CG76: =D76 -> 607.5867 | CH76: =E76 -> 756.41 | CI76: =F76 -> 858.42885 | CJ76: =K76 -> 913.34838 | CK76: =P76 -> 1039.9975 | CL76: =U76 -> 844.1182 | CM76: =Z76 -> 742.251 | CN76: =AE76 -> 840.005 | CO76: =AJ76 -> 831.8 | CP76: =AO76 -> 783 | CQ76: =AT76 -> 912 | CR76: =AY76 -> 1072.51 | CS76: =BD76 -> 1242.9 | CT76: =BI76 -> 1356 | CU76: =BN76 -> 1720 | CV76: =BS76 -> 2032.8801 | CW76: =BX76 -> 2232.3764 | CX76: =BY76 -> 2385.8773 | CY76: =BZ76 -> 2555.4274 | CZ76: =CA76 -> 2714.4698
A77: Amortization | B77: =+B36 -> 91.555 | C77: =+C36 -> 36.27 | D77: =+D36 -> 32.971 | E77: =+E36 -> 32.47 | F77: =+F36 -> 44.235 | G77: =+G36 -> 11.926 | H77: =+H36 -> 12.107 | I77: =+I36 -> 12.137 | J77: =+J36 -> 12.217 | K77: =+SUM(G77:J77) -> 48.387 | L77: =+L36 -> 11.612 | M77: =+M36 -> 11.468 | N77: =+N36 -> 11.709 | O77: =+O36 -> 13.614 | P77: =+SUM(L77:O77) -> 48.403 | Q77: =+Q36 -> 14.2 | R77: =+R36 -> 13.144 | S77: =+S36 -> 13.637 | T77: =+T36 -> 17.516 | U77: =+SUM(Q77:T77) -> 58.497 | V77: =+V36 -> 14.204 | W77: =+W36 -> 11.44 | X77: =+X36 -> 11.066 | Y77: =+Y36 -> 16.01 | Z77: =+SUM(V77:Y77) -> 52.72 | AA77: =+AA36 -> 10 | AB77: =+AB36 -> 13 | AC77: =+AC36 -> 8.4 | AD77: =+AD36 -> 14.195 | AE77: =+SUM(AA77:AD77) -> 45.595 | AF77: =+AF36 -> 14 | AG77: =+AG36 -> 14 | AH77: =+AH36 -> 14.8 | AI77: =+AI36 -> 15.2 | AJ77: =+SUM(AF77:AI77) -> 58 | AK77: =+AK36 -> 9 | AL77: =+AL36 -> 11 | AM77: =+AM36 -> 15 | AN77: =+AN36 -> 13 | AO77: =+SUM(AK77:AN77) -> 48 | AP77: =+AP36 -> 12 | AQ77: =+AQ36 -> 13 | AR77: =+AR36 -> 13 | AS77: =+AS36 -> 13 | AT77: =+SUM(AP77:AS77) -> 51 | AU77: =+AU36 -> 12 | AV77: =+AV36 -> 12 | AW77: =+AW36 -> 12 | AX77: =+AX36 -> 12 | AY77: =+SUM(AU77:AX77) -> 48 | AZ77: =+AZ36 -> 11 | BA77: =+BA36 -> 12 | BB77: =+BB36 -> 17 | BC77: =+BC36 -> 27 | BD77: =+SUM(AZ77:BC77) -> 67 | BE77: =+BE36 -> 24 | BF77: =+BF36 -> 23 | BG77: =+BG36 -> 24 | BH77: =+BH36 -> 25 | BI77: =+SUM(BE77:BH77) -> 96 | BJ77: =+BJ36 -> 24 | BK77: =+BK36 -> 25 | BL77: =+BL36 -> 24 | BM77: =+BM36 -> 25 | BN77: =+SUM(BJ77:BM77) -> 98 | BO77: =+BO36 -> 24 | BP77: =+BP36 -> 34.5 | BQ77: =+BQ36 -> 34.5 | BR77: =+BR36 -> 34.5 | BS77: =+SUM(BO77:BR77) -> 127.5 | BT77: =+BT36 -> 30.125 | BU77: =+BU36 -> 30.125 | BV77: =+BV36 -> 30.125 | BW77: =+BW36 -> 30.125 | BX77: =+SUM(BT77:BW77) -> 120.5 | BY77: =+BY36 -> 114.5 | BZ77: =+BZ36 -> 102.5 | CA77: =+CA36 -> 100.5 | CD77: =+A77 -> Amortization | CE77: =B77 -> 91.555 | CF77: =C77 -> 36.27 | CG77: =D77 -> 32.971 | CH77: =E77 -> 32.47 | CI77: =F77 -> 44.235 | CJ77: =K77 -> 48.387 | CK77: =P77 -> 48.403 | CL77: =U77 -> 58.497 | CM77: =Z77 -> 52.72 | CN77: =AE77 -> 45.595 | CO77: =AJ77 -> 58 | CP77: =AO77 -> 48 | CQ77: =AT77 -> 51 | CR77: =AY77 -> 48 | CS77: =BD77 -> 67 | CT77: =BI77 -> 96 | CU77: =BN77 -> 98 | CV77: =BS77 -> 127.5 | CW77: =BX77 -> 120.5 | CX77: =BY77 -> 114.5 | CY77: =BZ77 -> 102.5 | CZ77: =CA77 -> 100.5
A78: Tax Impact | B78: =+-B77*B245 -> -35.614895 | C78: =+-C77*C245 -> -14.10903 | D78: =+-D77*D245 -> -12.825719 | E78: =+-E77*E245 -> -12.79318 | F78: =+-F77*F245 -> -15.791895 | G78: =+-G77*G245 -> -4.674992 | H78: =+-H77*H245 -> -4.745944 | I78: =+-I77*I245 -> -4.757704 | J78: =+-J77*J245 -> -4.789064 | K78: =+SUM(G78:J78) -> -18.967704 | L78: =+-L77*L245 -> -4.58674 | M78: =+-M77*M245 -> -4.52986 | N78: =+-N77*N245 -> -4.625055 | O78: =+-O77*O245 -> -5.37753 | P78: =+SUM(L78:O78) -> -19.119185 | Q78: =+-Q77*Q245 -> -5.5664 | R78: =+-R77*R245 -> -5.152448 | S78: =+-S77*S245 -> -5.345704 | T78: =+-T77*T245 -> -6.866272 | U78: =+SUM(Q78:T78) -> -22.930824 | V78: =+-V77*V245 -> -5.525356 | W78: =+-W77*W245 -> -4.45016 | X78: =+-X77*X245 -> -4.304674 | Y78: =+-Y77*Y245 -> -6.22789 | Z78: =+SUM(V78:Y78) -> -20.50808 | AA78: =+-AA77*AA245 -> -3.89 | AB78: =+-AB77*AB245 -> -5.057 | AC78: =+-AC77*AC245 -> -3.2676 | AD78: =+-AD77*AD245 -> -5.521855 | AE78: =+SUM(AA78:AD78) -> -17.736455 | AF78: =+-AF77*AF245 -> -5.236 | AG78: =+-AG77*AG245 -> -5.236 | AH78: =+-AH77*AH245 -> -5.5352 | AI78: =+-AI77*AI245 -> -5.6848 | AJ78: =+SUM(AF78:AI78) -> -21.692 | AK78: =+-AK77*AK245 -> -3.474 | AL78: =+-AL77*AL245 -> -4.246 | AM78: =+-AM77*AM245 -> -5.79 | AN78: =+-AN77*AN245 -> -5.018 | AO78: =+SUM(AK78:AN78) -> -18.528 | AP78: =+-AP77*AP245 -> -4.632 | AQ78: =+-AQ77*AQ245 -> -5.018 | AR78: =+-AR77*AR245 -> -5.018 | AS78: =+-AS77*AS245 -> -4.914 | AT78: =+SUM(AP78:AS78) -> -19.582 | AU78: =+-AU77*AU245 -> -4.536 | AV78: =+-AV77*AV245 -> -4.536 | AW78: =+-AW77*AW245 -> -4.356 | AX78: =+-AX77*AX245 -> -4.356 | AY78: =+SUM(AU78:AX78) -> -17.784 | AZ78: -4 | BA78: =+-BA77*BA245 -> -4.356 | BB78: =+-BB77*BB245 -> -6.171 | BC78: =20-BC77 -> -7 | BD78: =+SUM(AZ78:BC78) -> -21.527 | BE78: -8 | BF78: -8 | BG78: -8 | BH78: -9 | BI78: =+SUM(BE78:BH78) -> -33 | BJ78: -9 | BK78: -8 | BL78: -9 | BM78: -9 | BN78: =+SUM(BJ78:BM78) -> -35 | BO78: -6 | BP78: =+-BP77*BP245 -> -7.6935 | BQ78: =+-BQ77*BQ245 -> -7.6935 | BR78: =+-BR77*BR245 -> -7.6935 | BS78: =+SUM(BO78:BR78) -> -29.0805 | BT78: =+-BT77*BT245 -> -6.717875 | BU78: =+-BU77*BU245 -> -6.717875 | BV78: =+-BV77*BV245 -> -6.717875 | BW78: =+-BW77*BW245 -> -6.717875 | BX78: =+SUM(BT78:BW78) -> -26.8715 | BY78: =+-BY77*BY245 -> -25.5335 | BZ78: =+-BZ77*BZ245 -> -22.8575 | CA78: =+-CA77*CA245 -> -22.4115 | CD78: =+A78 -> Tax Impact | CE78: =B78 -> -35.614895 | CF78: =C78 -> -14.10903 | CG78: =D78 -> -12.825719 | CH78: =E78 -> -12.79318 | CI78: =F78 -> -15.791895 | CJ78: =K78 -> -18.967704 | CK78: =P78 -> -19.119185 | CL78: =U78 -> -22.930824 | CM78: =Z78 -> -20.50808 | CN78: =AE78 -> -17.736455 | CO78: =AJ78 -> -21.692 | CP78: =AO78 -> -18.528 | CQ78: =AT78 -> -19.582 | CR78: =AY78 -> -17.784 | CS78: =BD78 -> -21.527 | CT78: =BI78 -> -33 | CU78: =BN78 -> -35 | CV78: =BS78 -> -29.0805 | CW78: =BX78 -> -26.8715 | CX78: =BY78 -> -25.5335 | CY78: =BZ78 -> -22.8575 | CZ78: =CA78 -> -22.4115
A79: Adj. Net Income (Ex- Amort) | B79: =+SUM(B76:B78) -> 432.9711 | C79: =+SUM(C76:C78) -> 602.98647 | D79: =+SUM(D76:D78) -> 627.73198 | E79: =+SUM(E76:E78) -> 776.08682 | F79: =+SUM(F76:F78) -> 886.87196 | G79: =+SUM(G76:G78) -> 95.941408 | H79: =+SUM(H76:H78) -> 228.32206 | I79: =+SUM(I76:I78) -> 399.0155 | J79: =+SUM(J76:J78) -> 219.48872 | K79: =+SUM(G79:J79) -> 942.76768 | L79: =+SUM(L76:L78) -> 140.39374 | M79: =+SUM(M76:M78) -> 284.01614 | N79: =+SUM(N76:N78) -> 459.10194 | O79: =+SUM(O76:O78) -> 185.76949 | P79: =+SUM(L79:O79) -> 1069.2813 | Q79: =+SUM(Q76:Q78) -> 89.7436 | R79: =+SUM(R76:R78) -> 234.69515 | S79: =+SUM(S76:S78) -> 412.6845 | T79: =+SUM(T76:T78) -> 142.56113 | U79: =+SUM(Q79:T79) -> 879.68438 | V79: =+SUM(V76:V78) -> 71.682644 | W79: =+SUM(W76:W78) -> 188.83178 | X79: =+SUM(X76:X78) -> 342.87233 | Y79: =+SUM(Y76:Y78) -> 171.07617 | Z79: =+SUM(V79:Y79) -> 774.46292 | AA79: =+SUM(AA76:AA78) -> 109.41 | AB79: =+SUM(AB76:AB78) -> 199.043 | AC79: =+SUM(AC76:AC78) -> 379.5324 | AD79: =+SUM(AD76:AD78) -> 179.87815 | AE79: =+SUM(AA79:AD79) -> 867.86355 | AF79: =+SUM(AF76:AF78) -> 129.764 | AG79: =+SUM(AG76:AG78) -> 219.764 | AH79: =+SUM(AH76:AH78) -> 376.0648 | AI79: =+SUM(AI76:AI78) -> 142.5152 | AJ79: =+SUM(AF79:AI79) -> 868.108 | AK79: =+SUM(AK76:AK78) -> 182.526 | AL79: =+SUM(AL76:AL78) -> 206.754 | AM79: =+SUM(AM76:AM78) -> 209.21 | AN79: =+SUM(AN76:AN78) -> 213.982 | AO79: =+SUM(AK79:AN79) -> 812.472 | AP79: =+SUM(AP76:AP78) -> 235.368 | AQ79: =+SUM(AQ76:AQ78) -> 264.982 | AR79: =+SUM(AR76:AR78) -> 218.982 | AS79: =+SUM(AS76:AS78) -> 224.086 | AT79: =+SUM(AP79:AS79) -> 943.418 | AU79: =+SUM(AU76:AU78) -> 248.474 | AV79: =+SUM(AV76:AV78) -> 292.964 | AW79: =+SUM(AW76:AW78) -> 288.644 | AX79: =+SUM(AX76:AX78) -> 272.644 | AY79: =+SUM(AU79:AX79) -> 1102.726 | AZ79: =+SUM(AZ76:AZ78) -> 306 | BA79: =+SUM(BA76:BA78) -> 342.544 | BB79: =+SUM(BB76:BB78) -> 335.829 | BC79: =+SUM(BC76:BC78) -> 304 | BD79: =+SUM(AZ79:BC79) -> 1288.373 | BE79: =+SUM(BE76:BE78) -> 320 | BF79: =+SUM(BF76:BF78) -> 385 | BG79: =+SUM(BG76:BG78) -> 380 | BH79: =+SUM(BH76:BH78) -> 334 | BI79: =+SUM(BE79:BH79) -> 1419 | BJ79: =+SUM(BJ76:BJ78) -> 422 | BK79: =+SUM(BK76:BK78) -> 446 | BL79: =+SUM(BL76:BL78) -> 441 | BM79: =+SUM(BM76:BM78) -> 474 | BN79: =+SUM(BJ79:BM79) -> 1783 | BO79: =+SUM(BO76:BO78) -> 509 | BP79: =+SUM(BP76:BP78) -> 543.08415 | BQ79: =+SUM(BQ76:BQ78) -> 528.39248 | BR79: =+SUM(BR76:BR78) -> 550.82293 | BS79: =+SUM(BO79:BR79) -> 2131.2996 | BT79: =+SUM(BT76:BT78) -> 553.12872 | BU79: =+SUM(BU76:BU78) -> 592.7977 | BV79: =+SUM(BV76:BV78) -> 578.30402 | BW79: =+SUM(BW76:BW78) -> 601.77449 | BX79: =+SUM(BT79:BW79) -> 2326.0049 | BY79: =+SUM(BY76:BY78) -> 2474.8438 | BZ79: =+SUM(BZ76:BZ78) -> 2635.0699 | CA79: =+SUM(CA76:CA78) -> 2792.5583 | CD79: =+A79 -> Adj. Net Income (Ex- Amort) | CE79: =B79 -> 432.9711 | CF79: =C79 -> 602.98647 | CG79: =D79 -> 627.73198 | CH79: =E79 -> 776.08682 | CI79: =F79 -> 886.87196 | CJ79: =K79 -> 942.76768 | CK79: =P79 -> 1069.2813 | CL79: =U79 -> 879.68438 | CM79: =Z79 -> 774.46292 | CN79: =AE79 -> 867.86355 | CO79: =AJ79 -> 868.108 | CP79: =AO79 -> 812.472 | CQ79: =AT79 -> 943.418 | CR79: =AY79 -> 1102.726 | CS79: =BD79 -> 1288.373 | CT79: =BI79 -> 1419 | CU79: =BN79 -> 1783 | CV79: =BS79 -> 2131.2996 | CW79: =BX79 -> 2326.0049 | CX79: =BY79 -> 2474.8438 | CY79: =BZ79 -> 2635.0699 | CZ79: =CA79 -> 2792.5583
A80: Cash EPS (Ex- Amort) - Diluted | B80: =+B79/B70 -> 2.2104685 | C80: =+C79/C70 -> 3.0990244 | D80: =+D79/D70 -> 3.2693523 | E80: =+E79/E70 -> 2.0115048 | F80: =+F79/F70 -> 2.3181953 | G80: =+G79/G70 -> 0.25426191 | H80: =+H79/H70 -> 0.62467218 | I80: =+I79/I70 -> 1.1055051 | J80: =+J79/J70 -> 0.60272606 | K80: =+SUM(G80:J80) -> 2.5871653 | L80: =+L79/L70 -> 0.38836764 | M80: =+M79/M70 -> 0.81078436 | N80: =+N79/N70 -> 1.3593636 | O80: =+O79/O70 -> 0.56163589 | P80: =+SUM(L80:O80) -> 3.1201515 | Q80: =+Q79/Q70 -> 0.27750031 | R80: =+R79/R70 -> 0.73093944 | S80: =+S79/S70 -> 1.3010107 | T80: =+T79/T70 -> 0.45570855 | U80: =+SUM(Q80:T80) -> 2.765159 | V80: =+V79/V70 -> 0.22973955 | W80: =+W79/W70 -> 0.60323282 | X80: =+X79/X70 -> 1.0931965 | Y80: =+Y79/Y70 -> 0.54399352 | Z80: =+SUM(V80:Y80) -> 2.4701624 | AA80: =+AA79/AA70 -> 0.34590579 | AB80: =+AB79/AB70 -> 0.63551405 | AC80: =+AC79/AC70 -> 1.2270689 | AD80: =+AD79/AD70 -> 0.57964812 | AE80: =+SUM(AA80:AD80) -> 2.7881368 | AF80: =+AF79/AF70 -> 0.41913437 | AG80: =+AG79/AG70 -> 0.71075032 | AH80: =+AH79/AH70 -> 1.2386851 | AI80: =+AI79/AI70 -> 0.48806575 | AJ80: =+SUM(AF80:AI80) -> 2.8566356 | AK80: =+AK79/AK70 -> 0.64315011 | AL80: =+AL79/AL70 -> 0.7246898 | AM80: =+AM79/AM70 -> 0.7351019 | AN80: =+AN79/AN70 -> 0.7516052 | AO80: =+SUM(AK80:AN80) -> 2.854547 | AP80: =+AP79/AP70 -> 0.82788604 | AQ80: =+AQ79/AQ70 -> 0.95214517 | AR80: =+AR79/AR70 -> 0.78544476 | AS80: =+AS79/AS70 -> 0.80606475 | AT80: =+SUM(AP80:AS80) -> 3.3715407 | AU80: =+AU79/AU70 -> 0.89637085 | AV80: =+AV79/AV70 -> 1.0610793 | AW80: =+AW79/AW70 -> 1.0480901 | AX80: =+AX79/AX70 -> 0.98712527 | AY80: =+SUM(AU80:AX80) -> 3.9926655 | AZ80: =+AZ79/AZ70 -> 1.1074919 | BA80: =+BA79/BA70 -> 1.2424519 | BB80: =+BB79/BB70 -> 1.2238666 | BC80: =+BC79/BC70 -> 1.1172363 | BD80: =+SUM(AZ80:BC80) -> 4.6910467 | BE80: =+BE79/BE70 -> 1.1976048 | BF80: =+BF79/BF70 -> 1.4435696 | BG80: =+BG79/BG70 -> 1.4323407 | BH80: =+BH79/BH70 -> 1.2767584 | BI80: =+SUM(BE80:BH80) -> 5.3502735 | BJ80: =+BJ79/BJ70 -> 1.6180982 | BK80: =+BK79/BK70 -> 1.7160446 | BL80: =+BL79/BL70 -> 1.7099651 | BM80: =+BM79/BM70 -> 1.844358 | BN80: =+SUM(BJ80:BM80) -> 6.8884659 | BO80: =+BO79/BO70 -> 2.0007862 | BP80: =+BP79/BP70 -> 2.1666923 | BQ80: =+BQ79/BQ70 -> 2.1178522 | BR80: =+BR79/BR70 -> 2.2183618 | BS80: =+SUM(BO80:BR80) -> 8.5036924 | BT80: =+BT79/BT70 -> 2.2385366 | BU80: =+BU79/BU70 -> 2.4098143 | BV80: =+BV79/BV70 -> 2.3606495 | BW80: =+BW79/BW70 -> 2.4670863 | BX80: =+SUM(BT80:BW80) -> 9.4760867 | BY80: =+BY79/BY70 -> 10.262843 | BZ80: =+BZ79/BZ70 -> 11.120495 | CA80: =+CA79/CA70 -> 11.999945 | CB80: =(CA80/BN80)^(1/5)-1 -> 0.11740689 | CD80: =A80 -> Cash EPS (Ex- Amort) - Diluted | CE80: =B80 -> 2.2104685 | CF80: =C80 -> 3.0990244 | CG80: =D80 -> 3.2693523 | CH80: =E80 -> 2.0115048 | CI80: =F80 -> 2.3181953 | CJ80: =K80 -> 2.5871653 | CK80: =P80 -> 3.1201515 | CL80: =U80 -> 2.765159 | CM80: =Z80 -> 2.4701624 | CN80: =AE80 -> 2.7881368 | CO80: =AJ80 -> 2.8566356 | CP80: =AO80 -> 2.854547 | CQ80: =AT80 -> 3.3715407 | CR80: =AY80 -> 3.9926655 | CS80: =BD80 -> 4.6910467 | CT80: =BI80 -> 5.3502735 | CU80: =BN80 -> 6.8884659 | CV80: =BS80 -> 8.5036924 | CW80: =BX80 -> 9.4760867 | CX80: =BY80 -> 10.262843 | CY80: =BZ80 -> 11.120495 | CZ80: =CA80 -> 11.999945
A82: Fiscal Year Ending December 31 | B82: 2001 | C82: 2002 | D82: 2003 | E82: 2004 | F82: 2005 | G82: 1Q06 | H82: 2Q06 | I82: 3Q06 | J82: 4Q06 | K82: 2006 | L82: 1Q07 | M82: 2Q07 | N82: 3Q07 | O82: 4Q07 | P82: 2007 | Q82: 1Q08 | R82: 2Q08 | S82: 3Q08 | T82: 4Q08 | U82: 2008 | V82: 1Q09 | W82: 2Q09 | X82: 3Q09 | Y82: 4Q09 | Z82: 2009 | AA82: 1Q10 | AB82: 2Q10 | AC82: 3Q10 | AD82: 4Q10 | AE82: 2010 | AF82: 1Q11 | AG82: 2Q11 | AH82: =AH9 -> 3Q11 | AI82: =AI9 -> 4Q11 | AJ82: =AJ9 -> 2011 | AK82: =AK9 -> 1Q12 | AL82: =AL9 -> 2Q12 | AM82: =AM9 -> 3Q12 | AN82: =AN9 -> 4Q12 | AO82: =AO9 -> 2012 | ... CA82: =CA9 -> 2022E | CD82: =A82 -> Fiscal Year Ending December 31 | CE82: =B82 -> 2001 | CF82: =C82 -> 2002 | CG82: =D82 -> 2003 | CH82: =E82 -> 2004 | CI82: =F82 -> 2005 | CJ82: =K82 -> 2006 | CK82: =P82 -> 2007 | CL82: =U82 -> 2008 | CM82: =Z82 -> 2009 | CN82: =AE82 -> 2010 | CO82: =AJ82 -> 2011 | CP82: =AO82 -> 2012 | CQ82: =AT82 -> 2013 | CR82: =AY82 -> 2014 | CS82: =BD82 -> 2015 | CT82: =BI82 -> 2016 | CU82: =BN82 -> 2017 | CV82: =BS82 -> 2018E | CW82: =BX82 -> 2019E | CX82: =BY82 -> 2020E | CY82: =BZ82 -> 2021E | CZ82: =CA82 -> 2022E | DB82: NTM
A83: Cash Flows from Operations | CD83: =A83 -> Cash Flows from Operations
A84: Net Income | B84: 377.031 | C84: 576.76 | D84: 687.65 | E84: 755.823 | F84: 844.306 | G84: 74.22 | H84: =295.181-G84 -> 220.961 | I84: =677.454-H84-G84 -> 382.273 | J84: =882.231-I84-H84-G84 -> 204.777 | K84: =SUM(G84:J84) -> 882.231 | L84: 143.838 | M84: =420.916-L84 -> 277.078 | N84: =872.934-M84-L84 -> 452.018 | O84: =1013.559-N84-M84-L84 -> 140.625 | P84: =SUM(L84:O84) -> 1013.559 | Q84: 81.11 | R84: =301.513-Q84 -> 220.403 | S84: =698.328-R84-Q84 -> 396.815 | T84: =819.365-S84-R84-Q84 -> 121.037 | U84: =SUM(Q84:T84) -> 819.365 | V84: 65.985 | W84: =233.876-V84 -> 167.891 | X84: =576.132-W84-V84 -> 342.256 | Y84: =749.761-X84-W84-V84 -> 173.629 | Z84: =SUM(V84:Y84) -> 749.761 | AA84: 107 | AB84: =301.2-AA84 -> 194.2 | AC84: =690.9-AB84-AA84 -> 389.7 | AD84: =851.869-AC84-AB84-AA84 -> 160.969 | AE84: =SUM(AA84:AD84) -> 851.869 | AF84: =AF56 -> 124 | AG84: =AG56 -> 216 | AH84: =713.8-AG84-AF84 -> 373.8 | AI84: =AI56 -> 221 | AJ84: =SUM(AF84:AI84) -> 934.8 | AK84: =AK56-AK53 -> 163 | AL84: =AL56-AL53 -> 180 | AM84: =AM56-AM53 -> 172 | AN84: =AN56-AN53 -> 211 | AO84: =SUM(AK84:AN84) -> 726 | AP84: =AP56-AP53 -> 174 | AQ84: =AQ56-AQ53 -> 273 | AR84: =AR56-AR53 -> 258 | AS84: =AS56-AS53 -> 182 | AT84: =SUM(AP84:AS84) -> 887 | AU84: =AU56-AU53 -> 268.5 | AV84: =AV56-AV53 -> 309.5 | AW84: =AW56-AW53 -> 215 | AX84: =AX56-AX53 -> -984 | AY84: =SUM(AU84:AX84) -> -191 | AZ84: =AZ56-AZ53 -> 329 | BA84: =BA56-BA53 -> 381 | BB84: =BB56-BB53 -> 281 | BC84: =BC56-BC53 -> 276 | BD84: =SUM(AZ84:BC84) -> 1267 | BE84: =BE56-BE53 -> 323 | BF84: =BF56-BF53 -> 412 | BG84: =BG56-BG53 -> 922 | BH84: =BH56-BH53 -> 569 | BI84: =SUM(BE84:BH84) -> 2226 | BJ84: =BJ56-BJ53 -> 430 | BK84: =BK56-BK53 -> 457 | BL84: =BL56-BL53 -> 452 | BM84: =BM56-BM53 -> 299 | BN84: =SUM(BJ84:BM84) -> 1638 | BO84: =BO56-BO53 -> 534 | BP84: =BP51 -> 556.19015 | BQ84: =BQ51 -> 541.04752 | BR84: =BR51 -> 565.01312 | BS84: =SUM(BO84:BR84) -> 2196.2508 | BT84: =BT51 -> 574.60062 | BU84: =BU51 -> 613.35353 | BV84: =BV51 -> 598.78311 | BW84: =BW51 -> 623.78355 | BX84: =SUM(BT84:BW84) -> 2410.5208 | BY84: =BY51 -> 2579.5373 | BZ84: =BZ51 -> 2765.7187 | CA84: =CA51 -> 2941.6046 | CD84: =A84 -> Net Income | CE84: =B84 -> 377.031 | CF84: =C84 -> 576.76 | CG84: =D84 -> 687.65 | CH84: =E84 -> 755.823 | CI84: =F84 -> 844.306 | CJ84: =K84 -> 882.231 | CK84: =P84 -> 1013.559 | CL84: =U84 -> 819.365 | CM84: =Z84 -> 749.761 | CN84: =AE84 -> 851.869 | CO84: =AJ84 -> 934.8 | CP84: =AO84 -> 726 | CQ84: =AT84 -> 887 | CR84: =AY84 -> -191 | CS84: =BD84 -> 1267 | CT84: =BI84 -> 2226 | CU84: =BN84 -> 1638 | CV84: =BS84 -> 2196.2508 | CW84: =BX84 -> 2410.5208 | CX84: =BY84 -> 2579.5373 | CY84: =BZ84 -> 2765.7187 | CZ84: =CA84 -> 2941.6046
A85: Adjustments to Reconcile Net Income to Cash Provided by Operating Activities | CD85: =A85 -> Adjustments to Reconcile Net Income to Cash Provided by Operating Activities
A86: Depreciation (including amortization of technology projects) | B86: 88.802 | C86: 89.589 | D86: 83.953 | E86: 92.268 | F86: 106.75 | G86: 27.564 | H86: =55.88-G86 -> 28.316 | I86: =82.748-H86-G86 -> 26.868 | J86: =113.2-I86-H86-G86 -> 30.452 | K86: =SUM(G86:J86) -> 113.2 | L86: 28.905 | M86: =57.703-L86 -> 28.798 | N86: =83.902-M86-L86 -> 26.199 | O86: =112.586-N86-M86-L86 -> 28.684 | P86: =SUM(L86:O86) -> 112.586 | Q86: 27.527 | R86: =57.938-Q86 -> 30.411 | S86: =87.89-R86-Q86 -> 29.952 | T86: =119.849-S86-R86-Q86 -> 31.959 | U86: =SUM(Q86:T86) -> 119.849 | V86: 29.412 | W86: =58.194-V86 -> 28.782 | X86: =84.225-W86-V86 -> 26.031 | Y86: =137.339-X86-W86-V86 -> 53.114 | Z86: =SUM(V86:Y86) -> 137.339 | AA86: 30.4 | AB86: =61.3-AA86 -> 30.9 | AC86: =91.3-AB86-AA86 -> 30 | AD86: =125.492-AC86-AB86-AA86 -> 34.192 | AE86: =SUM(AA86:AD86) -> 125.492 | AF86: 32.2 | AG86: =64.4-AF86 -> 32.2 | AH86: =95-AG86-AF86 -> 30.6 | AI86: =127-SUM(AF86:AH86) -> 32 | AJ86: =SUM(AF86:AI86) -> 127 | AK86: 22 | AL86: =45-AK86 -> 23 | AM86: =69-SUM(AK86:AL86) -> 24 | AN86: =93-SUM(AK86:AM86) -> 24 | AO86: =SUM(AK86:AN86) -> 93 | AP86: 23 | AQ86: =45-AP86 -> 22 | AR86: =65-SUM(AP86:AQ86) -> 20 | AS86: =86-SUM(AP86:AR86) -> 21 | AT86: =SUM(AP86:AS86) -> 86 | AU86: 21 | AV86: =42-AU86 -> 21 | AW86: =64-AV86-AU86 -> 22 | AX86: =86-SUM(AU86:AW86) -> 22 | AY86: =SUM(AU86:AX86) -> 86 | AZ86: 22 | BA86: =43-AZ86 -> 21 | BB86: =64-SUM(AZ86:BA86) -> 21 | BC86: =90-SUM(AZ86:BB86) -> 26 | BD86: =SUM(AZ86:BC86) -> 90 | BE86: 18 | BF86: =40-BE86 -> 22 | BG86: =63-SUM(BE86:BF86) -> 23 | BH86: =85-SUM(BE86:BG86) -> 22 | BI86: =SUM(BE86:BH86) -> 85 | BJ86: 19 | BK86: =39-BJ86 -> 20 | BL86: =61-SUM(BJ86:BK86) -> 22 | BM86: =82-SUM(BJ86:BL86) -> 21 | BN86: =SUM(BJ86:BM86) -> 82 | BO86: 21 | BP86: =BP35 -> 12.777577 | BQ86: =BQ35 -> 13.231036 | BR86: =BR35 -> 12.206683 | BS86: =SUM(BO86:BR86) -> 59.215296 | BT86: =BT35 -> 15.975089 | BU86: =BU35 -> 18.521219 | BV86: =BV35 -> 18.071057 | BW86: =BW35 -> 19.461689 | BX86: =SUM(BT86:BW86) -> 72.029054 | BY86: =BY35 -> 80.751197 | BZ86: =BZ35 -> 95.317851 | CA86: =CA35 -> 98.621369 | CD86: =A86 -> Depreciation (including amortization of technology projects) | CE86: =B86 -> 88.802 | CF86: =C86 -> 89.589 | CG86: =D86 -> 83.953 | CH86: =E86 -> 92.268 | CI86: =F86 -> 106.75 | CJ86: =K86 -> 113.2 | CK86: =P86 -> 112.586 | CL86: =U86 -> 119.849 | CM86: =Z86 -> 137.339 | CN86: =AE86 -> 125.492 | CO86: =AJ86 -> 127 | CP86: =AO86 -> 93 | CQ86: =AT86 -> 86 | CR86: =AY86 -> 86 | CS86: =BD86 -> 90 | CT86: =BI86 -> 85 | CU86: =BN86 -> 82 | CV86: =BS86 -> 59.215296 | CW86: =BX86 -> 72.029054 | CX86: =BY86 -> 80.751197 | CY86: =BZ86 -> 95.317851 | CZ86: =CA86 -> 98.621369
A87: Amortization of Intangibles | B87: 91.555 | C87: 38.789 | D87: 33.739 | E87: 32.47 | F87: 44.235 | G87: 11.926 | H87: =24.033-G87 -> 12.107 | I87: =36.17-H87-G87 -> 12.137 | J87: =48.387-I87-H87-G87 -> 12.217 | K87: =SUM(G87:J87) -> 48.387 | L87: 11.612 | M87: =23.08-L87 -> 11.468 | N87: =34.789-M87-L87 -> 11.709 | O87: =48.403-N87-M87-L87 -> 13.614 | P87: =SUM(L87:O87) -> 48.403 | Q87: 14.2 | R87: =27.344-Q87 -> 13.144 | S87: =40.981-R87-Q87 -> 13.637 | T87: =58.497-S87-R87-Q87 -> 17.516 | U87: =SUM(Q87:T87) -> 58.497 | V87: 14.204 | W87: =25.644-V87 -> 11.44 | X87: =36.71-W87-V87 -> 11.066 | Y87: =52.72-X87-W87-V87 -> 16.01 | Z87: =SUM(V87:Y87) -> 52.72 | AA87: 10 | AB87: =23-AA87 -> 13 | AC87: =32-AB87-AA87 -> 9 | AD87: =45.595-AC87-AB87-AA87 -> 13.595 | AE87: =SUM(AA87:AD87) -> 45.595 | AF87: 14.8 | AG87: =29.7-AF87 -> 14.9 | AH87: =45.1-AG87-AF87 -> 15.4 | AI87: =60-SUM(AF87:AH87) -> 14.9 | AJ87: =SUM(AF87:AI87) -> 60 | AK87: 9 | AL87: =20-AK87 -> 11 | AM87: =35-SUM(AK87:AL87) -> 15 | AN87: =48-SUM(AK87:AM87) -> 13 | AO87: =SUM(AK87:AN87) -> 48 | AP87: 12 | AQ87: =25-AP87 -> 13 | AR87: =38-SUM(AP87:AQ87) -> 13 | AS87: =51-SUM(AP87:AR87) -> 13 | AT87: =SUM(AP87:AS87) -> 51 | AU87: 12 | AV87: =24-AU87 -> 12 | AW87: =36-AV87-AU87 -> 12 | AX87: =48-SUM(AU87:AW87) -> 12 | AY87: =SUM(AU87:AX87) -> 48 | AZ87: 11 | BA87: =23-AZ87 -> 12 | BB87: =40-SUM(AZ87:BA87) -> 17 | BC87: =67-SUM(AZ87:BB87) -> 27 | BD87: =SUM(AZ87:BC87) -> 67 | BE87: 24 | BF87: =47-BE87 -> 23 | BG87: =71-SUM(BE87:BF87) -> 24 | BH87: =96-SUM(BE87:BG87) -> 25 | BI87: =SUM(BE87:BH87) -> 96 | BJ87: 24 | BK87: =49-BJ87 -> 25 | BL87: =73-SUM(BJ87:BK87) -> 24 | BM87: =98-SUM(BJ87:BL87) -> 25 | BN87: =SUM(BJ87:BM87) -> 98 | BO87: 24 | BP87: =BP36 -> 34.5 | BQ87: =BQ36 -> 34.5 | BR87: =BR36 -> 34.5 | BS87: =SUM(BO87:BR87) -> 127.5 | BT87: =BT36 -> 30.125 | BU87: =BU36 -> 30.125 | BV87: =BV36 -> 30.125 | BW87: =BW36 -> 30.125 | BX87: =SUM(BT87:BW87) -> 120.5 | BY87: =BY36 -> 114.5 | BZ87: =BZ36 -> 102.5 | CA87: =CA36 -> 100.5 | CD87: =A87 -> Amortization of Intangibles | CE87: =B87 -> 91.555 | CF87: =C87 -> 38.789 | CG87: =D87 -> 33.739 | CH87: =E87 -> 32.47 | CI87: =F87 -> 44.235 | CJ87: =K87 -> 48.387 | CK87: =P87 -> 48.403 | CL87: =U87 -> 58.497 | CM87: =Z87 -> 52.72 | CN87: =AE87 -> 45.595 | CO87: =AJ87 -> 60 | CP87: =AO87 -> 48 | CQ87: =AT87 -> 51 | CR87: =AY87 -> 48 | CS87: =BD87 -> 67 | CT87: =BI87 -> 96 | CU87: =BN87 -> 98 | CV87: =BS87 -> 127.5 | CW87: =BX87 -> 120.5 | CX87: =BY87 -> 114.5 | CY87: =BZ87 -> 102.5 | CZ87: =CA87 -> 100.5
A88: Amortization of Prepublication Costs | B88: 240.241 | C88: 280.393 | D88: 285.487 | E88: 267.975 | F88: 234.276 | G88: 22.52 | H88: =75.559-G88 -> 53.039 | I88: =178.878-H88-G88 -> 103.319 | J88: =228.405-I88-H88-G88 -> 49.527 | K88: =SUM(G88:J88) -> 228.405 | L88: 28.097 | M88: =84.939-L88 -> 56.842 | N88: =195.417-M88-L88 -> 110.478 | O88: =240.182-N88-M88-L88 -> 44.765 | P88: =SUM(L88:O88) -> 240.182 | Q88: 28.182 | R88: =94.229-Q88 -> 66.047 | S88: =218.788-R88-Q88 -> 124.559 | T88: =270.442-S88-R88-Q88 -> 51.654 | U88: =SUM(Q88:T88) -> 270.442 | V88: 27.291 | W88: =98.429-V88 -> 71.138 | X88: =225.602-W88-V88 -> 127.173 | Y88: =270.469-X88-W88-V88 -> 44.867 | Z88: =SUM(V88:Y88) -> 270.469 | AA88: 25.8 | AB88: =95.2-AA88 -> 69.4 | AC88: =207.2-AB88-AA88 -> 112 | AD88: =246.312-AC88-AB88-AA88 -> 39.112 | AE88: =SUM(AA88:AD88) -> 246.312 | AF88: 22.9 | AG88: =75.5-AF88 -> 52.6 | AH88: =164.5-AG88-AF88 -> 89 | AI88: =198-SUM(AF88:AH88) -> 33.5 | AJ88: =SUM(AF88:AI88) -> 198 | AK88: 0 | AL88: =0-AK88 -> 0 | AM88: =0-SUM(AK88:AL88) -> 0 | AN88: =0-SUM(AK88:AM88) -> 0 | AO88: =SUM(AK88:AN88) -> 0 | AP88: 0 | AQ88: =0-AP88 -> 0 | AR88: =0-SUM(AP88:AQ88) -> 0 | AS88: =0-SUM(AP88:AR88) -> 0 | AT88: =SUM(AP88:AS88) -> 0 | AU88: 0 | AV88: 0 | AW88: =0-AV88-AU88 -> 0 | AX88: 0 | AY88: =SUM(AU88:AX88) -> 0 | AZ88: 0 | BA88: 0 | BB88: 0 | BC88: 0 | BD88: =SUM(AZ88:BC88) -> 0 | BE88: 0 | BF88: 0 | BG88: 0 | BH88: 0 | BI88: =SUM(BE88:BH88) -> 0 | BJ88: 0 | BK88: 0 | BL88: 0 | BM88: 0 | BN88: =SUM(BJ88:BM88) -> 0 | BO88: 0 | BP88: 0 | BQ88: 0 | BR88: 0 | BS88: =SUM(BO88:BR88) -> 0 | BT88: 0 | BU88: 0 | BV88: 0 | BW88: 0 | BX88: =SUM(BT88:BW88) -> 0 | BY88: 0 | BZ88: 0 | CA88: 0 | CD88: =A88 -> Amortization of Prepublication Costs | CE88: =B88 -> 240.241 | CF88: =C88 -> 280.393 | CG88: =D88 -> 285.487 | CH88: =E88 -> 267.975 | CI88: =F88 -> 234.276 | CJ88: =K88 -> 228.405 | CK88: =P88 -> 240.182 | CL88: =U88 -> 270.442 | CM88: =Z88 -> 270.469 | CN88: =AE88 -> 246.312 | CO88: =AJ88 -> 198 | CP88: =AO88 -> 0 | CQ88: =AT88 -> 0 | CR88: =AY88 -> 0 | CS88: =BD88 -> 0 | CT88: =BI88 -> 0 | CU88: =BN88 -> 0 | CV88: =BS88 -> 0 | CW88: =BX88 -> 0 | CX88: =BY88 -> 0 | CY88: =BZ88 -> 0 | CZ88: =CA88 -> 0
A89: Provision for Losses on Accounts Receivable | B89: 55.254 | C89: 33.024 | D89: 29.839 | E89: 7.796 | F89: 18.896 | G89: 6.531 | H89: =12.025-G89 -> 5.494 | I89: =18.513-H89-G89 -> 6.488 | J89: =19.577-I89-H89-G89 -> 1.064 | K89: =SUM(G89:J89) -> 19.577 | L89: 5.032 | M89: =9.594-L89 -> 4.562 | N89: =8.047-M89-L89 -> -1.547 | O89: =14.991-N89-M89-L89 -> 6.944 | P89: =SUM(L89:O89) -> 14.991 | Q89: 1.465 | R89: =9.215-Q89 -> 7.75 | S89: =13.856-R89-Q89 -> 4.641 | T89: =27.098-S89-R89-Q89 -> 13.242 | U89: =SUM(Q89:T89) -> 27.098 | V89: 10.272 | W89: =15.88-V89 -> 5.608 | X89: =22.386-W89-V89 -> 6.506 | Y89: =31.635-X89-W89-V89 -> 9.249 | Z89: =SUM(V89:Y89) -> 31.635 | AA89: 9.8 | AB89: =6.1-AA89 -> -3.7 | AC89: =11.5-AB89-AA89 -> 5.4 | AD89: =19.316-AC89-AB89-AA89 -> 7.816 | AE89: =SUM(AA89:AD89) -> 19.316 | AF89: 5.4 | AG89: =3.8-AF89 -> -1.6 | AH89: =4.9-AG89-AF89 -> 1.1 | AI89: =1-SUM(AF89:AH89) -> -3.9 | AJ89: =SUM(AF89:AI89) -> 1 | AK89: 4 | AL89: =9-AK89 -> 5 | AM89: =20-SUM(AK89:AL89) -> 11 | AN89: =32-SUM(AK89:AM89) -> 12 | AO89: =SUM(AK89:AN89) -> 32 | AP89: 11 | AQ89: =14-AP89 -> 3 | AR89: =18-SUM(AP89:AQ89) -> 4 | AS89: =22-SUM(AP89:AR89) -> 4 | AT89: =SUM(AP89:AS89) -> 22 | AU89: -4 | AV89: =0-AU89 -> 4 | AW89: =5-AV89-AU89 -> 5 | AX89: =11-SUM(AU89:AW89) -> 6 | AY89: =SUM(AU89:AX89) -> 11 | AZ89: 0 | BA89: =4-AZ89 -> 4 | BB89: =3-SUM(AZ89:BA89) -> -1 | BC89: =8-SUM(AZ89:BB89) -> 5 | BD89: =SUM(AZ89:BC89) -> 8 | BE89: 3 | BF89: =8-BE89 -> 5 | BG89: =10-SUM(BE89:BF89) -> 2 | BH89: =9-SUM(BE89:BG89) -> -1 | BI89: =SUM(BE89:BH89) -> 9 | BJ89: 5 | BK89: =13-BJ89 -> 8 | BL89: =17-SUM(BJ89:BK89) -> 4 | BM89: =16-SUM(BJ89:BL89) -> -1 | BN89: =SUM(BJ89:BM89) -> 16 | BO89: 8 | BP89: 0 | BQ89: 0 | BR89: 0 | BS89: =SUM(BO89:BR89) -> 8 | BT89: 0 | BU89: 0 | BV89: 0 | BW89: 0 | BX89: =SUM(BT89:BW89) -> 0 | BY89: 0 | BZ89: 0 | CA89: 0 | CD89: =A89 -> Provision for Losses on Accounts Receivable | CE89: =B89 -> 55.254 | CF89: =C89 -> 33.024 | CG89: =D89 -> 29.839 | CH89: =E89 -> 7.796 | CI89: =F89 -> 18.896 | CJ89: =K89 -> 19.577 | CK89: =P89 -> 14.991 | CL89: =U89 -> 27.098 | CM89: =Z89 -> 31.635 | CN89: =AE89 -> 19.316 | CO89: =AJ89 -> 1 | CP89: =AO89 -> 32 | CQ89: =AT89 -> 22 | CR89: =AY89 -> 11 | CS89: =BD89 -> 8 | CT89: =BI89 -> 9 | CU89: =BN89 -> 16 | CV89: =BS89 -> 8 | CW89: =BX89 -> 0 | CX89: =BY89 -> 0 | CY89: =BZ89 -> 0 | CZ89: =CA89 -> 0
A90: Deferred Income Taxes | B90: 0 | C90: 0 | D90: 0 | E90: 0 | F90: -18.73 | G90: -21.715 | H90: =-36.545-G90 -> -14.83 | I90: =-48.519-H90-G90 -> -11.974 | J90: =-86.613-I90-H90-G90 -> -38.094 | K90: =SUM(G90:J90) -> -86.613 | L90: -39.012 | M90: =-60.701-L90 -> -21.689 | N90: =-68.256-M90-L90 -> -7.555 | O90: =-46.615-N90-M90-L90 -> 21.641 | P90: =SUM(L90:O90) -> -46.615 | Q90: -13.625 | R90: =-21.632-Q90 -> -8.007 | S90: =-4.791-R90-Q90 -> 16.841 | T90: =-0.017-S90-R90-Q90 -> 4.774 | U90: =SUM(Q90:T90) -> -0.017 | V90: -2.174 | W90: =-4.465-V90 -> -2.291 | X90: =-2.178-W90-V90 -> 2.287 | Y90: =5.688-X90-W90-V90 -> 7.866 | Z90: =SUM(V90:Y90) -> 5.688 | AA90: -10.8 | AB90: =-16.8-AA90 -> -6 | AC90: =-23.4-AB90-AA90 -> -6.6 | AD90: =74.406-AC90-AB90-AA90 -> 97.806 | AE90: =SUM(AA90:AD90) -> 74.406 | AF90: 4.5 | AG90: =0.1-AF90 -> -4.4 | AH90: =-4.8-AG90-AF90 -> -4.9 | AI90: =10-SUM(AF90:AH90) -> 14.8 | AJ90: =SUM(AF90:AI90) -> 10 | AK90: 2 | AL90: =3-AK90 -> 1 | AM90: =5-SUM(AK90:AL90) -> 2 | AN90: =53-SUM(AK90:AM90) -> 48 | AO90: =SUM(AK90:AN90) -> 53 | AP90: 1 | AQ90: =4-AP90 -> 3 | AR90: =3-SUM(AP90:AQ90) -> -1 | AS90: =43-SUM(AP90:AR90) -> 40 | AT90: =SUM(AP90:AS90) -> 43 | AU90: 0 | AV90: 0 | AW90: =-33-AV90-AU90 -> -33 | AX90: =-245-SUM(AU90:AW90) -> -212 | AY90: =SUM(AU90:AX90) -> -245 | AZ90: 39 | BA90: =166-AZ90 -> 127 | BB90: =166-SUM(AZ90:BA90) -> 0 | BC90: =280-SUM(AZ90:BB90) -> 114 | BD90: =SUM(AZ90:BC90) -> 280 | BE90: -1 | BF90: =+-4-BE90 -> -3 | BG90: =+-8-SUM(BE90:BF90) -> -4 | BH90: =79-SUM(BE90:BG90) -> 87 | BI90: =SUM(BE90:BH90) -> 79 | BJ90: -1 | BK90: =0-BJ90 -> 1 | BL90: =0-SUM(BJ90:BK90) -> 0 | BM90: 0 | BN90: =SUM(BJ90:BM90) -> 0 | BO90: 0 | BP90: =(BO146-BP146) -> 0 | BQ90: =(BP146-BQ146) -> 0 | BR90: =(BQ146-BR146) -> 0 | BS90: =SUM(BO90:BR90) -> 0 | BT90: =(BS146-BT146) -> 0 | BU90: =(BT146-BU146) -> 0 | BV90: =(BU146-BV146) -> 0 | BW90: =(BV146-BW146) -> 0 | BX90: =SUM(BT90:BW90) -> 0 | BY90: =(BX146-BY146) -> 0 | BZ90: =(BY146-BZ146) -> 0 | CA90: =(BZ146-CA146) -> 0 | CD90: =A90 -> Deferred Income Taxes | CE90: =B90 -> 0 | CF90: =C90 -> 0 | CG90: =D90 -> 0 | CH90: =E90 -> 0 | CI90: =F90 -> -18.73 | CJ90: =K90 -> -86.613 | CK90: =P90 -> -46.615 | CL90: =U90 -> -0.017 | CM90: =Z90 -> 5.688 | CN90: =AE90 -> 74.406 | CO90: =AJ90 -> 10 | CP90: =AO90 -> 53 | CQ90: =AT90 -> 43 | CR90: =AY90 -> -245 | CS90: =BD90 -> 280 | CT90: =BI90 -> 79 | CU90: =BN90 -> 0 | CV90: =BS90 -> 0 | CW90: =BX90 -> 0 | CX90: =BY90 -> 0 | CY90: =BZ90 -> 0 | CZ90: =CA90 -> 0
A91: Stock-Based Compensation | B91: 0 | C91: 0 | D91: 0 | E91: 0 | F91: 51.116 | G91: 54.011 | H91: =77.016-G91 -> 23.005 | I91: =106.242-H91-G91 -> 29.226 | J91: =136.181-I91-H91-G91 -> 29.939 | K91: =SUM(G91:J91) -> 136.181 | L91: 31.113 | M91: =62.811-L91 -> 31.698 | N91: =94.368-M91-L91 -> 31.557 | O91: =124.692-N91-M91-L91 -> 30.324 | P91: =SUM(L91:O91) -> 124.692 | Q91: 21.044 | R91: =43-Q91 -> 21.956 | S91: =3.564-R91-Q91 -> -39.436 | T91: =-1.934-S91-R91-Q91 -> -5.498 | U91: =SUM(Q91:T91) -> -1.934 | V91: 7.83 | W91: =17.233-V91 -> 9.403 | X91: =12.483-W91-V91 -> -4.75 | Y91: =22.268-X91-W91-V91 -> 9.785 | Z91: =SUM(V91:Y91) -> 22.268 | AA91: 8.3 | AB91: =23-AA91 -> 14.7 | AC91: =44.8-AB91-AA91 -> 21.8 | AD91: =66.485-AC91-AB91-AA91 -> 21.685 | AE91: =SUM(AA91:AD91) -> 66.485 | AF91: 18.1 | AG91: =41.2-AF91 -> 23.1 | AH91: =64.8-AG91-AF91 -> 23.6 | AI91: =97-SUM(AF91:AH91) -> 32.2 | AJ91: =SUM(AF91:AI91) -> 97 | AK91: 17 | AL91: =40-AK91 -> 23 | AM91: =63-SUM(AK91:AL91) -> 23 | AN91: =93-SUM(AK91:AM91) -> 30 | AO91: =SUM(AK91:AN91) -> 93 | AP91: 21 | AQ91: =47-AP91 -> 26 | AR91: =70-SUM(AP91:AQ91) -> 23 | AS91: =96-SUM(AP91:AR91) -> 26 | AT91: =SUM(AP91:AS91) -> 96 | AU91: 18 | AV91: =48-AU91 -> 30 | AW91: =72-AV91-AU91 -> 24 | AX91: =100-SUM(AU91:AW91) -> 28 | AY91: =SUM(AU91:AX91) -> 100 | AZ91: 18 | BA91: =37-AZ91 -> 19 | BB91: =55-SUM(AZ91:BA91) -> 18 | BC91: =78-SUM(AZ91:BB91) -> 23 | BD91: =SUM(AZ91:BC91) -> 78 | BE91: 14 | BF91: =34-BE91 -> 20 | BG91: =54-SUM(BE91:BF91) -> 20 | BH91: =76-SUM(BE91:BG91) -> 22 | BI91: =SUM(BE91:BH91) -> 76 | BJ91: 19 | BK91: =41-BJ91 -> 22 | BL91: =65-SUM(BJ91:BK91) -> 24 | BM91: =99-SUM(BJ91:BL91) -> 34 | BN91: =SUM(BJ91:BM91) -> 99 | BO91: 13 | BP91: =BP227 -> 23.915447 | BQ91: =BQ227 -> 25.750103 | BR91: =BR227 -> 35.75752 | BS91: =SUM(BO91:BR91) -> 98.42307 | BT91: =BT227 -> 13.658974 | BU91: =BU227 -> 25.329376 | BV91: =BV227 -> 27.30397 | BW91: =BW227 -> 37.893271 | BX91: =SUM(BT91:BW91) -> 104.18559 | BY91: =BY227 -> 109.57194 | BZ91: =BZ227 -> 115.28201 | CA91: =CA227 -> 120.68333 | CD91: =A91 -> Stock-Based Compensation | CE91: =B91 -> 0 | CF91: =C91 -> 0 | CG91: =D91 -> 0 | CH91: =E91 -> 0 | CI91: =F91 -> 51.116 | CJ91: =K91 -> 136.181 | CK91: =P91 -> 124.692 | CL91: =U91 -> -1.934 | CM91: =Z91 -> 22.268 | CN91: =AE91 -> 66.485 | CO91: =AJ91 -> 97 | CP91: =AO91 -> 93 | CQ91: =AT91 -> 96 | CR91: =AY91 -> 100 | CS91: =BD91 -> 78 | CT91: =BI91 -> 76 | CU91: =BN91 -> 99 | CV91: =BS91 -> 98.42307 | CW91: =BX91 -> 104.18559 | CX91: =BY91 -> 109.57194 | CY91: =BZ91 -> 115.28201 | CZ91: =CA91 -> 120.68333
A92: Goodwill Impairment | B92: 0 | C92: 0 | D92: 75.919 | E92: 0 | F92: 0 | G92: 0 | H92: 0 | I92: 0 | J92: 0 | K92: 0 | L92: 0 | M92: 0 | N92: 0 | O92: 0 | P92: 0 | Q92: 0 | R92: 0 | S92: 0 | T92: 0 | U92: 0 | V92: 0 | W92: 0 | X92: 0 | Y92: 0 | Z92: 0 | AA92: 0 | AB92: 0 | AC92: 0 | AD92: 0 | AE92: =SUM(AA92:AD92) -> 0 | AF92: 0 | AG92: 0 | AH92: 0 | AI92: 0 | AJ92: =SUM(AF92:AI92) -> 0 | AK92: 0 | AL92: =0 -> 0 | AM92: 0 | AN92: 0 | AO92: =SUM(AK92:AN92) -> 0 | AP92: 0 | AQ92: =0-AP92 -> 0 | AR92: =0-AQ92-AP92 -> 0 | AS92: 0 | AT92: =SUM(AP92:AS92) -> 0 | AU92: 0 | AV92: 0 | AW92: =0-AV92-AU92 -> 0 | AX92: 0 | AY92: =SUM(AU92:AX92) -> 0 | AZ92: 0 | BA92: 0 | BB92: 0 | BC92: 0 | BD92: =SUM(AZ92:BC92) -> 0 | BE92: 0 | BF92: 0 | BG92: 0 | BH92: 0 | BI92: =SUM(BE92:BH92) -> 0 | BJ92: 0 | BK92: 0 | BL92: 0 | BM92: 0 | BN92: =SUM(BJ92:BM92) -> 0 | BO92: 0 | BP92: 0 | BQ92: 0 | BR92: 0 | BS92: =SUM(BO92:BR92) -> 0 | BT92: 0 | BU92: 0 | BV92: 0 | BW92: 0 | BX92: =SUM(BT92:BW92) -> 0 | BY92: 0 | BZ92: 0 | CA92: 0 | CD92: =A92 -> Goodwill Impairment | CE92: =B92 -> 0 | CF92: =C92 -> 0 | CG92: =D92 -> 75.919 | CH92: =E92 -> 0 | CI92: =F92 -> 0 | CJ92: =K92 -> 0 | CK92: =P92 -> 0 | CL92: =U92 -> 0 | CM92: =Z92 -> 0 | CN92: =AE92 -> 0 | CO92: =AJ92 -> 0 | CP92: =AO92 -> 0 | CQ92: =AT92 -> 0 | CR92: =AY92 -> 0 | CS92: =BD92 -> 0 | CT92: =BI92 -> 0 | CU92: =BN92 -> 0 | CV92: =BS92 -> 0 | CW92: =BX92 -> 0 | CX92: =BY92 -> 0 | CY92: =BZ92 -> 0 | CZ92: =CA92 -> 0
A93: (Gain) Loss on Dispositions | B93: =-6.925 -> -6.925 | C93: =14.534 -> 14.534 | D93: =-86.953-131.25 -> -218.203 | E93: 0 | F93: 0 | G93: 0 | H93: =0-G93 -> 0 | I93: =0-H93-G93 -> 0 | J93: =0-I93-H93-G93 -> 0 | K93: =SUM(G93:J93) -> 0 | L93: =-17.305 -> -17.305 | M93: =-17.305-L93 -> 0 | N93: =-21.432-M93-L93 -> -4.127 | O93: =-21.432-N93-M93-L93 -> 0 | P93: =SUM(L93:O93) -> -21.432 | Q93: 0 | R93: 0 | S93: 0 | T93: 0 | U93: =SUM(Q93:T93) -> 0 | V93: 0 | W93: =13.849-V93 -> 13.849 | X93: =13.849-W93-V93 -> 0 | Y93: =3.304-X93-W93-V93 -> -10.545 | Z93: =SUM(V93:Y93) -> 3.304 | AA93: 0 | AB93: 0 | AC93: 0 | AD93: =-11.058-AC93-AB93-AA93 -> -11.058 | AE93: =SUM(AA93:AD93) -> -11.058 | AF93: 0 | AG93: 0 | AH93: 0 | AI93: =-136-SUM(AF93:AH93) -> -136 | AJ93: =SUM(AF93:AI93) -> -136 | AK93: 0 | AL93: 0 | AM93: =0-SUM(AK93:AL93) -> 0 | AN93: =0-SUM(AK93:AM93) -> 0 | AO93: =SUM(AK93:AN93) -> 0 | AP93: 0 | AQ93: 0 | AR93: =0-AQ93-AP93 -> 0 | AS93: 0 | AT93: =SUM(AP93:AS93) -> 0 | AU93: 0 | AV93: 0 | AW93: 0 | AX93: 0 | AY93: =SUM(AU93:AX93) -> 0 | AZ93: 0 | BA93: 0 | BB93: 0 | BC93: 0 | BD93: =SUM(AZ93:BC93) -> 0 | BE93: 0 | BF93: 0 | BG93: =+-722-SUM(BE93:BF93) -> -722 | BH93: =+-1101-SUM(BE93:BG93) -> -379 | BI93: =SUM(BE93:BH93) -> -1101 | BJ93: 0 | BK93: 0 | BL93: 0 | BM93: 0 | BN93: =SUM(BJ93:BM93) -> 0 | BO93: 0 | BP93: 0 | BQ93: 0 | BR93: 0 | BS93: =SUM(BO93:BR93) -> 0 | BT93: 0 | BU93: 0 | BV93: 0 | BW93: 0 | BX93: =SUM(BT93:BW93) -> 0 | BY93: 0 | BZ93: 0 | CA93: 0 | CD93: =A93 -> (Gain) Loss on Dispositions | CE93: =B93 -> -6.925 | CF93: =C93 -> 14.534 | CG93: =D93 -> -218.203 | CH93: =E93 -> 0 | CI93: =F93 -> 0 | CJ93: =K93 -> 0 | CK93: =P93 -> -21.432 | CL93: =U93 -> 0 | CM93: =Z93 -> 3.304 | CN93: =AE93 -> -11.058 | CO93: =AJ93 -> -136 | CP93: =AO93 -> 0 | CQ93: =AT93 -> 0 | CR93: =AY93 -> 0 | CS93: =BD93 -> 0 | CT93: =BI93 -> -1101 | CU93: =BN93 -> 0 | CV93: =BS93 -> 0 | CW93: =BX93 -> 0 | CX93: =BY93 -> 0 | CY93: =BZ93 -> 0 | CZ93: =CA93 -> 0
A94: Other | B94: =-8.347+158.962 -> 150.615 | C94: =-9.618 -> -9.618 | D94: =-12.468+103.5 -> 91.032 | E94: 9.338 | F94: 5.78 | G94: -6.766 | H94: =-4.982-G94 -> 1.784 | I94: =-0.347-H94-G94 -> 4.635 | J94: =2.896-I94-H94-G94 -> 3.243 | K94: =SUM(G94:J94) -> 2.896 | L94: =3.685 -> 3.685 | M94: =2.799-L94 -> -0.886 | N94: =7.27-M94-L94 -> 4.471 | O94: =12.639-N94-M94-L94 -> 5.369 | P94: =SUM(L94:O94) -> 12.639 | Q94: =2.055+2.462 -> 4.517 | R94: =-1.976-Q94 -> -6.493 | S94: =-6.946-R94-Q94 -> -4.97 | T94: =-16.029-S94-R94-Q94 -> -9.083 | U94: =SUM(Q94:T94) -> -16.029 | V94: -1.348 | W94: =2.866-V94 -> 4.214 | X94: =4.172-W94-V94 -> 1.306 | Y94: =11.539-X94-W94-V94 -> 7.367 | Z94: =SUM(V94:Y94) -> 11.539 | AA94: 1.7 | AB94: =2.4-AA94 -> 0.7 | AC94: =-4.5-AB94-AA94 -> -6.9 | AD94: =35.111-AC94-AB94-AA94 -> 39.611 | AE94: =SUM(AA94:AD94) -> 35.111 | AF94: 4.8 | AG94: =16.5-AF94 -> 11.7 | AH94: =12.9-AG94-AF94 -> -3.6 | AI94: =93-SUM(AF94:AH94) -> 80.1 | AJ94: =SUM(AF94:AI94) -> 93 | AK94: 19 | AL94: =18-AK94 -> -1 | AM94: =46-SUM(AK94:AL94) -> 28 | AN94: =16-SUM(AK94:AM94) -> -30 | AO94: =SUM(AK94:AN94) -> 16 | AP94: 87 | AQ94: =9-AP94 -> -78 | AR94: =0-SUM(AP94:AQ94)-38 -> -47 | AS94: =96-SUM(AP94:AR94) -> 134 | AT94: =SUM(AP94:AS94) -> 96 | AU94: 4 | AV94: =22-AU94-1 -> 17 | AW94: =106-AV94-AU94 -> 85 | AX94: =1587+80-SUM(AU94:AW94) -> 1561 | AY94: =SUM(AU94:AX94) -> 1667 | AZ94: 33 | BA94: =22-AZ94 -> -11 | BB94: =139-SUM(AZ94:BA94) -> 117 | BC94: =119+46-SUM(AZ94:BB94) -> 26 | BD94: =SUM(AZ94:BC94) -> 165 | BE94: 31 | BF94: =47-BE94+0.6 -> 16.6 | BG94: =56-SUM(BE94:BF94)+1.6 -> 10 | BH94: =54+30-SUM(BE94:BG94)+2 -> 28.4 | BI94: =SUM(BE94:BH94) -> 86 | BJ94: 14 | BK94: =26-BJ94 -> 12 | BL94: =42-SUM(BJ94:BK94) -> 16 | BM94: =55+96-SUM(BJ94:BL94) -> 109 | BN94: =SUM(BJ94:BM94) -> 151 | BO94: 16 | BP94: =BP53+BP54 -> -10.833333 | BQ94: =BQ53+BQ54 -> -10.833333 | BR94: =BR53+BR54 -> -10.833333 | BS94: =SUM(BO94:BR94) -> -16.5 | BT94: =BT53+BT54 -> 0 | BU94: =BU53+BU54 -> 0 | BV94: =BV53+BV54 -> 0 | BW94: =BW53+BW54 -> 0 | BX94: =SUM(BT94:BW94) -> 0 | BY94: =BY53+BY54 -> 0 | BZ94: =BZ53+BZ54 -> 0 | CA94: =CA53+CA54 -> 0 | CD94: =A94 -> Other | CE94: =B94 -> 150.615 | CF94: =C94 -> -9.618 | CG94: =D94 -> 91.032 | CH94: =E94 -> 9.338 | CI94: =F94 -> 5.78 | CJ94: =K94 -> 2.896 | CK94: =P94 -> 12.639 | CL94: =U94 -> -16.029 | CM94: =Z94 -> 11.539 | CN94: =AE94 -> 35.111 | CO94: =AJ94 -> 93 | CP94: =AO94 -> 16 | CQ94: =AT94 -> 96 | CR94: =AY94 -> 1667 | CS94: =BD94 -> 165 | CT94: =BI94 -> 86 | CU94: =BN94 -> 151 | CV94: =BS94 -> -16.5 | CW94: =BX94 -> 0 | CX94: =BY94 -> 0 | CY94: =BZ94 -> 0 | CZ94: =CA94 -> 0
A96: Changes in Operating Assets and Liabilities, Net of Effect of Acquisitions and Dispositions | CD96: =A96 -> Changes in Operating Assets and Liabilities, Net of Effect of Acquisitions and Dispositions
A97: Accounts Receivable | B97: 23.308 | C97: 61.623 | D97: 77.055 | E97: -100.176 | F97: -134.975 | G97: 226.879 | H97: =-15.405-G97 -> -242.284 | I97: =-214.064-H97-G97 -> -198.659 | J97: =-131.686-I97-H97-G97 -> 82.378 | K97: =SUM(G97:J97) -> -131.686 | L97: 262.148 | M97: =-49.702-L97 -> -311.85 | N97: =-242.221-M97-L97 -> -192.519 | O97: =71.448-N97-M97-L97 -> 313.669 | P97: =SUM(L97:O97) -> 71.448 | Q97: 230.742 | R97: =-77.385-Q97 -> -308.127 | S97: =-138.744-R97-Q97 -> -61.359 | T97: =95.07-S97-R97-Q97 -> 233.814 | U97: =SUM(Q97:T97) -> 95.07 | V97: 211.766 | W97: =-1.397-V97 -> -213.163 | X97: =-126.289-W97-V97 -> -124.892 | Y97: =50.313-X97-W97-V97 -> 176.602 | Z97: =SUM(V97:Y97) -> 50.313 | AA97: 190.6 | AB97: =-42.4-AA97 -> -233 | AC97: =-165.3-AB97-AA97 -> -122.9 | AD97: =-37.039-AC97-AB97-AA97 -> 128.261 | AE97: =SUM(AA97:AD97) -> -37.039 | AF97: 197.4 | AG97: =2.7-AF97 -> -194.7 | AH97: =-146.9-AG97-AF97 -> -149.6 | AI97: =-55-SUM(AF97:AH97) -> 91.9 | AJ97: =SUM(AF97:AI97) -> -55 | AK97: -47 | AL97: =-48-AK97 -> -1 | AM97: =-122-SUM(AK97:AL97) -> -74 | AN97: =-239-SUM(AK97:AM97) -> -117 | AO97: =SUM(AK97:AN97) -> -239 | AP97: -46 | AQ97: =-11-AP97 -> 35 | AR97: =-15-SUM(AP97:AQ97) -> -4 | AS97: =-35-SUM(AP97:AR97) -> -20 | AT97: =SUM(AP97:AS97) -> -35 | AU97: -9 | AV97: =-7-AU97 -> 2 | AW97: =12-AV97-AU97 -> 19 | AX97: =+-9-SUM(AU97:AW97) -> -21 | AY97: =SUM(AU97:AX97) -> -9 | AZ97: -69 | BA97: =+-136-AZ97 -> -67 | BB97: =+-44-SUM(AZ97:BA97) -> 92 | BC97: =+-118-SUM(AZ97:BB97) -> -74 | BD97: =SUM(AZ97:BC97) -> -118 | BE97: -7 | BF97: =+-39-BE97 -> -32 | BG97: =+-26-SUM(BE97:BF97) -> 13 | BH97: =+-177-SUM(BE97:BG97) -> -151 | BI97: =SUM(BE97:BH97) -> -177 | BJ97: 12 | BK97: =-49-BJ97 -> -61 | BL97: =-64-SUM(BJ97:BK97) -> -15 | BM97: =-196-SUM(BJ97:BL97) -> -132 | BN97: =SUM(BJ97:BM97) -> -196 | BO97: 7 | BP97: =BO144-BP144 -> 36.368095 | BQ97: =BP144-BQ144 -> -7.0167122 | BR97: =BQ144-BR144 -> -122.10104 | BS97: =SUM(BO97:BR97) -> -85.749656 | BT97: =BS144-BT144 -> 17.046411 | BU97: =BT144-BU144 -> 26.942239 | BV97: =BU144-BV144 -> -8.9109102 | BW97: =BV144-BW144 -> -197.7504 | BX97: =SUM(BT97:BW97) -> -162.67266 | BY97: =BX144-BY144 -> -137.74034 | BZ97: =BY144-BZ144 -> -130.6022 | CA97: =BZ144-CA144 -> -129.7011 | CD97: =A97 -> Accounts Receivable | CE97: =B97 -> 23.308 | CF97: =C97 -> 61.623 | CG97: =D97 -> 77.055 | CH97: =E97 -> -100.176 | CI97: =F97 -> -134.975 | CJ97: =K97 -> -131.686 | CK97: =P97 -> 71.448 | CL97: =U97 -> 95.07 | CM97: =Z97 -> 50.313 | CN97: =AE97 -> -37.039 | CO97: =AJ97 -> -55 | CP97: =AO97 -> -239 | CQ97: =AT97 -> -35 | CR97: =AY97 -> -9 | CS97: =BD97 -> -118 | CT97: =BI97 -> -177 | CU97: =BN97 -> -196 | CV97: =BS97 -> -85.749656 | CW97: =BX97 -> -162.67266 | CX97: =BY97 -> -137.74034 | CY97: =BZ97 -> -130.6022 | CZ97: =CA97 -> -129.7011
A98: Inventories | B98: 0 | C98: 0 | D98: 0 | E98: -27.393 | F98: -9.484 | G98: -35.149 | H98: =-53.441-G98 -> -18.292 | I98: =-3.858-H98-G98 -> 49.583 | J98: =21.619-I98-H98-G98 -> 25.477 | K98: =SUM(G98:J98) -> 21.619 | L98: -61.945 | M98: =-98.947-L98 -> -37.002 | N98: =-41.916-M98-L98 -> 57.031 | O98: =-11.601-N98-M98-L98 -> 30.315 | P98: =SUM(L98:O98) -> -11.601 | Q98: -88.332 | R98: =-143.096-Q98 -> -54.764 | S98: =-74.125-R98-Q98 -> 68.971 | T98: =-26.482-S98-R98-Q98 -> 47.643 | U98: =SUM(Q98:T98) -> -26.482 | V98: -20.797 | W98: =-20.907-V98 -> -0.11 | X98: =31.717-W98-V98 -> 52.624 | Y98: =67.645-X98-W98-V98 -> 35.928 | Z98: =SUM(V98:Y98) -> 67.645 | AA98: -17.1 | AB98: =-38.6-AA98 -> -21.5 | AC98: =6.6-AB98-AA98 -> 45.2 | AD98: =26.923-AC98-AB98-AA98 -> 20.323 | AE98: =SUM(AA98:AD98) -> 26.923 | AF98: -40.9 | AG98: =-63.1-AF98 -> -22.2 | AH98: =-11.9-AG98-AF98 -> 51.2 | AI98: =13-SUM(AF98:AH98) -> 24.9 | AJ98: =SUM(AF98:AI98) -> 13 | AK98: 0 | AL98: =0-AK98 -> 0 | AM98: =0-SUM(AK98:AL98) -> 0 | AN98: =0-SUM(AK98:AM98) -> 0 | AO98: =SUM(AK98:AN98) -> 0 | AP98: 0 | AQ98: =0-AP98 -> 0 | AR98: =0-SUM(AP98:AQ98) -> 0 | AS98: =0-SUM(AP98:AR98) -> 0 | AT98: =SUM(AP98:AS98) -> 0 | AU98: 0 | AV98: 0 | AW98: =0-AV98-AU98 -> 0 | AX98: 0 | AY98: =SUM(AU98:AX98) -> 0 | AZ98: 0 | BA98: =AZ145-BA145 -> 0 | BB98: =BA145-BB145 -> 0 | BC98: =BB145-BC145 -> 0 | BD98: =SUM(AZ98:BC98) -> 0 | BE98: 0 | BF98: 0 | BG98: 0 | BH98: 0 | BI98: =SUM(BE98:BH98) -> 0 | BJ98: 0 | BK98: 0 | BL98: 0 | BM98: 0 | BN98: =SUM(BJ98:BM98) -> 0 | BO98: 0 | BP98: =BO145-BP145 -> 0 | BQ98: =BP145-BQ145 -> 0 | BR98: =BQ145-BR145 -> 0 | BS98: =SUM(BO98:BR98) -> 0 | BT98: =BS145-BT145 -> 0 | BU98: =BT145-BU145 -> 0 | BV98: =BU145-BV145 -> 0 | BW98: =BV145-BW145 -> 0 | BX98: =SUM(BT98:BW98) -> 0 | BY98: =BX145-BY145 -> 0 | BZ98: =BY145-BZ145 -> 0 | CA98: =BZ145-CA145 -> 0 | CD98: =A98 -> Inventories | CE98: =B98 -> 0 | CF98: =C98 -> 0 | CG98: =D98 -> 0 | CH98: =E98 -> -27.393 | CI98: =F98 -> -9.484 | CJ98: =K98 -> 21.619 | CK98: =P98 -> -11.601 | CL98: =U98 -> -26.482 | CM98: =Z98 -> 67.645 | CN98: =AE98 -> 26.923 | CO98: =AJ98 -> 13 | CP98: =AO98 -> 0 | CQ98: =AT98 -> 0 | CR98: =AY98 -> 0 | CS98: =BD98 -> 0 | CT98: =BI98 -> 0 | CU98: =BN98 -> 0 | CV98: =BS98 -> 0 | CW98: =BX98 -> 0 | CX98: =BY98 -> 0 | CY98: =BZ98 -> 0 | CZ98: =CA98 -> 0
A99: Prepaid and Other Current Assets | B99: 27.023 | C99: 7.185 | D99: 18.927 | E99: -80.828 | F99: 57.913 | G99: -25.992 | H99: =-14.086-G99 -> 11.906 | I99: =-0.498-H99-G99 -> 13.588 | J99: =10.588-I99-H99-G99 -> 11.086 | K99: =SUM(G99:J99) -> 10.588 | L99: -12.657 | M99: =-2.907-L99 -> 9.75 | N99: =11.372-M99-L99 -> 14.279 | O99: =-4.717-N99-M99-L99 -> -16.089 | P99: =SUM(L99:O99) -> -4.717 | Q99: -14.912 | R99: =-9.257-Q99 -> 5.655 | S99: =13.146-R99-Q99 -> 22.403 | T99: =1.702-S99-R99-Q99 -> -11.444 | U99: =SUM(Q99:T99) -> 1.702 | V99: -19.862 | W99: =-14.221-V99 -> 5.641 | X99: =-6.239-W99-V99 -> 7.982 | Y99: =-11.807-X99-W99-V99 -> -5.568 | Z99: =SUM(V99:Y99) -> -11.807 | AA99: -26.9 | AB99: =-13-AA99 -> 13.9 | AC99: =5.8-AB99-AA99 -> 18.8 | AD99: =0.506-AC99-AB99-AA99 -> -5.294 | AE99: =SUM(AA99:AD99) -> 0.506 | AF99: -31.6 | AG99: =-15.7-AF99 -> 15.9 | AH99: =-3.4-AG99-AF99 -> 12.3 | AI99: =-11-SUM(AF99:AH99) -> -7.6 | AJ99: =SUM(AF99:AI99) -> -11 | AK99: -13 | AL99: =-3-AK99 -> 10 | AM99: =-28-SUM(AK99:AL99) -> -25 | AN99: =3-SUM(AK99:AM99) -> 31 | AO99: =SUM(AK99:AN99) -> 3 | AP99: -25 | AQ99: =-9-AP99 -> 16 | AR99: =-43-SUM(AP99:AQ99) -> -34 | AS99: =-29-SUM(AP99:AR99) -> 14 | AT99: =SUM(AP99:AS99) -> -29 | AU99: -6 | AV99: =-11-AU99 -> -5 | AW99: =-8-AV99-AU99 -> 3 | AX99: =+-7-SUM(AU99:AW99) -> 1 | AY99: =SUM(AU99:AX99) -> -7 | AZ99: -10 | BA99: =+-24-AZ99 -> -14 | BB99: =+-6-SUM(AZ99:BA99) -> 18 | BC99: =+-4-SUM(AZ99:BB99) -> 2 | BD99: =SUM(AZ99:BC99) -> -4 | BE99: -19 | BF99: =+-21-BE99 -> -2 | BG99: =+-2-SUM(BE99:BF99) -> 19 | BH99: =-2-SUM(BE99:BG99) -> 0 | BI99: =SUM(BE99:BH99) -> -2 | BJ99: 9 | BK99: =-13-BJ99 -> -22 | BL99: =3-SUM(BJ99:BK99) -> 16 | BM99: =10-SUM(BJ99:BL99) -> 7 | BN99: =SUM(BJ99:BM99) -> 10 | BO99: -21 | BP99: =BO147-BP147 -> 26.937624 | BQ99: =BP147-BQ147 -> 23.905466 | BR99: =BQ147-BR147 -> -60.905131 | BS99: =SUM(BO99:BR99) -> -31.06204 | BT99: =BS147-BT147 -> -0.8363806 | BU99: =BT147-BU147 -> 26.717415 | BV99: =BU147-BV147 -> 25.118199 | BW99: =BV147-BW147 -> -64.441901 | BX99: =SUM(BT99:BW99) -> -13.442668 | BY99: =BX147-BY147 -> -12.33059 | BZ99: =BY147-BZ147 -> -13.071662 | CA99: =BZ147-CA147 -> -12.36485 | CD99: =A99 -> Prepaid and Other Current Assets | CE99: =B99 -> 27.023 | CF99: =C99 -> 7.185 | CG99: =D99 -> 18.927 | CH99: =E99 -> -80.828 | CI99: =F99 -> 57.913 | CJ99: =K99 -> 10.588 | CK99: =P99 -> -4.717 | CL99: =U99 -> 1.702 | CM99: =Z99 -> -11.807 | CN99: =AE99 -> 0.506 | CO99: =AJ99 -> -11 | CP99: =AO99 -> 3 | CQ99: =AT99 -> -29 | CR99: =AY99 -> -7 | CS99: =BD99 -> -4 | CT99: =BI99 -> -2 | CU99: =BN99 -> 10 | CV99: =BS99 -> -31.06204 | CW99: =BX99 -> -13.442668 | CX99: =BY99 -> -12.33059 | CY99: =BZ99 -> -13.071662 | CZ99: =CA99 -> -12.36485
A100: Accounts Payable and Accrued Expenses | B100: 42.202 | C100: 4.373 | D100: 32.692 | E100: 53.253 | F100: 93.879 | G100: -371.39 | H100: =-271.965-G100 -> 99.425 | I100: =-109.958-H100-G100 -> 162.007 | J100: =44.334-I100-H100-G100 -> 154.292 | K100: =SUM(G100:J100) -> 44.334 | L100: -323.755 | M100: =-187.447-L100 -> 136.308 | N100: =-65.365-M100-L100 -> 122.082 | O100: =34.84-N100-M100-L100 -> 100.205 | P100: =SUM(L100:O100) -> 34.84 | Q100: -397.739 | R100: =-324.595-Q100 -> 73.144 | S100: =-291.444-R100-Q100 -> 33.151 | T100: =-242.327-S100-R100-Q100 -> 49.117 | U100: =SUM(Q100:T100) -> -242.327 | V100: -265.577 | W100: =-207.234-V100 -> 58.343 | X100: =-71.117-W100-V100 -> 136.117 | Y100: =0.079-X100-W100-V100 -> 71.196 | Z100: =SUM(V100:Y100) -> 0.079 | AA100: -253.5 | AB100: =-141.9-AA100 -> 111.6 | AC100: =-4.2-AB100-AA100 -> 137.7 | AD100: =134.003-AC100-AB100-AA100 -> 138.203 | AE100: =SUM(AA100:AD100) -> 134.003 | AF100: -370.2 | AG100: =-269-AF100 -> 101.2 | AH100: =-174.2-AG100-AF100 -> 94.8 | AI100: =-67-SUM(AF100:AH100) -> 107.2 | AJ100: =SUM(AF100:AI100) -> -67 | AK100: -189 | AL100: =-205-AK100 -> -16 | AM100: =-17-SUM(AK100:AL100) -> 188 | AN100: =60-SUM(AK100:AM100) -> 77 | AO100: =SUM(AK100:AN100) -> 60 | AP100: -242 | AQ100: =-193-AP100 -> 49 | AR100: =-165-SUM(AP100:AQ100) -> 28 | AS100: =-94-SUM(AP100:AR100) -> 71 | AT100: =SUM(AP100:AS100) -> -94 | AU100: -297 | AV100: =-251-AU100 -> 46 | AW100: =-211-AV100-AU100 -> 40 | AX100: =+-130-SUM(AU100:AW100) -> 81 | AY100: =SUM(AU100:AX100) -> -130 | AZ100: -305 | BA100: =+-257-AZ100 -> 48 | BB100: =+-186-SUM(AZ100:BA100) -> 71 | BC100: =+-92-SUM(AZ100:BB100) -> 94 | BD100: =SUM(AZ100:BC100) -> -92 | BE100: -274 | BF100: =+-212-BE100 -> 62 | BG100: =+-127-SUM(BE100:BF100) -> 85 | BH100: =+-26-SUM(BE100:BG100) -> 101 | BI100: =SUM(BE100:BH100) -> -26 | BJ100: -235 | BK100: =-139-BJ100 -> 96 | BL100: =-50-SUM(BJ100:BK100) -> 89 | BM100: =75-SUM(BJ100:BL100) -> 125 | BN100: =SUM(BJ100:BM100) -> 75 | BO100: -289 | BP100: =BP161-BO161+BP162-BO162+BP163-BO163 -> 104.70198 | BQ100: =BQ161-BP161+BQ162-BP162+BQ163-BP163 -> 86.894106 | BR100: =BR161-BQ161+BR162-BQ162+BR163-BQ163 -> 118.88232 | BS100: =SUM(BO100:BR100) -> 21.478415 | BT100: =BT161-BS161+BT162-BS162+BT163-BS163 -> -290.6585 | BU100: =BU161-BT161+BU162-BT162+BU163-BT163 -> 114.18897 | BV100: =BV161-BU161+BV162-BU162+BV163-BU163 -> 92.74342 | BW100: =BW161-BV161+BW162-BV162+BW163-BV163 -> 125.62451 | BX100: =SUM(BT100:BW100) -> 41.898408 | BY100: =BY161-BX161+BY162-BX162+BY163-BX163 -> 35.301234 | BZ100: =BZ161-BY161+BZ162-BY162+BZ163-BY163 -> 40.578883 | CA100: =CA161-BZ161+CA162-BZ162+CA163-BZ163 -> 38.384699 | CD100: =A100 -> Accounts Payable and Accrued Expenses | CE100: =B100 -> 42.202 | CF100: =C100 -> 4.373 | CG100: =D100 -> 32.692 | CH100: =E100 -> 53.253 | CI100: =F100 -> 93.879 | CJ100: =K100 -> 44.334 | CK100: =P100 -> 34.84 | CL100: =U100 -> -242.327 | CM100: =Z100 -> 0.079 | CN100: =AE100 -> 134.003 | CO100: =AJ100 -> -67 | CP100: =AO100 -> 60 | CQ100: =AT100 -> -94 | CR100: =AY100 -> -130 | CS100: =BD100 -> -92 | CT100: =BI100 -> -26 | CU100: =BN100 -> 75 | CV100: =BS100 -> 21.478415 | CW100: =BX100 -> 41.898408 | CX100: =BY100 -> 35.301234 | CY100: =BZ100 -> 40.578883 | CZ100: =CA100 -> 38.384699
A101: Unearned Revenue | B101: -42.696 | C101: -56.149 | D101: 51.451 | E101: 115.636 | F101: 123.414 | G101: 16.003 | H101: =38.385-G101 -> 22.382 | I101: =25.508-H101-G101 -> -12.877 | J101: =120.805-I101-H101-G101 -> 95.297 | K101: =SUM(G101:J101) -> 120.805 | L101: 9.688 | M101: =40.92-L101 -> 31.232 | N101: =7.306-M101-L101 -> -33.614 | O101: =86.877-N101-M101-L101 -> 79.571 | P101: =SUM(L101:O101) -> 86.877 | Q101: -3.883 | R101: =8.111-Q101 -> 11.994 | S101: =-13.697-R101-Q101 -> -21.808 | T101: =25.145-S101-R101-Q101 -> 38.842 | U101: =SUM(Q101:T101) -> 25.145 | V101: -7.725 | W101: =-6.575-V101 -> 1.15 | X101: =-32.915-W101-V101 -> -26.34 | Y101: =25.619-X101-W101-V101 -> 58.534 | Z101: =SUM(V101:Y101) -> 25.619 | AA101: 9.2 | AB101: =42.8-AA101 -> 33.6 | AC101: =2.2-AB101-AA101 -> -40.6 | AD101: =74.855-AC101-AB101-AA101 -> 72.655 | AE101: =SUM(AA101:AD101) -> 74.855 | AF101: 1.6 | AG101: =16.4-AF101 -> 14.8 | AH101: =23.7-AG101-AF101 -> 7.3 | AI101: =83-SUM(AF101:AH101) -> 59.3 | AJ101: =SUM(AF101:AI101) -> 83 | AK101: 8 | AL101: =-3-AK101 -> -11 | AM101: =-29-SUM(AK101:AL101) -> -26 | AN101: =17-SUM(AK101:AM101) -> 46 | AO101: =SUM(AK101:AN101) -> 17 | AP101: 63 | AQ101: =71-AP101 -> 8 | AR101: =44-SUM(AP101:AQ101) -> -27 | AS101: =109-SUM(AP101:AR101) -> 65 | AT101: =SUM(AP101:AS101) -> 109 | AU101: 1 | AV101: =11-AU101 -> 10 | AW101: =7-AV101-AU101 -> -4 | AX101: =78-SUM(AU101:AW101) -> 71 | AY101: =SUM(AU101:AX101) -> 78 | AZ101: 48 | BA101: =71-AZ101 -> 23 | BB101: =18-SUM(AZ101:BA101) -> -53 | BC101: =129-SUM(AZ101:BB101) -> 111 | BD101: =SUM(AZ101:BC101) -> 129 | BE101: 39 | BF101: =38-BE101 -> -1 | BG101: =+-6-SUM(BE101:BF101) -> -44 | BH101: =107-SUM(BE101:BG101) -> 113 | BI101: =SUM(BE101:BH101) -> 107 | BJ101: -6 | BK101: =-17-BJ101 -> -11 | BL101: =-107-SUM(BJ101:BK101) -> -90 | BM101: =85-SUM(BJ101:BL101) -> 192 | BN101: =SUM(BJ101:BM101) -> 85 | BO101: 27 | BP101: =BP166-BO166 -> -46.227235 | BQ101: =BQ166-BP166 -> -104.93329 | BR101: =BR166-BQ166 -> 168.53936 | BS101: =SUM(BO101:BR101) -> 44.378836 | BT101: =BT166-BS166 -> 67.730227 | BU101: =BU166-BT166 -> -34.803454 | BV101: =BV166-BU166 -> -109.27008 | BW101: =BW166-BV166 -> 177.66584 | BX101: =SUM(BT101:BW101) -> 101.32254 | BY101: =BY166-BX166 -> 92.940382 | BZ101: =BZ166-BY166 -> 98.526123 | CA101: =CA166-BZ166 -> 93.198614 | CD101: =A101 -> Unearned Revenue | CE101: =B101 -> -42.696 | CF101: =C101 -> -56.149 | CG101: =D101 -> 51.451 | CH101: =E101 -> 115.636 | CI101: =F101 -> 123.414 | CJ101: =K101 -> 120.805 | CK101: =P101 -> 86.877 | CL101: =U101 -> 25.145 | CM101: =Z101 -> 25.619 | CN101: =AE101 -> 74.855 | CO101: =AJ101 -> 83 | CP101: =AO101 -> 17 | CQ101: =AT101 -> 109 | CR101: =AY101 -> 78 | CS101: =BD101 -> 129 | CT101: =BI101 -> 107 | CU101: =BN101 -> 85 | CV101: =BS101 -> 44.378836 | CW101: =BX101 -> 101.32254 | CX101: =BY101 -> 92.940382 | CY101: =BZ101 -> 98.526123 | CZ101: =CA101 -> 93.198614
A102: Other Current Liabilities | B102: 0 | C102: 0 | D102: 0 | E102: -11.568 | F102: 44.001 | G102: -14.134 | H102: =-21.498-G102 -> -7.364 | I102: =-15.709-H102-G102 -> 5.789 | J102: =20.468-I102-H102-G102 -> 36.177 | K102: =SUM(G102:J102) -> 20.468 | L102: 27.571 | M102: =6.336-L102 -> -21.235 | N102: =8.604-M102-L102 -> 2.268 | O102: =71.636-N102-M102-L102 -> 63.032 | P102: =SUM(L102:O102) -> 71.636 | Q102: 1.419 | R102: =-9.222-Q102 -> -10.641 | S102: =0.497-R102-Q102 -> 9.719 | T102: =26.317-S102-R102-Q102 -> 25.82 | U102: =SUM(Q102:T102) -> 26.317 | V102: 20.236 | W102: =22.389-V102 -> 2.153 | X102: =6.609-W102-V102 -> -15.78 | Y102: =-14.453-X102-W102-V102 -> -21.062 | Z102: =SUM(V102:Y102) -> -14.453 | AA102: 9.2 | AB102: =-6.8-AA102 -> -16 | AC102: =-9.8-AB102-AA102 -> -3 | AD102: =-18.761-AC102-AB102-AA102 -> -8.961 | AE102: =SUM(AA102:AD102) -> -18.761 | AF102: 1 | AG102: =-12.7-AF102 -> -13.7 | AH102: =-50.6-AG102-AF102 -> -37.9 | AI102: =-67-SUM(AF102:AH102) -> -16.4 | AJ102: =SUM(AF102:AI102) -> -67 | AK102: -6 | AL102: =-64-AK102 -> -58 | AM102: =-32-SUM(AK102:AL102) -> 32 | AN102: =-70-SUM(AK102:AM102) -> -38 | AO102: =SUM(AK102:AN102) -> -70 | AP102: 14 | AQ102: =-40-AP102 -> -54 | AR102: =-44-SUM(AP102:AQ102) -> -4 | AS102: =-89-SUM(AP102:AR102) -> -45 | AT102: =SUM(AP102:AS102) -> -89 | AU102: 33 | AV102: =-69-AU102 -> -102 | AW102: =-65-AV102-AU102 -> 4 | AX102: =+-51-SUM(AU102:AW102) -> 14 | AY102: =SUM(AU102:AX102) -> -51 | AZ102: =+-1559-17 -> -1576 | BA102: =+-1609+-36-AZ102 -> -69 | BB102: =+-1624-53-SUM(AZ102:BA102) -> -32 | BC102: =+-1624-78-SUM(AZ102:BB102) -> -25 | BD102: =SUM(AZ102:BC102) -> -1702 | BE102: 22 | BF102: =+-23-BE102 -> -45 | BG102: =+-12-SUM(BE102:BF102) -> 11 | BH102: =+-21-SUM(BE102:BG102) -> -9 | BI102: =SUM(BE102:BH102) -> -21 | BJ102: -58 | BK102: =-85-4-BJ102 -> -31 | BL102: =-4-94-SUM(BJ102:BK102) -> -9 | BM102: =-4-85-SUM(BJ102:BL102) -> 9 | BN102: =SUM(BJ102:BM102) -> -89 | BO102: =19-29 -> -10 | BP102: =BP167-BO167 -> 0 | BQ102: =BQ167-BP167 -> 0 | BR102: =BR167-BQ167 -> 0 | BS102: =SUM(BO102:BR102) -> -10 | BT102: =BT167-BS167 -> 0 | BU102: =BU167-BT167 -> 0 | BV102: =BV167-BU167 -> 0 | BW102: =BW167-BV167 -> 0 | BX102: =SUM(BT102:BW102) -> 0 | BY102: =BY167-BX167 -> 0 | BZ102: =BZ167-BY167 -> 0 | CA102: =CA167-BZ167 -> 0 | CD102: =A102 -> Other Current Liabilities | CE102: =B102 -> 0 | CF102: =C102 -> 0 | CG102: =D102 -> 0 | CH102: =E102 -> -11.568 | CI102: =F102 -> 44.001 | CJ102: =K102 -> 20.468 | CK102: =P102 -> 71.636 | CL102: =U102 -> 26.317 | CM102: =Z102 -> -14.453 | CN102: =AE102 -> -18.761 | CO102: =AJ102 -> -67 | CP102: =AO102 -> -70 | CQ102: =AT102 -> -89 | CR102: =AY102 -> -51 | CS102: =BD102 -> -1702 | CT102: =BI102 -> -21 | CU102: =BN102 -> -89 | CV102: =BS102 -> -10 | CW102: =BX102 -> 0 | CX102: =BY102 -> 0 | CY102: =BZ102 -> 0 | CZ102: =CA102 -> 0
A103: Net Change in Prepaid/Accrued Income Taxes | B103: =42.618+7.357 -> 49.975 | C103: =18.475+64.492 -> 82.967 | D103: 169.935 | E103: =-106.8+28.664 -> -78.136 | F103: 48.048 | G103: 11.004 | H103: =107.702-G103 -> 96.698 | I103: =179.06-H103-G103 -> 71.358 | J103: =51.983-I103-H103-G103 -> -127.077 | K103: =SUM(G103:J103) -> 51.983 | L103: 19.176 | M103: =58.786-L103 -> 39.61 | N103: =132.672-M103-L103 -> 73.886 | O103: =-36.94-N103-M103-L103 -> -169.612 | P103: =SUM(L103:O103) -> -36.94 | Q103: 11.516 | R103: =90.828-Q103 -> 79.312 | S103: =170.148-R103-Q103 -> 79.32 | T103: =7.354-S103-R103-Q103 -> -162.794 | U103: =SUM(Q103:T103) -> 7.354 | V103: 1.608 | W103: =67.926-V103 -> 66.318 | X103: =161.624-W103-V103 -> 93.698 | Y103: =-17.892-X103-W103-V103 -> -179.516 | Z103: =SUM(V103:Y103) -> -17.892 | AA103: 12.3 | AB103: =61.5-AA103 -> 49.2 | AC103: =181.5-AB103-AA103 -> 120 | AD103: =-38.433-AC103-AB103-AA103 -> -219.933 | AE103: =SUM(AA103:AD103) -> -38.433 | AF103: 50.7 | AG103: =100-AF103 -> 49.3 | AH103: =288.4-AG103-AF103 -> 188.4 | AI103: =49-SUM(AF103:AH103) -> -239.4 | AJ103: =SUM(AF103:AI103) -> 49 | AK103: 53 | AL103: =94-AK103 -> 41 | AM103: =115-SUM(AK103:AL103) -> 21 | AN103: =119-SUM(AK103:AM103) -> 4 | AO103: =SUM(AK103:AN103) -> 119 | AP103: -148 | AQ103: =-166-AP103 -> -18 | AR103: =-121-SUM(AP103:AQ103) -> 45 | AS103: =-238-SUM(AP103:AR103) -> -117 | AT103: =SUM(AP103:AS103) -> -238 | AU103: 95 | AV103: =111-AU103 -> 16 | AW103: =93-AV103-AU103 -> -18 | AX103: =+-93-SUM(AU103:AW103) -> -186 | AY103: =SUM(AU103:AX103) -> -93 | AZ103: 110 | BA103: =119-AZ103 -> 9 | BB103: =140-SUM(AZ103:BA103) -> 21 | BC103: =61-SUM(AZ103:BB103) -> -79 | BD103: =SUM(AZ103:BC103) -> 61 | BE103: 99 | BF103: =73-BE103 -> -26 | BG103: =352-SUM(BE103:BF103) -> 279 | BH103: =132-SUM(BE103:BG103) -> -220 | BI103: =SUM(BE103:BH103) -> 132 | BJ103: 146 | BK103: =-45-BJ103 -> -191 | BL103: =-42-SUM(BJ103:BK103) -> 3 | BM103: =32-SUM(BJ103:BL103) -> 74 | BN103: =SUM(BJ103:BM103) -> 32 | BO103: 74 | BP103: =BP165-BO165 -> -14.121805 | BQ103: =BQ165-BP165 -> -3.2632794 | BR103: =BR165-BQ165 -> -49.192151 | BS103: =SUM(BO103:BR103) -> 7.4227647 | BT103: =BT165-BS165 -> 71.646268 | BU103: =BU165-BT165 -> -14.113545 | BV103: =BV165-BU165 -> -3.3552522 | BW103: =BW165-BV165 -> -52.181172 | BX103: =SUM(BT103:BW103) -> 1.996299 | BY103: =BY165-BX165 -> 1.8311502 | BZ103: =BZ165-BY165 -> 1.9412028 | CA103: =CA165-BZ165 -> 1.836238 | CD103: =A103 -> Net Change in Prepaid/Accrued Income Taxes | CE103: =B103 -> 49.975 | CF103: =C103 -> 82.967 | CG103: =D103 -> 169.935 | CH103: =E103 -> -78.136 | CI103: =F103 -> 48.048 | CJ103: =K103 -> 51.983 | CK103: =P103 -> -36.94 | CL103: =U103 -> 7.354 | CM103: =Z103 -> -17.892 | CN103: =AE103 -> -38.433 | CO103: =AJ103 -> 49 | CP103: =AO103 -> 119 | CQ103: =AT103 -> -238 | CR103: =AY103 -> -93 | CS103: =BD103 -> 61 | CT103: =BI103 -> 132 | CU103: =BN103 -> 32 | CV103: =BS103 -> 7.4227647 | CW103: =BX103 -> 1.996299 | CX103: =BY103 -> 1.8311502 | CY103: =BZ103 -> 1.9412028 | CZ103: =CA103 -> 1.836238
A104: Net change in Other Assets and Liabilities | B104: =3.196 -> 3.196 | C104: 18.921 | D104: =12.886-50.017 -> -37.131 | E104: 27.014 | F104: 50.465 | G104: 4.223 | H104: =25.405-G104 -> 21.182 | I104: =39.157-H104-G104 -> 13.752 | J104: =26.929-I104-H104-G104 -> -12.228 | K104: =SUM(G104:J104) -> 26.929 | L104: 12.535 | M104: =37.656-L104 -> 25.121 | N104: =59.41-M104-L104 -> 21.754 | O104: =6.403-N104-M104-L104 -> -53.007 | P104: =SUM(L104:O104) -> 6.403 | Q104: -15.488 | R104: =-7.603-Q104 -> 7.885 | S104: =-3.504-R104-Q104 -> 4.099 | T104: =4.703-S104-R104-Q104 -> 8.207 | U104: =SUM(Q104:T104) -> 4.703 | V104: -3.99 | W104: =-7.361-V104 -> -3.371 | X104: =-33.24-W104-V104 -> -25.879 | Y104: =-54.286-X104-W104-V104 -> -21.046 | Z104: =SUM(V104:Y104) -> -54.286 | AA104: 0.4 | AB104: =2.5-AA104 -> 2.1 | AC104: =-13.3-AB104-AA104 -> -15.8 | AD104: =-137.403-AC104-AB104-AA104 -> -124.103 | AE104: =SUM(AA104:AD104) -> -137.403 | AF104: 14.4 | AG104: =8.6-AF104 -> -5.8 | AH104: =16.3-AG104-AF104 -> 7.7 | AI104: =15-SUM(AF104:AH104) -> -1.3 | AJ104: =SUM(AF104:AI104) -> 15 | AK104: -16 | AL104: =-30-AK104 -> -14 | AM104: =-42-SUM(AK104:AL104) -> -12 | AN104: =-204-SUM(AK104:AM104) -> -162 | AO104: =SUM(AK104:AN104) -> -204 | AP104: 8 | AQ104: =-17-AP104 -> -25 | AR104: =-41-SUM(AP104:AQ104) -> -24 | AS104: =-110-SUM(AP104:AR104) -> -69 | AT104: =SUM(AP104:AS104) -> -110 | AU104: -23 | AV104: =-51-AU104 -> -28 | AW104: =-51-AV104-AU104 -> 0 | AX104: =+-55-SUM(AU104:AW104) -> -4 | AY104: =SUM(AU104:AX104) -> -55 | AZ104: 1 | BA104: =+-31-AZ104+1 -> -31 | BB104: =+-60-SUM(AZ104:BA104)+1 -> -29 | BC104: =+-35-SUM(AZ104:BB104) -> 24 | BD104: =SUM(AZ104:BC104) -> -35 | BE104: =+-31-108 -> -139 | BF104: =+-44-108-BE104 -> -13 | BG104: =+-134-57-SUM(BE104:BF104) -> -39 | BH104: =45-150-SUM(BE104:BG104) -> 86 | BI104: =SUM(BE104:BH104) -> -105 | BJ104: =-24-1 -> -25 | BK104: =-29-BJ104 -> -4 | BL104: =-36-SUM(BJ104:BK104) -> -7 | BM104: =15-SUM(BJ104:BL104) -> 51 | BN104: =SUM(BJ104:BM104) -> 15 | BO104: -44 | BP104: =BP172-BO172+BP173-BO173 -> 0 | BQ104: =BQ172-BP172+BQ173-BP173 -> 0 | BR104: =BR172-BQ172+BR173-BQ173 -> 0 | BS104: =SUM(BO104:BR104) -> -44 | BT104: =BT172-BS172+BT173-BS173 -> 0 | BU104: =BU172-BT172+BU173-BT173 -> 0 | BV104: =BV172-BU172+BV173-BU173 -> 0 | BW104: =BW172-BV172+BW173-BV173 -> 0 | BX104: =SUM(BT104:BW104) -> 0 | BY104: =BY172-BX172+BY173-BX173 -> 0 | BZ104: =BZ172-BY172+BZ173-BY173 -> 0 | CA104: =CA172-BZ172+CA173-BZ173 -> 0 | CD104: =A104 -> Net change in Other Assets and Liabilities | CE104: =B104 -> 3.196 | CF104: =C104 -> 18.921 | CG104: =D104 -> -37.131 | CH104: =E104 -> 27.014 | CI104: =F104 -> 50.465 | CJ104: =K104 -> 26.929 | CK104: =P104 -> 6.403 | CL104: =U104 -> 4.703 | CM104: =Z104 -> -54.286 | CN104: =AE104 -> -137.403 | CO104: =AJ104 -> 15 | CP104: =AO104 -> -204 | CQ104: =AT104 -> -110 | CR104: =AY104 -> -55 | CS104: =BD104 -> -35 | CT104: =BI104 -> -105 | CU104: =BN104 -> 15 | CV104: =BS104 -> -44 | CW104: =BX104 -> 0 | CX104: =BY104 -> 0 | CY104: =BZ104 -> 0 | CZ104: =CA104 -> 0
B105: ______ | C105: ______ | D105: ______ | E105: ______ | F105: ______ | G105: ______ | H105: ______ | I105: ______ | J105: ______ | K105: ______ | L105: ______ | M105: ______ | N105: ______ | O105: ______ | P105: ______ | Q105: ______ | R105: ______ | S105: ______ | T105: ______ | U105: ______ | V105: ______ | W105: ______ | X105: ______ | Y105: ______ | Z105: ______ | AA105: ______ | AB105: ______ | AC105: ______ | AD105: ______ | AE105: ______ | AF105: ______ | AG105: ______ | AH105: ______ | AI105: ______ | AJ105: ______ | AK105: ______ | AL105: ______ | AM105: ______ | AN105: ______ | AO105: ______ | AP105: ______ | AQ105: ______ | AR105: ______ | AS105: ______ | AT105: ______ | AU105: ______ | AV105: ______ | AW105: ______ | AX105: ______ | AY105: ______ | AZ105: ______ | BA105: ______ | BB105: ______ | BC105: ______ | BD105: ______ | BE105: ______ | BF105: ______ | BG105: ______ | BH105: ______ | BI105: ______ | BJ105: ______ | BK105: ______ | BL105: ______ | BM105: ______ | BN105: ______ | BO105: ______ | BP105: ______ | BQ105: ______ | BR105: ______ | BS105: ______ | BT105: ______ | BU105: ______ | BV105: ______ | BW105: ______ | BX105: ______ | BY105: ______ | BZ105: ______ | CA105: ______ | CE105: ______ | CF105: ______ | CG105: ______ | CH105: ______ | CI105: ______ | CJ105: ______ | CK105: ______ | CL105: ______ | CM105: ______ | CN105: ______ | CO105: ______ | CP105: ______ | CQ105: ______ | CR105: ______ | CS105: ______ | CT105: ______ | CU105: ______ | CV105: ______ | CW105: ______ | CX105: ______ | CY105: ______ | CZ105: ______
A106: Cash provided by operating activities | B106: =SUM(B84:B104) -> 1099.581 | C106: =SUM(C84:C104) -> 1142.391 | D106: =SUM(D84:D104) -> 1382.345 | E106: =SUM(E84:E104) -> 1063.472 | F106: =SUM(F84:F104) -> 1559.89 | G106: =SUM(G84:G104) -> -20.265 | H106: =SUM(H84:H104) -> 313.529 | I106: =SUM(I84:I104) -> 657.513 | ... AT106: =SUM(AT84:AT104) -> 795 | AU106: =+SUM(AU84:AU104) -> 113.5 | AV106: =+SUM(AV84:AV104) -> 332.5 | AW106: =+SUM(AW84:AW104) -> 374 | AX106: =+SUM(AX84:AX104) -> 389 | AY106: =SUM(AY84:AY104) -> 1209 | AZ106: =SUM(AZ84:AZ104) -> -1349 | BA106: =SUM(BA84:BA104) -> 452 | BB106: =SUM(BB84:BB104) -> 541 | BC106: =SUM(BC84:BC104) -> 550 | BD106: =SUM(BD84:BD104) -> 194 | BE106: =SUM(BE84:BE104) -> 133 | BF106: =SUM(BF84:BF104) -> 438.6 | ... CA106: =SUM(CA84:CA104) -> 3252.7629 | CD106: =A106 -> Cash provided by operating activities | CE106: =SUM(CE84:CE104) -> 1099.581 | CF106: =SUM(CF84:CF104) -> 1142.391 | CG106: =SUM(CG84:CG104) -> 1382.345 | CH106: =SUM(CH84:CH104) -> 1063.472 | CI106: =SUM(CI84:CI104) -> 1559.89 | CJ106: =SUM(CJ84:CJ104) -> 1509.304 | CK106: =SUM(CK84:CK104) -> 1716.951 | CL106: =SUM(CL84:CL104) -> 1168.753 | ... CZ106: =SUM(CZ84:CZ104) -> 3252.7629
A108: Cash Flows from Investing Activities | CD108: =A108 -> Cash Flows from Investing Activities
A109: Investment in Prepublication Costs | B109: -294.538 | C109: -249.317 | D109: -218.049 | E109: -237.76 | F109: -257.795 | G109: -61.59 | H109: =-125.061-G109 -> -63.471 | I109: =-189.358-H109-G109 -> -64.297 | J109: =-276.81-I109-H109-G109 -> -87.452 | K109: =SUM(G109:J109) -> -276.81 | L109: -57.409 | M109: =-132.646-L109 -> -75.237 | N109: =-209.539-M109-L109 -> -76.893 | O109: =-298.984-N109-M109-L109 -> -89.445 | P109: =SUM(L109:O109) -> -298.984 | Q109: -66.635 | R109: =-131.9-Q109 -> -65.265 | S109: =-197.264-R109-Q109 -> -65.364 | T109: =-254.106-S109-R109-Q109 -> -56.842 | U109: =SUM(Q109:T109) -> -254.106 | V109: -42.723 | W109: =-85.053-V109 -> -42.33 | X109: =-129.779-W109-V109 -> -44.726 | Y109: =-176.996-X109-W109-V109 -> -47.217 | Z109: =SUM(V109:Y109) -> -176.996 | AA109: -29.9 | AB109: =-60-AA109 -> -30.1 | AC109: =-99.3-AB109-AA109 -> -39.3 | AD109: =-150.842-AC109-AB109-AA109 -> -51.542 | AE109: =SUM(AA109:AD109) -> -150.842 | AF109: -28.1 | AG109: =-60.2-AF109 -> -32.1 | AH109: =-105.1-AG109-AF109 -> -44.9 | AI109: =-158-SUM(AF109:AH109) -> -52.9 | AJ109: =SUM(AF109:AI109) -> -158 | AK109: 0 | AL109: =0-AK109 -> 0 | AM109: =0-SUM(AK109:AL109) -> 0 | AN109: =0-SUM(AK109:AM109) -> 0 | AO109: =SUM(AK109:AN109) -> 0 | AP109: 0 | AQ109: =0-AP109 -> 0 | AR109: =0-SUM(AP109:AQ109) -> 0 | AS109: =0-SUM(AP109:AR109) -> 0 | AT109: =SUM(AP109:AS109) -> 0 | AU109: 0 | AV109: 0 | AW109: =0-AV109-AU109 -> 0 | AX109: 0 | AY109: =SUM(AU109:AX109) -> 0 | AZ109: 0 | BA109: 0 | BB109: 0 | BC109: 0 | BD109: =SUM(AZ109:BC109) -> 0 | BE109: 0 | BF109: 0 | BG109: 0 | BH109: 0 | BI109: =SUM(BE109:BH109) -> 0 | BJ109: 0 | BK109: 0 | BL109: 0 | BM109: 0 | BN109: =SUM(BJ109:BM109) -> 0 | BO109: 0 | BP109: 0 | BQ109: 0 | BR109: 0 | BS109: =SUM(BO109:BR109) -> 0 | BT109: 0 | BU109: 0 | BV109: 0 | BW109: 0 | BX109: =SUM(BT109:BW109) -> 0 | BY109: 0 | BZ109: 0 | CA109: 0 | CD109: =A109 -> Investment in Prepublication Costs | CE109: =B109 -> -294.538 | CF109: =C109 -> -249.317 | CG109: =D109 -> -218.049 | CH109: =E109 -> -237.76 | CI109: =F109 -> -257.795 | CJ109: =K109 -> -276.81 | CK109: =P109 -> -298.984 | CL109: =U109 -> -254.106 | CM109: =Z109 -> -176.996 | CN109: =AE109 -> -150.842 | CO109: =AJ109 -> -158 | CP109: =AO109 -> 0 | CQ109: =AT109 -> 0 | CR109: =AY109 -> 0 | CS109: =BD109 -> 0 | CT109: =BI109 -> 0 | CU109: =BN109 -> 0 | CV109: =BS109 -> 0 | CW109: =BX109 -> 0 | CX109: =BY109 -> 0 | CY109: =BZ109 -> 0 | CZ109: =CA109 -> 0
A110: Capital Expenditures | B110: =-116.895-28.84 -> -145.735 | C110: =-70.019-55.477 -> -125.496 | D110: =-114.984-28.145 -> -143.129 | E110: =-139.003-10.623 -> -149.626 | F110: =-120.232-16.456 -> -136.688 | G110: =-11.648-2.933 -> -14.581 | H110: =-32.176-10.716-G110 -> -28.311 | I110: =-56.798-15.434-H110-G110 -> -29.34 | J110: =-126.593-22.978-I110-H110-G110 -> -77.339 | K110: =SUM(G110:J110) -> -149.571 | L110: =-22.7-2.333 -> -25.033 | M110: =-83.449-L110-7.791 -> -66.207 | N110: =-146.453-10.483-M110-L110 -> -65.696 | O110: =-229.609-16.654-N110-M110-L110 -> -89.327 | P110: =SUM(L110:O110) -> -246.263 | Q110: =-23.572-6.006 -> -29.578 | R110: =-48.756-10.141-Q110 -> -29.319 | S110: =-66.437-18.581-R110-Q110 -> -26.121 | T110: =-105.978-25.353-S110-R110-Q110 -> -46.313 | U110: =SUM(Q110:T110) -> -131.331 | V110: =-8.025-1.711 -> -9.736 | W110: =-16.898-V110-7.671 -> -14.833 | X110: =-32.603-14.801-W110-V110 -> -22.835 | Y110: =-92.29-X110-W110-V110 -> -44.886 | Z110: =SUM(V110:Y110) -> -92.29 | AA110: -11.7 | AB110: =-39-AA110 -> -27.3 | AC110: =-65.3-AB110-AA110 -> -26.3 | AD110: =-115.443-AC110-AB110-AA110 -> -50.143 | AE110: =SUM(AA110:AD110) -> -115.443 | AF110: -18.4 | AG110: =-44.6-AF110 -> -26.2 | AH110: =-69.6-AG110-AF110 -> -25 | AI110: =-119-SUM(AF110:AH110) -> -49.4 | AJ110: =SUM(AF110:AI110) -> -119 | AK110: -10 | AL110: =-36-AK110 -> -26 | AM110: =-70-SUM(AK110:AL110) -> -34 | AN110: =-97-SUM(AK110:AM110) -> -27 | AO110: =SUM(AK110:AN110) -> -97 | AP110: -22 | AQ110: =-43-AP110 -> -21 | AR110: =-55-SUM(AP110:AQ110) -> -12 | AS110: =-117-SUM(AP110:AR110) -> -62 | AT110: =SUM(AP110:AS110) -> -117 | AU110: -20 | AV110: =-37-AU110 -> -17 | AW110: =-52-AV110-AU110 -> -15 | AX110: =+-92-SUM(AU110:AW110) -> -40 | AY110: =SUM(AU110:AX110) -> -92 | AZ110: -16 | BA110: =+-42-AZ110 -> -26 | BB110: =+-74-SUM(AZ110:BA110) -> -32 | BC110: =+-139-SUM(AZ110:BB110) -> -65 | BD110: =SUM(AZ110:BC110) -> -139 | BE110: -16 | BF110: =+-36-BE110 -> -20 | BG110: =+-67-SUM(BE110:BF110) -> -31 | BH110: =+-115-SUM(BE110:BG110) -> -48 | BI110: =SUM(BE110:BH110) -> -115 | BJ110: -23 | BK110: =-56-BJ110 -> -33 | BL110: =-77-SUM(BJ110:BK110) -> -21 | BM110: =-123-SUM(BJ110:BL110) -> -46 | BN110: =SUM(BJ110:BM110) -> -123 | BO110: -33 | BP110: =-BP252 -> -31.167262 | BQ110: =-BQ252 -> -30.843259 | BR110: =-BR252 -> -31.751626 | BS110: =SUM(BO110:BR110) -> -126.76215 | BT110: =-BT252 -> -32.928635 | BU110: =-BU252 -> -34.747299 | BV110: =-BV252 -> -34.425755 | BW110: =-BW252 -> -35.419064 | BX110: =SUM(BT110:BW110) -> -137.52075 | BY110: =-BY252 -> -137.39899 | BZ110: =-BZ252 -> -144.5592 | CA110: =-CA252 -> -151.33224 | CD110: =A110 -> Capital Expenditures | CE110: =B110 -> -145.735 | CF110: =C110 -> -125.496 | CG110: =D110 -> -143.129 | CH110: =E110 -> -149.626 | CI110: =F110 -> -136.688 | CJ110: =K110 -> -149.571 | CK110: =P110 -> -246.263 | CL110: =U110 -> -131.331 | CM110: =Z110 -> -92.29 | CN110: =AE110 -> -115.443 | CO110: =AJ110 -> -119 | CP110: =AO110 -> -97 | CQ110: =AT110 -> -117 | CR110: =AY110 -> -92 | CS110: =BD110 -> -139 | CT110: =BI110 -> -115 | CU110: =BN110 -> -123 | CV110: =BS110 -> -126.76215 | CW110: =BX110 -> -137.52075 | CX110: =BY110 -> -137.39899 | CY110: =BZ110 -> -144.5592 | CZ110: =CA110 -> -151.33224
A111: Acquisitions, Including Contingent Payments, Net of Cash Acquired | B111: -333.234 | C111: -19.31 | D111: -3.678 | E111: -306.232 | F111: -461.842 | G111: 0 | H111: =-0.893-G111 -> -0.893 | I111: =-9.784-H111-G111 -> -8.891 | J111: =-13.48-I111-H111-G111 -> -3.696 | K111: =SUM(G111:J111) -> -13.48 | L111: 0 | M111: =-40.07-L111 -> -40.07 | N111: =-84.251-M111-L111 -> -44.181 | O111: =-86.707-N111-M111-L111 -> -2.456 | P111: =SUM(L111:O111) -> -86.707 | Q111: -11.876 | R111: =-34.666-Q111 -> -22.79 | S111: =-39.461-R111-Q111 -> -4.795 | T111: =-48.261-S111-R111-Q111 -> -8.8 | U111: =SUM(Q111:T111) -> -48.261 | V111: 0 | W111: =0-V111 -> 0 | X111: =0-W111-V111 -> 0 | Y111: =0-X111-W111-V111 -> 0 | Z111: =SUM(V111:Y111) -> 0 | AA111: 0 | AB111: =-5-AA111 -> -5 | AC111: =-325-AB111-AA111 -> -320 | AD111: =-364.396-AC111-AB111-AA111 -> -39.396 | AE111: =SUM(AA111:AD111) -> -364.396 | AF111: -126.2 | AG111: =-126.1-AF111 -> 0.1 | AH111: =-198.9-AG111-AF111 -> -72.8 | AI111: =-200-SUM(AF111:AH111) -> -1.1 | AJ111: =SUM(AF111:AI111) -> -200 | AK111: -16 | AL111: =-148-AK111 -> -132 | AM111: =-156-SUM(AK111:AL111) -> -8 | AN111: =-177-SUM(AK111:AM111) -> -21 | AO111: =SUM(AK111:AN111) -> -177 | AP111: 0 | AQ111: =0-AP111 -> 0 | AR111: =0-SUM(AP111:AQ111) -> 0 | AS111: =-47-SUM(AP111:AR111) -> -47 | AT111: =SUM(AP111:AS111) -> -47 | AU111: -15 | AV111: =-16-AU111 -> -1 | AW111: =-65-AV111-AU111 -> -49 | AX111: =+-71-SUM(AU111:AW111) -> -6 | AY111: =SUM(AU111:AX111) -> -71 | AZ111: -2 | BA111: =+-2-AZ111 -> 0 | BB111: =+-2393-SUM(AZ111:BA111) -> -2391 | BC111: =+-2396-SUM(AZ111:BB111) -> -3 | BD111: =SUM(AZ111:BC111) -> -2396 | BE111: -7 | BF111: =+-52-BE111 -> -45 | BG111: =+-145-SUM(BE111:BF111) -> -93 | BH111: =+-177-SUM(BE111:BG111) -> -32 | BI111: =SUM(BE111:BH111) -> -177 | BJ111: -1 | BK111: =-70-BJ111 -> -69 | BL111: =-80-SUM(BJ111:BK111) -> -10 | BM111: =-83-SUM(BJ111:BL111) -> -3 | BN111: =SUM(BJ111:BM111) -> -83 | BO111: -57 | BP111: 0 | BQ111: 0 | BR111: 0 | BS111: =SUM(BO111:BR111) -> -57 | BT111: 0 | BU111: 0 | BV111: 0 | BW111: 0 | BX111: =SUM(BT111:BW111) -> 0 | BY111: 0 | BZ111: 0 | CA111: 0 | CD111: =A111 -> Acquisitions, Including Contingent Payments, Net of Cash Acquired | CE111: =B111 -> -333.234 | CF111: =C111 -> -19.31 | CG111: =D111 -> -3.678 | CH111: =E111 -> -306.232 | CI111: =F111 -> -461.842 | CJ111: =K111 -> -13.48 | CK111: =P111 -> -86.707 | CL111: =U111 -> -48.261 | CM111: =Z111 -> 0 | CN111: =AE111 -> -364.396 | CO111: =AJ111 -> -200 | CP111: =AO111 -> -177 | CQ111: =AT111 -> -47 | CR111: =AY111 -> -71 | CS111: =BD111 -> -2396 | CT111: =BI111 -> -177 | CU111: =BN111 -> -83 | CV111: =BS111 -> -57 | CW111: =BX111 -> 0 | CX111: =BY111 -> 0 | CY111: =BZ111 -> 0 | CZ111: =CA111 -> 0
A112: Proceeds from Dispositions | B112: 17.876 | C112: 24.304 | D112: 502.665 | E112: 46.904 | F112: 131.335 | G112: 12.257 | H112: =12.286-G112 -> 0.029 | I112: =12.286-H112-G112 -> 0 | J112: =12.381-I112-H112-G112 -> 0.095 | K112: =SUM(G112:J112) -> 12.381 | L112: 55.08 | M112: =55.204-L112 -> 0.124 | N112: =60.464-M112-L112 -> 5.26 | O112: =62.261-N112-M112-L112 -> 1.797 | P112: =SUM(L112:O112) -> 62.261 | Q112: 0.026 | R112: =0.165-Q112 -> 0.139 | S112: =0.281-R112-Q112 -> 0.116 | T112: =0.44-S112-R112-Q112 -> 0.159 | U112: =SUM(Q112:T112) -> 0.44 | V112: 0.031 | W112: =9.731+0.06-V112 -> 9.76 | X112: =9.731+0.088-W112-V112 -> 0.028 | Y112: =15.196-X112-W112-V112 -> 5.377 | Z112: =SUM(V112:Y112) -> 15.196 | AA112: 5.1 | AB112: =5.3-AA112 -> 0.2 | AC112: =30.6-AB112-AA112 -> 25.3 | AD112: =30.685-AC112-AB112-AA112 -> 0.085 | AE112: =SUM(AA112:AD112) -> 30.685 | AF112: 0 | AG112: =19.9-AF112 -> 19.9 | AH112: =21.4-AG112-AF112 -> 1.5 | AI112: =238-SUM(AF112:AH112) -> 216.6 | AJ112: =SUM(AF112:AI112) -> 238 | AK112: 0 | AL112: =0-AK112 -> 0 | AM112: =0-SUM(AK112:AL112) -> 0 | AN112: =0-SUM(AK112:AM112) -> 0 | AO112: =SUM(AK112:AN112) -> 0 | AP112: 0 | AQ112: =0-AP112 -> 0 | AR112: =52-SUM(AP112:AQ112) -> 52 | AS112: =51-SUM(AP112:AR112) -> -1 | AT112: =SUM(AP112:AS112) -> 51 | AU112: 0 | AV112: 0 | AW112: =83-AV112-AU112 -> 83 | AX112: =83-SUM(AU112:AW112) -> 0 | AY112: =SUM(AU112:AX112) -> 83 | AZ112: 0 | BA112: =14-AZ112 -> 14 | BB112: =14-SUM(AZ112:BA112) -> 0 | BC112: =14-SUM(AZ112:BB112) -> 0 | BD112: =SUM(AZ112:BC112) -> 14 | BE112: 0 | BF112: 0 | BG112: =1071-SUM(BE112:BF112) -> 1071 | BH112: =1498-SUM(BE112:BG112) -> 427 | BI112: =SUM(BE112:BH112) -> 1498 | BJ112: 2 | BK112: =2-BJ112 -> 0 | BL112: =2-SUM(BJ112:BK112) -> 0 | BM112: =2-SUM(BJ112:BL112) -> 0 | BN112: =SUM(BJ112:BM112) -> 2 | BO112: 0 | BP112: 0 | BQ112: 0 | BR112: 0 | BS112: =SUM(BO112:BR112) -> 0 | BT112: 0 | BU112: 0 | BV112: 0 | BW112: 0 | BX112: =SUM(BT112:BW112) -> 0 | BY112: 0 | BZ112: 0 | CA112: 0 | CD112: =A112 -> Proceeds from Dispositions | CE112: =B112 -> 17.876 | CF112: =C112 -> 24.304 | CG112: =D112 -> 502.665 | CH112: =E112 -> 46.904 | CI112: =F112 -> 131.335 | CJ112: =K112 -> 12.381 | CK112: =P112 -> 62.261 | CL112: =U112 -> 0.44 | CM112: =Z112 -> 15.196 | CN112: =AE112 -> 30.685 | CO112: =AJ112 -> 238 | CP112: =AO112 -> 0 | CQ112: =AT112 -> 51 | CR112: =AY112 -> 83 | CS112: =BD112 -> 14 | CT112: =BI112 -> 1498 | CU112: =BN112 -> 2 | CV112: =BS112 -> 0 | CW112: =BX112 -> 0 | CX112: =BY112 -> 0 | CY112: =BZ112 -> 0 | CZ112: =CA112 -> 0
A113: Changes in Short-Term Investments | B113: 0 | C113: 3.299 | D113: 0 | E113: 0 | F113: 0 | G113: 0 | H113: =0-G113 -> 0 | I113: =0-H113-G113 -> 0 | J113: =0-I113-H113-G113 -> 0 | K113: =SUM(G113:J113) -> 0 | L113: 0 | M113: =0-L113 -> 0 | N113: =0-M113-L113 -> 0 | O113: =0-N113-M113-L113 -> 0 | P113: =SUM(L113:O113) -> 0 | Q113: 0 | R113: =0-Q113 -> 0 | S113: =0-R113-Q113 -> 0 | T113: =0-S113-R113-Q113 -> 0 | U113: =SUM(Q113:T113) -> 0 | V113: 0 | W113: =0-V113 -> 0 | X113: =0-W113-V113 -> 0 | Y113: =-24.602-X113-W113-V113:V113 -> -24.602 | Z113: =SUM(V113:Y113) -> -24.602 | AA113: -0.5 | AB113: =-2.2-AA113 -> -1.7 | AC113: =-8.2-AB113-AA113 -> -6 | AD113: =2.446-AC113-AB113-AA113 -> 10.646 | AE113: =SUM(AA113:AD113) -> 2.446 | AF113: -6.3 | AG113: =-2.6-AF113 -> 3.7 | AH113: =-14-AG113-AF113 -> -11.4 | AI113: =-7-SUM(AF113:AH113) -> 7 | AJ113: =SUM(AF113:AI113) -> -7 | AK113: 5 | AL113: =26-AK113 -> 21 | AM113: =27-SUM(AK113:AL113) -> 1 | AN113: =27-SUM(AK113:AM113) -> 0 | AO113: =SUM(AK113:AN113) -> 27 | AP113: 0 | AQ113: =0-AP113 -> 0 | AR113: =-15-SUM(AP113:AQ113) -> -15 | AS113: =-17-SUM(AP113:AR113) -> -2 | AT113: =SUM(AP113:AS113) -> -17 | AU113: 0 | AV113: =1-AU113 -> 1 | AW113: =-1-AV113-AU113 -> -2 | AX113: =15-SUM(AU113:AW113) -> 16 | AY113: =SUM(AU113:AX113) -> 15 | AZ113: -1 | BA113: =+-7-AZ113 -> -6 | BB113: =+-3-SUM(AZ113:BA113) -> 4 | BC113: =+-4-SUM(AZ113:BB113) -> -1 | BD113: =SUM(AZ113:BC113) -> -4 | BE113: -1 | BF113: =0-BE113 -> 1 | BG113: =+-1-SUM(BE113:BF113) -> -1 | BH113: =-1-SUM(BE113:BG113) -> 0 | BI113: =SUM(BE113:BH113) -> -1 | BJ113: 0 | BK113: 0 | BL113: 0 | BM113: =-5-SUM(BJ113:BL113) -> -5 | BN113: =SUM(BJ113:BM113) -> -5 | BO113: 3 | BP113: =BO143-BP143 -> 0 | BQ113: =BP143-BQ143 -> 0 | BR113: =BQ143-BR143 -> 0 | BS113: =SUM(BO113:BR113) -> 3 | BT113: =BS143-BT143 -> 0 | BU113: =BT143-BU143 -> 0 | BV113: =BU143-BV143 -> 0 | BW113: =BV143-BW143 -> 0 | BX113: =SUM(BT113:BW113) -> 0 | BY113: =BX143-BY143 -> 0 | BZ113: =BY143-BZ143 -> 0 | CA113: =BZ143-CA143 -> 0 | CD113: =A113 -> Changes in Short-Term Investments | CE113: =B113 -> 0 | CF113: =C113 -> 3.299 | CG113: =D113 -> 0 | CH113: =E113 -> 0 | CI113: =F113 -> 0 | CJ113: =K113 -> 0 | CK113: =P113 -> 0 | CL113: =U113 -> 0 | CM113: =Z113 -> -24.602 | CN113: =AE113 -> 2.446 | CO113: =AJ113 -> -7 | CP113: =AO113 -> 27 | CQ113: =AT113 -> -17 | CR113: =AY113 -> 15 | CS113: =BD113 -> -4 | CT113: =BI113 -> -1 | CU113: =BN113 -> -5 | CV113: =BS113 -> 3 | CW113: =BX113 -> 0 | CX113: =BY113 -> 0 | CY113: =BZ113 -> 0 | CZ113: =CA113 -> 0
B114: ______ | C114: ______ | D114: ______ | E114: ______ | F114: ______ | G114: ______ | H114: ______ | I114: ______ | J114: ______ | K114: ______ | L114: ______ | M114: ______ | N114: ______ | O114: ______ | P114: ______ | Q114: ______ | R114: ______ | S114: ______ | T114: ______ | U114: ______ | V114: ______ | W114: ______ | X114: ______ | Y114: ______ | Z114: ______ | AA114: ______ | AB114: ______ | AC114: ______ | AD114: ______ | AE114: ______ | AF114: ______ | AG114: ______ | AH114: ______ | AI114: ______ | AJ114: ______ | AK114: ______ | AL114: ______ | AM114: ______ | AN114: ______ | AO114: ______ | AP114: ______ | AQ114: ______ | AR114: ______ | AS114: ______ | AT114: ______ | AU114: ______ | AV114: ______ | AW114: ______ | AX114: ______ | AY114: ______ | AZ114: ______ | BA114: ______ | BB114: ______ | BC114: ______ | BD114: ______ | BE114: ______ | BF114: ______ | BG114: ______ | BH114: ______ | BI114: ______ | BJ114: ______ | BK114: ______ | BL114: ______ | BM114: ______ | BN114: ______ | BO114: ______ | BP114: ______ | BQ114: ______ | BR114: ______ | BS114: ______ | BT114: ______ | BU114: ______ | BV114: ______ | BW114: ______ | BX114: ______ | BY114: ______ | BZ114: ______ | CA114: ______ | CE114: ______ | CF114: ______ | CG114: ______ | CH114: ______ | CI114: ______ | CJ114: ______ | CK114: ______ | CL114: ______ | CM114: ______ | CN114: ______ | CO114: ______ | CP114: ______ | CQ114: ______ | CR114: ______ | CS114: ______ | CT114: ______ | CU114: ______ | CV114: ______ | CW114: ______ | CX114: ______ | CY114: ______ | CZ114: ______
A115: Cash provided by Investing Activities | B115: =SUM(B109:B113) -> -755.631 | C115: =SUM(C109:C113) -> -366.52 | D115: =SUM(D109:D113) -> 137.809 | E115: =SUM(E109:E113) -> -646.714 | F115: =SUM(F109:F113) -> -724.99 | G115: =SUM(G109:G113) -> -63.914 | H115: =SUM(H109:H113) -> -92.646 | I115: =SUM(I109:I113) -> -102.528 | ... CA115: =SUM(CA109:CA113) -> -151.33224 | CD115: =A115 -> Cash provided by Investing Activities | CE115: =SUM(CE109:CE113) -> -755.631 | CF115: =SUM(CF109:CF113) -> -366.52 | CG115: =SUM(CG109:CG113) -> 137.809 | CH115: =SUM(CH109:CH113) -> -646.714 | CI115: =SUM(CI109:CI113) -> -724.99 | CJ115: =SUM(CJ109:CJ113) -> -427.48 | CK115: =SUM(CK109:CK113) -> -569.693 | CL115: =SUM(CL109:CL113) -> -433.258 | ... CZ115: =SUM(CZ109:CZ113) -> -151.33224
A117: Cash From Financing Activities | CD117: =A117 -> Cash From Financing Activities
A118: Payment/Additions to Short-Term Debt and Long-Term debt – net | B118: =12.137-0.741 -> 11.396 | C118: -478.501 | D118: -552.719 | E118: -22.718 | F118: -12.677 | G118: -0.075 | H118: =678.298-G118 -> 678.373 | I118: =232.112-H118-G118 -> -446.186 | J118: =-0.605-I118-H118-G118 -> -232.717 | K118: =SUM(G118:J118) -> -0.605 | L118: 604.777 | M118: =991.812-L118 -> 387.035 | N118: =1328.603-M118-L118 -> 336.791 | O118: =-2.345-N118-M118-L118+1188.803 -> -142.145 | P118: =SUM(L118:O118) -> 1186.458 | Q118: 396.2 | R118: =526.2-Q118 -> 130 | S118: =307.1-R118-Q118 -> -219.1 | T118: =70-S118-R118-Q118 -> -237.1 | U118: =SUM(Q118:T118) -> 70 | V118: 89.9 | W118: =19.6-V118 -> -70.3 | X118: =-70-W118-V118 -> -89.6 | Y118: =-70-X118-W118-V118 -> 0 | Z118: =SUM(V118:Y118) -> -70 | AA118: 0 | AB118: 0 | AC118: 0 | AD118: 0 | AE118: =SUM(AA118:AD118) -> 0 | AF118: 0 | AG118: 0 | AH118: 0 | AI118: 0 | AJ118: =SUM(AF118:AI118) -> 0 | AK118: 0 | AL118: =0-AK118 -> 0 | AM118: =0-SUM(AK118:AL118) -> 0 | AN118: =457-400-AK118-AL118-AM118 -> 57 | AO118: =SUM(AK118:AN118) -> 57 | AP118: -457 | AQ118: =-457-AP118 -> 0 | AR118: =-457-SUM(AP118:AQ118) -> 0 | AS118: =-457-AP118-AQ118-AR118 -> 0 | AT118: =SUM(AP118:AS118) -> -457 | AU118: 0 | AV118: 0 | AW118: =0-AV118-AU118 -> 0 | AX118: 0 | AY118: =SUM(AU118:AX118) -> 0 | AZ118: 365 | BA118: =690-AZ118 -> 325 | BB118: =2674-SUM(AZ118:BA118) -> 1984 | BC118: =143+2674-SUM(AZ118:BB118) -> 143 | BD118: =SUM(AZ118:BC118) -> 2817 | BE118: 329 | BF118: =166-BE118 -> -163 | BG118: =+-143+493-SUM(BE118:BF118) -> 184 | BH118: =+-143+493-421-SUM(BE118:BG118) -> -421 | BI118: =SUM(BE118:BH118) -> -71 | BJ118: 0 | BK118: 0 | BL118: 0 | BM118: 0 | BN118: =SUM(BJ118:BM118) -> 0 | BO118: 0 | BP118: 0 | BQ118: 0 | BR118: 0 | BS118: =SUM(BO118:BR118) -> 0 | BT118: 0 | BU118: 0 | BV118: 0 | BW118: 0 | BX118: =SUM(BT118:BW118) -> 0 | BY118: 0 | BZ118: 0 | CA118: 0 | CD118: =A118 -> Payment/Additions to Short-Term Debt and Long-Term debt – net | CE118: =B118 -> 11.396 | CF118: =C118 -> -478.501 | CG118: =D118 -> -552.719 | CH118: =E118 -> -22.718 | CI118: =F118 -> -12.677 | CJ118: =K118 -> -0.605 | CK118: =P118 -> 1186.458 | CL118: =U118 -> 70 | CM118: =Z118 -> -70 | CN118: =AE118 -> 0 | CO118: =AJ118 -> 0 | CP118: =AO118 -> 57 | CQ118: =AT118 -> -457 | CR118: =AY118 -> 0 | CS118: =BD118 -> 2817 | CT118: =BI118 -> -71 | CU118: =BN118 -> 0 | CV118: =BS118 -> 0 | CW118: =BX118 -> 0 | CX118: =BY118 -> 0 | CY118: =BZ118 -> 0 | CZ118: =CA118 -> 0
...

Sheet Op Metrics
A6: S&P Global, Inc.
A7: Operating Metrics ($M)
CB8: 17-22E
A9: Fiscal Year Ending December 31 | B9: =MHFI!B9 -> 2001 | C9: =MHFI!C9 -> 2002 | D9: =MHFI!D9 -> 2003 | E9: =MHFI!E9 -> 2004 | F9: =MHFI!F9 -> 2005 | G9: =MHFI!G9 -> 1Q06 | H9: =MHFI!H9 -> 2Q06 | I9: =MHFI!I9 -> 3Q06 | ... CA9: =MHFI!CA9 -> 2022E | CB9: CAGR | CF9: =+A9 -> Fiscal Year Ending December 31 | CG9: =+B9 -> 2001 | CH9: =+C9 -> 2002 | CI9: =+D9 -> 2003 | CJ9: =+E9 -> 2004 | CK9: =+F9 -> 2005 | CL9: =+K9 -> 2006 | CM9: =+P9 -> 2007 | CN9: =+U9 -> 2008 | CO9: =+Z9 -> 2009 | CP9: =+AE9 -> 2010 | CQ9: =+AJ9 -> 2011 | CR9: =+AO9 -> 2012 | CS9: =+AT9 -> 2013 | CT9: =+AY9 -> 2014 | CU9: =+BD9 -> 2015 | CV9: =+BI9 -> 2016 | CW9: =+BN9 -> 2017 | CX9: =+BS9 -> 2018E | CY9: =+BX9 -> 2019E | CZ9: =+BY9 -> 2020E | DA9: =+BZ9 -> 2021E | DB9: =+CA9 -> 2022E
A10: Revenue | CF10: =A10 -> Revenue
A12: S&P Ratings Services | B12: 1398 | C12: 1555 | D12: 1768 | E12: 2055 | F12: 2401 | G12: -- | H12: -- | I12: -- | J12: -- | K12: 1950 | L12: -- | M12: -- | N12: -- | O12: -- | P12: 2138 | Q12: -- | R12: -- | S12: -- | T12: -- | U12: 1583 | V12: 342.1 | W12: 403.7 | X12: 375.6 | Y12: 415.9 | Z12: 1537.3 | AA12: 401 | AB12: 405 | AC12: 417 | AD12: 472 | AE12: =SUM(AA12:AD12) -> 1695 | AF12: 443 | AG12: 480 | AH12: 410 | AI12: 434 | AJ12: =SUM(AF12:AI12) -> 1767 | AK12: 466 | AL12: 483 | AM12: 502 | AN12: 584 | AO12: =SUM(AK12:AN12) -> 2035 | AP12: 561 | AQ12: 599 | AR12: 540 | AS12: 574 | AT12: =SUM(AP12:AS12) -> 2274 | AU12: 569 | AV12: 664 | AW12: 604 | AX12: 618 | AY12: =SUM(AU12:AX12) -> 2455 | AZ12: 606 | BA12: 658 | BB12: 587 | BC12: =2428-SUM(AZ12:BB12) -> 577 | BD12: =SUM(AZ12:BC12) -> 2428 | BE12: 552 | BF12: 682 | BG12: 642 | BH12: 658 | BI12: =+SUM(BE12:BH12) -> 2534 | BJ12: 714 | BK12: 747 | BL12: 739 | BM12: 789 | BN12: =+SUM(BJ12:BM12) -> 2989 | BO12: 748 | BP12: =BP172 -> 808.39291 | BQ12: =BQ172 -> 782.73288 | BR12: =BR172 -> 802.24753 | BS12: =+SUM(BO12:BR12) -> 3141.3733 | BT12: =BT172 -> 781.50287 | BU12: =BU172 -> 846.21615 | BV12: =BV172 -> 818.56092 | BW12: =BW172 -> 838.67885 | BX12: =+SUM(BT12:BW12) -> 3284.9588 | BY12: =BY172 -> 3418.6628 | BZ12: =BZ172 -> 3560.0614 | CA12: =CA172 -> 3694.6923 | CB12: =(CA12/BN12)^(1/5)-1 -> 0.04330304 | CF12: =+A12 -> S&P Ratings Services | CG12: =+B12 -> 1398 | CH12: =+C12 -> 1555 | CI12: =+D12 -> 1768 | CJ12: =+E12 -> 2055 | CK12: =+F12 -> 2401 | CL12: =+K12 -> 1950 | CM12: =+P12 -> 2138 | CN12: =+U12 -> 1583 | CO12: =+Z12 -> 1537.3 | CP12: =+AE12 -> 1695 | CQ12: =+AJ12 -> 1767 | CR12: =+AO12 -> 2035 | CS12: =+AT12 -> 2274 | CT12: =+AY12 -> 2455 | CU12: =+BD12 -> 2428 | CV12: =+BI12 -> 2534 | CW12: =+BN12 -> 2989 | CX12: =+BS12 -> 3141.3733 | CY12: =+BX12 -> 3284.9588 | CZ12: =+BY12 -> 3418.6628 | DA12: =+BZ12 -> 3560.0614 | DB12: =+CA12 -> 3694.6923
A13: y/y change | K13: =K12/F12-1 -> -0.1878384 | P13: =P12/K12-1 -> 0.096410256 | U13: =U12/P12-1 -> -0.2595884 | Z13: =Z12/U12-1 -> -0.028869236 | AA13: =AA12/V12-1 -> 0.17217188 | AB13: =AB12/W12-1 -> 0.003220213 | AC13: =AC12/X12-1 -> 0.11022364 | AD13: =AD12/Y12-1 -> 0.13488819 | AE13: =AE12/Z12-1 -> 0.10258245 | AF13: =AF12/AA12-1 -> 0.10473815 | AG13: =AG12/AB12-1 -> 0.18518519 | ... BX13: =BX12/BS12-1 -> 0.045707868 | BY13: =BY12/BX12-1 -> 0.040701875 | BZ13: =BZ12/BY12-1 -> 0.041360798 | CA13: =CA12/BZ12-1 -> 0.037817027 | CF13: =+A13 -> y/y change | CL13: =+K13 -> -0.1878384 | CM13: =+P13 -> 0.096410256 | CN13: =+U13 -> -0.2595884 | CO13: =+Z13 -> -0.028869236 | CP13: =+AE13 -> 0.10258245 | CQ13: =+AJ13 -> 0.042477876 | CR13: =+AO13 -> 0.1516695 | CS13: =+AT13 -> 0.11744472 | CT13: =+AY13 -> 0.079595427 | CU13: =+BD13 -> -0.010997963 | CV13: =+BI13 -> 0.043657331 | CW13: =+BN13 -> 0.17955801 | CX13: =+BS13 -> 0.050978025 | CY13: =+BX13 -> 0.045707868 | CZ13: =+BY13 -> 0.040701875 | DA13: =+BZ13 -> 0.041360798 | DB13: =+CA13 -> 0.037817027
A14: S&P Dow Jones Indices | G14: -- | H14: -- | I14: -- | J14: -- | K14: -- | L14: -- | M14: -- | N14: -- | O14: -- | P14: -- | Q14: -- | R14: -- | S14: -- | T14: -- | U14: -- | V14: -- | W14: -- | X14: -- | Y14: -- | Z14: -- | AA14: 63 | AB14: 70 | AC14: 67 | AD14: 73 | AE14: =SUM(AA14:AD14) -> 273 | AF14: 76 | AG14: 80 | AH14: 87 | AI14: 80 | AJ14: =SUM(AF14:AI14) -> 323 | AK14: 79 | AL14: 89 | AM14: 109 | AN14: 110 | AO14: =SUM(AK14:AN14) -> 387 | AP14: 115 | AQ14: 123 | AR14: 124 | AS14: 130 | AT14: =SUM(AP14:AS14) -> 492 | AU14: 137 | AV14: 133 | AW14: 143 | AX14: 140 | AY14: =AY312 -> 553 | AZ14: 143 | BA14: 148 | BB14: 156 | BC14: =597-SUM(AZ14:BB14) -> 150 | BD14: =SUM(AZ14:BC14) -> 597 | BE14: 151 | BF14: 153 | BG14: 164 | BH14: 171 | BI14: =+SUM(BE14:BH14) -> 639 | BJ14: 171 | BK14: 184 | BL14: 187 | BM14: 191 | BN14: =+SUM(BJ14:BM14) -> 733 | BO14: 214 | BP14: =BP312 -> 209.75609 | BQ14: =BQ312 -> 210.0899 | BR14: =BR312 -> 215.50472 | BS14: =+SUM(BO14:BR14) -> 849.35071 | BT14: =BT312 -> 220.90981 | BU14: =BU312 -> 229.44725 | BV14: =BV312 -> 232.20421 | BW14: =BW312 -> 237.39683 | BX14: =+SUM(BT14:BW14) -> 919.9581 | BY14: =BY312 -> 991.54272 | BZ14: =BZ312 -> 1068.4572 | CA14: =CA312 -> 1144.7879 | CB14: =(CA14/BN14)^(1/5)-1 -> 0.093261888 | CF14: =+A14 -> S&P Dow Jones Indices | CP14: =+AE14 -> 273 | CQ14: =+AJ14 -> 323 | CR14: =+AO14 -> 387 | CS14: =+AT14 -> 492 | CT14: =+AY14 -> 553 | CU14: =+BD14 -> 597 | CV14: =+BI14 -> 639 | CW14: =+BN14 -> 733 | CX14: =+BS14 -> 849.35071 | CY14: =+BX14 -> 919.9581 | CZ14: =+BY14 -> 991.54272 | DA14: =+BZ14 -> 1068.4572 | DB14: =+CA14 -> 1144.7879
A15: y/y change | AF15: =AF14/AA14-1 -> 0.20634921 | AG15: =AG14/AB14-1 -> 0.14285714 | AH15: =AH14/AC14-1 -> 0.29850746 | AI15: =AI14/AD14-1 -> 0.095890411 | AJ15: =AJ14/AE14-1 -> 0.18315018 | AK15: =AK14/AF14-1 -> 0.039473684 | AL15: =AL14/AG14-1 -> 0.1125 | AM15: =AM14/AH14-1 -> 0.25287356 | ... BX15: =BX14/BS14-1 -> 0.083131015 | BY15: =BY14/BX14-1 -> 0.077812913 | BZ15: =BZ14/BY14-1 -> 0.07757048 | CA15: =CA14/BZ14-1 -> 0.071440115 | CF15: =+A15 -> y/y change | CQ15: =+AJ15 -> 0.18315018 | CR15: =+AO15 -> 0.19814241 | CS15: =+AT15 -> 0.27131783 | CT15: =+AY15 -> 0.12398374 | CU15: =+BD15 -> 0.079566004 | CV15: =+BI15 -> 0.070351759 | CW15: =+BN15 -> 0.14710485 | CX15: =+BS15 -> 0.15873221 | CY15: =+BX15 -> 0.083131015 | CZ15: =+BY15 -> 0.077812913 | DA15: =+BZ15 -> 0.07757048 | DB15: =+CA15 -> 0.071440115
A16: Market and Commodities Intelligence | AA16: =+AA18+AA21 -> 403 | AB16: =+AB18+AB21 -> 423 | AC16: =+AC18+AC21 -> 431 | AD16: =+AD18+AD21 -> 470 | AE16: =+SUM(AA16:AD16) -> 1727 | AF16: =+AF18+AF21 -> 455 | AG16: =+AG18+AG21 -> 475 | AH16: =+AH18+AH21 -> 490 | AI16: =+AI18+AI21 -> 507 | AJ16: =+SUM(AF16:AI16) -> 1927 | AK16: =+AK18+AK21 -> 507 | AL16: =+AL18+AL21 -> 517 | AM16: =+AM18+AM21 -> 523 | AN16: =+AN18+AN21 -> 550 | AO16: =+SUM(AK16:AN16) -> 2097 | AP16: =+AP18+AP21 -> 524 | AQ16: =+AQ18+AQ21 -> 546 | AR16: =+AR18+AR21 -> 506 | AS16: =+AS18+AS21 -> 521 | AT16: =+SUM(AP16:AS16) -> 2097 | AU16: =+AU18+AU21 -> 512 | AV16: =+AV18+AV21 -> 526 | AW16: =+AW18+AW21 -> 538 | AX16: =+AX18+AX21 -> 554 | AY16: =+SUM(AU16:AX16) -> 2130 | AZ16: =+AZ18+AZ21 -> 545 | BA16: =+BA18+BA21 -> 558 | BB16: =+BB18+BB21 -> 604 | BC16: =+BC18+BC21 -> 669 | BD16: =+SUM(AZ16:BC16) -> 2376 | BE16: =+BE18+BE21 -> 661 | BF16: =+BF18+BF21 -> 671 | BG16: =+BG18+BG21 -> 658 | BH16: 595 | BI16: =+SUM(BE16:BH16) -> 2585 | BJ16: 593 | BK16: 606 | BL16: 615 | BM16: 637 | BN16: =+SUM(BJ16:BM16) -> 2451 | BO16: =BO18+BO21 -> 633 | BP16: =+BP18+BP21 -> 650.23323 | BQ16: =+BQ18+BQ21 -> 658.50666 | BR16: =+BR18+BR21 -> 681.38598 | BS16: =+SUM(BO16:BR16) -> 2623.1259 | BT16: =+BT18+BT21 -> 672.01907 | BU16: =+BU18+BU21 -> 689.70155 | BV16: =+BV18+BV21 -> 698.52262 | BW16: =+BW18+BW21 -> 722.8775 | BX16: =+SUM(BT16:BW16) -> 2783.1207 | BY16: =+BY18+BY21 -> 2933.3203 | BZ16: =+BZ18+BZ21 -> 3091.8603 | CA16: =+CA18+CA21 -> 3237.3746 | CB16: =(CA16/BN16)^(1/5)-1 -> 0.057231095 | CF16: =+A16 -> Market and Commodities Intelligence | CP16: =+AE16 -> 1727 | CQ16: =+AJ16 -> 1927 | CR16: =+AO16 -> 2097 | CS16: =+AT16 -> 2097 | CT16: =+AY16 -> 2130 | CU16: =+BD16 -> 2376 | CV16: =+BI16 -> 2585 | CW16: =+BN16 -> 2451 | CX16: =+BS16 -> 2623.1259 | CY16: =+BX16 -> 2783.1207 | CZ16: =+BY16 -> 2933.3203 | DA16: =+BZ16 -> 3091.8603 | DB16: =+CA16 -> 3237.3746
A17: y/y change | AF17: =AF16/AA16-1 -> 0.12903226 | AG17: =AG16/AB16-1 -> 0.12293144 | AH17: =AH16/AC16-1 -> 0.13689095 | AI17: =AI16/AD16-1 -> 0.078723404 | AJ17: =AJ16/AE16-1 -> 0.11580776 | AK17: =AK16/AF16-1 -> 0.11428571 | AL17: =AL16/AG16-1 -> 0.088421053 | AM17: =AM16/AH16-1 -> 0.067346939 | ... BX17: =BX16/BS16-1 -> 0.060993976 | BY17: =BY16/BX16-1 -> 0.053968037 | BZ17: =BZ16/BY16-1 -> 0.054047978 | CA17: =CA16/BZ16-1 -> 0.047063652 | CF17: =+A17 -> y/y change | CV17: =+BI17 -> 0.087962963 | CW17: =+BN17 -> -0.051837524 | CX17: =+BS17 -> 0.070226792 | CY17: =+BX17 -> 0.060993976 | CZ17: =+BY17 -> 0.053968037 | DA17: =+BZ17 -> 0.054047978 | DB17: =+CA17 -> 0.047063652
A18: Market Intelligence | G18: -- | H18: -- | I18: -- | J18: -- | K18: -- | L18: -- | M18: -- | N18: -- | O18: -- | P18: -- | Q18: -- | R18: -- | S18: -- | T18: -- | U18: -- | V18: -- | W18: -- | X18: -- | Y18: -- | Z18: -- | AA18: 216 | AB18: 224 | AC18: 227 | AD18: 249 | AE18: =SUM(AA18:AD18) -> 916 | AF18: 248 | AG18: 253 | AH18: 262 | AI18: 268 | AJ18: =SUM(AF18:AI18) -> 1031 | AK18: 274 | AL18: 277 | AM18: 284 | AN18: 290 | AO18: =SUM(AK18:AN18) -> 1125 | AP18: 288 | AQ18: 287 | AR18: 293 | AS18: 301 | AT18: =SUM(AP18:AS18) -> 1169 | AU18: 301 | AV18: 307 | AW18: 311 | AX18: 318 | AY18: =SUM(AU18:AX18) -> 1237 | AZ18: 320 | BA18: 324 | BB18: 356 | BC18: =1405-SUM(AZ18:BB18) -> 405 | BD18: =SUM(AZ18:BC18) -> 1405 | BE18: 407 | BF18: 416 | BG18: 429 | BH18: 407 | BI18: =+SUM(BE18:BH18) -> 1659 | BJ18: 402 | BK18: 414 | BL18: 422 | BM18: 440 | BN18: =+SUM(BJ18:BM18) -> 1678 | BO18: 437 | BP18: =BP245 -> 448.63323 | BQ18: =BQ245 -> 455.85666 | BR18: =BR245 -> 474.53598 | BS18: =+SUM(BO18:BR18) -> 1816.0259 | BT18: =BT245 -> 468.17907 | BU18: =BU245 -> 480.03755 | BV18: =BV245 -> 487.76662 | BW18: =BW245 -> 507.7535 | BX18: =+SUM(BT18:BW18) -> 1943.7367 | BY18: =BY245 -> 2060.3609 | BZ18: =BZ245 -> 2183.9826 | CA18: =CA245 -> 2293.1817 | CB18: =(BY18/BD18)^(1/5)-1 -> 0.079576437 | CF18: =+A18 -> Market Intelligence | CP18: =+AE18 -> 916 | CQ18: =+AJ18 -> 1031 | CR18: =+AO18 -> 1125 | CS18: =+AT18 -> 1169 | CT18: =+AY18 -> 1237 | CU18: =+BD18 -> 1405 | CV18: =+BI18 -> 1659 | CW18: =+BN18 -> 1678 | CX18: =+BS18 -> 1816.0259 | CY18: =+BX18 -> 1943.7367 | CZ18: =+BY18 -> 2060.3609 | DA18: =+BZ18 -> 2183.9826 | DB18: =+CA18 -> 2293.1817
A19: y/y change | AF19: =AF18/AA18-1 -> 0.14814815 | AG19: =AG18/AB18-1 -> 0.12946429 | AH19: =AH18/AC18-1 -> 0.15418502 | AI19: =AI18/AD18-1 -> 0.076305221 | AJ19: =AJ18/AE18-1 -> 0.12554585 | AK19: =AK18/AF18-1 -> 0.10483871 | AL19: =AL18/AG18-1 -> 0.09486166 | AM19: =AM18/AH18-1 -> 0.083969466 | ... BX19: =BX18/BS18-1 -> 0.070324371 | BY19: =BY18/BX18-1 -> 0.06 | BZ19: =BZ18/BY18-1 -> 0.06 | CA19: =CA18/BZ18-1 -> 0.05 | CF19: =+A19 -> y/y change | CQ19: =+AJ19 -> 0.12554585 | CR19: =+AO19 -> 0.091173618 | CS19: =+AT19 -> 0.039111111 | CT19: =+AY19 -> 0.058169376 | CU19: =+BD19 -> 0.13581245 | CV19: =+BI19 -> 0.18078292 | CW19: =+BN19 -> 0.011452682 | CX19: =+BS19 -> 0.082256178 | CY19: =+BX19 -> 0.070324371 | CZ19: =+BY19 -> 0.06 | DA19: =+BZ19 -> 0.06 | DB19: =+CA19 -> 0.05
A20: S&P Market Intelligence / S&P Indices | G20: -- | H20: -- | I20: -- | J20: -- | K20: 824 | L20: -- | M20: -- | N20: -- | O20: -- | P20: 942 | Q20: -- | R20: -- | S20: -- | T20: -- | U20: 1113.5 | V20: 279.6 | W20: 282.3 | X20: 273.6 | Y20: 286.3 | Z20: 1121.8 | AA20: =SUM(AA18,AA14) -> 279 | AB20: =SUM(AB18,AB14) -> 294 | AC20: =SUM(AC18,AC14) -> 294 | AD20: =SUM(AD18,AD14) -> 322 | AE20: =SUM(AA20:AD20) -> 1189 | AF20: =SUM(AF18,AF14) -> 324 | AG20: =SUM(AG18,AG14) -> 333 | AH20: =SUM(AH18,AH14) -> 349 | AI20: =SUM(AI18,AI14) -> 348 | AJ20: =SUM(AF20:AI20) -> 1354 | AK20: =SUM(AK18,AK14) -> 353 | AL20: =SUM(AL18,AL14) -> 366 | AM20: =SUM(AM18,AM14) -> 393 | AN20: =SUM(AN18,AN14) -> 400 | AO20: =SUM(AK20:AN20) -> 1512 | AP20: =SUM(AP18,AP14) -> 403 | AQ20: =SUM(AQ18,AQ14) -> 410 | AR20: =SUM(AR18,AR14) -> 417 | AS20: =SUM(AS18,AS14) -> 431 | AT20: =SUM(AP20:AS20) -> 1661 | AU20: =SUM(AU18,AU14) -> 438 | AV20: =SUM(AV18,AV14) -> 440 | AW20: =SUM(AW18,AW14) -> 454 | AX20: =SUM(AX18,AX14) -> 458 | AY20: =SUM(AU20:AX20) -> 1790 | AZ20: =SUM(AZ18,AZ14) -> 463 | BA20: =SUM(BA18,BA14) -> 472 | BB20: =SUM(BB18,BB14) -> 512 | BC20: =SUM(BC18,BC14) -> 555 | BD20: =SUM(AZ20:BC20) -> 2002 | BE20: =SUM(BE18,BE14) -> 558 | BF20: =SUM(BF18,BF14) -> 569 | BG20: =SUM(BG18,BG14) -> 593 | BH20: =SUM(BH18,BH14) -> 578 | BI20: =+SUM(BE20:BH20) -> 2298 | BJ20: =SUM(BJ18,BJ14) -> 573 | BK20: =SUM(BK18,BK14) -> 598 | BL20: =SUM(BL18,BL14) -> 609 | BM20: =SUM(BM18,BM14) -> 631 | BN20: =+SUM(BJ20:BM20) -> 2411 | BO20: =SUM(BO18,BO14) -> 651 | BP20: =SUM(BP18,BP14) -> 658.38932 | BQ20: =SUM(BQ18,BQ14) -> 665.94656 | BR20: =SUM(BR18,BR14) -> 690.0407 | BS20: =+SUM(BO20:BR20) -> 2665.3766 | BT20: =SUM(BT18,BT14) -> 689.08888 | BU20: =SUM(BU18,BU14) -> 709.48481 | BV20: =SUM(BV18,BV14) -> 719.97083 | BW20: =SUM(BW18,BW14) -> 745.15033 | BX20: =+SUM(BT20:BW20) -> 2863.6948 | BY20: =SUM(BY18,BY14) -> 3051.9037 | BZ20: =SUM(BZ18,BZ14) -> 3252.4398 | CA20: =SUM(CA18,CA14) -> 3437.9696 | CB20: =(BY20/BD20)^(1/5)-1 -> 0.087981096 | CF20: =+A20 -> S&P Market Intelligence / S&P Indices | CL20: =+K20 -> 824 | CM20: =+P20 -> 942 | CN20: =+U20 -> 1113.5 | CO20: =+Z20 -> 1121.8 | CP20: =+AE20 -> 1189 | CQ20: =+AJ20 -> 1354 | CR20: =+AO20 -> 1512 | CS20: =+AT20 -> 1661 | CT20: =+AY20 -> 1790 | CU20: =+BD20 -> 2002 | CV20: =+BI20 -> 2298 | CW20: =+BN20 -> 2411 | CX20: =+BS20 -> 2665.3766 | CY20: =+BX20 -> 2863.6948 | CZ20: =+BY20 -> 3051.9037 | DA20: =+BZ20 -> 3252.4398 | DB20: =+CA20 -> 3437.9696
A21: S&P Platts | B21: 846 | C21: 810 | D21: 773 | E21: 800 | F21: 931 | G21: -- | H21: -- | I21: -- | J21: -- | K21: 985 | L21: -- | M21: -- | N21: -- | O21: -- | P21: 1020 | Q21: -- | R21: -- | S21: -- | T21: -- | U21: 1062 | V21: -- | W21: -- | X21: -- | Y21: -- | Z21: 873 | AA21: =SUM(AA22,AA23) -> 187 | AB21: =SUM(AB22,AB23) -> 199 | AC21: =SUM(AC22,AC23) -> 204 | AD21: =SUM(AD22,AD23) -> 221 | AE21: =SUM(AA21:AD21) -> 811 | AF21: =SUM(AF22,AF23) -> 207 | AG21: =SUM(AG22,AG23) -> 222 | AH21: =SUM(AH22,AH23) -> 228 | AI21: =SUM(AI22,AI23) -> 239 | AJ21: =SUM(AF21:AI21) -> 896 | AK21: =SUM(AK22,AK23) -> 233 | AL21: =SUM(AL22,AL23) -> 240 | AM21: =SUM(AM22,AM23) -> 239 | AN21: =SUM(AN22,AN23) -> 260 | AO21: =SUM(AK21:AN21) -> 972 | AP21: =SUM(AP22,AP23) -> 236 | AQ21: =SUM(AQ22,AQ23) -> 259 | AR21: =SUM(AR22,AR23) -> 213 | AS21: =SUM(AS22,AS23) -> 220 | AT21: =SUM(AP21:AS21) -> 928 | AU21: =AU367 -> 211 | AV21: =AV367 -> 219 | AW21: =AW367 -> 227 | AX21: =AX367 -> 236 | AY21: =AY367 -> 893 | AZ21: 225 | BA21: 234 | BB21: 248 | BC21: =971-SUM(AZ21:BB21) -> 264 | BD21: =SUM(AZ21:BC21) -> 971 | BE21: 254 | BF21: 255 | BG21: 229 | BH21: 188 | BI21: =+SUM(BE21:BH21) -> 926 | BJ21: 191 | BK21: 192 | BL21: 184 | BM21: 197 | BN21: =+SUM(BJ21:BM21) -> 764 | BO21: 196 | BP21: =BP367 -> 201.6 | BQ21: =BQ367 -> 202.65 | BR21: =BR367 -> 206.85 | BS21: =+SUM(BO21:BR21) -> 807.1 | BT21: =BT367 -> 203.84 | BU21: =BU367 -> 209.664 | BV21: =BV367 -> 210.756 | BW21: =BW367 -> 215.124 | BX21: =+SUM(BT21:BW21) -> 839.384 | BY21: =BY367 -> 872.95936 | BZ21: =BZ367 -> 907.87773 | CA21: =CA367 -> 944.19284 | CB21: =(BY21/BD21)^(1/5)-1 -> -0.021062514 | CF21: =+A21 -> S&P Platts | CG21: =+B21 -> 846 | CH21: =+C21 -> 810 | CI21: =+D21 -> 773 | CJ21: =+E21 -> 800 | CK21: =+F21 -> 931 | CL21: =+K21 -> 985 | CM21: =+P21 -> 1020 | CN21: =+U21 -> 1062 | CO21: =+Z21 -> 873 | CP21: =+AE21 -> 811 | CQ21: =+AJ21 -> 896 | CR21: =+AO21 -> 972 | CS21: =+AT21 -> 928 | CT21: =+AY21 -> 893 | CU21: =+BD21 -> 971 | CV21: =+BI21 -> 926 | CW21: =+BN21 -> 764 | CX21: =+BS21 -> 807.1 | CY21: =+BX21 -> 839.384 | CZ21: =+BY21 -> 872.95936 | DA21: =+BZ21 -> 907.87773 | DB21: =+CA21 -> 944.19284
A22: Commodities | G22: -- | H22: -- | I22: -- | J22: -- | K22: -- | L22: -- | M22: -- | N22: -- | O22: -- | P22: -- | Q22: -- | R22: -- | S22: -- | T22: -- | U22: -- | V22: -- | W22: -- | X22: -- | Y22: -- | Z22: -- | AA22: 83 | AB22: 85 | AC22: 85 | AD22: 91 | AE22: =SUM(AA22:AD22) -> 344 | AF22: 97 | AG22: 101 | AH22: 108 | AI22: 113 | AJ22: =SUM(AF22:AI22) -> 419 | AK22: 118 | AL22: 120 | AM22: 121 | AN22: 129 | AO22: =SUM(AK22:AN22) -> 488 | AP22: 130 | AQ22: 137 | AR22: 142 | AS22: =550-AR22-AQ22-AP22 -> 141 | AT22: =SUM(AP22:AS22) -> 550 | AU22: 148 | AV22: 149 | AW22: =+AW359 -> 152.65 | AX22: =+AX359 -> 151.575 | AY22: =SUM(AU22:AX22) -> 601.225 | AZ22: =+AZ359 -> 159.84 | BA22: =+BA359 -> 160.92 | BB22: =+BB359 -> 163.3355 | BC22: =+BC359 -> 167.85714 | BD22: =SUM(AZ22:BC22) -> 651.95264 | BE22: =+BE359 -> 174 | BF22: =+BF359 -> 172.1844 | BG22: =+BG359 -> 174 | BH22: =BH21 -> 188 | BI22: =SUM(BE22:BH22) -> 708.1844 | BJ22: =BJ21 -> 191 | BK22: =BK21 -> 192 | BL22: =BL21 -> 184 | BM22: =BM21 -> 197 | BN22: =BN21 -> 764 | BO22: =BO21 -> 196 | BP22: =+BP359 -> 0 | BQ22: =+BQ359 -> 0 | BR22: =+BR359 -> 0 | BS22: =SUM(BO22:BR22) -> 196 | BT22: =+BT359 -> 0 | BU22: =+BU359 -> 0 | BV22: =+BV359 -> 0 | BW22: =+BW359 -> 0 | BX22: =SUM(BT22:BW22) -> 0 | BY22: =+BY359 -> 0 | BZ22: =+BZ359 -> 0 | CA22: =+CA359 -> 0 | CF22: =+A22 -> Commodities | CP22: =+AE22 -> 344 | CQ22: =+AJ22 -> 419 | CR22: =+AO22 -> 488 | CS22: =+AT22 -> 550 | CT22: =+AY22 -> 601.225 | CU22: =+BD22 -> 651.95264 | CV22: =+BI22 -> 708.1844 | CW22: =+BN22 -> 764 | CX22: =+BS22 -> 196 | CY22: =+BX22 -> 0 | CZ22: =+BY22 -> 0 | DA22: =+BZ22 -> 0 | DB22: =+CA22 -> 0
A23: Commercial | G23: -- | H23: -- | I23: -- | J23: -- | K23: -- | L23: -- | M23: -- | N23: -- | O23: -- | P23: -- | Q23: -- | R23: -- | S23: -- | T23: -- | U23: -- | V23: -- | W23: -- | X23: -- | Y23: -- | Z23: -- | AA23: 104 | AB23: 114 | AC23: 119 | AD23: 130 | AE23: =SUM(AA23:AD23) -> 467 | AF23: 110 | AG23: 121 | AH23: 120 | AI23: 126 | AJ23: =SUM(AF23:AI23) -> 477 | AK23: 115 | AL23: 120 | AM23: 118 | AN23: 131 | AO23: =SUM(AK23:AN23) -> 484 | AP23: 106 | AQ23: 122 | AR23: =213-AR22 -> 71 | AS23: =220-AS22 -> 79 | AT23: =SUM(AP23:AS23) -> 378 | AU23: =103-42 -> 61 | AV23: =114-42 -> 72 | AW23: =+AW362 -> 74.35 | AX23: =+AX362 -> 84.425 | AY23: =SUM(AU23:AX23) -> 291.775 | AZ23: =+AZ362 -> 65.16 | BA23: =+BA362 -> 73.08 | BB23: =+BB362 -> 84.6645 | BC23: =+BC362 -> 96.142857 | BD23: =SUM(AZ23:BC23) -> 319.04736 | BE23: =+BE362 -> 80 | BF23: =+BF362 -> 82.8156 | BG23: =+BG362 -> 55 | CF23: =+A23 -> Commercial | CP23: =+AE23 -> 467 | CQ23: =+AJ23 -> 477 | CR23: =+AO23 -> 484 | CS23: =+AT23 -> 378 | CT23: =+AY23 -> 291.775 | CU23: =+BD23 -> 319.04736 | CV23: =+BI23 -> 0 | CW23: =+BN23 -> 0 | CX23: =+BS23 -> 0 | CY23: =+BX23 -> 0 | CZ23: =+BY23 -> 0 | DA23: =+BZ23 -> 0 | DB23: =+CA23 -> 0
A24: y/y chg | B24: -0.16 | C24: =C21/B21-1 -> -0.042553191 | D24: =D21/C21-1 -> -0.045679012 | E24: =E21/D21-1 -> 0.034928849 | F24: =F21/E21-1 -> 0.16375 | K24: =K21/F21-1 -> 0.058002148 | P24: =P21/K21-1 -> 0.035532995 | U24: =U21/P21-1 -> 0.041176471 | Z24: =Z21/U21-1 -> -0.1779661 | AE24: =AE21/Z21-1 -> -0.071019473 | AF24: =AF21/AA21-1 -> 0.10695187 | AG24: =AG21/AB21-1 -> 0.11557789 | AH24: =AH21/AC21-1 -> 0.11764706 | AI24: =AI21/AD21-1 -> 0.081447964 | AJ24: =AJ21/AE21-1 -> 0.10480888 | AK24: =AK21/AF21-1 -> 0.12560386 | AL24: =AL21/AG21-1 -> 0.081081081 | ... BX24: =BX21/BS21-1 -> 0.04 | BY24: =BY21/BX21-1 -> 0.04 | BZ24: =BZ21/BY21-1 -> 0.04 | CA24: =CA21/BZ21-1 -> 0.04 | CF24: =+A24 -> y/y chg | CG24: =+B24 -> -0.16 | CH24: =+C24 -> -0.042553191 | CI24: =+D24 -> -0.045679012 | CJ24: =+E24 -> 0.034928849 | CK24: =+F24 -> 0.16375 | CL24: =+K24 -> 0.058002148 | CM24: =+P24 -> 0.035532995 | CN24: =+U24 -> 0.041176471 | CO24: =+Z24 -> -0.1779661 | CP24: =+AE24 -> -0.071019473 | CQ24: =+AJ24 -> 0.10480888 | CR24: =+AO24 -> 0.084821429 | CS24: =+AT24 -> -0.04526749 | CT24: =+AY24 -> -0.037715517 | CU24: =+BD24 -> 0.087346025 | CV24: =+BI24 -> -0.046343975 | CW24: =+BN24 -> -0.174946 | CX24: =+BS24 -> 0.056413613 | CY24: =+BX24 -> 0.04 | CZ24: =+BY24 -> 0.04 | DA24: =+BZ24 -> 0.04 | DB24: =+CA24 -> 0.04
A25: Intersegment Elimination | B25: 0 | C25: 0 | D25: 0 | E25: 0 | F25: 0 | G25: -- | H25: -- | I25: -- | J25: -- | K25: -28 | L25: -- | M25: -- | N25: -- | O25: -- | P25: -34 | Q25: -- | R25: -- | S25: -- | T25: -- | U25: -42 | V25: -- | W25: -- | X25: -- | Y25: -- | Z25: -49 | AA25: -13 | AB25: -14 | AC25: -14 | AD25: -15 | AE25: =SUM(AA25:AD25) -> -56 | AF25: -15 | AG25: -15 | AH25: -16 | AI25: -17 | AJ25: =SUM(AF25:AI25) -> -63 | AK25: -17 | AL25: -17 | AM25: -18 | AN25: -18 | AO25: =SUM(AK25:AN25) -> -70 | AP25: -19 | AQ25: -18 | AR25: -18 | AS25: -19 | AT25: =SUM(AP25:AS25) -> -74 | AU25: -22 | AV25: -21 | AW25: -22 | AX25: -22 | AY25: =SUM(AU25:AX25) -> -87 | AZ25: -21 | BA25: -22 | BB25: -23 | BC25: -22 | BD25: =SUM(AZ25:BC25) -> -88 | BE25: -23 | BF25: -24 | BG25: -25 | BH25: -25 | BI25: =SUM(BE25:BH25) -> -97 | BJ25: -25 | BK25: -28 | BL25: -28 | BM25: -28 | BN25: =SUM(BJ25:BM25) -> -109 | BO25: -28 | BP25: =BO25 -> -28 | BQ25: =BP25 -> -28 | BR25: =BQ25 -> -28 | BS25: =SUM(BO25:BR25) -> -112 | BT25: =BR25 -> -28 | BU25: =BT25 -> -28 | BV25: =BU25 -> -28 | BW25: =BV25 -> -28 | BX25: =SUM(BT25:BW25) -> -112 | BY25: =BX25 -> -112 | BZ25: =BY25 -> -112 | CA25: =BZ25 -> -112 | CF25: =+A25 -> Intersegment Elimination | CL25: =+K25 -> -28 | CM25: =+P25 -> -34 | CN25: =+U25 -> -42 | CO25: =+Z25 -> -49 | CP25: =+AE25 -> -56 | CQ25: =+AJ25 -> -63 | CR25: =+AO25 -> -70 | CS25: =+AT25 -> -74 | CT25: =+AY25 -> -87 | CU25: =+BD25 -> -88 | CV25: =+BI25 -> -97 | CW25: =+BN25 -> -109 | CX25: =+BS25 -> -112 | CY25: =+BX25 -> -112 | CZ25: =+BY25 -> -112 | DA25: =+BZ25 -> -112 | DB25: =+CA25 -> -112
A27: Estimated FX Revenue Impact | BP27: =+BK30*BP28 -> 15.766134 | BQ27: =+BL30*BQ28 -> 9.0832789 | BR27: =+BM30*BR28 -> 6.179922 | BT27: =+BO30*BT28 -> 2.9453326
A28: % impact | BP28: 0.010448068 | BQ28: 0.006003489 | BR28: 0.0038891894 | BT28: 0.0018795996
A30: S&P Global | B30: =B12+B20+B21+B25 -> 2244 | C30: =C12+C20+C21+C25 -> 2365 | D30: =D12+D20+D21+D25 -> 2541 | E30: =E12+E20+E21+E25 -> 2855 | F30: =F12+F20+F21+F25 -> 3332 | G30: -- | H30: -- | I30: -- | J30: -- | K30: =K12+K20+K21+K25 -> 3731 | L30: -- | M30: -- | N30: -- | O30: -- | P30: =P12+P20+P21+P25 -> 4066 | Q30: -- | R30: -- | S30: -- | T30: -- | U30: =U12+U20+U21+U25 -> 3716.5 | V30: -- | W30: -- | X30: -- | Y30: -- | Z30: =Z12+Z20+Z21+Z25 -> 3483.1 | AA30: =AA12+AA18+AA14+AA21+AA25 -> 854 | AB30: =AB12+AB18+AB14+AB21+AB25 -> 884 | AC30: =AC12+AC18+AC14+AC21+AC25 -> 901 | AD30: =AD12+AD18+AD14+AD21+AD25 -> 1000 | AE30: =AE12+AE18+AE14+AE21+AE25 -> 3639 | AF30: =AF12+AF18+AF14+AF21+AF25 -> 959 | AG30: =AG12+AG18+AG14+AG21+AG25 -> 1020 | AH30: =AH12+AH18+AH14+AH21+AH25 -> 971 | ... BI30: =BI12+BI18+BI14+BI21+BI25 -> 5661 | BJ30: =+BJ12+BJ16+BJ14+BJ25 -> 1453 | BK30: =+BK12+BK16+BK14+BK25 -> 1509 | BL30: =+BL12+BL16+BL14+BL25 -> 1513 | BM30: =+BM12+BM16+BM14+BM25 -> 1589 | BN30: =+BN12+BN16+BN14+BN25 -> 6064 | BO30: =+BO12+BO16+BO14+BO25 -> 1567 | BP30: =+BP12+BP16+BP14+BP25 -> 1640.3822 | BQ30: =+BQ12+BQ16+BQ14+BQ25 -> 1623.3294 | ... CA30: =+CA12+CA16+CA14+CA25 -> 7964.8548 | CB30: =(CA30/BN30)^(1/5)-1 -> 0.056048183 | CF30: =+A30 -> S&P Global | CG30: =+B30 -> 2244 | CH30: =+C30 -> 2365 | CI30: =+D30 -> 2541 | CJ30: =+E30 -> 2855 | CK30: =+F30 -> 3332 | CL30: =+K30 -> 3731 | CM30: =+P30 -> 4066 | CN30: =+U30 -> 3716.5 | CO30: =+Z30 -> 3483.1 | CP30: =+AE30 -> 3639 | CQ30: =+AJ30 -> 3954 | CR30: =+AO30 -> 4449 | CS30: =+AT30 -> 4789 | CT30: =+AY30 -> 5051 | CU30: =+BD30 -> 5313 | CV30: =+BI30 -> 5661 | CW30: =+BN30 -> 6064 | CX30: =+BS30 -> 6501.8499 | CY30: =+BX30 -> 6876.0376 | CZ30: =+BY30 -> 7231.5258 | DA30: =+BZ30 -> 7608.3789 | DB30: =+CA30 -> 7964.8548
