Workbook
Name _1._Discounted_Cash_Flow_Valuation: "1. Discounted Cash Flow Valuation"
Name _2._Sum_of_the_Parts: "Sum of the Parts"
Name _3._Relative_Valuation: "Multiple Valuation"
Name AdditionalInstructions: IndexInformation!$B$42
Name Address: ImportantDisclosures!$A$2:$A$2
Name ANA: ModPubIndex!$A$7
Name Authors: ImportantDisclosures!$A$7
Name Authors: IndexInformation!$B$18
Name BRO: ModPubIndex!$A$1
Name CashFlowCapitalExpenditureCellular: 0
Name CashFlowCapitalExpenditureOther: 0
Name CashFlowCapitalExpenditurePaging: 0
Name CashFlowCapitalExpenditureTelephone: 0
Name CashFlowCapitalExpenditureWireless: 0
Name CashFlowDividendPaidPreferredStock: 0
Name CopyrightStamp: ImportantDisclosures!$A$27
Name Corinthian_Colleges: '[2]Print '!$B$2:$M$71
Name COU: ModPubIndex!$A$5
Name CQEnd: IndexInformation!$B$31
Name Currency: IndexInformation!$B$24
Name CurrentStockPrice: IndexInformation!$B$23
Name CurrQtrEPS: IndexInformation!$B$29
Name CurrYearEPS: IndexInformation!$B$11
Name CurrYearTotalRevenue: IndexInformation!$B$10
Name CurrYearTotalRevenueActual: IndexInformation!$B$32
Name CUSIP: IndexInformation!$B$20
Name CYEnd: IndexInformation!$B$30
Name Date: ImportantDisclosures!$A$8
Name Deleted: IndexInformation!$B$27
Name Description: IndexInformation!$B$7
Name Discipline: IndexInformation!$B$3
Name DISCIPLINE: ModPubIndex!$A$12
Name DisclosuresText: ImportantDisclosures!$A$22
Name Distribution: IndexInformation!$B$26
Name DistTable: ImportantDisclosures!#REF!
Name DistTablePreamble: ImportantDisclosures!#REF!
Name DOCDAT: ModPubIndex!$A$2
Name DOCTIME: ModPubIndex!$A$3
Name DocType: IndexInformation!$B$5
Name EMAIL_ALERT: ModPubIndex!$A$10
Name EmailAlert: IndexInformation!$B$28
Name EquityAdjustments: 0
Name EquityEmployeeStockOwnershipPlan: 0
Name EquityPaidInCapital: 0
Name EquityTreasuryStock: 0
Name FiveYearGrowthRate: IndexInformation!$B$16
Name FollowingYearEPS: IndexInformation!$B$15
Name FollowingYearTotalRevenue: IndexInformation!$B$14
Name FollowingYearTotalRevenueActual: IndexInformation!$B$34
Name HL: ModPubIndex!$A$8
Name IncomeEPSFullyDiluted: 0
Name IncomeEPSPrimary: 0
Name IncomeEPSRegular: 0
Name IND: ModPubIndex!$A$9
Name Industry: ImportantDisclosures!$A$12
Name IndustryId: IndexInformation!$B$40
Name IndustryRating: ImportantDisclosures!$A$13
Name KeepVersions: IndexInformation!$B$8
Name LanguageCode: IndexInformation!$B$38
Name LastCell: ImportantDisclosures!$A$22

Sheet ImportantDisclosures
A2: 1585 Broadway
A3: New York, NY 10036-8293
A4: United States
A5: Tel: +1 (1)212 761 4000
A7: Authors: Toni Kaplan, Priscilla Russo
A8: Date: 21 Feb 2018
A10: Ticker: VRSK.O
A11: Stock Rating: Equal-Weight
A12: Industry: Business & Education Services
A13: Industry View: In-Line
A14: Price as of 21 Feb 2018: 99.23
A15: Target Price: 107
... A120: Equal-weight and Not-Rated to hold and Underweight to sell recommendations, respectively.
B122: Coverage Universe | D122: Investment Banking Clients (IBC) | G122: Other Material Investment Services Clients (MISC)
A123: Stock Rating Category | B123: Count | C123: % of Total | D123: Count | E123: % of Total IBC | F123: % of Rating Category | G123: Count | H123: % of Total Other MISC
A124: Overweight/Buy | B124: 1173 | C124: 0.37 | D124: 318 | E124: 0.41 | F124: 0.27 | G124: 571 | H124: 0.39
A125: Equal-weight/Hold | B125: 1390 | C125: 0.44 | D125: 359 | E125: 0.47 | F125: 0.26 | G125: 653 | H125: 0.45
A126: Not-Rated/Hold | B126: 53 | C126: 0.02 | D126: 5 | E126: 0.01 | F126: 0.09 | G126: 8 | H126: 0.01
A127: Underweight/Sell | B127: 564 | C127: 0.18 | D127: 90 | E127: 0.12 | F127: 0.16 | G127: 219 | H127: 0.15
A128: Total | B128: 3180 | D128: 772 | G128: 1451
A130: Data include common stock and ADRs currently assigned ratings. Investment Banking Clients are companies
A131: from whom Morgan Stanley received investment banking compensation in the last 12 months. Due to rounding
A132: off of decimals, the percentages provided in the "% of total" column may not add up to exactly 100
A133: percent.
A135: Analyst Stock Ratings
A137: Overweight (O). The stock's total return is expected to exceed the average total return of the analyst's
A138: industry (or industry team's) coverage universe, on a risk-adjusted basis, over the next 12-18 months.
A140: Equal-weight (E). The stock's total return is expected to be in line with the average total return of
A141: the analyst's industry (or industry team's) coverage universe, on a risk-adjusted basis, over the next
A142: 12-18 months.
A144: Not-Rated (NR). Currently the analyst does not have adequate conviction about the stock's total return
A145: relative to the average total return of the analyst's industry (or industry team's) coverage universe,
... A391: © Copyright 2018 Morgan Stanley

Sheet VA
C1: 2005 | D1: 2006 | E1: 1Q07 | F1: 2Q07 | G1: 3Q07 | H1: 4Q07 | I1: 2007 | J1: 1Q08 | K1: 2Q08 | L1: 3Q08 | M1: 4Q08 | N1: 2008 | O1: 1Q09 | P1: 2Q09 | Q1: 3Q09 | R1: 4Q09 | S1: 2009 | T1: 1Q10 | U1: 2Q10 | V1: 3Q10 | W1: 4Q10 | X1: 2010 | Y1: 1Q11 | Z1: 2Q11 | AA1: 3Q11 | AB1: 4Q11 | AC1: 2011 | AD1: 1Q12 | AE1: 2Q12 | AF1: 3Q12 | AG1: 4Q12 | AH1: 2012 | AI1: 1Q13 | AJ1: 2Q13 | AK1: 3Q13 | AL1: 4Q13 | AM1: 2013 | AN1: 1Q14 | AO1: 2Q14 | AP1: 3Q14 | AQ1: 4Q14 | AR1: 2014 | AS1: 1Q15 | AT1: 2Q15 | AU1: 3Q15 | AV1: 4Q15 | AW1: 2015 | AX1: 1Q16 | AY1: 2Q16 | AZ1: 3Q16 | BA1: 4Q16 | BB1: 2016 | BC1: 1Q17 | BD1: 2Q17 | BE1: 3Q17 | BF1: 4Q17 | BG1: 2017 | BH1: 1Q18E | BI1: 2Q18E | BJ1: 3Q18E | BK1: 4Q18E | BL1: 2018E | BM1: 1Q19E | BN1: 2Q19E | BO1: 3Q19E | BP1: 4Q19E | BQ1: 2019E | BR1: 1Q20E | BS1: 2Q20E | BT1: 3Q20E | BU1: 4Q20E | BV1: 2020E | BW1: 1Q21E | BX1: 2Q21E | BY1: 3Q21E | BZ1: 4Q21E | CA1: 2021E | CJ1: =AC1 -> 2011 | CK1: =AH1 -> 2012 | CL1: =AM1 -> 2013 | CM1: =AR1 -> 2014 | CN1: =AW1 -> 2015 | CO1: =BB1 -> 2016 | CP1: =BG1 -> 2017 | CQ1: =BL1 -> 2018E | CR1: =BQ1 -> 2019E | CS1: =BV1 -> 2020E | CT1: =CA1 -> 2021E
A3: 2
A8: Verisk Analytics | CD8: Verisk Analytics
A9: Quarterly Income Statement | CD9: Annual Income Statement
A10: (Values in millions, except per-share amounts) | CB10: 4 YR CAGR | CD10: (Values in millions, except per-share amounts)
A11: Fiscal Year Ending Dec. 31 | C11: =C1 -> 2005 | D11: =D1 -> 2006 | E11: =E1 -> 1Q07 | F11: =F1 -> 2Q07 | G11: =G1 -> 3Q07 | H11: =H1 -> 4Q07 | I11: =I1 -> 2007 | J11: =J1 -> 1Q08 | ... AH11: =AH1 -> 2012 | AI11: =AI1&"R" -> 1Q13R | AJ11: =AJ1&"R" -> 2Q13R | AK11: =AK1&"R" -> 3Q13R | AL11: =AL1 -> 4Q13 | AM11: =AM1 -> 2013 | AN11: =AN1 -> 1Q14 | AO11: =AO1 -> 2Q14 | AP11: =AP1 -> 3Q14 | AQ11: =AQ1 -> 4Q14 | AR11: =AR1 -> 2014 | AS11: =AS1 -> 1Q15 | ... AW11: =AW1 -> 2015 | AX11: =AX$1 -> 1Q16 | AY11: =AY$1 -> 2Q16 | AZ11: =AZ$1 -> 3Q16 | BA11: =BA$1 -> 4Q16 | BB11: =BB$1 -> 2016 | BC11: =BC$1 -> 1Q17 | BD11: =BD$1 -> 2Q17 | BE11: =BE$1 -> 3Q17 | ... CA11: =CA$1 -> 2021E | CB11: '17 - '21 | CD11: =A11 -> Fiscal Year Ending Dec. 31 | CE11: =D11 -> 2006 | CF11: =I11 -> 2007 | CG11: =N11 -> 2008 | CH11: =S11 -> 2009 | CI11: =X11 -> 2010 | CJ11: =AC11 -> 2011 | CK11: =AH11 -> 2012 | CL11: =AM11 -> 2013 | CM11: =AR11 -> 2014 | CN11: =AW11 -> 2015 | CO11: =BB11 -> 2016 | CP11: =BG11 -> 2017 | CQ11: =BL11 -> 2018E | CR11: =BQ11 -> 2019E | CS11: =BV11 -> 2020E | CT11: =CA11 -> 2021E
A12: Total Revenue | B12: 12 | C12: =C245+C313 -> 645.66 | D12: =D245+D313 -> 730.133 | E12: =E245+E313 -> 198.834 | F12: =F245+F313 -> 201.154 | G12: =G245+G313 -> 199.723 | H12: =H245+H313 -> 202.484 | I12: =SUM(E12:H12) -> 802.195 | J12: =J245+J313 -> 215.618 | K12: =K245+K313 -> 222.072 | L12: =L245+L313 -> 224.391 | M12: =M245+M313 -> 231.469 | N12: =SUM(J12:M12) -> 893.55 | O12: =O245+O313 -> 245.751 | P12: =P245+P313 -> 257.916 | Q12: =Q245+Q313 -> 258.311 | R12: =R245+R313 -> 265.126 | S12: =SUM(O12:R12) -> 1027.104 | T12: =T245+T313 -> 276.154 | U12: =U245+U313 -> 281.677 | V12: =V245+V313 -> 287.354 | W12: =W245+W313 -> 293.158 | X12: =SUM(T12:W12) -> 1138.343 | Y12: =Y245+Y313 -> 312.869 | Z12: =Z245+Z313 -> 327.28 | AA12: =AA245+AA313 -> 340.098 | AB12: =AB245+AB313 -> 351.593 | AC12: =SUM(Y12:AB12) -> 1331.84 | AD12: =AD245+AD313 -> 346.501 | AE12: =AE245+AE313 -> 373.226 | AF12: =AF245+AF313 -> 398.863 | AG12: =AG245+AG313 -> 415.73 | AH12: =SUM(AD12:AG12) -> 1534.32 | AI12: =AI245+AI313 -> 376.697 | AJ12: =AJ245+AJ313 -> 390.366 | AK12: =AK245+AK313 -> 411.927 | AL12: =AL245+AL313 -> 416.723 | AM12: =SUM(AI12:AL12) -> 1595.713 | AN12: =AN245+AN313 -> 409.643 | AO12: =AO245+AO313 -> 423.554 | AP12: =AP245+AP313 -> 448.665 | AQ12: =AQ245+AQ313 -> 464.864 | AR12: =SUM(AN12:AQ12) -> 1746.726 | AS12: =AS245+AS313 -> 459.397 | AT12: =AT245+AT313 -> 497.65 | AU12: =AU245+AU313 -> 550.401 | AV12: =AV245+AV313 -> 560.6 | AW12: =SUM(AS12:AV12) -> 2068.048 | AX12: =AX245+AX313 -> 492.701 | AY12: =AY245+AY313 -> 498.296 | AZ12: =AZ245+AZ313 -> 498.081 | BA12: =BA245+BA313 -> 506.1 | BB12: =BB245+BB313 -> 1995.178 | BC12: =BC245+BC313 -> 502.6 | BD12: =BD245+BD313 -> 523.2 | BE12: =BE245+BE313 -> 549.1 | ... CA12: =CA245+CA313 -> 2784.2835 | CB12: =(CA12/BG12)^(1/4)-1 -> 0.067361217 | CD12: =A12 -> Total Revenue | CE12: =D12 -> 730.133 | CF12: =I12 -> 802.195 | CG12: =N12 -> 893.55 | CH12: =S12 -> 1027.104 | CI12: =X12 -> 1138.343 | CJ12: =AC12 -> 1331.84 | CK12: =AH12 -> 1534.32 | CL12: =AM12 -> 1595.713 | CM12: =AR12 -> 1746.726 | CN12: =AW12 -> 2068.048 | CO12: =BB12 -> 1995.178 | CP12: =BG12 -> 2145.2 | CQ12: =BL12 -> 2359.4133 | CR12: =BQ12 -> 2495.6575 | CS12: =BV12 -> 2635.8576 | CT12: =CA12 -> 2784.2835
A13: Annual Growth (2016 from continuing operations) | I13: =I12/D12-1 -> 0.098697087 | J13: =J12/E12-1 -> 0.084412123 | K13: =K12/F12-1 -> 0.10398998 | L13: =L12/G12-1 -> 0.12351106 | M13: =M12/H12-1 -> 0.14314711 | N13: =N12/I12-1 -> 0.11388129 | O13: =O12/J12-1 -> 0.13975178 | P13: =P12/K12-1 -> 0.16140711 | ... AW13: =AW12/AR12-1 -> 0.18395673 | AX13: 0.2820739 | AY13: 0.16261316 | AZ13: 0.058845663 | BA13: 0.060117302 | BB13: 0.13317317 | BC13: =BC12/AX12-1 -> 0.020091293 | BD13: =BD12/AY12-1 -> 0.049978326 | BE13: =BE12/AZ12-1 -> 0.10243113 | BF13: =BF12/BA12-1 -> 0.1268524 | BG13: =BG12/BB12-1 -> 0.075192289 | BH13: =BH12/BC12-1 -> 0.13042977 | BI13: =BI12/BD12-1 -> 0.11368884 | BJ13: =BJ12/BE12-1 -> 0.089470649 | ... CA13: =CA12/BV12-1 -> 0.056310316 | CD13: =A13 -> Annual Growth (2016 from continuing operations) | CF13: =I13 -> 0.098697087 | CG13: =N13 -> 0.11388129 | CH13: =S13 -> 0.1494645 | CI13: =X13 -> 0.10830354 | CJ13: =AC13 -> 0.16998128 | CK13: =AH13 -> 0.15203027 | CL13: =AM13 -> 0.040013165 | CM13: =AR13 -> 0.094636692 | CN13: =AW13 -> 0.18395673 | CO13: =BB13 -> 0.13317317 | CP13: =BG13 -> 0.075192289 | CQ13: =BL13 -> 0.099857045 | CR13: =BQ13 -> 0.057744931 | CS13: =BV13 -> 0.056177614 | CT13: =CA13 -> 0.056310316
A14: Total Revenue (pro forma for Mortgage) | X14: =+Revenue_end_mkt!H85 -> 1000.978 | Y14: =+Revenue_end_mkt!I85 -> 281.416 | Z14: =+Revenue_end_mkt!J85 -> 292.799 | AA14: =+Revenue_end_mkt!K85 -> 306.89251 | AB14: =+Revenue_end_mkt!L85 -> 321.35349 | AC14: =+Revenue_end_mkt!M85 -> 1202.461 | AD14: =+Revenue_end_mkt!N85 -> 313.469 | AE14: =+Revenue_end_mkt!O85 -> 339.089 | ... AM14: =+Revenue_end_mkt!W85 -> 1595.713 | CB14: =((1+BG14)*(1+#REF!)*(1+#REF!)*(1+BV14))^0.25-1 -> #REF! | CD14: =A14 -> Total Revenue (pro forma for Mortgage) | CF14: =I14 -> 0 | CG14: =N14 -> 0 | CH14: =S14 -> 0 | CI14: =X14 -> 1000.978 | CJ14: =AC14 -> 1202.461 | CK14: =AH14 -> 1407.806 | CL14: =AM14 -> 1595.713 | CM14: =AR14 -> 0 | CN14: =AW14 -> 0 | CO14: =BB14 -> 0 | CP14: =BG14 -> 0 | CQ14: =BL14 -> 0 | CR14: =BQ14 -> 0 | CS14: =BV14 -> 0 | CT14: =CA14 -> 0
A15: Revenue Growth (pro forma for mortgage, hc chg) | AC15: =+AC14/X14-1 -> 0.20128614 | AD15: =+AD14/Y14-1 -> 0.113899 | AE15: =+AE14/Z14-1 -> 0.1580948 | AF15: =+AF14/AA14-1 -> 0.19509924 | AG15: =+AG14/AB14-1 -> 0.20888992 | AH15: =+AH14/AC14-1 -> 0.17077061 | AI15: =+AI14/AD14-1 -> 0.20170416 | AJ15: =+AJ14/AE14-1 -> 0.15121989 | ... AM15: =+AM14/AH14-1 -> 0.13347507 | AN15: =+AN12/AI14-1 -> 0.087460213 | AO15: =+AO12/AJ14-1 -> 0.08501765 | AP15: =+AP12/AK14-1 -> 0.089185705 | AQ15: =+AQ12/AL14-1 -> 0.11552278 | AR15: =+AR12/AM14-1 -> 0.094636692 | AS15: =+AS12/AN12-1 -> 0.12145698 | AT15: =+AT12/AO12-1 -> 0.17493873 | AU15: =+AU12/AP12-1 -> 0.2267527 | AV15: =+AV12/AQ12-1 -> 0.2059441 | AW15: =AW12/(AR12+Revenue_end_mkt!AB53-Revenue_end_mkt!AB46)-1 -> 0.20896201 | AX15: =+AX12/AS12-1 -> 0.072495032 | AY15: =+AY12/AT12-1 -> 0.0012981011 | AZ15: =+AZ12/AU12-1 -> -0.095057967 | BA15: =+BA12/AV12-1 -> -0.097217267 | BB15: =BB12/(AW12+Revenue_end_mkt!AG53-Revenue_end_mkt!AG46)-1 -> -0.035236126 | BC15: =+BC12/AX12-1 -> 0.020091293 | BD15: =+BD12/AY12-1 -> 0.049978326 | BE15: =+BE12/AZ12-1 -> 0.10243113 | BF15: =+BF12/BA12-1 -> 0.1268524 | BG15: =BG12/(BB12+Revenue_end_mkt!AL53-Revenue_end_mkt!AL46)-1 -> 0.075192289 | BH15: =+BH12/BC12-1 -> 0.13042977 | BI15: =+BI12/BD12-1 -> 0.11368884 | BJ15: =+BJ12/BE12-1 -> 0.089470649 | BK15: =+BK12/BF12-1 -> 0.070224443 | BL15: =BL12/(BG12+Revenue_end_mkt!AQ53-Revenue_end_mkt!AQ46)-1 -> 0.099857045 | BM15: =+BM12/BH12-1 -> 0.056675382 | BN15: =+BN12/BI12-1 -> 0.057604603 | BO15: =+BO12/BJ12-1 -> 0.057874675 | BP15: =+BP12/BK12-1 -> 0.05874734 | BQ15: =BQ12/(BL12+Revenue_end_mkt!AV53-Revenue_end_mkt!AV46)-1 -> 0.057744931 | BR15: =+BR12/BM12-1 -> 0.056048728 | BS15: =+BS12/BN12-1 -> 0.056129551 | BT15: =+BT12/BO12-1 -> 0.056290787 | BU15: =+BU12/BP12-1 -> 0.056232353 | BV15: =BV12/(BQ12+Revenue_end_mkt!BA53-Revenue_end_mkt!BA46)-1 -> 0.056177614 | BW15: =+BW12/BR12-1 -> 0.056180432 | BX15: =+BX12/BS12-1 -> 0.056262956 | BY15: =+BY12/BT12-1 -> 0.056423292 | BZ15: =+BZ12/BU12-1 -> 0.056365477 | CA15: =CA12/(BV12+Revenue_end_mkt!BF53-Revenue_end_mkt!BF46)-1 -> 0.056310316 | CB15: =((1+BG15)*(1+#REF!)*(1+#REF!)*(1+BV15))^0.25-1 -> #REF! | CD15: =A15 -> Revenue Growth (pro forma for mortgage, hc chg) | CF15: =I15 -> 0 | CG15: =N15 -> 0 | CH15: =S15 -> 0 | CI15: =X15 -> 0 | CJ15: =AC15 -> 0.20128614 | CK15: =AH15 -> 0.17077061 | CL15: =AM15 -> 0.13347507 | CM15: =AR15 -> 0.094636692 | CN15: =AW15 -> 0.20896201 | CO15: =BB15 -> -0.035236126 | CP15: =BG15 -> 0.075192289 | CQ15: =BL15 -> 0.099857045 | CR15: =BQ15 -> 0.057744931 | CS15: =BV15 -> 0.056177614 | CT15: =CA15 -> 0.056310316
A16: Organic C/C Growth | AI16: =Revenue_end_mkt!S88 -> 0.068 | AJ16: =Revenue_end_mkt!T88 -> 0.078 | AK16: =Revenue_end_mkt!U88 -> 0.061 | AL16: =Revenue_end_mkt!V88 -> 0.073 | AM16: =Revenue_end_mkt!W88 -> 0.085 | AN16: =Revenue_end_mkt!X88 -> 0.087460213 | AO16: =Revenue_end_mkt!Y88 -> 0.08501765 | AP16: =Revenue_end_mkt!Z88 -> 0.089185705 | ... AW16: =Revenue_end_mkt!AG88 -> 0.074 | AX16: =Revenue_end_mkt!AH92 -> 0.05636045 | AY16: =Revenue_end_mkt!AI92 -> 0.061691434 | AZ16: =Revenue_end_mkt!AJ92 -> 0.062 | BA16: =Revenue_end_mkt!AK92 -> 0.062 | BB16: =Revenue_end_mkt!AL92 -> 0.058 | BC16: =Revenue_end_mkt!AM92 -> 0.025 | BD16: =Revenue_end_mkt!AN92 -> 0.041 | BE16: =Revenue_end_mkt!AO92 -> 0.07 | ... CA16: =Revenue_end_mkt!BK92 -> 0.056310316 | CD16: =A16 -> Organic C/C Growth | CF16: =I16 -> 0 | CG16: =N16 -> 0 | CH16: =S16 -> 0 | CI16: =X16 -> 0 | CJ16: =AC16 -> 0 | CK16: =AH16 -> 0 | CL16: =AM16 -> 0.085 | CM16: =AR16 -> 0.094 | CN16: =AW16 -> 0.074 | CO16: =BB16 -> 0.058 | CP16: =BG16 -> 0.052502882 | CQ16: =BL16 -> 0.058586612 | CR16: =BQ16 -> 0.057744931 | CS16: =BV16 -> 0.056177614 | CT16: =CA16 -> 0.056310316
A17: Cost Of Revenues | B17: 15 | C17: =C251+C317 -> 295.111 | D17: =D251+D317 -> 331.804 | E17: =E251+E317 -> 86.987 | F17: =F251+F317 -> 89.515 | G17: =G251+G317 -> 85.343 | H17: =H251+H317 -> 95.346 | I17: =SUM(E17:H17) -> 357.191 | J17: =J251+J317 -> 93.31 | K17: =K251+K317 -> 97.368 | L17: =L251+L317 -> 98.307 | M17: =M251+M317 -> 97.912 | N17: =SUM(J17:M17) -> 386.897 | O17: =O251+O317 -> 107.523 | P17: =P251+P317 -> 112.978 | Q17: 117.383 | R17: =R251+R317 -> 153.41 | S17: =SUM(O17:R17) -> 491.294 | T17: =T251+T317 -> 114.993 | U17: =U251+U317 -> 115 | V17: =V251+V317 -> 117.005 | W17: =W251+W317 -> 116.475 | X17: =SUM(T17:W17) -> 463.473 | Y17: =Y251+Y317 -> 124.556 | Z17: =Z251+Z317 -> 131.185 | AA17: =AA251+AA317 -> 137.619 | AB17: =AB251+AB317 -> 140.375 | AC17: =SUM(Y17:AB17) -> 533.735 | AD17: =AD251+AD317 -> 133.33 | AE17: =AE251+AE317 -> 147.074 | AF17: =AF251+AF317 -> 156.749 | AG17: =AG251+AG317 -> 170.021 | AH17: =SUM(AD17:AG17) -> 607.174 | AI17: =AI251+AI317 -> 143.632 | AJ17: =AJ251+AJ317 -> 152.428 | AK17: =AK251+AK317 -> 156.306 | AL17: =AL251+AL317 -> 170.156 | AM17: =SUM(AI17:AL17) -> 622.522 | AN17: =AN251+AN317 -> 169.673 | AO17: =AO251+AO317 -> 172.47 | AP17: =AP251+AP317 -> 180.873 | AQ17: =AQ251+AQ317 -> 193.582 | AR17: =SUM(AN17:AQ17) -> 716.598 | AS17: =AS251+AS317 -> 184.216 | AT17: =AT251+AT317 -> 195.196 | AU17: =AU251+AU317 -> 210.167 | AV17: =AV251+AV317 -> 213.7 | AW17: =SUM(AS17:AV17) -> 803.279 | AX17: =AX251+AX317 -> 173.277 | AY17: =AY251+AY317 -> 178.466 | AZ17: =AZ251+AZ317 -> 169.665 | BA17: =BA251+BA317 -> 193 | BB17: =SUM(AX17:BA17) -> 714.408 | BC17: =BC251+BC317 -> 182.9 | BD17: =BD251+BD317 -> 193.7 | BE17: =BE251+BE317 -> 198.5 | BF17: =BF251+BF317 -> 208.7 | BG17: =SUM(BC17:BF17) -> 783.8 | BH17: =BH251+BH317 -> 215.81868 | BI17: =BI251+BI317 -> 220.71229 | BJ17: =BJ251+BJ317 -> 216.90207 | BK17: =BK251+BK317 -> 223.75651 | BL17: =SUM(BH17:BK17) -> 877.18955 | BM17: =BM251+BM317 -> 227.24307 | BN17: =BN251+BN317 -> 232.58902 | BO17: =BO251+BO317 -> 228.56957 | BP17: =BP251+BP317 -> 236.02337 | BQ17: =SUM(BM17:BP17) -> 924.42503 | BR17: =BR251+BR317 -> 239.1054 | BS17: =BS251+BS317 -> 244.71876 | BT17: =BT251+BT317 -> 240.46133 | BU17: =BU251+BU317 -> 248.30346 | BV17: =SUM(BR17:BU17) -> 972.58895 | BW17: =BW251+BW317 -> 251.61519 | BX17: =BX251+BX317 -> 257.50969 | BY17: =BY251+BY317 -> 252.99867 | BZ17: =BZ251+BZ317 -> 261.25075 | CA17: =SUM(BW17:BZ17) -> 1023.3743 | CD17: =A17 -> Cost Of Revenues | CE17: =D17 -> 331.804 | CF17: =I17 -> 357.191 | CG17: =N17 -> 386.897 | CH17: =S17 -> 491.294 | CI17: =X17 -> 463.473 | CJ17: =AC17 -> 533.735 | CK17: =AH17 -> 607.174 | CL17: =AM17 -> 622.522 | CM17: =AR17 -> 716.598 | CN17: =AW17 -> 803.279 | CO17: =BB17 -> 714.408 | CP17: =BG17 -> 783.8 | CQ17: =BL17 -> 877.18955 | CR17: =BQ17 -> 924.42503 | CS17: =BV17 -> 972.58895 | CT17: =CA17 -> 1023.3743
A18: Gross Margin | B18: 16 | C18: =1-C17/C12 -> 0.54293126 | D18: =1-D17/D12 -> 0.54555677 | E18: =1-E17/E12 -> 0.56251446 | F18: =1-F17/F12 -> 0.55499269 | G18: =1-G17/G12 -> 0.57269318 | H18: =1-H17/H12 -> 0.52911835 | I18: =1-I17/I12 -> 0.55473295 | J18: =1-J17/J12 -> 0.56724392 | ... CA18: =1-CA17/CA12 -> 0.63244609 | CD18: =A18 -> Gross Margin | CE18: =D18 -> 0.54555677 | CF18: =I18 -> 0.55473295 | CG18: =N18 -> 0.56701136 | CH18: =S18 -> 0.52167064 | CI18: =X18 -> 0.59285295 | CJ18: =AC18 -> 0.59924991 | CK18: =AH18 -> 0.6042716 | CL18: =AM18 -> 0.60987847 | CM18: =AR18 -> 0.58974791 | CN18: =AW18 -> 0.61157623 | CO18: =BB18 -> 0.6419327 | CP18: =BG18 -> 0.63462614 | CQ18: =BL18 -> 0.62821709 | CR18: =BQ18 -> 0.62958658 | CS18: =BV18 -> 0.63101612 | CT18: =CA18 -> 0.63244609
A19: Selling General and Administrative | C19: =C257+C323 -> 88.723 | D19: =D257+D323 -> 100.124 | E19: =E257+E323 -> 27.925 | F19: =F257+F323 -> 27.675 | G19: =G257+G323 -> 26.989 | H19: =H257+H323 -> 24.987 | I19: =SUM(E19:H19) -> 107.576 | J19: =J257+J323 -> 28.674 | K19: =K257+K323 -> 30.354 | L19: =L257+L323 -> 32.265 | M19: =M257+M323 -> 39.946 | N19: =SUM(J19:M19) -> 131.239 | O19: =O257+O323 -> 33.32 | P19: =P257+P323 -> 38.905 | Q19: =38.5 -> 38.5 | R19: =R257+R323 -> 51.879 | S19: =SUM(O19:R19) -> 162.604 | T19: =T257+T323 -> 37.514 | U19: =U257+U323 -> 42.638 | V19: =V257+V323 -> 40.982 | W19: =W257+W323 -> 45.24 | X19: =SUM(T19:W19) -> 166.374 | Y19: =Y257+Y323 -> 49.256 | Z19: =Z257+Z323 -> 55.909 | AA19: =AA257+AA323 -> 51.475 | AB19: =AB257+AB323 -> 52.829 | AC19: =SUM(Y19:AB19) -> 209.469 | AD19: =AD257+AD323 -> 53.979 | AE19: =AE257+AE323 -> 62.473 | AF19: =AF257+AF323 -> 58.707 | AG19: =AG257+AG323 -> 56.2 | AH19: =SUM(AD19:AG19) -> 231.359 | AI19: =AI257+AI323 -> 56.322 | AJ19: =AJ257+AJ323 -> 58.198 | AK19: =AK257+AK323 -> 56.783 | AL19: =AL257+AL323 -> 57.679 | AM19: =SUM(AI19:AL19) -> 228.982 | AN19: =AN257+AN323 -> 57.134 | AO19: =AO257+AO323 -> 57.074 | AP19: =AP257+AP323 -> 56.164 | AQ19: =AQ257+AQ323 -> 56.934 | AR19: =SUM(AN19:AQ19) -> 227.306 | AS19: =AS257+AS323 -> 58.306 | AT19: =AT257+AT323 -> 91.292 | AU19: =AU257+AU323 -> 79.31 | AV19: =AV257+AV323 -> 83.8 | AW19: =SUM(AS19:AV19) -> 312.708 | AX19: =AX257+AX323 -> 71.037 | AY19: =AY257+AY323 -> 75.557 | AZ19: =AZ257+AZ323 -> 77.814 | BA19: =BA257+BA323 -> 77.2 | BB19: =SUM(AX19:BA19) -> 301.608 | BC19: =BC257+BC323 -> 75.9 | BD19: =BD257+BD323 -> 78.8 | BE19: =BE257+BE323 -> 80.9 | BF19: =BF257+BF323 -> 87.2 | BG19: =SUM(BC19:BF19) -> 322.8 | BH19: =BH257+BH323 -> 83.643193 | BI19: =BI257+BI323 -> 87.06328 | BJ19: =BJ257+BJ323 -> 88.653914 | BK19: =BK257+BK323 -> 93.607949 | BL19: =SUM(BH19:BK19) -> 352.96834 | BM19: =BM257+BM323 -> 87.661882 | BN19: =BN257+BN323 -> 91.343995 | BO19: =BO257+BO323 -> 93.040746 | BP19: =BP257+BP323 -> 98.340828 | BQ19: =SUM(BM19:BP19) -> 370.38745 | BR19: =BR257+BR323 -> 91.806375 | BS19: =BS257+BS323 -> 95.678304 | BT19: =BT257+BT323 -> 97.472846 | BU19: =BU257+BU323 -> 103.03517 | BV19: =SUM(BR19:BU19) -> 387.9927 | BW19: =BW257+BW323 -> 96.156162 | BX19: =BX257+BX323 -> 100.22818 | BY19: =BY257+BY323 -> 102.12614 | BZ19: =BZ257+BZ323 -> 107.96412 | CA19: =SUM(BW19:BZ19) -> 406.47459 | CD19: =A19 -> Selling General and Administrative | CE19: =D19 -> 100.124 | CF19: =I19 -> 107.576 | CG19: =N19 -> 131.239 | CH19: =S19 -> 162.604 | CI19: =X19 -> 166.374 | CJ19: =AC19 -> 209.469 | CK19: =AH19 -> 231.359 | CL19: =AM19 -> 228.982 | CM19: =AR19 -> 227.306 | CN19: =AW19 -> 312.708 | CO19: =BB19 -> 301.608 | CP19: =BG19 -> 322.8 | CQ19: =BL19 -> 352.96834 | CR19: =BQ19 -> 370.38745 | CS19: =BV19 -> 387.9927 | CT19: =CA19 -> 406.47459
A20: % of Total Revenue | C20: =C19/C12 -> 0.13741443 | D20: =D19/D12 -> 0.13713118 | E20: =E19/E12 -> 0.14044379 | F20: =F19/F12 -> 0.13758116 | G20: =G19/G12 -> 0.13513216 | H20: =H19/H12 -> 0.12340234 | I20: =I19/I12 -> 0.13410206 | J20: =J19/J12 -> 0.13298519 | ... CA20: =CA19/CA12 -> 0.14598893 | CD20: =A20 -> % of Total Revenue | CE20: =D20 -> 0.13713118 | CF20: =I20 -> 0.13410206 | CG20: =N20 -> 0.14687371 | CH20: =S20 -> 0.15831308 | CI20: =X20 -> 0.14615454 | CJ20: =AC20 -> 0.1572779 | CK20: =AH20 -> 0.15078927 | CL20: =AM20 -> 0.14349824 | CM20: =AR20 -> 0.1301326 | CN20: =AW20 -> 0.15120926 | CO20: =BB20 -> 0.15116847 | CP20: =BG20 -> 0.15047548 | CQ20: =BL20 -> 0.14960004 | CR20: =BQ20 -> 0.14841277 | CS20: =BV20 -> 0.1471979 | CT20: =CA20 -> 0.14598893
C21: ______ | D21: ______ | E21: ______ | F21: ______ | G21: ______ | H21: ______ | I21: ______ | J21: ______ | K21: ______ | L21: ______ | M21: ______ | N21: ______ | O21: ______ | P21: ______ | Q21: ______ | R21: ______ | S21: ______ | T21: ______ | U21: ______ | V21: ______ | W21: ______ | X21: ______ | Y21: ______ | Z21: ______ | AA21: ______ | AB21: ______ | AC21: ______ | AD21: ______ | AE21: ______ | AF21: ______ | AG21: ______ | AH21: ______ | AI21: ______ | AJ21: ______ | AK21: ______ | AL21: ______ | AM21: ______ | AN21: ______ | AO21: ______ | AP21: ______ | AQ21: ______ | AR21: ______ | AS21: ______ | AT21: ______ | AU21: ______ | AV21: ______ | AW21: ______ | AX21: ______ | AY21: ______ | AZ21: ______ | BA21: ______ | BB21: ______ | BC21: ______ | BD21: ______ | BE21: ______ | BF21: ______ | BG21: ______ | BH21: ______ | BI21: ______ | BJ21: ______ | BK21: ______ | BL21: ______ | BM21: ______ | BN21: ______ | BO21: ______ | BP21: ______ | BQ21: ______ | BR21: ______ | BS21: ______ | BT21: ______ | BU21: ______ | BV21: ______ | BW21: ______ | BX21: ______ | BY21: ______ | BZ21: ______ | CA21: ______
A22: Total Expenses | C22: =SUM(C17,C19) -> 383.834 | D22: =SUM(D17,D19) -> 431.928 | E22: =SUM(E17,E19) -> 114.912 | F22: =SUM(F17,F19) -> 117.19 | G22: =SUM(G17,G19) -> 112.332 | H22: =SUM(H17,H19) -> 120.333 | I22: =SUM(I17,I19) -> 464.767 | J22: =SUM(J17,J19) -> 121.984 | ... CA22: =SUM(CA17,CA19) -> 1429.8489 | CD22: =A22 -> Total Expenses | CE22: =D22 -> 431.928 | CF22: =I22 -> 464.767 | CG22: =N22 -> 518.136 | CH22: =S22 -> 653.898 | CI22: =X22 -> 629.847 | CJ22: =AC22 -> 743.204 | CK22: =AH22 -> 838.533 | CL22: =AM22 -> 851.504 | CM22: =AR22 -> 943.904 | CN22: =AW22 -> 1115.987 | CO22: =BB22 -> 1016.016 | CP22: =BG22 -> 1106.6 | CQ22: =BL22 -> 1230.1579 | CR22: =BQ22 -> 1294.8125 | CS22: =BV22 -> 1360.5816 | CT22: =CA22 -> 1429.8489
A24: Adjustments | D24: =D265+D331 -> 11.732 | I24: =I265+I331 -> 13.804 | J24: =J265+J331 -> 3.166 | K24: =K265+K331 -> 3.611 | L24: =L265+L331 -> 3.24 | M24: =M265+M331 -> 2.546 | N24: =N265+N331 -> 12.563 | O24: =O265+O331 -> 2.833 | P24: =P265+P331 -> 3.76 | Q24: =3.822+3.154 -> 6.976 | R24: =R265+R331 -> 60.725 | S24: =S265+S331 -> 74.27 | T24: 0 | U24: 0 | V24: 0 | W24: 0 | X24: =X265+X331 -> 0 | Y24: =Y265+Y331 -> 0 | Z24: =Z265+Z331 -> 3.364 | AA24: =AA265+AA331 -> 0 | AB24: =AB265+AB331 -> 0 | AC24: =AC265+AC331 -> 3.364 | AD24: =AD265+AD331 -> -0.435 | AE24: =AE265+AE331 -> -0.126 | ... AR24: =AR265+AR331 -> -0.158 | AS24: =-(AS265+AS331) -> 0.6 | AT24: =-26.617+0.221 -> -26.396 | AU24: =-(-AU265+AU331) -> -17.912 | AV24: =AV265+AV331 -> 0.1 | AW24: =SUM(AS24:AV24) -> -43.608 | AX24: =AX265+AX331 -> 0.212 | AY24: =AY265+AY331 -> 0.846 | AZ24: =AZ265+AZ331 -> 2.7 | BA24: =-(BA265-BA331) -> 21.9 | BB24: =SUM(AX24:BA24) -> 25.658 | BC24: =-(BC265-BC331) -> 1.9 | BD24: =-(BD265-BD331) -> 3.4 | BE24: =-(BE265-BE331) -> 2.6 | BF24: =-(BF265-BF331) -> 1.7 | BG24: =-(BG265-BG331) -> 9.6 | BH24: =-(BH265-BH331) -> 0 | BI24: =-(BI265-BI331) -> 0 | BJ24: =-(BJ265-BJ331) -> 0 | BK24: =-(BK265-BK331) -> 0 | BL24: =BL265+BL331 -> 0 | BM24: =-(BM265-BM331) -> 0 | BN24: =-(BN265-BN331) -> 0 | BO24: =-(BO265-BO331) -> 0 | BP24: =-(BP265-BP331) -> 0 | BQ24: =BQ265+BQ331 -> 0 | BR24: =-(BR265-BR331) -> 0 | BS24: =-(BS265-BS331) -> 0 | BT24: =-(BT265-BT331) -> 0 | BU24: =-(BU265-BU331) -> 0 | BV24: =BV265+BV331 -> 0 | BW24: =-(BW265-BW331) -> 0 | BX24: =-(BX265-BX331) -> 0 | BY24: =-(BY265-BY331) -> 0 | BZ24: =-(BZ265-BZ331) -> 0 | CA24: =CA265+CA331 -> 0 | CD24: =A24 -> Adjustments | CE24: =D24 -> 11.732 | CF24: =I24 -> 13.804 | CG24: =N24 -> 12.563 | CH24: =S24 -> 74.27 | CI24: =X24 -> 0 | CJ24: =AC24 -> 3.364 | CK24: =AH24 -> -0.128 | CL24: =AM24 -> 0.635 | CM24: =AR24 -> -0.158 | CN24: =AW24 -> -43.608 | CO24: =BB24 -> 25.658 | CP24: =BG24 -> 9.6 | CQ24: =BL24 -> 0 | CR24: =BQ24 -> 0 | CS24: =BV24 -> 0 | CT24: =CA24 -> 0
A25: % of Total Revenue | D25: =D24/D12 -> 0.016068305 | I25: =I24/I12 -> 0.017207786 | J25: =J24/J12 -> 0.014683375 | K25: =K24/K12 -> 0.016260492 | L25: =L24/L12 -> 0.014439082 | M25: =M24/M12 -> 0.010999313 | N25: =N24/N12 -> 0.01405965 | O25: =O24/O12 -> 0.011527929 | P25: =P24/P12 -> 0.01457839 | ... CA25: =CA24/CA12 -> 0 | CD25: =A25 -> % of Total Revenue | CE25: =D25 -> 0.016068305 | CF25: =I25 -> 0.017207786 | CG25: =N25 -> 0.01405965 | CH25: =S25 -> 0.072310107 | CI25: =X25 -> 0 | CJ25: =AC25 -> 0.0025258289 | CK25: =AH25 -> -8.3424579e-05 | CL25: =AM25 -> 0.00039794123 | CM25: =AR25 -> -9.0454943e-05 | CN25: =AW25 -> -0.021086551 | CO25: =BB25 -> 0.012860005 | CP25: =BG25 -> 0.0044751072 | CQ25: =BL25 -> 0 | CR25: =BQ25 -> 0 | CS25: =BV25 -> 0 | CT25: =CA25 -> 0
A27: Total Expenses ex. ESOP and IPO Expenses | C27: =C22-C24 -> 383.834 | D27: =D22-D24 -> 420.196 | E27: =E22-E24 -> 114.912 | F27: =F22-F24 -> 117.19 | G27: =G22-G24 -> 112.332 | H27: =H22-H24 -> 120.333 | I27: =I22-I24 -> 450.963 | J27: =J22-J24 -> 118.818 | ... AM27: =AM22-AM24 -> 850.869 | AR27: =AR22-AR24 -> 944.062 | AW27: =AW22-AW24 -> 1159.595 | BB27: =BB22-BB24 -> 990.358 | BG27: =BG22-BG24 -> 1097 | BL27: =BL22-BL24 -> 1230.1579 | BQ27: =BQ22-BQ24 -> 1294.8125 | BV27: =BV22-BV24 -> 1360.5816 | CA27: =CA22-CA24 -> 1429.8489 | CD27: =A27 -> Total Expenses ex. ESOP and IPO Expenses | CE27: =D27 -> 420.196 | CF27: =I27 -> 450.963 | CG27: =N27 -> 505.573 | CH27: =S27 -> 579.628 | CI27: =X27 -> 629.847 | CJ27: =AC27 -> 739.84 | CK27: =AH27 -> 838.661 | CL27: =AM27 -> 850.869 | CM27: =AR27 -> 944.062 | CN27: =AW27 -> 1159.595 | CO27: =BB27 -> 990.358 | CP27: =BG27 -> 1097 | CQ27: =BL27 -> 1230.1579 | CR27: =BQ27 -> 1294.8125 | CS27: =BV27 -> 1360.5816 | CT27: =CA27 -> 1429.8489
A29: EBITDA | C29: =C12-C22 -> 261.826 | D29: =D12-D22 -> 298.205 | E29: =E12-E22 -> 83.922 | F29: =F12-F22 -> 83.964 | G29: =G12-G22 -> 87.391 | H29: =H12-H22 -> 82.151 | I29: =I12-I22 -> 337.428 | J29: =J12-J22 -> 93.634 | ... AQ29: =AQ12-AQ22 -> 214.348 | AR29: =SUM(AN29:AQ29) -> 802.822 | AS29: =AS12-AS22 -> 216.875 | AT29: =AT12-AT22 -> 211.162 | AU29: =AU12-AU22 -> 260.924 | AV29: =AV12-AV22 -> 263.1 | AW29: =AW12-AW22 -> 952.061 | AX29: =AX12-AX22 -> 248.387 | AY29: =AY12-AY22 -> 244.273 | AZ29: =AZ12-AZ22 -> 250.602 | ... CA29: =CA12-CA22 -> 1354.4347 | CB29: =(CA29/BB29)^(1/5)-1 -> 0.067040005 | CD29: =A29 -> EBITDA | CE29: =D29 -> 298.205 | CF29: =I29 -> 337.428 | CG29: =N29 -> 375.414 | CH29: =S29 -> 373.206 | CI29: =X29 -> 508.496 | CJ29: =AC29 -> 588.636 | CK29: =AH29 -> 695.787 | CL29: =AM29 -> 744.209 | CM29: =AR29 -> 802.822 | CN29: =AW29 -> 952.061 | CO29: =BB29 -> 979.162 | CP29: =BG29 -> 1038.6 | CQ29: =BL29 -> 1129.2554 | CR29: =BQ29 -> 1200.845 | CS29: =BV29 -> 1275.2759 | CT29: =CA29 -> 1354.4347
A30: EBITDA Margin | C30: =C29/C12 -> 0.40551684 | D30: =D29/D12 -> 0.40842559 | E30: =E29/E12 -> 0.42207067 | F30: =F29/F12 -> 0.41741154 | G30: =G29/G12 -> 0.43756102 | H30: =H29/H12 -> 0.40571601 | I30: =I29/I12 -> 0.42063089 | J30: =J29/J12 -> 0.43425874 | ... CA30: =CA29/CA12 -> 0.48645716 | CD30: =A30 -> EBITDA Margin | CE30: =D30 -> 0.40842559 | CF30: =I30 -> 0.42063089 | CG30: =N30 -> 0.42013765 | CH30: =S30 -> 0.36335756 | CI30: =X30 -> 0.4466984 | CJ30: =AC30 -> 0.44197201 | CK30: =AH30 -> 0.45348232 | CL30: =AM30 -> 0.46638023 | CM30: =AR30 -> 0.4596153 | CN30: =AW30 -> 0.46036697 | CO30: =BB30 -> 0.49076423 | CP30: =BG30 -> 0.48415066 | CQ30: =BL30 -> 0.47861705 | CR30: =BQ30 -> 0.4811738 | CS30: =BV30 -> 0.48381822 | CT30: =CA30 -> 0.48645716
A31: Year-over-Year Growth | I31: =I29/D29-1 -> 0.13153032 | J31: =J29/E29-1 -> 0.11572651 | K31: =K29/F29-1 -> 0.12369587 | L31: =L29/G29-1 -> 0.073554485 | M31: =M29/H29-1 -> 0.13949921 | N31: =N29/I29-1 -> 0.11257513 | O31: =O29/J29-1 -> 0.12040498 | P31: =P29/K29-1 -> 0.12382618 | ... CA31: =CA29/BV29-1 -> 0.062071852 | CD31: =A31 -> Year-over-Year Growth | CF31: =I31 -> 0.13153032 | CG31: =N31 -> 0.11257513 | CH31: =S31 -> -0.0058815068 | CI31: =X31 -> 0.36250757 | CJ31: =AC31 -> 0.15760203 | CK31: =AH31 -> 0.1820327 | CL31: =AM31 -> 0.069593137 | CM31: =AR31 -> 0.07875879 | CN31: =AW31 -> 0.18589301 | CO31: =BB31 -> 0.028465613 | CP31: =BG31 -> 0.060702928 | CQ31: =BL31 -> 0.087286198 | CR31: =BQ31 -> 0.063395367 | CS31: =BV31 -> 0.061982119 | CT31: =CA31 -> 0.062071852
A33: Adj. EBITDA | C33: =C29+C24 -> 261.826 | D33: =D29+D24 -> 309.937 | E33: =E29+E24 -> 83.922 | F33: =F29+F24 -> 83.964 | G33: =G29+G24 -> 87.391 | H33: =H29+H24 -> 82.151 | I33: =I29+I24 -> 351.232 | J33: =J29+J24 -> 96.8 | ... O33: =O29+O24 -> 107.741 | P33: =P29+P24+P26 -> 109.793 | Q33: =Q29+Q24+Q26 -> 109.404 | R33: =R29+R24+R26 -> 120.562 | S33: =S29+S24+S26 -> 447.476 | T33: =T29+T24 -> 123.647 | U33: =U29+U24 -> 124.039 | V33: =V29+V24 -> 129.367 | W33: =W29+W24 -> 131.443 | X33: =X29+X24 -> 508.496 | Y33: =Y29+Y24 -> 139.057 | Z33: =Z29+Z24 -> 143.55 | AA33: =AA29+AA24 -> 151.004 | ... AC33: =AC29+AC24 -> 592 | AD33: =AD29-AD24 -> 159.627 | AE33: =AE29-AE24 -> 163.805 | AF33: =AF29-AF24 -> 182.905 | AG33: =AG29-AG24 -> 189.578 | AH33: =AH29-AH24 -> 695.915 | AI33: =AI29-AI24 -> 176.598 | AJ33: =AJ29-AJ24 -> 179.867 | AK33: =AK29-AK24 -> 199.066 | ... AQ33: =AQ29-AQ24 -> 214.582 | AR33: =SUM(AN33:AQ33) -> 802.98 | AS33: =AS29-AS24 -> 216.275 | AT33: =AT29-AT24 -> 237.558 | AU33: =AU29-AU24 -> 278.836 | AV33: =AV29-AV24 -> 263 | AW33: =AW29-AW24 -> 995.669 | AX33: =AX29+AX24 -> 248.599 | AY33: =AY29+AY24 -> 245.119 | AZ33: =AZ29+AZ24 -> 253.302 | BA33: =BA29+BA24 -> 257.8 | BB33: =BB29+BB24 -> 1004.82 | BC33: =BC29+BC24 -> 245.7 | BD33: =BD29+BD24 -> 254.1 | BE33: =BE29+BE24 -> 272.3 | ... CA33: =CA29+CA24 -> 1354.4347 | CB33: =(CA33/BG33)^(1/4)-1 -> 0.066174954 | CD33: =A33 -> Adj. EBITDA | CE33: =D33 -> 309.937 | CF33: =I33 -> 351.232 | CG33: =N33 -> 387.977 | CH33: =S33 -> 447.476 | CI33: =X33 -> 508.496 | CJ33: =AC33 -> 592 | CK33: =AH33 -> 695.915 | CL33: =AM33 -> 743.574 | CM33: =AR33 -> 802.98 | CN33: =AW33 -> 995.669 | CO33: =BB33 -> 1004.82 | CP33: =BG33 -> 1048.2 | CQ33: =BL33 -> 1129.2554 | CR33: =BQ33 -> 1200.845 | CS33: =BV33 -> 1275.2759 | CT33: =CA33 -> 1354.4347
A34: Adj. EBITDA Margin | C34: =C33/C12 -> 0.40551684 | D34: =D33/D12 -> 0.42449389 | E34: =E33/E12 -> 0.42207067 | F34: =F33/F12 -> 0.41741154 | G34: =G33/G12 -> 0.43756102 | H34: =H33/H12 -> 0.40571601 | I34: =I33/I12 -> 0.43783868 | J34: =J33/J12 -> 0.44894211 | ... CA34: =CA33/CA12 -> 0.48645716 | CD34: =A34 -> Adj. EBITDA Margin | CE34: =D34 -> 0.42449389 | CF34: =I34 -> 0.43783868 | CG34: =N34 -> 0.4341973 | CH34: =S34 -> 0.43566766 | CI34: =X34 -> 0.4466984 | CJ34: =AC34 -> 0.44449784 | CK34: =AH34 -> 0.45356575 | CL34: =AM34 -> 0.46598229 | CM34: =AR34 -> 0.45970576 | CN34: =AW34 -> 0.48145353 | CO34: =BB34 -> 0.50362424 | CP34: =BG34 -> 0.48862577 | CQ34: =BL34 -> 0.47861705 | CR34: =BQ34 -> 0.4811738 | CS34: =BV34 -> 0.48381822 | CT34: =CA34 -> 0.48645716
A35: Year-over-Year Growth | D35: =D33/C33-1 -> 0.1837518 | I35: =I33/D33-1 -> 0.13323675 | J35: =J33/E33-1 -> 0.15345201 | K35: =K33/F33-1 -> 0.1667024 | L35: =L33/G33-1 -> 0.11062924 | M35: =M33/H33-1 -> 0.17049093 | N35: =N33/I33-1 -> 0.10461746 | O35: =O33/J33-1 -> 0.11302686 | P35: =P33/K33-1 -> 0.12078276 | ... AW35: =AW33/AR33-1 -> 0.23996737 | AX35: 0.2411333 | AY35: 0.1249151 | AZ35: -0.0058791209 | BA35: 0.070153591 | BB35: 0.099485721 | BC35: =BC33/AX33-1 -> -0.01166135 | BD35: =BD33/AY33-1 -> 0.036639347 | BE35: =BE33/AZ33-1 -> 0.075001382 | BF35: =BF33/BA33-1 -> 0.07098526 | BG35: =BG33/BB33-1 -> 0.043171911 | BH35: =BH33/BC33-1 -> 0.093578053 | BI35: =BI33/BD33-1 -> 0.08188283 | BJ35: =BJ33/BE33-1 -> 0.07481583 | ... CA35: =CA33/BV33-1 -> 0.062071852 | CD35: =A35 -> Year-over-Year Growth | CE35: =D35 -> 0.1837518 | CF35: =I35 -> 0.13323675 | CG35: =N35 -> 0.10461746 | CH35: =S35 -> 0.15335703 | CI35: =X35 -> 0.13636486 | CJ35: =AC35 -> 0.16421761 | CK35: =AH35 -> 0.17553209 | CL35: =AM35 -> 0.068483938 | CM35: =AR35 -> 0.079892519 | CN35: =AW35 -> 0.23996737 | CO35: =BB35 -> 0.099485721 | CP35: =BG35 -> 0.043171911 | CQ35: =BL35 -> 0.077328224 | CR35: =BQ35 -> 0.063395367 | CS35: =BV35 -> 0.061982119 | CT35: =CA35 -> 0.062071852
A37: Depreciation and Amortization | C37: =C38+C39 -> 41.824 | D37: =D38+D39 -> 54.861 | E37: =E38+E39 -> 16.505 | F37: =F38+F39 -> 16.233 | G37: =G38+G39 -> 15.523 | H37: =H38+H39 -> 17.4 | I37: =I38+I39 -> 65.661 | J37: =J38+J39 -> 15.948 | ... AQ37: =AQ38+AQ39 -> 37.301 | AR37: =SUM(AN37:AQ37) -> 142.376 | AS37: =AS38+AS39 -> 38.583 | AT37: =AT38+AT39 -> 57.44 | AU37: =AU38+AU39 -> 52.044 | AV37: =AV38+AV39 -> 67.682 | AW37: =SUM(AS37:AV37) -> 215.749 | AX37: =AX38+AX39 -> 55.758 | AY37: =AY38+AY39 -> 53.194 | AZ37: =AZ38+AZ39 -> 52.18 | BA37: =BA38+BA39 -> 50.4 | BB37: =SUM(AX37:BA37) -> 211.532 | BC37: =BC38+BC39 -> 56.1 | BD37: =BD38+BD39 -> 55.7 | BE37: =BE38+BE39 -> 61.3 | BF37: =BF38+BF39 -> 64.3 | BG37: =SUM(BC37:BF37) -> 237.4 | BH37: =BH38+BH39 -> 70.91086 | BI37: =BI38+BI39 -> 70.04494 | BJ37: =BJ38+BJ39 -> 70.57008 | BK37: =BK38+BK39 -> 71.01484 | BL37: =SUM(BH37:BK37) -> 282.54072 | BM37: =BM38+BM39 -> 70.561862 | BN37: =BN38+BN39 -> 69.693847 | BO37: =BO38+BO39 -> 70.218594 | BP37: =BP38+BP39 -> 70.662655 | BQ37: =SUM(BM37:BP37) -> 281.13696 | BR37: =BR38+BR39 -> 69.855625 | BS37: =BS38+BS39 -> 68.98497 | BT37: =BT38+BT39 -> 69.509222 | BU37: =BU38+BU39 -> 69.952402 | BV37: =SUM(BR37:BU37) -> 278.30222 | BW37: =BW38+BW39 -> 67.613406 | BX37: =BX38+BX39 -> 66.749219 | BY37: =BY38+BY39 -> 67.274684 | BZ37: =BZ38+BZ39 -> 67.720022 | CA37: =SUM(BW37:BZ37) -> 269.35733 | CD37: =A37 -> Depreciation and Amortization | CE37: =D37 -> 54.861 | CF37: =I37 -> 65.661 | CG37: =N37 -> 64.872 | CH37: =S37 -> 71.199 | CI37: =X37 -> 67.582 | CJ37: =AC37 -> 78.619 | CK37: =AH37 -> 104.199 | CL37: =AM37 -> 129.93 | CM37: =AR37 -> 142.376 | CN37: =AW37 -> 215.749 | CO37: =BB37 -> 211.532 | CP37: =BG37 -> 237.4 | CQ37: =BL37 -> 282.54072 | CR37: =BQ37 -> 281.13696 | CS37: =BV37 -> 278.30222 | CT37: =CA37 -> 269.35733
A38: Depreciation | C38: =C277+C345 -> 22.024 | D38: =D277+D345 -> 28.007 | E38: =E277+E345 -> 7.582 | F38: =F277+F345 -> 7.916 | G38: =G277+G345 -> 7.799 | H38: =H277+H345 -> 8.448 | I38: =SUM(E38:H38) -> 31.745 | J38: =J277+J345 -> 7.907 | K38: =K277+K345 -> 8.517 | L38: =L277+L345 -> 9.054 | M38: =M277+M345 -> 9.839 | N38: =SUM(J38:M38) -> 35.317 | O38: =O277+O345 -> 9.195 | P38: =P277+P345 -> 9.718 | Q38: 9.621 | R38: =R277+R345 -> 10.044 | S38: =SUM(O38:R38) -> 38.578 | T38: =T277+T345 -> 9.929 | U38: =U277+U345 -> 9.944 | V38: =V277+V345 -> 10.035 | W38: =W277+W345 -> 10.82 | X38: =SUM(T38:W38) -> 40.728 | Y38: =Y277+Y345 -> 11.305 | Z38: =Z277+Z345 -> 10.855 | AA38: =AA277+AA345 -> 10.798 | AB38: =AB277+AB345 -> 10.869 | AC38: =SUM(Y38:AB38) -> 43.827 | AD38: =AD277+AD345 -> 11.644 | AE38: =AE277+AE345 -> 13.09 | AF38: =AF277+AF345 -> 12.714 | AG38: =AG277+AG345 -> 13.176 | AH38: =SUM(AD38:AG38) -> 50.624 | AI38: =AI277+AI345 -> 14.163 | AJ38: =AJ277+AJ345 -> 15.81 | AK38: =AK277+AK345 -> 16.745 | AL38: =AL277+AL345 -> 19.471 | AM38: =SUM(AI38:AL38) -> 66.189 | AN38: =AN277+AN345 -> 19.781 | AO38: =AO277+AO345 -> 20.723 | AP38: =AP277+AP345 -> 21.951 | AQ38: =AQ277+AQ345 -> 23.051 | AR38: =SUM(AN38:AQ38) -> 85.506 | AS38: =AS277+AS345 -> 24.442 | AT38: =AT277+AT345 -> 28.628 | AU38: =AU277+AU345 -> 33.501 | AV38: =AV277+AV345 -> 34.049 | AW38: =SUM(AS38:AV38) -> 120.62 | AX38: 31.887 | AY38: 29.388 | AZ38: 29.501 | BA38: 28.3 | BB38: =SUM(AX38:BA38) -> 119.076 | BC38: 33.8 | BD38: 31.8 | BE38: 33.8 | BF38: 36.2 | BG38: =SUM(BC38:BF38) -> 135.6 | BH38: =BH277+BH345 -> 38.63586 | BI38: =BI277+BI345 -> 37.76994 | BJ38: =BJ277+BJ345 -> 38.29508 | BK38: =BK277+BK345 -> 38.73984 | BL38: =SUM(BH38:BK38) -> 153.44072 | BM38: =BM277+BM345 -> 38.511862 | BN38: =BN277+BN345 -> 37.643847 | BO38: =BO277+BO345 -> 38.168594 | BP38: =BP277+BP345 -> 38.612655 | BQ38: =SUM(BM38:BP38) -> 152.93696 | BR38: =BR277+BR345 -> 38.355625 | BS38: =BS277+BS345 -> 37.48497 | BT38: =BT277+BT345 -> 38.009222 | BU38: =BU277+BU345 -> 38.452402 | BV38: =SUM(BR38:BU38) -> 152.30222 | BW38: =BW277+BW345 -> 38.738406 | BX38: =BX277+BX345 -> 37.874219 | BY38: =BY277+BY345 -> 38.399684 | BZ38: =BZ277+BZ345 -> 38.845022 | CA38: =SUM(BW38:BZ38) -> 153.85733 | CD38: =A38 -> Depreciation | CE38: =D38 -> 28.007 | CF38: =I38 -> 31.745 | CG38: =N38 -> 35.317 | CH38: =S38 -> 38.578 | CI38: =X38 -> 40.728 | CJ38: =AC38 -> 43.827 | CK38: =AH38 -> 50.624 | CL38: =AM38 -> 66.189 | CM38: =AR38 -> 85.506 | CN38: =AW38 -> 120.62 | CO38: =BB38 -> 119.076 | CP38: =BG38 -> 135.6 | CQ38: =BL38 -> 153.44072 | CR38: =BQ38 -> 152.93696 | CS38: =BV38 -> 152.30222 | CT38: =CA38 -> 153.85733
A39: Intangible Amortization | C39: =C279+C346 -> 19.8 | D39: =D279+D346 -> 26.854 | E39: =E279+E346 -> 8.923 | F39: =F279+F346 -> 8.317 | G39: =G279+G346 -> 7.724 | H39: =H279+H346 -> 8.952 | I39: =SUM(E39:H39) -> 33.916 | J39: =J279+J346 -> 8.041 | K39: =K279+K346 -> 6.896 | L39: =L279+L346 -> 7.041 | M39: =M279+M346 -> 7.577 | N39: =SUM(J39:M39) -> 29.555 | O39: =O279+O346 -> 8.51 | P39: =P279+P346 -> 8.464 | Q39: 8.012 | R39: =R279+R346 -> 7.635 | S39: =SUM(O39:R39) -> 32.621 | T39: =T279+T346 -> 7.304 | U39: =U279+U346 -> 7.02 | V39: =V279+V346 -> 5.614 | W39: =W279+W346 -> 6.916 | X39: =SUM(T39:W39) -> 26.854 | Y39: =Y279+Y346 -> 8.455 | Z39: =Z279+Z346 -> 8.877 | AA39: =AA279+AA346 -> 8.797 | AB39: =AB279+AB346 -> 8.663 | AC39: =SUM(Y39:AB39) -> 34.792 | AD39: =AD279+AD346 -> 8.587 | AE39: =AE279+AE346 -> 12.187 | AF39: =AF279+AF346 -> 15.442 | AG39: =AG279+AG346 -> 17.359 | AH39: =SUM(AD39:AG39) -> 53.575 | AI39: =AI279+AI346 -> 17.052 | AJ39: =AJ279+AJ346 -> 17.061 | AK39: =AK279+AK346 -> 15.258 | AL39: =AL279+AL346 -> 14.37 | AM39: =SUM(AI39:AL39) -> 63.741 | AN39: =AN279+AN346 -> 14.212 | AO39: =AO279+AO346 -> 14.221 | AP39: =AP279+AP346 -> 14.187 | AQ39: =AQ279+AQ346 -> 14.25 | AR39: =SUM(AN39:AQ39) -> 56.87 | AS39: =AS279+AS346 -> 14.141 | AT39: =AT279+AT346 -> 28.812 | AU39: =AU279+AU346 -> 18.543 | AV39: =AV279+AV346 -> 33.633 | AW39: =SUM(AS39:AV39) -> 95.129 | AX39: 23.871 | AY39: 23.806 | AZ39: 22.679 | BA39: 22.1 | BB39: =SUM(AX39:BA39) -> 92.456 | BC39: 22.3 | BD39: 23.9 | BE39: 27.5 | BF39: 28.1 | BG39: =SUM(BC39:BF39) -> 101.8 | BH39: =129.1/4 -> 32.275 | BI39: =BH39 -> 32.275 | BJ39: =BI39 -> 32.275 | BK39: =BJ39 -> 32.275 | BL39: =SUM(BH39:BK39) -> 129.1 | BM39: =128.2/4 -> 32.05 | BN39: =BM39 -> 32.05 | BO39: =BN39 -> 32.05 | BP39: =BO39 -> 32.05 | BQ39: =SUM(BM39:BP39) -> 128.2 | BR39: =126/4 -> 31.5 | BS39: =BR39 -> 31.5 | BT39: =BS39 -> 31.5 | BU39: =BT39 -> 31.5 | BV39: =SUM(BR39:BU39) -> 126 | BW39: =115.5/4 -> 28.875 | BX39: =BW39 -> 28.875 | BY39: =BX39 -> 28.875 | BZ39: =BY39 -> 28.875 | CA39: =SUM(BW39:BZ39) -> 115.5 | CD39: =A39 -> Intangible Amortization | CE39: =D39 -> 26.854 | CF39: =I39 -> 33.916 | CG39: =N39 -> 29.555 | CH39: =S39 -> 32.621 | CI39: =X39 -> 26.854 | CJ39: =AC39 -> 34.792 | CK39: =AH39 -> 53.575 | CL39: =AM39 -> 63.741 | CM39: =AR39 -> 56.87 | CN39: =AW39 -> 95.129 | CO39: =BB39 -> 92.456 | CP39: =BG39 -> 101.8 | CQ39: =BL39 -> 129.1 | CR39: =BQ39 -> 128.2 | CS39: =BV39 -> 126 | CT39: =CA39 -> 115.5
A40: % of Total Revenue | C40: =C37/C12 -> 0.064777127 | D40: =D37/D12 -> 0.075138365 | E40: =E37/E12 -> 0.083008942 | F40: =F37/F12 -> 0.080699365 | G40: =G37/G12 -> 0.077722646 | H40: =H37/H12 -> 0.085932716 | I40: =I37/I12 -> 0.081851669 | J40: =J37/J12 -> 0.07396414 | ... X40: =X37/X12 -> 0.059368749 | Z40: =Z37/Z12 -> 0.060290882 | AA40: =AA37/AA12 -> 0.057615746 | AB40: =AB37/AB12 -> 0.055552869 | AC40: =AC37/AC12 -> 0.059030364 | AD40: =AD37/AD12 -> 0.058386556 | AE40: =AE37/AE12 -> 0.067725721 | AF40: =AF37/AF12 -> 0.070590654 | AG40: =AF40 -> 0.070590654 | AH40: =AH37/AH12 -> 0.06791217 | AI40: =AI37/AI12 -> 0.082865008 | AJ40: =AJ37/AJ12 -> 0.084205592 | AK40: =AK37/AK12 -> 0.07769095 | AL40: =AL37/AL12 -> 0.081207421 | AM40: =AM37/AM12 -> 0.081424417 | AN40: =AN37/AN12 -> 0.082982011 | AO40: =AO37/AO12 -> 0.082501877 | AP40: =AP37/AP12 -> 0.080545619 | AQ40: =AP40 -> 0.080545619 | AR40: =AR37/AR12 -> 0.081510208 | AS40: =AS37/AS12 -> 0.083986182 | AT40: =AT37/AT12 -> 0.11542249 | AU40: 0.0302 | AV40: =AV37/AV12 -> 0.12073136 | AW40: =AW37/AW12 -> 0.10432495 | AX40: =AX37/AX12 -> 0.11316803 | AY40: =AY37/AY12 -> 0.10675181 | AZ40: =AZ37/AZ12 -> 0.10476208 | BA40: =BA37/BA12 -> 0.099585062 | BB40: =BB37/BB12 -> 0.10602162 | BC40: =BC37/BC12 -> 0.11161958 | ... CA40: =CA37/CA12 -> 0.096742062 | CD40: =A40 -> % of Total Revenue | CE40: =D40 -> 0.075138365 | CF40: =I40 -> 0.081851669 | CG40: =N40 -> 0.072600302 | CH40: =S40 -> 0.069320147 | CI40: =X40 -> 0.059368749 | CJ40: =AC40 -> 0.059030364 | CK40: =AH40 -> 0.06791217 | CL40: =AM40 -> 0.081424417 | CM40: =AR40 -> 0.081510208 | CN40: =AW40 -> 0.10432495 | CO40: =BB40 -> 0.10602162 | CP40: =BG40 -> 0.11066567 | CQ40: =BL40 -> 0.11975041 | CR40: =BQ40 -> 0.11265046 | CS40: =BV40 -> 0.10558318 | CT40: =CA40 -> 0.096742062
A42: Income from Operations | C42: =C12-C22-C37 -> 220.002 | D42: =D12-D22-D37 -> 243.344 | E42: =E12-E22-E37 -> 67.417 | F42: =F12-F22-F37 -> 67.731 | G42: =G12-G22-G37 -> 71.868 | H42: =H12-H22-H37 -> 64.751 | I42: =I12-I22-I37 -> 271.767 | J42: =J12-J22-J37 -> 77.686 | ... AQ42: =AQ12-AQ22-AQ37 -> 177.047 | AR42: =SUM(AN42:AQ42) -> 660.446 | AS42: =AS12-AS22-AS37 -> 178.292 | AT42: =AT12-AT22-AT37 -> 153.722 | AU42: =AU12-AU22-AU37 -> 208.88 | AV42: =AV12-AV22-AV37 -> 195.418 | AW42: =AW12-AW22-AW37 -> 736.312 | AX42: =AX12-AX22-AX37 -> 192.629 | AY42: =AY12-AY22-AY37 -> 191.079 | AZ42: =AZ12-AZ22-AZ37 -> 198.422 | ... CA42: =CA12-CA22-CA37 -> 1085.0773 | CD42: =A42 -> Income from Operations | CE42: =D42 -> 243.344 | CF42: =I42 -> 271.767 | CG42: =N42 -> 310.542 | CH42: =S42 -> 302.007 | CI42: =X42 -> 440.914 | CJ42: =AC42 -> 510.017 | CK42: =AH42 -> 591.588 | CL42: =AM42 -> 614.279 | CM42: =AR42 -> 660.446 | CN42: =AW42 -> 736.312 | CO42: =BB42 -> 767.63 | CP42: =BG42 -> 801.2 | CQ42: =BL42 -> 846.71472 | CR42: =BQ42 -> 919.70805 | CS42: =BV42 -> 996.97371 | CT42: =CA42 -> 1085.0773
A43: Operating Margin | C43: =C42/C12 -> 0.34073971 | D43: =D42/D12 -> 0.33328722 | E43: =E42/E12 -> 0.33906173 | F43: =F42/F12 -> 0.33671217 | G43: =G42/G12 -> 0.35983838 | H43: =H42/H12 -> 0.31978329 | I43: =I42/I12 -> 0.33877922 | J43: =J42/J12 -> 0.3602946 | ... CA43: =CA42/CA12 -> 0.3897151 | CD43: =A43 -> Operating Margin | CE43: =D43 -> 0.33328722 | CF43: =I43 -> 0.33877922 | CG43: =N43 -> 0.34753735 | CH43: =S43 -> 0.29403741 | CI43: =X43 -> 0.38732965 | CJ43: =AC43 -> 0.38294164 | CK43: =AH43 -> 0.38557015 | CL43: =AM43 -> 0.38495582 | CM43: =AR43 -> 0.37810509 | CN43: =AW43 -> 0.35604203 | CO43: =BB43 -> 0.38474261 | CP43: =BG43 -> 0.37348499 | CQ43: =BL43 -> 0.35886664 | CR43: =BQ43 -> 0.36852335 | CS43: =BV43 -> 0.37823504 | CT43: =CA43 -> 0.3897151
A45: Interest Income | C45: 2.919 | D45: 6.585 | E45: 2.1 | F45: =4.392-E45 -> 2.292 | G45: =5.953-SUM(E45:F45) -> 1.561 | H45: =8.442-SUM(E45:G45) -> 2.489 | I45: =SUM(E45:H45) -> 8.442 | J45: 0.816 | K45: =1.617-J45 -> 0.801 | L45: =2.005-SUM(J45:K45) -> 0.388 | M45: =2.233-SUM(J45:L45) -> 0.228 | N45: =SUM(J45:M45) -> 2.233 | O45: 0.043 | P45: =0.092-O45 -> 0.049 | Q45: 0.029 | R45: =0.195-SUM(O45:Q45) -> 0.074 | S45: =SUM(O45:R45) -> 0.195 | T45: 0.032 | U45: 0.092 | V45: 0.059 | W45: 0.122 | X45: =SUM(T45:W45) -> 0.305 | Y45: =0.01 -> 0.01 | Z45: -0.01 | AA45: 0.099 | AB45: 0.102 | AC45: 0.1983039 | AD45: 0.105 | AE45: 0.156 | AF45: 0.136 | AG45: =0.46-SUM(AD45:AF45) -> 0.063 | AH45: 0.68582109 | AI45: 0.044 | AJ45: 0.04 | AK45: 0.225 | AL45: 0.399 | AM45: =SUM(AI45:AL45) -> 0.708 | AN45: 0.02 | AO45: 0.074 | AP45: -0.285 | AQ45: 0.234 | AR45: =SUM(AN45:AQ45) -> 0.043 | AS45: -0.538 | AT45: -0.221 | AU45: 0 | AV45: -0.15 | AW45: =SUM(AS45:AV45) -> -0.909 | AX45: 0.044 | AY45: 0 | AZ45: 2.124 | BA45: 3.1 | BB45: =SUM(AX45:BA45) -> 5.268 | BC45: 1.9 | BD45: 3.4 | BE45: 2.6 | BF45: 1.3 | BG45: =SUM(BC45:BF45) -> 9.2 | BH45: =BH418 -> 1.3017817 | BI45: =BI418 -> 3.3550708 | BJ45: =BJ418 -> 3.3433209 | BK45: =BK418 -> 3.1192168 | BL45: =SUM(BH45:BK45) -> 11.11939 | BM45: =BM418 -> 2.460664 | BN45: =BN418 -> 4.385865 | BO45: =BO418 -> 4.1285554 | BP45: =BP418 -> 3.6436801 | BQ45: =SUM(BM45:BP45) -> 14.618764 | BR45: =BR418 -> 2.7015058 | BS45: =BS418 -> 4.667696 | BT45: =BT418 -> 4.3287483 | BU45: =BU418 -> 3.7486581 | BV45: =SUM(BR45:BU45) -> 15.446608 | BW45: =BW418 -> 2.688251 | BX45: =BX418 -> 4.9085526 | BY45: =BY418 -> 4.6945346 | BZ45: =BZ418 -> 4.2258027 | CA45: =SUM(BW45:BZ45) -> 16.517141 | CD45: =A45 -> Interest Income | CE45: =D45 -> 6.585 | CF45: =I45 -> 8.442 | CG45: =N45 -> 2.233 | CH45: =S45 -> 0.195 | CI45: =X45 -> 0.305 | CJ45: =AC45 -> 0.1983039 | CK45: =AH45 -> 0.68582109 | CL45: =AM45 -> 0.708 | CM45: =AR45 -> 0.043 | CN45: =AW45 -> -0.909 | CO45: =BB45 -> 5.268 | CP45: =BG45 -> 9.2 | CQ45: =BL45 -> 11.11939 | CR45: =BQ45 -> 14.618764 | CS45: =BV45 -> 15.446608 | CT45: =CA45 -> 16.517141
A46: Interest (Expense) | C46: -10.265 | D46: -16.668 | E46: -5.773 | F46: =-11.474-E46 -> -5.701 | G46: =-17.052-SUM(E46:F46) -> -5.578 | H46: =-22.928-SUM(E46:G46) -> -5.876 | I46: =SUM(E46:H46) -> -22.928 | J46: -6.326 | K46: =-14.173-J46 -> -7.847 | L46: =-22.566-SUM(J46:K46) -> -8.393 | M46: =-31.316-SUM(J46:L46) -> -8.75 | N46: =SUM(J46:M46) -> -31.316 | O46: -8.154 | P46: =-16.677-O46 -> -8.523 | Q46: =-9.449 -> -9.449 | R46: =-35.265-SUM(O46:Q46) -> -9.139 | S46: =SUM(O46:R46) -> -35.265 | T46: -8.466 | U46: -8.445 | V46: -8.484 | W46: =-9.269 -> -9.269 | X46: =SUM(T46:W46) -> -34.664 | Y46: -9.615 | Z46: -14.885 | AA46: -14.593 | AB46: -14.754 | AC46: =SUM(Y46:AB46) -> -53.847 | AD46: -16.385 | AE46: -17.377 | AF46: -18.133 | AG46: =-72.508-SUM(AD46:AF46) -> -20.613 | AH46: =SUM(AD46:AG46) -> -72.508 | AI46: -20.09 | AJ46: -19.704 | AK46: -18.692 | AL46: -17.65 | AM46: =SUM(AI46:AL46) -> -76.136 | AN46: -17.439 | AO46: =-17.459 -> -17.459 | AP46: -17.498 | AQ46: -17.588 | AR46: =SUM(AN46:AQ46) -> -69.984 | AS46: -18.262 | AT46: -37.662 | AU46: -33.003 | AV46: -32.389 | AW46: =SUM(AS46:AV46) -> -121.316 | AX46: -32.032 | AY46: -31.435 | AZ46: -28.15 | BA46: -28.4 | BB46: =SUM(AX46:BA46) -> -120.017 | BC46: -28.4 | BD46: -28.5 | BE46: -30.3 | BF46: -32.1 | BG46: -119.22476 | BH46: -33.156838 | BI46: -33.156838 | BJ46: -33.156838 | BK46: -33.156838 | BL46: -132.62735 | BM46: -33.156838 | BN46: -33.156838 | BO46: -33.156838 | BP46: -33.156838 | BQ46: -132.62735 | BR46: -33.156838 | BS46: -33.156838 | BT46: -33.156838 | BU46: -33.156838 | BV46: -132.62735 | BW46: -33.156838 | BX46: -33.156838 | BY46: -33.156838 | BZ46: -33.156838 | CA46: -132.62735 | CD46: =A46 -> Interest (Expense) | CE46: =D46 -> -16.668 | CF46: =I46 -> -22.928 | CG46: =N46 -> -31.316 | CH46: =S46 -> -35.265 | CI46: =X46 -> -34.664 | CJ46: =AC46 -> -53.847 | CK46: =AH46 -> -72.508 | CL46: =AM46 -> -76.136 | CM46: =AR46 -> -69.984 | CN46: =AW46 -> -121.316 | CO46: =BB46 -> -120.017 | CP46: =BG46 -> -119.22476 | CQ46: =BL46 -> -132.62735 | CR46: =BQ46 -> -132.62735 | CS46: =BV46 -> -132.62735 | CT46: =CA46 -> -132.62735
A47: Other Income (Expense) | C47: =0.027-0.014 -> 0.013 | D47: =-0.375-0.109 -> -0.484 | E47: =-0.018+0.012 -> -0.006 | F47: =0.592-0.021-E47 -> 0.577 | G47: =0.854-0.119-SUM(E47:F47) -> 0.164 | H47: =0.857+0.009-SUM(E47:G47) -> 0.131 | I47: =SUM(E47:H47) -> 0.866 | J47: -1.274 | K47: =-1.286-0.014-J47 -> -0.026 | L47: =-1.665-0.021-SUM(J47:K47) -> -0.386 | M47: =-2.511-0.049-SUM(J47:L47) -> -0.874 | N47: =SUM(J47:M47) -> -2.56 | O47: -0.398 | P47: =-0.365-O47 -> 0.033 | Q47: =0.024 -> 0.024 | R47: =-2.332-SUM(O47:Q47) -> -1.991 | S47: =SUM(O47:R47) -> -2.332 | T47: 0.032 | U47: 0.029 | V47: 0.009 | W47: =0.025 -> 0.025 | X47: =SUM(T47:W47) -> 0.095 | Y47: 0.362 | Z47: 0.125 | AA47: -0.086 | AB47: 0.285 | AC47: =SUM(Y47:AB47) -> 0.686 | AD47: 0.33 | AE47: -0.03 | AF47: -0.638 | AG47: =-0.332-SUM(AD47:AF47) -> 0.006 | AH47: =SUM(AD47:AG47) -> -0.332 | AI47: -0.193 | AJ47: 0.093 | AK47: 0 | AL47: 0.007 | AM47: =SUM(AI47:AL47) -> -0.093 | AN47: -0.011 | AO47: 0.126 | AP47: 0 | AQ47: 0 | AR47: =SUM(AN47:AQ47) -> 0.115 | AS47: 0 | AT47: 85.187 | AU47: 17.912 | AV47: 0 | AW47: =SUM(AS47:AV47) -> 103.099 | AX47: 0 | AY47: 0.846 | AZ47: 0 | BA47: 0 | BB47: =SUM(AX47:BA47) -> 0.846 | BC47: 0 | BD47: 0 | BE47: 0 | BF47: 0 | BG47: =SUM(BC47:BF47) -> 0 | BH47: 0 | BI47: 0 | BJ47: 0 | BK47: 0 | BL47: =SUM(BH47:BK47) -> 0 | BM47: 0 | BN47: 0 | BO47: 0 | BP47: 0 | BQ47: =SUM(BM47:BP47) -> 0 | BR47: 0 | BS47: 0 | BT47: 0 | BU47: 0 | BV47: =SUM(BR47:BU47) -> 0 | BW47: 0 | BX47: 0 | BY47: 0 | BZ47: 0 | CA47: =SUM(BW47:BZ47) -> 0 | CD47: =A47 -> Other Income (Expense) | CE47: =D47 -> -0.484 | CF47: =I47 -> 0.866 | CG47: =N47 -> -2.56 | CH47: =S47 -> -2.332 | CI47: =X47 -> 0.095 | CJ47: =AC47 -> 0.686 | CK47: =AH47 -> -0.332 | CL47: =AM47 -> -0.093 | CM47: =AR47 -> 0.115 | CN47: =AW47 -> 103.099 | CO47: =BB47 -> 0.846 | CP47: =BG47 -> 0 | CQ47: =BL47 -> 0 | CR47: =BQ47 -> 0 | CS47: =BV47 -> 0 | CT47: =CA47 -> 0
C48: ______ | D48: ______ | E48: ______ | F48: ______ | G48: ______ | H48: ______ | I48: ______ | J48: ______ | K48: ______ | L48: ______ | M48: ______ | N48: ______ | O48: ______ | P48: ______ | Q48: ______ | R48: ______ | S48: ______ | T48: ______ | U48: ______ | V48: ______ | W48: ______ | X48: ______ | Y48: ______ | Z48: ______ | AA48: ______ | AB48: ______ | AC48: ______ | AD48: ______ | AE48: ______ | AF48: ______ | AG48: ______ | AH48: ______ | AI48: ______ | AJ48: ______ | AK48: ______ | AL48: ______ | AM48: ______ | AN48: ______ | AO48: ______ | AP48: ______ | AQ48: ______ | AR48: ______ | AS48: ______ | AT48: ______ | AU48: ______ | AV48: ______ | AW48: ______ | AX48: ______ | AY48: ______ | AZ48: ______ | BA48: ______ | BB48: ______ | BC48: ______ | BD48: ______ | BE48: ______ | BF48: ______ | BG48: ______ | BH48: ______ | BI48: ______ | BJ48: ______ | BK48: ______ | BL48: ______ | BM48: ______ | BN48: ______ | BO48: ______ | BP48: ______ | BQ48: ______ | BR48: ______ | BS48: ______ | BT48: ______ | BU48: ______ | BV48: ______ | BW48: ______ | BX48: ______ | BY48: ______ | BZ48: ______ | CA48: ______
A49: Pretax Income | C49: =C42+C45+C46+C47 -> 212.669 | D49: =D42+D45+D46+D47 -> 232.777 | E49: =E42+E45+E46+E47 -> 63.738 | F49: =F42+F45+F46+F47 -> 64.899 | G49: =G42+G45+G46+G47 -> 68.015 | H49: =H42+H45+H46+H47 -> 61.495 | I49: =I42+I45+I46+I47 -> 258.147 | J49: =J42+J45+J46+J47 -> 70.902 | ... AQ49: =AQ42+AQ45+AQ46+AQ47 -> 159.693 | AR49: =SUM(AN49:AQ49) -> 590.62 | AS49: =AS42+AS45+AS46+AS47 -> 159.492 | AT49: =AT42+AT45+AT46+AT47 -> 201.026 | AU49: =AU42+AU45+AU46+AU47 -> 193.789 | AV49: =AV42+AV45+AV46+AV47 -> 162.879 | AW49: =SUM(AS49:AV49) -> 717.186 | AX49: =AX42+AX45+AX46+AX47 -> 160.641 | AY49: =AY42+AY45+AY46+AY47 -> 160.49 | AZ49: =AZ42+AZ45+AZ46+AZ47 -> 172.396 | BA49: =BA42+BA45+BA46+BA47 -> 160.2 | BB49: =SUM(AX49:BA49) -> 653.727 | BC49: =BC42+BC45+BC46+BC47 -> 161.2 | BD49: =BD42+BD45+BD46+BD47 -> 169.9 | BE49: =BE42+BE45+BE46+BE47 -> 180.7 | BF49: =BF42+BF45+BF46+BF47 -> 179.3 | BG49: =SUM(BC49:BF49) -> 691.1 | BH49: =BH42+BH45+BH46+BH47 -> 165.92621 | BI49: =BI42+BI45+BI46+BI47 -> 175.05972 | BJ49: =BJ42+BJ45+BJ46+BJ47 -> 192.28875 | BK49: =BK42+BK45+BK46+BK47 -> 191.93208 | BL49: =SUM(BH49:BK49) -> 725.20676 | BM49: =BM42+BM45+BM46+BM47 -> 184.19136 | BN49: =BN42+BN45+BN46+BN47 -> 193.84933 | BO49: =BO42+BO45+BO46+BO47 -> 211.99341 | BP49: =BP42+BP45+BP46+BP47 -> 211.66537 | BQ49: =SUM(BM49:BP49) -> 801.69946 | BR49: =BR42+BR45+BR46+BR47 -> 202.78071 | BS49: =BS42+BS45+BS46+BS47 -> 212.96566 | BT49: =BT42+BT45+BT46+BT47 -> 232.20278 | BU49: =BU42+BU45+BU46+BU47 -> 231.84382 | BV49: =SUM(BR49:BU49) -> 879.79297 | BW49: =BW42+BW45+BW46+BW47 -> 223.76869 | BX49: =BX42+BX45+BX46+BX47 -> 234.71948 | BY49: =BY42+BY45+BY46+BY47 -> 255.32998 | BZ49: =BZ42+BZ45+BZ46+BZ47 -> 255.14897 | CA49: =SUM(BW49:BZ49) -> 968.96713 | CD49: =A49 -> Pretax Income | CE49: =D49 -> 232.777 | CF49: =I49 -> 258.147 | CG49: =N49 -> 278.899 | CH49: =S49 -> 264.605 | CI49: =X49 -> 406.65 | CJ49: =AC49 -> 457.0543 | CK49: =AH49 -> 519.43382 | CL49: =AM49 -> 538.758 | CM49: =AR49 -> 590.62 | CN49: =AW49 -> 717.186 | CO49: =BB49 -> 653.727 | CP49: =BG49 -> 691.1 | CQ49: =BL49 -> 725.20676 | CR49: =BQ49 -> 801.69946 | CS49: =BV49 -> 879.79297 | CT49: =CA49 -> 968.96713
A50: Income Tax Benefit (Expense)- Reported | C50: -85.722 | D50: -91.992 | E50: -24.867 | F50: =-52.432-E50 -> -27.565 | G50: =-81.273-SUM(E50:F50) -> -28.841 | H50: =-103.184-SUM(E50:G50) -> -21.911 | I50: =SUM(E50:H50) -> -103.184 | J50: -29.876 | K50: =-61.818-J50 -> -31.942 | L50: =-90.311-SUM(J50:K50) -> -28.493 | M50: =-120.671-SUM(J50:L50) -> -30.36 | N50: =SUM(J50:M50) -> -120.671 | O50: -33.779 | P50: =-67.25-O50 -> -33.471 | Q50: -33.194 | R50: =-137.991-SUM(O50:Q50) -> -37.547 | S50: =SUM(O50:R50) -> -137.991 | T50: -42.637 | U50: -40.347 | V50: -42.422 | W50: -38.692 | X50: =SUM(T50:W50) -> -164.098 | Y50: -44.178 | Z50: -43.471 | AA50: -45.842 | AB50: -44.172 | AC50: =SUM(Y50:AB50) -> -177.663 | AD50: -48.41 | AE50: -47.82 | AF50: -53.705 | AG50: =-190.066-SUM(AD50:AF50) -> -40.131 | AH50: =SUM(AD50:AG50) -> -190.066 | AI50: -45.844 | AJ50: -45.68 | AK50: -53.474 | AL50: -51.428 | AM50: =SUM(AI50:AL50) -> -196.426 | AN50: -46.972 | AO50: -53.708 | AP50: =-AP49*AP380 -> -58.692 | AQ50: -60.383 | AR50: =SUM(AN50:AQ50) -> -219.755 | AS50: =-AS49*AS380 -> -60.806 | AT50: -37.706 | AU50: -61.975 | AV50: -49.372 | AW50: =SUM(AS50:AV50) -> -209.859 | AX50: -50.911 | AY50: -53.754 | AZ50: -44.819 | BA50: -52.7 | BB50: =SUM(AX50:BA50) -> -202.184 | BC50: -52.4 | BD50: -48.9 | BE50: -60 | BF50: 25.3 | BG50: =SUM(BC50:BF50) -> -136 | BH50: =-BH49*BH380 -> -36.503767 | BI50: =-BI49*BI380 -> -38.513138 | BJ50: =-BJ49*BJ380 -> -42.303526 | BK50: =-BK49*BK380 -> -42.225057 | BL50: =SUM(BH50:BK50) -> -159.54549 | BM50: =-BM49*BM380 -> -40.522099 | BN50: =-BN49*BN380 -> -42.646853 | BO50: =-BO49*BO380 -> -46.63855 | BP50: =-BP49*BP380 -> -46.566381 | BQ50: =SUM(BM50:BP50) -> -176.37388 | BR50: =-BR49*BR380 -> -44.611756 | BS50: =-BS49*BS380 -> -46.852446 | BT50: =-BT49*BT380 -> -51.084611 | BU50: =-BU49*BU380 -> -51.00564 | BV50: =SUM(BR50:BU50) -> -193.55445 | BW50: =-BW49*BW380 -> -49.229111 | BX50: =-BX49*BX380 -> -51.638285 | BY50: =-BY49*BY380 -> -56.172597 | BZ50: =-BZ49*BZ380 -> -56.132774 | CA50: =SUM(BW50:BZ50) -> -213.17277
A51: Income Tax Benefit (Expense)- Extraordinary income (expenses) | C51: 0 | D51: 0 | E51: 0 | F51: =0-E51 -> 0 | G51: 0 | H51: =0-SUM(E51:G51) -> 0 | I51: =SUM(E51:H51) -> 0 | J51: 0 | K51: =0-J51 -> 0 | L51: 0 | M51: =0-SUM(J51:L51) -> 0 | N51: =SUM(J51:M51) -> 0 | O51: 0 | P51: 0 | Q51: 0 | R51: 0 | S51: =SUM(O51:R51) -> 0 | T51: 0 | U51: 0 | V51: 0 | W51: 0 | X51: =SUM(T51:W51) -> 0 | Y51: 0 | Z51: 0 | AA51: 0 | AB51: 0 | AC51: =SUM(Y51:AB51) -> 0 | AD51: 0 | AE51: 0 | AF51: 0 | AG51: 0 | AH51: =SUM(AD51:AG51) -> 0 | AI51: 0 | AJ51: 0 | AK51: 0 | AL51: 0 | AM51: =SUM(AI51:AL51) -> 0 | AN51: 0 | AO51: 0 | AP51: 0 | AQ51: 0 | AR51: =SUM(AN51:AQ51) -> 0 | AS51: 0 | AT51: 0 | AU51: 0 | AV51: 0 | AW51: =SUM(AS51:AV51) -> 0 | AX51: 0 | AY51: 0 | AZ51: 0 | BA51: 0 | BB51: =SUM(AX51:BA51) -> 0 | BC51: 0 | BD51: 0 | BE51: 0 | BF51: 0 | BG51: =SUM(BC51:BF51) -> 0 | BH51: 0 | BI51: 0 | BJ51: 0 | BK51: 0 | BL51: =SUM(BH51:BK51) -> 0 | BM51: 0 | BN51: 0 | BO51: 0 | BP51: 0 | BQ51: =SUM(BM51:BP51) -> 0 | BR51: 0 | BS51: 0 | BT51: 0 | BU51: 0 | BV51: =SUM(BR51:BU51) -> 0 | BW51: 0 | BX51: 0 | BY51: 0 | BZ51: 0 | CA51: =SUM(BW51:BZ51) -> 0
A52: Income Tax Benefit (Expense) | C52: =SUM(C50:C51) -> -85.722 | D52: =SUM(D50:D51) -> -91.992 | E52: =SUM(E50:E51) -> -24.867 | F52: =SUM(F50:F51) -> -27.565 | G52: =SUM(G50:G51) -> -28.841 | H52: =SUM(H50:H51) -> -21.911 | I52: =SUM(I50:I51) -> -103.184 | J52: =SUM(J50:J51) -> -29.876 | ... AO52: =SUM(AO50:AO51) -> -53.708 | AP52: -58.692 | AQ52: =SUM(AQ50:AQ51) -> -60.383 | AR52: =SUM(AN52:AQ52) -> -219.755 | AS52: -60.806 | AT52: =SUM(AT50:AT51) -> -37.706 | AU52: =SUM(AU50:AU51) -> -61.975 | AV52: =SUM(AV50:AV51) -> -49.372 | AW52: =SUM(AS52:AV52) -> -209.859 | AX52: =SUM(AX50:AX51) -> -50.911 | AY52: =SUM(AY50:AY51) -> -53.754 | AZ52: =SUM(AZ50:AZ51) -> -44.819 | BA52: =SUM(BA50:BA51) -> -52.7 | BB52: =SUM(AX52:BA52) -> -202.184 | BC52: =SUM(BC50:BC51) -> -52.4 | BD52: =SUM(BD50:BD51) -> -48.9 | BE52: =SUM(BE50:BE51) -> -60 | BF52: =SUM(BF50:BF51) -> 25.3 | BG52: =SUM(BC52:BF52) -> -136 | BH52: =SUM(BH50:BH51) -> -36.503767 | BI52: =SUM(BI50:BI51) -> -38.513138 | BJ52: =SUM(BJ50:BJ51) -> -42.303526 | BK52: =SUM(BK50:BK51) -> -42.225057 | BL52: =SUM(BH52:BK52) -> -159.54549 | BM52: =SUM(BM50:BM51) -> -40.522099 | BN52: =SUM(BN50:BN51) -> -42.646853 | BO52: =SUM(BO50:BO51) -> -46.63855 | BP52: =SUM(BP50:BP51) -> -46.566381 | BQ52: =SUM(BM52:BP52) -> -176.37388 | BR52: =SUM(BR50:BR51) -> -44.611756 | BS52: =SUM(BS50:BS51) -> -46.852446 | BT52: =SUM(BT50:BT51) -> -51.084611 | BU52: =SUM(BU50:BU51) -> -51.00564 | BV52: =SUM(BR52:BU52) -> -193.55445 | BW52: =SUM(BW50:BW51) -> -49.229111 | BX52: =SUM(BX50:BX51) -> -51.638285 | BY52: =SUM(BY50:BY51) -> -56.172597 | BZ52: =SUM(BZ50:BZ51) -> -56.132774 | CA52: =SUM(BW52:BZ52) -> -213.17277 | CD52: =A52 -> Income Tax Benefit (Expense) | CE52: =D52 -> -91.992 | CF52: =I52 -> -103.184 | CG52: =N52 -> -120.671 | CH52: =S52 -> -137.991 | CI52: =X52 -> -164.098 | CJ52: =AC52 -> -177.663 | CK52: =AH52 -> -190.066 | CL52: =AM52 -> -196.426 | CM52: =AR52 -> -219.755 | CN52: =AW52 -> -209.859 | CO52: =BB52 -> -202.184 | CP52: =BG52 -> -136 | CQ52: =BL52 -> -159.54549 | CR52: =BQ52 -> -176.37388 | CS52: =BV52 -> -193.55445 | CT52: =CA52 -> -213.17277
C53: ______ | D53: ______ | E53: ______ | F53: ______ | G53: ______ | H53: ______ | I53: ______ | J53: ______ | K53: ______ | L53: ______ | M53: ______ | N53: ______ | O53: ______ | P53: ______ | Q53: ______ | R53: ______ | S53: ______ | T53: ______ | U53: ______ | V53: ______ | W53: ______ | X53: ______ | Y53: ______ | Z53: ______ | AA53: ______ | AB53: ______ | AC53: ______ | AD53: ______ | AE53: ______ | AF53: ______ | AG53: ______ | AH53: ______ | AI53: ______ | AJ53: ______ | AK53: ______ | AL53: ______ | AM53: ______ | AN53: ______ | AO53: ______ | AP53: ______ | AQ53: ______ | AR53: ______ | AS53: ______ | AT53: ______ | AU53: ______ | AV53: ______ | AW53: ______ | AX53: ______ | AY53: ______ | AZ53: ______ | BA53: ______ | BB53: ______ | BC53: ______ | BD53: ______ | BE53: ______ | BF53: ______ | BG53: ______ | BH53: ______ | BI53: ______ | BJ53: ______ | BK53: ______ | BL53: ______ | BM53: ______ | BN53: ______ | BO53: ______ | BP53: ______ | BQ53: ______ | BR53: ______ | BS53: ______ | BT53: ______ | BU53: ______ | BV53: ______ | BW53: ______ | BX53: ______ | BY53: ______ | BZ53: ______ | CA53: ______
A54: Net Income from Continuing Operations | C54: =C49+C52 -> 126.947 | D54: =D49+D52 -> 140.785 | E54: =E49+E52 -> 38.871 | F54: =F49+F52 -> 37.334 | G54: =G49+G52 -> 39.174 | H54: =H49+H52 -> 39.584 | I54: =I49+I52 -> 154.963 | J54: =J49+J52 -> 41.026 | ... AQ54: =AQ49+AQ52 -> 99.31 | AR54: =SUM(AN54:AQ54) -> 370.865 | AS54: =AS49+AS52 -> 98.686 | AT54: =AT49+AT52 -> 163.32 | AU54: =AU49+AU52 -> 131.814 | AV54: =AV49+AV52 -> 113.507 | AW54: =SUM(AS54:AV54) -> 507.327 | AX54: =AX49+AX52 -> 109.73 | AY54: =AY49+AY52 -> 106.736 | AZ54: =AZ49+AZ52 -> 127.577 | BA54: =BA49+BA52 -> 107.5 | BB54: =SUM(AX54:BA54) -> 451.543 | BC54: =BC49+BC52 -> 108.8 | BD54: =BD49+BD52 -> 121 | BE54: =BE49+BE52 -> 120.7 | BF54: =BF49+BF52 -> 204.6 | BG54: =SUM(BC54:BF54) -> 555.1 | BH54: =BH49+BH52 -> 129.42245 | BI54: =BI49+BI52 -> 136.54658 | BJ54: =BJ49+BJ52 -> 149.98523 | BK54: =BK49+BK52 -> 149.70702 | BL54: =SUM(BH54:BK54) -> 565.66128 | BM54: =BM49+BM52 -> 143.66926 | BN54: =BN49+BN52 -> 151.20248 | BO54: =BO49+BO52 -> 165.35486 | BP54: =BP49+BP52 -> 165.09899 | BQ54: =SUM(BM54:BP54) -> 625.32558 | BR54: =BR49+BR52 -> 158.16895 | BS54: =BS49+BS52 -> 166.11322 | BT54: =BT49+BT52 -> 181.11816 | BU54: =BU49+BU52 -> 180.83818 | BV54: =SUM(BR54:BU54) -> 686.23851 | BW54: =BW49+BW52 -> 174.53958 | BX54: =BX49+BX52 -> 183.08119 | BY54: =BY49+BY52 -> 199.15739 | BZ54: =BZ49+BZ52 -> 199.0162 | CA54: =SUM(BW54:BZ54) -> 755.79436 | CD54: =A54 -> Net Income from Continuing Operations | CE54: =D54 -> 140.785 | CF54: =I54 -> 154.963 | CG54: =N54 -> 158.228 | CH54: =S54 -> 126.614 | CI54: =X54 -> 242.552 | CJ54: =AC54 -> 279.3913 | CK54: =AH54 -> 329.36782 | CL54: =AM54 -> 342.332 | CM54: =AR54 -> 370.865 | CN54: =AW54 -> 507.327 | CO54: =BB54 -> 451.543 | CP54: =BG54 -> 555.1 | CQ54: =BL54 -> 565.66128 | CR54: =BQ54 -> 625.32558 | CS54: =BV54 -> 686.23851 | CT54: =CA54 -> 755.79436
A55: Income (loss) from Discontinued operations, net | C55: -2.574 | D55: -1.805 | E55: -0.61 | F55: =-1.302-E55 -> -0.692 | G55: =-3.322-SUM(E55:F55) -> -2.02 | H55: =-4.589-SUM(E55:G55) -> -1.267 | I55: =SUM(E55:H55) -> -4.589 | J55: 0 | K55: 0 | L55: 0 | M55: 0 | N55: =SUM(J55:M55) -> 0 | O55: 0 | P55: 0 | Q55: 0 | R55: 0 | S55: =SUM(O55:R55) -> 0 | T55: 0 | U55: 0 | V55: 0 | W55: 0 | X55: =SUM(T55:W55) -> 0 | Y55: 0 | Z55: 0 | AA55: 0 | AB55: 0 | AC55: =SUM(Y55:AB55) -> 0 | AD55: 0 | AE55: 0 | AF55: 0 | AG55: 0 | AH55: =SUM(AD55:AG55) -> 0 | AI55: 1.066 | AJ55: 2.605 | AK55: 1.547 | AL55: 0.848 | AM55: =SUM(AI55:AL55) -> 6.066 | AN55: 31.117 | AO55: 0 | AP55: 0 | AQ55: -1.94 | AR55: =SUM(AN55:AQ55) -> 29.177 | AS55: 0 | AT55: 0 | AU55: 0 | AV55: 0 | AW55: =SUM(AS55:AV55) -> 0 | AX55: =-18.871+1.78 -> -17.091 | AY55: 155 | AZ55: 0 | BA55: 1.8 | BB55: =SUM(AX55:BA55) -> 139.709 | BC55: 0 | BD55: 0 | BE55: 0 | BF55: 0 | BG55: =SUM(BC55:BF55) -> 0 | BH55: 0 | BI55: 0 | BJ55: 0 | BK55: 0 | BL55: =SUM(BH55:BK55) -> 0 | BM55: 0 | BN55: 0 | BO55: 0 | BP55: 0 | BQ55: =SUM(BM55:BP55) -> 0 | BR55: 0 | BS55: 0 | BT55: 0 | BU55: 0 | BV55: =SUM(BR55:BU55) -> 0 | BW55: 0 | BX55: 0 | BY55: 0 | BZ55: 0 | CA55: =SUM(BW55:BZ55) -> 0 | CD55: =A55 -> Income (loss) from Discontinued operations, net | CE55: =D55 -> -1.805 | CF55: =I55 -> -4.589 | CG55: =N55 -> 0 | CH55: =S55 -> 0 | CI55: =X55 -> 0 | CJ55: =AC55 -> 0 | CK55: =AH55 -> 0 | CL55: =AM55 -> 6.066 | CM55: =AR55 -> 29.177 | CN55: =AW55 -> 0 | CO55: =BB55 -> 139.709 | CP55: =BG55 -> 0 | CQ55: =BL55 -> 0 | CR55: =BQ55 -> 0 | CS55: =BV55 -> 0 | CT55: =CA55 -> 0
A56: Extraordinary (charges) / gains | C56: 0 | D56: 0 | E56: 0 | F56: =0-E56 -> 0 | G56: 0 | H56: 0 | I56: =SUM(E56:H56) -> 0 | J56: 0 | K56: 0 | L56: 0 | M56: 0 | N56: =SUM(J56:M56) -> 0 | O56: 0 | P56: 0 | Q56: 0 | R56: 0 | S56: =SUM(O56:R56) -> 0 | T56: 0 | U56: 0 | V56: 0 | W56: 0 | X56: =SUM(T56:W56) -> 0 | Y56: 0 | Z56: =Z24 -> 3.364 | AA56: 0 | AB56: 0 | AC56: =SUM(Y56:AB56) -> 3.364 | AD56: 0 | AE56: 0 | AF56: 0 | AG56: 0 | AH56: =SUM(AD56:AG56) -> 0 | AI56: 0 | AJ56: 0 | AK56: 0 | AL56: 0 | AM56: =SUM(AI56:AL56) -> 0 | AN56: 0 | AO56: 0 | AP56: 0 | AQ56: 0 | AR56: =SUM(AN56:AQ56) -> 0 | AS56: 0 | AT56: =-45.2-10.7 -> -55.9 | AU56: 0 | AV56: 0 | AW56: =SUM(AS56:AV56) -> -55.9 | AX56: 0 | AY56: 0 | AZ56: 0 | BA56: 0 | BB56: =SUM(AX56:BA56) -> 0 | BC56: 0 | BD56: 0 | BE56: 0 | BF56: 0 | BG56: =SUM(BC56:BF56) -> 0 | BH56: 0 | BI56: 0 | BJ56: 0 | BK56: 0 | BL56: =SUM(BH56:BK56) -> 0 | BM56: 0 | BN56: 0 | BO56: 0 | BP56: 0 | BQ56: =SUM(BM56:BP56) -> 0 | BR56: 0 | BS56: 0 | BT56: 0 | BU56: 0 | BV56: =SUM(BR56:BU56) -> 0 | BW56: 0 | BX56: 0 | BY56: 0 | BZ56: 0 | CA56: =SUM(BW56:BZ56) -> 0 | CD56: =A56 -> Extraordinary (charges) / gains | CE56: =D56 -> 0 | CF56: =I56 -> 0 | CG56: =N56 -> 0 | CH56: =S56 -> 0 | CI56: =X56 -> 0 | CJ56: =AC56 -> 3.364 | CK56: =AH56 -> 0 | CL56: =AM56 -> 0 | CM56: =AR56 -> 0 | CN56: =AW56 -> -55.9 | CO56: =BB56 -> 0 | CP56: =BG56 -> 0 | CQ56: =BL56 -> 0 | CR56: =BQ56 -> 0 | CS56: =BV56 -> 0 | CT56: =CA56 -> 0
C57: ______ | D57: ______ | E57: ______ | F57: ______ | G57: ______ | H57: ______ | I57: ______ | J57: ______ | K57: ______ | L57: ______ | M57: ______ | N57: ______ | O57: ______ | P57: ______ | Q57: ______ | R57: ______ | S57: ______ | T57: ______ | U57: ______ | V57: ______ | W57: ______ | X57: ______ | Y57: ______ | Z57: ______ | AA57: ______ | AB57: ______ | AC57: ______ | AD57: ______ | AE57: ______ | AF57: ______ | AG57: ______ | AH57: ______ | AI57: ______ | AJ57: ______ | AK57: ______ | AL57: ______ | AM57: ______ | AN57: ______ | AO57: ______ | AP57: ______ | AQ57: ______ | AR57: ______ | AS57: ______ | AT57: ______ | AU57: ______ | AV57: ______ | AW57: ______ | AX57: ______ | AY57: ______ | AZ57: ______ | BA57: ______ | BB57: ______ | BC57: ______ | BD57: ______ | BE57: ______ | BF57: ______ | BG57: ______ | BH57: ______ | BI57: ______ | BJ57: ______ | BK57: ______ | BL57: ______ | BM57: ______ | BN57: ______ | BO57: ______ | BP57: ______ | BQ57: ______ | BR57: ______ | BS57: ______ | BT57: ______ | BU57: ______ | BV57: ______ | BW57: ______ | BX57: ______ | BY57: ______ | BZ57: ______ | CA57: ______
A58: Net Income to Common Stockholders | C58: =SUM(C54:C56) -> 124.373 | D58: =SUM(D54:D56) -> 138.98 | E58: =SUM(E54:E56) -> 38.261 | F58: =SUM(F54:F56) -> 36.642 | G58: =SUM(G54:G56) -> 37.154 | H58: =SUM(H54:H56) -> 38.317 | I58: =SUM(I54:I56) -> 150.374 | J58: =SUM(J54:J56) -> 41.026 | ... AQ58: =SUM(AQ54:AQ56) -> 97.37 | AR58: =SUM(AN58:AQ58) -> 400.042 | AS58: =SUM(AS54:AS56) -> 98.686 | AT58: =SUM(AT54:AT56)-AT56 -> 163.32 | AU58: =SUM(AU54:AU56) -> 131.814 | AV58: =SUM(AV54:AV56) -> 113.507 | AW58: =SUM(AS58:AV58) -> 507.327 | AX58: =SUM(AX54:AX56) -> 92.639 | AY58: =SUM(AY54:AY56) -> 261.736 | AZ58: =SUM(AZ54:AZ56) -> 127.577 | BA58: =SUM(BA54:BA56) -> 109.3 | BB58: =SUM(AX58:BA58) -> 591.252 | BC58: =SUM(BC54:BC56) -> 108.8 | BD58: =SUM(BD54:BD56) -> 121 | BE58: =SUM(BE54:BE56) -> 120.7 | BF58: =SUM(BF54:BF56) -> 204.6 | BG58: =SUM(BC58:BF58) -> 555.1 | BH58: =SUM(BH54:BH56) -> 129.42245 | BI58: =SUM(BI54:BI56) -> 136.54658 | BJ58: =SUM(BJ54:BJ56) -> 149.98523 | BK58: =SUM(BK54:BK56) -> 149.70702 | BL58: =SUM(BH58:BK58) -> 565.66128 | BM58: =SUM(BM54:BM56) -> 143.66926 | BN58: =SUM(BN54:BN56) -> 151.20248 | BO58: =SUM(BO54:BO56) -> 165.35486 | BP58: =SUM(BP54:BP56) -> 165.09899 | BQ58: =SUM(BM58:BP58) -> 625.32558 | BR58: =SUM(BR54:BR56) -> 158.16895 | BS58: =SUM(BS54:BS56) -> 166.11322 | BT58: =SUM(BT54:BT56) -> 181.11816 | BU58: =SUM(BU54:BU56) -> 180.83818 | BV58: =SUM(BR58:BU58) -> 686.23851 | BW58: =SUM(BW54:BW56) -> 174.53958 | BX58: =SUM(BX54:BX56) -> 183.08119 | BY58: =SUM(BY54:BY56) -> 199.15739 | BZ58: =SUM(BZ54:BZ56) -> 199.0162 | CA58: =SUM(BW58:BZ58) -> 755.79436 | CD58: =A58 -> Net Income to Common Stockholders | CE58: =D58 -> 138.98 | CF58: =I58 -> 150.374 | CG58: =N58 -> 158.228 | CH58: =S58 -> 126.614 | CI58: =X58 -> 242.552 | CJ58: =AC58 -> 282.7553 | CK58: =AH58 -> 329.36782 | CL58: =AM58 -> 348.398 | CM58: =AR58 -> 400.042 | CN58: =AW58 -> 507.327 | CO58: =BB58 -> 591.252 | CP58: =BG58 -> 555.1 | CQ58: =BL58 -> 565.66128 | CR58: =BQ58 -> 625.32558 | CS58: =BV58 -> 686.23851 | CT58: =CA58 -> 755.79436
A59: Adj. Net Income (excl. ESOP & extraordinary items) | C59: =C58+C24 -> 124.373 | D59: =D58+D24 -> 150.712 | E59: =E58+E24 -> 38.261 | F59: =F58+F24 -> 36.642 | G59: =G58+G24 -> 37.154 | H59: =H58+H24 -> 38.317 | I59: =I58+I24 -> 164.178 | J59: =J58+J24 -> 44.192 | ... Y59: =Y58+Y24 -> 65.876 | Z59: =Z58+Z24-Z56 -> 65.577 | AA59: =AA58+AA24 -> 70.987 | AB59: =AB58+AB24 -> 80.318 | AC59: =AC58+AC24-AC56 -> 282.7553 | AD59: =AD58+AD24 -> 74.166 | AE59: =AE58+AE24 -> 73.205 | AF59: =AF58+AF24-AF56 -> 83.413 | AG59: =AG58+AG24 -> 98.23 | AH59: =AH58+AH24 -> 329.23982 | AI59: =AI58+AI24 -> 80.656 | AJ59: =AJ58+AJ24 -> 84.096 | AK59: =AK58+AK24 -> 96.213 | AL59: =AL58+AL24 -> 88.068 | AM59: =AM58+AM24 -> 349.033 | AN59: =AN58+AN24 -> 115.549 | ... AQ59: =AQ58+AQ24 -> 97.136 | AR59: =SUM(AN59:AQ59) -> 399.884 | AS59: =AS58+AS24 -> 99.286 | AT59: =AT58+AT24 -> 136.924 | AU59: =AU58+AU24 -> 113.902 | AV59: =AV58+AV24 -> 113.607 | AW59: =SUM(AS59:AV59) -> 463.719 | AX59: =AX58+AX24 -> 92.851 | AY59: =AY58+AY24 -> 262.582 | AZ59: =AZ58+AZ24 -> 130.277 | BA59: =BA58+BA24 -> 131.2 | BB59: =SUM(AX59:BA59) -> 616.91 | BC59: =BC58+BC24 -> 110.7 | BD59: =BD58+BD24 -> 124.4 | BE59: =BE58+BE24 -> 123.3 | BF59: =BF58+BF24 -> 206.3 | BG59: =SUM(BC59:BF59) -> 564.7 | BH59: =BH58+BH24 -> 129.42245 | BI59: =BI58+BI24 -> 136.54658 | BJ59: =BJ58+BJ24 -> 149.98523 | BK59: =BK58+BK24 -> 149.70702 | BL59: =SUM(BH59:BK59) -> 565.66128 | BM59: =BM58+BM24 -> 143.66926 | BN59: =BN58+BN24 -> 151.20248 | BO59: =BO58+BO24 -> 165.35486 | BP59: =BP58+BP24 -> 165.09899 | BQ59: =SUM(BM59:BP59) -> 625.32558 | BR59: =BR58+BR24 -> 158.16895 | BS59: =BS58+BS24 -> 166.11322 | BT59: =BT58+BT24 -> 181.11816 | BU59: =BU58+BU24 -> 180.83818 | BV59: =SUM(BR59:BU59) -> 686.23851 | BW59: =BW58+BW24 -> 174.53958 | BX59: =BX58+BX24 -> 183.08119 | BY59: =BY58+BY24 -> 199.15739 | BZ59: =BZ58+BZ24 -> 199.0162 | CA59: =SUM(BW59:BZ59) -> 755.79436 | CD59: =A59 -> Adj. Net Income (excl. ESOP & extraordinary items) | CE59: =D59 -> 150.712 | CF59: =I59 -> 164.178 | CG59: =N59 -> 170.791 | CH59: =S59 -> 200.884 | CI59: =X59 -> 242.552 | CJ59: =AC59 -> 282.7553 | CK59: =AH59 -> 329.23982 | CL59: =AM59 -> 349.033 | CM59: =AR59 -> 399.884 | CN59: =AW59 -> 463.719 | CO59: =BB59 -> 616.91 | CP59: =BG59 -> 564.7 | CQ59: =BL59 -> 565.66128 | CR59: =BQ59 -> 625.32558 | CS59: =BV59 -> 686.23851 | CT59: =CA59 -> 755.79436
A60: Tax Effect of amortization add back | Y60: =-Y59-Y39+Y61 -> -3.382 | Z60: =-Z59-Z39+Z61 -> -3.551 | AA60: =-AA59-AA39+AA61 -> -3.519 | AB60: =-AB59-AB39+AB61 -> -3.499852 | AC60: =-AC59-AC39+AC61 -> -13.949156 | AD60: =-AD59-AD39+AD61 -> -3.074146 | AE60: =-AE59-AE39+AE61 -> -4.8748 | AF60: =-AF59-AF39+AF61 -> -6.678 | ... AP60: =-AP59-AP39+AP61 -> -5.461995 | AQ60: -5.415 | AR60: =-AR59-AR39+AR61 -> -19.86288 | AS60: -5.3 | AT60: =-7.6+0.05 -> -7.55 | AU60: -4.8 | AV60: -8.6 | AW60: =-AW59-AW39+AW61 -> -38.542 | AX60: -6.2 | AY60: -6.3 | AZ60: -5.9 | BA60: =-(5.8+7.2) -> -13 | BB60: =SUM(AX60:BA60) -> -31.4 | BC60: -5.8 | BD60: -6.3 | BE60: -7.1 | BF60: -7.3 | BG60: =-BG59-BG39+BG61 -> -36.1 | BH60: =-BH381*BH39 -> -6.77775 | BI60: =-BI381*BI39 -> -6.77775 | BJ60: =-BJ381*BJ39 -> -6.77775 | BK60: =-BK381*BK39 -> -6.77775 | BL60: =-BL59-BL39+BL61 -> -33.566 | BM60: =-BM381*BM39 -> -6.7305 | BN60: =-BN381*BN39 -> -6.7305 | BO60: =-BO381*BO39 -> -6.7305 | BP60: =-BP381*BP39 -> -6.7305 | BQ60: =-BQ59-BQ39+BQ61 -> -33.332 | BR60: =-BR381*BR39 -> -6.615 | BS60: =-BS381*BS39 -> -6.615 | BT60: =-BT381*BT39 -> -6.615 | BU60: =-BU381*BU39 -> -6.615 | BV60: =-BV59-BV39+BV61 -> -32.76 | BW60: =-BW381*BW39 -> -6.06375 | BX60: =-BX381*BX39 -> -6.06375 | BY60: =-BY381*BY39 -> -6.06375 | BZ60: =-BZ381*BZ39 -> -6.06375 | CA60: =-CA59-CA39+CA61 -> -30.03 | CD60: =A60 -> Tax Effect of amortization add back | CJ60: =AC60 -> -13.949156 | CK60: =AH60 -> -21.796767 | CL60: =AM60 -> -30.0548 | CM60: =AR60 -> -19.86288 | CN60: =AW60 -> -38.542 | CO60: =BB60 -> -31.4 | CP60: =BG60 -> -36.1 | CQ60: =BL60 -> -33.566 | CR60: =BQ60 -> -33.332 | CS60: =BV60 -> -32.76 | CT60: =CA60 -> -30.03
A61: Adjusted Net Income | C61: =C59+(C39*(1-C375)) -> 136.2926 | D61: =D59+(D39*(1-D375)) -> 166.66366 | E61: =E59+(E39*(1-E375)) -> 43.517081 | F61: =F59+(F39*(1-F375)) -> 41.541118 | G61: =G59+(G39*(1-G375)) -> 41.703812 | H61: =H59+(H39*(1-H375)) -> 43.590163 | I61: =I59+(I39*(1-I375)) -> 184.15617 | J61: =J59+(J39*(1-J375)) -> 48.799534 | ... N61: =N59+(N39*(1-N375)) -> 187.72617 | O61: =O59+(O39-3.553) -> 52.705 | P61: =P59+(P39-3.534) -> 54.629 | Q61: =Q59+(Q39-3.345) -> 53.848 | R61: =(R59+(R39-3.187))+1.172 -> 59.9 | S61: =S59+(S39-13.619)+1.172 -> 221.058 | T61: =(T59+(T39-2.995))+2.362 -> 62.046 | U61: =U59+(U39-2.878) -> 62.546 | V61: =V59+((V39+0.544-2.525)) -> 66.513 | W61: =W59+(W39-2.835) -> 69.974 | X61: =X59+((X39+0.544-11.233))+2.362 -> 261.079 | Y61: =Y59+(Y39-3.382) -> 70.949 | Z61: =Z59+(Z39-3.551) -> 70.903 | AA61: =AA59+(AA39-3.519) -> 76.265 | AB61: =AB59+(AB39*(1-AB375)) -> 85.481148 | AC61: =SUM(Y61:AB61) -> 303.59815 | AD61: =AD59+(AD39*(1-AD375)) -> 79.678854 | AE61: =AE59+(AE39*(1-AE375)) -> 80.5172 | AF61: =AF58+(AF39-6.176) -> 92.177 | AG61: =AG59+(AG39-6.944) -> 108.645 | AH61: =SUM(AD61:AG61) -> 361.01805 | AI61: =AI59+(AI39*(1-AI375)) -> 90.8872 | AJ61: 92.178 | AK61: 104.354 | AL61: 95.3 | AM61: =SUM(AI61:AL61) -> 382.7192 | AN61: =AN59+(AN39*(1-AN375)) -> 124.0762 | AO61: =AO59+(AO39*(1-AO375)) -> 96.644915 | AP61: =AP59+(AP39*(1-AP375)) -> 108.02501 | AQ61: =AQ58+AQ39+AQ60-AQ55 -> 108.145 | AR61: =SUM(AN61:AQ61) -> 436.89112 | AS61: =AS58+AS39+AS60-AS55 -> 107.527 | AT61: =AT58+AT39+AT60-AT55+AT56 -> 128.682 | AU61: =AU58+AU39+AU60-AU55+AU56 -> 145.557 | AV61: =AV58+AV39+AV60-AV55+AV56 -> 138.54 | AW61: =SUM(AS61:AV61) -> 520.306 | AX61: =AX58+AX39+AX60-AX55 -> 127.401 | AY61: =AY58+AY39+AY60-AY55 -> 124.242 | AZ61: =AZ58+AZ39+AZ60-AZ55 -> 144.356 | BA61: =BA58+BA39+BA60-BA55+18.8 -> 135.4 | BB61: =SUM(AX61:BA61) -> 531.399 | BC61: =BC58+BC39+BC60-BC55 -> 125.3 | BD61: =BD58+BD39+BD60-BD55 -> 138.6 | BE61: =BE58+BE39+BE60-BE55 -> 141.1 | BF61: =BF58+BF39+BF60-BF55 -> 225.4 | BG61: =SUM(BC61:BF61) -> 630.4 | BH61: =BH59+(BH39*(1-0.26)) -> 153.30595 | BI61: =BI59+(BI39*(1-0.26)) -> 160.43008 | BJ61: =BJ59+(BJ39*(1-0.26)) -> 173.86873 | BK61: =BK59+(BK39*(1-0.26)) -> 173.59052 | BL61: =SUM(BH61:BK61) -> 661.19528 | BM61: =BM59+(BM39*(1-0.26)) -> 167.38626 | BN61: =BN59+(BN39*(1-0.26)) -> 174.91948 | BO61: =BO59+(BO39*(1-0.26)) -> 189.07186 | BP61: =BP59+(BP39*(1-0.26)) -> 188.81599 | BQ61: =SUM(BM61:BP61) -> 720.19358 | BR61: =BR59+(BR39*(1-0.26)) -> 181.47895 | BS61: =BS59+(BS39*(1-0.26)) -> 189.42322 | BT61: =BT59+(BT39*(1-0.26)) -> 204.42816 | BU61: =BU59+(BU39*(1-0.26)) -> 204.14818 | BV61: =SUM(BR61:BU61) -> 779.47851 | BW61: =BW59+(BW39*(1-0.26)) -> 195.90708 | BX61: =BX59+(BX39*(1-0.26)) -> 204.44869 | BY61: =BY59+(BY39*(1-0.26)) -> 220.52489 | BZ61: =BZ59+(BZ39*(1-0.26)) -> 220.3837 | CA61: =SUM(BW61:BZ61) -> 841.26436 | CB61: =(CA61/BG61)^(1/4)-1 -> 0.074803498 | CD61: =A61 -> Adjusted Net Income | CE61: =D61 -> 166.66366 | CF61: =I61 -> 184.15617 | CG61: =N61 -> 187.72617 | CH61: =S61 -> 221.058 | CI61: =X61 -> 261.079 | CJ61: =AC61 -> 303.59815 | CK61: =AH61 -> 361.01805 | CL61: =AM61 -> 382.7192 | CM61: =AR61 -> 436.89112 | CN61: =AW61 -> 520.306 | CO61: =BB61 -> 531.399 | CP61: =BG61 -> 630.4 | CQ61: =BL61 -> 661.19528 | CR61: =BQ61 -> 720.19358 | CS61: =BV61 -> 779.47851 | CT61: =CA61 -> 841.26436
A63: Basic Shares Outstanding | D63: =(2.9459+1.34754)*50 -> 214.672 | H63: =(2.873412+1.163066)*50 -> 201.8239 | I63: =H63 -> 201.8239 | K63: =(2.863742+0.946518)*50 -> 190.513 | L63: =(2.863742+0.887844)*50 -> 187.5793 | M63: =(2.863742+0.746139)*50 -> 180.49405 | N63: =M63 -> 180.49405 | O63: =(2.863742+0.713523)*50 -> 178.86325 | P63: =(2.863742+0.700188)*50 -> 178.1965 | Q63: 172.7964 | R63: =126.373495+27.118975*2 -> 180.61145 | S63: =R63 -> 180.61145 | T63: =126.373495+27.118975*2 -> 180.61145 | U63: =124.731552+27.118975*2 -> 178.9695 | V63: =125.404054+27.118975*2 -> 179.642 | W63: =143.107036+12.22548+14.77134 -> 170.10386 | X63: =W63 -> 170.10386 | Y63: =152.557291+14.77134 -> 167.32863 | Z63: =150.042965+14.77134 -> 164.81431 | AA63: 163.5401 | AB63: 164.79106 | AC63: =AC436 -> 164.79106 | AD63: 166.06601 | AE63: 165.83356 | AF63: 166.79852 | AG63: 166.79852 | AH63: =AH436 -> 166.79852 | AI63: 168.3953 | AJ63: 167.91545 | AK63: 168.22059 | AL63: 167.45793 | AM63: =AM436 -> 167.45793 | AN63: 166.53111 | AO63: 166.47513 | AP63: =544.003038-378.440138 -> 165.5629 | AQ63: 158.10845 | AR63: =+AQ63 -> 158.10845 | AS63: 158.46589 | AT63: 168.48674 | AU63: 169.104 | AV63: 169.42498 | AW63: =+AV63 -> 169.42498 | AX63: =AX64*2-AV63 -> 167.57502 | AY63: =AY436 -> 167.71808 | AZ63: =AZ436 -> 167.10409 | BA63: =BA436 -> 165.43157 | BB63: =+BA63 -> 165.43157 | BC63: 167.57502 | BD63: =BD436 -> 165.77462 | BE63: =BE436 -> 165.69648 | BF63: =BF436 -> 165.78919 | BG63: =+BF63 -> 165.78919 | BH63: =BH436 -> 164.44854 | BI63: =BI436 -> 163.1339 | BJ63: =BJ436 -> 161.84478 | BK63: =BK436 -> 160.58068 | BL63: =+BK63 -> 160.58068 | BM63: =BM436 -> 158.92793 | BN63: =BN436 -> 157.30725 | BO63: =BO436 -> 155.71803 | BP63: =BP436 -> 154.15964 | BQ63: =+BP63 -> 154.15964 | BR63: =BR436 -> 152.4132 | BS63: =BS436 -> 150.70066 | BT63: =BT436 -> 149.02135 | BU63: =BU436 -> 147.37463 | BV63: =+BU63 -> 147.37463 | BW63: =BW436 -> 145.75987 | BX63: =BX436 -> 144.17646 | BY63: =BY436 -> 142.62377 | BZ63: =BZ436 -> 141.10122 | CA63: =+BZ63 -> 141.10122 | CD63: =A63 -> Basic Shares Outstanding | CE63: =D63 -> 214.672 | CF63: =I63 -> 201.8239 | CG63: =N63 -> 180.49405 | CH63: =S63 -> 180.61145 | CI63: =X63 -> 170.10386 | CJ63: =AC63 -> 164.79106 | CK63: =AH63 -> 166.79852 | CL63: =AM63 -> 167.45793 | CM63: =AR63 -> 158.10845 | CN63: =AW63 -> 169.42498 | CO63: =BB63 -> 165.43157 | CP63: =BG63 -> 165.78919 | CQ63: =BL63 -> 160.58068 | CR63: =BQ63 -> 154.15964 | CS63: =BV63 -> 147.37463 | CT63: =CA63 -> 141.10122
A64: Average Basic Shares Outstanding | C64: =4.258989*50 -> 212.94945 | D64: =4.130962*50 -> 206.5481 | E64: =4.09632*50 -> 204.816 | F64: =4.077259*50 -> 203.86295 | G64: =4.04946*50 -> 202.473 | H64: =4.016928*50 -> 200.8464 | I64: =4.016928*50 -> 200.8464 | J64: =3.759913*50 -> 187.99565 | K64: =3.724876*50 -> 186.2438 | L64: =3.698519*50 -> 184.92595 | M64: 182.8857 | N64: 182.8857 | O64: 173.938 | P64: 172.88733 | Q64: 172.7964 | R64: 179.54563 | S64: 174.7678 | T64: 180.05355 | U64: 180.49211 | V64: 178.68724 | W64: 171.70112 | X64: 177.7335 | Y64: 169.03023 | Z64: 166.96081 | AA64: =164.195325 -> 164.19532 | AB64: 163.87459 | AC64: =AVERAGE(AC63,X63) -> 167.44746 | AD64: 164.83699 | AE64: 165.94601 | AF64: 165.97808 | AG64: 166.8 | AH64: =AVERAGE(AH63,AC63) -> 165.79479 | AI64: 168.07859 | AJ64: 168.14707 | AK64: 168.0441 | AL64: 167.85589 | AM64: =AVERAGE(AI63:AL63) -> 167.99732 | AN64: 166.98198 | AO64: 166.34363 | AP64: 166.18754 | AQ64: 163.78206 | AR64: 165.8238 | AS64: 158.08792 | AT64: 164.1418 | AU64: 168.73944 | AV64: 169.39236 | AW64: =AVERAGE(AS64:AV64) -> 165.09038 | AX64: 168.5 | AY64: 168.3 | AZ64: =AVERAGE(AY63:AZ63) -> 167.41108 | BA64: 167.4 | BB64: =AVERAGE(AX64:BA64) -> 167.90277 | BC64: 166.44299 | BD64: 164.9 | BE64: 164.57757 | BF64: 164.73009 | BG64: =AVERAGE(BC64:BF64) -> 165.16266 | BH64: =AVERAGE(BG63:BH63) -> 165.11886 | BI64: =AVERAGE(BH63:BI63) -> 163.79122 | BJ64: =AVERAGE(BI63:BJ63) -> 162.48934 | BK64: =AVERAGE(BJ63:BK63) -> 161.21273 | BL64: =AVERAGE(BH64:BK64) -> 163.15304 | BM64: =AVERAGE(BL63:BM63) -> 159.75431 | BN64: =AVERAGE(BM63:BN63) -> 158.11759 | BO64: =AVERAGE(BN63:BO63) -> 156.51264 | BP64: =AVERAGE(BO63:BP63) -> 154.93883 | BQ64: =AVERAGE(BM64:BP64) -> 157.33084 | BR64: =AVERAGE(BQ63:BR63) -> 153.28642 | BS64: =AVERAGE(BR63:BS63) -> 151.55693 | BT64: =AVERAGE(BS63:BT63) -> 149.861 | BU64: =AVERAGE(BT63:BU63) -> 148.19799 | BV64: =AVERAGE(BR64:BU64) -> 150.72559 | BW64: =AVERAGE(BV63:BW63) -> 146.56725 | BX64: =AVERAGE(BW63:BX63) -> 144.96816 | BY64: =AVERAGE(BX63:BY63) -> 143.40011 | BZ64: =AVERAGE(BY63:BZ63) -> 141.86249 | CA64: =AVERAGE(BW64:BZ64) -> 144.19951 | CD64: =A64 -> Average Basic Shares Outstanding | CE64: =D64 -> 206.5481 | CF64: =I64 -> 200.8464 | CG64: =N64 -> 182.8857 | CH64: =S64 -> 174.7678 | CI64: =X64 -> 177.7335 | CJ64: =AC64 -> 167.44746 | CK64: =AH64 -> 165.79479 | CL64: =AM64 -> 167.99732 | CM64: =AR64 -> 165.8238 | CN64: =AW64 -> 165.09038 | CO64: =BB64 -> 167.90277 | CP64: =BG64 -> 165.16266 | CQ64: =BL64 -> 163.15304 | CR64: =BQ64 -> 157.33084 | CS64: =BV64 -> 150.72559 | CT64: =CA64 -> 144.19951
A65: Diluted Shares Outstanding | C65: =4.462109*50 -> 223.10545 | D65: =4.302867*50 -> 215.14335 | E65: =4.269444*50 -> 213.4722 | F65: =4.240053*50 -> 212.00265 | G65: =4.212518*50 -> 210.6259 | H65: =4.185151*50 -> 209.25755 | I65: =4.185151*50 -> 209.25755 | J65: =3.926954*50 -> 196.3477 | K65: =193.8953*2-J65 -> 191.4429 | L65: =(3.849873*50)*3-K65-J65 -> 189.69035 | M65: =(3.804634*50)*4-L65-K65-J65 -> 183.44585 | N65: =3.804634*50 -> 190.2317 | O65: 180.60445 | P65: 179.82448 | Q65: 179.85085 | R65: 188.47902 | S65: 182.16566 | T65: 189.45476 | U65: 189.54189 | V65: 187.18867 | W65: 179.39453 | X65: 186.39496 | Y65: 176.96419 | Z65: 174.63405 | AA65: 171.16966 | AB65: 170.53254 | AC65: =AB65 -> 170.53254 | AD65: 171.35082 | AE65: 171.90135 | AF65: 171.66054 | AG65: 171.9 | AH65: =AG65 -> 171.9 | AI65: 172.76064 | AJ65: 172.46769 | AK65: 172.15455 | AL65: 171.72256 | AM65: =AL65 -> 171.72256 | AN65: 170.42149 | AO65: =169.503664 -> 169.50366 | AP65: 169.52245 | AQ65: 167.08209 | AR65: 169.13242 | AS65: 161.48121 | AT65: =AT67*2-AS65 -> 173.69099 | AU65: =AU67*2-AT65 -> 170.65169 | AV65: =AV67*2-AU65 -> 174.48176 | AW65: =AVERAGE(AS65:AV65) -> 170.07641 | AX65: 171.5 | AY65: 171.2 | AZ65: 171.7859 | BA65: 170.2 | BB65: =AVERAGE(AX65:BA65) -> 171.17147 | BC65: 170.15086 | BD65: 168.3 | BE65: 167.95706 | BF65: 168.33326 | BG65: =AVERAGE(BC65:BF65) -> 168.68529 | BH65: =BH63*BG65/BG63 -> 167.32122 | BI65: =BI63*BH65/BH63 -> 165.98362 | BJ65: =BJ63*BI65/BI63 -> 164.67198 | BK65: =BK63*BJ65/BJ63 -> 163.3858 | BL65: =AVERAGE(BH65:BK65) -> 165.34066 | BM65: =BM63*BL65/BL63 -> 163.63891 | BN65: =BN63*BM65/BM63 -> 161.97019 | BO65: =BO63*BN65/BN63 -> 160.33386 | BP65: =BP63*BO65/BO63 -> 158.72928 | BQ65: =AVERAGE(BM65:BP65) -> 161.16806 | BR65: =BR63*BQ65/BQ63 -> 159.34222 | BS65: =BS63*BR65/BR63 -> 157.55182 | BT65: =BT63*BS65/BS63 -> 155.79617 | BU65: =BU63*BT65/BT63 -> 154.07459 | BV65: =AVERAGE(BR65:BU65) -> 156.6912 | BW65: =BW63*BV65/BV63 -> 154.97436 | BX65: =BX63*BW65/BW63 -> 153.29085 | BY65: =BY63*BX65/BX63 -> 151.64 | BZ65: =BZ63*BY65/BY63 -> 150.0212 | CA65: =AVERAGE(BW65:BZ65) -> 152.4816 | CD65: =A65 -> Diluted Shares Outstanding | CE65: =D65 -> 215.14335 | CF65: =I65 -> 209.25755 | CG65: =N65 -> 190.2317 | CH65: =S65 -> 182.16566 | CI65: =X65 -> 186.39496 | CJ65: =AC65 -> 170.53254 | CK65: =AH65 -> 171.9 | CL65: =AM65 -> 171.72256 | CM65: =AR65 -> 169.13242 | CN65: =AW65 -> 170.07641 | CO65: =BB65 -> 171.17147 | CP65: =BG65 -> 168.68529 | CQ65: =BL65 -> 165.34066 | CR65: =BQ65 -> 161.16806 | CS65: =BV65 -> 156.6912 | CT65: =CA65 -> 152.4816
A66: Common Dividends | C66: 0 | D66: 0 | E66: 0 | F66: 0 | G66: 0 | H66: 0 | I66: =SUM(E66:H66) -> 0 | J66: 0 | K66: 0 | L66: 0 | M66: 0 | N66: =SUM(J66:M66) -> 0 | O66: 0 | P66: 0 | Q66: 0 | R66: 0 | S66: =SUM(O66:R66) -> 0 | T66: 0 | U66: 0 | V66: 0 | W66: 0 | X66: =SUM(T66:W66) -> 0 | Y66: 0 | Z66: 0 | AA66: 0 | AB66: 0 | AC66: 0 | AD66: 0 | AE66: 0 | AF66: 0 | AG66: 0 | AH66: 0 | AI66: 0 | AJ66: 0 | AK66: 0 | AL66: 0 | AM66: 0 | AN66: 0 | AO66: 0 | AP66: 0 | AQ66: 0 | AR66: 0 | AS66: 0 | AT66: 0 | AU66: 0 | AV66: 0 | AW66: 0 | AX66: 0 | AY66: 0 | AZ66: 0 | BA66: 0 | BB66: 0 | BC66: 0 | BD66: 0 | BE66: 0 | BF66: 0 | BG66: 0 | BH66: 0 | BI66: 0 | BJ66: 0 | BK66: 0 | BL66: 0 | BM66: 0 | BN66: 0 | BO66: 0 | BP66: 0 | BQ66: 0 | BR66: 0 | BS66: 0 | BT66: 0 | BU66: 0 | BV66: 0 | BW66: 0 | BX66: 0 | BY66: 0 | BZ66: 0 | CA66: 0 | CD66: =A66 -> Common Dividends | CE66: =D66 -> 0 | CF66: =I66 -> 0 | CG66: =N66 -> 0 | CH66: =S66 -> 0 | CI66: =X66 -> 0 | CJ66: =AC66 -> 0 | CK66: =AH66 -> 0 | CL66: =AM66 -> 0 | CM66: =AR66 -> 0 | CN66: =AW66 -> 0 | CO66: =BB66 -> 0 | CP66: =BG66 -> 0 | CQ66: =BL66 -> 0 | CR66: =BQ66 -> 0 | CS66: =BV66 -> 0 | CT66: =CA66 -> 0
A67: Avg. Diluted Shares Outstanding | C67: =C65 -> 223.10545 | D67: =D65 -> 215.14335 | E67: =E65 -> 213.4722 | F67: =F65 -> 212.00265 | G67: =G65 -> 210.6259 | H67: =H65 -> 209.25755 | I67: =I65 -> 209.25755 | J67: =J65 -> 196.3477 | ... AB67: =AB65 -> 170.53254 | AC67: =AVERAGE(Y67:AB67) -> 173.32511 | AD67: =AD65 -> 171.35082 | AE67: =AE65 -> 171.90135 | AF67: =AF65 -> 171.66054 | AG67: =AG65 -> 171.9 | AH67: =AVERAGE(AD67:AG67) -> 171.70318 | AI67: =AI65 -> 172.76064 | AJ67: =AJ65 -> 172.46769 | AK67: =AK65 -> 172.15455 | AL67: =AL65 -> 171.72256 | AM67: =AVERAGE(AI65:AL65) -> 172.27636 | AN67: =AN65 -> 170.42149 | AO67: =AO65 -> 169.50366 | AP67: =AP65 -> 169.52245 | AQ67: =AQ65 -> 167.08209 | AR67: =AR65 -> 169.13242 | AS67: 161.48121 | AT67: 167.5861 | AU67: 172.17134 | AV67: 172.56672 | AW67: =AVERAGE(AS65:AV65) -> 170.07641 | AX67: =AX65 -> 171.5 | AY67: =AY65 -> 171.2 | AZ67: =AZ65 -> 171.7859 | BA67: =BA65 -> 170.2 | BB67: =AVERAGE(AX65:BA65) -> 171.17147 | BC67: =BC65 -> 170.15086 | BD67: =BD65 -> 168.3 | BE67: =BE65 -> 167.95706 | BF67: =BF65 -> 168.33326 | BG67: =AVERAGE(BC65:BF65) -> 168.68529 | BH67: =BH65 -> 167.32122 | BI67: =BI65 -> 165.98362 | BJ67: =BJ65 -> 164.67198 | BK67: =BK65 -> 163.3858 | BL67: =AVERAGE(BH65:BK65) -> 165.34066 | BM67: =BM65 -> 163.63891 | BN67: =BN65 -> 161.97019 | BO67: =BO65 -> 160.33386 | BP67: =BP65 -> 158.72928 | BQ67: =AVERAGE(BM65:BP65) -> 161.16806 | BR67: =BR65 -> 159.34222 | BS67: =BS65 -> 157.55182 | BT67: =BT65 -> 155.79617 | BU67: =BU65 -> 154.07459 | BV67: =AVERAGE(BR65:BU65) -> 156.6912 | BW67: =BW65 -> 154.97436 | BX67: =BX65 -> 153.29085 | BY67: =BY65 -> 151.64 | BZ67: =BZ65 -> 150.0212 | CA67: =AVERAGE(BW65:BZ65) -> 152.4816 | CD67: =A67 -> Avg. Diluted Shares Outstanding | CE67: =D67 -> 215.14335 | CF67: =I67 -> 209.25755 | CG67: =N67 -> 190.2317 | CH67: =S67 -> 182.16566 | CI67: =X67 -> 186.39496 | CJ67: =AC67 -> 173.32511 | CK67: =AH67 -> 171.70318 | CL67: =AM67 -> 172.27636 | CM67: =AR67 -> 169.13242 | CN67: =AW67 -> 170.07641 | CO67: =BB67 -> 171.17147 | CP67: =BG67 -> 168.68529 | CQ67: =BL67 -> 165.34066 | CR67: =BQ67 -> 161.16806 | CS67: =BV67 -> 156.6912 | CT67: =CA67 -> 152.4816
A68: Diluted GAAP EPS (Continuing Ops.) | C68: =C54/C67 -> 0.569 | D68: =D54/D67 -> 0.65437765 | E68: =E54/E67 -> 0.18208928 | F68: =F54/F67 -> 0.17610157 | G68: =G54/G67 -> 0.18598852 | H68: =H54/H67 -> 0.18916402 | I68: =I54/I67 -> 0.7405372 | J68: =J54/J67 -> 0.20894566 | ... CA68: =CA54/CA67 -> 4.9566265 | CD68: =A68 -> Diluted GAAP EPS (Continuing Ops.) | CE68: =D68 -> 0.65437765 | CF68: =I68 -> 0.7405372 | CG68: =N68 -> 0.83176463 | CH68: =S68 -> 0.69504867 | CI68: =X68 -> 1.3012798 | CJ68: =AC68 -> 1.6119494 | CK68: =AH68 -> 1.9182395 | CL68: =AM68 -> 1.9871096 | CM68: =AR68 -> 2.1927493 | CN68: =AW68 -> 2.9829357 | CO68: =BB68 -> 2.6379571 | CP68: =BG68 -> 3.2907433 | CQ68: =BL68 -> 3.4211868 | CR68: =BQ68 -> 3.8799597 | CS68: =BV68 -> 4.37956 | CT68: =CA68 -> 4.9566265
A69: Diluted GAAP EPS Reported | C69: =C58/C67 -> 0.55746285 | D69: =D58/D67-0.01 -> 0.6359879 | E69: =E58/E67 -> 0.17923177 | F69: =F58/F67 -> 0.17283746 | G69: =G58/G67 -> 0.17639806 | H69: =H58/H67 -> 0.18310928 | I69: =I58/I67 -> 0.71860729 | J69: =J58/J67 -> 0.20894566 | K69: =K58/K67 -> 0.20853738 | L69: =L58/L67 -> 0.21529825 | ... CA69: =CA58/CA67 -> 4.9566265 | CD69: =A69 -> Diluted GAAP EPS Reported | CE69: =D69 -> 0.6359879 | CF69: =I69 -> 0.71860729 | CG69: =N69 -> 0.83176463 | CH69: =S69 -> 0.69504867 | CI69: =X69 -> 1.3012798 | CJ69: =AC69 -> 1.631358 | CK69: =AH69 -> 1.9182395 | CL69: =AM69 -> 2.0223204 | CM69: =AR69 -> 2.3652591 | CN69: =AW69 -> 2.9829357 | CO69: =BB69 -> 3.4541503 | CP69: =BG69 -> 3.2907433 | CQ69: =BL69 -> 3.4211868 | CR69: =BQ69 -> 3.8799597 | CS69: =BV69 -> 4.37956 | CT69: =CA69 -> 4.9566265
A70: Adj. EPS (excl. ESOP & extraordinary items) | C70: =C59/C67 -> 0.55746285 | D70: =D59/D67 -> 0.70051898 | E70: =E59/E67 -> 0.17923177 | F70: =F59/F67 -> 0.17283746 | G70: =G59/G67 -> 0.17639806 | H70: =H59/H67 -> 0.18310928 | I70: =I59/I67 -> 0.78457384 | J70: =J59/J67 -> 0.22507012 | ... AQ70: =AQ59/AQ67 -> 0.58136692 | AR70: =SUM(AN70:AQ70) -> 2.363716 | AS70: =AS59/AS67 -> 0.61484552 | AT70: =AT59/AT67 -> 0.81703674 | AU70: =AU59/AU67 -> 0.66156192 | AV70: =AV59/AV67 -> 0.65833666 | AW70: =SUM(AS70:AV70) -> 2.7517808 | AX70: =AX59/AX67 -> 0.54140525 | AY70: =AY59/AY67 -> 1.5337734 | AZ70: =AZ59/AZ67 -> 0.75836841 | BA70: =BA59/BA67 -> 0.77085781 | BB70: =SUM(AX70:BA70) -> 3.6044048 | BC70: =BC59/BC67 -> 0.65059911 | BD70: =BD59/BD67 -> 0.73915627 | BE70: =BE59/BE67 -> 0.73411622 | BF70: =BF59/BF67 -> 1.2255451 | BG70: =SUM(BC70:BF70) -> 3.3494167 | BH70: =BH59/BH67 -> 0.77349689 | BI70: =BI59/BI67 -> 0.82265093 | BJ70: =BJ59/BJ67 -> 0.91081205 | BK70: =BK59/BK67 -> 0.91627926 | BL70: =SUM(BH70:BK70) -> 3.4232391 | BM70: =BM59/BM67 -> 0.87796514 | BN70: =BN59/BN67 -> 0.93352039 | BO70: =BO59/BO67 -> 1.0313159 | BP70: =BP59/BP67 -> 1.0401293 | BQ70: =SUM(BM70:BP70) -> 3.8829308 | BR70: =BR59/BR67 -> 0.99263679 | BS70: =BS59/BS67 -> 1.0543402 | BT70: =BT59/BT67 -> 1.1625329 | BU70: =BU59/BU67 -> 1.1737054 | BV70: =SUM(BR70:BU70) -> 4.3832152 | BW70: =BW59/BW67 -> 1.1262481 | BX70: =BX59/BX67 -> 1.1943387 | BY70: =BY59/BY67 -> 1.3133565 | BZ70: =BZ59/BZ67 -> 1.3265872 | CA70: =SUM(BW70:BZ70) -> 4.9605305 | CD70: =A70 -> Adj. EPS (excl. ESOP & extraordinary items) | CE70: =D70 -> 0.70051898 | CF70: =I70 -> 0.78457384 | CG70: =N70 -> 0.89780515 | CH70: =S70 -> 1.1027545 | CI70: =X70 -> 1.3012798 | CJ70: =AC70 -> 1.631358 | CK70: =AH70 -> 1.917494 | CL70: =AM70 -> 2.0260064 | CM70: =AR70 -> 2.363716 | CN70: =AW70 -> 2.7517808 | CO70: =BB70 -> 3.6044048 | CP70: =BG70 -> 3.3494167 | CQ70: =BL70 -> 3.4232391 | CR70: =BQ70 -> 3.8829308 | CS70: =BV70 -> 4.3832152 | CT70: =CA70 -> 4.9605305
A71: Adjusted, Cont EPS | C71: =C61/C65 -> 0.61088871 | D71: =D61/D67 -> 0.77466333 | E71: =E61/E65 -> 0.20385362 | F71: =F61/F65 -> 0.19594622 | G71: =G61/G65 -> 0.19799945 | H71: =H61/H65 -> 0.20830868 | I71: =I61/I67 -> 0.88004554 | J71: =J61/J67 -> 0.24853632 | K71: =K61/K67 -> 0.24803972 | L71: =L61/L67 -> 0.25364774 | M71: =M61/M67 -> 0.23618228 | N71: =N61/N67 -> 0.98682905 | O71: =O61/O67 -> 0.29182559 | P71: =P61/P67 -> 0.30379068 | ... AH71: =AH61/AH67 -> 2.1025706 | AI71: =(AI61-AI55)/AI67 -> 0.51991703 | AJ71: =AJ61/AJ67 -> 0.53446533 | AK71: =AK61/AK67 -> 0.60616462 | AL71: =AL61/AL67 -> 0.55496495 | AM71: =AM61/AM67 -> 2.2215422 | AN71: =(AN61-AN55)/AN67 -> 0.54546642 | AO71: =(AO61-AO55)/AO67 -> 0.57016416 | AP71: =(AP61-AP55)/AP67 -> 0.63723127 | AQ71: =(AQ61)/AQ67 -> 0.64725668 | AR71: =SUM(AN71:AQ71) -> 2.4001185 | AS71: =(AS61-AS55)/AS67 -> 0.66587932 | AT71: =(AT61-AT55)/AT67 -> 0.76785605 | AU71: =(AU61-AU55)/AU67 -> 0.84541947 | AV71: =(AV61-AV55)/AV67 -> 0.80281991 | AW71: =SUM(AS71:AV71) -> 3.0819747 | AX71: =(AX61)/AX67 -> 0.74286297 | AY71: =(AY61)/AY67 -> 0.72571262 | AZ71: =(AZ61-AZ55)/AZ67 -> 0.84032508 | BA71: =(BA61)/BA67 -> 0.79553467 | BB71: =SUM(AX71:BA71) -> 3.1044353 | BC71: =(BC61-BC55)/BC67 -> 0.73640532 | BD71: =(BD61-BD55)/BD67 -> 0.82352941 | BE71: =(BE61-BE55)/BE67 -> 0.84009569 | BF71: =(BF61-BF55)/BF67 -> 1.3390105 | BG71: =SUM(BC71:BF71) -> 3.7390409 | BH71: =(BH61-BH55)/BH67 -> 0.91623731 | BI71: =(BI61-BI55)/BI67 -> 0.96654163 | BJ71: =(BJ61-BJ55)/BJ67 -> 1.0558489 | BK71: =(BK61-BK55)/BK67 -> 1.0624578 | BL71: =SUM(BH71:BK71) -> 4.0010856 | BM71: =(BM61-BM55)/BM67 -> 1.0229001 | BN71: =(BN61-BN55)/BN67 -> 1.0799486 | BO71: =(BO61-BO55)/BO67 -> 1.1792385 | BP71: =(BP61-BP55)/BP67 -> 1.1895473 | BQ71: =SUM(BM71:BP71) -> 4.4716344 | BR71: =(BR61-BR55)/BR67 -> 1.1389257 | BS71: =(BS61-BS55)/BS67 -> 1.2022915 | BT71: =(BT61-BT55)/BT67 -> 1.3121514 | BU71: =(BU61-BU55)/BU67 -> 1.3249958 | BV71: =SUM(BR71:BU71) -> 4.9783644 | BW71: =(BW61-BW55)/BW67 -> 1.2641257 | BX71: =(BX61-BX55)/BX67 -> 1.3337306 | BY71: =(BY61-BY55)/BY67 -> 1.4542659 | BZ71: =(BZ61-BZ55)/BZ67 -> 1.4690171 | CA71: =SUM(BW71:BZ71) -> 5.5211393 | CB71: =(CA71/BG71)^(1/4)-1 -> 0.10234395 | CD71: =A71 -> Adjusted, Cont EPS | CE71: =D71 -> 0.77466333 | CF71: =I71 -> 0.88004554 | CG71: =N71 -> 0.98682905 | CH71: =S71 -> 1.2134998 | CI71: =X71 -> 1.4006763 | CJ71: =AC71 -> 1.7516109 | CK71: =AH71 -> 2.1025706 | CL71: =AM71 -> 2.2215422 | CM71: =AR71 -> 2.4001185 | CN71: =AW71 -> 3.0819747 | CO71: =BB71 -> 3.1044353 | CP71: =BG71 -> 3.7390409 | CQ71: =BL71 -> 4.0010856 | CR71: =BQ71 -> 4.4716344 | CS71: =BV71 -> 4.9783644 | CT71: =CA71 -> 5.5211393
A72: Restated Adj EPS, Continuing | AD72: 0.44 | AE72: 0.45 | AF72: 0.52 | AG72: 0.62 | AH72: =SUM(AD72:AG72) -> 2.03 | AI72: 0.52 | AJ72: 0.53 | AK72: 0.61 | AL72: 0.55 | AM72: =SUM(AI72:AL72) -> 2.21 | CD72: =A72 -> Restated Adj EPS, Continuing | CE72: =D72 -> 0 | CF72: =I72 -> 0 | CG72: =N72 -> 0 | CH72: =S72 -> 0 | CI72: =X72 -> 0 | CK72: =AH72 -> 2.03 | CL72: =AM72 -> 2.21 | CM72: =+CM71 -> 2.4001185 | CN72: =+CN71 -> 3.0819747 | CO72: =+CO71 -> 3.1044353 | CP72: =+CP71 -> 3.7390409 | CQ72: =+CQ71 -> 4.0010856 | CR72: =+CR71 -> 4.4716344 | CS72: =+CS71 -> 4.9783644 | CT72: =+CT71 -> 5.5211393
A73: Performance Statistics
A74: Fiscal Year Ending December 31 | C74: =C$1 -> 2005 | D74: =D$1 -> 2006 | E74: =E$1 -> 1Q07 | F74: =F$1 -> 2Q07 | G74: =G$1 -> 3Q07 | H74: =H$1 -> 4Q07 | I74: =I$1 -> 2007 | J74: =J$1 -> 1Q08 | ... AL74: =AL$1 -> 4Q13
A75: Segment Performance
A77: Risk Assessment
A78: Revenue
A79: YoY Growth
A80: Adj. EBITDA
A81: Adj. EBITDA Margin
A82: Headcount
A83: Total Expenses per Employee
A85: Decision Analytics
A86: Total Revenue
A87: YoY Growth
A88: Fraud identification and detection solutions
... A108: Source: Company reports.
A111: Fiscal Year Ending December 31 | C111: =+C$1 -> 2005 | D111: =+D$1 -> 2006 | E111: =+E$1 -> 1Q07 | F111: =+F$1 -> 2Q07 | G111: =+G$1 -> 3Q07 | H111: =+H$1 -> 4Q07 | I111: =+I$1 -> 2007 | J111: =+J$1 -> 1Q08 | ... AM111: =+AM$1 -> 2013 | AN111: =AN11 -> 1Q14 | AO111: =AO11 -> 2Q14 | AP111: =AP11 -> 3Q14 | AQ111: =AQ11 -> 4Q14 | AR111: =+AR$1 -> 2014 | AS111: =AS11 -> 1Q15 | AT111: =AT11 -> 2Q15 | AU111: =AU11 -> 3Q15 | AV111: =AV11 -> 4Q15 | AW111: =+AW$1 -> 2015 | AX111: =AX11 -> 1Q16 | AY111: =AY11 -> 2Q16 | AZ111: =AZ11 -> 3Q16 | BA111: =BA11 -> 4Q16 | BB111: =+BB$1 -> 2016 | BC111: =BC11 -> 1Q17 | BD111: =BD11 -> 2Q17 | BE111: =BE11 -> 3Q17 | BF111: =BF11 -> 4Q17 | BG111: =+BG$1 -> 2017 | BH111: =BH11 -> 1Q18E | BI111: =BI11 -> 2Q18E | BJ111: =BJ11 -> 3Q18E | BK111: =BK11 -> 4Q18E | BL111: =+BL$1 -> 2018E | BM111: =BM11 -> 1Q19E | BN111: =BN11 -> 2Q19E | BO111: =BO11 -> 3Q19E | BP111: =BP11 -> 4Q19E | BQ111: =+BQ$1 -> 2019E | BR111: =BR11 -> 1Q20E | BS111: =BS11 -> 2Q20E | BT111: =BT11 -> 3Q20E | BU111: =BU11 -> 4Q20E | BV111: =+BV$1 -> 2020E | BW111: =BW11 -> 1Q21E | BX111: =BX11 -> 2Q21E | BY111: =BY11 -> 3Q21E | BZ111: =BZ11 -> 4Q21E | CA111: =+CA$1 -> 2021E | CD111: =A111 -> Fiscal Year Ending December 31 | CE111: =D111 -> 2006 | CF111: =I111 -> 2007 | CG111: =N111 -> 2008 | CH111: =S111 -> 2009 | CI111: =X111 -> 2010 | CJ111: =AC111 -> 2011 | CK111: =AH111 -> 2012 | CL111: =AM111 -> 2013 | CM111: =AR111 -> 2014 | CN111: =AW111 -> 2015 | CO111: =BB111 -> 2016 | CP111: =BG111 -> 2017 | CQ111: =BL111 -> 2018E | CR111: =BQ111 -> 2019E | CS111: =BV111 -> 2020E | CT111: =CA111 -> 2021E
A112: Cash Flows From Operations | CD112: =A112 -> Cash Flows From Operations
A113: Net income (loss) to Common Stockholders | C113: =C58 -> 124.373 | D113: =D58 -> 138.98 | E113: =E58 -> 38.261 | F113: =F58 -> 36.642 | G113: =G58 -> 37.154 | H113: =H58 -> 38.317 | I113: =SUM(E113:H113) -> 150.374 | J113: =J58 -> 41.026 | K113: =K58 -> 39.923 | L113: =L58 -> 40.84 | M113: =M58 -> 36.439 | N113: =SUM(J113:M113) -> 158.228 | O113: =O58 -> 44.915 | P113: =P58 -> 45.939 | Q113: =Q58 -> 42.205 | R113: =R58 -> -6.445 | S113: =SUM(O113:R113) -> 126.614 | T113: =T58 -> 55.375 | U113: =U58 -> 58.404 | V113: =V58 -> 62.88 | W113: =W58 -> 65.893 | X113: =SUM(T113:W113) -> 242.552 | Y113: =Y58 -> 65.876 | Z113: =Z58 -> 65.577 | AA113: =AA58 -> 70.987 | AB113: =AB58 -> 80.318 | AC113: =SUM(Y113:AB113) -> 282.758 | AD113: =AD58 -> 74.601 | AE113: =AE58 -> 73.331 | AF113: =AF58 -> 82.911 | AG113: =329.142-SUM(AD113:AF113) -> 98.299 | AH113: =SUM(AD113:AG113) -> 329.142 | AI113: =AI58 -> 80.511 | AJ113: =AJ58 -> 84.223 | AK113: =AK58 -> 96.441 | AL113: =AL58 -> 87.223 | AM113: =SUM(AI113:AL113) -> 348.398 | AN113: =AN58 -> 115.558 | AO113: =AO58 -> 88.099 | AP113: =AP58 -> 99.015 | AQ113: =AQ58 -> 97.37 | AR113: =SUM(AN113:AQ113) -> 400.042 | AS113: =AS58 -> 98.686 | AT113: =AT58 -> 163.32 | AU113: =AU58 -> 131.814 | AV113: =AV58 -> 113.507 | AW113: =SUM(AS113:AV113) -> 507.327 | AX113: =AX58 -> 92.639 | AY113: =AY58 -> 261.736 | AZ113: =AZ58 -> 127.577 | BA113: =BA58 -> 109.3 | BB113: =SUM(AX113:BA113) -> 591.252 | BC113: =BC58 -> 108.8 | BD113: =BD58 -> 121 | BE113: =BE58 -> 120.7 | BF113: =BF58 -> 204.6 | BG113: =SUM(BC113:BF113) -> 555.1 | BH113: =BH58 -> 129.42245 | BI113: =BI58 -> 136.54658 | BJ113: =BJ58 -> 149.98523 | BK113: =BK58 -> 149.70702 | BL113: =SUM(BH113:BK113) -> 565.66128 | BM113: =BM58 -> 143.66926 | BN113: =BN58 -> 151.20248 | BO113: =BO58 -> 165.35486 | BP113: =BP58 -> 165.09899 | BQ113: =SUM(BM113:BP113) -> 625.32558 | BR113: =BR58 -> 158.16895 | BS113: =BS58 -> 166.11322 | BT113: =BT58 -> 181.11816 | BU113: =BU58 -> 180.83818 | BV113: =SUM(BR113:BU113) -> 686.23851 | BW113: =BW58 -> 174.53958 | BX113: =BX58 -> 183.08119 | BY113: =BY58 -> 199.15739 | BZ113: =BZ58 -> 199.0162 | CA113: =SUM(BW113:BZ113) -> 755.79436 | CD113: =A113 -> Net income (loss) to Common Stockholders | CE113: =D113 -> 138.98 | CF113: =I113 -> 150.374 | CG113: =N113 -> 158.228 | CH113: =S113 -> 126.614 | CI113: =X113 -> 242.552 | CJ113: =AC113 -> 282.758 | CK113: =AH113 -> 329.142 | CL113: =AM113 -> 348.398 | CM113: =AR113 -> 400.042 | CN113: =AW113 -> 507.327 | CO113: =BB113 -> 591.252 | CP113: =BG113 -> 555.1 | CQ113: =BL113 -> 565.66128 | CR113: =BQ113 -> 625.32558 | CS113: =BV113 -> 686.23851 | CT113: =CA113 -> 755.79436
A114: Depreciation | C114: 22.123 | D114: 28.119 | E114: 7.605 | F114: =15.546-E114 -> 7.941 | G114: =23.373-SUM(E114:F114) -> 7.827 | H114: =31.843-SUM(E114:G114) -> 8.47 | I114: =SUM(E114:H114) -> 31.843 | J114: 7.907 | K114: =16.424-J114 -> 8.517 | L114: =25.478-SUM(J114:K114) -> 9.054 | M114: =35.317-SUM(J114:L114) -> 9.839 | N114: =SUM(J114:M114) -> 35.317 | O114: 9.195 | P114: =18.913-O114 -> 9.718 | Q114: =28.534-SUM(O114:P114) -> 9.621 | R114: =38.578-SUM(O114:Q114) -> 10.044 | S114: =SUM(O114:R114) -> 38.578 | T114: 9.929 | U114: =U38 -> 9.944 | V114: =V38 -> 10.035 | W114: =40.728-SUM(T114:V114) -> 10.82 | X114: =SUM(T114:W114) -> 40.728 | Y114: =Y38 -> 11.305 | Z114: =Z38 -> 10.855 | AA114: =AA38 -> 10.798 | AB114: =AB38 -> 10.869 | AC114: =SUM(Y114:AB114) -> 43.827 | AD114: =AD38 -> 11.644 | AE114: =AE38 -> 13.09 | AF114: =AF38 -> 12.714 | AG114: =AG38 -> 13.176 | AH114: =SUM(AD114:AG114) -> 50.624 | AI114: =AI38 -> 14.163 | AJ114: =AJ38 -> 15.81 | AK114: =AK38 -> 16.745 | AL114: =AL38 -> 19.471 | AM114: =SUM(AI114:AL114) -> 66.189 | AN114: =AN38 -> 19.781 | AO114: =AO38 -> 20.723 | AP114: =AP38 -> 21.951 | AQ114: =86.501-SUM(AN114:AP114) -> 24.046 | AR114: =SUM(AN114:AQ114) -> 86.501 | AS114: 24.442 | AT114: =AT38 -> 28.628 | AU114: =AU38 -> 33.501 | AV114: =AV38 -> 34.049 | AW114: =SUM(AS114:AV114) -> 120.62 | AX114: 38.874 | AY114: =68.331-AX114 -> 29.457 | AZ114: =97.832-SUM(AX114:AY114) -> 29.501 | BA114: =126.2-SUM(AX114:AZ114) -> 28.368 | BB114: =SUM(AX114:BA114) -> 126.2 | BC114: 33.8 | BD114: =65.6-BC114 -> 31.8 | BE114: =99.4-BD114-BC114 -> 33.8 | BF114: =135.6-SUM(BC114:BE114) -> 36.2 | BG114: =SUM(BC114:BF114) -> 135.6 | BH114: =BH38 -> 38.63586 | BI114: =BI38 -> 37.76994 | BJ114: =BJ38 -> 38.29508 | BK114: =BK38 -> 38.73984 | BL114: =SUM(BH114:BK114) -> 153.44072 | BM114: =BM38 -> 38.511862 | BN114: =BN38 -> 37.643847 | BO114: =BO38 -> 38.168594 | BP114: =BP38 -> 38.612655 | BQ114: =SUM(BM114:BP114) -> 152.93696 | BR114: =BR38 -> 38.355625 | BS114: =BS38 -> 37.48497 | BT114: =BT38 -> 38.009222 | BU114: =BU38 -> 38.452402 | BV114: =SUM(BR114:BU114) -> 152.30222 | BW114: =BW38 -> 38.738406 | BX114: =BX38 -> 37.874219 | BY114: =BY38 -> 38.399684 | BZ114: =BZ38 -> 38.845022 | CA114: =SUM(BW114:BZ114) -> 153.85733 | CD114: =A114 -> Depreciation | CE114: =D114 -> 28.119 | CF114: =I114 -> 31.843 | CG114: =N114 -> 35.317 | CH114: =S114 -> 38.578 | CI114: =X114 -> 40.728 | CJ114: =AC114 -> 43.827 | CK114: =AH114 -> 50.624 | CL114: =AM114 -> 66.189 | CM114: =AR114 -> 86.501 | CN114: =AW114 -> 120.62 | CO114: =BB114 -> 126.2 | CP114: =BG114 -> 135.6 | CQ114: =BL114 -> 153.44072 | CR114: =BQ114 -> 152.93696 | CS114: =BV114 -> 152.30222 | CT114: =CA114 -> 153.85733
A115: Amortization of intangible assets | C115: 19.8 | D115: 26.854 | E115: 8.923 | F115: =17.24-E115 -> 8.317 | G115: =24.964-SUM(E115:F115) -> 7.724 | H115: =33.916-SUM(E115:G115) -> 8.952 | I115: =SUM(E115:H115) -> 33.916 | J115: 8.041 | K115: =14.937-J115 -> 6.896 | L115: =21.978-SUM(J115:K115) -> 7.041 | M115: =29.555-SUM(J115:L115) -> 7.577 | N115: =SUM(J115:M115) -> 29.555 | O115: 8.51 | P115: =16.974-O115 -> 8.464 | Q115: =24.986-SUM(O115:P115) -> 8.012 | R115: =32.621-SUM(O115:Q115) -> 7.635 | S115: =SUM(O115:R115) -> 32.621 | T115: 7.304 | U115: =U39 -> 7.02 | V115: =20.482-SUM(T115:U115) -> 6.158 | W115: =27.398-SUM(T115:V115) -> 6.916 | X115: =SUM(T115:W115) -> 27.398 | Y115: =Y39 -> 8.455 | Z115: =Z39 -> 8.877 | AA115: =AA39 -> 8.797 | AB115: =AB39 -> 8.663 | AC115: =SUM(Y115:AB115) -> 34.792 | AD115: =AD39 -> 8.587 | AE115: =AE39 -> 12.187 | AF115: =AF39 -> 15.442 | AG115: =53.575-SUM(AD115:AF115) -> 17.359 | AH115: =SUM(AD115:AG115) -> 53.575 | AI115: =AI39 -> 17.052 | AJ115: =AJ39 -> 17.061 | AK115: =AK39 -> 15.258 | AL115: =AL39 -> 14.37 | AM115: =SUM(AI115:AL115) -> 63.741 | AN115: =AN39 -> 14.212 | AO115: =AO39 -> 14.221 | AP115: =AP39 -> 14.187 | AQ115: =56.982-SUM(AN115:AP115) -> 14.362 | AR115: =SUM(AN115:AQ115) -> 56.982 | AS115: 14.141 | AT115: =AT39 -> 28.812 | AU115: =AU39 -> 18.543 | AV115: =AV39 -> 33.633 | AW115: =SUM(AS115:AV115) -> 95.129 | AX115: 29.775 | AY115: =53.581-AX115 -> 23.806 | AZ115: =76.259-SUM(AX115:AY115) -> 22.678 | BA115: =98.4-SUM(AX115:AZ115) -> 22.141 | BB115: =SUM(AX115:BA115) -> 98.4 | BC115: 22.3 | BD115: =46.2-BC115 -> 23.9 | BE115: =73.6-BD115-BC115 -> 27.4 | BF115: =101.8-SUM(BC115:BE115) -> 28.2 | BG115: =SUM(BC115:BF115) -> 101.8 | BH115: =BH39 -> 32.275 | BI115: =BI39 -> 32.275 | BJ115: =BJ39 -> 32.275 | BK115: =BK39 -> 32.275 | BL115: =SUM(BH115:BK115) -> 129.1 | BM115: =BM39 -> 32.05 | BN115: =BN39 -> 32.05 | BO115: =BO39 -> 32.05 | BP115: =BP39 -> 32.05 | BQ115: =SUM(BM115:BP115) -> 128.2 | BR115: =BR39 -> 31.5 | BS115: =BS39 -> 31.5 | BT115: =BT39 -> 31.5 | BU115: =BU39 -> 31.5 | BV115: =SUM(BR115:BU115) -> 126 | BW115: =BW39 -> 28.875 | BX115: =BX39 -> 28.875 | BY115: =BY39 -> 28.875 | BZ115: =BZ39 -> 28.875 | CA115: =SUM(BW115:BZ115) -> 115.5 | CD115: =A115 -> Amortization of intangible assets | CE115: =D115 -> 26.854 | CF115: =I115 -> 33.916 | CG115: =N115 -> 29.555 | CH115: =S115 -> 32.621 | CI115: =X115 -> 27.398 | CJ115: =AC115 -> 34.792 | CK115: =AH115 -> 53.575 | CL115: =AM115 -> 63.741 | CM115: =AR115 -> 56.982 | CN115: =AW115 -> 95.129 | CO115: =BB115 -> 98.4 | CP115: =BG115 -> 101.8 | CQ115: =BL115 -> 129.1 | CR115: =BQ115 -> 128.2 | CS115: =BV115 -> 126 | CT115: =CA115 -> 115.5
A116: KSOP compensation expense | C116: 13.793 | D116: 18.779 | E116: 5.23 | F116: =10.899-E116 -> 5.669 | G116: =16.5-SUM(E116:F116) -> 5.601 | H116: =22.247-SUM(E116:G116) -> 5.747 | I116: =SUM(E116:H116) -> 22.247 | J116: 5.725 | K116: =11.564-J116 -> 5.839 | L116: =17.353-SUM(J116:K116) -> 5.789 | M116: =22.274-SUM(J116:L116) -> 4.921 | N116: =SUM(J116:M116) -> 22.274 | O116: 5.127 | P116: =10.738-O116 -> 5.611 | Q116: =17.62-SUM(O116:P116) -> 6.882 | R116: =76.065-SUM(O116:Q116) -> 58.445 | S116: =SUM(O116:R116) -> 76.065 | T116: 2.85 | U116: =5.729-T116 -> 2.879 | V116: =8.651-SUM(T116:U116) -> 2.922 | W116: =11.573-SUM(T116:V116) -> 2.922 | X116: =SUM(T116:W116) -> 11.573 | Y116: 3.111 | Z116: =6.408-Y116 -> 3.297 | AA116: =9.63-SUM(Y116:Z116) -> 3.222 | AB116: =12.615-SUM(Y116:AA116) -> 2.985 | AC116: =SUM(Y116:AB116) -> 12.615 | AD116: 2.931 | AE116: =6.186-AD116 -> 3.255 | AF116: =9.481-SUM(AD116:AE116) -> 3.295 | AG116: =13.111-SUM(AD116:AF116) -> 3.63 | AH116: =SUM(AD116:AG116) -> 13.111 | AI116: 3.57 | AJ116: =7.357-AI116 -> 3.787 | AK116: =11.174-SUM(AI116:AJ116) -> 3.817 | AL116: =14.93-SUM(AI116:AK116) -> 3.756 | AM116: =SUM(AI116:AL116) -> 14.93 | AN116: 3.901 | AO116: =7.703-AN116 -> 3.802 | AP116: =11.613-AO116-AN116 -> 3.91 | AQ116: =15.351-SUM(AN116:AP116) -> 3.738 | AR116: =SUM(AN116:AQ116) -> 15.351 | AS116: 3.821 | AT116: =7.969-AS116 -> 4.148 | AU116: =10.575-SUM(AS116:AT116) -> 2.606 | AV116: =14.076-SUM(AS116:AU116) -> 3.501 | AW116: =SUM(AS116:AV116) -> 14.076 | AX116: 4.286 | AY116: =8.214-AX116 -> 3.928 | AZ116: =11.386-SUM(AX116:AY116) -> 3.172 | BA116: =14.5-SUM(AX116:AZ116) -> 3.114 | BB116: =SUM(AX116:BA116) -> 14.5 | BC116: 0 | BD116: 0 | BE116: 0 | BF116: 0 | BG116: =SUM(BC116:BF116) -> 0 | BH116: =BG116 -> 0 | BI116: =BH116 -> 0 | BJ116: =BI116 -> 0 | BK116: =BJ116 -> 0 | BL116: =SUM(BH116:BK116) -> 0 | BM116: =BL116 -> 0 | BN116: =BM116 -> 0 | BO116: =BN116 -> 0 | BP116: =BO116 -> 0 | BQ116: =SUM(BM116:BP116) -> 0 | BR116: =BQ116 -> 0 | BS116: =BR116 -> 0 | BT116: =BS116 -> 0 | BU116: =BT116 -> 0 | BV116: =SUM(BR116:BU116) -> 0 | BW116: =BV116 -> 0 | BX116: =BW116 -> 0 | BY116: =BX116 -> 0 | BZ116: =BY116 -> 0 | CA116: =SUM(BW116:BZ116) -> 0 | CD116: =A116 -> KSOP compensation expense | CE116: =D116 -> 18.779 | CF116: =I116 -> 22.247 | CG116: =N116 -> 22.274 | CH116: =S116 -> 76.065 | CI116: =X116 -> 11.573 | CJ116: =AC116 -> 12.615 | CK116: =AH116 -> 13.111 | CL116: =AM116 -> 14.93 | CM116: =AR116 -> 15.351 | CN116: =AW116 -> 14.076 | CO116: =BB116 -> 14.5 | CP116: =BG116 -> 0 | CQ116: =BL116 -> 0 | CR116: =BQ116 -> 0 | CS116: =BV116 -> 0 | CT116: =CA116 -> 0
A117: Stock-based Compensation | C117: 4.094 | D117: 6.148 | E117: 1.521 | F117: =3.756-E117 -> 2.235 | G117: =6.078-SUM(E117:F117) -> 2.322 | H117: =8.244-SUM(E117:G117) -> 2.166 | I117: =SUM(E117:H117) -> 8.244 | J117: 2.052 | K117: =4.621-J117 -> 2.569 | L117: =7.522-SUM(J117:K117) -> 2.901 | M117: =9.881-SUM(J117:L117) -> 2.359 | N117: =SUM(J117:M117) -> 9.881 | O117: 2.005 | P117: =5.515-O117 -> 3.51 | Q117: =8.526-SUM(O117:P117) -> 3.011 | R117: =12.744-SUM(O117:Q117) -> 4.218 | S117: =SUM(O117:R117) -> 12.744 | T117: 3.886 | U117: =10.284-T117 -> 6.398 | V117: =15.99-SUM(T117:U117) -> 5.706 | W117: =21.298-SUM(T117:V117) -> 5.308 | X117: =SUM(T117:W117) -> 21.298 | Y117: 3.818 | Z117: =12.331-Y117 -> 8.513 | AA117: =17.288-SUM(Y117:Z117) -> 4.957 | AB117: =22.656-SUM(Y117:AA117) -> 5.368 | AC117: =SUM(Y117:AB117) -> 22.656 | AD117: 4.446 | AE117: =13.653-AD117 -> 9.207 | AF117: =19.303-SUM(AD117:AE117) -> 5.65 | AG117: =24.696-SUM(AD117:AF117) -> 5.393 | AH117: =SUM(AD117:AG117) -> 24.696 | AI117: 4.571 | AJ117: =10.955-AI117 -> 6.384 | AK117: =16.745-SUM(AI117:AJ117) -> 5.79 | AL117: =AL360 -> 4.342 | AM117: =SUM(AI117:AL117) -> 21.087 | AN117: 4.983 | AO117: =11.057-AN117 -> 6.074 | AP117: =16.323-AO117-AN117 -> 5.266 | AQ117: =20.253-SUM(AN117:AP117) -> 3.93 | AR117: =SUM(AN117:AQ117) -> 20.253 | AS117: 4.224 | AT117: =19.047-AS117 -> 14.823 | AU117: =25.471-SUM(AS117:AT117) -> 6.424 | AV117: =30.542-SUM(AS117:AU117) -> 5.071 | AW117: =SUM(AS117:AV117) -> 30.542 | AX117: 5.547 | AY117: =16.468-AX117 -> 10.921 | AZ117: =23.822-SUM(AX117:AY117) -> 7.354 | BA117: =30-SUM(AX117:AZ117) -> 6.178 | BB117: =SUM(AX117:BA117) -> 30 | BC117: 6.5 | BD117: =15.4-BC117 -> 8.9 | BE117: =24.2-BD117-BC117 -> 8.8 | BF117: =31.8-SUM(BC117:BE117) -> 7.6 | BG117: =SUM(BC117:BF117) -> 31.8 | BH117: =BH360 -> 8.52231 | BI117: =BI360 -> 8.74023 | BJ117: =BJ360 -> 8.973425 | BK117: =BK360 -> 9.155235 | BL117: =SUM(BH117:BK117) -> 35.3912 | BM117: =BM360 -> 9.0053152 | BN117: =BN360 -> 9.2437075 | BO117: =BO360 -> 9.4927591 | BP117: =BP360 -> 9.6930807 | BQ117: =SUM(BM117:BP117) -> 37.434862 | BR117: =BR360 -> 9.5100516 | BS117: =BS360 -> 9.7625526 | BT117: =BT360 -> 10.027114 | BU117: =BU360 -> 10.238145 | BV117: =SUM(BR117:BU117) -> 39.537864 | BW117: =BW360 -> 10.04433 | BX117: =BX360 -> 10.311823 | BY117: =BY360 -> 10.592877 | BZ117: =BZ360 -> 10.815223 | CA117: =SUM(BW117:BZ117) -> 41.764253 | CD117: =A117 -> Stock-based Compensation | CE117: =D117 -> 6.148 | CF117: =I117 -> 8.244 | CG117: =N117 -> 9.881 | CH117: =S117 -> 12.744 | CI117: =X117 -> 21.298 | CJ117: =AC117 -> 22.656 | CK117: =AH117 -> 24.696 | CL117: =AM117 -> 21.087 | CM117: =AR117 -> 20.253 | CN117: =AW117 -> 30.542 | CO117: =BB117 -> 30 | CP117: =BG117 -> 31.8 | CQ117: =BL117 -> 35.3912 | CR117: =BQ117 -> 37.434862 | CS117: =BV117 -> 39.537864 | CT117: =CA117 -> 41.764253
A118: Employee Compensation Expense | C118: 0.601 | D118: 1.909 | E118: 0.348 | F118: =1.387-E118 -> 1.039 | G118: =1.85-SUM(E118:F118) -> 0.463 | H118: =2.182-SUM(E118:G118) -> 0.332 | I118: =SUM(E118:H118) -> 2.182 | J118: 1.175 | K118: =2.327-J118 -> 1.152 | L118: =2.618-SUM(J118:K118) -> 0.291 | M118: =-0.091-SUM(J118:L118) -> -2.709 | N118: =SUM(J118:M118) -> -0.091 | O118: 0.61 | P118: =1.385-O118 -> 0.775 | Q118: =2.649-SUM(O118:P118) -> 1.264 | R118: =4.039-SUM(O118:Q118) -> 1.39 | S118: =SUM(O118:R118) -> 4.039 | T118: 0.566 | U118: =0.792-T118 -> 0.226 | V118: =0.515-SUM(T118:U118) -> -0.277 | W118: =0.789-SUM(T118:V118) -> 0.274 | X118: =SUM(T118:W118) -> 0.789 | Y118: =0.546 -> 0.546 | Z118: =0.583-Y118 -> 0.037 | AA118: =0.627-SUM(Y118:Z118) -> 0.044 | AB118: =0.585-SUM(Y118:AA118) -> -0.042 | AC118: =SUM(Y118:AB118) -> 0.585 | AD118: 0 | AE118: 0 | AF118: =0-SUM(AD118:AE118) -> 0 | AG118: 0 | AH118: =SUM(AD118:AG118) -> 0 | AI118: 0 | AJ118: 0 | AK118: 0 | AL118: 0 | AM118: =SUM(AI118:AL118) -> 0 | AN118: 0 | AO118: 0 | AP118: 0 | AQ118: 0 | AR118: =SUM(AN118:AQ118) -> 0 | AS118: 0 | AT118: 0 | AU118: 0 | AV118: 0 | AW118: =SUM(AS118:AV118) -> 0 | AX118: 0 | AY118: 0 | AZ118: 0 | BA118: 0 | BB118: =SUM(AX118:BA118) -> 0 | BC118: 0 | BD118: 0 | BE118: 0 | BF118: 0 | BG118: =SUM(BC118:BF118) -> 0 | BH118: 0 | BI118: 0 | BJ118: 0 | BK118: 0 | BL118: =SUM(BH118:BK118) -> 0 | BM118: 0 | BN118: 0 | BO118: 0 | BP118: 0 | BQ118: =SUM(BM118:BP118) -> 0 | BR118: 0 | BS118: 0 | BT118: 0 | BU118: 0 | BV118: =SUM(BR118:BU118) -> 0 | BW118: 0 | BX118: 0 | BY118: 0 | BZ118: 0 | CA118: =SUM(BW118:BZ118) -> 0 | CD118: =A118 -> Employee Compensation Expense | CE118: =D118 -> 1.909 | CF118: =I118 -> 2.182 | CG118: =N118 -> -0.091 | CH118: =S118 -> 4.039 | CI118: =X118 -> 0.789 | CJ118: =AC118 -> 0.585 | CK118: =AH118 -> 0 | CL118: =AM118 -> 0 | CM118: =AR118 -> 0 | CN118: =AW118 -> 0 | CO118: =BB118 -> 0 | CP118: =BG118 -> 0 | CQ118: =BL118 -> 0 | CR118: =BQ118 -> 0 | CS118: =BV118 -> 0 | CT118: =CA118 -> 0
A119: Deferred Taxes | C119: -7.776 | D119: -11.848 | E119: -0.381 | F119: =0-E119 -> 0.381 | G119: =0-SUM(E119:F119) -> 0 | H119: =-5.698-SUM(E119:G119) -> -5.698 | I119: =SUM(E119:H119) -> -5.698 | J119: 0.567 | K119: =0-J119 -> -0.567 | L119: =0-SUM(J119:K119) -> 0 | M119: =19.895-SUM(J119:L119) -> 19.895 | N119: =SUM(J119:M119) -> 19.895 | O119: 0.766 | P119: =-0.199-O119 -> -0.965 | Q119: =4.99-SUM(O119:P119) -> 5.189 | R119: =12.19-SUM(O119:Q119) -> 7.2 | S119: =SUM(O119:R119) -> 12.19 | T119: =0.973 -> 0.973 | U119: =0.507-T119 -> -0.466 | V119: =-1.893-SUM(T119:U119) -> -2.4 | W119: =10.294-SUM(T119:V119) -> 12.187 | X119: =SUM(T119:W119) -> 10.294 | Y119: -0.158 | Z119: =1.66-Y119 -> 1.818 | AA119: =-2.083-SUM(Y119:Z119) -> -3.743 | AB119: =21.321-SUM(Y119:AA119) -> 23.404 | AC119: =SUM(Y119:AB119) -> 21.321 | AD119: -0.349 | AE119: =-0.535-AD119 -> -0.186 | AF119: =-0.526-SUM(AD119:AE119) -> 0.009 | AG119: =63.261-SUM(AD119:AF119) -> 63.787 | AH119: =SUM(AD119:AG119) -> 63.261 | AI119: 0.622 | AJ119: =1.007-AI119 -> 0.385 | AK119: =5.888-SUM(AI119:AJ119) -> 4.881 | AL119: =44.14-SUM(AI119:AK119) -> 38.252 | AM119: =SUM(AI119:AL119) -> 44.14 | AN119: -3.64 | AO119: =-3.519-AN119 -> 0.121 | AP119: =-3.348-SUM(AN119:AO119) -> 0.171 | AQ119: =24.491-SUM(AN119:AP119) -> 27.839 | AR119: =SUM(AN119:AQ119) -> 24.491 | AS119: 0.506 | AT119: =-7.39-AS119 -> -7.896 | AU119: =1.498-SUM(AS119:AT119) -> 8.888 | AV119: =-4.05-SUM(AS119:AU119) -> -5.548 | AW119: =SUM(AS119:AV119) -> -4.05 | AX119: 17.807 | AY119: =6.123-AX119 -> -11.684 | AZ119: =-1.733-SUM(AX119:AY119) -> -7.856 | BA119: =14.8-SUM(AX119:AZ119) -> 16.533 | BB119: =SUM(AX119:BA119) -> 14.8 | BC119: -0.7 | BD119: 0.6 | BE119: =-4.1-BD119-BC119 -> -4 | BF119: =-73.6-SUM(BC119:BE119) -> -69.5 | BG119: =SUM(BC119:BF119) -> -73.6 | BH119: =(BG178-BH178)+(BG188-BH188) -> 0 | BI119: =(BH178-BI178)+(BH188-BI188) -> 0 | BJ119: =(BI178-BJ178)+(BI188-BJ188) -> 0 | BK119: =(BJ178-BK178)+(BJ188-BK188) -> 0 | BL119: =SUM(BH119:BK119) -> 0 | BM119: =(BL178-BM178)+(BL188-BM188) -> 0 | BN119: =(BM178-BN178)+(BM188-BN188) -> 0 | BO119: =(BN178-BO178)+(BN188-BO188) -> 0 | BP119: =(BO178-BP178)+(BO188-BP188) -> 0 | BQ119: =SUM(BM119:BP119) -> 0 | BR119: =(BQ178-BR178)+(BQ188-BR188) -> 0 | BS119: =(BR178-BS178)+(BR188-BS188) -> 0 | BT119: =(BS178-BT178)+(BS188-BT188) -> 0 | BU119: =(BT178-BU178)+(BT188-BU188) -> 0 | BV119: =SUM(BR119:BU119) -> 0 | BW119: =(BV178-BW178)+(BV188-BW188) -> 0 | BX119: =(BW178-BX178)+(BW188-BX188) -> 0 | BY119: =(BX178-BY178)+(BX188-BY188) -> 0 | BZ119: =(BY178-BZ178)+(BY188-BZ188) -> 0 | CA119: =SUM(BW119:BZ119) -> 0 | CD119: =A119 -> Deferred Taxes | CE119: =D119 -> -11.848 | CF119: =I119 -> -5.698 | CG119: =N119 -> 19.895 | CH119: =S119 -> 12.19 | CI119: =X119 -> 10.294 | CJ119: =AC119 -> 21.321 | CK119: =AH119 -> 63.261 | CL119: =AM119 -> 44.14 | CM119: =AR119 -> 24.491 | CN119: =AW119 -> -4.05 | CO119: =BB119 -> 14.8 | CP119: =BG119 -> -73.6 | CQ119: =BL119 -> 0 | CR119: =BQ119 -> 0 | CS119: =BV119 -> 0 | CT119: =CA119 -> 0
A120: Tax benefit on stock options exercised | C120: -27.852 | D120: -31.964 | E120: -8.821 | F120: =-12.428-E120 -> -3.607 | G120: =-12.461-SUM(E120:F120) -> -0.033 | H120: =-12.798-SUM(E120:G120) -> -0.337 | I120: =SUM(E120:H120) -> -12.798 | J120: -13.684 | K120: =-17.032-J120 -> -3.348 | L120: =-17.101-SUM(J120:K120) -> -0.069 | M120: =-26.099-SUM(J120:L120) -> -8.998 | N120: =SUM(J120:M120) -> -26.099 | O120: -0.171 | P120: =-0.658-O120 -> -0.487 | Q120: =-1.723-SUM(O120:P120) -> -1.065 | R120: =-19.976-SUM(O120:Q120) -> -18.253 | S120: =SUM(O120:R120) -> -19.976 | T120: -0.147 | U120: =-10.036-T120 -> -9.889 | V120: =-15.083-SUM(T120:U120) -> -5.047 | W120: =-49.015-T120-U120-V120 -> -33.932 | X120: =SUM(T120:W120) -> -49.015 | Y120: 0 | Z120: =-5.47-Y120 -> -5.47 | AA120: =-5.47-SUM(Y120:Z120) -> 0 | AB120: =-53.195-SUM(Y120:AA120) -> -47.725 | AC120: =SUM(Y120:AB120) -> -53.195 | AD120: 0 | AE120: =-31.624-AD120 -> -31.624 | AF120: =-55.056-SUM(AD120:AE120) -> -23.432 | AG120: =-60.672-SUM(AD120:AF120) -> -5.616 | AH120: =SUM(AD120:AG120) -> -60.672 | AI120: -36.128 | AJ120: =-63.934-AI120 -> -27.806 | AK120: =-81.689-SUM(AI120:AJ120) -> -17.755 | AL120: =-109.946-SUM(AI120:AK120) -> -28.257 | AM120: =SUM(AI120:AL120) -> -109.946 | AN120: 0 | AO120: =-6.094-AN120 -> -6.094 | AP120: =-16.665-SUM(AN120:AO120) -> -10.571 | AQ120: =-22.566-SUM(AN120:AP120) -> -5.901 | AR120: =SUM(AN120:AQ120) -> -22.566 | AS120: 0 | AT120: -8.419 | AU120: =-18.214-SUM(AS120:AT120) -> -9.795 | AV120: =-40.147-SUM(AS120:AU120) -> -21.933 | AW120: =SUM(AS120:AV120) -> -40.147 | AX120: 0 | AY120: =-6.57-AX120 -> -6.57 | AZ120: =-20.763-SUM(AX120:AY120) -> -14.193 | BA120: =-31.4-SUM(AX120:AZ120) -> -10.637 | BB120: =SUM(AX120:BA120) -> -31.4 | BC120: 0 | BD120: 0 | BE120: 0 | BF120: 0 | BG120: =SUM(BC120:BF120) -> 0 | BH120: 0 | BI120: 0 | BJ120: 0 | BK120: 0 | BL120: =SUM(BH120:BK120) -> 0 | BM120: 0 | BN120: 0 | BO120: 0 | BP120: 0 | BQ120: =SUM(BM120:BP120) -> 0 | BR120: 0 | BS120: 0 | BT120: 0 | BU120: 0 | BV120: =SUM(BR120:BU120) -> 0 | BW120: 0 | BX120: 0 | BY120: 0 | BZ120: 0 | CA120: =SUM(BW120:BZ120) -> 0 | CD120: =A120 -> Tax benefit on stock options exercised | CE120: =D120 -> -31.964 | CF120: =I120 -> -12.798 | CG120: =N120 -> -26.099 | CH120: =S120 -> -19.976 | CI120: =X120 -> -49.015 | CJ120: =AC120 -> -53.195 | CK120: =AH120 -> -60.672 | CL120: =AM120 -> -109.946 | CM120: =AR120 -> -22.566 | CN120: =AW120 -> -40.147 | CO120: =BB120 -> -31.4 | CP120: =BG120 -> 0 | CQ120: =BL120 -> 0 | CR120: =BQ120 -> 0 | CS120: =BV120 -> 0 | CT120: =CA120 -> 0
A121: Loss (Gain) on disposal of assets | C121: 0 | D121: 2.374 | E121: 1.419 | F121: =1.416-E121 -> -0.003 | G121: =1.551-SUM(E121:F121) -> 0.135 | H121: =1.791-SUM(E121:G121) -> 0.24 | I121: =SUM(E121:H121) -> 1.791 | J121: -0.009 | K121: =0-J121 -> 0.009 | L121: =0.031-SUM(J121:K121) -> 0.031 | M121: =1.082-SUM(J121:L121) -> 1.051 | N121: =SUM(J121:M121) -> 1.082 | O121: 0.228 | P121: =0.308-O121 -> 0.08 | Q121: =0.342-SUM(O121:P121) -> 0.034 | R121: =0.81-SUM(O121:Q121) -> 0.468 | S121: =SUM(O121:R121) -> 0.81 | T121: =0.011 -> 0.011 | U121: =0.038-T121 -> 0.027 | V121: =0.081-SUM(T121:U121) -> 0.043 | W121: =0.239-SUM(T121:V121) -> 0.158 | X121: =SUM(T121:W121) -> 0.239 | Y121: 0.096 | Z121: =0.221-Y121 -> 0.125 | AA121: =0.635-SUM(Y121:Z121) -> 0.414 | AB121: =0.868-SUM(Y121:AA121) -> 0.233 | AC121: =SUM(Y121:AB121) -> 0.868 | AD121: =-0.007 -> -0.007 | AE121: =0.021-AD121 -> 0.028 | AF121: =0.088-SUM(AD121:AE121) -> 0.067 | AG121: =0.597-SUM(AD121:AF121) -> 0.509 | AH121: =SUM(AD121:AG121) -> 0.597 | AI121: 0.426 | AJ121: =0.428-AI121 -> 0.002 | AK121: =0.476-SUM(AI121:AJ121) -> 0.048 | AL121: =0.628-SUM(AI121:AK121) -> 0.152 | AM121: =SUM(AI121:AL121) -> 0.628 | AN121: =-65.41+0.683 -> -64.727 | AO121: =-65.41-AN121 -> -0.683 | AP121: =-65.41+0.51-SUM(AN121:AO121) -> 0.51 | AQ121: =-65.41-SUM(AN121:AP121) -> -0.51 | AR121: =SUM(AN121:AQ121) -> -65.41 | AS121: 0.015 | AT121: =-0.003-AS121 -> -0.018 | AU121: =-0.002-SUM(AS121:AT121) -> 0.001 | AV121: =0.379-SUM(AS121:AU121) -> 0.381 | AW121: =SUM(AS121:AV121) -> 0.379 | AX121: -0.093 | AY121: =0.811-AX121 -> 0.904 | AZ121: =0.851-SUM(AX121:AY121) -> 0.04 | BA121: =1-SUM(AX121:AZ121) -> 0.149 | BB121: =SUM(AX121:BA121) -> 1 | BC121: 0 | BD121: 0 | BE121: 0 | BF121: =0.1-SUM(BC121:BE121) -> 0.1 | BG121: =SUM(BC121:BF121) -> 0.1 | BH121: 0 | BI121: 0 | BJ121: 0 | BK121: 0 | BL121: =SUM(BH121:BK121) -> 0 | BM121: 0 | BN121: 0 | BO121: 0 | BP121: 0 | BQ121: =SUM(BM121:BP121) -> 0 | BR121: 0 | BS121: 0 | BT121: 0 | BU121: 0 | BV121: =SUM(BR121:BU121) -> 0 | BW121: 0 | BX121: 0 | BY121: 0 | BZ121: 0 | CA121: =SUM(BW121:BZ121) -> 0 | CD121: =A121 -> Loss (Gain) on disposal of assets | CE121: =D121 -> 2.374 | CF121: =I121 -> 1.791 | CG121: =N121 -> 1.082 | CH121: =S121 -> 0.81 | CI121: =X121 -> 0.239 | CJ121: =AC121 -> 0.868 | CK121: =AH121 -> 0.597 | CL121: =AM121 -> 0.628 | CM121: =AR121 -> -65.41 | CN121: =AW121 -> 0.379 | CO121: =BB121 -> 1 | CP121: =BG121 -> 0.1 | CQ121: =BL121 -> 0 | CR121: =BQ121 -> 0 | CS121: =BV121 -> 0 | CT121: =CA121 -> 0
A122: Gain/Losses on Securities | C122: -0.027 | D122: 0.375 | E122: -0.012 | F122: =-0.592-E122 -> -0.58 | G122: =-0.854-SUM(E122:F122) -> -0.262 | H122: =-0.857-SUM(E122:G122) -> -0.003 | I122: =SUM(E122:H122) -> -0.857 | J122: 1.274 | K122: =1.286-J122 -> 0.012 | L122: =1.665-SUM(J122:K122) -> 0.379 | M122: =2.511-SUM(J122:L122) -> 0.846 | N122: =SUM(J122:M122) -> 2.511 | O122: 0.398 | P122: =0.365-O122 -> -0.033 | Q122: =0.341-SUM(O122:P122) -> -0.024 | R122: =2.332-SUM(O122:Q122) -> 1.991 | S122: =SUM(O122:R122) -> 2.332 | T122: =-0.032 -> -0.032 | U122: =-0.061-T122 -> -0.029 | V122: =-0.07-SUM(T122:U122) -> -0.009 | W122: =-0.095-SUM(T122:V122) -> -0.025 | X122: =SUM(T122:W122) -> -0.095 | Y122: =-0.362 -> -0.362 | Z122: =-0.487-Y122 -> -0.125 | AA122: =0-SUM(Y122:Z122) -> 0.487 | AB122: =-0.686-SUM(Y122:AA122) -> -0.686 | AC122: =SUM(Y122:AB122) -> -0.686 | AD122: =-0.33 -> -0.33 | AE122: =-0.3-AD122 -> 0.03 | AF122: =0.338-SUM(AD122:AE122) -> 0.638 | AG122: =0.332-SUM(AD122:AF122) -> -0.006 | AH122: =SUM(AD122:AG122) -> 0.332 | AI122: 0.193 | AJ122: =0.1-AI122 -> -0.093 | AK122: =0.099-SUM(AI122:AJ122) -> -0.001 | AL122: =0.092-SUM(AI122:AK122) -> -0.007 | AM122: =SUM(AI122:AL122) -> 0.092 | AN122: 0.011 | AO122: =-0.115-AN122 -> -0.126 | AP122: =-0.122-AO122-AN122 -> -0.007 | AQ122: =-0.257-SUM(AN122:AP122) -> -0.135 | AR122: =SUM(AN122:AQ122) -> -0.257 | AS122: 0.006 | AT122: =-AT47 -> -85.187 | AU122: 0 | AV122: 0 | AW122: =SUM(AS122:AV122) -> -85.181 | AX122: 0.19 | AY122: =0.274-AX122 -> 0.084 | AZ122: =0.311-SUM(AX122:AY122) -> 0.037 | BA122: 0.2 | BB122: =SUM(AX122:BA122) -> 0.511 | BC122: 0 | BD122: 0 | BE122: =-0.1-BD122-BC122 -> -0.1 | BF122: =0-SUM(BC122:BE122) -> 0.1 | BG122: =SUM(BC122:BF122) -> 0 | BH122: 0 | BI122: 0 | BJ122: 0 | BK122: 0 | BL122: =SUM(BH122:BK122) -> 0 | BM122: 0 | BN122: 0 | BO122: 0 | BP122: 0 | BQ122: =SUM(BM122:BP122) -> 0 | BR122: 0 | BS122: 0 | BT122: 0 | BU122: 0 | BV122: =SUM(BR122:BU122) -> 0 | BW122: 0 | BX122: 0 | BY122: 0 | BZ122: 0 | CA122: =SUM(BW122:BZ122) -> 0 | CD122: =A122 -> Gain/Losses on Securities | CE122: =D122 -> 0.375 | CF122: =I122 -> -0.857 | CG122: =N122 -> 2.511 | CH122: =S122 -> 2.332 | CI122: =X122 -> -0.095 | CJ122: =AC122 -> -0.686 | CK122: =AH122 -> 0.332 | CL122: =AM122 -> 0.092 | CM122: =AR122 -> -0.257 | CN122: =AW122 -> -85.181 | CO122: =BB122 -> 0.511 | CP122: =BG122 -> 0 | CQ122: =BL122 -> 0 | CR122: =BQ122 -> 0 | CS122: =BV122 -> 0 | CT122: =CA122 -> 0
A123: Goodwill Impairment | C123: 1.5 | D123: 0 | E123: 0 | F123: 0 | G123: =1.744-SUM(E123:F123) -> 1.744 | H123: =1.744-SUM(E123:G123) -> 0 | I123: =SUM(E123:H123) -> 1.744 | J123: 0 | K123: =0-J123 -> 0 | L123: =0-SUM(J123:K123) -> 0 | M123: =0-SUM(J123:L123) -> 0 | N123: =SUM(J123:M123) -> 0 | O123: 0 | P123: 0 | Q123: 0 | R123: 0 | S123: =SUM(O123:R123) -> 0 | T123: 0 | U123: =0-T123 -> 0 | V123: =0-SUM(T123:U123) -> 0 | W123: 0 | X123: =SUM(T123:W123) -> 0 | Y123: 0 | Z123: 0 | AA123: 0 | AB123: 0 | AC123: =SUM(Y123:AB123) -> 0 | AD123: 0 | AE123: 0 | AF123: 0 | AG123: 0 | AH123: =SUM(AD123:AG123) -> 0 | AI123: 0 | AJ123: 0 | AK123: 0 | AL123: 0 | AM123: =SUM(AI123:AL123) -> 0 | AN123: 0 | AO123: 0 | AP123: 0 | AQ123: 0 | AR123: =SUM(AN123:AQ123) -> 0 | AS123: 0 | AT123: 0 | AU123: 0 | AV123: 0 | AW123: =SUM(AS123:AV123) -> 0 | AX123: 0 | AY123: 0 | AZ123: 0 | BA123: 0 | BB123: =SUM(AX123:BA123) -> 0 | BC123: 0 | BD123: 0 | BE123: 0 | BF123: 0 | BG123: =SUM(BC123:BF123) -> 0 | BH123: 0 | BI123: 0 | BJ123: 0 | BK123: 0 | BL123: =SUM(BH123:BK123) -> 0 | BM123: 0 | BN123: 0 | BO123: 0 | BP123: 0 | BQ123: =SUM(BM123:BP123) -> 0 | BR123: 0 | BS123: 0 | BT123: 0 | BU123: 0 | BV123: =SUM(BR123:BU123) -> 0 | BW123: 0 | BX123: 0 | BY123: 0 | BZ123: 0 | CA123: =SUM(BW123:BZ123) -> 0 | CD123: =A123 -> Goodwill Impairment | CE123: =D123 -> 0 | CF123: =I123 -> 1.744 | CG123: =N123 -> 0 | CH123: =S123 -> 0 | CI123: =X123 -> 0 | CJ123: =AC123 -> 0 | CK123: =AH123 -> 0 | CL123: =AM123 -> 0 | CM123: =AR123 -> 0 | CN123: =AW123 -> 0 | CO123: =BB123 -> 0 | CP123: =BG123 -> 0 | CQ123: =BL123 -> 0 | CR123: =BQ123 -> 0 | CS123: =BV123 -> 0 | CT123: =CA123 -> 0
A124: Other | C124: =0.185-1.516 -> -1.331 | D124: =2.148+9.027+0.216-2.19 -> 9.201 | E124: =0.014+0.275-0.584 -> -0.295 | F124: =1.006+2.426-1.129+0.291-E124 -> 2.889 | G124: =-1.763+3.673+0.483+0.283+2.366-SUM(E124:F124) -> 2.448 | H124: =3.286+3.605+0.298-2.454-SUM(E124:G124) -> -0.307 | I124: =SUM(E124:H124) -> 4.735 | J124: =0.014+0.3-0.458 -> -0.144 | K124: =1.093+0.55-0.98+0.03-J124 -> 0.837 | L124: =0.282-1.142+0.55+0.266-SUM(J124:K124) -> -0.737 | M124: =1.536+0.3+0.284-1.05+2.318-SUM(J124:L124) -> 3.432 | N124: =SUM(J124:M124) -> 3.388 | O124: =0.015+0.349 -> 0.364 | P124: =0.509+0.03+0.196-O124 -> 0.371 | Q124: =0.692+0.207+0.196-SUM(O124:P124) -> 0.36 | R124: =0.785+0.916+0.222+0.196-SUM(O124:Q124) -> 1.024 | S124: =SUM(O124:R124) -> 2.119 | T124: =0.395+0.105+0.015 -> 0.515 | U124: =0.789+0.526+0.03-T124-0.2 -> 0.63 | V124: =1.156+0.562+-0.544+0.183-SUM(T124:U124) -> 0.212 | W124: =1.463+0.648+-0.544+0.198-SUM(T124:V124) -> 0.408 | X124: =SUM(T124:W124) -> 1.765 | Y124: =0.309+0.151+0.015 -> 0.475 | Z124: =0.729+0.025+-3.364+0.03+0.557-Y124 -> -2.498 | AA124: =1.155+0.051+0.852+-3.364+-0.401+0.133-SUM(Y124:Z124) -> 0.449 | AB124: =1.655+1.278+-3.364+0.132-SUM(Y124:AA124) -> 1.275 | AC124: =SUM(Y124:AB124) -> -0.299 | AD124: =0.355+0.545+0.01 -> 0.91 | AE124: =1.096+0.461+-0.018-AD124 -> 0.629 | AF124: =1.649+0.576+0.215-AE124-AD124 -> 0.901 | AG124: =2.337+1.065+0.265-SUM(AD124:AF124) -> 1.227 | AH124: =SUM(AD124:AG124) -> 3.667 | AI124: =0.688+0.298-0.007+15.214-AI114+17.207-AI115 -> 2.185 | AJ124: =(1.368+0.633+0.028)-AI124+1.2 -> 1.044 | AK124: =2.048+1.188+0.448-SUM(AI124:AJ124)+1.2 -> 1.655 | AL124: =2.713+2.482+0.448+70.279-AM114+64.299-AM115-SUM(AI124:AK124) -> 5.407 | AM124: =SUM(AI124:AL124) -> 10.291 | AN124: =0.661-0.227+20.776-AN114+14.323-AN115 -> 1.54 | AO124: =0.735+0.347+1.322+(41.499-SUM(AN114:AO114)+28.544-SUM(AN115:AO115)-AN124) -> 1.97 | AP124: =1.989+0.953+42.731-SUM(AN115:AP115)+63.45-SUM(AN114:AP114)-SUM(AN124:AO124) -> 0.538 | AQ124: =2.638+1.814+1.048-SUM(AN124:AP124) -> 1.452 | AR124: =SUM(AN124:AQ124) -> 5.5 | AS124: =1.195+0.125 -> 1.32 | AT124: =10.634-AS124-0.014-0.003+0.456 -> 9.753 | AU124: =1.151+0.019-15.602+11.77-SUM(AS124:AT124)-0.006 -> -13.741 | AV124: =1.305-15.602+12.899+0.547+0.2-SUM(AS124:AU124) -> 2.017 | AW124: =SUM(AS124:AV124) -> -0.651 | AX124: =1.128+0.518 -> 1.646 | AY124: =2.472+1.327-269.385-AX124 -> -267.232 | AZ124: =-1.464-269.385-AY124+1.483-AX124+3.999 -> 0.219 | BA124: =+-265.9-1.5-SUM(AX124:AZ124)+2.4+5 -> 5.367 | BB124: =SUM(AX124:BA124) -> -260 | BC124: =1.1+0.8 -> 1.9 | BD124: =2.1+0.8-BC124 -> 1 | BE124: =3.1+1.4-BD124-BC124 -> 1.6 | BF124: =4.2-SUM(BC124:BE124)+2 -> 1.7 | BG124: =SUM(BC124:BF124) -> 6.2 | BH124: =(BH199-BG199)+(BH207-BG207)+(BH208-BG208) -> 0 | BI124: =(BI199-BH199)+(BI207-BH207)+(BI208-BH208) -> 0 | BJ124: =(BJ199-BI199)+(BJ207-BI207)+(BJ208-BI208) -> 0 | BK124: =(BK199-BJ199)+(BK207-BJ207)+(BK208-BJ208) -> 0 | BL124: =SUM(BH124:BK124) -> 0 | BM124: =(BM199-BL199)+(BM207-BL207)+(BM208-BL208) -> 0 | BN124: =(BN199-BM199)+(BN207-BM207)+(BN208-BM208) -> 0 | BO124: =(BO199-BN199)+(BO207-BN207)+(BO208-BN208) -> 0 | BP124: =(BP199-BO199)+(BP207-BO207)+(BP208-BO208) -> 0 | BQ124: =SUM(BM124:BP124) -> 0 | BR124: =(BR199-BQ199)+(BR207-BQ207)+(BR208-BQ208) -> 0 | BS124: =(BS199-BR199)+(BS207-BR207)+(BS208-BR208) -> 0 | BT124: =(BT199-BS199)+(BT207-BS207)+(BT208-BS208) -> 0 | BU124: =(BU199-BT199)+(BU207-BT207)+(BU208-BT208) -> 0 | BV124: =SUM(BR124:BU124) -> 0 | BW124: =(BW199-BV199)+(BW207-BV207)+(BW208-BV208) -> 0 | BX124: =(BX199-BW199)+(BX207-BW207)+(BX208-BW208) -> 0 | BY124: =(BY199-BX199)+(BY207-BX207)+(BY208-BX208) -> 0 | BZ124: =(BZ199-BY199)+(BZ207-BY207)+(BZ208-BY208) -> 0 | CA124: =SUM(BW124:BZ124) -> 0 | CD124: =A124 -> Other | CE124: =D124 -> 9.201 | CF124: =I124 -> 4.735 | CG124: =N124 -> 3.388 | CH124: =S124 -> 2.119 | CI124: =X124 -> 1.765 | CJ124: =AC124 -> -0.299 | CK124: =AH124 -> 3.667 | CL124: =AM124 -> 10.291 | CM124: =AR124 -> 5.5 | CN124: =AW124 -> -0.651 | CO124: =BB124 -> -260 | CP124: =BG124 -> 6.2 | CQ124: =BL124 -> 0 | CR124: =BQ124 -> 0 | CS124: =BV124 -> 0 | CT124: =CA124 -> 0
A125: Net Changes in Operating Assets and Liabilities | CD125: =A125 -> Net Changes in Operating Assets and Liabilities | CE125: =D125 -> 0 | CF125: =I125 -> 0 | CG125: =N125 -> 0 | CH125: =S125 -> 0 | CI125: =X125 -> 0 | CJ125: =AC125 -> 0 | CK125: =AH125 -> 0 | CL125: =AM125 -> 0 | CM125: =AR125 -> 0 | CN125: =AW125 -> 0 | CO125: =BB125 -> 0 | CP125: =BG125 -> 0 | CQ125: =BL125 -> 0 | CR125: =BQ125 -> 0 | CS125: =BV125 -> 0 | CT125: =CA125 -> 0
A126: Accounts Receivable | C126: -12.263 | D126: -6.135 | E126: -18.812 | F126: =-4.17-E126 -> 14.642 | G126: =5.128-SUM(E126:F126) -> 9.298 | H126: =3.908-SUM(E126:G126) -> -1.22 | I126: =SUM(E126:H126) -> 3.908 | J126: -20.195 | K126: =-4.937-J126 -> 15.258 | L126: =4.145-SUM(J126:K126) -> 9.082 | M126: =3.609-SUM(J126:L126) -> -0.536 | N126: =SUM(J126:M126) -> 3.609 | O126: -28.219 | P126: =-20.256-O126 -> 7.963 | Q126: =-16.946-SUM(O126:P126) -> 3.31 | R126: =-1.99-SUM(O126:Q126) -> 14.956 | S126: =SUM(O126:R126) -> -1.99 | T126: -42.699 | U126: =-28.694-T126 -> 14.005 | V126: =-40.654-SUM(T126:U126) -> -11.96 | W126: =-24.559-SUM(T126:V126) -> 16.095 | X126: =SUM(T126:W126) -> -24.559 | Y126: -37.475 | Z126: =-16.979-Y126 -> 20.496 | AA126: =-24.445-SUM(Y126:Z126) -> -7.466 | AB126: =-25.926-SUM(Y126:AA126) -> -1.481 | AC126: =SUM(Y126:AB126) -> -25.926 | AD126: -34.479 | AE126: =-13.652-AD126 -> 20.827 | AF126: =-3.026-SUM(AD126:AE126) -> 10.626 | AG126: =-6.425-SUM(AD126:AF126) -> -3.399 | AH126: =SUM(AD126:AG126) -> -6.425 | AI126: -12.785 | AJ126: =-8.752-AI126 -> 4.033 | AK126: =9.475-SUM(AI126:AJ126) -> 18.227 | AL126: =2.106-SUM(AI126:AK126) -> -7.369 | AM126: =SUM(AI126:AL126) -> 2.106 | AN126: -7.078 | AO126: =-12.186-AN126 -> -5.108 | AP126: =-23.53-SUM(AN126:AO126) -> -11.344 | AQ126: =-54.515-SUM(AN126:AP126) -> -30.985 | AR126: =SUM(AN126:AQ126) -> -54.515 | AS126: -6.094 | AT126: =37.981-AS126 -> 44.075 | AU126: =39.651-SUM(AS126:AT126) -> 1.67 | AV126: =-14.609-SUM(AS126:AU126) -> -54.26 | AW126: =SUM(AS126:AV126) -> -14.609 | AX126: -34.016 | AY126: =21.179-AX126 -> 55.195 | AZ126: =32.608-SUM(AX126:AY126) -> 11.429 | BA126: =-5.7-SUM(AX126:AZ126) -> -38.308 | BB126: =SUM(AX126:BA126) -> -5.7 | BC126: -31 | BD126: =6.3-BC126 -> 37.3 | BE126: =4-BD126-BC126 -> -2.3 | BF126: =-45.5-SUM(BC126:BE126) -> -49.5 | BG126: =SUM(BC126:BF126) -> -45.5 | BH126: =BG175-BH175 -> 7.8406291 | BI126: =BH175-BI175 -> 40.972664 | BJ126: =BI175-BJ175 -> -14.684005 | BK126: =BJ175-BK175 -> -58.391834 | BL126: =SUM(BH126:BK126) -> -24.262545 | BM126: =BL175-BM175 -> 12.9662 | BN126: =BM175-BN175 -> 43.019118 | BO126: =BN175-BO175 -> -15.613964 | BP126: =BO175-BP175 -> -62.093921 | BQ126: =SUM(BM126:BP126) -> -21.722566 | BR126: =BQ175-BR175 -> 14.690785 | BS126: =BR175-BS175 -> 45.404925 | BT126: =BS175-BT175 -> -16.543478 | BU126: =BT175-BU175 -> -65.56636 | BV126: =SUM(BR126:BU126) -> -22.014129 | BW126: =BV175-BW175 -> 15.536446 | BX126: =BW175-BX175 -> 47.928446 | BY126: =BX175-BY175 -> -17.53005 | BZ126: =BY175-BZ175 -> -69.241924 | CA126: =SUM(BW126:BZ126) -> -23.307082 | CD126: =A126 -> Accounts Receivable | CE126: =D126 -> -6.135 | CF126: =I126 -> 3.908 | CG126: =N126 -> 3.609 | CH126: =S126 -> -1.99 | CI126: =X126 -> -24.559 | CJ126: =AC126 -> -25.926 | CK126: =AH126 -> -6.425 | CL126: =AM126 -> 2.106 | CM126: =AR126 -> -54.515 | CN126: =AW126 -> -14.609 | CO126: =BB126 -> -5.7 | CP126: =BG126 -> -45.5 | CQ126: =BL126 -> -24.262545 | CR126: =BQ126 -> -21.722566 | CS126: =BV126 -> -22.014129 | CT126: =CA126 -> -23.307082
A127: State/Federal Tax Receivables/Payable | C127: 25.938 | D127: =15.634+8.699 -> 24.333 | E127: =5.45+19.256 -> 24.706 | F127: =6.294-E127 -> -18.412 | G127: =10.825-SUM(E127:F127) -> 4.531 | H127: =18.137-5.075-SUM(E127:G127) -> 2.237 | I127: =SUM(E127:H127) -> 13.062 | J127: =3.003+25.433 -> 28.436 | K127: =5.352-J127 -> -23.084 | L127: =4.377-SUM(J127:K127) -> -0.975 | M127: =5.969-5.977-SUM(J127:L127) -> -4.385 | N127: =SUM(J127:M127) -> -0.008 | O127: =27.785-0.86 -> 26.925 | P127: =9.538+-3.901-O127 -> -21.288 | Q127: =10.46+-2.082-SUM(O127:P127) -> 2.741 | R127: =13.662+5.71-SUM(O127:Q127) -> 10.994 | S127: =SUM(O127:R127) -> 19.372 | T127: =32.937+6.405 -> 39.342 | U127: =17.929-1.387-T127 -> -22.8 | V127: =27.005+2.768-SUM(T127:U127) -> 13.231 | W127: =50.232-5.679-SUM(T127:V127) -> 14.78 | X127: =SUM(T127:W127) -> 44.553 | Y127: =35.954+4.83 -> 40.784 | Z127: =7.703+-0.14-Y127 -> -33.221 | AA127: =48.925+5.382-SUM(Y127:Z127) -> 46.744 | AB127: =48.356-1.397-SUM(Y127:AA127) -> -7.348 | AC127: =SUM(Y127:AB127) -> 46.959 | AD127: =40.511+6.754 -> 47.265 | AE127: =51.957+7.972-AD127 -> 12.664 | AF127: =84.621+14.887-SUM(AD127:AE127) -> 39.579 | AG127: =83.711-SUM(AD127:AF127) -> -15.797 | AH127: =SUM(AD127:AG127) -> 83.711 | AI127: 47.6 | AJ127: =24.171-AI127 -> -23.429 | AK127: =48.554-SUM(AI127:AJ127) -> 24.383 | AL127: =39.661-SUM(AI127:AK127) -> -8.893 | AM127: =SUM(AI127:AL127) -> 39.661 | AN127: 71.276 | AO127: =44.808-AN127 -> -26.468 | AP127: =45.369-SUM(AN127:AO127) -> 0.561 | AQ127: =13.76-SUM(AN127:AP127) -> -31.609 | AR127: =SUM(AN127:AQ127) -> 13.76 | AS127: 56.951 | AT127: =11.858-AS127 -> -45.093 | AU127: =44.716-SUM(AS127:AT127) -> 32.858 | AV127: =51.58-SUM(AS127:AU127) -> 6.864 | AW127: =SUM(AS127:AV127) -> 51.58 | AX127: 49.613 | AY127: =61.707-AX127 -> 12.094 | AZ127: =45.258-SUM(AX127:AY127) -> -16.449 | BA127: =8.7-SUM(AX127:AZ127) -> -36.558 | BB127: =SUM(AX127:BA127) -> 8.7 | BC127: 48.1 | BD127: =-3.3-BC127 -> -51.4 | BE127: =14.1-BD127-BC127 -> 17.4 | BF127: =22.7-SUM(BC127:BE127) -> 8.6 | BG127: =SUM(BC127:BF127) -> 22.7 | BH127: =(BG179-BH179)+(BH201-BG201)+(BG189-BH189) -> 0 | BI127: =(BH179-BI179)+(BI201-BH201)+(BH189-BI189) -> 0 | BJ127: =(BI179-BJ179)+(BJ201-BI201)+(BI189-BJ189) -> 0 | BK127: =(BJ179-BK179)+(BK201-BJ201)+(BJ189-BK189) -> 0 | BL127: =SUM(BH127:BK127) -> 0 | BM127: =(BL179-BM179)+(BM201-BL201)+(BL189-BM189) -> 0 | BN127: =(BM179-BN179)+(BN201-BM201)+(BM189-BN189) -> 0 | BO127: =(BN179-BO179)+(BO201-BN201)+(BN189-BO189) -> 0 | BP127: =(BO179-BP179)+(BP201-BO201)+(BO189-BP189) -> 0 | BQ127: =SUM(BM127:BP127) -> 0 | BR127: =(BQ179-BR179)+(BR201-BQ201)+(BQ189-BR189) -> 0 | BS127: =(BR179-BS179)+(BS201-BR201)+(BR189-BS189) -> 0 | BT127: =(BS179-BT179)+(BT201-BS201)+(BS189-BT189) -> 0 | BU127: =(BT179-BU179)+(BU201-BT201)+(BT189-BU189) -> 0 | BV127: =SUM(BR127:BU127) -> 0 | BW127: =(BV179-BW179)+(BW201-BV201)+(BV189-BW189) -> 0 | BX127: =(BW179-BX179)+(BX201-BW201)+(BW189-BX189) -> 0 | BY127: =(BX179-BY179)+(BY201-BX201)+(BX189-BY189) -> 0 | BZ127: =(BY179-BZ179)+(BZ201-BY201)+(BY189-BZ189) -> 0 | CA127: =SUM(BW127:BZ127) -> 0 | CD127: =A127 -> State/Federal Tax Receivables/Payable | CE127: =D127 -> 24.333 | CF127: =I127 -> 13.062 | CG127: =N127 -> -0.008 | CH127: =S127 -> 19.372 | CI127: =X127 -> 44.553 | CJ127: =AC127 -> 46.959 | CK127: =AH127 -> 83.711 | CL127: =AM127 -> 39.661 | CM127: =AR127 -> 13.76 | CN127: =AW127 -> 51.58 | CO127: =BB127 -> 8.7 | CP127: =BG127 -> 22.7 | CQ127: =BL127 -> 0 | CR127: =BQ127 -> 0 | CS127: =BV127 -> 0 | CT127: =CA127 -> 0
A128: Prepaid Expenses and Other Assets | C128: -3.486 | D128: -1.751 | E128: -2.941 | F128: =-5.182-E128 -> -2.241 | G128: =-0.048-SUM(E128:F128) -> 5.134 | H128: =2.213-SUM(E128:G128) -> 2.261 | I128: =SUM(E128:H128) -> 2.213 | J128: -6.753 | K128: =-4.426-J128 -> 2.327 | L128: =-3.479-SUM(J128:K128) -> 0.947 | M128: =-6.486-SUM(J128:L128) -> -3.007 | N128: =SUM(J128:M128) -> -6.486 | O128: -3.637 | P128: =-3.964-O128 -> -0.327 | Q128: =-2.241-SUM(O128:P128) -> 1.723 | R128: =-1.839-SUM(O128:Q128) -> 0.402 | S128: =SUM(O128:R128) -> -1.839 | T128: -4.591 | U128: =-5.504-T128 -> -0.913 | V128: =-1.331-SUM(T128:U128) -> 4.173 | W128: =0.899-SUM(T128:V128) -> 2.23 | X128: =SUM(T128:W128) -> 0.899 | Y128: -7.89 | Z128: =-8.082-Y128 -> -0.192 | AA128: =-3.229-SUM(Y128:Z128) -> 4.853 | AB128: =-2.72-SUM(Y128:AA128) -> 0.509 | AC128: =SUM(Y128:AB128) -> -2.72 | AD128: =-2.881 -> -2.881 | AE128: =4.289-AD128 -> 7.17 | AF128: =7.126-AE128-AD128 -> 2.837 | AG128: =0.55-SUM(AD128:AF128) -> -6.576 | AH128: =SUM(AD128:AG128) -> 0.55 | AI128: -2.624 | AJ128: =-1.696-AI128 -> 0.928 | AK128: =-4.727-SUM(AI128:AJ128) -> -3.031 | AL128: =-2.386-SUM(AI128:AK128) -> 2.341 | AM128: =SUM(AI128:AL128) -> -2.386 | AN128: -2.632 | AO128: =-13.593-AN128 -> -10.961 | AP128: =-12.102-SUM(AN128:AO128) -> 1.491 | AQ128: =-9.625-SUM(AN128:AP128) -> 2.477 | AR128: =SUM(AN128:AQ128) -> -9.625 | AS128: 2.861 | AT128: =9.747-AS128 -> 6.886 | AU128: =2.662-SUM(AS128:AT128) -> -7.085 | AV128: =12-SUM(AS128:AU128) -> 9.338 | AW128: =SUM(AS128:AV128) -> 12 | AX128: 4.088 | AY128: =-1.503-AX128 -> -5.591 | AZ128: =-15.053-SUM(AX128:AY128) -> -13.55 | BA128: =-16.6-SUM(AX128:AZ128) -> -1.547 | BB128: =SUM(AX128:BA128) -> -16.6 | BC128: -4.7 | BD128: =-18.2-BC128 -> -13.5 | BE128: =-26.4-BD128-BC128 -> -8.2 | BF128: =-30.6-SUM(BC128:BE128) -> -4.2 | BG128: =SUM(BC128:BF128) -> -30.6 | BH128: =BG177-BH177 -> -2.2629823 | BI128: =BH177-BI177 -> -1.0321029 | BJ128: =BI177-BJ177 -> -1.1044477 | BK128: =BJ177-BK177 -> -0.86108037 | BL128: =SUM(BH128:BK128) -> -5.2606133 | BM128: =BL177-BM177 -> -0.77193818 | BN128: =BM177-BN177 -> -1.1682945 | BO128: =BN177-BO177 -> -1.2205327 | BP128: =BO177-BP177 -> -0.9817208 | BQ128: =SUM(BM128:BP128) -> -4.1424862 | BR128: =BQ177-BR177 -> -0.76815356 | BS128: =BR177-BS177 -> -1.2816481 | BT128: =BS177-BT177 -> -1.342864 | BU128: =BT177-BU177 -> -1.0711567 | BV128: =SUM(BR128:BU128) -> -4.4638223 | BW128: =BV177-BW177 -> -0.84047716 | BX128: =BW177-BX177 -> -1.4063227 | BY128: =BX177-BY177 -> -1.4776228 | BZ128: =BY177-BZ177 -> -1.1689729 | CA128: =SUM(BW128:BZ128) -> -4.8933955 | CD128: =A128 -> Prepaid Expenses and Other Assets | CE128: =D128 -> -1.751 | CF128: =I128 -> 2.213 | CG128: =N128 -> -6.486 | CH128: =S128 -> -1.839 | CI128: =X128 -> 0.899 | CJ128: =AC128 -> -2.72 | CK128: =AH128 -> 0.55 | CL128: =AM128 -> -2.386 | CM128: =AR128 -> -9.625 | CN128: =AW128 -> 12 | CO128: =BB128 -> -16.6 | CP128: =BG128 -> -30.6 | CQ128: =BL128 -> -5.2606133 | CR128: =BQ128 -> -4.1424862 | CS128: =BV128 -> -4.4638223 | CT128: =CA128 -> -4.8933955
A129: Accounts Payable and Accrued Liabilities | C129: 9.656 | D129: 1.452 | E129: -29.08 | F129: =-15.888-E129 -> 13.192 | G129: =-14.874-SUM(E129:F129) -> 1.014 | H129: =1.759-SUM(E129:G129) -> 16.633 | I129: =SUM(E129:H129) -> 1.759 | J129: -34.581 | K129: =-16.088-J129 -> 18.493 | L129: =-9.082-SUM(J129:K129) -> 7.006 | M129: =3.075-SUM(J129:L129) -> 12.157 | N129: =SUM(J129:M129) -> 3.075 | O129: -24.06 | P129: =-11.196-O129 -> 12.864 | Q129: =1.359-SUM(O129:P129) -> 12.555 | R129: =2.986-SUM(O129:Q129) -> 1.627 | S129: =SUM(O129:R129) -> 2.986 | T129: -25.415 | U129: =-18.327-T129 -> 7.088 | V129: =-3.255-SUM(T129:U129) -> 15.072 | W129: =4.34-SUM(T129:V129) -> 7.595 | X129: =SUM(T129:W129) -> 4.34 | Y129: -22.1 | Z129: =-15.19-Y129 -> 6.91 | AA129: =12.509-SUM(Y129:Z129) -> 27.699 | AB129: =15.468-SUM(Y129:AA129) -> 2.959 | AC129: =SUM(Y129:AB129) -> 15.468 | AD129: =-20.966 -> -20.966 | AE129: =-24.124-AD129 -> -3.158 | AF129: =3.168-SUM(AD129:AE129) -> 27.292 | AG129: =11.256-SUM(AD129:AF129) -> 8.088 | AH129: =SUM(AD129:AG129) -> 11.256 | AI129: -36.206 | AJ129: =-12.833-AI129 -> 23.373 | AK129: =12.267-SUM(AI129:AJ129) -> 25.1 | AL129: =34.022-SUM(AI129:AK129) -> 21.755 | AM129: =SUM(AI129:AL129) -> 34.022 | AN129: -32.886 | AO129: =-26.674-AN129 -> 6.212 | AP129: =-2.164-SUM(AN129:AO129) -> 24.51 | AQ129: =12.675-SUM(AN129:AP129) -> 14.839 | AR129: =SUM(AN129:AQ129) -> 12.675 | AS129: -33.169 | AT129: =-27.393-AS129 -> 5.776 | AU129: =-1.175-SUM(AS129:AT129) -> 26.218 | AV129: =-8.832-SUM(AS129:AU129) -> -7.657 | AW129: =SUM(AS129:AV129) -> -8.832 | AX129: -46.156 | AY129: =-26.399-AX129 -> 19.757 | AZ129: =-7.205-SUM(AX129:AY129) -> 19.194 | BA129: =-2.6-SUM(AX129:AZ129) -> 4.605 | BB129: =SUM(AX129:BA129) -> -2.6 | BC129: -28.3 | BD129: =-16.6-BC129 -> 11.7 | BE129: =21.7-BD129-BC129 -> 38.3 | BF129: =28.5-SUM(BC129:BE129) -> 6.8 | BG129: =SUM(BC129:BF129) -> 28.5 | BH129: =BH196-BG196 -> -34.124943 | BI129: =BI196-BH196 -> -7.3671375 | BJ129: =BJ196-BI196 -> 45.778804 | BK129: =BK196-BJ196 -> 11.974596 | BL129: =SUM(BH129:BK129) -> 16.261321 | BM129: =BM196-BL196 -> -40.261093 | BN129: =BN196-BM196 -> -7.5960567 | BO129: =BO196-BN196 -> 48.237764 | BP129: =BP196-BO196 -> 12.867832 | BQ129: =SUM(BM129:BP129) -> 13.248446 | BR129: =BR196-BQ196 -> -42.996231 | BS129: =BS196-BR196 -> -8.0022911 | BT129: =BT196-BS196 -> 50.723372 | BU129: =BU196-BT196 -> 13.537876 | BV129: =SUM(BR129:BU129) -> 13.262726 | BW129: =BW196-BV196 -> -45.171826 | BX129: =BX196-BW196 -> -8.4314165 | BY129: =BY196-BX196 -> 53.341687 | BZ129: =BZ196-BY196 -> 14.244877 | CA129: =SUM(BW129:BZ129) -> 13.983322 | CD129: =A129 -> Accounts Payable and Accrued Liabilities | CE129: =D129 -> 1.452 | CF129: =I129 -> 1.759 | CG129: =N129 -> 3.075 | CH129: =S129 -> 2.986 | CI129: =X129 -> 4.34 | CJ129: =AC129 -> 15.468 | CK129: =AH129 -> 11.256 | CL129: =AM129 -> 34.022 | CM129: =AR129 -> 12.675 | CN129: =AW129 -> -8.832 | CO129: =BB129 -> -2.6 | CP129: =BG129 -> 28.5 | CQ129: =BL129 -> 16.261321 | CR129: =BQ129 -> 13.248446 | CS129: =BV129 -> 13.262726 | CT129: =CA129 -> 13.983322
A130: Fees Received in Advance | C130: 3.682 | D130: 27.219 | E130: 64.747 | F130: =34.777-E130 -> -29.97 | G130: =25.697-SUM(E130:F130) -> -9.08 | H130: =3.751-SUM(E130:G130) -> -21.946 | I130: =SUM(E130:H130) -> 3.751 | J130: 69.619 | K130: =49.151-J130 -> -20.468 | L130: =22.83-SUM(J130:K130) -> -26.321 | M130: =-1.042-SUM(J130:L130) -> -23.872 | N130: =SUM(J130:M130) -> -1.042 | O130: 88.692 | P130: =60.452-O130 -> -28.24 | Q130: =38.414-SUM(O130:P130) -> -22.038 | R130: =10.46-SUM(O130:Q130) -> -27.954 | S130: =SUM(O130:R130) -> 10.46 | T130: 88.273 | U130: =55.959-T130 -> -32.314 | V130: =29.551-SUM(T130:U130) -> -26.408 | W130: =20.984-SUM(T130:V130) -> -8.567 | X130: =SUM(T130:W130) -> 20.984 | Y130: 84.057 | Z130: =50.52-Y130 -> -33.537 | AA130: =24.841-SUM(Y130:Z130) -> -25.679 | AB130: =12.373-SUM(Y130:AA130) -> -12.468 | AC130: =SUM(Y130:AB130) -> 12.373 | AD130: 112.1 | AE130: =77.038-AD130 -> -35.062 | AF130: =39.588-SUM(AD130:AE130) -> -37.45 | AG130: =20.493-SUM(AD130:AF130) -> -19.095 | AH130: =SUM(AD130:AG130) -> 20.493 | AI130: 113.743 | AJ130: =86.866-AI130 -> -26.877 | AK130: =43.372-SUM(AI130:AJ130) -> -43.494 | AL130: =26.97-SUM(AI130:AK130) -> -16.402 | AM130: =SUM(AI130:AL130) -> 26.97 | AN130: 116.318 | AO130: =81.666-AN130 -> -34.652 | AP130: =26.651-SUM(AN130:AO130) -> -55.015 | AQ130: =22.114-SUM(AN130:AP130) -> -4.537 | AR130: =SUM(AN130:AQ130) -> 22.114 | AS130: 106.935 | AT130: =38.305-AS130 -> -68.63 | AU130: =-30.772-SUM(AS130:AT130) -> -69.077 | AV130: =-43.546-SUM(AS130:AU130) -> -12.774 | AW130: =SUM(AS130:AV130) -> -43.546 | AX130: 146.477 | AY130: =92.581-AX130 -> -53.896 | AZ130: =14.655-SUM(AX130:AY130) -> -77.926 | BA130: =-8.2-SUM(AX130:AZ130) -> -22.855 | BB130: =SUM(AX130:BA130) -> -8.2 | BC130: 168.1 | BD130: =111-BC130 -> -57.1 | BE130: =47.2-BD130-BC130 -> -63.8 | BF130: =29.2-SUM(BC130:BE130) -> -18 | BG130: =SUM(BC130:BF130) -> 29.2 | BH130: =(BH200-BG200) -> 182.32357 | BI130: =(BI200-BH200) -> -66.977282 | BJ130: =(BJ200-BI200) -> -75.152735 | BK130: =(BK200-BJ200) -> -13.17821 | BL130: =SUM(BH130:BK130) -> 27.015343 | BM130: =(BM200-BL200) -> 187.4445 | BN130: =(BN200-BM200) -> -70.308592 | BO130: =(BO200-BN200) -> -79.367126 | BP130: =(BP200-BO200) -> -13.581605 | BQ130: =SUM(BM130:BP130) -> 24.187181 | BR130: =(BR200-BQ200) -> 196.83947 | BS130: =(BS200-BR200) -> -74.206556 | BT130: =(BT200-BS200) -> -83.749495 | BU130: =(BU200-BT200) -> -14.371596 | BV130: =SUM(BR130:BU130) -> 24.511825 | BW130: =(BW200-BV200) -> 207.87536 | BX130: =(BX200-BW200) -> -78.329419 | BY130: =(BY200-BX200) -> -88.385363 | BZ130: =(BZ200-BY200) -> -15.209107 | CA130: =SUM(BW130:BZ130) -> 25.951475 | CD130: =A130 -> Fees Received in Advance | CE130: =D130 -> 27.219 | CF130: =I130 -> 3.751 | CG130: =N130 -> -1.042 | CH130: =S130 -> 10.46 | CI130: =X130 -> 20.984 | CJ130: =AC130 -> 12.373 | CK130: =AH130 -> 20.493 | CL130: =AM130 -> 26.97 | CM130: =AR130 -> 22.114 | CN130: =AW130 -> -43.546 | CO130: =BB130 -> -8.2 | CP130: =BG130 -> 29.2 | CQ130: =BL130 -> 27.015343 | CR130: =BQ130 -> 24.187181 | CS130: =BV130 -> 24.511825 | CT130: =CA130 -> 25.951475
A131: Acquisition related liabilities | C131: 0 | D131: -17.493 | E131: 0 | F131: =-14.007-E131 -> -14.007 | G131: =-14.007-SUM(E131:F131) -> 0 | H131: =-13.658-SUM(E131:G131) -> 0.349 | I131: =SUM(E131:H131) -> -13.658 | J131: 0 | K131: =-2.2-J131 -> -2.2 | L131: =-2.2-SUM(J131:K131) -> 0 | M131: =-2.2-SUM(J131:L131) -> 0 | N131: =SUM(J131:M131) -> -2.2 | O131: -0.3 | P131: =-0.3-O131 -> 0 | Q131: =-0.3-SUM(O131:P131) -> 0 | R131: =-0.3-SUM(O131:Q131) -> 0 | S131: =SUM(O131:R131) -> -0.3 | T131: 0 | U131: =0-T131 -> 0 | V131: =0-SUM(T131:U131) -> 0 | W131: =0-SUM(T131:V131) -> 0 | X131: =SUM(T131:W131) -> 0 | Y131: 0 | Z131: =0-Y131 -> 0 | AA131: =0-SUM(Y131:Z131) -> 0 | AB131: 0 | AC131: =SUM(Y131:AB131) -> 0 | AD131: 0 | AE131: =0-AD131 -> 0 | AF131: =0-SUM(AD131:AE131) -> 0 | AG131: =AG197-AF197 -> 0 | AH131: =SUM(AD131:AG131) -> 0 | AI131: 0 | AJ131: 0 | AK131: =AK197-AJ197 -> 0 | AL131: =AL197-AK197 -> 0 | AM131: =SUM(AI131:AL131) -> 0 | AN131: =AN197-AM197 -> 0 | AO131: 0 | AP131: =AP197-AO197 -> 0 | AQ131: =AQ197-AP197 -> 0 | AR131: =SUM(AN131:AQ131) -> 0 | AS131: 0 | AT131: 0 | AU131: 0 | AV131: =AV197-AU197 -> 0 | AW131: =SUM(AS131:AV131) -> 0 | AX131: 0 | AY131: 0 | AZ131: 0 | BA131: 0 | BB131: =SUM(AX131:BA131) -> 0 | BC131: 0 | BD131: 0 | BE131: 0 | BF131: 0 | BG131: =SUM(BC131:BF131) -> 0 | BH131: =BH197-BG197 -> 0 | BI131: =BI197-BH197 -> 0 | BJ131: =BJ197-BI197 -> 0 | BK131: =BK197-BJ197 -> 0 | BL131: =SUM(BH131:BK131) -> 0 | BM131: =BM197-BL197 -> 0 | BN131: =BN197-BM197 -> 0 | BO131: =BO197-BN197 -> 0 | BP131: =BP197-BO197 -> 0 | BQ131: =SUM(BM131:BP131) -> 0 | BR131: =BR197-BQ197 -> 0 | BS131: =BS197-BR197 -> 0 | BT131: =BT197-BS197 -> 0 | BU131: =BU197-BT197 -> 0 | BV131: =SUM(BR131:BU131) -> 0 | BW131: =BW197-BV197 -> 0 | BX131: =BX197-BW197 -> 0 | BY131: =BY197-BX197 -> 0 | BZ131: =BZ197-BY197 -> 0 | CA131: =SUM(BW131:BZ131) -> 0 | CD131: =A131 -> Acquisition related liabilities | CE131: =D131 -> -17.493 | CF131: =I131 -> -13.658 | CG131: =N131 -> -2.2 | CH131: =S131 -> -0.3 | CI131: =X131 -> 0 | CJ131: =AC131 -> 0 | CK131: =AH131 -> 0 | CL131: =AM131 -> 0 | CM131: =AR131 -> 0 | CN131: =AW131 -> 0 | CO131: =BB131 -> 0 | CP131: =BG131 -> 0 | CQ131: =BL131 -> 0 | CR131: =BQ131 -> 0 | CS131: =BV131 -> 0 | CT131: =CA131 -> 0
A132: Increase in Other Assets/Liabilities | C132: 1.246 | D132: =6.947 -> 6.947 | E132: 0.317 | F132: =0.591-E132 -> 0.274 | G132: =0.469-SUM(E132:F132) -> -0.122 | H132: =-0.237-SUM(E132:G132) -> -0.706 | I132: =SUM(E132:H132) -> -0.237 | J132: -0.592 | K132: =-0.692-J132 -> -0.1 | L132: =-3.834-SUM(J132:K132) -> -3.142 | M132: =-4.983-SUM(J132:L132) -> -1.149 | N132: =SUM(J132:M132) -> -4.983 | O132: =4.045 -> 4.045 | P132: =9.226-O132 -> 5.181 | Q132: =6.493-SUM(O132:P132) -> -2.733 | R132: =9.576-SUM(O132:Q132) -> 3.083 | S132: =SUM(O132:R132) -> 9.576 | T132: 1.049 | U132: =-3.316-T132 -> -4.365 | V132: =-8.874-SUM(T132:U132) -> -5.558 | W132: =-17.711-SUM(T132:V132) -> -8.837 | X132: =SUM(T132:W132) -> -17.711 | Y132: -4.957 | Z132: =-14.913-Y132 -> -9.956 | AA132: =-20.809-SUM(Y132:Z132) -> -5.896 | AB132: =-35.675-SUM(Y132:AA132) -> -14.866 | AC132: =SUM(Y132:AB132) -> -35.675 | AD132: =-11.59+-2.269 -> -13.859 | AE132: =-90.808+-7.617-AD132 -> -84.566 | AF132: =-97.809+-8.133-AE132-AD132 -> -7.517 | AG132: =-105.829-13.86-SUM(AD132:AF132) -> -13.747 | AH132: =SUM(AD132:AG132) -> -119.689 | AI132: =-1.93+-3.706 -> -5.636 | AJ132: =(-4.099-26.052)-AI132 -> -24.515 | AK132: =-6.532+-33.016-SUM(AI132:AJ132) -> -9.397 | AL132: =-11.392-41.593-SUM(AI132:AK132) -> -13.437 | AM132: =SUM(AI132:AL132) -> -52.985 | AN132: =-3.509-0.28 -> -3.789 | AO132: =-6.064+-0.848-AN132 -> -3.123 | AP132: =-9.763-0.522-SUM(AN132:AO132) -> -3.373 | AQ132: =-14.802+-1.042-SUM(AN132:AP132) -> -5.559 | AR132: =SUM(AN132:AQ132) -> -15.844 | AS132: =-3.264+-0.391 -> -3.655 | AT132: =-2.99-7.129-AS132 -> -6.464 | AU132: =2.148-10.552-SUM(AS132:AT132) -> 1.715 | AV132: =2.775-13.704-SUM(AS132:AU132) -> -2.525 | AW132: =SUM(AS132:AV132) -> -10.929 | AX132: =-4.218-2.58 -> -6.798 | AY132: =0.131-AX132-5.232 -> 1.697 | AZ132: =-3.17-SUM(AX132:AY132)-7.972 -> -6.041 | BA132: =-4.8-9.9-SUM(AX132:AZ132) -> -3.558 | BB132: =SUM(AX132:BA132) -> -14.7 | BC132: -6.9 | BD132: =-9.2-BC132 -> -2.3 | BE132: =-16.5-BD132-BC132 -> -7.3 | BF132: =-17.8-SUM(BC132:BE132) -> -1.3 | BG132: =SUM(BC132:BF132) -> -17.8 | BH132: =(BH202-BG202)+(BG180-BH180)+(BG190-BH190) -> 39.948774 | BI132: =(BI202-BH202)+(BH180-BI180)+(BH190-BI190) -> 0.93665758 | BJ132: =(BJ202-BI202)+(BI180-BJ180)+(BI190-BJ190) -> -27.295816 | BK132: =(BK202-BJ202)+(BJ180-BK180)+(BJ190-BK190) -> -31.398535 | BL132: =SUM(BH132:BK132) -> -17.808919 | BM132: =(BM202-BL202)+(BL180-BM180)+(BL190-BM190) -> 45.648928 | BN132: =(BN202-BM202)+(BM180-BN180)+(BM190-BN190) -> 0.79208428 | BO132: =(BO202-BN202)+(BN180-BO180)+(BN190-BO190) -> -28.933001 | BP132: =(BP202-BO202)+(BO180-BP180)+(BO190-BP190) -> -33.452564 | BQ132: =SUM(BM132:BP132) -> -15.944552 | BR132: =(BR202-BQ202)+(BQ180-BR180)+(BQ190-BR190) -> 48.93992 | BS132: =(BS202-BR202)+(BR180-BS180)+(BR190-BS190) -> 0.81829697 | BT132: =(BT202-BS202)+(BS180-BT180)+(BS190-BT190) -> -30.597935 | BU132: =(BU202-BT202)+(BT180-BU180)+(BT190-BU190) -> -35.318844 | BV132: =SUM(BR132:BU132) -> -16.158562 | BW132: =(BW202-BV202)+(BV180-BW180)+(BV190-BW190) -> 51.704306 | BX132: =(BX202-BW202)+(BW180-BX180)+(BW190-BX190) -> 0.84466201 | BY132: =(BY202-BX202)+(BX180-BY180)+(BX190-BY190) -> -32.362466 | BZ132: =(BZ202-BY202)+(BY180-BZ180)+(BY190-BZ190) -> -37.294102 | CA132: =SUM(BW132:BZ132) -> -17.107601 | CD132: =A132 -> Increase in Other Assets/Liabilities | CE132: =D132 -> 6.947 | CF132: =I132 -> -0.237 | CG132: =N132 -> -4.983 | CH132: =S132 -> 9.576 | CI132: =X132 -> -17.711 | CJ132: =AC132 -> -35.675 | CK132: =AH132 -> -119.689 | CL132: =AM132 -> -52.985 | CM132: =AR132 -> -15.844 | CN132: =AW132 -> -10.929 | CO132: =BB132 -> -14.7 | CP132: =BG132 -> -17.8 | CQ132: =BL132 -> -17.808919 | CR132: =BQ132 -> -15.944552 | CS132: =BV132 -> -16.158562 | CT132: =CA132 -> -17.107601
C133: ______ | D133: ______ | E133: ______ | F133: ______ | G133: ______ | H133: ______ | I133: ______ | J133: ______ | K133: ______ | L133: ______ | M133: ______ | N133: ______ | O133: ______ | P133: ______ | Q133: ______ | R133: ______ | S133: ______ | T133: ______ | U133: ______ | V133: ______ | W133: ______ | X133: ______ | Y133: ______ | Z133: ______ | AA133: ______ | AB133: ______ | AC133: ______ | AD133: ______ | AE133: ______ | AF133: ______ | AG133: ______ | AH133: ______ | AI133: ______ | AJ133: ______ | AK133: ______ | AL133: ______ | AM133: ______ | AN133: ______ | AO133: ______ | AP133: ______ | AQ133: ______ | AR133: ______ | AS133: ______ | AT133: ______ | AU133: ______ | AV133: ______ | AW133: ______ | AX133: ______ | AY133: ______ | AZ133: ______ | BA133: ______ | BB133: ______ | BC133: ______ | BD133: ______ | BE133: ______ | BF133: ______ | BG133: ______ | BH133: ______ | BI133: ______ | BJ133: ______ | BK133: ______ | BL133: ______ | BM133: ______ | BN133: ______ | BO133: ______ | BP133: ______ | BQ133: ______ | BR133: ______ | BS133: ______ | BT133: ______ | BU133: ______ | BV133: ______ | BW133: ______ | BX133: ______ | BY133: ______ | BZ133: ______ | CA133: ______
A134: Net Cash provided by Op. Activities from Cont. Ops. | C134: =SUM(C113:C124,C126:C132) -> 174.071 | D134: =SUM(D113:D124,D126:D132) -> 223.499 | E134: =SUM(E113:E124,E126:E132) -> 92.735 | F134: =SUM(F113:F124,F126:F132) -> 24.401 | G134: =SUM(G113:G124,G126:G132) -> 75.898 | H134: =SUM(H113:H124,H126:H132) -> 55.487 | I134: =SUM(I113:I124,I126:I132) -> 248.521 | J134: =SUM(J113:J124,J126:J132) -> 89.864 | ... CA134: =SUM(CA113:CA124,CA126:CA132) -> 1061.5427 | CD134: =A134 -> Net Cash provided by Op. Activities from Cont. Ops. | CE134: =D134 -> 223.499 | CF134: =I134 -> 248.521 | CG134: =N134 -> 247.906 | CH134: =S134 -> 326.401 | CI134: =X134 -> 336.032 | CJ134: =AC134 -> 375.721 | CK134: =AH134 -> 468.229 | CL134: =AM134 -> 506.938 | CM134: =AR134 -> 489.452 | CN134: =AW134 -> 623.708 | CO134: =BB134 -> 546.163 | CP134: =BG134 -> 743.5 | CQ134: =BL134 -> 879.53778 | CR134: =BQ134 -> 939.52343 | CS134: =BV134 -> 999.21663 | CT134: =CA134 -> 1061.5427
A136: Cash From Investing Activities | CD136: =A136 -> Cash From Investing Activities
A137: Capital Expenditures | C137: -24.019 | D137: -25.742 | E137: -14.406 | F137: =-23.05-E137 -> -8.644 | G137: =-28.328-SUM(E137:F137) -> -5.278 | H137: =-32.941-SUM(E137:G137) -> -4.613 | I137: =SUM(E137:H137) -> -32.941 | J137: -9.766 | K137: =-17.81-J137 -> -8.044 | L137: =-22.323-SUM(J137:K137) -> -4.513 | M137: =-30.652-SUM(J137:L137) -> -8.329 | N137: =SUM(J137:M137) -> -30.652 | O137: -8.359 | P137: =-16.195-O137 -> -7.836 | Q137: =-24.319-SUM(O137:P137) -> -8.124 | R137: =-38.694-SUM(O137:Q137) -> -14.375 | S137: =SUM(O137:R137) -> -38.694 | T137: -7.498 | U137: =-15.57-T137 -> -8.072 | V137: =-22.206-SUM(T137:U137) -> -6.636 | W137: =-38.641-T137-U137-V137 -> -16.435 | X137: =SUM(T137:W137) -> -38.641 | Y137: -13.648 | Z137: =-28.171-Y137 -> -14.523 | AA137: =-41.925-SUM(Y137:Z137) -> -13.754 | AB137: =-59.829-SUM(Y137:AA137) -> -17.904 | AC137: =SUM(Y137:AB137) -> -59.829 | AD137: -17.442 | AE137: =-36.532-AD137 -> -19.09 | AF137: =-55.724-SUM(AD137:AE137) -> -19.192 | AG137: =-74.373-SUM(AD137:AF137) -> -18.649 | AH137: =SUM(AD137:AG137) -> -74.373 | AI137: -28.065 | AJ137: =-63.505-AI137 -> -35.44 | AK137: =-107.915-SUM(AI137:AJ137) -> -44.41 | AL137: =-145.976-SUM(AI137:AK137) -> -38.061 | AM137: =SUM(AI137:AL137) -> -145.976 | AN137: -36.144 | AO137: =-75.764-AN137 -> -39.62 | AP137: =-102.992-SUM(AN137:AO137) -> -27.228 | AQ137: =-146.818-SUM(AN137:AP137) -> -43.826 | AR137: =SUM(AN137:AQ137) -> -146.818 | AS137: =-24.76 -> -24.76 | AT137: =-60.092-AS137 -> -35.332 | AU137: =-105.765-SUM(AS137:AT137) -> -45.673 | AV137: =-166.138-SUM(AS137:AU137) -> -60.373 | AW137: =SUM(AS137:AV137) -> -166.138 | AX137: -30.763 | AY137: =-62.231-AX137 -> -31.468 | AZ137: =-98.57-SUM(AX137:AY137) -> -36.339 | BA137: =-156.5-SUM(AX137:AZ137) -> -57.93 | BB137: =SUM(AX137:BA137) -> -156.5 | BC137: -31.1 | BD137: =-72.5-BC137 -> -41.4 | BE137: =-113.8-BD137-BC137 -> -41.3 | BF137: =-183.5-SUM(BC137:BE137) -> -69.7 | BG137: =SUM(BC137:BF137) -> -183.5 | BH137: =-BH383 -> -40.837906 | BI137: =-BI383 -> -51.933538 | BJ137: =-BJ383 -> -50.977421 | BK137: =-BK383 -> -80.698134 | BL137: =SUM(BH137:BK137) -> -224.447 | BM137: =-BM383 -> -37.148866 | BN137: =-BN383 -> -48.762677 | BO137: =-BO383 -> -47.599217 | BP137: =-BP383 -> -78.976881 | BQ137: =SUM(BM137:BP137) -> -212.48764 | BR137: =-BR383 -> -33.524982 | BS137: =-BS383 -> -45.642173 | BT137: =-BT383 -> -44.262346 | BU137: =-BU383 -> -77.275049 | BV137: =SUM(BR137:BU137) -> -200.70455 | BW137: =-BW383 -> -32.06032 | BX137: =-BX383 -> -44.772862 | BY137: =-BY383 -> -43.228814 | BZ137: =-BZ383 -> -78.02562 | CA137: =SUM(BW137:BZ137) -> -198.08762 | CD137: =A137 -> Capital Expenditures | CE137: =D137 -> -25.742 | CF137: =I137 -> -32.941 | CG137: =N137 -> -30.652 | CH137: =S137 -> -38.694 | CI137: =X137 -> -38.641 | CJ137: =AC137 -> -59.829 | CK137: =AH137 -> -74.373 | CL137: =AM137 -> -145.976 | CM137: =AR137 -> -146.818 | CN137: =AW137 -> -166.138 | CO137: =BB137 -> -156.5 | CP137: =BG137 -> -183.5 | CQ137: =BL137 -> -224.447 | CR137: =BQ137 -> -212.48764 | CS137: =BV137 -> -200.70455 | CT137: =CA137 -> -198.08762
...

Sheet Revenue_end_mkt
A1: Fiscal Year Ending Dec. 31 | B1: 2008 | C1: 2009 | D1: 1Q10 | E1: 2Q10 | F1: 3Q10 | G1: 4Q10 | H1: 2010 | I1: 1Q11 | J1: 2Q11 | K1: 3Q11 | L1: =VA!AB1 -> 4Q11 | M1: =VA!AC1 -> 2011 | N1: =VA!AD1 -> 1Q12 | O1: =VA!AE1 -> 2Q12 | P1: =VA!AF1 -> 3Q12 | Q1: =VA!AG1 -> 4Q12 | R1: =VA!AH1 -> 2012 | S1: =VA!AI1 -> 1Q13 | ... BK1: =VA!CA1 -> 2021E | BR1: Fiscal Year Ending Dec. 31 | BS1: 2010 | BT1: 2011 | BU1: 2012 | BV1: 2013 | BW1: 2014 | BX1: 2015 | BY1: 2016E | BZ1: =AQ1 -> 2017 | CA1: =AV1 -> 2018E | CB1: =BA1 -> 2019E | CC1: =BF1 -> 2020E | CD1: =BK1 -> 2021E
A3: Risk Assessment | BR3: =A3 -> Risk Assessment
A4: Industry Standard Insurance Programs | B4: =VA!R233 -> 84.727 | C4: =VA!S233 -> 341.079 | D4: =VA!T233 -> 88.044 | E4: =VA!U233 -> 87.427 | F4: =VA!V233 -> 88.644 | G4: =VA!W233 -> 89.386 | H4: =VA!X233 -> 353.501 | I4: =VA!Y233 -> 92.857 | ... K4: =VA!AA233 -> 92.894 | L4: 93.754 | M4: =SUM(I4:L4) -> 371.894 | N4: =VA!AD233 -> 99.134 | O4: =VA!AE233 -> 98.01 | P4: =VA!AF233 -> 98.27 | Q4: =VA!AG233 -> 114.052 | R4: =SUM(N4:Q4) -> 409.466 | S4: =VA!AI233 -> 116.45 | T4: =VA!AJ233 -> 117.289 | U4: =VA!AK233 -> 118.234 | V4: =VA!AL233 -> 119.157 | W4: =SUM(S4:V4) -> 471.13 | X4: =VA!AN233 -> 123.817 | Y4: 123.194 | Z4: 122.83 | AA4: 125.224 | AB4: =SUM(X4:AA4) -> 495.065 | AC4: 130.596 | AD4: 130.776 | AE4: 131.093 | AF4: 132.1 | AG4: =SUM(AC4:AF4) -> 524.565 | AH4: 137.427 | AI4: 138.599 | AJ4: 138.178 | AK4: 139.9 | AL4: =SUM(AH4:AK4) -> 554.104 | AM4: 145.6 | AN4: 148.1 | AO4: 149 | AP4: 151 | AQ4: =SUM(AM4:AP4) -> 593.7 | AR4: =+AM4*(1+AR5) -> 153.244 | AS4: =+AN4*(1+AS5) -> 155.87525 | AT4: =+AO4*(1+AT5) -> 155.705 | AU4: =+AP4*(1+AU5) -> 157.4175 | AV4: =SUM(AR4:AU4) -> 622.24175 | AW4: =+AR4*(1+AW5) -> 161.67242 | AX4: =+AS4*(1+AX5) -> 164.44839 | AY4: =+AT4*(1+AY5) -> 164.26877 | AZ4: =+AU4*(1+AZ5) -> 166.07546 | BA4: =SUM(AW4:AZ4) -> 656.46505 | BB4: =+AW4*(1+BB5) -> 170.5644 | BC4: =+AX4*(1+BC5) -> 173.49305 | BD4: =+AY4*(1+BD5) -> 173.30356 | BE4: =+AZ4*(1+BE5) -> 175.20961 | BF4: =SUM(BB4:BE4) -> 692.57062 | BG4: =+BB4*(1+BG5) -> 179.94545 | BH4: =+BC4*(1+BH5) -> 183.03517 | BI4: =+BD4*(1+BI5) -> 182.83525 | BJ4: =+BE4*(1+BJ5) -> 184.84614 | BK4: =SUM(BG4:BJ4) -> 730.66201 | BR4: =A4 -> Industry Standard Insurance Programs | BS4: =H4 -> 353.501 | BT4: =M4 -> 371.894 | BU4: =R4 -> 409.466 | BV4: =W4 -> 471.13 | BW4: =AB4 -> 495.065 | BX4: =AG4 -> 524.565 | BY4: =AL4 -> 554.104 | BZ4: =AQ4 -> 593.7 | CA4: =AV4 -> 622.24175 | CB4: =BA4 -> 656.46505 | CC4: =BF4 -> 692.57062 | CD4: =BK4 -> 730.66201
A5: YoY Change | B5: =VA!R234 -> 0.02901455 | C5: =VA!S234 -> 0.034017668 | D5: =VA!T234 -> 0.034023512 | E5: =VA!U234 -> 0.0043769961 | F5: =VA!V234 -> 0.053291983 | G5: =VA!W234 -> 0.054988374 | H5: =VA!X234 -> 0.036419715 | I5: =VA!Y234 -> 0.054665849 | ... K5: =VA!AA234 -> 0.047944587 | L5: =L4/G4-1 -> 0.048866713 | M5: =M4/H4-1 -> 0.05203097 | N5: =N4/I4-1 -> 0.067598566 | O5: =O4/J4-1 -> 0.060840576 | P5: =P4/K4-1 -> 0.057872414 | Q5: =Q4/SUM(L4,L10,L13)-1 -> 0.058006104 | R5: =AVERAGE(N5:Q5) -> 0.061079415 | S5: =S4/SUM(N4,N10,N13)-1 -> 0.035921432 | T5: =T4/SUM(O4,O10,O13)-1 -> 0.049753871 | U5: =U4/SUM(P4,P10,P13)-1 -> 0.051417494 | V5: =V4/SUM(Q4,Q10,Q13)-1 -> 0.044760285 | W5: =+W4/(R4+SUM(N10:P10,N13:P13))-1 -> 0.045454747 | X5: =X4/SUM(S4,S10,S13)-1 -> 0.063263203 | Y5: =Y4/SUM(T4,T10,T13)-1 -> 0.050345727 | Z5: =Z4/SUM(U4,U10,U13)-1 -> 0.038872067 | AA5: =AA4/SUM(V4,V10,V13)-1 -> 0.050916018 | AB5: =+AB4/(W4+SUM(S10:U10,S13:U13))-1 -> 0.050803388 | AC5: =AC4/X4-1 -> 0.054750155 | AD5: =AD4/Y4-1 -> 0.061545205 | AE5: =AE4/Z4-1 -> 0.067271839 | AF5: =AF4/AA4-1 -> 0.054909602 | AG5: =+AG4/(AB4+SUM(X10:Z10,X13:Z13))-1 -> 0.059588135 | AH5: =AH4/AC4-1 -> 0.052306349 | AI5: =AI4/AD4-1 -> 0.059819845 | AJ5: =AJ4/AE4-1 -> 0.054045601 | AK5: =AK4/AF4-1 -> 0.059046177 | AL5: =+AL4/(AG4+SUM(AC10:AE10,AC13:AE13))-1 -> 0.05631142 | AM5: =+AM4/(AH4+SUM(AD10:AF10,AD13:AF13))-1 -> 0.059471574 | AN5: =+AN4/(AI4+SUM(AE10:AG10,AE13:AG13))-1 -> 0.068550278 | AO5: =+AO4/(AJ4+SUM(AF10:AH10,AF13:AH13))-1 -> 0.078319269 | AP5: =+AP4/(AK4+SUM(AG10:AI10,AG13:AI13))-1 -> 0.079342387 | AQ5: =+AQ4/(AL4+SUM(AH10:AJ10,AH13:AJ13))-1 -> 0.071459509 | AR5: 0.0525 | AS5: 0.0525 | AT5: 0.045 | AU5: 0.0425 | AV5: =+AV4/(AQ4+SUM(AM10:AO10,AM13:AO13))-1 -> 0.048074364 | AW5: 0.055 | AX5: 0.055 | AY5: 0.055 | AZ5: 0.055 | BA5: =+BA4/(AV4+SUM(AR10:AT10,AR13:AT13))-1 -> 0.055 | BB5: 0.055 | BC5: 0.055 | BD5: 0.055 | BE5: 0.055 | BF5: =+BF4/(BA4+SUM(AW10:AY10,AW13:AY13))-1 -> 0.055 | BG5: 0.055 | BH5: 0.055 | BI5: 0.055 | BJ5: 0.055 | BK5: =+BK4/(BF4+SUM(BB10:BD10,BB13:BD13))-1 -> 0.055 | BR5: =A5 -> YoY Change | BS5: =H5 -> 0.036419715 | BT5: =M5 -> 0.05203097 | BU5: =R5 -> 0.061079415 | BV5: =W5 -> 0.045454747 | BW5: =AB5 -> 0.050803388 | BX5: =AG5 -> 0.059588135 | BY5: =AL5 -> 0.05631142 | BZ5: =AQ5 -> 0.071459509 | CA5: =AV5 -> 0.048074364 | CB5: =BA5 -> 0.055 | CC5: =BF5 -> 0.055 | CD5: =BK5 -> 0.055
A7: Property-Specific Rating and U/W Info (SPI Database) | B7: =VA!R236 -> 32.939 | C7: =VA!S236 -> 132.027 | D7: =VA!T236 -> 33.959 | E7: =VA!U236 -> 34.267 | F7: =VA!V236 -> 34.507 | G7: =VA!W236 -> 34.338 | H7: =VA!X236 -> 137.071 | I7: =VA!Y236 -> 34.497 | ... L7: =VA!AB236 -> 34.512 | M7: =SUM(I7:L7) -> 137.133 | N7: =VA!AD236 -> 32.557 | O7: =VA!AE236 -> 32.459 | P7: =VA!AF236 -> 31.415 | Q7: =VA!AG236 -> 32.429 | R7: =SUM(N7:Q7) -> 128.86 | S7: =VA!AI236 -> 36.163 | T7: =VA!AJ236 -> 36.97 | U7: =VA!AK236 -> 36.821 | V7: =VA!AL236 -> 37.192 | W7: =SUM(S7:V7) -> 147.146 | X7: =VA!AN236 -> 38.496 | Y7: 38.758 | Z7: 38.624 | AA7: 39.709 | AB7: =+AB16-AB4 -> 155.587 | AC7: 40.346 | AD7: 40.954 | AE7: 40.634 | AF7: 41.7 | AG7: =+AG16-AG4 -> 163.634 | AH7: 42.329 | AI7: 42.518 | AJ7: 42.596 | AK7: 42.7 | AL7: =+AL16-AL4 -> 170.143 | AM7: 43.8 | AN7: 44.5 | AO7: 44.2 | AP7: 44.2 | AQ7: =+AQ16-AQ4 -> 176.7 | AR7: =+AR16-AR4 -> 45.1525 | AS7: =+AS16-AS4 -> 45.87325 | AT7: =+AT16-AT4 -> 46.672 | AU7: =+AU16-AU4 -> 46.0785 | AV7: =+AV16-AV4 -> 183.77625 | AW7: =+AW16-AW4 -> 46.643905 | AX7: =+AX16-AX4 -> 47.387536 | ... BK7: =+BK16-BK4 -> 202.40458 | BR7: =A7 -> Property-Specific Rating and U/W Info (SPI Database) | BS7: =H7 -> 137.071 | BT7: =M7 -> 137.133 | BU7: =R7 -> 128.86 | BV7: =W7 -> 147.146 | BW7: =AB7 -> 155.587 | BX7: =AG7 -> 163.634 | BY7: =AL7 -> 170.143 | BZ7: =AQ7 -> 176.7 | CA7: =AV7 -> 183.77625 | CB7: =BA7 -> 189.85385 | CC7: =BF7 -> 196.06422 | CD7: =BK7 -> 202.40458
A8: YoY Change | B8: =VA!R237 -> 0.053677106 | C8: =VA!S237 -> 0.049207295 | D8: =VA!T237 -> 0.061185588 | E8: =VA!U237 -> 0.011781032 | F8: =VA!V237 -> 0.038772991 | G8: =VA!W237 -> 0.042472449 | H8: =VA!X237 -> 0.038204307 | I8: =VA!Y237 -> 0.015842634 | ... K8: =VA!AA237 -> -0.040571478 | L8: =L7/G7-1 -> 0.0050672724 | M8: =M7/H7-1 -> 0.00045232033 | N8: =N7/I7-1 -> -0.056236774 | O8: =O7/J7-1 -> -0.073050233 | P8: =P7/K7-1 -> -0.051107017 | Q8: =Q7/L7-1 -> -0.060355818 | R8: =R7/M7-1 -> -0.060328294 | S8: =S7/N7-1 -> 0.11075959 | ... BK8: =BK7/BF7-1 -> 0.032338169 | BR8: =A8 -> YoY Change | BS8: =H8 -> 0.038204307 | BT8: =M8 -> 0.00045232033 | BU8: =R8 -> -0.060328294 | BV8: =W8 -> 0.14190594 | BW8: =AB8 -> 0.057364794 | BX8: =AG8 -> 0.051720259 | BY8: =AL8 -> 0.039777797 | BZ8: =AQ8 -> 0.038538171 | CA8: =AV8 -> 0.040046689 | CB8: =BA8 -> 0.03307067 | CC8: =BF8 -> 0.032711306 | CD8: =BK8 -> 0.032338169
A10: Statistical Agency and Data Services | B10: =VA!R239 -> 7.465 | C10: =VA!S239 -> 28.619 | D10: =VA!T239 -> 7.179 | E10: =VA!U239 -> 7.19 | F10: =VA!V239 -> 7.51 | G10: =VA!W239 -> 7.478 | H10: =VA!X239 -> 29.357 | I10: =VA!Y239 -> 7.742 | ... K10: =VA!AA239 -> 7.888 | L10: 8.255 | M10: =SUM(I10:L10) -> 31.518 | N10: 7.724 | O10: 8.13 | P10: 8.056 | R10: =SUM(N10:P10) -> 23.91
A11: YoY Change | B11: =VA!R240 -> 0.0826686 | C11: =VA!S240 -> 0.042548541 | D11: =VA!T240 -> 0.017143667 | E11: =VA!U240 -> 0.015967218 | F11: =VA!V240 -> 0.069952985 | G11: =VA!W240 -> 0.0017414601 | H11: =VA!X240 -> 0.025787065 | I11: =VA!Y240 -> 0.078423179 | ... K11: =VA!AA240 -> 0.050332889 | L11: =L10/G10-1 -> 0.10390479 | M11: =M10/H10-1 -> 0.073611064 | N11: =N10/I10-1 -> -0.0023249806 | O11: =O10/J10-1 -> 0.065112014 | P11: =P10/K10-1 -> 0.021298174
A13: Actuarial Services | B13: =VA!R242 -> 5.952 | C13: =VA!S242 -> 22.251 | D13: =VA!T242 -> 5.396 | E13: =VA!U242 -> 5.405 | F13: =VA!V242 -> 5.608 | G13: =VA!W242 -> 5.8 | H13: =VA!X242 -> 22.209 | I13: =VA!Y242 -> 5.447 | ... K13: =VA!AA242 -> 6.088 | L13: 5.79 | M13: =SUM(I13:L13) -> 22.816 | N13: 5.554 | O13: 5.59 | P13: 6.126 | R13: =SUM(N13:P13) -> 17.27
A14: YoY Change | B14: =VA!R243 -> 0.11148459 | C14: =VA!S243 -> 0.04725373 | D14: =VA!T243 -> 0.0067164179 | E14: =VA!U243 -> 0.016741911 | F14: =VA!V243 -> -0.0026676152 | G14: =VA!W243 -> -0.025537634 | H14: =VA!X243 -> -0.0018875556 | I14: =VA!Y243 -> 0.0094514455 | ... K14: =VA!AA243 -> 0.085592011 | L14: =L13/G13-1 -> -0.0017241379 | M14: =M13/H13-1 -> 0.027331262 | N14: =N13/I13-1 -> 0.019643841 | O14: =O13/J13-1 -> 0.018029503 | P14: =P13/K13-1 -> 0.0062417871
A16: Total Risk Assessment | B16: =VA!N245 -> 504.391 | C16: =VA!S245 -> 523.976 | D16: =VA!T245 -> 134.578 | E16: =VA!U245 -> 134.289 | F16: =VA!V245 -> 136.269 | G16: =VA!W245 -> 137.002 | H16: =VA!X245 -> 542.138 | I16: =VA!Y245 -> 140.543 | J16: =VA!Z245 -> 140.53 | ... L16: =VA!AB245 -> 142.311 | M16: =SUM(I16:L16) -> 563.361 | N16: =SUM(N4,N7,N10,N13) -> 144.969 | O16: =SUM(O4,O7,O10,O13) -> 144.189 | P16: =SUM(P4,P7,P10,P13) -> 143.867 | Q16: =VA!AG245 -> 146.481 | R16: =SUM(N16:Q16) -> 579.506 | S16: =VA!AI245 -> 152.613 | T16: =VA!AJ245 -> 154.259 | U16: =VA!AK245 -> 155.055 | V16: =VA!AL245 -> 156.349 | W16: =SUM(S16:V16) -> 618.276 | X16: =VA!AN245 -> 162.313 | Y16: =VA!AO245 -> 161.952 | Z16: =VA!AP245 -> 161.454 | AA16: =VA!AQ245 -> 164.933 | AB16: =SUM(X16:AA16) -> 650.652 | AC16: =AC4+AC7 -> 170.942 | AD16: =AD4+AD7 -> 171.73 | AE16: =AE4+AE7 -> 171.727 | AF16: =AF4+AF7 -> 173.8 | AG16: =SUM(AC16:AF16) -> 688.199 | AH16: =AH4+AH7 -> 179.756 | AI16: =AI4+AI7 -> 181.117 | AJ16: =AJ4+AJ7 -> 180.774 | AK16: =AK4+AK7 -> 182.6 | AL16: =SUM(AH16:AK16) -> 724.247 | AM16: =AM4+AM7 -> 189.4 | AN16: =AN4+AN7 -> 192.6 | AO16: =AO4+AO7 -> 193.2 | AP16: =AP4+AP7 -> 195.2 | AQ16: =SUM(AM16:AP16) -> 770.4 | AR16: =AM16*(1+AR17) -> 198.3965 | AS16: =AN16*(1+AS17) -> 201.7485 | AT16: =AO16*(1+AT17) -> 202.377 | AU16: =AP16*(1+AU17) -> 203.496 | AV16: =SUM(AR16:AU16) -> 806.018 | AW16: =AR16*(1+AW17) -> 208.31633 | AX16: =AS16*(1+AX17) -> 211.83593 | AY16: =AT16*(1+AY17) -> 212.49585 | AZ16: =AU16*(1+AZ17) -> 213.6708 | BA16: =SUM(AW16:AZ16) -> 846.3189 | BB16: =AW16*(1+BB17) -> 218.73214 | BC16: =AX16*(1+BC17) -> 222.42772 | BD16: =AY16*(1+BD17) -> 223.12064 | BE16: =AZ16*(1+BE17) -> 224.35434 | BF16: =SUM(BB16:BE16) -> 888.63485 | BG16: =BB16*(1+BG17) -> 229.66875 | BH16: =BC16*(1+BH17) -> 233.54911 | BI16: =BD16*(1+BI17) -> 234.27667 | BJ16: =BE16*(1+BJ17) -> 235.57206 | BK16: =SUM(BG16:BJ16) -> 933.06659 | BR16: =A16 -> Total Risk Assessment | BS16: =H16 -> 542.138 | BT16: =M16 -> 563.361 | BU16: =R16 -> 579.506 | BV16: =W16 -> 618.276 | BW16: =AB16 -> 650.652 | BX16: =AG16 -> 688.199 | BY16: =AL16 -> 724.247 | BZ16: =AQ16 -> 770.4 | CA16: =AV16 -> 806.018 | CB16: =BA16 -> 846.3189 | CC16: =BF16 -> 888.63485 | CD16: =BK16 -> 933.06659
A17: YoY Change | C17: =VA!S246 -> 0.038829004 | D17: =VA!T246 -> 0.038682988 | E17: =VA!U246 -> 0.0073664549 | F17: =VA!V246 -> 0.048061837 | G17: =VA!W246 -> 0.045154597 | H17: =VA!X246 -> 0.034661893 | I17: =VA!Y246 -> 0.044323738 | J17: =VA!Z246 -> 0.046474395 | ... L17: =VA!AB246 -> 0.038751259 | M17: =M16/H16-1 -> 0.039146859 | N17: =N16/I16-1 -> 0.031492141 | O17: =O16/J16-1 -> 0.026037145 | P17: =P16/K16-1 -> 0.02779028 | Q17: =Q16/L16-1 -> 0.029302022 | R17: =R16/M16-1 -> 0.028658356 | S17: =S16/N16-1 -> 0.052728514 | T17: =T16/O16-1 -> 0.069838892 | ... AQ17: =AQ16/AL16-1 -> 0.063725497 | AR17: =CHOOSE(VA!$A$3,AR18,AR19,AR20) -> 0.0475 | AS17: =CHOOSE(VA!$A$3,AS18,AS19,AS20) -> 0.0475 | AT17: =CHOOSE(VA!$A$3,AT18,AT19,AT20) -> 0.0475 | AU17: =CHOOSE(VA!$A$3,AU18,AU19,AU20) -> 0.0425 | AV17: =AV16/AQ16-1 -> 0.046233126 | AW17: =CHOOSE(VA!$A$3,AW18,AW19,AW20) -> 0.05 | AX17: =CHOOSE(VA!$A$3,AX18,AX19,AX20) -> 0.05 | AY17: =CHOOSE(VA!$A$3,AY18,AY19,AY20) -> 0.05 | AZ17: =CHOOSE(VA!$A$3,AZ18,AZ19,AZ20) -> 0.05 | BA17: =BA16/AV16-1 -> 0.05 | BB17: =CHOOSE(VA!$A$3,BB18,BB19,BB20) -> 0.05 | BC17: =CHOOSE(VA!$A$3,BC18,BC19,BC20) -> 0.05 | BD17: =CHOOSE(VA!$A$3,BD18,BD19,BD20) -> 0.05 | BE17: =CHOOSE(VA!$A$3,BE18,BE19,BE20) -> 0.05 | BF17: =BF16/BA16-1 -> 0.05 | BG17: =CHOOSE(VA!$A$3,BG18,BG19,BG20) -> 0.05 | BH17: =CHOOSE(VA!$A$3,BH18,BH19,BH20) -> 0.05 | BI17: =CHOOSE(VA!$A$3,BI18,BI19,BI20) -> 0.05 | BJ17: =CHOOSE(VA!$A$3,BJ18,BJ19,BJ20) -> 0.05 | BK17: =BK16/BF16-1 -> 0.05 | BR17: =A17 -> YoY Change | BS17: =H17 -> 0.034661893 | BT17: =M17 -> 0.039146859 | BU17: =R17 -> 0.028658356 | BV17: =W17 -> 0.066901809 | BW17: =AB17 -> 0.052364963 | BX17: =AG17 -> 0.057706731 | BY17: =AL17 -> 0.052380198 | BZ17: =AQ17 -> 0.063725497 | CA17: =AV17 -> 0.046233126 | CB17: =BA17 -> 0.05 | CC17: =BF17 -> 0.05 | CD17: =BK17 -> 0.05
A18: BEAR | AR18: =AR19-0.015 -> 0.0325 | AS18: =AS19-0.015 -> 0.0325 | AT18: =AT19-0.015 -> 0.0325 | AU18: =AU19-0.015 -> 0.0275 | AW18: =AW19-0.015 -> 0.035 | AX18: =AX19-0.015 -> 0.035 | AY18: =AY19-0.015 -> 0.035 | AZ18: =AZ19-0.015 -> 0.035 | BB18: =BB19-0.015 -> 0.035 | BC18: =BC19-0.015 -> 0.035 | BD18: =BD19-0.015 -> 0.035 | BE18: =BE19-0.015 -> 0.035 | BG18: =BG19-0.015 -> 0.035 | BH18: =BH19-0.015 -> 0.035 | BI18: =BI19-0.015 -> 0.035 | BJ18: =BJ19-0.015 -> 0.035 | BR18: =A18 -> BEAR
A19: BASE | AR19: =AR21 -> 0.0475 | AS19: =AS21 -> 0.0475 | AT19: =AT21 -> 0.0475 | AU19: =AU21 -> 0.0425 | AV19: =AVERAGE(AR19:AU19) -> 0.04625 | AW19: =AW21 -> 0.05 | AX19: =AX21 -> 0.05 | AY19: =AY21 -> 0.05 | AZ19: =AZ21 -> 0.05 | BA19: =AVERAGE(AW19:AZ19) -> 0.05 | BB19: =BB21 -> 0.05 | BC19: =BC21 -> 0.05 | BD19: =BD21 -> 0.05 | BE19: =BE21 -> 0.05 | BF19: =AVERAGE(BB19:BE19) -> 0.05 | BG19: =BG21 -> 0.05 | BH19: =BH21 -> 0.05 | BI19: =BI21 -> 0.05 | BJ19: =BJ21 -> 0.05 | BK19: =AVERAGE(BG19:BJ19) -> 0.05 | BR19: =A19 -> BASE
A20: BULL | AR20: =AR19+0.015 -> 0.0625 | AS20: =AS19+0.015 -> 0.0625 | AT20: =AT19+0.015 -> 0.0625 | AU20: =AU19+0.015 -> 0.0575 | AW20: =AW19+0.015 -> 0.065 | AX20: =AX19+0.015 -> 0.065 | AY20: =AY19+0.015 -> 0.065 | AZ20: =AZ19+0.015 -> 0.065 | BB20: =BB19+0.015 -> 0.065 | BC20: =BC19+0.015 -> 0.065 | BD20: =BD19+0.015 -> 0.065 | BE20: =BE19+0.015 -> 0.065 | BG20: =BG19+0.015 -> 0.065 | BH20: =BH19+0.015 -> 0.065 | BI20: =BI19+0.015 -> 0.065 | BJ20: =BJ19+0.015 -> 0.065 | BR20: =A20 -> BULL
A21: Organic growth | C21: 0.039 | D21: 0.039 | E21: 0.007 | F21: 0.048 | G21: 0.045 | H21: 0.035 | I21: 0.044 | J21: 0.046 | K21: 0.027 | L21: =L17 -> 0.038751259 | M21: =M17 -> 0.039146859 | N21: 0.052 | O21: 0.049 | P21: 0.049 | Q21: 0.05 | R21: =+(R16+12)/M16-1 -> 0.049959085 | S21: 0.053 | T21: =T17 -> 0.069838892 | U21: 0.078 | V21: =+V17 -> 0.067367099 | W21: =W17 -> 0.066901809 | X21: =+X17 -> 0.063559461 | Y21: =+Y17 -> 0.049870672 | Z21: =+Z17 -> 0.041269227 | AA21: =+AA17 -> 0.054902814 | AB21: 0.052 | AC21: =+AC17 -> 0.053162716 | AD21: =AD17 -> 0.060375914 | AE21: =AE17 -> 0.06362803 | AF21: 0.054 | AG21: =AG17 -> 0.057706731 | AH21: =AH17 -> 0.051561348 | AI21: 0.053 | AJ21: 0.05 | AK21: =((1.054)*AF4+(1.014)*AF7)/AF16-1 -> 0.044402762 | AL21: =((1.053)*AG4+(1.037)*AG7)/AG16-1 -> 0.049195659 | AM21: 0.042 | AN21: 0.044 | AO21: 0.049 | AP21: 0.053 | AQ21: =SUMPRODUCT(AM21:AP21,AH16:AK16)/AL16 -> 0.047020735 | AR21: 0.0475 | AS21: 0.0475 | AT21: 0.0475 | AU21: 0.0425 | AV21: =SUMPRODUCT(AR21:AU21,AM16:AP16)/AQ16 -> 0.046233126 | AW21: 0.05 | AX21: 0.05 | AY21: 0.05 | AZ21: 0.05 | BA21: =SUMPRODUCT(AW21:AZ21,AR16:AU16)/AV16 -> 0.05 | BB21: 0.05 | BC21: 0.05 | BD21: 0.05 | BE21: 0.05 | BF21: =SUMPRODUCT(BB21:BE21,AW16:AZ16)/BA16 -> 0.05 | BG21: 0.05 | BH21: 0.05 | BI21: 0.05 | BJ21: 0.05 | BK21: =SUMPRODUCT(BG21:BJ21,BB16:BE16)/BF16 -> 0.05 | BR21: =A21 -> Organic growth | BS21: =H21 -> 0.035 | BT21: =M21 -> 0.039146859 | BU21: =R21 -> 0.049959085 | BV21: =W21 -> 0.066901809 | BW21: =AB21 -> 0.052 | BX21: =AG21 -> 0.057706731 | BY21: =AL21 -> 0.049195659 | BZ21: =AQ21 -> 0.047020735 | CA21: =AV21 -> 0.046233126 | CB21: =BA21 -> 0.05 | CC21: =BF21 -> 0.05 | CD21: =BK21 -> 0.05
AO22: =(AJ24*(1+AO27)+AJ16*(1+AO21))/SUM(AJ24,AJ16)-1 -> 0.069694916 | AP22: =(AK24*(1+AP27)+AK16*(1+AP21))/SUM(AK24,AK16)-1 -> 0.067332225 | AV22: =(AQ24*(1+AV29)+AQ16*(1+AV21))/SUM(AQ24,AQ16)-1 -> 0.059527683
A23: Decision Analytics | S23: Note: CLGX statements suggest Equecat added ~$32M in 1H | X23: =((1+X17)*S16+(1+X25)*S24)/(S16+S24)-1 -> 0.088052815 | Y23: =((1+Y17)*T16+(1+Y25)*T24)/(T16+T24)-1 -> 0.092829568 | Z23: =((1+Z17)*U16+(1+Z25)*U24)/(U16+U24)-1 -> 0.051124648 | AA23: =((1+AA17)*V16+(1+AA25)*V24)/(V16+V24)-1 -> 0.086751089 | AB23: =((1+AB17)*W16+(1+AB25)*W24)/(W16+W24)-1 -> 0.079472035 | AC23: =((1+AC17)*X16+(1+AC25)*X24)/(X16+X24)-1 -> 0.068913522 | AD23: =((1+AD17)*Y16+(1+AD25)*Y24)/(Y16+Y24)-1 -> 0.07059784 | AE23: =((1+AE17)*Z16+(1+AE25)*Z24)/(Z16+Z24)-1 -> 0.074446052 | ... BK23: =((1+BK17)*BF16+(1+BK25)*BF24)/(BF16+BF24)-1 -> 0.060584673 | BR23: =A23 -> Decision Analytics
A24: Insurance | B24: 311.125 | C24: 331.587 | D24: 87.817 | E24: 93.018 | F24: 93.828 | G24: 98.18 | H24: =SUM(D24:G24) -> 372.843 | I24: 105.3 | J24: 112.334 | K24: 116.281 | L24: 117.301 | M24: =SUM(I24:L24) -> 451.216 | N24: 116.336 | O24: 122.21 | P24: 126.301 | Q24: 128.609 | R24: =SUM(N24:Q24) -> 493.456 | S24: 126.549 | T24: 133.785 | U24: 140.771 | V24: 138.045 | W24: =SUM(S24:V24) -> 539.15 | X24: 141.43 | Y24: 152.831 | Z24: 149.496 | AA24: 155 | AB24: =SUM(X24:AA24) -> 598.757 | AC24: 153.733 | AD24: 165.276 | AE24: 162.372 | AF24: 165.8 | AG24: =SUM(AC24:AF24) -> 647.181 | AH24: 171.545 | AI24: 175.476 | AJ24: 174.446 | AK24: 178.3 | AL24: =SUM(AH24:AK24) -> 699.767 | AM24: 178.6 | AN24: 191 | AO24: 203.9 | AP24: 211.2 | AQ24: =SUM(AM24:AP24) -> 784.7 | AR24: =(1+AR25)*AM24 -> 206.424 | AS24: =(1+AS25)*AN24 -> 216.12 | AT24: =(1+AT25)*AO24 -> 222.48683 | AU24: =(1+AU25)*AP24 -> 225.456 | AV24: =SUM(AR24:AU24) -> 870.48683 | AW24: =(1+AW25)*AR24 -> 220.87368 | AX24: =(1+AX25)*AS24 -> 231.7887 | AY24: =(1+AY25)*AT24 -> 238.61713 | AZ24: =(1+AZ25)*AU24 -> 242.3652 | BA24: =SUM(AW24:AZ24) -> 933.64471 | BB24: =(1+BB25)*AW24 -> 236.33484 | BC24: =(1+BC25)*AX24 -> 248.01391 | BD24: =(1+BD25)*AY24 -> 255.32033 | BE24: =(1+BE25)*AZ24 -> 259.33076 | BF24: =SUM(BB24:BE24) -> 998.99984 | BG24: =(1+BG25)*BB24 -> 252.87828 | BH24: =(1+BH25)*BC24 -> 265.37488 | BI24: =(1+BI25)*BD24 -> 273.19275 | BJ24: =(1+BJ25)*BE24 -> 277.48392 | BK24: =SUM(BG24:BJ24) -> 1068.9298 | BR24: =A24 -> Insurance | BS24: =H24 -> 372.843 | BT24: =M24 -> 451.216 | BU24: =R24 -> 493.456 | BV24: =W24 -> 539.15 | BW24: =AB24 -> 598.757 | BX24: =AG24 -> 647.181 | BY24: =AL24 -> 699.767 | BZ24: =AQ24 -> 784.7 | CA24: =AV24 -> 870.48683 | CB24: =BA24 -> 933.64471 | CC24: =BF24 -> 998.99984 | CD24: =BK24 -> 1068.9298
A25: YoY Change | C25: =C24/B24-1 -> 0.065767778 | D25: 0.112 | E25: 0.123 | F25: 0.102 | G25: 0.16 | H25: =H24/C24-1 -> 0.12441984 | I25: =I24/D24-1 -> 0.19908446 | J25: =J24/E24-1 -> 0.20765873 | K25: =K24/F24-1 -> 0.23929957 | L25: =L24/G24-1 -> 0.19475453 | M25: =M24/H24-1 -> 0.21020376 | N25: =N24/I24-1 -> 0.10480532 | O25: =O24/J24-1 -> 0.087916392 | ... AQ25: =AQ24/AL24-1 -> 0.12137326 | AR25: =CHOOSE(VA!$A$3,AR26,AR27,AR28) -> 0.15578947 | AS25: =CHOOSE(VA!$A$3,AS26,AS27,AS28) -> 0.13151832 | AT25: =CHOOSE(VA!$A$3,AT26,AT27,AT28) -> 0.091156613 | AU25: =CHOOSE(VA!$A$3,AU26,AU27,AU28) -> 0.0675 | AV25: =AV24/AQ24-1 -> 0.10932437 | AW25: =CHOOSE(VA!$A$3,AW26,AW27,AW28) -> 0.07 | AX25: =CHOOSE(VA!$A$3,AX26,AX27,AX28) -> 0.0725 | AY25: =CHOOSE(VA!$A$3,AY26,AY27,AY28) -> 0.0725 | AZ25: =CHOOSE(VA!$A$3,AZ26,AZ27,AZ28) -> 0.075 | BA25: =BA24/AV24-1 -> 0.072554659 | BB25: =CHOOSE(VA!$A$3,BB26,BB27,BB28) -> 0.07 | BC25: =CHOOSE(VA!$A$3,BC26,BC27,BC28) -> 0.07 | BD25: =CHOOSE(VA!$A$3,BD26,BD27,BD28) -> 0.07 | BE25: =CHOOSE(VA!$A$3,BE26,BE27,BE28) -> 0.07 | BF25: =BF24/BA24-1 -> 0.07 | BG25: =CHOOSE(VA!$A$3,BG26,BG27,BG28) -> 0.07 | BH25: =CHOOSE(VA!$A$3,BH26,BH27,BH28) -> 0.07 | BI25: =CHOOSE(VA!$A$3,BI26,BI27,BI28) -> 0.07 | BJ25: =CHOOSE(VA!$A$3,BJ26,BJ27,BJ28) -> 0.07 | BK25: =BK24/BF24-1 -> 0.07 | BR25: =A25 -> YoY Change | BS25: =H25 -> 0.12441984 | BT25: =M25 -> 0.21020376 | BU25: =R25 -> 0.093613702 | BV25: =W25 -> 0.092599948 | BW25: =AB25 -> 0.11055736 | BX25: =AG25 -> 0.080874211 | BY25: =AL25 -> 0.081253931 | BZ25: =AQ25 -> 0.12137326 | CA25: =AV25 -> 0.10932437 | CB25: =BA25 -> 0.072554659 | CC25: =BF25 -> 0.07 | CD25: =BK25 -> 0.07
A26: BEAR | AR26: =AR27-4% -> 0.11578947 | AS26: =AS27-4% -> 0.091518325 | AT26: =AT27-4% -> 0.051156613 | AU26: =AU27-4% -> 0.0275 | AW26: =AW27-4% -> 0.03 | AX26: =AX27-4% -> 0.0325 | AY26: =AY27-4% -> 0.0325 | AZ26: =AZ27-4% -> 0.035 | BB26: =BB27-4% -> 0.03 | BC26: =BC27-4% -> 0.03 | BD26: =BD27-4% -> 0.03 | BE26: =BE27-4% -> 0.03 | BG26: =BG27-4% -> 0.03 | BH26: =BH27-4% -> 0.03 | BI26: =BI27-4% -> 0.03 | BJ26: =BJ27-4% -> 0.03 | BR26: =A26 -> BEAR
A27: BASE | AH27: =(AH29-0.09)*AC24 -> 3.97603 | AM27: 0.065 | AO27: =((AJ24*(1+AO29)-8))/AJ24-1 -> 0.091140536 | AP27: =((AK24*(1+AP29)-8.2))/AK24-1 -> 0.082010095 | AQ27: =AVERAGE(AM27:AP27) -> 0.079383544 | AR27: =AR29+(15/4+8)/AM24 -> 0.15578947 | AS27: =AS29+(15/4+8)/AN24 -> 0.13151832 | AT27: =AT29+(8*(2/3)/AO24) -> 0.091156613 | AU27: =AU29 -> 0.0675 | AV27: =AVERAGE(AR27:AU27) -> 0.1114911 | AW27: =AW29 -> 0.07 | AX27: =AX29 -> 0.0725 | AY27: =AY29 -> 0.0725 | AZ27: =AZ29 -> 0.075 | BA27: =AVERAGE(AW27:AZ27) -> 0.0725 | BB27: =BB29 -> 0.07 | BC27: =BC29 -> 0.07 | BD27: =BD29 -> 0.07 | BE27: =BE29 -> 0.07 | BF27: =AVERAGE(BB27:BE27) -> 0.07 | BG27: =BG29 -> 0.07 | BH27: =BH29 -> 0.07 | BI27: =BI29 -> 0.07 | BJ27: =BJ29 -> 0.07 | BK27: =AVERAGE(BG27:BJ27) -> 0.07 | BR27: =A27 -> BASE
A28: BULL | AP28: =AP24-AK24*(1+AP29) -> 10.0776 | AR28: =AR27+0.015 -> 0.17078947 | AS28: =AS27+0.015 -> 0.14651832 | AT28: =AT27+0.015 -> 0.10615661 | AU28: =AU27+0.015 -> 0.0825 | AW28: =AW27+0.015 -> 0.085 | AX28: =AX27+0.015 -> 0.0875 | AY28: =AY27+0.015 -> 0.0875 | AZ28: =AZ27+0.015 -> 0.09 | BB28: =BB27+0.015 -> 0.085 | BC28: =BC27+0.015 -> 0.085 | BD28: =BD27+0.015 -> 0.085 | BE28: =BE27+0.015 -> 0.085 | BG28: =BG27+0.015 -> 0.085 | BH28: =BH27+0.015 -> 0.085 | BI28: =BI27+0.015 -> 0.085 | BJ28: =BJ27+0.015 -> 0.085 | BR28: =A28 -> BULL
A29: Organic growth | C29: 0.065 | D29: 0.109 | E29: 0.119 | F29: 0.099 | G29: 0.143 | H29: 0.118 | I29: 0.129 | J29: 0.142 | K29: 0.168 | L29: 0.146 | M29: 0.146 | N29: =N25 -> 0.10480532 | O29: =O25 -> 0.087916392 | P29: 0.083 | Q29: 0.093 | R29: =AVERAGE(N29:Q29) -> 0.092180428 | S29: 0.083 | T29: 0.089 | U29: 0.115 | V29: =V25 -> 0.073369671 | W29: =(W24-1)/R24-1 -> 0.090573425 | X29: =X25 -> 0.11759081 | Y29: =Y25 -> 0.14236275 | Z29: =Z25 -> 0.061980095 | AA29: =AA25 -> 0.12282227 | AB29: 0.111 | AC29: =AC25 -> 0.08699003 | AD29: =AD25 -> 0.081429815 | AE29: =AE25 -> 0.086129395 | AF29: 0.07 | AG29: 0.081 | AH29: =AH25 -> 0.11586322 | AI29: 0.062 | AJ29: 0.074 | AK29: 0.073 | AL29: 0.081 | AM29: 0.04 | AN29: 0.084 | AO29: 0.137 | AP29: 0.128 | AQ29: =SUMPRODUCT(AM29:AP29,AH24:AK24)/AL24 -> 0.097637194 | AR29: 0.09 | AS29: 0.07 | AT29: 0.065 | AU29: 0.0675 | AV29: =SUMPRODUCT(AR29:AU29,AM24:AP24)/AQ24 -> 0.072579967 | AW29: 0.07 | AX29: 0.0725 | AY29: 0.0725 | AZ29: 0.075 | BA29: =SUMPRODUCT(AW29:AZ29,AR24:AU24)/AV24 -> 0.072554659 | BB29: 0.07 | BC29: 0.07 | BD29: 0.07 | BE29: 0.07 | BF29: =SUMPRODUCT(BB29:BE29,AW24:AZ24)/BA24 -> 0.07 | BG29: 0.07 | BH29: 0.07 | BI29: 0.07 | BJ29: 0.07 | BK29: =SUMPRODUCT(BG29:BJ29,BB24:BE24)/BF24 -> 0.07 | BR29: =A29 -> Organic growth | BS29: =H29 -> 0.118 | BT29: =M29 -> 0.146 | BU29: =R29 -> 0.092180428 | BV29: =W29 -> 0.090573425 | BW29: =AB29 -> 0.111 | BX29: =AG29 -> 0.081 | BY29: =AL29 -> 0.081 | BZ29: =AQ29 -> 0.097637194 | CA29: =AV29 -> 0.072579967 | CB29: =BA29 -> 0.072554659 | CC29: =BF29 -> 0.07 | CD29: =BK29 -> 0.07
A31: Financial Services | B31: 55.196 | C31: 105.627 | D31: 33.767 | E31: 32.955 | F31: 36.056 | G31: 34.587 | H31: =SUM(D31:G31) -> 137.365 | I31: 32.696 | J31: 35.643 | K31: 34.272 | L31: 32.091 | M31: =SUM(I31:L31) -> 134.702 | N31: 34.275 | O31: 35.299 | P31: 37.96 | Q31: 45.505 | R31: =SUM(N31:Q31) -> 153.039 | S31: 17.282 | T31: 19.575 | U31: 21.379 | V31: =+V42+V40 -> 22.888 | W31: =SUM(S31:V31) -> 81.124 | X31: 21.016 | Y31: 21.837 | Z31: 25.258 | AA31: 28.652 | AB31: =SUM(X31:AA31) -> 96.763 | AC31: 35.17 | AD31: 26.38 | AE31: 27.104 | AF31: 27.9 | AG31: =SUM(AC31:AF31) -> 116.554 | AH31: 28.474 | AI31: 30.585 | AJ31: 33.751 | AK31: 35.5 | AL31: =SUM(AH31:AK31) -> 128.31 | AM31: 28.3 | AN31: 29.3 | AO31: 40.6 | AP31: 47.3 | AQ31: =SUM(AM31:AP31) -> 145.5 | AR31: =(1+AR32)*(AM31) -> 43.25 | AS31: =(1+AS32)*(AN31) -> 40.55 | AT31: =(1+AT32)*(AO31) -> 47.9515 | AU31: =(1+AU32)*(AP31) -> 50.55 | AV31: =SUM(AR31:AU31) -> 182.3015 | AW31: =(1+AW32)*(AR31) -> 46.2775 | AX31: =(1+AX32)*(AS31) -> 43.3885 | AY31: =(1+AY32)*(AT31) -> 51.308105 | AZ31: =(1+AZ32)*(AU31) -> 54.0885 | BA31: =SUM(AW31:AZ31) -> 195.06261 | BB31: =(1+BB32)*(AW31) -> 49.05415 | BC31: =(1+BC32)*(AX31) -> 45.99181 | BD31: =(1+BD32)*(AY31) -> 54.386591 | BE31: =(1+BE32)*(AZ31) -> 57.33381 | BF31: =SUM(BB31:BE31) -> 206.76636 | BG31: =(1+BG32)*(BB31) -> 51.997399 | BH31: =(1+BH32)*(BC31) -> 48.751319 | BI31: =(1+BI32)*(BD31) -> 57.649787 | BJ31: =(1+BJ32)*(BE31) -> 60.773839 | BK31: =SUM(BG31:BJ31) -> 219.17234 | BR31: =A31 -> Financial Services | BS31: =H31 -> 137.365 | BT31: =M31 -> 134.702 | BU31: =R31 -> 153.039 | BV31: =W31 -> 81.124 | BW31: =AB31 -> 96.763 | BX31: =AG31 -> 116.554 | BY31: =AL31 -> 128.31 | BZ31: =AQ31 -> 145.5 | CA31: =AV31 -> 182.3015 | CB31: =BA31 -> 195.06261 | CC31: =BF31 -> 206.76636 | CD31: =BK31 -> 219.17234
A32: YoY Change | C32: =C31/B31-1 -> 0.91367128 | D32: 0.443 | E32: 0.359 | F32: 0.345 | G32: 0.11 | H32: =H31/C31-1 -> 0.30047242 | I32: =I31/D31-1 -> -0.031717357 | J32: =J31/E31-1 -> 0.081565772 | K32: =K31/F31-1 -> -0.049478589 | L32: =L31/G31-1 -> -0.072165843 | M32: =M31/H31-1 -> -0.019386307 | N32: =N31/I31-1 -> 0.048293369 | O32: =O31/J31-1 -> -0.0096512639 | ... U32: =U31/P31-1 -> -0.4368019 | V32: =V31/SUM(Q40,Q42)-1 -> 0.2537248 | W32: =W31/R31-1 -> -0.4699129 | X32: =X31/SUM(S40,S42)-1 -> 0.21606296 | Y32: =Y31/SUM(T40,T42)-1 -> 0.11555556 | Z32: =Z31/SUM(U40,U42)-1 -> 0.18143973 | AA32: =AA31/SUM(V40,V42)-1 -> 0.25183502 | AB32: =AB31/(W40+W42)-1 -> 0.19277896 | AC32: =AC31/X31-1 -> 0.67348687 | AD32: =AD31/Y31-1 -> 0.2080414 | AE32: =AE31/Z31-1 -> 0.073085755 | AF32: =AF31/AA31-1 -> -0.026245986 | AG32: =+AG31/AB31-1 -> 0.20453066 | AH32: =AH31/AC31-1 -> -0.19038954 | AI32: =AI31/AD31-1 -> 0.15940106 | AJ32: =AJ31/AE31-1 -> 0.24524055 | AK32: =AK31/AF31-1 -> 0.27240143 | AL32: =+AL31/AG31-1 -> 0.10086312 | AM32: =AM31/AH31-1 -> -0.006110838 | AN32: =AN31/AI31-1 -> -0.042014059 | AO32: =AO31/AJ31-1 -> 0.20292732 | AP32: =AP31/AK31-1 -> 0.33239437 | AQ32: =+AQ31/AL31-1 -> 0.13397241 | AR32: =CHOOSE(VA!$A$3,AR33,AR34,AR35) -> 0.52826855 | AS32: =CHOOSE(VA!$A$3,AS33,AS34,AS35) -> 0.38395904 | AT32: =CHOOSE(VA!$A$3,AT33,AT34,AT35) -> 0.18107143 | AU32: =CHOOSE(VA!$A$3,AU33,AU34,AU35) -> 0.068710359 | AV32: =+AV31/AQ31-1 -> 0.25293127 | AW32: =CHOOSE(VA!$A$3,AW33,AW34,AW35) -> 0.07 | AX32: =CHOOSE(VA!$A$3,AX33,AX34,AX35) -> 0.07 | AY32: =CHOOSE(VA!$A$3,AY33,AY34,AY35) -> 0.07 | AZ32: =CHOOSE(VA!$A$3,AZ33,AZ34,AZ35) -> 0.07 | BA32: =+BA31/AV31-1 -> 0.07 | BB32: =CHOOSE(VA!$A$3,BB33,BB34,BB35) -> 0.06 | BC32: =CHOOSE(VA!$A$3,BC33,BC34,BC35) -> 0.06 | BD32: =CHOOSE(VA!$A$3,BD33,BD34,BD35) -> 0.06 | BE32: =CHOOSE(VA!$A$3,BE33,BE34,BE35) -> 0.06 | BF32: =+BF31/BA31-1 -> 0.06 | BG32: =CHOOSE(VA!$A$3,BG33,BG34,BG35) -> 0.06 | BH32: =CHOOSE(VA!$A$3,BH33,BH34,BH35) -> 0.06 | BI32: =CHOOSE(VA!$A$3,BI33,BI34,BI35) -> 0.06 | BJ32: =CHOOSE(VA!$A$3,BJ33,BJ34,BJ35) -> 0.06 | BK32: =+BK31/BF31-1 -> 0.06 | BR32: =A32 -> YoY Change | BS32: =H32 -> 0.30047242 | BT32: =M32 -> -0.019386307 | BU32: =R32 -> 0.13613012 | BV32: =W32 -> -0.4699129 | BW32: =AB32 -> 0.19277896 | BX32: =AG32 -> 0.20453066 | BY32: =AL32 -> 0.10086312 | BZ32: =AQ32 -> 0.13397241 | CA32: =AV32 -> 0.25293127 | CB32: =BA32 -> 0.07 | CC32: =BF32 -> 0.06 | CD32: =BK32 -> 0.06
A33: BEAR | AN33: =AN31-(AI31*(1+AN36)) -> 1.559405 | AO33: =AO31-(AJ31*(1+AO36)) -> 7.52402 | AP33: =AP31-(AK31*(1+AP36)) -> 11.729 | AR33: =AR34-0.04 -> 0.48826855 | AS33: =AS34-0.04 -> 0.34395904 | AT33: =AT34-0.04 -> 0.14107143 | AU33: =AU34-0.04 -> 0.028710359 | AW33: =AW34-0.04 -> 0.03 | AX33: =AX34-0.04 -> 0.03 | AY33: =AY34-0.04 -> 0.03 | AZ33: =AZ34-0.04 -> 0.03 | BB33: =BB34-0.04 -> 0.02 | BC33: =BC34-0.04 -> 0.02 | BD33: =BD34-0.04 -> 0.02 | BE33: =BE34-0.04 -> 0.02 | BG33: =BG34-0.04 -> 0.02 | BH33: =BH34-0.04 -> 0.02 | BI33: =BI34-0.04 -> 0.02 | BJ33: =BJ34-0.04 -> 0.02 | BR33: =A33 -> BEAR
A34: BASE | AC34: 0.151 | AH34: 0.177 | AN34: =(AI31*(1+AN36))/(AI31-(11/4))-1 -> -0.0033915933 | AO34: =(AJ31*(1+AO36))/(AJ31-(11/4))-1 -> 0.06693268 | AP34: =(AK31*(1+AP36))/(AK31-(11/4))-1 -> 0.086137405 | AQ34: =AVERAGE(AM34:AP34) -> 0.04989283 | AR34: =AR36+11.7/AM31 -> 0.52826855 | AS34: =AS36+8/AN31 -> 0.38395904 | AT34: =AT36+8*(1.5/3)/AO31 -> 0.18107143 | AU34: =AU36 -> 0.068710359 | AV34: =AVERAGE(AR34:AU34) -> 0.29050235 | AW34: =AW36 -> 0.07 | AX34: =AX36 -> 0.07 | AY34: =AY36 -> 0.07 | AZ34: =AZ36 -> 0.07 | BA34: =AVERAGE(AW34:AZ34) -> 0.07 | BB34: =BB36 -> 0.06 | BC34: =BC36 -> 0.06 | BD34: =BD36 -> 0.06 | BE34: =BE36 -> 0.06 | BF34: =AVERAGE(BB34:BE34) -> 0.06 | BG34: =BG36 -> 0.06 | BH34: =BH36 -> 0.06 | BI34: =BI36 -> 0.06 | BJ34: =BJ36 -> 0.06 | BK34: =AVERAGE(BG34:BJ34) -> 0.06 | BR34: =A34 -> BASE
A35: BULL | AR35: =AR34+0.04 -> 0.56826855 | AS35: =AS34+0.04 -> 0.42395904 | AT35: =AT34+0.04 -> 0.22107143 | AU35: =AU34+0.04 -> 0.10871036 | AW35: =AW34+0.04 -> 0.11 | AX35: =AX34+0.04 -> 0.11 | AY35: =AY34+0.04 -> 0.11 | AZ35: =AZ34+0.04 -> 0.11 | BB35: =BB34+0.04 -> 0.1 | BC35: =BC34+0.04 -> 0.1 | BD35: =BD34+0.04 -> 0.1 | BE35: =BE34+0.04 -> 0.1 | BG35: =BG34+0.04 -> 0.1 | BH35: =BH34+0.04 -> 0.1 | BI35: =BI34+0.04 -> 0.1 | BJ35: =BJ34+0.04 -> 0.1 | BR35: =A35 -> BULL
A36: Organic growth | C36: 0.914 | D36: 0.439 | E36: 0.326 | F36: 0.31 | G36: 0.075 | H36: 0.273 | I36: -0.064 | J36: 0.082 | K36: -0.049 | L36: =L32 -> -0.072165843 | N36: -0.041 | O36: -0.099 | P36: -0.119 | Q36: -0.196 | R36: -0.113 | S36: -0.191 | T36: -0.089 | U36: -0.166 | V36: =+V43 -> 0.27640058 | W36: =AVERAGE(S36:V36) -> -0.042399855 | X36: =X32 -> 0.21606296 | Y36: =Y32 -> 0.11555556 | Z36: =Z32 -> 0.18143973 | AA36: =AA32 -> 0.25183502 | AB36: 0.193 | AC36: =AC32 -> 0.67348687 | AD36: =AD32 -> 0.2080414 | AE36: =AE32 -> 0.073085755 | AF36: -0.026 | AG36: 0.205 | AH36: =AH32 -> -0.19038954 | AI36: 0.159 | AJ36: =AJ32 -> 0.24524055 | AK36: =AK32 -> 0.27240143 | AL36: =AL32 -> 0.10086312 | AM36: -0.001 | AN36: -0.093 | AO36: -0.02 | AP36: 0.002 | AQ36: =SUMPRODUCT(AM36:AP36,AH31:AK31)/AL31 -> -0.027097646 | AR36: =13/4/AM31 -> 0.11484099 | AS36: =13/4/AN31 -> 0.1109215 | AT36: =13/4/AO31+0.0025 -> 0.082549261 | AU36: =13/4/AP31 -> 0.068710359 | AV36: =SUMPRODUCT(AR36:AU36,AM31:AP31)/AQ31 -> 0.090044674 | AW36: 0.07 | AX36: 0.07 | AY36: 0.07 | AZ36: 0.07 | BA36: =SUMPRODUCT(AW36:AZ36,AR31:AU31)/AV31 -> 0.07 | BB36: 0.06 | BC36: 0.06 | BD36: 0.06 | BE36: 0.06 | BF36: =SUMPRODUCT(BB36:BE36,AW31:AZ31)/BA31 -> 0.06 | BG36: 0.06 | BH36: 0.06 | BI36: 0.06 | BJ36: 0.06 | BK36: =SUMPRODUCT(BG36:BJ36,BB31:BE31)/BF31 -> 0.06 | BR36: =A36 -> Organic growth | BS36: =H36 -> 0.273 | BT36: =M36 -> 0 | BU36: =R36 -> -0.113 | BV36: =W36 -> -0.042399855 | BW36: =AB36 -> 0.193 | BX36: =AG36 -> 0.205 | BY36: =AL36 -> 0.10086312 | BZ36: =AQ36 -> -0.027097646 | CA36: =AV36 -> 0.090044674 | CB36: =BA36 -> 0.07 | CC36: =BF36 -> 0.06 | CD36: =BK36 -> 0.06
A38: FS Mortgage | I38: =+I31 -> 32.696 | J38: =+J31 -> 35.643 | K38: =+K31 -> 34.272 | L38: =+L31 -> 32.091 | M38: =SUM(I38:L38) -> 134.702 | N38: =+N31 -> 34.275 | O38: =+O31 -> 35.299 | P38: =+K31*(1+P36)+(P21-P17)*K16 -> 33.162505 | Q38: =+L31*(1+Q36)+(Q21-Q17)*L16 -> 28.746714 | R38: =SUM(N38:Q38) -> 131.48322 | S38: =+N31*(1+S36) -> 27.728475 | T38: =+O31*(1+T36) -> 32.157389 | U38: =+P31*(1+U36) -> 31.65864 | V38: 24.9 | W38: =SUM(S38:V38) -> 116.4445 | X38: 1.1296597 | Y38: 1.2083529 | Z38: 0.91860005 | AA38: 0 | AB38: =SUM(X38:AA38) -> 3.2566127 | BR38: =A38 -> FS Mortgage | BS38: =H38 -> 0 | BT38: =M38 -> 134.702 | BU38: =R38 -> 131.48322 | BV38: =W38 -> 116.4445 | BW38: =AB38 -> 3.2566127
A39: YoY Change | B39: -- | C39: -- | D39: -- | E39: -- | F39: -- | G39: -- | H39: -- | I39: -- | J39: -- | K39: -- | L39: -- | M39: -- | N39: -- | O39: -- | P39: -- | Q39: -- | R39: -- | S39: =+S38/N38-1 -> -0.191 | T39: =+T38/O38-1 -> -0.089 | U39: =+U38/P38-1 -> -0.045348354 | V39: =+V38/Q38-1 -> -0.13381404 | W39: =+W38/R38-1 -> -0.11437745 | X39: =+X38/S40-1 -> 0.01 | Y39: 0.01 | Z39: 0.01 | AA39: 0 | AB39: =+AB38/W40-1 -> -0.31034404 | BR39: =A39 -> YoY Change | BS39: =H39 -> -- | BT39: =M39 -> -- | BU39: =R39 -> -- | BV39: =W39 -> -0.11437745 | BW39: =AB39 -> -0.31034404
A40: Fin Servies - Mortgage, Cont | I40: =+N40 -> 1.243 | J40: =+O40 -> 1.162 | K40: =+P40 -> 1.066505 | L40: =+L38-L41 -> 1.851495 | M40: =SUM(I40:L40) -> 5.323 | N40: =168.5-N76+N38 -> 1.243 | O40: =194.9-O76+O38 -> 1.162 | P40: =222.9-P76+P38 -> 1.066505 | Q40: =242-Q76+Q38 -> 1.497714 | R40: =SUM(N40:Q40) -> 4.969219 | S40: 1.118475 | T40: 1.196389 | U40: 0.909505 | V40: =+Q40 -> 1.497714 | W40: =SUM(S40:V40) -> 4.722083 | BR40: =A40 -> Fin Servies - Mortgage, Cont | BS40: =H40 -> 0 | BT40: =M40 -> 5.323 | BU40: =R40 -> 4.969219 | BV40: =W40 -> 4.722083 | BW40: =AB40 -> 0
A41: Fin Servies - Mortgage, Disc | I41: =+I38-I40 -> 31.453 | J41: =+J38-J40 -> 34.481 | K41: =+K38-K40 -> 33.205495 | L41: =+M41-SUM(I41:K41) -> 30.239505 | M41: =M76-639.1 -> 129.379 | N41: =+N38-N40 -> 33.032 | O41: =+O38-O40 -> 34.137 | P41: =+P38-P40 -> 32.096 | Q41: =+Q38-Q40 -> 27.249 | R41: =SUM(N41:Q41) -> 126.514 | S41: =+S38-S40 -> 26.61 | T41: =+T38-T40 -> 30.961 | U41: =+U38-U40 -> 30.749135 | V41: =+V38-V40 -> 23.402286 | W41: =SUM(S41:V41) -> 111.72242 | BR41: =A41 -> Fin Servies - Mortgage, Disc
A42: FS Argus | B42: -- | C42: -- | D42: -- | E42: -- | F42: -- | G42: -- | H42: -- | I42: -- | J42: -- | K42: -- | L42: -- | M42: -- | N42: -- | O42: -- | P42: =+P31-P38 -> 4.797495 | Q42: =+Q31-Q38 -> 16.758286 | R42: =SUM(P42:Q42) -> 21.555781 | S42: =+S31-S40 -> 16.163525 | T42: =+T31-T40 -> 18.378611 | U42: =+U31-U40 -> 20.469495 | V42: =22.888-V40 -> 21.390286 | W42: =SUM(S42:V42) -> 76.401917 | X42: =+X31-X38 -> 19.88634 | Y42: =+Y31-Y38 -> 20.628647 | Z42: =+Z31-Z38 -> 24.3394 | AA42: =+AA31-AA38 -> 28.652 | AB42: =SUM(X42:AA42) -> 93.506387 | BR42: =A42 -> FS Argus | BS42: =H42 -> -- | BT42: =M42 -> -- | BU42: =R42 -> 21.555781 | BV42: =W42 -> 76.401917 | BW42: =AB42 -> 93.506387
A43: YoY Change | B43: -- | C43: -- | D43: -- | E43: -- | F43: -- | G43: -- | H43: -- | I43: -- | J43: -- | K43: -- | L43: -- | M43: -- | N43: -- | O43: -- | P43: -- | Q43: -- | R43: -- | S43: -- | T43: -- | U43: NM | V43: =+V42/Q42-1 -> 0.27640058 | W43: NM | X43: =+X42/S42-1 -> 0.23032199 | Y43: =+Y42/T42-1 -> 0.12242689 | Z43: =+Z42/U42-1 -> 0.18905718 | AA43: =+AA42/V42-1 -> 0.33948653 | AB43: =+AB42/W42-1 -> 0.22387488 | BR43: =A43 -> YoY Change | BS43: =H43 -> -- | BT43: =M43 -> -- | BU43: =R43 -> -- | BV43: =W43 -> NM | BW43: =AB43 -> 0.22387488
A44: Argus Mix | B44: -- | C44: -- | D44: -- | E44: -- | F44: -- | G44: -- | H44: -- | I44: -- | J44: -- | K44: -- | L44: -- | M44: -- | N44: -- | O44: -- | P44: =+P42/P31 -> 0.1263829 | Q44: =+Q42/Q31 -> 0.36827351 | R44: =+R42/R31 -> 0.14085155 | S44: =+S42/S31 -> 0.93528093 | T44: =+T42/T31 -> 0.93888179 | U44: =+U42/U31 -> 0.95745802 | V44: =+V42/V31 -> 0.93456335 | W44: =+W42/W31 -> 0.94179179 | ... AB44: =+AB42/AB31 -> 0.96634444 | BR44: =A44 -> Argus Mix | BS44: =H44 -> -- | BT44: =M44 -> -- | BU44: =R44 -> 0.14085155 | BV44: =W44 -> 0.94179179 | BW44: =AB44 -> 0.96634444
A46: Healthcare | B46: 21.503 | C46: 50.064 | D46: 14.294 | E46: 15.037 | F46: 14.389 | G46: 14.252 | H46: =SUM(D46:G46) -> 57.972 | I46: 15.617 | J46: 19.322 | K46: 30.277 | L46: 38.506 | M46: =SUM(I46:L46) -> 103.722 | N46: 30.448 | O46: 50.381 | P46: 69.324 | Q46: 72.802 | R46: =SUM(N46:Q46) -> 222.955 | S46: 59.049 | T46: 61.087 | U46: 73.612 | V46: 77.79 | W46: =SUM(S46:V46) -> 271.538 | X46: 63.896 | Y46: 65.092 | Z46: 91.9 | AA46: 94.74 | AB46: =SUM(X46:AA46) -> 315.628 | AC46: =AC53 -> 75.104 | AD46: =AD53 -> 69.051 | AE46: =AE53 -> 79.993 | AF46: =AF53 -> 83.2 | AG46: =AG53 -> 307.348 | AH46: =AH53 -> 69.151 | BR46: =A46 -> Healthcare | BS46: =H46 -> 57.972 | BT46: =M46 -> 103.722 | BU46: =R46 -> 222.955 | BV46: =W46 -> 271.538 | BW46: =AB46 -> 315.628 | BX46: =AG46 -> 307.348 | BY46: =AL46 -> 0 | BZ46: =AQ46 -> 0 | CA46: =AV46 -> 0 | CB46: =BA46 -> 0 | CC46: =BF46 -> 0 | CD46: =BK46 -> 0
A47: YoY Change | C47: =C46/B46-1 -> 1.3282333 | D47: 0.428 | E47: 0.047 | F47: 0.158 | G47: 0.074 | H47: =H46/C46-1 -> 0.15795781 | I47: =I46/D46-1 -> 0.092556317 | J47: =J46/E46-1 -> 0.28496376 | K47: =K46/F46-1 -> 1.1041768 | L47: =L46/G46-1 -> 1.7017962 | M47: =M46/H46-1 -> 0.78917408 | N47: =N46/I46-1 -> 0.94967023 | O47: =O46/J46-1 -> 1.6074423 | ... AH47: =AH46/AC46-1 -> -0.079263421 | BR47: =A47 -> YoY Change | BS47: =H47 -> 0.15795781 | BT47: =M47 -> 0.78917408 | BU47: =R47 -> 1.149544 | BV47: =W47 -> 0.21790496 | BW47: =AB47 -> 0.16237138 | BX47: =AG47 -> -0.026233414 | BY47: =AL47 -> 0 | BZ47: =AQ47 -> 0 | CA47: =AV47 -> 0 | CB47: =BA47 -> 0 | CC47: =BF47 -> 0 | CD47: =BK47 -> 0
A48: BEAR | BR48: =A48 -> BEAR
A49: BASE | BR49: =A49 -> BASE
A50: BULL | BR50: =A50 -> BULL
A51: Organic growth | C51: 0.465 | D51: 0.324 | E51: -0.048 | F51: 0.08 | G51: 0.074 | H51: 0.091 | I51: 0.093 | J51: 0.075 | K51: 0.258 | L51: 0.373 | M51: 0.198 | N51: 0.329 | O51: 0.367 | P51: 0.474 | Q51: 0.285 | R51: =AVERAGE(N51:Q51) -> 0.36375 | S51: 0.39 | T51: 0.213 | U51: 0.062 | V51: =+V47 -> 0.068514601 | W51: =(SUM((N46*(1+S51))+(O46*(1+T51)+(P46*(1+U51)+(Q46*(1+V51))))))/R46-1 -> 0.14304214 | X51: =+X47 -> 0.082084371 | Y51: =+Y47 -> 0.065562231 | Z51: =+Z47 -> 0.24843775 | AA51: =+AA47 -> 0.21789433 | AB51: 0.162 | BR51: =A51 -> Organic growth | BS51: =H51 -> 0.091 | BT51: =M51 -> 0.198 | BU51: =R51 -> 0.36375 | BV51: =W51 -> 0.14304214 | BW51: =AB51 -> 0.162 | BX51: =AG51 -> 0 | BY51: =AL51 -> 0 | BZ51: =AQ51 -> 0 | CA51: =AV51 -> 0 | CB51: =BA51 -> 0 | CC51: =BF51 -> 0 | CD51: =BK51 -> 0
A52: Combined Organic Growth, Insurance + Fin Svcs | AC52: =(X31*(1+AC36)+X24*(1+AC29)+X16*(1+AC21))/SUM(X31,X24,X16)-1 -> 0.10803704 | AD52: =(Y31*(1+AD36)+Y24*(1+AD29)+Y16*(1+AD21))/SUM(Y31,Y24,Y16)-1 -> 0.079513992 | AE52: =(Z31*(1+AE36)+Z24*(1+AE29)+Z16*(1+AE21))/SUM(Z31,Z24,Z16)-1 -> 0.074343859 | AF52: =(AA31*(1+AF36)+AA24*(1+AF29)+AA16*(1+AF21))/SUM(AA31,AA24,AA16)-1 -> 0.054538864 | AG52: =(AB31*(1+AG36)+AB24*(1+AG29)+AB16*(1+AG21))/SUM(AB31,AB24,AB16)-1 -> 0.078654683 | AH52: =(AC31*(1+AH36)+AC24*(1+AH29)+AC16*(1+AH21))/SUM(AC31,AC24,AC16)-1 -> 0.055384957 | AI52: =(AD31*(1+AI36)+AD24*(1+AI29)+AD16*(1+AI21))/SUM(AD31,AD24,AD16)-1 -> 0.064788467 | AJ52: =(AE31*(1+AJ36)+AE24*(1+AJ29)+AE16*(1+AJ21))/SUM(AE31,AE24,AE16)-1 -> 0.075439235 | ... BK52: =(BF31*(1+BK36)+BF24*(1+BK29)+BF16*(1+BK21))/SUM(BF31,BF24,BF16)-1 -> 0.060526953 | BR52: =A52 -> Combined Organic Growth, Insurance + Fin Svcs
A53: Healthcare (Reflects Acc Chg) | B53: 21.503 | C53: 50.064 | D53: 14.294 | E53: 15.037 | F53: 14.389 | G53: 14.252 | H53: =SUM(D53:G53) -> 57.972 | I53: 15.617 | J53: 19.322 | K53: 30.277 | L53: 38.506 | M53: =SUM(I53:L53) -> 103.722 | N53: 30.448 | O53: 50.381 | P53: 69.324 | Q53: 72.802 | R53: =SUM(N53:Q53) -> 222.955 | S53: 59.049 | T53: 61.087 | U53: 73.612 | V53: 77.79 | W53: =SUM(S53:V53) -> 271.538 | X53: 58.4 | Y53: 56 | Z53: 81.1 | AA53: 84 | AB53: =SUM(X53:AA53) -> 279.5 | AC53: 75.104 | AD53: 69.051 | AE53: 79.993 | AF53: 83.2 | AG53: =SUM(AC53:AF53) -> 307.348 | AH53: 69.151 | BR53: =A53 -> Healthcare (Reflects Acc Chg) | BS53: =H53 -> 57.972 | BT53: =M53 -> 103.722 | BU53: =R53 -> 222.955 | BV53: =W53 -> 271.538 | BW53: =AB53 -> 279.5 | BX53: =AG53 -> 307.348 | BY53: =AL53 -> 0 | BZ53: =AQ53 -> 0 | CA53: =AV53 -> 0 | CB53: =BA53 -> 0 | CC53: =BF53 -> 0 | CD53: =BK53 -> 0
A54: YoY Change | C54: =C53/B53-1 -> 1.3282333 | D54: 0.428 | E54: 0.047 | F54: 0.158 | G54: 0.074 | H54: =H53/C53-1 -> 0.15795781 | I54: =I53/D53-1 -> 0.092556317 | J54: =J53/E53-1 -> 0.28496376 | K54: =K53/F53-1 -> 1.1041768 | L54: =L53/G53-1 -> 1.7017962 | M54: =M53/H53-1 -> 0.78917408 | N54: =N53/I53-1 -> 0.94967023 | O54: =O53/J53-1 -> 1.6074423 | ... W54: =W53/R53-1 -> 0.21790496 | AC54: =AC53/X53-1 -> 0.2860274 | AD54: =AD53/Y53-1 -> 0.23305357 | AE54: =AE53/Z53-1 -> -0.013649815 | AF54: =AF53/AA53-1 -> -0.0095238095 | AG54: =AG53/AB53-1 -> 0.099635063 | AH54: =AH53/AC53-1 -> -0.079263421 | BR54: =A54 -> YoY Change | BS54: =H54 -> 0.15795781 | BT54: =M54 -> 0.78917408 | BU54: =R54 -> 1.149544 | BV54: =W54 -> 0.21790496 | BW54: =BW47 -> 0.16237138 | BX54: =AG54 -> 0.099635063 | BY54: =AL54 -> 0 | BZ54: =AQ54 -> 0 | CA54: =AV54 -> 0 | CB54: =BA54 -> 0 | CC54: =BF54 -> 0 | CD54: =BK54 -> 0
A55: BEAR | BR55: =A55 -> BEAR
A56: BASE | BR56: =A56 -> BASE
A57: BULL | BR57: =A57 -> BULL
