Workbook
Name AdditionalInstructions: IndexInformation!$B$42
Name Address: ImportantDisclosures!$A$2:$A$2
Name ANA: ModPubIndex!$A$7
Name Authors: ImportantDisclosures!$A$7
Name Authors: IndexInformation!$B$18
Name BRO: ModPubIndex!$A$1
Name CopyrightStamp: ImportantDisclosures!$A$27
Name COU: ModPubIndex!$A$5
Name CQEnd: IndexInformation!$B$31
Name Currency: IndexInformation!$B$24
Name CurrentStockPrice: IndexInformation!$B$23
Name CurrQtrEPS: IndexInformation!$B$29
Name CurrYearEPS: IndexInformation!$B$11
Name CurrYearTotalRevenue: IndexInformation!$B$10
Name CurrYearTotalRevenueActual: IndexInformation!$B$32
Name CUSIP: IndexInformation!$B$20
Name CYEnd: IndexInformation!$B$30
Name Date: ImportantDisclosures!$A$8
Name Deleted: IndexInformation!$B$27
Name Description: IndexInformation!$B$7
Name Discipline: IndexInformation!$B$3
Name DISCIPLINE: ModPubIndex!$A$12
Name DisclosuresText: ImportantDisclosures!$A$22
Name Distribution: IndexInformation!$B$26
Name DistTable: ImportantDisclosures!#REF!
Name DistTablePreamble: ImportantDisclosures!#REF!
Name DOCDAT: ModPubIndex!$A$2
Name DOCTIME: ModPubIndex!$A$3
Name DocType: IndexInformation!$B$5
Name EMAIL_ALERT: ModPubIndex!$A$10
Name EmailAlert: IndexInformation!$B$28
Name FiveYearGrowthRate: IndexInformation!$B$16
Name FollowingYearEPS: IndexInformation!$B$15
Name FollowingYearTotalRevenue: IndexInformation!$B$14
Name FollowingYearTotalRevenueActual: IndexInformation!$B$34
Name HL: ModPubIndex!$A$8
Name IND: ModPubIndex!$A$9
Name Industry: ImportantDisclosures!$A$12
Name IndustryId: IndexInformation!$B$40
Name IndustryRating: ImportantDisclosures!$A$13
Name KeepVersions: IndexInformation!$B$8
Name LanguageCode: IndexInformation!$B$38
Name LastCell: ImportantDisclosures!$A$22
Name MacroVersion: IndexInformation!$B$1
Name ModelPrice: ImportantDisclosures!$A$14
Name Multiplier: IndexInformation!$B$35
Name NextYearEPS: IndexInformation!$B$13
Name NextYearTotalRevenue: IndexInformation!$B$12
Name NextYearTotalRevenueActual: IndexInformation!$B$33
Name NUEestimates: Estimates!$B$3:$V$36
Name NUESummary: Summary!$B$5:$P$60
Name NUEvariance: Variance!$B$2:$K$30
Name ObjectType: IndexInformation!$B$37
Name PANA: ModPubIndex!$A$11
Name PathName: IndexInformation!$B$25
Name PRODUCT: ModPubIndex!$A$6
Name PSYM: ModPubIndex!$A$4
Name PublishDate: IndexInformation!$B$2
Name Rating: IndexInformation!$B$9
Name RatingsDefined: ImportantDisclosures!$A$21

Sheet ImportantDisclosures
A2: 1585 Broadway
A3: New York, NY 10036-8293
A4: United States
A5: Tel: +1 (1)212 761 4000
A7: Authors: Piyush Sood, Lynn Bernabei, Serena Rocha Calejon
A8: Date: 24 Apr 2018
A10: Ticker: NUE.N
A11: Stock Rating: Equal-Weight
A12: Industry: Steel
A13: Industry View: In-Line
A14: Price as of 24 Apr 2018: 62.88
A15: Target Price: 73
... A116: Equal-weight and Not-Rated to hold and Underweight to sell recommendations, respectively.
B118: Coverage Universe | D118: Investment Banking Clients (IBC) | G118: Other Material Investment Services Clients (MISC)
A119: Stock Rating Category | B119: Count | C119: % of Total | D119: Count | E119: % of Total IBC | F119: % of Rating Category | G119: Count | H119: % of Total Other MISC
A120: Overweight/Buy | B120: 1189 | C120: 0.38 | D120: 315 | E120: 0.41 | F120: 0.26 | G120: 555 | H120: 0.39
A121: Equal-weight/Hold | B121: 1355 | C121: 0.43 | D121: 364 | E121: 0.47 | F121: 0.27 | G121: 644 | H121: 0.45
A122: Not-Rated/Hold | B122: 53 | C122: 0.02 | D122: 4 | E122: 0.01 | F122: 0.08 | G122: 7 | H122: 0
A123: Underweight/Sell | B123: 545 | C123: 0.17 | D123: 84 | E123: 0.11 | F123: 0.15 | G123: 214 | H123: 0.15
A124: Total | B124: 3142 | D124: 767 | G124: 1420
A126: Data include common stock and ADRs currently assigned ratings. Investment Banking Clients are companies
A127: from whom Morgan Stanley received investment banking compensation in the last 12 months. Due to rounding
A128: off of decimals, the percentages provided in the "% of total" column may not add up to exactly 100
A129: percent.
A131: Analyst Stock Ratings
A133: Overweight (O). The stock's total return is expected to exceed the average total return of the analyst's
A134: industry (or industry team's) coverage universe, on a risk-adjusted basis, over the next 12-18 months.
A136: Equal-weight (E). The stock's total return is expected to be in line with the average total return of
A137: the analyst's industry (or industry team's) coverage universe, on a risk-adjusted basis, over the next
A138: 12-18 months.
A140: Not-Rated (NR). Currently the analyst does not have adequate conviction about the stock's total return
A141: relative to the average total return of the analyst's industry (or industry team's) coverage universe,
... A387: © Copyright 2018 Morgan Stanley

Sheet Summary
B2: Nucor Corporation
B3: Summary Information
B5: Key Assumptions | J5: Income Statement
B6: Year End December | C6: 2014 | D6: 2015 | E6: 2016 | F6: 2017 | G6: 2018E | H6: 2019E | J6: Year End December (US$M) | K6: =C6 -> 2014 | L6: =D6 -> 2015 | M6: =E6 -> 2016 | N6: =F6 -> 2017 | O6: =G6 -> 2018E | P6: =H6 -> 2019E
B7: Realizations, $/t | J7: Sales | K7: =Financials!$BV$15 -> 21105.141 | L7: =Financials!$CA$15 -> 16439.276 | M7: =Financials!$CF$15 -> 16208.122 | N7: =Financials!$CK$15 -> 20252.393 | O7: =Financials!$CP$15 -> 25483.944 | P7: =Financials!$CU$15 -> 26897.497
B8: Sheet | C8: =Operations!BV18 -> 735.75 | D8: =Operations!CA18 -> 570.75 | E8: =Operations!CF18 -> 572.5 | F8: =Operations!CK18 -> 689 | G8: =Operations!CP18 -> 845.78828 | H8: =Operations!CU18 -> 852.72645 | J8: Cash COGS | K8: =Financials!$BV$19 -> 18439.187 | L8: =Financials!$CA$19 -> 14152.668 | M8: =Financials!$CF$19 -> 13596.941 | N8: =Financials!$CK$19 -> 16917.664 | O8: =Financials!$CP$19 -> 21176.541 | P8: =Financials!$CU$19 -> 22695.771
B9: Tubular | C9: NA | D9: NA | E9: NA | F9: =Operations!CK158 -> 1000 | G9: =Operations!CP158 -> 0 | H9: =Operations!CU158 -> 0 | J9: D&A | K9: =Financials!$BV$21 -> 724.423 | L9: =Financials!$CA$21 -> 700.017 | M9: =Financials!$CF$21 -> 687.054 | N9: =Financials!$CK$21 -> 727.061 | O9: =Financials!$CP$21 -> 696 | P9: =Financials!$CU$21 -> 696
B10: Bars | C10: =Operations!BV19 -> 732.75 | D10: =Operations!CA19 -> 626 | E10: =Operations!CF19 -> 544.25 | F10: =Operations!CK19 -> 609 | G10: =Operations!CP19 -> 728.47678 | H10: =Operations!CU19 -> 736.47568 | J10: SG&A | K10: =Financials!$BV$28 -> 546.198 | L10: =Financials!$CA$28 -> 466.689 | M10: =Financials!$CF$28 -> 596.761 | N10: =Financials!$CK$28 -> 667.281 | O10: =Financials!$CP$28 -> 700.76365 | P10: =Financials!$CU$28 -> 699.33493
B11: Structural | C11: =Operations!BV20 -> 1025.25 | D11: =Operations!CA20 -> 959 | E11: =Operations!CF20 -> 854.25 | F11: =Operations!CK20 -> 759.25 | G11: =Operations!CP20 -> 876.66975 | H11: =Operations!CU20 -> 968.52453 | J11: EBITDA | K11: =Financials!$BV$97 -> 2119.756 | L11: =Financials!$CA$97 -> 1819.919 | M11: =Financials!$CF$97 -> 2014.42 | N11: =Financials!$CK$97 -> 2667.448 | O11: =Financials!$CP$97 -> 3606.6397 | P11: =Financials!$CU$97 -> 3502.3915
B12: Plate | C12: =Operations!BV21 -> 847.75 | D12: =Operations!CA21 -> 683 | E12: =Operations!CF21 -> 598.5 | F12: =Operations!CK21 -> 731.25 | G12: =Operations!CP21 -> 886.91192 | H12: =Operations!CU21 -> 916.72144 | J12: EBIT | K12: =Financials!$BV$31 -> 1395.333 | L12: =Financials!$CA$31 -> 1119.902 | M12: =Financials!$CF$31 -> 1327.366 | N12: =Financials!$CK$31 -> 1940.387 | O12: =Financials!$CP$31 -> 2910.6397 | P12: =Financials!$CU$31 -> 2806.3915
B13: Shipments, kt | J13: Pre-Tax Income | K13: =Financials!$BV$48 -> 1226.077 | L13: =Financials!$CA$48 -> 946.371 | M13: =Financials!$CF$48 -> 1158.122 | N13: =Financials!$CK$48 -> 1766.807 | O13: =Financials!$CP$48 -> 2747.0596 | P13: =Financials!$CU$48 -> 2650.1684
B14: Sheet | C14: =Operations!BV33 -> 8153 | D14: =Operations!CA33 -> 8080 | E14: =Operations!CF33 -> 9118 | F14: =Operations!CK33 -> 9311 | G14: =Operations!CP33 -> 9320.2 | H14: =Operations!CU33 -> 9506.604 | J14: Tax | K14: =Financials!$BV$51 -> 383.537 | L14: =Financials!$CA$51 -> 243.547 | M14: =Financials!$CF$51 -> 348.796 | N14: =Financials!$CK$51 -> 554.224 | O14: =Financials!$CP$51 -> 666.04343 | P14: =Financials!$CU$51 -> 636.04042
B15: Tubular | C15: NA | D15: NA | E15: NA | F15: =Operations!CK124 -> 917 | G15: =Operations!CP124 -> 1082.1 | H15: =Operations!CU124 -> 1103.742 | J15: Minority Interest | K15: =Financials!$BV$47 -> 0 | L15: =Financials!$CA$47 -> 0 | M15: =Financials!$CF$47 -> 0 | N15: =Financials!$CK$47 -> 0 | O15: =Financials!$CP$47 -> 0 | P15: =Financials!$CU$47 -> 0
B16: Bars | C16: =Operations!BV34+Operations!BV35 -> 5526 | D16: =Operations!CA34+Operations!CA35 -> 4790 | E16: =Operations!CF34+Operations!CF35 -> 5304 | F16: =Operations!CK34+Operations!CK35 -> 5838 | G16: =Operations!CP34+Operations!CP35 -> 6214.96 | H16: =Operations!CU34+Operations!CU35 -> 6307.2592 | J16: Adj. Net Income | K16: =Financials!$BV$57 -> 740.696 | L16: =Financials!$CA$57 -> 564.399 | M16: =Financials!$CF$57 -> 711.061 | N16: =Financials!$CK$57 -> 1150.7 | O16: =Financials!$CP$57 -> 1985.0832 | P16: =Financials!$CU$57 -> 1926.128
B17: Structural | C17: =Operations!BV36 -> 2560 | D17: =Operations!CA36 -> 2231 | E17: =Operations!CF36 -> 2319 | F17: =Operations!CK36 -> 1739 | G17: =Operations!CP36 -> 1754.66 | H17: =Operations!CU36 -> 1789.7532 | J17: Adj. EPS | K17: =Financials!$BV$60 -> 2.3137079 | L17: =Financials!$CA$60 -> 1.7599273 | M17: =Financials!$CF$60 -> 2.2233023 | N17: =Financials!$CK$60 -> 3.587244 | O17: =Financials!$CP$60 -> 6.2160938 | P17: =Financials!$CU$60 -> 6.0385929
B18: Plate | C18: =Operations!BV37 -> 2442 | D18: =Operations!CA37 -> 1905 | E18: =Operations!CF37 -> 2023 | F18: =Operations!CK37 -> 2249 | G18: =Operations!CP37 -> 2281.58 | H18: =Operations!CU37 -> 2327.2116 | J18: Reported EPS | K18: =Financials!$BV$92 -> 2.2301491 | L18: =Financials!$CA$92 -> 1.1152639 | M18: =Financials!$CF$92 -> 2.2956551 | N18: =Financials!$CK$92 -> 4.1534905 | O18: =Financials!$CP$92 -> 6.1478293 | P18: =Financials!$CU$92 -> 6.0385929
B19: Fabrication Productions | C19: =Operations!$BV$126 -> 6732 | D19: =Operations!$CA$126 -> 5674 | E19: =Operations!$CF$126 -> 5545 | F19: =Operations!$CK$126 -> 7355 | G19: =Operations!$CP$126 -> 7843.11 | H19: =Operations!$CU$126 -> 8034.7552
B20: Capacity Utilization | C20: =Operations!$BV$63 -> 0.77247807 | D20: =Operations!$CA$63 -> 0.66969802 | E20: =Operations!$CF$63 -> 0.79707865 | F20: =Operations!$CK$63 -> 0.88873708 | G20: =Operations!$CP$63 -> 0.8793329 | H20: =Operations!$CU$63 -> 0.89548182 | J20: Balance Sheet
J21: =+$J$6 -> Year End December (US$M) | K21: =+K6 -> 2014 | L21: =+L6 -> 2015 | M21: =+M6 -> 2016 | N21: =+N6 -> 2017 | O21: =+O6 -> 2018E | P21: =+P6 -> 2019E
B22: Segment EBIT | J22: Cash and Equivalents | K22: =Financials!$BV$113 -> 1024.144 | L22: =Financials!$CA$113 -> 1939.469 | M22: =Financials!$CF$113 -> 2045.961 | N22: =Financials!$CK$113 -> 949.104 | O22: =Financials!$CP$113 -> 1674.7993 | P22: =Financials!$CU$113 -> 3033.9736
B23: =+J6 -> Year End December (US$M) | C23: =+C6 -> 2014 | D23: =+D6 -> 2015 | E23: =+E6 -> 2016 | F23: =+F6 -> 2017 | G23: =+G6 -> 2018E | H23: =+H6 -> 2019E | J23: Receivables | K23: =Financials!BV115 -> 2068.298 | L23: =Financials!CA115 -> 1383.823 | M23: =Financials!CF115 -> 1631.676 | N23: =Financials!CK115 -> 2028.545 | O23: =Financials!CP115 -> 2621.148 | P23: =Financials!CU115 -> 2558.1728
B24: Steel | C24: =Financials!BV35 -> 1615.852 | D24: =Financials!CA35 -> 782.256 | E24: =Financials!CF35 -> 1688.568 | F24: =Financials!CK35 -> 1939.225 | G24: =Financials!CP35 -> 3058.31 | H24: =Financials!CU35 -> 2955.6011 | J24: Inventories | K24: =Financials!BV116 -> 2745.032 | L24: =Financials!CA116 -> 2145.444 | M24: =Financials!CF116 -> 2479.958 | N24: =Financials!CK116 -> 3461.686 | O24: =Financials!CP116 -> 4302.2041 | P24: =Financials!CU116 -> 4321.1195
B25: Steel Products | C25: =Financials!BV36 -> 166.323 | D25: =Financials!CA36 -> 276.048 | E25: =Financials!CF36 -> 249.97 | F25: =Financials!CK36 -> 351.802 | G25: =Financials!CP36 -> 372.13675 | H25: =Financials!CU36 -> 326.93932 | J25: Other Current Assets | K25: =K29-SUM(K26:K28,K22:K24) -> 604.414 | L25: =L29-SUM(L26:L28,L22:L24) -> 285.644 | M25: =M29-SUM(M26:M28,M22:M24) -> 348.798 | N25: =N29-SUM(N26:N28,N22:N24) -> 385.085 | O25: =O29-SUM(O26:O28,O22:O24) -> 238.701 | P25: =P29-SUM(P26:P28,P22:P24) -> 238.701
B26: Raw Materials | C26: =Financials!BV37 -> -29.053 | D26: =Financials!CA37 -> -199.805 | E26: =Financials!CF37 -> -95.121 | F26: =Financials!CK37 -> 129.296 | G26: =Financials!CP37 -> 213.2156 | H26: =Financials!CU37 -> 218.4173 | J26: Goodwill and Intangibles | K26: =Financials!BV122+Financials!BV123 -> 2930.757 | L26: =Financials!CA122+Financials!CA123 -> 2781.95 | M26: =Financials!CF122+Financials!CF123 -> 2919.563 | N26: =Financials!CK122+Financials!CK123 -> 3110.704 | O26: =Financials!CP122+Financials!CP123 -> 3087.686 | P26: =Financials!CU122+Financials!CU123 -> 3087.686
B27: Others | C27: =Financials!BV38+Financials!BV39 -> -357.789 | D27: =Financials!CA38+Financials!CA39 -> 261.403 | E27: =Financials!CF38+Financials!CF39 -> -516.051 | F27: =Financials!CK38+Financials!CK39 -> -479.936 | G27: =Financials!CP38+Financials!CP39 -> -733.02264 | H27: =Financials!CU38+Financials!CU39 -> -694.56626 | J27: Net PP&E | K27: =Financials!$BV$121 -> 5287.639 | L27: =Financials!$CA$121 -> 4891.153 | M27: =Financials!$CF$121 -> 5078.65 | N27: =Financials!$CK$121 -> 5093.147 | O27: =Financials!$CP$121 -> 5318.89 | P27: =Financials!$CU$121 -> 5487.89
J28: Other Long Term Assets | K28: =Financials!$BV$124 -> 955.643 | L28: =Financials!$CA$124 -> 822.916 | M28: =Financials!$CF$124 -> 718.912 | N28: =Financials!$CK$124 -> 812.987 | O28: =Financials!$CP$124 -> 1020.3063 | P28: =Financials!$CU$124 -> 995.7926
B29: Quarterly Data | J29: Total Assets | K29: =Financials!$BV$126 -> 15615.927 | L29: =Financials!$CA$126 -> 14250.399 | M29: =Financials!$CF$126 -> 15223.518 | N29: =Financials!$CK$126 -> 15841.258 | O29: =Financials!$CP$126 -> 18263.735 | P29: =Financials!$CU$126 -> 19723.335
B30: =+B6 -> Year End December | C30: =ROUNDUP(MONTH(C62)/3,0)&"Q"&YEAR(C62)-2000 -> 3Q17 | D30: =ROUNDUP(MONTH(D62)/3,0)&"Q"&YEAR(D62)-2000 -> 4Q17 | E30: =ROUNDUP(MONTH(E62)/3,0)&"Q"&YEAR(E62)-2000 -> 1Q18 | F30: =ROUNDUP(MONTH(F62)/3,0)&"Q"&YEAR(F62)-2000&"e" -> 2Q18e | G30: =ROUNDUP(MONTH(G62)/3,0)&"Q"&YEAR(G62)-2000&"e" -> 3Q18e | H30: =ROUNDUP(MONTH(H62)/3,0)&"Q"&YEAR(H62)-2000&"e" -> 4Q18e
B31: Quarterly Operating Data | J31: Short Term Debt | K31: =Financials!$BV$130 -> 223.811 | L31: =Financials!$CA$130 -> 51.315 | M31: =Financials!$CF$130 -> 617.959 | N31: =Financials!$CK$130 -> 552.833 | O31: =Financials!$CP$130 -> 0 | P31: =Financials!$CU$130 -> 0
B32: Sheet Realization | C32: =Operations!CI18 -> 695 | D32: =Operations!CJ18 -> 691 | E32: =Operations!CL18 -> 723 | F32: =Operations!CM18 -> 870.25 | G32: =Operations!CN18 -> 907.1875 | H32: =Operations!CO18 -> 882.71562 | J32: Long Term Debt | K32: =Financials!$BV$136 -> 4360.6 | L32: =Financials!$CA$136 -> 4360.6 | M32: =Financials!$CF$136 -> 3739.141 | N32: =Financials!$CK$136 -> 3242.242 | O32: =Financials!$CP$136 -> 4360.6 | P32: =Financials!$CU$136 -> 4360.6
B33: Steel Shipments | C33: =Operations!CI38 -> 4698 | D33: =Operations!CJ38 -> 4629 | E33: =Operations!CL38 -> 5016 | F33: =Operations!CM38 -> 5047.48 | G33: =Operations!CN38 -> 4789.21 | H33: =Operations!CO38 -> 4718.71 | J33: Payables | K33: =Financials!$BV$129 -> 993.872 | L33: =Financials!$CA$129 -> 566.527 | M33: =Financials!$CF$129 -> 838.109 | N33: =Financials!$CK$129 -> 1181.346 | O33: =Financials!$CP$129 -> 1468.1839 | P33: =Financials!$CU$129 -> 1474.639
B34: Capacity Utilization | C34: =Operations!CI63 -> 0.87942355 | D34: =Operations!CJ63 -> 0.86430288 | E34: =Operations!CL63 -> 0.91398552 | F34: =Operations!CM63 -> 0.90961478 | G34: =Operations!CN63 -> 0.85369031 | H34: =Operations!CO63 -> 0.84112348 | J34: Other Current Liabilities | K34: =Financials!$BV$134-SUM(K33,K31) -> 880.093 | L34: =Financials!$CA$134-L31-L33 -> 767.331 | M34: =Financials!$CF$134-M33-M31 -> 933.898 | N34: =Financials!$CK$134-N33-N31 -> 1090.585 | O34: =Financials!$CP$134-O33-O31 -> 1111.5172 | P34: =Financials!$CU$134-P33-P31 -> 1084.8121
B35: Quarterly Financial Data | J35: Other Long Term Liabilities | K35: =K38-SUM(K36:K37)-SUM(K31:K34) -> 1082.433 | L35: =L38-SUM(L36:L37)-SUM(L31:L34) -> 718.613 | M35: =M38-SUM(M36:M37)-SUM(M31:M34) -> 839.703 | N35: =N38-SUM(N36:N37)-SUM(N31:N34) -> 689.464 | O35: =O38-SUM(O36:O37)-SUM(O31:O34) -> 710.881 | P35: =P38-SUM(P36:P37)-SUM(P31:P34) -> 710.881
B36: Sales | C36: =Financials!CI15 -> 5170.117 | D36: =Financials!CJ15 -> 5092.328 | E36: =Financials!CL15 -> 5568.419 | F36: =Financials!CM15 -> 6597.9083 | G36: =Financials!CN15 -> 6737.6567 | H36: =Financials!CO15 -> 6579.9601 | J36: Minority Interest | K36: =Financials!$BV$147 -> 302.648 | L36: =Financials!$CA$147 -> 369.135 | M36: =Financials!$CF$147 -> 374.843 | N36: =Financials!$CK$147 -> 345.752 | O36: =Financials!$CP$147 -> 387.462 | P36: =Financials!$CU$147 -> 421.239
B37: EBITDA | C37: =Financials!CI97 -> 600.46 | D37: =Financials!CJ97 -> 548.171 | E37: =Financials!CL97 -> 748.826 | F37: =Financials!CM97 -> 962.59615 | G37: =Financials!CN97 -> 979.40743 | H37: =Financials!CO97 -> 915.8101 | J37: Shareholders' Equity | K37: =Financials!$BV$149-K36 -> 7772.47 | L37: =Financials!$CA$149-L36 -> 7416.878 | M37: =Financials!$CF$149-M36 -> 7879.865 | N37: =Financials!$CK$149-N36 -> 8739.036 | O37: =Financials!$CP$149-O36 -> 10225.091 | P37: =Financials!$CU$149-P36 -> 11671.164
B38: EBIT | C38: =Financials!CI31 -> 420.965 | D38: =Financials!CJ31 -> 364.326 | E38: =Financials!CL31 -> 574.826 | F38: =Financials!CM31 -> 788.59615 | G38: =Financials!CN31 -> 805.40743 | H38: =Financials!CO31 -> 741.8101 | J38: Liabilities & Equity | K38: =K29 -> 15615.927 | L38: =L29 -> 14250.399 | M38: =M29 -> 15223.518 | N38: =N29 -> 15841.258 | O38: =O29 -> 18263.735 | P38: =P29 -> 19723.335
B39: Adj. EPS | C39: =Financials!CI60 -> 0.79591474 | D39: =Financials!CJ60 -> 0.65222664 | E39: =Financials!CL60 -> 1.1731966 | F39: =Financials!CM60 -> 1.6981154 | G39: =Financials!CN60 -> 1.7468192 | H39: =Financials!CO60 -> 1.5997587
B40: Reported EPS | C40: =Financials!CI92 -> 0.83706662 | D40: =Financials!CJ92 -> 1.1997831 | E40: =Financials!CL92 -> 1.1051723 | F40: =Financials!CM92 -> 1.6981154 | G40: =Financials!CN92 -> 1.7468192 | H40: =Financials!CO92 -> 1.5997587 | J40: Cash flow Statement
J41: =+$J$6 -> Year End December (US$M) | K41: =+K21 -> 2014 | L41: =+L21 -> 2015 | M41: =+M21 -> 2016 | N41: =+N21 -> 2017 | O41: =+O21 -> 2018E | P41: =+P21 -> 2019E
B42: Important Ratios | J42: Net Income | K42: =Financials!$BV$192 -> 815.79 | L42: =Financials!$CA$192 -> 496.084 | M42: =Financials!$CF$192 -> 832.466 | N42: =Financials!$CK$192 -> 1394.221 | O42: =Financials!$CP$192 -> 2059.2162 | P42: =Financials!$CU$192 -> 2014.128
B43: =+$B$30 -> Year End December | C43: =+C23 -> 2014 | D43: =+D23 -> 2015 | E43: =+E23 -> 2016 | F43: =+F23 -> 2017 | G43: =+G23 -> 2018E | H43: =+H23 -> 2019E | J43: D&A | K43: =K9 -> 724.423 | L43: =L9 -> 700.017 | M43: =M9 -> 687.054 | N43: =N9 -> 727.061 | O43: =O9 -> 696 | P43: =P9 -> 696
B44: Diluted Shares Out (m) | C44: =Financials!$BV$63 -> 320.13375 | D44: =Financials!$CA$63 -> 320.6945 | E44: =Financials!$CF$63 -> 319.822 | F44: =Financials!$CK$63 -> 320.7755 | G44: =Financials!$CP$63 -> 319.34576 | H44: =Financials!$CU$63 -> 318.96967 | J44: Others | K44: =K46-K45-K42-K43 -> 202.874 | L44: =L46-L45-L42-L43 -> 217.912 | M44: =M46-M45-M42-M43 -> 197.083 | N44: =N46-N45-N42-N43 -> -130.437 | O44: =O46-O45-O42-O43 -> -65.084284 | P44: =P46-P45-P42-P43 -> 24.513688
B45: Adj. EPS | C45: =+K17 -> 2.3137079 | D45: =+L17 -> 1.7599273 | E45: =+M17 -> 2.2233023 | F45: =+N17 -> 3.587244 | G45: =+O17 -> 6.2160938 | H45: =+P17 -> 6.0385929 | J45: (Increase) in Working Capital | K45: =Financials!$BV$203 -> -400.189 | L45: =Financials!$CA$203 -> 743.03 | M45: =Financials!$CF$203 -> 20.93 | N45: =Financials!$CK$203 -> -939.582 | O45: =Financials!$CP$203 -> -995.33102 | P45: =Financials!$CU$203 -> 23.809834
B46: EPS Growth YoY | C46: =C45/Financials!BQ60-1 -> 0.55241135 | D46: =D45/C45-1 -> -0.23934769 | E46: =E45/D45-1 -> 0.26329216 | F46: =F45/E45-1 -> 0.61347558 | G46: =G45/F45-1 -> 0.73283272 | H46: =H45/G45-1 -> -0.028555062 | J46: Net Cash from Operations | K46: =Financials!$BV$206 -> 1342.898 | L46: =Financials!$CA$206 -> 2157.043 | M46: =Financials!$CF$206 -> 1737.533 | N46: =Financials!$CK$206 -> 1051.263 | O46: =Financials!$CP$206 -> 1694.8009 | P46: =Financials!$CU$206 -> 2758.4515
B47: P/E | C47: =C63/C45 -> 27.177155 | D47: =D63/D45 -> 35.728749 | E47: =E63/E45 -> 28.282253 | F47: =F63/F45 -> 17.528777 | G47: =G63/G45 -> 10.115677 | H47: =H63/H45 -> 10.413022
B48: P/B | C48: =C63/(K37/C44) -> 2.5899116 | D48: =D63/(L37/D44) -> 2.7188354 | E48: =E63/(M37/E44) -> 2.5521259 | F48: =F63/(N37/F44) -> 2.3080765 | G48: =G63/(O37/G44) -> 1.9638419 | H48: =H63/(P37/H44) -> 1.7184929 | J48: Acquisitions | K48: =Financials!$BV$210 -> -768.581 | L48: =Financials!$CA$210 -> -19.089 | M48: =Financials!$CF$210 -> -474.788 | N48: =Financials!$CK$210 -> -544.041 | O48: =Financials!$CP$210 -> 0 | P48: =Financials!$CU$210 -> 0
B49: EV | C49: =(C44*C63)+C56+K36 -> 23992.925 | D49: =(D44*D63)+D56+L36 -> 23006.851 | E49: =(E44*E63)+E56+M36 -> 22796.389 | F49: =(F44*F63)+F56+N36 -> 23362.086 | G49: =(G44*G63)+G56+O36 -> 23153.724 | H49: =(H44*H63)+H56+P36 -> 21804.678 | J49: Capex | K49: =Financials!$BV$209 -> -667.982 | L49: =Financials!$CA$209 -> -374.123 | M49: =Financials!$CF$209 -> -604.84 | N49: =Financials!$CK$209 -> -448.555 | O49: =Financials!$CP$209 -> -978.766 | P49: =Financials!$CU$209 -> -865
B50: EV/EBITDA | C50: =C49/K11 -> 11.31872 | D50: =D49/L11 -> 12.64169 | E50: =E49/M11 -> 11.316602 | F50: =F49/N11 -> 8.7582163 | G50: =G49/O11 -> 6.4197497 | H50: =H49/P11 -> 6.2256543 | J50: Others | K50: =K51-K48-K49 -> -1.499 | L50: =L51-L48-L49 -> -48.484 | M50: =M51-M48-M49 -> 54.51 | N50: =N51-N48-N49 -> 73.704 | O50: =O51-O48-O49 -> 1.041 | P50: =P51-P48-P49 -> 0
B51: Dividend Per Share | C51: =Financials!$BV$65 -> 1.4825 | D51: =Financials!$CA$65 -> 1.49 | E51: =Financials!$CF$65 -> 1.5025 | F51: =Financials!$CK$65 -> 1.51 | G51: =Financials!$CP$65 -> 1.51 | H51: =Financials!$CU$65 -> 1.51 | J51: Net Cash used in Investing | K51: =Financials!$BV$214 -> -1438.062 | L51: =Financials!$CA$214 -> -441.696 | M51: =Financials!$CF$214 -> -1025.118 | N51: =Financials!$CK$214 -> -918.892 | O51: =Financials!$CP$214 -> -977.725 | P51: =Financials!$CU$214 -> -865
B52: Payout ratio | C52: =C51/C45 -> 0.64074638 | D52: =D51/D45 -> 0.84662589 | E52: =E51/E45 -> 0.67579653 | F52: =F51/F45 -> 0.42093596 | G52: =G51/G45 -> 0.24291783 | H52: =H51/H45 -> 0.25005825
B53: Div. Yield | C53: =+C51/C63 -> 0.023576654 | D53: =+D51/D63 -> 0.023695929 | E53: =+E51/E63 -> 0.02389472 | F53: =+F51/F63 -> 0.024013995 | G53: =+G51/G63 -> 0.024013995 | H53: =+H51/H63 -> 0.024013995 | J53: Proceeds from Equity | K53: =Financials!BV218+Financials!BV219 -> 5.614 | L53: =Financials!CA218+Financials!CA219 -> -66.082 | M53: =Financials!CF218+Financials!CF219 -> 10.578 | N53: =Financials!CK218+Financials!CK219 -> -79.159 | O53: =Financials!CP218+Financials!CP219 -> -13.881 | P53: =Financials!CU218+Financials!CU219 -> 0
B54: ROE | C54: =K16/(Financials!BQ149-Financials!BQ147) -> 0.096876586 | D54: =L16/K37 -> 0.07261514 | E54: =M16/L37 -> 0.095870661 | F54: =N16/M37 -> 0.14603042 | G54: =O16/N37 -> 0.22715128 | H54: =P16/O37 -> 0.18837271 | J54: Proceeds from Debt | K54: =Financials!BV220+Financials!BV221+Financials!BV222+Financials!BV223 -> 172.95 | L54: =Financials!CA220+Financials!CA221+Financials!CA222+Financials!CA223 -> -172.116 | M54: =Financials!CF220+Financials!CF221+Financials!CF222+Financials!CF223 -> -33.36 | N54: =Financials!CK220+Financials!CK221+Financials!CK222+Financials!CK223 -> -565.128 | O54: =Financials!CP220+Financials!CP221+Financials!CP222+Financials!CP223 -> 564.902 | P54: =Financials!CU220+Financials!CU221+Financials!CU222+Financials!CU223 -> 0
B55: ROIC | C55: =(Financials!BV31*(1-Financials!BV52))/(Financials!BQ149-Financials!BQ147+Financials!BQ130+Financials!BQ136-Financials!BQ113) -> 0.090697814 | D55: =(Financials!CA41*(1-Financials!CA52))/(Summary!K37+Summary!K32+Summary!K31-Summary!K22) -> 0.073388899 | E55: =(Financials!CF41*(1-Financials!CF52))/(Summary!L37+Summary!L32+Summary!L31-Summary!L22) -> 0.093797932 | F55: =(Financials!CK41*(1-Financials!CK52))/(Summary!M37+Summary!M32+Summary!M31-Summary!M22) -> 0.13067537 | G55: =(Financials!CP41*(1-Financials!CP52))/(Summary!N37+Summary!N32+Summary!N31-Summary!N22) -> 0.19032661 | H55: =(Financials!CU41*(1-Financials!CU52))/(Summary!O37+Summary!O32+Summary!O31-Summary!O22) -> 0.16519832 | J55: Others | K55: =K56-K54-K53 -> -537.611 | L55: =L56-L54-L53 -> -551.553 | M55: =M56-M54-M53 -> -591.184 | N55: =N56-N54-N53 -> -593.944 | O55: =O56-O54-O53 -> -542.32463 | P55: =P56-P54-P53 -> -534.27718
B56: Net Debt | C56: =K32+K31-K22 -> 3560.267 | D56: =L32+L31-L22 -> 2472.446 | E56: =M32+M31-M22 -> 2311.139 | F56: =N32+N31-N22 -> 2845.971 | G56: =O32+O31-O22 -> 2685.8007 | H56: =P32+P31-P22 -> 1326.6264 | J56: Net Cash used in Financing | K56: =Financials!$BV$228 -> -359.047 | L56: =Financials!$CA$228 -> -789.751 | M56: =Financials!$CF$228 -> -613.966 | N56: =Financials!$CK$228 -> -1238.231 | O56: =Financials!$CP$228 -> 8.6963667 | P56: =Financials!$CU$228 -> -534.27718
B57: Leverage (Net Debt/Capital) | C57: =C56/(C56+K37) -> 0.31415774 | D57: =D56/(D56+L37) -> 0.25001163 | E57: =E56/(E56+M37) -> 0.22678227 | F57: =F56/(F56+N37) -> 0.24565984 | G57: =G56/(G56+O37) -> 0.20802597 | H57: =H56/(H56+P37) -> 0.10206553
B58: Leverage (Net Debt/EBITDA) | C58: =C56/K11 -> 1.6795645 | D58: =D56/L11 -> 1.3585473 | E58: =E56/M11 -> 1.1472975 | F58: =F56/N11 -> 1.0669265 | G58: =G56/O11 -> 0.7446823 | H58: =H56/P11 -> 0.3787773 | J58: Net Cash Inflow | K58: =Financials!$BV$231 -> -459.108 | L58: =Financials!$CA$231 -> 915.325 | M58: =Financials!$CF$231 -> 106.492 | N58: =Financials!$CK$231 -> -1096.857 | O58: =Financials!$CP$231 -> 725.69525 | P58: =Financials!$CU$231 -> 1359.1744
B59: FCF Per Share | C59: =Financials!$BV$238 -> 2.1082313 | D59: =Financials!$CA$238 -> 5.559559 | E59: =Financials!$CF$238 -> 3.5416357 | F59: =Financials!$CK$238 -> 1.8789091 | G59: =Financials!$CP$238 -> 2.2421932 | H59: =Financials!$CU$238 -> 5.9361491 | J59: Closing Cash Balance | K59: =K22 -> 1024.144 | L59: =L22 -> 1939.469 | M59: =M22 -> 2045.961 | N59: =N22 -> 949.104 | O59: =O22 -> 1674.7993 | P59: =P22 -> 3033.9736
B60: FCF Yield | C60: =(C59)/C63 -> 0.033527852 | D60: =(D59)/D63 -> 0.088415379 | E60: =(E59)/E63 -> 0.056323722 | F60: =(F59)/F63 -> 0.02988087 | G60: =(G59)/G63 -> 0.035658289 | H60: =(H59)/H63 -> 0.094404406
B62: Lookups | C62: 43008 | D62: =EOMONTH(C62,3) -> 43100 | E62: =EOMONTH(D62,3) -> 43190 | F62: =EOMONTH(E62,3) -> 43281 | G62: =EOMONTH(F62,3) -> 43373 | H62: =EOMONTH(G62,3) -> 43465
B63: Average Stock Price | C63: =D63 -> 62.88 | D63: =E63 -> 62.88 | E63: =F63 -> 62.88 | F63: =G63 -> 62.88 | G63: =H63 -> 62.88 | H63: 62.88

Sheet Operations
A2: Nucor Corporation
A3: Operating Drivers | AN3: 39508 | AO3: 39600 | AP3: 39692 | AQ3: 39783 | AS3: 39873 | AT3: 39965 | AU3: 40057 | AV3: 40148 | AW3: FY9 | AX3: 40238 | AY3: 40330 | AZ3: 40422 | BA3: 40513 | BB3: FY10 | BC3: 40603 | BD3: 40695 | BE3: 40787 | BF3: 40878 | BG3: FY11 | BH3: 40969 | BI3: 41061 | BJ3: 41153 | BK3: 41244 | BL3: FY12 | BM3: 41334 | BN3: 41426 | BO3: 41518 | BP3: 41609 | BQ3: FY13 | BR3: 41699 | BS3: 41791 | BT3: 41883 | BU3: 41974 | BV3: FY14 | BW3: 42064 | BX3: 42156 | BY3: 42248 | BZ3: 42339 | CA3: FY15 | CB3: 42430 | CC3: 42522 | CD3: 42614 | CE3: 42705 | CF3: FY16 | CG3: 42795 | CH3: 42887 | CI3: 42979 | CJ3: 43070 | CK3: FY17 | CL3: 43160 | CM3: 43252 | CN3: 43344 | CO3: 43435 | CP3: FY18 | CQ3: 43525 | CR3: 43617 | CS3: 43709 | CT3: 43800 | CU3: FY19 | CV3: 43891 | CW3: 43983 | CX3: 44075 | CY3: 44166 | CZ3: FY20
E4: 1997 | F4: 1998 | G4: 1999 | H4: 2000 | I4: 2001 | J4: 1Q | K4: 2Q | L4: 3Q | M4: 4Q | N4: 2002 | O4: 1Q | P4: 2Q | Q4: 3Q | R4: 4Q | S4: 2003 | T4: 1Q | U4: 2Q | V4: 3Q | W4: 4Q | X4: 2004 | Y4: 1Q | Z4: 2Q | AA4: 3Q | AB4: 4Q | AC4: 2005 | AD4: 1Q | AE4: 2Q | AF4: 3Q | AG4: 4Q | AH4: 2006 | AI4: 1Q | AJ4: 2Q | AK4: 3Q | AL4: 4Q | AM4: 2007 | AN4: 1Q | AO4: 2Q | AP4: 3Q | AQ4: 4Q | AR4: 2008 | AS4: 1Q | AT4: 2Q | AU4: 3Q | AV4: 4Q | AW4: 2009 | AX4: 1Q | AY4: 2Q | AZ4: 3Q | BA4: 4Q | BB4: 2010 | BC4: 1Q | BD4: 2Q | BE4: 3Q | BF4: 4Q | BG4: 2011 | BH4: 1Q | BI4: 2Q | BJ4: 3Q | BK4: 4Q | BL4: 2012 | BM4: 1Q | BN4: 2Q | BO4: 3Q | BP4: 4Q | BQ4: 2013 | BR4: 1Q | BS4: 2Q | BT4: 3Q | BU4: 4Q | BV4: 2014 | BW4: 1Q | BX4: 2Q | BY4: 3Q | BZ4: 4Q | CA4: 2015 | CB4: 1Q | CC4: 2Q | CD4: 3Q | CE4: 4Q | CF4: 2016 | CG4: 1Q | CH4: 2Q | CI4: 3Q | CJ4: 4Q | CK4: 2017 | CL4: 1Q | CM4: 2QE | CN4: 3QE | CO4: 4QE | CP4: 2018E | CQ4: 1QE | CR4: 2QE | CS4: 3QE | CT4: 4QE | CU4: 2019E | CV4: 1QE | CW4: 2QE | CX4: 3QE | CY4: 4QE | CZ4: 2020E
A5: Prices (US$ per Ton)
B6: Hot-Rolled Sheet | E6: 340 | F6: 303.33333 | G6: 291.66667 | H6: 301.25 | I6: 223.5 | N6: 322.08333 | S6: 290.5 | T6: 462.33333 | U6: 610 | V6: 703.33333 | W6: 658.33333 | X6: =AVERAGE(T6:W6) -> 608.5 | Y6: 631.66667 | Z6: 532.5 | AA6: 461.66667 | AB6: 550 | AC6: =AVERAGE(Y6:AB6) -> 543.95833 | AD6: 550 | AE6: 591.66667 | AF6: 621.66667 | AG6: 563.33333 | AH6: =AVERAGE(AD6:AG6) -> 581.66667 | AI6: 518.33333 | AJ6: 553.33333 | AK6: 516.66667 | AL6: 535 | AM6: =AVERAGE(AI6:AL6) -> 530.83333 | AN6: 691.66667 | AO6: 976.66667 | AP6: 1051.6667 | AQ6: 714 | AR6: =AVERAGE(AN6:AQ6) -> 858.5 | AS6: 508.66667 | AT6: 399 | AU6: 491.33333 | AV6: 528 | AW6: =AVERAGE(AS6:AV6) -> 481.75 | AX6: 592 | AY6: 682 | AZ6: 582.66667 | BA6: 557 | BB6: =AVERAGE(AX6:BA6) -> 603.41667 | BC6: 795.66667 | BD6: 813 | BE6: 687.66782 | BF6: 657.66667 | BG6: =AVERAGE(BC6:BF6) -> 738.50029 | BH6: 720.66667 | BI6: 660 | BJ6: 625.66667 | BK6: 619.99869 | BL6: =AVERAGE(BH6:BK6) -> 656.58301 | BM6: 616.66667 | BN6: 592.33333 | BO6: 643.66667 | BP6: 658.99708 | BQ6: =AVERAGE(BM6:BP6) -> 627.91594 | BR6: 654.66667 | BS6: 671 | BT6: 667.66667 | BU6: 634.33333 | BV6: =AVERAGE(BR6:BU6) -> 656.91667 | BW6: 536.33333 | BX6: 453.66667 | BY6: 459 | BZ6: 387 | CA6: =AVERAGE(BW6:BZ6) -> 459 | CB6: 398.33333 | CC6: 561.66667 | CD6: 592 | CE6: 521 | CF6: =AVERAGE(CB6:CE6) -> 518.25 | CG6: 622.66667 | CH6: 623.5942 | CI6: 621.41848 | CJ6: 618.09489 | CK6: =AVERAGE(CG6:CJ6) -> 621.44356 | CL6: 741.07743 | CM6: 885 | CN6: 830 | CO6: 785 | CP6: =AVERAGE(CL6:CO6) -> 810.26936 | CQ6: 800 | CR6: 770 | CS6: 760 | CT6: 715 | CU6: =AVERAGE(CQ6:CT6) -> 761.25 | CV6: 660 | CW6: 675 | CX6: 645 | CY6: 645 | CZ6: =AVERAGE(CV6:CY6) -> 656.25
B7: Hollow Sections ASTM A500 | AS7: 823.08333 | AT7: 649.26 | AU7: 698.53333 | AV7: 733.61333 | AW7: =AVERAGE(AS7:AV7) -> 726.1225 | AX7: 801.66667 | AY7: 872.42667 | AZ7: 836.59 | BA7: 817.80667 | BB7: =AVERAGE(AX7:BA7) -> 832.1225 | BC7: 1076.6667 | BD7: 1076.4267 | BE7: 961.71667 | BF7: 930.25667 | BG7: =AVERAGE(BC7:BF7) -> 1011.2667 | BH7: 993.95333 | BI7: 971.94667 | BJ7: 916.49667 | BK7: 903.70333 | BL7: =AVERAGE(BH7:BK7) -> 946.525 | BM7: 925.77 | BN7: 912.12 | BO7: 930.15333 | BP7: 952.18667 | BQ7: =AVERAGE(BM7:BP7) -> 930.0575 | BR7: 981.62 | BS7: 956.29333 | BT7: 935.44 | BU7: 895.50667 | BV7: =AVERAGE(BR7:BU7) -> 942.215 | BW7: 836.28333 | BX7: 719.63667 | BY7: 705.09 | BZ7: 623.33667 | CA7: =AVERAGE(BW7:BZ7) -> 721.08667 | CB7: 631.63667 | CC7: 772.28667 | CD7: 818.83333 | CE7: 803.60333 | CF7: =AVERAGE(CB7:CE7) -> 756.59 | CG7: 908.79333 | CH7: 925.30333 | CI7: 886.70667 | CJ7: 892.08333 | CK7: =AVERAGE(CG7:CJ7) -> 903.22167 | CL7: 920 | CM7: 1080 | CN7: =+CN8-CM8+CM7 -> 1075 | CO7: =+CO8-CN8+CN7 -> 1060 | CP7: =AVERAGE(CL7:CO7) -> 1033.75 | CQ7: =+CQ8-CO8+CO7 -> 1070 | CR7: =+CR8-CQ8+CQ7 -> 1075 | CS7: =+CS8-CR8+CR7 -> 1045 | CT7: =+CT8-CS8+CS7 -> 1000 | CU7: =AVERAGE(CQ7:CT7) -> 1047.5 | CV7: =+CV8-CT8+CT7 -> 940 | CW7: =+CW8-CV8+CV7 -> 935 | CX7: =+CX8-CW8+CW7 -> 925 | CY7: =+CY8-CX8+CX7 -> 910 | CZ7: =AVERAGE(CV7:CY7) -> 927.5
B8: Rebar | E8: 328.75 | F8: 342.08333 | G8: 283.75 | H8: 272.91667 | I8: 276.66667 | N8: 272.5 | S8: 279.16667 | T8: 424.33333 | U8: 520 | V8: 546.66667 | W8: 520 | X8: =AVERAGE(T8:W8) -> 502.75 | Y8: 483.33333 | Z8: 480 | AA8: 473.33333 | AB8: 506.66667 | AC8: =AVERAGE(Y8:AB8) -> 485.83333 | AD8: 500 | AE8: 516.66667 | AF8: 550 | AG8: 533.33333 | AH8: =AVERAGE(AD8:AG8) -> 525 | AI8: 535 | AJ8: 645.06667 | AK8: 601.46667 | AL8: 575.46667 | AM8: =AVERAGE(AI8:AL8) -> 589.25 | AN8: 652.66667 | AO8: 848.13333 | AP8: 1007.4667 | AQ8: 766.73333 | AR8: =AVERAGE(AN8:AQ8) -> 818.75 | AS8: 618.86667 | AT8: 495.06667 | AU8: 536.26667 | AV8: 494.46667 | AW8: =AVERAGE(AS8:AV8) -> 536.16667 | AX8: 522 | AY8: 616.86667 | AZ8: 599.93333 | BA8: 645.53333 | BB8: =AVERAGE(AX8:BA8) -> 596.08333 | BC8: 761.66667 | BD8: 754.8 | BE8: 750.26667 | BF8: 782.06667 | BG8: =AVERAGE(BC8:BF8) -> 762.2 | BH8: 767.13333 | BI8: 740.86667 | BJ8: 690.33333 | BK8: 661.73333 | BL8: =AVERAGE(BH8:BK8) -> 715.01667 | BM8: 678.73333 | BN8: 662.53333 | BO8: 645 | BP8: 651.8 | BQ8: =AVERAGE(BM8:BP8) -> 659.51667 | BR8: 687 | BS8: 687.13333 | BT8: 662.6 | BU8: 671.93333 | BV8: =AVERAGE(BR8:BU8) -> 677.16667 | BW8: 622.66667 | BX8: 587.66667 | BY8: 565.53333 | BZ8: 507.13333 | CA8: =AVERAGE(BW8:BZ8) -> 570.75 | CB8: 478.8 | CC8: 540.4 | CD8: 524.53333 | CE8: 503.93333 | CF8: =AVERAGE(CB8:CE8) -> 511.91667 | CG8: 545.06667 | CH8: 532.8 | CI8: 549 | CJ8: 564.4 | CK8: =AVERAGE(CG8:CJ8) -> 547.81667 | CL8: 637 | CM8: 730 | CN8: 725 | CO8: 710 | CP8: =AVERAGE(CL8:CO8) -> 700.5 | CQ8: 720 | CR8: 725 | CS8: 695 | CT8: 650 | CU8: =AVERAGE(CQ8:CT8) -> 697.5 | CV8: 590 | CW8: 585 | CX8: 575 | CY8: 560 | CZ8: =AVERAGE(CV8:CY8) -> 577.5
B9: SBQ | AN9: 766.6 | AO9: 963.33333 | AP9: 1240 | AQ9: 1055.0667 | AR9: =AVERAGE(AN9:AQ9) -> 1006.25 | AS9: 773.93333 | AT9: 691.73333 | AU9: 678.6 | AV9: 710 | AW9: =AVERAGE(AS9:AV9) -> 713.56667 | AX9: 824.73333 | AY9: 840.73333 | AZ9: 854.4 | BA9: 852.33333 | BB9: =AVERAGE(AX9:BA9) -> 843.05 | BC9: 963 | BD9: 1039.7333 | BE9: 1053.6667 | BF9: 1056.6667 | BG9: =AVERAGE(BC9:BF9) -> 1028.2667 | BH9: 1093.8667 | BI9: 1021.2 | BJ9: 900.86667 | BK9: 870.93333 | BL9: =AVERAGE(BH9:BK9) -> 971.71667 | BM9: 868.06667 | BN9: 863.93333 | BO9: 831.93333 | BP9: 824.06667 | BQ9: =AVERAGE(BM9:BP9) -> 847 | BR9: 877.86667 | BS9: 897.6 | BT9: 902.46667 | BU9: 926.06667 | BV9: =AVERAGE(BR9:BU9) -> 901 | BW9: 895.46667 | BX9: 776.33333 | BY9: 727.33333 | BZ9: 648 | CA9: =AVERAGE(BW9:BZ9) -> 761.78333 | CB9: 623.2 | CC9: 645.26667 | CD9: 639.4 | CE9: 601.26667 | CF9: =AVERAGE(CB9:CE9) -> 627.28333 | CG9: 691.2 | CH9: 754.66667 | CI9: 796.93333 | CJ9: 788.8 | CK9: =AVERAGE(CG9:CJ9) -> 757.9 | CL9: 824.13333 | CM9: 910 | CN9: 925 | CO9: 895 | CP9: =AVERAGE(CL9:CO9) -> 888.53333 | CQ9: 905 | CR9: 910 | CS9: 890 | CT9: 845 | CU9: =AVERAGE(CQ9:CT9) -> 887.5 | CV9: 805 | CW9: 810 | CX9: 800 | CY9: 785 | CZ9: =AVERAGE(CV9:CY9) -> 800
B10: Blended Bar | BC10: =(BC35*BC9+BC34*BC8)/(BC34+BC35) -> 818.91674 | BD10: =(BD35*BD9+BD34*BD8)/(BD34+BD35) -> 828.37574 | BE10: =(BE35*BE9+BE34*BE8)/(BE34+BE35) -> 826.24071 | BF10: =(BF35*BF9+BF34*BF8)/(BF34+BF35) -> 852.49904 | BG10: =(BG35*BG9+BG34*BG8)/(BG34+BG35) -> 831.84352 | BH10: =(BH35*BH9+BH34*BH8)/(BH34+BH35) -> 846.48471 | BI10: =(BI35*BI9+BI34*BI8)/(BI34+BI35) -> 805.66069 | BJ10: =(BJ35*BJ9+BJ34*BJ8)/(BJ34+BJ35) -> 738.84788 | ... CZ10: =(CZ35*CZ9+CZ34*CZ8)/(CZ34+CZ35) -> 626.9332
B11: Structural | E11: 384.58333 | F11: 379.58333 | G11: 333.75 | H11: 345.83333 | I11: 342.91667 | N11: 335.83333 | S11: 315.83333 | T11: 442.33333 | U11: 525.33333 | V11: 558 | W11: 578.66667 | X11: =AVERAGE(T11:W11) -> 526.08333 | Y11: 583 | Z11: 583 | AA11: 540 | AB11: 620 | AC11: =AVERAGE(Y11:AB11) -> 581.5 | AD11: 620 | AE11: 640.66667 | AF11: 670 | AG11: 670 | AH11: =AVERAGE(AD11:AG11) -> 650.16667 | AI11: 695 | AJ11: 770 | AK11: 770 | AL11: 787 | AM11: =AVERAGE(AI11:AL11) -> 755.5 | AN11: 855.33333 | AO11: 987 | AP11: 1133 | AQ11: 991.66667 | AR11: =AVERAGE(AN11:AQ11) -> 991.75 | AS11: 894 | AT11: 716.66667 | AU11: 741.66667 | AV11: 735 | AW11: =AVERAGE(AS11:AV11) -> 771.83333 | AX11: 735 | AY11: 769.66667 | AZ11: 734.66667 | BA11: 758.66667 | BB11: =AVERAGE(AX11:BA11) -> 749.5 | BC11: 875 | BD11: 895 | BE11: 831.332 | BF11: 820.33333 | BG11: =AVERAGE(BC11:BF11) -> 855.41633 | BH11: 837.66667 | BI11: 819 | BJ11: 769.66667 | BK11: 757.66499 | BL11: =AVERAGE(BH11:BK11) -> 795.99958 | BM11: 766.99497 | BN11: 769.66162 | BO11: 762.32833 | BP11: 758.66169 | BQ11: =AVERAGE(BM11:BP11) -> 764.41165 | BR11: 791.33333 | BS11: 794 | BT11: 799 | BU11: 796 | BV11: =AVERAGE(BR11:BU11) -> 795.08333 | BW11: 751.33333 | BX11: 702 | BY11: 685 | BZ11: 644 | CA11: =AVERAGE(BW11:BZ11) -> 695.58333 | CB11: 615.66667 | CC11: 642.06667 | CD11: 668.66667 | CE11: 650.33333 | CF11: =AVERAGE(CB11:CE11) -> 644.18333 | CG11: 703 | CH11: 712.2 | CI11: 700 | CJ11: 620 | CK11: =AVERAGE(CG11:CJ11) -> 683.8 | CL11: 690 | CM11: 835 | CN11: 830 | CO11: 815 | CP11: =AVERAGE(CL11:CO11) -> 792.5 | CQ11: 825 | CR11: 830 | CS11: 800 | CT11: 755 | CU11: =AVERAGE(CQ11:CT11) -> 802.5 | CV11: 695 | CW11: 705 | CX11: 695 | CY11: 680 | CZ11: =AVERAGE(CV11:CY11) -> 693.75
B12: Plate | E12: 417.91667 | F12: 430.37709 | G12: 330.86629 | H12: 340.5 | I12: 290.66667 | N12: 323.75 | S12: 331.66667 | T12: 490 | U12: 621 | V12: 716.33333 | W12: 786.33333 | X12: =AVERAGE(T12:W12) -> 653.41667 | Y12: 776.33333 | Z12: 742 | AA12: 690 | AB12: 765 | AC12: =AVERAGE(Y12:AB12) -> 743.33333 | AD12: 765 | AE12: 776.66667 | AF12: 796.66667 | AG12: 790 | AH12: =AVERAGE(AD12:AG12) -> 782.08333 | AI12: 760 | AJ12: 800 | AK12: 790 | AL12: 790 | AM12: =AVERAGE(AI12:AL12) -> 785 | AN12: 910 | AO12: 1235 | AP12: 1443.3333 | AQ12: 1130 | AR12: =AVERAGE(AN12:AQ12) -> 1179.5833 | AS12: 743.33333 | AT12: 566.66667 | AU12: 600 | AV12: 596.66667 | AW12: =AVERAGE(AS12:AV12) -> 626.66667 | AX12: 681.66667 | AY12: 823.33333 | AZ12: 755.66667 | BA12: 736.66667 | BB12: =AVERAGE(AX12:BA12) -> 749.33333 | BC12: 943.33333 | BD12: 1040 | BE12: 994.00088 | BF12: 904.66667 | BG12: =AVERAGE(BC12:BF12) -> 970.50022 | BH12: 914.66667 | BI12: 870.66667 | BJ12: 781 | BK12: 700.33333 | BL12: =AVERAGE(BH12:BK12) -> 816.66667 | BM12: 718 | BN12: 718 | BO12: 706.33333 | BP12: 721.33333 | BQ12: =AVERAGE(BM12:BP12) -> 715.91667 | BR12: 787 | BS12: 811.66667 | BT12: 846.66667 | BU12: 794 | BV12: =AVERAGE(BR12:BU12) -> 809.83333 | BW12: 664.33333 | BX12: 581.33333 | BY12: 540.66667 | BZ12: 458.66667 | CA12: =AVERAGE(BW12:BZ12) -> 561.25 | CB12: 473.33333 | CC12: 622 | CD12: 570.33333 | CE12: 509.66667 | CF12: =AVERAGE(CB12:CE12) -> 543.83333 | CG12: 682 | CH12: 717.78261 | CI12: 691.80105 | CJ12: 640.61304 | CK12: =AVERAGE(CG12:CJ12) -> 683.04918 | CL12: 819.59279 | CM12: 965 | CN12: 910 | CO12: 865 | CP12: =AVERAGE(CL12:CO12) -> 889.8982 | CQ12: 880 | CR12: 850 | CS12: 840 | CT12: 795 | CU12: =AVERAGE(CQ12:CT12) -> 841.25 | CV12: 740 | CW12: 755 | CX12: 725 | CY12: 725 | CZ12: =AVERAGE(CV12:CY12) -> 736.25
B13: Shredded Scrap (Long Ton) | T13: 244.5 | U13: 201.46667 | V13: 265.48333 | W13: 287.01667 | X13: =AVERAGE(T13:W13) -> 249.61667 | Y13: 246.37667 | Z13: 203.84667 | AA13: 220.79667 | AB13: 246.94 | AC13: =AVERAGE(Y13:AB13) -> 229.49 | AD13: 241.68333 | AE13: 267.78 | AF13: 254.14667 | AG13: 228.62 | AH13: =AVERAGE(AD13:AG13) -> 248.0575 | AI13: 299.89 | AJ13: 286.15333 | AK13: 278.87 | AL13: 295.4 | AM13: =AVERAGE(AI13:AL13) -> 290.07833 | AN13: 392.54 | AO13: 547.20667 | AP13: 513.71333 | AQ13: 193.66333 | AR13: =AVERAGE(AN13:AQ13) -> 411.78083 | AS13: 213.37333 | AT13: 191.80667 | AU13: 269.50667 | AV13: 265.71333 | AW13: =AVERAGE(AS13:AV13) -> 235.1 | AX13: 358.61667 | AY13: 368.89333 | AZ13: 339.70667 | BA13: 367.51667 | BB13: =AVERAGE(AX13:BA13) -> 358.68333 | BC13: 456.45667 | BD13: 447.39333 | BE13: 450 | BF13: 429.87 | BG13: =AVERAGE(BC13:BF13) -> 445.93 | BH13: 449.5 | BI13: 414.82667 | BJ13: 373.72 | BK13: 369.33 | BL13: =AVERAGE(BH13:BK13) -> 401.84417 | BM13: 390.07333 | BN13: 374.86667 | BO13: 366.60333 | BP13: 383.98333 | BQ13: =AVERAGE(BM13:BP13) -> 378.88167 | BR13: 412.41333 | BS13: 383.64333 | BT13: 374.24333 | BU13: 338.38333 | BV13: =AVERAGE(BR13:BU13) -> 377.17083 | BW13: 277.58667 | BX13: 249.18333 | BY13: 244.09 | BZ13: 171.85667 | CA13: =AVERAGE(BW13:BZ13) -> 235.67917 | CB13: 194.21667 | CC13: 260.70667 | CD13: 235.08 | CE13: 227.43667 | CF13: =AVERAGE(CB13:CE13) -> 229.36 | CG13: 301.52667 | CH13: 292.27333 | CI13: 289.08667 | CJ13: 272.81667 | CK13: =AVERAGE(CG13:CJ13) -> 288.92583 | CL13: 332.51333 | CM13: 375 | CN13: 360 | CO13: 345 | CP13: =AVERAGE(CL13:CO13) -> 353.12833 | CQ13: 355 | CR13: 360 | CS13: 350 | CT13: 335 | CU13: =AVERAGE(CQ13:CT13) -> 350 | CV13: 305 | CW13: 310 | CX13: 300 | CY13: 285 | CZ13: =AVERAGE(CV13:CY13) -> 300
B14: #1 Busheling Scrap (Long Ton) | T14: 260.22006 | U14: 251.76046 | V14: 365.16595 | W14: 411.30952 | X14: =AVERAGE(T14:W14) -> 322.114 | Y14: 303.50324 | Z14: 206.73882 | AA14: 223.92754 | AB14: 265.51587 | AC14: =AVERAGE(Y14:AB14) -> 249.92137 | AD14: 265.2193 | AE14: 315.45455 | AF14: 298.47101 | AG14: 231.23333 | AH14: =AVERAGE(AD14:AG14) -> 277.59455 | AI14: 301.20106 | AJ14: 310.33 | AK14: 312.79333 | AL14: 320.09333 | AM14: =AVERAGE(AI14:AL14) -> 311.10443 | AN14: 414.93667 | AO14: 682.81333 | AP14: 773.15667 | AQ14: 218.44667 | AR14: =AVERAGE(AN14:AQ14) -> 522.33833 | AS14: 226.29667 | AT14: 198.70333 | AU14: 315.73667 | AV14: 307.81667 | AW14: =AVERAGE(AS14:AV14) -> 262.13833 | AX14: 414.06333 | AY14: 467.11333 | AZ14: 417.85667 | BA14: 406.64 | BB14: =AVERAGE(AX14:BA14) -> 426.41833 | BC14: 485.19333 | BD14: 498.10667 | BE14: 511.63333 | BF14: 482.8 | BG14: =AVERAGE(BC14:BF14) -> 494.43333 | BH14: 487.22667 | BI14: 429.26333 | BJ14: 382.78 | BK14: 371.63 | BL14: =AVERAGE(BH14:BK14) -> 417.725 | BM14: 393.10333 | BN14: 392.21333 | BO14: 404.1 | BP14: 417.89333 | BQ14: =AVERAGE(BM14:BP14) -> 401.8275 | BR14: 414.45 | BS14: 397.29333 | BT14: 397 | BU14: 362.80667 | BV14: =AVERAGE(BR14:BU14) -> 392.8875 | BW14: 290.99333 | BX14: 248.18333 | BY14: 254.76333 | BZ14: 175.89333 | CA14: =AVERAGE(BW14:BZ14) -> 242.45833 | CB14: 183.29333 | CC14: 259.92333 | CD14: 261.29333 | CE14: 234.56333 | CF14: =AVERAGE(CB14:CE14) -> 234.76833 | CG14: 325.11 | CH14: 351.33333 | CI14: 359.13 | CJ14: 332.75667 | CK14: =AVERAGE(CG14:CJ14) -> 342.0825 | CL14: 366.45667 | CM14: 385 | CN14: 370 | CO14: 355 | CP14: =AVERAGE(CL14:CO14) -> 369.11417 | CQ14: 365 | CR14: 370 | CS14: 360 | CT14: 355 | CU14: =AVERAGE(CQ14:CT14) -> 362.5 | CV14: 325 | CW14: 330 | CX14: 320 | CY14: 305 | CZ14: =AVERAGE(CV14:CY14) -> 320
A16: Steel Segment
A17: Nucor Realizations
B18: Sheet | S18: =S83/S33*1000 -> 341.04271 | X18: =X83/X33*1000 -> 601.19695 | Y18: 675 | Z18: 609 | AA18: 523 | AB18: 583 | AC18: =AC83/AC33*1000 -> 598.54049 | AD18: 594 | AE18: 625 | AF18: 673 | AG18: 624 | AH18: =AH83/AH33*1000 -> 628.90453 | AI18: 596 | AJ18: 630 | AK18: 602 | AL18: 606 | AM18: =AVERAGE(AI18:AL18) -> 608.5 | AN18: 660 | AO18: 872 | AP18: 1090 | AQ18: 854 | AR18: =AVERAGE(AN18:AQ18) -> 869 | AS18: 610 | AT18: 499 | AU18: 510 | AV18: 597 | AW18: =AVERAGE(AS18:AV18) -> 554 | AX18: 634 | AY18: 726 | AZ18: 680 | BA18: 637 | BB18: =AVERAGE(AX18:BA18) -> 669.25 | BC18: 755 | BD18: 894 | BE18: 800 | BF18: 747 | BG18: 796 | BH18: 780 | BI18: 759 | BJ18: 707 | BK18: 690 | BL18: 735 | BM18: 699 | BN18: 676 | BO18: 693 | BP18: 724 | BQ18: =AVERAGE(BM18:BP18) -> 698 | BR18: 744 | BS18: 737 | BT18: 750 | BU18: 712 | BV18: =AVERAGE(BR18:BU18) -> 735.75 | BW18: 663 | BX18: 560 | BY18: 552 | BZ18: 508 | CA18: =AVERAGE(BW18:BZ18) -> 570.75 | CB18: 471 | CC18: 550 | CD18: 666 | CE18: 603 | CF18: =AVERAGE(CB18:CE18) -> 572.5 | CG18: 661 | CH18: 709 | CI18: 695 | CJ18: 691 | CK18: =AVERAGE(CG18:CJ18) -> 689 | CL18: 723 | CM18: ='Price Relationships'!$C$70 -> 870.25 | CN18: ='Price Relationships'!$C$71 -> 907.1875 | CO18: ='Price Relationships'!$C$72 -> 882.71562 | CP18: =AVERAGE(CL18:CO18) -> 845.78828 | CQ18: ='Price Relationships'!$C$73 -> 884.95047 | CR18: ='Price Relationships'!$C$74 -> 864.13266 | CS18: ='Price Relationships'!$C$75 -> 849.64643 | CT18: ='Price Relationships'!$C$76 -> 812.17625 | CU18: =AVERAGE(CQ18:CT18) -> 852.72645 | CV18: ='Price Relationships'!$C$77 -> 779.46169 | CW18: ='Price Relationships'!$C$78 -> 778.81159 | CX18: ='Price Relationships'!$C$79 -> 756.98406 | CY18: ='Price Relationships'!$C$80 -> 749.34442 | CZ18: =AVERAGE(CV18:CY18) -> 766.15044
B19: Bars | S19: =S84/S34*1000 -> 315.87794 | X19: =X84/X34*1000 -> 502.09115 | Y19: 514 | Z19: 499 | AA19: 496 | AB19: 542 | AC19: =AC84/AC34*1000 -> 511.74411 | AD19: 543 | AE19: 567 | AF19: 601 | AG19: 576 | AH19: =AH84/AH34*1000 -> 571.39229 | AI19: 585 | AJ19: 650 | AK19: 631 | AL19: 627 | AM19: =AVERAGE(AI19:AL19) -> 623.25 | AN19: 696 | AO19: 862 | AP19: 1011 | AQ19: 758 | AR19: =AVERAGE(AN19:AQ19) -> 831.75 | AS19: 633 | AT19: 538 | AU19: 557 | AV19: 535 | AW19: =AVERAGE(AS19:AV19) -> 565.75 | AX19: 618 | AY19: 709 | AZ19: 666 | BA19: 669 | BB19: =AVERAGE(AX19:BA19) -> 665.5 | BC19: 779 | BD19: 803 | BE19: 811 | BF19: 796 | BG19: 798 | BH19: 823 | BI19: 795 | BJ19: 745 | BK19: 723 | BL19: 772 | BM19: 732 | BN19: 731 | BO19: 708 | BP19: 709 | BQ19: =AVERAGE(BM19:BP19) -> 720 | BR19: 737 | BS19: 732 | BT19: 738 | BU19: 724 | BV19: =AVERAGE(BR19:BU19) -> 732.75 | BW19: 698 | BX19: 623 | BY19: 625 | BZ19: 558 | CA19: =AVERAGE(BW19:BZ19) -> 626 | CB19: 505 | CC19: 561 | CD19: 567 | CE19: 544 | CF19: =AVERAGE(CB19:CE19) -> 544.25 | CG19: 600 | CH19: 605 | CI19: 624 | CJ19: 607 | CK19: =AVERAGE(CG19:CJ19) -> 609 | CL19: 660 | CM19: ='Price Relationships'!$E$70 -> 744.02332 | CN19: ='Price Relationships'!$E$71 -> 761.16689 | CO19: ='Price Relationships'!$E$72 -> 748.71692 | CP19: =AVERAGE(CL19:CO19) -> 728.47678 | CQ19: ='Price Relationships'!$E$73 -> 751.06516 | CR19: ='Price Relationships'!$E$74 -> 758.72568 | CS19: ='Price Relationships'!$E$75 -> 738.44975 | CT19: ='Price Relationships'!$E$76 -> 697.66211 | CU19: =AVERAGE(CQ19:CT19) -> 736.47568 | CV19: ='Price Relationships'!$E$77 -> 637.39445 | CW19: ='Price Relationships'!$E$78 -> 626.54625 | CX19: ='Price Relationships'!$E$79 -> 616.49294 | CY19: ='Price Relationships'!$E$80 -> 601.7096 | CZ19: =AVERAGE(CV19:CY19) -> 620.53581
B20: Structural | S20: =S86/S36*1000 -> 361.81978 | X20: =X86/X36*1000 -> 543.79638 | Y20: 605 | Z20: 574 | AA20: 561 | AB20: 634 | AC20: =AC86/AC36*1000 -> 593.84299 | AD20: 649 | AE20: 667 | AF20: 703 | AG20: 727 | AH20: =AH86/AH36*1000 -> 687.16142 | AI20: 754 | AJ20: 825 | AK20: 839 | AL20: 867 | AM20: =AVERAGE(AI20:AL20) -> 821.25 | AN20: 930 | AO20: 1041 | AP20: 1153 | AQ20: 1109 | AR20: =AVERAGE(AN20:AQ20) -> 1058.25 | AS20: 967 | AT20: 763 | AU20: 738 | AV20: 726 | AW20: =AVERAGE(AS20:AV20) -> 798.5 | AX20: 740 | AY20: 770 | AZ20: 786 | BA20: 773 | BB20: =AVERAGE(AX20:BA20) -> 767.25 | BC20: 831 | BD20: 923 | BE20: 901 | BF20: 891 | BG20: 884 | BH20: 866 | BI20: 905 | BJ20: 958 | BK20: 956 | BL20: 925 | BM20: 949 | BN20: 959 | BO20: 923 | BP20: 969 | BQ20: =AVERAGE(BM20:BP20) -> 950 | BR20: 941 | BS20: 1039 | BT20: 1058 | BU20: 1063 | BV20: =AVERAGE(BR20:BU20) -> 1025.25 | BW20: 996 | BX20: 991 | BY20: 926 | BZ20: 923 | CA20: =AVERAGE(BW20:BZ20) -> 959 | CB20: 870 | CC20: 845 | CD20: 865 | CE20: 837 | CF20: =AVERAGE(CB20:CE20) -> 854.25 | CG20: 738 | CH20: 766 | CI20: 769 | CJ20: 764 | CK20: =AVERAGE(CG20:CJ20) -> 759.25 | CL20: 798 | CM20: ='Price Relationships'!$G$70 -> 864.1 | CN20: ='Price Relationships'!$G$71 -> 908.87 | CO20: ='Price Relationships'!$G$72 -> 935.709 | CP20: =AVERAGE(CL20:CO20) -> 876.66975 | CQ20: ='Price Relationships'!$G$73 -> 957.4963 | CR20: ='Price Relationships'!$G$74 -> 974.24741 | CS20: ='Price Relationships'!$G$75 -> 976.97319 | CT20: ='Price Relationships'!$G$76 -> 965.38123 | CU20: =AVERAGE(CQ20:CT20) -> 968.52453 | CV20: ='Price Relationships'!$G$77 -> 939.26686 | CW20: ='Price Relationships'!$G$78 -> 923.9868 | CX20: ='Price Relationships'!$G$79 -> 910.29076 | CY20: ='Price Relationships'!$G$80 -> 896.20353 | CZ20: =AVERAGE(CV20:CY20) -> 917.43699
B21: Plate | S21: =S87/S37*1000 -> 322.17417 | X21: =X87/X37*1000 -> 656.37361 | Y21: 763 | Z21: 708 | AA21: 625 | AB21: 684 | AC21: =AC87/AC37*1000 -> 696.65455 | AD21: 698 | AE21: 712 | AF21: 746 | AG21: 732 | AH21: =AH87/AH37*1000 -> 721.78973 | AI21: 685 | AJ21: 741 | AK21: 724 | AL21: 715 | AM21: =AVERAGE(AI21:AL21) -> 716.25 | AN21: 751 | AO21: 974 | AP21: 1289 | AQ21: 1096 | AR21: =AVERAGE(AN21:AQ21) -> 1027.5 | AS21: 714 | AT21: 542 | AU21: 555 | AV21: 595 | AW21: =AVERAGE(AS21:AV21) -> 601.5 | AX21: 637 | AY21: 761 | AZ21: 752 | BA21: 731 | BB21: =AVERAGE(AX21:BA21) -> 720.25 | BC21: 880 | BD21: 1029 | BE21: 1021 | BF21: 946 | BG21: 970 | BH21: 929 | BI21: 922 | BJ21: 837 | BK21: 778 | BL21: 872 | BM21: 769 | BN21: 765 | BO21: 753 | BP21: 767 | BQ21: =AVERAGE(BM21:BP21) -> 763.5 | BR21: 816 | BS21: 837 | BT21: 863 | BU21: 875 | BV21: =AVERAGE(BR21:BU21) -> 847.75 | BW21: 805 | BX21: 691 | BY21: 648 | BZ21: 588 | CA21: =AVERAGE(BW21:BZ21) -> 683 | CB21: 545 | CC21: 604 | CD21: 661 | CE21: 584 | CF21: =AVERAGE(CB21:CE21) -> 598.5 | CG21: 703 | CH21: 746 | CI21: 749 | CJ21: 727 | CK21: =AVERAGE(CG21:CJ21) -> 731.25 | CL21: 785 | CM21: ='Price Relationships'!$I$70 -> 911.08845 | CN21: ='Price Relationships'!$I$71 -> 947.47484 | CO21: ='Price Relationships'!$I$72 -> 904.0844 | CP21: =AVERAGE(CL21:CO21) -> 886.91192 | CQ21: ='Price Relationships'!$I$73 -> 934.03233 | CR21: ='Price Relationships'!$I$74 -> 924.40004 | CS21: ='Price Relationships'!$I$75 -> 920.92803 | CT21: ='Price Relationships'!$I$76 -> 887.52538 | CU21: =AVERAGE(CQ21:CT21) -> 916.72144 | CV21: ='Price Relationships'!$I$77 -> 839.76573 | CW21: ='Price Relationships'!$I$78 -> 840.40475 | CX21: ='Price Relationships'!$I$79 -> 812.60095 | CY21: ='Price Relationships'!$I$80 -> 805.56259 | CZ21: =AVERAGE(CV21:CY21) -> 824.58351
C22: Total Average Price | H22: =1000*H89/H38 -> 369.58611 | I22: =1000*I89/I38 -> 312.69449 | J22: =1000*J89/J38 -> 306.66184 | K22: =1000*K89/K38 -> 324.22745 | L22: =1000*L89/L38 -> 345.15783 | M22: =1000*M89/M38 -> 343.36313 | N22: =1000*N89/N38 -> 329.91631 | O22: =1000*O89/O38 -> 321.2573 | ... R22: =1000*R89/R38 -> 351.52998 | S22: =(S18*S33+S19*S34+S20*S36+S21*S37)/S38 -> 334.87837 | T22: =1000*T89/T38 -> 436.74757 | U22: =1000*U89/U38 -> 552.30566 | V22: =1000*V89/V38 -> 638.57591 | W22: =1000*W89/W38 -> 660.29759 | X22: =(X18*X33+X19*X34+X20*X36+X21*X37)/X38 -> 568.3606 | Y22: =1000*Y89/Y38 -> 629.26621 | Z22: =1000*Z89/Z38 -> 578.87854 | AA22: =1000*AA89/AA38 -> 530.30973 | AB22: =1000*AB89/AB38 -> 590.70095 | AC22: =(AC18*AC33+AC19*AC34+AC20*AC36+AC21*AC37)/AC38 -> 581.59458 | AD22: =1000*AD89/AD38 -> 598.06798 | AE22: =(AE18*AE33+AE19*AE34+AE20*AE36+AE21*AE37)/AE38 -> 621.72807 | AF22: =(AF18*AF33+AF19*AF34+AF20*AF36+AF21*AF37)/AF38 -> 664.02566 | AG22: =(AG18*AG33+AG19*AG34+AG20*AG36+AG21*AG37)/AG38 -> 640.51135 | AH22: =(AH18*AH33+AH19*AH34+AH20*AH36+AH21*AH37)/AH38 -> 630.77092 | AI22: =(AI18*AI33+AI19*AI34+AI20*AI36+AI21*AI37)/AI38 -> 625.92656 | AJ22: =(AJ18*AJ33+AJ19*AJ34+AJ20*AJ36+AJ21*AJ37)/AJ38 -> 681.86135 | AK22: =(AK18*AK33+AK19*AK34+AK20*AK36+AK21*AK37)/AK38 -> 663.89976 | AL22: =(AL18*AL33+AL19*AL34+AL20*AL36+AL21*AL37)/AL38 -> 666.64947 | ... BB22: =(BB18*BB33+BB19*BB34+BB20*BB36+BB21*BB37)/BB38 -> 688.73232 | BC22: =(BC18*BC33+BC19*(BC34+BC35)+BC20*BC36+BC21*BC37)/BC38 -> 788.94885 | BD22: =(BD18*BD33+BD19*(BD34+BD35)+BD20*BD36+BD21*BD37)/BD38 -> 890.83218 | BE22: =(BE18*BE33+BE19*(BE34+BE35)+BE20*BE36+BE21*BE37)/BE38 -> 847.09847 | BF22: =(BF18*BF33+BF19*(BF34+BF35)+BF20*BF36+BF21*BF37)/BF38 -> 806.20474 | BG22: =(BG18*BG33+BG19*(BG34+BG35)+BG20*BG36+BG21*BG37)/BG38 -> 832.40605 | BH22: =(BH18*BH33+BH19*(BH34+BH35)+BH20*BH36+BH21*BH37)/BH38 -> 824.25577 | BI22: =(BI18*BI33+BI19*(BI34+BI35)+BI20*BI36+BI21*BI37)/BI38 -> 811.37626 | BJ22: =(BJ18*BJ33+BJ19*(BJ34+BJ35)+BJ20*BJ36+BJ21*BJ37)/BJ38 -> 771.67007 | ... CC22: =(CC18*CC33+CC19*(CC34+CC35)+CC20*CC36+CC21*CC37)/CC38 -> 593.37584 | CD22: =(CD18*CD33+CD19*(CD34+CD35)+CD20*CD36+CD21*CD37+CD158*CD124)/CD38 -> 663.7084 | CE22: =(CE18*CE33+CE19*(CE34+CE35)+CE20*CE36+CE21*CE37+CE158*CE124)/CE38 -> 614.37636 | CF22: =(CF18*CF33+CF19*(CF34+CF35)+CF20*CF36+CF21*CF37+CF158*CF124)/CF38 -> 602.72537 | CG22: =(CG18*CG33+CG19*(CG34+CG35)+CG20*CG36+CG21*CG37)/CG38 -> 657.06337 | CH22: =(CH18*CH33+CH19*(CH34+CH35)+CH20*CH36+CH21*CH37)/CH38 -> 687.51919 | CI22: =(CI18*CI33+CI19*(CI34+CI35)+CI20*CI36+CI21*CI37)/CI38 -> 684.86356 | CJ22: =(CJ18*CJ33+CJ19*(CJ34+CJ35)+CJ20*CJ36+CJ21*CJ37)/CJ38 -> 673.67725 | CK22: =(CK18*CK33+CK19*(CK34+CK35)+CK20*CK36+CK21*CK37)/CK38 -> 675.94388 | CL22: =(CL18*CL33+CL19*(CL34+CL35)+CL20*CL36+CL21*CL37)/CL38 -> 716.43142 | CM22: =(CM18*CM33+CM19*(CM34+CM35)+CM20*CM36+CM21*CM37)/CM38 -> 837.22241 | CN22: =(CN18*CN33+CN19*(CN34+CN35)+CN20*CN36+CN21*CN37)/CN38 -> 865.81747 | ... CZ22: =(CZ18*CZ33+CZ19*(CZ34+CZ35)+CZ20*CZ36+CZ21*CZ37)/CZ38 -> 736.90109
C23: Y-O-Y Change | I23: =I22/H22-1 -> -0.15393331 | N23: =N22/I22-1 -> 0.055075538 | O23: =O22/J22-1 -> 0.047594631 | P23: =P22/K22-1 -> 0.030141598 | Q23: =Q22/L22-1 -> -0.036676345 | R23: =R22/M22-1 -> 0.023784876 | S23: =S22/N22-1 -> 0.015040376 | T23: =T22/O22-1 -> 0.35949461 | U23: =U22/P22-1 -> 0.65360884 | ... CZ23: =CZ22/CU22-1 -> -0.11622298
C24: Sequential Change | K24: =K22/J22-1 -> 0.057280061 | L24: =L22/K22-1 -> 0.064554631 | M24: =M22/L22-1 -> -0.0051996474 | P24: =P22/O22-1 -> 0.039665667 | Q24: =Q22/P22-1 -> -0.0044954391 | R24: =R22/Q22-1 -> 0.05723715 | T24: =T22/R22-1 -> 0.2424191 | U24: =U22/T22-1 -> 0.26458782 | V24: =V22/U22-1 -> 0.15620021 | W24: =W22/V22-1 -> 0.034015815 | Y24: =Y22/W22-1 -> -0.046996054 | Z24: =Z22/Y22-1 -> -0.080073692 | AA24: =AA22/Z22-1 -> -0.083901564 | AB24: =AB22/AA22-1 -> 0.11387916 | AD24: =AD22/AB22-1 -> 0.012471676 | AE24: =AE22/AD22-1 -> 0.039560871 | AF24: =AF22/AE22-1 -> 0.068032286 | AG24: =AG22/AF22-1 -> -0.03541174 | AI24: =AI22/AG22-1 -> -0.022770538 | AJ24: =AJ22/AI22-1 -> 0.089363177 | AK24: =AK22/AJ22-1 -> -0.026341994 | AL24: =AL22/AK22-1 -> 0.0041417495 | AN24: =AN22/AL22-1 -> 0.084529996 | AO24: =AO22/AN22-1 -> 0.25483361 | AP24: =AP22/AO22-1 -> 0.22165037 | AQ24: =AQ22/AP22-1 -> -0.18038221 | AS24: =AS22/AQ22-1 -> -0.24932107 | AT24: =AT22/AS22-1 -> -0.18394575 | AU24: =AU22/AT22-1 -> 0.0048550757 | AV24: =AV22/AU22-1 -> 0.064384229 | AX24: =AX22/AV22-1 -> 0.080280447 | AY24: =AY22/AX22-1 -> 0.14070151 | AZ24: =AZ22/AY22-1 -> -0.044041397 | BA24: =BA22/AZ22-1 -> -0.032360575 | BC24: =BC22/BA22-1 -> 0.16286419 | BD24: =BD22/BC22-1 -> 0.12913808 | BE24: =BE22/BD22-1 -> -0.049093094 | BF24: =BF22/BE22-1 -> -0.048275061 | BH24: =BH22/BF22-1 -> 0.022390131 | BI24: =BI22/BH22-1 -> -0.015625622 | BJ24: =BJ22/BI22-1 -> -0.048936848 | BK24: =BK22/BJ22-1 -> -0.028039585 | BM24: =BM22/BK22-1 -> 0.0080085788 | BN24: =BN22/BM22-1 -> -0.013896097 | BO24: =BO22/BN22-1 -> -0.005689124 | BP24: =BP22/BO22-1 -> 0.029120046 | BR24: =BR22/BP22-1 -> 0.025856296 | BS24: =BS22/BR22-1 -> 0.0085867518 | BT24: =BT22/BS22-1 -> 0.019396306 | BU24: =BU22/BT22-1 -> -0.036064509 | BW24: =BW22/BU22-1 -> -0.056142054 | BX24: =BX22/BW22-1 -> -0.11849553 | BY24: =BY22/BX22-1 -> -0.015852934 | BZ24: =BZ22/BY22-1 -> -0.074919505 | CB24: =CB22/BZ22-1 -> -0.084939619 | CC24: =CC22/CB22-1 -> 0.103731 | CD24: =CD22/CC22-1 -> 0.11852954 | CE24: =CE22/CD22-1 -> -0.074327875 | CG24: =CG22/CE22-1 -> 0.06948023 | CH24: =CH22/CG22-1 -> 0.046351415 | CI24: =CI22/CH22-1 -> -0.003862631 | CJ24: =CJ22/CI22-1 -> -0.016333628 | CL24: =CL22/CJ22-1 -> 0.063463873 | CM24: =CM22/CL22-1 -> 0.16860091 | CN24: =CN22/CM22-1 -> 0.034154682 | CO24: =CO22/CN22-1 -> -0.02297405 | CQ24: =CQ22/CO22-1 -> 0.0090286829 | CR24: =CR22/CQ22-1 -> -0.0037582822 | CS24: =CS22/CR22-1 -> -0.019616688 | CT24: =CT22/CS22-1 -> -0.044638418 | CV24: =CV22/CT22-1 -> -0.056499051 | CW24: =CW22/CV22-1 -> -0.00099868885 | CX24: =CX22/CW22-1 -> -0.029062298 | CY24: =CY22/CX22-1 -> -0.016784073
A26: Volume Growth
B27: Sheet | I27: =Operations!I33/Operations!H33-1 -> 0.13868941 | N27: =Operations!N33/Operations!I33-1 -> 0.14426488 | S27: =Operations!S33/Operations!N33-1 -> 0.19772649 | T27: =Operations!T33/Operations!O33-1 -> 0.21661891 | U27: =Operations!U33/Operations!P33-1 -> 0.24422051 | V27: =Operations!V33/Operations!Q33-1 -> 0.14042069 | W27: =Operations!W33/Operations!R33-1 -> 0.049347703 | X27: =Operations!X33/Operations!S33-1 -> 0.16163359 | Y27: =Operations!Y33/Operations!T33-1 -> -0.026848799 | Z27: =Operations!Z33/Operations!U33-1 -> -0.049070986 | ... AZ27: =Operations!AZ33/Operations!AU33-1 -> 0.058045977 | BA27: 0.1 | BB27: =Operations!BB33/Operations!AW33-1 -> 0.42632387 | BC27: =Operations!BC33/Operations!AX33-1 -> 0.044 | BD27: =Operations!BD33/Operations!AY33-1 -> -0.092445853 | BE27: =Operations!BE33/Operations!AZ33-1 -> 0.0065181966 | BF27: =Operations!BF33/Operations!BA33-1 -> 0.082941176 | BG27: =Operations!BG33/Operations!BB33-1 -> 0.0088781275 | BH27: =Operations!BH33/Operations!BC33-1 -> -0.019157088 | BI27: =Operations!BI33/Operations!BD33-1 -> 0.12048894 | ... CL27: =Operations!CL33/Operations!CG33-1 -> -0.052223582 | CM27: 0.02 | CN27: 0.02 | CO27: 0.02 | CP27: =Operations!CP33/Operations!CK33-1 -> 0.00098807862 | CQ27: 0.02 | CR27: 0.02 | CS27: 0.02 | CT27: 0.02 | CU27: =Operations!CU33/Operations!CP33-1 -> 0.02 | CV27: 0.08 | CW27: 0.08 | CX27: 0.08 | CY27: 0.08 | CZ27: =Operations!CZ33/Operations!CU33-1 -> 0.08
B28: Bars | I28: =Operations!I34/Operations!H34-1 -> 0.21638751 | N28: =Operations!N34/Operations!I34-1 -> 0.096762188 | S28: =Operations!S34/Operations!N34-1 -> 0.87648456 | T28: =Operations!T34/Operations!O34-1 -> 0.02050581 | U28: =Operations!U34/Operations!P34-1 -> 0.0045420136 | V28: =Operations!V34/Operations!Q34-1 -> -0.1015299 | W28: =Operations!W34/Operations!R34-1 -> -0.13455657 | X28: =Operations!X34/Operations!S34-1 -> -0.051717902 | Y28: =Operations!Y34/Operations!T34-1 -> -0.078365707 | Z28: =Operations!Z34/Operations!U34-1 -> 0.14770158 | ... AZ28: =Operations!AZ34/Operations!AU34-1 -> 0.063200815 | BA28: -0.05 | BB28: =Operations!BB34/Operations!AW34-1 -> 0.10746762 | BC28: =Operations!BC34/Operations!AX34-1 -> -0.25097182 | BD28: =Operations!BD34/Operations!AY34-1 -> -0.02032294 | BE28: =Operations!BE34/Operations!AZ34-1 -> -0.12104506 | BF28: =Operations!BF34/Operations!BA34-1 -> -0.15371783 | BG28: =Operations!BG34/Operations!BB34-1 -> -0.14033342 | BH28: =Operations!BH34/Operations!BC34-1 -> 0.23872851 | BI28: =Operations!BI34/Operations!BD34-1 -> 0.15799943 | ... CL28: =Operations!CL34/Operations!CG34-1 -> 0.33085106 | CM28: 0.02 | CN28: 0.02 | CO28: 0.02 | CP28: =Operations!CP34/Operations!CK34-1 -> 0.088947617 | CQ28: 0.02 | CR28: 0.02 | CS28: 0.02 | CT28: 0.02 | CU28: =Operations!CU34/Operations!CP34-1 -> 0.02 | CV28: 0.19 | CW28: 0.19 | CX28: 0.19 | CY28: 0.19 | CZ28: =Operations!CZ34/Operations!CU34-1 -> 0.19
B29: Structural | I29: =Operations!I36/Operations!H36-1 -> -0.11150614 | N29: =Operations!N36/Operations!I36-1 -> -0.021826119 | S29: =Operations!S36/Operations!N36-1 -> 0.033841577 | T29: =Operations!T36/Operations!O36-1 -> 0.2640264 | U29: =Operations!U36/Operations!P36-1 -> -0.0098452883 | V29: =Operations!V36/Operations!Q36-1 -> -0.044034091 | W29: =Operations!W36/Operations!R36-1 -> -0.18708827 | X29: =Operations!X36/Operations!S36-1 -> -0.0071942446 | Y29: =Operations!Y36/Operations!T36-1 -> -0.14490862 | Z29: =Operations!Z36/Operations!U36-1 -> -0.029829545 | ... AZ29: =Operations!AZ36/Operations!AU36-1 -> 0.12350598 | BA29: 0.15 | BB29: =Operations!BB36/Operations!AW36-1 -> 0.31549815 | BC29: =Operations!BC36/Operations!AX36-1 -> 0.36983471 | BD29: =Operations!BD36/Operations!AY36-1 -> 0.042435424 | BE29: =Operations!BE36/Operations!AZ36-1 -> -0.069148936 | BF29: =Operations!BF36/Operations!BA36-1 -> 0.06557377 | BG29: =Operations!BG36/Operations!BB36-1 -> 0.093034128 | BH29: =Operations!BH36/Operations!BC36-1 -> 0.0045248869 | BI29: =Operations!BI36/Operations!BD36-1 -> 0.053097345 | ... CL29: =Operations!CL36/Operations!CG36-1 -> -0.017786561 | CM29: 0.02 | CN29: 0.02 | CO29: 0.02 | CP29: =Operations!CP36/Operations!CK36-1 -> 0.0090051754 | CQ29: 0.02 | CR29: 0.02 | CS29: 0.02 | CT29: 0.02 | CU29: =Operations!CU36/Operations!CP36-1 -> 0.02 | CV29: 0.02 | CW29: 0.02 | CX29: 0.02 | CY29: 0.02 | CZ29: =Operations!CZ36/Operations!CU36-1 -> 0.02
B30: Plate | I30: =Operations!I37/Operations!H37-1 -> 25.1 | N30: =Operations!N37/Operations!I37-1 -> 0.67049808 | S30: =Operations!S37/Operations!N37-1 -> 0.1456422 | T30: =Operations!T37/Operations!O37-1 -> 0.52212389 | U30: =Operations!U37/Operations!P37-1 -> 0.39316239 | V30: =Operations!V37/Operations!Q37-1 -> 0.99616858 | W30: =Operations!W37/Operations!R37-1 -> 0.84892086 | X30: =Operations!X37/Operations!S37-1 -> 0.70670671 | Y30: =Operations!Y37/Operations!T37-1 -> 0.71802326 | Z30: =Operations!Z37/Operations!U37-1 -> 0.50613497 | ... AZ30: =Operations!AZ37/Operations!AU37-1 -> 0.13070539 | BA30: 0.1 | BB30: =Operations!BB37/Operations!AW37-1 -> 0.38619403 | BC30: =Operations!BC37/Operations!AX37-1 -> 0.066907776 | BD30: =Operations!BD37/Operations!AY37-1 -> -0.010186757 | BE30: =Operations!BE37/Operations!AZ37-1 -> 0.088073394 | BF30: =Operations!BF37/Operations!BA37-1 -> -0.055350554 | BG30: =Operations!BG37/Operations!BB37-1 -> 0.021982952 | BH30: =Operations!BH37/Operations!BC37-1 -> 0.042372881 | BI30: =Operations!BI37/Operations!BD37-1 -> 0.036020583 | ... CL30: =Operations!CL37/Operations!CG37-1 -> -0.031971581 | CM30: 0.03 | CN30: 0.03 | CO30: 0.03 | CP30: =Operations!CP37/Operations!CK37-1 -> 0.014486438 | CQ30: 0.02 | CR30: 0.02 | CS30: 0.02 | CT30: 0.02 | CU30: =Operations!CU37/Operations!CP37-1 -> 0.02 | CV30: 0.02 | CW30: 0.02 | CX30: 0.02 | CY30: 0.02 | CZ30: =Operations!CZ37/Operations!CU37-1 -> 0.02
A32: Shipments
B33: Sheet | H33: 4456 | I33: 5074 | J33: 1436 | K33: 1396 | L33: 1432 | M33: 1542 | N33: =SUM(J33:M33) -> 5806 | O33: 1745 | P33: 1687 | Q33: 1759 | R33: 1763 | S33: =SUM(O33:R33) -> 6954 | T33: 2123 | U33: 2099 | V33: 2006 | W33: 1850 | X33: =SUM(T33:W33) -> 8078 | Y33: 2066 | Z33: 1996 | AA33: 1954 | AB33: 2010 | AC33: =SUM(Y33:AB33) -> 8026 | AD33: 2241 | AE33: 2221 | AF33: 2177 | AG33: 1856 | AH33: =SUM(AD33:AG33) -> 8495 | AI33: 2020 | AJ33: 2068 | AK33: 2038 | AL33: 2140 | AM33: =SUM(AI33:AL33) -> 8266 | AN33: 2211 | AO33: 2280 | AP33: 1920 | AQ33: 1094 | AR33: =SUM(AN33:AQ33) -> 7505 | AS33: 957 | AT33: 966 | AU33: 1740 | AV33: 1549 | AW33: =SUM(AS33:AV33) -> 5212 | AX33: 2000 | AY33: 1893 | AZ33: 1841 | BA33: 1700 | BB33: =SUM(AX33:BA33) -> 7434 | BC33: 2088 | BD33: 1718 | BE33: 1853 | BF33: 1841 | BG33: =SUM(BC33:BF33) -> 7500 | BH33: 2048 | BI33: 1925 | BJ33: 1804 | BK33: 1845 | BL33: =SUM(BH33:BK33) -> 7622 | BM33: 1837 | BN33: 1796 | BO33: 1965 | BP33: 1893 | BQ33: =SUM(BM33:BP33) -> 7491 | BR33: 1877 | BS33: 1972 | BT33: 2040 | BU33: 2264 | BV33: =SUM(BR33:BU33) -> 8153 | BW33: 1956 | BX33: 2196 | BY33: 2109 | BZ33: 1819 | CA33: =SUM(BW33:BZ33) -> 8080 | CB33: 2392 | CC33: 2522 | CD33: 2121 | CE33: 2083 | CF33: =SUM(CB33:CE33) -> 9118 | CG33: 2451 | CH33: 2371 | CI33: 2282 | CJ33: 2207 | CK33: =SUM(CG33:CJ33) -> 9311 | CL33: 2323 | CM33: =(1+Operations!CM27)*Operations!CH33 -> 2418.42 | CN33: =(1+Operations!CN27)*Operations!CI33 -> 2327.64 | CO33: =(1+Operations!CO27)*Operations!CJ33 -> 2251.14 | CP33: =SUM(CL33:CO33) -> 9320.2 | CQ33: =(1+Operations!CQ27)*Operations!CL33 -> 2369.46 | CR33: =(1+Operations!CR27)*Operations!CM33 -> 2466.7884 | CS33: =(1+Operations!CS27)*Operations!CN33 -> 2374.1928 | CT33: =(1+Operations!CT27)*Operations!CO33 -> 2296.1628 | CU33: =SUM(CQ33:CT33) -> 9506.604 | CV33: =(1+Operations!CV27)*Operations!CQ33 -> 2559.0168 | CW33: =(1+Operations!CW27)*Operations!CR33 -> 2664.1315 | CX33: =(1+Operations!CX27)*Operations!CS33 -> 2564.1282 | CY33: =(1+Operations!CY27)*Operations!CT33 -> 2479.8558 | CZ33: =SUM(CV33:CY33) -> 10267.132
B34: Rebar/M Bar | H34: 2209 | I34: 2687 | J34: 699 | K34: 774 | L34: 710 | M34: 764 | N34: =SUM(J34:M34) -> 2947 | O34: 1463 | P34: 1321 | Q34: 1438 | R34: 1308 | S34: =SUM(O34:R34) -> 5530 | T34: 1493 | U34: 1327 | V34: 1292 | W34: 1132 | X34: =SUM(T34:W34) -> 5244 | Y34: 1376 | Z34: 1523 | AA34: 1674 | AB34: 1410 | AC34: =SUM(Y34:AB34) -> 5983 | AD34: 1638 | AE34: 1809 | AF34: 1613 | AG34: 1453 | AH34: =SUM(AD34:AG34) -> 6513 | AI34: 1819 | AJ34: 1404 | AK34: 1548 | AL34: 1516 | AM34: =SUM(AI34:AL34) -> 6287 | AN34: 1516 | AO34: 1632 | AP34: 1272 | AQ34: 846 | AR34: =SUM(AN34:AQ34) -> 5266 | AS34: 781 | AT34: 918 | AU34: 981 | AV34: 949 | AW34: =SUM(AS34:AV34) -> 3629 | AX34: 1029 | AY34: 898 | AZ34: 1043 | BA34: 1049 | BB34: =SUM(AX34:BA34) -> 4019 | BC34: =1077-BC35 -> 770.75 | BD34: =1186-BD35 -> 879.75 | BE34: =1223-BE35 -> 916.75 | BF34: =1194-BF35 -> 887.75 | BG34: =SUM(BC34:BF34) -> 3455 | BH34: =1261-BH35 -> 954.75 | BI34: =1325-BI35 -> 1018.75 | BJ34: =1329-BJ35 -> 1022.75 | BK34: =1163-BK35 -> 856.75 | BL34: =SUM(BH34:BK34) -> 3853 | BM34: =1273-BM35 -> 951.4375 | BN34: =1272-BN35 -> 950.4375 | BO34: =1345-BO35 -> 1023.4375 | BP34: =1294-BP35 -> 972.4375 | BQ34: =SUM(BM34:BP34) -> 3897.75 | BR34: =1351-BR35 -> 951 | BS34: =1430-BS35 -> 1030 | BT34: =1502-BT35 -> 1102 | BU34: =1243-BU35 -> 843 | BV34: =SUM(BR34:BU34) -> 3926 | BW34: =1173-BW35 -> 773 | BX34: =1324-BX35 -> 924 | BY34: =1219-BY35 -> 819 | BZ34: =1074-BZ35 -> 674 | CA34: =SUM(BW34:BZ34) -> 3190 | CB34: =1355-CB35 -> 955 | CC34: =1384-CC35 -> 984 | CD34: =1308-CD35 -> 908 | CE34: =1257-CE35 -> 857 | CF34: =SUM(CB34:CE34) -> 3704 | CG34: =1340-CG35 -> 940 | CH34: =1493-CH35 -> 1093 | CI34: =1489-CI35 -> 1089 | CJ34: =1516-CJ35 -> 1116 | CK34: =SUM(CG34:CJ34) -> 4238 | CL34: =1651-CL35 -> 1251 | CM34: =(1+Operations!CM28)*Operations!CH34 -> 1114.86 | CN34: =(1+Operations!CN28)*Operations!CI34 -> 1110.78 | CO34: =(1+Operations!CO28)*Operations!CJ34 -> 1138.32 | CP34: =SUM(CL34:CO34) -> 4614.96 | CQ34: =(1+Operations!CQ28)*Operations!CL34 -> 1276.02 | CR34: =(1+Operations!CR28)*Operations!CM34 -> 1137.1572 | CS34: =(1+Operations!CS28)*Operations!CN34 -> 1132.9956 | CT34: =(1+Operations!CT28)*Operations!CO34 -> 1161.0864 | CU34: =SUM(CQ34:CT34) -> 4707.2592 | CV34: =(1+Operations!CV28)*Operations!CQ34 -> 1518.4638 | CW34: =(1+Operations!CW28)*Operations!CR34 -> 1353.2171 | CX34: =(1+Operations!CX28)*Operations!CS34 -> 1348.2648 | CY34: =(1+Operations!CY28)*Operations!CT34 -> 1381.6928 | CZ34: =SUM(CV34:CY34) -> 5601.6384
B35: SBQ | BC35: =BD35 -> 306.25 | BD35: =BE35 -> 306.25 | BE35: =BF35 -> 306.25 | BF35: =BG35/4 -> 306.25 | BG35: 1225 | BH35: =BI35 -> 306.25 | BI35: =BJ35 -> 306.25 | BJ35: =BK35 -> 306.25 | BK35: =BL35/4 -> 306.25 | BL35: 1225 | BM35: =BN35 -> 321.5625 | BN35: =BO35 -> 321.5625 | BO35: =BP35 -> 321.5625 | BP35: =BQ35/4 -> 321.5625 | BQ35: 1286.25 | BR35: 400 | BS35: 400 | BT35: 400 | BU35: 400 | BV35: =SUM(BR35:BU35) -> 1600 | BW35: 400 | BX35: 400 | BY35: 400 | BZ35: 400 | CA35: =SUM(BW35:BZ35) -> 1600 | CB35: 400 | CC35: 400 | CD35: 400 | CE35: 400 | CF35: =SUM(CB35:CE35) -> 1600 | CG35: 400 | CH35: 400 | CI35: =CJ35 -> 400 | CJ35: =CK35/4 -> 400 | CK35: 1600 | CL35: 400 | CM35: =CN35 -> 400 | CN35: =CO35 -> 400 | CO35: =CP35/4 -> 400 | CP35: 1600 | CQ35: =CR35 -> 400 | CR35: =CS35 -> 400 | CS35: =CT35 -> 400 | CT35: =CU35/4 -> 400 | CU35: 1600 | CV35: =CW35 -> 400 | CW35: =CX35 -> 400 | CX35: =CY35 -> 400 | CY35: =CZ35/4 -> 400 | CZ35: 1600
B36: Structural | H36: 3094 | I36: 2749 | J36: 689 | K36: 725 | L36: 617 | M36: 658 | N36: =SUM(J36:M36) -> 2689 | O36: 606 | P36: 711 | Q36: 704 | R36: 759 | S36: =SUM(O36:R36) -> 2780 | T36: 766 | U36: 704 | V36: 673 | W36: 617 | X36: =SUM(T36:W36) -> 2760 | Y36: 655 | Z36: 683 | AA36: 755 | AB36: 773 | AC36: =SUM(Y36:AB36) -> 2866 | AD36: 763 | AE36: 810 | AF36: 822 | AG36: 814 | AH36: =SUM(AD36:AG36) -> 3209 | AI36: 765 | AJ36: 811 | AK36: 781 | AL36: 797 | AM36: =SUM(AI36:AL36) -> 3154 | AN36: 776 | AO36: 825 | AP36: 818 | AQ36: 515 | AR36: =SUM(AN36:AQ36) -> 2934 | AS36: 335 | AT36: 373 | AU36: 502 | AV36: 416 | AW36: =SUM(AS36:AV36) -> 1626 | AX36: 484 | AY36: 542 | AZ36: 564 | BA36: 549 | BB36: =SUM(AX36:BA36) -> 2139 | BC36: 663 | BD36: 565 | BE36: 525 | BF36: 585 | BG36: =SUM(BC36:BF36) -> 2338 | BH36: 666 | BI36: 595 | BJ36: 620 | BK36: 624 | BL36: =SUM(BH36:BK36) -> 2505 | BM36: 664 | BN36: 618 | BO36: 730 | BP36: 683 | BQ36: =SUM(BM36:BP36) -> 2695 | BR36: 706 | BS36: 623 | BT36: 693 | BU36: 538 | BV36: =SUM(BR36:BU36) -> 2560 | BW36: 521 | BX36: 562 | BY36: 623 | BZ36: 525 | CA36: =SUM(BW36:BZ36) -> 2231 | CB36: 600 | CC36: 588 | CD36: 610 | CE36: 521 | CF36: =SUM(CB36:CE36) -> 2319 | CG36: 506 | CH36: 438 | CI36: 402 | CJ36: 393 | CK36: =SUM(CG36:CJ36) -> 1739 | CL36: 497 | CM36: =(1+Operations!CM29)*Operations!CH36 -> 446.76 | CN36: =(1+Operations!CN29)*Operations!CI36 -> 410.04 | CO36: =(1+Operations!CO29)*Operations!CJ36 -> 400.86 | CP36: =SUM(CL36:CO36) -> 1754.66 | CQ36: =(1+Operations!CQ29)*Operations!CL36 -> 506.94 | CR36: =(1+Operations!CR29)*Operations!CM36 -> 455.6952 | CS36: =(1+Operations!CS29)*Operations!CN36 -> 418.2408 | CT36: =(1+Operations!CT29)*Operations!CO36 -> 408.8772 | CU36: =SUM(CQ36:CT36) -> 1789.7532 | CV36: =(1+Operations!CV29)*Operations!CQ36 -> 517.0788 | CW36: =(1+Operations!CW29)*Operations!CR36 -> 464.8091 | CX36: =(1+Operations!CX29)*Operations!CS36 -> 426.60562 | CY36: =(1+Operations!CY29)*Operations!CT36 -> 417.05474 | CZ36: =SUM(CV36:CY36) -> 1825.5483
B37: Plate | H37: 20 | I37: 522 | J37: 199 | K37: 238 | L37: 203 | M37: 232 | N37: =SUM(J37:M37) -> 872 | O37: 226 | P37: 234 | Q37: 261 | R37: 278 | S37: =SUM(O37:R37) -> 999 | T37: 344 | U37: 326 | V37: 521 | W37: 514 | X37: =SUM(T37:W37) -> 1705 | Y37: 591 | Z37: 491 | AA37: 531 | AB37: 532 | AC37: =SUM(Y37:AB37) -> 2145 | AD37: 624 | AE37: 610 | AF37: 611 | AG37: 590 | AH37: =SUM(AD37:AG37) -> 2435 | AI37: 625 | AJ37: 607 | AK37: 671 | AL37: 625 | AM37: =SUM(AI37:AL37) -> 2528 | AN37: 700 | AO37: 657 | AP37: 678 | AQ37: 445 | AR37: =SUM(AN37:AQ37) -> 2480 | AS37: 360 | AT37: 312 | AU37: 482 | AV37: 454 | AW37: =SUM(AS37:AV37) -> 1608 | AX37: 553 | AY37: 589 | AZ37: 545 | BA37: 542 | BB37: =SUM(AX37:BA37) -> 2229 | BC37: 590 | BD37: 583 | BE37: 593 | BF37: 512 | BG37: =SUM(BC37:BF37) -> 2278 | BH37: 615 | BI37: 604 | BJ37: 560 | BK37: 489 | BL37: =SUM(BH37:BK37) -> 2268 | BM37: 560 | BN37: 588 | BO37: 600 | BP37: 615 | BQ37: =SUM(BM37:BP37) -> 2363 | BR37: 666 | BS37: 621 | BT37: 616 | BU37: 539 | BV37: =SUM(BR37:BU37) -> 2442 | BW37: 515 | BX37: 496 | BY37: 489 | BZ37: 405 | CA37: =SUM(BW37:BZ37) -> 1905 | CB37: 552 | CC37: 588 | CD37: 426 | CE37: 457 | CF37: =SUM(CB37:CE37) -> 2023 | CG37: 563 | CH37: 648 | CI37: 525 | CJ37: 513 | CK37: =SUM(CG37:CJ37) -> 2249 | CL37: 545 | CM37: =(1+Operations!CM30)*Operations!CH37 -> 667.44 | CN37: =(1+Operations!CN30)*Operations!CI37 -> 540.75 | CO37: =(1+Operations!CO30)*Operations!CJ37 -> 528.39 | CP37: =SUM(CL37:CO37) -> 2281.58 | CQ37: =(1+Operations!CQ30)*Operations!CL37 -> 555.9 | CR37: =(1+Operations!CR30)*Operations!CM37 -> 680.7888 | CS37: =(1+Operations!CS30)*Operations!CN37 -> 551.565 | CT37: =(1+Operations!CT30)*Operations!CO37 -> 538.9578 | CU37: =SUM(CQ37:CT37) -> 2327.2116 | CV37: =(1+Operations!CV30)*Operations!CQ37 -> 567.018 | CW37: =(1+Operations!CW30)*Operations!CR37 -> 694.40458 | CX37: =(1+Operations!CX30)*Operations!CS37 -> 562.5963 | CY37: =(1+Operations!CY30)*Operations!CT37 -> 549.73696 | CZ37: =SUM(CV37:CY37) -> 2373.7558
C38: Total Steel | H38: =H33+H34+H36+H37 -> 9779 | I38: =I33+I34+I36+I37 -> 11032 | J38: =J33+J34+J36+J37 -> 3023 | K38: =K33+K34+K36+K37 -> 3133 | L38: =L33+L34+L36+L37 -> 2962 | M38: =M33+M34+M36+M37 -> 3196 | N38: =N33+N34+N36+N37 -> 12314 | O38: =O33+O34+O36+O37 -> 4040 | ... AG38: =AG33+AG34+AG36+AG37 -> 4713 | AH38: =SUM(AD38:AG38) -> 20652 | AI38: =AI33+AI34+AI36+AI37 -> 5229 | AJ38: =AJ33+AJ34+AJ36+AJ37 -> 4890 | AK38: =AK33+AK34+AK36+AK37 -> 5038 | AL38: =AL33+AL34+AL36+AL37 -> 5078 | AM38: =SUM(AI38:AL38) -> 20235 | AN38: =AN33+AN34+AN36+AN37 -> 5203 | AO38: =AO33+AO34+AO36+AO37 -> 5394 | AP38: =AP33+AP34+AP36+AP37 -> 4688 | AQ38: =AQ33+AQ34+AQ36+AQ37 -> 2900 | AR38: =SUM(AN38:AQ38) -> 18185 | AS38: =AS33+AS34+AS36+AS37 -> 2433 | AT38: =AT33+AT34+AT36+AT37 -> 2569 | AU38: =AU33+AU34+AU36+AU37 -> 3705 | AV38: =AV33+AV34+AV36+AV37 -> 3368 | AW38: =SUM(AS38:AV38) -> 12075 | AX38: =AX33+AX34+AX36+AX37 -> 4066 | AY38: =AY33+AY34+AY36+AY37 -> 3922 | AZ38: =AZ33+AZ34+AZ36+AZ37 -> 3993 | BA38: =BA33+BA34+BA36+BA37 -> 3840 | BB38: =SUM(AX38:BA38) -> 15821 | BC38: =BC33+BC34+BC36+BC37+BC35 -> 4418 | BD38: =BD33+BD34+BD36+BD37+BD35 -> 4052 | BE38: =BE33+BE34+BE36+BE37+BE35 -> 4194 | BF38: =BF33+BF34+BF36+BF37+BF35 -> 4132 | BG38: =SUM(BC38:BF38) -> 16796 | BH38: =BH33+BH34+BH36+BH37+BH35 -> 4590 | BI38: =BI33+BI34+BI36+BI37+BI35 -> 4449 | BJ38: =BJ33+BJ34+BJ36+BJ37+BJ35 -> 4313 | BK38: =BK33+BK34+BK36+BK37+BK35 -> 4121 | BL38: =SUM(BH38:BK38) -> 17473 | BM38: =BM33+BM34+BM36+BM37+BM35 -> 4334 | BN38: =BN33+BN34+BN36+BN37+BN35 -> 4274 | BO38: =BO33+BO34+BO36+BO37+BO35 -> 4640 | BP38: =BP33+BP34+BP36+BP37+BP35 -> 4485 | BQ38: =SUM(BM38:BP38) -> 17733 | BR38: =BR33+BR34+BR36+BR37+BR35 -> 4600 | BS38: =BS33+BS34+BS36+BS37+BS35 -> 4646 | BT38: =BT33+BT34+BT36+BT37+BT35 -> 4851 | BU38: =BU33+BU34+BU36+BU37+BU35 -> 4584 | BV38: =SUM(BR38:BU38) -> 18681 | BW38: =BW33+BW34+BW36+BW37+BW35 -> 4165 | BX38: =BX33+BX34+BX36+BX37+BX35 -> 4578 | BY38: =BY33+BY34+BY36+BY37+BY35 -> 4440 | BZ38: =BZ33+BZ34+BZ36+BZ37+BZ35 -> 3823 | CA38: =SUM(BW38:BZ38) -> 17006 | CB38: =CB33+CB34+CB36+CB37+CB35 -> 4899 | CC38: =CC33+CC34+CC36+CC37+CC35 -> 5082 | CD38: =CD33+CD34+CD36+CD37+CD35+CD124 -> 4465 | CE38: =CE33+CE34+CE36+CE37+CE35+CE124 -> 4400 | CF38: =SUM(CB38:CE38) -> 18846 | CG38: =CG33+CG34+CG36+CG37+CG35 -> 4860 | CH38: =CH33+CH34+CH36+CH37+CH35 -> 4950 | CI38: =CI33+CI34+CI36+CI37+CI35 -> 4698 | CJ38: =CJ33+CJ34+CJ36+CJ37+CJ35 -> 4629 | CK38: =CK33+CK34+CK36+CK37+CK35 -> 19137 | CL38: =CL33+CL34+CL36+CL37+CL35 -> 5016 | CM38: =CM33+CM34+CM36+CM37+CM35 -> 5047.48 | CN38: =CN33+CN34+CN36+CN37+CN35 -> 4789.21 | ... CZ38: =CZ33+CZ34+CZ36+CZ37+CZ35 -> 21668.075
C39: Y-O-Y Change | I39: =I38/H38-1 -> 0.12813171 | N39: =N38/I38-1 -> 0.1162074 | O39: =O38/J38-1 -> 0.33642077 | P39: =P38/K38-1 -> 0.26172997 | Q39: =Q38/L38-1 -> 0.40513167 | R39: =R38/M38-1 -> 0.2853567 | S39: =S38/N38-1 -> 0.3206919 | T39: =T38/O38-1 -> 0.16980198 | U39: =U38/P38-1 -> 0.12724513 | ... CZ39: =CZ38/CU38-1 -> 0.087163808
C40: Sequential Change | K40: =K38/J38-1 -> 0.036387694 | L40: =L38/K38-1 -> -0.054580274 | M40: =M38/L38-1 -> 0.079000675 | P40: =P38/O38-1 -> -0.021534653 | Q40: =Q38/P38-1 -> 0.052871237 | R40: =R38/Q38-1 -> -0.012974531 | T40: =T38/R38-1 -> 0.15043817 | U40: =U38/T38-1 -> -0.057130766 | V40: =V38/U38-1 -> 0.0080789946 | W40: =W38/V38-1 -> -0.084372217 | Y40: =Y38/W38-1 -> 0.13980063 | Z40: =Z38/Y38-1 -> 0.0010665529 | AA40: =AA38/Z38-1 -> 0.047091413 | AB40: =AB38/AA38-1 -> -0.038461538 | AD40: =AD38/AB38-1 -> 0.11449735 | AE40: =AE38/AD38-1 -> 0.034941132 | AF40: =AF38/AE38-1 -> -0.041651376 | AG40: =AG38/AF38-1 -> -0.097645032 | AI40: =AI38/AG38-1 -> 0.1094844 | AJ40: =AJ38/AI38-1 -> -0.064830752 | AK40: =AK38/AJ38-1 -> 0.030265849 | AL40: =AL38/AK38-1 -> 0.0079396586 | AN40: =AN38/AL38-1 -> 0.024615991 | AO40: =AO38/AN38-1 -> 0.036709591 | AP40: =AP38/AO38-1 -> -0.13088617 | AQ40: =AQ38/AP38-1 -> -0.38139932 | AS40: =AS38/AQ38-1 -> -0.16103448 | AT40: =AT38/AS38-1 -> 0.055898068 | AU40: =AU38/AT38-1 -> 0.44219541 | AV40: =AV38/AU38-1 -> -0.090958165 | AX40: =AX38/AV38-1 -> 0.20724466 | AY40: =AY38/AX38-1 -> -0.035415642 | AZ40: =AZ38/AY38-1 -> 0.018103009 | BA40: =BA38/AZ38-1 -> -0.038317055 | BC40: =BC38/BA38-1 -> 0.15052083 | BD40: =BD38/BC38-1 -> -0.082842915 | BE40: =BE38/BD38-1 -> 0.035044423 | BF40: =BF38/BE38-1 -> -0.014783023 | BH40: =BH38/BF38-1 -> 0.11084221 | BI40: =BI38/BH38-1 -> -0.030718954 | BJ40: =BJ38/BI38-1 -> -0.030568667 | BK40: =BK38/BJ38-1 -> -0.044516578 | BM40: =BM38/BK38-1 -> 0.051686484 | BN40: =BN38/BM38-1 -> -0.013844024 | BO40: =BO38/BN38-1 -> 0.085634066 | BP40: =BP38/BO38-1 -> -0.033405172 | BR40: =BR38/BP38-1 -> 0.025641026 | BS40: =BS38/BR38-1 -> 0.01 | BT40: =BT38/BS38-1 -> 0.044123978 | BU40: =BU38/BT38-1 -> -0.055040198 | BW40: =BW38/BU38-1 -> -0.091404887 | BX40: =BX38/BW38-1 -> 0.099159664 | BY40: =BY38/BX38-1 -> -0.030144168 | BZ40: =BZ38/BY38-1 -> -0.13896396 | CB40: =CB38/BZ38-1 -> 0.28145436 | CC40: =CC38/CB38-1 -> 0.037354562 | CD40: =CD38/CC38-1 -> -0.12140889 | CE40: =CE38/CD38-1 -> -0.014557671 | CG40: =CG38/CE38-1 -> 0.10454545 | CH40: =CH38/CG38-1 -> 0.018518519 | CI40: =CI38/CH38-1 -> -0.050909091 | CJ40: =CJ38/CI38-1 -> -0.014687101 | CL40: =CL38/CJ38-1 -> 0.08360337 | CM40: =CM38/CL38-1 -> 0.0062759171 | CN40: =CN38/CM38-1 -> -0.051168108 | CO40: =CO38/CN38-1 -> -0.014720591 | CQ40: =CQ38/CO38-1 -> 0.082567058 | CR40: =CR38/CQ38-1 -> 0.0062857456 | CS40: =CS38/CR38-1 -> -0.05124774 | CT40: =CT38/CS38-1 -> -0.014744738 | CV40: =CV38/CT38-1 -> 0.15743599 | CW40: =CW38/CV38-1 -> 0.0026943471 | CX40: =CX38/CW38-1 -> -0.049307675 | CY40: =CY38/CX38-1 -> -0.013817458
A42: Product Mix
B43: Sheet | H43: =H33/H$38 -> 0.45567031 | I43: =I33/I$38 -> 0.45993474 | J43: =J33/J$38 -> 0.47502481 | K43: =K33/K$38 -> 0.44557932 | L43: =L33/L$38 -> 0.48345712 | M43: =M33/M$38 -> 0.4824781 | N43: =N33/N$38 -> 0.47149586 | O43: =O33/O$38 -> 0.43193069 | ... CZ43: =CZ33/CZ$38 -> 0.47383685
B44: Rebar/M Bar | H44: =H34/H$38 -> 0.22589222 | I44: =I34/I$38 -> 0.24356418 | J44: =J34/J$38 -> 0.23122726 | K44: =K34/K$38 -> 0.24704756 | L44: =L34/L$38 -> 0.2397029 | M44: =M34/M$38 -> 0.23904881 | N44: =N34/N$38 -> 0.2393211 | O44: =O34/O$38 -> 0.36212871 | ... CZ44: =CZ34/CZ$38 -> 0.25852036
B45: SBQ | BC45: =BC35/BC$38 -> 0.069318696 | BD45: =BD35/BD$38 -> 0.075579961 | BE45: =BE35/BE$38 -> 0.073020982 | BF45: =BF35/BF$38 -> 0.074116651 | BG45: =BG35/BG$38 -> 0.072934032 | BH45: =BH35/BH$38 -> 0.066721133 | BI45: =BI35/BI$38 -> 0.068835693 | BJ45: =BJ35/BJ$38 -> 0.07100626 | ... CZ45: =CZ35/CZ$38 -> 0.073841355
B46: Structural | H46: =H36/H$38 -> 0.31639227 | I46: =I36/I$38 -> 0.24918419 | J46: =J36/J$38 -> 0.22791929 | K46: =K36/K$38 -> 0.2314076 | L46: =L36/L$38 -> 0.2083052 | M46: =M36/M$38 -> 0.20588235 | N46: =N36/N$38 -> 0.21836934 | O46: =O36/O$38 -> 0.15 | ... CZ46: =CZ36/CZ$38 -> 0.084250598
B47: Plate | H47: =H37/H$38 -> 0.0020451989 | I47: =I37/I$38 -> 0.047316896 | J47: =J37/J$38 -> 0.065828647 | K47: =K37/K$38 -> 0.075965528 | L47: =L37/L$38 -> 0.068534774 | M47: =M37/M$38 -> 0.072590738 | N47: =N37/N$38 -> 0.070813708 | O47: =O37/O$38 -> 0.055940594 | ... CZ47: =CZ37/CZ$38 -> 0.10955084
C48: Total Steel | H48: =H38/H$38 -> 1 | I48: =I38/I$38 -> 1 | J48: =J38/J$38 -> 1 | K48: =K38/K$38 -> 1 | L48: =L38/L$38 -> 1 | M48: =M38/M$38 -> 1 | N48: =N38/N$38 -> 1 | O48: =O38/O$38 -> 1 | ... CZ48: =CZ38/CZ$38 -> 1
A50: Total Finished Product Capacity
B51: Sheet | H51: 5900 | I51: 6000 | J51: =N51*90/365 -> 2071.2329 | K51: =N51*91/365 -> 2094.2466 | L51: =N51*92/365 -> 2117.2603 | M51: =N51*92/365 -> 2117.2603 | N51: 8400 | O51: =S51*90/365 -> 2145.2055 | P51: =S51*91/365 -> 2169.0411 | Q51: =S51*92/365 -> 2192.8767 | R51: =S51*92/365 -> 2192.8767 | S51: 8700 | T51: =X51*90/365 -> 2243.8356 | U51: =X51*91/365 -> 2268.7671 | V51: =X51*92/365 -> 2293.6986 | W51: =X51*92/365 -> 2293.6986 | X51: 9100 | Y51: =AC51*90/365 -> 2663.0137 | Z51: =AC51*91/365 -> 2692.6027 | AA51: =AC51*92/365 -> 2722.1918 | AB51: =AC51*92/365 -> 2722.1918 | AC51: 10800 | AD51: =AH51*90/365 -> 2663.0137 | AE51: =AH51*91/365 -> 2692.6027 | AF51: =AH51*92/365 -> 2722.1918 | AG51: =AH51*92/365 -> 2722.1918 | AH51: 10800 | AI51: =AM51*90/365 -> 2663.0137 | AJ51: =AM51*91/365 -> 2692.6027 | AK51: =AM51*92/365 -> 2722.1918 | AL51: =AM51*92/365 -> 2722.1918 | AM51: 10800 | AN51: =AR51*90/365 -> 2663.0137 | AO51: =AR51*91/365 -> 2692.6027 | AP51: =AR51*92/365 -> 2722.1918 | AQ51: =AR51*92/365 -> 2722.1918 | AR51: 10800 | AS51: =AW51*90/365 -> 2684.9015 | AT51: =AW51*91/365 -> 2714.7337 | AU51: =AW51*92/365 -> 2744.566 | AV51: =AW51*92/365 -> 2744.566 | AW51: =AQ51*4 -> 10888.767 | AX51: =BB51*90/365 -> 2663.0137 | AY51: =BB51*91/365 -> 2692.6027 | AZ51: =BB51*92/365 -> 2722.1918 | BA51: =BB51*92/365 -> 2722.1918 | BB51: 10800 | BC51: =BG51*90/365 -> 2663.0137 | BD51: =BG51*91/365 -> 2692.6027 | BE51: =BG51*92/365 -> 2722.1918 | BF51: =BG51*92/365 -> 2722.1918 | BG51: =BB51 -> 10800 | BH51: =BL51*90/365 -> 2786.3014 | BI51: =BL51*91/365 -> 2817.2603 | BJ51: =BL51*92/365 -> 2848.2192 | BK51: =BL51*92/365 -> 2848.2192 | BL51: =BG51+500 -> 11300 | BM51: =BQ51*90/365 -> 2786.3014 | BN51: =BQ51*91/365 -> 2817.2603 | BO51: =BQ51*92/365 -> 2848.2192 | BP51: =BQ51*92/365 -> 2848.2192 | BQ51: =BL51 -> 11300 | BR51: =BM51 -> 2786.3014 | BS51: =BN51 -> 2817.2603 | BT51: =BO51 -> 2848.2192 | BU51: =BP51+1800/4 -> 3298.2192 | BV51: =SUM(BR51:BU51) -> 11750 | BW51: =CA51/365*BW$106 -> 3230.137 | BX51: =CA51/365*BX$106 -> 3266.0274 | BY51: =CA51/365*BY$106 -> 3301.9178 | BZ51: =CA51/365*BZ$106 -> 3301.9178 | CA51: 13100 | CB51: =CF51/365*CB$106 -> 3266.0274 | CC51: =CF51/365*CC$106 -> 3266.0274 | CD51: =CF51/365*CD$106 -> 3301.9178 | CE51: =CF51/365*CE$106 -> 3301.9178 | CF51: 13100 | CG51: =CK51/365*CG$106 -> 3230.137 | CH51: =CK51/365*CH$106 -> 3266.0274 | CI51: =CK51/365*CI$106 -> 3301.9178 | CJ51: =CK51/365*CJ$106 -> 3301.9178 | CK51: 13100 | CL51: =CP51*90/365 -> 3230.137 | CM51: =CP51*91/365 -> 3266.0274 | CN51: =CP51*92/365 -> 3301.9178 | CO51: =CP51*92/365 -> 3301.9178 | CP51: 13100 | CQ51: =CU51*90/365 -> 3230.137 | CR51: =CU51*91/365 -> 3266.0274 | CS51: =CU51*92/365 -> 3301.9178 | CT51: =CU51*92/365 -> 3301.9178 | CU51: 13100 | CV51: =CZ51*90/365 -> 3526.0274 | CW51: =CZ51*91/365 -> 3565.2055 | CX51: =CZ51*92/365 -> 3604.3836 | CY51: =CZ51*92/365 -> 3604.3836 | CZ51: =+CU51+500+500+200 -> 14300
B52: Bars | H52: 3000 | I52: 3700 | J52: =N52*90/365 -> 1430.137 | K52: =N52*91/365 -> 1446.0274 | L52: =N52*92/365 -> 1461.9178 | M52: =N52*92/365 -> 1461.9178 | N52: 5800 | O52: =S52*90/365 -> 1479.4521 | P52: =S52*91/365 -> 1495.8904 | Q52: =S52*92/365 -> 1512.3288 | R52: =S52*92/365 -> 1512.3288 | S52: 6000 | T52: =X52*90/365 -> 1553.4247 | U52: =X52*91/365 -> 1570.6849 | V52: =X52*92/365 -> 1587.9452 | W52: =X52*92/365 -> 1587.9452 | X52: 6300 | Y52: =AC52*90/365 -> 1843.1507 | Z52: =AC52*91/365 -> 1863.6301 | AA52: =AC52*92/365 -> 1884.1096 | AB52: =AC52*92/365 -> 1884.1096 | AC52: 7475 | AD52: =AH52*90/365 -> 1962.7397 | AE52: =AH52*91/365 -> 1984.5479 | AF52: =AH52*92/365 -> 2006.3562 | AG52: =AH52*92/365 -> 2006.3562 | AH52: 7960 | AI52: =AM52*90/365 -> 1987.3973 | AJ52: =AM52*91/365 -> 2009.4795 | AK52: =AM52*92/365 -> 2031.5616 | AL52: =AM52*92/365 -> 2031.5616 | AM52: 8060 | AN52: =AR52*90/365 -> 2196.9863 | AO52: =AR52*91/365 -> 2221.3973 | AP52: =AR52*92/365 -> 2245.8082 | AQ52: =AR52*92/365 -> 2245.8082 | AR52: 8910 | AS52: =AW52*90/365 -> 2196.9863 | AT52: =AW52*91/365 -> 2221.3973 | AU52: =AW52*92/365 -> 2245.8082 | AV52: =AW52*92/365 -> 2245.8082 | AW52: =AR52 -> 8910 | AX52: =BB52*90/365 -> 2246.3014 | AY52: =BB52*91/365 -> 2271.2603 | AZ52: =BB52*92/365 -> 2296.2192 | BA52: =BB52*92/365 -> 2296.2192 | BB52: 9110 | BC52: =BG52*90/365 -> 2246.3014 | BD52: =BG52*91/365 -> 2271.2603 | BE52: =BG52*92/365 -> 2296.2192 | BF52: =BG52*92/365 -> 2296.2192 | BG52: =BB52 -> 9110 | BH52: =BL52*90/365 -> 2246.3014 | BI52: =BL52*91/365 -> 2271.2603 | BJ52: =BL52*92/365 -> 2296.2192 | BK52: =BL52*92/365 -> 2296.2192 | BL52: =BG52 -> 9110 | BM52: =BQ52*90/365 -> 2246.3014 | BN52: =BQ52*91/365 -> 2271.2603 | BO52: =BQ52*92/365 -> 2296.2192 | BP52: =BQ52*92/365 -> 2296.2192 | BQ52: =BL52 -> 9110 | BR52: =BV52*90/365 -> 2246.3014 | BS52: =BV52*91/365 -> 2271.2603 | BT52: =BV52*92/365 -> 2296.2192 | BU52: =BV52*92/365 -> 2296.2192 | BV52: =BQ52 -> 9110 | BW52: =CA52/365*BW$106 -> 2246.3014 | BX52: =CA52/365*BX$106 -> 2271.2603 | BY52: =CA52/365*BY$106 -> 2296.2192 | BZ52: =CA52/365*BZ$106 -> 2296.2192 | CA52: 9110 | CB52: =CF52/365*CB$106 -> 2271.2603 | CC52: =CF52/365*CC$106 -> 2271.2603 | CD52: =CF52/365*CD$106 -> 2296.2192 | CE52: =CF52/365*CE$106 -> 2296.2192 | CF52: 9110 | CG52: =CK52/365*CG$106 -> 2246.3014 | CH52: =CK52/365*CH$106 -> 2271.2603 | CI52: =CK52/365*CI$106 -> 2296.2192 | CJ52: =CK52/365*CJ$106 -> 2296.2192 | CK52: 9110 | CL52: =CP52*90/365 -> 2246.3014 | CM52: =CP52*91/365 -> 2271.2603 | CN52: =CP52*92/365 -> 2296.2192 | CO52: =CP52*92/365 -> 2296.2192 | CP52: 9110 | CQ52: =CU52*90/365 -> 2246.3014 | CR52: =CU52*91/365 -> 2271.2603 | CS52: =CU52*92/365 -> 2296.2192 | CT52: =CU52*92/365 -> 2296.2192 | CU52: 9110 | CV52: =CZ52*90/365 -> 2455.8904 | CW52: =CZ52*91/365 -> 2483.1781 | CX52: =CZ52*92/365 -> 2510.4658 | CY52: =CZ52*92/365 -> 2510.4658 | CZ52: =+CU52+500+350 -> 9960
B53: Structural | H53: 2900 | I53: 2900 | J53: =N53*90/365 -> 789.0411 | K53: =N53*91/365 -> 797.80822 | L53: =N53*92/365 -> 806.57534 | M53: =N53*92/365 -> 806.57534 | N53: 3200 | O53: =S53*90/365 -> 789.0411 | P53: =S53*91/365 -> 797.80822 | Q53: =S53*92/365 -> 806.57534 | R53: =S53*92/365 -> 806.57534 | S53: 3200 | T53: =X53*90/365 -> 789.0411 | U53: =X53*91/365 -> 797.80822 | V53: =X53*92/365 -> 806.57534 | W53: =X53*92/365 -> 806.57534 | X53: 3200 | Y53: =AC53*90/365 -> 912.32877 | Z53: =AC53*91/365 -> 922.46575 | AA53: =AC53*92/365 -> 932.60274 | AB53: =AC53*92/365 -> 932.60274 | AC53: 3700 | AD53: =AH53*90/365 -> 912.32877 | AE53: =AH53*91/365 -> 922.46575 | AF53: =AH53*92/365 -> 932.60274 | AG53: =AH53*92/365 -> 932.60274 | AH53: 3700 | AI53: =AM53*90/365 -> 912.32877 | AJ53: =AM53*91/365 -> 922.46575 | AK53: =AM53*92/365 -> 932.60274 | AL53: =AM53*92/365 -> 932.60274 | AM53: 3700 | AN53: =AR53*90/365 -> 912.32877 | AO53: =AR53*91/365 -> 922.46575 | AP53: =AR53*92/365 -> 932.60274 | AQ53: =AR53*92/365 -> 932.60274 | AR53: =AM53 -> 3700 | AS53: =AW53*90/365 -> 912.32877 | AT53: =AW53*91/365 -> 922.46575 | AU53: =AW53*92/365 -> 932.60274 | AV53: =AW53*92/365 -> 932.60274 | AW53: =AR53 -> 3700 | AX53: =BB53*90/365 -> 912.32877 | AY53: =BB53*91/365 -> 922.46575 | AZ53: =BB53*92/365 -> 932.60274 | BA53: =BB53*92/365 -> 932.60274 | BB53: =AW53 -> 3700 | BC53: =BG53*90/365 -> 912.32877 | BD53: =BG53*91/365 -> 922.46575 | BE53: =BG53*92/365 -> 932.60274 | BF53: =BG53*92/365 -> 932.60274 | BG53: =BB53 -> 3700 | BH53: =BL53*90/365 -> 912.32877 | BI53: =BL53*91/365 -> 922.46575 | BJ53: =BL53*92/365 -> 932.60274 | BK53: =BL53*92/365 -> 932.60274 | BL53: =BG53 -> 3700 | BM53: =BQ53*90/365 -> 912.32877 | BN53: =BQ53*91/365 -> 922.46575 | BO53: =BQ53*92/365 -> 932.60274 | BP53: =BQ53*92/365 -> 932.60274 | BQ53: =BL53 -> 3700 | BR53: =BV53*90/365 -> 912.32877 | BS53: =BV53*91/365 -> 922.46575 | BT53: =BV53*92/365 -> 932.60274 | BU53: =BV53*92/365 -> 932.60274 | BV53: =BQ53 -> 3700 | BW53: =CA53/365*BW$106 -> 912.32877 | BX53: =CA53/365*BX$106 -> 922.46575 | BY53: =CA53/365*BY$106 -> 932.60274 | BZ53: =CA53/365*BZ$106 -> 932.60274 | CA53: 3700 | CB53: =CF53/365*CB$106 -> 922.46575 | CC53: =CF53/365*CC$106 -> 922.46575 | CD53: =CF53/365*CD$106 -> 932.60274 | CE53: =CF53/365*CE$106 -> 932.60274 | CF53: 3700 | CG53: =CK53/365*CG$106 -> 912.32877 | CH53: =CK53/365*CH$106 -> 922.46575 | CI53: =CK53/365*CI$106 -> 932.60274 | CJ53: =CK53/365*CJ$106 -> 932.60274 | CK53: 3700 | CL53: =CP53*90/365 -> 912.32877 | CM53: =CP53*91/365 -> 922.46575 | CN53: =CP53*92/365 -> 932.60274 | CO53: =CP53*92/365 -> 932.60274 | CP53: 3700 | CQ53: =CU53*90/365 -> 912.32877 | CR53: =CU53*91/365 -> 922.46575 | CS53: =CU53*92/365 -> 932.60274 | CT53: =CU53*92/365 -> 932.60274 | CU53: 3700 | CV53: =CZ53*90/365 -> 912.32877 | CW53: =CZ53*91/365 -> 922.46575 | CX53: =CZ53*92/365 -> 932.60274 | CY53: =CZ53*92/365 -> 932.60274 | CZ53: 3700
B54: Plate | H54: 1000 | I54: 1000 | J54: =N54*90/365 -> 295.89041 | K54: =N54*91/365 -> 299.17808 | L54: =N54*92/365 -> 302.46575 | M54: =N54*92/365 -> 302.46575 | N54: 1200 | O54: =S54*90/365 -> 295.89041 | P54: =S54*91/365 -> 299.17808 | Q54: =S54*92/365 -> 302.46575 | R54: =S54*92/365 -> 302.46575 | S54: 1200 | T54: =X54*90/365 -> 419.17808 | U54: =X54*91/365 -> 423.83562 | V54: =X54*92/365 -> 428.49315 | W54: =X54*92/365 -> 428.49315 | X54: 1700 | Y54: =AC54*90/365 -> 690.41096 | Z54: =AC54*91/365 -> 698.08219 | AA54: =AC54*92/365 -> 705.75342 | AB54: =AC54*92/365 -> 705.75342 | AC54: 2800 | AD54: =AH54*90/365 -> 690.41096 | AE54: =AH54*91/365 -> 698.08219 | AF54: =AH54*92/365 -> 705.75342 | AG54: =AH54*92/365 -> 705.75342 | AH54: 2800 | AI54: =AM54*90/365 -> 690.41096 | AJ54: =AM54*91/365 -> 698.08219 | AK54: =AM54*92/365 -> 705.75342 | AL54: =AM54*92/365 -> 705.75342 | AM54: 2800 | AN54: =AR54*90/365 -> 690.41096 | AO54: =AR54*91/365 -> 698.08219 | AP54: =AR54*92/365 -> 705.75342 | AQ54: =AR54*92/365 -> 705.75342 | AR54: =AM54 -> 2800 | AS54: =AW54*90/365 -> 690.41096 | AT54: =AW54*91/365 -> 698.08219 | AU54: =AW54*92/365 -> 705.75342 | AV54: =AW54*92/365 -> 705.75342 | AW54: =AR54 -> 2800 | AX54: =BB54*90/365 -> 690.41096 | AY54: =BB54*91/365 -> 698.08219 | AZ54: =BB54*92/365 -> 705.75342 | BA54: =BB54*92/365 -> 705.75342 | BB54: =AW54 -> 2800 | BC54: =BG54*90/365 -> 690.41096 | BD54: =BG54*91/365 -> 698.08219 | BE54: =BG54*92/365 -> 705.75342 | BF54: =BG54*92/365 -> 705.75342 | BG54: =BB54 -> 2800 | BH54: =BL54*90/365 -> 690.41096 | BI54: =BL54*91/365 -> 698.08219 | BJ54: =BL54*92/365 -> 705.75342 | BK54: =BL54*92/365 -> 705.75342 | BL54: =BG54 -> 2800 | BM54: =BQ54*90/365 -> 690.41096 | BN54: =BQ54*91/365 -> 698.08219 | BO54: =BQ54*92/365 -> 705.75342 | BP54: =BQ54*92/365 -> 705.75342 | BQ54: =BL54 -> 2800 | BR54: =BV54*90/365 -> 690.41096 | BS54: =BV54*91/365 -> 698.08219 | BT54: =BV54*92/365 -> 705.75342 | BU54: =BV54*92/365 -> 705.75342 | BV54: =BQ54 -> 2800 | BW54: =CA54/365*BW$106 -> 715.06849 | BX54: =CA54/365*BX$106 -> 723.0137 | BY54: =CA54/365*BY$106 -> 730.9589 | BZ54: =CA54/365*BZ$106 -> 730.9589 | CA54: 2900 | CB54: =CF54/365*CB$106 -> 723.0137 | CC54: =CF54/365*CC$106 -> 723.0137 | CD54: =CF54/365*CD$106 -> 730.9589 | CE54: =CF54/365*CE$106 -> 730.9589 | CF54: 2900 | CG54: =CK54/365*CG$106 -> 715.06849 | CH54: =CK54/365*CH$106 -> 723.0137 | CI54: =CK54/365*CI$106 -> 730.9589 | CJ54: =CK54/365*CJ$106 -> 730.9589 | CK54: 2900 | CL54: =CP54*90/365 -> 715.06849 | CM54: =CP54*91/365 -> 723.0137 | CN54: =CP54*92/365 -> 730.9589 | CO54: =CP54*92/365 -> 730.9589 | CP54: 2900 | CQ54: =CU54*90/365 -> 715.06849 | CR54: =CU54*91/365 -> 723.0137 | CS54: =CU54*92/365 -> 730.9589 | CT54: =CU54*92/365 -> 730.9589 | CU54: 2900 | CV54: =CZ54*90/365 -> 715.06849 | CW54: =CZ54*91/365 -> 723.0137 | CX54: =CZ54*92/365 -> 730.9589 | CY54: =CZ54*92/365 -> 730.9589 | CZ54: 2900
C55: Total Steel | H55: =SUM(H51:H54) -> 12800 | I55: =SUM(I51:I54) -> 13600 | J55: =N55/4 -> 4650 | K55: =N55/4 -> 4650 | L55: =N55/4 -> 4650 | M55: =N55/4 -> 4650 | N55: =SUM(N51:N54) -> 18600 | O55: =S55/4 -> 4775 | P55: =S55/4 -> 4775 | Q55: =S55/4 -> 4775 | R55: =S55/4 -> 4775 | S55: =SUM(S51:S54) -> 19100 | T55: =X55/4 -> 5075 | U55: =X55/4 -> 5075 | V55: =X55/4 -> 5075 | W55: =X55/4 -> 5075 | X55: =SUM(X51:X54) -> 20300 | Y55: =AC55/4 -> 6193.75 | Z55: =AC55/4 -> 6193.75 | AA55: =AC55/4 -> 6193.75 | AB55: =AC55/4 -> 6193.75 | AC55: =SUM(AC51:AC54) -> 24775 | AD55: =AH55/4 -> 6315 | AE55: =AH55/4 -> 6315 | AF55: =AH55/4 -> 6315 | AG55: =AH55/4 -> 6315 | AH55: =SUM(AH51:AH54) -> 25260 | AI55: =AM55/4 -> 6340 | AJ55: =AM55/4 -> 6340 | AK55: =AM55/4 -> 6340 | AL55: =AM55/4 -> 6340 | AM55: =SUM(AM51:AM54) -> 25360 | AN55: =AR55/4 -> 6552.5 | AO55: =AR55/4 -> 6552.5 | AP55: =AR55/4 -> 6552.5 | AQ55: =AR55/4 -> 6552.5 | AR55: =SUM(AR51:AR54) -> 26210 | AS55: =AW55/4 -> 6574.6918 | AT55: =AW55/4 -> 6574.6918 | AU55: =AW55/4 -> 6574.6918 | AV55: =AW55/4 -> 6574.6918 | AW55: =SUM(AW51:AW54) -> 26298.767 | AX55: =BB55/4 -> 6602.5 | AY55: =BB55/4 -> 6602.5 | AZ55: =BB55/4 -> 6602.5 | BA55: =BB55/4 -> 6602.5 | BB55: =SUM(BB51:BB54) -> 26410 | BC55: =BG55/4 -> 6602.5 | BD55: =BG55/4 -> 6602.5 | BE55: =BG55/4 -> 6602.5 | BF55: =BG55/4 -> 6602.5 | BG55: =SUM(BG51:BG54) -> 26410 | BH55: =BL55/4 -> 6727.5 | BI55: =BL55/4 -> 6727.5 | BJ55: =BL55/4 -> 6727.5 | BK55: =BL55/4 -> 6727.5 | BL55: =SUM(BL51:BL54) -> 26910 | BM55: =BQ55/4 -> 6727.5 | BN55: =BQ55/4 -> 6727.5 | BO55: =BQ55/4 -> 6727.5 | BP55: =BQ55/4 -> 6727.5 | BQ55: =SUM(BQ51:BQ54) -> 26910 | BR55: =BV55/4 -> 6840 | BS55: =BV55/4 -> 6840 | BT55: =BV55/4 -> 6840 | BU55: =BV55/4 -> 6840 | BV55: =SUM(BV51:BV54) -> 27360 | BW55: =SUM(BW51:BW54) -> 7103.8356 | BX55: =SUM(BX51:BX54) -> 7182.7671 | BY55: =SUM(BY51:BY54) -> 7261.6986 | BZ55: =SUM(BZ51:BZ54) -> 7261.6986 | CA55: =SUM(CA51:CA54) -> 28810 | CB55: =SUM(CB51:CB54) -> 7182.7671 | CC55: =SUM(CC51:CC54) -> 7182.7671 | ... CZ55: =SUM(CZ51:CZ54) -> 30860
A57: Capacity Utilization
B58: Nucor Steelmaking Capacity | H58: =H55 -> 12800 | I58: =I55 -> 13600 | J58: =N58*90/365 -> 4586.3014 | K58: =N58*91/365 -> 4637.2603 | L58: =N58*92/365 -> 4688.2192 | M58: =N58*92/365 -> 4688.2192 | N58: =N55 -> 18600 | O58: =S58*90/365 -> 4709.589 | P58: =S58*91/365 -> 4761.9178 | Q58: =S58*92/365 -> 4814.2466 | R58: =S58*92/365 -> 4814.2466 | S58: =S55 -> 19100 | T58: =X58*90/365 -> 5005.4795 | U58: =X58*91/365 -> 5061.0959 | V58: =X58*92/365 -> 5116.7123 | W58: =X58*92/365 -> 5116.7123 | X58: =X55 -> 20300 | Y58: =AC58*90/365 -> 6108.9041 | Z58: =AC58*91/365 -> 6176.7808 | AA58: =AC58*92/365 -> 6244.6575 | AB58: =AC58*92/365 -> 6244.6575 | AC58: =AC55 -> 24775 | AD58: =AH58*90/365 -> 6228.4932 | AE58: =AH58*91/365 -> 6297.6986 | AF58: =AH58*92/365 -> 6366.9041 | AG58: =AH58*92/365 -> 6366.9041 | AH58: =AH55 -> 25260 | AI58: =AM58*90/365 -> 6253.1507 | AJ58: =AM58*91/365 -> 6322.6301 | AK58: =AM58*92/365 -> 6392.1096 | AL58: =AM58*92/365 -> 6392.1096 | AM58: =AM55 -> 25360 | AN58: =AR58*90/365 -> 6462.7397 | AO58: =AR58*91/365 -> 6534.5479 | AP58: =AR58*92/365 -> 6606.3562 | AQ58: =AR58*92/365 -> 6606.3562 | AR58: =AR55 -> 26210 | AS58: =AW58*90/365 -> 6484.6275 | AT58: =AW58*91/365 -> 6556.6789 | AU58: =AW58*92/365 -> 6628.7303 | AV58: =AW58*92/365 -> 6628.7303 | AW58: =AW55 -> 26298.767 | AX58: =BB58*90/365 -> 6512.0548 | AY58: =BB58*91/365 -> 6584.411 | AZ58: =BB58*92/365 -> 6656.7671 | BA58: =BB58*92/365 -> 6656.7671 | BB58: =BB55 -> 26410 | BC58: =BG58*90/365 -> 6512.0548 | BD58: =BG58*91/365 -> 6584.411 | BE58: =BG58*92/365 -> 6656.7671 | BF58: =BG58*92/365 -> 6656.7671 | BG58: =BG55 -> 26410 | BH58: =BL58*90/365 -> 6635.3425 | BI58: =BL58*91/365 -> 6709.0685 | BJ58: =BL58*92/365 -> 6782.7945 | BK58: =BL58*92/365 -> 6782.7945 | BL58: =BL55 -> 26910 | BM58: =BQ58*90/365 -> 6635.3425 | BN58: =BQ58*91/365 -> 6709.0685 | BO58: =BQ58*92/365 -> 6782.7945 | BP58: =BQ58*92/365 -> 6782.7945 | BQ58: =BQ55 -> 26910 | BR58: =BV58*90/365 -> 6746.3014 | BS58: =BV58*91/365 -> 6821.2603 | BT58: =BV58*92/365 -> 6896.2192 | BU58: =BV58*92/365 -> 6896.2192 | BV58: =BV55 -> 27360 | BW58: =CA58*90/365 -> 7103.8356 | BX58: =CA58*91/365 -> 7182.7671 | BY58: =CA58*92/365 -> 7261.6986 | BZ58: =CA58*92/365 -> 7261.6986 | CA58: =CA55 -> 28810 | CB58: =CF58*90/365 -> 6583.5616 | CC58: =CF58*91/365 -> 6656.7123 | CD58: =CF58*92/365 -> 6729.863 | CE58: =CF58*92/365 -> 6729.863 | CF58: 26700 | CG58: =CK58*90/365 -> 6583.5616 | CH58: =CK58*91/365 -> 6656.7123 | CI58: =CK58*92/365 -> 6729.863 | CJ58: =CK58*92/365 -> 6729.863 | CK58: 26700 | CL58: =CP58*90/365 -> 6583.5616 | CM58: =CP58*91/365 -> 6656.7123 | CN58: =CP58*92/365 -> 6729.863 | CO58: =CP58*92/365 -> 6729.863 | CP58: 26700 | CQ58: =CU58*90/365 -> 6583.5616 | CR58: =CU58*91/365 -> 6656.7123 | CS58: =CU58*92/365 -> 6729.863 | CT58: =CU58*92/365 -> 6729.863 | CU58: 26700 | CV58: =CZ58*90/365 -> 6793.1507 | CW58: =CZ58*91/365 -> 6868.6301 | CX58: =CZ58*92/365 -> 6944.1096 | CY58: =CZ58*92/365 -> 6944.1096 | CZ58: =+CU58+500+350 -> 27550
B59: Nucor Production | H59: 11271 | I59: 12316 | J59: 3237 | K59: 3517 | L59: 3280 | M59: 3588 | N59: =SUM(J59:M59) -> 13622 | O59: 4258 | P59: 4287 | Q59: 4470 | R59: 4426 | S59: =SUM(O59:R59) -> 17441 | T59: 4960 | U59: 5121 | V59: 5072 | W59: 4584 | X59: =SUM(T59:W59) -> 19737 | Y59: 5108 | Z59: 4943 | AA59: 5085 | AB59: 5196 | AC59: =SUM(Y59:AB59) -> 20332 | AD59: 5791 | AE59: 5728 | AF59: 5799 | AG59: 5064 | AH59: =SUM(AD59:AG59) -> 22382 | AI59: 5585 | AJ59: 5518 | AK59: 5400 | AL59: 5586 | AM59: =SUM(AI59:AL59) -> 22089 | AN59: 5831 | AO59: 6043 | AP59: 5510 | AQ59: 3062 | AR59: =SUM(AN59:AQ59) -> 20446 | AS59: 2879 | AT59: 2964 | AU59: 4433 | AV59: 3722 | AW59: =SUM(AS59:AV59) -> 13998 | AX59: 4712 | AY59: 4648 | AZ59: 4426 | BA59: 4472 | BB59: =SUM(AX59:BA59) -> 18258 | BC59: 5219 | BD59: 4667 | BE59: 4910 | BF59: 4765 | BG59: =SUM(BC59:BF59) -> 19561 | BH59: 5259 | BI59: 5061 | BJ59: 4819 | BK59: 4726 | BL59: =SUM(BH59:BK59) -> 19865 | BM59: 4818 | BN59: 4892 | BO59: 5202 | BP59: 4988 | BQ59: =SUM(BM59:BP59) -> 19900 | BR59: 5194 | BS59: 5324 | BT59: 5412 | BU59: 5205 | BV59: =SUM(BR59:BU59) -> 21135 | BW59: 4758 | BX59: 5196 | BY59: 4942 | BZ59: 4398 | CA59: =SUM(BW59:BZ59) -> 19294 | CB59: 5390 | CC59: 5890 | CD59: 5012 | CE59: 4990 | CF59: =SUM(CB59:CE59) -> 21282 | CG59: =CG60*0.96 -> 5901.12 | CH59: =CH60*0.96 -> 6093.12 | CI59: =CI60*0.96 -> 5918.4 | CJ59: =CJ60*0.96 -> 5816.64 | CK59: =SUM(CG59:CJ59) -> 23729.28 | CL59: =CL60*0.96 -> 6017.28 | CM59: =CM60*0.96 -> 6055.044 | CN59: =CN60*0.96 -> 5745.2188 | CO59: =CO60*0.96 -> 5660.6458 | CP59: =SUM(CL59:CO59) -> 23478.189 | CQ59: =CQ60*0.96 -> 6128.0287 | CR59: =CR60*0.96 -> 6166.5479 | CS59: =CS60*0.96 -> 5850.5262 | CT59: =CT60*0.96 -> 5764.2618 | CU59: =SUM(CQ59:CT59) -> 23909.365 | CV59: =CV60*0.96 -> 6671.764 | CW59: =CW60*0.96 -> 6689.7401 | CX59: =CX60*0.96 -> 6359.8846 | CY59: =CY60*0.96 -> 6272.0071 | CZ59: =SUM(CV59:CY59) -> 25993.396
B60: Total Shipments | H60: 10980 | I60: 12141 | J60: 3272 | K60: 3393 | L60: 3321 | M60: 3452 | N60: =SUM(J60:M60) -> 13438 | O60: 4346 | P60: 4297 | Q60: 4546 | R60: 4467 | S60: =SUM(O60:R60) -> 17656 | T60: 5145 | U60: 4905 | V60: 4968 | W60: 4446 | X60: =SUM(T60:W60) -> 19464 | Y60: 5043 | Z60: 5103 | AA60: 5358 | AB60: 5165 | AC60: =SUM(Y60:AB60) -> 20669 | AD60: 5721 | AE60: 5895 | AF60: 5670 | AG60: 5060 | AH60: =SUM(AD60:AG60) -> 22346 | AI60: 5660 | AJ60: 5407 | AK60: 5596 | AL60: 5684 | AM60: =SUM(AI60:AL60) -> 22347 | AN60: 5951 | AO60: 6117 | AP60: 5438 | AQ60: 3426 | AR60: =SUM(AN60:AQ60) -> 20932 | AS60: 2808 | AT60: 2999 | AU60: 4312 | AV60: 3917 | AW60: =SUM(AS60:AV60) -> 14036 | AX60: 4706 | AY60: 4597 | AZ60: 4702 | BA60: 4568 | BB60: =SUM(AX60:BA60) -> 18573 | BC60: 5200 | BD60: 4864 | BE60: 5128 | BF60: 4933 | BG60: =SUM(BC60:BF60) -> 20125 | BH60: 5235 | BI60: 5202 | BJ60: 5043 | BK60: 4762 | BL60: =SUM(BH60:BK60) -> 20242 | BM60: 5075 | BN60: 5025 | BO60: 5359 | BP60: 5191 | BQ60: =SUM(BM60:BP60) -> 20650 | BR60: 5432 | BS60: 5477 | BT60: 5741 | BU60: 5317 | BV60: =SUM(BR60:BU60) -> 21967 | BW60: 4887 | BX60: 5348 | BY60: 5166 | BZ60: 4459 | CA60: =SUM(BW60:BZ60) -> 19860 | CB60: 5647 | CC60: 5930 | CD60: 5213 | CE60: 5151 | CF60: =SUM(CB60:CE60) -> 21941 | CG60: 6147 | CH60: 6347 | CI60: 6165 | CJ60: 6059 | CK60: =SUM(CG60:CJ60) -> 24718 | CL60: 6268 | CM60: =CM61/CM64 -> 6307.3374 | CN60: =CN61/CN64 -> 5984.6029 | CO60: =CO61/CO64 -> 5896.506 | CP60: =SUM(CL60:CO60) -> 24456.446 | CQ60: =CQ61/CQ64 -> 6383.3632 | CR60: =CR61/CR64 -> 6423.4874 | CS60: =CS61/CS64 -> 6094.2982 | CT60: =CT61/CT64 -> 6004.4393 | CU60: =SUM(CQ60:CT60) -> 24905.588 | CV60: =CV61/CV64 -> 6949.7542 | CW60: =CW61/CW64 -> 6968.4793 | CX60: =CX61/CX64 -> 6624.8798 | CY60: =CY61/CY64 -> 6533.3408 | CZ60: =SUM(CV60:CY60) -> 27076.454
B61: Nucor (Shipments to Outside Customers) | H61: =H38 -> 9779 | I61: =I38 -> 11032 | J61: =J38 -> 3023 | K61: =K38 -> 3133 | L61: =L38 -> 2962 | M61: =M38 -> 3196 | N61: =N38 -> 12314 | O61: =O38 -> 4040 | ... R61: =R38 -> 4108 | S61: =SUM(O61:R61) -> 16263 | T61: =T38 -> 4726 | U61: =U38 -> 4456 | V61: =V38 -> 4492 | W61: =W38 -> 4113 | X61: =SUM(T61:W61) -> 17787 | Y61: =Y38 -> 4688 | Z61: =Z38 -> 4693 | AA61: =AA38 -> 4914 | AB61: =AB38 -> 4725 | AC61: =SUM(Y61:AB61) -> 19020 | AD61: =AD38 -> 5266 | AE61: =AE38 -> 5450 | AF61: =AF38 -> 5223 | AG61: =AG38 -> 4713 | AH61: =SUM(AD61:AG61) -> 20652 | AI61: =AI38 -> 5229 | AJ61: =AJ38 -> 4890 | AK61: =AK38 -> 5038 | AL61: =AL38 -> 5078 | AM61: =SUM(AI61:AL61) -> 20235 | AN61: =AN38 -> 5203 | AO61: =AO38 -> 5394 | AP61: =AP38 -> 4688 | AQ61: 2900 | AR61: =SUM(AN61:AQ61) -> 18185 | AS61: 2433 | AT61: 2569 | AU61: 3705 | AV61: 3368 | AW61: =SUM(AS61:AV61) -> 12075 | AX61: =AX38 -> 4066 | AY61: =AY38 -> 3922 | AZ61: =AZ38 -> 3993 | BA61: =BA38 -> 3840 | BB61: =SUM(AX61:BA61) -> 15821 | BC61: =BC38 -> 4418 | BD61: =BD38 -> 4052 | BE61: 4194 | BF61: 4132 | BG61: =SUM(BC61:BF61) -> 16796 | BH61: 4590 | BI61: 4449 | BJ61: 4313 | BK61: 4121 | BL61: =SUM(BH61:BK61) -> 17473 | BM61: 4334 | BN61: 4274 | BO61: 4640 | BP61: 4485 | BQ61: =SUM(BM61:BP61) -> 17733 | BR61: 4600 | BS61: 4646 | BT61: 4851 | BU61: 4584 | BV61: =SUM(BR61:BU61) -> 18681 | BW61: =BW38 -> 4165 | BX61: =BX38 -> 4578 | BY61: =BY38 -> 4440 | BZ61: =BZ38 -> 3823 | CA61: =SUM(BW61:BZ61) -> 17006 | CB61: =CB38 -> 4899 | CC61: =CC38 -> 5082 | CD61: =CD38 -> 4465 | CE61: =CE38 -> 4400 | CF61: =SUM(CB61:CE61) -> 18846 | CG61: =CG38 -> 4860 | CH61: =CH38 -> 4950 | CI61: =CI38 -> 4698 | CJ61: =CJ38 -> 4629 | CK61: =SUM(CG61:CJ61) -> 19137 | CL61: =CL38 -> 5016 | CM61: =CM38 -> 5047.48 | CN61: =CN38 -> 4789.21 | CO61: =CO38 -> 4718.71 | CP61: =SUM(CL61:CO61) -> 19571.4 | CQ61: =CQ38 -> 5108.32 | CR61: =CR38 -> 5140.4296 | CS61: =CS38 -> 4876.9942 | CT61: =CT38 -> 4805.0842 | CU61: =SUM(CQ61:CT61) -> 19930.828 | CV61: =CV38 -> 5561.5774 | CW61: =CW38 -> 5576.5622 | CX61: =CX38 -> 5301.5949 | CY61: =CY38 -> 5228.3403 | CZ61: =SUM(CV61:CY61) -> 21668.075
C63: Capacity Utilization | H63: =H59/H58 -> 0.88054687 | I63: =I59/I58 -> 0.90558824 | J63: =J59/J58 -> 0.70579749 | K63: =K59/K58 -> 0.75842195 | L63: =L59/L58 -> 0.69962599 | M63: =M59/M58 -> 0.76532258 | N63: =N59/N58 -> 0.73236559 | O63: =O59/O58 -> 0.90411286 | ... CZ63: =CZ59/CZ58 -> 0.94349894
C64: Outside shipment to total | H64: =H61/H60 -> 0.89061931 | I64: =I61/I60 -> 0.90865662 | J64: =J61/J60 -> 0.92389976 | K64: =K61/K60 -> 0.92337165 | L64: =L61/L60 -> 0.89190003 | M64: =M61/M60 -> 0.92584009 | N64: =N61/N60 -> 0.9163566 | O64: =O61/O60 -> 0.92959043 | ... CH64: =CH61/CH60 -> 0.77989601 | CI64: =CH64 -> 0.77989601 | CJ64: =CI64 -> 0.77989601 | CK64: =CK61/CK60 -> 0.77421312 | CL64: =CL61/CL60 -> 0.80025526 | CM64: =CL64 -> 0.80025526 | CN64: =CM64 -> 0.80025526 | CO64: =CN64 -> 0.80025526 | CP64: =CP61/CP60 -> 0.80025526 | CQ64: =CO64 -> 0.80025526 | CR64: =CQ64 -> 0.80025526 | CS64: =CR64 -> 0.80025526 | CT64: =CS64 -> 0.80025526 | CU64: =CU61/CU60 -> 0.80025526 | CV64: =CT64 -> 0.80025526 | CW64: =CV64 -> 0.80025526 | CX64: =CW64 -> 0.80025526 | CY64: =CX64 -> 0.80025526 | CZ64: =CZ61/CZ60 -> 0.80025526
A66: Shipments/Finished Capacity
B67: Sheet | T67: =Operations!T33/Operations!T51 -> 0.94614774 | U67: =Operations!U33/Operations!U51 -> 0.92517208 | V67: =Operations!V33/Operations!V51 -> 0.87457 | W67: =Operations!W33/Operations!W51 -> 0.80655757 | X67: =Operations!X33/Operations!X51 -> 0.88769231 | Y67: =Operations!Y33/Operations!Y51 -> 0.77581276 | Z67: =Operations!Z33/Operations!Z51 -> 0.74129019 | AA67: =Operations!AA33/Operations!AA51 -> 0.71780395 | ... AQ67: =Operations!AQ33/Operations!AQ51 -> 0.40188205 | AR67: =(Operations!AR33)/Operations!AR51 -> 0.69490741 | AS67: =(Operations!AS33)/Operations!AS51 -> 0.35643766 | AT67: =(Operations!AT33)/Operations!AT51 -> 0.355836 | AU67: =(Operations!AU33)/Operations!AU51 -> 0.63398003 | AV67: =(Operations!AV33)/Operations!AV51 -> 0.56438797 | AW67: =(Operations!AW33)/Operations!AW51 -> 0.47865841 | AX67: =(Operations!AX33)/Operations!AX51 -> 0.75102881 | AY67: =(Operations!AY33)/Operations!AY51 -> 0.70303724 | ... CZ67: =(Operations!CZ33)/Operations!CZ51 -> 0.71798128
B68: Bars | T68: =Operations!T34/Operations!T52 -> 0.96110229 | U68: =Operations!U34/Operations!U52 -> 0.84485435 | V68: =Operations!V34/Operations!V52 -> 0.81363009 | W68: =Operations!W34/Operations!W52 -> 0.71287095 | X68: =Operations!X34/Operations!X52 -> 0.83238095 | Y68: =Operations!Y34/Operations!Y52 -> 0.74654775 | Z68: =Operations!Z34/Operations!Z52 -> 0.81722224 | AA68: =Operations!AA34/Operations!AA52 -> 0.88848335 | ... CZ68: =Operations!CZ34/Operations!CZ52 -> 0.5624135
B69: Structural | T69: =Operations!T36/Operations!T53 -> 0.97079861 | U69: =Operations!U36/Operations!U53 -> 0.88241758 | V69: =Operations!V36/Operations!V53 -> 0.83439198 | W69: =Operations!W36/Operations!W53 -> 0.76496264 | X69: =Operations!X36/Operations!X53 -> 0.8625 | Y69: =Operations!Y36/Operations!Y53 -> 0.71794294 | Z69: =Operations!Z36/Operations!Z53 -> 0.74040689 | AA69: =Operations!AA36/Operations!AA53 -> 0.80956228 | ... CZ69: =Operations!CZ36/Operations!CZ53 -> 0.49339142
B70: Plate | T70: =Operations!T37/Operations!T54 -> 0.82065359 | U70: =Operations!U37/Operations!U54 -> 0.76916613 | V70: =Operations!V37/Operations!V54 -> 1.2158887 | W70: =Operations!W37/Operations!W54 -> 1.1995524 | X70: =Operations!X37/Operations!X54 -> 1.0029412 | Y70: =Operations!Y37/Operations!Y54 -> 0.8560119 | Z70: =Operations!Z37/Operations!Z54 -> 0.70335557 | AA70: =Operations!AA37/Operations!AA54 -> 0.75238742 | ... CZ70: =Operations!CZ37/Operations!CZ54 -> 0.81853649
B72: Shredded Scrap | J72: 76.541667 | K72: 96.348214 | L72: 101.02679 | M72: 95.440476 | N72: =AVERAGE(J72:M72) -> 92.339286 | O72: 110.24405 | P72: 113.60714 | Q72: 122.32143 | R72: 144.72619 | S72: =AVERAGE(O72:R72) -> 122.7247 | T72: =Operations!T13 -> 244.5 | U72: =Operations!U13 -> 201.46667 | V72: =Operations!V13 -> 265.48333 | W72: =Operations!W13 -> 287.01667 | X72: =AVERAGE(T72:W72) -> 249.61667 | Y72: =Operations!Y13 -> 246.37667 | Z72: =Operations!Z13 -> 203.84667 | AA72: =Operations!AA13 -> 220.79667 | AB72: =Operations!AB13 -> 246.94 | AC72: =AVERAGE(Y72:AB72) -> 229.49 | AD72: =Operations!AD13 -> 241.68333 | AE72: =Operations!AE13 -> 267.78 | AF72: =Operations!AF13 -> 254.14667 | AG72: =Operations!AG13 -> 228.62 | AH72: =AVERAGE(AD72:AG72) -> 248.0575 | AI72: =Operations!AI13 -> 299.89 | AJ72: =Operations!AJ13 -> 286.15333 | AK72: =Operations!AK13 -> 278.87 | AL72: =Operations!AL13 -> 295.4 | AM72: =AVERAGE(AI72:AL72) -> 290.07833 | AN72: =Operations!AN13 -> 392.54 | AO72: =Operations!AO13 -> 547.20667 | AP72: =Operations!AP13 -> 513.71333 | AQ72: =Operations!AQ13 -> 193.66333 | AR72: =AVERAGE(AN72:AQ72) -> 411.78083 | AS72: =Operations!AS13 -> 213.37333 | AT72: =Operations!AT13 -> 191.80667 | AU72: =Operations!AU13 -> 269.50667 | AV72: =Operations!AV13 -> 265.71333 | AW72: =AVERAGE(AS72:AV72) -> 235.1 | AX72: =Operations!AX13 -> 358.61667 | AY72: =Operations!AY13 -> 368.89333 | AZ72: =Operations!AZ13 -> 339.70667 | BA72: =Operations!BA13 -> 367.51667 | BB72: =AVERAGE(AX72:BA72) -> 358.68333 | BC72: =Operations!BC13 -> 456.45667 | BD72: =Operations!BD13 -> 447.39333 | BE72: =Operations!BE13 -> 450 | BF72: =Operations!BF13 -> 429.87 | BG72: =AVERAGE(BC72:BF72) -> 445.93 | BH72: =Operations!BH13 -> 449.5 | BI72: =Operations!BI13 -> 414.82667 | BJ72: =Operations!BJ13 -> 373.72 | BK72: =Operations!BK13 -> 369.33 | BL72: =AVERAGE(BH72:BK72) -> 401.84417 | BM72: =Operations!BM13 -> 390.07333 | BN72: =Operations!BN13 -> 374.86667 | BO72: =Operations!BO13 -> 366.60333 | BP72: =Operations!BP13 -> 383.98333 | BQ72: =AVERAGE(BM72:BP72) -> 378.88167 | BR72: =Operations!BR13 -> 412.41333 | BS72: =Operations!BS13 -> 383.64333 | BT72: =Operations!BT13 -> 374.24333 | BU72: =Operations!BU13 -> 338.38333 | BV72: =AVERAGE(BR72:BU72) -> 377.17083 | BW72: =Operations!BW13 -> 277.58667 | BX72: =Operations!BX13 -> 249.18333 | BY72: =Operations!BY13 -> 244.09 | BZ72: =Operations!BZ13 -> 171.85667 | CA72: =AVERAGE(BW72:BZ72) -> 235.67917 | CB72: =Operations!CB13 -> 194.21667 | CC72: =Operations!CC13 -> 260.70667 | CD72: =Operations!CD13 -> 235.08 | CE72: =Operations!CE13 -> 227.43667 | CF72: =AVERAGE(CB72:CE72) -> 229.36 | CG72: =Operations!CG13 -> 301.52667 | CH72: =Operations!CH13 -> 292.27333 | CI72: =Operations!CI13 -> 289.08667 | CJ72: =Operations!CJ13 -> 272.81667 | CK72: =AVERAGE(CG72:CJ72) -> 288.92583 | CL72: =Operations!CL13 -> 332.51333 | CM72: =Operations!CM13 -> 375 | CN72: =Operations!CN13 -> 360 | CO72: =Operations!CO13 -> 345 | CP72: =AVERAGE(CL72:CO72) -> 353.12833 | CQ72: =Operations!CQ13 -> 355 | CR72: =Operations!CR13 -> 360 | CS72: =Operations!CS13 -> 350 | CT72: =Operations!CT13 -> 335 | CU72: =AVERAGE(CQ72:CT72) -> 350 | CV72: =Operations!CV13 -> 305 | CW72: =Operations!CW13 -> 310 | CX72: =Operations!CX13 -> 300 | CY72: =Operations!CY13 -> 285 | CZ72: =AVERAGE(CV72:CY72) -> 300
B73: #1 Busheling Scrap | J73: 77.957543 | K73: 96.689665 | L73: 110.05141 | M73: 112.39989 | N73: =AVERAGE(J73:M73) -> 99.274625 | O73: 121.64041 | P73: 125 | Q73: 134.67326 | R73: 157.54677 | S73: =AVERAGE(O73:R73) -> 134.71511 | T73: =Operations!T14 -> 260.22006 | U73: =Operations!U14 -> 251.76046 | V73: =Operations!V14 -> 365.16595 | W73: =Operations!W14 -> 411.30952 | X73: =AVERAGE(T73:W73) -> 322.114 | Y73: =Operations!Y14 -> 303.50324 | Z73: =Operations!Z14 -> 206.73882 | AA73: =Operations!AA14 -> 223.92754 | AB73: =Operations!AB14 -> 265.51587 | AC73: =AVERAGE(Y73:AB73) -> 249.92137 | AD73: =Operations!AD14 -> 265.2193 | AE73: =Operations!AE14 -> 315.45455 | AF73: =Operations!AF14 -> 298.47101 | AG73: =Operations!AG14 -> 231.23333 | AH73: =AVERAGE(AD73:AG73) -> 277.59455 | AI73: =Operations!AI14 -> 301.20106 | AJ73: =Operations!AJ14 -> 310.33 | AK73: =Operations!AK14 -> 312.79333 | AL73: =Operations!AL14 -> 320.09333 | AM73: =AVERAGE(AI73:AL73) -> 311.10443 | AN73: =Operations!AN14 -> 414.93667 | AO73: =Operations!AO14 -> 682.81333 | AP73: =Operations!AP14 -> 773.15667 | AQ73: =Operations!AQ14 -> 218.44667 | AR73: =AVERAGE(AN73:AQ73) -> 522.33833 | AS73: =Operations!AS14 -> 226.29667 | AT73: =Operations!AT14 -> 198.70333 | AU73: =Operations!AU14 -> 315.73667 | AV73: =Operations!AV14 -> 307.81667 | AW73: =AVERAGE(AS73:AV73) -> 262.13833 | AX73: =Operations!AX14 -> 414.06333 | AY73: =Operations!AY14 -> 467.11333 | AZ73: =Operations!AZ14 -> 417.85667 | BA73: =Operations!BA14 -> 406.64 | BB73: =AVERAGE(AX73:BA73) -> 426.41833 | BC73: =Operations!BC14 -> 485.19333 | BD73: =Operations!BD14 -> 498.10667 | BE73: =Operations!BE14 -> 511.63333 | BF73: =Operations!BF14 -> 482.8 | BG73: =AVERAGE(BC73:BF73) -> 494.43333 | BH73: =Operations!BH14 -> 487.22667 | BI73: =Operations!BI14 -> 429.26333 | BJ73: =Operations!BJ14 -> 382.78 | BK73: =Operations!BK14 -> 371.63 | BL73: =AVERAGE(BH73:BK73) -> 417.725 | BM73: =Operations!BM14 -> 393.10333 | BN73: =Operations!BN14 -> 392.21333 | BO73: =Operations!BO14 -> 404.1 | BP73: =Operations!BP14 -> 417.89333 | BQ73: =AVERAGE(BM73:BP73) -> 401.8275 | BR73: =Operations!BR14 -> 414.45 | BS73: =Operations!BS14 -> 397.29333 | BT73: =Operations!BT14 -> 397 | BU73: =Operations!BU14 -> 362.80667 | BV73: =AVERAGE(BR73:BU73) -> 392.8875 | BW73: =Operations!BW14 -> 290.99333 | BX73: =Operations!BX14 -> 248.18333 | BY73: =Operations!BY14 -> 254.76333 | BZ73: =Operations!BZ14 -> 175.89333 | CA73: =AVERAGE(BW73:BZ73) -> 242.45833 | CB73: =Operations!CB14 -> 183.29333 | CC73: =Operations!CC14 -> 259.92333 | CD73: =Operations!CD14 -> 261.29333 | CE73: =Operations!CE14 -> 234.56333 | CF73: =AVERAGE(CB73:CE73) -> 234.76833 | CG73: =Operations!CG14 -> 325.11 | CH73: =Operations!CH14 -> 351.33333 | CI73: =Operations!CI14 -> 359.13 | CJ73: =Operations!CJ14 -> 332.75667 | CK73: =AVERAGE(CG73:CJ73) -> 342.0825 | CL73: =Operations!CL14 -> 366.45667 | CM73: =Operations!CM14 -> 385 | CN73: =Operations!CN14 -> 370 | CO73: =Operations!CO14 -> 355 | CP73: =AVERAGE(CL73:CO73) -> 369.11417 | CQ73: =Operations!CQ14 -> 365 | CR73: =Operations!CR14 -> 370 | CS73: =Operations!CS14 -> 360 | CT73: =Operations!CT14 -> 355 | CU73: =AVERAGE(CQ73:CT73) -> 362.5 | CV73: =Operations!CV14 -> 325 | CW73: =Operations!CW14 -> 330 | CX73: =Operations!CX14 -> 320 | CY73: =Operations!CY14 -> 305 | CZ73: =AVERAGE(CV73:CY73) -> 320
C74: Blended Spot Scrap Cost | J74: =(J72*0.33+J73*0.67) -> 77.490304 | K74: =(K72*0.33+K73*0.67) -> 96.576986 | L74: =(L72*0.33+L73*0.67) -> 107.07328 | M74: =(M72*0.33+M73*0.67) -> 106.80328 | N74: =(N72*0.33+N73*0.67) -> 96.985963 | O74: =(O72*0.33+O73*0.67) -> 117.87961 | P74: =(P72*0.33+P73*0.67) -> 121.24036 | Q74: =(Q72*0.33+Q73*0.67) -> 130.59716 | ... CZ74: =(CZ72*0.33+CZ73*0.67) -> 313.4
A76: Scrap Analysis
B77: Scrap Realized Price($/ton) | H77: 120 | I77: 101 | J77: 96 | K77: 107 | L77: 118 | M77: 118 | N77: 110 | O77: 122 | P77: 131 | Q77: 137 | R77: 158 | S77: =AVERAGE(O77:R77) -> 137 | T77: 200 | U77: 227 | V77: 248 | W77: 278 | X77: =AVERAGE(T77:W77) -> 238.25 | Y77: 272 | Z77: 246 | AA77: 217 | AB77: 240 | AC77: =AVERAGE(Y77:AB77) -> 243.75 | AD77: 237 | AE77: 247 | AF77: 257 | AG77: 243 | AH77: =AVERAGE(AD77:AG77) -> 246 | AI77: 259 | AJ77: 291 | AK77: 277 | AL77: 285 | AM77: =AVERAGE(AI77:AL77) -> 278 | AN77: 333 | AO77: 456 | AP77: 533 | AQ77: 435 | AR77: =AVERAGE(AN77:AQ77) -> 439.25 | AS77: 333 | AT77: 312 | AU77: 299 | AV77: 276 | AW77: =AVERAGE(AS77:AV77) -> 305 | AX77: 318 | AY77: 373 | AZ77: 354 | BA77: 359 | BB77: =AVERAGE(AX77:BA77) -> 351 | BC77: 424 | BD77: 444 | BE77: 449 | BF77: 441 | BG77: 439 | BH77: 445 | BI77: 427 | BJ77: 380 | BK77: 372 | BL77: 407 | BM77: 379 | BN77: 377 | BO77: 372 | BP77: 377 | BQ77: =AVERAGE(BM77:BP77) -> 376.25 | BR77: 398 | BS77: 384 | BT77: 379 | BU77: 363 | BV77: =AVERAGE(BR77:BU77) -> 381 | BW77: 324 | BX77: 271 | BY77: 262 | BZ77: 219 | CA77: =AVERAGE(BW77:BZ77) -> 269 | CB77: 193 | CC77: 232 | CD77: 252 | CE77: 236 | CF77: =AVERAGE(CB77:CE77) -> 228.25 | CG77: 284 | CH77: 313 | CI77: 317 | CJ77: 317 | CK77: =AVERAGE(CG77:CJ77) -> 307.75 | CL77: 337 | CM77: ='Price Relationships'!$K$70 -> 359.985 | CN77: ='Price Relationships'!$K$71 -> 367.78107 | CO77: ='Price Relationships'!$K$72 -> 366.53974 | CP77: =AVERAGE(CL77:CO77) -> 357.82645 | CQ77: ='Price Relationships'!$K$73 -> 369.72115 | CR77: ='Price Relationships'!$K$74 -> 373.57408 | CS77: ='Price Relationships'!$K$75 -> 371.94658 | CT77: ='Price Relationships'!$K$76 -> 367.56821 | CU77: =AVERAGE(CQ77:CT77) -> 370.7025 | CV77: ='Price Relationships'!$K$77 -> 353.20309 | CW77: ='Price Relationships'!$K$78 -> 346.61584 | CX77: ='Price Relationships'!$K$79 -> 338.77642 | CY77: ='Price Relationships'!$K$80 -> 328.23197 | CZ77: =AVERAGE(CV77:CY77) -> 341.70683
C78: Annual Increase % | I78: =I77/H77-1 -> -0.15833333 | N78: =N77/I77-1 -> 0.089108911 | O78: =O77/J77-1 -> 0.27083333 | P78: =P77/K77-1 -> 0.22429907 | Q78: =Q77/L77-1 -> 0.16101695 | R78: =R77/M77-1 -> 0.33898305 | S78: =S77/N77-1 -> 0.24545455 | T78: =T77/O77-1 -> 0.63934426 | U78: =U77/P77-1 -> 0.73282443 | ... CZ78: =CZ77/CU77-1 -> -0.078218179
C79: Seq. Increase % | K79: =K77/J77-1 -> 0.11458333 | L79: =L77/K77-1 -> 0.10280374 | M79: =M77/L77-1 -> 0 | O79: =O77/M77-1 -> 0.033898305 | P79: =P77/O77-1 -> 0.073770492 | Q79: =Q77/P77-1 -> 0.045801527 | R79: =R77/Q77-1 -> 0.15328467 | T79: =T77/R77-1 -> 0.26582278 | U79: =U77/T77-1 -> 0.135 | V79: =V77/U77-1 -> 0.092511013 | W79: =W77/V77-1 -> 0.12096774 | Y79: =Y77/W77-1 -> -0.021582734 | Z79: =Z77/Y77-1 -> -0.095588235 | AA79: =AA77/Z77-1 -> -0.11788618 | AB79: =AB77/AA77-1 -> 0.10599078 | AD79: =AD77/AB77-1 -> -0.0125 | AE79: =AE77/AD77-1 -> 0.042194093 | AF79: =AF77/AE77-1 -> 0.04048583 | AG79: =AG77/AF77-1 -> -0.054474708 | AI79: =AI77/AG77-1 -> 0.065843621 | AJ79: =AJ77/AI77-1 -> 0.12355212 | AK79: =AK77/AJ77-1 -> -0.048109966 | AL79: =AL77/AK77-1 -> 0.028880866 | AN79: =AN77/AL77-1 -> 0.16842105 | AO79: =AO77/AN77-1 -> 0.36936937 | AP79: =AP77/AO77-1 -> 0.16885965 | AQ79: =AQ77/AP77-1 -> -0.18386492 | AS79: =AS77/AQ77-1 -> -0.23448276 | AT79: =AT77/AS77-1 -> -0.063063063 | AU79: =AU77/AT77-1 -> -0.041666667 | AV79: =AV77/AU77-1 -> -0.076923077 | AX79: =AX77/AV77-1 -> 0.15217391 | AY79: =AY77/AX77-1 -> 0.17295597 | AZ79: =AZ77/AY77-1 -> -0.050938338 | BA79: =BA77/AZ77-1 -> 0.014124294 | BC79: =BC77/BA77-1 -> 0.1810585 | BD79: =BD77/BC77-1 -> 0.047169811 | BE79: =BE77/BD77-1 -> 0.011261261 | BF79: =BF77/BE77-1 -> -0.017817372 | BH79: =BH77/BF77-1 -> 0.0090702948 | BI79: =BI77/BH77-1 -> -0.040449438 | BJ79: =BJ77/BI77-1 -> -0.11007026 | BK79: =BK77/BJ77-1 -> -0.021052632 | BM79: =BM77/BK77-1 -> 0.018817204 | BN79: =BN77/BM77-1 -> -0.0052770449 | BO79: =BO77/BN77-1 -> -0.013262599 | BP79: =BP77/BO77-1 -> 0.01344086 | BR79: =BR77/BP77-1 -> 0.055702918 | BS79: =BS77/BR77-1 -> -0.035175879 | BT79: =BT77/BS77-1 -> -0.013020833 | BU79: =BU77/BT77-1 -> -0.042216359 | BW79: =BW77/BU77-1 -> -0.10743802 | BX79: =BX77/BW77-1 -> -0.16358025 | BY79: =BY77/BX77-1 -> -0.033210332 | BZ79: =BZ77/BY77-1 -> -0.16412214 | CB79: =CB77/BZ77-1 -> -0.11872146 | CC79: =CC77/CB77-1 -> 0.20207254 | CD79: =CD77/CC77-1 -> 0.086206897 | CE79: =CE77/CD77-1 -> -0.063492063 | CG79: =CG77/CE77-1 -> 0.20338983 | CH79: =CH77/CG77-1 -> 0.10211268 | CI79: =CI77/CH77-1 -> 0.012779553 | CJ79: =CJ77/CI77-1 -> 0 | CK79: =CK77/CJ77-1 -> -0.029179811 | CL79: =CL77/CJ77-1 -> 0.063091483 | CM79: =CM77/CL77-1 -> 0.068204748 | CN79: =CN77/CM77-1 -> 0.021656666 | CO79: =CO77/CN77-1 -> -0.0033752019 | CP79: =CP77/CO77-1 -> -0.023771736 | CQ79: =CQ77/CP77-1 -> 0.033241509 | CR79: =CR77/CQ77-1 -> 0.010421195 | CS79: =CS77/CR77-1 -> -0.0043565735 | CT79: =CT77/CS77-1 -> -0.011771487 | ... CZ79: =CZ77/CY77-1 -> 0.041052851
B80: Discount/Premium to List | J80: =J77/J72 -> 1.2542188 | K80: =K77/K72 -> 1.1105551 | L80: =L77/L72 -> 1.1680071 | M80: =M77/M72 -> 1.2363727 | N80: =N77/N72 -> 1.1912589 | O80: =O77/O72 -> 1.1066357 | P80: =P77/P72 -> 1.1530965 | Q80: =Q77/Q72 -> 1.12 | ... CZ80: =CZ77/CZ72 -> 1.1390228
A82: Revenues
B83: Sheet | S83: =S89-SUM(S84:S87) -> 2371.611 | X83: =X89-SUM(X84:X87) -> 4856.469 | Y83: =Y33*Y18/1000 -> 1394.55 | Z83: =Z33*Z18/1000 -> 1215.564 | AA83: =AA33*AA18/1000 -> 1021.942 | AB83: =AB33*AB18/1000 -> 1171.83 | AC83: =SUM(Y83:AB83) -> 4803.886 | AD83: =AD33*AD18/1000 -> 1331.154 | AE83: =AE33*AE18/1000 -> 1388.125 | AF83: =AF33*AF18/1000 -> 1465.121 | AG83: =AG33*AG18/1000 -> 1158.144 | AH83: =SUM(AD83:AG83) -> 5342.544 | AI83: =AI33*AI18/1000 -> 1203.92 | AJ83: =AJ33*AJ18/1000 -> 1302.84 | AK83: =AK33*AK18/1000 -> 1226.876 | AL83: =AL33*AL18/1000 -> 1296.84 | AM83: =SUM(AI83:AL83) -> 5030.476 | AN83: =AN33*AN18/1000 -> 1459.26 | AO83: =AO33*AO18/1000 -> 1988.16 | AP83: =AP33*AP18/1000 -> 2092.8 | AQ83: =AQ33*AQ18/1000 -> 934.276 | AR83: =AR33*AR18/1000 -> 6521.845 | AS83: =AS33*AS18/1000 -> 583.77 | AT83: =AT33*AT18/1000 -> 482.034 | AU83: =AU33*AU18/1000 -> 887.4 | ... CZ83: =CZ33*CZ18/1000 -> 7866.1679
B84: Rebar/M Bar | S84: 1746.805 | X84: 2632.966 | Y84: =Y34*Y19/1000 -> 707.264 | Z84: =Z34*Z19/1000 -> 759.977 | AA84: =AA34*AA19/1000 -> 830.304 | AB84: =AB34*AB19/1000 -> 764.22 | AC84: =SUM(Y84:AB84) -> 3061.765 | AD84: =AD34*AD19/1000 -> 889.434 | AE84: =AE34*AE19/1000 -> 1025.703 | AF84: =AF34*AF19/1000 -> 969.413 | AG84: =AG34*AG19/1000 -> 836.928 | AH84: =SUM(AD84:AG84) -> 3721.478 | AI84: =AI34*AI19/1000 -> 1064.115 | AJ84: =AJ34*AJ19/1000 -> 912.6 | AK84: =AK34*AK19/1000 -> 976.788 | AL84: =AL34*AL19/1000 -> 950.532 | AM84: =SUM(AI84:AL84) -> 3904.035 | AN84: =AN34*AN19/1000 -> 1055.136 | AO84: =AO34*AO19/1000 -> 1406.784 | AP84: =AP34*AP19/1000 -> 1285.992 | AQ84: =AQ34*AQ19/1000 -> 641.268 | AR84: =(AR34+AR35)*AR19/1000-AR85 -> 4379.9955 | AS84: =(AS34+AS35)*AS19/1000-AS85 -> 494.373 | AT84: =(AT34+AT35)*AT19/1000-AT85 -> 493.884 | AU84: =(AU34+AU35)*AU19/1000-AU85 -> 546.417 | AV84: =(AV34+AV35)*AV19/1000-AV85 -> 507.715 | AW84: =(AW34+AW35)*AW19/1000-AW85 -> 2053.1067 | AX84: =(AX34+AX35)*AX19/1000-AX85 -> 635.922 | AY84: =(AY34+AY35)*AY19/1000-AY85 -> 636.682 | ... CZ84: =(CZ34+CZ35)*CZ19/1000-CZ85 -> 3188.8745
B85: SBQ | BB85: =BB35*BB9/1000 -> 0 | BC85: =BC35*BC9/1000 -> 294.91875 | BD85: =BD35*BD9/1000 -> 318.41833 | BE85: =BE35*BE9/1000 -> 322.68542 | BF85: =BF35*BF9/1000 -> 323.60417 | BG85: =BG35*BG9/1000 -> 1259.6267 | BH85: =BH35*BH9/1000 -> 334.99667 | BI85: =BI35*BI9/1000 -> 312.7425 | ... CZ85: =CZ35*CZ9/1000 -> 1280
B86: Structural | S86: 1005.859 | X86: 1500.878 | Y86: =Y36*Y20/1000 -> 396.275 | Z86: =Z36*Z20/1000 -> 392.042 | AA86: =AA36*AA20/1000 -> 423.555 | AB86: =AB36*AB20/1000 -> 490.082 | AC86: =SUM(Y86:AB86) -> 1701.954 | AD86: =AD36*AD20/1000 -> 495.187 | AE86: =AE36*AE20/1000 -> 540.27 | AF86: =AF36*AF20/1000 -> 577.866 | AG86: =AG36*AG20/1000 -> 591.778 | AH86: =SUM(AD86:AG86) -> 2205.101 | AI86: =AI36*AI20/1000 -> 576.81 | AJ86: =AJ36*AJ20/1000 -> 669.075 | AK86: =AK36*AK20/1000 -> 655.259 | AL86: =AL36*AL20/1000 -> 690.999 | AM86: =SUM(AI86:AL86) -> 2592.143 | AN86: =AN36*AN20/1000 -> 721.68 | AO86: =AO36*AO20/1000 -> 858.825 | AP86: =AP36*AP20/1000 -> 943.154 | AQ86: =AQ36*AQ20/1000 -> 571.135 | AR86: =AR36*AR20/1000 -> 3104.9055 | AS86: =AS36*AS20/1000 -> 323.945 | AT86: =AT36*AT20/1000 -> 284.599 | AU86: =AU36*AU20/1000 -> 370.476 | ... CZ86: =CZ36*CZ20/1000 -> 1674.8255
B87: Plate | S87: 321.852 | X87: 1119.117 | Y87: =Y37*Y21/1000 -> 450.933 | Z87: =Z37*Z21/1000 -> 347.628 | AA87: =AA37*AA21/1000 -> 331.875 | AB87: =AB37*AB21/1000 -> 363.888 | AC87: =SUM(Y87:AB87) -> 1494.324 | AD87: =AD37*AD21/1000 -> 435.552 | AE87: =AE37*AE21/1000 -> 434.32 | AF87: =AF37*AF21/1000 -> 455.806 | AG87: =AG37*AG21/1000 -> 431.88 | AH87: =SUM(AD87:AG87) -> 1757.558 | AI87: =AI37*AI21/1000 -> 428.125 | AJ87: =AJ37*AJ21/1000 -> 449.787 | AK87: =AK37*AK21/1000 -> 485.804 | AL87: =AL37*AL21/1000 -> 446.875 | AM87: =SUM(AI87:AL87) -> 1810.591 | AN87: =AN37*AN21/1000 -> 525.7 | AO87: =AO37*AO21/1000 -> 639.918 | AP87: =AP37*AP21/1000 -> 873.942 | AQ87: =AQ37*AQ21/1000 -> 487.72 | AR87: =AR37*AR21/1000 -> 2548.2 | AS87: =AS37*AS21/1000 -> 257.04 | AT87: =AT37*AT21/1000 -> 169.104 | AU87: =AU37*AU21/1000 -> 267.51 | ... CZ87: =CZ37*CZ21/1000 -> 1957.3599
B88: Others | AN88: =AN89-SUM(AN83:AN87) -> -2.323 | AO88: =AO89-SUM(AO83:AO87) -> -0.55 | AP88: =AP89-SUM(AP83:AP87) -> -3.806 | AQ88: =AQ89-SUM(AQ83:AQ87) -> -1.171 | AR88: =AR89-SUM(AR83:AR87) -> -77.046 | AS88: =AS89-SUM(AS83:AS87) -> -2.888 | AT88: =AT89-SUM(AT83:AT87) -> -0.337 | AU88: =AU89-SUM(AU83:AU87) -> -1.601 | ... CG88: =CG89-SUM(CG83:CG87) -> 136.496 | CH88: =CH89-SUM(CH83:CH87)-CH160 -> 169.004 | CI88: =CI89-SUM(CI83:CI87)-CI160 -> 177.821 | CJ88: =CJ89-SUM(CJ83:CJ87) -> 388.749 | CK88: =SUM(CG88:CJ88) -> 872.07 | CL88: =+CL90*(CL84+CL85) -> 392.2776 | CM88: =+CM90*(CM84+CM85) -> 405.75282 | CN88: =+CN90*(CN84+CN85) -> 413.98406 | CO88: =+CO90*(CO84+CO85) -> 414.63584 | CP88: =SUM(CL88:CO88) -> 1626.6503 | CQ88: =+CQ90*(CQ84+CQ85) -> 453.16808 | CR88: =+CR90*(CR84+CR85) -> 419.86103 | CS88: =+CS90*(CS84+CS85) -> 407.53448 | CT88: =+CT90*(CT84+CT85) -> 392.0799 | CU88: =SUM(CQ88:CT88) -> 1672.6435 | CV88: =+CV90*(CV84+CV85) -> 440.21454 | CW88: =+CW90*(CW84+CW85) -> 395.44977 | CX88: =+CX90*(CX84+CX85) -> 388.00544 | CY88: =+CY90*(CY84+CY85) -> 385.9422 | CZ88: =SUM(CV88:CY88) -> 1609.612
B89: SEGMENT REVENUE | H89: 3614.1825 | I89: 3449.6456 | J89: 927.03875 | K89: 1015.8046 | L89: 1022.3575 | M89: 1097.3886 | N89: =SUM(J89:M89) -> 4062.5894 | O89: 1297.8795 | P89: 1320.3027 | Q89: 1383.8596 | R89: 1444.0852 | S89: =SUM(O89:R89) -> 5446.127 | T89: 2064.069 | U89: 2461.074 | V89: 2868.483 | W89: 2715.804 | X89: =SUM(T89:W89) -> 10109.43 | Y89: 2950 | Z89: 2716.677 | AA89: 2605.942 | AB89: 2791.062 | AC89: =SUM(Y89:AB89) -> 11063.681 | AD89: =6537.494-AE89 -> 3149.426 | AE89: =3388.068 -> 3388.068 | AF89: 3469.443 | AG89: =AH89-SUM(AD89:AF89) -> 3018.186 | AH89: 13025.123 | AI89: =6609.41-AJ89 -> 3273.254 | AJ89: =3336.156 -> 3336.156 | AK89: 3344.116 | AL89: =AM89-SUM(AI89:AK89) -> 3357.686 | AM89: 13311.212 | AN89: 3759.453 | AO89: 4893.137 | AP89: 5192.082 | AQ89: =AR89-SUM(AN89:AP89) -> 2633.228 | AR89: 16477.9 | AS89: 1656.24 | AT89: 1429.284 | AU89: 2070.202 | AV89: =AW89-SUM(AS89:AU89) -> 2003.786 | AW89: 7159.512 | AX89: 2612.016 | AY89: 2875.338 | AZ89: 2798.419 | BA89: =BB89-SUM(AX89:AZ89) -> 2574.987 | BB89: 10860.76 | BC89: 3448.197 | BD89: 3569.786 | BE89: 3617.867 | BF89: =BG89-SUM(BC89:BE89) -> 3324.395 | BG89: 13960.245 | BH89: 3626.139 | BI89: 3476.661 | BJ89: 3204.898 | BK89: =BL89-SUM(BH89:BJ89) -> 3010.282 | BL89: 13317.98 | BM89: 3268.154 | BN89: 3197.433 | BO89: 3435.884 | BP89: =BQ89-SUM(BM89:BO89) -> 3410.477 | BQ89: 13311.948 | BR89: 3607.764 | BS89: 3674.14 | BT89: 3898.031 | BU89: =BV89-SUM(BR89:BT89) -> 3543.707 | BV89: 14723.642 | BW89: 3053.339 | BX89: 2968.644 | BY89: 2816.441 | BZ89: =CA89-SUM(BW89:BY89) -> 2245.907 | CA89: 11084.331 | CB89: 2634.589 | CC89: 3016.322 | CD89: 2960.642 | CE89: =CF89-SUM(CB89:CD89)-CE160 -> 2640.061 | CF89: 11312.048 | CG89: =3542.789-CG160 -> 3329.824 | CH89: 3800.359 | CI89: 3639.488 | CJ89: =CK89-SUM(CG89:CI89)-CJ160 -> 3507.201 | CK89: 14508.847 | CL89: =SUM(CL83:CL88) -> 3985.8976 | CM89: =SUM(CM83:CM88) -> 4631.6162 | CN89: =SUM(CN83:CN88) -> 4560.5658 | CO89: =SUM(CO83:CO88) -> 4406.316 | CP89: =SUM(CL89:CO89) -> 17584.395 | CQ89: =SUM(CQ83:CQ88) -> 4813.4448 | CR89: =SUM(CR83:CR88) -> 4791.0552 | CS89: =SUM(CS83:CS88) -> 4473.3609 | CT89: =SUM(CT83:CT88) -> 4219.1407 | CU89: =SUM(CQ89:CT89) -> 18297.002 | CV89: =SUM(CV83:CV88) -> 4619.5255 | CW89: =SUM(CW83:CW88) -> 4581.8362 | CX89: =SUM(CX83:CX88) -> 4252.304 | CY89: =SUM(CY83:CY88) -> 4132.8834 | CZ89: =SUM(CV89:CY89) -> 17586.549
B90: Others, as a % of bar revenue | BC90: =BC88/SUM(BC84:BC85) -> -0.04455275 | BD90: =BD88/SUM(BD84:BD85) -> -0.041860309 | BE90: =BE88/SUM(BE84:BE85) -> 0.065671022 | BF90: =BF88/SUM(BF84:BF85) -> -0.0071999444 | BG90: =BG88/SUM(BG84:BG85) -> -0.0055820641 | BH90: =BH88/SUM(BH84:BH85) -> -0.15146902 | BI90: =BI88/SUM(BI84:BI85) -> -0.12640513 | BJ90: =BJ88/SUM(BJ84:BJ85) -> -0.1245474 | ... CK90: =CK88/SUM(CK84:CK85) -> 0.24528442 | CL90: 0.36 | CM90: 0.36 | CN90: 0.36 | CO90: 0.36 | CP90: =CP88/SUM(CP84:CP85) -> 0.35928588 | CQ90: 0.36 | CR90: 0.36 | CS90: 0.36 | CT90: 0.36 | CU90: =CU88/SUM(CU84:CU85) -> 0.36008439 | CV90: 0.36 | CW90: 0.36 | CX90: 0.36 | CY90: 0.36 | CZ90: =CZ88/SUM(CZ84:CZ85) -> 0.36018285
C92: Steel Revenue per ton | H92: =+H22 -> 369.58611 | I92: =+I22 -> 312.69449 | J92: =+J22 -> 306.66184 | K92: =+K22 -> 324.22745 | L92: =L22 -> 345.15783 | M92: =M22 -> 343.36313 | N92: =N22 -> 329.91631 | O92: =O22 -> 321.2573 | P92: =P22 -> 334.00018 | Q92: =Q22 -> 332.49871 | R92: =R22 -> 351.52998 | S92: =S22 -> 334.87837 | ... AM92: =AM22 -> 659.70528 | AN92: =+AN22 -> 723.00135 | AO92: =+AO22 -> 907.24638 | AP92: =+AP22 -> 1108.3379 | AQ92: =+AQ22 -> 908.41345 | AR92: =+AR22 -> 910.36272 | AS92: =+AS22 -> 681.92684 | AT92: =+AT22 -> 556.4893 | AU92: =+AU22 -> 559.19109 | ... BF92: =+BF22 -> 806.20474 | BG92: =AVERAGE(BC92:BF92) -> 833.27106 | BH92: =+BH22 -> 824.25577 | BI92: =+BI22 -> 811.37626 | BJ92: =+BJ22 -> 771.67007 | BK92: =+BK22 -> 750.03276 | BL92: =AVERAGE(BH92:BK92) -> 789.33372 | BM92: =+BM22 -> 756.03946 | BN92: =+BN22 -> 745.53346 | BO92: =+BO22 -> 741.29203 | BP92: =+BP22 -> 762.87848 | BQ92: =AVERAGE(BM92:BP92) -> 751.43586 | BR92: =+BR22 -> 782.6037 | BS92: =+BS22 -> 789.32372 | BT92: =+BT22 -> 804.63368 | BU92: =+BU22 -> 775.61497 | BV92: =AVERAGE(BR92:BU92) -> 788.04402 | BW92: =+BW22 -> 732.07035 | BX92: =+BX22 -> 645.32329 | BY92: =+BY22 -> 635.09302 | BZ92: =+BZ22 -> 587.51216 | CA92: =AVERAGE(BW92:BZ92) -> 649.9997 | CB92: =+CB22 -> 537.6091 | CC92: =+CC22 -> 593.37584 | CD92: =+CD22 -> 663.7084 | CE92: =+CE22 -> 614.37636 | CF92: =AVERAGE(CB92:CE92) -> 602.26743 | CG92: =+CG22 -> 657.06337 | CH92: =+CH22 -> 687.51919 | CI92: =+CI22 -> 684.86356 | CJ92: =+CJ22 -> 673.67725 | CK92: =AVERAGE(CG92:CJ92) -> 675.78084 | CL92: =+CL22 -> 716.43142 | CM92: =+CM22 -> 837.22241 | CN92: =+CN22 -> 865.81747 | CO92: =+CO22 -> 845.92614 | CP92: =AVERAGE(CL92:CO92) -> 816.34936 | CQ92: =+CQ22 -> 853.56374 | CR92: =+CR22 -> 850.3558 | CS92: =+CS22 -> 833.67464 | CT92: =+CT22 -> 796.46072 | CU92: =AVERAGE(CQ92:CT92) -> 833.51373 | CV92: =+CV22 -> 751.46145 | CW92: =+CW22 -> 750.71097 | CX92: =+CX22 -> 728.89358 | CY92: =+CY22 -> 716.65978 | CZ92: =AVERAGE(CV92:CY92) -> 736.93145
C93: Scrap cost per ton | H93: =H77 -> 120 | I93: =I77 -> 101 | J93: =J77 -> 96 | K93: =K77 -> 107 | L93: =L77 -> 118 | M93: =M77 -> 118 | N93: =N77 -> 110 | O93: =O77 -> 122 | ... BF93: =BF77 -> 441 | BG93: =AVERAGE(BC93:BF93) -> 439.5 | BH93: =BH77 -> 445 | BI93: =BI77 -> 427 | BJ93: =BJ77 -> 380 | BK93: =BK77 -> 372 | BL93: =AVERAGE(BH93:BK93) -> 406 | BM93: =BM77 -> 379 | BN93: =BN77 -> 377 | BO93: =BO77 -> 372 | BP93: =BP77 -> 377 | BQ93: =AVERAGE(BM93:BP93) -> 376.25 | BR93: =BR77 -> 398 | BS93: =BS77 -> 384 | BT93: =BT77 -> 379 | BU93: =BU77 -> 363 | BV93: =AVERAGE(BR93:BU93) -> 381 | BW93: =BW77 -> 324 | BX93: =BX77 -> 271 | BY93: =BY77 -> 262 | BZ93: =BZ77 -> 219 | CA93: =AVERAGE(BW93:BZ93) -> 269 | CB93: =CB77 -> 193 | CC93: =CC77 -> 232 | CD93: =CD77 -> 252 | CE93: =CE77 -> 236 | CF93: =AVERAGE(CB93:CE93) -> 228.25 | CG93: =CG77 -> 284 | CH93: =CH77 -> 313 | CI93: =CI77 -> 317 | CJ93: =CJ77 -> 317 | CK93: =AVERAGE(CG93:CJ93) -> 307.75 | CL93: =CL77 -> 337 | CM93: =CM77 -> 359.985 | CN93: =CN77 -> 367.78107 | CO93: =CO77 -> 366.53974 | CP93: =AVERAGE(CL93:CO93) -> 357.82645 | CQ93: =CQ77 -> 369.72115 | CR93: =CR77 -> 373.57408 | CS93: =CS77 -> 371.94658 | CT93: =CT77 -> 367.56821 | CU93: =AVERAGE(CQ93:CT93) -> 370.7025 | CV93: =CV77 -> 353.20309 | CW93: =CW77 -> 346.61584 | CX93: =CX77 -> 338.77642 | CY93: =CY77 -> 328.23197 | CZ93: =AVERAGE(CV93:CY93) -> 341.70683
C94: Metal Spread | H94: =H92-H93 -> 249.58611 | I94: =I92-I93 -> 211.69449 | J94: =J92-J93 -> 210.66184 | K94: =K92-K93 -> 217.22745 | L94: =L92-L93 -> 227.15783 | M94: =M92-M93 -> 225.36313 | N94: =N92-N93 -> 219.91631 | O94: =O92-O93 -> 199.2573 | ... AM94: =AM92-AM93 -> 381.70528 | AN94: =AN22-AN77 -> 390.00135 | AO94: =AO22-AO77 -> 451.24638 | AP94: =AP22-AP77 -> 575.33788 | AQ94: =AQ92-AQ93 -> 473.41345 | AR94: =AR92-AR93 -> 471.11272 | AS94: =AS92-AS93 -> 348.92684 | AT94: =AT92-AT93 -> 244.4893 | AU94: =AU92-AU93 -> 260.19109 | AV94: =AV92-AV93 -> 319.19418 | AW94: =AW92-AW93 -> 291.78077 | AX94: =AX92-AX93 -> 324.97664 | ... BF94: =BF92-BF93 -> 365.20474 | BG94: =AVERAGE(BC94:BF94) -> 393.77106 | BH94: =BH92-BH93 -> 379.25577 | BI94: =BI92-BI93 -> 384.37626 | BJ94: =BJ92-BJ93 -> 391.67007 | BK94: =BK92-BK93 -> 378.03276 | BL94: =AVERAGE(BH94:BK94) -> 383.33372 | BM94: =BM92-BM93 -> 377.03946 | BN94: =BN92-BN93 -> 368.53346 | BO94: =BO92-BO93 -> 369.29203 | BP94: =BP92-BP93 -> 385.87848 | BQ94: =AVERAGE(BM94:BP94) -> 375.18586 | BR94: =BR92-BR93 -> 384.6037 | BS94: =BS92-BS93 -> 405.32372 | BT94: =BT92-BT93 -> 425.63368 | BU94: =BU92-BU93 -> 412.61497 | BV94: =AVERAGE(BR94:BU94) -> 407.04402 | BW94: =BW92-BW93 -> 408.07035 | BX94: =BX92-BX93 -> 374.32329 | BY94: =BY92-BY93 -> 373.09302 | BZ94: =BZ92-BZ93 -> 368.51216 | CA94: =AVERAGE(BW94:BZ94) -> 380.9997 | CB94: =CB92-CB93 -> 344.6091 | CC94: =CC92-CC93 -> 361.37584 | CD94: =CD92-CD93 -> 411.7084 | CE94: =CE92-CE93 -> 378.37636 | CF94: =AVERAGE(CB94:CE94) -> 374.01743 | CG94: =CG92-CG93 -> 373.06337 | CH94: =CH92-CH93 -> 374.51919 | CI94: =CI92-CI93 -> 367.86356 | CJ94: =CJ92-CJ93 -> 356.67725 | CK94: =AVERAGE(CG94:CJ94) -> 368.03084 | CL94: =CL92-CL93 -> 379.43142 | CM94: =CM92-CM93 -> 477.23741 | CN94: =CN92-CN93 -> 498.0364 | CO94: =CO92-CO93 -> 479.3864 | CP94: =AVERAGE(CL94:CO94) -> 458.52291 | CQ94: =CQ92-CQ93 -> 483.84259 | CR94: =CR92-CR93 -> 476.78172 | CS94: =CS92-CS93 -> 461.72806 | CT94: =CT92-CT93 -> 428.89251 | CU94: =AVERAGE(CQ94:CT94) -> 462.81122 | CV94: =CV92-CV93 -> 398.25836 | CW94: =CW92-CW93 -> 404.09513 | CX94: =CX92-CX93 -> 390.11716 | CY94: =CY92-CY93 -> 388.42781 | CZ94: =AVERAGE(CV94:CY94) -> 395.22462
C95: EBTDA per Ton | H95: =H102/H38*1000 -> 82.887398 | I95: =I102/I38*1000 -> 43.634309 | J95: =J102/J38*1000 -> 49.783908 | K95: =K102/K38*1000 -> 56.093032 | L95: =L102/L38*1000 -> 120.82654 | M95: =M102/M38*1000 -> 2.0572848 | N95: =N102/N38*1000 -> 56.090588 | O95: =O102/O38*1000 -> 34.926349 | ... BF95: =BF102/BF38*1000 -> 101.96394 | BG95: =AVERAGE(BC95:BF95) -> 124.39805 | BH95: =BH102/BH38*1000 -> 105.40109 | BI95: =BI102/BI38*1000 -> 96.559901 | BJ95: =BJ102/BJ38*1000 -> 72.09112 | BK95: =BK102/BK38*1000 -> 75.498665 | BL95: =AVERAGE(BH95:BK95) -> 87.387694 | BM95: =BM102/BM38*1000 -> 82.787321 | BN95: =BN102/BN38*1000 -> 75.723971 | BO95: =BO102/BO38*1000 -> 85.589062 | BP95: =BP102/BP38*1000 -> 94.382664 | BQ95: =AVERAGE(BM95:BP95) -> 84.620755 | BR95: =BR102/BR38*1000 -> 91.794837 | BS95: =BS102/BS38*1000 -> 99.784169 | BT95: =BT102/BT38*1000 -> 125.88379 | BU95: =BU102/BU38*1000 -> 109.33099 | BV95: =AVERAGE(BR95:BU95) -> 106.69845 | BW95: =BW102/BW38*1000 -> 76.14964 | BX95: =BX102/BX38*1000 -> 65.210845 | BY95: =BY102/BY38*1000 -> 81.263795 | BZ95: =BZ102/BZ38*1000 -> 53.854891 | CA95: =AVERAGE(BW95:BZ95) -> 69.119793 | CB95: =CB102/CB38*1000 -> 77.538579 | CC95: =CC102/CC38*1000 -> 124.11521 | CD95: =CD102/CD38*1000 -> 155.24647 | CE95: =CE102/CE38*1000 -> 87.473523 | CF95: =AVERAGE(CB95:CE95) -> 111.09345 | CG95: =CG102/CG38*1000 -> 156.01235 | CH95: =CH102/CH38*1000 -> 140.68747 | CI95: =CI102/CI38*1000 -> 108.9304 | CJ95: =CJ102/CJ38*1000 -> 92.675524 | CK95: =AVERAGE(CG95:CJ95) -> 124.57644 | CL95: =CL102/CL38*1000 -> 131.67923 | CM95: =+CM94-CM96 -> 189.27407 | CN95: =+CN94-CN96 -> 203.0364 | CO95: =+CO94-CO96 -> 184.3864 | CP95: =AVERAGE(CL95:CO95) -> 177.09402 | CQ95: =+CQ94-CQ96 -> 188.84259 | CR95: =+CR94-CR96 -> 181.78172 | CS95: =+CS94-CS96 -> 166.72806 | CT95: =+CT94-CT96 -> 133.89251 | CU95: =AVERAGE(CQ95:CT95) -> 167.81122 | CV95: =+CV94-CV96 -> 138.25836 | CW95: =+CW94-CW96 -> 144.09513 | CX95: =+CX94-CX96 -> 130.11716 | CY95: =+CY94-CY96 -> 128.42781 | CZ95: =AVERAGE(CV95:CY95) -> 135.22462
C96: Realized Non Metal Cost, $/t | J96: =J94-J95 -> 160.87793 | K96: =K94-K95 -> 161.13442 | L96: =L94-L95 -> 106.3313 | M96: =M94-M95 -> 223.30585 | N96: =N94-N95 -> 163.82572 | O96: =O94-O95 -> 164.33095 | P96: =P94-P95 -> 167.19156 | Q96: =Q94-Q95 -> 161.63159 | ... BF96: =BF94-BF95 -> 263.2408 | BG96: =AVERAGE(BC96:BF96) -> 269.37301 | BH96: =BH94-BH95 -> 273.85468 | BI96: =BI94-BI95 -> 287.81636 | BJ96: =BJ94-BJ95 -> 319.57895 | BK96: =BK94-BK95 -> 302.53409 | BL96: =AVERAGE(BH96:BK96) -> 295.94602 | BM96: =BM94-BM95 -> 294.25213 | BN96: =BN94-BN95 -> 292.80949 | BO96: =BO94-BO95 -> 283.70296 | BP96: =BP94-BP95 -> 291.49582 | BQ96: =AVERAGE(BM96:BP96) -> 290.5651 | BR96: =BR94-BR95 -> 292.80886 | BS96: =BS94-BS95 -> 305.53955 | BT96: =BT94-BT95 -> 299.7499 | BU96: =BU94-BU95 -> 303.28398 | BV96: =AVERAGE(BR96:BU96) -> 300.34557 | BW96: =BW94-BW95 -> 331.92071 | BX96: =BX94-BX95 -> 309.11244 | BY96: =BY94-BY95 -> 291.82922 | BZ96: =BZ94-BZ95 -> 314.65727 | CA96: =AVERAGE(BW96:BZ96) -> 311.87991 | CB96: =CB94-CB95 -> 267.07052 | CC96: =CC94-CC95 -> 237.26063 | CD96: =CD94-CD95 -> 256.46193 | CE96: =CE94-CE95 -> 290.90284 | CF96: =AVERAGE(CB96:CE96) -> 262.92398 | CG96: =CG94-CG95 -> 217.05103 | CH96: =CH94-CH95 -> 233.83172 | CI96: =CI94-CI95 -> 258.93316 | CJ96: =CJ94-CJ95 -> 264.00173 | CK96: =AVERAGE(CG96:CJ96) -> 243.45441 | CL96: =CL94-CL95 -> 247.75219 | CM96: =CM98+CM97 -> 287.96334 | CN96: =CN98+CN97 -> 295 | CO96: =CO98+CO97 -> 295 | CP96: =AVERAGE(CL96:CO96) -> 281.42888 | CQ96: =CQ98+CQ97 -> 295 | CR96: =CR98+CR97 -> 295 | CS96: =CS98+CS97 -> 295 | CT96: =CT98+CT97 -> 295 | CU96: =AVERAGE(CQ96:CT96) -> 295 | CV96: =CV98+CV97 -> 260 | CW96: =CW98+CW97 -> 260 | CX96: =CX98+CX97 -> 260 | CY96: =CY98+CY97 -> 260 | CZ96: =AVERAGE(CV96:CY96) -> 260
C97: Additional Costs, $/t | BC97: =+BC96-BC98 -> 23.825413 | BD97: =+BD96-BD98 -> -32.508594 | BE97: =+BE96-BE98 -> -2.762447 | BF97: =+BF96-BF98 -> -11.952927 | BG97: =AVERAGE(BC97:BF97) -> -5.8496385 | BH97: =+BH96-BH98 -> 16.233086 | BI97: =+BI96-BI98 -> 5.2312681 | BJ97: =+BJ96-BJ98 -> 25.466409 | BK97: =+BK96-BK98 -> -12.856244 | BL97: =AVERAGE(BH97:BK97) -> 8.51863 | BM97: =+BM96-BM98 -> 2.2946699 | BN97: =+BN96-BN98 -> 1.0753592 | BO97: =+BO96-BO98 -> 4.2720547 | BP97: =+BP96-BP98 -> 1.2525022 | BQ97: =AVERAGE(BM97:BP97) -> 2.2236465 | BR97: =+BR96-BR98 -> 4.0774518 | BS97: =+BS96-BS98 -> 9.5562631 | BT97: =+BT96-BT98 -> -5.813688 | BU97: =+BU96-BU98 -> -6.7173848 | BV97: =AVERAGE(BR97:BU97) -> 0.27566052 | BW97: =+BW96-BW98 -> 16.208335 | BX97: =+BX96-BX98 -> 2.2538601 | BY97: =+BY96-BY98 -> -13.368804 | BZ97: =+BZ96-BZ98 -> 10.266528 | CA97: =AVERAGE(BW97:BZ97) -> 3.8399799 | CB97: =+CB96-CB98 -> -0.037643979 | CC97: =+CC96-CC98 -> -27.644816 | CD97: =+CD96-CD98 -> -16.419354 | CE97: =+CE96-CE98 -> 23.885308 | CF97: =AVERAGE(CB97:CE97) -> -5.0541264 | CG97: =+CG96-CG98 -> -59.667785 | CH97: =+CH96-CH98 -> -0.44122058 | CI97: =+CI96-CI98 -> 6.1623474 | CJ97: =+CJ96-CJ98 -> -0.06227458 | CK97: =AVERAGE(CG97:CJ97) -> -13.502233 | CL97: =+CL96-CL98 -> -13.582701 | CM97: 8 | CN97: =IF(CN98<295,0,295-CN98) -> -24.774127 | CO97: =IF(CO98<295,0,295-CO98) -> -21.534103 | CP97: =AVERAGE(CL97:CO97) -> -12.972733 | CQ97: =IF(CQ98<295,0,295-CQ98) -> -11.317473 | CR97: =IF(CR98<295,0,295-CR98) -> -18.550555 | CS97: =IF(CS98<295,0,295-CS98) -> -21.885207 | CT97: =IF(CT98<295,0,295-CT98) -> -10.529212 | CU97: =AVERAGE(CQ97:CT97) -> -15.570612 | CV97: =IF(CV98<260,0,260-CV98) -> -19.050183 | CW97: =IF(CW98<260,0,260-CW98) -> -13.162889 | CX97: =IF(CX98<260,0,260-CX98) -> -16.095924 | CY97: =IF(CY98<260,0,260-CY98) -> -11.64627 | CZ97: =AVERAGE(CV97:CY97) -> -14.988817
C98: Calculated Non Metal Cost, $/t | BC98: =BA96*0.713+BC94*0.218-115*(BC38/BA38-1) -> 249.32307 | BD98: =BC96*0.713+BD94*0.218-115*(BD38/BC38-1) -> 301.69122 | BE98: =BD96*0.713+BE94*0.218-115*(BE38/BD38-1) -> 274.68257 | BF98: =BE96*0.713+BF94*0.218-115*(BF38/BE38-1) -> 275.19373 | BG98: =AVERAGE(BC98:BF98) -> 275.22265 | BH98: =BF96*0.713+BH94*0.218-115*(BH38/BF38-1) -> 257.6216 | BI98: =BH96*0.713+BI94*0.218-115*(BI38/BH38-1) -> 282.5851 | BJ98: =BI96*0.713+BJ94*0.218-115*(BJ38/BI38-1) -> 294.11254 | BK98: =BJ96*0.713+BK94*0.218-115*(BK38/BJ38-1) -> 315.39034 | BL98: =AVERAGE(BH98:BK98) -> 287.42739 | BM98: =BK96*0.713+BM94*0.218-115*(BM38/BK38-1) -> 291.95746 | BN98: =BM96*0.713+BN94*0.218-115*(BN38/BM38-1) -> 291.73413 | BO98: =BN96*0.713+BO94*0.218-115*(BO38/BN38-1) -> 279.43091 | BP98: =BO96*0.713+BP94*0.218-115*(BP38/BO38-1) -> 290.24332 | BQ98: =AVERAGE(BM98:BP98) -> 288.34145 | BR98: =BP96*0.713+BR94*0.218-115*(BR38/BP38-1) -> 288.73141 | BS98: =BR96*0.713+BS94*0.218-115*(BS38/BR38-1) -> 295.98329 | BT98: =BS96*0.713+BT94*0.218-115*(BT38/BS38-1) -> 305.56358 | BU98: =BT96*0.713+BU94*0.218-115*(BU38/BT38-1) -> 310.00136 | BV98: =AVERAGE(BR98:BU98) -> 300.06991 | BW98: =BU96*0.713+BW94*0.218-115*(BW38/BU38-1) -> 315.71237 | BX98: =BW96*0.713+BX94*0.218-115*(BX38/BW38-1) -> 306.85858 | BY98: =BX96*0.713+BY94*0.218-115*(BY38/BX38-1) -> 305.19803 | BZ98: =BY96*0.713+BZ94*0.218-115*(BZ38/BY38-1) -> 304.39074 | CA98: =AVERAGE(BW98:BZ98) -> 308.03993 | CB98: =BZ96*0.713+CB94*0.218-115*(CB38/BZ38-1) -> 267.10817 | CC98: =CB96*0.713+CC94*0.218-115*(CC38/CB38-1) -> 264.90544 | CD98: =CC96*0.713+CD94*0.218-115*(CD38/CC38-1) -> 272.88128 | CE98: =CD96*0.713+CE94*0.218-115*(CE38/CD38-1) -> 267.01753 | CF98: =AVERAGE(CB98:CE98) -> 267.97811 | CG98: =CE96*0.713+CG94*0.218-115*(CG38/CE38-1) -> 276.71881 | CH98: =CG96*0.713+CH94*0.218-115*(CH38/CG38-1) -> 234.27294 | CI98: =CH96*0.713+CI94*0.218-115*(CI38/CH38-1) -> 252.77082 | CJ98: =CI96*0.713+CJ94*0.218-115*(CJ38/CI38-1) -> 264.064 | CK98: =AVERAGE(CG98:CJ98) -> 256.95664 | CL98: =CJ96*0.713+CL94*0.218-115*(CL38/CJ38-1) -> 261.33489 | CM98: =CL96*0.713+CM94*0.218-115*(CM38/CL38-1) -> 279.96334 | CN98: =CM96*0.713+CN94*0.218-115*(CN38/CM38-1) -> 319.77413 | CO98: =CN96*0.713+CO94*0.218-115*(CO38/CN38-1) -> 316.5341 | CP98: =AVERAGE(CL98:CO98) -> 294.40162 | CQ98: =CO96*0.713+CQ94*0.218-115*(CQ38/CO38-1) -> 306.31747 | CR98: =CQ96*0.713+CR94*0.218-115*(CR38/CQ38-1) -> 313.55055 | CS98: =CR96*0.713+CS94*0.218-115*(CS38/CR38-1) -> 316.88521 | CT98: =CS96*0.713+CT94*0.218-115*(CT38/CS38-1) -> 305.52921 | CU98: =AVERAGE(CQ98:CT98) -> 310.57061 | CV98: =CT96*0.713+CV94*0.218-115*(CV38/CT38-1) -> 279.05018 | CW98: =CV96*0.713+CW94*0.218-115*(CW38/CV38-1) -> 273.16289 | CX98: =CW96*0.713+CX94*0.218-115*(CX38/CW38-1) -> 276.09592 | CY98: =CX96*0.713+CY94*0.218-115*(CY38/CX38-1) -> 271.64627 | CZ98: =AVERAGE(CV98:CY98) -> 274.98882
B100: SEGMENT PROFIT (EBIT) | H100: 562.4161 | I100: 207.35815 | J100: 78.27694 | K100: 103.51966 | L100: 285.66838 | M100: -65.644732 | N100: =SUM(J100:M100) -> 401.82025 | O100: 54.568451 | P100: =47.817481+7.2 -> 55.017481 | Q100: 54.420944 | R100: =S100-O100-P100-Q100 -> 45.393124 | S100: 209.4 | T100: 235.267 | U100: 532.748 | V100: 795.434 | W100: =X100-T100-U100-V100 -> 627.886 | X100: 2191.335 | Y100: 658.135 | Z100: 524.239 | AA100: 488.892 | AB100: =AC100-Y100-Z100-AA100 -> 536.355 | AC100: 2207.621 | AD100: 731.438 | AE100: 836.913 | AF100: 905.595 | AG100: =AH100-SUM(AD100:AF100) -> 720.714 | AH100: 3194.66 | AI100: 735.329 | AJ100: =667.465 -> 667.465 | AK100: 744.51 | AL100: =AM100-SUM(AI100:AK100) -> 706.848 | AM100: 2854.152 | AN100: 799.284 | AO100: 1040.582 | AP100: 1223.035 | AQ100: =AR100-SUM(AN100:AP100) -> 541.88 | AR100: 3604.781 | AS100: -223.875 | AT100: -205.426 | AU100: -55.914 | AV100: =AW100-SUM(AS100:AU100) -> 134.843 | AW100: -350.372 | AX100: 158.5 | AY100: 262.147 | AZ100: 231.803 | BA100: =BB100-SUM(AX100:AZ100) -> 126.496 | BB100: 778.946 | BC100: 312.578 | BD100: 626.84 | BE100: 436.196 | BF100: =BG100-SUM(BC100:BE100) -> 328.319 | BG100: 1703.933 | BH100: 390.292 | BI100: 336.096 | BJ100: 217.43 | BK100: =BL100-SUM(BH100:BJ100) -> 217.631 | BL100: 1161.449 | BM100: 272.258 | BN100: 237.102 | BO100: 310.591 | BP100: =BQ100-SUM(BM100:BO100) -> 336.764 | BQ100: 1156.715 | BR100: =317.797+9 -> 326.797 | BS100: 368.138 | BT100: =502.703+12.5 -> 515.203 | BU100: =BV100-SUM(BR100:BT100) -> 405.714 | BV100: =1594.352+9+12.5 -> 1615.852 | BW100: 217.128 | BX100: 198.5 | BY100: 260.776 | BZ100: =CA100-SUM(BW100:BY100)+153 -> 105.852 | CA100: 629.256 | CB100: 279.835 | CC100: 530.727 | CD100: 593.149 | CE100: =CF100-SUM(CB100:CD100)-77.6+42 -> 284.857 | CF100: 1724.168 | CG100: 644.183 | CH100: =617.366-35 -> 582.366 | CI100: =432.718-35 -> 397.718 | CJ100: =349.958-35 -> 314.958 | CK100: =SUM(CG100:CJ100) -> 1939.225 | CL100: 560.503 | CM100: =+CM102-CM101 -> 855.35708 | CN100: =+CN102-CN101 -> 872.38394 | CO100: =+CO102-CO101 -> 770.06594 | CP100: =SUM(CL100:CO100) -> 3058.31 | CQ100: =+CQ102-CQ101 -> 864.66839 | CR100: =+CR102-CR101 -> 834.43615 | CS100: =+CS102-CS101 -> 713.13179 | CT100: =+CT102-CT101 -> 543.36478 | CU100: =SUM(CQ100:CT100) -> 2955.6011 | CV100: =+CV102-CV101 -> 668.93457 | CW100: =+CW102-CW101 -> 703.55548 | CX100: =+CX102-CX101 -> 589.82848 | CY100: =+CY102-CY101 -> 571.4643 | CZ100: =SUM(CV100:CY100) -> 2533.7828
C101: Depreciation and Amortization | H101: 248.13976 | I101: 274.01554 | J101: =K101 -> 72.219814 | K101: =L101 -> 72.219814 | L101: =M101 -> 72.219814 | M101: =N101/4 -> 72.219814 | N101: 288.87926 | O101: =P101 -> 86.534 | P101: =Q101 -> 86.534 | Q101: =R101 -> 86.534 | R101: =S101/4 -> 86.534 | S101: 346.136 | T101: =U101 -> 91.50575 | U101: =V101 -> 91.50575 | V101: =W101 -> 91.50575 | W101: =X101/4 -> 91.50575 | X101: 366.023 | Y101: =AC101/4 -> 88.97175 | Z101: =AC101/4 -> 88.97175 | AA101: =AC101/4 -> 88.97175 | AB101: =AC101/4 -> 88.97175 | AC101: 355.887 | AD101: =AE101 -> 86.29125 | AE101: =AF101 -> 86.29125 | AF101: =AH101/4 -> 86.29125 | AG101: =AH101/4 -> 86.29125 | AH101: 345.165 | AI101: =AJ101 -> 88.447895 | AJ101: =AK101 -> 88.447895 | AK101: =AM101/4 -> 88.447895 | AL101: =AM101/4 -> 88.447895 | AM101: 353.79158 | AN101: =AO101 -> 90.135 | AO101: =AP101 -> 90.135 | AP101: =AR101/4 -> 90.135 | AQ101: =AR101/4 -> 90.135 | AR101: =360.14+0.4 -> 360.54 | AS101: =AT101 -> 89.5305 | AT101: =AU101 -> 89.5305 | AU101: =AW101/4 -> 89.5305 | AV101: =AW101/4 -> 89.5305 | AW101: =357.722+0.4 -> 358.122 | AX101: =AY101 -> 92.68 | AY101: =AZ101 -> 92.68 | AZ101: =BB101/4 -> 92.68 | BA101: =BB101/4 -> 92.68 | BB101: =370.458+0.262 -> 370.72 | BC101: =BD101 -> 92.996 | BD101: =BE101 -> 92.996 | BE101: =BF101 -> 92.996 | BF101: =BG101/4 -> 92.996 | BG101: 371.984 | BH101: =BI101 -> 93.499 | BI101: =BJ101 -> 93.499 | BJ101: =BK101 -> 93.499 | BK101: =BL101/4 -> 93.499 | BL101: =366.117+7.879 -> 373.996 | BM101: =BN101 -> 86.54225 | BN101: =BO101 -> 86.54225 | BO101: =BP101 -> 86.54225 | BP101: =BQ101/4 -> 86.54225 | BQ101: =332.258+13.911 -> 346.169 | BR101: =BS101 -> 95.45925 | BS101: =BT101 -> 95.45925 | BT101: =BU101 -> 95.45925 | BU101: =BV101/4 -> 95.45925 | BV101: =366.568+15.269 -> 381.837 | BW101: =BX101 -> 100.03525 | BX101: =BY101 -> 100.03525 | BY101: =BZ101 -> 100.03525 | BZ101: =CA101/4 -> 100.03525 | CA101: =381.352+18.789 -> 400.141 | CB101: =CC101 -> 100.0265 | CC101: =CD101 -> 100.0265 | CD101: =CE101 -> 100.0265 | CE101: =CF101/4 -> 100.0265 | CF101: =377.627+22.479 -> 400.106 | CG101: =CH101 -> 114.037 | CH101: =CI101 -> 114.037 | CI101: =CJ101 -> 114.037 | CJ101: =CK101/4 -> 114.037 | CK101: =414.67+41.478 -> 456.148 | CL101: 100 | CM101: 100 | CN101: 100 | CO101: 100 | CP101: =SUM(CL101:CO101) -> 400 | CQ101: 100 | CR101: 100 | CS101: 100 | CT101: 100 | CU101: =SUM(CQ101:CT101) -> 400 | CV101: 100 | CW101: 100 | CX101: 100 | CY101: 100 | CZ101: =SUM(CV101:CY101) -> 400
C102: EBITDA | H102: =H100+H101 -> 810.55586 | I102: =I100+I101 -> 481.37369 | J102: =J100+J101 -> 150.49675 | K102: =K100+K101 -> 175.73947 | L102: =L100+L101 -> 357.8882 | M102: =M100+M101 -> 6.5750823 | N102: =N100+N101 -> 690.69951 | O102: =O100+O101 -> 141.10245 | ... CL102: =CL100+CL101 -> 660.503 | CM102: =+CM95*CM38/1000 -> 955.35708 | CN102: =+CN95*CN38/1000 -> 972.38394 | CO102: =+CO95*CO38/1000 -> 870.06594 | CP102: =CP100+CP101 -> 3458.31 | CQ102: =+CQ95*CQ38/1000 -> 964.66839 | CR102: =+CR95*CR38/1000 -> 934.43615 | CS102: =+CS95*CS38/1000 -> 813.13179 | CT102: =+CT95*CT38/1000 -> 643.36478 | CU102: =CU100+CU101 -> 3355.6011 | CV102: =+CV95*CV38/1000 -> 768.93457 | CW102: =+CW95*CW38/1000 -> 803.55548 | CX102: =+CX95*CX38/1000 -> 689.82848 | CY102: =+CY95*CY38/1000 -> 671.4643 | CZ102: =CZ100+CZ101 -> 2933.7828
B104: CapEx | H104: 389.80959 | I104: 206.56169 | J104: =N104/4 -> 59.382145 | K104: =N104/4 -> 59.382145 | L104: =N104/4 -> 59.382145 | M104: =N104/4 -> 59.382145 | N104: 237.52858 | O104: =S104/4 -> 50.2835 | P104: =S104/4 -> 50.2835 | Q104: =S104/4 -> 50.2835 | R104: =S104/4 -> 50.2835 | S104: 201.134 | T104: =X104/4 -> 60.6215 | U104: =X104/4 -> 60.6215 | V104: =X104/4 -> 60.6215 | W104: =X104/4 -> 60.6215 | X104: 242.486 | Y104: =AC104/4 -> 54.01175 | Z104: =AC104/4 -> 54.01175 | AA104: =AC104/4 -> 54.01175 | AB104: =AC104/4 -> 54.01175 | AC104: 216.047 | AD104: =AH104/4 -> 48.88725 | AE104: =AH104/4 -> 48.88725 | AF104: =AH104/4 -> 48.88725 | AG104: =AH104/4 -> 48.88725 | AH104: 195.549 | AI104: =AM104/4 -> 102.4965 | AJ104: =AM104/4 -> 102.4965 | AK104: =AM104/4 -> 102.4965 | AL104: =AM104/4 -> 102.4965 | AM104: 409.986 | AN104: =AR104/4 -> 192.805 | AO104: =AR104/4 -> 192.805 | AP104: =AR104/4 -> 192.805 | AQ104: =AR104/4 -> 192.805 | AR104: 771.22 | AS104: =AW104/4 -> 54.4225 | AT104: =AW104/4 -> 54.4225 | AU104: =AW104/4 -> 54.4225 | AV104: =AW104/4 -> 54.4225 | AW104: 217.69 | AX104: =BB104/4 -> 46.559 | AY104: =BB104/4 -> 46.559 | AZ104: =BB104/4 -> 46.559 | BA104: =BB104/4 -> 46.559 | BB104: 186.236 | BC104: =BG104/4 -> 45.2945 | BD104: =BG104/4 -> 45.2945 | BE104: =BG104/4 -> 45.2945 | BF104: =BG104/4 -> 45.2945 | BG104: 181.178 | BH104: =BL104/4 -> 92.36575 | BI104: =BL104/4 -> 92.36575 | BJ104: =BL104/4 -> 92.36575 | BK104: =BL104/4 -> 92.36575 | BL104: 369.463 | BM104: =BQ104/4 -> 147.40525 | BN104: =BQ104/4 -> 147.40525 | BO104: =BQ104/4 -> 147.40525 | BP104: =BQ104/4 -> 147.40525 | BQ104: 589.621 | BR104: =BV104/4 -> 85.94175 | BS104: =BV104/4 -> 85.94175 | BT104: =BV104/4 -> 85.94175 | BU104: =BV104/4 -> 85.94175 | BV104: 343.767 | BW104: =CA104/4 -> 62.133 | BX104: =CA104/4 -> 62.133 | BY104: =CA104/4 -> 62.133 | BZ104: =CA104/4 -> 62.133 | CA104: 248.532 | CB104: =CF104/4 -> 93.999 | CC104: =CF104/4 -> 93.999 | CD104: =CF104/4 -> 93.999 | CE104: =CF104/4 -> 93.999 | CF104: 375.996 | CG104: =CK104/4 -> 89.80375 | CH104: =CK104/4 -> 89.80375 | CI104: =CK104/4 -> 89.80375 | CJ104: =CK104/4 -> 89.80375 | CK104: 359.215
C105: CapEx per ton | H105: =H104/H38*1000 -> 39.861907 | I105: =I104/I38*1000 -> 18.723866 | J105: =J104/J38*1000 -> 19.643448 | K105: =K104/K38*1000 -> 18.953765 | L105: =L104/L38*1000 -> 20.047989 | M105: =M104/M38*1000 -> 18.580145 | N105: =N104/N38*1000 -> 19.289311 | O105: =O104/O38*1000 -> 12.446411 | ... CZ105: =CZ104/CZ38*1000 -> 0
A106: Days in Quarter | BW106: 90 | BX106: 91 | BY106: 92 | BZ106: 92 | CA106: =SUM(BW106:BZ106) -> 365 | CB106: 91 | CC106: 91 | CD106: 92 | CE106: 92 | CF106: =SUM(CB106:CE106) -> 366 | CG106: 90 | CH106: 91 | CI106: 92 | CJ106: 92 | CK106: =SUM(CG106:CJ106) -> 365 | CL106: 90 | CM106: 91 | CN106: 92 | CO106: 92 | CP106: =SUM(CL106:CO106) -> 365 | CQ106: 90 | CR106: 91 | CS106: 92 | CT106: 92 | CU106: =SUM(CQ106:CT106) -> 365 | CV106: 90 | CW106: 91 | CX106: 92 | CY106: 92 | CZ106: =SUM(CV106:CY106) -> 365
A108: Steel Products Segment
B109: Volume Growth
B110: Steel Joists | I110: =Operations!Q119/Operations!H119-1 -> -0.76672104 | N110: =Operations!R119/Operations!I119-1 -> -0.76503759 | S110: =Operations!S119/Operations!N119-1 -> 0.088744589 | T110: =Operations!T119/Operations!O119-1 -> 0.08411215 | U110: =Operations!U119/Operations!P119-1 -> 0.0625 | V110: =Operations!V119/Operations!Q119-1 -> 0.006993007 | W110: =Operations!W119/Operations!R119-1 -> 0.008 | X110: =Operations!X119/Operations!S119-1 -> 0.03777336 | Y110: =Operations!Y119/Operations!T119-1 -> 0.060344828 | Z110: =Operations!Z119/Operations!U119-1 -> 0.022058824 | ... AZ110: =Operations!AZ119/Operations!AU119-1 -> 0.028985507 | BA110: 0 | BB110: =Operations!BB119/Operations!AW119-1 -> 0.045454545 | BC110: =Operations!BC119/Operations!AX119-1 -> 0.13559322 | BD110: =Operations!BD119/Operations!AY119-1 -> -0.027777778 | BE110: =Operations!BE119/Operations!AZ119-1 -> 0.15492958 | BF110: =Operations!BF119/Operations!BA119-1 -> -0.067567568 | BG110: =Operations!BG119/Operations!BB119-1 -> 0.043478261 | BH110: =Operations!BH119/Operations!BC119-1 -> -0.044776119 | BI110: =Operations!BI119/Operations!BD119-1 -> 0.071428571 | ... CL110: =Operations!CL119/Operations!CG119-1 -> 0.03960396 | CM110: 0.03 | CN110: 0.03 | CO110: 0.03 | CP110: =Operations!CP119/Operations!CK119-1 -> 0.032055085 | CQ110: 0.02 | CR110: 0.02 | CS110: 0.02 | CT110: 0.02 | CU110: =Operations!CU119/Operations!CP119-1 -> 0.02 | CV110: 0.02 | CW110: 0.02 | CX110: 0.02 | CY110: 0.02 | CZ110: =Operations!CZ119/Operations!CU119-1 -> 0.02
B111: Steel Deck | I111: =Operations!Q120/Operations!H120-1 -> -0.73371105 | N111: =Operations!R120/Operations!I120-1 -> -0.74709302 | S111: =Operations!S120/Operations!N120-1 -> 0.06969697 | T111: =Operations!T120/Operations!O120-1 -> -0.075 | U111: =Operations!U120/Operations!P120-1 -> 0.02173913 | V111: =Operations!V120/Operations!Q120-1 -> 0.095744681 | W111: =Operations!W120/Operations!R120-1 -> 0.068965517 | X111: =Operations!X120/Operations!S120-1 -> 0.031161473 | Y111: =Operations!Y120/Operations!T120-1 -> 0.081081081 | Z111: =Operations!Z120/Operations!U120-1 -> 0.074468085 | ... AZ111: =Operations!AZ120/Operations!AU120-1 -> -0.035714286 | BA111: 0 | BB111: =Operations!BB120/Operations!AW120-1 -> -0.012903226 | BC111: =Operations!BC120/Operations!AX120-1 -> 0.058823529 | BD111: =Operations!BD120/Operations!AY120-1 -> -0.024691358 | BE111: =Operations!BE120/Operations!AZ120-1 -> 0.024691358 | BF111: =Operations!BF120/Operations!BA120-1 -> 0.026315789 | BG111: =Operations!BG120/Operations!BB120-1 -> 0.019607843 | BH111: =Operations!BH120/Operations!BC120-1 -> -0.097222222 | BI111: =Operations!BI120/Operations!BD120-1 -> -0.037974684 | ... CL111: =Operations!CL120/Operations!CG120-1 -> 0 | CM111: 0.03 | CN111: 0.03 | CO111: 0.03 | CP111: =Operations!CP120/Operations!CK120-1 -> 0.023041575 | CQ111: 0.02 | CR111: 0.02 | CS111: 0.02 | CT111: 0.02 | CU111: =Operations!CU120/Operations!CP120-1 -> 0.02 | CV111: 0.02 | CW111: 0.02 | CX111: 0.02 | CY111: 0.02 | CZ111: =Operations!CZ120/Operations!CU120-1 -> 0.02
B112: Cold Finished Sheet | I112: =Operations!Q121/Operations!H121-1 -> -0.784 | N112: =Operations!R121/Operations!I121-1 -> -0.72906404 | S112: =Operations!S121/Operations!N121-1 -> 0.048672566 | T112: =Operations!T121/Operations!O121-1 -> 0.072463768 | U112: =Operations!U121/Operations!P121-1 -> 0.20338983 | V112: =Operations!V121/Operations!Q121-1 -> 0.22222222 | W112: =Operations!W121/Operations!R121-1 -> 0.090909091 | X112: =Operations!X121/Operations!S121-1 -> 0.14345992 | Y112: =Operations!Y121/Operations!T121-1 -> 0.2027027 | Z112: =Operations!Z121/Operations!U121-1 -> 0.22535211 | ... AZ112: =Operations!AZ121/Operations!AU121-1 -> 0.4137931 | BA112: 0.2 | BB112: =Operations!BB121/Operations!AW121-1 -> 0.4 | BC112: =Operations!BC121/Operations!AX121-1 -> 0.20720721 | BD112: =Operations!BD121/Operations!AY121-1 -> 0.1025641 | BE112: =Operations!BE121/Operations!AZ121-1 -> -0.040650407 | BF112: =Operations!BF121/Operations!BA121-1 -> 0.018018018 | BG112: =Operations!BG121/Operations!BB121-1 -> 0.069264069 | BH112: =Operations!BH121/Operations!BC121-1 -> 0.029850746 | BI112: =Operations!BI121/Operations!BD121-1 -> 0.023255814 | ... CL112: =Operations!CL121/Operations!CG121-1 -> 0.20491803 | CM112: 0.03 | CN112: 0.03 | CO112: 0.03 | CP112: =Operations!CP121/Operations!CK121-1 -> 0.073819302 | CQ112: 0.02 | CR112: 0.02 | CS112: 0.02 | CT112: 0.02 | CU112: =Operations!CU121/Operations!CP121-1 -> 0.02 | CV112: 0.02 | CW112: 0.02 | CX112: 0.02 | CY112: 0.02 | CZ112: =Operations!CZ121/Operations!CU121-1 -> 0.02
B113: Rebar Fabrication | AN113: =Operations!AN122/Operations!AI122-1 -> 3.475 | AO113: =Operations!AO122/Operations!AJ122-1 -> 0.41463415 | AP113: =Operations!AP122/Operations!AK122-1 -> 0.42541436 | AQ113: =Operations!AQ122/Operations!AL122-1 -> 0.44444444 | AR113: =Operations!AR122/Operations!AM122-1 -> 0.6380789 | AS113: =Operations!AS122/Operations!AN122-1 -> 0.16201117 | AT113: =Operations!AT122/Operations!AO122-1 -> 0.099137931 | AU113: =Operations!AU122/Operations!AP122-1 -> 0.085271318 | ... AZ113: =Operations!AZ122/Operations!AU122-1 -> 0.039285714 | BA113: 0.05 | BB113: =Operations!BB122/Operations!AW122-1 -> 0.028301887 | BC113: =Operations!BC122/Operations!AX122-1 -> 0.13917526 | BD113: =Operations!BD122/Operations!AY122-1 -> 0.033834586 | BE113: =Operations!BE122/Operations!AZ122-1 -> 0.072164948 | BF113: =Operations!BF122/Operations!BA122-1 -> 0.15652174 | BG113: =Operations!BG122/Operations!BB122-1 -> 0.094801223 | BH113: =Operations!BH122/Operations!BC122-1 -> 0.13122172 | BI113: =Operations!BI122/Operations!BD122-1 -> 0.17090909 | ... CL113: =Operations!CL122/Operations!CG122-1 -> 0.17408907 | CM113: 0.03 | CN113: 0.03 | CO113: 0.03 | CP113: =Operations!CP122/Operations!CK122-1 -> 0.061164623 | CQ113: 0.02 | CR113: 0.02 | CS113: 0.02 | CT113: 0.02 | CU113: =Operations!CU122/Operations!CP122-1 -> 0.02 | CV113: 0.02 | CW113: 0.02 | CX113: 0.02 | CY113: 0.02 | CZ113: =Operations!CZ122/Operations!CU122-1 -> 0.02
B114: Piling | CL114: =Operations!CL123/Operations!CG123-1 -> 0.058823529 | CM114: 0.05 | CN114: 0.05 | CO114: 0.05 | CP114: =Operations!CP123/Operations!CK123-1 -> 0.051861702 | CQ114: 0.02 | CR114: 0.02 | CS114: 0.02 | CT114: 0.02 | CU114: =Operations!CU123/Operations!CP123-1 -> 0.02 | CV114: 0.02 | CW114: 0.02 | CX114: 0.02 | CY114: 0.02 | CZ114: =Operations!CZ123/Operations!CU123-1 -> 0.02
B115: Tubular | CJ115: =Operations!CJ124/Operations!CE124-1 -> 1.7439024 | CK115: =Operations!CK124/Operations!CF124-1 -> 10.182927 | CL115: =Operations!CL124/Operations!CG124-1 -> 0.2735426 | CM115: 0.15 | CN115: 0.15 | CO115: 0.15 | CP115: =Operations!CP124/Operations!CK124-1 -> 0.18004362 | CQ115: 0.02 | CR115: 0.02 | CS115: 0.02 | CT115: 0.02 | CU115: =Operations!CU124/Operations!CP124-1 -> 0.02 | CV115: 0.02 | CW115: 0.02 | CX115: 0.02 | CY115: 0.02 | CZ115: =Operations!CZ124/Operations!CU124-1 -> 0.02
B116: Others | I116: =Operations!Q125/Operations!H125-1 -> -0.84536082 | N116: =Operations!R125/Operations!I125-1 -> -0.73809524 | S116: =Operations!S125/Operations!N125-1 -> 0.063636364 | T116: =Operations!T125/Operations!O125-1 -> 0.32142857 | U116: =Operations!U125/Operations!P125-1 -> 0.65384615 | V116: =Operations!V125/Operations!Q125-1 -> 0.5 | W116: =Operations!W125/Operations!R125-1 -> 0.21212121 | X116: =Operations!X125/Operations!S125-1 -> 0.41025641 | Y116: =Operations!Y125/Operations!T125-1 -> -0.054054054 | Z116: =Operations!Z125/Operations!U125-1 -> 0 | ... CL116: =Operations!CL125/Operations!CG125-1 -> 0.10794045 | CM116: 0.03 | CN116: 0.03 | CO116: 0.03 | CP116: =Operations!CP125/Operations!CK125-1 -> 0.048944511 | CQ116: 0.03 | CR116: 0.03 | CS116: 0.03 | CT116: 0.03 | CU116: =Operations!CU125/Operations!CP125-1 -> 0.03 | CV116: 0.03 | CW116: 0.03 | CX116: 0.03 | CY116: 0.03 | CZ116: =Operations!CZ125/Operations!CU125-1 -> 0.03
...

Sheet Financials
AN3: 39508 | AO3: 39600 | AP3: 39692 | AQ3: 39783 | AR3: FY8 | AS3: 39873 | AT3: 39965 | AU3: 40057 | AV3: 40148 | AW3: FY9 | AX3: 40238 | AY3: 40330 | AZ3: 40422 | BA3: 40513 | BB3: FY10 | BC3: 40603 | BD3: 40695 | BE3: 40787 | BF3: 40878 | BG3: FY11 | BH3: 40969 | BI3: 41061 | BJ3: 41153 | BK3: 41244 | BL3: FY12 | BM3: 41334 | BN3: 41426 | BO3: 41518 | BP3: 41609 | BQ3: FY13 | BR3: 41699 | BS3: 41791 | BT3: 41883 | BU3: 41974 | BV3: FY14 | BW3: 42064 | BX3: 42156 | BY3: 42248 | BZ3: 42339 | CA3: FY15 | CB3: 42430 | CC3: 42522 | CD3: 42614 | CE3: 42705 | CF3: FY16 | CG3: 42795 | CH3: 42887 | CI3: 42979 | CJ3: 43070 | CK3: FY17 | CL3: 43160 | CM3: 43252 | CN3: 43344 | CO3: 43435 | CP3: FY18 | CQ3: 43525 | CR3: 43617 | CS3: 43709 | CT3: 43800 | CU3: FY19 | CV3: 43891 | CW3: 43983 | CX3: 44075 | CY3: 44166 | CZ3: FY20
A4: Nucor Corporation
A5: Quarterly Income Statement
A7: ($ millions Except Per Share Data) | J7: 2002 | O7: 2003 | T7: =X8 -> 2004 | Y7: =AC8 -> 2005 | AD7: =AH8 -> 2006 | AI7: =AM8 -> 2007 | AN7: =AR8 -> 2008 | AS7: =AW8 -> 2009 | AX7: =BB8 -> 2010 | BC7: =BG8 -> 2011 | BH7: =BL8 -> 2012 | BM7: =BQ8 -> 2013 | BR7: =BV8 -> 2014 | BW7: =CA8 -> 2015 | CB7: =CF8 -> 2016 | CG7: =CK8 -> 2017 | CL7: =CP8 -> 2018E | CQ7: =CU8 -> 2019E | CV7: =CZ8 -> 2020E
J8: 1Q | K8: 2Q | L8: 3Q | M8: 4Q | N8: =J7 -> 2002 | O8: 1Q | P8: 2Q | Q8: 3Q | R8: 4Q | S8: =O7 -> 2003 | T8: =Operations!T4 -> 1Q | U8: =Operations!U4 -> 2Q | V8: =Operations!V4 -> 3Q | W8: =Operations!W4 -> 4Q | X8: =Operations!X4 -> 2004 | Y8: =Operations!Y4 -> 1Q | Z8: =Operations!Z4 -> 2Q | AA8: =Operations!AA4 -> 3Q | ... CZ8: =Operations!CZ4 -> 2020E
A9: Revenues
B10: Steel | J10: 927.03875 | K10: 1015.8046 | L10: 1022.3575 | M10: =N10-J10-K10-L10 -> 1097.3886 | N10: 4062.5894 | O10: =Operations!O89 -> 1297.8795 | P10: =Operations!P89 -> 1320.3027 | Q10: =Operations!Q89 -> 1383.8596 | R10: =Operations!R89 -> 1444.0852 | S10: =SUM(O10:R10) -> 5446.127 | T10: =Operations!T89 -> 2064.069 | U10: =Operations!U89 -> 2461.074 | V10: =Operations!V89 -> 2868.483 | W10: =Operations!W89 -> 2715.804 | X10: =SUM(T10:W10) -> 10109.43 | Y10: =Operations!Y89 -> 2950 | Z10: =Operations!Z89 -> 2716.677 | AA10: =Operations!AA89 -> 2605.942 | AB10: =Operations!AB89 -> 2791.062 | AC10: =SUM(Y10:AB10) -> 11063.681 | AD10: =Operations!AD89 -> 3149.426 | AE10: =Operations!AE89 -> 3388.068 | AF10: =Operations!AF89 -> 3469.443 | AG10: =Operations!AG89 -> 3018.186 | AH10: =SUM(AD10:AG10) -> 13025.123 | AI10: =Operations!AI89 -> 3273.254 | AJ10: =Operations!AJ89 -> 3336.156 | AK10: =Operations!AK89 -> 3344.116 | AL10: =Operations!AL89 -> 3357.686 | AM10: =SUM(AI10:AL10) -> 13311.212 | AN10: =Operations!AN89 -> 3759.453 | AO10: =Operations!AO89 -> 4893.137 | AP10: =Operations!AP89 -> 5192.082 | AQ10: =Operations!AQ89 -> 2633.228 | AR10: =SUM(AN10:AQ10) -> 16477.9 | AS10: =Operations!AS89 -> 1656.24 | AT10: =Operations!AT89 -> 1429.284 | AU10: =Operations!AU89 -> 2070.202 | AV10: =Operations!AV89 -> 2003.786 | AW10: =SUM(AS10:AV10) -> 7159.512 | AX10: =Operations!AX89 -> 2612.016 | AY10: =Operations!AY89 -> 2875.338 | AZ10: =Operations!AZ89 -> 2798.419 | BA10: =Operations!BA89 -> 2574.987 | BB10: =SUM(AX10:BA10) -> 10860.76 | BC10: =Operations!BC89 -> 3448.197 | BD10: =Operations!BD89 -> 3569.786 | BE10: =Operations!BE89 -> 3617.867 | BF10: =Operations!BF89 -> 3324.395 | BG10: =SUM(BC10:BF10) -> 13960.245 | BH10: =Operations!BH89 -> 3626.139 | BI10: =Operations!BI89 -> 3476.661 | BJ10: =Operations!BJ89 -> 3204.898 | BK10: =Operations!BK89 -> 3010.282 | BL10: =SUM(BH10:BK10) -> 13317.98 | BM10: =Operations!BM89 -> 3268.154 | BN10: =Operations!BN89 -> 3197.433 | BO10: =Operations!BO89 -> 3435.884 | BP10: =Operations!BP89 -> 3410.477 | BQ10: =SUM(BM10:BP10) -> 13311.948 | BR10: =Operations!BR89 -> 3607.764 | BS10: =Operations!BS89 -> 3674.14 | BT10: =Operations!BT89 -> 3898.031 | BU10: =Operations!BU89 -> 3543.707 | BV10: =SUM(BR10:BU10) -> 14723.642 | BW10: =Operations!BW89 -> 3053.339 | BX10: =Operations!BX89 -> 2968.644 | BY10: =Operations!BY89 -> 2816.441 | BZ10: =Operations!BZ89 -> 2245.907 | CA10: =SUM(BW10:BZ10) -> 11084.331 | CB10: =Operations!CB89 -> 2634.589 | CC10: =Operations!CC89 -> 3016.322 | CD10: =Operations!CD89 -> 2960.642 | CE10: =Operations!CE89 -> 2640.061 | CF10: =SUM(CB10:CE10) -> 11251.614 | CG10: =Operations!CG89 -> 3329.824 | CH10: =Operations!CH89 -> 3800.359 | CI10: =Operations!CI89 -> 3639.488 | CJ10: =Operations!CJ89 -> 3507.201 | CK10: =SUM(CG10:CJ10) -> 14276.872 | CL10: =Operations!CL89 -> 3985.8976 | CM10: =Operations!CM89 -> 4631.6162 | CN10: =Operations!CN89 -> 4560.5658 | CO10: =Operations!CO89 -> 4406.316 | CP10: =SUM(CL10:CO10) -> 17584.395 | CQ10: =Operations!CQ89 -> 4813.4448 | CR10: =Operations!CR89 -> 4791.0552 | CS10: =Operations!CS89 -> 4473.3609 | CT10: =Operations!CT89 -> 4219.1407 | CU10: =SUM(CQ10:CT10) -> 18297.002 | CV10: =Operations!CV89 -> 4619.5255 | CW10: =Operations!CW89 -> 4581.8362 | CX10: =Operations!CX89 -> 4252.304 | CY10: =Operations!CY89 -> 4132.8834 | CZ10: =SUM(CV10:CY10) -> 17586.549
B11: Steel Products | J11: 153.59823 | K11: 182.22761 | L11: 206.17192 | M11: =N11-J11-K11-L11 -> 197.18935 | N11: 739.18711 | O11: =Operations!O132 -> 182.3915 | P11: =Operations!P132 -> 200.15816 | Q11: =Operations!Q132 -> 220.15173 | R11: =Operations!R132 -> 216.99461 | S11: =SUM(O11:R11) -> 819.696 | T11: =Operations!T132 -> 222.347 | U11: =Operations!U132 -> 300.748 | V11: =Operations!V132 -> 371.109 | W11: =Operations!W132 -> 373.194 | X11: =SUM(T11:W11) -> 1267.398 | Y11: =Operations!Y132 -> 371.703 | Z11: =Operations!Z132 -> 428.326 | AA11: =Operations!AA132 -> 419.969 | AB11: =Operations!AB132 -> 417.32 | AC11: =SUM(Y11:AB11) -> 1637.318 | AD11: =Operations!AD132 -> 395.671 | AE11: =Operations!AE132 -> 418.282 | AF11: =Operations!AF132 -> 461.79 | AG11: =Operations!AG132 -> 450.404 | AH11: =SUM(AD11:AG11) -> 1726.147 | AI11: =Operations!AI132 -> 484.032 | AJ11: =Operations!AJ132 -> 748.759 | AK11: =Operations!AK132 -> 853.495 | AL11: =Operations!AL132 -> 965.362 | AM11: =SUM(AI11:AL11) -> 3051.648 | AN11: =Operations!AN132 -> 885.507 | AO11: =Operations!AO132 -> 1119.271 | AP11: =Operations!AP132 -> 1238.642 | AQ11: =Operations!AQ132 -> 1096.104 | AR11: =SUM(AN11:AQ11) -> 4339.524 | AS11: =Operations!AS132 -> 713.827 | AT11: =Operations!AT132 -> 693.934 | AU11: =Operations!AU132 -> 681.331 | AV11: =Operations!AV132 -> 602.23 | AW11: =SUM(AS11:AV11) -> 2691.322 | AX11: =Operations!AX132 -> 561.035 | AY11: =Operations!AY132 -> 737.693 | AZ11: =Operations!AZ132 -> 794.289 | BA11: =Operations!BA132 -> 738.192 | BB11: =SUM(AX11:BA11) -> 2831.209 | BC11: =Operations!BC132 -> 732.139 | BD11: =Operations!BD132 -> 875.365 | BE11: =Operations!BE132 -> 958.224 | BF11: =Operations!BF132 -> 865.762 | BG11: =SUM(BC11:BF11) -> 3431.49 | BH11: =Operations!BH132 -> 842.245 | BI11: =Operations!BI132 -> 991.444 | BJ11: =Operations!BJ132 -> 1006.366 | BK11: =Operations!BK132 -> 898.326 | BL11: =SUM(BH11:BK11) -> 3738.381 | BM11: =Operations!BM132 -> 789.347 | BN11: =Operations!BN132 -> 937.104 | BO11: =Operations!BO132 -> 964.153 | BP11: =Operations!BP132 -> 916.729 | BQ11: =SUM(BM11:BP11) -> 3607.333 | BR11: =Operations!BR132 -> 874.169 | BS11: =Operations!BS132 -> 1035.923 | BT11: =Operations!BT132 -> 1142.043 | BU11: =Operations!BU132 -> 980.25 | BV11: =SUM(BR11:BU11) -> 4032.385 | BW11: =Operations!BW132 -> 921.384 | BX11: =Operations!BX132 -> 1015.646 | BY11: =Operations!BY132 -> 1081.047 | BZ11: =Operations!BZ132 -> 948.818 | CA11: =SUM(BW11:BZ11) -> 3966.895 | CB11: =Operations!CB132 -> 828.376 | CC11: =Operations!CC132 -> 923.357 | CD11: =Operations!CD132 -> 1011.602 | CE11: =Operations!CE132 -> 924.113 | CF11: =SUM(CB11:CE11) -> 3687.448 | CG11: =Operations!CG132 -> 860.075 | CH11: =Operations!CH132 -> 970.398 | CI11: =Operations!CI132 -> 1089.519 | CJ11: =Operations!CJ132 -> 1080.614 | CK11: =SUM(CG11:CJ11) -> 4000.606 | CL11: =Operations!CL132 -> 1539.4624 | CM11: =Operations!CM132 -> 1541.5589 | CN11: =Operations!CN132 -> 1710.6325 | CO11: =Operations!CO132 -> 1682.1793 | CP11: =SUM(CL11:CO11) -> 6473.8332 | CQ11: =Operations!CQ132 -> 1640.6943 | CR11: =Operations!CR132 -> 1618.9662 | CS11: =Operations!CS132 -> 1751.9832 | CT11: =Operations!CT132 -> 1706.2667 | CU11: =SUM(CQ11:CT11) -> 6717.9105 | CV11: =Operations!CV132 -> 1673.2629 | CW11: =Operations!CW132 -> 1658.0428 | CX11: =Operations!CX132 -> 1818.4943 | CY11: =Operations!CY132 -> 1775.5933 | CZ11: =SUM(CV11:CY11) -> 6925.3934
B12: Raw Materials | AN12: =Operations!AN165 -> 235.229 | AO12: =Operations!AO165 -> 927.029 | AP12: =Operations!AP165 -> 897.539 | AQ12: =Operations!AQ165 -> 343.278 | AR12: =Operations!AR165 -> 2403.075 | AS12: =Operations!AS165 -> 236.931 | AT12: =Operations!AT165 -> 277.869 | AU12: =Operations!AU165 -> 289.072 | ... BU12: =Operations!BU165 -> 479.796 | BV12: =SUM(BR12:BU12) -> 2349.114 | BW12: =Operations!BW165 -> 424.717 | BX12: =Operations!BX165 -> 373.319 | BY12: =Operations!BY165 -> 328.026 | BZ12: =Operations!BZ165 -> 261.988 | CA12: =SUM(BW12:BZ12) -> 1388.05 | CB12: =Operations!CB165 -> 252.611 | CC12: =Operations!CC165 -> 306.093 | CD12: =Operations!CD165 -> 317.992 | CE12: =Operations!CE165 -> 331.93 | CF12: =SUM(CB12:CE12) -> 1208.626 | CG12: =Operations!CG165 -> 412.315 | CH12: =Operations!CH165 -> 404.012 | CI12: =Operations!CI165 -> 441.11 | CJ12: =Operations!CJ165 -> 485.503 | CK12: =Operations!CK165 -> 1742.94 | CL12: =Operations!CL165 -> 460.00209 | CM12: =Operations!CM165 -> 424.7332 | CN12: =Operations!CN165 -> 466.45843 | ... CZ12: =Operations!CZ165 -> 1757.4186
B13: Other | AI13: 11.599 | AJ13: =4186.11-AJ11-AJ10 -> 101.195 | AK13: 61.61 | AL13: =4396.76-AL11-AL10 -> 73.712 | AM13: =SUM(AI13:AL13) -> 248.116 | AN13: =4974.269-AN11-AN10-AN12 -> 94.08 | AO13: =7090.599-AO12-AO11-AO10 -> 151.162 | AP13: =AP15-SUM(AP10:AP12) -> 119.257 | AQ13: =AQ15-SUM(AQ10:AQ12) -> 78.326 | AR13: =SUM(AN13:AQ13) -> 442.825 | AS13: =AS15-SUM(AS10:AS12) -> 47.321 | AT13: =AT15-SUM(AT10:AT12) -> 76.941 | AU13: =AU15-SUM(AU10:AU12) -> 79.4 | AV13: =AV15-SUM(AV10:AV12) -> 58.836 | AW13: =SUM(AS13:AV13) -> 262.498 | AX13: =AX15-SUM(AX10:AX12) -> 85.046 | AY13: =AY15-SUM(AY10:AY12) -> 78.855 | AZ13: =AZ15-SUM(AZ10:AZ12) -> 83.846 | BA13: =BA15-SUM(BA10:BA12) -> 90.582 | BB13: =SUM(AX13:BA13) -> 338.329 | BC13: =BC15-SUM(BC10:BC12) -> 126.135 | BD13: =BD15-SUM(BD10:BD12) -> 107.113 | BE13: =BE15-SUM(BE10:BE12) -> 140.405 | BF13: =BF15-SUM(BF10:BF12) -> 129.785 | BG13: =SUM(BC13:BF13) -> 503.438 | BH13: =BH15-SUM(BH10:BH12) -> 122.002 | BI13: =BI15-SUM(BI10:BI12) -> 138.49 | BJ13: =BJ15-SUM(BJ10:BJ12) -> 114.62 | BK13: =BK15-SUM(BK10:BK12) -> 88.705 | BL13: =SUM(BH13:BK13) -> 463.817 | BM13: =BM15-SUM(BM10:BM12) -> 0 | BN13: =BN15-SUM(BN10:BN12) -> 0 | BO13: =BO15-SUM(BO10:BO12) -> 0 | BP13: =BP15-SUM(BP10:BP12) -> 0 | BQ13: =SUM(BM13:BP13) -> 0 | BR13: =BR15-SUM(BR10:BR12) -> 0 | BS13: =BS15-SUM(BS10:BS12) -> 0 | BT13: =BT15-SUM(BT10:BT12) -> 0 | BU13: =BU15-SUM(BU10:BU12) -> 0 | BV13: =SUM(BR13:BU13) -> 0 | BW13: =BW15-SUM(BW10:BW12) -> 0 | BX13: =BX15-SUM(BX10:BX12) -> 0 | BY13: =BY15-SUM(BY10:BY12) -> 0 | BZ13: =BZ15-SUM(BZ10:BZ12) -> 0 | CA13: =SUM(BW13:BZ13) -> 0 | CB13: =CB15-SUM(CB10:CB12) -> 0 | CC13: =CC15-SUM(CC10:CC12) -> 0 | CD13: =CD15-SUM(CD10:CD12) -> 0 | CE13: =CE15-SUM(CE10:CE12) -> 60.434 | CF13: =SUM(CB13:CE13) -> 60.434 | CG13: =CG15-SUM(CG10:CG12) -> 212.965 | CH13: =CH15-SUM(CH10:CH12) -> 0 | CI13: =CI15-SUM(CI10:CI12) -> 0 | CJ13: =CJ15-SUM(CJ10:CJ12) -> 19.01 | CK13: =SUM(CG13:CJ13) -> 231.975 | CL13: =CL15-SUM(CL10:CL12) -> -416.94312 | CM13: 0 | CN13: 0 | CO13: 0 | CP13: =SUM(CL13:CO13) -> -416.94312 | CQ13: 0 | CR13: 0 | CS13: 0 | CT13: 0 | CU13: =SUM(CQ13:CT13) -> 0 | CV13: 0 | CW13: 0 | CX13: 0 | CY13: 0 | CZ13: =SUM(CV13:CY13) -> 0
C15: Total Net Sales | J15: =J11+J10 -> 1080.637 | K15: =K11+K10 -> 1198.0322 | L15: =L11+L10 -> 1228.5294 | M15: =M11+M10 -> 1294.5779 | N15: =N11+N10 -> 4801.7765 | O15: =O11+O10 -> 1480.271 | P15: =P11+P10 -> 1520.4609 | Q15: =Q11+Q10 -> 1604.0113 | ... AH15: =AH11+AH10 -> 14751.27 | AI15: =AI11+AI10+AI13 -> 3768.885 | AJ15: =AJ11+AJ10+AJ13 -> 4186.11 | AK15: =AK11+AK10+AK13 -> 4259.221 | AL15: =AL11+AL10+AL13 -> 4396.76 | AM15: =AM11+AM10+AM13 -> 16610.976 | AN15: =SUM(AN10:AN13) -> 4974.269 | AO15: =SUM(AO10:AO13) -> 7090.599 | AP15: 7447.52 | AQ15: 4150.936 | AR15: =SUM(AR10:AR13) -> 23663.324 | AS15: 2654.319 | AT15: 2478.028 | AU15: 3120.005 | AV15: 2937.944 | AW15: =SUM(AW10:AW13) -> 11190.296 | AX15: 3654.842 | AY15: 4195.966 | AZ15: 4140.069 | BA15: 3853.75 | BB15: =SUM(BB10:BB13) -> 15844.627 | BC15: 4833.934 | BD15: 5107.809 | BE15: 5252.144 | BF15: 4829.677 | BG15: =SUM(BG10:BG13) -> 20023.564 | BH15: 5072.594 | BI15: 5104.199 | BJ15: 4801.206 | BK15: 4451.274 | BL15: =SUM(BL10:BL13) -> 19429.273 | BM15: 4550.772 | BN15: 4665.588 | BO15: 4940.936 | BP15: 4894.75 | BQ15: =SUM(BQ10:BQ13) -> 19052.046 | BR15: 5108.444 | BS15: 5291.075 | BT15: 5701.869 | BU15: 5003.753 | BV15: =SUM(BV10:BV13) -> 21105.141 | BW15: 4399.44 | BX15: 4357.609 | BY15: 4225.514 | BZ15: 3456.713 | CA15: =SUM(CA10:CA13) -> 16439.276 | CB15: 3715.576 | CC15: 4245.772 | CD15: 4290.236 | CE15: 3956.538 | CF15: =SUM(CF10:CF13) -> 16208.122 | CG15: 4815.179 | CH15: 5174.769 | CI15: 5170.117 | CJ15: 5092.328 | CK15: =SUM(CK10:CK13) -> 20252.393 | CL15: 5568.419 | CM15: =SUM(CM10:CM13) -> 6597.9083 | CN15: =SUM(CN10:CN13) -> 6737.6567 | CO15: =SUM(CO10:CO13) -> 6579.9601 | CP15: =SUM(CP10:CP13) -> 25483.944 | CQ15: =SUM(CQ10:CQ13) -> 6932.6503 | CR15: =SUM(CR10:CR13) -> 6844.1372 | CS15: =SUM(CS10:CS13) -> 6698.8387 | CT15: =SUM(CT10:CT13) -> 6421.8712 | ... CZ15: =SUM(CZ10:CZ13) -> 26269.361
C16: Annual Growth % | O16: =O15/J15-1 -> 0.36981337 | P16: =P15/K15-1 -> 0.2691319 | Q16: =Q15/L15-1 -> 0.30563527 | R16: =R15/M15-1 -> 0.28310529 | S16: =S15/N15-1 -> 0.30489683 | T16: =T15/O15-1 -> 0.54459286 | U16: =U15/P15-1 -> 0.81643739 | V16: =V15/Q15-1 -> 1.0196815 | ... CZ16: =CZ15/CU15-1 -> -0.023352963
C17: Seq. Growth % | K17: =K15/J15-1 -> 0.10863521 | L17: =L15/K15-1 -> 0.025456091 | M17: =M15/L15-1 -> 0.053762248 | N17: =N15/M15-1 -> 2.7091445 | O17: =O15/M15-1 -> 0.14343907 | P17: =P15/O15-1 -> 0.027150365 | Q17: =Q15/P15-1 -> 0.054950746 | R17: =R15/Q15-1 -> 0.035578577 | T17: =T15/R15-1 -> 0.37646368 | U17: =U15/T15-1 -> 0.20792629 | V17: =V15/U15-1 -> 0.17299087 | W17: =W15/V15-1 -> -0.046485483 | Y17: =Y15/W15-1 -> 0.07533349 | Z17: =Z15/Y15-1 -> -0.053195605 | AA17: =AA15/Z15-1 -> -0.037867054 | AB17: =AB15/AA15-1 -> 0.060302831 | AD17: =AD15/AB15-1 -> 0.10494854 | AE17: =AE15/AD15-1 -> 0.073694175 | AF17: =AF15/AE15-1 -> 0.032809122 | AG17: =AG15/AF15-1 -> -0.11768394 | AI17: =AI15/AG15-1 -> 0.086575525 | AJ17: =AJ15/AI15-1 -> 0.1107025 | AK17: =AK15/AJ15-1 -> 0.017465141 | AL17: =AL15/AK15-1 -> 0.032292055 | AN17: =AN15/AL15-1 -> 0.13134877 | AO17: =AO15/AN15-1 -> 0.42545548 | AP17: =AP15/AO15-1 -> 0.050337214 | AQ17: =AQ15/AP15-1 -> -0.44264185 | AS17: =AS15/AQ15-1 -> -0.36054928 | AT17: =AT15/AS15-1 -> -0.066416659 | AU17: =AU15/AT15-1 -> 0.25906769 | AV17: =AV15/AU15-1 -> -0.058352791 | AX17: =AX15/AV15-1 -> 0.2440135 | AY17: =AY15/AX15-1 -> 0.14805674 | AZ17: =AZ15/AY15-1 -> -0.013321605 | BA17: =BA15/AZ15-1 -> -0.069158026 | BC17: =BC15/BA15-1 -> 0.25434551 | BD17: =BD15/BC15-1 -> 0.056656752 | BE17: =BE15/BD15-1 -> 0.028257713 | BF17: =BF15/BE15-1 -> -0.080437056 | BH17: =BH15/BF15-1 -> 0.050296738 | BI17: =BI15/BH15-1 -> 0.00623054 | BJ17: =BJ15/BI15-1 -> -0.059361518 | BK17: =BK15/BJ15-1 -> -0.072884188 | BM17: =BM15/BK15-1 -> 0.022352702 | BN17: =BN15/BM15-1 -> 0.025230005 | BO17: =BO15/BN15-1 -> 0.059016784 | BP17: =BP15/BO15-1 -> -0.0093476216 | BR17: =BR15/BP15-1 -> 0.043657797 | BS17: =BS15/BR15-1 -> 0.035750808 | BT17: =BT15/BS15-1 -> 0.077639043 | BU17: =BU15/BT15-1 -> -0.12243634 | BW17: =BW15/BU15-1 -> -0.12077195 | BX17: =BX15/BW15-1 -> -0.0095082556 | BY17: =BY15/BX15-1 -> -0.030313642 | BZ17: =BZ15/BY15-1 -> -0.1819426 | CB17: =CB15/BZ15-1 -> 0.074887039 | CC17: =CC15/CB15-1 -> 0.14269551 | CD17: =CD15/CC15-1 -> 0.010472536 | CE17: =CE15/CD15-1 -> -0.077780803 | CG17: =CG15/CE15-1 -> 0.21701826 | CH17: =CH15/CG15-1 -> 0.074678428 | CI17: =CI15/CH15-1 -> -0.00089897733 | CJ17: =CJ15/CI15-1 -> -0.015045888 | CL17: =CL15/CJ15-1 -> 0.093491817 | CM17: =CM15/CL15-1 -> 0.18488 | CN17: =CN15/CM15-1 -> 0.021180705 | CO17: =CO15/CN15-1 -> -0.023405248 | CQ17: =CQ15/CO15-1 -> 0.053600655 | CR17: =CR15/CQ15-1 -> -0.012767572 | CS17: =CS15/CR15-1 -> -0.021229636 | CT17: =CT15/CS15-1 -> -0.041345586 | CV17: =CV15/CT15-1 -> 0.052013627 | CW17: =CW15/CV15-1 -> -0.015964853 | CX17: =CX15/CW15-1 -> -0.021227833 | CY17: =CY15/CX15-1 -> -0.022807346
B19: Cash Cost of Goods Sold | J19: =J15-J31-J28-J21 -> 904.02335 | K19: =K15-K31-K28-K21 -> 993.3414 | L19: =L15-L31-L28-L21 -> 1030.4329 | M19: =M15-M31-M28-M21 -> 1097.3786 | N19: =N15-N31-N28-N21 -> 4025.1763 | O19: =O15-O31-O28-O21 -> 1314.9652 | P19: =P15-P31-P28-P21 -> 1360.0666 | Q19: =Q15-Q31-Q28-Q21 -> 1441.9925 | ... AL19: =AL15-AL31-AL28-AL21 -> 3504.325 | AM19: =SUM(AI19:AL19) -> 13053.371 | AN19: =AN15-AN31-AN28-AN21 -> 3948.519 | AO19: =AO15-AO31-AO28-AO21 -> 5739.43 | AP19: =AP15-AP31-AP28-AP21 -> 5848.358 | AQ19: =AQ15-AQ31-AQ28-AQ21 -> 3484.669 | AR19: =AR15-AR31-AR28-AR21 -> 19020.976 | AS19: =AS15-AS31-AS28-AS21 -> 2640.483 | AT19: =AT15-AT31-AT28-AT21 -> 2399.269 | AU19: =AU15-AU31-AU28-AU21 -> 2857.223 | ... CZ19: =CZ15-CZ31-CZ28-CZ21 -> 22224.191
C20: % of Revenue | J20: =J19/J15 -> 0.83656525 | K20: =K19/K15 -> 0.82914416 | L20: =L19/L15 -> 0.83875317 | M20: =M19/M15 -> 0.84767288 | N20: =N19/N15 -> 0.83826814 | O20: =O19/O15 -> 0.88832734 | P20: =P19/P15 -> 0.89450941 | Q20: =Q19/Q15 -> 0.89899146 | ... CZ20: =CZ19/CZ15 -> 0.84601184
B21: Depreciation & Amortization | J21: =J193 -> 75.715271 | K21: =K193 -> 76.304456 | L21: =L193 -> 76.16607 | M21: =M193 -> 78.915235 | N21: =N193 -> 307.10103 | O21: =O193 -> 91.459693 | P21: =P193 -> 91.57892 | Q21: =Q193 -> 90.864866 | ... AL21: =AL193 -> 113.839 | AM21: =Operations!AM186 -> 427.556 | AN21: =AN193 -> 123.073 | AO21: =AO193 -> 140.225 | AP21: =AP193 -> 142.049 | AQ21: =AQ193 -> 143.56 | AR21: =Operations!AR186 -> 548.907 | AS21: =AS193 -> 137.841 | AT21: =AT193 -> 140.635 | AU21: =AU193 -> 143.628 | AV21: =AV193 -> 144.319 | AW21: =Operations!AW186 -> 566.423 | AX21: =AX193 -> 146.104 | AY21: =AY193 -> 145.013 | AZ21: =AZ193 -> 147.368 | BA21: =BA193 -> 144.117 | BB21: =Operations!BB186 -> 582.602 | BC21: =BC193 -> 144.666 | BD21: =BD193 -> 146.073 | BE21: =BE193 -> 152.783 | BF21: =Operations!BF186 -> 146.878 | BG21: =Operations!BG186 -> 590.4 | BH21: =Operations!BH186 -> 147.922 | BI21: =Operations!BI186 -> 146.168 | BJ21: =Operations!BJ186 -> 154.118 | BK21: =Operations!BK186 -> 158.813 | BL21: =Operations!BL186 -> 607.021 | BM21: =Operations!BM186 -> 149.473 | ... CZ21: =Operations!CZ186 -> 696
C23: Total Cost of Goods Sold | J23: =J19+J21 -> 979.73862 | K23: =K19+K21 -> 1069.6459 | L23: =L19+L21 -> 1106.599 | M23: =M19+M21 -> 1176.2938 | N23: =N19+N21 -> 4332.2773 | O23: =O19+O21 -> 1406.4249 | P23: =P19+P21 -> 1451.6455 | Q23: =Q19+Q21 -> 1532.8574 | ... AL23: =AL19+AL21 -> 3618.164 | AM23: =SUM(AI23:AL23) -> 13480.927 | AN23: =AN19+AN21 -> 4071.592 | AO23: 5879.655 | AP23: 5990.407 | AQ23: =AQ19+AQ21 -> 3628.229 | AR23: =AR19+AR21 -> 19569.883 | AS23: =AS19+AS21 -> 2778.324 | AT23: =AT19+AT21 -> 2539.904 | AU23: =AU19+AU21 -> 3000.851 | AV23: =AV19+AV21 -> 2719.624 | AW23: =AW19+AW21 -> 11038.703 | AX23: =AX19+AX21 -> 3460.424 | ... CZ23: =CZ19+CZ21 -> 22920.191
B25: Gross Profit | J25: =J15-J23 -> 100.89836 | K25: =K15-K23 -> 128.38635 | L25: =L15-L23 -> 121.93041 | M25: =M15-M23 -> 118.28409 | N25: =N15-N23 -> 469.49921 | O25: =O15-O23 -> 73.846099 | P25: =P15-P23 -> 68.815396 | Q25: =Q15-Q23 -> 71.153977 | ... CZ25: =CZ15-CZ23 -> 3349.1705
B26: % of Revenue | J26: =J25/J15 -> 0.093369342 | K26: =K25/K15 -> 0.10716435 | L26: =L25/L15 -> 0.099249073 | M26: =M25/M15 -> 0.091368845 | N26: =N25/N15 -> 0.097776147 | O26: =O25/O15 -> 0.049886879 | P26: =P25/P15 -> 0.045259564 | Q26: =Q25/Q15 -> 0.044360021 | ... CK26: =CK25/CK15 -> 0.12875851 | CL26: =CL25/$AD$15 -> 0.21375607 | CM26: =CM25/CM15 -> 0.14552214 | CN26: =CN25/CN15 -> 0.14553821 | CO26: =CO25/CO15 -> 0.13873778 | CP26: =CP25/CP15 -> 0.14171289 | CQ26: =CQ25/$AD$15 -> 0.2776922 | CR26: =CR25/CR15 -> 0.13686748 | CS26: =CS25/CS15 -> 0.12758284 | CT26: =CT25/CT15 -> 0.11365595 | CU26: =CU25/CU15 -> 0.13033653 | CV26: =CV25/$AD$15 -> 0.23903537 | CW26: =CW25/CW15 -> 0.13111458 | CX26: =CX25/CX15 -> 0.1250148 | CY26: =CY25/CY15 -> 0.12843438 | CZ26: =CZ25/CZ15 -> 0.12749341
AE27: =SUM(AD28:AE28) -> 289.802 | AF27: =SUM(AD28:AF28) -> 450.266 | AG27: =SUM(AD28:AG28) -> 592.473
B28: Marketing, admin. & other | J28: 37.273774 | K28: 41.20652 | L28: 47.673315 | M28: =+N28-L28-K28-J28 -> 49.434738 | N28: 175.58835 | O28: =40.190832 -> 40.190832 | P28: =45.938117-P79 -> 41.238117 | Q28: =44.497217-Q79 -> 44.497217 | R28: 34.742869 | S28: =165.369035-S79 -> 160.66904 | T28: =77.399-T79 -> 77.399 | U28: 110.006 | V28: 131.573 | W28: =X28-T28-U28-V28 -> 96.052 | X28: =415.03 -> 415.03 | Y28: =125.429 -> 125.429 | Z28: 102.619 | AA28: 118.13 | AB28: =AC28-Y28-Z28-AA28 -> 147.382 | AC28: =493.56 -> 493.56 | AD28: =289.802-AE28 -> 143.2 | AE28: 146.602 | AF28: 160.464 | AG28: 142.207 | AH28: =SUM(AD28:AG28) -> 592.473 | AI28: 136.21 | AJ28: 148.925 | AK28: 145.47 | AL28: 147.159 | AM28: =SUM(AI28:AL28) -> 577.764 | AN28: 169.714 | AO28: 220.172 | AP28: 215.755 | AQ28: 145.343 | AR28: =SUM(AN28:AQ28) -> 750.984 | AS28: 125.376 | AT28: 106.925 | AU28: 105.913 | AV28: 92.605 | AW28: =SUM(AS28:AV28) -> 430.819 | AX28: 92.594 | AY28: 107.77 | AZ28: 88.866 | BA28: 102.145 | BB28: =SUM(AX28:BA28) -> 391.375 | BC28: 125.378 | BD28: 147.014 | BE28: 140.206 | BF28: 108.05 | BG28: =SUM(BC28:BF28) -> 520.648 | BH28: 107.119 | BI28: 112.528 | BJ28: 114.392 | BK28: 120.861 | BL28: =SUM(BH28:BK28) -> 454.9 | BM28: 116.225 | BN28: 123.15 | BO28: 125.126 | BP28: 117.403 | BQ28: =SUM(BM28:BP28) -> 481.904 | BR28: 133.434 | BS28: 132.813 | BT28: 152.604 | BU28: 127.347 | BV28: =SUM(BR28:BU28) -> 546.198 | BW28: 124.561 | BX28: 128.592 | BY28: 124.339 | BZ28: 89.197 | CA28: =SUM(BW28:BZ28) -> 466.689 | CB28: 109.745 | CC28: 161.711 | CD28: 169.223 | CE28: 156.082 | CF28: =SUM(CB28:CE28) -> 596.761 | CG28: 176.426 | CH28: 170.211 | CI28: 152.542 | CJ28: 168.102 | CK28: =SUM(CG28:CJ28) -> 667.281 | CL28: 182.96 | CM28: =CM15*CM29 -> 171.54562 | CN28: =CN15*CN29 -> 175.17907 | CO28: =CO15*CO29 -> 171.07896 | CP28: =SUM(CL28:CO28) -> 700.76365 | CQ28: =CQ15*CQ29 -> 180.24891 | CR28: =CR15*CR29 -> 177.94757 | CS28: =CS15*CS29 -> 174.1698 | CT28: =CT15*CT29 -> 166.96865 | CU28: =SUM(CQ28:CT28) -> 699.33493 | CV28: =CV15*CV29 -> 175.6533 | CW28: =CW15*CW29 -> 172.84902 | CX28: =CX15*CX29 -> 169.17981 | CY28: =CY15*CY29 -> 165.32127 | CZ28: =SUM(CV28:CY28) -> 683.00339
C29: Percent of sales | J29: =J28/J15 -> 0.03449241 | K29: =K28/K15 -> 0.034395169 | L29: =L28/L15 -> 0.038805188 | M29: =M28/M15 -> 0.038185989 | N29: =N28/N15 -> 0.036567372 | O29: =O28/O15 -> 0.027150996 | P29: =P28/P15 -> 0.027122116 | Q29: =Q28/Q15 -> 0.027741211 | ... AA29: =AA28/AA15 -> 0.039039483 | AB29: =AB28/$AD$15 -> 0.041573475 | AC29: =AC28/AC15 -> 0.038859935 | AD29: =AD28/AD15 -> 0.040393817 | AE29: =AE28/AE15 -> 0.038515113 | AF29: =AF28/AF15 -> 0.040817728 | AG29: =AG28/AG15 -> 0.040998504 | AH29: =AH28/AH15 -> 0.040164203 | AI29: =AI28/AI15 -> 0.036140662 | AJ29: =AJ28/AJ15 -> 0.035575988 | ... CL29: =CL28/CL15 -> 0.032856723 | CM29: 0.026 | CN29: 0.026 | CO29: 0.026 | CP29: =CP28/CP15 -> 0.027498242 | CQ29: 0.026 | CR29: 0.026 | CS29: 0.026 | CT29: 0.026 | CU29: =CU28/CU15 -> 0.026 | CV29: 0.026 | CW29: 0.026 | CX29: 0.026 | CY29: 0.026 | CZ29: =CZ28/CZ15 -> 0.026
C31: EBIT | J31: =J41 -> 63.62459 | K31: =K41 -> 87.179826 | L31: =L41 -> 74.257092 | M31: =M41 -> 68.849352 | N31: =N41 -> 293.91086 | O31: =O41 -> 33.655267 | P31: =P41 -> 27.577279 | Q31: =Q41 -> 26.65676 | ... AN31: =AN41 -> 732.963 | AO31: =AO25-AO28 -> 990.772 | AP31: =AP25-AP28 -> 1241.358 | AQ31: =AQ41 -> 377.364 | AR31: =AR41 -> 3342.457 | AS31: =AS41 -> -249.381 | AT31: =AT41 -> -168.801 | AU31: =AU41 -> 13.241 | AV31: =AV41 -> 125.715 | AW31: =AW41 -> -279.226 | AX31: =AX41 -> 101.824 | ... CZ31: =CZ41 -> 2666.1671
C32: % of Revenue | J32: =J31/J15 -> 0.058876932 | K32: =K31/K15 -> 0.072769184 | L32: =L31/L15 -> 0.060443886 | M32: =M31/M15 -> 0.053182856 | N32: =N31/N15 -> 0.061208775 | O32: =O31/O15 -> 0.022735882 | P32: =P31/P15 -> 0.018137447 | Q32: =Q31/Q15 -> 0.01661881 | ... CZ32: =CZ31/CZ15 -> 0.10149341
A34: Segment Operating Profit
B35: Steel | J35: =Operations!J100 -> 78.27694 | K35: =Operations!K100 -> 103.51966 | L35: =Operations!L100 -> 285.66838 | M35: =Operations!M100 -> -65.644732 | N35: =SUM(J35:M35) -> 401.82025 | O35: =Operations!O100 -> 54.568451 | P35: =Operations!P100 -> 55.017481 | Q35: =Operations!Q100 -> 54.420944 | R35: =Operations!R100 -> 45.393124 | S35: =SUM(O35:R35) -> 209.4 | T35: =Operations!T100 -> 235.267 | U35: =Operations!U100 -> 532.748 | V35: =Operations!V100 -> 795.434 | W35: =Operations!W100 -> 627.886 | X35: =SUM(T35:W35) -> 2191.335 | Y35: =Operations!Y100 -> 658.135 | Z35: =Operations!Z100 -> 524.239 | AA35: =Operations!AA100 -> 488.892 | AB35: =Operations!AB100 -> 536.355 | AC35: =SUM(Y35:AB35) -> 2207.621 | AD35: =Operations!AD100 -> 731.438 | AE35: =Operations!AE100 -> 836.913 | AF35: =Operations!AF100 -> 905.595 | AG35: =Operations!AG100 -> 720.714 | AH35: =SUM(AD35:AG35) -> 3194.66 | AI35: =Operations!AI100 -> 735.329 | AJ35: =Operations!AJ100 -> 667.465 | AK35: =Operations!AK100 -> 744.51 | AL35: =Operations!AL100 -> 706.848 | AM35: =SUM(AI35:AL35) -> 2854.152 | AN35: =Operations!AN100 -> 799.284 | AO35: =Operations!AO100 -> 1040.582 | AP35: =Operations!AP100 -> 1223.035 | AQ35: =Operations!AQ100 -> 541.88 | AR35: =SUM(AN35:AQ35) -> 3604.781 | AS35: =Operations!AS100 -> -223.875 | AT35: =Operations!AT100 -> -205.426 | AU35: =Operations!AU100 -> -55.914 | AV35: =Operations!AV100 -> 134.843 | AW35: =SUM(AS35:AV35) -> -350.372 | AX35: =Operations!AX100 -> 158.5 | AY35: =Operations!AY100 -> 262.147 | AZ35: =Operations!AZ100 -> 231.803 | BA35: =Operations!BA100 -> 126.496 | BB35: =SUM(AX35:BA35) -> 778.946 | BC35: =Operations!BC100 -> 312.578 | BD35: =Operations!BD100 -> 626.84 | BE35: =Operations!BE100 -> 436.196 | BF35: =Operations!BF100 -> 328.319 | BG35: =SUM(BC35:BF35) -> 1703.933 | BH35: =Operations!BH100 -> 390.292 | BI35: =Operations!BI100 -> 336.096 | BJ35: =Operations!BJ100 -> 217.43 | BK35: =Operations!BK100 -> 217.631 | BL35: =SUM(BH35:BK35) -> 1161.449 | BM35: =Operations!BM100 -> 272.258 | BN35: =Operations!BN100 -> 237.102 | BO35: =Operations!BO100 -> 310.591 | BP35: =Operations!BP100 -> 336.764 | BQ35: =SUM(BM35:BP35) -> 1156.715 | BR35: =Operations!BR100 -> 326.797 | BS35: =Operations!BS100 -> 368.138 | BT35: =Operations!BT100 -> 515.203 | BU35: =Operations!BU100 -> 405.714 | BV35: =SUM(BR35:BU35) -> 1615.852 | BW35: =Operations!BW100 -> 217.128 | BX35: =Operations!BX100 -> 198.5 | BY35: =Operations!BY100 -> 260.776 | BZ35: =Operations!BZ100 -> 105.852 | CA35: =SUM(BW35:BZ35) -> 782.256 | CB35: =Operations!CB100 -> 279.835 | CC35: =Operations!CC100 -> 530.727 | CD35: =Operations!CD100 -> 593.149 | CE35: =Operations!CE100 -> 284.857 | CF35: =SUM(CB35:CE35) -> 1688.568 | CG35: =Operations!CG100 -> 644.183 | CH35: =Operations!CH100 -> 582.366 | CI35: =Operations!CI100 -> 397.718 | CJ35: =Operations!CJ100 -> 314.958 | CK35: =SUM(CG35:CJ35) -> 1939.225 | CL35: =Operations!CL100 -> 560.503 | CM35: =Operations!CM100 -> 855.35708 | CN35: =Operations!CN100 -> 872.38394 | CO35: =Operations!CO100 -> 770.06594 | CP35: =SUM(CL35:CO35) -> 3058.31 | CQ35: =Operations!CQ100 -> 864.66839 | CR35: =Operations!CR100 -> 834.43615 | CS35: =Operations!CS100 -> 713.13179 | CT35: =Operations!CT100 -> 543.36478 | CU35: =SUM(CQ35:CT35) -> 2955.6011 | CV35: =Operations!CV100 -> 668.93457 | CW35: =Operations!CW100 -> 703.55548 | CX35: =Operations!CX100 -> 589.82848 | CY35: =Operations!CY100 -> 571.4643 | CZ35: =SUM(CV35:CY35) -> 2533.7828
B36: Steel Products | J36: -3.12629 | K36: 1.848145 | L36: -2.708706 | M36: 3.579362 | N36: =SUM(J36:M36) -> -0.407489 | O36: =Operations!O148 -> -9.147654 | P36: =Operations!P148 -> -3.099034 | Q36: =Operations!Q148 -> -3.472486 | R36: =Operations!R148 -> 1.391174 | S36: =SUM(O36:R36) -> -14.328 | T36: =Operations!T148 -> 5.836 | U36: =Operations!U148 -> 31.532 | V36: =Operations!V148 -> 56.182 | W36: =Operations!W148 -> 56.06 | X36: =SUM(T36:W36) -> 149.61 | Y36: =Operations!Y148 -> 46.615 | Z36: =Operations!Z148 -> 45.756 | AA36: =Operations!AA148 -> 44.213 | AB36: =Operations!AB148 -> 44.172 | AC36: =SUM(Y36:AB36) -> 180.756 | AD36: =Operations!AD148 -> 41.768 | AE36: =Operations!AE148 -> 47.702 | AF36: =Operations!AF148 -> 53.003 | AG36: =Operations!AG148 -> 49.041 | AH36: =SUM(AD36:AG36) -> 191.514 | AI36: =Operations!AI148 -> 51.095 | AJ36: =Operations!AJ148 -> 69.632 | AK36: =Operations!AK148 -> 86.872 | AL36: =Operations!AL148 -> 94.563 | AM36: =SUM(AI36:AL36) -> 302.162 | AN36: =Operations!AN148 -> 50.186 | AO36: =Operations!AO148 -> 100.263 | AP36: =Operations!AP148 -> 100.034 | AQ36: =Operations!AQ148 -> 45.401 | AR36: =SUM(AN36:AQ36) -> 295.884 | AS36: =Operations!AS148 -> -33.576 | AT36: =Operations!AT148 -> -17.649 | AU36: =Operations!AU148 -> -19.723 | AV36: =Operations!AV148 -> -41.852 | AW36: =SUM(AS36:AV36) -> -112.8 | AX36: =Operations!AX148 -> -67.696 | AY36: =Operations!AY148 -> -35.295 | AZ36: =Operations!AZ148 -> -40.826 | BA36: =Operations!BA148 -> -29.616 | BB36: =SUM(AX36:BA36) -> -173.433 | BC36: =Operations!BC148 -> -35.895 | BD36: =Operations!BD148 -> -10.01 | BE36: =Operations!BE148 -> -10.527 | BF36: =Operations!BF148 -> -3.85 | BG36: =SUM(BC36:BF36) -> -60.282 | BH36: =Operations!BH148 -> -33.044 | BI36: =Operations!BI148 -> 9.202 | BJ36: =Operations!BJ148 -> 35.548 | BK36: =Operations!BK148 -> 16.954 | BL36: =SUM(BH36:BK36) -> 28.66 | BM36: =Operations!BM148 -> -11.924 | BN36: =Operations!BN148 -> 32.073 | BO36: =Operations!BO148 -> 24.909 | BP36: =Operations!BP148 -> 37.071 | BQ36: =SUM(BM36:BP36) -> 82.129 | BR36: =Operations!BR148 -> 1.72 | BS36: =Operations!BS148 -> 42.612 | BT36: =Operations!BT148 -> 63.89 | BU36: =Operations!BU148 -> 58.101 | BV36: =SUM(BR36:BU36) -> 166.323 | BW36: =Operations!BW148 -> 32.458 | BX36: =Operations!BX148 -> 70.636 | BY36: =Operations!BY148 -> 96.167 | BZ36: =Operations!BZ148 -> 76.787 | CA36: =SUM(BW36:BZ36) -> 276.048 | CB36: =Operations!CB148 -> 42.367 | CC36: =Operations!CC148 -> 82.946 | CD36: =Operations!CD148 -> 72.578 | CE36: =Operations!CE148 -> 52.079 | CF36: =SUM(CB36:CE36) -> 249.97 | CG36: =Operations!CG148 -> 66.919 | CH36: =Operations!CH148 -> 80.809 | CI36: =Operations!CI148 -> 94.225 | CJ36: =Operations!CJ148 -> 109.849 | CK36: =SUM(CG36:CJ36) -> 351.802 | CL36: =Operations!CL148 -> 85.814 | CM36: =Operations!CM148 -> 99.013477 | CN36: =Operations!CN148 -> 93.70928 | CO36: =Operations!CO148 -> 93.59999 | CP36: =SUM(CL36:CO36) -> 372.13675 | CQ36: =Operations!CQ148 -> 86.744473 | CR36: =Operations!CR148 -> 75.557683 | CS36: =Operations!CS148 -> 80.018937 | CT36: =Operations!CT148 -> 84.618227 | CU36: =SUM(CQ36:CT36) -> 326.93932 | CV36: =Operations!CV148 -> 92.788095 | CW36: =Operations!CW148 -> 105.54305 | CX36: =Operations!CX148 -> 126.99819 | CY36: =Operations!CY148 -> 139.63543 | CZ36: =SUM(CV36:CY36) -> 464.96477
B37: Raw Materials | AN37: =Operations!AN168 -> 16.756 | AO37: =Operations!AO168 -> 115.624 | AP37: =Operations!AP168 -> 135.505 | AQ37: =Operations!AQ168 -> -106.159 | AR37: =Operations!AR168 -> 161.726 | AS37: =Operations!AS168 -> -31.537 | AT37: =Operations!AT168 -> -31.621 | AU37: =Operations!AU168 -> 2.885 | AV37: =Operations!AV168 -> -16.692 | AW37: =SUM(AS37:AV37) -> -76.965 | AX37: =Operations!AX168 -> 32.784 | AY37: =Operations!AY168 -> 53.769 | AZ37: =Operations!AZ168 -> 7.444 | BA37: =Operations!BA168 -> 12.32 | BB37: =Operations!BB168 -> 106.317 | BC37: =Operations!BC168 -> 57.358 | BD37: =Operations!BD168 -> 51.922 | BE37: =Operations!BE168 -> 22.481 | ... BP37: =Operations!BP168 -> 0.425 | BQ37: =SUM(BM37:BP37) -> 27.686 | BR37: =Operations!BR168 -> 8.359 | BS37: =Operations!BS168 -> -9.635 | BT37: =Operations!BT168 -> -19.321 | BU37: =Operations!BU168 -> -8.456 | BV37: =SUM(BR37:BU37) -> -29.053 | BW37: =Operations!BW168 -> -41.497 | BX37: =Operations!BX168 -> -38.104 | BY37: =Operations!BY168 -> -43.117 | BZ37: =Operations!BZ168 -> -77.087 | CA37: =SUM(BW37:BZ37) -> -199.805 | CB37: =Operations!CB168 -> -63.372 | CC37: =Operations!CC168 -> -27.181 | CD37: =Operations!CD168 -> 14.313 | CE37: =Operations!CE168 -> -18.881 | CF37: =SUM(CB37:CE37) -> -95.121 | CG37: =Operations!CG168 -> 26.391 | CH37: =Operations!CH168 -> 66.227 | CI37: =Operations!CI168 -> 9.957 | CJ37: =Operations!CJ168 -> 26.721 | CK37: =SUM(CG37:CJ37) -> 129.296 | CL37: =Operations!CL168 -> 74.547 | CM37: =Operations!CM168 -> 35.234508 | CN37: =Operations!CN168 -> 44.324432 | CO37: =Operations!CO168 -> 59.109662 | CP37: =SUM(CL37:CO37) -> 213.2156 | CQ37: =Operations!CQ168 -> 55.981086 | CR37: =Operations!CR168 -> 44.890939 | CS37: =Operations!CS168 -> 54.922319 | CT37: =Operations!CT168 -> 62.622952 | CU37: =SUM(CQ37:CT37) -> 218.4173 | CV37: =Operations!CV168 -> 67.22722 | CW37: =Operations!CW168 -> 55.042845 | CX37: =Operations!CX168 -> 66.063988 | CY37: =Operations!CY168 -> 74.524416 | CZ37: =SUM(CV37:CY37) -> 262.85847
B38: Corporate & Other Expense | J38: =30.962295+2.912045+29.75025-J35-J36-J39 -> -6.01756 | K38: =89.607302-29.9+24.46876+3.003764-K35-K36-K39 -> -12.679475 | L38: =59.5918+12.00501+2.660282-L35-L36-L39 -> -201.00259 | M38: =+N38-L38-K38-J38 -> 146.51472 | N38: =230.053015-29.9+79.471911+14.285934-N35-N36-N39 -> -73.184899 | O38: =22.649759-2.300855+6.23908+7.067283-O35-O36-O39 -> -5.36553 | P38: =9.48409+4.346126+6.547063-P35-P36+7.2-P39 -> -17.841168 | Q38: =1604.011344-1532.857367-44.497217-Q35-Q36-Q39 -> 2.308302 | R38: =15.819595-4.411545+7.166677+4.6432-R35-R36-R39 -> 51.933629 | S38: =SUM(O38:R38) -> 31.035233 | T38: =176.784-1.596+10.798+6.662-T35-T36-T39 -> -16.255 | U38: =396.296+15.488+6.116-U35-U36+13.2-U39 -> -66.08 | V38: =635.387+34.061+5.053-V35-V36-V39 -> -53.015 | W38: =522.809+20.547+4.521-W35-W36-W39 -> 16.431 | X38: =SUM(T38:W38) -> -118.919 | Y38: =3322.621-2620.628-125.429-Y35-Y36-Y39 -> -154.286 | Z38: =499.436+20.515+2.341-Z35-Z36-Z39 -> -117.603 | AA38: =446.668+0.922+24.915-AA35-AA36-AA39 -> -112.6 | AB38: =519.798+34.079-3.195-AB35-AB36-AB39 -> -33.445 | AC38: =2016.368-9.2+110.674+4.201-AC35-AC36-AC39 -> -417.934 | AD38: =588.261-5.732+40.326-AD35-AD36-AD39 -> -141.351 | AE38: =694.755-9.588+48.606-AE35-AE36-AE39 -> -135.342 | AF38: =844.188-AF35-AF36-AF39 -> -93.91 | AG38: =615.285-11.612+71.185-AG35-AG36-AG39 -> -134.497 | AH38: =SUM(AD38:AG38) -> -505.1 | AI38: =589.667+60.572-9.162-AI35-AI36-AI39 -> -120.847 | AJ38: =532.714+77.587+4.979-AJ36-AJ35-AJ39 -> -55.317 | AK38: =4259.221-3449.26-145.47-AK35-AK36-AK39 -> -155.891 | AL38: =4396.76-3618.164-147.159-AL36-AL35-AL39 -> -77.674 | AM38: =SUM(AI38:AL38) -> -409.729 | AN38: =AN15-4071.592-169.714-AN36-AN35-AN37-AN39 -> -64.263 | AO38: =AO41-AO35-AO36-AO37-AO39 -> -51.697 | AP38: =AP41-AP35-AP36-AP37-AP39 -> -77.216 | AQ38: =AQ41-AQ35-AQ36-AQ37-AQ39 -> -184.958 | AR38: =SUM(AN38:AQ38) -> -378.134 | AS38: =AS41-AS35-AS36-AS37-AS39 -> -65.393 | AT38: =AT41-AT35-AT36-AT37-AT39 -> -39.105 | AU38: =AU41-AU35-AU36-AU37-AU39 -> -34.007 | AV38: =AV41-AV35-AV36-AV37-AV39 -> -67.484 | AW38: =SUM(AS38:AV38) -> -205.989 | AX38: =AX41-SUM(AX35:AX37,AX39) -> 2.236 | AY38: =AY41-SUM(AY35:AY37,AY39) -> -20.726 | AZ38: =AZ41-SUM(AZ35:AZ37,AZ39) -> -52.729 | BA38: =BA41-SUM(BA35:BA37,BA39) -> -46.403 | BB38: =SUM(AX38:BA38) -> -117.622 | BC38: =BC41-SUM(BC35:BC37,BC39) -> 5.78 | BD38: =BD41-SUM(BD35:BD37,BD39) -> -116.281 | BE38: =BE41-SUM(BE35:BE37,BE39) -> -95.742 | BF38: =BF41-SUM(BF35:BF37,BF39) -> -55.731 | BG38: =SUM(BC38:BF38) -> -261.974 | BH38: =BH41-SUM(BH35:BH37,BH39) -> -90.586 | BI38: =BI41-SUM(BI35:BI37,BI39) -> -64.67 | BJ38: =BJ41-SUM(BJ35:BJ37,BJ39) -> -73.633 | BK38: =BK41-SUM(BK35:BK37,BK39) -> -46.269 | BL38: =SUM(BH38:BK38) -> -275.158 | BM38: =BM41-SUM(BM35:BM37,BM39) -> -58.051 | BN38: =BN41-SUM(BN35:BN37,BN39) -> -89.833 | BO38: =BO41-SUM(BO35:BO37,BO39) -> -67.338 | BP38: =BP41-SUM(BP35:BP37,BP39) -> -81.89 | BQ38: =SUM(BM38:BP38) -> -297.112 | BR38: =BR41-SUM(BR35:BR37,BR39) -> -65.134 | BS38: =BS41-SUM(BS35:BS37,BS39) -> -114.859 | BT38: =BT41-SUM(BT35:BT37,BT39) -> -112.438 | BU38: =BU41-SUM(BU35:BU37,BU39) -> -122.658 | BV38: =SUM(BR38:BU38) -> -415.089 | BW38: =BW41-SUM(BW35:BW37,BW39) -> -61.127 | BX38: =BX41-SUM(BX35:BX37,BX39) -> -68.124 | BY38: =BY41-SUM(BY35:BY37,BY39) -> -51.214 | BZ38: =BZ41-SUM(BZ35:BZ37,BZ39) -> -24.932 | CA38: =SUM(BW38:BZ38) -> -205.397 | CB38: =CB41-SUM(CB35:CB37,CB39) -> -44.882 | CC38: =CC41-SUM(CC35:CC37,CC39) -> -156.124 | CD38: =CD41-SUM(CD35:CD37,CD39) -> -151.459 | CE38: =CE41-SUM(CE35:CE37,CE39) -> -57.786 | CF38: =SUM(CB38:CE38) -> -410.251 | CG38: =CG41-SUM(CG35:CG37,CG39) -> -135.113 | CH38: =CH41-SUM(CH35:CH37,CH39) -> -176.686 | CI38: =CI41-SUM(CI35:CI37,CI39) -> -80.935 | CJ38: =CJ41-SUM(CJ35:CJ37,CJ39) -> -87.202 | CK38: =SUM(CG38:CJ38) -> -479.936 | CL38: =CL41-SUM(CL35:CL37,CL39) -> -146.038 | CM38: =-0.235*CM35 -> -201.00891 | CN38: =-0.235*CN35 -> -205.01023 | CO38: =-0.235*CO35 -> -180.9655 | CP38: =SUM(CL38:CO38) -> -733.02264 | CQ38: =-0.235*CQ35 -> -203.19707 | CR38: =-0.235*CR35 -> -196.09249 | CS38: =-0.235*CS35 -> -167.58597 | CT38: =-0.235*CT35 -> -127.69072 | CU38: =SUM(CQ38:CT38) -> -694.56626 | CV38: =-0.235*CV35 -> -157.19962 | CW38: =-0.235*CW35 -> -165.33554 | CX38: =-0.235*CX35 -> -138.60969 | CY38: =-0.235*CY35 -> -134.29411 | CZ38: =SUM(CV38:CY38) -> -595.43896
B39: LIFO Credit (Charge) | J39: -5.5085 | K39: -5.5085 | L39: -7.7 | M39: -15.6 | N39: -34.317 | O39: -6.4 | P39: -6.5 | Q39: -26.6 | R39: -75.5 | S39: -115 | T39: -32.2 | U39: -67.1 | V39: -124.1 | W39: -152.5 | X39: -375.9 | Y39: 26.1 | Z39: 69.9 | AA39: 52 | AB39: 3.6 | AC39: 151.6 | AD39: -9 | AE39: -15.5 | AF39: -20.5 | AG39: 39.6 | AH39: -5.4 | AI39: -24.5 | AJ39: -66.5 | AK39: -11 | AL39: -92.3 | AM39: -194.3 | AN39: -69 | AO39: -214 | AP39: -140 | AQ39: 81.2 | AR39: -341.8 | AS39: 105 | AT39: 125 | AU39: 120 | AV39: 116.9 | AW39: =SUM(AS39:AV39) -> 466.9 | AX39: -24 | AY39: -67 | AZ39: -50 | BA39: -23 | BB39: =SUM(AX39:BA39) -> -164 | BC39: -31 | BD39: -32 | BE39: =-28 -> -28 | BF39: -51.8 | BG39: =SUM(BC39:BF39) -> -142.8 | BH39: -14.5 | BJ39: 84 | BK39: 71.9 | BL39: =SUM(BH39:BK39) -> 141.4 | BM39: -18 | BN39: 0 | BO39: 18 | BP39: -17.4 | BQ39: =SUM(BM39:BP39) -> -17.4 | BR39: -14.5 | BS39: 0 | BT39: 14.5 | BU39: 57.3 | BV39: =SUM(BR39:BU39) -> 57.3 | BW39: 16.5 | BX39: 95.5 | BY39: 137 | BZ39: 217.8 | CA39: =SUM(BW39:BZ39) -> 466.8 | CB39: -27.5 | CC39: -19 | CD39: -59.3 | CE39: 0 | CF39: =SUM(CB39:CE39) -> -105.8 | CG39: 0 | CH39: 0 | CI39: 0 | CJ39: 0 | CK39: =SUM(CG39:CJ39) -> 0 | CL39: 0 | CM39: 0 | CN39: 0 | CO39: 0 | CP39: =SUM(CL39:CO39) -> 0 | CQ39: 0 | CR39: 0 | CS39: 0 | CT39: 0 | CU39: =SUM(CQ39:CT39) -> 0 | CV39: 0 | CW39: 0 | CX39: 0 | CY39: 0 | CZ39: =SUM(CV39:CY39) -> 0
