Workbook
Name AdditionalInstructions: IndexInformation!$B$42
Name Address: ImportantDisclosures!$A$2:$A$2
Name ANA: ModPubIndex!$A$7
Name Authors: ImportantDisclosures!$A$7
Name Authors: IndexInformation!$B$18
Name BRO: ModPubIndex!$A$1
Name BSMethod: 2
Name calc: 'Deals and Terms'!calc
Name calc: 'Financings and Debt info'!calc
Name calc: Revs!calc
Name calc: 'Deals and Terms'!calc
Name cmdOK2_click: [5]!cmdOK2_click
Name cmdOK2_click: [5]!cmdOK2_click
Name CopyrightStamp: ImportantDisclosures!$A$27
Name COU: ModPubIndex!$A$5
Name CQEnd: IndexInformation!$B$31
Name Currency: IndexInformation!$B$24
Name CurrentStockPrice: IndexInformation!$B$23
Name CurrQtrEPS: IndexInformation!$B$29
Name CurrYearEPS: IndexInformation!$B$11
Name CurrYearTotalRevenue: IndexInformation!$B$10
Name CurrYearTotalRevenueActual: IndexInformation!$B$32
Name CUSIP: IndexInformation!$B$20
Name CYEnd: IndexInformation!$B$30
Name DATA_NEW: [6]Input!$H$6:$BE$465
Name dataseries4: OFFSET([7]c1!$G$12,0,0,COUNTA([7]c1!$G$12:$G$31),1)
Name Date: ImportantDisclosures!$A$8
Name Deleted: IndexInformation!$B$27
Name Description: IndexInformation!$B$7
Name DEVELOPMENT: 5
Name Discipline: IndexInformation!$B$3
Name DISCIPLINE: ModPubIndex!$A$12
Name Disclosure: [8]Input!$H$6:$BE$465
Name DisclosuresText: ImportantDisclosures!$A$22
Name Distribution: IndexInformation!$B$26
Name DistTable: ImportantDisclosures!#REF!
Name DistTablePreamble: ImportantDisclosures!#REF!
Name DOCDAT: ModPubIndex!$A$2
Name DOCTIME: ModPubIndex!$A$3
Name DocType: IndexInformation!$B$5
Name Drugs: 'Deals and Terms'!Drugs
Name Drugs: 'Financings and Debt info'!Drugs
Name Drugs: Revs!Drugs
Name Drugs: 'Deals and Terms'!Drugs
Name EMAIL_ALERT: ModPubIndex!$A$10
Name EmailAlert: IndexInformation!$B$28
Name FiveYearGrowthRate: IndexInformation!$B$16
Name FollowingYearEPS: IndexInformation!$B$15
Name FollowingYearTotalRevenue: IndexInformation!$B$14
Name FollowingYearTotalRevenueActual: IndexInformation!$B$34
Name FR_CODE_COPY_LINK: " "
Name FR_CODE_DOWNLOAD_START: " "
Name FR_CODE_STOCK_LINK: " "
Name FR_COM_ABBR: "CHKP"
Name FR_COM_AGG: 0
Name FR_COU_ABBR: "usa"
Name FR_COU_NAME_LINK: " "
Name FR_DATABOX_DOWNLOAD: "N"
Name FR_DISP_HIDDEN: FALSE
Name FR_END_DATE: "'"

Sheet ImportantDisclosures
A2: 1585 Broadway
A3: New York, NY 10036-8293
A4: United States
A5: Tel: +1 (1)212 761 4000
A7: Authors: Matthew Harrison
A8: Date: 16 Apr 2018
A10: Ticker: VRTX.O
A11: Stock Rating: Overweight
A12: Industry: Biotechnology
A13: Industry View: In-Line
A14: Price as of 16 Apr 2018: 159.56
A15: Target Price: 200
... A120: Equal-weight and Not-Rated to hold and Underweight to sell recommendations, respectively.
B122: Coverage Universe | D122: Investment Banking Clients (IBC) | G122: Other Material Investment Services Clients (MISC)
A123: Stock Rating Category | B123: Count | C123: % of Total | D123: Count | E123: % of Total IBC | F123: % of Rating Category | G123: Count | H123: % of Total Other MISC
A124: Overweight/Buy | B124: 1189 | C124: 0.38 | D124: 315 | E124: 0.41 | F124: 0.26 | G124: 555 | H124: 0.39
A125: Equal-weight/Hold | B125: 1355 | C125: 0.43 | D125: 364 | E125: 0.47 | F125: 0.27 | G125: 644 | H125: 0.45
A126: Not-Rated/Hold | B126: 53 | C126: 0.02 | D126: 4 | E126: 0.01 | F126: 0.08 | G126: 7 | H126: 0
A127: Underweight/Sell | B127: 545 | C127: 0.17 | D127: 84 | E127: 0.11 | F127: 0.15 | G127: 214 | H127: 0.15
A128: Total | B128: 3142 | D128: 767 | G128: 1420
A130: Data include common stock and ADRs currently assigned ratings. Investment Banking Clients are companies
A131: from whom Morgan Stanley received investment banking compensation in the last 12 months. Due to rounding
A132: off of decimals, the percentages provided in the "% of total" column may not add up to exactly 100
A133: percent.
A135: Analyst Stock Ratings
A137: Overweight (O). The stock's total return is expected to exceed the average total return of the analyst's
A138: industry (or industry team's) coverage universe, on a risk-adjusted basis, over the next 12-18 months.
A140: Equal-weight (E). The stock's total return is expected to be in line with the average total return of
A141: the analyst's industry (or industry team's) coverage universe, on a risk-adjusted basis, over the next
A142: 12-18 months.
A144: Not-Rated (NR). Currently the analyst does not have adequate conviction about the stock's total return
A145: relative to the average total return of the analyst's industry (or industry team's) coverage universe,
... A388: © Copyright 2018 Morgan Stanley

Sheet DCF
B3: ($ in millions) | E3: 2015 | F3: =E3+1 -> 2016 | G3: =F4+1 -> 2017 | H3: =G3+1 -> 2018 | I3: =H3+1 -> 2019 | J3: =I3+1 -> 2020 | K3: =J3+1 -> 2021 | L3: =K3+1 -> 2022 | M3: =L3+1 -> 2023 | N3: =M3+1 -> 2024 | O3: =N3+1 -> 2025 | ... T3: =S3+1 -> 2030 | U3: Terminal
F4: =E3+1 -> 2016 | U4: =T3+1 -> 2031
B5: Non-GAAP EBIT | E5: =IS!V41 -> -265.899 | F5: =IS!AA41 -> 210.893 | G5: =IS!AF41 -> 501.326 | H5: =IS!AK41 -> 767.36771 | I5: =IS!AP41 -> 917.00412 | J5: =IS!AU41 -> 1840.756 | K5: =IS!AZ41 -> 3006.2752 | L5: =IS!BE41 -> 3790.1287 | M5: =IS!BJ41 -> 4222.4732 | N5: =IS!BO41 -> 4528.4506 | O5: =IS!BT41 -> 5385.8072 | P5: =IS!BY41 -> 7005.921 | Q5: =IS!CD41 -> 7362.9783 | R5: =IS!CI41 -> 7769.2531 | S5: =IS!CN41 -> 8095.4751 | T5: =IS!CS41 -> 8542.5074
B6: Growth | F6: =IF(E5<0,"NM",F5/E5-1) -> NM | G6: =IF(F5<0,"NM",G5/F5-1) -> 1.3771581 | H6: =IF(G5<0,"NM",H5/G5-1) -> 0.53067607 | I6: =IF(H5<0,"NM",I5/H5-1) -> 0.19499962 | J6: =IF(I5<0,"NM",J5/I5-1) -> 1.0073585 | K6: =IF(J5<0,"NM",K5/J5-1) -> 0.6331742 | L6: =IF(K5<0,"NM",L5/K5-1) -> 0.26073912 | M6: =IF(L5<0,"NM",M5/L5-1) -> 0.11407119 | ... T6: =IF(S5<0,"NM",T5/S5-1) -> 0.055220013
B8: Taxes | E8: =IS!V42 -> 0.65 | F8: =IS!AA42 -> -0.079 | G8: =IS!AF42 -> 6.766 | H8: =IS!AK42 -> 0 | I8: =IS!AP42 -> 0 | J8: =IS!AU42 -> 0 | K8: =IS!AZ42 -> 0 | L8: =IS!BE42 -> 643.73552 | M8: =IS!BJ42 -> 855.15675 | N8: =IS!BO42 -> 920.94188 | O8: =IS!BT42 -> 1105.2735 | P8: =IS!BY42 -> 1453.598 | Q8: =IS!CD42 -> 1530.3653 | R8: =IS!CI42 -> 1617.7144 | S8: =IS!CN42 -> 1687.8522 | T8: =IS!CS42 -> 1783.9641
B9: Tax rate | H9: =H8/H5 -> 0 | I9: =I8/I5 -> 0 | J9: =J8/J5 -> 0 | K9: =K8/K5 -> 0 | L9: =L8/L5 -> 0.16984529 | M9: =M8/M5 -> 0.20252508 | N9: =N8/N5 -> 0.20336799 | O9: =O8/O5 -> 0.20521966 | ... T9: =T8/T5 -> 0.20883378
B10: Non-GAAP EBIT, after tax | E10: =E5-E8 -> -266.549 | F10: =F5-F8 -> 210.972 | G10: =G5-G8 -> 494.56 | H10: =H5-H8 -> 767.36771 | I10: =I5-I8 -> 917.00412 | J10: =J5-J8 -> 1840.756 | K10: =K5-K8 -> 3006.2752 | L10: =L5-L8 -> 3146.3932 | ... T10: =T5-T8 -> 6758.5433
B11: Plus: D&A | E11: =CF!I7 -> 62.343 | F11: =CF!J7 -> 61.398 | G11: =CF!K7 -> 62.822322 | H11: =CF!L7 -> 65.128658 | I11: =CF!M7 -> 67.341659 | J11: =CF!N7 -> 70.06428 | K11: =CF!O7 -> 70.633066 | L11: =CF!P7 -> 68.592163 | ... T11: =CF!X7 -> 55.54057
B12: Plus/Less: Change in non-Cash WC | E12: =((BS!E10-BS!E5-BS!E6)-BS!E25)-((BS!D10-BS!D5-BS!D6)-BS!D25) -> 67.191 | F12: =((BS!F10-BS!F5-BS!F6)-BS!F25)-((BS!E10-BS!E5-BS!E6)-BS!E25) -> -253.896 | G12: =((BS!G10-BS!G5-BS!G6)-BS!G25)-((BS!F10-BS!F5-BS!F6)-BS!F25) -> 148.591 | H12: =((BS!H10-BS!H5-BS!H6)-BS!H25)-((BS!G10-BS!G5-BS!G6)-BS!G25) -> 197.61204 | I12: =((BS!I10-BS!I5-BS!I6)-BS!I25)-((BS!H10-BS!H5-BS!H6)-BS!H25) -> 19.447086 | J12: =((BS!J10-BS!J5-BS!J6)-BS!J25)-((BS!I10-BS!I5-BS!I6)-BS!I25) -> 213.00661 | K12: =((BS!K10-BS!K5-BS!K6)-BS!K25)-((BS!J10-BS!J5-BS!J6)-BS!J25) -> 269.7896 | L12: =((BS!L10-BS!L5-BS!L6)-BS!L25)-((BS!K10-BS!K5-BS!K6)-BS!K25) -> 175.10691 | ... O12: =((BS!O10-BS!O5-BS!O6)-BS!O25)-((BS!N10-BS!N5-BS!N6)-BS!N25) -> 176.92824 | P12: =O12*1.1 -> 194.62106 | Q12: =P12*1.1 -> 214.08317 | R12: =Q12*1.1 -> 235.49149 | S12: =R12*1.1 -> 259.04063 | T12: =S12*1.1 -> 284.9447
B13: Less: Capital expenditures | E13: =CF!I27 -> -45.302 | F13: =CF!J27 -> -56.563 | G13: =CF!K27 -> -99.421 | H13: =CF!L27 -> -93.060137 | I13: =CF!M27 -> -90.676213 | J13: =CF!N27 -> -108.68412 | K13: =CF!O27 -> -144.23648 | L13: =CF!P27 -> -166.55293 | ... T13: =CF!X27 -> -211.08949
B14: Free Cash Flow to Firm (FCFF) | E14: =SUM(E10:E13) -> -182.317 | F14: =SUM(F10:F13) -> -38.089 | G14: =SUM(G10:G13) -> 606.55232 | H14: =SUM(H10:H13) -> 937.04827 | I14: =SUM(I10:I13) -> 913.11665 | J14: =SUM(J10:J13) -> 2015.1428 | K14: =SUM(K10:K13) -> 3202.4614 | L14: =SUM(L10:L13) -> 3223.5393 | ... T14: =SUM(T10:T13) -> 6887.9391 | U14: =T14*(1+C25)/(C23-C25) -> 72867.145
B15: YoY Growth | G15: =G14/F14-1 -> -16.924606 | H15: =H14/G14-1 -> 0.54487625 | I15: =I14/H14-1 -> -0.025539369 | J15: =J14/I14-1 -> 1.2068842 | K15: =K14/J14-1 -> 0.58919826 | L15: =L14/K14-1 -> 0.006581806 | M15: =M14/L14-1 -> 0.037852565 | N15: =N14/M14-1 -> 0.060512627 | ... U15: =U14/T14-1 -> 9.5789474
B16: Present Value of FCFF | E16: =E14/(1+$C$23)^(E3-$C$26) -> -254.50807 | F16: =F14/(1+$C$23)^(F4-$C$26) -> -48.337177 | G16: =G14/(1+$C$23)^(G3-$C$26) -> 699.77319 | H16: =H14/(1+$C$23)^(H3-$C$26) -> 982.78452 | I16: =I14/(1+$C$23)^(I3-$C$26) -> 870.62257 | J16: =J14/(1+$C$23)^(J3-$C$26) -> 1746.6938 | K16: =K14/(1+$C$23)^(K3-$C$26) -> 2523.4935 | L16: =L14/(1+$C$23)^(L3-$C$26) -> 2309.1842 | M16: =M14/(1+$C$23)^(M3-$C$26) -> 2178.7207 | N16: =N14/(1+$C$23)^(N3-$C$26) -> 2100.5098 | ... T16: =T14/(1+$C$23)^(T3-$C$26) -> 2301.8309 | U16: =U14/(1+$C$23)^(U4-$C$26) -> 22137.225
B18: Sum of Discounted CF | C18: =SUM(I16:U16)+H16*0.5 -> 49207.209
B19: Net Cash | C19: =BS!H5+BS!H6-BS!H21-BS!H30 -> 2717.6959
B20: Equity Value | C20: =C18+C19 -> 51924.904
B21: Equity Value Per Share | C21: =C20/C27 -> 200.04697
B23: Discount Rate | C23: 0.1
B24: Intermediate Growth Rate
B25: Terminal Growth Rate | C25: 0.005
B26: Time of Valuation | C26: 2018.5
B27: Shares Outstanding | C27: =IS!AK52 -> 259.56357
B29: Bull / Base / Bear Scenarios
A30: 1 | B30: Selector ---> | C30: 2 | D30: 1 = Bull
A31: 2 | D31: 2 = Base
A32: 3 | D32: 3 = Bear

Sheet IS
DG1: RIC | DH1: VRTX.O
B2: VERTEX PHARMACEUTICALS INC. (NSDQ:VRTX) | C2: 1Q12 | D2: 2Q12 | E2: 3Q12 | F2: 4Q12 | G2: 2012 | H2: 1Q13A | I2: 2Q13A | J2: 3Q13A | K2: 4Q13A | L2: 2013A | M2: 1Q14A | N2: 2Q14A | O2: 3Q14A | P2: 4Q14A | Q2: 2014A | R2: 1Q15A | S2: 2Q15A | T2: 3Q15A | U2: 4Q15A | V2: 2015A | W2: 1Q16A | X2: 2Q16A | Y2: 3Q16A | Z2: 4Q16A | AA2: 2016A | AB2: 1Q17A | AC2: 2Q17A | AD2: 3Q17A | AE2: 4Q17A | AF2: 2017A | AG2: 1Q18E | AH2: 2Q18E | AI2: 3Q18E | AJ2: 4Q18E | AK2: 2018E | AL2: 1Q19E | AM2: 2Q19E | AN2: 3Q19E | AO2: 4Q19E | AP2: 2019E | AQ2: 1Q20E | AR2: 2Q20E | AS2: 3Q20E | AT2: 4Q20E | AU2: 2020E | AV2: 1Q21E | AW2: 2Q21E | AX2: 3Q21E | AY2: 4Q21E | AZ2: 2021E | BA2: 1Q22E | BB2: 2Q22E | BC2: 3Q22E | BD2: 4Q22E | BE2: 2022E | BF2: 1Q23E | BG2: 2Q23E | BH2: 3Q23E | BI2: 4Q23E | BJ2: 2023E | BK2: 1Q24E | BL2: 2Q24E | BM2: 3Q24E | BN2: 4Q24E | BO2: 2024E | BP2: 1Q25E | BQ2: 2Q25E | BR2: 3Q25E | BS2: 4Q25E | BT2: 2025E | BU2: 1Q26E | BV2: 2Q26E | BW2: 3Q26E | BX2: 4Q26E | BY2: 2026E | BZ2: 1Q27E | CA2: 2Q27E | CB2: 3Q27E | CC2: 4Q27E | CD2: 2027E | CE2: 1Q28E | CF2: 2Q28E | CG2: 3Q28E | CH2: 4Q28E | CI2: 2028E | CJ2: 1Q29E | CK2: 2Q29E | CL2: 3Q29E | CM2: 4Q29E | CN2: 2029E | CO2: 1Q30E | CP2: 2Q30E | CQ2: 3Q30E | CR2: 4Q30E | CS2: 2030E | DG2: Currency | DH2: =_xll.TR(DH$1,"TR.NetIncome.currency","Null=-") -> #NAME?
B3: Kalydeco | H3: =H84 -> 61.827 | I3: =I84 -> 98.973 | J3: =J84 -> 101.061 | K3: =K84 -> 109.424 | L3: =SUM(H3:K3) -> 371.285 | M3: =M84 -> 99.515 | N3: =N84 -> 113.055 | O3: =O84 -> 126.801 | P3: =P84 -> 124.379 | Q3: =SUM(M3:P3) -> 463.75 | R3: =R84 -> 130.174 | S3: =S84 -> 154.888 | T3: =T84 -> 165.9 | U3: =U84 -> 180.712 | V3: =SUM(R3:U3) -> 631.674 | W3: =W84 -> 170.5 | X3: =X84 -> 180 | Y3: =Y84 -> 176 | Z3: =Z84 -> 176.9 | AA3: =SUM(W3:Z3) -> 703.4 | AB3: =AB84 -> 186 | AC3: =AC84 -> 190 | AD3: =AD84 -> 213 | AE3: =AE84 -> 256 | AF3: =AE3+AD3+AC3+AB3 -> 845 | AG3: =AG84 -> 230 | AH3: =AH84 -> 235 | AI3: =AI84 -> 240 | AJ3: =AJ84 -> 244.21633 | AK3: =Revs!BO7 -> 949.21633 | AP3: =Revs!BT7 -> 980.27101 | AU3: =Revs!BY7 -> 1110.9818 | AZ3: =Revs!CD7 -> 1156.4902 | BE3: =Revs!CI7 -> 1148.5928 | BJ3: =Revs!CN7 -> 1140.8533 | BO3: =Revs!CS7 -> 1133.2686 | BT3: =Revs!CX7 -> 549.58741 | BY3: =Revs!DC7 -> 309.22509 | CD3: =Revs!DH7 -> 305.22555 | CI3: =Revs!DM7 -> 53.740211 | CN3: =Revs!DR7 -> 8.7714489 | CS3: =Revs!DW7 -> 0
B5: Deuterated Kalydeco | AK5: =Revs!BO14 -> 0 | AP5: =Revs!BT14 -> 0 | AU5: =Revs!BY14 -> 0 | AZ5: =Revs!CD14 -> 0 | BE5: =Revs!CI14 -> 0 | BJ5: =Revs!CN14 -> 0 | BO5: =Revs!CS14 -> 0 | BT5: =Revs!CX14 -> 611.54792 | BY5: =Revs!DC14 -> 787.69957 | CD5: =Revs!DH14 -> 784.24476 | CI5: =Revs!DM14 -> 1068.4306 | CN5: =Revs!DR14 -> 1069.6362 | CS5: =Revs!DW14 -> 1159.5553
B7: Orkambi | H7: =H86 -> 0 | I7: =I86 -> 0 | J7: =J86 -> 0 | K7: =K86 -> 0 | L7: =SUM(H7:K7) -> 0 | M7: =M86 -> 0 | N7: =N86 -> 0 | O7: =O86 -> 0 | P7: =P86 -> 0 | Q7: =SUM(M7:P7) -> 0 | R7: =R86 -> 0 | S7: =S86 -> 0 | T7: =T86 -> 130.8 | U7: =U86 -> 219.863 | V7: =SUM(R7:U7) -> 350.663 | W7: =W86 -> 223.91 | X7: =X86 -> 245.651 | Y7: =Y86 -> 233.689 | Z7: =Z86 -> 276.982 | AA7: =SUM(W7:Z7) -> 980.232 | AB7: =AB86 -> 294.622 | AC7: =AC86 -> 323.988 | AD7: =AD86 -> 336.642 | AE7: =AE86 -> 365.228 | AF7: =AE7+AD7+AC7+AB7 -> 1320.48 | AG7: =AG86 -> 360 | AH7: =AH86 -> 370 | AI7: =AI86 -> 380 | AJ7: =AJ86 -> 383.74949 | AK7: =Revs!BO29 -> 1493.7495 | AP7: =Revs!BT29 -> 1464.5138 | AU7: =Revs!BY29 -> 1274.3007 | AZ7: =Revs!CD29 -> 1205.8609 | BE7: =Revs!CI29 -> 1054.5016 | BJ7: =Revs!CN29 -> 899.68021 | BO7: =Revs!CS29 -> 620.57975 | BT7: =Revs!CX29 -> 388.74281 | BY7: =Revs!DC29 -> 212.1148 | CD7: =Revs!DH29 -> 110.87855 | CI7: =Revs!DM29 -> 52.19564 | CN7: =Revs!DR29 -> 17.92106 | CS7: =Revs!DW29 -> 1.4870667
B9: Symdeko | AG9: =AG87 -> 10 | AH9: =AH87 -> 40 | AI9: =AI87 -> 75 | AJ9: =AJ87 -> 94.718853 | AK9: =Revs!BO36 -> 219.71885 | AP9: =Revs!BT36 -> 485.0044 | AU9: =Revs!BY36 -> 571.63076 | AZ9: =Revs!CD36 -> 599.76369 | BE9: =Revs!CI36 -> 538.73244 | BJ9: =Revs!CN36 -> 465.68008 | BO9: =Revs!CS36 -> 291.16133 | BT9: =Revs!CX36 -> 149.56093 | BY9: =Revs!DC36 -> 78.350642 | CD9: =Revs!DH36 -> 40.13191 | CI9: =Revs!DM36 -> 15.948799 | CN9: =Revs!DR36 -> 6.1827656 | CS9: =Revs!DW36 -> 0.513038
B11: Triple Combo | AG11: =AG88 -> 0 | AH11: =AH88 -> 0 | AI11: =AI88 -> 0 | AJ11: =AJ88 -> 0 | AK11: =Revs!BO43 -> 0 | AP11: =Revs!BT43 -> 0 | AU11: =Revs!BY43 -> 1075.9316 | AZ11: =Revs!CD43 -> 2389.9398 | BE11: =Revs!CI43 -> 3438.3045 | BJ11: =Revs!CN43 -> 4043.2969 | BO11: =Revs!CS43 -> 4662.0948 | BT11: =Revs!CX43 -> 5668.0216 | BY11: =Revs!DC43 -> 7490.0759 | CD11: =Revs!DH43 -> 7760.3895 | CI11: =Revs!DM43 -> 7913.4381 | CN11: =Revs!DR43 -> 8012.4009 | CS11: =Revs!DW43 -> 8036.3479
B14: INCIVEK | H14: =H89 -> 205.554 | I14: =I89 -> 155.816 | J14: =J89 -> 85.592 | K14: =K89 -> 19.398 | L14: =SUM(H14:K14) -> 466.36 | M14: =M89+M59 -> 0 | N14: =N89+N59 -> 0 | O14: =O89+O59 -> 0 | P14: =P89+P59 -> 1.126 | Q14: =SUM(M14:P14) -> 1.126 | R14: =R89+R59 -> 0 | S14: =S89+S59 -> 0 | T14: =T89+T59 -> 0 | U14: =U89+U59 -> 0 | V14: =SUM(R14:U14) -> 0 | W14: =W89+W59 -> 0 | X14: =X89+X59 -> 0 | Y14: =Y89+Y59 -> 0 | Z14: =Z89+Z59 -> 0 | AA14: =Revs!BE23 -> 0 | AF14: =Revs!BJ23 -> 0 | AK14: =Revs!BO23 -> 0 | AP14: =Revs!BT23 -> 0 | AU14: =Revs!BY23 -> 0 | AZ14: =Revs!CD23 -> 0 | BE14: =Revs!CI23 -> 0 | BJ14: =Revs!CN23 -> 0 | BO14: =Revs!CS23 -> 0 | BT14: =Revs!CX23 -> 0 | BY14: =Revs!DC23 -> 0 | CD14: =Revs!DH23 -> 0 | CI14: =Revs!DM23 -> 0 | CN14: =Revs!DR23 -> 0 | CS14: =Revs!DW23 -> 0
B15: Net product sales | H15: =H3+H7+H14 -> 267.381 | I15: =I3+I7+I14 -> 254.789 | J15: =J3+J7+J14 -> 186.653 | K15: =K3+K7+K14 -> 128.822 | L15: =L3+L7+L14 -> 837.645 | M15: =M3+M7+M14 -> 99.515 | N15: =N3+N7+N14 -> 113.055 | O15: =O3+O7+O14 -> 126.801 | ... AA15: =AA3+AA7+AA14 -> 1683.632 | AB15: =AB83 -> 480.622 | AC15: =AC3+AC7+AC14 -> 513.988 | AD15: =AD3+AD7+AD14 -> 549.642 | AE15: =AE3+AE7+AE14 -> 621.228 | AF15: =AF3+AF7+AF14+AF9+AF11+AF5 -> 2165.48 | AG15: =AG83 -> 600 | AH15: =AH83 -> 645 | AI15: =AI83 -> 695 | AJ15: =AJ83 -> 722.68467 | AK15: =AK3+AK7+AK14+AK9+AK11+AK5 -> 2662.6847 | AP15: =AP3+AP7+AP14+AP9+AP11+AP5 -> 2929.7892 | AU15: =AU3+AU7+AU14+AU9+AU11+AU5 -> 4032.845 | AZ15: =AZ3+AZ7+AZ14+AZ9+AZ11+AZ5 -> 5352.0546 | BE15: =BE3+BE7+BE14+BE9+BE11+BE5 -> 6180.1313 | BJ15: =BJ3+BJ7+BJ14+BJ9+BJ11+BJ5 -> 6549.5105 | BO15: =BO3+BO7+BO14+BO9+BO11+BO5 -> 6707.1044 | BT15: =BT3+BT7+BT14+BT9+BT11+BT5 -> 7367.4607 | BY15: =BY3+BY7+BY14+BY9+BY11+BY5 -> 8877.466 | CD15: =CD3+CD7+CD14+CD9+CD11+CD5 -> 9000.8703 | CI15: =CI3+CI7+CI14+CI9+CI11+CI5 -> 9103.7533 | CN15: =CN3+CN7+CN14+CN9+CN11+CN5 -> 9114.9124 | CS15: =CS3+CS7+CS14+CS9+CS11+CS5 -> 9197.9033
AI16: Co. Guidance | AK16: $2,650-2,800M
B17: Collaboration and license agreement revenues | H17: =17.414+H58 -> 17.414 | I17: =6.841+I58 -> 6.841 | J17: =8.035+J58 -> 8.035 | K17: =185.448+K58 -> 3.052 | L17: =SUM(H17:K17) -> 35.342 | M17: =4.257+M60 -> 2.857 | N17: =3.087+N60 -> 1.587 | O17: =33.502+O60 -> 32.102 | P17: =10.829+P60 -> 8.029 | Q17: =SUM(M17:P17) -> 44.575 | R17: =0.842+R60 -> 0.174 | S17: =0.611+S60 -> 0 | T17: =T91+T60 -> 0.942 | U17: =U91+U60 -> 4.958 | V17: =SUM(R17:U17) -> 6.074 | W17: =W91+W60 -> 0 | X17: =X91+X60 -> 0.102 | Y17: =Y91+Y60 -> 0.216 | Z17: =Z91+Z60 -> 0.816 | AA17: =SUM(W17:Z17) -> 1.134 | AB17: =AB91+AB60 -> 0.083 | AC17: =AC91+AC60 -> 0.064 | AD17: =AD91+AD60 -> 0.001 | AE17: =AE91+AE60 -> 0.055 | AF17: =AE17+AD17+AC17+AB17 -> 0.203 | AG17: =AG91+AG60 -> 0 | AH17: =AH91+AH60 -> 0 | AI17: =AI91+AI60 -> 0 | AJ17: =AJ91+AJ60 -> 0 | AK17: =Revs!BO51 -> 0 | AP17: =Revs!BT51 -> 0 | AU17: =Revs!BY51 -> 0 | AZ17: =Revs!CD51 -> 0 | BE17: =Revs!CI51 -> 0 | BJ17: =Revs!CN51 -> 0 | BO17: =Revs!CS51 -> 0 | BT17: =Revs!CX51 -> 0 | BY17: =Revs!DC51 -> 0 | CD17: =Revs!DH51 -> 0 | CI17: =Revs!DM51 -> 0 | CN17: =Revs!DR51 -> 0 | CS17: =Revs!DW51 -> 0
B18: Royalty revenues | H18: 43.573 | I18: 49.12 | J18: 27.012 | K18: 36.887 | L18: =SUM(H18:K18) -> 156.592 | M18: =10.733+M61 -> 5.838 | N18: =13.015+N61 -> 7.334 | O18: =8.386+O61 -> 6.112 | P18: =8.785+P61 -> 7.054 | Q18: =SUM(M18:P18) -> 26.338 | R18: =6.792+R61 -> 5.292 | S18: =5.077+S61 -> 5.094 | T18: =T93+T61 -> 4.654 | U18: =U93+U61 -> 4.822 | V18: =SUM(R18:U18) -> 19.862 | W18: =W93+W61 -> 2.745 | X18: =X93+X61 -> 5.771 | Y18: =Y93+Y61 -> 3.632 | Z18: =Z93+Z61 -> 3.887 | AA18: =SUM(W18:Z18) -> 16.035 | AB18: =AB93 -> 1.551 | AC18: =AC93 -> 2.861 | AD18: =AD93 -> 2.231 | AE18: =AE93 -> 1.345 | AF18: =AE18+AD18+AC18+AB18 -> 7.988 | AG18: =AG93 -> 0 | AH18: =AH93 -> 0 | AI18: =AI93 -> 0 | AJ18: =AJ93 -> 0 | AK18: =Revs!BO50 -> 0 | AP18: =Revs!BT50 -> 0 | AU18: =Revs!BY50 -> 0 | AZ18: =Revs!CD50 -> 0 | BE18: =Revs!CI50 -> 0 | BJ18: =Revs!CN50 -> 0 | BO18: =Revs!CS50 -> 0 | BT18: =Revs!CX50 -> 0 | BY18: =Revs!DC50 -> 0 | CD18: =Revs!DH50 -> 0 | CI18: =Revs!DM50 -> 0 | CN18: =Revs!DR50 -> 0 | CS18: =Revs!DW50 -> 0
B19: Non-GAAP Revenues | H19: =H15+H17+H18 -> 328.368 | I19: =I15+I17+I18 -> 310.75 | J19: =J15+J17+J18 -> 221.7 | K19: =K15+K17+K18 -> 168.761 | L19: =L15+L17+L18 -> 1029.579 | M19: =M15+M17+M18+M57 -> 108.21 | N19: =N15+N17+N18+N57 -> 121.976 | O19: =O15+O17+O18 -> 165.015 | P19: =P15+P17+P18+P57 -> 140.588 | Q19: =Q15+Q17+Q18+Q57 -> 535.789 | R19: =R15+R17+R18+R62 -> 135.44 | S19: =S15+S17+S18+S62 -> 159.908 | T19: =T15+T17+T18+T62 -> 302.296 | U19: =U15+U17+U18+U62 -> 410.355 | V19: =V15+V17+V18+V62 -> 1007.999 | W19: =W15+W17+W18+W62 -> 397.155 | X19: =X15+X17+X18+X62 -> 431.524 | Y19: =Y15+Y17+Y18+Y62 -> 413.537 | ... AE19: =AE15+AE17+AE18+AE62 -> 622.628 | AF19: =AF15+AF17+AF18+AF57 -> 2173.671 | AG19: =AG15+AG17+AG18+AG62 -> 600 | AH19: =AH15+AH17+AH18+AH62 -> 645 | AI19: =AI15+AI17+AI18+AI62 -> 695 | AJ19: =AJ15+AJ17+AJ18+AJ62 -> 722.68467 | AK19: =AK15+AK17+AK18+AK57 -> 2662.6847 | AP19: =AP15+AP17+AP18+AP57 -> 2929.7892 | AU19: =AU15+AU17+AU18+AU57 -> 4032.845 | AZ19: =AZ15+AZ17+AZ18+AZ57 -> 5352.0546 | BE19: =BE15+BE17+BE18+BE57 -> 6180.1313 | BJ19: =BJ15+BJ17+BJ18+BJ57 -> 6549.5105 | BO19: =BO15+BO17+BO18+BO57 -> 6707.1044 | BT19: =BT15+BT17+BT18+BT57 -> 7367.4607 | BY19: =BY15+BY17+BY18+BY57 -> 8877.466 | CD19: =CD15+CD17+CD18+CD57 -> 9000.8703 | CI19: =CI15+CI17+CI18+CI57 -> 9103.7533 | CN19: =CN15+CN17+CN18+CN57 -> 9114.9124 | CS19: =CS15+CS17+CS18+CS57 -> 9197.9033
B20: Consensus Revenue | AG20: =_xll.TR($DH$1,"TR.RevenueMean","Period=#1 Curn=#2 Scale=6 Null=BLANK",,LEFT(AG$2,1)&"CQ20"&MID(AG$2,3,2),$DH$2) -> #NAME? | AH20: =_xll.TR($DH$1,"TR.RevenueMean","Period=#1 Curn=#2 Scale=6 Null=BLANK",,LEFT(AH$2,1)&"CQ20"&MID(AH$2,3,2),$DH$2) -> #NAME? | AI20: =_xll.TR($DH$1,"TR.RevenueMean","Period=#1 Curn=#2 Scale=6 Null=BLANK",,LEFT(AI$2,1)&"CQ20"&MID(AI$2,3,2),$DH$2) -> #NAME? | AJ20: =_xll.TR($DH$1,"TR.RevenueMean","Period=#1 Curn=#2 Scale=6 Null=BLANK",,LEFT(AJ$2,1)&"CQ20"&MID(AJ$2,3,2),$DH$2) -> #NAME? | AK20: =_xll.TR($DH$1,"AVAIL(TR.RevenueMean(Methodology=WeightedAnnual),TR.RevenueMean(Methodology=Interimsum))","Period=#1 Curn=#2 Scale=6 Null=BLANK",,"CY"&LEFT(AK$2,4),$DH$2) -> #NAME? | AP20: =_xll.TR($DH$1,"AVAIL(TR.RevenueMean(Methodology=WeightedAnnual),TR.RevenueMean(Methodology=Interimsum))","Period=#1 Curn=#2 Scale=6 Null=BLANK",,"CY"&LEFT(AP$2,4),$DH$2) -> #NAME? | AU20: =_xll.TR($DH$1,"AVAIL(TR.RevenueMean(Methodology=WeightedAnnual),TR.RevenueMean(Methodology=Interimsum))","Period=#1 Curn=#2 Scale=6 Null=BLANK",,"CY"&LEFT(AU$2,4),$DH$2) -> #NAME?
B22: Costs and expenses | V22: =SUM(R42:U42) -> 0.65
B23: Cost of product revenues/royalties | H23: =H98+H63 -> 42.743 | I23: =I98+I63 -> 32.848 | J23: =J98+J63 -> 22.063 | K23: =K98+K63 -> 22.264 | L23: 119.919 | M23: =M98+M63 -> 9.589 | N23: =N98+N63 -> 11.067 | O23: =O98+O63 -> 11.018 | P23: =P98+P63 -> 13.226 | Q23: 44.951 | R23: =R98+R63 -> 10.711 | S23: =S98+S63 -> 16.489 | T23: =T98+T63 -> 33.506 | U23: =U98+U63 -> 63.176 | V23: =V98+V63 -> 123.882 | W23: =W98+W63 -> 50.51 | X23: =X98+X63 -> 45.258 | Y23: =Y98+Y63 -> 54.093 | ... AE23: =AE98+AE63 -> 84.052 | AF23: =AE23+AD23+AC23+AB23 -> 275.119 | AG23: =AG98+AG63 -> 72.321663 | AH23: =AH98+AH63 -> 77.745788 | AI23: =AI98+AI63 -> 83.772594 | AJ23: =AK23-AG23-AH23-AI23 -> 87.109596 | AK23: =AK98+AK63 -> 320.94964 | AP23: =AP98+AP63 -> 354.09854 | AU23: =AU98+AU63 -> 466.44801 | AZ23: =AZ98+AZ63 -> 585.35894 | BE23: =BE98+BE63 -> 652.17576 | BJ23: =BJ98+BJ63 -> 665.53142 | BO23: =BO98+BO63 -> 650.93668 | BT23: =BT98+BT63 -> 628.91172 | BY23: =BY98+BY63 -> 726.81424 | CD23: =CD98+CD63 -> 740.2834 | CI23: =CI98+CI63 -> 721.35077 | CN23: =CN98+CN63 -> 723.58173 | CS23: =CS98+CS63 -> 723.42132
B24: Bull | R24: =R153 -> 177.174 | S24: =S153 -> 181.911 | T24: =T153 -> 201.588 | U24: =U153 -> 203.51 | V24: =SUM(R24:U24) -> 764.183 | W24: =W153 -> 222.046 | X24: =X153 -> 215 | Y24: =Y153 -> 217.51345 | Z24: =Z153 -> 219.58729 | AA24: =SUM(W24:Z24) -> 874.14674 | AE24: =AE153 -> 187.84338 | AF24: =AF153 -> 911.13157 | AK24: =AK153 -> 1066.0239 | AP24: =AP153 -> 1140.6456 | AU24: =AU153 -> 1197.6779 | AZ24: =AZ153 -> 1233.6082 | BE24: =BE153 -> 1233.6082 | BJ24: =BJ153 -> 1196.6 | BO24: =BO153 -> 1136.77 | BT24: =BT153 -> 1057.1961 | BY24: =BY153 -> 983.19236 | CD24: =CD153 -> 924.20082 | CI24: =CI153 -> 859.50676 | CN24: =CN153 -> 799.34129 | CS24: =CS153 -> 731.39728
B25: Base | R25: =R154 -> 177.174 | S25: =S154 -> 181.911 | T25: =T154 -> 201.588 | U25: =U154 -> 203.51 | V25: =SUM(R25:U25) -> 764.183 | W25: =W154 -> 222.046 | X25: =X154 -> 215 | Y25: =Y154 -> 210 | Z25: =Z154 -> 226.03308 | AA25: =SUM(W25:Z25) -> 873.07908 | AB25: =AB27 -> 226.581 | AC25: =AC27 -> 240.459 | AD25: =AD27 -> 243.212 | AE25: =AF25-AB25-AC25-AD25 -> 254.50038 | AF25: =AF154 -> 964.75238 | AK25: =AK154 -> 1109.4652 | AL25: =AL154 -> 0 | AM25: =AM154 -> 0 | AN25: =AN154 -> 0 | AO25: =AO154 -> 0 | AP25: =AP154 -> 1187.1278 | AQ25: =AQ154 -> 0 | AR25: =AR154 -> 0 | ... CS25: =CS154 -> 753.10439
B26: Bear | R26: =R155 -> 177.174 | S26: =S155 -> 181.911 | T26: =T155 -> 201.588 | U26: =U155 -> 203.51 | V26: =SUM(R26:U26) -> 764.183 | W26: =W155 -> 222.046 | X26: =X155 -> 215 | Y26: =Y155 -> 207.63564 | Z26: =Z155 -> 209.6153 | AA26: =SUM(W26:Z26) -> 854.29694 | AE26: =AE155 -> 128.18417 | AF26: =AF155 -> 708.39764 | AK26: =AK155 -> 602.13799 | AP26: =AP155 -> 451.6035 | AU26: =AU155 -> 338.70262 | AZ26: =AZ155 -> 254.02697 | BE26: =BE155 -> 190.52022 | BJ26: =BJ155 -> 142.89017 | BO26: =BO155 -> 107.16763 | BT26: =BT155 -> 80.37572 | BY26: =BY155 -> 60.28179 | CD26: =CD155 -> 45.211342 | CI26: =CI155 -> 33.908507 | CN26: =CN155 -> 25.43138 | CS26: =CS155 -> 19.073535
B27: Research & development | H27: =H101+H64 -> 194.774 | I27: =I101+I64 -> 191.189 | J27: =J101+J64 -> 200.2865 | K27: =K101+K64 -> 208.132 | L27: 787.639 | M27: =M101+M64 -> 181.535 | N27: =N101+N64 -> 179.512 | O27: =O101+O64 -> 157.383 | P27: =P101+P64 -> 175.677 | Q27: 694.192 | R27: =R101+R64 -> 177.174 | S27: =S101+S64 -> 181.911 | T27: =T101+T64 -> 201.588 | U27: =U101+U64 -> 203.51 | V27: =V101+V64 -> 764.183 | W27: =W101+W64 -> 222.046 | X27: =X101+X64 -> 217.673 | Y27: =Y101+Y64 -> 210.966 | Z27: =Z101+Z64 -> 207.085 | AA27: =SUM(W27:Z27) -> 857.77 | AB27: =AB101+AB64 -> 226.581 | AC27: =AC101+AC64 -> 240.459 | AD27: =AD101+AD64 -> 243.212 | AE27: =AE101+AE64 -> 249.234 | AF27: =AE27+AD27+AC27+AB27 -> 959.486 | AG27: =AK27/4 -> 277.36631 | AH27: =AK27/4 -> 277.36631 | AI27: =AK27/4 -> 277.36631 | AJ27: =AK27-SUM(AG27:AI27) -> 277.36631 | AK27: =CHOOSE($B$149,AK24,AK25,AK26) -> 1109.4652 | AP27: =CHOOSE($B$149,AP24,AP25,AP26) -> 1187.1278 | AU27: =CHOOSE($B$149,AU24,AU25,AU26) -> 1246.4842 | AZ27: =CHOOSE($B$149,AZ24,AZ25,AZ26) -> 1283.8787 | BE27: =CHOOSE($B$149,BE24,BE25,BE26) -> 1283.8787 | BJ27: =CHOOSE($B$149,BJ24,BJ25,BJ26) -> 1245.3624 | BO27: =CHOOSE($B$149,BO24,BO25,BO26) -> 1183.0942 | BT27: =CHOOSE($B$149,BT24,BT25,BT26) -> 1100.2776 | BY27: =CHOOSE($B$149,BY24,BY25,BY26) -> 1023.2582 | CD27: =CHOOSE($B$149,CD24,CD25,CD26) -> 951.63013 | CI27: =CHOOSE($B$149,CI24,CI25,CI26) -> 885.01602 | CN27: =CHOOSE($B$149,CN24,CN25,CN26) -> 823.0649 | CS27: =CHOOSE($B$149,CS24,CS25,CS26) -> 753.10439
B28: Bull | R28: =R161 -> 69.149 | S28: =S161 -> 72.016 | T28: =T161 -> 76.117 | U28: =U161 -> 77.63 | V28: =SUM(R28:U28) -> 294.912 | W28: =W161 -> 83.679 | X28: =X161 -> 84 | Y28: =Y161 -> 89.627768 | Z28: =Z161 -> 91.409325 | AA28: =SUM(W28:Z28) -> 348.71609 | AE28: =AE161 -> 97.598042 | AF28: =AF161 -> 376.77588 | AK28: =AK161 -> 418.22123 | AP28: =AP161 -> 439.13229 | AU28: =AU161 -> 461.08891 | AZ28: =AZ161 -> 484.14335 | BE28: =BE161 -> 508.35052 | BJ28: =BJ161 -> 533.76805 | BO28: =BO161 -> 544.44341 | BT28: =BT161 -> 555.33228 | BY28: =BY161 -> 555.33228 | CD28: =CD161 -> 555.33228 | CI28: =CI161 -> 555.33228 | CN28: =CN161 -> 555.33228 | CS28: =CS161 -> 555.33228
B29: Base | R29: =R162 -> 69.149 | S29: =S162 -> 72.016 | T29: =T162 -> 76.117 | U29: =U162 -> 77.63 | V29: =SUM(R29:U29) -> 294.912 | W29: =W162 -> 83.679 | X29: =X162 -> 84 | Y29: =Y162 -> 84 | Z29: =Z162 -> 84.52068 | AA29: =SUM(W29:Z29) -> 336.19968 | AB29: =AB31 -> 86.344 | AC29: =AC31 -> 92.906 | AD29: =AD31 -> 90.557 | AE29: =AF29-AB29-AC29-AD29 -> 94.969653 | AF29: =AF162 -> 364.77665 | AK29: =AK162 -> 404.90208 | AP29: =AP162 -> 425.14719 | AU29: =AU162 -> 446.40455 | AZ29: =AZ162 -> 468.72478 | BE29: =BE162 -> 492.16101 | BJ29: =BJ162 -> 516.76907 | BO29: =BO162 -> 527.10445 | BT29: =BT162 -> 537.64654 | BY29: =BY162 -> 537.64654 | CD29: =CD162 -> 537.64654 | CI29: =CI162 -> 537.64654 | CN29: =CN162 -> 537.64654 | CS29: =CS162 -> 537.64654
B30: Bear | R30: =R163 -> 69.149 | S30: =S163 -> 72.016 | T30: =T163 -> 76.117 | U30: =U163 -> 77.63 | V30: =SUM(R30:U30) -> 294.912 | W30: =W163 -> 83.679 | X30: =X163 -> 84 | Y30: =Y163 -> 63.253227 | Z30: =Z163 -> 64.51053 | AA30: =SUM(W30:Z30) -> 295.44276 | AE30: 90 | AF30: =AF163 -> 220.56468 | AK30: =AK163 -> 198.50822 | AP30: =AP163 -> 168.73198 | AU30: =AU163 -> 143.42219 | AZ30: =AZ163 -> 121.90886 | BE30: =BE163 -> 103.62253 | BJ30: =BJ163 -> 88.07915 | BO30: =BO163 -> 74.867278 | BT30: =BT163 -> 63.637186 | BY30: =BY163 -> 54.091608 | CD30: =CD163 -> 45.977867 | CI30: =CI163 -> 39.081187 | CN30: =CN163 -> 33.219009 | CS30: =CS163 -> 28.236157
B31: Selling, general & administrative | H31: =H102+H69 -> 79.759 | I31: =I102+I69 -> 89.517 | J31: =J102+J69 -> 74.385 | K31: =K102+K69 -> 65.448 | L31: 309.097 | M31: =M102+M69 -> 52.411 | N31: =N102+N69 -> 57.883 | O31: =O102+O69 -> 55.054 | P31: =P102+P69 -> 60.368 | Q31: 225.634 | R31: =R102+R69 -> 69.149 | S31: =S102+S69 -> 72.016 | T31: =T102+T69 -> 76.117 | U31: =U102+U69 -> 77.63 | V31: =SUM(R31:U31) -> 294.912 | W31: =W102+W69 -> 83.679 | X31: =X102+X69 -> 88.591 | Y31: =Y102+Y69 -> 83.992 | Z31: =Z102+Z69 -> 87.922 | AA31: =SUM(W31:Z31) -> 344.184 | AB31: =AB102+AB69 -> 86.344 | AC31: =AC102+AC69 -> 92.906 | AD31: =AD102+AD69 -> 90.557 | AE31: =AE102+AE69 -> 105.504 | AF31: =AE31+AD31+AC31+AB31 -> 375.311 | AG31: =AK31/4 -> 101.22552 | AH31: =AK31/4 -> 101.22552 | AI31: =AK31/4 -> 101.22552 | AJ31: =AK31-SUM(AG31:AI31) -> 101.22552 | AK31: =CHOOSE($B$149,AK28,AK29,AK30) -> 404.90208 | AP31: =CHOOSE($B$149,AP28,AP29,AP30) -> 425.14719 | AU31: =CHOOSE($B$149,AU28,AU29,AU30) -> 446.40455 | AZ31: =CHOOSE($B$149,AZ28,AZ29,AZ30) -> 468.72478 | BE31: =CHOOSE($B$149,BE28,BE29,BE30) -> 492.16101 | BJ31: =CHOOSE($B$149,BJ28,BJ29,BJ30) -> 516.76907 | BO31: =CHOOSE($B$149,BO28,BO29,BO30) -> 527.10445 | BT31: =CHOOSE($B$149,BT28,BT29,BT30) -> 537.64654 | BY31: =CHOOSE($B$149,BY28,BY29,BY30) -> 537.64654 | CD31: =CHOOSE($B$149,CD28,CD29,CD30) -> 537.64654 | CI31: =CHOOSE($B$149,CI28,CI29,CI30) -> 537.64654 | CN31: =CHOOSE($B$149,CN28,CN29,CN30) -> 537.64654 | CS31: =CHOOSE($B$149,CS28,CS29,CS30) -> 537.64654
B33: Total non-GAAP R&D and SG&A | L33: =L27+L31 -> 1096.736 | Q33: =Q27+Q31 -> 919.826 | V33: =V27+V31 -> 1059.095 | AA33: =AA27+AA31 -> 1201.954 | AF33: =AF27+AF31 -> 1334.797 | AK33: =AK27+AK31 -> 1514.3673 | AP33: =AP27+AP31 -> 1612.275 | AU33: =AU27+AU31 -> 1692.8887 | AZ33: =AZ27+AZ31 -> 1752.6035 | BE33: =BE27+BE31 -> 1776.0397 | BJ33: =BJ27+BJ31 -> 1762.1314 | BO33: =BO27+BO31 -> 1710.1987 | BT33: =BT27+BT31 -> 1637.9242 | BY33: =BY27+BY31 -> 1560.9047 | CD33: =CD27+CD31 -> 1489.2767 | CI33: =CI27+CI31 -> 1422.6626 | CN33: =CN27+CN31 -> 1360.7114 | CS33: =CS27+CS31 -> 1290.7509
AF34: Co. Guidance: $1.33-1.36B
B35: Restructuring expense, impairment charges | H35: =H104+H74 -> 0 | I35: =I104+I74 -> 0 | J35: =J104+J74 -> 0 | K35: =K104+K74 -> 0 | L35: =L104+L74 -> 0 | M35: =M104+M74 -> 0 | N35: =N104+N74 -> 0 | O35: =O104+O74 -> 0 | ... AE35: =AE104+AE74 -> 0 | AF35: =AE35+AD35+AC35+AB35 -> 0 | AG35: =AG104+AG74 -> 0 | AH35: =AH104+AH74 -> 0 | AI35: =AI104+AI74 -> 0 | AJ35: 0 | AK35: =AK104+AK74 -> 0 | AP35: =AP104+AP74 -> 0 | AU35: =AU104+AU74 -> 0 | AZ35: =AZ104+AZ74 -> 0 | BE35: =BE104+BE74 -> 0 | BJ35: =BJ104+BJ74 -> 0 | BO35: =BO104+BO74 -> 0 | BT35: =BT104+BT74 -> 0 | BY35: =BY104+BY74 -> 0 | CD35: =CD104+CD74 -> 0 | CI35: =CI104+CI74 -> 0 | CN35: =CN104+CN74 -> 0 | CS35: =CS104+CS74 -> 0
B37: Non-GAAP Operating Income (Loss) | H37: =H19-H23-H27-H31-H35 -> 11.092 | I37: =I19-I23-I27-I31-I35 -> -2.804 | J37: =J19-J23-J27-J31-J35 -> -75.0345 | K37: =K19-K23-K27-K31-K35 -> -127.083 | L37: =L19-L23-L27-L31-L35 -> -187.076 | M37: =M19-M23-M27-M31-M35 -> -135.325 | N37: =N19-N23-N27-N31-N35 -> -126.486 | O37: =O19-O23-O27-O31-O35 -> -58.44 | ... AK37: =AK19-AK23-AK27-AK31-AK35 -> 827.36771 | AP37: =AP19-AP23-AP27-AP31-AP35 -> 963.41564 | AU37: =AU19-AU23-AU27-AU31-AU35 -> 1873.5082 | AZ37: =AZ19-AZ23-AZ27-AZ31-AZ35 -> 3014.0922 | BE37: =BE19-BE23-BE27-BE31-BE35 -> 3751.9158 | BJ37: =BJ19-BJ23-BJ27-BJ31-BJ35 -> 4121.8477 | BO37: =BO19-BO23-BO27-BO31-BO35 -> 4345.9691 | BT37: =BT19-BT23-BT27-BT31-BT35 -> 5100.6248 | BY37: =BY19-BY23-BY27-BY31-BY35 -> 6589.747 | CD37: =CD19-CD23-CD27-CD31-CD35 -> 6771.3103 | CI37: =CI19-CI23-CI27-CI31-CI35 -> 6959.74 | CN37: =CN19-CN23-CN27-CN31-CN35 -> 7030.6192 | CS37: =CS19-CS23-CS27-CS31-CS35 -> 7183.7311
B39: Other income/(expense) | H39: =H110+H75 -> -4.644 | I39: =I110+I75 -> -2.853 | J39: =J110+J75 -> 4.656 | K39: =K110+K75 -> -0.011 | L39: =L110+L75 -> -3.027 | M39: =M110+M75 -> -15.266 | N39: =N110+N75 -> -14.539 | O39: =O110+O75 -> -24.374 | P39: =P110+P75 -> -24.982 | Q39: -79.148 | R39: =R110+R75 -> -26.42 | S39: =S110+S75 -> -19.697 | T39: =T110+T75 -> -22.46 | U39: =U110+U75 -> -22.344 | V39: =V110+V75 -> -90.921 | W39: =W110+W75 -> -16.076 | X39: =X110+X75 -> -21.41 | Y39: =Y110+Y75 -> -20.343 | ... AE39: =AE110+AE75 -> -13.299 | AF39: =AE39+AD39+AC39+AB39 -> -62.429 | AG39: =AG110+AG75 -> -15 | AH39: =AH110+AH75 -> -15 | AI39: =AI110+AI75 -> -15 | AJ39: =AK39-AG39-AH39-AI39 -> -15 | AK39: =AK199+AF172 -> -60 | AP39: =AP199+AK172 -> -46.411521 | AU39: =AU199+AP172 -> -32.752231 | AZ39: =AZ199+AU172 -> -7.8170204 | BE39: =BE199+AZ172 -> 38.212892 | BJ39: =BJ199+BE172 -> 100.62556 | BO39: =BO199+BJ172 -> 182.48153 | BT39: =BT199+BO172 -> 285.1824 | BY39: =BY199+BT172 -> 416.17398 | CD39: =CD199+BY172 -> 591.66805 | CI39: =CI199+CD172 -> 809.5131 | CN39: =CN199+CI172 -> 1064.8559 | CS39: =CS199+CN172 -> 1358.7763
B41: Pretax Income (Loss) | H41: =H37+H39 -> 6.448 | I41: =I37+I39 -> -5.657 | J41: =J37+J39 -> -70.3785 | K41: =K37+K39 -> -127.094 | L41: =L37+L39 -> -190.103 | M41: =M37+M39 -> -150.591 | N41: =N37+N39 -> -141.025 | O41: =O37+O39 -> -82.814 | ... AK41: =AK37+AK39 -> 767.36771 | AP41: =AP37+AP39 -> 917.00412 | AU41: =AU37+AU39 -> 1840.756 | AZ41: =AZ37+AZ39 -> 3006.2752 | BE41: =BE37+BE39 -> 3790.1287 | BJ41: =BJ37+BJ39 -> 4222.4732 | BO41: =BO37+BO39 -> 4528.4506 | BT41: =BT37+BT39 -> 5385.8072 | BY41: =BY37+BY39 -> 7005.921 | CD41: =CD37+CD39 -> 7362.9783 | CI41: =CI37+CI39 -> 7769.2531 | CN41: =CN37+CN39 -> 8095.4751 | CS41: =CS37+CS39 -> 8542.5074
B42: Income Taxes (expense) benefit | H42: =H113-H76 -> 0.699 | I42: =I113-I76 -> 0.558 | J42: =J113-J76 -> 2.555 | K42: =K113-K76 -> 4.056 | L42: =L113-L76 -> 13.651 | M42: =M113-M76 -> 0.803 | N42: =N113-N76 -> 0.693 | O42: =O113-O76 -> 3.419 | P42: =P113-P76 -> 5.919 | Q42: 3.082 | R42: =R113-R76 -> 0.362 | S42: =S113-S76 -> 0.478 | T42: =T113-T76 -> 0.553 | U42: =U113-U76 -> -0.743 | V42: =V113-V76 -> 0.65 | W42: =W113-W76 -> 2.422 | X42: =X113-X76 -> 0.62 | Y42: =Y113-Y76 -> 1.012 | Z42: =Z113-Z76 -> -4.133 | AA42: =SUM(W42:Z42) -> -0.079 | AB42: =AB113-AB76 -> 3.594 | AC42: =AC113-AC76 -> -3.795 | AD42: =AD113-AD76 -> -5.722 | AE42: =AE113-AE76 -> 12.689 | AF42: =AE42+AD42+AC42+AB42 -> 6.766 | AG42: =AG113-AG76 -> 0 | AH42: =AH113-AH76 -> 0 | AI42: =AI113-AI76 -> 0 | AJ42: =AJ113-AJ76 -> 0 | AK42: =AK182 -> 0 | AP42: =AP182 -> 0 | AU42: =AU182 -> 0 | AZ42: =AZ182 -> 0 | BE42: =BE182 -> 643.73552 | BJ42: =BJ182 -> 855.15675 | BO42: =BO182 -> 920.94188 | BT42: =BT182 -> 1105.2735 | BY42: =BY182 -> 1453.598 | CD42: =CD182 -> 1530.3653 | CI42: =CI182 -> 1617.7144 | CN42: =CN182 -> 1687.8522 | CS42: =CS182 -> 1783.9641
B43: Tax Rate | R43: =IF(R41<0,0,R42/R41) -> 0 | S43: =IF(S41<0,0,S42/S41) -> 0 | T43: =IF(T41<0,0,T42/T41) -> 0 | U43: =IF(U41<0,0,U42/U41) -> -0.017004234 | V43: 0 | W43: =IF(W41<0,0,W42/W41) -> 0.097488327 | X43: =IF(X41<0,0,X42/X41) -> 0.010581649 | Y43: =IF(Y41<0,0,Y42/Y41) -> 0.022925492 | Z43: =IF(Z41<0,0,Z42/Z41) -> -0.049607509 | AA43: =IF(AA41<0,0,AA42/AA41) -> -0.00037459754 | AB43: =IF(AB41<0,0,AB42/AB41) -> 0.034228571 | AC43: =IF(AC41<0,0,AC42/AC41) -> -0.039904524 | AD43: =IF(AD41<0,0,AD42/AD41) -> -0.043784673 | ... AJ43: =IF(AJ41<0,0,AJ42/AJ41) -> 0 | AK43: =AK42/AK41 -> 0 | AP43: =AP42/AP41 -> 0 | AU43: =AU42/AU41 -> 0 | AZ43: =AZ42/AZ41 -> 0 | BE43: =BE42/BE41 -> 0.16984529 | BJ43: =BJ42/BJ41 -> 0.20252508 | BO43: =BO42/BO41 -> 0.20336799 | BT43: =BT42/BT41 -> 0.20521966 | BY43: =BY42/BY41 -> 0.20748136 | CD43: =CD42/CD41 -> 0.20784597 | CI43: =CI42/CI41 -> 0.20822007 | CN43: =CN42/CN41 -> 0.20849328 | CS43: =CS42/CS41 -> 0.20883378
B45: Non-GAAP Net Income (Loss) from Continuing Operations | H45: =H41-H42 -> 5.749 | I45: =I41-I42 -> -6.215 | J45: =J41-J42-1.22 -> -74.1535 | K45: =K41-K42 -> -131.15 | L45: =L41-L42+0.452 -> -203.302 | M45: =M41-M42 -> -151.394 | N45: =N41-N42 -> -141.718 | O45: =O41-O42 -> -86.233 | P45: =P41-P42 -> -139.584 | Q45: =Q41-Q42 -> -511.218 | R45: =R41-R42 -> -148.376 | S45: =S41-S42 -> -130.683 | T45: =T41-T42 -> -31.928 | U45: =U41-U42 -> 44.438 | V45: =SUM(R45:U45) -> -266.549 | W45: =W41-W42 -> 22.422 | X45: =X41-X42 -> 57.972 | Y45: =Y41-Y42 -> 43.131 | Z45: =Z41-Z42 -> 87.447 | AA45: =AA41+AA42 -> 210.814 | AB45: =AB41-AB42 -> 101.406 | AC45: =AC41-AC42 -> 98.897 | AD45: =AD41-AD42 -> 136.407 | AE45: =AE41-AE42 -> 157.85 | AF45: =AF41-AF42 -> 494.56 | AG45: =AG41-AG42 -> 134.08651 | AH45: =AH41-AH42 -> 173.66238 | AI45: =AI41-AI42 -> 217.63558 | ... AK45: =AK41-AK42 -> 767.36771 | AP45: =AP41-AP42 -> 917.00412 | AU45: =AU41-AU42 -> 1840.756 | AZ45: =AZ41-AZ42 -> 3006.2752 | BE45: =BE41-BE42 -> 3146.3932 | BJ45: =BJ41-BJ42 -> 3367.3165 | BO45: =BO41-BO42 -> 3607.5087 | BT45: =BT41-BT42 -> 4280.5336 | BY45: =BY41-BY42 -> 5552.3229 | CD45: =CD41-CD42 -> 5832.613 | CI45: =CI41-CI42 -> 6151.5387 | CN45: =CN41-CN42 -> 6407.623 | CS45: =CS41-CS42 -> 6758.5433
B47: Non-GAAP EPS (basic) | H47: =H45/H135 -> 0.026687277 | I47: =I45/I135 -> -0.027988813 | J47: =J45/J135 -> -0.32170018 | K47: =K45/K135 -> -0.5671008 | L47: =L45/L135 -> -0.90394209 | M47: =M45/M135 -> -0.65007493 | N47: =N45/N135 -> -0.60612982 | O47: =O45/O135 -> -0.36518208 | ... S47: =S45/S135 -> -0.54280042 | T47: =T45/T51 -> -0.13195079 | U47: =U45/U51 -> 0.18041712 | V47: =V45/V51 -> -1.100844 | W47: =W45/W51 -> 0.090895087 | X47: =X45/X51 -> 0.23712175 | Y47: =Y45/Y51 -> 0.17390901 | Z47: =Z45/Z51 -> 0.35295471 | AA47: =AA45/AA51 -> 0.85442504 | ... AK47: =AK45/AK51 -> 2.9563768 | AP47: =AP45/AP51 -> 3.4978902 | AU47: =AU45/AU51 -> 6.9519996 | AZ47: =AZ45/AZ51 -> 11.241412 | BE47: =BE45/BE51 -> 11.648869 | BJ47: =BJ45/BJ51 -> 12.343358 | BO47: =BO45/BO51 -> 13.092887 | BT47: =BT45/BT51 -> 15.381708 | BY47: =BY45/BY51 -> 19.754225 | CD47: =CD45/CD51 -> 20.545989 | CI47: =CI45/CI51 -> 21.45489 | CN47: =CN45/CN51 -> 22.126774 | CS47: =CS45/CS51 -> 23.107495
B48: Non-GAAP EPS (diluted) | H48: =H45/H136 -> 0.026687277 | I48: =I45/I136 -> -0.027988813 | J48: =J45/J136 -> -0.32170018 | K48: =K45/K136 -> -0.5671008 | L48: =L45/L136 -> -0.90394209 | M48: =M45/M136 -> -0.65007493 | N48: =N45/N136 -> -0.60612982 | O48: =O45/O136 -> -0.36518208 | ... S48: =S45/S136 -> -0.54280042 | T48: =T45/T52 -> -0.13195079 | U48: =U45/U52 -> 0.18041712 | V48: =V45/V52 -> -1.100844 | W48: =W45/W52 -> 0.090895087 | X48: =X45/X52 -> 0.23712175 | Y48: =Y45/Y52 -> 0.17390901 | Z48: =Z45/Z52 -> 0.35295471 | AA48: =AA45/AA52 -> 0.83502375 | ... AK48: =AK45/AK52 -> 2.9563768 | AP48: =AP45/AP52 -> 3.4978902 | AU48: =AU45/AU52 -> 6.9519996 | AZ48: =AZ45/AZ52 -> 11.241412 | BE48: =BE45/BE52 -> 11.648869 | BJ48: =BJ45/BJ52 -> 12.343358 | BO48: =BO45/BO52 -> 13.092887 | BT48: =BT45/BT52 -> 15.381708 | BY48: =BY45/BY52 -> 19.754225 | CD48: =CD45/CD52 -> 20.545989 | CI48: =CI45/CI52 -> 21.45489 | CN48: =CN45/CN52 -> 22.126774 | CS48: =CS45/CS52 -> 23.107495
B49: Consensus EPS | AG49: =_xll.TR($DH$1,"TR.EPSMean","Period=#1 Curn=#2 Null=-",,LEFT(AG$2,1)&"CQ20"&MID(AG$2,3,2),$DH$2) -> #NAME? | AH49: =_xll.TR($DH$1,"TR.EPSMean","Period=#1 Curn=#2 Null=-",,LEFT(AH$2,1)&"CQ20"&MID(AH$2,3,2),$DH$2) -> #NAME? | AI49: =_xll.TR($DH$1,"TR.EPSMean","Period=#1 Curn=#2 Null=-",,LEFT(AI$2,1)&"CQ20"&MID(AI$2,3,2),$DH$2) -> #NAME? | AJ49: =_xll.TR($DH$1,"TR.EPSMean","Period=#1 Curn=#2 Null=-",,LEFT(AJ$2,1)&"CQ20"&MID(AJ$2,3,2),$DH$2) -> #NAME? | AK49: =_xll.TR($DH$1,"AVAIL(TR.EPSMean(Methodology=WeightedAnnual),TR.EPSMean(Methodology=Interimsum))","Period=#1 Curn=#2 Null=BLANK",,"CY"&LEFT(AK$2,4),$DH$2) -> #NAME? | AP49: =_xll.TR($DH$1,"AVAIL(TR.EPSMean(Methodology=WeightedAnnual),TR.EPSMean(Methodology=Interimsum))","Period=#1 Curn=#2 Null=BLANK",,"CY"&LEFT(AP$2,4),$DH$2) -> #NAME? | AU49: =_xll.TR($DH$1,"AVAIL(TR.EPSMean(Methodology=WeightedAnnual),TR.EPSMean(Methodology=Interimsum))","Period=#1 Curn=#2 Null=BLANK",,"CY"&LEFT(AU$2,4),$DH$2) -> #NAME?
B51: Basic Shares Outstanding | H51: 215.421 | I51: 222.053 | J51: 230.505 | K51: 231.264 | L51: 224.906 | M51: 232.887 | N51: 233.808 | O51: 236.137 | P51: 238.272 | Q51: 235.307 | R51: 239.493 | S51: 240.757 | T51: 241.969 | U51: 246.307 | V51: =AVERAGE(R51:U51) -> 242.1315 | W51: 246.68 | X51: 244.482 | Y51: 248.009 | Z51: 247.757 | AA51: =AVERAGE(W51:Z51) -> 246.732 | AB51: 248.7 | AC51: 251.635 | AD51: 255.792 | AE51: 256.804 | AF51: =AVERAGE(AB51:AE51) -> 253.23275 | AG51: =AK51 -> 259.56357 | AH51: =AK51 -> 259.56357 | AI51: =AK51 -> 259.56357 | AJ51: =AK51 -> 259.56357 | AK51: =AF51*1.025 -> 259.56357 | AP51: =AK51*1.01 -> 262.1592 | AU51: =AP51*1.01 -> 264.7808 | AZ51: =AU51*1.01 -> 267.4286 | BE51: =AZ51*1.01 -> 270.10289 | BJ51: =BE51*1.01 -> 272.80392 | BO51: =BJ51*1.01 -> 275.53196 | BT51: =BO51*1.01 -> 278.28728 | BY51: =BT51*1.01 -> 281.07015 | CD51: =BY51*1.01 -> 283.88085 | CI51: =CD51*1.01 -> 286.71966 | CN51: =CI51*1.01 -> 289.58686 | CS51: =CN51*1.01 -> 292.48273
B52: Diluted Shares Outstanding | H52: 215.421 | I52: 222.053 | J52: 230.505 | K52: 231.264 | L52: 224.906 | M52: =M51 -> 232.887 | N52: 233.808 | O52: 236.137 | P52: 238.272 | Q52: 235.307 | R52: =R51 -> 239.493 | S52: 240.757 | T52: =T51 -> 241.969 | U52: 246.307 | V52: =AVERAGE(R52:U52) -> 242.1315 | W52: =W51 -> 246.68 | X52: =X51 -> 244.482 | Y52: =Y51 -> 248.009 | Z52: =Z51 -> 247.757 | AA52: =U52*1.025 -> 252.46467 | AB52: =AB51 -> 248.7 | AC52: =AC51 -> 251.635 | AD52: =AD51 -> 255.792 | AE52: =AE51 -> 256.804 | AF52: =AVERAGE(AB52:AE52) -> 253.23275 | AG52: =AG51 -> 259.56357 | AH52: =AH51 -> 259.56357 | AI52: =AI51 -> 259.56357 | AJ52: =AJ51 -> 259.56357 | AK52: =AF52*1.025 -> 259.56357 | AP52: =AK52*1.01 -> 262.1592 | AU52: =AP52*1.01 -> 264.7808 | AZ52: =AU52*1.01 -> 267.4286 | BE52: =AZ52*1.01 -> 270.10289 | BJ52: =BE52*1.01 -> 272.80392 | BO52: =BJ52*1.01 -> 275.53196 | BT52: =BO52*1.01 -> 278.28728 | BY52: =BT52*1.01 -> 281.07015 | CD52: =BY52*1.01 -> 283.88085 | CI52: =CD52*1.01 -> 286.71966 | CN52: =CI52*1.01 -> 289.58686 | CS52: =CN52*1.01 -> 292.48273
L54: =+L57+L63+L64+L69+L74+L75+L76 -> -923.0845
B56: Non-GAAP Adjustments
B57: Non-GAAP Adjustment to Revenue | G57: =G58+G62 -> 0 | H57: =H58+H62 -> 0 | I57: =I58+I62 -> 0 | J57: =J58+J62 -> 0 | K57: =K58+K62 -> -182.396 | L57: =L58+L62 -> -182.396 | M57: 0 | N57: 0 | O57: =O58+O62 -> -13.972 | P57: 0 | R57: =R58+R62 -> -3.069 | S57: =S58+S62 -> -6.168 | T57: =T58+T62 -> -7.52 | U57: =U58+U62 -> -7.58 | V57: =V58+V62 -> -24.337 | W57: =W58+W62 -> -0.925 | X57: =X58+X62 -> -0.084 | Y57: =Y58+Y62 -> -0.246 | ... AA57: =AA58+AA62 -> -1.47 | AF57: =AF58+AF62 -> 0 | AK57: =AK58+AK62 -> 0 | AP57: =AP58+AP62 -> 0 | AU57: =AU58+AU62 -> 0
B58: HCV related revenues | H58: 0 | I58: 0 | J58: 0 | K58: -182.396 | L58: =SUM(H58:K58) -> -182.396 | M58: -10.241 | N58: -16.445 | O58: =-44.626-M58-N58-P58 -> -13.972 | P58: -3.968 | Q58: =SUM(M58:P58) -> -44.626 | R58: -2.869 | S58: -6.094 | T58: =T59+T60+T61 -> -7.52 | U58: =U59+U60+U61 -> -7.58 | V58: =SUM(R58:U58) -> -24.063 | W58: =W59+W60+W61+W62 -> -0.925 | X58: =X59+X60+X61+X62 -> -0.084 | Y58: =Y59+Y60+Y61+Y62 -> -0.246 | Z58: =Z59+Z60+Z61 -> -0.121 | AA58: =SUM(W58:Z58) -> -1.376
B59: INCIVEK revenues | M59: -3.946 | N59: -9.264 | O59: -10.298 | P59: =24.071-SUM(M89:O89) -> 0.563 | Q59: =SUM(M59:P59) -> -22.945 | R59: -0.701 | S59: -5.5 | T59: =-T89 -> -5.811 | U59: =-U89 -> -5.975 | V59: =SUM(R59:U59) -> -17.987 | AA59: =SUM(W59:Z59) -> 0
B60: Collaborative revenues | M60: -1.4 | N60: -1.5 | O60: -1.4 | P60: -2.8 | Q60: =SUM(M60:P60) -> -7.1 | R60: =R58-R59-R61 -> -0.668 | S60: -0.611 | T60: =-6.415-T59 -> -0.604 | U60: =-6.071-U59 -> -0.096 | V60: =SUM(R60:U60) -> -1.979 | W60: -0.074 | X60: -0.573 | Y60: -0.043 | Z60: -0.121 | AA60: =SUM(W60:Z60) -> -0.811 | AB60: -232.462 | AC60: -27.222 | AD60: =-21.082-5.209 -> -26.291 | AE60: =-0.497-28.509 -> -29.006 | AF60: =AE60+AD60+AC60+AB60 -> -314.981
B61: Royalty revenues | M61: =M58-M59-M60 -> -4.895 | N61: =N58-N59-N60 -> -5.681 | O61: =O58-O59-O60 -> -2.274 | P61: =P58-P59-P60 -> -1.731 | Q61: =SUM(M61:P61) -> -14.581 | R61: -1.5 | S61: =S58-S59-S60 -> 0.017 | T61: -1.105 | U61: -1.509 | V61: =SUM(R61:U61) -> -4.097 | W61: =-0.851 -> -0.851 | X61: 0.489 | Y61: -0.203 | Z61: 0 | AA61: =SUM(W61:Z61) -> -0.565
B62: Other adjustments | H62: 0 | I62: 0 | J62: 0 | K62: 0 | L62: =SUM(H62:K62) -> 0 | M62: 0 | N62: 0 | O62: 0 | P62: 0 | Q62: =SUM(M62:P62) -> 0 | R62: -0.2 | S62: -0.074 | V62: =SUM(R62:U62) -> -0.274 | Z62: -0.094 | AA62: =SUM(W62:Z62) -> -0.094
B63: Non-GAAP Adjustment to cost of product/royalties | H63: 0 | I63: =-5.083 -> -5.083 | J63: =-17.324+12.048 -> -5.276 | K63: 0 | L63: =SUM(H63:K63) -> -10.359 | M63: -5.887 | N63: -6.233 | O63: =(-142.203+58.44)-(O64+O69+O74-O58-O62) -> -3.166 | P63: -0.801 | Q63: =SUM(M63:P63) -> -16.087 | R63: -1.596 | S63: -0.371 | T63: 1.546 | U63: -0.209 | V63: =SUM(R63:U63) -> -0.63 | W63: -0.139 | X63: 0.006 | Y63: =0.016 -> 0.016 | Z63: 0.098 | AA63: =SUM(W63:Z63) -> -0.019 | AB63: 0 | AC63: 0 | AF63: =AE63+AD63+AC63+AB63 -> 0 | AK63: 0 | AP63: 0 | AU63: 0 | AZ63: 0 | BE63: 0 | BJ63: 0 | BO63: 0 | BT63: 0 | BY63: 0 | CD63: 0 | CI63: 0 | CN63: 0 | CS63: 0
B64: Non-GAAP Adjustment to R&D | G64: =SUM(C64:F64) -> 0 | H64: =SUM(H65:H68) -> -23.321 | I64: =SUM(I65:I68) -> -31.266 | J64: =SUM(J65:J68) -> -19.1555 | K64: =SUM(K65:K68) -> -30.329 | L64: =SUM(L65:L68) -> -104.0715 | M64: =SUM(M65:M68) -> -57.428 | N64: =SUM(N65:N68) -> -45.268 | O64: =SUM(O65:O68) -> -33.556 | ... U64: =SUM(U65:U68) -> -106.671 | V64: =SUM(R64:U64) -> -231.739 | W64: =SUM(W65:W68) -> -33.814 | X64: =SUM(X65:X68) -> -53.335 | Y64: =SUM(Y65:Y68) -> -61.404 | Z64: =SUM(Z65:Z68) -> -41.367 | AA64: =SUM(W64:Z64) -> -189.92 | AB64: =SUM(AB65:AB68) -> -46.982 | AC64: =SUM(AC65:AC68) -> -48.992 | AD64: =SUM(AD65:AD68) -> -211.735 | AE64: =SUM(AE65:AE68) -> -57.43 | AF64: =AE64+AD64+AC64+AB64 -> -365.139 | AG64: =SUM(AG65:AG68) -> -41.25 | AH64: =SUM(AH65:AH68) -> -41.25 | AI64: =SUM(AI65:AI68) -> -41.25 | AJ64: =SUM(AJ65:AJ68) -> -41.25 | AK64: =+SUM(AK65:AK68) -> -165 | AP64: =+SUM(AP65:AP68) -> -165 | AU64: =+SUM(AU65:AU68) -> -165 | AZ64: =+SUM(AZ65:AZ68) -> -165 | BE64: =+SUM(BE65:BE68) -> -165 | BJ64: =+SUM(BJ65:BJ68) -> -165 | BO64: =+SUM(BO65:BO68) -> -165 | BT64: =+SUM(BT65:BT68) -> -165 | BY64: =+SUM(BY65:BY68) -> -165 | CD64: =+SUM(CD65:CD68) -> -165 | CI64: =+SUM(CI65:CI68) -> -165 | CN64: =+SUM(CN65:CN68) -> -165 | CS64: =+SUM(CS65:CS68) -> -165
B65: Stock-based compesnation expense | H65: -19.273 | I65: -25.7 | J65: -19.1555 | K65: -17.075 | L65: =SUM(H65:K65) -> -81.2035 | M65: -32.9 | N65: -27.253 | O65: -31.131 | P65: -25.714 | Q65: =SUM(M65:P65) -> -116.998 | R65: -38.217 | S65: -41.632 | T65: -44.7 | U65: -28.696 | V65: =SUM(R65:U65) -> -153.245 | W65: -34.448 | X65: -40.64 | Y65: -39.98 | Z65: -38.383 | AA65: =SUM(W65:Z65) -> -153.451 | AB65: -44.837 | AC65: -43.832 | AD65: -46.186 | AE65: -47.045 | AF65: =AE65+AD65+AC65+AB65 -> -181.9 | AG65: =AK65/4 -> -41.25 | AH65: =AK65/4 -> -41.25 | AI65: =AK65/4 -> -41.25 | AJ65: =AK65-SUM(AG65:AI65) -> -41.25 | AK65: =-AK141 -> -165 | AP65: =-AP141 -> -165 | AU65: =-AU141 -> -165 | AZ65: =-AZ141 -> -165 | BE65: =-BE141 -> -165 | BJ65: =-BJ141 -> -165 | BO65: =-BO141 -> -165 | BT65: =-BT141 -> -165 | BY65: =-BY141 -> -165 | CD65: =-CD141 -> -165 | CI65: =-CI141 -> -165 | CN65: =-CN141 -> -165 | CS65: =-CS141 -> -165
B66: Real estate restructuring costs | H66: 0 | I66: 0 | J66: 0 | K66: -5.288 | L66: =SUM(H66:K66) -> -5.288 | M66: -12.201 | N66: -9.382 | O66: -3.511 | P66: 0 | Q66: =SUM(M66:P66) -> -25.094 | R66: 0 | S66: 0 | T66: 0 | U66: 0 | V66: =SUM(R66:U66) -> 0 | AA66: =SUM(W66:Z66) -> 0 | AF66: 0 | AK66: 0 | AP66: 0 | AU66: 0 | AZ66: 0 | BE66: 0 | BJ66: 0 | BO66: 0 | BT66: 0 | BY66: 0 | CD66: 0 | CI66: 0 | CN66: 0 | CS66: 0
B67: HCV related costs | H67: 0 | I67: 0 | J67: 0 | K67: -7.966 | L67: =SUM(H67:K67) -> -7.966 | M67: -9.002 | N67: -5.049 | O67: -1.494 | P67: -0.159 | Q67: =SUM(M67:P67) -> -15.704 | R67: 0.488 | S67: 0.512 | T67: -0.294 | U67: -0.213 | V67: =SUM(R67:U67) -> 0.493 | W67: 0.826 | X67: 0.051 | Y67: 2.465 | Z67: -0.013 | AA67: =SUM(W67:Z67) -> 3.329 | AF67: 0 | AK67: 0 | AP67: 0 | AU67: 0 | AZ67: 0 | BE67: 0 | BJ67: 0 | BO67: 0 | BT67: 0 | BY67: 0 | CD67: 0 | CI67: 0 | CN67: 0 | CS67: 0
B68: Other adjustments | H68: -4.048 | I68: -5.566 | J68: 0 | K68: 0 | L68: =SUM(H68:K68) -> -9.614 | M68: -3.325 | N68: -3.584 | O68: 2.58 | P68: 0.087 | Q68: =SUM(M68:P68) -> -4.242 | R68: -0.696 | S68: -0.827 | T68: 0.298 | U68: =-77.762 -> -77.762 | V68: =SUM(R68:U68) -> -78.987 | W68: -0.192 | X68: -12.746 | Y68: -23.889 | Z68: -2.971 | AA68: =SUM(W68:Z68) -> -39.798 | AB68: =-2.009-0.136 -> -2.145 | AC68: =-5.024-0.136 -> -5.16 | AD68: =-160-3.548-1.865-0.136 -> -165.549 | AE68: =-0.967-9.282-0.136 -> -10.385 | AF68: =AE68+AD68+AC68+AB68 -> -183.239 | AK68: 0 | AP68: 0 | AU68: 0 | AZ68: 0 | BE68: 0 | BJ68: 0 | BO68: 0 | BT68: 0 | BY68: 0 | CD68: 0 | CI68: 0 | CN68: 0 | CS68: 0
B69: Non-GAAP Adjustment to SG&A | G69: =SUM(C69:F69) -> 0 | H69: =SUM(H70:H73) -> -13.12 | I69: =SUM(I70:I73) -> -17.004 | J69: =SUM(J70:J73) -> -12.042 | K69: =SUM(K70:K73) -> -7.607 | L69: =SUM(H69:K69) -> -49.773 | M69: =SUM(M70:M73) -> -21.801 | N69: =SUM(N70:N73) -> -19.563 | O69: =SUM(O70:O73) -> -20.17 | P69: =SUM(P70:P73) -> -18.159 | Q69: =SUM(M69:P69) -> -79.693 | R69: =SUM(R70:R73) -> -16.711 | S69: =SUM(S70:S73) -> -22.378 | T69: =SUM(T70:T73) -> -23.655 | U69: =SUM(U70:U73) -> -18.919 | V69: =SUM(R69:U69) -> -81.663 | W69: =SUM(W70:W73) -> -21.535 | X69: =SUM(X70:X73) -> -23.061 | Y69: =SUM(Y70:Y73) -> -22.063 | Z69: =SUM(Z70:Z73) -> -21.986 | AA69: =SUM(W69:Z69) -> -88.645 | AB69: =SUM(AB70:AB73) -> -26.982 | AC69: =SUM(AC70:AC73) -> -34.343 | AD69: =SUM(AD70:AD73) -> -30.153 | AE69: =SUM(AE70:AE73) -> -29.29 | AF69: =AE69+AD69+AC69+AB69 -> -120.768 | AG69: =SUM(AG70:AG73) -> -20 | AH69: =SUM(AH70:AH73) -> -20 | AI69: =SUM(AI70:AI73) -> -20 | AJ69: =SUM(AJ70:AJ73) -> -20 | AK69: =SUM(AK70:AK73) -> -80 | AP69: =SUM(AP70:AP73) -> -80 | AU69: =SUM(AU70:AU73) -> -80 | AZ69: =SUM(AZ70:AZ73) -> -80 | BE69: =SUM(BE70:BE73) -> -80 | BJ69: =SUM(BJ70:BJ73) -> -80 | BO69: =SUM(BO70:BO73) -> -80 | BT69: =SUM(BT70:BT73) -> -80 | BY69: =SUM(BY70:BY73) -> -80 | CD69: =SUM(CD70:CD73) -> -80 | CI69: =SUM(CI70:CI73) -> -80 | CN69: =SUM(CN70:CN73) -> -80 | CS69: =SUM(CS70:CS73) -> -80
B70: Stock-based compesnation expense | H70: -11.879 | I70: -15.563 | J70: -12.042 | K70: -6.165 | L70: =SUM(H70:K70) -> -45.649 | M70: -13.68 | N70: -15.191 | O70: -15.005 | P70: -16.667 | Q70: =SUM(M70:P70) -> -60.543 | R70: -19.167 | S70: -21.629 | T70: -21.034 | U70: -16.743 | V70: =SUM(R70:U70) -> -78.573 | W70: -21.024 | X70: -21.302 | Y70: -21.229 | Z70: -20.699 | AA70: =SUM(W70:Z70) -> -84.254 | AB70: -24.145 | AC70: -28.75 | AD70: -27.584 | AE70: -28.357 | AF70: =AE70+AD70+AC70+AB70 -> -108.836 | AG70: =AK70/4 -> -20 | AH70: =AK70/4 -> -20 | AI70: =AK70/4 -> -20 | AJ70: =AK70-SUM(AG70:AI70) -> -20 | AK70: =-AK142 -> -80 | AP70: =-AP142 -> -80 | AU70: =-AU142 -> -80 | AZ70: =-AZ142 -> -80 | BE70: =-BE142 -> -80 | BJ70: =-BJ142 -> -80 | BO70: =-BO142 -> -80 | BT70: =-BT142 -> -80 | BY70: =-BY142 -> -80 | CD70: =-CD142 -> -80 | CI70: =-CI142 -> -80 | CN70: =-CN142 -> -80 | CS70: =-CS142 -> -80
B71: Real estate restructuring costs | H71: 0 | I71: 0 | J71: 0 | K71: -1.442 | L71: =SUM(H71:K71) -> -1.442 | M71: -2.2 | N71: -1.706 | O71: -0.633 | P71: -0.122 | Q71: =SUM(M71:P71) -> -4.661 | R71: 0 | S71: 0 | T71: 0 | U71: 0 | V71: =SUM(R71:U71) -> 0 | AA71: =SUM(W71:Z71) -> 0 | AF71: 0 | AK71: 0 | AP71: 0 | AU71: 0 | AZ71: 0 | BE71: 0 | BJ71: 0 | BO71: 0 | BT71: 0 | BY71: 0 | CD71: 0 | CI71: 0 | CN71: 0 | CS71: 0
B72: HCV related costs | H72: 0 | I72: 0 | J72: 0 | K72: 0 | L72: =SUM(H72:K72) -> 0 | M72: -5.921 | N72: -2.666 | O72: -4.532 | P72: -0.879 | Q72: =SUM(M72:P72) -> -13.998 | R72: 2.904 | S72: -0.054 | T72: -0.043 | U72: 0 | V72: =SUM(R72:U72) -> 2.807 | W72: 0.032 | X72: -0.061 | Y72: -0.076 | Z72: -0.127 | AA72: =SUM(W72:Z72) -> -0.232 | AF72: 0 | AK72: 0 | AP72: 0 | AU72: 0 | AZ72: 0 | BE72: 0 | BJ72: 0 | BO72: 0 | BT72: 0 | BY72: 0 | CD72: 0 | CI72: 0 | CN72: 0 | CS72: 0
B73: Other adjustments | H73: -1.241 | I73: -1.441 | J73: 0 | K73: 0 | L73: =SUM(H73:K73) -> -2.682 | M73: 0 | N73: 0 | O73: 0 | P73: -0.491 | Q73: =SUM(M73:P73) -> -0.491 | R73: -0.448 | S73: -0.695 | T73: -2.578 | U73: -2.176 | V73: =SUM(R73:U73) -> -5.897 | W73: -0.543 | X73: -1.698 | Y73: -0.758 | Z73: -1.16 | AA73: =SUM(W73:Z73) -> -4.159 | AB73: =-2.004-0.833 -> -2.837 | AC73: =-4.984-0.609 -> -5.593 | AD73: =-0.962-1.201-0.109-0.297 -> -2.569 | AE73: =-0.465-0.05-0.418 -> -0.933 | AF73: =AE73+AD73+AC73+AB73 -> -11.932 | AK73: 0 | AP73: 0 | AU73: 0 | AZ73: 0 | BE73: 0 | BJ73: 0 | BO73: 0 | BT73: 0 | BY73: 0 | CD73: 0 | CI73: 0 | CN73: 0 | CS73: 0
B74: Non-GAAP Adjustment to restructuring expense, impairment charges | G74: =SUM(C74:F74) -> 0 | H74: =-H104 -> -412.939 | I74: =-I104 -> -0.776 | J74: =-J104 -> -12.048 | K74: =-K104 -> -27.658 | L74: =SUM(H74:K74) -> -453.421 | M74: =-M104 -> -6.188 | N74: =-N104 -> 0.27 | O74: =-O104 -> -40.843 | P74: =-P104 -> -4.164 | Q74: =SUM(M74:P74) -> -50.925 | R74: =-R104 -> 3.272 | S74: =-S104 -> -2.128 | T74: =-T104 -> -1.826 | U74: =-U104 -> -1.524 | V74: =SUM(R74:U74) -> -2.206 | W74: =-W104 -> -0.687 | X74: =-X104 -> -0.343 | Y74: =-Y104 -> -0.008 | AA74: =SUM(W74:Z74) -> -1.038 | AB74: =-10.968+0.136+0.833 -> -9.999 | AC74: -3.523 | AD74: =-255.34-0.337 -> -255.677 | AE74: -0.387 | AF74: =AE74+AD74+AC74+AB74 -> -269.586 | AK74: =SUM(AG74:AJ74) -> 0 | AP74: =SUM(AL74:AO74) -> 0 | AU74: =SUM(AQ74:AT74) -> 0 | AZ74: =SUM(AV74:AY74) -> 0 | BE74: =SUM(BA74:BD74) -> 0 | BJ74: =SUM(BF74:BI74) -> 0 | BO74: =SUM(BK74:BN74) -> 0 | BT74: =SUM(BP74:BS74) -> 0 | BY74: =SUM(BU74:BX74) -> 0 | CD74: =SUM(BZ74:CC74) -> 0 | CI74: =SUM(CE74:CH74) -> 0 | CN74: =SUM(CJ74:CM74) -> 0 | CS74: =SUM(CO74:CR74) -> 0
B75: Non-GAAP Adjustment to other income/(expense) | G75: =SUM(C75:F75) -> 0 | H75: 0.008 | I75: =3.908-0.183 -> 3.725 | J75: 0 | K75: 9.276 | L75: =SUM(H75:K75) -> 13.009 | M75: 0 | N75: -36.685 | O75: 0 | P75: -0.013 | Q75: =SUM(M75:P75) -> -36.698 | R75: 0 | S75: 0 | V75: =SUM(R75:U75) -> 0 | W75: 0.211 | X75: -0.036 | Y75: -0.036 | Z75: -0.032 | AA75: =SUM(W75:Z75) -> 0.107 | AB75: -0.034 | AC75: -0.04 | AD75: 76.581 | AE75: -0.004 | AF75: =AE75+AD75+AC75+AB75 -> 76.503 | AK75: =SUM(AG75:AJ75) -> 0 | AP75: =SUM(AL75:AO75) -> 0 | AU75: =SUM(AQ75:AT75) -> 0 | AZ75: =SUM(AV75:AY75) -> 0 | BE75: =SUM(BA75:BD75) -> 0 | BJ75: =SUM(BF75:BI75) -> 0 | BO75: =SUM(BK75:BN75) -> 0 | BT75: =SUM(BP75:BS75) -> 0 | BY75: =SUM(BU75:BX75) -> 0 | CD75: =SUM(BZ75:CC75) -> 0 | CI75: =SUM(CE75:CH75) -> 0 | CN75: =SUM(CJ75:CM75) -> 0 | CS75: =SUM(CO75:CR75) -> 0
B76: Non-GAAP Adjustment to taxes | H76: -131.012 | I76: -2.357 | J76: 0 | K76: -2.704 | L76: =SUM(H76:K76) -> -136.073 | M76: 0 | N76: 0 | O76: 0 | P76: -3.876 | R76: -0.063 | S76: 29.653 | T76: 0.777 | U76: -0.636 | V76: =SUM(R76:U76) -> 29.731 | W76: 3.063 | X76: 17.51 | Y76: -0.509 | Z76: -3.32 | AA76: =SUM(W76:Z76) -> 16.744 | AB76: 0.391 | AC76: 8.132 | AD76: -120.181 | AE76: -2.432 | AF76: =AE76+AD76+AC76+AB76 -> -114.09 | AK76: 0 | AP76: 0 | AU76: 0 | AZ76: 0 | BE76: 0 | BJ76: 0 | BO76: 0 | BT76: 0 | BY76: 0 | CD76: 0 | CI76: 0 | CN76: 0 | CS76: 0
B79: VERTEX PHARMACEUTICALS INC. (NSDQ:VRTX) | C79: 1Q12 | D79: 2Q12 | E79: 3Q12 | F79: 4Q12 | G79: 2012 | H79: 1Q13 | I79: 2Q13 | J79: 3Q13 | K79: 4Q13 | L79: 2013 | M79: 1Q14 | N79: 2Q14 | O79: 3Q14 | P79: 4Q14 | Q79: 2014 | R79: 1Q15A | S79: 2Q15A | T79: 3Q15A | U79: 4Q15A | V79: 2015A | W79: 1Q16A | X79: 2Q16A | Y79: 3Q16A | Z79: 4Q16A | AA79: 2016A | AB79: 1Q17A | AC79: 2Q17A | AD79: 3Q17A | AE79: 4Q17A | AF79: 2017A | AG79: 1Q18E | AH79: 2Q18E | AI79: 3Q18E | AJ79: 4Q18E | AK79: 2018E | AL79: 1Q19E | AM79: 2Q19E | AN79: 3Q19E | AO79: 4Q19E | AP79: 2019E | AQ79: 1Q20E | AR79: 2Q20E | AS79: 3Q20E | AT79: 4Q20E | AU79: 2020E | AV79: 1Q21E | AW79: 2Q21E | AX79: 3Q21E | AY79: 4Q21E | AZ79: 2021E | BA79: 1Q22E | BB79: 2Q22E | BC79: 3Q22E | BD79: 4Q22E | BE79: 2022E | BF79: 1Q23E | BG79: 2Q23E | BH79: 3Q23E | BI79: 4Q23E | BJ79: 2023E | BK79: 1Q24E | BL79: 2Q24E | BM79: 3Q24E | BN79: 4Q24E | BO79: 2024E | BP79: 1Q25E | BQ79: 2Q25E | BR79: 3Q25E | BS79: 4Q25E | BT79: 2025E | BU79: 1Q26E | BV79: 2Q26E | BW79: 3Q26E | BX79: 4Q26E | BY79: 2026E | BZ79: 1Q27E | CA79: 2Q27E | CB79: 3Q27E | CC79: 4Q27E | CD79: 2027E | CE79: 1Q28E | CF79: 2Q28E | CG79: 3Q28E | CH79: 4Q28E | CI79: 2028E | CJ79: 1Q29E | CK79: 2Q29E | CL79: 3Q29E | CM79: 4Q29E | CN79: 2029E | CO79: 1Q30E | CP79: 2Q30E | CQ79: 3Q30E | CR79: 4Q30E | CS79: 2030E
B81: Revenues | H81: =H83+H91+H93 -> 328.368 | I81: =I83+I91+I93 -> 310.75 | J81: =J83+J91+J93 -> 221.7 | K81: =K83+K91+K93 -> 351.157 | L81: =L83+L91+L93 -> 1211.975 | M81: =M83+M91+M93 -> 118.451 | N81: =N83+N91+N93 -> 138.421 | O81: =O83+O91+O93 -> 178.987 | ... U81: =U83+U91+U93 -> 417.935 | V81: =SUM(R81:U81) -> 1032.336 | W81: =W83+W91+W93 -> 398.08 | X81: =X83+X91+X93 -> 431.608 | Y81: =Y83+Y91+Y93 -> 413.783 | Z81: =Z83+Z91+Z93 -> 458.706 | AA81: =AA15+AA17+AA18 -> 1700.801 | AB81: =AB83+AB91+AB93 -> 714.718 | AC81: =AC83+AC91+AC93 -> 544.135 | AD81: =AD83+AD91+AD93 -> 578.165 | AE81: =AE83+AE91+AE93 -> 651.634 | AF81: =AF83+AF91+AF93 -> 2488.652 | AG81: =AG83+AG91+AG93 -> 600 | AH81: =AH83+AH91+AH93 -> 645 | AI81: =AI83+AI91+AI93 -> 695 | AJ81: =AJ83+AJ91+AJ93 -> 722.68467 | AK81: =AK15+AK17+AK18 -> 2662.6847 | AP81: =AP15+AP17+AP18 -> 2929.7892 | AU81: =AU15+AU17+AU18 -> 4032.845 | AZ81: =AZ15+AZ17+AZ18 -> 5352.0546 | BE81: =BE15+BE17+BE18 -> 6180.1313 | BJ81: =BJ15+BJ17+BJ18 -> 6549.5105 | BO81: =BO15+BO17+BO18 -> 6707.1044 | BT81: =BT15+BT17+BT18 -> 7367.4607 | BY81: =BY15+BY17+BY18 -> 8877.466 | CD81: =CD15+CD17+CD18 -> 9000.8703 | CI81: =CI15+CI17+CI18 -> 9103.7533 | CN81: =CN15+CN17+CN18 -> 9114.9124 | CS81: =CS15+CS17+CS18 -> 9197.9033
AJ82: =SUM(AG96:AJ96) -> 320.94964
B83: Net product sales | H83: =H84+H86+H89 -> 267.381 | I83: =I84+I86+I89 -> 254.789 | J83: =J84+J86+J89 -> 186.653 | K83: =K84+K86+K89 -> 128.822 | L83: =L84+L86+L89 -> 837.645 | M83: =M84+M86+M89 -> 103.461 | N83: =N84+N86+N89 -> 122.319 | O83: =O84+O86+O89 -> 137.099 | ... AC83: =AC84+AC86+AC89 -> 513.988 | AD83: 549.642 | AE83: 621.228 | AF83: =AF84+AF86+AF89+AF87+AF88 -> 2165.48 | AG83: =SUM(AG84:AG89) -> 600 | AH83: =SUM(AH84:AH89) -> 645 | AI83: =SUM(AI84:AI89) -> 695 | AJ83: =SUM(AJ84:AJ89) -> 722.68467 | AK83: =AK84+AK86+AK89+AK87+AK88 -> 2662.6847 | AP83: =AP84+AP86+AP89+AP87+AP88 -> 2929.7892 | AU83: =AU84+AU86+AU89+AU87+AU88 -> 4032.845 | AZ83: =AZ84+AZ86+AZ89+AZ87+AZ88 -> 5352.0546 | BE83: =BE84+BE86+BE89+BE87+BE88 -> 6180.1313 | BJ83: =BJ84+BJ86+BJ89+BJ87+BJ88 -> 6549.5105 | BO83: =BO84+BO86+BO89+BO87+BO88 -> 6707.1044 | BT83: =BT84+BT86+BT89+BT87+BT88 -> 6755.9128 | BY83: =BY84+BY86+BY89+BY87+BY88 -> 8089.7664 | CD83: =CD84+CD86+CD89+CD87+CD88 -> 8216.6256 | CI83: =CI84+CI86+CI89+CI87+CI88 -> 8035.3227 | CN83: =CN84+CN86+CN89+CN87+CN88 -> 8045.2762 | CS83: =CS84+CS86+CS89+CS87+CS88 -> 8038.348
B84: KALYDECO | H84: 61.827 | I84: 98.973 | J84: 101.061 | K84: =371.285-SUM(H84:J84) -> 109.424 | L84: =SUM(H84:K84) -> 371.285 | M84: 99.515 | N84: 113.055 | O84: 126.801 | P84: =463.75-SUM(M84:O84) -> 124.379 | Q84: =SUM(M84:P84) -> 463.75 | R84: 130.174 | S84: 154.888 | T84: 165.9 | U84: =V84-SUM(R84:T84) -> 180.712 | V84: 631.674 | W84: 170.5 | X84: 180 | Y84: 176 | Z84: =AA84-SUM(W84:Y84) -> 176.9 | AA84: 703.4 | AB84: 186 | AC84: 190 | AD84: 213 | AE84: 256 | AF84: =AE84+AD84+AC84+AB84 -> 845 | AG84: =Revs!BK7 -> 230 | AH84: =Revs!BL7 -> 235 | AI84: =Revs!BM7 -> 240 | AJ84: =Revs!BN7 -> 244.21633 | AK84: =AK3 -> 949.21633 | AP84: =AP3 -> 980.27101 | AU84: =AU3 -> 1110.9818 | AZ84: =AZ3 -> 1156.4902 | BE84: =BE3 -> 1148.5928 | BJ84: =BJ3 -> 1140.8533 | BO84: =BO3 -> 1133.2686 | BT84: =BT3 -> 549.58741 | BY84: =BY3 -> 309.22509 | CD84: =CD3 -> 305.22555 | CI84: =CI3 -> 53.740211 | CN84: =CN3 -> 8.7714489 | CS84: =CS3 -> 0
B85: DEUTERATED KALYDECO | AG85: =Revs!BK14 -> 0 | AH85: =Revs!BL14 -> 0 | AI85: =Revs!BM14 -> 0 | AJ85: =Revs!BN14 -> 0 | AK85: =AK5 -> 0 | AP85: =AP5 -> 0 | AU85: =AU5 -> 0 | AZ85: =AZ5 -> 0 | BE85: =BE5 -> 0 | BJ85: =BJ5 -> 0 | BO85: =BO5 -> 0 | BT85: =BT5 -> 611.54792 | BY85: =BY5 -> 787.69957 | CD85: =CD5 -> 784.24476 | CI85: =CI5 -> 1068.4306 | CN85: =CN5 -> 1069.6362 | CS85: =CS5 -> 1159.5553
B86: ORKAMBI | H86: 0 | I86: 0 | J86: 0 | K86: 0 | L86: =SUM(H86:K86) -> 0 | M86: 0 | N86: 0 | O86: 0 | P86: 0 | Q86: =SUM(M86:P86) -> 0 | R86: 0 | S86: 0 | T86: 130.8 | U86: =V86-SUM(R86:T86) -> 219.863 | V86: 350.663 | W86: =394.41-W84 -> 223.91 | X86: =425.651-X84 -> 245.651 | Y86: =409.689-Y84 -> 233.689 | Z86: =AA86-SUM(W86:Y86) -> 276.982 | AA86: 980.232 | AB86: =480.622-AB84 -> 294.622 | AC86: =513.988-AC84 -> 323.988 | AD86: =AD83-AD84 -> 336.642 | AE86: =AE83-AE84 -> 365.228 | AF86: =AE86+AD86+AC86+AB86 -> 1320.48 | AG86: =Revs!BK29 -> 360 | AH86: =Revs!BL29 -> 370 | AI86: =Revs!BM29 -> 380 | AJ86: =Revs!BN29 -> 383.74949 | AK86: =AK7 -> 1493.7495 | AP86: =AP7 -> 1464.5138 | AU86: =AU7 -> 1274.3007 | AZ86: =AZ7 -> 1205.8609 | BE86: =BE7 -> 1054.5016 | BJ86: =BJ7 -> 899.68021 | BO86: =BO7 -> 620.57975 | BT86: =BT7 -> 388.74281 | BY86: =BY7 -> 212.1148 | CD86: =CD7 -> 110.87855 | CI86: =CI7 -> 52.19564 | CN86: =CN7 -> 17.92106 | CS86: =CS7 -> 1.4870667
B87: TEZ/IVA | AG87: =Revs!BK36 -> 10 | AH87: =Revs!BL36 -> 40 | AI87: =Revs!BM36 -> 75 | AJ87: =Revs!BN36 -> 94.718853 | AK87: =AK9 -> 219.71885 | AP87: =AP9 -> 485.0044 | AU87: =AU9 -> 571.63076 | AZ87: =AZ9 -> 599.76369 | BE87: =BE9 -> 538.73244 | BJ87: =BJ9 -> 465.68008 | BO87: =BO9 -> 291.16133 | BT87: =BT9 -> 149.56093 | BY87: =BY9 -> 78.350642 | CD87: =CD9 -> 40.13191 | CI87: =CI9 -> 15.948799 | CN87: =CN9 -> 6.1827656 | CS87: =CS9 -> 0.513038
B88: TRIPLET | AG88: =Revs!BK43 -> 0 | AH88: =Revs!BL43 -> 0 | AI88: =Revs!BM43 -> 0 | AJ88: =Revs!BN43 -> 0 | AK88: =AK11 -> 0 | AP88: =AP11 -> 0 | AU88: =AU11 -> 1075.9316 | AZ88: =AZ11 -> 2389.9398 | BE88: =BE11 -> 3438.3045 | BJ88: =BJ11 -> 4043.2969 | BO88: =BO11 -> 4662.0948 | BT88: =BT11 -> 5668.0216 | BY88: =BY11 -> 7490.0759 | CD88: =CD11 -> 7760.3895 | CI88: =CI11 -> 7913.4381 | CN88: =CN11 -> 8012.4009 | CS88: =CS11 -> 8036.3479
B89: INCIVEK | H89: 205.554 | I89: 155.816 | J89: 85.592 | K89: =466.36-SUM(H89:J89) -> 19.398 | L89: =SUM(H89:K89) -> 466.36 | M89: 3.946 | N89: 9.264 | O89: 10.298 | P89: =24.071-SUM(M89:O89) -> 0.563 | Q89: =SUM(M89:P89) -> 24.071 | R89: 0.701 | S89: 5.5 | T89: 5.811 | U89: =V89-SUM(R89:T89) -> 5.975 | V89: 17.987 | W89: 0 | X89: 0 | Y89: 0 | Z89: 0 | AA89: =AA14 -> 0 | AB89: 0 | AC89: =Revs!BG23 -> 0 | AD89: =Revs!BH23 -> 0 | AE89: =Revs!BI23 -> 0 | AF89: =AE89+AD89+AC89+AB89 -> 0 | AK89: =AK14 -> 0 | AP89: =AP14 -> 0 | AU89: =AU14 -> 0 | AZ89: =AZ14 -> 0 | BE89: =BE14 -> 0 | BJ89: =BJ14 -> 0 | BO89: =BO14 -> 0 | BT89: =BT14 -> 0 | BY89: =BY14 -> 0 | CD89: =CD14 -> 0 | CI89: =CI14 -> 0 | CN89: =CN14 -> 0 | CS89: =CS14 -> 0
B91: Collaboration and license agreement revenues | H91: 17.414 | I91: 6.841 | J91: 8.035 | K91: 185.448 | L91: =SUM(H91:K91) -> 217.738 | M91: 4.257 | N91: 3.087 | O91: 33.502 | P91: 10.829 | Q91: =SUM(M91:P91) -> 51.675 | R91: 0.842 | S91: 0.611 | T91: 1.546 | U91: 5.054 | V91: =SUM(R91:U91) -> 8.053 | W91: 0.074 | X91: 0.675 | Y91: 0.259 | Z91: 0.937 | AA91: =SUM(W91:Z91) -> 1.945 | AB91: 232.545 | AC91: 27.286 | AD91: 26.292 | AE91: 29.061 | AF91: =AE91+AD91+AC91+AB91 -> 315.184 | AG91: =Revs!BK51 -> 0 | AH91: =Revs!BL51 -> 0 | AI91: =Revs!BM51 -> 0 | AJ91: =Revs!BN51 -> 0 | AK91: =Revs!BO51 -> 0 | AP91: =Revs!BT51 -> 0 | AU91: =Revs!BY51 -> 0 | AZ91: =Revs!CD51 -> 0 | BE91: =Revs!CI51 -> 0 | BJ91: =Revs!CN51 -> 0 | BO91: =Revs!CS51 -> 0 | BT91: =Revs!CX51 -> 0 | BY91: =Revs!DC51 -> 0 | CD91: =Revs!DH51 -> 0 | CI91: =Revs!DM51 -> 0 | CN91: =Revs!DR51 -> 0 | CS91: =Revs!DW51 -> 0
B93: Royalty revenues | H93: 43.573 | I93: 49.12 | J93: 27.012 | K93: 36.887 | L93: =SUM(H93:K93) -> 156.592 | M93: 10.733 | N93: 13.015 | O93: 8.386 | P93: 8.785 | Q93: =SUM(M93:P93) -> 40.919 | R93: 6.792 | S93: 5.077 | T93: 5.759 | U93: 6.331 | V93: =SUM(R93:U93) -> 23.959 | W93: 3.596 | X93: 5.282 | Y93: 3.835 | Z93: 3.887 | AA93: =SUM(W93:Z93) -> 16.6 | AB93: 1.551 | AC93: 2.861 | AD93: 2.231 | AE93: 1.345 | AF93: =AE93+AD93+AC93+AB93 -> 7.988 | AG93: =Revs!BK50 -> 0 | AH93: =Revs!BL50 -> 0 | AI93: =Revs!BM50 -> 0 | AJ93: =Revs!BN50 -> 0 | AK93: =Revs!BO50 -> 0 | AP93: =Revs!BT50 -> 0 | AU93: =Revs!BY50 -> 0 | AZ93: =Revs!CD50 -> 0 | BE93: =Revs!CI50 -> 0 | BJ93: =Revs!CN50 -> 0 | BO93: =Revs!CS50 -> 0 | BT93: =Revs!CX50 -> 0 | BY93: =Revs!DC50 -> 0 | CD93: =Revs!DH50 -> 0 | CI93: =Revs!DM50 -> 0 | CN93: =Revs!DR50 -> 0 | CS93: =Revs!DW50 -> 0
B95: Costs and expenses
B96: Cost of product revenues | H96: 30.955 | I96: 24.695 | J96: 20.048 | K96: 13.281 | L96: =SUM(H96:K96) -> 88.979 | M96: 8.572 | N96: 9.655 | O96: 10.208 | P96: 11.29 | Q96: =SUM(M96:P96) -> 39.725 | R96: 9.381 | S96: 15.409 | T96: 30.269 | U96: =V96-SUM(R96:T96) -> 62.092 | V96: 117.151 | W96: 49.789 | X96: 44.154 | Y96: 53.222 | Z96: 59.646 | AA96: =SUM(W96:Z96) -> 206.811 | AB96: 46.242 | AC96: 70.535 | AD96: 72.186 | AE96: 83.712 | AF96: =AE96+AD96+AC96+AB96 -> 272.675 | AG96: =AG19/AK19*AK96 -> 72.321663 | AH96: =AH19/AK19*AK96 -> 77.745788 | AI96: =AI19/AK19*AK96 -> 83.772594 | AJ96: =AJ19/AK19*AK96 -> 87.109596 | AK96: =(0.015*(AK3+AK7+AK9+AK11))+'CF Market'!M352+'CF Market'!M353+'CF Market'!M354+'CF Market'!M355 -> 320.94964 | AP96: =(0.015*(AP3+AP7+AP9+AP11))+'CF Market'!N352+'CF Market'!N353+'CF Market'!N354+'CF Market'!N355 -> 354.09854 | AU96: =(0.015*(AU3+AU7+AU9+AU11))+'CF Market'!O352+'CF Market'!O353+'CF Market'!O354+'CF Market'!O355 -> 466.44801 | AZ96: =(0.015*(AZ3+AZ7+AZ9+AZ11))+'CF Market'!P352+'CF Market'!P353+'CF Market'!P354+'CF Market'!P355 -> 585.35894 | BE96: =(0.015*(BE3+BE7+BE9+BE11))+'CF Market'!Q352+'CF Market'!Q353+'CF Market'!Q354+'CF Market'!Q355 -> 652.17576 | BJ96: =(0.015*(BJ3+BJ7+BJ9+BJ11))+'CF Market'!R352+'CF Market'!R353+'CF Market'!R354+'CF Market'!R355 -> 665.53142 | BO96: =(0.015*(BO35+BO7+BO9+BO11))+'CF Market'!S352+'CF Market'!S353+'CF Market'!S354+'CF Market'!S355 -> 650.93668 | BT96: =(0.015*(BT3+BT7+BT9+BT11))+'CF Market'!T352+'CF Market'!T353+'CF Market'!T354+'CF Market'!T355 -> 628.91172 | BY96: =(0.015*(BY3+BY7+BY9+BY11))+'CF Market'!U352+'CF Market'!U353+'CF Market'!U354+'CF Market'!U355 -> 726.81424 | CD96: =(0.015*(CD3+CD7+CD9+CD11))+'CF Market'!V352+'CF Market'!V353+'CF Market'!V354+'CF Market'!V355 -> 740.2834 | CI96: =(0.015*(CI3+CI7+CI9+CI11))+'CF Market'!W352+'CF Market'!W353+'CF Market'!W354+'CF Market'!W355 -> 721.35077 | CN96: =(0.015*(CN3+CN7+CN9+CN11))+'CF Market'!X352+'CF Market'!X353+'CF Market'!X354+'CF Market'!X355 -> 723.58173 | CS96: =(0.015*(CS3+CS7+CS9+CS11))+'CF Market'!Y352+'CF Market'!Y353+'CF Market'!Y354+'CF Market'!Y355 -> 723.42132
B97: Royalty expenses | H97: 11.788 | I97: 13.236 | J97: 7.291 | K97: 8.983 | L97: =SUM(H97:K97) -> 41.298 | M97: 6.904 | N97: 7.645 | O97: 3.976 | P97: 2.737 | Q97: =SUM(M97:P97) -> 21.262 | R97: 2.926 | S97: 1.451 | T97: 1.691 | U97: =V97-SUM(R97:T97) -> 1.293 | V97: 7.361 | W97: 0.86 | X97: 1.098 | Y97: 0.855 | Z97: 0.836 | AA97: =SUM(W97:Z97) -> 3.649 | AB97: 0.746 | AC97: 0.67 | AD97: 0.688 | AE97: 0.34 | AF97: =AE97+AD97+AC97+AB97 -> 2.444
B98: Cost of product revenues/royalties | H98: =H96+H97 -> 42.743 | I98: =I96+I97 -> 37.931 | J98: =J96+J97 -> 27.339 | K98: =K96+K97 -> 22.264 | L98: =L96+L97 -> 130.277 | M98: =M96+M97 -> 15.476 | N98: =N96+N97 -> 17.3 | O98: =O96+O97 -> 14.184 | ... AE98: =AE96+AE97 -> 84.052 | AF98: =AE98+AD98+AC98+AB98 -> 275.119 | AG98: =AG96+AG97 -> 72.321663 | AH98: =AH96+AH97 -> 77.745788 | AI98: =AI96+AI97 -> 83.772594 | AJ98: =AJ96+AJ97 -> 87.109596 | AK98: =AK96+AK97 -> 320.94964 | AP98: =AP96+AP97 -> 354.09854 | AU98: =AU96+AU97 -> 466.44801 | AZ98: =AZ96+AZ97 -> 585.35894 | BE98: =BE96+BE97 -> 652.17576 | BJ98: =BJ96+BJ97 -> 665.53142 | BO98: =BO96+BO97 -> 650.93668 | BT98: =BT96+BT97 -> 628.91172 | BY98: =BY96+BY97 -> 726.81424 | CD98: =CD96+CD97 -> 740.2834 | CI98: =CI96+CI97 -> 721.35077 | CN98: =CN96+CN97 -> 723.58173 | CS98: =CS96+CS97 -> 723.42132
B99: % COGS | V99: =V98/V83 -> 0.12447167 | W99: =W98/W83 -> 0.12841713 | X99: =X98/X83 -> 0.10631245 | Y99: =Y98/Y83 -> 0.13199525 | Z99: =Z98/Z83 -> 0.1332549 | AA99: =AA98/AA83 -> 0.12500356 | AB99: =AB98/AB83 -> 0.09776498 | AC99: =AC98/AC83 -> 0.13853436 | ... CS99: =CS98/CS83 -> 0.089996268
B101: Research & development | H101: 218.095 | I101: 222.455 | J101: 219.442 | K101: 238.461 | L101: 882.097 | M101: 238.963 | N101: 224.78 | O101: 190.939 | P101: 201.463 | Q101: =SUM(M101:P101) -> 856.145 | R101: 215.599 | S101: 223.858 | T101: 246.284 | U101: =V101-SUM(R101:T101) -> 310.181 | V101: 995.922 | W101: 255.86 | X101: 271.008 | Y101: 272.37 | Z101: 248.452 | AA101: =AA27-AA64 -> 1047.69 | AB101: 273.563 | AC101: 289.451 | AD101: 454.947 | AE101: 306.664 | AF101: =AE101+AD101+AC101+AB101 -> 1324.625 | AG101: =AG27-AG64 -> 318.61631 | AH101: =AH27-AH64 -> 318.61631 | AI101: =AI27-AI64 -> 318.61631 | AJ101: =AJ27-AJ64 -> 318.61631 | AK101: =AK27-AK64 -> 1274.4652 | AP101: =AP27-AP64 -> 1352.1278 | AU101: =AU27-AU64 -> 1411.4842 | AZ101: =AZ27-AZ64 -> 1448.8787 | BE101: =BE27-BE64 -> 1448.8787 | BJ101: =BJ27-BJ64 -> 1410.3624 | BO101: =BO27-BO64 -> 1348.0942 | BT101: =BT27-BT64 -> 1265.2776 | BY101: =BY27-BY64 -> 1188.2582 | CD101: =CD27-CD64 -> 1116.6301 | CI101: =CI27-CI64 -> 1050.016 | CN101: =CN27-CN64 -> 988.0649 | CS101: =CS27-CS64 -> 918.10439
B102: Selling, general & administrative | H102: 92.879 | I102: 106.521 | J102: 86.427 | K102: 73.055 | L102: 356.188 | M102: 74.212 | N102: 77.446 | O102: 75.224 | P102: 78.527 | Q102: =SUM(M102:P102) -> 305.409 | R102: 85.86 | S102: 94.394 | T102: 99.772 | U102: =V102-SUM(R102:T102) -> 96.549 | V102: 376.575 | W102: =216.866-X102 -> 105.214 | X102: 111.652 | Y102: 106.055 | Z102: 109.908 | AA102: =AA31-AA69 -> 432.829 | AB102: 113.326 | AC102: 127.249 | AD102: 120.71 | AE102: 134.794 | AF102: =AE102+AD102+AC102+AB102 -> 496.079 | AG102: =AG31-AG69 -> 121.22552 | AH102: =AH31-AH69 -> 121.22552 | AI102: =AI31-AI69 -> 121.22552 | AJ102: =AJ31-AJ69 -> 121.22552 | AK102: =AK31-AK69 -> 484.90208 | AP102: =AP31-AP69 -> 505.14719 | AU102: =AU31-AU69 -> 526.40455 | AZ102: =AZ31-AZ69 -> 548.72478 | BE102: =BE31-BE69 -> 572.16101 | BJ102: =BJ31-BJ69 -> 596.76907 | BO102: =BO31-BO69 -> 607.10445 | BT102: =BT31-BT69 -> 617.64654 | BY102: =BY31-BY69 -> 617.64654 | CD102: =CD31-CD69 -> 617.64654 | CI102: =CI31-CI69 -> 617.64654 | CN102: =CN31-CN69 -> 617.64654 | CS102: =CS31-CS69 -> 617.64654
B104: Restructuring expense, impairment charges | H104: =412.9+0.039 -> 412.939 | I104: 0.776 | J104: 12.048 | K104: 27.658 | L104: =412.9+40.521 -> 453.421 | M104: 6.188 | N104: -0.27 | O104: 40.843 | P104: 4.164 | Q104: =SUM(M104:P104) -> 50.925 | R104: -3.272 | S104: 2.128 | T104: 1.826 | U104: =V104-SUM(R104:T104) -> 1.524 | V104: 2.206 | W104: 0.687 | X104: 0.343 | Y104: 0.008 | Z104: 0.224 | AA104: =SUM(W104:Z104) -> 1.262 | AB104: 9.999 | AC104: 3.523 | AD104: =255.34+0.337 -> 255.677 | AE104: 0.387 | AF104: =AE104+AD104+AC104+AB104 -> 269.586 | AG104: 0 | AH104: 0 | AI104: 0 | AJ104: 0 | AK104: =SUM(AG104:AJ104) -> 0 | AP104: =SUM(AL104:AO104) -> 0 | AU104: =SUM(AQ104:AT104) -> 0 | AZ104: =SUM(AV104:AY104) -> 0 | BE104: =SUM(BA104:BD104) -> 0 | BJ104: =SUM(BF104:BI104) -> 0 | BO104: =SUM(BK104:BN104) -> 0 | BT104: =SUM(BP104:BS104) -> 0 | BY104: =SUM(BU104:BX104) -> 0 | CD104: =SUM(BZ104:CC104) -> 0 | CI104: =SUM(CE104:CH104) -> 0 | CN104: =SUM(CJ104:CM104) -> 0 | CS104: =SUM(CO104:CR104) -> 0
B106: Operating Income (Loss) | H106: =H81-H98-H101-H102-H104 -> -438.288 | I106: =I81-I98-I101-I102-I104 -> -56.933 | J106: =J81-J98-J101-J102-J104 -> -123.556 | K106: =K81-K98-K101-K102-K104 -> -10.281 | L106: =L81-L98-L101-L102-L104 -> -610.008 | M106: =M81-M98-M101-M102-M104 -> -216.388 | N106: =N81-N98-N101-N102-N104 -> -180.835 | O106: =O81-O98-O101-O102-O104 -> -142.203 | ... U106: =U81-U98-U101-U102-U104 -> -53.704 | V106: =SUM(R106:U106) -> -466.879 | W106: =W81-W98-W101-W102-W104 -> -14.33 | X106: =X81-X98-X101-X102-X104 -> 3.353 | Y106: =Y81-Y98-Y101-Y102-Y104 -> -18.727 | Z106: =Z81-Z98-Z101-Z102-Z104 -> 39.64 | AA106: =SUM(W106:Z106) -> 9.936 | AB106: =AB81-AB98-AB101-AB102-AB104 -> 270.842 | AC106: =AC81-AC98-AC101-AC102-AC104 -> 52.707 | AD106: =AD81-AD98-AD101-AD102-AD104 -> -326.043 | AE106: =AE81-AE98-AE101-AE102-AE104 -> 125.737 | AF106: =AF81-AF98-AF101-AF102-AF104 -> 123.243 | AG106: =AG81-AG98-AG101-AG102-AG104 -> 87.836506 | AH106: =AH81-AH98-AH101-AH102-AH104 -> 127.41238 | AI106: =AI81-AI98-AI101-AI102-AI104 -> 171.38558 | ... AK106: =AK81-AK98-AK101-AK102-AK104 -> 582.36771 | AP106: =AP81-AP98-AP101-AP102-AP104 -> 718.41564 | AU106: =AU81-AU98-AU101-AU102-AU104 -> 1628.5082 | AZ106: =AZ81-AZ98-AZ101-AZ102-AZ104 -> 2769.0922 | BE106: =BE81-BE98-BE101-BE102-BE104 -> 3506.9158 | BJ106: =BJ81-BJ98-BJ101-BJ102-BJ104 -> 3876.8477 | BO106: =BO81-BO98-BO101-BO102-BO104 -> 4100.9691 | BT106: =BT81-BT98-BT101-BT102-BT104 -> 4855.6248 | BY106: =BY81-BY98-BY101-BY102-BY104 -> 6344.747 | CD106: =CD81-CD98-CD101-CD102-CD104 -> 6526.3103 | CI106: =CI81-CI98-CI101-CI102-CI104 -> 6714.74 | CN106: =CN81-CN98-CN101-CN102-CN104 -> 6785.6192 | CS106: =CS81-CS98-CS101-CS102-CS104 -> 6938.7311
B108: Interest expense, net | H108: -3.465 | I108: -6.551 | J108: -0.095 | K108: -12.626 | L108: -22.926 | M108: -15.717 | N108: -15.585 | O108: -20.384 | P108: -21.177 | Q108: =SUM(M108:P108) -> -72.863 | R108: -21.307 | S108: -21.111 | T108: -21.134 | U108: -20.654 | V108: =SUM(R108:U108) -> -84.206 | W108: -20.698 | X108: -20.155 | Y108: -20.14 | Z108: -20.439 | AA108: =AA199 -> -74.605278 | AB108: -16.765 | AC108: -14.664 | AD108: -13.574 | AE108: -12.547 | AF108: =AE108+AD108+AC108+AB108 -> -57.55 | AG108: =AK108/4 -> -15 | AH108: =AK108/4 -> -15 | AI108: =AK108/4 -> -15 | AJ108: =AK108-SUM(AG108:AI108) -> -15 | AK108: =AK39 -> -60 | AP108: =AP39 -> -46.411521 | AU108: =AU39 -> -32.752231 | AZ108: =AZ39 -> -7.8170204 | BE108: =BE39 -> 38.212892 | BJ108: =BJ39 -> 100.62556 | BO108: =BO39 -> 182.48153 | BT108: =BT39 -> 285.1824 | BY108: =BY39 -> 416.17398 | CD108: =CD39 -> 591.66805 | CI108: =CI39 -> 809.5131 | CN108: =CN39 -> 1064.8559 | CS108: =CS39 -> 1358.7763
B109: Other income/(expense) | H109: -1.187 | I109: -0.027 | J109: 4.751 | K109: 3.339 | L109: 6.89 | M109: 0.451 | N109: 37.731 | O109: -3.99 | P109: -3.792 | Q109: =SUM(M109:P109) -> 30.4 | R109: -5.113 | S109: 1.414 | T109: -1.326 | U109: =V109-SUM(R109:T109) -> -1.69 | V109: -6.715 | W109: 4.411 | X109: -1.219 | Y109: -0.167 | Z109: 1.105 | AA109: =SUM(W109:Z109) -> 4.13 | AB109: -0.544 | AC109: -2.537 | AD109: -77.553 | AE109: -0.748 | AF109: =AE109+AD109+AC109+AB109 -> -81.382 | AG109: =AK109 -> 0 | AH109: =AK109 -> 0 | AI109: =AK109 -> 0 | AJ109: =AK109-SUM(AG109:AI109) -> 0 | AK109: 0 | AP109: 0 | AU109: 0 | AZ109: 0 | BE109: 0 | BJ109: 0 | BO109: 0 | BT109: 0 | BY109: 0 | CD109: 0 | CI109: 0 | CN109: 0 | CS109: 0
B110: Total Other income/(expense) | H110: =H109+H108 -> -4.652 | I110: =I109+I108 -> -6.578 | J110: =J109+J108 -> 4.656 | K110: =K109+K108 -> -9.287 | L110: =L109+L108 -> -16.036 | M110: =M109+M108 -> -15.266 | N110: =N109+N108 -> 22.146 | O110: =O109+O108 -> -24.374 | P110: =P109+P108 -> -24.969 | Q110: =SUM(M110:P110) -> -42.463 | R110: =R109+R108 -> -26.42 | S110: =S109+S108 -> -19.697 | T110: =T109+T108 -> -22.46 | U110: =U109+U108 -> -22.344 | V110: =SUM(R110:U110) -> -90.921 | W110: =W109+W108 -> -16.287 | X110: =X109+X108 -> -21.374 | Y110: =Y109+Y108 -> -20.307 | Z110: =Z109+Z108 -> -19.334 | AA110: =SUM(W110:Z110) -> -77.302 | AB110: =AB109+AB108 -> -17.309 | AC110: =AC109+AC108 -> -17.201 | AD110: =AD109+AD108 -> -91.127 | AE110: =AE109+AE108 -> -13.295 | AF110: =AF109+AF108 -> -138.932 | AG110: =AG109+AG108 -> -15 | AH110: =AH109+AH108 -> -15 | AI110: =AI109+AI108 -> -15 | ... AK110: =AK109+AK108 -> -60 | AP110: =AP109+AP108 -> -46.411521 | AU110: =AU109+AU108 -> -32.752231 | AZ110: =AZ109+AZ108 -> -7.8170204 | BE110: =BE109+BE108 -> 38.212892 | BJ110: =BJ109+BJ108 -> 100.62556 | BO110: =BO109+BO108 -> 182.48153 | BT110: =BT109+BT108 -> 285.1824 | BY110: =BY109+BY108 -> 416.17398 | CD110: =CD109+CD108 -> 591.66805 | CI110: =CI109+CI108 -> 809.5131 | CN110: =CN109+CN108 -> 1064.8559 | CS110: =CS109+CS108 -> 1358.7763
B112: Pretax Income (Loss) | H112: =H106+H110 -> -442.94 | I112: =I106+I110 -> -63.511 | J112: =J106+J110 -> -118.9 | K112: =K106+K110 -> -19.568 | L112: =L106+L110 -> -626.044 | M112: =M106+M110 -> -231.654 | N112: =N106+N110 -> -158.689 | O112: =O106+O110 -> -166.577 | ... U112: =U106+U110 -> -76.048 | V112: =SUM(R112:U112) -> -557.8 | W112: =W106+W110 -> -30.617 | X112: =X106+X110 -> -18.021 | Y112: =Y106+Y110 -> -39.034 | Z112: =Z106+Z110 -> 20.306 | AA112: =SUM(W112:Z112) -> -67.366 | AB112: =AB106+AB110 -> 253.533 | AC112: =AC106+AC110 -> 35.506 | AD112: =AD106+AD110 -> -417.17 | AE112: =AE106+AE110 -> 112.442 | AF112: =AF106+AF110 -> -15.689 | AG112: =AG106+AG110 -> 72.836506 | AH112: =AH106+AH110 -> 112.41238 | AI112: =AI106+AI110 -> 156.38558 | ... AK112: =AK106+AK110 -> 522.36771 | AP112: =AP106+AP110 -> 672.00412 | AU112: =AU106+AU110 -> 1595.756 | AZ112: =AZ106+AZ110 -> 2761.2752 | BE112: =BE106+BE110 -> 3545.1287 | BJ112: =BJ106+BJ110 -> 3977.4732 | BO112: =BO106+BO110 -> 4283.4506 | BT112: =BT106+BT110 -> 5140.8072 | BY112: =BY106+BY110 -> 6760.921 | CD112: =CD106+CD110 -> 7117.9783 | CI112: =CI106+CI110 -> 7524.2531 | CN112: =CN106+CN110 -> 7850.4751 | CS112: =CS106+CS110 -> 8297.5074
B113: Income Taxes (expense) benefit | H113: -130.313 | I113: -1.799 | J113: 2.555 | K113: 1.352 | L113: -122.422 | M113: 0.803 | N113: 0.693 | O113: 3.419 | P113: 2.043 | Q113: =SUM(M113:P113) -> 6.958 | R113: 0.299 | S113: 30.131 | T113: 1.33 | U113: -1.379 | V113: =SUM(R113:U113) -> 30.381 | W113: 5.485 | X113: 18.13 | Y113: 0.503 | Z113: -7.453 | AA113: =SUM(W113:Z113) -> 16.665 | AB113: 3.985 | AC113: 4.337 | AD113: -125.903 | AE113: 10.257 | AF113: =AE113+AD113+AC113+AB113 -> -107.324 | AG113: =AG112*AG114 -> 0 | AH113: =AH112*AH114 -> 0 | AI113: =AI112*AI114 -> 0 | AJ113: =AJ112*AJ114 -> 0 | AK113: =AK42 -> 0 | AP113: =AP42 -> 0 | AU113: =AU42 -> 0 | AZ113: =AZ42 -> 0 | BE113: =BE42 -> 643.73552 | BJ113: =BJ42 -> 855.15675 | BO113: =BO42 -> 920.94188 | BT113: =BT42 -> 1105.2735 | BY113: =BY42 -> 1453.598 | CD113: =CD42 -> 1530.3653 | CI113: =CI42 -> 1617.7144 | CN113: =CN42 -> 1687.8522 | CS113: =CS42 -> 1783.9641
B114: Tax Rate | H114: =IF(H112<0,0,H113/H112) -> 0 | I114: =IF(I112<0,0,I113/I112) -> 0 | J114: =IF(J112<0,0,J113/J112) -> 0 | K114: =IF(K112<0,0,K113/K112) -> 0 | L114: =IF(L112<0,0,L113/L112) -> 0 | M114: =IF(M112<0,0,M113/M112) -> 0 | N114: =IF(N112<0,0,N113/N112) -> 0 | O114: =IF(O112<0,0,O113/O112) -> 0 | ... AA114: =IF(AA112<0,0,AA113/AA112) -> 0 | AB114: 0 | AC114: 0 | AD114: 0 | AE114: 0 | AF114: =IF(AF112<0,0,AF113/AF112) -> 0 | AG114: =AK114 -> 0 | AH114: =AK114 -> 0 | AI114: =AK114 -> 0 | AJ114: =AK114 -> 0 | AK114: =IF(AK112<0,0,AK113/AK112) -> 0 | AP114: =IF(AP112<0,0,AP113/AP112) -> 0 | AU114: =IF(AU112<0,0,AU113/AU112) -> 0 | AZ114: =IF(AZ112<0,0,AZ113/AZ112) -> 0 | BE114: =IF(BE112<0,0,BE113/BE112) -> 0.18158312 | BJ114: =IF(BJ112<0,0,BJ113/BJ112) -> 0.215 | BO114: =IF(BO112<0,0,BO113/BO112) -> 0.215 | BT114: =IF(BT112<0,0,BT113/BT112) -> 0.215 | BY114: =IF(BY112<0,0,BY113/BY112) -> 0.215 | CD114: =IF(CD112<0,0,CD113/CD112) -> 0.215 | CI114: =IF(CI112<0,0,CI113/CI112) -> 0.215 | CN114: =IF(CN112<0,0,CN113/CN112) -> 0.215 | CS114: =IF(CS112<0,0,CS113/CS112) -> 0.215
B116: Net Income (Loss) from Continuing Operations | H116: =H112-H113 -> -312.627 | I116: =I112-I113 -> -61.712 | J116: =J112-J113 -> -121.455 | K116: =K112-K113 -> -20.92 | L116: =L112-L113 -> -503.622 | M116: =M112-M113 -> -232.457 | N116: =N112-N113 -> -159.382 | O116: =O112-O113 -> -169.996 | ... U116: =U112-U113 -> -74.669 | V116: =SUM(R116:U116) -> -588.181 | W116: =W112-W113 -> -36.102 | X116: =X112-X113 -> -36.151 | Y116: =Y112-Y113 -> -39.537 | Z116: =Z112-Z113 -> 27.759 | AA116: =SUM(W116:Z116) -> -84.031 | AB116: =AB112-AB113 -> 249.548 | AC116: =AC112-AC113 -> 31.169 | AD116: =AD112-AD113 -> -291.267 | AE116: =AE112-AE113 -> 102.185 | AF116: =AF112-AF113 -> 91.635 | AG116: =AG112-AG113 -> 72.836506 | AH116: =AH112-AH113 -> 112.41238 | AI116: =AI112-AI113 -> 156.38558 | ... AK116: =AK112-AK113 -> 522.36771 | AP116: =AP112-AP113 -> 672.00412 | AU116: =AU112-AU113 -> 1595.756 | AZ116: =AZ112-AZ113 -> 2761.2752 | BE116: =BE112-BE113 -> 2901.3932 | BJ116: =BJ112-BJ113 -> 3122.3165 | BO116: =BO112-BO113 -> 3362.5087 | BT116: =BT112-BT113 -> 4035.5336 | BY116: =BY112-BY113 -> 5307.3229 | CD116: =CD112-CD113 -> 5587.613 | CI116: =CI112-CI113 -> 5906.5387 | CN116: =CN112-CN113 -> 6162.623 | CS116: =CS112-CS113 -> 6513.5433
B118: Income (loss) from discontinued operations | H118: 0 | I118: 0 | J118: 7.207 | K118: 163.629 | L118: 183.928 | M118: 0 | N118: 0 | O118: 0.064 | P118: 0.209 | Q118: =SUM(M118:P118) -> 0.273 | R118: 0 | S118: 0 | T118: 0 | U118: 0 | V118: =SUM(R118:U118) -> 0 | W118: 0 | X118: 0 | Y118: 0 | Z118: 0 | AA118: =SUM(W118:Z118) -> 0 | AB118: 0 | AC118: 0 | AD118: 0 | AE118: 0 | AF118: =AE118+AD118+AC118+AB118 -> 0 | AG118: 0 | AH118: 0 | AI118: 0 | AJ118: 0 | AK118: =SUM(AG118:AJ118) -> 0 | AP118: =SUM(AL118:AO118) -> 0 | AU118: =SUM(AQ118:AT118) -> 0 | AZ118: =SUM(AV118:AY118) -> 0 | BE118: =SUM(BA118:BD118) -> 0 | BJ118: =SUM(BF118:BI118) -> 0 | BO118: =SUM(BK118:BN118) -> 0 | BT118: =SUM(BP118:BS118) -> 0 | BY118: =SUM(BU118:BX118) -> 0 | CD118: =SUM(BZ118:CC118) -> 0 | CI118: =SUM(CE118:CH118) -> 0 | CN118: =SUM(CJ118:CM118) -> 0 | CS118: =SUM(CO118:CR118) -> 0
B119: Income (loss) attributable to noncontrolling interest | H119: -4.611 | I119: -4.547 | J119: -4.53 | K119: -228.834 | L119: =SUM(H119:K119) -> -242.522 | M119: 0 | N119: 0 | O119: 0 | P119: -4.19 | Q119: =SUM(M119:P119) -> -4.19 | R119: -0.098 | S119: -32.144 | T119: 1.333 | U119: -0.938 | V119: =SUM(R119:U119) -> -31.847 | W119: 5.529 | X119: 28.374 | Y119: -0.696 | Z119: -5.186 | AA119: =SUM(W119:Z119) -> 28.021 | AB119: 1.792 | AC119: 13.173 | AD119: -188.315 | AE119: 1.501 | AF119: =AE119+AD119+AC119+AB119 -> -171.849 | AG119: 0 | AH119: 0 | AI119: 0 | AJ119: 0 | AK119: =SUM(AG119:AJ119) -> 0 | AP119: =SUM(AL119:AO119) -> 0 | AU119: =SUM(AQ119:AT119) -> 0 | AZ119: =SUM(AV119:AY119) -> 0 | BE119: =SUM(BA119:BD119) -> 0 | BJ119: =SUM(BF119:BI119) -> 0 | BO119: =SUM(BK119:BN119) -> 0 | BT119: =SUM(BP119:BS119) -> 0 | BY119: =SUM(BU119:BX119) -> 0 | CD119: =SUM(BZ119:CC119) -> 0 | CI119: =SUM(CE119:CH119) -> 0 | CN119: =SUM(CJ119:CM119) -> 0 | CS119: =SUM(CO119:CR119) -> 0
B120: Non-GAAP Adjustment | J120: -1.22
B122: Net Income (Loss) | H122: =H116-H118-H119 -> -308.016 | I122: =I116-I118-I119 -> -57.165 | J122: =J116-J118-J119 -> -124.132 | K122: =K116-K118-K119 -> 44.285 | L122: =L116-L118-L119 -> -445.028 | M122: =M116-M118-M119 -> -232.457 | N122: =N116-N118-N119 -> -159.382 | O122: =O116-O118-O119 -> -170.06 | P122: =P116-P118-P119 -> -176.656 | Q122: =SUM(M122:P122) -> -738.555 | R122: =R116-R118-R119 -> -198.606 | S122: =S116-S118-S119 -> -188.848 | T122: =T116-T118-T119 -> -95.149 | U122: =U116-U118-U119 -> -73.731 | V122: =SUM(R122:U122) -> -556.334 | W122: =W116-W118-W119 -> -41.631 | X122: =X116-X118-X119 -> -64.525 | Y122: =Y116-Y118-Y119 -> -38.841 | Z122: =Z116-Z118-Z119 -> 32.945 | AA122: =SUM(W122:Z122) -> -112.052 | AB122: =AB116-AB118-AB119 -> 247.756 | AC122: =AC116-AC118-AC119 -> 17.996 | AD122: =AD116-AD118-AD119 -> -102.952 | AE122: =AE116-AE118-AE119 -> 100.684 | AF122: =AF116-AF118-AF119 -> 263.484 | AG122: =AG116-AG118-AG119 -> 72.836506 | AH122: =AH116-AH118-AH119 -> 112.41238 | AI122: =AI116-AI118-AI119 -> 156.38558 | ... AK122: =AK116-AK118-AK119 -> 522.36771 | AP122: =AP116-AP118-AP119 -> 672.00412 | AU122: =AU116-AU118-AU119 -> 1595.756 | AZ122: =AZ116-AZ118-AZ119 -> 2761.2752 | BE122: =BE116-BE118-BE119 -> 2901.3932 | BJ122: =BJ116-BJ118-BJ119 -> 3122.3165 | BO122: =BO116-BO118-BO119 -> 3362.5087 | BT122: =BT116-BT118-BT119 -> 4035.5336 | BY122: =BY116-BY118-BY119 -> 5307.3229 | CD122: =CD116-CD118-CD119 -> 5587.613 | CI122: =CI116-CI118-CI119 -> 5906.5387 | CN122: =CN116-CN118-CN119 -> 6162.623 | CS122: =CS116-CS118-CS119 -> 6513.5433
B123: Non-GAAP Net Income (Loss) | H123: =H45-H118-H119 -> 10.36 | I123: =I45-I118-I119 -> -1.668 | J123: =J45-J118-J119-J120 -> -75.6105 | K123: =K45-K118-K119-K120 -> -65.945 | L123: =L45-L118-L119 -> -144.708 | M123: =M45-M118-M119 -> -151.394 | N123: =N45-N118-N119 -> -141.718 | O123: =O45-O118-O119 -> -86.297 | P123: =P45-P118-P119-P120 -> -135.603 | Q123: =Q45-Q118-Q119 -> -507.301 | R123: =R45-R118-R119 -> -148.278 | S123: =S45-S118-S119 -> -98.539 | T123: =T45-T118-T119 -> -33.261 | U123: =U45-U118-U119 -> 45.376 | V123: =V45-V118-V119 -> -234.702 | W123: =W45-W118-W119 -> 16.893 | X123: =X45-X118-X119 -> 29.598 | ... AE123: =AE45-AE118-AE119 -> 156.349 | AF123: =AF45 -> 494.56 | AG123: =AG45-AG118-AG119 -> 134.08651 | AH123: =AH45-AH118-AH119 -> 173.66238 | AI123: =AI45-AI118-AI119 -> 217.63558 | AJ123: =AJ45-AJ118-AJ119 -> 241.98325 | AK123: =AK45-AK118-AK119 -> 767.36771 | AP123: =AP45-AP118-AP119 -> 917.00412 | AU123: =AU45-AU118-AU119 -> 1840.756 | AZ123: =AZ45-AZ118-AZ119 -> 3006.2752 | BE123: =BE45-BE118-BE119 -> 3146.3932 | BJ123: =BJ45-BJ118-BJ119 -> 3367.3165 | BO123: =BO45-BO118-BO119 -> 3607.5087 | BT123: =BT45-BT118-BT119 -> 4280.5336 | BY123: =BY45-BY118-BY119 -> 5552.3229 | CD123: =CD45-CD118-CD119 -> 5832.613 | CI123: =CI45-CI118-CI119 -> 6151.5387 | CN123: =CN45-CN118-CN119 -> 6407.623 | CS123: =CS45-CS118-CS119 -> 6758.5433
B125: EPS (basic) | H125: =H122/ H135 -> -1.4298327 | I125: =I122/ I135 -> -0.25743854 | J125: =J122/ J135 -> -0.53852194 | K125: =K122/ K135 -> 0.19149111 | L125: =L122/ L135 -> -1.9787289 | M125: =M122/ M135 -> -0.99815361 | N125: =N122/ N135 -> -0.68167898 | O125: =O122/ O135 -> -0.72017515 | ... AK125: =AK122/ AK135 -> 2.0124847 | AP125: =AP122/ AP135 -> 2.5633436 | AU125: =AU122/ AU135 -> 6.0267059 | AZ125: =AZ122/ AZ135 -> 10.32528 | BE125: =BE122/ BE135 -> 10.741807 | BJ125: =BJ122/ BJ135 -> 11.445277 | BO125: =BO122/ BO135 -> 12.203698 | BT125: =BT122/ BT135 -> 14.501323 | BY125: =BY122/ BY135 -> 18.882556 | CD125: =CD122/ CD135 -> 19.682951 | CI125: =CI122/ CI135 -> 20.600396 | CN125: =CN122/ CN135 -> 21.280741 | CS125: =CS122/ CS135 -> 22.269839
B126: EPS (diluted) | H126: =H122/H135 -> -1.4298327 | I126: =I122/I135 -> -0.25743854 | J126: =J122/J135 -> -0.53852194 | K126: =K122/K135 -> 0.19149111 | L126: =L122/L135 -> -1.9787289 | M126: =M122/M135 -> -0.99815361 | N126: =N122/N135 -> -0.68167898 | O126: =O122/O135 -> -0.72017515 | ... Q126: =Q122/Q135 -> -3.1386869 | R126: =R122/R136 -> -0.82927685 | S126: =S122/S136 -> -0.78439256 | T126: =T122/T136 -> -0.39322806 | U126: =U122/U136 -> -0.30343599 | V126: =V122/V136 -> -2.3055555 | W126: =W116/W135 -> -0.14806157 | X126: =X122/X135 -> -0.26392536 | Y126: =Y116/Y135 -> -0.16142822 | Z126: =Z116/Z135 -> 0.11333905 | AA126: =AA122/AA136 -> -0.44383239 | AB126: =AB116/AB135 -> 1.0143238 | AC126: =AC122/AC135 -> 0.072704942 | AD126: =AD122/AD135 -> -0.41136701 | AE126: =AE116/AE135 -> 0.39791047 | AF126: =AF122/AF136 -> 1.0405134 | AG126: =AG116/AG135 -> 0.28061144 | AH126: =AH122/AH135 -> 0.43308228 | AI126: =AI122/AI135 -> 0.60249432 | AJ126: =AJ116/AJ135 -> 0.69629666 | AK126: =AK122/AK136 -> 2.0124847 | AP126: =AP122/AP136 -> 2.5633436 | AU126: =AU122/AU136 -> 6.0267059 | AZ126: =AZ122/AZ136 -> 10.32528 | BE126: =BE122/BE136 -> 10.741807 | BJ126: =BJ122/BJ136 -> 11.445277 | BO126: =BO122/BO136 -> 12.203698 | BT126: =BT122/BT136 -> 14.501323 | BY126: =BY122/BY136 -> 18.882556 | CD126: =CD122/CD136 -> 19.682951 | CI126: =CI122/CI136 -> 20.600396 | CN126: =CN122/CN136 -> 21.280741 | CS126: =CS122/CS136 -> 22.269839
B129: Options Expense | H129: =H140 -> 31.152 | I129: =I140 -> 41.263 | J129: =J140 -> 31.1975 | K129: =K140 -> 23.24 | L129: =L140 -> 126.8525 | M129: =M140 -> 46.58 | N129: =N140 -> 42.444 | O129: =O140 -> 46.136 | ... U129: =U140 -> 45.439 | V129: =SUM(R129:U129) -> 227.084 | W129: =W140 -> 55.472 | X129: =X140 -> 61.942 | Y129: =Y140 -> 61.209 | Z129: =Z140 -> 66.377 | AA129: =AA140 -> 245 | AB129: =AB140 -> 68.982 | AC129: =AC140 -> 72.582 | AD129: =AD140 -> 73.77 | ... AK129: =AK140 -> 245 | AP129: =AP140 -> 245 | AU129: =AU140 -> 245 | AZ129: =AZ140 -> 245 | BE129: =BE140 -> 245 | BJ129: =BJ140 -> 245 | BO129: =BO140 -> 245 | BT129: =BT140 -> 245 | BY129: =BY140 -> 245 | CD129: =CD140 -> 245 | CI129: =CI140 -> 245 | CN129: =CN140 -> 245 | CS129: =CS140 -> 245
B130: % of operating expense | H130: =H129/(H98+H101+H102) -> 0.088070407 | I130: =I129/(I98+I101+I102) -> 0.11246174 | J130: =J129/(J98+J101+J102) -> 0.093627704 | K130: =K129/(K98+K101+K102) -> 0.0696267 | L130: =L129/(L98+L101+L102) -> 0.092690357 | M130: =M129/(M98+M101+M102) -> 0.14173089 | N130: =N129/(N98+N101+N102) -> 0.13283426 | O130: =O129/(O98+O101+O102) -> 0.16456748 | ... AK130: =AK129/(AK98+AK101+AK102) -> 0.11777051 | AP130: =AP129/(AP98+AP101+AP102) -> 0.11079087 | AU130: =AU129/(AU98+AU101+AU102) -> 0.1018992 | AZ130: =AZ129/(AZ98+AZ101+AZ102) -> 0.094852328 | BE130: =BE129/(BE98+BE101+BE102) -> 0.091649925 | BJ130: =BJ129/(BJ98+BJ101+BJ102) -> 0.091668876 | BO130: =BO129/(BO98+BO101+BO102) -> 0.094008931 | BT130: =BT129/(BT98+BT101+BT102) -> 0.097538219 | BY130: =BY129/(BY98+BY101+BY102) -> 0.096733985 | CD130: =CD129/(CD98+CD101+CD102) -> 0.099007498 | CI130: =CI129/(CI98+CI101+CI102) -> 0.1025528 | CN130: =CN129/(CN98+CN101+CN102) -> 0.10518212 | CS130: =CS129/(CS98+CS101+CS102) -> 0.1084468
B131: Tax impact | H131: 0 | I131: 0 | J131: 0 | K131: 0 | L131: 0 | M131: 0 | N131: 0 | O131: 0 | P131: 0 | Q131: 0 | R131: 0 | S131: 0 | T131: 0 | U131: 0 | V131: =SUM(R131:U131) -> 0 | W131: 0 | X131: 0 | Y131: 0 | Z131: 0 | AA131: 0 | AB131: 0 | AC131: 0 | AD131: 0 | AE131: 0 | AF131: 0 | AG131: 0 | AH131: 0 | AI131: 0 | AJ131: 0 | AK131: 0 | AP131: 0 | AU131: 0 | AZ131: 0 | BE131: 0 | BJ131: 0 | BO131: 0 | BT131: 0 | BY131: 0 | CD131: 0 | CI131: 0 | CN131: 0 | CS131: 0
B132: Net Income (non-GAAP, incl option exp) | H132: =H123-H129-H131 -> -20.792 | I132: =I123-I129-I131 -> -42.931 | J132: =J123-J129-J131 -> -106.808 | K132: =K123-K129-K131 -> -89.185 | L132: =L123-L129-L131 -> -271.5605 | M132: =M123-M129-M131 -> -197.974 | N132: =N123-N129-N131 -> -184.162 | O132: =O123-O129-O131 -> -132.433 | ... AK132: =AK123-AK129-AK131 -> 522.36771 | AP132: =AP123-AP129-AP131 -> 672.00412 | AU132: =AU123-AU129-AU131 -> 1595.756 | AZ132: =AZ123-AZ129-AZ131 -> 2761.2752 | BE132: =BE123-BE129-BE131 -> 2901.3932 | BJ132: =BJ123-BJ129-BJ131 -> 3122.3165 | BO132: =BO123-BO129-BO131 -> 3362.5087 | BT132: =BT123-BT129-BT131 -> 4035.5336 | BY132: =BY123-BY129-BY131 -> 5307.3229 | CD132: =CD123-CD129-CD131 -> 5587.613 | CI132: =CI123-CI129-CI131 -> 5906.5387 | CN132: =CN123-CN129-CN131 -> 6162.623 | CS132: =CS123-CS129-CS131 -> 6513.5433
B133: EPS, diluted (non-GAAP, incl option exp) | H133: =+H132/H136 -> -0.096517981 | I133: =+I132/I136 -> -0.19333673 | J133: =+J132/J136 -> -0.46336522 | K133: =+K132/K136 -> -0.38564152 | L133: =+L132/L136 -> -1.20744 | M133: =+M132/M136 -> -0.85008609 | N133: =+N132/N136 -> -0.78766338 | O133: =+O132/O136 -> -0.56083121 | ... AK133: =+AK132/AK136 -> 2.0124847 | AP133: =+AP132/AP136 -> 2.5633436 | AU133: =+AU132/AU136 -> 6.0267059 | AZ133: =+AZ132/AZ136 -> 10.32528 | BE133: =+BE132/BE136 -> 10.741807 | BJ133: =+BJ132/BJ136 -> 11.445277 | BO133: =+BO132/BO136 -> 12.203698 | BT133: =+BT132/BT136 -> 14.501323 | BY133: =+BY132/BY136 -> 18.882556 | CD133: =+CD132/CD136 -> 19.682951 | CI133: =+CI132/CI136 -> 20.600396 | CN133: =+CN132/CN136 -> 21.280741 | CS133: =+CS132/CS136 -> 22.269839
...

Sheet MW-Cache
A1: $F$2
A2: VRTX.O,mscalc:sedolCodeCalc | B2: 2931034 | C2: VRTX.O,mscalc:targetPrice,,,,USD | D2: 200 | E2: VRTX.O,mscalc:closePriceCurrencyCalc | F2: USD

Sheet Revs
B4: Product revenue | C4: 1Q06A | D4: 2Q06A | E4: 3Q06A | F4: 4Q06A | G4: 2006 | H4: 1Q07A | I4: 2Q07A | J4: 3Q07A | K4: 4Q07A | L4: 2007 | M4: 1Q08A | N4: 2Q08A | O4: 3Q08A | P4: 4Q08A | Q4: 2008 | R4: 1Q09A | S4: 2Q09A | T4: 3Q09A | U4: 4Q09A | V4: 2009 | W4: 1Q10A | X4: 2Q10A | Y4: 3Q10A | Z4: 4Q10A | AA4: 2010 | AB4: 1Q11A | AC4: 2Q11A | AD4: 3Q11A | AE4: 4Q11A | AF4: 2011 | AG4: 1Q12A | AH4: 2Q12A | AI4: 3Q12A | AJ4: 4Q12A | AK4: 2012 | AL4: 1Q13A | AM4: 2Q13A | AN4: 3Q13A | AO4: 4Q13A | AP4: 2013 | AQ4: 1Q14A | AR4: 2Q14A | AS4: 3Q14A | AT4: 4Q14A | AU4: 2014A | AV4: 1Q15A | AW4: 2Q15A | AX4: 3Q15A | AY4: 4Q15A | AZ4: 2015A | BA4: 1Q16A | BB4: 2Q16A | BC4: 3Q16A | BD4: 4Q16A | BE4: 2016A | BF4: 1Q17A | BG4: 2Q17A | BH4: 3Q17A | BI4: 4Q17A | BJ4: 2017A | BK4: 1Q18E | BL4: 2Q18E | BM4: 3Q18E | BN4: 4Q18E | BO4: 2018E | BP4: 1Q19E | BQ4: 2Q19E | BR4: 3Q19E | BS4: 4Q19E | BT4: 2019E | BU4: 1Q20E | BV4: 2Q20E | BW4: 3Q20E | BX4: 4Q20E | BY4: 2020E | BZ4: 1Q21E | CA4: 2Q21E | CB4: 3Q21E | CC4: 4Q21E | CD4: 2021E | CE4: 1Q22E | CF4: 2Q22E | CG4: 3Q22E | CH4: 4Q22E | CI4: 2022E | CJ4: 1Q23E | CK4: 2Q23E | CL4: 3Q23E | CM4: 4Q23E | CN4: 2023E | CO4: 1Q24E | CP4: 2Q24E | CQ4: 3Q24E | CR4: 4Q24E | CS4: 2024E | CT4: 1Q25E | CU4: 2Q25E | CV4: 3Q25E | CW4: 4Q25E | CX4: 2025E | CY4: 1Q26E | CZ4: 2Q26E | DA4: 3Q26E | DB4: 4Q26E | DC4: 2026E | DD4: 1Q27E | DE4: 2Q27E | DF4: 3Q27E | DG4: 4Q27E | DH4: 2027E | DI4: 1Q28E | DJ4: 2Q28E | DK4: 3Q28E | DL4: 4Q28E | DM4: 2028E | DN4: 1Q29E | DO4: 2Q29E | DP4: 3Q29E | DQ4: 4Q29E | DR4: 2029E | DS4: 1Q30E | DT4: 2Q30E | DU4: 3Q30E | DV4: 4Q30E | DW4: 2030E
B5: Kalydeco Sales (US) | C5: 0 | D5: 0 | E5: 0 | F5: 0 | G5: =SUM(C5:F5) -> 0 | H5: 0 | I5: 0 | J5: 0 | K5: 0 | L5: =SUM(H5:K5) -> 0 | M5: 0 | N5: 0 | O5: 0 | P5: 0 | Q5: =SUM(M5:P5) -> 0 | R5: 0 | S5: 0 | T5: 0 | U5: 0 | V5: =SUM(R5:U5) -> 0 | W5: 0 | X5: 0 | Y5: 0 | Z5: 0 | AA5: =SUM(W5:Z5) -> 0 | AB5: 0 | AC5: 0 | AD5: 0 | AE5: 0 | AF5: =SUM(AB5:AE5) -> 0 | AG5: 18.448 | AH5: 45.534 | AI5: 49.161 | AJ5: 50 | AK5: =SUM(AG5:AJ5) -> 163.143 | AL5: 50 | AM5: 55 | AN5: 55 | AO5: 56 | AP5: =SUM(AL5:AO5) -> 216 | AQ5: 56 | AR5: 63 | AS5: 74 | AT5: 68 | AU5: =SUM(AQ5:AT5) -> 261 | AV5: 72 | AW5: 93 | AX5: =165.929-AX6 -> 95.029 | AY5: =180-AY6 -> 105 | AZ5: =AY5+AX5+AW5+AV5 -> 365.029 | BA5: 95 | BB5: 103 | BC5: 101 | BD5: 101 | BE5: =SUM(BA5:BD5) -> 400 | BF5: 102 | BG5: 112 | BH5: 133 | BI5: 164 | BJ5: =SUM(BF5:BI5) -> 511 | BK5: 150 | BL5: 155 | BM5: 160 | BN5: =BO5-SUM(BK5:BM5) -> 171.23235 | BO5: ='CF Market'!M327 -> 636.23235 | BT5: ='CF Market'!N327 -> 673.904 | BY5: ='CF Market'!O327 -> 719.66808 | CD5: ='CF Market'!P327 -> 761.61849 | CI5: ='CF Market'!Q327 -> 761.61849 | CN5: ='CF Market'!R327 -> 761.61849 | CS5: ='CF Market'!S327 -> 761.61849 | CX5: ='CF Market'!T327 -> 408.62116 | DC5: ='CF Market'!U327 -> 216.07716 | DH5: ='CF Market'!V327 -> 216.07716 | DM5: ='CF Market'!W327 -> 43.857245 | DR5: ='CF Market'!X327 -> 8.7714489 | DW5: ='CF Market'!Y327 -> 0
B6: Kalydeco Sales (ex-US) | C6: 0 | D6: 0 | E6: 0 | F6: 0 | G6: =SUM(C6:F6) -> 0 | H6: 0 | I6: 0 | J6: 0 | K6: 0 | L6: =SUM(H6:K6) -> 0 | M6: 0 | N6: 0 | O6: 0 | P6: 0 | Q6: =SUM(M6:P6) -> 0 | R6: 0 | S6: 0 | T6: 0 | U6: 0 | V6: =SUM(R6:U6) -> 0 | W6: 0 | X6: 0 | Y6: 0 | Z6: 0 | AA6: =SUM(W6:Z6) -> 0 | AB6: 0 | AC6: 0 | AD6: 0 | AE6: 0 | AF6: =SUM(AB6:AE6) -> 0 | AG6: 0 | AH6: 0 | AI6: 0 | AJ6: =58.5-AJ5 -> 8.5 | AK6: =SUM(AG6:AJ6) -> 8.5 | AL6: =61.8-AL5 -> 11.8 | AM6: =99-AM5 -> 44 | AN6: =101.1-AN5 -> 46.1 | AO6: =109.5-AO5 -> 53.5 | AP6: =SUM(AL6:AO6) -> 155.4 | AQ6: =99.5-AQ5 -> 43.5 | AR6: =122.319-AR5-AR19 -> 50.019 | AS6: =137.099-AS5-AS19 -> 52.799 | AT6: =124.942-AT5-AT19 -> 56.342 | AU6: =SUM(AQ6:AT6) -> 202.66 | AV6: =130.875-AV5-AV19 -> 58.2 | AW6: 62 | AX6: 70.9 | AY6: 75 | AZ6: =AY6+AX6+AW6+AV6 -> 266.1 | BA6: =BA7-BA5 -> 75.5 | BB6: =BB7-BB5 -> 77 | BC6: =BC7-BC5 -> 75 | BD6: =BD7-BD5 -> 75.9 | BE6: =SUM(BA6:BD6) -> 303.4 | BF6: =BF7-BF5 -> 84 | BG6: =BG7-BG5 -> 78 | BH6: =BH7-BH5 -> 80 | BI6: =BI7-BI5 -> 92 | BJ6: =SUM(BF6:BI6) -> 334 | BK6: 80 | BL6: 80 | BM6: 80 | BN6: =BO6-SUM(BK6:BM6) -> 72.983977 | BO6: ='CF Market'!M333+'CF Market'!M339 -> 312.98398 | BT6: ='CF Market'!N333+'CF Market'!N339 -> 306.36701 | BY6: ='CF Market'!O333+'CF Market'!O339 -> 391.31375 | CD6: ='CF Market'!P333+'CF Market'!P339 -> 394.87173 | CI6: ='CF Market'!Q333+'CF Market'!Q339 -> 386.9743 | CN6: ='CF Market'!R333+'CF Market'!R339 -> 379.23481 | CS6: ='CF Market'!S333+'CF Market'!S339 -> 371.65012 | CX6: ='CF Market'!T333+'CF Market'!T339 -> 140.96626 | DC6: ='CF Market'!U333+'CF Market'!U339 -> 93.147931 | DH6: ='CF Market'!V333+'CF Market'!V339 -> 89.148392 | DM6: ='CF Market'!W333+'CF Market'!W339 -> 9.8829666 | DR6: ='CF Market'!X333+'CF Market'!X339 -> 0 | DW6: ='CF Market'!Y333+'CF Market'!Y339 -> 0
B7: Kalydeco revenues, net | C7: =C5+C6 -> 0 | D7: =D5+D6 -> 0 | E7: =E5+E6 -> 0 | F7: =F5+F6 -> 0 | G7: =G5+G6 -> 0 | H7: =H5+H6 -> 0 | I7: =I5+I6 -> 0 | J7: =J5+J6 -> 0 | ... AS7: =AS5+AS6 -> 126.799 | AT7: =AT6+AT5 -> 124.342 | AU7: =AU5+AU6 -> 463.66 | AV7: =AV5+AV6 -> 130.2 | AW7: 154.9 | AX7: 166 | AY7: =AY5+AY6 -> 180 | AZ7: =AZ5+AZ6 -> 631.129 | BA7: =IS!W84 -> 170.5 | BB7: =IS!X84 -> 180 | BC7: =IS!Y84 -> 176 | BD7: =IS!Z84 -> 176.9 | BE7: =BE5+BE6 -> 703.4 | BF7: =IS!AB84 -> 186 | BG7: =IS!AC84 -> 190 | BH7: =IS!AD84 -> 213 | BI7: =IS!AE84 -> 256 | BJ7: =BJ5+BJ6 -> 845 | BK7: =BK5+BK6 -> 230 | BL7: =BL5+BL6 -> 235 | BM7: =BM5+BM6 -> 240 | BN7: =BN5+BN6 -> 244.21633 | BO7: =BO5+BO6 -> 949.21633 | BT7: =BT5+BT6 -> 980.27101 | BY7: =BY5+BY6 -> 1110.9818 | CD7: =CD5+CD6 -> 1156.4902 | CI7: =CI5+CI6 -> 1148.5928 | CN7: =CN5+CN6 -> 1140.8533 | CS7: =CS5+CS6 -> 1133.2686 | CX7: =CX5+CX6 -> 549.58741 | DC7: =DC5+DC6 -> 309.22509 | DH7: =DH5+DH6 -> 305.22555 | DM7: =DM5+DM6 -> 53.740211 | DR7: =DR5+DR6 -> 8.7714489 | DW7: =DW5+DW6 -> 0
BH8: Co. Guidance | BJ8: $810-830M
B9: QoQ Growth | C9: NM | D9: =IF(C7=0,"NM",D7/C7-1) -> NM | E9: =IF(D7=0,"NM",E7/D7-1) -> NM | F9: =IF(E7=0,"NM",F7/E7-1) -> NM | G9: NM | H9: =IF(F7=0,"NM",H7/F7-1) -> NM | I9: =IF(H7=0,"NM",I7/H7-1) -> NM | J9: =IF(I7=0,"NM",J7/I7-1) -> NM | K9: =IF(J7=0,"NM",K7/J7-1) -> NM | L9: NM | M9: =IF(K7=0,"NM",M7/K7-1) -> NM | N9: =IF(M7=0,"NM",N7/M7-1) -> NM | O9: =IF(N7=0,"NM",O7/N7-1) -> NM | P9: =IF(O7=0,"NM",P7/O7-1) -> NM | Q9: NM | R9: =IF(P7=0,"NM",R7/P7-1) -> NM | S9: =IF(R7=0,"NM",S7/R7-1) -> NM | T9: =IF(S7=0,"NM",T7/S7-1) -> NM | U9: =IF(T7=0,"NM",U7/T7-1) -> NM | V9: NM | W9: =IF(U7=0,"NM",W7/U7-1) -> NM | X9: =IF(W7=0,"NM",X7/W7-1) -> NM | Y9: =IF(X7=0,"NM",Y7/X7-1) -> NM | Z9: =IF(Y7=0,"NM",Z7/Y7-1) -> NM | AA9: NM | AB9: =IF(Z7=0,"NM",AB7/Z7-1) -> NM | AC9: =IF(AB7=0,"NM",AC7/AB7-1) -> NM | AD9: =IF(AC7=0,"NM",AD7/AC7-1) -> NM | AE9: =IF(AD7=0,"NM",AE7/AD7-1) -> NM | AF9: NM | AG9: =IF(AE7=0,"NM",AG7/AE7-1) -> NM | AH9: =IF(AG7=0,"NM",AH7/AG7-1) -> 1.468235 | AI9: =IF(AH7=0,"NM",AI7/AH7-1) -> 0.079654763 | AJ9: =IF(AI7=0,"NM",AJ7/AI7-1) -> 0.18996766 | AK9: NM | AL9: =IF(AJ7=0,"NM",AL7/AJ7-1) -> 0.056410256 | AM9: =IF(AL7=0,"NM",AM7/AL7-1) -> 0.60194175 | AN9: =IF(AM7=0,"NM",AN7/AM7-1) -> 0.021212121 | AO9: =IF(AN7=0,"NM",AO7/AN7-1) -> 0.083086053 | AP9: NM | AQ9: =IF(AO7=0,"NM",AQ7/AO7-1) -> -0.091324201 | AR9: =IF(AQ7=0,"NM",AR7/AQ7-1) -> 0.13586935 | AS9: =IF(AR7=0,"NM",AS7/AR7-1) -> 0.1219264 | AT9: =IF(AS7=0,"NM",AT7/AS7-1) -> -0.019377124 | AU9: NM | AV9: =IF(AT7=0,"NM",AV7/AT7-1) -> 0.047111998 | AW9: =IF(AV7=0,"NM",AW7/AV7-1) -> 0.18970814 | AX9: =IF(AW7=0,"NM",AX7/AW7-1) -> 0.071659135 | AY9: =IF(AX7=0,"NM",AY7/AX7-1) -> 0.084337349 | AZ9: NM | BA9: =IF(AY7=0,"NM",BA7/AY7-1) -> -0.052777778 | BB9: =IF(BA7=0,"NM",BB7/BA7-1) -> 0.055718475 | BC9: =IF(BB7=0,"NM",BC7/BB7-1) -> -0.022222222 | BD9: =IF(BC7=0,"NM",BD7/BC7-1) -> 0.0051136364 | BE9: NM | BF9: =IF(BD7=0,"NM",BF7/BD7-1) -> 0.051441492 | BG9: =IF(BF7=0,"NM",BG7/BF7-1) -> 0.021505376 | BH9: =IF(BG7=0,"NM",BH7/BG7-1) -> 0.12105263 | BI9: =IF(BH7=0,"NM",BI7/BH7-1) -> 0.20187793 | BJ9: NM | BK9: =IF(BI7=0,"NM",BK7/BI7-1) -> -0.1015625 | BL9: =IF(BK7=0,"NM",BL7/BK7-1) -> 0.02173913 | BM9: =IF(BL7=0,"NM",BM7/BL7-1) -> 0.021276596 | BN9: =IF(BM7=0,"NM",BN7/BM7-1) -> 0.017568033 | BO9: NM | BT9: NM | BY9: NM | CD9: NM | CI9: NM | CN9: NM | CS9: NM | CX9: NM | DC9: NM | DH9: NM | DM9: NM | DR9: NM | DW9: NM
B10: YoY Growth | C10: NM | D10: NM | E10: MN | F10: NM | G10: NM | H10: =IF(C7=0,"NM",H7/C7-1) -> NM | I10: =IF(D7=0,"NM",I7/D7-1) -> NM | J10: =IF(E7=0,"NM",J7/E7-1) -> NM | K10: =IF(F7=0,"NM",K7/F7-1) -> NM | L10: =IF(G7=0,"NM",L7/G7-1) -> NM | M10: =IF(H7=0,"NM",M7/H7-1) -> NM | N10: =IF(I7=0,"NM",N7/I7-1) -> NM | O10: =IF(J7=0,"NM",O7/J7-1) -> NM | ... BO10: =IF(BJ7=0,"NM",BO7/BJ7-1) -> 0.12333293 | BT10: =IF(BO7=0,"NM",BT7/BO7-1) -> 0.03271613 | BY10: =IF(BT7=0,"NM",BY7/BT7-1) -> 0.13334151 | CD10: =IF(BY7=0,"NM",CD7/BY7-1) -> 0.040962319 | CI10: =IF(CD7=0,"NM",CI7/CD7-1) -> -0.006828795 | CN10: =IF(CI7=0,"NM",CN7/CI7-1) -> -0.0067382331 | CS10: =IF(CN7=0,"NM",CS7/CN7-1) -> -0.006648266 | CX10: =IF(CS7=0,"NM",CX7/CS7-1) -> -0.51504223 | DC10: =IF(CX7=0,"NM",DC7/CX7-1) -> -0.43735049 | DH10: =IF(DC7=0,"NM",DH7/DC7-1) -> -0.01293407 | DM10: =IF(DH7=0,"NM",DM7/DH7-1) -> -0.82393279 | DR10: =IF(DM7=0,"NM",DR7/DM7-1) -> -0.83678053 | DW10: =IF(DR7=0,"NM",DW7/DR7-1) -> -1
B12: Deuterated Kalydeco Sales (US) | BJ12: ='CF Market'!L328 -> 0 | BO12: ='CF Market'!M328 -> 0 | BT12: ='CF Market'!N328 -> 0 | BY12: ='CF Market'!O328 -> 0 | CD12: ='CF Market'!P328 -> 0 | CI12: ='CF Market'!Q328 -> 0 | CN12: ='CF Market'!R328 -> 0 | CS12: ='CF Market'!S328 -> 0 | CX12: ='CF Market'!T328 -> 388.29707 | DC12: ='CF Market'!U328 -> 529.496 | DH12: ='CF Market'!V328 -> 529.496 | DM12: ='CF Market'!W328 -> 741.2944 | DR12: ='CF Market'!X328 -> 741.2944 | DW12: ='CF Market'!Y328 -> 837.78034
B13: Deuterated Kalydeco Sales (ex-US) | BJ13: ='CF Market'!L334+'CF Market'!L340 -> 0 | BO13: ='CF Market'!M334+'CF Market'!M340 -> 0 | BT13: ='CF Market'!N334+'CF Market'!N340 -> 0 | BY13: ='CF Market'!O334+'CF Market'!O340 -> 0 | CD13: ='CF Market'!P334+'CF Market'!P340 -> 0 | CI13: ='CF Market'!Q334+'CF Market'!Q340 -> 0 | CN13: ='CF Market'!R334+'CF Market'!R340 -> 0 | CS13: ='CF Market'!S334+'CF Market'!S340 -> 0 | CX13: ='CF Market'!T334+'CF Market'!T340 -> 223.25086 | DC13: ='CF Market'!U334+'CF Market'!U340 -> 258.20357 | DH13: ='CF Market'!V334+'CF Market'!V340 -> 254.74876 | DM13: ='CF Market'!W334+'CF Market'!W340 -> 327.13624 | DR13: ='CF Market'!X334+'CF Market'!X340 -> 328.34176 | DW13: ='CF Market'!Y334+'CF Market'!Y340 -> 321.77493
B14: Deuterated Kalydeco revenues, net | BJ14: =BJ12+BJ13 -> 0 | BO14: =BO12+BO13 -> 0 | BT14: =BT12+BT13 -> 0 | BY14: =BY12+BY13 -> 0 | CD14: =CD12+CD13 -> 0 | CI14: =CI12+CI13 -> 0 | CN14: =CN12+CN13 -> 0 | CS14: =CS12+CS13 -> 0 | CX14: =CX12+CX13 -> 611.54792 | DC14: =DC12+DC13 -> 787.69957 | DH14: =DH12+DH13 -> 784.24476 | DM14: =DM12+DM13 -> 1068.4306 | DR14: =DR12+DR13 -> 1069.6362 | DW14: =DW12+DW13 -> 1159.5553
B16: QoQ Growth | C16: NM | D16: =IF(C10=0,"NM",D10/C10-1) -> #VALUE! | E16: =IF(D10=0,"NM",E10/D10-1) -> #VALUE! | F16: =IF(E10=0,"NM",F10/E10-1) -> #VALUE! | G16: NM | H16: =IF(F10=0,"NM",H10/F10-1) -> #VALUE! | I16: =IF(H10=0,"NM",I10/H10-1) -> #VALUE! | J16: =IF(I10=0,"NM",J10/I10-1) -> #VALUE! | K16: =IF(J10=0,"NM",K10/J10-1) -> #VALUE! | L16: NM | M16: =IF(K10=0,"NM",M10/K10-1) -> #VALUE! | N16: =IF(M10=0,"NM",N10/M10-1) -> #VALUE! | O16: =IF(N10=0,"NM",O10/N10-1) -> #VALUE! | P16: =IF(O10=0,"NM",P10/O10-1) -> #VALUE! | Q16: NM | R16: =IF(P10=0,"NM",R10/P10-1) -> #VALUE! | S16: =IF(R10=0,"NM",S10/R10-1) -> #VALUE! | T16: =IF(S10=0,"NM",T10/S10-1) -> #VALUE! | U16: =IF(T10=0,"NM",U10/T10-1) -> #VALUE! | V16: NM | W16: =IF(U10=0,"NM",W10/U10-1) -> #VALUE! | X16: =IF(W10=0,"NM",X10/W10-1) -> #VALUE! | Y16: =IF(X10=0,"NM",Y10/X10-1) -> #VALUE! | Z16: =IF(Y10=0,"NM",Z10/Y10-1) -> #VALUE! | AA16: NM | AB16: =IF(Z10=0,"NM",AB10/Z10-1) -> #VALUE! | AC16: =IF(AB10=0,"NM",AC10/AB10-1) -> #VALUE! | AD16: =IF(AC10=0,"NM",AD10/AC10-1) -> #VALUE! | AE16: =IF(AD10=0,"NM",AE10/AD10-1) -> #VALUE! | BJ16: NM | BO16: NM | BT16: NM | BY16: NM | CD16: NM | CI16: NM | CN16: NM | CS16: NM | CX16: NM | DC16: NM | DH16: NM | DM16: NM | DR16: NM | DW16: NM
B17: YoY Growth | C17: NM | D17: NM | E17: MN | F17: NM | G17: NM | H17: =IF(C10=0,"NM",H10/C10-1) -> #VALUE! | I17: =IF(D10=0,"NM",I10/D10-1) -> #VALUE! | J17: =IF(E10=0,"NM",J10/E10-1) -> #VALUE! | K17: =IF(F10=0,"NM",K10/F10-1) -> #VALUE! | L17: =IF(G10=0,"NM",L10/G10-1) -> #VALUE! | M17: =IF(H10=0,"NM",M10/H10-1) -> #VALUE! | N17: =IF(I10=0,"NM",N10/I10-1) -> #VALUE! | O17: =IF(J10=0,"NM",O10/J10-1) -> #VALUE! | ... AE17: =IF(Z10=0,"NM",AE10/Z10-1) -> #VALUE! | BJ17: =IF(BE14=0,"NM",BJ14/BE14-1) -> NM | BO17: =IF(BJ14=0,"NM",BO14/BJ14-1) -> NM | BT17: =IF(BO14=0,"NM",BT14/BO14-1) -> NM | BY17: =IF(BT14=0,"NM",BY14/BT14-1) -> NM | CD17: =IF(BY14=0,"NM",CD14/BY14-1) -> NM | CI17: =IF(CD14=0,"NM",CI14/CD14-1) -> NM | CN17: =IF(CI14=0,"NM",CN14/CI14-1) -> NM | CS17: =IF(CN14=0,"NM",CS14/CN14-1) -> NM | CX17: =IF(CS14=0,"NM",CX14/CS14-1) -> NM | DC17: =IF(CX14=0,"NM",DC14/CX14-1) -> 0.28804226 | DH17: =IF(DC14=0,"NM",DH14/DC14-1) -> -0.004385945 | DM17: =IF(DH14=0,"NM",DM14/DH14-1) -> 0.36236886 | DR17: =IF(DM14=0,"NM",DR14/DM14-1) -> 0.0011283099 | DW17: =IF(DR14=0,"NM",DW14/DR14-1) -> 0.084065129
B19: Incivek sale (US) | C19: 0 | D19: 0 | E19: 0 | F19: 0 | G19: =SUM(C19:F19) -> 0 | H19: 0 | I19: 0 | J19: 0 | K19: 0 | L19: =SUM(H19:K19) -> 0 | M19: 0 | N19: 0 | O19: 0 | P19: 0 | Q19: =SUM(M19:P19) -> 0 | R19: 0 | S19: 0 | T19: 0 | U19: 0 | V19: =SUM(R19:U19) -> 0 | W19: 0 | X19: 0 | Y19: 0 | Z19: 0 | AA19: =SUM(W19:Z19) -> 0 | AB19: 0 | AC19: 74.535 | AD19: 419.595 | AE19: 456.759 | AF19: =SUM(AB19:AE19) -> 950.889 | AG19: 356.927 | AH19: 327.739 | AI19: 254.34 | AJ19: 222.809 | AK19: =SUM(AG19:AJ19) -> 1161.815 | AL19: =267.381-AL7 -> 205.581 | AM19: =254.789-AM7 -> 155.789 | AN19: 85.553 | AO19: 19.322 | AP19: =SUM(AL19:AO19) -> 466.245 | AQ19: =103.461-AQ7 -> 3.961 | AR19: 9.3 | AS19: 10.3 | AT19: 0.6 | AU19: =SUM(AQ19:AT19) -> 24.161 | AV19: =138.509-130.2-AV50-AV51 -> 0.675 | AW19: 5.488 | AX19: 0 | AY19: 0 | AZ19: =SUM(AV19:AY19) -> 6.163 | BA19: 0 | BB19: 0 | BC19: 0 | BD19: 0 | BE19: =SUM(BA19:BD19) -> 0 | BJ19: =SUM(BF19:BI19) -> 0 | BO19: =SUM(BK19:BN19) -> 0 | BT19: =SUM(BP19:BS19) -> 0 | BY19: =SUM(BU19:BX19) -> 0 | CD19: =SUM(BZ19:CC19) -> 0 | CI19: =SUM(CE19:CH19) -> 0 | CN19: =SUM(CJ19:CM19) -> 0 | CS19: =SUM(CO19:CR19) -> 0 | CX19: =SUM(CT19:CW19) -> 0 | DC19: =SUM(CY19:DB19) -> 0 | DH19: =SUM(DD19:DG19) -> 0 | DM19: =SUM(DI19:DL19) -> 0 | DR19: =SUM(DN19:DQ19) -> 0 | DW19: =SUM(DS19:DV19) -> 0
B20: Incivek sale (ex-US) | C20: 0 | D20: 0 | E20: 0 | F20: 0 | G20: =SUM(C20:F20) -> 0 | H20: 0 | I20: 0 | J20: 0 | K20: 0 | L20: =SUM(H20:K20) -> 0 | M20: 0 | N20: 0 | O20: 0 | P20: 0 | Q20: =SUM(M20:P20) -> 0 | R20: 0 | S20: 0 | T20: 0 | U20: 0 | V20: =SUM(R20:U20) -> 0 | W20: 0 | X20: 0 | Y20: 0 | Z20: 0 | AA20: =SUM(W20:Z20) -> 0 | AB20: 0 | AC20: 0 | AD20: 0 | AE20: 72 | AF20: =SUM(AB20:AE20) -> 72 | AG20: 132 | AH20: 102 | AI20: 71 | AJ20: 138 | AK20: =SUM(AG20:AJ20) -> 443 | AL20: 162 | AM20: 172 | AN20: 76 | AO20: 0 | AP20: =SUM(AL20:AO20) -> 410 | AQ20: 0 | AR20: 0 | AS20: 0 | AT20: 0 | AU20: =SUM(AQ20:AT20) -> 0 | AV20: 0 | AW20: 0 | AX20: 0 | AY20: 0 | AZ20: =SUM(AV20:AY20) -> 0 | BA20: 0 | BB20: 0 | BC20: 0 | BD20: 0 | BE20: =SUM(BA20:BD20) -> 0 | BJ20: =SUM(BF20:BI20) -> 0 | BO20: =SUM(BK20:BN20) -> 0 | BT20: =SUM(BP20:BS20) -> 0 | BY20: =SUM(BU20:BX20) -> 0 | CD20: =SUM(BZ20:CC20) -> 0 | CI20: =SUM(CE20:CH20) -> 0 | CN20: =SUM(CJ20:CM20) -> 0 | CS20: =SUM(CO20:CR20) -> 0 | CX20: =SUM(CT20:CW20) -> 0 | DC20: =SUM(CY20:DB20) -> 0 | DH20: =SUM(DD20:DG20) -> 0 | DM20: =SUM(DI20:DL20) -> 0 | DR20: =SUM(DN20:DQ20) -> 0 | DW20: =SUM(DS20:DV20) -> 0
B22: Incivek royalty (ex-US) | C22: 0 | D22: 0 | E22: 0 | F22: 0 | G22: =SUM(C22:F22) -> 0 | H22: 0 | I22: 0 | J22: 0 | K22: 0 | L22: =SUM(H22:K22) -> 0 | M22: 0 | N22: 0 | O22: 0 | P22: 0 | Q22: =SUM(M22:P22) -> 0 | R22: 0 | S22: 0 | T22: 0 | U22: 0 | V22: =SUM(R22:U22) -> 0 | W22: 0 | X22: 0 | Y22: 0 | Z22: 0 | AA22: =SUM(W22:Z22) -> 0 | AB22: 0 | AC22: 0 | AD22: 0 | AE22: =25.405-AE50 -> 20.315 | AF22: =SUM(AB22:AE22) -> 20.315 | AG22: 32.884 | AH22: 27.97 | AI22: 19.957 | AJ22: =36.8 -> 36.8 | AK22: =SUM(AG22:AJ22) -> 117.611 | AL22: 39 | AM22: 44.1 | AN22: 21 | AO22: 26.387 | AP22: =SUM(AL22:AO22) -> 130.487 | AQ22: 0 | AR22: 0 | AS22: 0 | AT22: 0 | AU22: =SUM(AQ22:AT22) -> 0 | AV22: 0 | AW22: 0 | AX22: 0 | AY22: 0 | AZ22: =SUM(AV22:AY22) -> 0 | BA22: 0 | BB22: 0 | BC22: 0 | BD22: 0 | BE22: =SUM(BA22:BD22) -> 0 | BJ22: =SUM(BF22:BI22) -> 0 | BO22: =SUM(BK22:BN22) -> 0 | BT22: =SUM(BP22:BS22) -> 0 | BY22: =SUM(BU22:BX22) -> 0 | CD22: =SUM(BZ22:CC22) -> 0 | CI22: =SUM(CE22:CH22) -> 0 | CN22: =SUM(CJ22:CM22) -> 0 | CS22: =SUM(CO22:CR22) -> 0 | CX22: =SUM(CT22:CW22) -> 0 | DC22: =SUM(CY22:DB22) -> 0 | DH22: =SUM(DD22:DG22) -> 0 | DM22: =SUM(DI22:DL22) -> 0 | DR22: =SUM(DN22:DQ22) -> 0 | DW22: =SUM(DS22:DV22) -> 0
B23: Incivek revenues, net | C23: =C19+C22 -> 0 | D23: =D19+D22 -> 0 | E23: =E19+E22 -> 0 | F23: =F19+F22 -> 0 | G23: =G19+G22 -> 0 | H23: =H19+H22 -> 0 | I23: =I19+I22 -> 0 | J23: =J19+J22 -> 0 | ... AV23: =AV19+AV22 -> 0.675 | AW23: =AW22+AW19 -> 5.488 | AX23: =AX19+AX22 -> 0 | AY23: =AY19+AY22 -> 0 | AZ23: =AZ19+AZ22 -> 6.163 | BA23: =BA19+BA22 -> 0 | BB23: =BB19+BB22 -> 0 | BC23: =BC19+BC22 -> 0 | BD23: =BD19+BD22 -> 0 | BE23: =BE19+BE22 -> 0 | BJ23: =BJ19+BJ22 -> 0 | BO23: =BO19+BO22 -> 0 | BT23: =BT19+BT22 -> 0 | BY23: =BY19+BY22 -> 0 | CD23: =CD19+CD22 -> 0 | CI23: =CI19+CI22 -> 0 | CN23: =CN19+CN22 -> 0 | CS23: =CS19+CS22 -> 0 | CX23: =CX19+CX22 -> 0 | DC23: =DC19+DC22 -> 0 | DH23: =DH19+DH22 -> 0 | DM23: =DM19+DM22 -> 0 | DR23: =DR19+DR22 -> 0 | DW23: =DW19+DW22 -> 0
B24: QoQ Growth | C24: NM | D24: =IF(C23=0,"NM",D23/C23-1) -> NM | E24: =IF(D23=0,"NM",E23/D23-1) -> NM | F24: =IF(E23=0,"NM",F23/E23-1) -> NM | G24: NM | H24: =IF(F23=0,"NM",H23/F23-1) -> NM | I24: =IF(H23=0,"NM",I23/H23-1) -> NM | J24: =IF(I23=0,"NM",J23/I23-1) -> NM | K24: =IF(J23=0,"NM",K23/J23-1) -> NM | L24: NM | M24: =IF(K23=0,"NM",M23/K23-1) -> NM | N24: =IF(M23=0,"NM",N23/M23-1) -> NM | O24: =IF(N23=0,"NM",O23/N23-1) -> NM | P24: =IF(O23=0,"NM",P23/O23-1) -> NM | Q24: NM | R24: =IF(P23=0,"NM",R23/P23-1) -> NM | S24: =IF(R23=0,"NM",S23/R23-1) -> NM | T24: =IF(S23=0,"NM",T23/S23-1) -> NM | U24: =IF(T23=0,"NM",U23/T23-1) -> NM | V24: NM | W24: =IF(U23=0,"NM",W23/U23-1) -> NM | X24: =IF(W23=0,"NM",X23/W23-1) -> NM | Y24: =IF(X23=0,"NM",Y23/X23-1) -> NM | Z24: =IF(Y23=0,"NM",Z23/Y23-1) -> NM | AA24: NM | AB24: =IF(Z23=0,"NM",AB23/Z23-1) -> NM | AC24: =IF(AB23=0,"NM",AC23/AB23-1) -> NM | AD24: =IF(AC23=0,"NM",AD23/AC23-1) -> 4.6295029 | AE24: =IF(AD23=0,"NM",AE23/AD23-1) -> 0.13698686 | AF24: NM | AG24: =IF(AE23=0,"NM",AG23/AE23-1) -> -0.18291292 | AH24: =IF(AG23=0,"NM",AH23/AG23-1) -> -0.087483421 | AI24: =IF(AH23=0,"NM",AI23/AH23-1) -> -0.22887248 | AJ24: =IF(AI23=0,"NM",AJ23/AI23-1) -> -0.053547797 | AK24: NM | AL24: =IF(AJ23=0,"NM",AL23/AJ23-1) -> -0.057887053 | AM24: =IF(AL23=0,"NM",AM23/AL23-1) -> -0.18272883 | AN24: =IF(AM23=0,"NM",AN23/AM23-1) -> -0.46693915 | AO24: =IF(AN23=0,"NM",AO23/AN23-1) -> -0.57102099 | AP24: NM | AQ24: =IF(AO23=0,"NM",AQ23/AO23-1) -> -0.91334311 | AR24: =IF(AQ23=0,"NM",AR23/AQ23-1) -> 1.3478919 | AS24: =IF(AR23=0,"NM",AS23/AR23-1) -> 0.10752688 | AT24: =IF(AS23=0,"NM",AT23/AS23-1) -> -0.94174757 | AU24: NM | AV24: =IF(AT23=0,"NM",AV23/AT23-1) -> 0.125 | AW24: =IF(AV23=0,"NM",AW23/AV23-1) -> 7.1303704 | AX24: =IF(AW23=0,"NM",AX23/AW23-1) -> -1 | AY24: =IF(AX23=0,"NM",AY23/AX23-1) -> NM | AZ24: NM | BA24: =IF(AY23=0,"NM",BA23/AY23-1) -> NM | BB24: =IF(BA23=0,"NM",BB23/BA23-1) -> NM | BC24: =IF(BB23=0,"NM",BC23/BB23-1) -> NM | BD24: =IF(BC23=0,"NM",BD23/BC23-1) -> NM | BE24: NM | BJ24: NM | BO24: NM | BT24: NM | BY24: NM | CD24: NM | CI24: NM | CN24: NM | CS24: NM | CX24: NM | DC24: NM | DH24: NM | DM24: NM | DR24: NM | DW24: NM
B25: YoY Growth | C25: NM | D25: NM | E25: MN | F25: NM | G25: NM | H25: =IF(C23=0,"NM",H23/C23-1) -> NM | I25: =IF(D23=0,"NM",I23/D23-1) -> NM | J25: =IF(E23=0,"NM",J23/E23-1) -> NM | K25: =IF(F23=0,"NM",K23/F23-1) -> NM | L25: =IF(G23=0,"NM",L23/G23-1) -> NM | M25: =IF(H23=0,"NM",M23/H23-1) -> NM | N25: =IF(I23=0,"NM",N23/I23-1) -> NM | O25: =IF(J23=0,"NM",O23/J23-1) -> NM | ... BE25: =IF(AZ23=0,"NM",BE23/AZ23-1) -> -1 | BJ25: =IF(BE23=0,"NM",BJ23/BE23-1) -> NM | BO25: =IF(BJ23=0,"NM",BO23/BJ23-1) -> NM | BT25: =IF(BO23=0,"NM",BT23/BO23-1) -> NM | BY25: =IF(BT23=0,"NM",BY23/BT23-1) -> NM | CD25: =IF(BY23=0,"NM",CD23/BY23-1) -> NM | CI25: =IF(CD23=0,"NM",CI23/CD23-1) -> NM | CN25: =IF(CI23=0,"NM",CN23/CI23-1) -> NM | CS25: =IF(CN23=0,"NM",CS23/CN23-1) -> NM | CX25: =IF(CS23=0,"NM",CX23/CS23-1) -> NM | DC25: =IF(CX23=0,"NM",DC23/CX23-1) -> NM | DH25: =IF(DC23=0,"NM",DH23/DC23-1) -> NM | DM25: =IF(DH23=0,"NM",DM23/DH23-1) -> NM | DR25: =IF(DM23=0,"NM",DR23/DM23-1) -> NM | DW25: =IF(DR23=0,"NM",DW23/DR23-1) -> NM
B27: Orkambi Sales (US) | C27: 0 | D27: 0 | E27: 0 | F27: 0 | G27: =SUM(C27:F27) -> 0 | H27: 0 | I27: 0 | J27: 0 | K27: 0 | L27: =SUM(H27:K27) -> 0 | M27: 0 | N27: 0 | O27: 0 | P27: 0 | Q27: =SUM(M27:P27) -> 0 | R27: 0 | S27: 0 | T27: 0 | U27: 0 | V27: =SUM(R27:U27) -> 0 | W27: 0 | X27: 0 | Y27: 0 | Z27: 0 | AA27: =SUM(W27:Z27) -> 0 | AB27: 0 | AC27: 0 | AD27: 0 | AE27: 0 | AF27: =SUM(AB27:AE27) -> 0 | AG27: 0 | AH27: 0 | AI27: 0 | AJ27: 0 | AK27: =SUM(AG27:AJ27) -> 0 | AL27: 0 | AM27: 0 | AN27: 0 | AO27: 0 | AP27: =SUM(AL27:AO27) -> 0 | AQ27: 0 | AR27: 0 | AS27: 0 | AT27: 0 | AU27: =SUM(AQ27:AT27) -> 0 | AV27: 0 | AW27: 0 | AX27: 130.8 | AY27: 220 | AZ27: =AY27+AX27+AW27+AV27 -> 350.8 | BA27: =223.1-BA28 -> 214.1 | BB27: 229.4 | BC27: 211 | BD27: 248 | BE27: =SUM(BA27:BD27) -> 902.5 | BF27: 264 | BG27: 288 | BH27: 293 | BI27: 308 | BJ27: =SUM(BF27:BI27) -> 1153 | BK27: 300 | BL27: 295 | BM27: 290 | BN27: =BO27-SUM(BK27:BM27) -> 287.59083 | BO27: ='CF Market'!M329 -> 1172.5908 | BT27: ='CF Market'!N329 -> 986.48238 | BY27: ='CF Market'!O329 -> 754.65364 | CD27: ='CF Market'!P329 -> 524.16962 | CI27: ='CF Market'!Q329 -> 438.24238 | CN27: ='CF Market'!R329 -> 365.96398 | CS27: ='CF Market'!S329 -> 221.60891 | CX27: ='CF Market'!T329 -> 161.36571 | DC27: ='CF Market'!U329 -> 80.682855 | DH27: ='CF Market'!V329 -> 29.314771 | DM27: ='CF Market'!W329 -> 14.657385 | DR27: ='CF Market'!X329 -> 0 | DW27: ='CF Market'!Y329 -> 0
B28: Orkambi Sales (ex-US) | C28: 0 | D28: 0 | E28: 0 | F28: 0 | G28: =SUM(C28:F28) -> 0 | H28: 0 | I28: 0 | J28: 0 | K28: 0 | L28: =SUM(H28:K28) -> 0 | M28: 0 | N28: 0 | O28: 0 | P28: 0 | Q28: =SUM(M28:P28) -> 0 | R28: 0 | S28: 0 | T28: 0 | U28: 0 | V28: =SUM(R28:U28) -> 0 | W28: 0 | X28: 0 | Y28: 0 | Z28: 0 | AA28: =SUM(W28:Z28) -> 0 | AB28: 0 | AC28: 0 | AD28: 0 | AE28: 0 | AF28: =SUM(AB28:AE28) -> 0 | AG28: 0 | AH28: 0 | AI28: 0 | AJ28: 0 | AK28: =SUM(AG28:AJ28) -> 0 | AL28: 0 | AM28: 0 | AN28: 0 | AO28: 0 | AP28: =SUM(AL28:AO28) -> 0 | AQ28: 0 | AR28: 0 | AS28: 0 | AT28: 0 | AU28: =SUM(AQ28:AT28) -> 0 | AV28: 0 | AW28: 0 | AX28: 0 | AY28: =AZ28-AX28-AW28-AV28 -> 0 | AZ28: ='CF Market'!J335 -> 0 | BA28: 9 | BB28: =BB29-BB27 -> 16.251 | BC28: =BC29-BC27 -> 22.689 | BD28: =BD29-BD27 -> 28.982 | BE28: =SUM(BA28:BD28) -> 76.922 | BF28: =BF29-BF27 -> 30.622 | BG28: =BG29-BG27 -> 35.988 | BH28: =BH29-BH27 -> 43.642 | BI28: =BI29-BI27 -> 57.228 | BJ28: =SUM(BF28:BI28) -> 167.48 | BK28: 60 | BL28: 75 | BM28: 90 | BN28: =BO28-SUM(BK28:BM28) -> 96.158662 | BO28: ='CF Market'!M335+'CF Market'!M341 -> 321.15866 | BT28: ='CF Market'!N335+'CF Market'!N341 -> 478.03138 | BY28: ='CF Market'!O335+'CF Market'!O341 -> 519.64711 | CD28: ='CF Market'!P335+'CF Market'!P341 -> 681.6913 | CI28: ='CF Market'!Q335+'CF Market'!Q341 -> 616.25918 | CN28: ='CF Market'!R335+'CF Market'!R341 -> 533.71623 | CS28: ='CF Market'!S335+'CF Market'!S341 -> 398.97084 | CX28: ='CF Market'!T335+'CF Market'!T341 -> 227.3771 | DC28: ='CF Market'!U335+'CF Market'!U341 -> 131.43194 | DH28: ='CF Market'!V335+'CF Market'!V341 -> 81.563778 | DM28: ='CF Market'!W335+'CF Market'!W341 -> 37.538254 | DR28: ='CF Market'!X335+'CF Market'!X341 -> 17.92106 | DW28: ='CF Market'!Y335+'CF Market'!Y341 -> 1.4870667
B29: Orkambi revenues, net | C29: =C27+C28 -> 0 | D29: =D27+D28 -> 0 | E29: =E27+E28 -> 0 | F29: =F27+F28 -> 0 | G29: =G27+G28 -> 0 | H29: =H27+H28 -> 0 | I29: =I27+I28 -> 0 | J29: =J27+J28 -> 0 | ... AZ29: =AZ27+AZ28 -> 350.8 | BA29: =394.41-BA7 -> 223.91 | BB29: =425.651-BB7 -> 245.651 | BC29: =IS!Y86 -> 233.689 | BD29: =IS!Z86 -> 276.982 | BE29: =BE27+BE28 -> 979.422 | BF29: =IS!AB86 -> 294.622 | BG29: =IS!AC86 -> 323.988 | BH29: =IS!AD86 -> 336.642 | BI29: =IS!AE86 -> 365.228 | BJ29: =BJ27+BJ28 -> 1320.48 | BK29: =SUM(BK27:BK28) -> 360 | BL29: =SUM(BL27:BL28) -> 370 | BM29: =SUM(BM27:BM28) -> 380 | BN29: =SUM(BN27:BN28) -> 383.74949 | BO29: =BO27+BO28 -> 1493.7495 | BT29: =BT27+BT28 -> 1464.5138 | BY29: =BY27+BY28 -> 1274.3007 | CD29: =CD27+CD28 -> 1205.8609 | CI29: =CI27+CI28 -> 1054.5016 | CN29: =CN27+CN28 -> 899.68021 | CS29: =CS27+CS28 -> 620.57975 | CX29: =CX27+CX28 -> 388.74281 | DC29: =DC27+DC28 -> 212.1148 | DH29: =DH27+DH28 -> 110.87855 | DM29: =DM27+DM28 -> 52.19564 | DR29: =DR27+DR28 -> 17.92106 | DW29: =DW27+DW28 -> 1.4870667
BH30: Co. Guidance | BJ30: $1,290-1,320M
B31: QoQ Growth | C31: NM | D31: =IF(C29=0,"NM",D29/C29-1) -> NM | E31: =IF(D29=0,"NM",E29/D29-1) -> NM | F31: =IF(E29=0,"NM",F29/E29-1) -> NM | G31: NM | H31: =IF(F29=0,"NM",H29/F29-1) -> NM | I31: =IF(H29=0,"NM",I29/H29-1) -> NM | J31: =IF(I29=0,"NM",J29/I29-1) -> NM | K31: =IF(J29=0,"NM",K29/J29-1) -> NM | L31: NM | M31: =IF(K29=0,"NM",M29/K29-1) -> NM | N31: =IF(M29=0,"NM",N29/M29-1) -> NM | O31: =IF(N29=0,"NM",O29/N29-1) -> NM | P31: =IF(O29=0,"NM",P29/O29-1) -> NM | Q31: NM | R31: =IF(P29=0,"NM",R29/P29-1) -> NM | S31: =IF(R29=0,"NM",S29/R29-1) -> NM | T31: =IF(S29=0,"NM",T29/S29-1) -> NM | U31: =IF(T29=0,"NM",U29/T29-1) -> NM | V31: NM | W31: =IF(U29=0,"NM",W29/U29-1) -> NM | X31: =IF(W29=0,"NM",X29/W29-1) -> NM | Y31: =IF(X29=0,"NM",Y29/X29-1) -> NM | Z31: =IF(Y29=0,"NM",Z29/Y29-1) -> NM | AA31: NM | AB31: =IF(Z29=0,"NM",AB29/Z29-1) -> NM | AC31: =IF(AB29=0,"NM",AC29/AB29-1) -> NM | AD31: =IF(AC29=0,"NM",AD29/AC29-1) -> NM | AE31: =IF(AD29=0,"NM",AE29/AD29-1) -> NM | AF31: NM | AG31: =IF(AE29=0,"NM",AG29/AE29-1) -> NM | AH31: =IF(AG29=0,"NM",AH29/AG29-1) -> NM | AI31: =IF(AH29=0,"NM",AI29/AH29-1) -> NM | AJ31: =IF(AI29=0,"NM",AJ29/AI29-1) -> NM | AK31: NM | AL31: =IF(AJ29=0,"NM",AL29/AJ29-1) -> NM | AM31: =IF(AL29=0,"NM",AM29/AL29-1) -> NM | AN31: =IF(AM29=0,"NM",AN29/AM29-1) -> NM | AO31: =IF(AN29=0,"NM",AO29/AN29-1) -> NM | AP31: NM | AQ31: =IF(AO29=0,"NM",AQ29/AO29-1) -> NM | AR31: =IF(AQ29=0,"NM",AR29/AQ29-1) -> NM | AS31: =IF(AR29=0,"NM",AS29/AR29-1) -> NM | AT31: =IF(AS29=0,"NM",AT29/AS29-1) -> NM | AU31: NM | AV31: =IF(AT29=0,"NM",AV29/AT29-1) -> NM | AW31: =IF(AV29=0,"NM",AW29/AV29-1) -> NM | AX31: =IF(AW29=0,"NM",AX29/AW29-1) -> NM | AY31: =IF(AX29=0,"NM",AY29/AX29-1) -> 0.68195719 | AZ31: NM | BA31: =IF(AY29=0,"NM",BA29/AY29-1) -> 0.017772727 | BB31: =IF(BA29=0,"NM",BB29/BA29-1) -> 0.097097048 | BC31: =IF(BB29=0,"NM",BC29/BB29-1) -> -0.0486951 | BD31: =IF(BC29=0,"NM",BD29/BC29-1) -> 0.18525904 | BE31: NM | BF31: =IF(BD29=0,"NM",BF29/BD29-1) -> 0.063686449 | BG31: =IF(BF29=0,"NM",BG29/BF29-1) -> 0.09967348 | BH31: =IF(BG29=0,"NM",BH29/BG29-1) -> 0.039057002 | BI31: =IF(BH29=0,"NM",BI29/BH29-1) -> 0.084915132 | BJ31: NM | BK31: =IF(BI29=0,"NM",BK29/BI29-1) -> -0.014314346 | BL31: =IF(BK29=0,"NM",BL29/BK29-1) -> 0.027777778 | BM31: =IF(BL29=0,"NM",BM29/BL29-1) -> 0.027027027 | BN31: =IF(BM29=0,"NM",BN29/BM29-1) -> 0.0098670829 | BO31: NM | BT31: NM | BY31: NM | CD31: NM | CI31: NM | CN31: NM | CS31: NM | CX31: NM | DC31: NM | DH31: NM | DM31: NM | DR31: NM | DW31: NM
B32: YoY Growth | C32: NM | D32: NM | E32: MN | F32: NM | G32: NM | H32: =IF(C29=0,"NM",H29/C29-1) -> NM | I32: =IF(D29=0,"NM",I29/D29-1) -> NM | J32: =IF(E29=0,"NM",J29/E29-1) -> NM | K32: =IF(F29=0,"NM",K29/F29-1) -> NM | L32: =IF(G29=0,"NM",L29/G29-1) -> NM | M32: =IF(H29=0,"NM",M29/H29-1) -> NM | N32: =IF(I29=0,"NM",N29/I29-1) -> NM | O32: =IF(J29=0,"NM",O29/J29-1) -> NM | ... BO32: =IF(BJ29=0,"NM",BO29/BJ29-1) -> 0.13121705 | BT32: =IF(BO29=0,"NM",BT29/BO29-1) -> -0.019572045 | BY32: =IF(BT29=0,"NM",BY29/BT29-1) -> -0.12988134 | CD32: =IF(BY29=0,"NM",CD29/BY29-1) -> -0.053707756 | CI32: =IF(CD29=0,"NM",CI29/CD29-1) -> -0.12551975 | CN32: =IF(CI29=0,"NM",CN29/CI29-1) -> -0.14681946 | CS32: =IF(CN29=0,"NM",CS29/CN29-1) -> -0.31022185 | CX32: =IF(CS29=0,"NM",CX29/CS29-1) -> -0.37358123 | DC32: =IF(CX29=0,"NM",DC29/CX29-1) -> -0.45435698 | DH32: =IF(DC29=0,"NM",DH29/DC29-1) -> -0.47727103 | DM32: =IF(DH29=0,"NM",DM29/DH29-1) -> -0.52925394 | DR32: =IF(DM29=0,"NM",DR29/DM29-1) -> -0.656656 | DW32: =IF(DR29=0,"NM",DW29/DR29-1) -> -0.91702128
B34: Symdeko Sales (US) | BJ34: ='CF Market'!L330 -> 0 | BK34: 10 | BL34: 40 | BM34: 70 | BN34: =BO34-SUM(BK34:BM34) -> 84.718853 | BO34: ='CF Market'!M330 -> 204.71885 | BT34: ='CF Market'!N330 -> 390.79841 | BY34: ='CF Market'!O330 -> 308.72194 | CD34: ='CF Market'!P330 -> 238.41784 | CI34: ='CF Market'!Q330 -> 179.28097 | CN34: ='CF Market'!R330 -> 149.71254 | CS34: ='CF Market'!S330 -> 90.65819 | CX34: ='CF Market'!T330 -> 66.013245 | DC34: ='CF Market'!U330 -> 33.006623 | DH34: ='CF Market'!V330 -> 11.992406 | DM34: ='CF Market'!W330 -> 2.9981016 | DR34: ='CF Market'!X330 -> 0 | DW34: ='CF Market'!Y330 -> 0
B35: Symdeko Sales (ex-US) | BJ35: ='CF Market'!LL336+'CF Market'!L342 -> 0 | BK35: 0 | BL35: 0 | BM35: 5 | BN35: =BO35-BK35-BL35-BM35 -> 10 | BO35: 15 | BT35: ='CF Market'!N336+'CF Market'!N342 -> 94.205987 | BY35: ='CF Market'!O336+'CF Market'!O342 -> 262.90882 | CD35: ='CF Market'!P336+'CF Market'!P342 -> 361.34585 | CI35: ='CF Market'!Q336+'CF Market'!Q342 -> 359.45147 | CN35: ='CF Market'!R336+'CF Market'!R342 -> 315.96754 | CS35: ='CF Market'!S336+'CF Market'!S342 -> 200.50314 | CX35: ='CF Market'!T336+'CF Market'!T342 -> 83.547685 | DC35: ='CF Market'!U336+'CF Market'!U342 -> 45.34402 | DH35: ='CF Market'!V336+'CF Market'!V342 -> 28.139503 | DM35: ='CF Market'!W336+'CF Market'!W342 -> 12.950698 | DR35: ='CF Market'!X336+'CF Market'!X342 -> 6.1827656 | DW35: ='CF Market'!Y336+'CF Market'!Y342 -> 0.513038
B36: Symdeko revenues, net | BJ36: =BJ34+BJ35 -> 0 | BK36: =SUM(BK34:BK35) -> 10 | BL36: =SUM(BL34:BL35) -> 40 | BM36: =SUM(BM34:BM35) -> 75 | BN36: =SUM(BN34:BN35) -> 94.718853 | BO36: =BO34+BO35 -> 219.71885 | BT36: =BT34+BT35 -> 485.0044 | BY36: =BY34+BY35 -> 571.63076 | CD36: =CD34+CD35 -> 599.76369 | CI36: =CI34+CI35 -> 538.73244 | CN36: =CN34+CN35 -> 465.68008 | CS36: =CS34+CS35 -> 291.16133 | CX36: =CX34+CX35 -> 149.56093 | DC36: =DC34+DC35 -> 78.350642 | DH36: =DH34+DH35 -> 40.13191 | DM36: =DM34+DM35 -> 15.948799 | DR36: =DR34+DR35 -> 6.1827656 | DW36: =DW34+DW35 -> 0.513038
B38: QoQ Growth | BJ38: NM | BO38: NM | BT38: NM | BY38: NM | CD38: NM | CI38: NM | CN38: NM | CS38: NM | CX38: NM | DC38: NM | DH38: NM | DM38: NM | DR38: NM | DW38: NM
B39: YoY Growth | BJ39: =IF(BE36=0,"NM",BJ36/BE36-1) -> NM | BO39: =IF(BJ36=0,"NM",BO36/BJ36-1) -> NM | BT39: =IF(BO36=0,"NM",BT36/BO36-1) -> 1.2073864 | BY39: =IF(BT36=0,"NM",BY36/BT36-1) -> 0.17860944 | CD39: =IF(BY36=0,"NM",CD36/BY36-1) -> 0.049215214 | CI39: =IF(CD36=0,"NM",CI36/CD36-1) -> -0.10175883 | CN39: =IF(CI36=0,"NM",CN36/CI36-1) -> -0.13560045 | CS39: =IF(CN36=0,"NM",CS36/CN36-1) -> -0.37476104 | CX39: =IF(CS36=0,"NM",CX36/CS36-1) -> -0.48632968 | DC39: =IF(CX36=0,"NM",DC36/CX36-1) -> -0.47612895 | DH39: =IF(DC36=0,"NM",DH36/DC36-1) -> -0.48779093 | DM39: =IF(DH36=0,"NM",DM36/DH36-1) -> -0.60259057 | DR39: =IF(DM36=0,"NM",DR36/DM36-1) -> -0.61233661 | DW39: =IF(DR36=0,"NM",DW36/DR36-1) -> -0.91702128
B41: Triplet Sales (US) | BJ41: ='CF Market'!L331 -> 0 | BO41: ='CF Market'!M331 -> 0 | BT41: ='CF Market'!N331 -> 0 | BY41: ='CF Market'!O331 -> 1075.9316 | CD41: ='CF Market'!P331 -> 2289.5734 | CI41: ='CF Market'!Q331 -> 3097.3572 | CN41: ='CF Market'!R331 -> 3280.7838 | CS41: ='CF Market'!S331 -> 3481.3099 | CX41: ='CF Market'!T331 -> 4130.9495 | DC41: ='CF Market'!U331 -> 5573.7506 | DH41: ='CF Market'!V331 -> 5692.2279 | DM41: ='CF Market'!W331 -> 5810.4635 | DR41: ='CF Market'!X331 -> 5927.4824 | DW41: ='CF Market'!Y331 -> 5974.0103
B42: Triplet Sales (ex-US) | BJ42: ='CF Market'!L337+'CF Market'!L343 -> 0 | BO42: ='CF Market'!M337+'CF Market'!M343 -> 0 | BT42: ='CF Market'!N337+'CF Market'!N343 -> 0 | BY42: ='CF Market'!O337+'CF Market'!O343 -> 0 | CD42: ='CF Market'!P337+'CF Market'!P343 -> 100.36645 | CI42: ='CF Market'!Q337+'CF Market'!Q343 -> 340.94738 | CN42: ='CF Market'!R337+'CF Market'!R343 -> 762.51308 | CS42: ='CF Market'!S337+'CF Market'!S343 -> 1180.7849 | CX42: ='CF Market'!T337+'CF Market'!T343 -> 1537.0721 | DC42: ='CF Market'!U337+'CF Market'!U343 -> 1916.3253 | DH42: ='CF Market'!V337+'CF Market'!V343 -> 2068.1617 | DM42: ='CF Market'!W337+'CF Market'!W343 -> 2102.9746 | DR42: ='CF Market'!X337+'CF Market'!X343 -> 2084.9185 | DW42: ='CF Market'!Y337+'CF Market'!Y343 -> 2062.3376
B43: Triplet revenues, net (risk-adj) | BJ43: =BJ41+BJ42 -> 0 | BO43: =BO41+BO42 -> 0 | BT43: =BT41+BT42 -> 0 | BY43: =(BY41+BY42) -> 1075.9316 | BZ43: =(BZ41+BZ42) -> 0 | CA43: =(CA41+CA42) -> 0 | CB43: =(CB41+CB42) -> 0 | CC43: =(CC41+CC42) -> 0 | CD43: =(CD41+CD42) -> 2389.9398 | CE43: =(CE41+CE42) -> 0 | CF43: =(CF41+CF42) -> 0 | ... DW43: =(DW41+DW42) -> 8036.3479
B45: QoQ Growth | BJ45: NM | BO45: NM | BT45: NM | BY45: NM | CD45: NM | CI45: NM | CN45: NM | CS45: NM | CX45: NM | DC45: NM | DH45: NM | DM45: NM | DR45: NM | DW45: NM
B46: YoY Growth | BJ46: =IF(BE43=0,"NM",BJ43/BE43-1) -> NM | BO46: =IF(BJ43=0,"NM",BO43/BJ43-1) -> NM | BT46: =IF(BO43=0,"NM",BT43/BO43-1) -> NM | BY46: =IF(BT43=0,"NM",BY43/BT43-1) -> NM | CD46: =IF(BY43=0,"NM",CD43/BY43-1) -> 1.2212748 | CI46: =IF(CD43=0,"NM",CI43/CD43-1) -> 0.43865738 | CN46: =IF(CI43=0,"NM",CN43/CI43-1) -> 0.1759566 | CS46: =IF(CN43=0,"NM",CS43/CN43-1) -> 0.15304289 | CX46: =IF(CS43=0,"NM",CX43/CS43-1) -> 0.21576714 | DC46: =IF(CX43=0,"NM",DC43/CX43-1) -> 0.32146212 | DH46: =IF(DC43=0,"NM",DH43/DC43-1) -> 0.036089579 | DM46: =IF(DH43=0,"NM",DM43/DH43-1) -> 0.019721755 | DR46: =IF(DM43=0,"NM",DR43/DM43-1) -> 0.012505674 | DW46: =IF(DR43=0,"NM",DW43/DR43-1) -> 0.0029887412
B49: Total product revenue | C49: =C7+C23+C29 -> 0 | D49: =D7+D23+D29 -> 0 | E49: =E7+E23+E29 -> 0 | F49: =F7+F23+F29 -> 0 | G49: =SUM(C49:F49) -> 0 | H49: =H7+H23+H29 -> 0 | I49: =I7+I23+I29 -> 0 | J49: =J7+J23+J29 -> 0 | K49: =K7+K23+K29 -> 0 | L49: =SUM(H49:K49) -> 0 | M49: =M7+M23+M29 -> 0 | N49: =N7+N23+N29 -> 0 | O49: =O7+O23+O29 -> 0 | P49: =P7+P23+P29 -> 0 | Q49: =SUM(M49:P49) -> 0 | R49: =R7+R23+R29 -> 0 | S49: =S7+S23+S29 -> 0 | T49: =T7+T23+T29 -> 0 | U49: =U7+U23+U29 -> 0 | V49: =SUM(R49:U49) -> 0 | W49: =W7+W23+W29 -> 0 | X49: =X7+X23+X29 -> 0 | Y49: =Y7+Y23+Y29 -> 0 | Z49: =Z7+Z23+Z29 -> 0 | AA49: =SUM(W49:Z49) -> 0 | AB49: =AB7+AB23+AB29 -> 0 | AC49: =AC7+AC23+AC29 -> 74.535 | AD49: =AD7+AD23+AD29 -> 419.595 | AE49: =AE7+AE23+AE29 -> 477.074 | AF49: =SUM(AB49:AE49) -> 971.204 | AG49: =AG7+AG23+AG29 -> 408.259 | AH49: =AH7+AH23+AH29 -> 401.243 | AI49: =AI7+AI23+AI29 -> 323.458 | AJ49: =AJ7+AJ23+AJ29 -> 318.109 | AK49: =SUM(AG49:AJ49) -> 1451.069 | AL49: =AL7+AL23+AL29 -> 306.381 | AM49: =AM7+AM23+AM29 -> 298.889 | AN49: =AN7+AN23+AN29 -> 207.653 | AO49: =AO7+AO23+AO29 -> 155.209 | AP49: =SUM(AL49:AO49) -> 968.132 | AQ49: =AQ7+AQ23+AQ29 -> 103.461 | AR49: =AR7+AR23+AR29 -> 122.319 | AS49: =AS7+AS23+AS29 -> 137.099 | AT49: =AT7+AT23+AT29 -> 124.942 | AU49: =SUM(AQ49:AT49) -> 487.821 | AV49: =AV7+AV23+AV29 -> 130.875 | AW49: =AW7+AW23+AW29 -> 160.388 | AX49: =AX7+AX23+AX29 -> 296.8 | AY49: =AY7+AY23+AY29 -> 400 | AZ49: =SUM(AV49:AY49) -> 988.063 | BA49: =BA7+BA23+BA29 -> 394.41 | BB49: =BB7+BB23+BB29 -> 425.651 | BC49: =BC7+BC23+BC29 -> 409.689 | BD49: =BD7+BD23+BD29 -> 453.882 | BE49: =BE7+BE23+BE29 -> 1682.822 | BF49: =BF7+BF29 -> 480.622 | BG49: =BG7+BG29 -> 513.988 | BH49: =BH7+BH29 -> 549.642 | BI49: =BI7+BI23+BI29 -> 621.228 | BJ49: =BJ7+BJ23+BJ29+BJ14+BJ36+BJ43 -> 2165.48 | BK49: =BK7+BK23+BK29+BK36 -> 600 | BL49: =BL7+BL23+BL29+BL36 -> 645 | BM49: =BM7+BM23+BM29+BM36 -> 695 | BN49: =BN7+BN23+BN29+BN36 -> 722.68467 | BO49: =BO7+BO23+BO29+BO14+BO36+BO43 -> 2662.6847 | BT49: =BT7+BT23+BT29+BT14+BT36+BT43 -> 2929.7892 | BY49: =BY7+BY23+BY29+BY14+BY36+BY43 -> 4032.845 | CD49: =CD7+CD23+CD29+CD14+CD36+CD43 -> 5352.0546 | CI49: =CI7+CI23+CI29+CI14+CI36+CI43 -> 6180.1313 | CN49: =CN7+CN23+CN29+CN14+CN36+CN43 -> 6549.5105 | CS49: =CS7+CS23+CS29+CS14+CS36+CS43 -> 6707.1044 | CX49: =CX7+CX23+CX29+CX14+CX36+CX43 -> 7367.4607 | DC49: =DC7+DC23+DC29+DC14+DC36+DC43 -> 8877.466 | DH49: =DH7+DH23+DH29+DH14+DH36+DH43 -> 9000.8703 | DM49: =DM7+DM23+DM29+DM14+DM36+DM43 -> 9103.7533 | DR49: =DR7+DR23+DR29+DR14+DR36+DR43 -> 9114.9124 | DW49: =DW7+DW23+DW29+DW14+DW36+DW43 -> 9197.9033
B50: Royalty revenues | C50: 9.179 | D50: 9.005 | E50: 10.902 | F50: =41.208-E50-D50-C50 -> 12.122 | G50: =SUM(C50:F50) -> 41.208 | H50: 9.796 | I50: 10.967 | J50: =12.522 -> 12.522 | K50: =14.688 -> 14.688 | L50: =SUM(H50:K50) -> 47.973 | M50: 10.851 | N50: 9.741 | O50: 7.763 | P50: 9.128 | Q50: =SUM(M50:P50) -> 37.483 | R50: 6.14 | S50: 5.917 | T50: 7.834 | U50: 8.429 | V50: =SUM(R50:U50) -> 28.32 | W50: 6.407 | X50: 7.262 | Y50: 8.173 | Z50: 8.402 | AA50: =SUM(W50:Z50) -> 30.244 | AB50: 6.061 | AC50: 10.01 | AD50: 8.539 | AE50: =29.7-SUM(AB50:AD50) -> 5.09 | AF50: =SUM(AB50:AE50) -> 29.7 | AG50: =38.981-AG22 -> 6.097 | AH50: =33.48-AH22 -> 5.51 | AI50: =25.586-AI22 -> 5.629 | AJ50: =43.451-AJ22 -> 6.651 | AK50: =SUM(AG50:AJ50) -> 23.887 | AL50: =43.573-AL22 -> 4.573 | AM50: =49.12-AM22 -> 5.02 | AN50: 6.012 | AO50: 10.5 | AP50: =SUM(AL50:AO50) -> 26.105 | AQ50: 10.733 | AR50: 13.015 | AS50: 8.386 | AT50: 8.785 | AU50: =SUM(AQ50:AT50) -> 40.919 | AV50: 6.792 | AW50: 5.077 | AX50: 5.759 | AY50: 6.331 | AZ50: =SUM(AV50:AY50) -> 23.959 | BA50: =IS!W18 -> 2.745 | BB50: =IS!X18 -> 5.771 | BC50: =IS!Y18 -> 3.632 | BD50: =BE50-SUM(BA50:BC50) -> 5.352 | BE50: 17.5 | BF50: =IS!AB18 -> 1.551 | BG50: =IS!AC18 -> 2.861 | BH50: =IS!AD18 -> 2.231 | BI50: =IS!AE18 -> 1.345 | BJ50: =SUM(BF50:BI50) -> 7.988 | BK50: =BO50/4 -> 0 | BL50: =BO50/4 -> 0 | BM50: =BO50/4 -> 0 | BN50: =BO50-SUM(BK50:BM50) -> 0 | BO50: 0 | BT50: =BO50 -> 0 | BY50: =BT50 -> 0 | CD50: =BY50 -> 0 | CI50: =CD50 -> 0 | CN50: =CI50 -> 0 | CS50: =CN50 -> 0 | CX50: =CS50 -> 0 | DC50: =CX50 -> 0 | DH50: =DC50 -> 0 | DM50: =DH50 -> 0 | DR50: =DM50 -> 0 | DW50: =DR50 -> 0
B51: Collaborative & other R&D revenues | C51: 29.908 | D51: 20.721 | E51: 42.387 | F51: =175.148-E51-D51-C51 -> 82.132 | G51: =SUM(C51:F51) -> 175.148 | H51: 59.014 | I51: =27.229 -> 27.229 | J51: =28.492 -> 28.492 | K51: =36.304 -> 36.304 | L51: =SUM(H51:K51) -> 151.039 | M51: 30.824 | N51: 59.668 | O51: 23.846 | P51: 23.683 | Q51: =SUM(M51:P51) -> 138.021 | R51: 17.839 | S51: 13.147 | T51: 17.123 | U51: 25.46 | V51: =SUM(R51:U51) -> 73.569 | W51: 16.022 | X51: 24.36 | Y51: 15.622 | Z51: =57.122 -> 57.122 | AA51: =SUM(W51:Z51) -> 113.126 | AB51: =67.601 -> 67.601 | AC51: 29.879 | AD51: =231.066 -> 231.066 | AE51: 81.176 | AF51: =SUM(AB51:AE51) -> 409.722 | AG51: 24.381 | AH51: 11.552 | AI51: 6.919 | AJ51: 9.234 | AK51: =SUM(AG51:AJ51) -> 52.086 | AL51: 17.414 | AM51: 6.841 | AN51: 8.035 | AO51: 0 | AP51: =SUM(AL51:AO51) -> 32.29 | AQ51: 4.257 | AR51: 3.087 | AS51: 33.502 | AT51: 10.829 | AU51: =SUM(AQ51:AT51) -> 51.675 | AV51: 0.842 | AW51: 0.611 | AX51: 1.546 | AY51: 5.054 | AZ51: =SUM(AV51:AY51) -> 8.053 | BA51: =IS!W17 -> 0 | BB51: =IS!X17 -> 0.102 | BC51: =IS!Y17 -> 0.216 | BD51: 0 | BE51: =SUM(BA51:BD51) -> 0.318 | BF51: 0 | BG51: 0 | BH51: 0 | BI51: 0 | BJ51: =SUM(BF51:BI51) -> 0 | BK51: 0 | BL51: 0 | BM51: 0 | BN51: 0 | BO51: =SUM(BK51:BN51) -> 0 | BT51: =SUM(BP51:BS51) -> 0 | BY51: =SUM(BU51:BX51) -> 0 | CD51: =SUM(BZ51:CC51) -> 0 | CI51: =SUM(CE51:CH51) -> 0 | CN51: =SUM(CJ51:CM51) -> 0 | CS51: =SUM(CO51:CR51) -> 0 | CX51: =SUM(CT51:CW51) -> 0 | DC51: =SUM(CY51:DB51) -> 0 | DH51: =SUM(DD51:DG51) -> 0 | DM51: =SUM(DI51:DL51) -> 0 | DR51: =SUM(DN51:DQ51) -> 0 | DW51: =SUM(DS51:DV51) -> 0
B52: Total Revenue | C52: =C51+C50+C29+C23+C7 -> 39.087 | D52: =D51+D50+D29+D23+D7 -> 29.726 | E52: =E51+E50+E29+E23+E7 -> 53.289 | F52: =F51+F50+F29+F23+F7 -> 94.254 | G52: =G51+G50+G29+G23+G7 -> 216.356 | H52: =H51+H50+H29+H23+H7 -> 68.81 | I52: =I51+I50+I29+I23+I7 -> 38.196 | J52: =J51+J50+J29+J23+J7 -> 41.014 | ... AP52: =AP51+AP50+AP29+AP23+AP7 -> 1026.527 | AQ52: =AQ51+AQ50+AQ29+AQ23+AQ7+AQ98 -> 118.451 | AR52: =AR51+AR50+AR29+AR23+AR7+AR98 -> 138.421 | AS52: =AS51+AS50+AS29+AS23+AS7+AS98 -> 178.987 | AT52: =AT51+AT50+AT29+AT23+AT7+AT98 -> 144.556 | AU52: =AU51+AU50+AU29+AU23+AU7 -> 580.415 | AV52: =AV51+AV50+AV29+AV23+AV7 -> 138.509 | AW52: =AW51+AW50+AW29+AW23+AW7 -> 166.076 | AX52: =AX51+AX50+AX29+AX23+AX7 -> 304.105 | AY52: =AY51+AY50+AY29+AY23+AY7 -> 411.385 | AZ52: =AZ51+AZ50+AZ29+AZ23+AZ7 -> 1020.104 | BA52: =BA51+BA50+BA29+BA23+BA7 -> 397.155 | BB52: =BB51+BB50+BB29+BB23+BB7 -> 431.524 | ... BE52: =BE51+BE50+BE29+BE23+BE7 -> 1700.64 | BF52: =BF50+BF51+BF49 -> 482.173 | BG52: =BG50+BG51+BG49 -> 516.849 | BH52: =BH51+BH50+BH29+BH23+BH7 -> 551.873 | BI52: =BI51+BI50+BI29+BI23+BI7 -> 622.573 | BJ52: =BJ51+BJ50+BJ29+BJ23+BJ7+BJ43+BJ36+BJ14 -> 2173.468 | BK52: =BK50+BK51+BK49 -> 600 | BL52: =BL50+BL51+BL49 -> 645 | BM52: =BM50+BM51+BM49 -> 695 | BN52: =BN50+BN51+BN49 -> 722.68467 | BO52: =BO51+BO50+BO29+BO23+BO7+BO43+BO36+BO14 -> 2662.6847 | BT52: =BT51+BT50+BT29+BT23+BT7+BT43+BT36+BT14 -> 2929.7892 | BY52: =BY51+BY50+BY29+BY23+BY7+BY43+BY36+BY14 -> 4032.845 | CD52: =CD51+CD50+CD29+CD23+CD7+CD43+CD36+CD14 -> 5352.0546 | CI52: =CI51+CI50+CI29+CI23+CI7+CI43+CI36+CI14 -> 6180.1313 | CN52: =CN51+CN50+CN29+CN23+CN7+CN43+CN36+CN14 -> 6549.5105 | CS52: =CS51+CS50+CS29+CS23+CS7+CS43+CS36+CS14 -> 6707.1044 | CX52: =CX51+CX50+CX29+CX23+CX7+CX43+CX36+CX14 -> 7367.4607 | DC52: =DC51+DC50+DC29+DC23+DC7+DC43+DC36+DC14 -> 8877.466 | DH52: =DH51+DH50+DH29+DH23+DH7+DH43+DH36+DH14 -> 9000.8703 | DM52: =DM51+DM50+DM29+DM23+DM7+DM43+DM36+DM14 -> 9103.7533 | DR52: =DR51+DR50+DR29+DR23+DR7+DR43+DR36+DR14 -> 9114.9124 | DW52: =DW51+DW50+DW29+DW23+DW7+DW43+DW36+DW14 -> 9197.9033
B53: YoY Growth | C53: NM | D53: NM | E53: MN | F53: NM | G53: NM | H53: =IF(C52=0,"NM",H52/C52-1) -> 0.76043186 | I53: =IF(D52=0,"NM",I52/D52-1) -> 0.28493575 | J53: =IF(E52=0,"NM",J52/E52-1) -> -0.23034773 | K53: =IF(F52=0,"NM",K52/F52-1) -> -0.45899378 | L53: =IF(G52=0,"NM",L52/G52-1) -> -0.080164174 | M53: =IF(H52=0,"NM",M52/H52-1) -> -0.39434675 | N53: =IF(I52=0,"NM",N52/I52-1) -> 0.81717981 | O53: =IF(J52=0,"NM",O52/J52-1) -> -0.22931194 | ... BO53: =IF(BJ52=0,"NM",BO52/BJ52-1) -> 0.22508575 | BT53: =IF(BO52=0,"NM",BT52/BO52-1) -> 0.10031398 | BY53: =IF(BT52=0,"NM",BY52/BT52-1) -> 0.37649665 | CD53: =IF(BY52=0,"NM",CD52/BY52-1) -> 0.32711638 | CI53: =IF(CD52=0,"NM",CI52/CD52-1) -> 0.15472127 | CN53: =IF(CI52=0,"NM",CN52/CI52-1) -> 0.059768825 | CS53: =IF(CN52=0,"NM",CS52/CN52-1) -> 0.02406194 | CX53: =IF(CS52=0,"NM",CX52/CS52-1) -> 0.098456233 | DC53: =IF(CX52=0,"NM",DC52/CX52-1) -> 0.204956 | DH53: =IF(DC52=0,"NM",DH52/DC52-1) -> 0.013900854 | DM53: =IF(DH52=0,"NM",DM52/DH52-1) -> 0.011430342 | DR53: =IF(DM52=0,"NM",DR52/DM52-1) -> 0.0012257606 | DW53: =IF(DR52=0,"NM",DW52/DR52-1) -> 0.0091049614

Sheet BS
B2: VERTEX PHARMACEUTICALS INC. (NSDQ:VRTX) | C2: 2013 | D2: 2014 | E2: 2015 | F2: 2016 | G2: 2017 | H2: 2018 | I2: 2019 | J2: 2020 | K2: =J2+1 -> 2021 | L2: =K2+1 -> 2022 | M2: =L2+1 -> 2023 | N2: =M2+1 -> 2024 | O2: =N2+1 -> 2025 | P2: =O2+1 -> 2026 | Q2: =P2+1 -> 2027 | R2: =Q2+1 -> 2028 | ... T2: =S2+1 -> 2030
B4: Cash and ST Investments:
B5: Cash and cash equivalents | C5: 569.299 | D5: 625.259 | E5: 714.768 | F5: 1183.945 | G5: =1665.412 -> 1665.412 | H5: =CF!L47 -> 2294.4419 | I5: =CF!M47 -> 3209.7819 | J5: =CF!N47 -> 4795.044 | K5: =CF!O47 -> 7433.7773 | L5: =CF!P47 -> 10285.117 | M5: =CF!Q47 -> 13432.833 | N5: =CF!R47 -> 16835.866 | O5: =CF!S47 -> 20740.034 | ... T5: =CF!X47 -> 49748.52
B6: Marketable securities, available for sale | C6: 895.777 | D6: 761.847 | E6: 327.694 | F6: 250.612 | G6: 423.254 | H6: =G6-CF!L24-CF!L25-CF!L26-CF!L28 -> 423.254 | I6: =H6-CF!M24-CF!M25-CF!M26-CF!M28 -> 423.254 | J6: =I6-CF!N24-CF!N25-CF!N26-CF!N28 -> 423.254 | K6: =J6-CF!O24-CF!O25-CF!O26-CF!O28 -> 423.254 | L6: =K6-CF!P24-CF!P25-CF!P26-CF!P28 -> 423.254 | M6: =L6-CF!Q24-CF!Q25-CF!Q26-CF!Q28 -> 423.254 | N6: =M6-CF!R24-CF!R25-CF!R26-CF!R28 -> 423.254 | O6: =N6-CF!S24-CF!S25-CF!S26-CF!S28 -> 423.254 | ... T6: =S6-CF!X24-CF!X25-CF!X26-CF!X28 -> 423.254
B7: Accounts receivable, net | C7: 85.517 | D7: 75.964 | E7: 177.639 | F7: 201.083 | G7: 281.343 | H7: =H63 -> 301.01746 | I7: =I63 -> 331.21372 | J7: =J63 -> 455.91457 | K7: =K63 -> 605.05169 | L7: =L63 -> 698.66606 | M7: =M63 -> 740.42451 | N7: =N63 -> 758.24056 | O7: =O63 -> 832.89407 | ... T7: =T63 -> 1039.8263
B8: Inventories | C8: 14.147 | D8: 30.848 | E8: 57.207 | F8: 77.604 | G8: 111.83 | H8: =H67 -> 119.65033 | I8: =I67 -> 131.65293 | J8: =J67 -> 181.21981 | K8: =K67 -> 240.49978 | L8: =L67 -> 277.71022 | M8: =M67 -> 294.30863 | N8: =N67 -> 301.39027 | O8: =O67 -> 331.06402 | ... T8: =T67 -> 413.31674
B9: Prepaid expenses and other current assets | C9: 23.836 | D9: 52.593 | E9: =50.935+78.91 -> 129.845 | F9: =70.534+47.762 -> 118.296 | G9: =165.635+1.489 -> 167.124 | H9: =H65 -> 178.81106 | I9: =I65 -> 196.74831 | J9: =J65 -> 270.82339 | K9: =K65 -> 359.41416 | L9: =L65 -> 415.02318 | M9: =M65 -> 439.82863 | N9: =N65 -> 450.41176 | O9: =O65 -> 494.7576 | ... T9: =T65 -> 617.67993
B10: Total current assets | C10: =SUM(C5:C9) -> 1588.576 | D10: =SUM(D5:D9) -> 1546.511 | E10: =SUM(E5:E9) -> 1407.153 | F10: =SUM(F5:F9) -> 1831.54 | G10: =SUM(G5:G9) -> 2648.963 | H10: =SUM(H5:H9) -> 3317.1747 | I10: =SUM(I5:I9) -> 4292.6508 | J10: =SUM(J5:J9) -> 6126.2557 | ... T10: =SUM(T5:T9) -> 52242.596
B12: Property and equipment, net | C12: 696.911 | D12: 715.812 | E12: 697.715 | F12: 698.362 | G12: 789.437 | H12: =H86 -> 817.36848 | I12: =I86 -> 840.70303 | J12: =J86 -> 879.32287 | K12: =K86 -> 952.92629 | L12: =L86 -> 1050.8871 | M12: =M86 -> 1160.7414 | N12: =N86 -> 1276.6847 | O12: =O86 -> 1412.1743 | ... T12: =T86 -> 2304.0944
B13: Other non-current assets | C13: =2.562+30.992 -> 33.554 | D13: =3.441+29+39.915 -> 72.356 | E13: =284.34+50.384+30+22.083+7.2 -> 394.007 | F13: =284.34+50.384+20.276+0.052+11.833 -> 366.885 | G13: =29+50.384+20.447+7.783 -> 107.614 | H13: =H69 -> 115.1395 | I13: =I69 -> 126.6896 | J13: =J69 -> 174.38781 | K13: =K69 -> 231.43292 | L13: =L69 -> 267.24052 | M13: =M69 -> 283.21317 | N13: =N69 -> 290.02783 | O13: =O69 -> 318.58288 | ... T13: =T69 -> 397.73466
B14: Total Assets | C14: =C10+SUM(C12:C13) -> 2319.041 | D14: =D10+SUM(D12:D13) -> 2334.679 | E14: =E10+SUM(E12:E13) -> 2498.875 | F14: =F10+SUM(F12:F13) -> 2896.787 | G14: =G10+SUM(G12:G13) -> 3546.014 | H14: =H10+SUM(H12:H13) -> 4249.6827 | I14: =I10+SUM(I12:I13) -> 5260.0435 | J14: =J10+SUM(J12:J13) -> 7179.9664 | ... T14: =T10+SUM(T12:T13) -> 54944.426
B16: Current liabilities:
B17: Accounts payable | C17: 49.327 | D17: 71.194 | E17: 74.942 | F17: 61.451 | G17: 73.994 | H17: =H71 -> 83.948417 | I17: =I71 -> 89.375894 | J17: =J71 -> 93.844689 | K17: =K71 -> 97.154955 | L17: =L71 -> 98.454135 | M17: =M71 -> 97.683133 | N17: =N71 -> 94.80426 | O17: =O71 -> 90.797748 | ... T17: =T71 -> 71.552321
B18: Accrued expenses | C18: =271.077+14.286 -> 285.363 | D18: =209.676+33.107 -> 242.783 | E18: =305.82+7.894 -> 313.714 | F18: =315.249+6.047 -> 321.296 | G18: =443.961+2.175 -> 446.136 | H18: =H75 -> 506.1547 | I18: =I75 -> 538.87888 | J18: =J75 -> 565.82283 | K18: =K75 -> 585.78159 | L18: =L75 -> 593.61481 | M18: =M75 -> 588.96616 | N18: =N75 -> 571.60842 | O18: =O75 -> 547.45174 | ... T18: =T75 -> 431.41425
B19: Deferred revenues, current portion | C19: 21.51 | D19: 17.468 | E19: 16.296 | F19: 6.005 | G19: 5.169 | H19: =(G19/(G19+G27))*H73 -> 5.5304707 | I19: =(H19/(H19+H27))*I73 -> 6.0852543 | J19: =(I19/(I19+I27))*J73 -> 8.3763321 | K19: =(J19/(J19+J27))*K73 -> 11.116368 | L19: =(K19/(K19+K27))*L73 -> 12.836306 | M19: =(L19/(L19+L27))*M73 -> 13.603517 | N19: =(M19/(M19+M27))*N73 -> 13.930844 | O19: =(N19/(N19+N27))*O73 -> 15.302422 | ... T19: =(S19/(S19+S27))*T73 -> 19.104303
B20: Capital lease obligations, current portion | C20: 16.893 | D20: 17.806 | E20: 15.545 | F20: 19.426 | G20: 22.531 | H20: =G20 -> 22.531 | I20: =H20 -> 22.531 | J20: =I20 -> 22.531 | K20: =J20 -> 22.531 | L20: =K20 -> 22.531 | M20: =L20 -> 22.531 | N20: =M20 -> 22.531 | O20: =N20 -> 22.531 | ... T20: =S20 -> 22.531
B21: Debt, current portion | C21: 0 | D21: 14.206 | E21: 71.478 | F21: 0 | G21: 0 | H21: 0 | I21: 0 | J21: 0 | K21: 0 | L21: 0 | M21: 0 | N21: 0 | O21: 0 | P21: 0 | Q21: 0 | R21: 0 | S21: 0 | T21: 0
B22: Customer Deposits | F22: 73.416 | G22: 232.401
B23: Credit Facility | F23: 300
B24: Other liabilities, current portion | C24: 24.736 | D24: 4.797 | E24: 14.374 | F24: 10.943 | G24: 27.029 | H24: =(G24/(G24+G31))*H77 -> 30.665213 | I24: =(H24/(H24+H31))*I77 -> 32.647796 | J24: =(I24/(I24+I31))*J77 -> 34.280186 | K24: =(J24/(J24+J31))*K77 -> 35.489381 | L24: =(K24/(K24+K31))*L77 -> 35.963954 | M24: =(L24/(L24+L31))*M77 -> 35.682317 | N24: =(M24/(M24+M31))*N77 -> 34.630704 | O24: =(N24/(N24+N31))*O77 -> 33.16718 | ... T24: =(S24/(S24+S31))*T77 -> 26.137088
B25: Total current liabilities | C25: =SUM(C17:C24) -> 397.829 | D25: =SUM(D17:D24) -> 368.254 | E25: =SUM(E17:E24) -> 506.349 | F25: =SUM(F17:F24) -> 792.537 | G25: =SUM(G17:G24) -> 807.26 | H25: =SUM(H17:H24) -> 648.8298 | I25: =SUM(I17:I24) -> 689.51883 | J25: =SUM(J17:J24) -> 724.85503 | ... T25: =SUM(T17:T24) -> 570.73897
B27: Deferred revenue, excluding current portion | C27: 49.459 | D27: 27.808 | E27: 9.714 | F27: 6.632 | G27: 1.726 | H27: =H73-H19 -> 1.8467 | I27: =I73-I19 -> 2.0319499 | J27: =J73-J19 -> 2.7969722 | K27: =K73-K19 -> 3.7119076 | L27: =L73-L19 -> 4.2862187 | M27: =M73-M19 -> 4.5424009 | N27: =N73-N19 -> 4.6516999 | O27: =O73-O19 -> 5.1096888 | ... T27: =T73-T19 -> 6.3791888
B28: Accrued restructuring expense, excluding current portion | C28: 14.067 | D28: 12.748 | E28: 7.464 | F28: 1.907 | G28: 0 | H28: =G28 -> 0 | I28: =H28 -> 0 | J28: =I28 -> 0 | K28: =J28 -> 0 | L28: =K28 -> 0 | M28: =L28 -> 0 | N28: =M28 -> 0 | O28: =N28 -> 0 | ... T28: =S28 -> 0
B29: Capital lease obligations, excluding current portion | C29: 48.754 | D29: 39.293 | E29: 42.923 | F29: 34.976 | G29: 20.496 | H29: =G29 -> 20.496 | I29: =H29 -> 20.496 | J29: =I29 -> 20.496 | K29: =J29 -> 20.496 | L29: =K29 -> 20.496 | M29: =L29 -> 20.496 | N29: =M29 -> 20.496 | O29: =N29 -> 20.496 | ... T29: =S29 -> 20.496
B30: Long-term debt | C30: 0 | D30: 280.569 | E30: 223.969 | F30: 0 | G30: 0 | H30: 0 | I30: 0 | J30: 0 | K30: 0 | L30: 0 | M30: 0 | N30: 0 | O30: 0 | P30: 0 | Q30: 0 | R30: 0 | S30: 0 | T30: 0
B31: Other liabilitites | C31: =11.59+440.937 -> 452.527 | D31: =21.707+473.073+15.044 -> 509.824 | E31: =31.778+472.611+110.439 -> 614.828 | F31: =102.122+486.359+134.063 -> 722.544 | G31: =6.341+563.406+78.431+26.048 -> 674.226 | H31: =H77-H24 -> 764.92967 | I31: =I77-I24 -> 814.3843 | J31: =J77-J24 -> 855.10351 | K31: =K77-K24 -> 885.26633 | L31: =L77-L24 -> 897.10433 | M31: =M77-M24 -> 890.07903 | N31: =N77-N24 -> 863.84703 | O31: =O77-O24 -> 827.34009 | ... T31: =T77-T24 -> 651.97766
B32: Total liabilities | C32: =SUM(C25,C27:C31) -> 962.636 | D32: =SUM(D25,D27:D31) -> 1238.496 | E32: =SUM(E25,E27:E31) -> 1405.247 | F32: =SUM(F25,F27:F31) -> 1558.596 | G32: =SUM(G25,G27:G31) -> 1503.708 | H32: =SUM(H25,H27:H31) -> 1436.1022 | I32: =SUM(I25,I27:I31) -> 1526.4311 | J32: =SUM(J25,J27:J31) -> 1603.2515 | ... T32: =SUM(T25,T27:T31) -> 1249.5918
B34: Stockholders’ equity:
B35: Common stock | C35: 2.32 | D35: 2.385 | E35: 2.427 | F35: 2.45 | G35: 2.512 | H35: =G35 -> 2.512 | I35: =H35 -> 2.512 | J35: =I35 -> 2.512 | K35: =J35 -> 2.512 | L35: =K35 -> 2.512 | M35: =L35 -> 2.512 | N35: =M35 -> 2.512 | O35: =N35 -> 2.512 | ... T35: =S35 -> 2.512
B36: Additional paid-in capital | C36: 5321.286 | D36: 5777.154 | E36: 6197.5 | F36: 6506.795 | G36: 7157.362 | H36: =G36+CF!L82 -> 7406.2688 | I36: =H36+CF!M82 -> 7654.2966 | J36: =I36+CF!N82 -> 7901.6431 | K36: =J36+CF!O82 -> 8148.4616 | L36: =K36+CF!P82 -> 8394.871 | M36: =L36+CF!Q82 -> 8640.9633 | N36: =M36+CF!R82 -> 8886.8098 | O36: =N36+CF!S82 -> 9132.4658 | ... T36: =S36+CF!X82 -> 10359.094
B37: Accumulated other comprehensive income(loss) | C37: -0.306 | D37: 0.917 | E37: 1.824 | F37: 21.173 | G37: -11.572 | H37: =G37 -> -11.572 | I37: =H37 -> -11.572 | J37: =I37 -> -11.572 | K37: =J37 -> -11.572 | L37: =K37 -> -11.572 | M37: =L37 -> -11.572 | N37: =M37 -> -11.572 | O37: =N37 -> -11.572 | ... T37: =S37 -> -11.572
B38: Retained earnings (accumulated deficit) | C38: -3966.895 | D38: -4705.45 | E38: -5261.784 | F38: -5373.836 | G38: -5119.723 | H38: =G38+CF!L5 -> -4597.3553 | I38: =H38+CF!M5 -> -3925.3512 | J38: =I38+CF!N5 -> -2329.5952 | K38: =J38+CF!O5 -> 431.67999 | L38: =K38+CF!P5 -> 3333.0732 | M38: =L38+CF!Q5 -> 6455.3897 | N38: =M38+CF!R5 -> 9817.8984 | O38: =N38+CF!S5 -> 13853.432 | ... T38: =S38+CF!X5 -> 43331.073
B39: Total stockholders’ equity | C39: =SUM(C35:C38) -> 1356.405 | D39: =SUM(D35:D38) -> 1075.006 | E39: =SUM(E35:E38) -> 939.967 | F39: =SUM(F35:F38) -> 1156.582 | G39: =SUM(G35:G38) -> 2028.579 | H39: =SUM(H35:H38) -> 2799.8535 | I39: =SUM(I35:I38) -> 3719.8854 | J39: =SUM(J35:J38) -> 5562.9879 | ... T39: =SUM(T35:T38) -> 53681.107
B40: Noncontrolling interest | C40: 0 | D40: 21.177 | E40: 153.661 | F40: 181.609 | G40: 13.727 | H40: =G40 -> 13.727 | I40: =H40 -> 13.727 | J40: =I40 -> 13.727 | K40: =J40 -> 13.727 | L40: =K40 -> 13.727 | M40: =L40 -> 13.727 | N40: =M40 -> 13.727 | O40: =N40 -> 13.727 | ... T40: =S40 -> 13.727
B41: Total Liabilities and Stockholders’ Equity | C41: =C32+C39+C40 -> 2319.041 | D41: =D32+D39+D40 -> 2334.679 | E41: =E32+E39+E40 -> 2498.875 | F41: =F32+F39+F40 -> 2896.787 | G41: =G32+G39+G40 -> 3546.014 | H41: =H32+H39+H40 -> 4249.6827 | I41: =I32+I39+I40 -> 5260.0435 | J41: =J32+J39+J40 -> 7179.9664 | ... T41: =T32+T39+T40 -> 54944.426
Z42: `
B43: Check | C43: =C41-C14 -> 0 | D43: =D41-D14 -> 0 | E43: =E41-E14 -> 0 | F43: =F41-F14 -> 0 | G43: =G41-G14 -> 0 | H43: =H41-H14 -> 0 | I43: =I41-I14 -> 0 | J43: =J41-J14 -> 0 | ... T43: =T41-T14 -> 0
F44: =F43-E43 -> 0 | G44: =G43-F43 -> 0 | H44: =H43-G43 -> 0 | I44: =I43-H43 -> 0 | J44: =J43-I43 -> 0 | K44: =K43-J43 -> 0 | L44: =L43-K43 -> 0 | M44: =M43-L43 -> 0 | ... T44: =T43-S43 -> 0
B46: Key Numbers
B47: Revenues | C47: =IS!L81 -> 1211.975 | D47: =IS!Q81 -> 580.415 | E47: =IS!V81 -> 1032.336 | F47: =IS!AA81 -> 1700.801 | G47: =IS!AF81 -> 2488.652 | H47: =IS!AK81 -> 2662.6847 | I47: =IS!AP81 -> 2929.7892 | J47: =IS!AU81 -> 4032.845 | K47: =IS!AZ81 -> 5352.0546 | L47: =IS!BE81 -> 6180.1313 | M47: =IS!BJ81 -> 6549.5105 | N47: =IS!BO81 -> 6707.1044 | O47: =IS!BT81 -> 7367.4607 | P47: =IS!BY81 -> 8877.466 | Q47: =IS!CD81 -> 9000.8703 | R47: =IS!CI81 -> 9103.7533 | S47: =IS!CN81 -> 9114.9124 | T47: =IS!CS81 -> 9197.9033
B48: COGS | C48: =IS!L98 -> 130.277 | D48: =IS!Q98 -> 60.987 | E48: =IS!V98 -> 124.512 | F48: =IS!AA98 -> 210.46 | G48: =IS!AF98 -> 275.119 | H48: =IS!AK98 -> 320.94964 | I48: =IS!AP98 -> 354.09854 | J48: =IS!AU98 -> 466.44801 | K48: =IS!AZ98 -> 585.35894 | L48: =IS!BE98 -> 652.17576 | M48: =IS!BJ98 -> 665.53142 | N48: =IS!BO98 -> 650.93668 | O48: =IS!BT98 -> 628.91172 | P48: =IS!BY98 -> 726.81424 | Q48: =IS!CD98 -> 740.2834 | R48: =IS!CI98 -> 721.35077 | S48: =IS!CN98 -> 723.58173 | T48: =IS!CS98 -> 723.42132
B49: Operating expenses | C49: =IS!L101+IS!L102+IS!L104 -> 1691.706 | D49: =IS!M101+IS!M102+IS!M104 -> 319.363 | E49: =IS!V27+IS!V31+IS!V35 -> 1059.095 | F49: =IS!AA27+IS!AA31+IS!AA35 -> 1202.178 | G49: =IS!AF27+IS!AF31+IS!AF35 -> 1334.797 | H49: =IS!AK27+IS!AK31+IS!AK35 -> 1514.3673 | I49: =IS!AP27+IS!AP31+IS!AP35 -> 1612.275 | J49: =IS!AU27+IS!AU31+IS!AU35 -> 1692.8887 | K49: =IS!AZ27+IS!AZ31+IS!AZ35 -> 1752.6035 | L49: =IS!BE27+IS!BE31+IS!BE35 -> 1776.0397 | M49: =IS!BJ27+IS!BJ31+IS!BJ35 -> 1762.1314 | N49: =IS!BO27+IS!BO31+IS!BO35 -> 1710.1987 | O49: =IS!BT27+IS!BT31+IS!BT35 -> 1637.9242 | P49: =IS!BY27+IS!BY31+IS!BY35 -> 1560.9047 | Q49: =IS!CD27+IS!CD31+IS!CD35 -> 1489.2767 | R49: =IS!CI27+IS!CI31+IS!CI35 -> 1422.6626 | S49: =IS!CN27+IS!CN31+IS!CN35 -> 1360.7114 | T49: =IS!CS27+IS!CS31+IS!CS35 -> 1290.7509
B50: Taxes | C50: =IS!L113 -> -122.422 | D50: =IS!Q113 -> 6.958 | E50: =IS!V113 -> 30.381 | F50: =IS!AA113 -> 16.665 | G50: =IS!AF113 -> -107.324 | H50: =IS!AK113 -> 0 | I50: =IS!AP113 -> 0 | J50: =IS!AU113 -> 0 | K50: =IS!AZ113 -> 0 | L50: =IS!BE113 -> 643.73552 | M50: =IS!BJ113 -> 855.15675 | N50: =IS!BO113 -> 920.94188 | O50: =IS!BT113 -> 1105.2735 | P50: =IS!BY113 -> 1453.598 | Q50: =IS!CD113 -> 1530.3653 | R50: =IS!CI113 -> 1617.7144 | S50: =IS!CN113 -> 1687.8522 | T50: =IS!CS113 -> 1783.9641
B51: NI | C51: =IS!L122 -> -445.028 | D51: =IS!Q122 -> -738.555 | E51: =IS!V122 -> -556.334 | F51: =IS!AA122 -> -112.052 | G51: =IS!AF122 -> 263.484 | H51: =IS!AK122 -> 522.36771 | I51: =IS!AP122 -> 672.00412 | J51: =IS!AU122 -> 1595.756 | K51: =IS!AZ122 -> 2761.2752 | L51: =IS!BE122 -> 2901.3932 | M51: =IS!BJ122 -> 3122.3165 | N51: =IS!BO122 -> 3362.5087 | O51: =IS!BT122 -> 4035.5336 | P51: =IS!BY122 -> 5307.3229 | Q51: =IS!CD122 -> 5587.613 | R51: =IS!CI122 -> 5906.5387 | S51: =IS!CN122 -> 6162.623 | T51: =IS!CS122 -> 6513.5433
B52: Operating CF | C52: =CF!G20 -> -51.57 | D52: =CF!H20 -> -513.199 | E52: =CF!I20 -> -365.432 | F52: =CF!J20 -> 236.103 | G52: =CF!K20 -> 844.942 | H52: =CF!L20 -> 718.18319 | I52: =CF!M20 -> 1002.9885 | J52: =CF!N20 -> 1691.5997 | ... T52: =CF!X20 -> 6728.0242
B53: Capex | C53: =CF!G27 -> -51.393 | D53: =CF!H27 -> -51.201 | E53: =CF!I27 -> -45.302 | F53: =CF!J27 -> -56.563 | G53: =CF!K27 -> -99.421 | H53: =CF!L27 -> -93.060137 | I53: =CF!M27 -> -90.676213 | J53: =CF!N27 -> -108.68412 | ... T53: =CF!X27 -> -211.08949
B56: Operating Activity
B57: AR Turnover (Total Sales / AR) | C57: =IF(ISERROR(C47/C7),"NM",C47/C7) -> 14.172328 | D57: =IF(ISERROR(D47/D7),"NM",D47/D7) -> 7.6406587 | E57: =IF(ISERROR(E47/E7),"NM",E47/E7) -> 5.8114265 | F57: =IF(ISERROR(F47/F7),"NM",F47/F7) -> 8.4582038 | G57: =IF(ISERROR(G47/G7),"NM",G47/G7) -> 8.8456155 | H57: =IF(ISERROR(H47/H7),"NM",H47/H7) -> 8.8456155 | I57: =IF(ISERROR(I47/I7),"NM",I47/I7) -> 8.8456155 | J57: =IF(ISERROR(J47/J7),"NM",J47/J7) -> 8.8456155 | ... T57: =IF(ISERROR(T47/T7),"NM",T47/T7) -> 8.8456155
B58: Inventory Turnover (COGS / Inv) | C58: =IF(ISERROR(C48/C8),"NM",C48/C8) -> 9.2088075 | D58: =IF(ISERROR(D48/D8),"NM",D48/D8) -> 1.9770163 | E58: =IF(ISERROR(E48/E8),"NM",E48/E8) -> 2.1765169 | F58: =IF(ISERROR(F48/F8),"NM",F48/F8) -> 2.7119736 | G58: =IF(ISERROR(G48/G8),"NM",G48/G8) -> 2.4601538 | H58: =IF(ISERROR(H48/H8),"NM",H48/H8) -> 2.6823967 | I58: =IF(ISERROR(I48/I8),"NM",I48/I8) -> 2.6896366 | J58: =IF(ISERROR(J48/J8),"NM",J48/J8) -> 2.573935 | ... T58: =IF(ISERROR(T48/T8),"NM",T48/T8) -> 1.7502831
B59: AP & Accrued Liabilities Turnover (COGS / AP & Accrued Liabilities) | C59: =IF(ISERROR(C48/(C17+C18)),"NM",C48/(C17+C18)) -> 0.38924677 | D59: =IF(ISERROR(D48/(D17+D18)),"NM",D48/(D17+D18)) -> 0.19424034 | E59: =IF(ISERROR(E48/(E17+E18)),"NM",E48/(E17+E18)) -> 0.32036557 | F59: =IF(ISERROR(F48/(F17+F18)),"NM",F48/(F17+F18)) -> 0.54986714 | G59: =IF(ISERROR(G48/(G17+G18)),"NM",G48/(G17+G18)) -> 0.52894276 | H59: =IF(ISERROR(H48/(H17+H18)),"NM",H48/(H17+H18)) -> 0.54388738 | I59: =IF(ISERROR(I48/(I17+I18)),"NM",I48/(I17+I18)) -> 0.56362251 | J59: =IF(ISERROR(J48/(J17+J18)),"NM",J48/(J17+J18)) -> 0.70709562 | ... T59: =IF(ISERROR(T48/(T17+T18)),"NM",T48/(T17+T18)) -> 1.4383089
B60: Days Sales Outstanding | C60: =IF(ISERROR(366/C57), "NM", (366/C57)) -> 25.824973 | D60: =IF(ISERROR(366/D57), "NM", (366/D57)) -> 47.901629 | E60: =IF(ISERROR(366/E57), "NM", (366/E57)) -> 62.979373 | F60: =IF(ISERROR(366/F57), "NM", (366/F57)) -> 43.271598 | G60: =IF(ISERROR(366/G57), "NM", (366/G57)) -> 41.376431 | H60: =IF(ISERROR(366/H57), "NM", (366/H57)) -> 41.376431 | I60: =IF(ISERROR(366/I57), "NM", (366/I57)) -> 41.376431 | J60: =IF(ISERROR(366/J57), "NM", (366/J57)) -> 41.376431 | ... T60: =IF(ISERROR(366/T57), "NM", (366/T57)) -> 41.376431
B61: Days inventory outstanding | C61: =IF(ISERROR(366/C58), "NM", (366/C58)) -> 39.74456 | D61: =IF(ISERROR(366/D58), "NM", (366/D58)) -> 185.12745 | E61: =IF(ISERROR(366/E58), "NM", (366/E58)) -> 168.15859 | F61: =IF(ISERROR(366/F58), "NM", (366/F58)) -> 134.95707 | G61: =IF(ISERROR(366/G58), "NM", (366/G58)) -> 148.77119 | H61: =IF(ISERROR(366/H58), "NM", (366/H58)) -> 136.44514 | I61: =IF(ISERROR(366/I58), "NM", (366/I58)) -> 136.07786 | J61: =IF(ISERROR(366/J58), "NM", (366/J58)) -> 142.19474 | ... T61: =IF(ISERROR(366/T58), "NM", (366/T58)) -> 209.10902
B62: Days payable outstanding | C62: =IF(ISERROR(366/C59), "NM", (366/C59)) -> 940.27756 | D62: =IF(ISERROR(365/D59), "NM", (365/D59)) -> 1879.1153 | E62: =IF(ISERROR(365/E59), "NM", (365/E59)) -> 1139.3234 | F62: =IF(ISERROR(365/F59), "NM", (365/F59)) -> 663.79671 | G62: =IF(ISERROR(365/G59), "NM", (365/G59)) -> 690.05576 | H62: =IF(ISERROR(365/H59), "NM", (365/H59)) -> 671.09481 | I62: =IF(ISERROR(365/I59), "NM", (365/I59)) -> 647.59656 | J62: =IF(ISERROR(365/J59), "NM", (365/J59)) -> 516.19609 | K62: =IF(ISERROR(365/K59), "NM", (365/K59)) -> 425.84443 | ... T62: =IF(ISERROR(365/T59), "NM", (365/T59)) -> 253.77024
B63: Accounts receivable | C63: =C7 -> 85.517 | D63: =D7 -> 75.964 | E63: =E7 -> 177.639 | F63: =F7 -> 201.083 | G63: =G7 -> 281.343 | H63: =H64*H47 -> 301.01746 | I63: =I64*I47 -> 331.21372 | J63: =J64*J47 -> 455.91457 | K63: =K64*K47 -> 605.05169 | L63: =L64*L47 -> 698.66606 | M63: =M64*M47 -> 740.42451 | N63: =N64*N47 -> 758.24056 | O63: =O64*O47 -> 832.89407 | ... T63: =T64*T47 -> 1039.8263
B64: % of revenue | C64: =C63/C47 -> 0.070560036 | D64: =D63/D47 -> 0.13087877 | E64: =E63/E47 -> 0.17207479 | F64: =F63/F47 -> 0.11822841 | G64: =G63/G47 -> 0.11305036 | H64: =G64 -> 0.11305036 | I64: =H64 -> 0.11305036 | J64: =I64 -> 0.11305036 | K64: =J64 -> 0.11305036 | L64: =K64 -> 0.11305036 | M64: =L64 -> 0.11305036 | N64: =M64 -> 0.11305036 | O64: =N64 -> 0.11305036 | ... T64: =S64 -> 0.11305036
B65: Prepaid expenses and other current assets | C65: =C9 -> 23.836 | D65: =D9 -> 52.593 | E65: =E9 -> 129.845 | F65: =F9 -> 118.296 | G65: =G9 -> 167.124 | H65: =H47*H66 -> 178.81106 | I65: =I47*I66 -> 196.74831 | J65: =J47*J66 -> 270.82339 | K65: =K47*K66 -> 359.41416 | L65: =L47*L66 -> 415.02318 | M65: =M47*M66 -> 439.82863 | N65: =N47*N66 -> 450.41176 | O65: =O47*O66 -> 494.7576 | ... T65: =T47*T66 -> 617.67993
B66: % of revenue | C66: =C65/C47 -> 0.019667072 | D66: =D65/D47 -> 0.090612751 | E66: =E65/E47 -> 0.12577785 | F66: =F65/F47 -> 0.069553111 | G66: =G65/G47 -> 0.067154427 | H66: =G66 -> 0.067154427 | I66: =H66 -> 0.067154427 | J66: =I66 -> 0.067154427 | K66: =J66 -> 0.067154427 | L66: =K66 -> 0.067154427 | M66: =L66 -> 0.067154427 | N66: =M66 -> 0.067154427 | O66: =N66 -> 0.067154427 | ... T66: =S66 -> 0.067154427
B67: Inventories | C67: =C8 -> 14.147 | D67: =D8 -> 30.848 | E67: =E8 -> 57.207 | F67: =F8 -> 77.604 | G67: =G8 -> 111.83 | H67: =H47*H68 -> 119.65033 | I67: =I47*I68 -> 131.65293 | J67: =J47*J68 -> 181.21981 | K67: =K47*K68 -> 240.49978 | L67: =L47*L68 -> 277.71022 | M67: =M47*M68 -> 294.30863 | N67: =N47*N68 -> 301.39027 | O67: =O47*O68 -> 331.06402 | ... T67: =T47*T68 -> 413.31674
B68: % of revenue | C68: =C67/C47 -> 0.011672683 | D68: =D67/D47 -> 0.053148178 | E68: =E67/E47 -> 0.055415097 | F68: =F67/F47 -> 0.045627913 | G68: =G67/G47 -> 0.044935973 | H68: =G68 -> 0.044935973 | I68: =H68 -> 0.044935973 | J68: =I68 -> 0.044935973 | K68: =J68 -> 0.044935973 | L68: =K68 -> 0.044935973 | M68: =L68 -> 0.044935973 | N68: =M68 -> 0.044935973 | O68: =N68 -> 0.044935973 | ... T68: =S68 -> 0.044935973
B69: Other non-current assets | C69: =C13 -> 33.554 | D69: =D13 -> 72.356 | E69: =E13 -> 394.007 | F69: =F13 -> 366.885 | G69: =G13 -> 107.614 | H69: =H47*H70 -> 115.1395 | I69: =I47*I70 -> 126.6896 | J69: =J47*J70 -> 174.38781 | K69: =K47*K70 -> 231.43292 | L69: =L47*L70 -> 267.24052 | M69: =M47*M70 -> 283.21317 | N69: =N47*N70 -> 290.02783 | O69: =O47*O70 -> 318.58288 | ... T69: =T47*T70 -> 397.73466
B70: % of revenue | C70: =C69/C47 -> 0.02768539 | D70: =D69/D47 -> 0.12466253 | E70: =E69/E47 -> 0.38166547 | F70: =F69/F47 -> 0.21571307 | G70: =G69/G47 -> 0.043241884 | H70: =G70 -> 0.043241884 | I70: =H70 -> 0.043241884 | J70: =I70 -> 0.043241884 | K70: =J70 -> 0.043241884 | L70: =K70 -> 0.043241884 | M70: =L70 -> 0.043241884 | N70: =M70 -> 0.043241884 | O70: =N70 -> 0.043241884 | ... T70: =S70 -> 0.043241884
B71: Accounts payable | C71: =C17 -> 49.327 | D71: =D17 -> 71.194 | E71: =E17 -> 74.942 | F71: =F17 -> 61.451 | G71: =G17 -> 73.994 | H71: =H49*H72 -> 83.948417 | I71: =I49*I72 -> 89.375894 | J71: =J49*J72 -> 93.844689 | K71: =K49*K72 -> 97.154955 | L71: =L49*L72 -> 98.454135 | M71: =M49*M72 -> 97.683133 | N71: =N49*N72 -> 94.80426 | O71: =O49*O72 -> 90.797748 | ... T71: =T49*T72 -> 71.552321
B72: % operating expenses | C72: =C71/C49 -> 0.02915814 | D72: =D71/D49 -> 0.22292501 | E72: =E71/E49 -> 0.070760413 | F72: =F71/F49 -> 0.05111639 | G72: =G71/G49 -> 0.055434647 | H72: =G72 -> 0.055434647 | I72: =H72 -> 0.055434647 | J72: =I72 -> 0.055434647 | K72: =J72 -> 0.055434647 | L72: =K72 -> 0.055434647 | M72: =L72 -> 0.055434647 | N72: =M72 -> 0.055434647 | O72: =N72 -> 0.055434647 | ... T72: =S72 -> 0.055434647
B73: Deferred revenue | C73: =C27+C19 -> 70.969 | D73: =D27+D19 -> 45.276 | E73: =E27+E19 -> 26.01 | F73: =F27+F19 -> 12.637 | G73: =G27+G19 -> 6.895 | H73: =H47*H74 -> 7.3771708 | I73: =I47*I74 -> 8.1172041 | J73: =J47*J74 -> 11.173304 | K73: =K47*K74 -> 14.828275 | L73: =L47*L74 -> 17.122525 | M73: =M47*M74 -> 18.145918 | N73: =N47*N74 -> 18.582544 | O73: =O47*O74 -> 20.412111 | ... T73: =T47*T74 -> 25.483492
B74: % of revenue | C74: =C73/C47 -> 0.058556488 | D74: =D73/D47 -> 0.078006254 | E74: =E73/E47 -> 0.025195285 | F74: =F73/F47 -> 0.0074300286 | G74: =G73/G47 -> 0.0027705762 | H74: =G74 -> 0.0027705762 | I74: =H74 -> 0.0027705762 | J74: =I74 -> 0.0027705762 | K74: =J74 -> 0.0027705762 | L74: =K74 -> 0.0027705762 | M74: =L74 -> 0.0027705762 | N74: =M74 -> 0.0027705762 | O74: =N74 -> 0.0027705762 | ... T74: =S74 -> 0.0027705762
B75: Accrued expenses | C75: =C18 -> 285.363 | D75: =D18 -> 242.783 | E75: =E18 -> 313.714 | F75: =F18 -> 321.296 | G75: =G18 -> 446.136 | H75: =H49*H76 -> 506.1547 | I75: =I49*I76 -> 538.87888 | J75: =J49*J76 -> 565.82283 | K75: =K49*K76 -> 585.78159 | L75: =L49*L76 -> 593.61481 | M75: =M49*M76 -> 588.96616 | N75: =N49*N76 -> 571.60842 | O75: =O49*O76 -> 547.45174 | ... T75: =T49*T76 -> 431.41425
B76: % operating expenses | C76: =C75/C49 -> 0.16868357 | D76: =D75/D49 -> 0.76021017 | E76: =E75/E49 -> 0.2962095 | F76: =F75/F49 -> 0.26726159 | G76: =G75/G49 -> 0.33423509 | H76: =G76 -> 0.33423509 | I76: =H76 -> 0.33423509 | J76: =I76 -> 0.33423509 | K76: =J76 -> 0.33423509 | L76: =K76 -> 0.33423509 | M76: =L76 -> 0.33423509 | N76: =M76 -> 0.33423509 | O76: =N76 -> 0.33423509 | ... T76: =S76 -> 0.33423509
B77: Other liabilities | C77: =C31+C24 -> 477.263 | D77: =D31+D24 -> 514.621 | E77: =E31+E24 -> 629.202 | F77: =F31+F24 -> 733.487 | G77: =G31+G24 -> 701.255 | H77: =H49*H78 -> 795.59488 | I77: =I49*I78 -> 847.0321 | J77: =J49*J78 -> 889.3837 | K77: =K49*K78 -> 920.75571 | L77: =L49*L78 -> 933.06828 | M77: =M49*M78 -> 925.76135 | N77: =N49*N78 -> 898.47773 | O77: =O49*O78 -> 860.50727 | ... T77: =T49*T78 -> 678.11475
B78: % operating expenses | C78: =C77/C49 -> 0.28211935 | D78: =D77/D49 -> 1.6113983 | E78: =E77/E49 -> 0.59409401 | F78: =F77/F49 -> 0.61013178 | G78: =G77/G49 -> 0.52536453 | H78: =G78 -> 0.52536453 | I78: =H78 -> 0.52536453 | J78: =I78 -> 0.52536453 | K78: =J78 -> 0.52536453 | L78: =K78 -> 0.52536453 | M78: =L78 -> 0.52536453 | N78: =M78 -> 0.52536453 | O78: =N78 -> 0.52536453 | ... T78: =S78 -> 0.52536453
B80: Property and Equipment, Net
B81: Beginning balance | C81: 433.609 | D81: =C86 -> 696.911 | E81: =D86 -> 715.812 | F81: =E86 -> 697.715 | G81: =F86 -> 698.362 | H81: =G86 -> 789.437 | I81: =H86 -> 817.36848 | J81: =I86 -> 840.70303 | K81: =J86 -> 879.32287 | ... T81: =S86 -> 2148.5455
B82: Capital expenditures, net | C82: =-BS!C53 -> 51.393 | D82: =-BS!D53 -> 51.201 | E82: =-BS!E53 -> 45.302 | F82: =-BS!F53 -> 56.563 | G82: =-BS!G53 -> 99.421 | H82: =H83*H47 -> 93.060137 | I82: =I83*I47 -> 90.676213 | J82: =J83*J47 -> 108.68412 | K82: =K83*K47 -> 144.23648 | L82: =L83*L47 -> 166.55293 | M82: =M83*M47 -> 176.5076 | N82: =N83*N47 -> 180.75472 | O82: =O83*O47 -> 198.55115 | ... T82: =T83*T47 -> 211.08949
B83: % of revenue | C83: =C82/C47 -> 0.04240434 | D83: =D82/D47 -> 0.088214467 | E83: =E82/E47 -> 0.043882999 | F83: =F82/F47 -> 0.033256683 | G83: =G82/G47 -> 0.03994974 | H83: =G83-0.005 -> 0.03494974 | I83: =H83-0.004 -> 0.03094974 | J83: =I83-0.004 -> 0.02694974 | K83: =J83 -> 0.02694974 | L83: =K83 -> 0.02694974 | M83: =L83 -> 0.02694974 | N83: =M83 -> 0.02694974 | O83: =N83 -> 0.02694974 | P83: =O83 -> 0.02694974 | Q83: =P83 -> 0.02694974 | R83: =Q83 -> 0.02694974 | S83: =R83 -> 0.02694974 | T83: =S83-0.004 -> 0.02294974
B84: Depreciation | C84: =-CF!G8 -> -47.3 | D84: =-CF!H8 -> -62.3 | E84: =-CF!I7 -> -62.343 | F84: =-CF!J7 -> -61.398 | G84: =-CF!K7 -> -62.822322 | H84: =-CF!L7 -> -65.128658 | I84: =-CF!M7 -> -67.341659 | J84: =-CF!N7 -> -70.06428 | K84: =-CF!O7 -> -70.633066 | L84: =-CF!P7 -> -68.592163 | ... T84: =-CF!X7 -> -55.54057
B85: Others | C85: =C86-C81-C82-C84 -> 259.209 | D85: =D86-D81-D82-D84 -> 30 | E85: =E86-E81-E82-E84 -> -1.056 | F85: =F86-F81-F82-F84 -> 5.482 | G85: =G86-G81-G82-G84 -> 54.476322 | H85: 0 | I85: 0 | J85: 0 | K85: 0 | L85: 0 | M85: 0 | N85: 0 | O85: 0 | P85: 0 | Q85: 0 | R85: 0 | S85: 0 | T85: 0
B86: Ending Balance | C86: =C12 -> 696.911 | D86: =D12 -> 715.812 | E86: =E12 -> 697.715 | F86: =F12 -> 698.362 | G86: =G12 -> 789.437 | H86: =H81+H82+H84+H85 -> 817.36848 | I86: =I81+I82+I84+I85 -> 840.70303 | J86: =J81+J82+J84+J85 -> 879.32287 | K86: =K81+K82+K84+K85 -> 952.92629 | L86: =L81+L82+L84+L85 -> 1050.8871 | M86: =M81+M82+M84+M85 -> 1160.7414 | N86: =N81+N82+N84+N85 -> 1276.6847 | O86: =O81+O82+O84+O85 -> 1412.1743 | ... T86: =T81+T82+T84+T85 -> 2304.0944
B88: Depreciation & Amortization | C88: 20
B90: Existing PP&E | C90: =C109-SUM(C91:C98) -> 46.015175 | D90: =D109-SUM(D91:D98) -> 58.450325 | E90: =D90-D90*(1/$C$88) -> 55.527809 | F90: =E90-E90*(1/$C$88) -> 52.751418 | G90: =F90-F90*(1/$C$88) -> 50.113847 | H90: =G90-G90*(1/$C$88) -> 47.608155 | I90: =H90-H90*(1/$C$88) -> 45.227747 | J90: =I90-I90*(1/$C$88) -> 42.96636 | K90: =J90-J90*(1/$C$88) -> 40.818042 | L90: =K90-K90*(1/$C$88) -> 38.77714 | ... T90: =S90-S90*(1/$C$88) -> 25.725547
B91: 2013 capital expenditures | C91: =C$82/$C$88/2 -> 1.284825 | D91: =MAX(0,MIN($C$91*2,D$82-SUM($C91:C91))) -> 2.56965 | E91: =MAX(0,MIN($C$91*2,E$82-SUM($C91:D91))) -> 2.56965 | F91: =MAX(0,MIN($C$91*2,F$82-SUM($C91:E91))) -> 2.56965 | G91: =MAX(0,MIN($C$91*2,G$82-SUM($C91:F91))) -> 2.56965 | H91: =MAX(0,MIN($C$91*2,H$82-SUM($C91:G91))) -> 2.56965 | I91: =MAX(0,MIN($C$91*2,I$82-SUM($C91:H91))) -> 2.56965 | J91: =MAX(0,MIN($C$91*2,J$82-SUM($C91:I91))) -> 2.56965 | K91: =MAX(0,MIN($C$91*2,K$82-SUM($C91:J91))) -> 2.56965 | ... T91: =MAX(0,MIN($C$91*2,T$82-SUM($C91:S91))) -> 2.56965
B92: 2014 capital expenditures | D92: =D$82/$C$88/2 -> 1.280025 | E92: =MAX(0,MIN($D$92*2,E$82-SUM($D92:D92))) -> 2.56005 | F92: =MAX(0,MIN($D$92*2,F$82-SUM($D92:E92))) -> 2.56005 | G92: =MAX(0,MIN($D$92*2,G$82-SUM($D92:F92))) -> 2.56005 | H92: =MAX(0,MIN($D$92*2,H$82-SUM($D92:G92))) -> 2.56005 | I92: =MAX(0,MIN($D$92*2,I$82-SUM($D92:H92))) -> 2.56005 | J92: =MAX(0,MIN($D$92*2,J$82-SUM($D92:I92))) -> 2.56005 | K92: =MAX(0,MIN($D$92*2,K$82-SUM($D92:J92))) -> 2.56005 | L92: =MAX(0,MIN($D$92*2,L$82-SUM($D92:K92))) -> 2.56005 | ... T92: =MAX(0,MIN($D$92*2,T$82-SUM($D92:S92))) -> 2.56005
B93: 2015 capital expenditures | E93: =E$82/$C$88/2 -> 1.13255 | F93: =MAX(0,MIN($E$93*2,F$82-SUM($E93:E93))) -> 2.2651 | G93: =MAX(0,MIN($E$93*2,G$82-SUM($E93:F93))) -> 2.2651 | H93: =MAX(0,MIN($E$93*2,H$82-SUM($E93:G93))) -> 2.2651 | I93: =MAX(0,MIN($E$93*2,I$82-SUM($E93:H93))) -> 2.2651 | J93: =MAX(0,MIN($E$93*2,J$82-SUM($E93:I93))) -> 2.2651 | K93: =MAX(0,MIN($E$93*2,K$82-SUM($E93:J93))) -> 2.2651 | L93: =MAX(0,MIN($E$93*2,L$82-SUM($E93:K93))) -> 2.2651 | M93: =MAX(0,MIN($E$93*2,M$82-SUM($E93:L93))) -> 2.2651 | ... T93: =MAX(0,MIN($E$93*2,T$82-SUM($E93:S93))) -> 2.2651
B94: 2016 capital expenditures | F94: =F$82/$C$88/2 -> 1.414075 | G94: =MAX(0,MIN($F$94*2,G$82-SUM($F94:F94))) -> 2.82815 | H94: =MAX(0,MIN($F$94*2,H$82-SUM($F94:G94))) -> 2.82815 | I94: =MAX(0,MIN($F$94*2,I$82-SUM($F94:H94))) -> 2.82815 | J94: =MAX(0,MIN($F$94*2,J$82-SUM($F94:I94))) -> 2.82815 | K94: =MAX(0,MIN($F$94*2,K$82-SUM($F94:J94))) -> 2.82815 | L94: =MAX(0,MIN($F$94*2,L$82-SUM($F94:K94))) -> 2.82815 | M94: =MAX(0,MIN($F$94*2,M$82-SUM($F94:L94))) -> 2.82815 | N94: =MAX(0,MIN($F$94*2,N$82-SUM($F94:M94))) -> 2.82815 | ... T94: =MAX(0,MIN($F$94*2,T$82-SUM($F94:S94))) -> 2.82815
B95: 2017 capital expenditures | G95: =G$82/$C$88/2 -> 2.485525 | H95: =MAX(0,MIN($G$95*2,H$82-SUM($G95:G95))) -> 4.97105 | I95: =MAX(0,MIN($G$95*2,I$82-SUM($G95:H95))) -> 4.97105 | J95: =MAX(0,MIN($G$95*2,J$82-SUM($G95:I95))) -> 4.97105 | K95: =MAX(0,MIN($G$95*2,K$82-SUM($G95:J95))) -> 4.97105 | L95: =MAX(0,MIN($G$95*2,L$82-SUM($G95:K95))) -> 4.97105 | M95: =MAX(0,MIN($G$95*2,M$82-SUM($G95:L95))) -> 4.97105 | N95: =MAX(0,MIN($G$95*2,N$82-SUM($G95:M95))) -> 4.97105 | O95: =MAX(0,MIN($G$95*2,O$82-SUM($G95:N95))) -> 4.97105 | ... T95: =MAX(0,MIN($G$95*2,T$82-SUM($G95:S95))) -> 4.97105
B96: 2018 capital expenditures | H96: =H$82/$C$88/2 -> 2.3265034 | I96: =MAX(0,MIN($H$96*2,I$82-SUM($H96:H96))) -> 4.6530068 | J96: =MAX(0,MIN($H$96*2,J$82-SUM($H96:I96))) -> 4.6530068 | K96: =MAX(0,MIN($H$96*2,K$82-SUM($H96:J96))) -> 4.6530068 | L96: =MAX(0,MIN($H$96*2,L$82-SUM($H96:K96))) -> 4.6530068 | M96: =MAX(0,MIN($H$96*2,M$82-SUM($H96:L96))) -> 4.6530068 | N96: =MAX(0,MIN($H$96*2,N$82-SUM($H96:M96))) -> 4.6530068 | O96: =MAX(0,MIN($H$96*2,O$82-SUM($H96:N96))) -> 4.6530068 | P96: =MAX(0,MIN($H$96*2,P$82-SUM($H96:O96))) -> 4.6530068 | ... T96: =MAX(0,MIN($H$96*2,T$82-SUM($H96:S96))) -> 4.6530068
B97: 2019 capital expenditures | I97: =I$82/$C$88/2 -> 2.2669053 | J97: =MAX(0,MIN($I$97*2,J$82-SUM($I97:I97))) -> 4.5338106 | K97: =MAX(0,MIN($I$97*2,K$82-SUM($I97:J97))) -> 4.5338106 | L97: =MAX(0,MIN($I$97*2,L$82-SUM($I97:K97))) -> 4.5338106 | M97: =MAX(0,MIN($I$97*2,M$82-SUM($I97:L97))) -> 4.5338106 | N97: =MAX(0,MIN($I$97*2,N$82-SUM($I97:M97))) -> 4.5338106 | O97: =MAX(0,MIN($I$97*2,O$82-SUM($I97:N97))) -> 4.5338106 | P97: =MAX(0,MIN($I$97*2,P$82-SUM($I97:O97))) -> 4.5338106 | Q97: =MAX(0,MIN($I$97*2,Q$82-SUM($I97:P97))) -> 4.5338106 | ... T97: =MAX(0,MIN($I$97*2,T$82-SUM($I97:S97))) -> 4.5338106
B98: 2020 capital expenditures | J98: =J$82/$C$88/2 -> 2.7171031 | K98: =MAX(0,MIN($J$98*2,K$82-SUM($J98:J98))) -> 5.4342061 | L98: =MAX(0,MIN($J$98*2,L$82-SUM($J98:K98))) -> 5.4342061 | M98: =MAX(0,MIN($J$98*2,M$82-SUM($J98:L98))) -> 5.4342061 | N98: =MAX(0,MIN($J$98*2,N$82-SUM($J98:M98))) -> 5.4342061 | O98: =MAX(0,MIN($J$98*2,O$82-SUM($J98:N98))) -> 5.4342061 | P98: =MAX(0,MIN($J$98*2,P$82-SUM($J98:O98))) -> 5.4342061 | Q98: =MAX(0,MIN($J$98*2,Q$82-SUM($J98:P98))) -> 5.4342061 | R98: =MAX(0,MIN($J$98*2,R$82-SUM($J98:Q98))) -> 5.4342061 | ... T98: =MAX(0,MIN($J$98*2,T$82-SUM($J98:S98))) -> 5.4342061
B99: 2021 capital expenditures | K99: =K$82/$C$88/2 -> 3.605912 | L99: =MAX(0,MIN($K$99*2,L$82-SUM($K99:K99))) -> 7.211824 | M99: =MAX(0,MIN($K$99*2,M$82-SUM($K99:L99))) -> 7.211824 | N99: =MAX(0,MIN($K$99*2,N$82-SUM($K99:M99))) -> 7.211824 | O99: =MAX(0,MIN($K$99*2,O$82-SUM($K99:N99))) -> 7.211824 | P99: =MAX(0,MIN($K$99*2,P$82-SUM($K99:O99))) -> 7.211824 | Q99: =MAX(0,MIN($K$99*2,Q$82-SUM($K99:P99))) -> 7.211824 | R99: =MAX(0,MIN($K$99*2,R$82-SUM($K99:Q99))) -> 7.211824 | S99: =MAX(0,MIN($K$99*2,S$82-SUM($K99:R99))) -> 7.211824 | T99: =MAX(0,MIN($K$99*2,T$82-SUM($K99:S99))) -> 7.211824
B100: 2022 capital expenditures | L100: =L$82/$C$88/2 -> 4.1638233 | M100: =MAX(0,MIN($L$100*2,M$82-SUM($L100:L100))) -> 8.3276466 | N100: =MAX(0,MIN($L$100*2,N$82-SUM($L100:M100))) -> 8.3276466 | O100: =MAX(0,MIN($L$100*2,O$82-SUM($L100:N100))) -> 8.3276466 | P100: =MAX(0,MIN($L$100*2,P$82-SUM($L100:O100))) -> 8.3276466 | Q100: =MAX(0,MIN($L$100*2,Q$82-SUM($L100:P100))) -> 8.3276466 | R100: =MAX(0,MIN($L$100*2,R$82-SUM($L100:Q100))) -> 8.3276466 | S100: =MAX(0,MIN($L$100*2,S$82-SUM($L100:R100))) -> 8.3276466 | T100: =MAX(0,MIN($L$100*2,T$82-SUM($L100:S100))) -> 8.3276466
B101: 2023 capital expenditures | M101: =M$82/$C$88/2 -> 4.4126901 | N101: =MAX(0,MIN($M$101*2,N$82-SUM($M101:M101))) -> 8.8253802 | O101: =MAX(0,MIN($M$101*2,O$82-SUM($M101:N101))) -> 8.8253802 | P101: =MAX(0,MIN($M$101*2,P$82-SUM($M101:O101))) -> 8.8253802 | Q101: =MAX(0,MIN($M$101*2,Q$82-SUM($M101:P101))) -> 8.8253802 | R101: =MAX(0,MIN($M$101*2,R$82-SUM($M101:Q101))) -> 8.8253802 | S101: =MAX(0,MIN($M$101*2,S$82-SUM($M101:R101))) -> 8.8253802 | T101: =MAX(0,MIN($M$101*2,T$82-SUM($M101:S101))) -> 8.8253802
B102: 2024 capital expenditures | N102: =N$82/$C$88/2 -> 4.518868 | O102: =MAX(0,MIN($N$102*2,O$82-SUM($N102:N102))) -> 9.037736 | P102: =MAX(0,MIN($N$102*2,P$82-SUM($N102:O102))) -> 9.037736 | Q102: =MAX(0,MIN($N$102*2,Q$82-SUM($N102:P102))) -> 9.037736 | R102: =MAX(0,MIN($N$102*2,R$82-SUM($N102:Q102))) -> 9.037736 | S102: =MAX(0,MIN($N$102*2,S$82-SUM($N102:R102))) -> 9.037736 | T102: =MAX(0,MIN($N$102*2,T$82-SUM($N102:S102))) -> 9.037736
B103: 2025 capital expenditures | O103: =O$82/$C$88/2 -> 4.9637787 | P103: =MAX(0,MIN($O$103*2,P$82-SUM($O103:O103))) -> 9.9275574 | Q103: =MAX(0,MIN($O$103*2,Q$82-SUM($O103:P103))) -> 9.9275574 | R103: =MAX(0,MIN($O$103*2,R$82-SUM($O103:Q103))) -> 9.9275574 | S103: =MAX(0,MIN($O$103*2,S$82-SUM($O103:R103))) -> 9.9275574 | T103: =MAX(0,MIN($O$103*2,T$82-SUM($O103:S103))) -> 9.9275574
B104: 2026 capital expenditures | P104: =P$82/$C$88/2 -> 5.981135 | Q104: =MAX(0,MIN($P$104*2,Q$82-SUM($P104:P104))) -> 11.96227 | R104: =MAX(0,MIN($P$104*2,R$82-SUM($P104:Q104))) -> 11.96227 | S104: =MAX(0,MIN($P$104*2,S$82-SUM($P104:R104))) -> 11.96227 | T104: =MAX(0,MIN($P$104*2,T$82-SUM($P104:S104))) -> 11.96227
B105: 2027 capital expenditures | Q105: =Q$82/$C$88/2 -> 6.0642778 | R105: =MAX(0,MIN($Q$105*2,R$82-SUM($Q105:Q105))) -> 12.128556 | S105: =MAX(0,MIN($Q$105*2,S$82-SUM($Q105:R105))) -> 12.128556 | T105: =MAX(0,MIN($Q$105*2,T$82-SUM($Q105:S105))) -> 12.128556
B106: 2028 capital expenditures | R106: =R$82/$C$88/2 -> 6.1335946 | S106: =MAX(0,MIN($R$106*2,S$82-SUM($R106:R106))) -> 12.267189 | T106: =MAX(0,MIN($R$106*2,T$82-SUM($R106:S106))) -> 12.267189
B107: 2029 capital expenditures | S107: =S$82/$C$88/2 -> 6.1411129 | T107: =MAX(0,MIN($S$107*2,T$82-SUM($S107:S107))) -> 12.282226
B108: 2030 capital expenditures | T108: =T$82/$C$88/2 -> 5.2772372
B109: Total depreciation | C109: =-C84 -> 47.3 | D109: =-D84 -> 62.3 | E109: =-E84 -> 62.343 | F109: =-F84 -> 61.398 | G109: =SUM(G90:G98) -> 62.822322 | H109: =SUM(H90:H98) -> 65.128658 | I109: =SUM(I90:I98) -> 67.341659 | J109: =SUM(J90:J98) -> 70.06428 | K109: =SUM(K90:K98) -> 70.633066 | L109: =SUM(L90:L98) -> 68.592163 | M109: =SUM(M90:M98) -> 66.653306 | N109: =SUM(N90:N98) -> 64.811392 | ... T109: =SUM(T90:T98) -> 55.54057

Sheet CF
B2: VERTEX PHARMACEUTICALS INC. (NSDQ:VRTX) | C2: 2009 | D2: 2010 | E2: 2011 | F2: 2012 | G2: 2013 | H2: 2014 | I2: 2015 | J2: 2016 | K2: 2017 | L2: 2018 | M2: 2019 | N2: 2020 | O2: =N2+1 -> 2021 | P2: =O2+1 -> 2022 | Q2: =P2+1 -> 2023 | R2: =Q2+1 -> 2024 | S2: =R2+1 -> 2025 | T2: =S2+1 -> 2026 | U2: =T2+1 -> 2027 | V2: =U2+1 -> 2028 | ... X2: =W2+1 -> 2030
B3: Cash Flows From Operating Activities
B5: Net loss | G5: -687.55 | H5: -742.745 | I5: -588.181 | J5: -84.031 | K5: 91.635 | L5: =IS!AK116 -> 522.36771 | M5: =IS!AP116 -> 672.00412 | N5: =IS!AU116 -> 1595.756 | O5: =IS!AZ116 -> 2761.2752 | P5: =IS!BE116 -> 2901.3932 | Q5: =IS!BJ116 -> 3122.3165 | R5: =IS!BO116 -> 3362.5087 | S5: =IS!BT116 -> 4035.5336 | T5: =IS!BY116 -> 5307.3229 | U5: =IS!CD116 -> 5587.613 | V5: =IS!CI116 -> 5906.5387 | W5: =IS!CN116 -> 6162.623 | X5: =IS!CS116 -> 6513.5433
B6: Adjustments to reconcile net loss to net cash used in operating activities:
B7: Depreciation and amortization expense | G7: 48.365 | H7: 63.257 | I7: 62.343 | J7: 61.398 | K7: =BS!G109 -> 62.822322 | L7: =BS!H109 -> 65.128658 | M7: =BS!I109 -> 67.341659 | N7: =BS!J109 -> 70.06428 | O7: =BS!K109 -> 70.633066 | P7: =BS!L109 -> 68.592163 | Q7: =BS!M109 -> 66.653306 | R7: =BS!N109 -> 64.811392 | ... X7: =BS!T109 -> 55.54057
B8: Depreciation | G8: 47.3 | H8: 62.3 | I8: 62.3 | K8: 61.397 | L8: =L7 -> 65.128658 | M8: =M7 -> 67.341659 | N8: =N7 -> 70.06428 | O8: =O7 -> 70.633066 | P8: =P7 -> 68.592163 | Q8: =Q7 -> 66.653306 | R8: =R7 -> 64.811392 | S8: =S7 -> 63.061574 | ... X8: =X7 -> 55.54057
B9: Amortization | G9: =+G7-G8 -> 1.065 | H9: =+H7-H8 -> 0.957 | I9: =+I7-I8 -> 0.043 | K9: 0 | L9: =L7-L8 -> 0 | M9: =M7-M8 -> 0 | N9: =N7-N8 -> 0 | O9: =O7-O8 -> 0 | P9: =P7-P8 -> 0 | Q9: =Q7-Q8 -> 0 | R9: =R7-R8 -> 0 | S9: =S7-S8 -> 0 | ... X9: =X7-X8 -> 0
B10: Stock-based compensation expense | G10: 127.303 | H10: 177.542 | I10: 231.025 | J10: 237.705 | K10: 290.736 | L10: =IS!AK140 -> 245 | M10: =IS!AP140 -> 245 | N10: =IS!AU140 -> 245 | O10: =IS!AZ140 -> 245 | P10: =IS!BE140 -> 245 | Q10: =IS!BJ140 -> 245 | R10: =IS!BO140 -> 245 | S10: =IS!BT140 -> 245 | T10: =IS!BY140 -> 245 | U10: =IS!CD140 -> 245 | V10: =IS!CI140 -> 245 | W10: =IS!CN140 -> 245 | X10: =IS!CS140 -> 245
B11: Other non-cash items, net | G11: =5.86+663.5-285.053+7.594+55.11+10.358+1.252+6.742 -> 465.363 | H11: =0.281+1.689-2.16 -> -0.19 | I11: =3.283+2.516+9.532 -> 15.331 | J11: =16.961+6.14 -> 23.101 | K11: =15.292-120.513+1.951+255.34+160+76.644-2.804 -> 385.91 | L11: 0 | M11: 0 | N11: 0 | O11: 0 | P11: 0 | Q11: 0 | R11: 0 | S11: 0 | T11: 0 | U11: 0 | V11: 0 | W11: 0 | X11: 0
B13: Changes in operating assets and liabilities:
B14: Accounts receivable, net | G14: 53.363 | H14: 7.428 | I14: -104.847 | J14: -33.027 | K14: -71.759 | L14: =BS!G7-BS!H7 -> -19.674456 | M14: =BS!H7-BS!I7 -> -30.196259 | N14: =BS!I7-BS!J7 -> -124.70085 | O14: =BS!J7-BS!K7 -> -149.13712 | P14: =BS!K7-BS!L7 -> -93.614367 | Q14: =BS!L7-BS!M7 -> -41.75845 | R14: =BS!M7-BS!N7 -> -17.81605 | S14: =BS!N7-BS!O7 -> -74.653509 | ... X14: =BS!S7-BS!T7 -> -9.3821539
B15: Inventories | G15: 7.142 | H15: -16.469 | I15: -23.146 | J15: -16.45 | K15: -44.984 | L15: =BS!G8-BS!H8 -> -7.8203275 | M15: =BS!H8-BS!I8 -> -12.002601 | N15: =BS!I8-BS!J8 -> -49.566886 | O15: =BS!J8-BS!K8 -> -59.27997 | P15: =BS!K8-BS!L8 -> -37.210432 | Q15: =BS!L8-BS!M8 -> -16.598413 | R15: =BS!M8-BS!N8 -> -7.0816365 | S15: =BS!N8-BS!O8 -> -29.67375 | ... X15: =BS!S8-BS!T8 -> -3.729278
B16: Prepaid expenses and other assets | G16: -12.061 | H16: -15.771 | I16: -9.26 | J16: -8.699 | K16: -111.063 | L16: =(BS!G9+BS!G13)-(BS!H9+BS!H13) -> -19.212565 | M16: =(BS!H9+BS!H13)-(BS!I9+BS!I13) -> -29.487351 | N16: =(BS!I9+BS!I13)-(BS!J9+BS!J13) -> -121.77329 | O16: =(BS!J9+BS!J13)-(BS!K9+BS!K13) -> -145.63588 | P16: =(BS!K9+BS!K13)-(BS!L9+BS!L13) -> -91.416612 | Q16: =(BS!L9+BS!L13)-(BS!M9+BS!M13) -> -40.7781 | R16: =(BS!M9+BS!M13)-(BS!N9+BS!N13) -> -17.397788 | S16: =(BS!N9+BS!N13)-(BS!O9+BS!O13) -> -72.900892 | ... X16: =(BS!S9+BS!S13)-(BS!T9+BS!T13) -> -9.161892
B17: Accounts payable | G17: -49.234 | H17: 25.048 | I17: -1.709 | J17: =-11.745 -> -11.745 | K17: 8.753 | L17: =BS!H17-BS!G17 -> 9.9544174 | M17: =BS!I17-BS!H17 -> 5.4274771 | N17: =BS!J17-BS!I17 -> 4.4687947 | O17: =BS!K17-BS!J17 -> 3.3102662 | P17: =BS!L17-BS!K17 -> 1.2991796 | Q17: =BS!M17-BS!L17 -> -0.7710023 | R17: =BS!N17-BS!M17 -> -2.8788729 | S17: =BS!O17-BS!N17 -> -4.0065118 | ... X17: =BS!T17-BS!S17 -> -3.8782365
B18: Accrued expenses and other liabilities | G18: =43.725+5.025 -> 48.75 | H18: =-3.27+17.502 -> 14.232 | I18: =102.746-30.492 -> 72.254 | J18: =88.649-7.426 -> 81.223 | K18: =246.217-5.987 -> 240.23 | L18: =(BS!H18+BS!H20+BS!H24+BS!H28+BS!H29+BS!H31+BS!H22)-(BS!G18+BS!G20+BS!G24+BS!G28+BS!G29+BS!G31+BS!G22) -> -78.042418 | M18: =(BS!I18+BS!I20+BS!I24+BS!I28+BS!I29+BS!I31+BS!I22)-(BS!H18+BS!H20+BS!H24+BS!H28+BS!H29+BS!H31+BS!H22) -> 84.161397 | N18: =(BS!J18+BS!J20+BS!J24+BS!J28+BS!J29+BS!J31+BS!J22)-(BS!I18+BS!I20+BS!I24+BS!I28+BS!I29+BS!I31+BS!I22) -> 69.295549 | O18: =(BS!K18+BS!K20+BS!K24+BS!K28+BS!K29+BS!K31+BS!K22)-(BS!J18+BS!J20+BS!J24+BS!J28+BS!J29+BS!J31+BS!J22) -> 51.330779 | P18: =(BS!L18+BS!L20+BS!L24+BS!L28+BS!L29+BS!L31+BS!L22)-(BS!K18+BS!K20+BS!K24+BS!K28+BS!K29+BS!K31+BS!K22) -> 20.145782 | Q18: =(BS!M18+BS!M20+BS!M24+BS!M28+BS!M29+BS!M31+BS!M22)-(BS!L18+BS!L20+BS!L24+BS!L28+BS!L29+BS!L31+BS!L22) -> -11.955579 | R18: =(BS!N18+BS!N20+BS!N24+BS!N28+BS!N29+BS!N31+BS!N22)-(BS!M18+BS!M20+BS!M24+BS!M28+BS!M29+BS!M31+BS!M22) -> -44.641361 | S18: =(BS!O18+BS!O20+BS!O24+BS!O28+BS!O29+BS!O31+BS!O22)-(BS!N18+BS!N20+BS!N24+BS!N28+BS!N29+BS!N31+BS!N22) -> -62.12714 | ... X18: =(BS!T18+BS!T20+BS!T24+BS!T28+BS!T29+BS!T31+BS!T22)-(BS!S18+BS!S20+BS!S24+BS!S28+BS!S29+BS!S31+BS!S22) -> -60.138034
B19: Deferred revenue | G19: -53.011 | H19: -25.531 | I19: -19.242 | J19: -13.372 | K19: -5.913 | L19: =(BS!H19+BS!H27)-(BS!G19+BS!G27) -> 0.48217078 | M19: =(BS!I19+BS!I27)-(BS!H19+BS!H27) -> 0.74003336 | N19: =(BS!J19+BS!J27)-(BS!I19+BS!I27) -> 3.0561002 | O19: =(BS!K19+BS!K27)-(BS!J19+BS!J27) -> 3.6549709 | P19: =(BS!L19+BS!L27)-(BS!K19+BS!K27) -> 2.2942496 | Q19: =(BS!M19+BS!M27)-(BS!L19+BS!L27) -> 1.0233932 | R19: =(BS!N19+BS!N27)-(BS!M19+BS!M27) -> 0.43662598 | S19: =(BS!O19+BS!O27)-(BS!N19+BS!N27) -> 1.8295673 | ... X19: =(BS!T19+BS!T27)-(BS!S19+BS!S27) -> 0.22993268
B20: Net cash used in operating activities | C20: =SUM(C5:C19) -> 0 | D20: =SUM(D5:D19) -> 0 | E20: =SUM(E5:E19) -> 0 | F20: =SUM(F5:F19) -> 0 | G20: =SUM(G8:G19)+G5 -> -51.57 | H20: =SUM(H8:H19)+H5 -> -513.199 | I20: =SUM(I8:I19)+I5 -> -365.432 | J20: =SUM(J7:J19)+J5 -> 236.103 | K20: =SUM(K8:K19)+K5 -> 844.942 | L20: =SUM(L8:L19)+L5 -> 718.18319 | M20: =SUM(M8:M19)+M5 -> 1002.9885 | N20: =SUM(N8:N19)+N5 -> 1691.5997 | O20: =SUM(O8:O19)+O5 -> 2781.1513 | P20: =SUM(P8:P19)+P5 -> 3016.4832 | Q20: =SUM(Q8:Q19)+Q5 -> 3323.1316 | R20: =SUM(R8:R19)+R5 -> 3582.941 | ... X20: =SUM(X8:X19)+X5 -> 6728.0242
B22: Cash Flows From Investing Activities
B24: Purchases of marketable securities | G24: -2412.418 | H24: -1424.172 | I24: -633.041 | J24: -616.625 | K24: -532.581 | L24: 0 | M24: 0 | N24: 0 | O24: 0 | P24: 0 | Q24: 0 | R24: 0 | S24: 0 | T24: 0 | U24: 0 | V24: 0 | W24: 0 | X24: 0
B25: Sales and maturities of marketable securities | G25: 2348.295 | H25: 1557.938 | I25: 1067.443 | J25: =757.562 -> 757.562 | K25: 369.214 | L25: 0 | M25: 0 | N25: 0 | O25: 0 | P25: 0 | Q25: 0 | R25: 0 | S25: 0 | T25: 0 | U25: 0 | V25: 0 | W25: 0 | X25: 0
B26: Payment for acquisition of variable interest entity | G26: 0 | H26: -10 | I26: -80 | J26: 0 | K26: 0 | L26: 0 | M26: 0 | N26: 0 | O26: 0 | P26: 0 | Q26: 0 | R26: 0 | S26: 0 | T26: 0 | U26: 0 | V26: 0 | W26: 0 | X26: 0
B27: Expenditures for property and equipment | G27: -51.393 | H27: -51.201 | I27: -45.302 | J27: -56.563 | K27: -99.421 | L27: =-BS!H82 -> -93.060137 | M27: =-BS!I82 -> -90.676213 | N27: =-BS!J82 -> -108.68412 | O27: =-BS!K82 -> -144.23648 | P27: =-BS!L82 -> -166.55293 | Q27: =-BS!M82 -> -176.5076 | R27: =-BS!N82 -> -180.75472 | S27: =-BS!O82 -> -198.55115 | ... X27: =-BS!T82 -> -211.08949
B28: (Increase) decrease in other assets | G28: =1.698+31.804+27.884 -> 61.386 | H28: =-0.244+1.638 -> 1.394 | I28: =-30-21.981+11.685+0.052 -> -40.244 | J28: =-20-13.075+22.029+31.148-0.007 -> 20.095 | K28: =-160-15.329+0.436 -> -174.893 | L28: 0 | M28: 0 | N28: 0 | O28: 0 | P28: 0 | Q28: 0 | R28: 0 | S28: 0 | T28: 0 | U28: 0 | V28: 0 | W28: 0 | X28: 0
B29: Net cash used in investing activities | C29: =SUM(C24:C28) -> 0 | D29: =SUM(D24:D28) -> 0 | E29: =SUM(E24:E28) -> 0 | F29: =SUM(F24:F28) -> 0 | G29: =SUM(G24:G28) -> -54.13 | H29: =SUM(H24:H28) -> 73.959 | I29: =SUM(I24:I28) -> 268.856 | J29: =SUM(J24:J28) -> 104.469 | ... X29: =SUM(X24:X28) -> -211.08949
B31: Cash Flows From Financing Activities
B33: Issuances of common stock under benefit plans | G33: 265.878 | H33: 274.615 | I33: 185.592 | J33: 68.23 | K33: 344.84 | L33: =L75 -> 3.9068 | M33: =M75 -> 3.02777 | N33: =N75 -> 2.3465217 | O33: =O75 -> 1.8185544 | P33: =P75 -> 1.4093796 | Q33: =Q75 -> 1.0922692 | R33: =R75 -> 0.84650864 | S33: =S75 -> 0.65604419 | ... X33: =X75 -> 0.18341785
B34: Payments to redeem secured notes | G34: -0.158 | H34: 0 | I34: 0 | J34: 0 | K34: 0 | L34: 0 | M34: 0 | N34: 0 | O34: 0 | P34: 0 | Q34: 0 | R34: 0 | S34: 0 | T34: 0 | U34: 0 | V34: 0 | W34: 0 | X34: 0
B35: Payments on capital lease obligations | G35: -16.057 | H35: -21.443 | I35: -19.954 | J35: -17.597 | K35: =7.484-18.795 -> -11.311 | L35: 0 | M35: 0 | N35: 0 | O35: 0 | P35: 0 | Q35: 0 | R35: 0 | S35: 0 | T35: 0 | U35: 0 | V35: 0 | W35: 0 | X35: 0
B36: Proceeds from senior secured term loan | G36: 0 | H36: 294.243 | I36: 0 | J36: -75 | K36: =(BS!G21+BS!G30)-(BS!F21+BS!F30) -> 0 | L36: =(BS!H21+BS!H30)-(BS!G21+BS!G30) -> 0 | M36: =(BS!I21+BS!I30)-(BS!H21+BS!H30) -> 0 | N36: =(BS!J21+BS!J30)-(BS!I21+BS!I30) -> 0 | O36: =(BS!K21+BS!K30)-(BS!J21+BS!J30) -> 0 | P36: =(BS!L21+BS!L30)-(BS!K21+BS!K30) -> 0 | Q36: =(BS!M21+BS!M30)-(BS!L21+BS!L30) -> 0 | R36: =(BS!N21+BS!N30)-(BS!M21+BS!M30) -> 0 | ... X36: =(BS!T21+BS!T30)-(BS!S21+BS!S30) -> 0
B37: Proceeds from revolving credit facility | J37: 74.965 | K37: -300
B38: Tax benefit from stock options | G38: -1.252 | H38: 2.16 | I38: 0 | J38: 0 | K38: 0 | L38: 0 | M38: 0 | N38: 0 | O38: 0 | P38: 0 | Q38: 0 | R38: 0 | S38: 0 | T38: 0 | U38: 0 | V38: 0 | W38: 0 | X38: 0
B39: Other financing activities | G39: =-67.527 -> -67.527 | H39: =8.05-60.249 -> -52.199 | I39: =-0.381+23.662 -> 23.281 | J39: =-0.432+11.208-3.103+75 -> 82.673 | K39: =12.5-0.541+27.182-4.266 -> 34.875 | L39: =BS!H40-BS!G40 -> 0 | M39: =BS!I40-BS!H40 -> 0 | N39: =BS!J40-BS!I40 -> 0 | O39: =BS!K40-BS!J40 -> 0 | P39: =BS!L40-BS!K40 -> 0 | Q39: =BS!M40-BS!L40 -> 0 | R39: =BS!N40-BS!M40 -> 0 | S39: =BS!O40-BS!N40 -> 0 | ... X39: =BS!T40-BS!S40 -> 0
B40: Net cash provided by financing activities | C40: =SUM(C33:C39) -> 0 | D40: =SUM(D33:D39) -> 0 | E40: =SUM(E33:E39) -> 0 | F40: =SUM(F33:F39) -> 0 | G40: =SUM(G33:G39) -> 180.884 | H40: =SUM(H33:H39) -> 497.376 | I40: =SUM(I33:I39) -> 188.919 | J40: =SUM(J33:J39) -> 133.271 | ... X40: =SUM(X33:X39) -> 0.18341785
B42: Effect of exchange rate changes on cash and cash equivalents | C42: 0 | D42: 0 | E42: 0 | F42: 0 | G42: 4.708 | H42: -2.176 | I42: -2.834 | J42: -4.666 | K42: 5.802 | L42: 0 | M42: 0 | N42: 0 | O42: 0 | P42: 0 | Q42: 0 | R42: 0 | S42: 0 | T42: 0 | U42: 0 | V42: 0 | W42: 0 | X42: 0
B44: Net (decrease) increase in cash and cash equivalents | C44: =C20+C29+C40+C42 -> 0 | D44: =D20+D29+D40+D42 -> 0 | E44: =E20+E29+E40+E42 -> 0 | F44: =F20+F29+F40+F42 -> 0 | G44: =G20+G29+G40+G42 -> 79.892 | H44: =H20+H29+H40+H42 -> 55.96 | I44: =I20+I29+I40+I42 -> 89.509 | J44: =J20+J29+J40+J42 -> 469.177 | ... X44: =X20+X29+X40+X42 -> 6517.1181
B46: Cash and cash equivalents at beginning of period | D46: =C47 -> 0 | E46: =D47 -> 0 | F46: =E47 -> 0 | G46: 489.407 | H46: =G47 -> 569.299 | I46: =H47 -> 625.259 | J46: =I47 -> 714.768 | K46: =J47 -> 1183.945 | L46: =K47 -> 1665.412 | M46: =L47 -> 2294.4419 | N46: =M47 -> 3209.7819 | O46: =N47 -> 4795.044 | ... X46: =W47 -> 43231.401
B47: Cash and cash equivalents at end of period | C47: =C44+C46 -> 0 | D47: =D44+D46 -> 0 | E47: =E44+E46 -> 0 | F47: =F44+F46 -> 0 | G47: =G44+G46 -> 569.299 | H47: =H44+H46 -> 625.259 | I47: =I44+I46 -> 714.768 | J47: =J44+J46 -> 1183.945 | ... X47: =X44+X46 -> 49748.52
B49: Check | C49: -18.486 | D49: -21.127 | E49: =CF!I96 -> 0 | F49: -54.663 | G49: =G47-BS!C5 -> 0 | H49: =H47-BS!D5 -> 0 | I49: =I47-BS!E5 -> 0 | J49: =J47-BS!F5 -> 0 | K49: =K47-BS!G5 -> 0 | L49: =L47-BS!H5 -> 0 | M49: =M47-BS!I5 -> 0 | N49: =N47-BS!J5 -> 0 | ... X49: =X47-BS!T5 -> 0
B51: Stock Options and Share Count | G51: 0.1
A52: 0.1 | B52: Stock Price (average) | G52: 73.45 | H52: 118.8 | I52: 123.78 | J52: =I52*(1+$G$51) -> 136.158 | K52: =J52*(1+$G$51) -> 149.7738 | L52: =K52*(1+$G$51) -> 164.75118 | M52: =L52*(1+$G$51) -> 181.2263 | N52: =M52*(1+$G$51) -> 199.34893 | O52: =N52*(1+$G$51) -> 219.28382 | P52: =O52*(1+$G$51) -> 241.2122 | Q52: =P52*(1+$G$51) -> 265.33342 | ... X52: =W52*(1+$G$51) -> 517.05978
B53: Option Balance (Beginning Year) | C53: 9.0491 | D53: 10.681895 | E53: 12.739831 | F53: 13.754568 | G53: 19.726 | H53: =G68 -> 15.729 | I53: =H68 -> 12.003 | J53: =I53+I65-I57-I59 -> 11.145 | K53: 12.642 | L53: =K53+K65-K57-K59 -> 9.767 | M53: =L53+L65-L57-L59 -> 7.569425 | N53: =M53+M65-M57-M59 -> 5.8663044 | O53: =N53+N65-N57-N59 -> 4.5463859 | P53: =O53+O65-O57-O59 -> 3.5234491 | Q53: =P53+P65-P57-P59 -> 2.730673 | R53: =Q53+Q65-Q57-Q59 -> 2.1162716 | S53: =R53+R65-R57-R59 -> 1.6401105 | ... X53: =W53+W65-W57-W59 -> 0.45854464
B54: Average Options Exercisable | C54: 0 | D54: 0 | E54: 13.204038 | F54: 11.500542 | G54: 7.95 | H54: 11.38 | I54: 10.461 | J54: =((J53+K53)/2)*J55 -> 8.824977 | K54: 5.313 | L54: =((L53+M53)/2)*L55 -> 6.4318137 | M54: =((M53+N53)/2)*M55 -> 4.9846556 | N54: =((N53+O53)/2)*N55 -> 3.8631081 | O54: =((O53+P53)/2)*O55 -> 2.9939088 | P54: =((P53+Q53)/2)*P55 -> 2.3202793 | Q54: =((Q53+R53)/2)*Q55 -> 1.7982165 | R54: =((R53+S53)/2)*R55 -> 1.3936178 | S54: =((S53+T53)/2)*S55 -> 1.0800538 | ... W54: =((W53+X53)/2)*W55 -> 0.38962982 | X54: =((X53+X53)/2)*X55 -> 0.34024012
B55: % Exercisable | C55: =IF(ISERROR(C54/C53), "NM", (C54/C53)) -> 0 | D55: =IF(ISERROR(D54/D53), "NM", (D54/D53)) -> 0 | E55: =IF(ISERROR(E54/E53), "NM", (E54/E53)) -> 1.0364375 | F55: =IF(ISERROR(F54/F53), "NM", (F54/F53)) -> 0.83612528 | G55: =IF(ISERROR(G54/G53), "NM", (G54/G53)) -> 0.40302139 | H55: =IF(ISERROR(H54/H53), "NM", (H54/H53)) -> 0.72350436 | I55: =IF(ISERROR(I54/I53), "NM", (I54/I53)) -> 0.87153212 | J55: 0.742 | K55: =K54/K53 -> 0.42026578 | L55: 0.742 | M55: 0.742 | N55: 0.742 | O55: 0.742 | P55: 0.742 | Q55: 0.742 | R55: 0.742 | S55: 0.742 | T55: 0.742 | U55: 0.742 | V55: 0.742 | W55: 0.742 | X55: 0.742
B56: Weighted Average Exercise Price of exercisable | C56: 0 | D56: 0 | E56: 11.43 | F56: 14.05 | G56: 38.84 | H56: 55.94 | I56: 74.11 | J56: =I56*(1+DCF!$C$23) -> 81.521 | K56: 80.14 | L56: =K56*(1+DCF!$C$23) -> 88.154 | M56: =L56*(1+DCF!$C$23) -> 96.9694 | N56: =M56*(1+DCF!$C$23) -> 106.66634 | O56: =N56*(1+DCF!$C$23) -> 117.33297 | P56: =O56*(1+DCF!$C$23) -> 129.06627 | Q56: =P56*(1+DCF!$C$23) -> 141.9729 | R56: =Q56*(1+DCF!$C$23) -> 156.17019 | S56: =R56*(1+DCF!$C$23) -> 171.78721 | ... X56: =W56*(1+DCF!$C$23) -> 276.66502
B57: Options Cancelled | C57: 0.203975 | D57: 0.165862 | E57: 0.143899 | F57: 0.372142 | G57: =1.822+0.02 -> 1.842 | H57: =1.173+0.014 -> 1.187 | I57: 1.1 | J57: =J58*J53 -> 0.724425 | K57: =0.062+0.611 -> 0.673 | L57: =L58*L53 -> 0.634855 | M57: =M58*M53 -> 0.49201262 | N57: =N58*N53 -> 0.38130978 | O57: =O58*O53 -> 0.29551508 | P57: =P58*P53 -> 0.22902419 | Q57: =Q58*Q53 -> 0.17749375 | R57: =R58*R53 -> 0.13755765 | S57: =S58*S53 -> 0.10660718 | ... X57: =X58*X53 -> 0.029805401
B58: % Cancelled | C58: =IF(ISERROR(C57/C53), "NM", (C57/C53)) -> 0.022540916 | D58: =IF(ISERROR(D57/D53), "NM", (D57/D53)) -> 0.015527395 | E58: =IF(ISERROR(E57/E53), "NM", (E57/E53)) -> 0.011295205 | F58: =IF(ISERROR(F57/F53), "NM", (F57/F53)) -> 0.027055884 | G58: =IF(ISERROR(G57/G53), "NM", (G57/G53)) -> 0.093379296 | H58: =IF(ISERROR(H57/H53), "NM", (H57/H53)) -> 0.0754657 | I58: =IF(ISERROR(I57/I53), "NM", (I57/I53)) -> 0.091643756 | J58: 0.065 | K58: =K57/K53 -> 0.053235248 | L58: 0.065 | M58: 0.065 | N58: 0.065 | O58: 0.065 | P58: 0.065 | Q58: 0.065 | R58: 0.065 | S58: 0.065 | T58: 0.065 | U58: 0.065 | V58: 0.065 | W58: 0.065 | X58: 0.065
B59: Options Exercised | C59: 0.653054 | D59: 0.880417 | E59: 1.669489 | F59: 3.398947 | G59: 6.995 | H59: 6.153 | I59: 3.289 | J59: =J53*J60 -> 4.458 | K59: 4.561 | L59: =L53*L60 -> 3.9068 | M59: =M53*M60 -> 3.02777 | N59: =N53*N60 -> 2.3465217 | O59: =O53*O60 -> 1.8185544 | P59: =P53*P60 -> 1.4093796 | Q59: =Q53*Q60 -> 1.0922692 | R59: =R53*R60 -> 0.84650864 | S59: =S53*S60 -> 0.65604419 | ... X59: =X53*X60 -> 0.18341785
B60: % of Outstanding Options | C60: =IF(ISERROR(C59/C53), "NM", (C59/C53)) -> 0.07216784 | D60: =IF(ISERROR(D59/D53), "NM", (D59/D53)) -> 0.082421424 | E60: =IF(ISERROR(E59/E53), "NM", (E59/E53)) -> 0.13104483 | F60: =IF(ISERROR(F59/F53), "NM", (F59/F53)) -> 0.24711405 | G60: =IF(ISERROR(G59/G53), "NM", (G59/G53)) -> 0.35460813 | H60: =IF(ISERROR(H59/H53), "NM", (H59/H53)) -> 0.39118825 | I60: =IF(ISERROR(I59/I53), "NM", (I59/I53)) -> 0.27401483 | J60: 0.4 | K60: =K59/K53 -> 0.36078152 | L60: 0.4 | M60: 0.4 | N60: 0.4 | O60: 0.4 | P60: 0.4 | Q60: 0.4 | R60: 0.4 | S60: 0.4 | T60: 0.4 | U60: 0.4 | V60: 0.4 | W60: 0.4 | X60: 0.4
B61: Weighted Average Exercise Price | C61: 5.37 | D61: 6.67 | E61: 7.38 | F61: 9.25 | G61: 35.28 | H61: 41.53 | I61: 50.34 | J61: =I61*(1+DCF!$C$23) -> 55.374 | K61: 70.9 | L61: =K61*(1+DCF!$C$23) -> 77.99 | M61: =L61*(1+DCF!$C$23) -> 85.789 | N61: =M61*(1+DCF!$C$23) -> 94.3679 | O61: =N61*(1+DCF!$C$23) -> 103.80469 | P61: =O61*(1+DCF!$C$23) -> 114.18516 | Q61: =P61*(1+DCF!$C$23) -> 125.60367 | R61: =Q61*(1+DCF!$C$23) -> 138.16404 | S61: =R61*(1+DCF!$C$23) -> 151.98045 | ... X61: =W61*(1+DCF!$C$23) -> 244.76603
B62: Statutory Tax rate | C62: 0.38 | D62: 0.35 | E62: 0.34 | F62: 0.32 | G62: 0.35 | H62: 0.35 | I62: 0.35 | J62: 0.35 | K62: 0.35 | L62: 0.35 | M62: 0.35 | N62: 0.35 | O62: 0.35 | P62: 0.35 | Q62: 0.35 | R62: 0.35 | S62: 0.35 | T62: 0.35 | U62: 0.35 | V62: 0.35 | W62: 0.35 | X62: 0.35
B63: Proceeds from option | C63: =C59*C61 -> 3.5069 | D63: =D59*D61 -> 5.8723814 | E63: =E59*E61 -> 12.320829 | F63: =F59*F61 -> 31.44026 | G63: =G59*G61 -> 246.7836 | H63: =H59*H61 -> 255.53409 | I63: =I59*I61 -> 165.56826 | J63: =J59*J61 -> 246.85729 | ... X63: =X59*X61 -> 44.89446
B64: Tax Benefit from Options | C64: 0 | D64: 0 | E64: 0 | F64: 0 | G64: =((G52-G61)*G59)*G62 -> 93.449703 | H64: =((H52-H61)*H59)*H62 -> 166.40481 | I64: =((I52-I61)*I59)*I62 -> 84.540456 | J64: =((J52-J61)*J59)*J62 -> 126.04728 | K64: =((K52-K61)*K59)*K62 -> 125.91019 | L64: =((L52-L61)*L59)*L62 -> 118.6355 | M64: =((M52-M61)*M59)*M62 -> 101.13677 | N64: =((N52-N61)*N59)*N62 -> 86.219093 | ... X64: =((X52-X61)*X59)*X62 -> 17.480237
B65: Options Granted | C65: 2.489824 | D65: 3.104215 | E65: 2.828125 | F65: 1.908688 | G65: 4.84 | H65: 3.614 | I65: 3.531 | J65: =J53*J66 -> 2.6748 | K65: 2.359 | L65: =L53*L66 -> 2.34408 | M65: =M53*M66 -> 1.816662 | N65: =N53*N66 -> 1.407913 | O65: =O53*O66 -> 1.0911326 | P65: =P53*P66 -> 0.84562778 | Q65: =Q53*Q66 -> 0.65536153 | R65: =R53*R66 -> 0.50790518 | S65: =S53*S66 -> 0.39362652 | ... X65: =X53*X66 -> 0.11005071
B66: % of Outstanding Options | C66: =IF(ISERROR(C65/C53), "NM", (C65/C53)) -> 0.27514604 | D66: =D65/D53 -> 0.29060527 | E66: =E65/E53 -> 0.22199078 | F66: =F65/F53 -> 0.13876757 | G66: =G65/G53 -> 0.24536145 | H66: =H65/H53 -> 0.22976667 | I66: =I65/I53 -> 0.29417646 | J66: 0.24 | K66: =K65/K53 -> 0.18660022 | L66: 0.24 | M66: 0.24 | N66: 0.24 | O66: 0.24 | P66: 0.24 | Q66: 0.24 | R66: 0.24 | S66: 0.24 | T66: 0.24 | U66: 0.24 | V66: 0.24 | W66: 0.24 | X66: 0.24
B68: Closing Balance | C68: =C53-C59+C65-C57 -> 10.681895 | D68: =D53-D59+D65-D57 -> 12.739831 | E68: =E53-E59+E65-E57 -> 13.754568 | F68: =F53-F59+F65-F57 -> 11.892167 | G68: =G53-G59+G65-G57 -> 15.729 | H68: =H53-H59+H65-H57 -> 12.003 | I68: =I53-I59+I65-I57 -> 11.145
B69: Keyed | C69: 10.681895 | D69: 12.739831 | E69: 13.754568 | F69: 11.892167 | G69: 15.729 | H69: 12.003 | I69: 11.145
B71: Check | C71: =C68-C69 -> 0 | D71: =D68-D69 -> 0 | E71: =E68-E69 -> 0 | F71: =F68-F69 -> 0 | G71: =G68-G69 -> 0 | H71: =H68-H69 -> 0 | I71: =I68-I69 -> 0 | J71: =J68-J69 -> 0 | ... X71: =X68-X69 -> 0
B73: Shares Issued | C73: 0.146 | D73: 0.173 | E73: 0.229 | F73: 0.288 | G73: 8.226 | H73: 7.975 | I73: 4.543 | J73: 0 | K73: 0 | L73: 0 | M73: 0 | N73: 0 | O73: 0 | P73: 0 | Q73: 0 | R73: 0 | S73: 0 | T73: 0 | U73: 0 | V73: 0 | W73: 0 | X73: 0
B74: Proceeds from share issuance | C74: =1.24+192.121 -> 193.361 | D74: 1.506 | E74: =2.526+168.042 -> 170.568 | F74: 4.284 | G74: 271.713 | H74: 274.743 | I74: 185.234 | J74: 0 | K74: 0 | L74: 0 | M74: 0 | N74: 0 | O74: 0 | P74: 0 | Q74: 0 | R74: 0 | S74: 0 | T74: 0 | U74: 0 | V74: 0 | W74: 0 | X74: 0
B75: Stock option exercises | C75: 3.505 | D75: 5.87 | E75: 12.325 | F75: 31.436 | G75: 0 | H75: 0 | J75: =J59 -> 4.458 | K75: =K59 -> 4.561 | L75: =L59 -> 3.9068 | M75: =M59 -> 3.02777 | N75: =N59 -> 2.3465217 | O75: =O59 -> 1.8185544 | P75: =P59 -> 1.4093796 | Q75: =Q59 -> 1.0922692 | ... X75: =X59 -> 0.18341785
B76: Warrant exercise | C76: 0 | D76: 0 | E76: 5.077 | F76: 0 | G76: 0 | H76: =G76 -> 0 | I76: 0 | J76: 0 | K76: 0 | L76: 0 | M76: 0 | N76: 0 | O76: 0 | P76: 0 | Q76: 0 | R76: 0 | S76: 0 | T76: 0 | U76: 0 | V76: 0 | W76: 0 | X76: 0
B77: Shares Repurchased (mm) | C77: 0 | D77: 0 | E77: 0 | F77: 0 | G77: 0 | H77: 0 | I77: 0 | J77: 0 | K77: 0 | L77: 0 | M77: 0 | N77: 0 | O77: 0 | P77: 0 | Q77: 0 | R77: 0 | S77: 0 | T77: 0 | U77: 0 | V77: 0 | W77: 0 | X77: 0
B78: Share Repurchase Cost | C78: 0 | D78: 0 | E78: 0 | F78: 0 | G78: 0 | H78: =H77*H52 -> 0 | I78: 0 | J78: 0 | K78: 0 | L78: 0 | M78: 0 | N78: 0 | O78: 0 | P78: 0 | Q78: 0 | R78: 0 | S78: 0 | T78: 0 | U78: 0 | V78: 0 | W78: 0 | X78: 0
B79: Stock options expense | C79: 11.849 | D79: 14.33 | E79: 19.984 | F79: 25.34 | G79: 127.883 | H79: 178.965 | I79: 235.112 | J79: =IS!AA140 -> 245 | K79: =IS!AF140 -> 290.736 | L79: =IS!AK140 -> 245 | M79: =IS!AP140 -> 245 | N79: =IS!AU140 -> 245 | O79: =IS!AZ140 -> 245 | P79: =IS!BE140 -> 245 | Q79: =IS!BJ140 -> 245 | R79: =IS!BO140 -> 245 | S79: =IS!BT140 -> 245 | T79: =IS!BY140 -> 245 | U79: =IS!CD140 -> 245 | V79: =IS!CI140 -> 245 | W79: =IS!CN140 -> 245 | X79: =IS!CS140 -> 245
B80: Tax benefit from equity compensation | G80: -1.252 | H80: 2.16 | I80: 0 | J80: =IS!AA131 -> 0 | K80: =IS!AF131 -> 0 | L80: =IS!AK131 -> 0 | M80: =IS!AP131 -> 0 | N80: =IS!AU131 -> 0 | O80: =IS!AZ131 -> 0 | P80: =IS!BE131 -> 0 | Q80: =IS!BJ131 -> 0 | R80: =IS!BO131 -> 0 | S80: =IS!BT131 -> 0 | T80: =IS!BY131 -> 0 | U80: =IS!CD131 -> 0 | V80: =IS!CI131 -> 0 | W80: =IS!CN131 -> 0 | X80: =IS!CS131 -> 0
B81: Others | C81: 0 | D81: 0 | E81: 0 | F81: 0 | G81: =402.182+1.312 -> 403.494 | H81: 0 | I81: 0 | J81: 0 | K81: 0 | L81: 0 | M81: 0 | N81: 0 | O81: 0 | P81: 0 | Q81: 0 | R81: 0 | S81: 0 | T81: 0 | U81: 0 | V81: 0 | W81: 0 | X81: 0
B82: Total Change in APIC | C82: =+C74+C78+C79+C81+C75+C76 -> 208.715 | D82: =+D74+D78+D79+D81+D75+D76 -> 21.706 | E82: =+E74+E78+E79+E81+E75+E76 -> 207.954 | F82: =+F74+F78+F79+F81+F75+F76 -> 61.06 | G82: =+G74+G78+G79+G81+G75+G76+G80 -> 801.838 | H82: =+H74+H78+H79+H81+H75+H76+H80 -> 455.868 | I82: =+I74+I78+I79+I81+I75+I76+I80 -> 420.346 | J82: =+J74+J78+J79+J81+J75+J76+J80 -> 249.458 | K82: =+K74+K78+K79+K81+K75+K76+K80 -> 295.297 | L82: =+L74+L78+L79+L81+L75+L76+L80 -> 248.9068 | M82: =+M74+M78+M79+M81+M75+M76+M80 -> 248.02777 | N82: =+N74+N78+N79+N81+N75+N76+N80 -> 247.34652 | ... X82: =+X74+X78+X79+X81+X75+X76+X80 -> 245.18342
B84: Check | G84: =BS!C36-4519.448-G82 -> 0 | H84: =BS!D36-BS!C36-H82 -> 0
B86: Beginning Period Shares | C86: 79.791 | D86: =C87 -> 100.554 | E86: =D87 -> 101.607 | F86: =E87 -> 116.023 | G86: 217.28687 | H86: =G87 -> 233.78885 | I86: =H87 -> 241.7644
B87: End of Period Shares | C87: 100.554 | D87: 101.607 | E87: 116.023 | F87: 119.71 | G87: 233.78885 | H87: 241.7644 | I87: 246.30682
B88: Average Shares Outstanding-basic | C88: 90.988 | D88: 101.055 | E88: 113.098 | F88: 117.851 | G88: =IS!L135 -> 224.906 | H88: =IS!Q135 -> 235.307 | I88: =IS!R135 -> 239.493
B89: Average Shares Outstanding-diluted | C89: 90.988 | D89: 101.055 | E89: 113.098 | F89: 117.851 | G89: =IS!L136 -> 224.906 | H89: =IS!Q136 -> 235.307 | I89: =IS!R136 -> 239.493
C92: 2009-FY | D92: 2010-FY | E92: 2011-FY | F92: 2012-FY

Sheet CF Market
C2: Case | D2: =DCF!C30 -> 2
B4: United States | G4: 2012 | H4: =G4+1 -> 2013 | I4: =H4+1 -> 2014 | J4: =I4+1 -> 2015 | K4: =J4+1 -> 2016 | L4: =K4+1 -> 2017 | M4: =L4+1 -> 2018 | N4: =M4+1 -> 2019 | O4: =N4+1 -> 2020 | ... Y4: =X4+1 -> 2030
B6: Penetration
B8: Kalydeco (2027 US Patent) | G8: =CHOOSE($D$2,G9,G10,G11) -> 0.93262638 | H8: =CHOOSE($D$2,H9,H10,H11) -> 0.93378602 | I8: =CHOOSE($D$2,I9,I10,I11) -> 0.97129247 | J8: =CHOOSE($D$2,J9,J10,J11) -> 0.97297931 | K8: =CHOOSE($D$2,K9,K10,K11) -> 0.97734449 | L8: =CHOOSE($D$2,L9,L10,L11) -> 0.915 | M8: =CHOOSE($D$2,M9,M10,M11) -> 0.9 | N8: =CHOOSE($D$2,N9,N10,N11) -> 0.9 | ... Y8: =CHOOSE($D$2,Y9,Y10,Y11) -> 0.09
C9: Bull | G9: =G108/G50 -> 0.93262638 | H9: =H108/H50 -> 0.93378602 | I9: =I108/I50 -> 0.97129247 | J9: =J108/J50 -> 0.97297931 | K9: =K108/K50 -> 0.97734449 | L9: 0.9 | M9: 0.9 | N9: 0.95 | O9: 0.95 | P9: 0.95 | Q9: 0.95 | R9: 0.95 | S9: 0.95 | T9: 0.95 | U9: 0.95 | V9: 0.95 | W9: =V9 -> 0.95 | X9: =W9 -> 0.95 | Y9: =X9 -> 0.95
C10: Base | G10: =G108/G50 -> 0.93262638 | H10: =H108/H50 -> 0.93378602 | I10: =I108/I50 -> 0.97129247 | J10: =J108/J50 -> 0.97297931 | K10: =K108/K50 -> 0.97734449 | L10: 0.915 | M10: 0.9 | N10: =M10 -> 0.9 | O10: =N10 -> 0.9 | P10: =O10 -> 0.9 | Q10: =P10 -> 0.9 | R10: =Q10 -> 0.9 | S10: =R10 -> 0.9 | T10: =S10 -> 0.9 | U10: =T10 -> 0.9 | V10: =U10 -> 0.9 | W10: 0.45 | X10: 0.09 | Y10: 0.09
C11: Bear | G11: =G108/G50 -> 0.93262638 | H11: =H108/H50 -> 0.93378602 | I11: =I108/I50 -> 0.97129247 | J11: =J108/J50 -> 0.97297931 | K11: =K108/K50 -> 0.97734449 | L11: =L10*0.9 -> 0.8235 | M11: =M10*0.9 -> 0.81 | N11: 0.85 | O11: 0.85 | P11: 0.85 | Q11: 0.85 | R11: 0.85 | S11: 0.85 | T11: 0.85 | U11: 0.85 | V11: 0.85 | W11: 0.3 | X11: 0 | Y11: 0
B13: Deuterated Kalydeco | O13: =CHOOSE($D$2,O14,O15,O16) -> 0.9 | P13: =CHOOSE($D$2,P14,P15,P16) -> 0.9 | Q13: =CHOOSE($D$2,Q14,Q15,Q16) -> 0.9 | R13: =CHOOSE($D$2,R14,R15,R16) -> 0.9 | S13: =CHOOSE($D$2,S14,S15,S16) -> 0.9 | T13: =CHOOSE($D$2,T14,T15,T16) -> 0.9 | U13: =CHOOSE($D$2,U14,U15,U16) -> 0.9 | V13: =CHOOSE($D$2,V14,V15,V16) -> 0.9 | ... Y13: =CHOOSE($D$2,Y14,Y15,Y16) -> 0.9
C14: Bull | O14: =O9 -> 0.95 | P14: =P9 -> 0.95 | Q14: =Q9 -> 0.95 | R14: =R9 -> 0.95 | S14: =S9 -> 0.95 | T14: =T9 -> 0.95 | U14: =U9 -> 0.95 | V14: =V9 -> 0.95 | W14: =V14 -> 0.95 | X14: =W14 -> 0.95 | Y14: =X14 -> 0.95
