Workbook
Name _Agreement1: AGREEMENTS!$H$9:$S$83
Name _Agreement2: AGREEMENTS!$H$84:$S$146
Name _AIS: 'IS-ANNUAL'!$H$9:$CE$79
Name _ARev1: 'REV-ANNUAL'!$H$9:$CE$82
Name _ARev2: 'REV-ANNUAL'!$H$106:$CE$217
Name _ARev3: 'REV-ANNUAL'!$H$219:$CE$237
Name _ARev4: 'REV-ANNUAL'!$H$239:$CE$333
Name _ARev5: 'REV-ANNUAL'!$H$336:$CE$447
Name _ARev6: 'REV-ANNUAL'!$H$449:$CE$467
Name _BS: CFBS!$H$64:$CE$115
Name _CF: CFBS!$H$9:$CE$59
Name _DCF: DCF!$H$9:$CE$59
Name _FCF: DCF!$H$9:$CE$14
Name _FinMet: CFBS!$H$120:$CE$183
Name _Footnotes: FOOTNOTES!$H$10:$P$268
Name _MgmtProj: 'MGMT PROJECTIONS'!$H$10:$O$22
Name _Pipe1: PIPELINE!$H$9:$CE$45
Name _Pipe2: PIPELINE!$H$46:$CE$78
Name _TheoPipe: PIPELINE!$H$80:$CE$91
Name AdditionalInstructions: IndexInformation!$B$42
Name Address: ImportantDisclosures!$A$2:$A$2
Name ANA: ModPubIndex!$A$7
Name Authors: ImportantDisclosures!$A$7
Name Authors: IndexInformation!$B$18
Name BRO: ModPubIndex!$A$1
Name CompanyName: summary!$J$7
Name CompanyName: summary!$J$7
Name CompanyName: summary!$J$7
Name CompanyName: summary!$J$7
Name CompanyName: summary!$J$7
Name CompanyName: summary!$J$7
Name CompanyName: summary!$J$7
Name CompanyName: summary!$J$7
Name CompanyName: summary!$J$7
Name CompanyName: summary!$J$7
Name CompanyName: summary!$J$7
Name CompanyTicker: summary!$J$8
Name CompanyTicker: summary!$J$8
Name CopyrightStamp: ImportantDisclosures!$A$27
Name COU: ModPubIndex!$A$5
Name CQEnd: IndexInformation!$B$31
Name Currency: IndexInformation!$B$24
Name CurrentStockPrice: IndexInformation!$B$23
Name CurrPrice: [11]summary!$J$16
Name CurrQtrEPS: IndexInformation!$B$29
Name CurrYearEPS: IndexInformation!$B$11
Name CurrYearTotalRevenue: IndexInformation!$B$10
Name CurrYearTotalRevenueActual: IndexInformation!$B$32
Name CUSIP: IndexInformation!$B$20
Name CYEnd: IndexInformation!$B$30
Name dataseries4: OFFSET([12]c1!$G$12,0,0,COUNTA([12]c1!$G$12:$G$31),1)
Name Date: ImportantDisclosures!$A$8
Name Deleted: IndexInformation!$B$27
Name Description: IndexInformation!$B$7
Name Discipline: IndexInformation!$B$3
Name DISCIPLINE: ModPubIndex!$A$12
Name DisclosuresText: ImportantDisclosures!$A$22
Name Distribution: IndexInformation!$B$26
Name DistTable: ImportantDisclosures!#REF!
Name DistTablePreamble: ImportantDisclosures!#REF!

Sheet summary
FZ1: Section Header
L4: 38442 | M4: 38533 | N4: 38625 | O4: 38717 | P4: 38717 | Q4: 38807 | R4: 38898 | S4: 38990 | T4: 39082 | U4: 39082 | V4: 39172 | W4: 39263 | X4: 39355 | Y4: 39447 | Z4: 39447 | AA4: 39538 | AB4: 39629 | AC4: 39721 | AD4: 39813 | AE4: 39813 | AF4: 39903 | AG4: 39994 | AH4: 40086 | AI4: 40178 | AJ4: 40178 | AK4: 40268 | AL4: 40359 | AM4: 40451 | AN4: 40543 | AO4: 40543 | AP4: 40633 | AQ4: 40724 | AR4: 40816 | AS4: 40908 | AT4: 40908 | AU4: 40999 | AV4: 41090 | AW4: 41182 | AX4: 41274 | AY4: 41274 | AZ4: 41364 | BA4: 41455 | BB4: 41547 | BC4: 41639 | BD4: 41639 | BE4: 41729 | BF4: 41820 | BG4: 41912 | BH4: 42004 | BI4: 42004 | BJ4: 42094 | BK4: 42185 | BL4: 42277 | BM4: 42369 | BN4: 42369 | BO4: 42460 | BP4: 42551 | BQ4: 42643 | BR4: 42735 | BS4: 42735 | BT4: 42825 | BU4: 42916 | BV4: 43008 | BW4: 43100 | BX4: 43100 | BY4: 43190 | BZ4: 43281 | CA4: 43373 | CB4: 43465 | CC4: 43465 | CD4: 43555 | CE4: 43646 | CF4: 43738 | CG4: 43830 | CH4: 43830 | CI4: 43921 | CJ4: 44012 | CK4: 44104 | CL4: 44196 | CM4: 44196
H5: =CompanyName -> Eli Lilly & Co. | J5: =LatestRpQ -> 43190
H6: summary page | J6: =LatestFiledQ -> 43100
H7: Company name | J7: Eli Lilly & Co.
H8: Ticker | J8: LLY
H9: TRSL ticker | J9: LLY-N
H10: Latest reported quarter | J10: 43190
H11: Latest filed quarter | J11: 43100 | CP11: Bear | CQ11: Rev disapointment | CR11: Base | CS11: EPS upside | CT11: M&A | CU11: PE expan | CV11: Bull
H12: Rating | J12: Equal-weight | CQ12: 23 | CS12: 5 | CT12: 5 | CU12: 9
H13: Price Target | J13: 93 | CP13: =CQ13 -> 67 | CQ13: =CR13-CQ12 -> 67 | CR13: 90 | CS13: =CR13 -> 90 | CT13: =CS12+CS13 -> 95 | CU13: =CT12+CT13 -> 100 | CV13: =CU12+CU13 -> 109
H14: Date Last Updated | J14: 43214
H15: MW ticker | J15: LLY.N
H17: Price | J17: =_xll.ThomsonONEAddinShim.SpreadsheetFormulas.TF($J$9,"TF.PR.PriceClose()") -> $80.09 | K17: =_xll.ThomsonONEAddinShim.SpreadsheetFormulas.TF(FDS_ticker, "TF.PR.Pricedate()") -> 43214
H18: Shares Outstanding (Qtr) | J18: ='IS-ANNUAL'!BN50 -> 1065.668
H19: Market Cap | J19: =J18*J17 -> 85349.35
H21: Net Debt (Qtr) | J21: =CFBS!BI172 -> 3194.5
H23: Total Enterprise Value | J23: =J19+J21 -> 88543.85
H24: No. of Employees | J24: 38270
H25: Current Quarter EPS | J25: ='IS-ANNUAL'!BC49 -> 0.73857064
H26: Date | J26: =LatestRpQ -> 43190
H27: Last Year's Quarter EPS | J27: ='IS-ANNUAL'!AX49 -> 0.84857317
H29: Stockholder's Equity (Yr) | J29: =CFBS!AY113 -> 14773.9
H30: Book Value per share (Qtr) | J30: =CFBS!BB156 -> 15.583114
H31: LT Debt/Total Capital | J31: =CFBS!AY176 -> 0.27240805
H32: Date | J32: =CFBS!AY9 -> 2012A
H34: IBES Growth Rate | J34: =_xll.ThomsonONEAddinShim.SpreadsheetFormulas.TF(FDS_ticker, "TF.ES.EPS.LTGMean()") -> 0.12 | AE34: =78/4.51 -> 17.2949
H36: Beginning year | J36: 2016a | K36: 2017e | AE36: =AE34/9 -> 1.9216556
H37: Ending year | J37: 2020e | K37: 2020E
H38: CAGR number of yrs | J38: 4 | K38: 3
J40: =J36 & "–" & J37 & " CAGR" -> 2016a–2020e CAGR | K40: =K36 & "–" & K37 & " CAGR" -> 2017e–2020E CAGR
H41: ='IS-ANNUAL'!H11 -> Total revenues | J41: =(INDEX('IS-ANNUAL'!$11:$11,0,MATCH(summary!$J$37,'IS-ANNUAL'!$9:$9,0))/INDEX('IS-ANNUAL'!$11:$11,0,MATCH(summary!$J$36,'IS-ANNUAL'!$9:$9,0)))^(1/$J$38)-1 -> 0.047269598 | K41: =(INDEX('IS-ANNUAL'!$11:$11,0,MATCH(summary!$K$37,'IS-ANNUAL'!$9:$9,0))/INDEX('IS-ANNUAL'!$11:$11,0,MATCH(summary!$K$36,'IS-ANNUAL'!$9:$9,0)))^(1/$K$38)-1 -> #N/A
H42: ='IS-ANNUAL'!H24 -> COGS | J42: =(INDEX('IS-ANNUAL'!$24:$24,0,MATCH(summary!$J$37,'IS-ANNUAL'!$9:$9,0))/INDEX('IS-ANNUAL'!$24:$24,0,MATCH(summary!$J$36,'IS-ANNUAL'!$9:$9,0)))^(1/$J$38)-1 -> 0.04754276 | K42: =(INDEX('IS-ANNUAL'!$24:$24,0,MATCH(summary!$K$37,'IS-ANNUAL'!$9:$9,0))/INDEX('IS-ANNUAL'!$24:$24,0,MATCH(summary!$K$36,'IS-ANNUAL'!$9:$9,0)))^(1/$K$38)-1 -> #N/A
H43: ='IS-ANNUAL'!H25 -> Gross profit | J43: =(INDEX('IS-ANNUAL'!$25:$25,0,MATCH(summary!$J$37,'IS-ANNUAL'!$9:$9,0))/INDEX('IS-ANNUAL'!$25:$25,0,MATCH(summary!$J$36,'IS-ANNUAL'!$9:$9,0)))^(1/$J$38)-1 -> 0.047185756 | K43: =(INDEX('IS-ANNUAL'!$25:$25,0,MATCH(summary!$K$37,'IS-ANNUAL'!$9:$9,0))/INDEX('IS-ANNUAL'!$25:$25,0,MATCH(summary!$K$36,'IS-ANNUAL'!$9:$9,0)))^(1/$K$38)-1 -> #N/A
H44: ='IS-ANNUAL'!H28 -> R&D | J44: =(INDEX('IS-ANNUAL'!$28:$28,0,MATCH(summary!$J$37,'IS-ANNUAL'!$9:$9,0))/INDEX('IS-ANNUAL'!$28:$28,0,MATCH(summary!$J$36,'IS-ANNUAL'!$9:$9,0)))^(1/$J$38)-1 -> 0.0032337096 | K44: =(INDEX('IS-ANNUAL'!$28:$28,0,MATCH(summary!$K$37,'IS-ANNUAL'!$9:$9,0))/INDEX('IS-ANNUAL'!$28:$28,0,MATCH(summary!$K$36,'IS-ANNUAL'!$9:$9,0)))^(1/$K$38)-1 -> #N/A
H45: ='IS-ANNUAL'!H26 -> SG&A | J45: =(INDEX('IS-ANNUAL'!$26:$26,0,MATCH(summary!$J$37,'IS-ANNUAL'!$9:$9,0))/INDEX('IS-ANNUAL'!$26:$26,0,MATCH(summary!$J$36,'IS-ANNUAL'!$9:$9,0)))^(1/$J$38)-1 -> -0.0029484618 | K45: =(INDEX('IS-ANNUAL'!$26:$26,0,MATCH(summary!$K$37,'IS-ANNUAL'!$9:$9,0))/INDEX('IS-ANNUAL'!$26:$26,0,MATCH(summary!$K$36,'IS-ANNUAL'!$9:$9,0)))^(1/$K$38)-1 -> #N/A
H46: ='IS-ANNUAL'!H29 -> Operating income, EBITA | J46: =(INDEX('IS-ANNUAL'!$29:$29,0,MATCH(summary!$J$37,'IS-ANNUAL'!$9:$9,0))/INDEX('IS-ANNUAL'!$29:$29,0,MATCH(summary!$J$36,'IS-ANNUAL'!$9:$9,0)))^(1/$J$38)-1 -> 0.14608052 | K46: =(INDEX('IS-ANNUAL'!$29:$29,0,MATCH(summary!$K$37,'IS-ANNUAL'!$9:$9,0))/INDEX('IS-ANNUAL'!$29:$29,0,MATCH(summary!$K$36,'IS-ANNUAL'!$9:$9,0)))^(1/$K$38)-1 -> #N/A
H47: ='IS-ANNUAL'!H44 -> Pretax income | J47: =(INDEX('IS-ANNUAL'!$44:$44,0,MATCH(summary!$J$37,'IS-ANNUAL'!$9:$9,0))/INDEX('IS-ANNUAL'!$44:$44,0,MATCH(summary!$J$36,'IS-ANNUAL'!$9:$9,0)))^(1/$J$38)-1 -> 0.14489102 | K47: =(INDEX('IS-ANNUAL'!$44:$44,0,MATCH(summary!$K$37,'IS-ANNUAL'!$9:$9,0))/INDEX('IS-ANNUAL'!$44:$44,0,MATCH(summary!$K$36,'IS-ANNUAL'!$9:$9,0)))^(1/$K$38)-1 -> #N/A
H48: ='IS-ANNUAL'!H47 -> Net income | J48: =(INDEX('IS-ANNUAL'!$47:$47,0,MATCH(summary!$J$37,'IS-ANNUAL'!$9:$9,0))/INDEX('IS-ANNUAL'!$47:$47,0,MATCH(summary!$J$36,'IS-ANNUAL'!$9:$9,0)))^(1/$J$38)-1 -> 0.15766638 | K48: =(INDEX('IS-ANNUAL'!$47:$47,0,MATCH(summary!$K$37,'IS-ANNUAL'!$9:$9,0))/INDEX('IS-ANNUAL'!$47:$47,0,MATCH(summary!$K$36,'IS-ANNUAL'!$9:$9,0)))^(1/$K$38)-1 -> #N/A
H49: ='IS-ANNUAL'!H49 -> Adj. Dil. EPS | J49: =(INDEX('IS-ANNUAL'!$49:$49,0,MATCH(summary!$J$37,'IS-ANNUAL'!$9:$9,0))/INDEX('IS-ANNUAL'!$49:$49,0,MATCH(summary!$J$36,'IS-ANNUAL'!$9:$9,0)))^(1/$J$38)-1 -> 0.16275907 | K49: =(INDEX('IS-ANNUAL'!$49:$49,0,MATCH(summary!$K$37,'IS-ANNUAL'!$9:$9,0))/INDEX('IS-ANNUAL'!$49:$49,0,MATCH(summary!$K$36,'IS-ANNUAL'!$9:$9,0)))^(1/$K$38)-1 -> #N/A
H51: ($M) | L51: ="1Q:" & RIGHT(YEAR(L$4),2) & IF(L$4<=LatestRpQ, "A", "E") -> 1Q:05A | M51: ="2Q:" & RIGHT(YEAR(M$4),2) & IF(M$4<=LatestRpQ, "A", "E") -> 2Q:05A | N51: ="3Q:" & RIGHT(YEAR(N$4),2) & IF(N$4<=LatestRpQ, "A", "E") -> 3Q:05A | O51: ="4Q:" & RIGHT(YEAR(O$4),2) & IF(O$4<=LatestRpQ, "A", "E") -> 4Q:05A | P51: =YEAR(P$4) & IF(P$4<=LatestRpQ, "A", "E") -> 2005A | Q51: ="1Q:" & RIGHT(YEAR(Q$4),2) & IF(Q$4<=LatestRpQ, "A", "E") -> 1Q:06A | R51: ="2Q:" & RIGHT(YEAR(R$4),2) & IF(R$4<=LatestRpQ, "A", "E") -> 2Q:06A | S51: ="3Q:" & RIGHT(YEAR(S$4),2) & IF(S$4<=LatestRpQ, "A", "E") -> 3Q:06A | T51: ="4Q:" & RIGHT(YEAR(T$4),2) & IF(T$4<=LatestRpQ, "A", "E") -> 4Q:06A | U51: =YEAR(U$4) & IF(U$4<=LatestRpQ, "A", "E") -> 2006A | V51: ="1Q:" & RIGHT(YEAR(V$4),2) & IF(V$4<=LatestRpQ, "A", "E") -> 1Q:07A | W51: ="2Q:" & RIGHT(YEAR(W$4),2) & IF(W$4<=LatestRpQ, "A", "E") -> 2Q:07A | X51: ="3Q:" & RIGHT(YEAR(X$4),2) & IF(X$4<=LatestRpQ, "A", "E") -> 3Q:07A | Y51: ="4Q:" & RIGHT(YEAR(Y$4),2) & IF(Y$4<=LatestRpQ, "A", "E") -> 4Q:07A | Z51: =YEAR(Z$4) & IF(Z$4<=LatestRpQ, "A", "E") -> 2007A | AA51: ="1Q:" & RIGHT(YEAR(AA$4),2) & IF(AA$4<=LatestRpQ, "A", "E") -> 1Q:08A | AB51: ="2Q:" & RIGHT(YEAR(AB$4),2) & IF(AB$4<=LatestRpQ, "A", "E") -> 2Q:08A | AC51: ="3Q:" & RIGHT(YEAR(AC$4),2) & IF(AC$4<=LatestRpQ, "A", "E") -> 3Q:08A | AD51: ="4Q:" & RIGHT(YEAR(AD$4),2) & IF(AD$4<=LatestRpQ, "A", "E") -> 4Q:08A | AE51: =YEAR(AE$4) & IF(AE$4<=LatestRpQ, "A", "E") -> 2008A | AF51: ="1Q:" & RIGHT(YEAR(AF$4),2) & IF(AF$4<=LatestRpQ, "A", "E") -> 1Q:09A | AG51: ="2Q:" & RIGHT(YEAR(AG$4),2) & IF(AG$4<=LatestRpQ, "A", "E") -> 2Q:09A | AH51: ="3Q:" & RIGHT(YEAR(AH$4),2) & IF(AH$4<=LatestRpQ, "A", "E") -> 3Q:09A | AI51: ="4Q:" & RIGHT(YEAR(AI$4),2) & IF(AI$4<=LatestRpQ, "A", "E") -> 4Q:09A | AJ51: =YEAR(AJ$4) & IF(AJ$4<=LatestRpQ, "A", "E") -> 2009A | AK51: ="1Q:" & RIGHT(YEAR(AK$4),2) & IF(AK$4<=LatestRpQ, "A", "E") -> 1Q:10A | AL51: ="2Q:" & RIGHT(YEAR(AL$4),2) & IF(AL$4<=LatestRpQ, "A", "E") -> 2Q:10A | AM51: ="3Q:" & RIGHT(YEAR(AM$4),2) & IF(AM$4<=LatestRpQ, "A", "E") -> 3Q:10A | AN51: ="4Q:" & RIGHT(YEAR(AN$4),2) & IF(AN$4<=LatestRpQ, "A", "E") -> 4Q:10A | AO51: =YEAR(AO$4) & IF(AO$4<=LatestRpQ, "A", "E") -> 2010A | AP51: ="1Q:" & RIGHT(YEAR(AP$4),2) & IF(AP$4<=LatestRpQ, "A", "E") -> 1Q:11A | AQ51: ="2Q:" & RIGHT(YEAR(AQ$4),2) & IF(AQ$4<=LatestRpQ, "A", "E") -> 2Q:11A | AR51: ="3Q:" & RIGHT(YEAR(AR$4),2) & IF(AR$4<=LatestRpQ, "A", "E") -> 3Q:11A | AS51: ="4Q:" & RIGHT(YEAR(AS$4),2) & IF(AS$4<=LatestRpQ, "A", "E") -> 4Q:11A | AT51: =YEAR(AT$4) & IF(AT$4<=LatestRpQ, "A", "E") -> 2011A | AU51: ="1Q:" & RIGHT(YEAR(AU$4),2) & IF(AU$4<=LatestRpQ, "A", "E") -> 1Q:12A | AV51: ="2Q:" & RIGHT(YEAR(AV$4),2) & IF(AV$4<=LatestRpQ, "A", "E") -> 2Q:12A | AW51: ="3Q:" & RIGHT(YEAR(AW$4),2) & IF(AW$4<=LatestRpQ, "A", "E") -> 3Q:12A | AX51: ="4Q:" & RIGHT(YEAR(AX$4),2) & IF(AX$4<=LatestRpQ, "A", "E") -> 4Q:12A | AY51: =YEAR(AY$4) & IF(AY$4<=LatestRpQ, "A", "E") -> 2012A | AZ51: ="1Q:" & RIGHT(YEAR(AZ$4),2) & IF(AZ$4<=LatestRpQ, "A", "E") -> 1Q:13A | BA51: ="2Q:" & RIGHT(YEAR(BA$4),2) & IF(BA$4<=LatestRpQ, "A", "E") -> 2Q:13A | BB51: ="3Q:" & RIGHT(YEAR(BB$4),2) & IF(BB$4<=LatestRpQ, "A", "E") -> 3Q:13A | BC51: ="4Q:" & RIGHT(YEAR(BC$4),2) & IF(BC$4<=LatestRpQ, "A", "E") -> 4Q:13A | BD51: =YEAR(BD$4) & IF(BD$4<=LatestRpQ, "A", "E") -> 2013A | BE51: ="1Q:" & RIGHT(YEAR(BE$4),2) & IF(BE$4<=LatestRpQ, "A", "E") -> 1Q:14A | BF51: ="2Q:" & RIGHT(YEAR(BF$4),2) & IF(BF$4<=LatestRpQ, "A", "E") -> 2Q:14A | BG51: ="3Q:" & RIGHT(YEAR(BG$4),2) & IF(BG$4<=LatestRpQ, "A", "E") -> 3Q:14A | BH51: ="4Q:" & RIGHT(YEAR(BH$4),2) & IF(BH$4<=LatestRpQ, "A", "E") -> 4Q:14A | BI51: =YEAR(BI$4) & IF(BI$4<=LatestRpQ, "A", "E") -> 2014A | BJ51: ="1Q:" & RIGHT(YEAR(BJ$4),2) & IF(BJ$4<=LatestRpQ, "A", "E") -> 1Q:15A | BK51: ="2Q:" & RIGHT(YEAR(BK$4),2) & IF(BK$4<=LatestRpQ, "A", "E") -> 2Q:15A | BL51: ="3Q:" & RIGHT(YEAR(BL$4),2) & IF(BL$4<=LatestRpQ, "A", "E") -> 3Q:15A | BM51: ="4Q:" & RIGHT(YEAR(BM$4),2) & IF(BM$4<=LatestRpQ, "A", "E") -> 4Q:15A | BN51: =YEAR(BN$4) & IF(BN$4<=LatestRpQ, "A", "E") -> 2015A | BO51: ="1Q:" & RIGHT(YEAR(BO$4),2) & IF(BO$4<=LatestRpQ, "A", "E") -> 1Q:16A | BP51: ="2Q:" & RIGHT(YEAR(BP$4),2) & IF(BP$4<=LatestRpQ, "A", "E") -> 2Q:16A | BQ51: ="3Q:" & RIGHT(YEAR(BQ$4),2) & IF(BQ$4<=LatestRpQ, "A", "E") -> 3Q:16A | BR51: ="4Q:" & RIGHT(YEAR(BR$4),2) & IF(BR$4<=LatestRpQ, "A", "E") -> 4Q:16A | BS51: =YEAR(BS$4) & IF(BS$4<=LatestRpQ, "A", "E") -> 2016A | BT51: ="1Q:" & RIGHT(YEAR(BT$4),2) & IF(BT$4<=LatestRpQ, "A", "E") -> 1Q:17A | BU51: ="2Q:" & RIGHT(YEAR(BU$4),2) & IF(BU$4<=LatestRpQ, "A", "E") -> 2Q:17A | BV51: ="3Q:" & RIGHT(YEAR(BV$4),2) & IF(BV$4<=LatestRpQ, "A", "E") -> 3Q:17A | BW51: ="4Q:" & RIGHT(YEAR(BW$4),2) & IF(BW$4<=LatestRpQ, "A", "E") -> 4Q:17A | BX51: =YEAR(BX$4) & IF(BX$4<=LatestRpQ, "A", "E") -> 2017A | BY51: ="1Q:" & RIGHT(YEAR(BY$4),2) & IF(BY$4<=LatestRpQ, "A", "E") -> 1Q:18A | BZ51: ="2Q:" & RIGHT(YEAR(BZ$4),2) & IF(BZ$4<=LatestRpQ, "A", "E") -> 2Q:18E | CA51: ="3Q:" & RIGHT(YEAR(CA$4),2) & IF(CA$4<=LatestRpQ, "A", "E") -> 3Q:18E | CB51: ="4Q:" & RIGHT(YEAR(CB$4),2) & IF(CB$4<=LatestRpQ, "A", "E") -> 4Q:18E | CC51: =YEAR(CC$4) & IF(CC$4<=LatestRpQ, "A", "E") -> 2018E | CD51: ="1Q:" & RIGHT(YEAR(CD$4),2) & IF(CD$4<=LatestRpQ, "A", "E") -> 1Q:19E | CE51: ="2Q:" & RIGHT(YEAR(CE$4),2) & IF(CE$4<=LatestRpQ, "A", "E") -> 2Q:19E | CF51: ="3Q:" & RIGHT(YEAR(CF$4),2) & IF(CF$4<=LatestRpQ, "A", "E") -> 3Q:19E | CG51: ="4Q:" & RIGHT(YEAR(CG$4),2) & IF(CG$4<=LatestRpQ, "A", "E") -> 4Q:19E | CH51: =YEAR(CH$4) & IF(CH$4<=LatestRpQ, "A", "E") -> 2019E | CI51: ="1Q:" & RIGHT(YEAR(CI$4),2) & IF(CI$4<=LatestRpQ, "A", "E") -> 1Q:20E | CJ51: ="2Q:" & RIGHT(YEAR(CJ$4),2) & IF(CJ$4<=LatestRpQ, "A", "E") -> 2Q:20E | CK51: ="3Q:" & RIGHT(YEAR(CK$4),2) & IF(CK$4<=LatestRpQ, "A", "E") -> 3Q:20E | CL51: ="4Q:" & RIGHT(YEAR(CL$4),2) & IF(CL$4<=LatestRpQ, "A", "E") -> 4Q:20E | CM51: =YEAR(CM$4) & IF(CM$4<=LatestRpQ, "A", "E") -> 2020E
H53: Endocrinology-non Diabetes | BN53: ='REV-ANNUAL'!BN47-BN54 -> 2210.4 | BS53: ='REV-ANNUAL'!BS47-BS54 -> 2297.7 | BX53: ='REV-ANNUAL'!BX47-BX54 -> 2437.5 | CC53: ='REV-ANNUAL'!CC47-CC54 -> 2172.995 | CH53: ='REV-ANNUAL'!CD47-CH54 -> 1890.1837 | CM53: ='REV-ANNUAL'!CE47-CM54 -> 1482.8745
H54: Endocrinology- Diabetes | BN54: ='REV-ANNUAL'!BN50+'REV-ANNUAL'!BN53+'REV-ANNUAL'!BN68+'REV-ANNUAL'!BN71+'REV-ANNUAL'!BN74+'REV-ANNUAL'!BN77 -> 4826.4 | BS54: ='REV-ANNUAL'!BS50+'REV-ANNUAL'!BS53+'REV-ANNUAL'!BS68+'REV-ANNUAL'!BS71+'REV-ANNUAL'!BS74+'REV-ANNUAL'!BS77 -> 5785.1 | BX54: ='REV-ANNUAL'!BX50+'REV-ANNUAL'!BX53+'REV-ANNUAL'!BX68+'REV-ANNUAL'!BX71+'REV-ANNUAL'!BX74+'REV-ANNUAL'!BX77 -> 7647.8 | CC54: ='REV-ANNUAL'!CC50+'REV-ANNUAL'!CC53+'REV-ANNUAL'!CC68+'REV-ANNUAL'!CC71+'REV-ANNUAL'!CC74+'REV-ANNUAL'!CC77 -> 9708.719 | CH54: ='REV-ANNUAL'!CD50+'REV-ANNUAL'!CD53+'REV-ANNUAL'!CD68+'REV-ANNUAL'!CD71+'REV-ANNUAL'!CD74+'REV-ANNUAL'!CD77 -> 10776.099 | CM54: ='REV-ANNUAL'!CE50+'REV-ANNUAL'!CE53+'REV-ANNUAL'!CE68+'REV-ANNUAL'!CE71+'REV-ANNUAL'!CE74+'REV-ANNUAL'!CE77 -> 11389.554
H55: Oncology | BN55: ='REV-ANNUAL'!BN106+'REV-ANNUAL'!#REF!+PIPELINE!#REF! -> #REF! | BS55: ='REV-ANNUAL'!BS106+'REV-ANNUAL'!#REF!+PIPELINE!#REF! -> #REF! | BX55: ='REV-ANNUAL'!BX106+'REV-ANNUAL'!#REF!+PIPELINE!#REF! -> #REF! | CC55: ='REV-ANNUAL'!CC106+'REV-ANNUAL'!#REF!+PIPELINE!#REF! -> #REF! | CH55: ='REV-ANNUAL'!CD106+'REV-ANNUAL'!#REF!+PIPELINE!#REF! -> #REF! | CM55: ='REV-ANNUAL'!CE106+'REV-ANNUAL'!#REF!+PIPELINE!#REF! -> #REF!
H56: Cardiovascular | BN56: ='REV-ANNUAL'!BN137 -> 3068 | BS56: ='REV-ANNUAL'!BS137 -> 3225.4 | BX56: ='REV-ANNUAL'!BX137 -> 2871.3 | CC56: ='REV-ANNUAL'!CC137 -> 1746.538 | CH56: ='REV-ANNUAL'!CD137 -> 691.9092 | CM56: ='REV-ANNUAL'!CE137 -> 588.41256
H57: Neuroscience | BN57: ='REV-ANNUAL'!BN15 -> 2935.5 | BS57: ='REV-ANNUAL'!BS15+PIPELINE!BS14+PIPELINE!BS17+PIPELINE!BS11+PIPELINE!BS29 -> 2720.3 | BX57: ='REV-ANNUAL'!BX15+PIPELINE!BX14+PIPELINE!BX17+PIPELINE!BX11+PIPELINE!BX29 -> 2171.1 | CC57: ='REV-ANNUAL'!CC15+PIPELINE!CC14+PIPELINE!CC17+PIPELINE!CC11+PIPELINE!CC29 -> 1818.946 | CH57: ='REV-ANNUAL'!CD15+PIPELINE!CD14+PIPELINE!CD17+PIPELINE!CD11+PIPELINE!CD29 -> 1632.6671 | CM57: ='REV-ANNUAL'!CE15+PIPELINE!CE14+PIPELINE!CE17+PIPELINE!CE11+PIPELINE!CE29 -> 1564.7208
H58: Immunology | BN58: ='REV-ANNUAL'!BN168+PIPELINE!BN20 -> 0 | BS58: ='REV-ANNUAL'!BS168+PIPELINE!BS20 -> 113.1 | BX58: ='REV-ANNUAL'!BX168+PIPELINE!BX20 -> 605 | CC58: ='REV-ANNUAL'!CC168+PIPELINE!CC20 -> 972.944 | CH58: ='REV-ANNUAL'!CD168+PIPELINE!CD20 -> 1406.8506 | CM58: ='REV-ANNUAL'!CE168+PIPELINE!CE20 -> 1832.6657
H59: Other Pharmaceuticals | BN59: ='REV-ANNUAL'!BN178+PIPELINE!BN32 -> 227.5 | BS59: ='REV-ANNUAL'!BS178+PIPELINE!BS32 -> 200.5 | BX59: ='REV-ANNUAL'!BX178+PIPELINE!BX32 -> 241.3 | CC59: ='REV-ANNUAL'!CC178+PIPELINE!CC32 -> 245.89 | CH59: ='REV-ANNUAL'!CD178+PIPELINE!CD32 -> 233.5955 | CM59: ='REV-ANNUAL'!CE178+PIPELINE!CE32 -> 221.91572
H60: Animal Health | BN60: ='REV-ANNUAL'!BN206 -> 3181.1 | BS60: ='REV-ANNUAL'!BS206 -> 3158.2 | BX60: ='REV-ANNUAL'!BX206 -> 3085.7 | CC60: ='REV-ANNUAL'!CC206 -> 3161.501 | CH60: ='REV-ANNUAL'!CD206 -> 3369.7132 | CM60: ='REV-ANNUAL'!CE206 -> 3602.4887
BN61: =SUM(BN53:BN60) -> #REF! | BS61: =SUM(BS53:BS60) -> #REF! | BX61: =SUM(BX53:BX60) -> #REF! | CC61: =SUM(CC53:CC60) -> #REF! | CH61: =SUM(CH53:CH60) -> #REF! | CM61: =SUM(CM53:CM60) -> #REF!
I62: % of total | BS62: =YEAR(BS$4) & IF(BS$4<=LatestRpQ, "A", "E") -> 2016A | BT62: ="1Q:" & RIGHT(YEAR(BT$4),2) & IF(BT$4<=LatestRpQ, "A", "E") -> 1Q:17A | BU62: ="2Q:" & RIGHT(YEAR(BU$4),2) & IF(BU$4<=LatestRpQ, "A", "E") -> 2Q:17A | BV62: ="3Q:" & RIGHT(YEAR(BV$4),2) & IF(BV$4<=LatestRpQ, "A", "E") -> 3Q:17A | BW62: ="4Q:" & RIGHT(YEAR(BW$4),2) & IF(BW$4<=LatestRpQ, "A", "E") -> 4Q:17A | BX62: =YEAR(BX$4) & IF(BX$4<=LatestRpQ, "A", "E") -> 2017A | BY62: ="1Q:" & RIGHT(YEAR(BY$4),2) & IF(BY$4<=LatestRpQ, "A", "E") -> 1Q:18A | BZ62: ="2Q:" & RIGHT(YEAR(BZ$4),2) & IF(BZ$4<=LatestRpQ, "A", "E") -> 2Q:18E | CA62: ="3Q:" & RIGHT(YEAR(CA$4),2) & IF(CA$4<=LatestRpQ, "A", "E") -> 3Q:18E | CB62: ="4Q:" & RIGHT(YEAR(CB$4),2) & IF(CB$4<=LatestRpQ, "A", "E") -> 4Q:18E | CC62: =YEAR(CC$4) & IF(CC$4<=LatestRpQ, "A", "E") -> 2018E | CD62: ="1Q:" & RIGHT(YEAR(CD$4),2) & IF(CD$4<=LatestRpQ, "A", "E") -> 1Q:19E | CE62: ="2Q:" & RIGHT(YEAR(CE$4),2) & IF(CE$4<=LatestRpQ, "A", "E") -> 2Q:19E | CF62: ="3Q:" & RIGHT(YEAR(CF$4),2) & IF(CF$4<=LatestRpQ, "A", "E") -> 3Q:19E | CG62: ="4Q:" & RIGHT(YEAR(CG$4),2) & IF(CG$4<=LatestRpQ, "A", "E") -> 4Q:19E | CH62: =YEAR(CH$4) & IF(CH$4<=LatestRpQ, "A", "E") -> 2019E | CI62: ="1Q:" & RIGHT(YEAR(CI$4),2) & IF(CI$4<=LatestRpQ, "A", "E") -> 1Q:20E | CJ62: ="2Q:" & RIGHT(YEAR(CJ$4),2) & IF(CJ$4<=LatestRpQ, "A", "E") -> 2Q:20E | CK62: ="3Q:" & RIGHT(YEAR(CK$4),2) & IF(CK$4<=LatestRpQ, "A", "E") -> 3Q:20E | CL62: ="4Q:" & RIGHT(YEAR(CL$4),2) & IF(CL$4<=LatestRpQ, "A", "E") -> 4Q:20E | CM62: =YEAR(CM$4) & IF(CM$4<=LatestRpQ, "A", "E") -> 2020E
I63: Diabetes | BS63: 0.26994951 | BX63: 0.31278788 | CC63: 0.35582573 | CH63: 0.37722732 | CM63: 0.36232127
I64: Oncology | BS64: 0.17906303 | BX64: 0.17018684 | CC64: 0.17543152 | CH64: 0.18467924 | CM64: 0.19362731
I65: Animal Health | BS65: 0.14924931 | BX65: 0.15549698 | CC65: 0.16460528 | CH65: 0.16952262 | CM65: 0.16764662
I66: Immunology | BS66: 0.0050665675 | BX66: 0.027506444 | CC66: 0.07086169 | CH66: 0.108833 | CM66: 0.13264007
I67: Neuroscience | BS67: 0.12752318 | BX67: 0.089004116 | CC67: 0.072493977 | CH67: 0.06834855 | CM67: 0.072177671
I68: Non Diabetes Endocrine | BS68: 0.10700524 | BX68: 0.098785804 | CC68: 0.098477276 | CH68: 0.057047621 | CM68: 0.035149193
I69: Other Pharmaceuticals | BS69: 0.010510756 | BX69: 0.009800649 | CC69: 0.0096605256 | CH69: 0.01126531 | CM69: 0.018230146
I70: Cardiovascular | BS70: 0.1516324 | BX70: 0.13643129 | CC70: 0.052643998 | CH70: 0.023076347 | CM70: 0.018207713
H73: Total revenues | L73: ='IS-ANNUAL'!L11 -> 3497.4 | M73: ='IS-ANNUAL'!M11 -> 3667.7 | N73: ='IS-ANNUAL'!N11 -> 3601.1 | O73: ='IS-ANNUAL'!O11 -> 3879.1 | P73: ='IS-ANNUAL'!P11 -> 14645.3 | Q73: ='IS-ANNUAL'!Q11 -> 3714.8 | R73: ='IS-ANNUAL'!R11 -> 3867.1 | S73: ='IS-ANNUAL'!S11 -> 3864.05 | ... AJ73: ='IS-ANNUAL'!AJ11 -> 21836.01 | AO73: ='IS-ANNUAL'!AO11 -> 23076.08 | AT73: ='IS-ANNUAL'!AT11 -> 24286.6 | AY73: ='IS-ANNUAL'!AY11 -> 22603.3 | BD73: ='IS-ANNUAL'!BD11 -> 23112.8 | BI73: ='IS-ANNUAL'!BI11 -> 19615.6 | BN73: ='IS-ANNUAL'!BN11 -> 19958.7 | BS73: ='IS-ANNUAL'!BS11 -> 21210.2 | BX73: ='IS-ANNUAL'!BX11 -> 22871.6 | CC73: ='IS-ANNUAL'!CC11 -> 24022.339 | CH73: ='IS-ANNUAL'!CD11 -> 24592.021 | CM73: ='IS-ANNUAL'!CE11 -> 25514.012
H74: COGS | P74: ='IS-ANNUAL'!P24 -> 3474.2 | U74: ='IS-ANNUAL'!U24 -> 3546.5 | Z74: ='IS-ANNUAL'!Z24 -> 4248.8 | AE74: ='IS-ANNUAL'!AE24 -> 4468.5 | AJ74: ='IS-ANNUAL'!AJ24 -> 4247 | AO74: ='IS-ANNUAL'!AO24 -> 4366.2 | AT74: ='IS-ANNUAL'!AT24 -> 5067.9 | AY74: ='IS-ANNUAL'!AY24 -> 4796.5 | BD74: ='IS-ANNUAL'!BD24 -> 4908.1 | BI74: ='IS-ANNUAL'!BI24 -> 4547.4 | BN74: ='IS-ANNUAL'!BN24 -> 4367.5 | BS74: ='IS-ANNUAL'!BS24 -> 4979.2 | BX74: ='IS-ANNUAL'!BX24 -> 5359 | CC74: ='IS-ANNUAL'!CC24 -> 6012.9294 | CH74: ='IS-ANNUAL'!CD24 -> 5975.8612 | CM74: ='IS-ANNUAL'!CE24 -> 5995.7927
H75: Gross Profit | L75: ='IS-ANNUAL'!L25 -> 2638.4 | M75: ='IS-ANNUAL'!M25 -> 2796.4 | N75: ='IS-ANNUAL'!N25 -> 2755.4 | O75: ='IS-ANNUAL'!O25 -> 2980.9 | P75: ='IS-ANNUAL'!P25 -> 11171.1 | Q75: ='IS-ANNUAL'!Q25 -> 2908.3 | R75: ='IS-ANNUAL'!R25 -> 3006.5 | S75: ='IS-ANNUAL'!S25 -> 3003.65 | ... AJ75: ='IS-ANNUAL'!AJ25 -> 17589.01 | AO75: ='IS-ANNUAL'!AO25 -> 18709.88 | AT75: ='IS-ANNUAL'!AT25 -> 19218.7 | AY75: ='IS-ANNUAL'!AY25 -> 17806.8 | BD75: ='IS-ANNUAL'!BD25 -> 18204.7 | BI75: ='IS-ANNUAL'!BI25 -> 15068.2 | BN75: ='IS-ANNUAL'!BN25 -> 15591.2 | BS75: ='IS-ANNUAL'!BS25 -> 16231 | BX75: ='IS-ANNUAL'!BX25 -> 17512.6 | CC75: ='IS-ANNUAL'!CC25 -> 18009.41 | CH75: ='IS-ANNUAL'!CD25 -> 18616.16 | CM75: ='IS-ANNUAL'!CE25 -> 19518.219
H76: Margin | L76: =L75/L73 -> 0.75438897 | M76: =M75/M73 -> 0.76243968 | N76: =N75/N73 -> 0.76515509 | O76: =O75/O73 -> 0.76845144 | P76: =P75/P73 -> 0.76277714 | Q76: =Q75/Q73 -> 0.78289545 | R76: =R75/R73 -> 0.77745597 | S76: =S75/S73 -> 0.77733207 | ... AJ76: =AJ75/AJ73 -> 0.80550476 | AO76: =AO75/AO73 -> 0.81079109 | AT76: =AT75/AT73 -> 0.79132938 | AY76: =AY75/AY73 -> 0.78779647 | BD76: =BD75/BD73 -> 0.78764581 | BI76: =BI75/BI73 -> 0.76817431 | BN76: =BN75/BN73 -> 0.78117312 | BS76: =BS75/BS73 -> 0.76524502 | BX76: =BX75/BX73 -> 0.76569195 | CC76: =CC75/CC73 -> 0.74969426 | CH76: =CH75/CH73 -> 0.757 | CM76: =CM75/CM73 -> 0.765
H78: Unadjusted EBITDA | L78: ='IS-ANNUAL'!L29+CFBS!L16 -> 1004.5 | M78: ='IS-ANNUAL'!M29+CFBS!M16 -> 1046.6 | N78: ='IS-ANNUAL'!N29+CFBS!N16 -> 1117.4 | O78: ='IS-ANNUAL'!O29+CFBS!O16 -> 1206.5 | P78: =P80-P79 -> 4364.273 | Q78: ='IS-ANNUAL'!Q29+CFBS!Q16 -> 1229.5 | R78: ='IS-ANNUAL'!R29+CFBS!R16 -> 1202.9 | S78: ='IS-ANNUAL'!S29+CFBS!S16 -> 1263.95 | T78: ='IS-ANNUAL'!T29+CFBS!T16 -> 1231.1 | U78: =U80-U79 -> 4830.45 | V78: ='IS-ANNUAL'!V29+CFBS!V16 -> 1377.8 | W78: ='IS-ANNUAL'!W29+CFBS!W16 -> 1515.4 | X78: ='IS-ANNUAL'!X29+CFBS!X16 -> 1475.4 | Y78: ='IS-ANNUAL'!Y29+CFBS!Y16 -> 1482.4 | Z78: =Z80-Z79 -> 5840 | AA78: ='IS-ANNUAL'!AA29+CFBS!AA16 -> 1545.3 | AB78: ='IS-ANNUAL'!AB29+CFBS!AB16 -> 1615.3 | AC78: ='IS-ANNUAL'!AC29+CFBS!AC16 -> 1723.2 | AD78: ='IS-ANNUAL'!AD29+CFBS!AD16 -> 1769.1 | AE78: =AE80-AE79 -> 6652.9 | AF78: ='IS-ANNUAL'!AF29+CFBS!AF16 -> 2059.9 | AG78: ='IS-ANNUAL'!AG29+CFBS!AG16 -> 1902.61 | AH78: ='IS-ANNUAL'!AH29+CFBS!AH16 -> 1996.1 | AI78: ='IS-ANNUAL'!AI29+CFBS!AI16 -> 1709.2 | AJ78: =AJ80-AJ79 -> 7667.81 | AO78: =AO80-AO79 -> 8100.48 | AT78: =AT80-AT79 -> 7691.6 | AY78: =AY80-AY79 -> 6477.4087 | BD78: =BD80-BD79 -> 6993.4 | BI78: =BI80-BI79 -> 5356.8 | BN78: =BN80-BN79 -> 5772.9 | BS78: =BS80-BS79 -> 6039.3 | BX78: =BX80-BX79 -> 7216.3 | CC78: =CC80-CC79 -> 7735.2876 | CH78: =CH80-CH79 -> 8228.1388 | CM78: =CM80-CM79 -> 9013.2462
H79: Cialis JV Income | L79: ='IS-ANNUAL'!L42 -> -12.73 | M79: ='IS-ANNUAL'!M42 -> -0.543 | N79: ='IS-ANNUAL'!N42 -> 6 | O79: ='IS-ANNUAL'!O42 -> 18 | P79: ='IS-ANNUAL'!P42 -> 10.727 | Q79: ='IS-ANNUAL'!Q42 -> 20 | R79: ='IS-ANNUAL'!R42 -> 23 | S79: ='IS-ANNUAL'!S42 -> 23.8 | ... AD79: ='IS-ANNUAL'!AD42 -> 0
H80: Adjusted EBITDA | L80: =CFBS!L148 -> 1004.5 | M80: =CFBS!M148 -> 1046.6 | N80: =CFBS!N148 -> 1117.4 | O80: =CFBS!O148 -> 1206.5 | P80: =CFBS!P148 -> 4375 | Q80: =CFBS!Q148 -> 1229.5 | R80: =CFBS!R148 -> 1202.9 | S80: =CFBS!S148 -> 1263.95 | ... AJ80: =CFBS!AJ148 -> 7667.81 | AO80: =CFBS!AO148 -> 8100.48 | AT80: =CFBS!AT148 -> 7691.6 | AY80: =CFBS!AY148 -> 6477.4087 | BD80: =CFBS!BD148 -> 6993.4 | BI80: =CFBS!BI148 -> 5356.8 | BN80: =CFBS!BN148 -> 5772.9 | BS80: =CFBS!BS148 -> 6039.3 | BX80: =CFBS!BX148 -> 7216.3 | CC80: =CFBS!CC148 -> 7735.2876 | CH80: =CFBS!CD148 -> 8228.1388 | CM80: =CFBS!CE148 -> 9013.2462
H81: Margin | L81: =L80/L73 -> 0.28721336 | M81: =M80/M73 -> 0.28535595 | N81: =N80/N73 -> 0.31029408 | O81: =O80/O73 -> 0.31102575 | P81: =P80/P73 -> 0.29873065 | Q81: =Q80/Q73 -> 0.3309734 | R81: =R80/R73 -> 0.31105997 | S81: =S80/S73 -> 0.32710498 | ... AJ81: =AJ80/AJ73 -> 0.35115435 | AO81: =AO80/AO73 -> 0.35103362 | AT81: =AT80/AT73 -> 0.31670139 | AY81: =AY80/AY73 -> 0.28656916 | BD81: =BD80/BD73 -> 0.30257693 | BI81: =BI80/BI73 -> 0.27308877 | BN81: =BN80/BN73 -> 0.28924229 | BS81: =BS80/BS73 -> 0.28473565 | BX81: =BX80/BX73 -> 0.31551356 | CC81: =CC80/CC73 -> 0.32200393 | CH81: =CH80/CH73 -> 0.33458571 | CM81: =CM80/CM73 -> 0.35326653
H83: Pretax Income | L83: ='IS-ANNUAL'!L44 -> 944.4 | M83: ='IS-ANNUAL'!M44 -> 933.657 | N83: ='IS-ANNUAL'!N44 -> 1018.2 | O83: ='IS-ANNUAL'!O44 -> 1066 | P83: ='IS-ANNUAL'!P44 -> 3962.257 | Q83: ='IS-ANNUAL'!Q44 -> 1056.3 | R83: ='IS-ANNUAL'!R44 -> 1040.8 | S83: ='IS-ANNUAL'!S44 -> 1105.75 | ... AJ83: ='IS-ANNUAL'!AJ44 -> 6140.51 | AO83: ='IS-ANNUAL'!AO44 -> 6767.28 | AT83: ='IS-ANNUAL'!AT44 -> 6139 | AY83: ='IS-ANNUAL'!AY44 -> 4901.4087 | BD83: ='IS-ANNUAL'!BD44 -> 5571.3 | BI83: ='IS-ANNUAL'!BI44 -> 4226.3 | BN83: ='IS-ANNUAL'!BN44 -> 4598.5 | BS83: ='IS-ANNUAL'!BS44 -> 4661.8 | BX83: ='IS-ANNUAL'!BX44 -> 5701.4 | CC83: ='IS-ANNUAL'!CC44 -> 6569.3766 | CH83: ='IS-ANNUAL'!CD44 -> 7206.5952 | CM83: ='IS-ANNUAL'!CE44 -> 8009.5889
H84: Margin | L84: =L83/L73 -> 0.27002916 | M84: =M83/M73 -> 0.25456199 | N84: =N83/N73 -> 0.28274694 | O84: =O83/O73 -> 0.27480601 | P84: =P83/P73 -> 0.27054803 | Q84: =Q83/Q73 -> 0.28434909 | R84: =R83/R73 -> 0.26914225 | S84: =S83/S73 -> 0.28616348 | ... AJ84: =AJ83/AJ73 -> 0.28121026 | AO84: =AO83/AO73 -> 0.29325951 | AT84: =AT83/AT73 -> 0.25277313 | AY84: =AY83/AY73 -> 0.21684483 | BD84: =BD83/BD73 -> 0.24104825 | BI84: =BI83/BI73 -> 0.21545607 | BN84: =BN83/BN73 -> 0.23040078 | BS84: =BS83/BS73 -> 0.21979048 | BX84: =BX83/BX73 -> 0.24927858 | CC84: =CC83/CC73 -> 0.27346948 | CH84: =CH83/CH73 -> 0.29304607 | CM84: =CM83/CM73 -> 0.31392903
H86: Net Income | L86: ='IS-ANNUAL'!L47 -> 736.632 | M86: ='IS-ANNUAL'!M47 -> 728.25246 | N86: ='IS-ANNUAL'!N47 -> 794.1 | O86: ='IS-ANNUAL'!O47 -> 871 | P86: ='IS-ANNUAL'!P47 -> 3129.9845 | Q86: ='IS-ANNUAL'!Q47 -> 834.4 | R86: ='IS-ANNUAL'!R47 -> 822.3 | S86: ='IS-ANNUAL'!S47 -> 873.55 | ... AJ86: ='IS-ANNUAL'!AJ47 -> 4851.01 | AO86: ='IS-ANNUAL'!AO47 -> 5240.88 | AT86: ='IS-ANNUAL'!AT47 -> 4913.6 | AY86: ='IS-ANNUAL'!AY47 -> 3784.0087 | BD86: ='IS-ANNUAL'!BD47 -> 4502.3 | BI86: ='IS-ANNUAL'!BI47 -> 3336 | BN86: ='IS-ANNUAL'!BN47 -> 3630.2 | BS86: ='IS-ANNUAL'!BS47 -> 3723.6 | BX86: ='IS-ANNUAL'!BX47 -> 4530.7 | CC86: ='IS-ANNUAL'!CC47 -> 5446.6657 | CH86: ='IS-ANNUAL'!CD47 -> 5995.8872 | CM86: ='IS-ANNUAL'!CE47 -> 6688.0067
H87: Margin | L87: =L86/L73 -> 0.21062275 | M87: =M86/M73 -> 0.19855835 | N87: =N86/N73 -> 0.22051595 | O87: =O86/O73 -> 0.22453662 | P87: =P86/P73 -> 0.21371938 | Q87: =Q86/Q73 -> 0.22461505 | R87: =R86/R73 -> 0.21263996 | S87: =S86/S73 -> 0.22607109 | ... AJ87: =AJ86/AJ73 -> 0.22215643 | AO87: =AO86/AO73 -> 0.2271131 | AT87: =AT86/AT73 -> 0.20231733 | AY87: =AY86/AY73 -> 0.16740957 | BD87: =BD86/BD73 -> 0.19479682 | BI87: =BI86/BI73 -> 0.17006872 | BN87: =BN86/BN73 -> 0.18188559 | BS87: =BS86/BS73 -> 0.17555704 | BX87: =BX86/BX73 -> 0.19809283 | CC87: =CC86/CC73 -> 0.22673336 | CH87: =CH86/CH73 -> 0.24381433 | CM87: =CM86/CM73 -> 0.26213074
H89: EPS (inc-Options Expense) | L89: ='IS-ANNUAL'!L49 -> 0.67630492 | M89: ='IS-ANNUAL'!M49 -> 0.66798731 | N89: ='IS-ANNUAL'!N49 -> 0.72762292 | O89: ='IS-ANNUAL'!O49 -> 0.79651691 | P89: ='IS-ANNUAL'!P49 -> 2.8687207 | Q89: ='IS-ANNUAL'!Q49 -> 0.76762153 | R89: ='IS-ANNUAL'!R49 -> 0.75766371 | S89: ='IS-ANNUAL'!S49 -> 0.80406881 | ... AJ89: ='IS-ANNUAL'!AJ49 -> 4.4164169 | AO89: ='IS-ANNUAL'!AO49 -> 4.7409771 | AT89: ='IS-ANNUAL'!AT49 -> 4.411062 | AY89: ='IS-ANNUAL'!AY49 -> 3.3867353 | BD89: ='IS-ANNUAL'!BD49 -> 4.1504019 | BI89: ='IS-ANNUAL'!BI49 -> 3.1058365 | BN89: ='IS-ANNUAL'!BN49 -> 3.4065018 | BS89: ='IS-ANNUAL'!BS49 -> 3.5083273 | BX89: ='IS-ANNUAL'!BX49 -> 4.2879901 | CC89: ='IS-ANNUAL'!CC49 -> 5.1913866 | CH89: ='IS-ANNUAL'!CD49 -> 5.732063 | CM89: ='IS-ANNUAL'!CE49 -> 6.4129675
H90: YOY Growth | P90: 0.017156201 | Q90: =Q89/L89-1 -> 0.13502283 | R90: =R89/M89-1 -> 0.13424865 | S90: =S89/N89-1 -> 0.10506251 | T90: =T89/O89-1 -> 0.071604563 | U90: =U89/P89-1 -> 0.10957875 | V90: =V89/Q89-1 -> 0.091422518 | W90: =W89/R89-1 -> 0.1852569 | X90: =X89/S89-1 -> 0.13709692 | ... AJ90: =AJ89/AE89-1 -> 0.15732226 | AO90: =AO89/AJ89-1 -> 0.073489492 | AT90: =AT89/AO89-1 -> -0.069587998 | AY90: =AY89/AT89-1 -> -0.23221771 | BD90: =BD89/AY89-1 -> 0.22548754 | BI90: =BI89/BD89-1 -> -0.25167813 | BN90: =BN89/BI89-1 -> 0.09680654 | BS90: =BS89/BN89-1 -> 0.029891499 | BX90: =BX89/BS89-1 -> 0.22223207 | CC90: =CC89/BX89-1 -> 0.21068064 | CH90: =CH89/CC89-1 -> 0.10414874 | CM90: =CM89/CH89-1 -> 0.11878874
H91: P/E | AJ91: =$J$17/AJ$89 -> 18.13461 | AO91: =$J$17/AO$89 -> 16.893142 | AT91: =$J$17/AT$89 -> 18.156625 | AY91: =$J$17/AY$89 -> 23.648143 | BD91: =$J$17/BD$89 -> 19.296926 | BI91: =$J$17/BI$89 -> 25.786933 | BN91: =$J$17/BN$89 -> 23.510922 | BS91: =$J$17/BS$89 -> 22.828543 | BX91: =$J$17/BX$89 -> 18.677748 | CC91: =$J$17/CC$89 -> 15.427477 | CH91: =$J$17/CH$89 -> 13.972282 | CM91: =$J$17/CM$89 -> 12.488758
H92: ="PEG (" & K40 & ")" -> PEG (2017e–2020E CAGR) | AJ92: =IF(ISNUMBER(AJ$91), IF($K$49>0, AJ$91/$K$49/100, "NM"), "NM") -> #N/A | AO92: =IF(ISNUMBER(AO$91), IF($K$49>0, AO$91/$K$49/100, "NM"), "NM") -> #N/A | AT92: =IF(ISNUMBER(AT$91), IF($K$49>0, AT$91/$K$49/100, "NM"), "NM") -> #N/A | AY92: =IF(ISNUMBER(AY$91), IF($K$49>0, AY$91/$K$49/100, "NM"), "NM") -> #N/A | BD92: =IF(ISNUMBER(BD$91), IF($K$49>0, BD$91/$K$49/100, "NM"), "NM") -> #N/A | BI92: =IF(ISNUMBER(BI$91), IF($K$49>0, BI$91/$K$49/100, "NM"), "NM") -> #N/A | BN92: =IF(ISNUMBER(BN$91), IF($K$49>0, BN$91/$K$49/100, "NM"), "NM") -> #N/A | BS92: =IF(ISNUMBER(BS$91), IF($K$49>0, BS$91/$K$49/100, "NM"), "NM") -> #N/A | BX92: =IF(ISNUMBER(BX$91), IF($K$49>0, BX$91/$K$49/100, "NM"), "NM") -> #N/A | CC92: =IF(ISNUMBER(CC$91), IF($K$49>0, CC$91/$K$49/100, "NM"), "NM") -> #N/A | CH92: =IF(ISNUMBER(CH$91), IF($K$49>0, CH$91/$K$49/100, "NM"), "NM") -> #N/A | CM92: =IF(ISNUMBER(CM$91), IF($K$49>0, CM$91/$K$49/100, "NM"), "NM") -> #N/A
H93: ="PEG (" & J40 & ")" -> PEG (2016a–2020e CAGR) | AJ93: =IF(ISNUMBER(AJ$91), IF($J$49>0, AJ$91/$J$49/100, "NM"), "NM") -> 1.1141997 | AO93: =IF(ISNUMBER(AO$91), IF($J$49>0, AO$91/$J$49/100, "NM"), "NM") -> 1.0379232 | AT93: =IF(ISNUMBER(AT$91), IF($J$49>0, AT$91/$J$49/100, "NM"), "NM") -> 1.1155523 | AY93: =IF(ISNUMBER(AY$91), IF($J$49>0, AY$91/$J$49/100, "NM"), "NM") -> 1.4529539 | BD93: =IF(ISNUMBER(BD$91), IF($J$49>0, BD$91/$J$49/100, "NM"), "NM") -> 1.185613 | BI93: =IF(ISNUMBER(BI$91), IF($J$49>0, BI$91/$J$49/100, "NM"), "NM") -> 1.5843623 | BN93: =IF(ISNUMBER(BN$91), IF($J$49>0, BN$91/$J$49/100, "NM"), "NM") -> 1.444523 | BS93: =IF(ISNUMBER(BS$91), IF($J$49>0, BS$91/$J$49/100, "NM"), "NM") -> 1.4025973 | BX93: =IF(ISNUMBER(BX$91), IF($J$49>0, BX$91/$J$49/100, "NM"), "NM") -> 1.1475704 | CC93: =IF(ISNUMBER(CC$91), IF($J$49>0, CC$91/$J$49/100, "NM"), "NM") -> 0.94787207 | CH93: =IF(ISNUMBER(CH$91), IF($J$49>0, CH$91/$J$49/100, "NM"), "NM") -> 0.85846412 | CM93: =IF(ISNUMBER(CM$91), IF($J$49>0, CM$91/$J$49/100, "NM"), "NM") -> 0.76731566
H95: Depreciation & amortization | L95: =CFBS!L16 -> 158.7 | M95: =CFBS!M16 -> 158.7 | N95: =CFBS!N16 -> 183.9 | O95: =CFBS!O16 -> 225.1 | P95: =CFBS!P16 -> 726.4 | Q95: =CFBS!Q16 -> 204.9 | R95: =CFBS!R16 -> 209.1 | S95: =CFBS!S16 -> 214.2 | ... AJ95: =CFBS!AJ16 -> 1297.8 | AO95: =CFBS!AO16 -> 1328.2 | AT95: =CFBS!AT16 -> 1373.6 | AY95: =CFBS!AY16 -> 1462.2 | BD95: =CFBS!BD16 -> 1445.6 | BI95: =CFBS!BI16 -> 1379 | BN95: =CFBS!BN16 -> 1427.7 | BS95: =CFBS!BS16 -> 1496.6 | BX95: =CFBS!BX16 -> 1567.3 | CC95: =CFBS!CC16 -> 1354.7 | CH95: =CFBS!CD16 -> 1177.1 | CM95: =CFBS!CE16 -> 1175.8
H97: OCF (Oper. Cash Flow) | L97: =CFBS!L30 -> 804.8 | M97: =CFBS!M30 -> 674.1 | N97: =CFBS!N30 -> -379.6 | O97: =CFBS!O30 -> 814.3 | P97: =CFBS!P30 -> 1913.6 | Q97: =CFBS!Q30 -> 254.5 | R97: =CFBS!R30 -> 687.7 | S97: =CFBS!S30 -> 1176 | ... CC97: =CFBS!CC30 -> 7801.2555 | CD97: =CFBS!#REF! -> #REF! | CE97: =CFBS!#REF! -> #REF! | CF97: =CFBS!#REF! -> #REF! | CG97: =CFBS!#REF! -> #REF! | CH97: =CFBS!CD30 -> 4168.9931 | CI97: =CFBS!#REF! -> #REF! | CJ97: =CFBS!#REF! -> #REF! | CK97: =CFBS!#REF! -> #REF! | CL97: =CFBS!#REF! -> #REF! | CM97: =CFBS!CE30 -> 8682.0399
H98: Fully diluted shares outstanding | L98: =CFBS!L191 -> 1089.201 | M98: =CFBS!M191 -> 1090.219 | N98: =CFBS!N191 -> 1091.362 | O98: =CFBS!O191 -> 1093.511 | P98: =CFBS!P191 -> 1091.0732 | Q98: =CFBS!Q191 -> 1086.994 | R98: =CFBS!R191 -> 1085.31 | S98: =CFBS!S191 -> 1086.412 | ... AJ98: =CFBS!AJ191 -> 1098.404 | AO98: =CFBS!AO191 -> 1105.443 | AT98: =CFBS!AT191 -> 1113.9268 | AY98: =CFBS!AY191 -> 1117.3028 | BD98: =CFBS!BD191 -> 1084.7865 | BI98: =CFBS!BI191 -> 1074.1067 | BN98: =CFBS!BN191 -> 1065.668 | BS98: =CFBS!BS191 -> 1061.3605 | BX98: =CFBS!BX191 -> 1056.6023 | CC98: =CFBS!CC191 -> 1049.1736 | CH98: =CFBS!CD191 -> 1046.0261 | CM98: =CFBS!CE191 -> 1042.888
H99: OCF / Share | L99: =L97/L98 -> 0.73889025 | M99: =M97/M98 -> 0.61831614 | N99: =N97/N98 -> -0.34782226 | O99: =O97/O98 -> 0.74466558 | P99: =P97/P98 -> 1.7538694 | Q99: =Q97/Q98 -> 0.23413193 | R99: =R97/R98 -> 0.63364384 | S99: =S97/S98 -> 1.0824623 | ... AJ99: =AJ97/AJ98 -> 3.9470905 | AO99: =AO97/AO98 -> 6.2027622 | AT99: =AT97/AT98 -> 6.4945922 | AY99: =AY97/AY98 -> 4.7478627 | BD99: =BD97/BD98 -> 5.2867546 | BI99: =BI97/BI98 -> 4.065797 | BN99: =BN97/BN98 -> 2.6019361 | BS99: =BS97/BS98 -> 4.5705488 | BX99: =BX97/BX98 -> 5.3147719 | CC99: =CC97/CC98 -> 7.4356195 | CH99: =CH97/CH98 -> 3.9855538 | CM99: =CM97/CM98 -> 8.3249975
H101: OCF/Net Income | L101: =L97/L86 -> 1.0925401 | M101: =M97/M86 -> 0.92564054 | N101: =N97/N86 -> -0.47802544 | O101: =O97/O86 -> 0.93490241 | P101: =P97/P86 -> 0.61137684 | Q101: =Q97/Q86 -> 0.30500959 | R101: =R97/R86 -> 0.83631278 | S101: =S97/S86 -> 1.3462309 | ... AJ101: =AJ97/AJ86 -> 0.89373141 | AO101: =AO97/AO86 -> 1.3083299 | AT101: =AT97/AT86 -> 1.4723421 | AY101: =AY97/AY86 -> 1.4018995 | BD101: =BD97/BD86 -> 1.2737934 | BI101: =BI97/BI86 -> 1.3090827 | BN101: =BN97/BN86 -> 0.76381467 | BS101: =BS97/BS86 -> 1.3027715 | BX101: =BX97/BX86 -> 1.2394553 | CC101: =CC97/CC86 -> 1.4322993 | CH101: =CH97/CH86 -> 0.6953088 | CM101: =CM97/CM86 -> 1.2981506
H103: CapEx | L103: =-CFBS!L32 -> 242.2 | M103: =-CFBS!M32 -> 377.7 | N103: =-CFBS!N32 -> 258.6 | O103: =-CFBS!O32 -> 408.5 | P103: =-CFBS!P32 -> 1287 | Q103: =-CFBS!Q32 -> 160.7 | R103: =-CFBS!R32 -> 231.4 | S103: =-CFBS!S32 -> 275.7 | ... AJ103: =-CFBS!AJ32 -> 747.3 | AO103: =-CFBS!AO32 -> 669.7 | AT103: =-CFBS!AT32 -> 646.7 | AY103: =-CFBS!AY32 -> 883.4 | BD103: =-CFBS!BD32 -> 832.7 | BI103: =-CFBS!BI32 -> 1147.3 | BN103: =-CFBS!BN32 -> 973.6 | BS103: =-CFBS!BS32 -> 963.6 | BX103: =-CFBS!BX32 -> 1036.1 | CC103: =-CFBS!CC32 -> 1200 | CH103: =-CFBS!CD32 -> 1000 | CM103: =-CFBS!CE32 -> 1000
H105: Cash | L105: =CFBS!L66 -> 5620.3 | M105: =CFBS!M66 -> 5501.1 | N105: =CFBS!N66 -> 6232.9 | O105: =CFBS!O66 -> 5037.7 | P105: =CFBS!P66 -> 5037.7 | Q105: =CFBS!Q66 -> 4503.7 | R105: =CFBS!R66 -> 4590.7 | S105: =CFBS!S66 -> 3618.5 | ... AJ105: =CFBS!AJ66 -> 4497.6 | AO105: =CFBS!AO66 -> 6727 | AT105: =CFBS!AT66 -> 6897.1 | AY105: =CFBS!AY66 -> 5684.3 | BD105: =CFBS!BD66 -> 5397.3 | BI105: =CFBS!BI66 -> 4827 | BN105: =CFBS!BN66 -> 4451.8 | BS105: =CFBS!BS66 -> 6038.6 | BX105: =CFBS!BX66 -> 8034.1 | CC105: =CFBS!CC66 -> 5786.535 | CH105: =CFBS!CD66 -> 4627.3777 | CM105: =CFBS!CE66 -> 9098.2019
H106: Interest income | L106: ='IS-ANNUAL'!L36 -> 46 | M106: ='IS-ANNUAL'!M36 -> 46.3 | N106: ='IS-ANNUAL'!N36 -> 52 | O106: ='IS-ANNUAL'!O36 -> 67.9 | P106: ='IS-ANNUAL'!P36 -> 212.2 | Q106: ='IS-ANNUAL'!Q36 -> 59.7 | R106: ='IS-ANNUAL'!R36 -> 68 | S106: ='IS-ANNUAL'!S36 -> 67.5 | ... AJ106: ='IS-ANNUAL'!AJ36 -> 75.2 | AO106: ='IS-ANNUAL'!AO36 -> 51.9 | AT106: ='IS-ANNUAL'!AT36 -> 79.9 | AY106: ='IS-ANNUAL'!AY36 -> 105.1 | BD106: ='IS-ANNUAL'!BD36 -> 119.7 | BI106: ='IS-ANNUAL'!BI36 -> 121 | BN106: ='IS-ANNUAL'!BN36 -> 87 | BS106: ='IS-ANNUAL'!BS36 -> 108.7 | BX106: ='IS-ANNUAL'!BX36 -> 167.3 | CC106: ='IS-ANNUAL'!CC36 -> 180.5 | CH106: ='IS-ANNUAL'!CD36 -> 180.5 | CM106: ='IS-ANNUAL'!CE36 -> 180.5
H107: Total debt | L107: =CFBS!L86+CFBS!L96 -> 4590.1 | M107: =CFBS!M86+CFBS!M96 -> 4676.1 | N107: =CFBS!N86+CFBS!N96 -> 6510.2 | O107: =CFBS!O86+CFBS!O96 -> 6498.2 | P107: =CFBS!P86+CFBS!P96 -> 6498.2 | Q107: =CFBS!Q86+CFBS!Q96 -> 6348.5 | R107: =CFBS!R86+CFBS!R96 -> 6316.6 | S107: =CFBS!S86+CFBS!S96 -> 4887.5 | ... AJ107: =CFBS!AJ86+CFBS!AJ96 -> 6662.1 | AO107: =CFBS!AO86+CFBS!AO96 -> 6926.5 | AT107: =CFBS!AT86+CFBS!AT96 -> 6987 | AY107: =CFBS!AY86+CFBS!AY96 -> 5531.3 | BD107: =CFBS!BD86+CFBS!BD96 -> 5212.9 | BI107: =CFBS!BI86+CFBS!BI96 -> 8021.5 | BN107: =CFBS!BN86+CFBS!BN96 -> 7978.5 | BS107: =CFBS!BS86+CFBS!BS96 -> 10305.2 | BX107: =CFBS!BX86+CFBS!BX96 -> 13647.1 | CC107: =CFBS!CC86+CFBS!CC96 -> 5605.82 | CH107: =CFBS!CD86+CFBS!CD96 -> 4704.45 | CM107: =CFBS!CE86+CFBS!CE96 -> 4704.45
H108: Interest expense | L108: =-'IS-ANNUAL'!L35 -> 24.6 | M108: =-'IS-ANNUAL'!M35 -> 12 | N108: =-'IS-ANNUAL'!N35 -> 24.3 | O108: =-'IS-ANNUAL'!O35 -> 44.3 | P108: =-'IS-ANNUAL'!P35 -> 105.2 | Q108: =-'IS-ANNUAL'!Q35 -> 65 | R108: =-'IS-ANNUAL'!R35 -> 66 | S108: =-'IS-ANNUAL'!S35 -> 62.7 | ... AJ108: =-'IS-ANNUAL'!AJ35 -> 261.3 | AO108: =-'IS-ANNUAL'!AO35 -> 185.5 | AT108: =-'IS-ANNUAL'!AT35 -> 185.9 | AY108: =-'IS-ANNUAL'!AY35 -> 177.9 | BD108: =-'IS-ANNUAL'!BD35 -> 160.1 | BI108: =-'IS-ANNUAL'!BI35 -> 148.8 | BN108: =-'IS-ANNUAL'!BN35 -> 172.4 | BS108: =-'IS-ANNUAL'!BS35 -> 185.2 | BX108: =-'IS-ANNUAL'!BX35 -> 225 | CC108: =-'IS-ANNUAL'!CC35 -> 224.91102 | CH108: =-'IS-ANNUAL'!CD35 -> 149.94362 | CM108: =-'IS-ANNUAL'!CE35 -> 133.35731
H109: Net Debt/(cash) | L109: =CFBS!L172 -> -1030.2 | M109: =CFBS!M172 -> -825 | N109: =CFBS!N172 -> 277.3 | O109: =CFBS!O172 -> 1460.5 | P109: =CFBS!P172 -> 1460.5 | Q109: =CFBS!Q172 -> 1844.8 | R109: =CFBS!R172 -> 1725.9 | S109: =CFBS!S172 -> 1269 | ... AJ109: =CFBS!AJ172 -> 2164.5 | AO109: =CFBS!AO172 -> 199.5 | AT109: =CFBS!AT172 -> 89.9 | AY109: =CFBS!AY172 -> -153 | BD109: =CFBS!BD172 -> -184.4 | BI109: =CFBS!BI172 -> 3194.5 | BN109: =CFBS!BN172 -> 3526.7 | BS109: =CFBS!BS172 -> 4266.6 | BX109: =CFBS!BX172 -> 5613 | CC109: =CFBS!CC172 -> -180.715 | CH109: =CFBS!CD172 -> 77.07233 | CM109: =CFBS!CE172 -> -4393.7519
H110: Net Debt/Total Capital | L110: =CFBS!L174 -> -0.063640126 | M110: =CFBS!M174 -> -0.055201301 | N110: =CFBS!N174 -> 0.015497248 | O110: =CFBS!O174 -> 0.084470304 | P110: =CFBS!P174 -> 0.084470304 | Q110: =CFBS!Q174 -> 0.10224634 | R110: =CFBS!R174 -> 0.094595261 | S110: =CFBS!S174 -> 0.070727113 | ... AJ110: =CFBS!AJ174 -> 0.13371511 | AO110: =CFBS!AO174 -> 0.010315782 | AT110: =CFBS!AT174 -> 0.0043805366 | AY110: =CFBS!AY174 -> -0.0075350157 | BD110: =CFBS!BD174 -> -0.0080687507 | BI110: =CFBS!BI174 -> 0.13646111 | BN110: =CFBS!BN174 -> 0.1562644 | BS110: =CFBS!BS174 -> 0.1749632 | BX110: =CFBS!BX174 -> 0.22172625 | CC110: =CFBS!CC174 -> -0.0098430015 | CH110: =CFBS!CD174 -> 0.0040505796 | CM110: =CFBS!CE174 -> -0.20431995
H112: Dividend/share | L112: =CFBS!L180 -> 0.38 | M112: =CFBS!M180 -> 0.38 | N112: =CFBS!N180 -> 0.38 | O112: =CFBS!O180 -> 0.38 | P112: =CFBS!P180 -> 1.52 | Q112: =CFBS!Q180 -> 0.4 | R112: =CFBS!R180 -> 0.4 | S112: =CFBS!S180 -> 0.4 | ... AJ112: =CFBS!AJ180 -> 1.96 | AO112: =CFBS!AO180 -> 1.96 | AT112: =CFBS!AT180 -> 1.96 | AY112: =CFBS!AY180 -> 1.96 | BD112: =CFBS!BD180 -> 1.96 | BI112: =CFBS!BI180 -> 1.96 | BN112: =CFBS!BN180 -> 1.99 | BS112: =CFBS!BS180 -> 2.04 | BX112: =CFBS!BX180 -> 2.08 | CC112: =CFBS!CC180 -> 2.25 | CH112: =CFBS!CD180 -> 2.32 | CM112: =CFBS!CE180 -> 2.36
H113: Dividend yield | L113: =L112/$J$17 -> 0.0047446623 | M113: =M112/$J$17 -> 0.0047446623 | N113: =N112/$J$17 -> 0.0047446623 | O113: =O112/$J$17 -> 0.0047446623 | P113: =P112/$J$17 -> 0.018978649 | Q113: =Q112/$J$17 -> 0.0049943813 | R113: =R112/$J$17 -> 0.0049943813 | S113: =S112/$J$17 -> 0.0049943813 | ... AJ113: =AJ112/$J$17 -> 0.024472468 | AO113: =AO112/$J$17 -> 0.024472468 | AT113: =AT112/$J$17 -> 0.024472468 | AY113: =AY112/$J$17 -> 0.024472468 | BD113: =BD112/$J$17 -> 0.024472468 | BI113: =BI112/$J$17 -> 0.024472468 | BN113: =BN112/$J$17 -> 0.024847047 | BS113: =BS112/$J$17 -> 0.025471345 | BX113: =BX112/$J$17 -> 0.025970783 | CC113: =CC112/$J$17 -> 0.028093395 | CH113: =CH112/$J$17 -> 0.028967412 | CM113: =CM112/$J$17 -> 0.02946685
H115: Other Margins
H116: COGS | L116: ='IS-ANNUAL'!L56 -> 0.24561103 | M116: ='IS-ANNUAL'!M56 -> 0.23756032 | N116: ='IS-ANNUAL'!N56 -> 0.23484491 | O116: ='IS-ANNUAL'!O56 -> 0.23154856 | P116: ='IS-ANNUAL'!P56 -> 0.23722286 | Q116: ='IS-ANNUAL'!Q56 -> 0.21710455 | R116: ='IS-ANNUAL'!R56 -> 0.22254403 | S116: ='IS-ANNUAL'!S56 -> 0.22266793 | ... AJ116: ='IS-ANNUAL'!AJ56 -> 0.19449524 | AO116: ='IS-ANNUAL'!AO56 -> 0.18920891 | AT116: ='IS-ANNUAL'!AT56 -> 0.20867062 | AY116: ='IS-ANNUAL'!AY56 -> 0.21220353 | BD116: ='IS-ANNUAL'!BD56 -> 0.21235419 | BI116: ='IS-ANNUAL'!BI56 -> 0.23182569 | BN116: ='IS-ANNUAL'!BN56 -> 0.21882688 | BS116: ='IS-ANNUAL'!BS56 -> 0.23475498 | BX116: ='IS-ANNUAL'!BX56 -> 0.23430805 | CC116: ='IS-ANNUAL'!CC56 -> 0.25030574 | CH116: ='IS-ANNUAL'!CD56 -> 0.243 | CM116: ='IS-ANNUAL'!CE56 -> 0.235
H117: R&D | L117: ='IS-ANNUAL'!L59 -> 0.20077772 | M117: ='IS-ANNUAL'!M59 -> 0.20786869 | N117: ='IS-ANNUAL'!N59 -> 0.20854739 | O117: ='IS-ANNUAL'!O59 -> 0.20878554 | P117: ='IS-ANNUAL'!P59 -> 0.20658505 | Q117: ='IS-ANNUAL'!Q59 -> 0.19941854 | R117: ='IS-ANNUAL'!R59 -> 0.20035686 | S117: ='IS-ANNUAL'!S59 -> 0.195572 | ... AJ117: ='IS-ANNUAL'!AJ59 -> 0.19813601 | AO117: ='IS-ANNUAL'!AO59 -> 0.2116564 | AT117: ='IS-ANNUAL'!AT59 -> 0.20673128 | AY117: ='IS-ANNUAL'!AY59 -> 0.23350977 | BD117: ='IS-ANNUAL'!BD59 -> 0.23931761 | BI117: ='IS-ANNUAL'!BI59 -> 0.24125186 | BN117: ='IS-ANNUAL'!BN59 -> 0.24161393 | BS117: ='IS-ANNUAL'!BS59 -> 0.24720182 | BX117: ='IS-ANNUAL'!BX59 -> 0.23091082 | CC117: ='IS-ANNUAL'!CC59 -> 0.21891132 | CH117: ='IS-ANNUAL'!CD59 -> 0.21384017 | CM117: ='IS-ANNUAL'!CE59 -> 0.20817383
H118: SG&A | L118: ='IS-ANNUAL'!L58 -> 0.31177446 | M118: ='IS-ANNUAL'!M58 -> 0.31248466 | N118: ='IS-ANNUAL'!N58 -> 0.29738136 | O118: ='IS-ANNUAL'!O58 -> 0.30666907 | P118: ='IS-ANNUAL'!P58 -> 0.30706097 | Q118: ='IS-ANNUAL'!Q58 -> 0.30766125 | R118: ='IS-ANNUAL'!R58 -> 0.32011068 | S118: ='IS-ANNUAL'!S58 -> 0.31008916 | ... AJ118: ='IS-ANNUAL'!AJ58 -> 0.31564833 | AO118: ='IS-ANNUAL'!AO58 -> 0.3056585 | AT118: ='IS-ANNUAL'!AT58 -> 0.32445464 | AY118: ='IS-ANNUAL'!AY58 -> 0.33240721 | BD118: ='IS-ANNUAL'!BD58 -> 0.3082967 | BI118: ='IS-ANNUAL'!BI58 -> 0.32413487 | BN118: ='IS-ANNUAL'!BN58 -> 0.32184962 | BS118: ='IS-ANNUAL'!BS58 -> 0.30386795 | BX118: ='IS-ANNUAL'!BX58 -> 0.2877936 | CC118: ='IS-ANNUAL'!CC58 -> 0.26517235 | CH118: ='IS-ANNUAL'!CD58 -> 0.25643924 | CM118: ='IS-ANNUAL'!CE58 -> 0.24964412
H119: Tax Rate | L119: ='IS-ANNUAL'!L46 -> 0.22 | M119: ='IS-ANNUAL'!M46 -> 0.22 | N119: ='IS-ANNUAL'!N46 -> 0.22009428 | O119: ='IS-ANNUAL'!O46 -> 0.18292683 | P119: ='IS-ANNUAL'!P46 -> 0.21005012 | Q119: ='IS-ANNUAL'!Q46 -> 0.2100729 | R119: ='IS-ANNUAL'!R46 -> 0.20993467 | S119: ='IS-ANNUAL'!S46 -> 0.20999322 | ... AJ119: ='IS-ANNUAL'!AJ46 -> 0.20999884 | AO119: ='IS-ANNUAL'!AO46 -> 0.22555591 | AT119: ='IS-ANNUAL'!AT46 -> 0.19960906 | AY119: ='IS-ANNUAL'!AY46 -> 0.22797528 | BD119: ='IS-ANNUAL'!BD46 -> 0.19187622 | BI119: ='IS-ANNUAL'!BI46 -> 0.21065708 | BN119: ='IS-ANNUAL'!BN46 -> 0.21056866 | BS119: ='IS-ANNUAL'!BS46 -> 0.20125273 | BX119: ='IS-ANNUAL'!BX46 -> 0.20533553 | CC119: ='IS-ANNUAL'!CC46 -> 0.17090068 | CH119: ='IS-ANNUAL'!CD46 -> 0.168 | CM119: ='IS-ANNUAL'!CE46 -> 0.165
H121: Free Cash Flow | L121: =CFBS!L151 -> 707.492 | M121: =CFBS!M151 -> 214.80954 | N121: =CFBS!N151 -> -675.15801 | O121: =CFBS!O151 -> 479.17561 | P121: =CFBS!P151 -> 726.32669 | Q121: =CFBS!Q151 -> 68.759311 | R121: =CFBS!R151 -> 419.16693 | S121: =CFBS!S151 -> 856.05962 | ... AJ121: =CFBS!AJ151 -> 3769.5053 | AO121: =CFBS!AO151 -> 6330.7594 | AT121: =CFBS!AT151 -> 6736.5927 | AY121: =CFBS!AY151 -> 4558.7432 | BD121: =CFBS!BD151 -> 5031.6806 | BI121: =CFBS!BI151 -> 3337.2542 | BN121: =CFBS!BN151 -> 1935.298 | BS121: =CFBS!BS151 -> 4035.328 | BX121: =CFBS!BX151 -> 4758.2995 | CC121: =CFBS!CC151 -> 6787.7291 | CH121: =CFBS!CD151 -> 3293.7462 | CM121: =CFBS!CE151 -> 7793.3932
H122: FCF/share | L122: =L121/CFBS!L191 -> 0.64955137 | M122: =M121/CFBS!M191 -> 0.19703339 | N122: =N121/CFBS!N191 -> -0.61863801 | O122: =O121/CFBS!O191 -> 0.43819917 | P122: =P121/CFBS!P191 -> 0.66569929 | Q122: =Q121/CFBS!Q191 -> 0.063256385 | R122: =R121/CFBS!R191 -> 0.38621862 | S122: =S121/CFBS!S191 -> 0.78796959 | ... AJ122: =AJ121/CFBS!AJ191 -> 3.4318022 | AO122: =AO121/CFBS!AO191 -> 5.7268981 | AT122: =AT121/CFBS!AT191 -> 6.0476083 | AY122: =AY121/CFBS!AY191 -> 4.0801324 | BD122: =BD121/CFBS!BD191 -> 4.6384064 | BI122: =BI121/CFBS!BI191 -> 3.1070042 | BN122: =BN121/CFBS!BN191 -> 1.8160421 | BS122: =BS121/CFBS!BS191 -> 3.8020333 | BX122: =BX121/CFBS!BX191 -> 4.5033971 | CC122: =CC121/CFBS!CC191 -> 6.4695959 | CH122: =CH121/CFBS!CD191 -> 3.1488185 | CM122: =CM121/CFBS!CE191 -> 7.4728958
H123: FCF yield | L123: =L122/$J$17 -> 0.0081102681 | M123: =M122/$J$17 -> 0.0024601496 | N123: =N122/$J$17 -> -0.0077242853 | O123: =O122/$J$17 -> 0.0054713343 | P123: =P122/$J$17 -> 0.0083118903 | Q123: =Q122/$J$17 -> 0.00078981627 | R123: =R122/$J$17 -> 0.0048223076 | S123: =S122/$J$17 -> 0.0098385515 | ... AJ123: =AJ122/$J$17 -> 0.042849322 | AO123: =AO122/$J$17 -> 0.071505782 | AT123: =AT122/$J$17 -> 0.075510155 | AY123: =AY122/$J$17 -> 0.050944343 | BD123: =BD122/$J$17 -> 0.057914925 | BI123: =BI122/$J$17 -> 0.03879391 | BN123: =BN122/$J$17 -> 0.022675017 | BS123: =BS122/$J$17 -> 0.047472011 | BX123: =BX122/$J$17 -> 0.056229206 | CC123: =CC122/$J$17 -> 0.080779073 | CH123: =CH122/$J$17 -> 0.039316001 | CM123: =CM122/$J$17 -> 0.093306228
H124: Yellow Shaded Portions indicate source cells are in highly moveable columns. Please double check quarterly.
AX155: TR | AY155: 2012 | BD155: 2013 | BI155: 2014 | BN155: 2015 | BS155: 2016 | BX155: 2017
...

Sheet ImportantDisclosures
A2: 1585 Broadway
A3: New York, NY 10036-8293
A4: United States
A5: Tel: +1 (1)212 761 4000
A7: Authors: David Risinger
A8: Date: 25 Apr 2018
A10: Ticker: LLY.N
A11: Stock Rating: Equal-Weight
A12: Industry: Major Pharmaceuticals
A13: Industry View: In-Line
A14: Price as of 25 Apr 2018: 80.09
A15: Target Price: 93
... A126: Equal-weight and Not-Rated to hold and Underweight to sell recommendations, respectively.
B128: Coverage Universe | D128: Investment Banking Clients (IBC) | G128: Other Material Investment Services Clients (MISC)
A129: Stock Rating Category | B129: Count | C129: % of Total | D129: Count | E129: % of Total IBC | F129: % of Rating Category | G129: Count | H129: % of Total Other MISC
A130: Overweight/Buy | B130: 1189 | C130: 0.38 | D130: 315 | E130: 0.41 | F130: 0.26 | G130: 555 | H130: 0.39
A131: Equal-weight/Hold | B131: 1355 | C131: 0.43 | D131: 364 | E131: 0.47 | F131: 0.27 | G131: 644 | H131: 0.45
A132: Not-Rated/Hold | B132: 53 | C132: 0.02 | D132: 4 | E132: 0.01 | F132: 0.08 | G132: 7 | H132: 0
A133: Underweight/Sell | B133: 545 | C133: 0.17 | D133: 84 | E133: 0.11 | F133: 0.15 | G133: 214 | H133: 0.15
A134: Total | B134: 3142 | D134: 767 | G134: 1420
A136: Data include common stock and ADRs currently assigned ratings. Investment Banking Clients are companies
A137: from whom Morgan Stanley received investment banking compensation in the last 12 months. Due to rounding
A138: off of decimals, the percentages provided in the "% of total" column may not add up to exactly 100
A139: percent.
A141: Analyst Stock Ratings
A143: Overweight (O). The stock's total return is expected to exceed the average total return of the analyst's
A144: industry (or industry team's) coverage universe, on a risk-adjusted basis, over the next 12-18 months.
A146: Equal-weight (E). The stock's total return is expected to be in line with the average total return of
A147: the analyst's industry (or industry team's) coverage universe, on a risk-adjusted basis, over the next
A148: 12-18 months.
A150: Not-Rated (NR). Currently the analyst does not have adequate conviction about the stock's total return
A151: relative to the average total return of the analyst's industry (or industry team's) coverage universe,
... A397: © Copyright 2018 Morgan Stanley

Sheet COVER SHEET
FZ1: Section Header
D2: =CompanyName -> Eli Lilly & Co.
D3: ="Ticker: " & CompanyTicker -> Ticker: LLY
D4: ="Rating: " & Rating -> Rating: Equal-weight
D5: ="Price Target: " & TEXT(PriceTarget, "$0") -> Price Target: $93
D6: ="Date: " & TEXT(DtLastUpdt, "m/d/yyyy") -> Date: 4/24/2018
D8: David R. Risinger, CFA
D9: Senior US Major Pharmaceuticals Analyst
D10: (212) 761-6494
D11: david.risinger@morganstanley.com
B13: Go to Annual Income Statement | D13: Go to Footnotes | F13: Go to Management Projections
B15: Go to Quarterly Income Statement | D15: Go to Agreements | F15: Go to Selected Franchises
B17: Go to Annual Revenues | D17: Go to Pipeline | F17: Go to DCF
B19: Go to Quarterly Revenues | D19: Go to Cash Flow/Balance Sheet

Sheet MW-Cache
A1: $FZ$2
A2: LLY.N,mstag:researchAndDevelopment,2015FY,,FYR | B2: 4,819.8927559 | C2: LLY.N,mstag:researchAndDevelopment,2012FY,,FYR | D2: 5,240.21 | E2: LLY.N,mstag:revenueNet,2018Q3,,FYR | F2: 5,896.886 | G2: LLY.N,mstag:revenueNet,2018Q1,,FYR | H2: 5,539.322 | I2: PFE.N,mstag:revenueNet,2012FY,,FYR,USD | J2: 62,880.57093596 | K2: LLY.N,mstag:sellingGeneralAndAdministrativeExpenses,2013FY,,FYR | L2: 7,708.264 | M2: NOVOb.CO,mscalc:marketCapitalizationCurrent | N2: 532,335.205932404 | O2: LLY.N,mscalc:epsForConsensusForThomsonFeed,2018Q3,,FYR | P2: 1.29745235543281 | Q2: LLY.N,mscalc:epsForConsensusForThomsonFeed,2016Q3,,FYR | R2: 0.877651100221911 | S2: NOVOb.CO,mstag:revenueNet,2013FY,,FYR | T2: 83,789.2855310202 | U2: LLY.N,mscalc:epsForConsensusForThomsonFeed,2016Q1,,FYR | V2: 0.829950850128166 | W2: NOVOb.CO,mstag:revenueNet,2014FY,,FYR | X2: 91,763.306526585 | Y2: LLY.N,mscalc:epsForConsensusForThomsonFeed,2017Q1,,FYR | Z2: 0.98427917667797 | AA2: LLY.N,mstag:revenueNet,2017FY,,FYR | AB2: 22,659.922 | AC2: LLY.N,mstag:revenueNet,2016FY,,FYR | AD2: 21,210.2 | AE2: NOVOb.CO,mscalc:priceToSales,2012FY,,FYR | AF2: 7.05828823393677 | AG2: LLY.N,mscalc:closePriceCurrencyCalc | AH2: USD | AI2: LLY.N,mstag:revenueNet,2017Q4,,FYR | AJ2: 6,160.8 | AK2: LLY.N,mscalc:targetPrice | AL2: 35 | AM2: LLY.N,mstag:revenueNet,2018Q2,,FYR | AN2: 5,919.644 | AO2: LLY.N,mscalc:epsForConsensusForThomsonFeed,2022FY,,FYR | AP2: 7.59880083712444 | AQ2: NOVOb.CO,mscalc:sharePriceCurrent | AR2: 944.5 | AS2: LLY.N,mscalc:targetPrice,,,,USD | AT2: 93 | AU2: LLY.N,mstag:revenueNet,2017Q3,,FYR | AV2: 5,658.1 | AW2: LLY.N,mscalc:epsForConsensusForThomsonFeed,2023FY,,FYR | AX2: 8.23734103140301 | AY2: LLY.N,mscalc:epsForConsensusForThomsonFeed,2016Q2,,FYR | AZ2: 0.857291363034781 | BA2: LLY.N,mstag:revenueNet,2015FY,,FYR | BB2: 19,958.7 | BC2: LLY.N,mscalc:epsForConsensusForThomsonFeed,2021FY,,FYR | BD2: 6.87922774344024 | BE2: LLY.N,mscalc:epsForConsensusForThomsonFeed,2017Q2,,FYR | BF2: 1.11379137459678 | BG2: LLY.N,mstag:revenueNet,2014FY,,FYR | BH2: 20,706.8357451 | BI2: LLY.N,mstag:researchAndDevelopment,2013FY,,FYR | BJ2: 5,397.4163 | BK2: LLY.N,mstag:sellingGeneralAndAdministrativeExpenses,2012FY,,FYR | BL2: 7,708.264 | BM2: LLY.N,mstag:researchAndDevelopment,2016FY,,FYR | BN2: 4,578.898118105 | BO2: LLY.N,mstag:revenueNet,2022FY,,FYR | BP2: 28,570.8276999715 | BQ2: PFE.N,mscalc:epsForConsensusForThomsonFeed,2012FY,,FYR,USD | BR2: 2.30043255392233 | BS2: LLY.N,mscalc:epsForConsensusForThomsonFeed,2015FY,,FYR | BT2: 3.40650183734521 | BU2: LLY.N,mscalc:epsForConsensusForThomsonFeed,2018Q4,,FYR | BV2: 1.18354579796166 | BW2: LLY.N,mscalc:epsForConsensusForThomsonFeed,2014FY,,FYR | BX2: 2.73980739540057 | BY2: LLY.N,mscalc:epsForConsensusForThomsonFeed,2018FY,,FYR | BZ2: 4.90238940806421 | CA2: LLY.N,mstag:sellingGeneralAndAdministrativeExpenses,2015FY,,FYR | CB2: 6,937.4376 | CC2: LLY.N,mstag:revenueNet,2020FY,,FYR | CD2: 25,383.6853101 | CE2: ,mscalc:sedolCodeCalc | CF2: NA | CG2: ,mscalc:targetPrice,,,,USD | CH2: NA | CI2: LLY.N,mscalc:sedolCodeCalc | CJ2: 2516152 | CK2: LLY.N,mstag:revenueNet,2017Q1,,FYR | CL2: 5,228.4 | CM2: NOVOb.CO,mstag:revenueNet,2015FY,,FYR | CN2: 100,088.46242012 | CO2: LLY.N,mscalc:epsForConsensusForThomsonFeed,2017Q3,,FYR | CP2: 1.04808124807651 | CQ2: LLY.N,mstag:revenueNet,2016Q1,,FYR | CR2: 4,865.1 | CS2: NOVOb.CO,mstag:revenueNet,2016FY,,FYR | CT2: 105,840.518468098 | CU2: LLY.N,mscalc:epsForConsensusForThomsonFeed,2018Q1,,FYR | CV2: 1.17060883235996 | CW2: LLY.N,mscalc:epsForConsensusForThomsonFeed,2020FY,,FYR | CX2: 6.13264701376174 | CY2: LLY.N,mscalc:marketCapitalizationCurrent | CZ2: 47,366.05438 | DA2: LLY.N,mstag:revenueNet,2012FY,,FYR | DB2: 22,829.187 | DC2: LLY.N,mscalc:priceToSales,2012FY,,FYR | DD2: 2.07480250523157 | DE2: LLY.N,mstag:sellingGeneralAndAdministrativeExpenses,2017FY,,FYR | DF2: 6,590.56572 | DG2: LLY.N,mstag:revenueNet,2023FY,,FYR | DH2: 29,907.3390228689 | DI2: LLY.N,mscalc:factsetIdCalc | DJ2: NA | DK2: ,mscalc:closePriceCurrencyCalc | DL2: NA | DM2: NOVOb.CO,mstag:revenueNet,2011FY,,FYR | DN2: 66,345.7 | DO2: LLY.N,mscalc:epsForConsensusForThomsonFeed,2017Q4,,FYR | DP2: 1.14175642025113 | DQ2: NOVOb.CO,mstag:revenueNet,2012FY,,FYR | DR2: 75,419.8735286691 | DS2: LLY.N,mstag:revenueNet,2017Q2,,FYR | DT2: 5,824.3 | DU2: LLY.N,mscalc:epsForConsensusForThomsonFeed,2017FY,,FYR | DV2: 4.22949843436989 | DW2: LLY.N,mstag:revenueNet,2016Q2,,FYR | DX2: 5,404.8 | DY2: LLY.N,mscalc:epsForConsensusForThomsonFeed,2018Q2,,FYR | DZ2: 1.25080870206138 | EA2: LLY.N,mstag:revenueNet,2018FY,,FYR | EB2: 23,524.735 | EC2: LLY.N,mstag:revenueNet,2016Q3,,FYR | ED2: 5,191.7 | EE2: LLY.N,mstag:sellingGeneralAndAdministrativeExpenses,2014FY,,FYR | EF2: 6,937.4376 | EG2: LLY.N,mstag:researchAndDevelopment,2017FY,,FYR | EH2: 4,349.95321219975 | EI2: LLY.N,mstag:revenueNet,2021FY,,FYR | EJ2: 27,006.288050128 | EK2: LLY.N,mstag:revenueNet,2013FY,,FYR | EL2: 24,132.15242 | EM2: LLY.N,mstag:revenueNet,2016Q4,,FYR | EN2: 5,760.5 | EO2: LLY.N,mscalc:epsForConsensusForThomsonFeed,2012FY,,FYR | EP2: 3.42075776568533 | EQ2: LLY.N,mscalc:epsForConsensusForThomsonFeed,2013FY,,FYR | ER2: 4.0229705476243 | ES2: LLY.N,mstag:researchAndDevelopment,2014FY,,FYR | ET2: 5,073.571322 | EU2: LLY.N,mscalc:epsForConsensusForThomsonFeed,2019FY,,FYR | EV2: 5.42559190656427 | EW2: LLY.N,mstag:sellingGeneralAndAdministrativeExpenses,2016FY,,FYR | EX2: 6937.4376 | EY2: LLY.N,mstag:revenueNet,2018Q4,,FYR | EZ2: 6,168.883 | FA2: LLY.N,mscalc:epsForConsensusForThomsonFeed,2016FY,,FYR | FB2: 3.50832728370803 | FC2: LLY.N,mscalc:epsForConsensusForThomsonFeed,2016Q4,,FYR | FD2: 0.954688562766958 | FE2: LLY.N,mstag:revenueNet,2019FY,,FYR | FF2: 24,130.36493 | FG2: NOVOb.CO,mscalc:currentDilutedSharesOutstandingCalc | FH2: 563.61589

Sheet IS-ANNUAL
EW1: Section Header
AS3: =LEFT(AS9,1)&"FQ"&LEFT($AT9,4) -> 4FQ2011 | AU3: =LEFT(AU9,1)&"FQ"&LEFT($AY9,4) -> 1FQ2012 | AV3: =LEFT(AV9,1)&"FQ"&LEFT($AY9,4) -> 2FQ2012 | AW3: =LEFT(AW9,1)&"FQ"&LEFT($AY9,4) -> 3FQ2012 | AX3: =LEFT(AX9,1)&"FQ"&LEFT($AY9,4) -> 4FQ2012 | AZ3: =LEFT(AZ9,1)&"FQ"&LEFT($BD9,4) -> 1FQ2013 | BA3: =LEFT(BA9,1)&"FQ"&LEFT($BD9,4) -> 2FQ2013 | BB3: =LEFT(BB9,1)&"FQ"&LEFT($BD9,4) -> 3FQ2013 | BC3: =LEFT(BC9,1)&"FQ"&LEFT($BD9,4) -> 4FQ2013 | BE3: =LEFT(BE9,1)&"FQ"&LEFT($BI9,4) -> 1FQ2014 | BF3: =LEFT(BF9,1)&"FQ"&LEFT($BI9,4) -> 2FQ2014 | BG3: =LEFT(BG9,1)&"FQ"&LEFT($BI9,4) -> 3FQ2014 | BH3: =LEFT(BH9,1)&"FQ"&LEFT($BI9,4) -> 4FQ2014 | BJ3: =LEFT(BJ9,1)&"FQ"&LEFT(BN9,4) -> 1FQ2015 | BK3: =LEFT(BK9,1)&"FQ"&LEFT(BN9,4) -> 2FQ2015 | BL3: =LEFT(BL9,1)&"FQ"&LEFT(BN9,4) -> 3FQ2015 | BM3: =LEFT(BM9,1)&"FQ"&LEFT(BN9,4) -> 4FQ2015 | BO3: =LEFT(BO9,1)&"FQ"&LEFT(BS9,4) -> 1FQ2016 | BP3: =LEFT(BP9,1)&"FQ"&LEFT(BS9,4) -> 2FQ2016 | BQ3: =LEFT(BQ9,1)&"FQ"&LEFT(BS9,4) -> 3FQ2016 | BR3: =LEFT(BR9,1)&"FQ"&LEFT(BS9,4) -> 4FQ2016 | BT3: =LEFT(BT9,1)&"FQ"&LEFT(BX9,4) -> 1FQ2017 | BU3: =LEFT(BU9,1)&"FQ"&LEFT(BX9,4) -> 2FQ2017 | BV3: =LEFT(BV9,1)&"FQ"&LEFT(BX9,4) -> 3FQ2017 | BW3: =LEFT(BW9,1)&"FQ"&LEFT(BX9,4) -> 4FQ2017 | BY3: =LEFT(BY9,1)&"FQ"&LEFT(CC9,4) -> 1FQ2018 | BZ3: =LEFT(BZ9,1)&"FQ"&LEFT(CC9,4) -> 2FQ2018 | CA3: =LEFT(CA9,1)&"FQ"&LEFT(CC9,4) -> 3FQ2018 | CB3: =LEFT(CB9,1)&"FQ"&LEFT(CC9,4) -> 4FQ2018
L4: 38442 | M4: 38533 | N4: 38625 | O4: 38717 | P4: 38717 | Q4: 38807 | R4: 38898 | S4: 38990 | T4: 39082 | U4: 39082 | V4: 39172 | W4: 39263 | X4: 39355 | Y4: 39447 | Z4: 39447 | AA4: 39538 | AB4: 39629 | AC4: 39721 | AD4: 39813 | AE4: 39813 | AF4: 39903 | AG4: 39994 | AH4: 40086 | AI4: 40178 | AJ4: 40178 | AK4: 40268 | AL4: 40359 | AM4: 40451 | AN4: 40543 | AO4: 40543 | AP4: 40633 | AQ4: 40724 | AR4: 40816 | AS4: 40908 | AT4: 40908 | AU4: 40999 | AV4: 41090 | AW4: 41182 | AX4: 41274 | AY4: 41274 | AZ4: 41364 | BA4: 41455 | BB4: 41547 | BC4: 41639 | BD4: 41639 | BE4: 41729 | BF4: 41820 | BG4: 41912 | BH4: 42004 | BI4: 42004 | BJ4: 42094 | BK4: 42185 | BL4: 42277 | BM4: 42369 | BN4: 42369 | BO4: 42460 | BP4: 42551 | BQ4: 42643 | BR4: 42735 | BS4: 42735 | BT4: 42825 | BU4: 42916 | BV4: 43008 | BW4: 43100 | BX4: 43100 | BY4: 43190 | BZ4: 43281 | CA4: 43373 | CB4: 43465 | CC4: 43465 | CD4: 43830 | CE4: 44196 | CF4: 44561 | CG4: 44926 | CH4: 45291
H5: =CompanyName -> Eli Lilly & Co. | J5: =LatestRpQ -> 43190
H6: Annual Income Statement | J6: =LatestFiledQ -> 43100
H9: ($M) | L9: ="1Q:" & RIGHT(YEAR(L$4),2) & IF(L$4<=LatestRpQ, "A", "E") -> 1Q:05A | M9: ="2Q:" & RIGHT(YEAR(M$4),2) & IF(M$4<=LatestRpQ, "A", "E") -> 2Q:05A | N9: ="3Q:" & RIGHT(YEAR(N$4),2) & IF(N$4<=LatestRpQ, "A", "E") -> 3Q:05A | O9: ="4Q:" & RIGHT(YEAR(O$4),2) & IF(O$4<=LatestRpQ, "A", "E") -> 4Q:05A | P9: =YEAR(P$4) & IF(P$4<=LatestRpQ, "A", "E") -> 2005A | Q9: ="1Q:" & RIGHT(YEAR(Q$4),2) & IF(Q$4<=LatestRpQ, "A", "E") -> 1Q:06A | R9: ="2Q:" & RIGHT(YEAR(R$4),2) & IF(R$4<=LatestRpQ, "A", "E") -> 2Q:06A | S9: ="3Q:" & RIGHT(YEAR(S$4),2) & IF(S$4<=LatestRpQ, "A", "E") -> 3Q:06A | T9: ="4Q:" & RIGHT(YEAR(T$4),2) & IF(T$4<=LatestRpQ, "A", "E") -> 4Q:06A | U9: =YEAR(U$4) & IF(U$4<=LatestRpQ, "A", "E") -> 2006A | V9: ="1Q:" & RIGHT(YEAR(V$4),2) & IF(V$4<=LatestRpQ, "A", "E") -> 1Q:07A | W9: ="2Q:" & RIGHT(YEAR(W$4),2) & IF(W$4<=LatestRpQ, "A", "E") -> 2Q:07A | X9: ="3Q:" & RIGHT(YEAR(X$4),2) & IF(X$4<=LatestRpQ, "A", "E") -> 3Q:07A | Y9: ="4Q:" & RIGHT(YEAR(Y$4),2) & IF(Y$4<=LatestRpQ, "A", "E") -> 4Q:07A | Z9: =YEAR(Z$4) & IF(Z$4<=LatestRpQ, "A", "E") -> 2007A | AA9: ="1Q:" & RIGHT(YEAR(AA$4),2) & IF(AA$4<=LatestRpQ, "A", "E") -> 1Q:08A | AB9: ="2Q:" & RIGHT(YEAR(AB$4),2) & IF(AB$4<=LatestRpQ, "A", "E") -> 2Q:08A | AC9: ="3Q:" & RIGHT(YEAR(AC$4),2) & IF(AC$4<=LatestRpQ, "A", "E") -> 3Q:08A | AD9: ="4Q:" & RIGHT(YEAR(AD$4),2) & IF(AD$4<=LatestRpQ, "A", "E") -> 4Q:08A | AE9: =YEAR(AE$4) & IF(AE$4<=LatestRpQ, "A", "E") -> 2008A | AF9: ="1Q:" & RIGHT(YEAR(AF$4),2) & IF(AF$4<=LatestRpQ, "A", "E") -> 1Q:09A | AG9: ="2Q:" & RIGHT(YEAR(AG$4),2) & IF(AG$4<=LatestRpQ, "A", "E") -> 2Q:09A | AH9: ="3Q:" & RIGHT(YEAR(AH$4),2) & IF(AH$4<=LatestRpQ, "A", "E") -> 3Q:09A | AI9: ="4Q:" & RIGHT(YEAR(AI$4),2) & IF(AI$4<=LatestRpQ, "A", "E") -> 4Q:09A | AJ9: =YEAR(AJ$4) & IF(AJ$4<=LatestRpQ, "A", "E") -> 2009A | AK9: ="1Q:" & RIGHT(YEAR(AK$4),2) & IF(AK$4<=LatestRpQ, "A", "E") -> 1Q:10A | AL9: ="2Q:" & RIGHT(YEAR(AL$4),2) & IF(AL$4<=LatestRpQ, "A", "E") -> 2Q:10A | AM9: ="3Q:" & RIGHT(YEAR(AM$4),2) & IF(AM$4<=LatestRpQ, "A", "E") -> 3Q:10A | AN9: ="4Q:" & RIGHT(YEAR(AN$4),2) & IF(AN$4<=LatestRpQ, "A", "E") -> 4Q:10A | AO9: =YEAR(AO$4) & IF(AO$4<=LatestRpQ, "A", "E") -> 2010A | AP9: ="1Q:" & RIGHT(YEAR(AP$4),2) & IF(AP$4<=LatestRpQ, "A", "E") -> 1Q:11A | AQ9: ="2Q:" & RIGHT(YEAR(AQ$4),2) & IF(AQ$4<=LatestRpQ, "A", "E") -> 2Q:11A | AR9: ="3Q:" & RIGHT(YEAR(AR$4),2) & IF(AR$4<=LatestRpQ, "A", "E") -> 3Q:11A | AS9: ="4Q:" & RIGHT(YEAR(AS$4),2) & IF(AS$4<=LatestRpQ, "A", "E") -> 4Q:11A | AT9: =YEAR(AT$4) & IF(AT$4<=LatestRpQ, "A", "E") -> 2011A | AU9: ="1Q:" & RIGHT(YEAR(AU$4),2) & IF(AU$4<=LatestRpQ, "A", "E") -> 1Q:12A | AV9: ="2Q:" & RIGHT(YEAR(AV$4),2) & IF(AV$4<=LatestRpQ, "A", "E") -> 2Q:12A | AW9: ="3Q:" & RIGHT(YEAR(AW$4),2) & IF(AW$4<=LatestRpQ, "A", "E") -> 3Q:12A | AX9: ="4Q:" & RIGHT(YEAR(AX$4),2) & IF(AX$4<=LatestRpQ, "A", "E") -> 4Q:12A | AY9: =YEAR(AY$4) & IF(AY$4<=LatestRpQ, "A", "E") -> 2012A | AZ9: ="1Q:" & RIGHT(YEAR(AZ$4),2) & IF(AZ$4<=LatestRpQ, "A", "E") -> 1Q:13A | BA9: ="2Q:" & RIGHT(YEAR(BA$4),2) & IF(BA$4<=LatestRpQ, "A", "E") -> 2Q:13A | BB9: ="3Q:" & RIGHT(YEAR(BB$4),2) & IF(BB$4<=LatestRpQ, "A", "E") -> 3Q:13A | BC9: ="4Q:" & RIGHT(YEAR(BC$4),2) & IF(BC$4<=LatestRpQ, "A", "E") -> 4Q:13A | BD9: =YEAR(BD$4) & IF(BD$4<=LatestRpQ, "A", "E") -> 2013A | BE9: ="1Q:" & RIGHT(YEAR(BE$4),2) & IF(BE$4<=LatestRpQ, "A", "E") -> 1Q:14A | BF9: ="2Q:" & RIGHT(YEAR(BF$4),2) & IF(BF$4<=LatestRpQ, "A", "E") -> 2Q:14A | BG9: ="3Q:" & RIGHT(YEAR(BG$4),2) & IF(BG$4<=LatestRpQ, "A", "E") -> 3Q:14A | BH9: ="4Q:" & RIGHT(YEAR(BH$4),2) & IF(BH$4<=LatestRpQ, "A", "E") -> 4Q:14A | BI9: =YEAR(BI$4) & IF(BI$4<=LatestRpQ, "A", "E") -> 2014A | BJ9: ="1Q:" & RIGHT(YEAR(BJ$4),2) & IF(BJ$4<=LatestRpQ, "A", "E") -> 1Q:15A | BK9: ="2Q:" & RIGHT(YEAR(BK$4),2) & IF(BK$4<=LatestRpQ, "A", "E") -> 2Q:15A | BL9: ="3Q:" & RIGHT(YEAR(BL$4),2) & IF(BL$4<=LatestRpQ, "A", "E") -> 3Q:15A | BM9: ="4Q:" & RIGHT(YEAR(BM$4),2) & IF(BM$4<=LatestRpQ, "A", "E") -> 4Q:15A | BN9: =YEAR(BN$4) & IF(BN$4<=LatestRpQ, "A", "E") -> 2015A | BO9: ="1Q:" & RIGHT(YEAR(BO$4),2) & IF(BO$4<=LatestRpQ, "A", "E") -> 1Q:16A | BP9: ="2Q:" & RIGHT(YEAR(BP$4),2) & IF(BP$4<=LatestRpQ, "A", "E") -> 2Q:16A | BQ9: ="3Q:" & RIGHT(YEAR(BQ$4),2) & IF(BQ$4<=LatestRpQ, "A", "E") -> 3Q:16A | BR9: ="4Q:" & RIGHT(YEAR(BR$4),2) & IF(BR$4<=LatestRpQ, "A", "E") -> 4Q:16A | BS9: =YEAR(BS$4) & IF(BS$4<=LatestRpQ, "A", "E") -> 2016A | BT9: ="1Q:" & RIGHT(YEAR(BT$4),2) & IF(BT$4<=LatestRpQ, "A", "E") -> 1Q:17A | BU9: ="2Q:" & RIGHT(YEAR(BU$4),2) & IF(BU$4<=LatestRpQ, "A", "E") -> 2Q:17A | BV9: ="3Q:" & RIGHT(YEAR(BV$4),2) & IF(BV$4<=LatestRpQ, "A", "E") -> 3Q:17A | BW9: ="4Q:" & RIGHT(YEAR(BW$4),2) & IF(BW$4<=LatestRpQ, "A", "E") -> 4Q:17A | BX9: =YEAR(BX$4) & IF(BX$4<=LatestRpQ, "A", "E") -> 2017A | BY9: ="1Q:" & RIGHT(YEAR(BY$4),2) & IF(BY$4<=LatestRpQ, "A", "E") -> 1Q:18A | BZ9: ="2Q:" & RIGHT(YEAR(BZ$4),2) & IF(BZ$4<=LatestRpQ, "A", "E") -> 2Q:18E | CA9: ="3Q:" & RIGHT(YEAR(CA$4),2) & IF(CA$4<=LatestRpQ, "A", "E") -> 3Q:18E | CB9: ="4Q:" & RIGHT(YEAR(CB$4),2) & IF(CB$4<=LatestRpQ, "A", "E") -> 4Q:18E | CC9: =YEAR(CC$4) & IF(CC$4<=LatestRpQ, "A", "E") -> 2018E | CD9: =YEAR(CD$4) & IF(CD$4<=LatestRpQ, "A", "E") -> 2019E | CE9: =YEAR(CE$4) & IF(CE$4<=LatestRpQ, "A", "E") -> 2020E | CF9: =YEAR(CF$4) & IF(CF$4<=LatestRpQ, "A", "E") -> 2021E | CG9: =YEAR(CG$4) & IF(CG$4<=LatestRpQ, "A", "E") -> 2022E | CH9: =YEAR(CH$4) & IF(CH$4<=LatestRpQ, "A", "E") -> 2023E
H11: Total revenues | L11: 3497.4 | M11: 3667.7 | N11: 3601.1 | O11: 3879.1 | P11: 14645.3 | Q11: ='REV-ANNUAL'!Q235 -> 3714.8 | R11: ='REV-ANNUAL'!R235 -> 3867.1 | S11: ='REV-ANNUAL'!S235 -> 3864.05 | T11: ='REV-ANNUAL'!T235 -> 4245.3 | U11: =Q11+R11+S11+T11 -> 15691.25 | V11: ='REV-ANNUAL'!V235 -> 4226.2 | W11: ='REV-ANNUAL'!W235 -> 4630.9 | X11: ='REV-ANNUAL'!X235 -> 4586.8 | Y11: ='REV-ANNUAL'!Y235 -> 5189.8 | Z11: =V11+W11+X11+Y11 -> 18633.7 | AA11: ='REV-ANNUAL'!AA235 -> 4911 | AB11: ='REV-ANNUAL'!AB235 -> 5251 | AC11: ='REV-ANNUAL'!AC235 -> 5308.7 | AD11: ='REV-ANNUAL'!AD235 -> 5261.7 | AE11: =AA11+AB11+AC11+AD11 -> 20732.4 | AF11: ='REV-ANNUAL'!AF235 -> 5046.5 | AG11: ='REV-ANNUAL'!AG235 -> 5292.61 | AH11: ='REV-ANNUAL'!AH235 -> 5562.2 | AI11: ='REV-ANNUAL'!AI235 -> 5934.7 | AJ11: =AF11+AG11+AH11+AI11 -> 21836.01 | AK11: ='REV-ANNUAL'!AK235 -> 5485.4 | AL11: ='REV-ANNUAL'!AL235 -> 5748.7 | AM11: ='REV-ANNUAL'!AM235 -> 5654.9 | AN11: ='REV-ANNUAL'!AN235 -> 6187.08 | AO11: ='REV-ANNUAL'!AO235 -> 23076.08 | AP11: ='REV-ANNUAL'!AP235 -> 5839.2 | AQ11: ='REV-ANNUAL'!AQ235 -> 6253 | AR11: ='REV-ANNUAL'!AR235 -> 6148 | ... CH11: ='REV-ANNUAL'!CH235 -> 28120.927 | EW11: Non-GAAP P&L
H12: Pharmaceuticals | L12: 3301.9 | M12: 3466.8 | N12: 3385.5 | O12: 3627.7 | P12: 13785.1 | Q12: ='REV-ANNUAL'!Q11 -> 3516.4 | R12: ='REV-ANNUAL'!R11 -> 3666.1 | S12: ='REV-ANNUAL'!S11 -> 3647.85 | T12: ='REV-ANNUAL'!T11 -> 3985.4 | U12: ='REV-ANNUAL'!U11 -> 14815.55 | V12: ='REV-ANNUAL'!V11 -> 4011.1 | W12: ='REV-ANNUAL'!W11 -> 4416.2 | X12: ='REV-ANNUAL'!X11 -> 4350.2 | ... AD12: ='REV-ANNUAL'!AD11 -> 4775.2 | AE12: =SUM(AA12:AD12) -> 18917 | AF12: ='REV-ANNUAL'!AF11 -> 4627.3 | AG12: ='REV-ANNUAL'!AG11 -> 4837.75 | AH12: ='REV-ANNUAL'!AH11 -> 5071.1 | AI12: ='REV-ANNUAL'!AI11 -> 5428.1 | AJ12: =SUM(AF12:AI12) -> 19964.25 | AK12: ='REV-ANNUAL'!AK11 -> 5042.9 | AL12: ='REV-ANNUAL'!AL11 -> 5265.2 | AM12: ='REV-ANNUAL'!AM11 -> 5133.7 | AN12: ='REV-ANNUAL'!AN11 -> 5609.48 | AO12: ='REV-ANNUAL'!AO11 -> 21051.28 | AP12: ='REV-ANNUAL'!AP11 -> 5320.2 | AQ12: ='REV-ANNUAL'!AQ11 -> 5697.2 | AR12: ='REV-ANNUAL'!AR11 -> 5520.7 | ... CH12: ='REV-ANNUAL'!CH11 -> 23755.99
H13: ='REV-ANNUAL'!H118 -> Cyramza | AO13: ='REV-ANNUAL'!AO118 -> 0 | AT13: ='REV-ANNUAL'!AT118 -> 0 | AY13: ='REV-ANNUAL'!AY118 -> 0 | BD13: ='REV-ANNUAL'!BD118 -> 0 | BE13: ='REV-ANNUAL'!BE19 -> 283.1 | BF13: ='REV-ANNUAL'!BF19 -> 243.8 | BG13: ='REV-ANNUAL'!BG19 -> 257.4 | BH13: ='REV-ANNUAL'!BH19 -> 253.1 | BI13: ='REV-ANNUAL'!BI118 -> 75.7 | BJ13: ='REV-ANNUAL'!BJ118 -> 67.5 | BK13: ='REV-ANNUAL'!BK118 -> 87.7 | BL13: ='REV-ANNUAL'!BL118 -> 111.2 | BM13: ='REV-ANNUAL'!BM118 -> 117.5 | BN13: ='REV-ANNUAL'!BN118 -> 383.9 | BO13: ='REV-ANNUAL'!BO118 -> 131 | BP13: ='REV-ANNUAL'!BP118 -> 147 | ... CH13: ='REV-ANNUAL'!CH118 -> 890.77652
H14: ='REV-ANNUAL'!H71 -> Jardiance/Glyxambi (100% GM, receive 50% GP from BI) | AO14: ='REV-ANNUAL'!AO71 -> 0 | AT14: ='REV-ANNUAL'!AT71 -> 0 | AY14: ='REV-ANNUAL'!AY71 -> 0 | BD14: ='REV-ANNUAL'!BD71 -> 0 | BE14: ='REV-ANNUAL'!BE71 -> 0 | BF14: ='REV-ANNUAL'!BF71 -> 0 | BG14: ='REV-ANNUAL'!BG71 -> 4.5 | BH14: ='REV-ANNUAL'!BH71 -> 5.6 | BI14: ='REV-ANNUAL'!BI71 -> 10.1 | BJ14: ='REV-ANNUAL'!BJ71 -> 19.3 | BK14: ='REV-ANNUAL'!BK71 -> 11.1 | ... CH14: ='REV-ANNUAL'!CH71 -> 1759.8203
H15: ='REV-ANNUAL'!H68 -> Tradjenta/Jenta (100% GM, receive 50% GP from BI) | AO15: ='REV-ANNUAL'!AO68 -> 0 | AP15: ='REV-ANNUAL'!AP68 -> 0 | AQ15: ='REV-ANNUAL'!AQ68 -> 5.6 | AR15: ='REV-ANNUAL'!AR68 -> 2.8 | AS15: ='REV-ANNUAL'!AS68 -> 6.7 | AT15: ='REV-ANNUAL'!AT68 -> 15.1 | AU15: ='REV-ANNUAL'!AU68 -> 12.8 | AV15: ='REV-ANNUAL'!AV68 -> 13.2 | ... CH15: ='REV-ANNUAL'!CH68 -> 753.49251
H16: ='REV-ANNUAL'!H25 -> Cymbalta | L16: ='REV-ANNUAL'!L25 -> 106.8 | M16: ='REV-ANNUAL'!M25 -> 161.4 | N16: ='REV-ANNUAL'!N25 -> 182.7 | O16: ='REV-ANNUAL'!O25 -> 228.8 | P16: ='REV-ANNUAL'!P25 -> 679.7 | Q16: ='REV-ANNUAL'!Q25 -> 233.2 | R16: ='REV-ANNUAL'!R25 -> 310.4 | S16: ='REV-ANNUAL'!S25 -> 348.6 | ... CH16: ='REV-ANNUAL'!CH25 -> 176.23155
H17: ='REV-ANNUAL'!H50 -> Humulin | L17: ='REV-ANNUAL'!L50 -> 256.9 | M17: ='REV-ANNUAL'!M50 -> 249.7 | N17: ='REV-ANNUAL'!N50 -> 250.9 | O17: ='REV-ANNUAL'!O50 -> 247.2 | P17: ='REV-ANNUAL'!P50 -> 1004.7 | Q17: ='REV-ANNUAL'!Q50 -> 218.5 | R17: ='REV-ANNUAL'!R50 -> 219.8 | S17: ='REV-ANNUAL'!S50 -> 230 | ... CH17: ='REV-ANNUAL'!CH50 -> 1137.3212
H18: ='REV-ANNUAL'!H53 -> Humalog | L18: ='REV-ANNUAL'!L53 -> 286.1 | M18: ='REV-ANNUAL'!M53 -> 296.2 | N18: ='REV-ANNUAL'!N53 -> 306.2 | O18: ='REV-ANNUAL'!O53 -> 309.1 | P18: ='REV-ANNUAL'!P53 -> 1197.6 | Q18: ='REV-ANNUAL'!Q53 -> 304.5 | R18: ='REV-ANNUAL'!R53 -> 320.5 | S18: ='REV-ANNUAL'!S53 -> 322.2 | ... CH18: ='REV-ANNUAL'!CH53 -> 1629.5046
H19: ='REV-ANNUAL'!H115 -> Alimta | L19: ='REV-ANNUAL'!L115 -> 93.9 | M19: ='REV-ANNUAL'!M115 -> 111.1 | N19: ='REV-ANNUAL'!N115 -> 122.3 | O19: ='REV-ANNUAL'!O115 -> 135.9 | P19: ='REV-ANNUAL'!P115 -> 463.2 | Q19: ='REV-ANNUAL'!Q115 -> 130.1 | R19: ='REV-ANNUAL'!R115 -> 153.1 | S19: ='REV-ANNUAL'!S115 -> 157.2 | ... CH19: ='REV-ANNUAL'!CH115 -> 250.76596
H20: ='REV-ANNUAL'!H143 -> Cialis | L20: ='REV-ANNUAL'!L143 -> 0 | M20: ='REV-ANNUAL'!M143 -> 0 | N20: ='REV-ANNUAL'!N143 -> 0 | O20: ='REV-ANNUAL'!O143 -> 0 | P20: ='REV-ANNUAL'!P143 -> 0 | Q20: ='REV-ANNUAL'!Q143 -> 0 | R20: ='REV-ANNUAL'!R143 -> 0 | S20: ='REV-ANNUAL'!S143 -> 0 | ... CH20: ='REV-ANNUAL'!CH143 -> 305.41451
H21: Animal health | L21: 195.5 | M21: 201 | N21: 215.8 | O21: 251.5 | P21: 863.8 | Q21: ='REV-ANNUAL'!Q206 -> 198.4 | R21: ='REV-ANNUAL'!R206 -> 201 | S21: ='REV-ANNUAL'!S206 -> 216.2 | T21: ='REV-ANNUAL'!T206 -> 259.9 | U21: ='REV-ANNUAL'!U206 -> 875.5 | V21: ='REV-ANNUAL'!V206 -> 215.1 | W21: ='REV-ANNUAL'!W206 -> 214.7 | X21: ='REV-ANNUAL'!X206 -> 236.6 | ... AD21: ='REV-ANNUAL'!AD206 -> 326.4 | AE21: =SUM(AA21:AD21) -> 1093.3 | AF21: ='REV-ANNUAL'!AF206 -> 264.1 | AG21: ='REV-ANNUAL'!AG206 -> 275.4 | AH21: ='REV-ANNUAL'!AH206 -> 314.6 | AI21: ='REV-ANNUAL'!AI206 -> 353.2 | AJ21: =SUM(AF21:AI21) -> 1207.3 | AK21: ='REV-ANNUAL'!AK206 -> 289.6 | AL21: ='REV-ANNUAL'!AL206 -> 324.1 | AM21: ='REV-ANNUAL'!AM206 -> 353.3 | AN21: ='REV-ANNUAL'!AN206 -> 424.3 | AO21: ='REV-ANNUAL'!AO206 -> 1391.3 | AP21: ='REV-ANNUAL'!AP206 -> 369.8 | AQ21: ='REV-ANNUAL'!AQ206 -> 389.5 | AR21: ='REV-ANNUAL'!AR206 -> 451.1 | ... CH21: ='REV-ANNUAL'!CH206 -> 4364.9374
H22: Pipeline | L22: 195.5 | M22: 201 | N22: 215.8 | O22: 251.5 | Q22: ='REV-ANNUAL'!Q207 -> 84 | R22: ='REV-ANNUAL'!R207 -> 92.7 | S22: ='REV-ANNUAL'!S207 -> 98 | T22: ='REV-ANNUAL'!T207 -> 131.2 | V22: ='REV-ANNUAL'!V207 -> 92.7 | W22: ='REV-ANNUAL'!W207 -> 96.1 | X22: ='REV-ANNUAL'!X207 -> 112.4 | Y22: ='REV-ANNUAL'!Y207 -> 179.7 | AF22: ='REV-ANNUAL'!AF201 -> 0 | AG22: ='REV-ANNUAL'!AG201 -> 0 | AH22: ='REV-ANNUAL'!AH201 -> 0 | AI22: ='REV-ANNUAL'!AI201 -> 0 | AJ22: ='REV-ANNUAL'!AJ201 -> 0 | AK22: ='REV-ANNUAL'!AK201 -> 0 | AL22: ='REV-ANNUAL'!AL201 -> 0 | AM22: ='REV-ANNUAL'!AM201 -> 0 | ... CH22: ='REV-ANNUAL'!CH201 -> 4099.8971
H24: COGS | L24: 859 | M24: 871.3 | N24: 845.7 | O24: 898.2 | P24: =SUM(L24:O24) -> 3474.2 | Q24: 806.5 | R24: 860.6 | S24: 860.4 | T24: 1019 | U24: =SUM(Q24:T24) -> 3546.5 | V24: 922.5 | W24: 998.9 | X24: 1054.6 | Y24: 1272.8 | Z24: =SUM(V24:Y24) -> 4248.8 | AA24: 1155.1 | AB24: 1183.3 | AC24: 1199.2 | AD24: 930.9 | AE24: =SUM(AA24:AD24) -> 4468.5 | AF24: 816.4 | AG24: 947.4 | AH24: 1051.9 | AI24: 1431.3 | AJ24: =SUM(AF24:AI24) -> 4247 | AK24: 1122.5 | AL24: 1023.9 | AM24: 987.6 | AN24: 1232.2 | AO24: =SUM(AK24:AN24) -> 4366.2 | AP24: 1180.1 | AQ24: 1228 | AR24: 1338.1 | AS24: 1321.7 | AT24: =SUM(AP24:AS24) -> 5067.9 | AU24: 1197.9 | AV24: 1146.7 | AW24: 1203.6 | AX24: 1248.3 | AY24: =SUM(AU24:AX24) -> 4796.5 | AZ24: 1158.3 | BA24: 1165.2 | BB24: 1198.1 | BC24: 1386.5 | BD24: =SUM(AZ24:BC24) -> 4908.1 | BE24: =1222.7-92.4 -> 1130.3 | BF24: =1189.7-95.8 -> 1093.9 | BG24: =1267-98.1 -> 1168.9 | BH24: =1253.1-98.8 -> 1154.3 | BI24: =SUM(BE24:BH24) -> 4547.4 | BJ24: 1012.3 | BK24: 1033.9 | BL24: 1099 | BM24: 1222.3 | BN24: =SUM(BJ24:BM24) -> 4367.5 | BO24: 1152.4 | BP24: 1298.4 | BQ24: 1225.1 | BR24: 1303.3 | BS24: =SUM(BO24:BR24) -> 4979.2 | BT24: 1143 | BU24: 1359.2 | BV24: 1406.1 | BW24: 1450.7 | BX24: =SUM(BT24:BW24) -> 5359 | BY24: =1420.2 -> 1420.2 | BZ24: =BZ11*BZ56 -> 1504.315 | CA24: =CA11*CA56 -> 1527.0779 | CB24: =CB11*CB56 -> 1561.3365 | CC24: =SUM(BY24:CB24) -> 6012.9294 | CD24: =CD11*CD56 -> 5975.8612 | CE24: =CE11*CE56 -> 5995.7927 | CF24: =CF11*CF56 -> 6081.14 | CG24: =CG11*CG56 -> 6123.9603 | CH24: =CH11*CH56 -> 6186.604
H25: Gross profit | L25: =L11-L24 -> 2638.4 | M25: =M11-M24 -> 2796.4 | N25: =N11-N24 -> 2755.4 | O25: =O11-O24 -> 2980.9 | P25: =P11-P24 -> 11171.1 | Q25: =Q11-Q24 -> 2908.3 | R25: =R11-R24 -> 3006.5 | S25: =S11-S24 -> 3003.65 | ... CH25: =CH11-CH24 -> 21934.323
H26: SG&A | L26: 1090.4 | M26: 1146.1 | N26: 1070.9 | O26: 1189.6 | P26: =SUM(L26:O26) -> 4497 | Q26: 1142.9 | R26: 1237.9 | S26: 1198.2 | T26: 1310.8 | U26: =SUM(Q26:T26) -> 4889.8 | V26: 1336.8 | W26: 1524.7 | X26: 1477.8 | Y26: 1755.8 | Z26: =SUM(V26:Y26) -> 6095.1 | AA26: 1575 | AB26: 1739.6 | AC26: 1673.2 | AD26: 1740.5 | AE26: =SUM(AA26:AD26) -> 6728.3 | AF26: 1529.2 | AG26: 1708.2 | AH26: 1701.8 | AI26: 1953.3 | AJ26: =SUM(AF26:AI26) -> 6892.5 | AK26: 1614.4 | AL26: 1755.4 | AM26: 1694.9 | AN26: 1988.7 | AO26: =SUM(AK26:AN26) -> 7053.4 | AP26: 1785.7 | AQ26: 2043 | AR26: 1917.8 | AS26: 2133.4 | AT26: =SUM(AP26:AS26) -> 7879.9 | AU26: 1847.5 | AV26: 1931.1 | AW26: 1757.4 | AX26: 1977.5 | AY26: =SUM(AU26:AX26) -> 7513.5 | AZ26: 1652 | BA26: 1867.6 | BB26: 1652.4 | BC26: 1953.6 | BD26: =SUM(AZ26:BC26) -> 7125.6 | BE26: =1484.9-35.7 -> 1449.2 | BF26: =1663.9-36 -> 1627.9 | BG26: =1672.1-119-36.3 -> 1516.8 | BH26: =1799.9-35.7 -> 1764.2 | BI26: =SUM(BE26:BH26) -> 6358.1 | BJ26: 1487.9 | BK26: =1635.4-35.8 -> 1599.6 | BL26: =1575.7-35.8 -> 1539.9 | BM26: 1796.3 | BN26: =SUM(BJ26:BM26) -> 6423.7 | BO26: =1473.9-1.7 -> 1472.2 | BP26: 1620.8 | BQ26: 1563.7 | BR26: 1788.4 | BS26: =SUM(BO26:BR26) -> 6445.1 | BT26: =1544.7-1.8 -> 1542.9 | BU26: 1705.8 | BV26: 1554.3 | BW26: 1779.3 | BX26: =SUM(BT26:BW26) -> 6582.3 | BY26: =1498.9 -> 1498.9 | BZ26: =BU26*(1+BZ70) -> 1637.568 | CA26: =BV26*(1+CA70) -> 1507.671 | CB26: =BW26*(1+CB70) -> 1725.921 | CC26: =SUM(BY26:CB26) -> 6370.06 | CD26: =CC26*(1+CD70) -> 6306.3594 | CE26: =CD26*(1+CE70) -> 6369.423 | CF26: =CE26*(1+CF70) -> 6496.8115 | CG26: =CF26*(1+CG70) -> 6626.7477 | CH26: =CG26*(1+CH70) -> 6759.2826
H27: IMCL collab agreemt reimbursemt | P27: 64.796 | Q27: 21.109 | R27: 13.43 | S27: 16.266 | T27: 17.698 | U27: =SUM(Q27:T27) -> 68.503 | V27: 19.385 | W27: 15.818 | X27: 18.495 | Y27: 16.934 | Z27: =SUM(V27:Y27) -> 70.632 | AA27: 18.082 | AB27: 19.544 | AC27: 23.112 | AD27: NA | BG27: 1243.2 | BW27: 1779.1 | BX27: =SUM(BT27:BW27) -> 1779.1 | BY27: 1779.1 | CC27: =SUM(BY27:CB27) -> 1779.1
H28: R&D | L28: 702.2 | M28: 762.4 | N28: 751 | O28: 809.9 | P28: =SUM(L28:O28) -> 3025.5 | Q28: 740.8 | R28: 774.8 | S28: 755.7 | T28: 858 | U28: =SUM(Q28:T28) -> 3129.3 | V28: 834.2 | W28: 854.4 | X28: 844.5 | Y28: 953.6 | Z28: =SUM(V28:Y28) -> 3486.7 | AA28: 913.1 | AB28: 994.3 | AC28: 996.4 | AD28: 1101.5 | AE28: =SUM(AA28:AD28) -> 4005.3 | AF28: 947.3 | AG28: 1040.4 | AH28: 1122.1 | AI28: 1216.7 | AJ28: =SUM(AF28:AI28) -> 4326.5 | AK28: 1039.1 | AL28: 1187.2 | AM28: 1219.8 | AN28: 1438.1 | AO28: =SUM(AK28:AN28) -> 4884.2 | AP28: 1124 | AQ28: 1260.6 | AR28: 1280.9 | AS28: 1355.3 | AT28: =SUM(AP28:AS28) -> 5020.8 | AU28: 1151.5 | AV28: 1320.7 | AW28: 1342.8 | AX28: =1463.091316 -> 1463.0913 | AY28: =SUM(AU28:AX28) -> 5278.0913 | AZ28: 1348.1 | BA28: 1330.4 | BB28: 1377.4 | BC28: 1475.4 | BD28: =SUM(AZ28:BC28) -> 5531.3 | BE28: =1109.3-0.7 -> 1108.6 | BF28: =1195.4-0.2 -> 1195.2 | BG28: =1243.2-0.2 -> 1243 | BH28: =1185.7-0.2 -> 1185.5 | BI28: =SUM(BE28:BH28) -> 4732.3 | BJ28: 1039.1 | BK28: 1169.5 | BL28: 1169.5 | BM28: 1444.2 | BN28: =SUM(BJ28:BM28) -> 4822.3 | BO28: =1221-0.2 -> 1220.8 | BP28: 1335.7 | BQ28: 1236.2 | BR28: 1450.5 | BS28: =SUM(BO28:BR28) -> 5243.2 | BT28: 1238.3 | BU28: 1250.8 | BV28: 1319.2 | BW28: 1473 | BX28: =SUM(BT28:BW28) -> 5281.3 | BY28: =1176.7 -> 1176.7 | BZ28: =BU28*(1+BZ71) -> 1288.324 | CA28: =BV28*(1+CA71) -> 1306.008 | CB28: =BW28*(1+CB71) -> 1487.73 | CC28: =SUM(BY28:CB28) -> 5258.762 | CD28: =CC28*(1+CD71) -> 5258.762 | CE28: =CD28*(1+CE71) -> 5311.3496 | CF28: =CE28*(1+CF71) -> 5417.5766 | CG28: =CF28*(1+CG71) -> 5525.9281 | CH28: =CG28*(1+CH71) -> 5636.4467
H29: Operating income, EBITA | L29: =L25-L26-L28 -> 845.8 | M29: =M25-M26-M28 -> 887.9 | N29: =N25-N26-N28 -> 933.5 | O29: =O25-O26-O28 -> 981.4 | P29: =P25-P26-P28 -> 3648.6 | Q29: =Q25-Q26-Q28 -> 1024.6 | R29: =R25-R26-R28 -> 993.8 | S29: =S25-S26-S28 -> 1049.75 | ... CH29: =CH25-CH26-CH28 -> 9538.5938
H30: Amortization (from 10-Q/K) | AO30: 385.7 | AT30: 469 | AU30: 147.7 | AV30: 133.1 | AW30: 140.8 | AX30: 141.4 | AY30: =SUM(AU30:AX30) -> 563 | AZ30: 146.1 | BA30: 145.2 | BB30: 132.2 | BC30: 131.5 | BD30: =SUM(AZ30:BC30) -> 555
H31: EBITA (est.) | AO31: =AO29+AO30 -> 7157.98 | AT31: =AT29+AT30 -> 6787 | AU31: =AU29+AU30 -> 1552.8 | AV31: =AV29+AV30 -> 1335.3 | AW31: =AW29+AW30 -> 1280.3 | AX31: =AX29+AX30 -> 1409.8087 | AY31: =AY29+AY30 -> 5578.2087 | AZ31: =AZ29+AZ30 -> 1589.4 | BA31: =BA29+BA30 -> 1711.7 | ... BD31: =BD29+BD30 -> 6102.8
H32: Depreciation (from 10-Q/K) | L32: =P32/4 -> 180.25 | M32: =(P32-L32)/3 -> 180.25 | N32: =(P32-L32-M32)/2 -> 180.25 | O32: =P32-N32-M32-L32 -> 180.25 | P32: 721 | Q32: =U32/4 -> 198.55 | R32: =(U32-Q32)/3 -> 198.55 | S32: =(U32-Q32-R32)/2 -> 198.55 | T32: =U32-S32-R32-Q32 -> 198.55 | U32: 794.2 | V32: =Z32/4 -> 218.775 | W32: =(Z32-V32)/3 -> 218.775 | X32: =(Z32-V32-W32)/2 -> 218.775 | Y32: =Z32-X32-W32-V32 -> 218.775 | Z32: 875.1 | AA32: =AE32/4 -> 232.3 | AB32: =(AE32-AA32)/3 -> 232.3 | AC32: =(AE32-AA32-AB32)/2 -> 232.3 | AD32: =AE32-AC32-AB32-AA32 -> 232.3 | AE32: 929.2 | AF32: =AJ32/4 -> 255.2 | AG32: =(AJ32-AF32)/3 -> 255.2 | AH32: =(AJ32-AF32-AG32)/2 -> 255.2 | AI32: =AJ32-AH32-AG32-AF32 -> 255.2 | AJ32: 1020.8 | AO32: 942.5 | AT32: 904.6 | AU32: 238.2 | AV32: 228.9 | AW32: 228.9 | AX32: 203.2 | AY32: =SUM(AU32:AX32) -> 899.2 | AZ32: 235.4 | BA32: 218.7 | BB32: 216.8 | BC32: 219.7 | BD32: =SUM(AZ32:BC32) -> 890.6 | BE32: 216.8 | BF32: 214.3 | BG32: 208.4 | BH32: 203.6 | BI32: =SUM(BE32:BH32) -> 843.1 | BJ32: 203.3 | BK32: 215.1 | BL32: 204.2 | BM32: 173.3 | BN32: =SUM(BJ32:BM32) -> 795.9 | BO32: 213 | BP32: 205.1 | BQ32: 215.1 | BR32: 175.5 | BS32: =SUM(BO32:BR32) -> 808.7 | BT32: 210.8 | BU32: 217.5 | BV32: 217.1 | BW32: 238.5 | BX32: =SUM(BT32:BW32) -> 883.9 | BY32: 215.75 | BZ32: 215.75 | CA32: 215.75 | CB32: 215.75 | CC32: =SUM(BY32:CB32) -> 863 | CD32: =CC32 -> 863 | CE32: =CD32 -> 863 | CF32: =CE32 -> 863 | CG32: =CF32 -> 863 | CH32: =CG32 -> 863
H33: EBITDA | L33: =L29+L32 -> 1026.05 | M33: =M29+M32 -> 1068.15 | N33: =N29+N32 -> 1113.75 | O33: =O29+O32 -> 1161.65 | P33: =P29+P32 -> 4369.6 | Q33: =Q29+Q32 -> 1223.15 | R33: =R29+R32 -> 1192.35 | S33: =S29+S32 -> 1248.3 | ... AJ33: =AJ29+AJ32 -> 7390.81 | AO33: =AO29+AO32+AO30 -> 8100.48 | AT33: =AT29+AT32+AT30 -> 7691.6 | AU33: =AU29+AU32+AU30 -> 1791 | AV33: =AV29+AV32+AV30 -> 1564.2 | AW33: =AW29+AW32+AW30 -> 1509.2 | AX33: =AX29+AX32+AX30 -> 1613.0087 | AY33: =AY29+AY32+AY30 -> 6477.4087 | AZ33: =AZ29+AZ32+AZ30 -> 1824.8 | BA33: =BA29+BA32+BA30 -> 1930.4 | ... BD33: =BD29+BD32+BD30 -> 6993.4 | BE33: =BE29+BE32 -> 1211.8 | BF33: =BF29+BF32 -> 1232.9 | BG33: =BG29+BG32 -> 1155.3 | BH33: =BH29+BH32 -> 1220.9 | BI33: =BI29+BI32 -> 4820.9 | BJ33: =BJ29+BJ32 -> 1308.7 | BK33: =BK29+BK32 -> 1390.8 | BL33: =BL29+BL32 -> 1355.5 | ... CH33: =CH29+CH32 -> 10401.594
H34: Other income (expense) | L34: =L37+L35+L36 -> 98.6 | M34: =M37+M35+M36 -> 45.757 | N34: =N37+N35+N36 -> 84.7 | O34: =O37+O35+O36 -> 84.6 | P34: =P37+P35+P36 -> 313.657 | Q34: =Q37+Q35+Q36 -> 31.7 | R34: =R37+R35+R36 -> 47 | S34: =S37+S35+S36 -> 56 | ... AN34: =AN37+AN35+AN36 -> -39.4 | AO34: =AO35+AO37+AO36 -> -5 | AP34: =AP37+AP35+AP36 -> -11.2 | AQ34: =AQ37+AQ35+AQ36 -> -57.6 | AR34: =AR37+AR35+AR36 -> -83.4 | AS34: =AS37+AS35+AS36 -> -26.8 | AT34: =AT37+AT35+AT36 -> -179 | AU34: =AU37+AU35+AU36 -> -46 | AV34: =AV37+AV35+AV36 -> -16.5 | AW34: =AW37+AW35+AW36 -> 0.7 | ... CH34: =CH37+CH35+CH36 -> 178.68569 | EW34: Non-GAAP Other Income/(Deductions)
H35: Interest expense | L35: -24.6 | M35: -12 | N35: -24.3 | O35: -44.3 | P35: =SUM(L35:O35) -> -105.2 | Q35: -65 | R35: -66 | S35: -62.7 | T35: -44.6 | U35: =SUM(Q35:T35) -> -238.3 | V35: -53 | W35: -59 | X35: -55.8 | Y35: -60.4 | Z35: =SUM(V35:Y35) -> -228.2 | AA35: -73.8 | AB35: -68.6 | AC35: -62 | AD35: -61.1 | AE35: =SUM(AA35:AD35) -> -265.5 | AF35: -87.6 | AG35: -64.3 | AH35: -59.2 | AI35: -50.2 | AJ35: =SUM(AF35:AI35) -> -261.3 | AK35: -47.6 | AL35: -47.5 | AM35: -47.2 | AN35: -43.2 | AO35: =SUM(AK35:AN35) -> -185.5 | AP35: -45.8 | AQ35: -45.1 | AR35: -45 | AS35: -50 | AT35: =SUM(AP35:AS35) -> -185.9 | AU35: -45.3 | AV35: -43 | AW35: -47 | AX35: -42.6 | AY35: =SUM(AU35:AX35) -> -177.9 | AZ35: -40.3 | BA35: -40.3 | BB35: -39.8 | BC35: -39.7 | BD35: =SUM(AZ35:BC35) -> -160.1 | BE35: -37.8 | BF35: -35.5 | BG35: -38.1 | BH35: -37.4 | BI35: =SUM(BE35:BH35) -> -148.8 | BJ35: -40.9 | BK35: -48 | BL35: -39.3 | BM35: -44.2 | BN35: =SUM(BJ35:BM35) -> -172.4 | BO35: -43.4 | BP35: -43.2 | BQ35: -47.2 | BR35: -51.4 | BS35: =SUM(BO35:BR35) -> -185.2 | BT35: -46.6 | BU35: -53.6 | BV35: -61.9 | BW35: -62.9 | BX35: =SUM(BT35:BW35) -> -225 | BY35: =-61.2 -> -61.2 | BZ35: =(CC35-BY35)/3 -> -54.570342 | CA35: =(CC35-BY35-BZ35)/2 -> -54.570342 | CB35: =CC35-BY35-BZ35-CA35 -> -54.570342 | CC35: =-DEBT!CC20 -> -224.91102 | CD35: =-DEBT!CD20 -> -149.94362 | CE35: =-DEBT!CE20 -> -133.35731 | CF35: =-DEBT!CF20 -> -133.35731 | CG35: =-DEBT!CG20 -> -130.08581 | CH35: =-DEBT!CH20 -> -126.81431
H36: Interest income | L36: 46 | M36: 46.3 | N36: 52 | O36: 67.9 | P36: =SUM(L36:O36) -> 212.2 | Q36: 59.7 | R36: 68 | S36: 67.5 | T36: 66.3 | U36: =SUM(Q36:T36) -> 261.5 | V36: 57 | W36: 50 | X36: 50 | Y36: 58 | Z36: =SUM(V36:Y36) -> 215 | AA36: 17.8 | AB36: 2.5 | AC36: 4.7 | AD36: 1.8 | AE36: =SUM(AA36:AD36) -> 26.8 | AF36: 27.4 | AG36: 18.8 | AH36: 15.2 | AI36: 13.8 | AJ36: =SUM(AF36:AI36) -> 75.2 | AK36: 10.6 | AL36: 11 | AM36: 16.3 | AN36: 14 | AO36: =SUM(AK36:AN36) -> 51.9 | AP36: 15.5 | AQ36: 17.8 | AR36: 22.2 | AS36: 24.4 | AT36: =SUM(AP36:AS36) -> 79.9 | AU36: 26.1 | AV36: 27.2 | AW36: 25.7 | AX36: 26.1 | AY36: =SUM(AU36:AX36) -> 105.1 | AZ36: 23.6 | BA36: 29.7 | BB36: 32.2 | BC36: 34.2 | BD36: =SUM(AZ36:BC36) -> 119.7 | BE36: 34.4 | BF36: 33.6 | BG36: 28.8 | BH36: 24.2 | BI36: =SUM(BE36:BH36) -> 121 | BJ36: 21.4 | BK36: 20.6 | BL36: 21.2 | BM36: 23.8 | BN36: =SUM(BJ36:BM36) -> 87 | BO36: 24.2 | BP36: 23.5 | BQ36: 29.1 | BR36: 31.9 | BS36: =SUM(BO36:BR36) -> 108.7 | BT36: 32.6 | BU36: 36.9 | BV36: 45.1 | BW36: 52.7 | BX36: =SUM(BT36:BW36) -> 167.3 | BY36: =45.5 -> 45.5 | BZ36: =180/4 -> 45 | CA36: =180/4 -> 45 | CB36: =180/4 -> 45 | CC36: =SUM(BY36:CB36) -> 180.5 | CD36: =CC36 -> 180.5 | CE36: =CD36 -> 180.5 | CF36: =CE36 -> 180.5 | CG36: =CF36 -> 180.5 | CH36: =CG36 -> 180.5
H37: Other income (expense), net | L37: =L38+L39+L40+L41+L42 -> 77.2 | M37: =M38+M39+M40+M41+M42 -> 11.457 | N37: =N38+N39+N40+N41+N42 -> 57 | O37: =O38+O39+O40+O41+O42 -> 61 | P37: =P38+P39+P40+P41+P42 -> 206.657 | Q37: =Q38+Q39+Q40+Q41+Q42 -> 37 | R37: =R38+R39+R40+R41+R42 -> 45 | S37: =S38+S39+S40+S41+S42 -> 51.2 | ... V37: =V38+V39+V40+V41+V42 -> 34 | W37: =W38+W39+W40+W41 -> 11 | X37: =X38+X39+X40+X41 -> 56 | Y37: =Y38+Y39+Y40+Y41 -> 34 | Z37: =Z38+Z39+Z40+Z41+Z42 -> 135 | AA37: =AA38+AA39+AA40+AA41 -> 10.7 | AB37: =AB38+AB39+AB40+AB41 -> 29.1 | AC37: =AC38+AC39+AC40+AC41 -> -19 | AD37: =AD38+AD39+AD40+AD41 -> -50 | AE37: =AE38+AE39+AE40+AE41 -> -29.2 | AF37: =AF38+AF39+AF40+AF41 -> -10.5 | AG37: =AG38+AG39+AG40+AG41 -> 21.4 | AH37: =AH38+AH39+AH40+AH41 -> -22.9 | ... AO37: =AO38+AO39+AO40+AO41 -> 128.6 | AP37: 19.1 | AQ37: =40.4-0.9-69.8 -> -30.3 | AR37: =9.8+11.6-82 -> -60.6 | AS37: =-4.7+10.8-7.3 -> -1.2 | AT37: =SUM(AP37:AS37) -> -73 | AU37: -26.8 | AV37: -0.7 | AW37: 22 | AX37: -35.5 | AY37: =SUM(AU37:AX37) -> -41 | AZ37: 50.5 | BA37: 22.5 | BB37: -23.7 | BC37: 14.6 | BD37: =SUM(AZ37:BC37) -> 63.9 | BE37: 59.4 | BF37: 55.7 | BG37: =-8+77+33.8 -> 102.8 | BH37: 58.4 | BI37: =SUM(BE37:BH37) -> 276.3 | BJ37: 112.2 | BK37: 56.8 | BL37: 104.6 | BM37: 65.1 | BN37: =SUM(BJ37:BM37) -> 338.7 | BO37: 74.1 | BP37: 40.9 | BQ37: 45.3 | BR37: 35.3 | BS37: =SUM(BO37:BR37) -> 195.6 | BT37: 29.1 | BU37: 12.8 | BV37: 2.9 | BW37: 65.3 | BX37: =SUM(BT37:BW37) -> 110.1 | BY37: 83.2 | BZ37: 50 | CA37: 50 | CB37: 50 | CC37: =SUM(BY37:CB37) -> 233.2 | CD37: 125 | CE37: 125 | CF37: 125 | CG37: 125 | CH37: 125
H38: Outlicense of mkt. prod. | L38: 14.5 | M38: 10 | N38: 12 | O38: 43 | P38: =SUM(L38:O38) -> 79.5 | Q38: 1 | R38: 1 | S38: 10.1 | T38: 12.6 | U38: =SUM(Q38:T38) -> 24.7 | V38: 2 | W38: 1 | X38: 26 | Y38: 5 | Z38: =SUM(V38:Y38) -> 34 | AA38: 4 | AB38: 5.4 | AC38: 11.7 | AD38: 33.8 | AE38: =SUM(AA38:AD38) -> 54.9 | AF38: 3.3 | AG38: 4.8 | AH38: 0 | AI38: 0 | AJ38: =SUM(AF38:AI38) -> 8.1 | AK38: 0 | AL38: 0 | AM38: 0 | AN38: 0 | AO38: =SUM(AK38:AN38) -> 0 | AP38: 0 | AQ38: 0 | AR38: 0 | AS38: 0 | AT38: =SUM(AP38:AS38) -> 0 | AU38: 0 | AV38: 0 | AW38: 0 | AX38: 0 | AY38: =SUM(AU38:AX38) -> 0 | AZ38: 0 | BD38: 0 | BE38: 0 | BF38: 0 | BG38: 0 | BH38: 0 | BI38: 0 | BN38: 0 | BS38: 0 | BT38: 0 | BU38: 0 | BV38: 0 | BW38: 0 | BX38: 0 | BY38: 0 | BZ38: 0 | CA38: 0 | CB38: 0 | CC38: 0 | CD38: 0 | CE38: 0 | CF38: 0 | CG38: 0 | CH38: 0
H39: Outlicense of dev. stage prod. | L39: 39 | M39: 13 | N39: 0 | O39: 12 | P39: =SUM(L39:O39) -> 64 | Q39: 8 | R39: 16 | S39: 3.1 | T39: 21.6 | U39: =SUM(Q39:T39) -> 48.7 | V39: 25 | W39: 29 | X39: 31 | Y39: 39 | Z39: =SUM(V39:Y39) -> 124 | AA39: 25 | AB39: 13 | AC39: 0 | AD39: 2 | AE39: =SUM(AA39:AD39) -> 40 | AF39: 1 | AG39: 0 | AH39: 0 | AI39: 0 | AJ39: =SUM(AF39:AI39) -> 1 | AK39: 11.2 | AL39: 1.6 | AM39: 3.5 | AN39: 1.2 | AO39: =SUM(AK39:AN39) -> 17.5 | AP39: 0 | AQ39: 0 | AR39: 0 | AS39: 0 | AT39: =SUM(AP39:AS39) -> 0 | AU39: 0 | AV39: 0 | AW39: 0 | AX39: 0 | AY39: =SUM(AU39:AX39) -> 0 | AZ39: 0 | BD39: 0 | BE39: 0 | BF39: 0 | BG39: 0 | BH39: 0 | BI39: 0 | BN39: 0 | BS39: 0 | BT39: 0 | BU39: 0 | BV39: 0 | BW39: 0 | BX39: 0 | BY39: 0 | BZ39: 0 | CA39: 0 | CB39: 0 | CC39: 0 | CD39: 0 | CE39: 0 | CF39: 0 | CG39: 0 | CH39: 0
H40: Partnered prod. in dev. | L40: 1.63 | M40: 2 | N40: 2 | O40: 3 | P40: =SUM(L40:O40) -> 8.63 | Q40: 1 | R40: 1 | S40: 1.1 | T40: 0.6 | U40: =SUM(Q40:T40) -> 3.7 | V40: 14 | W40: 0 | X40: 10 | Y40: 3 | Z40: =SUM(V40:Y40) -> 27 | AA40: 0 | AB40: 2.5 | AC40: 0 | AD40: 1.1 | AE40: =SUM(AA40:AD40) -> 3.6 | AF40: 0 | AG40: 0 | AH40: 0 | AI40: 0 | AJ40: =SUM(AF40:AI40) -> 0 | AK40: 0 | AL40: 0 | AM40: 0 | AN40: 0 | AO40: =SUM(AK40:AN40) -> 0 | AP40: 0 | AQ40: 0 | AR40: 0 | AS40: 0 | AT40: =SUM(AP40:AS40) -> 0 | AU40: 0 | AV40: 0 | AW40: 0 | AX40: 0 | AY40: =SUM(AU40:AX40) -> 0 | AZ40: 0 | BD40: 0 | BE40: 0 | BF40: 0 | BG40: 0 | BH40: 0 | BI40: 0 | BN40: 0 | BS40: 0 | BT40: 0 | BU40: 0 | BV40: 0 | BW40: 0 | BX40: 0 | BY40: 0 | BZ40: 0 | CA40: 0 | CB40: 0 | CC40: 0 | CD40: 0 | CE40: 0 | CF40: 0 | CG40: 0 | CH40: 0
H41: Miscellaneous income/(expense) | L41: 34.8 | M41: -13 | N41: 37 | O41: -15 | P41: =SUM(L41:O41) -> 43.8 | Q41: 7 | R41: 4 | S41: 13.1 | T41: 16 | U41: =SUM(Q41:T41) -> 40.1 | V41: -18 | W41: -19 | X41: -11 | Y41: -13 | Z41: =SUM(V41:Y41) -> -61 | AA41: -18.3 | AB41: 8.2 | AC41: -30.7 | AD41: -86.9 | AE41: =SUM(AA41:AD41) -> -127.7 | AF41: -14.8 | AG41: 16.6 | AH41: -22.9 | AI41: -31.4 | AJ41: =SUM(AF41:AI41) -> -52.5 | AK41: 100.3 | AL41: 16.5 | AM41: 5.7 | AN41: -11.4 | AO41: =SUM(AK41:AN41) -> 111.1 | AP41: 0 | AQ41: 0 | AR41: 0 | AS41: 0 | AT41: =SUM(AP41:AS41) -> 0 | AU41: 0 | AV41: 0 | AW41: 0 | AX41: 0 | AY41: =SUM(AU41:AX41) -> 0 | AZ41: 0 | BD41: =AY41 -> 0 | BE41: 0 | BF41: =BA41 -> 0 | BG41: =BB41 -> 0 | BH41: =BC41 -> 0 | BI41: =BD41 -> 0 | BN41: =BI41 -> 0 | BS41: =BN41 -> 0 | BT41: =BO41 -> 0 | BU41: =BP41 -> 0 | BV41: =BQ41 -> 0 | BW41: =BR41 -> 0 | BX41: =BS41 -> 0 | BY41: =BT41 -> 0 | BZ41: =BU41 -> 0 | ... CC41: =BX41 -> 0 | CD41: =CC41 -> 0 | CE41: =CD41 -> 0 | CF41: =CE41 -> 0 | CG41: =CF41 -> 0 | CH41: =CG41 -> 0
H42: Cialis JV | L42: -12.73 | M42: -0.543 | N42: 6 | O42: 18 | P42: =SUM(L42:O42) -> 10.727 | Q42: 20 | R42: 23 | S42: 23.8 | T42: 30.2 | U42: =SUM(Q42:T42) -> 97 | V42: 11 | W42: 0 | X42: 0 | Y42: 0 | Z42: =SUM(V42:Y42) -> 11 | AA42: 0 | AB42: 0 | AC42: 0 | AD42: 0 | AE42: =SUM(AA42:AD42) -> 0 | AF42: 0 | AJ42: =SUM(AF42:AI42) -> 0 | AO42: =SUM(AK42:AN42) -> 0
H43: IMCL lic fees and milestones | P43: 96.442 | Q43: 144.403 | R43: 33.456 | S43: 34.948 | T43: 19.462 | U43: =SUM(Q43:T43) -> 232.269 | V43: 29.294 | W43: 33.445 | X43: 19.226 | Y43: 20.945 | Z43: =SUM(V43:Y43) -> 102.91 | AA43: 24.132 | AB43: 27.818 | AC43: 25.771 | AD43: NA | AE43: =SUM(AA43:AD43) -> 77.721 | AF43: 0
H44: Pretax income | L44: 944.4 | M44: 933.657 | N44: 1018.2 | O44: 1066 | P44: =P29+P34 -> 3962.257 | Q44: =Q29+Q34 -> 1056.3 | R44: =R29+R34 -> 1040.8 | S44: =S29+S34 -> 1105.75 | T44: =T29+T34 -> 1160.2 | U44: =U29+U34 -> 4363.05 | V44: =V29+V34 -> 1170.7 | W44: =W29+W34 -> 1254.9 | ... AD44: =AD29+AD34 -> 1379.5 | AE44: =SUM(AA44:AD44) -> 5262.4 | AF44: =AF29+AF34 -> 1682.9 | AG44: =AG29+AG34 -> 1572.51 | AH44: =AH29+AH34 -> 1619.5 | AI44: =AI29+AI34 -> 1265.6 | AJ44: =SUM(AF44:AI44) -> 6140.51 | AK44: =AK29+AK34 -> 1783.9 | AL44: =AL29+AL34 -> 1763.8 | AM44: =AM29+AM34 -> 1730.9 | AN44: =AN29+AN34 -> 1488.68 | AO44: =SUM(AK44:AN44) -> 6767.28 | AP44: =AP29+AP34 -> 1738.2 | AQ44: =AQ29+AQ34 -> 1663.8 | AR44: =AR29+AR34 -> 1527.8 | AS44: =AS29+AS34 -> 1209.2 | AT44: =AT29+AT34 -> 6139 | AU44: =AU29+AU34 -> 1359.1 | AV44: =AV29+AV34 -> 1185.7 | AW44: =AW29+AW34 -> 1140.2 | ... CH44: =CH29+CH34 -> 9717.2795 | EW44: Pretax Income
H45: Taxes | L45: 207.768 | M45: 205.40454 | N45: 224.1 | O45: 195 | P45: =SUM(L45:O45) -> 832.27254 | Q45: 221.9 | R45: 218.5 | S45: 232.2 | T45: 230.6 | U45: =SUM(Q45:T45) -> 903.2 | V45: 257.6 | W45: 276.1 | X45: 263.3 | Y45: 253.1 | Z45: =SUM(V45:Y45) -> 1050.1 | AA45: 260.1 | AB45: 273.6 | AC45: 288.2 | AD45: 263.4 | AE45: =SUM(AA45:AD45) -> 1085.3 | AF45: 370.3 | AG45: 346 | AH45: 307.5 | AI45: 265.7 | AJ45: =SUM(AF45:AI45) -> 1289.5 | AK45: 486.4 | AL45: 396.9 | AM45: 389.4 | AN45: 253.7 | AO45: =SUM(AK45:AN45) -> 1526.4 | AP45: 363.3 | AQ45: 347.7 | AR45: 273.9 | AS45: 240.5 | AT45: =SUM(AP45:AS45) -> 1225.4 | AU45: 332.2 | AV45: 262.1 | AW45: 251.9 | AX45: 271.2 | AY45: =SUM(AU45:AX45) -> 1117.4 | AZ45: 229.7 | BA45: 323.5 | BB45: 310.3 | BC45: 205.5 | BD45: =SUM(AZ45:BC45) -> 1069 | BE45: =172.3+44.1 -> 216.4 | BF45: =206.9+45.2 -> 252.1 | BG45: =199.3+46.1 -> 245.4 | BH45: =130.2+46.2 -> 176.4 | BI45: =SUM(BE45:BH45) -> 890.3 | BJ45: 274.4 | BK45: 250.3 | BL45: 314.3 | BM45: 129.3 | BN45: =SUM(BJ45:BM45) -> 968.3 | BO45: 192.3 | BP45: 262.3 | BQ45: 262.9 | BR45: 220.7 | BS45: =SUM(BO45:BR45) -> 938.2 | BT45: 279.6 | BU45: 327.2 | BV45: 257.8 | BW45: 306.1 | BX45: =SUM(BT45:BW45) -> 1170.7 | BY45: =265.6 -> 265.6 | BZ45: =BZ44*BZ46 -> 284.80947 | CA45: =CA44*CA46 -> 307.9135 | CB45: =CB44*CB46 -> 264.38793 | CC45: =SUM(BY45:CB45) -> 1122.7109 | CD45: =CD44*CD46 -> 1210.708 | CE45: =CE44*CE46 -> 1321.5822 | CF45: =CF44*CF46 -> 1421.6984 | CG45: =CG44*CG46 -> 1504.2026 | CH45: =CH44*CH46 -> 1603.3511
H46: Tax Rate | L46: 0.22 | M46: 0.22 | N46: 0.22009428 | O46: 0.18292683 | P46: =P45/P44 -> 0.21005012 | Q46: =Q45/Q44 -> 0.2100729 | R46: =R45/R44 -> 0.20993467 | S46: =S45/S44 -> 0.20999322 | T46: =T45/T44 -> 0.19875883 | U46: =U45/U44 -> 0.20701115 | V46: =V45/V44 -> 0.22003929 | W46: =W45/W44 -> 0.22001753 | ... BY46: =BY45/BY44 -> 0.15888018 | BZ46: 0.175 | CA46: 0.175 | CB46: 0.175 | CC46: =CC45/CC44 -> 0.17090068 | CD46: 0.168 | CE46: 0.165 | CF46: 0.165 | CG46: 0.165 | CH46: 0.165
H47: Net income | L47: 736.632 | M47: 728.25246 | N47: 794.1 | O47: 871 | P47: =P44-P45 -> 3129.9845 | Q47: =Q44-Q45 -> 834.4 | R47: =R44-R45 -> 822.3 | S47: =S44-S45 -> 873.55 | T47: =T44-T45 -> 929.6 | U47: =U44-U45 -> 3459.85 | V47: =V44-V45 -> 913.1 | W47: =W44-W45 -> 978.8 | ... CH47: =CH44-CH45 -> 8113.9283
H49: Adj. Dil. EPS | L49: 0.67630492 | M49: 0.66798731 | N49: 0.72762292 | O49: 0.79651691 | P49: =P47/P50 -> 2.8687207 | Q49: =Q47/Q50 -> 0.76762153 | R49: =R47/R50 -> 0.75766371 | S49: =S47/S50 -> 0.80406881 | T49: =T47/T50 -> 0.85355115 | U49: =U47/U50 -> 3.1830716 | V49: =V47/V50 -> 0.83779943 | W49: =W47/W50 -> 0.89802614 | ... CH49: =CH47/CH50 -> 7.8506937
H50: Dil. shares outstanding | L50: 1089.201 | M50: 1090.219 | N50: 1091.362 | O50: 1093.511 | P50: =AVERAGE(L50:O50) -> 1091.0732 | Q50: 1086.994 | R50: 1085.31 | S50: 1086.412 | T50: 1089.097 | U50: =AVERAGE(Q50:T50) -> 1086.9533 | V50: 1089.879 | W50: 1089.946 | X50: 1090.228 | Y50: 1092.636 | Z50: =AVERAGE(V50:Y50) -> 1090.6723 | AA50: 1094.056 | AB50: 1093.832 | AC50: 1094.024 | AD50: 1096.525 | AE50: =AVERAGE(AA50:AD50) -> 1094.6092 | AF50: 1097.256 | AG50: 1097.213 | AH50: 1097.7 | AI50: 1101.447 | AJ50: =AVERAGE(AF50:AI50) -> 1098.404 | AK50: 1103.406 | AL50: 1103.807 | AM50: 1105.198 | AN50: 1109.361 | AO50: =AVERAGE(AK50:AN50) -> 1105.443 | AP50: 1112.026 | AQ50: 1113.957 | AR50: 1113.841 | AS50: 1115.883 | AT50: =AVERAGE(AP50:AS50) -> 1113.9268 | AU50: 1116.983 | AV50: 1118.707 | AW50: 1119.641 | AX50: 1113.88 | AY50: =AVERAGE(AU50:AX50) -> 1117.3028 | AZ50: 1091.876 | BA50: 1084.037 | BB50: 1084.257 | BC50: 1078.976 | BD50: =AVERAGE(AZ50:BC50) -> 1084.7865 | BE50: 1075.836 | BF50: 1076.418 | BG50: 1074.386 | BH50: 1069.787 | BI50: =AVERAGE(BE50:BH50) -> 1074.1067 | BJ50: 1067.036 | BK50: 1065.584 | BL50: 1065.159 | BM50: 1064.893 | BN50: =AVERAGE(BJ50:BM50) -> 1065.668 | BO50: 1063.075 | BP50: 1060.083 | BQ50: 1060.786 | BR50: 1061.498 | BS50: =AVERAGE(BO50:BR50) -> 1061.3605 | BT50: 1056.306 | BU50: 1057.11 | BV50: 1056.025 | BW50: 1056.968 | BX50: =AVERAGE(BT50:BW50) -> 1056.6023 | BY50: =1049.839 -> 1049.839 | BZ50: =BU50*(1+BZ77) -> 1049.7102 | CA50: =BV50*(1+CA77) -> 1048.6328 | CB50: =BW50*(1+CB77) -> 1048.5123 | CC50: =AVERAGE(BY50:CB50) -> 1049.1736 | CD50: =CC50*(1+CD77) -> 1046.0261 | CE50: =CD50*(1+CE77) -> 1042.888 | CF50: =CE50*(1+CF77) -> 1039.7593 | CG50: =CF50*(1+CG77) -> 1036.64 | CH50: =CG50*(1+CH77) -> 1033.5301 | EW50: GAAP P&L
H51: Basic shares outstanding | L51: 1086.841 | M51: 1087.582 | N51: 1088.936 | O51: 1091.655 | P51: =AVERAGE(L51:O51) -> 1088.7535 | Q51: 1086.035 | R51: 1084.686 | S51: 1085.603 | T51: 1088.612 | U51: =AVERAGE(Q51:T51) -> 1086.234 | V51: 1089.732 | W51: 1089 | X51: 1090.067 | Y51: 1092.472 | Z51: =AVERAGE(V51:Y51) -> 1090.3177 | AA51: 1093.866 | AB51: 1092.1 | AC51: 1093.977 | AD51: 1096.491 | AE51: =AVERAGE(AA51:AD51) -> 1094.1085 | AF51: 1097.224 | AG51: 1097.2 | AH51: 1097.7 | AI51: 1101.42 | AJ51: =AVERAGE(AF51:AI51) -> 1098.386 | AK51: 1103.38 | AL51: 1103.782 | AM51: 1105.173 | AN51: 1109.336 | AO51: =AVERAGE(AK51:AN51) -> 1105.4178 | AP51: 1112.003 | AQ51: 1113.933 | AR51: 1113.82 | AS51: 1115.846 | AT51: =AVERAGE(AP51:AS51) -> 1113.9005 | AU51: 1116.962 | AV51: 1118.686 | AW51: 1119.617 | AX51: =AS51*(1+AX77) -> 1113.8431 | AY51: =AVERAGE(AU51:AX51) -> 1117.277 | AZ51: 1087.9 | BA51: 1080.2 | BB51: 1076.6 | BC51: =AX51*(1+BC77) -> 1078.9402 | BD51: =AVERAGE(AZ51:BC51) -> 1080.9101 | BE51: =AZ51*(1+BE77) -> 1071.9184 | BF51: =BA51*(1+BF77) -> 1072.608 | BG51: =BB51*(1+BG77) -> 1066.7987 | BH51: =BC51*(1+BH77) -> 1069.7515 | BI51: =AVERAGE(BE51:BH51) -> 1070.2692 | BJ51: =BE51*(1+BJ77) -> 1063.1505 | BK51: =BF51*(1+BK77) -> 1061.8123 | BL51: =BG51*(1+BL77) -> 1057.6369 | BM51: =BH51*(1+BM77) -> 1064.8577 | BN51: =BI51*(1+BN77) -> 1061.8606 | BO51: =BJ51*(1+BO77) -> 1059.2039 | BP51: =BK51*(1+BP77) -> 1056.3308 | BQ51: =BL51*(1+BQ77) -> 1053.2948 | ... BV51: =BQ51*(1+BV77) -> 1048.5674 | BW51: 1051.091 | BX51: =BS51*(1+BX77) -> 1052.8272 | BY51: =BT51*(1+BY77) -> 1046.0161 | BZ51: =BU51*(1+BZ77) -> 1045.9947 | CA51: =BV51*(1+CA77) -> 1041.2274 | CB51: =BW51*(1+CB77) -> 1042.6823 | CC51: =BX51*(1+CC77) -> 1045.4251 | CD51: =CC51*(1+CD77) -> 1042.2888 | CE51: =CD51*(1+CE77) -> 1039.1619 | CF51: =CE51*(1+CF77) -> 1036.0444 | CG51: =CF51*(1+CG77) -> 1032.9363 | CH51: =CG51*(1+CH77) -> 1029.8375
H52: Period-end basic shares outstanding | L52: =L51 -> 1086.841 | M52: =M51 -> 1087.582 | N52: =N51 -> 1088.936 | O52: =O51 -> 1091.655 | P52: =P51 -> 1088.7535 | Q52: =Q51 -> 1086.035 | R52: =R51 -> 1084.686 | S52: =S51 -> 1085.603 | ... AT52: =AT51 -> 1113.9005 | AU52: 1116.9827 | AV52: =AV51 -> 1118.686 | AW52: =AW51 -> 1119.617 | AX52: =AX51 -> 1113.8431 | AY52: =AY51 -> 1117.277 | AZ52: =AZ51 -> 1087.9 | BA52: =BA51 -> 1080.2 | BB52: =BB51 -> 1076.6 | BC52: =BC51 -> 1078.9402 | BD52: =BC52 -> 1078.9402 | BE52: =BE51 -> 1071.9184 | BF52: =BF51 -> 1072.608 | BG52: =BG51 -> 1066.7987 | BH52: =BH51 -> 1069.7515 | BI52: =BH52 -> 1069.7515 | BJ52: =BJ51 -> 1063.1505 | BK52: =BK51 -> 1061.8123 | BL52: =BL51 -> 1057.6369 | BM52: =BM51 -> 1064.8577 | BN52: =BN51 -> 1061.8606 | BO52: =BO51 -> 1059.2039 | BP52: =BP51 -> 1056.3308 | BQ52: =BQ51 -> 1053.2948 | ... CH52: =CH51 -> 1029.8375
H55: Margin Analysis | L55: ="1Q:" & RIGHT(YEAR(L$4),2) & IF(L$4<=LatestRpQ, "A", "E") -> 1Q:05A | M55: ="2Q:" & RIGHT(YEAR(M$4),2) & IF(M$4<=LatestRpQ, "A", "E") -> 2Q:05A | N55: ="3Q:" & RIGHT(YEAR(N$4),2) & IF(N$4<=LatestRpQ, "A", "E") -> 3Q:05A | O55: ="4Q:" & RIGHT(YEAR(O$4),2) & IF(O$4<=LatestRpQ, "A", "E") -> 4Q:05A | P55: =YEAR(P$4) & IF(P$4<=LatestRpQ, "A", "E") -> 2005A | Q55: ="1Q:" & RIGHT(YEAR(Q$4),2) & IF(Q$4<=LatestRpQ, "A", "E") -> 1Q:06A | R55: ="2Q:" & RIGHT(YEAR(R$4),2) & IF(R$4<=LatestRpQ, "A", "E") -> 2Q:06A | S55: ="3Q:" & RIGHT(YEAR(S$4),2) & IF(S$4<=LatestRpQ, "A", "E") -> 3Q:06A | T55: ="4Q:" & RIGHT(YEAR(T$4),2) & IF(T$4<=LatestRpQ, "A", "E") -> 4Q:06A | U55: =YEAR(U$4) & IF(U$4<=LatestRpQ, "A", "E") -> 2006A | V55: ="1Q:" & RIGHT(YEAR(V$4),2) & IF(V$4<=LatestRpQ, "A", "E") -> 1Q:07A | W55: ="2Q:" & RIGHT(YEAR(W$4),2) & IF(W$4<=LatestRpQ, "A", "E") -> 2Q:07A | X55: ="3Q:" & RIGHT(YEAR(X$4),2) & IF(X$4<=LatestRpQ, "A", "E") -> 3Q:07A | Y55: ="4Q:" & RIGHT(YEAR(Y$4),2) & IF(Y$4<=LatestRpQ, "A", "E") -> 4Q:07A | Z55: =YEAR(Z$4) & IF(Z$4<=LatestRpQ, "A", "E") -> 2007A | AA55: ="1Q:" & RIGHT(YEAR(AA$4),2) & IF(AA$4<=LatestRpQ, "A", "E") -> 1Q:08A | AB55: ="2Q:" & RIGHT(YEAR(AB$4),2) & IF(AB$4<=LatestRpQ, "A", "E") -> 2Q:08A | AC55: ="3Q:" & RIGHT(YEAR(AC$4),2) & IF(AC$4<=LatestRpQ, "A", "E") -> 3Q:08A | AD55: ="4Q:" & RIGHT(YEAR(AD$4),2) & IF(AD$4<=LatestRpQ, "A", "E") -> 4Q:08A | AE55: =YEAR(AE$4) & IF(AE$4<=LatestRpQ, "A", "E") -> 2008A | AF55: ="1Q:" & RIGHT(YEAR(AF$4),2) & IF(AF$4<=LatestRpQ, "A", "E") -> 1Q:09A | AG55: ="2Q:" & RIGHT(YEAR(AG$4),2) & IF(AG$4<=LatestRpQ, "A", "E") -> 2Q:09A | AH55: ="3Q:" & RIGHT(YEAR(AH$4),2) & IF(AH$4<=LatestRpQ, "A", "E") -> 3Q:09A | AI55: ="4Q:" & RIGHT(YEAR(AI$4),2) & IF(AI$4<=LatestRpQ, "A", "E") -> 4Q:09A | AJ55: =YEAR(AJ$4) & IF(AJ$4<=LatestRpQ, "A", "E") -> 2009A | AK55: ="1Q:" & RIGHT(YEAR(AK$4),2) & IF(AK$4<=LatestRpQ, "A", "E") -> 1Q:10A | AL55: ="2Q:" & RIGHT(YEAR(AL$4),2) & IF(AL$4<=LatestRpQ, "A", "E") -> 2Q:10A | AM55: ="3Q:" & RIGHT(YEAR(AM$4),2) & IF(AM$4<=LatestRpQ, "A", "E") -> 3Q:10A | AN55: ="4Q:" & RIGHT(YEAR(AN$4),2) & IF(AN$4<=LatestRpQ, "A", "E") -> 4Q:10A | AO55: =YEAR(AO$4) & IF(AO$4<=LatestRpQ, "A", "E") -> 2010A | AP55: ="1Q:" & RIGHT(YEAR(AP$4),2) & IF(AP$4<=LatestRpQ, "A", "E") -> 1Q:11A | AQ55: ="2Q:" & RIGHT(YEAR(AQ$4),2) & IF(AQ$4<=LatestRpQ, "A", "E") -> 2Q:11A | AR55: ="3Q:" & RIGHT(YEAR(AR$4),2) & IF(AR$4<=LatestRpQ, "A", "E") -> 3Q:11A | AS55: ="4Q:" & RIGHT(YEAR(AS$4),2) & IF(AS$4<=LatestRpQ, "A", "E") -> 4Q:11A | AT55: =YEAR(AT$4) & IF(AT$4<=LatestRpQ, "A", "E") -> 2011A | AU55: ="1Q:" & RIGHT(YEAR(AU$4),2) & IF(AU$4<=LatestRpQ, "A", "E") -> 1Q:12A | AV55: ="2Q:" & RIGHT(YEAR(AV$4),2) & IF(AV$4<=LatestRpQ, "A", "E") -> 2Q:12A | AW55: ="3Q:" & RIGHT(YEAR(AW$4),2) & IF(AW$4<=LatestRpQ, "A", "E") -> 3Q:12A | AX55: ="4Q:" & RIGHT(YEAR(AX$4),2) & IF(AX$4<=LatestRpQ, "A", "E") -> 4Q:12A | AY55: =YEAR(AY$4) & IF(AY$4<=LatestRpQ, "A", "E") -> 2012A | AZ55: ="1Q:" & RIGHT(YEAR(AZ$4),2) & IF(AZ$4<=LatestRpQ, "A", "E") -> 1Q:13A | BA55: ="2Q:" & RIGHT(YEAR(BA$4),2) & IF(BA$4<=LatestRpQ, "A", "E") -> 2Q:13A | BB55: ="3Q:" & RIGHT(YEAR(BB$4),2) & IF(BB$4<=LatestRpQ, "A", "E") -> 3Q:13A | BC55: ="4Q:" & RIGHT(YEAR(BC$4),2) & IF(BC$4<=LatestRpQ, "A", "E") -> 4Q:13A | BD55: =YEAR(BD$4) & IF(BD$4<=LatestRpQ, "A", "E") -> 2013A | BE55: ="1Q:" & RIGHT(YEAR(BE$4),2) & IF(BE$4<=LatestRpQ, "A", "E") -> 1Q:14A | BF55: ="2Q:" & RIGHT(YEAR(BF$4),2) & IF(BF$4<=LatestRpQ, "A", "E") -> 2Q:14A | BG55: ="3Q:" & RIGHT(YEAR(BG$4),2) & IF(BG$4<=LatestRpQ, "A", "E") -> 3Q:14A | BH55: ="4Q:" & RIGHT(YEAR(BH$4),2) & IF(BH$4<=LatestRpQ, "A", "E") -> 4Q:14A | BI55: =YEAR(BI$4) & IF(BI$4<=LatestRpQ, "A", "E") -> 2014A | BJ55: ="1Q:" & RIGHT(YEAR(BJ$4),2) & IF(BJ$4<=LatestRpQ, "A", "E") -> 1Q:15A | BK55: ="2Q:" & RIGHT(YEAR(BK$4),2) & IF(BK$4<=LatestRpQ, "A", "E") -> 2Q:15A | BL55: ="3Q:" & RIGHT(YEAR(BL$4),2) & IF(BL$4<=LatestRpQ, "A", "E") -> 3Q:15A | BM55: ="4Q:" & RIGHT(YEAR(BM$4),2) & IF(BM$4<=LatestRpQ, "A", "E") -> 4Q:15A | BN55: =YEAR(BN$4) & IF(BN$4<=LatestRpQ, "A", "E") -> 2015A | BO55: ="1Q:" & RIGHT(YEAR(BO$4),2) & IF(BO$4<=LatestRpQ, "A", "E") -> 1Q:16A | BP55: ="2Q:" & RIGHT(YEAR(BP$4),2) & IF(BP$4<=LatestRpQ, "A", "E") -> 2Q:16A | BQ55: ="3Q:" & RIGHT(YEAR(BQ$4),2) & IF(BQ$4<=LatestRpQ, "A", "E") -> 3Q:16A | BR55: ="4Q:" & RIGHT(YEAR(BR$4),2) & IF(BR$4<=LatestRpQ, "A", "E") -> 4Q:16A | BS55: =YEAR(BS$4) & IF(BS$4<=LatestRpQ, "A", "E") -> 2016A | BT55: ="1Q:" & RIGHT(YEAR(BT$4),2) & IF(BT$4<=LatestRpQ, "A", "E") -> 1Q:17A | BU55: ="2Q:" & RIGHT(YEAR(BU$4),2) & IF(BU$4<=LatestRpQ, "A", "E") -> 2Q:17A | BV55: ="3Q:" & RIGHT(YEAR(BV$4),2) & IF(BV$4<=LatestRpQ, "A", "E") -> 3Q:17A | BW55: ="4Q:" & RIGHT(YEAR(BW$4),2) & IF(BW$4<=LatestRpQ, "A", "E") -> 4Q:17A | BX55: =YEAR(BX$4) & IF(BX$4<=LatestRpQ, "A", "E") -> 2017A | BY55: ="1Q:" & RIGHT(YEAR(BY$4),2) & IF(BY$4<=LatestRpQ, "A", "E") -> 1Q:18A | BZ55: ="2Q:" & RIGHT(YEAR(BZ$4),2) & IF(BZ$4<=LatestRpQ, "A", "E") -> 2Q:18E | CA55: ="3Q:" & RIGHT(YEAR(CA$4),2) & IF(CA$4<=LatestRpQ, "A", "E") -> 3Q:18E | CB55: ="4Q:" & RIGHT(YEAR(CB$4),2) & IF(CB$4<=LatestRpQ, "A", "E") -> 4Q:18E | CC55: =YEAR(CC$4) & IF(CC$4<=LatestRpQ, "A", "E") -> 2018E | CD55: =YEAR(CD$4) & IF(CD$4<=LatestRpQ, "A", "E") -> 2019E | CE55: =YEAR(CE$4) & IF(CE$4<=LatestRpQ, "A", "E") -> 2020E | CF55: =YEAR(CF$4) & IF(CF$4<=LatestRpQ, "A", "E") -> 2021E | CG55: =YEAR(CG$4) & IF(CG$4<=LatestRpQ, "A", "E") -> 2022E | CH55: =YEAR(CH$4) & IF(CH$4<=LatestRpQ, "A", "E") -> 2023E
H56: =H24 -> COGS | L56: 0.24561103 | M56: 0.23756032 | N56: 0.23484491 | O56: 0.23154856 | P56: 0.23722286 | Q56: =Q24/Q11 -> 0.21710455 | R56: =R24/R11 -> 0.22254403 | S56: =S24/S11 -> 0.22266793 | T56: =T24/T11 -> 0.24003015 | U56: =U24/U11 -> 0.22601769 | V56: =V24/V11 -> 0.2182812 | W56: =W24/W11 -> 0.21570321 | X56: =X24/X11 -> 0.22992064 | ... BY56: =BY24/BY11 -> 0.24915789 | BZ56: 0.25 | CA56: 0.252 | CB56: 0.25 | CC56: =CC24/CC11 -> 0.25030574 | CD56: 0.243 | CE56: 0.235 | CF56: 0.23 | CG56: 0.225 | CH56: 0.22
H57: Gross margin | L57: 0.75438897 | M57: 0.76243968 | N57: 0.76515509 | O57: 0.76845144 | P57: 0.76277714 | Q57: =Q25/Q11 -> 0.78289545 | R57: =R25/R11 -> 0.77745597 | S57: =S25/S11 -> 0.77733207 | T57: =T25/T11 -> 0.75996985 | U57: =U25/U11 -> 0.77398231 | V57: =V25/V11 -> 0.7817188 | W57: =W25/W11 -> 0.78429679 | X57: =X25/X11 -> 0.77007936 | ... CH57: =CH25/CH11 -> 0.78
H58: =H26 -> SG&A | L58: 0.31177446 | M58: 0.31248466 | N58: 0.29738136 | O58: 0.30666907 | P58: 0.30706097 | Q58: =Q26/Q11 -> 0.30766125 | R58: =R26/R11 -> 0.32011068 | S58: =S26/S11 -> 0.31008916 | T58: =T26/T11 -> 0.30876499 | U58: =U26/U11 -> 0.31162591 | V58: =V26/V11 -> 0.31631253 | W58: =W26/W11 -> 0.32924486 | X58: =X26/X11 -> 0.3221854 | ... CH58: =CH26/CH11 -> 0.24036486
H59: =H28 -> R&D | L59: 0.20077772 | M59: 0.20786869 | N59: 0.20854739 | O59: 0.20878554 | P59: 0.20658505 | Q59: =Q28/Q11 -> 0.19941854 | R59: =R28/R11 -> 0.20035686 | S59: =S28/S11 -> 0.195572 | T59: =T28/T11 -> 0.20210586 | U59: =U28/U11 -> 0.19942962 | V59: =V28/V11 -> 0.19738772 | W59: =W28/W11 -> 0.18449977 | X59: =X28/X11 -> 0.18411529 | ... CH59: =CH28/CH11 -> 0.20043602
H60: Opex total | AO60: =AO58+AO59 -> 0.5173149 | AP60: =AP58+AP59 -> 0.49830456 | AQ60: =AQ58+AQ59 -> 0.52832241 | AR60: =AR58+AR59 -> 0.52028302 | AS60: =AS58+AS59 -> 0.57698796 | AT60: =AT58+AT59 -> 0.53118592 | AU60: =AU58+AU59 -> 0.53534452 | AV60: =AV58+AV59 -> 0.580606 | ... CH60: =CH58+CH59 -> 0.44080088
H61: Operating margin | L61: 0.24183679 | M61: 0.24208632 | N61: 0.25922635 | O61: 0.25299683 | P61: 0.24913112 | Q61: =Q29/Q11 -> 0.27581566 | R61: =R29/R11 -> 0.25698844 | S61: =S29/S11 -> 0.27167092 | T61: =T29/T11 -> 0.249099 | U61: =U29/U11 -> 0.26292679 | V61: =V29/V11 -> 0.26801855 | W61: =W29/W11 -> 0.27055216 | X61: =X29/X11 -> 0.26377867 | ... CH61: =CH29/CH11 -> 0.33919912
H62: EBITDA margin | L62: =L33/L11 -> 0.29337508 | M62: =M33/M11 -> 0.29123156 | N62: =N33/N11 -> 0.3092805 | O62: =O33/O11 -> 0.29946379 | P62: =P33/P11 -> 0.29836193 | Q62: =Q33/Q11 -> 0.32926402 | R62: =R33/R11 -> 0.30833182 | S62: =S33/S11 -> 0.32305483 | ... CH62: =CH33/CH11 -> 0.36988801
H63: Pretax margin | L63: 0.27002916 | M63: 0.25456199 | N63: 0.28274694 | O63: 0.27480601 | P63: 0.27054803 | Q63: =Q44/Q11 -> 0.28434909 | R63: =R44/R11 -> 0.26914225 | S63: =S44/S11 -> 0.28616348 | T63: =T44/T11 -> 0.27329046 | U63: =U44/U11 -> 0.27805624 | V63: =V44/V11 -> 0.27701008 | W63: =W44/W11 -> 0.27098404 | X63: =X44/X11 -> 0.27472312 | ... CH63: =CH44/CH11 -> 0.34555331
H64: Net margin | L64: 0.21062275 | M64: 0.19855835 | N64: 0.22051595 | O64: 0.22453662 | P64: 0.21371938 | Q64: =Q47/Q11 -> 0.22461505 | R64: =R47/R11 -> 0.21263996 | S64: =S47/S11 -> 0.22607109 | T64: =T47/T11 -> 0.21897157 | U64: =U47/U11 -> 0.2204955 | V64: =V47/V11 -> 0.21605698 | W64: =W47/W11 -> 0.2113628 | X64: =X47/X11 -> 0.21731926 | ... CH64: =CH47/CH11 -> 0.28853701
H66: YOY % Change | L66: ="1Q:" & RIGHT(YEAR(L$4),2) & IF(L$4<=LatestRpQ, "A", "E") -> 1Q:05A | M66: ="2Q:" & RIGHT(YEAR(M$4),2) & IF(M$4<=LatestRpQ, "A", "E") -> 2Q:05A | N66: ="3Q:" & RIGHT(YEAR(N$4),2) & IF(N$4<=LatestRpQ, "A", "E") -> 3Q:05A | O66: ="4Q:" & RIGHT(YEAR(O$4),2) & IF(O$4<=LatestRpQ, "A", "E") -> 4Q:05A | P66: =YEAR(P$4) & IF(P$4<=LatestRpQ, "A", "E") -> 2005A | Q66: ="1Q:" & RIGHT(YEAR(Q$4),2) & IF(Q$4<=LatestRpQ, "A", "E") -> 1Q:06A | R66: ="2Q:" & RIGHT(YEAR(R$4),2) & IF(R$4<=LatestRpQ, "A", "E") -> 2Q:06A | S66: ="3Q:" & RIGHT(YEAR(S$4),2) & IF(S$4<=LatestRpQ, "A", "E") -> 3Q:06A | T66: ="4Q:" & RIGHT(YEAR(T$4),2) & IF(T$4<=LatestRpQ, "A", "E") -> 4Q:06A | U66: =YEAR(U$4) & IF(U$4<=LatestRpQ, "A", "E") -> 2006A | V66: ="1Q:" & RIGHT(YEAR(V$4),2) & IF(V$4<=LatestRpQ, "A", "E") -> 1Q:07A | W66: ="2Q:" & RIGHT(YEAR(W$4),2) & IF(W$4<=LatestRpQ, "A", "E") -> 2Q:07A | X66: ="3Q:" & RIGHT(YEAR(X$4),2) & IF(X$4<=LatestRpQ, "A", "E") -> 3Q:07A | Y66: ="4Q:" & RIGHT(YEAR(Y$4),2) & IF(Y$4<=LatestRpQ, "A", "E") -> 4Q:07A | Z66: =YEAR(Z$4) & IF(Z$4<=LatestRpQ, "A", "E") -> 2007A | AA66: ="1Q:" & RIGHT(YEAR(AA$4),2) & IF(AA$4<=LatestRpQ, "A", "E") -> 1Q:08A | AB66: ="2Q:" & RIGHT(YEAR(AB$4),2) & IF(AB$4<=LatestRpQ, "A", "E") -> 2Q:08A | AC66: ="3Q:" & RIGHT(YEAR(AC$4),2) & IF(AC$4<=LatestRpQ, "A", "E") -> 3Q:08A | AD66: ="4Q:" & RIGHT(YEAR(AD$4),2) & IF(AD$4<=LatestRpQ, "A", "E") -> 4Q:08A | AE66: =YEAR(AE$4) & IF(AE$4<=LatestRpQ, "A", "E") -> 2008A | AF66: ="1Q:" & RIGHT(YEAR(AF$4),2) & IF(AF$4<=LatestRpQ, "A", "E") -> 1Q:09A | AG66: ="2Q:" & RIGHT(YEAR(AG$4),2) & IF(AG$4<=LatestRpQ, "A", "E") -> 2Q:09A | AH66: ="3Q:" & RIGHT(YEAR(AH$4),2) & IF(AH$4<=LatestRpQ, "A", "E") -> 3Q:09A | AI66: ="4Q:" & RIGHT(YEAR(AI$4),2) & IF(AI$4<=LatestRpQ, "A", "E") -> 4Q:09A | AJ66: =YEAR(AJ$4) & IF(AJ$4<=LatestRpQ, "A", "E") -> 2009A | AK66: ="1Q:" & RIGHT(YEAR(AK$4),2) & IF(AK$4<=LatestRpQ, "A", "E") -> 1Q:10A | AL66: ="2Q:" & RIGHT(YEAR(AL$4),2) & IF(AL$4<=LatestRpQ, "A", "E") -> 2Q:10A | AM66: ="3Q:" & RIGHT(YEAR(AM$4),2) & IF(AM$4<=LatestRpQ, "A", "E") -> 3Q:10A | AN66: ="4Q:" & RIGHT(YEAR(AN$4),2) & IF(AN$4<=LatestRpQ, "A", "E") -> 4Q:10A | AO66: =YEAR(AO$4) & IF(AO$4<=LatestRpQ, "A", "E") -> 2010A | AP66: ="1Q:" & RIGHT(YEAR(AP$4),2) & IF(AP$4<=LatestRpQ, "A", "E") -> 1Q:11A | AQ66: ="2Q:" & RIGHT(YEAR(AQ$4),2) & IF(AQ$4<=LatestRpQ, "A", "E") -> 2Q:11A | AR66: ="3Q:" & RIGHT(YEAR(AR$4),2) & IF(AR$4<=LatestRpQ, "A", "E") -> 3Q:11A | AS66: ="4Q:" & RIGHT(YEAR(AS$4),2) & IF(AS$4<=LatestRpQ, "A", "E") -> 4Q:11A | AT66: =YEAR(AT$4) & IF(AT$4<=LatestRpQ, "A", "E") -> 2011A | AU66: ="1Q:" & RIGHT(YEAR(AU$4),2) & IF(AU$4<=LatestRpQ, "A", "E") -> 1Q:12A | AV66: ="2Q:" & RIGHT(YEAR(AV$4),2) & IF(AV$4<=LatestRpQ, "A", "E") -> 2Q:12A | AW66: ="3Q:" & RIGHT(YEAR(AW$4),2) & IF(AW$4<=LatestRpQ, "A", "E") -> 3Q:12A | AX66: ="4Q:" & RIGHT(YEAR(AX$4),2) & IF(AX$4<=LatestRpQ, "A", "E") -> 4Q:12A | AY66: =YEAR(AY$4) & IF(AY$4<=LatestRpQ, "A", "E") -> 2012A | AZ66: ="1Q:" & RIGHT(YEAR(AZ$4),2) & IF(AZ$4<=LatestRpQ, "A", "E") -> 1Q:13A | BA66: ="2Q:" & RIGHT(YEAR(BA$4),2) & IF(BA$4<=LatestRpQ, "A", "E") -> 2Q:13A | BB66: ="3Q:" & RIGHT(YEAR(BB$4),2) & IF(BB$4<=LatestRpQ, "A", "E") -> 3Q:13A | BC66: ="4Q:" & RIGHT(YEAR(BC$4),2) & IF(BC$4<=LatestRpQ, "A", "E") -> 4Q:13A | BD66: =YEAR(BD$4) & IF(BD$4<=LatestRpQ, "A", "E") -> 2013A | BE66: ="1Q:" & RIGHT(YEAR(BE$4),2) & IF(BE$4<=LatestRpQ, "A", "E") -> 1Q:14A | BF66: ="2Q:" & RIGHT(YEAR(BF$4),2) & IF(BF$4<=LatestRpQ, "A", "E") -> 2Q:14A | BG66: ="3Q:" & RIGHT(YEAR(BG$4),2) & IF(BG$4<=LatestRpQ, "A", "E") -> 3Q:14A | BH66: ="4Q:" & RIGHT(YEAR(BH$4),2) & IF(BH$4<=LatestRpQ, "A", "E") -> 4Q:14A | BI66: =YEAR(BI$4) & IF(BI$4<=LatestRpQ, "A", "E") -> 2014A | BJ66: ="1Q:" & RIGHT(YEAR(BJ$4),2) & IF(BJ$4<=LatestRpQ, "A", "E") -> 1Q:15A | BK66: ="2Q:" & RIGHT(YEAR(BK$4),2) & IF(BK$4<=LatestRpQ, "A", "E") -> 2Q:15A | BL66: ="3Q:" & RIGHT(YEAR(BL$4),2) & IF(BL$4<=LatestRpQ, "A", "E") -> 3Q:15A | BM66: ="4Q:" & RIGHT(YEAR(BM$4),2) & IF(BM$4<=LatestRpQ, "A", "E") -> 4Q:15A | BN66: =YEAR(BN$4) & IF(BN$4<=LatestRpQ, "A", "E") -> 2015A | BO66: ="1Q:" & RIGHT(YEAR(BO$4),2) & IF(BO$4<=LatestRpQ, "A", "E") -> 1Q:16A | BP66: ="2Q:" & RIGHT(YEAR(BP$4),2) & IF(BP$4<=LatestRpQ, "A", "E") -> 2Q:16A | BQ66: ="3Q:" & RIGHT(YEAR(BQ$4),2) & IF(BQ$4<=LatestRpQ, "A", "E") -> 3Q:16A | BR66: ="4Q:" & RIGHT(YEAR(BR$4),2) & IF(BR$4<=LatestRpQ, "A", "E") -> 4Q:16A | BS66: =YEAR(BS$4) & IF(BS$4<=LatestRpQ, "A", "E") -> 2016A | BT66: ="1Q:" & RIGHT(YEAR(BT$4),2) & IF(BT$4<=LatestRpQ, "A", "E") -> 1Q:17A | BU66: ="2Q:" & RIGHT(YEAR(BU$4),2) & IF(BU$4<=LatestRpQ, "A", "E") -> 2Q:17A | BV66: ="3Q:" & RIGHT(YEAR(BV$4),2) & IF(BV$4<=LatestRpQ, "A", "E") -> 3Q:17A | BW66: ="4Q:" & RIGHT(YEAR(BW$4),2) & IF(BW$4<=LatestRpQ, "A", "E") -> 4Q:17A | BX66: =YEAR(BX$4) & IF(BX$4<=LatestRpQ, "A", "E") -> 2017A | BY66: ="1Q:" & RIGHT(YEAR(BY$4),2) & IF(BY$4<=LatestRpQ, "A", "E") -> 1Q:18A | BZ66: ="2Q:" & RIGHT(YEAR(BZ$4),2) & IF(BZ$4<=LatestRpQ, "A", "E") -> 2Q:18E | CA66: ="3Q:" & RIGHT(YEAR(CA$4),2) & IF(CA$4<=LatestRpQ, "A", "E") -> 3Q:18E | CB66: ="4Q:" & RIGHT(YEAR(CB$4),2) & IF(CB$4<=LatestRpQ, "A", "E") -> 4Q:18E | CC66: =YEAR(CC$4) & IF(CC$4<=LatestRpQ, "A", "E") -> 2018E | CD66: =YEAR(CD$4) & IF(CD$4<=LatestRpQ, "A", "E") -> 2019E | CE66: =YEAR(CE$4) & IF(CE$4<=LatestRpQ, "A", "E") -> 2020E | CF66: =YEAR(CF$4) & IF(CF$4<=LatestRpQ, "A", "E") -> 2021E | CG66: =YEAR(CG$4) & IF(CG$4<=LatestRpQ, "A", "E") -> 2022E | CH66: =YEAR(CH$4) & IF(CH$4<=LatestRpQ, "A", "E") -> 2023E
H67: =H11 -> Total revenues | L67: 0.035806308 | M67: 0.031354852 | N67: 0.097762468 | O67: 0.06437097 | P67: 0.05684276 | Q67: =Q11/L11-1 -> 0.062160462 | R67: =R11/M11-1 -> 0.054366497 | S67: =S11/N11-1 -> 0.073019355 | T67: =T11/O11-1 -> 0.094403341 | U67: =U11/P11-1 -> 0.071418817 | V67: =V11/Q11-1 -> 0.13766555 | W67: =W11/R11-1 -> 0.19751235 | X67: =X11/S11-1 -> 0.18704468 | ... CC67: =CC11/BX11-1 -> 0.050313008 | CD67: =CD11/CC11-1 -> 0.023714695 | CE67: =CE11/CD11-1 -> 0.037491432 | CF67: =CF11/CE11-1 -> 0.036283101 | CG67: =CG11/CF11-1 -> 0.029420202 | CH67: =CH11/CG11-1 -> 0.033189023
H68: =H24 -> COGS | L68: 0.14274312 | M68: 0.094048217 | N68: 0.043945192 | O68: 0.037541874 | P68: 0.077638885 | Q68: =Q24/L24-1 -> -0.061117579 | R68: =R24/M24-1 -> -0.0122805 | S68: =S24/N24-1 -> 0.01738205 | T68: =T24/O24-1 -> 0.1344912 | U68: =U24/P24-1 -> 0.020810546 | V68: =V24/Q24-1 -> 0.14383137 | W68: =W24/R24-1 -> 0.16070184 | X68: =X24/S24-1 -> 0.22570897 | ... CC68: =CC24/BX24-1 -> 0.12202452 | CD68: =CD24/CC24-1 -> -0.0061647495 | CE68: =CE24/CD24-1 -> 0.0033353356 | CF68: =CF24/CE24-1 -> 0.014234524 | CG68: =CG24/CF24-1 -> 0.0070415021 | CH68: =CH24/CG24-1 -> 0.010229267
H69: =H25 -> Gross profit | L69: 0.0051813472 | M69: 0.013263299 | N69: 0.11541108 | O69: 0.072729236 | P69: 0.050537837 | Q69: =Q25/L25-1 -> 0.10229685 | R69: =R25/M25-1 -> 0.075132313 | S69: =S25/N25-1 -> 0.090095812 | T69: =T25/O25-1 -> 0.08232413 | U69: =U25/P25-1 -> 0.087157934 | V69: =V25/Q25-1 -> 0.13595571 | W69: =W25/R25-1 -> 0.20804923 | X69: =X25/S25-1 -> 0.17596924 | ... CC69: =CC25/BX25-1 -> 0.028368694 | CD69: =CD25/CC25-1 -> 0.033690758 | CE69: =CE25/CD25-1 -> 0.048455675 | CF69: =CF25/CE25-1 -> 0.043056193 | CG69: =CG25/CF25-1 -> 0.036104749 | CH69: =CH25/CG25-1 -> 0.039854759
H70: =H26 -> SG&A | L70: 0.024908356 | M70: -0.02059477 | N70: 0.12501313 | O70: 0.083227099 | P70: 0.049670884 | Q70: =Q26/L26-1 -> 0.048147469 | R70: =R26/M26-1 -> 0.080097723 | S70: =S26/N26-1 -> 0.11887198 | T70: =T26/O26-1 -> 0.10188299 | U70: =U26/P26-1 -> 0.08734712 | V70: =V26/Q26-1 -> 0.16965614 | W70: =W26/R26-1 -> 0.23168269 | X70: =X26/S26-1 -> 0.23335003 | ... BY70: =BY26/BT26-1 -> -0.028517726 | BZ70: -0.04 | CA70: -0.03 | CB70: -0.03 | CC70: =CC26/BX26-1 -> -0.032244048 | CD70: -0.01 | CE70: 0.01 | CF70: 0.02 | CG70: 0.02 | CH70: 0.02
H71: =H28 -> R&D | L71: 0.086660477 | M71: 0.11429407 | N71: 0.14691509 | O71: 0.14798016 | P71: 0.12442859 | Q71: =Q28/L28-1 -> 0.054970094 | R71: =R28/M28-1 -> 0.016264428 | S71: =S28/N28-1 -> 0.0062583222 | T71: =T28/O28-1 -> 0.059390048 | U71: =U28/P28-1 -> 0.034308379 | V71: =V28/Q28-1 -> 0.12607991 | W71: =W28/R28-1 -> 0.10273619 | X71: =X28/S28-1 -> 0.11750695 | ... BY71: =BY28/BT28-1 -> -0.049745619 | BZ71: 0.03 | CA71: -0.01 | CB71: 0.01 | CC71: =CC28/BX28-1 -> -0.0042675099 | CD71: 0 | CE71: 0.01 | CF71: 0.02 | CG71: 0.02 | CH71: 0.02
H72: =H29 -> Operating income, EBITA | L72: -0.075325243 | M72: -0.019324141 | N72: 0.08094025 | O72: 0.0064608758 | P72: -0.0027867091 | Q72: =Q29/L29-1 -> 0.21139749 | R72: =R29/M29-1 -> 0.11927019 | S72: =S29/N29-1 -> 0.12453133 | T72: =T29/O29-1 -> 0.077542287 | U72: =U29/P29-1 -> 0.13074878 | V72: =V29/Q29-1 -> 0.10550459 | W72: =W29/R29-1 -> 0.26071644 | X72: =X29/S29-1 -> 0.15256013 | ... CC72: =CC29/BX29-1 -> 0.12950745 | CD72: =CD29/CC29-1 -> 0.10507673 | CE72: =CE29/CD29-1 -> 0.11153071 | CF72: =CF29/CE29-1 -> 0.07741868 | CG72: =CG29/CF29-1 -> 0.058827799 | CH72: =CH29/CG29-1 -> 0.066841604
H73: EBITDA | Q73: =Q33/L33-1 -> 0.1920959 | R73: =R33/M33-1 -> 0.1162758 | S73: =S33/N33-1 -> 0.12080808 | T73: =T33/O33-1 -> 0.08126372 | U73: =U33/P33-1 -> 0.12592686 | V73: =V33/Q33-1 -> 0.10491354 | W73: =W33/R33-1 -> 0.23426427 | X73: =X33/S33-1 -> 0.14449652 | ... AJ73: =AJ33/AE33-1 -> 0.14417679 | AO73: =AO33/AJ33-1 -> 0.096020599 | AT73: =AT33/AO33-1 -> -0.050476021 | AY73: =AY33/AT33-1 -> -0.15785939 | AZ73: =AZ33/AU33-1 -> 0.018872138 | BA73: =BA33/AV33-1 -> 0.23411328 | BB73: =BB33/AW33-1 -> 0.25477074 | BC73: =BC33/AX33-1 -> -0.1664645 | BD73: =BD33/AY33-1 -> 0.079660145 | BE73: =BE33/AZ33-1 -> -0.33592722 | BF73: =BF33/BA33-1 -> -0.36132408 | ... CC73: =CC33/BX33-1 -> 0.10878593 | CD73: =CD33/CC33-1 -> 0.0925579 | CE73: =CE33/CD33-1 -> 0.099368654 | CF73: =CF33/CE33-1 -> 0.069739496 | CG73: =CG33/CF33-1 -> 0.053373062 | CH73: =CH33/CG33-1 -> 0.060957832
H74: =H44 -> Pretax income | L74: -0.034097914 | M74: -0.01435714 | N74: 0.051425031 | O74: 0.020877227 | P74: 0.006263021 | Q74: =Q44/L44-1 -> 0.11848793 | R74: =R44/M44-1 -> 0.11475628 | S74: =S44/N44-1 -> 0.085985072 | T74: =T44/O44-1 -> 0.08836773 | U74: =U44/P44-1 -> 0.1011527 | V74: =V44/Q44-1 -> 0.10830257 | W74: =W44/R44-1 -> 0.20570715 | X74: =X44/S44-1 -> 0.13958851 | ... CC74: =CC44/BX44-1 -> 0.1522392 | CD74: =CD44/CC44-1 -> 0.096998346 | CE74: =CE44/CD44-1 -> 0.11142484 | CF74: =CF44/CE44-1 -> 0.075754792 | CG74: =CG44/CF44-1 -> 0.058032187 | CH74: =CH44/CG44-1 -> 0.065914321
H75: =H47 -> Net income | L75: -0.034101141 | M75: -0.014352495 | N75: 0.051231136 | O75: 0.06936771 | P75: 0.019075596 | Q75: =Q47/L47-1 -> 0.13272299 | R75: =R47/M47-1 -> 0.1291414 | S75: =S47/N47-1 -> 0.10005037 | T75: =T47/O47-1 -> 0.06727899 | U75: =U47/P47-1 -> 0.10538887 | V75: =V47/Q47-1 -> 0.094319271 | W75: =W47/R47-1 -> 0.19031983 | X75: =X47/S47-1 -> 0.14109095 | ... CC75: =CC47/BX47-1 -> 0.20216869 | CD75: =CD47/CC47-1 -> 0.10083629 | CE75: =CE47/CD47-1 -> 0.11543238 | CF75: =CF47/CE47-1 -> 0.075754792 | CG75: =CG47/CF47-1 -> 0.058032187 | CH75: =CH47/CG47-1 -> 0.065914321
H76: =H49 -> Adj. Dil. EPS | L76: -0.036097318 | M76: -0.013921248 | N76: 0.049148636 | O76: 0.065178295 | P76: 0.017156201 | Q76: =Q49/L49-1 -> 0.13502283 | R76: =R49/M49-1 -> 0.13424865 | S76: =S49/N49-1 -> 0.10506251 | T76: =T49/O49-1 -> 0.071604563 | U76: =U49/P49-1 -> 0.10957875 | V76: =V49/Q49-1 -> 0.091422518 | W76: =W49/R49-1 -> 0.1852569 | X76: =X49/S49-1 -> 0.13709692 | ... CC76: =CC49/BX49-1 -> 0.21068064 | CD76: =CD49/CC49-1 -> 0.10414874 | CE76: =CE49/CD49-1 -> 0.11878874 | CF76: =CF49/CE49-1 -> 0.078991767 | CG76: =CG49/CF49-1 -> 0.061215834 | CH76: =CH49/CG49-1 -> 0.069121686
H77: =H50 -> Dil. shares outstanding | L77: 0.0020709324 | M77: -0.00043733543 | N77: 0.0019849431 | O77: 0.0039330645 | P77: 0.0018870207 | Q77: =Q50/L50-1 -> -0.0020262559 | R77: =R50/M50-1 -> -0.004502765 | S77: =S50/N50-1 -> -0.004535617 | T77: =T50/O50-1 -> -0.0040365392 | U77: =U50/P50-1 -> -0.0037760984 | V77: =V50/Q50-1 -> 0.0026541085 | W77: =W50/R50-1 -> 0.0042715906 | X77: =X50/S50-1 -> 0.0035124796 | ... BY77: =BY50/BT50-1 -> -0.006122279 | BZ77: -0.007 | CA77: -0.007 | CB77: -0.008 | CC77: =CC50/BX50-1 -> -0.0070307178 | CD77: -0.003 | CE77: -0.003 | CF77: -0.003 | CG77: -0.003 | CH77: -0.003
H86: =CFBS!H66 -> Cash and short-term investments | P86: 5037.7 | U86: 3891 | Z86: 4831.2 | AE86: 5926.1 | AJ86: 4497.6
H87: =CFBS!H66 & " (from BS)" -> Cash and short-term investments (from BS) | P87: =CFBS!P66 -> 5037.7 | U87: =CFBS!U66 -> 3891 | Z87: =CFBS!Z66 -> 4831.2 | AE87: =CFBS!AE66 -> 5926.1 | AJ87: =CFBS!AJ66 -> 4497.6
H88: =H36 -> Interest income | J88: =J36 -> 0 | P88: 212.2 | U88: 261.5 | Z88: 215 | AE88: 26.8 | AJ88: =AJ36 -> 75.2
H89: Interest rate earned | U89: =U88/AVERAGE(U87,P87) -> 0.058575157 | Z89: =Z88/AVERAGE(Z87,U87) -> 0.049299489 | AE89: =AE88/AVERAGE(AE87,Z87) -> 0.0049826629 | AJ89: =AJ88/AVERAGE(AJ87,AE87) -> 0.014428658
BI90: 0 | BJ90: 0 | BK90: 0 | BL90: 0 | BM90: 0 | BN90: 0 | BO90: 0 | BP90: 0 | BQ90: 0 | BR90: 0 | BS90: 0 | BT90: 0 | BU90: 0 | BV90: 0 | BW90: 0 | BX90: 0 | BY90: 0 | BZ90: 0 | CA90: 0 | CB90: 0 | CC90: 0 | CD90: 0 | CE90: 0 | CF90: 0 | CG90: 0 | CH90: 0
BI91: =BI30 -> 0 | BJ91: =BJ30 -> 0 | BK91: =BK30 -> 0 | BL91: =BL30 -> 0 | BM91: =BM30 -> 0 | BN91: =BN30 -> 0 | BO91: =BO30 -> 0 | BP91: =BP30 -> 0 | ... CH91: =CH30 -> 0
L92: =35%-4.8% -> 0.302 | M92: =35%-4.8% -> 0.302 | N92: =35%-4.8% -> 0.302 | O92: =35%-4.8% -> 0.302 | P92: =35%-4.8% -> 0.302 | Q92: =35%-6.72% -> 0.2828 | R92: =35%-6.72% -> 0.2828 | S92: =35%-6.72% -> 0.2828 | T92: =35%-6.72% -> 0.2828 | U92: =35%-6.72% -> 0.2828 | V92: =35%-11.6% -> 0.234 | W92: =35%-11.6% -> 0.234 | X92: =35%-11.6% -> 0.234 | Y92: =35%-11.6% -> 0.234 | Z92: =35%-11.6% -> 0.234 | AA92: =35%+49% -> 0.84 | AB92: =35%+49% -> 0.84 | AC92: =35%+49% -> 0.84 | AD92: =35%+49% -> 0.84 | AE92: =35%+49% -> 0.84 | AF92: =35%-17.12% -> 0.1788 | AG92: =35%-17.12% -> 0.1788 | AH92: =35%-17.12% -> 0.1788 | AI92: =35%-17.12% -> 0.1788 | AJ92: =35%-17.12% -> 0.1788 | AK92: =35%-16.24% -> 0.1876 | AL92: =35%-16.24% -> 0.1876 | AM92: =35%-16.24% -> 0.1876 | AN92: =35%-16.24% -> 0.1876 | AO92: =AJ92 -> 0.1788 | AP92: =AK92 -> 0.1876 | AQ92: =AL92 -> 0.1876 | AR92: =AM92 -> 0.1876 | AS92: =AN92 -> 0.1876 | AT92: =AO92 -> 0.1788 | AU92: =AP92 -> 0.1876 | AV92: =AQ92 -> 0.1876 | ... CC92: =BX92 -> 0.1788 | CD92: =CC92 -> 0.1788 | CE92: =CD92 -> 0.1788 | CF92: =CE92 -> 0.1788 | CG92: =CF92 -> 0.1788 | CH92: =CG92 -> 0.1788
H93: One time non recurring and extraordinary items | L93: =L94-L47 -> -0.032 | M93: =M94-M47 -> -980.25246 | N93: =N94-N47 -> 0.3 | O93: =O94-O47 -> -170.4 | P93: =P94-P47 -> -1150.3845 | Q93: =Q94-Q47 -> 0.4 | R93: =R94-R47 -> -0.3 | S93: =S94-S47 -> 0.05 | ... CH93: =CH94-CH47 -> -1000
H94: GAAP NI | L94: =CFBS!L15 -> 736.6 | M94: =CFBS!M15 -> -252 | N94: =CFBS!N15 -> 794.4 | O94: =CFBS!O15 -> 700.6 | P94: =CFBS!P15 -> 1979.6 | Q94: =CFBS!Q15 -> 834.8 | R94: =CFBS!R15 -> 822 | S94: =CFBS!S15 -> 873.6 | ... CH94: =CFBS!CH15 -> 7113.9283
H97: 3-year forward EPS growth | P97: =(P76+U76+Z76)/3 -> 0.080949709 | U97: =(U76+Z76+AE76)/3 -> 0.099944177 | Z97: =(Z76+AE76+AJ76)/3 -> 0.11585868 | AE97: =(AE76+AJ76+AO76)/3 -> 0.10165045 | AJ97: =(AJ76+AO76+AT76)/3 -> 0.053741251 | AO97: =(AO76+AT76+AY76)/3 -> -0.076105405 | AT97: =(AT76+AY76+BD76)/3 -> -0.025439388 | AY97: =(AY76+BD76+BI76)/3 -> -0.086136098 | BD97: =(BD76+BI76+BN76)/3 -> 0.023538651

Sheet REV-ANNUAL
EX1: Section Header
A3: REV-ANNUAL
L4: 38442 | M4: 38533 | N4: 38625 | O4: 38717 | P4: 38717 | Q4: 38807 | R4: 38898 | S4: 38990 | T4: 39082 | U4: 39082 | V4: 39172 | W4: 39263 | X4: 39355 | Y4: 39447 | Z4: 39447 | AA4: 39538 | AB4: 39629 | AC4: 39721 | AD4: 39813 | AE4: 39813 | AF4: 39903 | AG4: 39994 | AH4: 40086 | AI4: 40178 | AJ4: 40178 | AK4: 40268 | AL4: 40359 | AM4: 40451 | AN4: 40543 | AO4: 40543 | AP4: 40633 | AQ4: 40724 | AR4: 40816 | AS4: 40908 | AT4: 40908 | AU4: 40999 | AV4: 41090 | AW4: 41182 | AX4: 41274 | AY4: 41274 | AZ4: 41364 | BA4: 41455 | BB4: 41547 | BC4: 41639 | BD4: 41639 | BE4: 41729 | BF4: 41820 | BG4: 41912 | BH4: 42004 | BI4: 42004 | BJ4: 42094 | BK4: 42185 | BL4: 42277 | BM4: 42369 | BN4: 42369 | BO4: 42460 | BP4: 42551 | BQ4: 42643 | BR4: 42735 | BS4: 42735 | BT4: 42825 | BU4: 42916 | BV4: 43008 | BW4: 43100 | BX4: 43100 | BY4: 43190 | BZ4: 43281 | CA4: 43373 | CB4: 43465 | CC4: 43465 | CD4: 43830 | CE4: 44196 | CF4: 44561 | CG4: 44926 | CH4: 45291
H5: Eli Lilly & Co. | J5: =LatestRpQ -> 43190
H6: Annual Revenues | J6: =LatestFiledQ -> 43100
H9: ($M) | L9: ="1Q:" & RIGHT(YEAR(L$4),2) & IF(L$4<=LatestRpQ, "A", "E") -> 1Q:05A | M9: ="2Q:" & RIGHT(YEAR(M$4),2) & IF(M$4<=LatestRpQ, "A", "E") -> 2Q:05A | N9: ="3Q:" & RIGHT(YEAR(N$4),2) & IF(N$4<=LatestRpQ, "A", "E") -> 3Q:05A | O9: ="4Q:" & RIGHT(YEAR(O$4),2) & IF(O$4<=LatestRpQ, "A", "E") -> 4Q:05A | P9: =YEAR(P$4) & IF(P$4<=LatestRpQ, "A", "E") -> 2005A | Q9: ="1Q:" & RIGHT(YEAR(Q$4),2) & IF(Q$4<=LatestRpQ, "A", "E") -> 1Q:06A | R9: ="2Q:" & RIGHT(YEAR(R$4),2) & IF(R$4<=LatestRpQ, "A", "E") -> 2Q:06A | S9: ="3Q:" & RIGHT(YEAR(S$4),2) & IF(S$4<=LatestRpQ, "A", "E") -> 3Q:06A | T9: ="4Q:" & RIGHT(YEAR(T$4),2) & IF(T$4<=LatestRpQ, "A", "E") -> 4Q:06A | U9: =YEAR(U$4) & IF(U$4<=LatestRpQ, "A", "E") -> 2006A | V9: ="1Q:" & RIGHT(YEAR(V$4),2) & IF(V$4<=LatestRpQ, "A", "E") -> 1Q:07A | W9: ="2Q:" & RIGHT(YEAR(W$4),2) & IF(W$4<=LatestRpQ, "A", "E") -> 2Q:07A | X9: ="3Q:" & RIGHT(YEAR(X$4),2) & IF(X$4<=LatestRpQ, "A", "E") -> 3Q:07A | Y9: ="4Q:" & RIGHT(YEAR(Y$4),2) & IF(Y$4<=LatestRpQ, "A", "E") -> 4Q:07A | Z9: =YEAR(Z$4) & IF(Z$4<=LatestRpQ, "A", "E") -> 2007A | AA9: ="1Q:" & RIGHT(YEAR(AA$4),2) & IF(AA$4<=LatestRpQ, "A", "E") -> 1Q:08A | AB9: ="2Q:" & RIGHT(YEAR(AB$4),2) & IF(AB$4<=LatestRpQ, "A", "E") -> 2Q:08A | AC9: ="3Q:" & RIGHT(YEAR(AC$4),2) & IF(AC$4<=LatestRpQ, "A", "E") -> 3Q:08A | AD9: ="4Q:" & RIGHT(YEAR(AD$4),2) & IF(AD$4<=LatestRpQ, "A", "E") -> 4Q:08A | AE9: =YEAR(AE$4) & IF(AE$4<=LatestRpQ, "A", "E") -> 2008A | AF9: ="1Q:" & RIGHT(YEAR(AF$4),2) & IF(AF$4<=LatestRpQ, "A", "E") -> 1Q:09A | AG9: ="2Q:" & RIGHT(YEAR(AG$4),2) & IF(AG$4<=LatestRpQ, "A", "E") -> 2Q:09A | AH9: ="3Q:" & RIGHT(YEAR(AH$4),2) & IF(AH$4<=LatestRpQ, "A", "E") -> 3Q:09A | AI9: ="4Q:" & RIGHT(YEAR(AI$4),2) & IF(AI$4<=LatestRpQ, "A", "E") -> 4Q:09A | AJ9: =YEAR(AJ$4) & IF(AJ$4<=LatestRpQ, "A", "E") -> 2009A | AK9: ="1Q:" & RIGHT(YEAR(AK$4),2) & IF(AK$4<=LatestRpQ, "A", "E") -> 1Q:10A | AL9: ="2Q:" & RIGHT(YEAR(AL$4),2) & IF(AL$4<=LatestRpQ, "A", "E") -> 2Q:10A | AM9: ="3Q:" & RIGHT(YEAR(AM$4),2) & IF(AM$4<=LatestRpQ, "A", "E") -> 3Q:10A | AN9: ="4Q:" & RIGHT(YEAR(AN$4),2) & IF(AN$4<=LatestRpQ, "A", "E") -> 4Q:10A | AO9: =YEAR(AO$4) & IF(AO$4<=LatestRpQ, "A", "E") -> 2010A | AP9: ="1Q:" & RIGHT(YEAR(AP$4),2) & IF(AP$4<=LatestRpQ, "A", "E") -> 1Q:11A | AQ9: ="2Q:" & RIGHT(YEAR(AQ$4),2) & IF(AQ$4<=LatestRpQ, "A", "E") -> 2Q:11A | AR9: ="3Q:" & RIGHT(YEAR(AR$4),2) & IF(AR$4<=LatestRpQ, "A", "E") -> 3Q:11A | AS9: ="4Q:" & RIGHT(YEAR(AS$4),2) & IF(AS$4<=LatestRpQ, "A", "E") -> 4Q:11A | AT9: =YEAR(AT$4) & IF(AT$4<=LatestRpQ, "A", "E") -> 2011A | AU9: ="1Q:" & RIGHT(YEAR(AU$4),2) & IF(AU$4<=LatestRpQ, "A", "E") -> 1Q:12A | AV9: ="2Q:" & RIGHT(YEAR(AV$4),2) & IF(AV$4<=LatestRpQ, "A", "E") -> 2Q:12A | AW9: ="3Q:" & RIGHT(YEAR(AW$4),2) & IF(AW$4<=LatestRpQ, "A", "E") -> 3Q:12A | AX9: ="4Q:" & RIGHT(YEAR(AX$4),2) & IF(AX$4<=LatestRpQ, "A", "E") -> 4Q:12A | AY9: =YEAR(AY$4) & IF(AY$4<=LatestRpQ, "A", "E") -> 2012A | AZ9: ="1Q:" & RIGHT(YEAR(AZ$4),2) & IF(AZ$4<=LatestRpQ, "A", "E") -> 1Q:13A | BA9: ="2Q:" & RIGHT(YEAR(BA$4),2) & IF(BA$4<=LatestRpQ, "A", "E") -> 2Q:13A | BB9: ="3Q:" & RIGHT(YEAR(BB$4),2) & IF(BB$4<=LatestRpQ, "A", "E") -> 3Q:13A | BC9: ="4Q:" & RIGHT(YEAR(BC$4),2) & IF(BC$4<=LatestRpQ, "A", "E") -> 4Q:13A | BD9: =YEAR(BD$4) & IF(BD$4<=LatestRpQ, "A", "E") -> 2013A | BE9: ="1Q:" & RIGHT(YEAR(BE$4),2) & IF(BE$4<=LatestRpQ, "A", "E") -> 1Q:14A | BF9: ="2Q:" & RIGHT(YEAR(BF$4),2) & IF(BF$4<=LatestRpQ, "A", "E") -> 2Q:14A | BG9: ="3Q:" & RIGHT(YEAR(BG$4),2) & IF(BG$4<=LatestRpQ, "A", "E") -> 3Q:14A | BH9: ="4Q:" & RIGHT(YEAR(BH$4),2) & IF(BH$4<=LatestRpQ, "A", "E") -> 4Q:14A | BI9: =YEAR(BI$4) & IF(BI$4<=LatestRpQ, "A", "E") -> 2014A | BJ9: ="1Q:" & RIGHT(YEAR(BJ$4),2) & IF(BJ$4<=LatestRpQ, "A", "E") -> 1Q:15A | BK9: ="2Q:" & RIGHT(YEAR(BK$4),2) & IF(BK$4<=LatestRpQ, "A", "E") -> 2Q:15A | BL9: ="3Q:" & RIGHT(YEAR(BL$4),2) & IF(BL$4<=LatestRpQ, "A", "E") -> 3Q:15A | BM9: ="4Q:" & RIGHT(YEAR(BM$4),2) & IF(BM$4<=LatestRpQ, "A", "E") -> 4Q:15A | BN9: =YEAR(BN$4) & IF(BN$4<=LatestRpQ, "A", "E") -> 2015A | BO9: ="1Q:" & RIGHT(YEAR(BO$4),2) & IF(BO$4<=LatestRpQ, "A", "E") -> 1Q:16A | BP9: ="2Q:" & RIGHT(YEAR(BP$4),2) & IF(BP$4<=LatestRpQ, "A", "E") -> 2Q:16A | BQ9: ="3Q:" & RIGHT(YEAR(BQ$4),2) & IF(BQ$4<=LatestRpQ, "A", "E") -> 3Q:16A | BR9: ="4Q:" & RIGHT(YEAR(BR$4),2) & IF(BR$4<=LatestRpQ, "A", "E") -> 4Q:16A | BS9: =YEAR(BS$4) & IF(BS$4<=LatestRpQ, "A", "E") -> 2016A | BT9: ="1Q:" & RIGHT(YEAR(BT$4),2) & IF(BT$4<=LatestRpQ, "A", "E") -> 1Q:17A | BU9: ="2Q:" & RIGHT(YEAR(BU$4),2) & IF(BU$4<=LatestRpQ, "A", "E") -> 2Q:17A | BV9: ="3Q:" & RIGHT(YEAR(BV$4),2) & IF(BV$4<=LatestRpQ, "A", "E") -> 3Q:17A | BW9: ="4Q:" & RIGHT(YEAR(BW$4),2) & IF(BW$4<=LatestRpQ, "A", "E") -> 4Q:17A | BX9: =YEAR(BX$4) & IF(BX$4<=LatestRpQ, "A", "E") -> 2017A | BY9: ="1Q:" & RIGHT(YEAR(BY$4),2) & IF(BY$4<=LatestRpQ, "A", "E") -> 1Q:18A | BZ9: ="2Q:" & RIGHT(YEAR(BZ$4),2) & IF(BZ$4<=LatestRpQ, "A", "E") -> 2Q:18E | CA9: ="3Q:" & RIGHT(YEAR(CA$4),2) & IF(CA$4<=LatestRpQ, "A", "E") -> 3Q:18E | CB9: ="4Q:" & RIGHT(YEAR(CB$4),2) & IF(CB$4<=LatestRpQ, "A", "E") -> 4Q:18E | CC9: =YEAR(CC$4) & IF(CC$4<=LatestRpQ, "A", "E") -> 2018E | CD9: =YEAR(CD$4) & IF(CD$4<=LatestRpQ, "A", "E") -> 2019E | CE9: =YEAR(CE$4) & IF(CE$4<=LatestRpQ, "A", "E") -> 2020E | CF9: =YEAR(CF$4) & IF(CF$4<=LatestRpQ, "A", "E") -> 2021E | CG9: =YEAR(CG$4) & IF(CG$4<=LatestRpQ, "A", "E") -> 2022E | CH9: =YEAR(CH$4) & IF(CH$4<=LatestRpQ, "A", "E") -> 2023E
H11: Pharmaceuticals | L11: 3301.9 | M11: 3466.8 | N11: 3385.5 | O11: 3627.7 | P11: 13785.1 | Q11: 3516.4 | R11: 3666.1 | S11: 3647.85 | T11: 3985.4 | U11: 14815.55 | V11: 4011.1 | W11: 4416.2 | X11: 4350.2 | Y11: 4860.4 | Z11: 17638 | AA11: 4500 | AB11: 4800.5 | AC11: 4841.3 | AD11: 4775.2 | AE11: 18916.9 | AF11: 4627.3 | AG11: 4837.75 | AH11: 5071.1 | AI11: 5428.1 | AJ11: 19964.25 | AK11: 5042.9 | AL11: 5265.2 | AM11: 5133.7 | AN11: 5609.48 | AO11: 21051.28 | AP11: 5320.2 | AQ11: 5697.2 | AR11: 5520.7 | AS11: 5388.2 | AT11: 21926.3 | AU11: 5111.3 | AV11: 5088.5 | AW11: 4963.9 | AX11: 5403.2 | AY11: 20566.9 | AZ11: 5102.9 | BA11: 5386.2 | BB11: 5242.3 | BC11: 5230.4 | BD11: =BD15+BD47+BD106+BD137+BD178+BD201 -> 20961.8 | BE11: 4155.7 | BF11: 4334.4 | BG11: 4290.9 | BH11: 4488 | BI11: =BI15+BI47+BI106+BI137+BI178+BI201 -> 17269 | BJ11: 3894.9 | BK11: 4137.9 | BL11: 4180.9 | BM11: 4563.9 | BN11: =BN15+BN47+BN106+BN137+BN178+BN201 -> 16777.6 | BO11: =BO15+BO47+BO106+BO137+BO178+BO201 -> 4110.5 | BP11: =BP15+BP47+BP106+BP137+BP168+BP178+BP201 -> 4545 | BQ11: =BQ15+BQ47+BQ106+BQ137+BQ168+BQ178+BQ201 -> 4485.5 | BR11: =BR15+BR47+BR106+BR137+BR168+BR178+BR201 -> 4922.9 | BS11: =BS15+BS47+BS106+BS137+BS168+BS178+BS201 -> 18052 | BT11: =BT15+BT47+BT106+BT137+BT168+BT178+BT201 -> 4459 | BU11: =BU15+BU47+BU106+BU137+BU168+BU178+BU201 -> 5039.5 | BV11: =BV15+BV47+BV106+BV137+BV168+BV178+BV201 -> 4917.5 | BW11: =BW15+BW47+BW106+BW137+BW168+BW178+BW201 -> 5369.9 | ... CH11: =CH15+CH47+CH106+CH137+CH168+CH178+CH201 -> 23755.99 | EX11: Pharmaceuticals
H12: U.S. | L12: 1770.1 | M12: 1858.9 | N12: 1834.2 | O12: 1964.6 | P12: 7431 | Q12: 1951.5 | R12: 2004.9 | S12: 2008.55 | T12: 2228.3 | U12: 8193.05 | V12: 2218.3 | W12: 2407.6 | X12: 2364.9 | Y12: 2674.2 | Z12: 9665.1 | AA12: 2366.5 | AB12: 2475.4 | AC12: 2551.9 | AD12: 2653.8 | AE12: 10047.5 | AF12: 2583 | AG12: 2712.89 | AH12: 2820.8 | AI12: 2949.6 | AJ12: 11066.29 | AK12: 2748.8 | AL12: 2956.9 | AM12: 2837.3 | AN12: 3064.88 | AO12: 11607.88 | AP12: 2757.3 | AQ12: 3003.4 | AR12: 2887.1 | AS12: 2879.8 | AT12: 11527.6 | AU12: 2815.3 | AV12: 2707.7 | AW12: 2710.9 | AX12: 2917.5 | AY12: 11151.4 | AZ12: 2841.9 | BA12: 3076 | BB12: 3006.9 | BC12: 2738 | BD12: =BD16+BD48+BD107+BD138+BD179+BD202 -> 11663 | BE12: 1776.7 | BF12: 2047.7 | BG12: 1904.9 | BH12: 2130.5 | BI12: =BI16+BI48+BI107+BI138+BI179+BI202 -> 7859.8 | BJ12: 1840.7 | BK12: 2117.8 | BL12: 2145.1 | BM12: 2438.8 | BN12: =BN16+BN48+BN107+BN138+BN179+BN202 -> 8542.4 | BO12: 2163.2 | BP12: 2445.4 | BQ12: 2499 | BR12: 2834.1 | BS12: =BS16+BS48+BS107+BS138+BS169+BS179+BS202 -> 9930.2 | BT12: 2519.7 | BU12: 2917.4 | BV12: 2751.3 | BW12: 3085.5 | BX12: =BX16+BX48+BX107+BX138+BX169+BX179+BX202 -> 11274.1 | BY12: =2779 -> 2779 | BZ12: =BZ16+BZ48+BZ107+BZ138+BZ169+BZ179+BZ202 -> 3008.027 | CA12: =CA16+CA48+CA107+CA138+CA169+CA179+CA202 -> 3059.231 | CB12: =CB16+CB48+CB107+CB138+CB169+CB179+CB202 -> 3088.073 | CC12: =CC16+CC48+CC107+CC138+CC169+CC179+CC202 -> 11934.331 | CD12: =CD16+CD48+CD107+CD138+CD169+CD179+CD202 -> 12121.981 | CE12: =CE16+CE48+CE107+CE138+CE169+CE179+CE202 -> 12827.781 | CF12: =CF16+CF48+CF107+CF138+CF169+CF179+CF202 -> 13472.529 | CG12: =CG16+CG48+CG107+CG138+CG169+CG179+CG202 -> 13708.295 | CH12: =CH16+CH48+CH107+CH138+CH169+CH179+CH202 -> 14028.195
H13: ex-US | L13: 1531.8 | M13: 1607.9 | N13: 1551.3 | O13: 1663.1 | P13: 6354.1 | Q13: 1564.9 | R13: 1661.2 | S13: 1639.3 | T13: 1757.1 | U13: 6622.5 | V13: 1792.8 | W13: 2008.6 | X13: 1985.3 | Y13: 2186.2 | Z13: 7972.9 | AA13: 2133.5 | AB13: 2325.1 | AC13: 2289.4 | AD13: 2121.4 | AE13: 8869.4 | AF13: 2044.3 | AG13: 2124.86 | AH13: 2250.3 | AI13: 2478.5 | AJ13: 8897.96 | AK13: 2294.1 | AL13: 2308.3 | AM13: 2296.4 | AN13: 2544.6 | AO13: 9443.4 | AP13: 2562.9 | AQ13: 2693.8 | AR13: 2633.6 | AS13: 2508.4 | AT13: 10398.7 | AU13: 2296 | AV13: 2380.8 | AW13: 2253 | AX13: 2485.7 | AY13: 9415.5 | AZ13: 2261 | BA13: 2310.2 | BB13: 2235.4 | BC13: 2235.4 | BD13: =BD17+BD49+BD108+BD139+BD180+BD203 -> 9298.8 | BE13: 2379 | BF13: 2286.7 | BG13: 2386 | BH13: 2357.5 | BI13: =BI17+BI49+BI108+BI139+BI180+BI203 -> 9409.2 | BJ13: 2054.2 | BK13: 2020.1 | BL13: 2035.8 | BM13: 2125.1 | BN13: =BN17+BN49+BN108+BN139+BN180+BN203 -> 8235.2 | BO13: 1947.3 | BP13: 2099.6 | BQ13: 1986.5 | BR13: 2088.8 | BS13: =BS17+BS49+BS108+BS139+BS170+BS180+BS203 -> 8121.8 | BT13: 1939.2 | BU13: 2122 | BV13: 2166.1 | BW13: 2284.4 | BX13: =BX17+BX49+BX108+BX139+BX170+BX180+BX203 -> 8511.8 | BY13: =2159.7 -> 2159.7 | BZ13: =BZ17+BZ49+BZ108+BZ139+BZ170+BZ180+BZ203 -> 2212.355 | CA13: =CA17+CA49+CA108+CA139+CA170+CA180+CA203 -> 2237.896 | CB13: =CB17+CB49+CB108+CB139+CB170+CB180+CB203 -> 2316.556 | CC13: =CC17+CC49+CC108+CC139+CC170+CC180+CC203 -> 8926.507 | CD13: =CD17+CD49+CD108+CD139+CD170+CD180+CD203 -> 9100.3268 | CE13: =CE17+CE49+CE108+CE139+CE170+CE180+CE203 -> 9083.7417 | CF13: =CF17+CF49+CF108+CF139+CF170+CF180+CF203 -> 9127.1339 | CG13: =CG17+CG49+CG108+CG139+CG170+CG180+CG203 -> 9415.4595 | CH13: =CH17+CH49+CH108+CH139+CH170+CH180+CH203 -> 9727.7948
H15: Neuroscience | L15: 1427.8 | M15: 1547.4 | N15: 1515 | O15: 1589.8 | P15: 6080 | Q15: =Q28+Q19+Q43+Q22+Q25+Q31+Q37+Q40 -> 1507 | R15: =R28+R19+R43+R22+R25+R31+R37+R40 -> 1686.3 | S15: =S28+S19+S43+S22+S25+S31+S37+S40 -> 1676.15 | T15: =T28+T19+T43+T22+T25+T31+T37+T40 -> 1859.3 | U15: =U28+U19+U43+U22+U25+U31+U37+U40 -> 6728.75 | V15: =V28+V19+V43+V22+V25+V31+V37+V40 -> 1797.5 | W15: =W28+W19+W43+W22+W25+W31+W37+W40 -> 1981.2 | X15: =X28+X19+X43+X22+X25+X31+X37+X40 -> 1903.7 | ... AO15: =AO28+AO19+AO43+AO22+AO25+AO31+AO37+AO40 -> 9397.7 | AP15: =AP28+AP19+AP22+AP25+AP31+AP37 -> 2405.2 | AQ15: =AQ28+AQ19+AQ22+AQ25+AQ31+AQ37 -> 2653.9 | AR15: =AR28+AR19+AR22+AR25+AR31+AR37 -> 2488 | AS15: =AS28+AS19+AS22+AS25+AS31+AS37 -> 2176.8 | AT15: =AT28+AT19+AT22+AT25+AT31+AT37 -> 9723.9 | AU15: =AU16+AU17 -> 1905.3 | AV15: =AV16+AV17 -> 1827 | AW15: =AW16+AW17 -> 1818.8 | AX15: =AX16+AX17 -> 2033 | AY15: =AY16+AY17 -> 7584.1 | AZ15: =AZ16+AZ17 -> 1848.8 | BA15: =BA16+BA17 -> 2004.5 | BB15: =BB16+BB17 -> 1878.1 | ... CH15: =CH16+CH17 -> 668.03912 | EX15: Neuroscience
H16: U.S. | L16: 803.2 | M16: 885.4 | N16: 877.6 | O16: 907.3 | P16: 3473.5 | Q16: =Q29+Q20+Q44+Q23+Q26+Q32+Q38+Q41 -> 884.1 | R16: =R29+R20+R44+R23+R26+R32+R38+R41 -> 988.6 | S16: =S29+S20+S44+S23+S26+S32+S38+S41 -> 989.15 | T16: =T29+T20+T44+T23+T26+T32+T38+T41 -> 1116.8 | U16: =U29+U20+U44+U23+U26+U32+U38+U41 -> 3978.65 | V16: =V29+V20+V44+V23+V26+V32+V38+V41 -> 1076.2 | W16: =W29+W20+W44+W23+W26+W32+W38+W41 -> 1187.3 | X16: =X29+X20+X44+X23+X26+X32+X38+X41 -> 1135.4 | ... AO16: =AO29+AO20+AO44+AO23+AO26+AO32+AO38+AO41 -> 5829.9 | AP16: =AP29+AP20+AP23+AP26+AP32+AP38 -> 1412.1 | AQ16: =AQ29+AQ20+AQ23+AQ26+AQ32+AQ38 -> 1608.6 | AR16: =AR29+AR20+AR23+AR26+AR32+AR38 -> 1511.2 | AS16: =AS29+AS20+AS23+AS26+AS32+AS38 -> 1355.1 | AT16: =AT29+AT20+AT23+AT26+AT32+AT38 -> 5887 | AU16: 1195.9 | AV16: 1109.2 | AW16: 1147.4 | AX16: 1320.8 | AY16: =AY29+AY20+AY23+AY26+AY32 -> 4773.3 | AZ16: 1215.6 | BA16: 1361.4 | BB16: 1274.3 | BC16: 763.2 | BD16: =BD29+BD20+BD23+BD26+BD32 -> 4614.5 | BE16: 303.9 | BF16: 300.1 | BG16: 229.3 | BH16: 236.8 | BI16: =BI29+BI20+BI23+BI26+BI32 -> 1070.1 | BJ16: 205.6 | BK16: 236.7 | BL16: 222.6 | BM16: 217.7 | BN16: =BN29+BN20+BN23+BN26+BN32 -> 882.6 | BO16: 198.1 | BP16: 240.4 | BQ16: 312.2 | BR16: 239.1 | BS16: =BS29+BS20+BS23+BS26+BS32 -> 989.8 | BT16: 214.8 | BU16: 192.2 | BV16: 108.4 | BW16: 75.6 | BX16: =BX29+BX20+BX23+BX26+BX32 -> 591 | BY16: =91.2 -> 91.2 | BZ16: =BZ29+BZ20+BZ23+BZ26+BZ32 -> 76.202 | CA16: =CA29+CA20+CA23+CA26+CA32 -> 63.38 | CB16: =CB29+CB20+CB23+CB26+CB32 -> 58.32 | CC16: =CC29+CC20+CC23+CC26+CC32 -> 289.102 | CD16: =CD29+CD20+CD23+CD26+CD32 -> 222.4743 | CE16: =CE29+CE20+CE23+CE26+CE32 -> 193.8689 | CF16: =CF29+CF20+CF23+CF26+CF32 -> 176.35101 | CG16: =CG29+CG20+CG23+CG26+CG32 -> 160.5849 | CH16: =CH29+CH20+CH23+CH26+CH32 -> 146.39541
H17: ex-US | L17: 624.6 | M17: 662 | N17: 637.4 | O17: 682.5 | P17: 2606.5 | Q17: =Q30+Q21+Q45+Q24+Q27+Q33+Q39+Q42 -> 622.9 | R17: =R30+R21+R45+R24+R27+R33+R39+R42 -> 697.7 | S17: =S30+S21+S45+S24+S27+S33+S39+S42 -> 687 | T17: =T30+T21+T45+T24+T27+T33+T39+T42 -> 742.5 | U17: =U30+U21+U45+U24+U27+U33+U39+U42 -> 2750.1 | V17: =V30+V21+V45+V24+V27+V33+V39+V42 -> 721.3 | W17: =W30+W21+W45+W24+W27+W33+W39+W42 -> 793.9 | X17: =X30+X21+X45+X24+X27+X33+X39+X42 -> 768.3 | ... AO17: =AO30+AO21+AO45+AO24+AO27+AO33+AO39+AO42 -> 3567.8 | AP17: =AP30+AP21+AP24+AP27+AP33+AP39 -> 993.1 | AQ17: =AQ30+AQ21+AQ24+AQ27+AQ33+AQ39 -> 1045.3 | AR17: =AR30+AR21+AR24+AR27+AR33+AR39 -> 976.8 | AS17: =AS30+AS21+AS24+AS27+AS33+AS39 -> 821.7 | AT17: =AT30+AT21+AT24+AT27+AT33+AT39 -> 3836.9 | AU17: 709.4 | AV17: 717.8 | AW17: 671.4 | AX17: 712.2 | AY17: =AY30+AY21+AY24+AY27+AY33 -> 2810.8 | AZ17: 633.2 | BA17: 643.1 | BB17: 603.8 | BC17: 721.6 | BD17: =BD30+BD21+BD24+BD27+BD33 -> 2601.7 | BE17: 660.5 | BF17: 593.6 | BG17: 640.6 | BH17: 631.7 | BI17: =BI30+BI21+BI24+BI27+BI33 -> 2526.4 | BJ17: 519.7 | BK17: 527.2 | BL17: 501.9 | BM17: 504.1 | BN17: =BN30+BN21+BN24+BN27+BN33 -> 2052.9 | BO17: 445.6 | BP17: 477.3 | BQ17: 396.3 | BR17: 411.3 | BS17: =BS30+BS21+BS24+BS27+BS33 -> 1730.5 | BT17: 364.6 | BU17: 394.5 | BV17: 399.3 | BW17: 421.7 | BX17: =BX30+BX21+BX24+BX27+BX33 -> 1580.1 | BY17: =381.5 -> 381.5 | BZ17: =BZ30+BZ21+BZ24+BZ27+BZ33 -> 375.917 | CA17: =CA30+CA21+CA24+CA27+CA33 -> 374.067 | CB17: =CB30+CB21+CB24+CB27+CB33 -> 376.36 | CC17: =CC30+CC21+CC24+CC27+CC33 -> 1507.844 | CD17: =CD30+CD21+CD24+CD27+CD33 -> 1257.6677 | CE17: =CE30+CE21+CE24+CE27+CE33 -> 919.07692 | CF17: =CF30+CF21+CF24+CF27+CF33 -> 698.9783 | CG17: =CG30+CG21+CG24+CG27+CG33 -> 601.997 | CH17: =CH30+CH21+CH24+CH27+CH33 -> 521.64371
H18: Total Zyprexa Franchise | L18: 1050.8 | M18: 1111.6 | N18: 1048.1 | O18: 1045.6 | P18: 4256.1 | Q18: =Q19+Q37 -> 1020.9 | R18: =R19+R37 -> 1126.1 | S18: =S19+S37 -> 1098.7 | T18: =T19+T37 -> 1171.9 | U18: =U19+U37 -> 4417.6 | V18: =V19+V37 -> 1122.4 | W18: =W19+W37 -> 1225.3 | X18: =X19+X37 -> 1179.7 | ... CH18: =CH19+CH37 -> 297.38257
H19: Zyprexa (incl. depot) | L19: 1038.2 | M19: 1096.7 | N19: 1035.1 | O19: 1032.2 | P19: 4202.2 | Q19: =Q20+Q21 -> 1007.4 | R19: =R20+R21 -> 1115.1 | S19: =S20+S21 -> 1084.7 | T19: =T20+T21 -> 1156.6 | U19: =U20+U21 -> 4363.8 | V19: =V20+V21 -> 1108 | W19: =W20+W21 -> 1212.9 | X19: =X20+X21 -> 1166.2 | ... CH19: =CH20+CH21 -> 297.38257 | EX19: Zyprexa (incl. depot)
H20: U.S. (10/23/11*) | L20: 517.4 | M20: 549.3 | N20: 503.9 | O20: 464.2 | P20: 2034.8 | Q20: 493.9 | R20: 542.9 | S20: 519 | T20: 550.5 | U20: =SUM(Q20:T20) -> 2106.3 | V20: 523.3 | W20: 563.5 | X20: 540.6 | Y20: 608.6 | Z20: =SUM(V20:Y20) -> 2236 | AA20: 499.3 | AB20: 563.6 | AC20: 555.6 | AD20: 584 | AE20: =SUM(AA20:AD20) -> 2202.5 | AF20: 535.4 | AG20: 582.2 | AH20: 569.6 | AI20: 644.6 | AJ20: =SUM(AF20:AI20) -> 2331.8 | AK20: 583.5 | AL20: 638.2 | AM20: 604.6 | AN20: 669.3 | AO20: =SUM(AK20:AN20) -> 2495.6 | AP20: 597.1 | AQ20: 711.2 | AR20: 563.2 | AS20: 293.9 | AT20: =SUM(AP20:AS20) -> 2165.4 | AU20: 202.8 | AV20: 29.8 | AW20: 67.8 | AX20: 60.1 | AY20: =SUM(AU20:AX20) -> 360.5 | AZ20: 32 | BA20: 19.5 | BB20: 32.9 | BC20: 39.2 | BD20: =SUM(AZ20:BC20) -> 123.6 | BE20: 27.2 | BF20: 39.6 | BG20: 18.8 | BH20: 34.2 | BI20: =SUM(BE20:BH20) -> 119.8 | BJ20: 26.6 | BK20: 57.6 | BL20: 46.9 | BM20: 25.7 | BN20: =SUM(BJ20:BM20) -> 156.8 | BO20: 37.9 | BP20: 14.5 | BQ20: 7.3 | BR20: 10 | BS20: =SUM(BO20:BR20) -> 69.7 | BT20: 23.7 | BU20: 13 | BV20: 12.6 | BW20: 26.2 | BX20: =SUM(BT20:BW20) -> 75.5 | BY20: =8.8 -> 8.8 | BZ20: =BU20*(1+BZ250) -> 11.7 | CA20: =BV20*(1+CA250) -> 12.6 | CB20: =BW20*(1+CB250) -> 13.1 | CC20: =SUM(BY20:CB20) -> 46.2 | CD20: =CC20*(1+CD250) -> 41.58 | CE20: =CD20*(1+CE250) -> 37.422 | CF20: =CE20*(1+CF250) -> 33.6798 | CG20: =CF20*(1+CG250) -> 30.31182 | CH20: =CG20*(1+CH250) -> 27.280638
H21: ex-U.S. (EU Sep-11, Japan Jun-16) | L21: 520.8 | M21: 547.4 | N21: 531.2 | O21: 568 | P21: 2167.4 | Q21: 513.5 | R21: 572.2 | S21: 565.7 | T21: 606.1 | U21: =SUM(Q21:T21) -> 2257.5 | V21: 584.7 | W21: 649.4 | X21: 625.6 | Y21: 665.3 | Z21: =SUM(V21:Y21) -> 2525 | AA21: 620.9 | AB21: 676.2 | AC21: 633.9 | AD21: 562.7 | AE21: =SUM(AA21:AD21) -> 2493.7 | AF21: 587.6 | AG21: 621 | AH21: 653.4 | AI21: 721.9 | AJ21: =SUM(AF21:AI21) -> 2583.9 | AK21: 631.5 | AL21: 624.7 | AM21: 608.2 | AN21: 666.5 | AO21: =SUM(AK21:AN21) -> 2530.9 | AP21: 684.8 | AQ21: 697.1 | AR21: 619.1 | AS21: 455.7 | AT21: =SUM(AP21:AS21) -> 2456.7 | AU21: 359.9 | AV21: 349.7 | AW21: 306.7 | AX21: 324.7 | AY21: =SUM(AU21:AX21) -> 1341 | AZ21: 252.8 | BA21: 263.7 | BB21: 245.8 | BC21: 309 | BD21: =SUM(AZ21:BC21) -> 1071.3 | BE21: 255.9 | BF21: 204.2 | BG21: 238.6 | BH21: 218.9 | BI21: =SUM(BE21:BH21) -> 917.6 | BJ21: 192.9 | BK21: 196.1 | BL21: 191 | BM21: 203.4 | BN21: =SUM(BJ21:BM21) -> 783.4 | BO21: 174.9 | BP21: 196.2 | BQ21: 141.6 | BR21: 143 | BS21: =SUM(BO21:BR21) -> 655.7 | BT21: 123.8 | BU21: 127.8 | BV21: 128 | BW21: 126 | BX21: =SUM(BT21:BW21) -> 505.6 | BY21: =113.8 -> 113.8 | BZ21: =BU21*(1+BZ251) -> 115.02 | CA21: =BV21*(1+CA251) -> 115.2 | CB21: =BW21*(1+CB251) -> 113.4 | CC21: =SUM(BY21:CB21) -> 457.42 | CD21: =CC21*(1+CD251) -> 411.678 | CE21: =CD21*(1+CE251) -> 370.5102 | CF21: =CE21*(1+CF251) -> 333.45918 | CG21: =CF21*(1+CG251) -> 300.11326 | CH21: =CG21*(1+CH251) -> 270.10194
H22: Strattera | L22: 119.7 | M22: 123.4 | N22: 140.9 | O22: 167.9 | P22: 551.9 | Q22: =Q23+Q24 -> 152.2 | R22: =R23+R24 -> 144.2 | S22: =S23+S24 -> 126.4 | T22: =T23+T24 -> 156.3 | U22: =U23+U24 -> 579.1 | V22: =V23+V24 -> 139.9 | W22: =W23+W24 -> 142.3 | X22: =X23+X24 -> 130.5 | ... CH22: =CH23+CH24 -> 56.918045 | EX22: Strattera
H23: U.S. (5/26/17*) | L23: 112.3 | M23: 110.9 | N23: 125 | O23: 150.4 | P23: 498.6 | Q23: 135.3 | R23: 125.9 | S23: 112.3 | T23: 135.8 | U23: =SUM(Q23:T23) -> 509.3 | V23: 117.7 | W23: 117.2 | X23: 103.6 | Y23: 126.1 | Z23: =SUM(V23:Y23) -> 464.6 | AA23: 115.5 | AB23: 101.4 | AC23: 109.5 | AD23: 111.4 | AE23: =SUM(AA23:AD23) -> 437.8 | AF23: 115.6 | AG23: 105.7 | AH23: 106.9 | AI23: 117.5 | AJ23: =SUM(AF23:AI23) -> 445.7 | AK23: 102.9 | AL23: 100.4 | AM23: 85.1 | AN23: 101.4 | AO23: =SUM(AK23:AN23) -> 389.8 | AP23: 86.6 | AQ23: 98 | AR23: 96.3 | AS23: 111.2 | AT23: =SUM(AP23:AS23) -> 392.1 | AU23: 104.8 | AV23: 93.5 | AW23: 90 | AX23: 95.8 | AY23: =SUM(AU23:AX23) -> 384.1 | AZ23: 105.5 | BA23: 102.6 | BB23: 111.1 | BC23: 127 | BD23: =SUM(AZ23:BC23) -> 446.2 | BE23: 83.1 | BF23: 129.5 | BG23: 120.9 | BH23: 119.1 | BI23: =SUM(BE23:BH23) -> 452.6 | BJ23: 108.5 | BK23: 121.1 | BL23: 128.8 | BM23: 143.7 | BN23: =SUM(BJ23:BM23) -> 502.1 | BO23: 116.6 | BP23: 143.5 | BQ23: 119.5 | BR23: 155.3 | BS23: =SUM(BO23:BR23) -> 534.9 | BT23: 122.4 | BU23: 101.5 | BV23: 52.9 | BW23: 8 | BX23: =SUM(BT23:BW23) -> 284.8 | BY23: =46.9 -> 46.9 | BZ23: =BU23*(1+BZ253) -> 30.45 | CA23: =BV23*(1+CA253) -> 21.16 | CB23: =BW23*(1+CB253) -> 12.8 | CC23: =SUM(BY23:CB23) -> 111.31 | CD23: =CC23*(1+CD253) -> 66.786 | CE23: =CD23*(1+CE253) -> 53.4288 | CF23: =CE23*(1+CF253) -> 48.08592 | CG23: =CF23*(1+CG253) -> 43.277328 | CH23: =CG23*(1+CH253) -> 38.949595
H24: ex-US (EU May-19) | L24: 7.4 | M24: 12.5 | N24: 15.9 | O24: 17.5 | P24: 53.3 | Q24: 16.9 | R24: 18.3 | S24: 14.1 | T24: 20.5 | U24: =SUM(Q24:T24) -> 69.8 | V24: 22.2 | W24: 25.1 | X24: 26.9 | Y24: 30.6 | Z24: =SUM(V24:Y24) -> 104.8 | AA24: 32.6 | AB24: 33.8 | AC24: 40 | AD24: 35.4 | AE24: =SUM(AA24:AD24) -> 141.8 | AF24: 43.3 | AG24: 37.1 | AH24: 38.7 | AI24: 44.7 | AJ24: =SUM(AF24:AI24) -> 163.8 | AK24: 43.5 | AL24: 46.7 | AM24: 42.8 | AN24: 53.9 | AO24: =SUM(AK24:AN24) -> 186.9 | AP24: 52.1 | AQ24: 59.6 | AR24: 56.8 | AS24: 59.4 | AT24: =SUM(AP24:AS24) -> 227.9 | AU24: 54.1 | AV24: 59.5 | AW24: 55.6 | AX24: 68.1 | AY24: =SUM(AU24:AX24) -> 237.3 | AZ24: 61.2 | BA24: 65.7 | BB24: 62.1 | BC24: 74.1 | BD24: =SUM(AZ24:BC24) -> 263.1 | BE24: 71.3 | BF24: 67.9 | BG24: 71 | BH24: 75.8 | BI24: =SUM(BE24:BH24) -> 286 | BJ24: 65.2 | BK24: 70.7 | BL24: 68.1 | BM24: 77.9 | BN24: =SUM(BJ24:BM24) -> 281.9 | BO24: 71.5 | BP24: 81.1 | BQ24: 79.3 | BR24: 87.9 | BS24: =SUM(BO24:BR24) -> 319.8 | BT24: 73.8 | BU24: 85.1 | BV24: 84.1 | BW24: 90.3 | BX24: =SUM(BT24:BW24) -> 333.3 | BY24: =83.7 -> 83.7 | BZ24: =BU24*(1+BZ254) -> 87.653 | CA24: =BV24*(1+CA254) -> 85.782 | CB24: =BW24*(1+CB254) -> 92.106 | CC24: =SUM(BY24:CB24) -> 349.241 | CD24: =CC24*(1+CD254) -> 209.5446 | CE24: =CD24*(1+CE254) -> 52.38615 | CF24: =CE24*(1+CF254) -> 36.670305 | CG24: =CF24*(1+CG254) -> 25.669213 | CH24: =CG24*(1+CH254) -> 17.968449
H25: Cymbalta | L25: 106.8 | M25: 161.4 | N25: 182.7 | O25: 228.8 | P25: 679.7 | Q25: =Q26+Q27 -> 233.2 | R25: =R26+R27 -> 310.4 | S25: =S26+S27 -> 348.6 | T25: =T26+T27 -> 424.1 | U25: =U26+U27 -> 1316.3 | V25: =V26+V27 -> 441.8 | W25: =W26+W27 -> 519.5 | X25: =X26+X27 -> 513.2 | ... CH25: =CH26+CH27 -> 176.23155 | EX25: Cymbalta
H26: U.S. (12/11/13*) | L26: 102.4 | M26: 151.2 | N26: 170.1 | O26: 212.5 | P26: 636.2 | Q26: 205.8 | R26: 269.9 | S26: 306.5 | T26: 376.4 | U26: =SUM(Q26:T26) -> 1158.6 | V26: 386.3 | W26: 457.6 | X26: 444.3 | Y26: 547.3 | Z26: =SUM(V26:Y26) -> 1835.5 | AA26: 511.1 | AB26: 542.8 | AC26: 597.1 | AD26: 602.7 | AE26: =SUM(AA26:AD26) -> 2253.7 | AF26: 597.1 | AG26: 621.3 | AH26: 652.7 | AI26: 680.7 | AJ26: =SUM(AF26:AI26) -> 2551.8 | AK26: 650.6 | AL26: 707.9 | AM26: 643.2 | AN26: 770.3 | AO26: =SUM(AK26:AN26) -> 2772 | AP26: 691.1 | AQ26: 758.4 | AR26: 809.5 | AS26: 914.4 | AT26: =SUM(AP26:AS26) -> 3173.4 | AU26: 857.6 | AV26: 955 | AW26: 964.6 | AX26: 1140.6 | AY26: =SUM(AU26:AX26) -> 3917.8 | AZ26: 1056.9 | BA26: 1217.4 | BB26: 1109.2 | BC26: 577.3 | BD26: =SUM(AZ26:BC26) -> 3960.8 | BE26: 176 | BF26: 112.3 | BG26: 69.4 | BH26: 62.8 | BI26: =SUM(BE26:BH26) -> 420.5 | BJ26: 54.4 | BK26: 40.5 | BL26: 24.6 | BM26: 25.1 | BN26: =SUM(BJ26:BM26) -> 144.6 | BO26: 23.3 | BP26: 60.5 | BQ26: 162.3 | BR26: 23.2 | BS26: =SUM(BO26:BR26) -> 269.3 | BT26: 34.1 | BU26: 47.1 | BV26: 19.6 | BW26: 14.1 | BX26: =SUM(BT26:BW26) -> 114.9 | BY26: =12.2 -> 12.2 | BZ26: =BU26*(1+BZ256) -> 9.42 | CA26: =BV26*(1+CA256) -> 9.8 | CB26: =BW26*(1+CB256) -> 9.87 | CC26: =SUM(BY26:CB26) -> 41.29 | CD26: =CC26*(1+CD256) -> 30.9675 | CE26: =CD26*(1+CE256) -> 26.322375 | CF26: =CE26*(1+CF256) -> 23.690138 | CG26: =CF26*(1+CG256) -> 21.321124 | CH26: =CG26*(1+CH256) -> 19.189011
H27: ex-US (EU Aug-14, Japan mid-21) | L27: 4.4 | M27: 10.2 | N27: 12.6 | O27: 16.3 | P27: 43.5 | Q27: 27.4 | R27: 40.5 | S27: 42.1 | T27: 47.7 | U27: =SUM(Q27:T27) -> 157.7 | V27: 55.5 | W27: 61.9 | X27: 68.9 | Y27: 81 | Z27: =SUM(V27:Y27) -> 267.3 | AA27: 94 | AB27: 111.5 | AC27: 119.3 | AD27: 118.5 | AE27: =SUM(AA27:AD27) -> 443.3 | AF27: 112.2 | AG27: 123.15 | AH27: 137.5 | AI27: 150.1 | AJ27: =SUM(AF27:AI27) -> 522.95 | AK27: 152.6 | AL27: 159.8 | AM27: 162.8 | AN27: 212 | AO27: =SUM(AK27:AN27) -> 687.2 | AP27: 217.6 | AQ27: 245 | AR27: 259.1 | AS27: 266.6 | AT27: =SUM(AP27:AS27) -> 988.3 | AU27: 257.3 | AV27: 268.1 | AW27: 271.2 | AX27: 279.8 | AY27: =SUM(AU27:AX27) -> 1076.4 | AZ27: 271.3 | BA27: 279.8 | BB27: 266.6 | BC27: 305.9 | BD27: =SUM(AZ27:BC27) -> 1123.6 | BE27: 302.2 | BF27: 289 | BG27: 298.6 | BH27: 304.5 | BI27: =SUM(BE27:BH27) -> 1194.3 | BJ27: 232.6 | BK27: 233.6 | BL27: 218.3 | BM27: 198.5 | BN27: =SUM(BJ27:BM27) -> 883 | BO27: 175.4 | BP27: 176 | BQ27: 151.2 | BR27: 158.7 | BS27: =SUM(BO27:BR27) -> 661.3 | BT27: 140.5 | BU27: 159.6 | BV27: 163.5 | BW27: 178.7 | BX27: =SUM(BT27:BW27) -> 642.3 | BY27: =157.3 -> 157.3 | BZ27: =BU27*(1+BZ257) -> 151.62 | CA27: =BV27*(1+CA257) -> 150.42 | CB27: =BW27*(1+CB257) -> 146.534 | CC27: =SUM(BY27:CB27) -> 605.874 | CD27: =CC27*(1+CD257) -> 545.2866 | CE27: =CD27*(1+CE257) -> 408.96495 | CF27: =CE27*(1+CF257) -> 245.37897 | CG27: =CF27*(1+CG257) -> 196.30318 | CH27: =CG27*(1+CH257) -> 157.04254
H28: Prozac Family | L28: 112.4 | M28: 114.3 | N28: 112.4 | O28: 114.4 | P28: 453.5 | Q28: =Q29+Q30 -> 77.4 | R28: =R29+R30 -> 80 | S28: =S29+S30 -> 78.3 | T28: =T29+T30 -> 79.5 | U28: =U30+U29 -> 315.2 | V28: =V29+V30 -> 72.6 | W28: =W29+W30 -> 72.3 | X28: =X29+X30 -> 71.3 | Y28: =Y29+Y30 -> 72.6 | Z28: =Z30+Z29 -> 288.8 | AA28: =AA29+AA30 -> 66.2 | AB28: =AB29+AB30 -> 63.1 | AC28: =AC29+AC30 -> 64.5 | AD28: =AD29+AD30 -> 60.7 | AE28: =AE30+AE29 -> 254.5 | AF28: =AF29+AF30 -> 53 | AG28: =AG29+AG30 -> 58.09 | AH28: =AH29+AH30 -> 58.2 | AI28: =AI29+AI30 -> 60.1 | AJ28: =AJ30+AJ29 -> 229.39 | AK28: =AK29+AK30 -> 51.8 | AL28: =AL29+AL30 -> 51.3 | AM28: =AM29+AM30 -> 48.6 | AN28: =AN29+AN30 -> 54.5 | AO28: =AO30+AO29 -> 206.2 | AP28: =AP29+AP30 -> 44.4 | AQ28: =AQ29+AQ30 -> 48.9 | AR28: =AR29+AR30 -> 49.9 | AS28: =AS29+AS30 -> 45.5 | AT28: =AT30+AT29 -> 188.7 | AU28: =AU29+AU30 -> 42.7 | AV28: =AV29+AV30 -> 44.6 | AW28: =AW29+AW30 -> 44.4 | AX28: =AX29+AX30 -> 48.4 | AY28: =AY30+AY29 -> 180.1 | AZ28: =AZ29+AZ30 -> 43.2 | BA28: =BA29+BA30 -> 45.9 | BB28: =BB29+BB30 -> 43.4 | BC28: =BC29+BC30 -> 42.3 | BD28: =BD30+BD29 -> 174.8 | BE28: =BE29+BE30 -> 40.2 | BF28: =BF30+BF29 -> 42 | BG28: =BG30+BG29 -> 44.1 | BH28: =BH30+BH29 -> 43.9 | BI28: =BI30+BI29 -> 170.2 | BJ28: =BJ30+BJ29 -> 37.2 | BK28: =BK30+BK29 -> 38.7 | BL28: =BL30+BL29 -> 39.9 | BM28: =BM30+BM29 -> 38.8 | ... CH28: =CH30+CH29 -> 106.51695 | EX28: Prozac Family
H29: U.S. | L29: 57.2 | M29: 59.1 | N29: 65.5 | O29: 67.4 | P29: 249.2 | Q29: 36.2 | R29: 39.5 | S29: 37.8 | T29: 39.4 | U29: =SUM(Q29:T29) -> 152.9 | V29: 35.1 | W29: 37.2 | X29: 34 | Y29: 37.7 | Z29: =SUM(V29:Y29) -> 144 | AA29: 32.7 | AB29: 31.2 | AC29: 32.6 | AD29: 33.8 | AE29: =SUM(AA29:AD29) -> 130.3 | AF29: 28.4 | AG29: 31.8 | AH29: 30 | AI29: 31.9 | AJ29: =SUM(AF29:AI29) -> 122.1 | AK29: 26 | AL29: 24.3 | AM29: 23.7 | AN29: 25.2 | AO29: =SUM(AK29:AN29) -> 99.2 | AP29: 20.4 | AQ29: 20.5 | AR29: 22.6 | AS29: 19.2 | AT29: =SUM(AP29:AS29) -> 82.7 | AU29: 17.7 | AV29: 17.8 | AW29: 20.1 | AX29: 21 | AY29: =SUM(AU29:AX29) -> 76.6 | AZ29: 18.6 | BA29: 20.5 | BB29: 19.3 | BC29: 17.2 | BD29: =SUM(AZ29:BC29) -> 75.6 | BE29: 16.3 | BF29: 17.2 | BG29: 18.9 | BH29: 18.9 | BI29: =SUM(BE29:BH29) -> 71.3 | BJ29: 14.4 | BK29: 16.4 | BL29: 19.6 | BM29: 18.5 | BN29: =SUM(BJ29:BM29) -> 68.9 | BO29: 17.7 | BP29: 17.6 | BQ29: 17.8 | BR29: 45.7 | BS29: =SUM(BO29:BR29) -> 98.8 | BT29: 25.8 | BU29: 22.4 | BV29: 14.6 | BW29: 17.8 | BX29: =SUM(BT29:BW29) -> 80.6 | BY29: =19.5 -> 19.5 | BZ29: =BU29*(1+BZ259) -> 19.712 | CA29: =BV29*(1+CA259) -> 14.6 | CB29: =BW29*(1+CB259) -> 17.8 | CC29: =SUM(BY29:CB29) -> 71.612 | CD29: =CC29*(1+CD259) -> 64.4508 | CE29: =CD29*(1+CE259) -> 58.00572 | CF29: =CE29*(1+CF259) -> 52.205148 | CG29: =CF29*(1+CG259) -> 46.984633 | CH29: =CG29*(1+CH259) -> 42.28617
H30: ex-US | L30: 55.2 | M30: 55.2 | N30: 46.9 | O30: 47 | P30: 204.3 | Q30: 41.2 | R30: 40.5 | S30: 40.5 | T30: 40.1 | U30: =SUM(Q30:T30) -> 162.3 | V30: 37.5 | W30: 35.1 | X30: 37.3 | Y30: 34.9 | Z30: =SUM(V30:Y30) -> 144.8 | AA30: 33.5 | AB30: 31.9 | AC30: 31.9 | AD30: 26.9 | AE30: =SUM(AA30:AD30) -> 124.2 | AF30: 24.6 | AG30: 26.29 | AH30: 28.2 | AI30: 28.2 | AJ30: =SUM(AF30:AI30) -> 107.29 | AK30: 25.8 | AL30: 27 | AM30: 24.9 | AN30: 29.3 | AO30: =SUM(AK30:AN30) -> 107 | AP30: 24 | AQ30: 28.4 | AR30: 27.3 | AS30: 26.3 | AT30: =SUM(AP30:AS30) -> 106 | AU30: 25 | AV30: 26.8 | AW30: 24.3 | AX30: 27.4 | AY30: =SUM(AU30:AX30) -> 103.5 | AZ30: 24.6 | BA30: 25.4 | BB30: 24.1 | BC30: 25.1 | BD30: =SUM(AZ30:BC30) -> 99.2 | BE30: 23.9 | BF30: 24.8 | BG30: 25.2 | BH30: 25 | BI30: =SUM(BE30:BH30) -> 98.9 | BJ30: 22.8 | BK30: 22.3 | BL30: 20.3 | BM30: 20.3 | BN30: =SUM(BJ30:BM30) -> 85.7 | BO30: 20.7 | BP30: 21.2 | BQ30: 21.6 | BR30: 19.2 | BS30: =SUM(BO30:BR30) -> 82.7 | BT30: 24 | BU30: 18.8 | BV30: 20.7 | BW30: 23.8 | BX30: =SUM(BT30:BW30) -> 87.3 | BY30: =23.5 -> 23.5 | BZ30: =BU30*(1+BZ260) -> 18.424 | CA30: =BV30*(1+CA260) -> 19.665 | CB30: =BW30*(1+CB260) -> 21.42 | CC30: =SUM(BY30:CB30) -> 83.009 | CD30: =CC30*(1+CD260) -> 78.85855 | CE30: =CD30*(1+CE260) -> 74.915622 | CF30: =CE30*(1+CF260) -> 71.169841 | CG30: =CF30*(1+CG260) -> 67.611349 | CH30: =CG30*(1+CH260) -> 64.230782
H31: Other | L31: 0.9 | M31: 0.9 | N31: 1.4 | O31: 0.8 | P31: 4 | Q31: =Q32+Q33 -> -0.3 | R31: =R32+R33 -> -1.1 | S31: =S32+S33 -> -0.25 | T31: =T32+T33 -> 0.3 | U31: =U32+U33 -> -1.35 | V31: =V32+V33 -> 0.1 | W31: =W32+W33 -> 0.6 | X31: =X32+X33 -> -8.1 | ... CH31: =CH32+CH33 -> 30.99 | EX31: Other Neuro
H32: U.S. | L32: 0 | M32: 0 | N32: 0.4 | O32: -0.2 | P32: 0.2 | Q32: -0.1 | R32: -0.2 | S32: -0.05 | T32: 0 | U32: =SUM(Q32:T32) -> -0.35 | V32: 0 | W32: 0 | X32: 0 | Y32: 0 | Z32: =SUM(V32:Y32) -> 0 | AA32: 0 | AB32: 0 | AC32: 0 | AD32: 0 | AE32: =SUM(AA32:AD32) -> 0 | AF32: 0 | AG32: 0 | AH32: 0 | AI32: 0 | AJ32: =SUM(AF32:AI32) -> 0 | AK32: 0 | AL32: 0 | AM32: 0 | AN32: 0 | AO32: =SUM(AK32:AN32) -> 0 | AP32: 0 | AQ32: 0 | AR32: 0 | AS32: 0 | AT32: =SUM(AP32:AS32) -> 0 | AU32: =AU16-AU20-AU23-AU26-AU29 -> 13 | AV32: =AV16-AV20-AV23-AV26-AV29 -> 13.1 | AW32: =AW16-AW20-AW23-AW26-AW29 -> 4.9 | AX32: =AX16-AX20-AX23-AX26-AX29 -> 3.3 | AY32: =SUM(AU32:AX32) -> 34.3 | AZ32: =AZ16-AZ20-AZ23-AZ26-AZ29 -> 2.6 | BA32: =BA16-BA20-BA23-BA26-BA29 -> 1.4 | BB32: =BB16-BB20-BB23-BB26-BB29 -> 1.8 | BC32: =BC16-BC20-BC23-BC26-BC29 -> 2.5 | BD32: =SUM(AZ32:BC32) -> 8.3 | BE32: =BE16-BE20-BE23-BE26-BE29 -> 1.3 | BF32: =BF16-BF20-BF23-BF26-BF29 -> 1.5 | BG32: =BG16-BG20-BG23-BG26-BG29 -> 1.3 | BH32: =BH16-BH20-BH23-BH26-BH29 -> 1.8 | BI32: =SUM(BE32:BH32) -> 5.9 | BJ32: =BJ16-BJ20-BJ23-BJ26-BJ29 -> 1.7 | BK32: =BK16-BK20-BK23-BK26-BK29 -> 1.1 | BL32: =BL16-BL20-BL23-BL26-BL29 -> 2.7 | BM32: =BM16-BM20-BM23-BM26-BM29 -> 4.7 | BN32: =SUM(BJ32:BM32) -> 10.2 | BO32: =BO16-BO20-BO23-BO26-BO29 -> 2.6 | BP32: =BP16-BP20-BP23-BP26-BP29 -> 4.3 | BQ32: =BQ16-BQ20-BQ23-BQ26-BQ29 -> 5.3 | BR32: =BR16-BR20-BR23-BR26-BR29 -> 4.9 | BS32: =SUM(BO32:BR32) -> 17.1 | BT32: =BT16-BT20-BT23-BT26-BT29 -> 8.8 | BU32: =BU16-BU20-BU23-BU26-BU29 -> 8.2 | BV32: =BV16-BV20-BV23-BV26-BV29 -> 8.7 | BW32: =BW16-BW20-BW23-BW26-BW29 -> 9.5 | BX32: =SUM(BT32:BW32) -> 35.2 | BY32: =BY16-BY20-BY23-BY26-BY29 -> 3.8 | BZ32: =BU32*(1+BZ262) -> 4.92 | CA32: =BV32*(1+CA262) -> 5.22 | CB32: =BW32*(1+CB262) -> 4.75 | CC32: =SUM(BY32:CB32) -> 18.69 | CD32: =CC32*(1+CD262) -> 18.69 | CE32: =CD32*(1+CE262) -> 18.69 | CF32: =CE32*(1+CF262) -> 18.69 | CG32: =CF32*(1+CG262) -> 18.69 | CH32: =CG32*(1+CH262) -> 18.69
H33: ex-US | L33: 0.9 | M33: 0.9 | N33: 1 | O33: 1 | P33: 3.8 | Q33: -0.2 | R33: -0.9 | S33: -0.2 | T33: 0.3 | U33: =SUM(Q33:T33) -> -1 | V33: 0.1 | W33: 0.6 | X33: -8.1 | Y33: 0 | Z33: =SUM(V33:Y33) -> -7.4 | AA33: 0 | AB33: 0.3 | AC33: 0.1 | AD33: 0 | AE33: =SUM(AA33:AD33) -> 0.4 | AF33: 0 | AG33: 0 | AH33: 0.1 | AI33: 0.2 | AJ33: =SUM(AF33:AI33) -> 0.3 | AK33: 0 | AL33: 0 | AM33: 0 | AN33: 0 | AO33: =SUM(AK33:AN33) -> 0 | AP33: 13.9 | AQ33: 13.9 | AR33: 13.3 | AS33: 12.8 | AT33: =SUM(AP33:AS33) -> 53.9 | AU33: =AU17-AU21-AU24-AU27-AU30 -> 13.1 | AV33: =AV17-AV21-AV24-AV27-AV30 -> 13.7 | AW33: =AW17-AW21-AW24-AW27-AW30 -> 13.6 | AX33: =AX17-AX21-AX24-AX27-AX30 -> 12.2 | AY33: =SUM(AU33:AX33) -> 52.6 | AZ33: =AZ17-AZ21-AZ24-AZ27-AZ30 -> 23.3 | BA33: =BA17-BA21-BA24-BA27-BA30 -> 8.5 | BB33: =BB17-BB21-BB24-BB27-BB30 -> 5.2 | BC33: =BC17-BC21-BC24-BC27-BC30 -> 7.5 | BD33: =SUM(AZ33:BC33) -> 44.5 | BE33: =BE17-BE21-BE24-BE27-BE30 -> 7.2 | BF33: =BF17-BF21-BF24-BF27-BF30 -> 7.7 | BG33: =BG17-BG21-BG24-BG27-BG30 -> 7.2 | BH33: =BH17-BH21-BH24-BH27-BH30 -> 7.5 | BI33: =SUM(BE33:BH33) -> 29.6 | BJ33: =BJ17-BJ21-BJ24-BJ27-BJ30 -> 6.2 | BK33: =BK17-BK21-BK24-BK27-BK30 -> 4.5 | BL33: =BL17-BL21-BL24-BL27-BL30 -> 4.2 | BM33: =BM17-BM21-BM24-BM27-BM30 -> 4 | BN33: =SUM(BJ33:BM33) -> 18.9 | BO33: =BO17-BO21-BO24-BO27-BO30 -> 3.1 | BP33: =BP17-BP21-BP24-BP27-BP30 -> 2.8 | BQ33: =BQ17-BQ21-BQ24-BQ27-BQ30 -> 2.6 | BR33: =BR17-BR21-BR24-BR27-BR30 -> 2.5 | BS33: =SUM(BO33:BR33) -> 11 | BT33: =BT17-BT21-BT24-BT27-BT30 -> 2.5 | BU33: =BU17-BU21-BU24-BU27-BU30 -> 3.2 | BV33: =BV17-BV21-BV24-BV27-BV30 -> 3 | BW33: =BW17-BW21-BW24-BW27-BW30 -> 2.9 | BX33: =SUM(BT33:BW33) -> 11.6 | BY33: =BY17-BY21-BY24-BY27-BY30 -> 3.2 | BZ33: =BU33*(1+BZ263) -> 3.2 | CA33: =BV33*(1+CA263) -> 3 | CB33: =BW33*(1+CB263) -> 2.9 | CC33: =SUM(BY33:CB33) -> 12.3 | CD33: =CC33*(1+CD263) -> 12.3 | CE33: =CD33*(1+CE263) -> 12.3 | CF33: =CE33*(1+CF263) -> 12.3 | CG33: =CF33*(1+CG263) -> 12.3 | CH33: =CG33*(1+CH263) -> 12.3
H34: Amyvid | AU34: =AU35+AU36 -> 0 | AV34: =AV35+AV36 -> 0.3 | AW34: =AW35+AW36 -> 0.9 | AX34: =AX35+AX36 -> 0.9 | AY34: =AY36+AY35 -> 2.1 | AZ34: =AZ35+AZ36 -> 0.5 | BA34: =BA35+BA36 -> 0.8 | BB34: =BB35+BB36 -> 0.9 | BC34: =BC35+BC36 -> 0 | BD34: =BD36+BD35 -> 2.2 | BE34: =BE35+BE36 -> 0.5
H35: U.S. | AU35: 0 | AV35: 0 | AW35: 0.1 | AX35: 2 | AY35: =SUM(AU35:AX35) -> 2.1 | AZ35: 0.5 | BA35: 0.7 | BB35: 0.8 | BC35: 0 | BD35: =SUM(AZ35:BC35) -> 2 | BE35: 0.5
H36: ex-US | AU36: 0 | AV36: 0.3 | AW36: 0.8 | AX36: -1.1 | AY36: =SUM(AU36:AX36) -> 0 | AZ36: 0 | BA36: 0.1 | BB36: 0.1 | BC36: 0 | BD36: =SUM(AZ36:BC36) -> 0.2 | BE36: 0
H37: Symbyax | L37: 12.6 | M37: 14.9 | N37: 13 | O37: 13.4 | P37: 53.9 | Q37: =Q38+Q39 -> 13.5 | R37: =R38+R39 -> 11 | S37: =S38+S39 -> 14 | T37: =T38+T39 -> 15.3 | U37: =U38+U39 -> 53.8 | V37: =V38+V39 -> 14.4 | W37: =W38+W39 -> 12.4 | X37: =X38+X39 -> 13.5 | ... AY37: =AY38+AY39 -> 37.3
H38: U.S. (3/24/17) | L38: 12.4 | M38: 14.5 | N38: 12.7 | O38: 13 | P38: 52.6 | Q38: 13 | R38: 10.6 | S38: 13.6 | T38: 14.7 | U38: =SUM(Q38:T38) -> 51.9 | V38: 13.8 | W38: 11.8 | X38: 12.9 | Y38: 17.9 | Z38: =SUM(V38:Y38) -> 56.4 | AA38: 16.1 | AB38: 13.5 | AC38: 22.7 | AD38: 18.4 | AE38: =SUM(AA38:AD38) -> 70.7 | AF38: 17.6 | AG38: 20.5 | AH38: 20.4 | AI38: 23.4 | AJ38: =SUM(AF38:AI38) -> 81.9 | AK38: 14.3 | AL38: 20.4 | AM38: 18.2 | AN38: 20.4 | AO38: =SUM(AK38:AN38) -> 73.3 | AP38: 16.9 | AQ38: 20.5 | AR38: 19.6 | AS38: 16.4 | AT38: =SUM(AP38:AS38) -> 73.4 | AU38: 13 | AV38: 13.1 | AW38: 4.8 | AX38: 1.4 | AY38: =SUM(AU38:AX38) -> 32.3
H39: ex-US | L39: 0.2 | M39: 0.4 | N39: 0.3 | O39: 0.4 | P39: 1.3 | Q39: 0.5 | R39: 0.4 | S39: 0.4 | T39: 0.6 | U39: =SUM(Q39:T39) -> 1.9 | V39: 0.6 | W39: 0.6 | X39: 0.6 | Y39: 0.7 | Z39: =SUM(V39:Y39) -> 2.5 | AA39: 0.7 | AB39: 0.8 | AC39: 0.9 | AD39: 0.8 | AE39: =SUM(AA39:AD39) -> 3.2 | AF39: 0.6 | AG39: 0.68 | AH39: 1 | AI39: 0.9 | AJ39: =SUM(AF39:AI39) -> 3.18 | AK39: 0.8 | AL39: 0.8 | AM39: 1.2 | AN39: 1.2 | AO39: =SUM(AK39:AN39) -> 4 | AP39: 0.7 | AQ39: 1.3 | AR39: 1.2 | AS39: 0.9 | AT39: =SUM(AP39:AS39) -> 4.1 | AU39: 1.2 | AV39: 1 | AW39: 1.5 | AX39: 1.3 | AY39: =SUM(AU39:AX39) -> 5
H40: Yentreve | L40: 4.9 | M40: 4.8 | N40: 3.6 | O40: 4.8 | P40: 18.1 | Q40: =Q41+Q42 -> 4.8 | R40: =R41+R42 -> 4.7 | S40: =S41+S42 -> 5 | T40: =T41+T42 -> 5.5 | U40: =U41+U42 -> 20 | V40: =V41+V42 -> 5.4 | W40: =W41+W42 -> 5.7 | X40: =X41+X42 -> 5.7 | ... AO40: =AO41+AO42 -> 20
H41: U.S. | AE41: =Z41*(1+AE271) -> 0 | AJ41: =AE41*(1+AJ271) -> 0 | AO41: =AJ41*(1+AO271) -> 0
H42: ex-US | L42: 4.9 | M42: 4.8 | N42: 3.6 | O42: 4.8 | P42: 18.1 | Q42: 4.8 | R42: 4.7 | S42: 5 | T42: 5.5 | U42: =SUM(Q42:T42) -> 20 | V42: 5.4 | W42: 5.7 | X42: 5.7 | Y42: 5.5 | Z42: =SUM(V42:Y42) -> 22.3 | AA42: 5.4 | AB42: 7.2 | AC42: 6.3 | AD42: 6.2 | AE42: =SUM(AA42:AD42) -> 25.1 | AF42: 6.2 | AG42: 5.49 | AH42: 4.4 | AI42: 5.5 | AJ42: =SUM(AF42:AI42) -> 21.59 | AK42: 5.5 | AL42: 4.7 | AM42: 4.5 | AN42: 5.3 | AO42: =SUM(AK42:AN42) -> 20
H43: Permax | L43: 32.3 | M43: 31 | N43: 25.9 | O43: 27.5 | P43: 116.7 | Q43: =Q44+Q45 -> 18.8 | R43: =R44+R45 -> 22 | S43: =S44+S45 -> 19.4 | T43: =T44+T45 -> 21.7 | U43: =U44+U45 -> 81.9 | V43: =V44+V45 -> 15.3 | W43: =W44+W45 -> 15.5 | X43: =X44+X45 -> 11.4 | ... AO43: =AO44+AO45 -> 31.8
H44: U.S. | L44: 1.5 | M44: 0.4 | N44: 0 | O44: 0 | P44: 1.9 | Q44: 0 | R44: 0 | S44: 0 | T44: 0 | U44: =SUM(Q44:T44) -> 0 | V44: 0 | W44: 0 | X44: 0 | Y44: =T44*(1+Y274) -> 0 | Z44: =SUM(V44:Y44) -> 0 | AA44: 0 | AB44: 0 | AC44: 0 | AD44: 0 | AE44: =SUM(AA44:AD44) -> 0 | AF44: 0 | AG44: 0 | AH44: 0 | AI44: 0.7 | AJ44: =SUM(AF44:AI44) -> 0.7 | AK44: 0 | AL44: 0 | AM44: 0 | AN44: 0 | AO44: =SUM(AK44:AN44) -> 0
H45: ex-US | L45: 30.8 | M45: 30.6 | N45: 25.9 | O45: 27.5 | P45: 114.8 | Q45: 18.8 | R45: 22 | S45: 19.4 | T45: 21.7 | U45: =SUM(Q45:T45) -> 81.9 | V45: 15.3 | W45: 15.5 | X45: 11.4 | Y45: 13.2 | Z45: =SUM(V45:Y45) -> 55.4 | AA45: 9.4 | AB45: 12.4 | AC45: 10.5 | AD45: 12.2 | AE45: =SUM(AA45:AD45) -> 44.5 | AF45: 9 | AG45: 10.52 | AH45: 9.4 | AI45: 10.7 | AJ45: =SUM(AF45:AI45) -> 39.62 | AK45: 7.2 | AL45: 8.8 | AM45: 8.1 | AN45: 7.7 | AO45: =SUM(AK45:AN45) -> 31.8
H47: Endocrine | L47: 1144.7 | M47: 1141.6 | N47: 1116 | O47: 1234.5 | P47: 4640.2 | Q47: =Q50+Q53+Q83+Q56+Q59+Q62+Q80+Q95 -> 1228.8 | R47: =R50+R53+R83+R56+R59+R62+R80+R95 -> 1231.1 | S47: =S50+S53+S83+S56+S59+S62+S80+S95 -> 1220.9 | T47: =T50+T53+T83+T56+T59+T62+T80+T95 -> 1333.4 | U47: =U50+U53+U83+U56+U59+U62+U80+U95 -> 5014.2 | V47: =V50+V53+V83+V56+V59+V62+V80+V95 -> 1265.8 | W47: =W50+W53+W83+W56+W59+W62+W80+W95 -> 1360.4 | X47: =X50+X53+X83+X56+X59+X62+X80+X95 -> 1363.8 | ... AO47: =AO50+AO53+AO83+AO56+AO59+AO62+AO80+AO95 -> 5873.3 | AP47: =AP50+AP53+AP83+AP56+AP59+AP62+AP80+AP95+AP65 -> 1528.1 | AQ47: =AQ50+AQ53+AQ83+AQ56+AQ59+AQ62+AQ80+AQ95+AQ65 -> 1618.8 | AR47: =AR50+AR53+AR83+AR56+AR59+AR62+AR80+AR95+AR65 -> 1629.7 | AS47: =AS50+AS53+AS83+AS56+AS59+AS62+AS80+AS95+AS65 -> 1771.7 | AT47: =AT50+AT53+AT83+AT56+AT59+AT62+AT80+AT95+AT65 -> 6548.3 | AU47: =AU48+AU49 -> 1689.4 | AV47: =AV48+AV49 -> 1701.9 | AW47: =AW48+AW49 -> 1643.9 | AX47: =AX48+AX49 -> 1772.3 | AY47: =AY48+AY49 -> 6807.5 | AZ47: =AZ48+AZ49 -> 1725 | BA47: =BA48+BA49 -> 1784.3 | BB47: =BB48+BB49 -> 1764.7 | ... CH47: =CH48+CH49 -> 12724.583 | EX47: Endocrine
H48: U.S. | L48: 677.1 | M48: 650.8 | N48: 637.9 | O48: 729.2 | P48: 2698.4 | Q48: =Q51+Q54+Q88+Q57+Q60+Q63+Q81+Q102 -> 760.2 | R48: =R51+R54+R88+R57+R60+R63+R81+R102 -> 720.5 | S48: =S51+S54+S88+S57+S60+S63+S81+S102 -> 724.8 | T48: =T51+T54+T88+T57+T60+T63+T81+T102 -> 804.7 | U48: =U51+U54+U88+U57+U60+U63+U81+U102 -> 3010.2 | V48: =V51+V54+V88+V57+V60+V63+V81+V102 -> 757 | W48: =W51+W54+W88+W57+W60+W63+W81+W102 -> 786.1 | X48: =X51+X54+X88+X57+X60+X63+X81+X102 -> 796.3 | ... Z48: =Z51+Z54+Z88+Z57+Z60+Z63+Z81+Z102 -> 3194.8 | AA48: =AA51+AA54+AA84+AA57+AA60+AA63+AA81+AA96 -> 695.5 | AB48: =AB51+AB54+AB84+AB57+AB60+AB63+AB81+AB96 -> 723.1 | AC48: =AC51+AC54+AC84+AC57+AC60+AC63+AC81+AC96 -> 699.3 | AD48: =AD51+AD54+AD84+AD57+AD60+AD63+AD81+AD96 -> 755.8 | AE48: =SUM(AA48:AD48) -> 2873.7 | AF48: =AF51+AF54+AF84+AF57+AF60+AF63+AF81+AF96 -> 736.1 | AG48: =AG51+AG54+AG84+AG57+AG60+AG63+AG81+AG96 -> 757.49 | AH48: =AH51+AH54+AH84+AH57+AH60+AH63+AH81+AH96 -> 800.2 | AI48: =AI51+AI54+AI84+AI57+AI60+AI63+AI81+AI96 -> 804.8 | AJ48: =SUM(AF48:AI48) -> 3098.59 | AK48: =AK51+AK54+AK84+AK57+AK60+AK63+AK81+AK96 -> 760.4 | AL48: =AL51+AL54+AL84+AL57+AL60+AL63+AL81+AL96 -> 791.2 | AM48: =AM51+AM54+AM84+AM57+AM60+AM63+AM81+AM96 -> 768.9 | AN48: =AN51+AN54+AN84+AN57+AN60+AN63+AN81+AN96 -> 827.1 | AO48: =SUM(AK48:AN48) -> 3147.6 | AP48: =AP51+AP54+AP84+AP57+AP60+AP63+AP81+AP96+AP66 -> 792 | AQ48: =AQ51+AQ54+AQ84+AQ57+AQ60+AQ63+AQ81+AQ96+AQ66 -> 841.9 | AR48: =AR51+AR54+AR84+AR57+AR60+AR63+AR81+AR96+AR66 -> 851.2 | AS48: =AS51+AS54+AS84+AS57+AS60+AS63+AS81+AS96+AS66 -> 963.4 | AT48: =AT51+AT54+AT84+AT57+AT60+AT63+AT81+AT96+AT66 -> 3448.5 | AU48: 929.3 | AV48: 905 | AW48: 877.5 | AX48: 900 | AY48: =AY51+AY54+AY57+AY60+AY63+AY81+AY66+AY69 -> 3611.8 | AZ48: 933.2 | BA48: 971.8 | BB48: 979.3 | BC48: 1150.3 | BD48: =BD51+BD54+BD57+BD60+BD63+BD81+BD66+BD69 -> 4034.6 | BE48: 831.3 | BF48: 925.8 | BG48: 864.9 | BH48: 990 | BI48: =BI51+BI54+BI57+BI60+BI63+BI81+BI66+BI69+BI75+BI72 -> 3612 | BJ48: 899.5 | BK48: 915 | BL48: 1032.8 | BM48: 1162 | BN48: =BN51+BN54+BN57+BN60+BN63+BN81+BN66+BN69+BN75+BN72+BN78 -> 4009.3 | BO48: 1029.9 | BP48: 1136.8 | BQ48: 1165.3 | BR48: 1499.9 | BS48: =BS51+BS54+BS57+BS60+BS63+BS81+BS66+BS69+BS75+BS72+BS78 -> 4831.9 | BT48: 1316.9 | BU48: 1552.1 | BV48: 1624.4 | BW48: 1879.6 | BX48: =BX51+BX54+BX57+BX60+BX63+BX81+BX66+BX69+BX75+BX72+BX78 -> 6373 | BY48: =1715.9 -> 1715.9 | BZ48: =BZ51+BZ54+BZ57+BZ60+BZ63+BZ81+BZ66+BZ69+BZ75+BZ72+BZ78 -> 1846.338 | CA48: =CA51+CA54+CA57+CA60+CA63+CA81+CA66+CA69+CA75+CA72+CA78 -> 1958.382 | CB48: =CB51+CB54+CB57+CB60+CB63+CB81+CB66+CB69+CB75+CB72+CB78 -> 2109.893 | CC48: =CC51+CC54+CC57+CC60+CC63+CC81+CC66+CC69+CC75+CC72+CC78 -> 7630.513 | CD48: =CD51+CD54+CD57+CD60+CD63+CD81+CD66+CD69+CD75+CD72+CD78 -> 8229.7317 | CE48: =CE51+CE54+CE57+CE60+CE63+CE81+CE66+CE69+CE75+CE72+CE78 -> 8404.7991 | CF48: =CF51+CF54+CF57+CF60+CF63+CF81+CF66+CF69+CF75+CF72+CF78 -> 8460.0121 | CG48: =CG51+CG54+CG57+CG60+CG63+CG81+CG66+CG69+CG75+CG72+CG78 -> 8428.1227 | CH48: =CH51+CH54+CH57+CH60+CH63+CH81+CH66+CH69+CH75+CH72+CH78 -> 8331.3777
H49: ex-US | L49: 467.6 | M49: 490.8 | N49: 478.1 | O49: 505.3 | P49: 1941.8 | Q49: =Q52+Q55+Q91+Q58+Q61+Q64+Q82+Q103 -> 468.6 | R49: =R52+R55+R91+R58+R61+R64+R82+R103 -> 510.6 | S49: =S52+S55+S91+S58+S61+S64+S82+S103 -> 496.1 | T49: =T52+T55+T91+T58+T61+T64+T82+T103 -> 528.7 | U49: =U52+U55+U91+U58+U61+U64+U82+U103 -> 2004 | V49: =V52+V55+V91+V58+V61+V64+V82+V103 -> 508.8 | W49: =W52+W55+W91+W58+W61+W64+W82+W103 -> 574.3 | X49: =X52+X55+X91+X58+X61+X64+X82+X103 -> 567.5 | ... AD49: =AD52+AD55+AD91+AD58+AD61+AD64+AD82+AD103 -> 638.8 | AE49: =SUM(AA49:AD49) -> 2619.7 | AF49: =AF52+AF55+AF91+AF58+AF61+AF64+AF82+AF103 -> 590.1 | AG49: =AG52+AG55+AG91+AG58+AG61+AG64+AG82+AG103 -> 631.65 | AH49: =AH52+AH55+AH91+AH58+AH61+AH64+AH82+AH103 -> 648.5 | AI49: =AI52+AI55+AI91+AI58+AI61+AI64+AI82+AI103 -> 708.5 | AJ49: =SUM(AF49:AI49) -> 2578.75 | AK49: =AK52+AK55+AK91+AK58+AK61+AK64+AK82+AK103 -> 645 | AL49: =AL52+AL55+AL91+AL58+AL61+AL64+AL82+AL103 -> 664.5 | AM49: =AM52+AM55+AM91+AM58+AM61+AM64+AM82+AM103 -> 678 | AN49: =AN52+AN55+AN91+AN58+AN61+AN64+AN82+AN103 -> 738.2 | AO49: =SUM(AK49:AN49) -> 2725.7 | AP49: =AP52+AP55+AP91+AP58+AP61+AP64+AP82+AP103+AP67 -> 736.1 | AQ49: =AQ52+AQ55+AQ91+AQ58+AQ61+AQ64+AQ82+AQ103+AQ67 -> 776.9 | AR49: =AR52+AR55+AR91+AR58+AR61+AR64+AR82+AR103+AR67 -> 778.5 | AS49: =AS52+AS55+AS91+AS58+AS61+AS64+AS82+AS103+AS67 -> 808.3 | AT49: =AT52+AT55+AT91+AT58+AT61+AT64+AT82+AT103+AT67 -> 3099.8 | AU49: 760.1 | AV49: 796.9 | AW49: 766.4 | AX49: 872.3 | AY49: =AY52+AY55+AY58+AY61+AY64+AY82+AY67+AY70 -> 3195.7 | AZ49: 791.8 | BA49: 812.5 | BB49: 785.4 | BC49: 880.2 | BD49: =BD52+BD55+BD58+BD61+BD64+BD82+BD67+BD70 -> 3269.9 | BE49: 807.9 | BF49: 813.8 | BG49: 843.4 | BH49: 862 | BI49: =BI52+BI55+BI58+BI61+BI64+BI82+BI67+BI70+BI76+BI73 -> 3327.1 | BJ49: 726.8 | BK49: 722.9 | BL49: 753.6 | BM49: 824.2 | BN49: =BN52+BN55+BN58+BN61+BN64+BN82+BN67+BN70+BN76+BN73+BN79 -> 3027.5 | BO49: 726.8 | BP49: 821.6 | BQ49: 810.5 | BR49: 892 | BS49: =BS52+BS55+BS58+BS61+BS64+BS82+BS67+BS70+BS76+BS73+BS79 -> 3250.9 | BT49: 806.2 | BU49: 939.2 | BV49: 936.3 | BW49: 1030.6 | BX49: =BX52+BX55+BX58+BX61+BX64+BX82+BX67+BX70+BX76+BX73+BX79 -> 3712.3 | BY49: =982.9 -> 982.9 | BZ49: =BZ52+BZ55+BZ58+BZ61+BZ64+BZ82+BZ67+BZ70+BZ76+BZ73+BZ79 -> 1056.86 | CA49: =CA52+CA55+CA58+CA61+CA64+CA82+CA67+CA70+CA76+CA73+CA79 -> 1077.308 | CB49: =CB52+CB55+CB58+CB61+CB64+CB82+CB67+CB70+CB76+CB73+CB79 -> 1134.133 | CC49: =CC52+CC55+CC58+CC61+CC64+CC82+CC67+CC70+CC76+CC73+CC79 -> 4251.201 | CD49: =CD52+CD55+CD58+CD61+CD64+CD82+CD67+CD70+CD76+CD73+CD79 -> 4436.5509 | CE49: =CE52+CE55+CE58+CE61+CE64+CE82+CE67+CE70+CE76+CE73+CE79 -> 4467.6289 | CF49: =CF52+CF55+CF58+CF61+CF64+CF82+CF67+CF70+CF76+CF73+CF79 -> 4532.0766 | CG49: =CG52+CG55+CG58+CG61+CG64+CG82+CG67+CG70+CG76+CG73+CG79 -> 4492.8607 | CH49: =CH52+CH55+CH58+CH61+CH64+CH82+CH67+CH70+CH76+CH73+CH79 -> 4393.2057
H50: Humulin | L50: 256.9 | M50: 249.7 | N50: 250.9 | O50: 247.2 | P50: 1004.7 | Q50: =Q51+Q52 -> 218.5 | R50: =R51+R52 -> 219.8 | S50: =S51+S52 -> 230 | T50: =T51+T52 -> 256.9 | U50: =U51+U52 -> 925.2 | V50: =V51+V52 -> 225.8 | W50: =W51+W52 -> 242.8 | X50: =X51+X52 -> 243.3 | ... CH50: =CH51+CH52 -> 1137.3212 | EX50: Humulin
H51: U.S. | L51: 104.9 | M51: 102.6 | N51: 107.7 | O51: 95.4 | P51: 410.6 | Q51: 88.2 | R51: 79.9 | S51: 96.7 | T51: 103.1 | U51: =SUM(Q51:T51) -> 367.9 | V51: 85.2 | W51: 87.7 | X51: 90.8 | Y51: 101.5 | Z51: =SUM(V51:Y51) -> 365.2 | AA51: 93.1 | AB51: 91.6 | AC51: 95.1 | AD51: 101.1 | AE51: =SUM(AA51:AD51) -> 380.9 | AF51: 99 | AG51: 95.1 | AH51: 105.8 | AI51: 102.5 | AJ51: =SUM(AF51:AI51) -> 402.4 | AK51: 114.5 | AL51: 115.3 | AM51: 120.7 | AN51: 120.4 | AO51: =SUM(AK51:AN51) -> 470.9 | AP51: 129.4 | AQ51: 146 | AR51: 142.6 | AS51: 170 | AT51: =SUM(AP51:AS51) -> 588 | AU51: 155.1 | AV51: 142.1 | AW51: 131.9 | AX51: 163 | AY51: =SUM(AU51:AX51) -> 592.1 | AZ51: 163.4 | BA51: 158.1 | BB51: 161.4 | BC51: 194.2 | BD51: =SUM(AZ51:BC51) -> 677.1 | BE51: 154.8 | BF51: 181.7 | BG51: 165.8 | BH51: 210.9 | BI51: =SUM(BE51:BH51) -> 713.2 | BJ51: 179.5 | BK51: 188.1 | BL51: 185.5 | BM51: 211.2 | BN51: =SUM(BJ51:BM51) -> 764.3 | BO51: 240.1 | BP51: 204.3 | BQ51: 195.6 | BR51: 221.8 | BS51: =SUM(BO51:BR51) -> 861.8 | BT51: 205.4 | BU51: 226.5 | BV51: 203 | BW51: 249.7 | BX51: =SUM(BT51:BW51) -> 884.6 | BY51: =221.6 -> 221.6 | BZ51: =BU51*(1+BZ281) -> 226.5 | CA51: =BV51*(1+CA281) -> 227.36 | CB51: =BW51*(1+CB281) -> 249.7 | CC51: =SUM(BY51:CB51) -> 925.16 | CD51: =CC51*(1+CD281) -> 925.16 | CE51: =CD51*(1+CE281) -> 906.6568 | CF51: =CE51*(1+CF281) -> 888.52366 | CG51: =CF51*(1+CG281) -> 870.75319 | CH51: =CG51*(1+CH281) -> 853.33813
H52: ex-US | L52: 152 | M52: 147.1 | N52: 143.2 | O52: 151.8 | P52: 594.1 | Q52: 130.3 | R52: 139.9 | S52: 133.3 | T52: 153.8 | U52: =SUM(Q52:T52) -> 557.3 | V52: 140.6 | W52: 155.1 | X52: 152.5 | Y52: 171.9 | Z52: =SUM(V52:Y52) -> 620.1 | AA52: 164.6 | AB52: 179.8 | AC52: 176.6 | AD52: 161.3 | AE52: =SUM(AA52:AD52) -> 682.3 | AF52: 141.5 | AG52: 152.98 | AH52: 154.6 | AI52: 170.5 | AJ52: =SUM(AF52:AI52) -> 619.58 | AK52: 143.3 | AL52: 150 | AM52: 157.3 | AN52: 167.5 | AO52: =SUM(AK52:AN52) -> 618.1 | AP52: 160.4 | AQ52: 165.8 | AR52: 158.9 | AS52: 175.6 | AT52: =SUM(AP52:AS52) -> 660.7 | AU52: 152.6 | AV52: 160.9 | AW52: 153.5 | AX52: 180 | AY52: =SUM(AU52:AX52) -> 647 | AZ52: 148.5 | BA52: 169.4 | BB52: 145.6 | BC52: 175.3 | BD52: =SUM(AZ52:BC52) -> 638.8 | BE52: 161.4 | BF52: 170.7 | BG52: 170.1 | BH52: 184.7 | BI52: =SUM(BE52:BH52) -> 686.9 | BJ52: 136.2 | BK52: 128.3 | BL52: 131.2 | BM52: 147.4 | BN52: =SUM(BJ52:BM52) -> 543.1 | BO52: 116.3 | BP52: 128 | BQ52: 126.4 | BR52: 133.5 | BS52: =SUM(BO52:BR52) -> 504.2 | BT52: 109.1 | BU52: 131.3 | BV52: 97.5 | BW52: 112.8 | BX52: =SUM(BT52:BW52) -> 450.7 | BY52: =104.3 -> 104.3 | BZ52: =BU52*(1+BZ282) -> 118.17 | CA52: =BV52*(1+CA282) -> 102.375 | CB52: =BW52*(1+CB282) -> 106.032 | CC52: =SUM(BY52:CB52) -> 430.877 | CD52: =CC52*(1+CD282) -> 396.40684 | CE52: =CD52*(1+CE282) -> 364.69429 | CF52: =CE52*(1+CF282) -> 335.51875 | CG52: =CF52*(1+CG282) -> 308.67725 | CH52: =CG52*(1+CH282) -> 283.98307
H53: Humalog | L53: 286.1 | M53: 296.2 | N53: 306.2 | O53: 309.1 | P53: 1197.6 | Q53: =Q54+Q55 -> 304.5 | R53: =R54+R55 -> 320.5 | S53: =S54+S55 -> 322.2 | T53: =T54+T55 -> 352.1 | U53: =SUM(U54:U55) -> 1299.3 | V53: =V54+V55 -> 339.6 | W53: =W54+W55 -> 358.4 | X53: =X54+X55 -> 362.5 | Y53: =Y54+Y55 -> 414.1 | Z53: =SUM(Z54:Z55) -> 1474.6 | AA53: =AA54+AA55 -> 407.4 | AB53: =AB54+AB55 -> 437.9 | AC53: =AC54+AC55 -> 432.6 | AD53: =AD54+AD55 -> 458 | AE53: =SUM(AE54:AE55) -> 1735.9 | AF53: =AF54+AF55 -> 450.6 | AG53: =AG54+AG55 -> 477.49 | AH53: =AH54+AH55 -> 500.2 | AI53: =AI54+AI55 -> 530.8 | AJ53: =SUM(AJ54:AJ55) -> 1959.09 | AK53: =AK54+AK55 -> 506.4 | AL53: =AL54+AL55 -> 504.7 | AM53: =AM54+AM55 -> 494 | AN53: =AN54+AN55 -> 549.2 | AO53: =SUM(AO54:AO55) -> 2054.3 | AP53: =AP54+AP55 -> 525.4 | AQ53: =AQ54+AQ55 -> 586.9 | AR53: =AR54+AR55 -> 593.2 | AS53: =AS54+AS55 -> 662 | AT53: =SUM(AT54:AT55) -> 2367.5 | AU53: =AU54+AU55 -> 590.3 | AV53: =AV54+AV55 -> 613.4 | AW53: =AW54+AW55 -> 575.8 | AX53: =AX54+AX55 -> 616 | AY53: =SUM(AY54:AY55) -> 2395.5 | AZ53: =AZ54+AZ55 -> 632.7 | BA53: =BA54+BA55 -> 628.6 | BB53: =BB54+BB55 -> 616 | BC53: =BC54+BC55 -> 733.9 | BD53: =SUM(BD54:BD55) -> 2611.2 | BE53: =BE54+BE55 -> 650 | BF53: =SUM(BF54:BF55) -> 700.1 | BG53: =SUM(BG54:BG55) -> 706.1 | BH53: =SUM(BH54:BH55) -> 729.1 | BI53: =SUM(BI54:BI55) -> 2785.3 | BJ53: =SUM(BJ54:BJ55) -> 684 | BK53: =SUM(BK54:BK55) -> 654.3 | BL53: =SUM(BL54:BL55) -> 705 | BM53: =SUM(BM54:BM55) -> 798.7 | BN53: =BN54+BN55 -> 2842 | BO53: =SUM(BO54:BO55) -> 606.3 | BP53: =SUM(BP54:BP55) -> 701.9 | BQ53: =SUM(BQ54:BQ55) -> 640.8 | BR53: =SUM(BR54:BR55) -> 819.8 | BS53: =BS54+BS55 -> 2768.8 | BT53: =SUM(BT54:BT55) -> 708.5 | BU53: =SUM(BU54:BU55) -> 678.4 | BV53: =SUM(BV54:BV55) -> 696.2 | BW53: =SUM(BW54:BW55) -> 782.2 | BX53: =BX54+BX55 -> 2865.3 | BY53: =SUM(BY54:BY55) -> 791.7 | BZ53: =SUM(BZ54:BZ55) -> 723.2 | CA53: =SUM(CA54:CA55) -> 728.197 | CB53: =SUM(CB54:CB55) -> 756.992 | CC53: =CC54+CC55 -> 3000.089 | CD53: =SUM(CD54:CD55) -> 2700.0801 | CE53: =SUM(CE54:CE55) -> 2377.1173 | CF53: =SUM(CF54:CF55) -> 2094.3941 | CG53: =SUM(CG54:CG55) -> 1846.6949 | CH53: =SUM(CH54:CH55) -> 1629.5046 | EX53: Humalog
H54: U.S. (5/7/2013) | L54: 176.1 | M54: 181.8 | N54: 194.1 | O54: 187.5 | P54: 739.5 | Q54: 188.6 | R54: 196.6 | S54: 199 | T54: 226.7 | U54: =SUM(Q54:T54) -> 810.9 | V54: 210.3 | W54: 213.1 | X54: 216.1 | Y54: 248.5 | Z54: =SUM(V54:Y54) -> 888 | AA54: 238.6 | AB54: 249.5 | AC54: 245.1 | AD54: 275.2 | AE54: =SUM(AA54:AD54) -> 1008.4 | AF54: 286.2 | AG54: 292 | AH54: 310.6 | AI54: 319.6 | AJ54: =SUM(AF54:AI54) -> 1208.4 | AK54: 309.9 | AL54: 299.7 | AM54: 288.9 | AN54: 324 | AO54: =SUM(AK54:AN54) -> 1222.5 | AP54: 303.8 | AQ54: 341.6 | AR54: 345.5 | AS54: 408 | AT54: =SUM(AP54:AS54) -> 1398.9 | AU54: 348.4 | AV54: 353.6 | AW54: 337.3 | AX54: 331.6 | AY54: =SUM(AU54:AX54) -> 1370.9 | AZ54: 378.2 | BA54: 351.9 | BB54: 357.8 | BC54: 433.5 | BD54: =SUM(AZ54:BC54) -> 1521.4 | BE54: 375.4 | BF54: 413.1 | BG54: 415 | BH54: 424.1 | BI54: =SUM(BE54:BH54) -> 1627.6 | BJ54: 420.6 | BK54: 399.7 | BL54: 440.9 | BM54: 511 | BN54: =SUM(BJ54:BM54) -> 1772.2 | BO54: 361.6 | BP54: 420 | BQ54: 378.8 | BR54: 524.8 | BS54: =SUM(BO54:BR54) -> 1685.2 | BT54: 449.1 | BU54: 390.4 | BV54: 414.9 | BW54: 463.4 | BX54: =SUM(BT54:BW54) -> 1717.8 | BY54: =504.1 -> 504.1 | BZ54: =BU54*(1+BZ284) -> 429.44 | CA54: =BV54*(1+CA284) -> 435.645 | CB54: =BW54*(1+CB284) -> 454.132 | CC54: =SUM(BY54:CB54) -> 1823.317 | CD54: =CC54*(1+CD284) -> 1640.9853 | CE54: =CD54*(1+CE284) -> 1476.8868 | CF54: =CE54*(1+CF284) -> 1329.1981 | CG54: =CF54*(1+CG284) -> 1196.2783 | CH54: =CG54*(1+CH284) -> 1076.6505
H55: ex-US (EU Nov-10, hex. Jun-15, Japan Sep-14, hex. Sep-15) | L55: 110 | M55: 114.4 | N55: 112.1 | O55: 121.6 | P55: 458.1 | Q55: 115.9 | R55: 123.9 | S55: 123.2 | T55: 125.4 | U55: =SUM(Q55:T55) -> 488.4 | V55: 129.3 | W55: 145.3 | X55: 146.4 | Y55: 165.6 | Z55: =SUM(V55:Y55) -> 586.6 | AA55: 168.8 | AB55: 188.4 | AC55: 187.5 | AD55: 182.8 | AE55: =SUM(AA55:AD55) -> 727.5 | AF55: 164.4 | AG55: 185.49 | AH55: 189.6 | AI55: 211.2 | AJ55: =SUM(AF55:AI55) -> 750.69 | AK55: 196.5 | AL55: 205 | AM55: 205.1 | AN55: 225.2 | AO55: =SUM(AK55:AN55) -> 831.8 | AP55: 221.6 | AQ55: 245.3 | AR55: 247.7 | AS55: 254 | AT55: =SUM(AP55:AS55) -> 968.6 | AU55: 241.9 | AV55: 259.8 | AW55: 238.5 | AX55: 284.4 | AY55: =SUM(AU55:AX55) -> 1024.6 | AZ55: 254.5 | BA55: 276.7 | BB55: 258.2 | BC55: 300.4 | BD55: =SUM(AZ55:BC55) -> 1089.8 | BE55: 274.6 | BF55: 287 | BG55: 291.1 | BH55: 305 | BI55: =SUM(BE55:BH55) -> 1157.7 | BJ55: 263.4 | BK55: 254.6 | BL55: 264.1 | BM55: 287.7 | BN55: =SUM(BJ55:BM55) -> 1069.8 | BO55: 244.7 | BP55: 281.9 | BQ55: 262 | BR55: 295 | BS55: =SUM(BO55:BR55) -> 1083.6 | BT55: 259.4 | BU55: 288 | BV55: 281.3 | BW55: 318.8 | BX55: =SUM(BT55:BW55) -> 1147.5 | BY55: =287.6 -> 287.6 | BZ55: =BU55*(1+BZ285) -> 293.76 | CA55: =BV55*(1+CA285) -> 292.552 | CB55: =BW55*(1+CB285) -> 302.86 | CC55: =SUM(BY55:CB55) -> 1176.772 | CD55: =CC55*(1+CD285) -> 1059.0948 | CE55: =CD55*(1+CE285) -> 900.23058 | CF55: =CE55*(1+CF285) -> 765.19599 | CG55: =CF55*(1+CG285) -> 650.41659 | CH55: =CG55*(1+CH285) -> 552.8541
H56: Evista | L56: 248.9 | M56: 261.6 | N56: 260.3 | O56: 265.3 | P56: 1036.1 | Q56: =Q57+Q58 -> 241.6 | R56: =R57+R58 -> 275.5 | S56: =S57+S58 -> 257.9 | T56: =T57+T58 -> 270.3 | U56: =U57+U58 -> 1045.3 | V56: =V57+V58 -> 263.8 | W56: =W57+W58 -> 278 | X56: =X57+X58 -> 263.2 | ... BX56: =BX57+BX58 -> 107.6 | EX56: Evista
H57: U.S. (3/2/14) | L57: 158.6 | M57: 162.9 | N57: 161.3 | O57: 170.1 | P57: 652.9 | Q57: 149.1 | R57: 175 | S57: 162.8 | T57: 177.1 | U57: =SUM(Q57:T57) -> 664 | V57: 172.1 | W57: 176.9 | X57: 169.5 | Y57: 187.7 | Z57: =SUM(V57:Y57) -> 706.2 | AA57: 171.3 | AB57: 178.3 | AC57: 170.8 | AD57: 180.1 | AE57: =SUM(AA57:AD57) -> 700.5 | AF57: 163.8 | AG57: 168.1 | AH57: 174.4 | AI57: 175.9 | AJ57: =SUM(AF57:AI57) -> 682.2 | AK57: 158.3 | AL57: 175.6 | AM57: 166.4 | AN57: 181.6 | AO57: =SUM(AK57:AN57) -> 681.9 | AP57: 174.2 | AQ57: 174.5 | AR57: 176.8 | AS57: 182 | AT57: =SUM(AP57:AS57) -> 707.5 | AU57: 171.7 | AV57: 182.4 | AW57: 168.3 | AX57: 177 | AY57: =SUM(AU57:AX57) -> 699.4 | AZ57: 171.6 | BA57: 199.3 | BB57: 191.8 | BC57: 209.3 | BD57: =SUM(AZ57:BC57) -> 772 | BE57: 98 | BF57: 55 | BG57: 34.8 | BH57: 19.4 | BI57: =SUM(BE57:BH57) -> 207.2 | BJ57: 24.2 | BK57: 13.7 | BL57: 15.5 | BM57: 8.4 | BN57: =SUM(BJ57:BM57) -> 61.8 | BO57: 2.7 | BP57: 5.1 | BQ57: 2.6 | BR57: 40 | BS57: =SUM(BO57:BR57) -> 50.4 | BT57: 2 | BU57: 0 | BV57: 1.4 | BW57: 3.6 | BX57: =SUM(BT57:BW57) -> 7
H58: ex-US (EU Aug-13, Japan Jul-18) | L58: 90.3 | M58: 98.7 | N58: 99 | O58: 95.2 | P58: 383.2 | Q58: 92.5 | R58: 100.5 | S58: 95.1 | T58: 93.2 | U58: =SUM(Q58:T58) -> 381.3 | V58: 91.7 | W58: 101.1 | X58: 93.7 | Y58: 98.1 | Z58: =SUM(V58:Y58) -> 384.6 | AA58: 89.8 | AB58: 101.5 | AC58: 94.9 | AD58: 88.9 | AE58: =SUM(AA58:AD58) -> 375.1 | AF58: 93.1 | AG58: 83.23 | AH58: 85.1 | AI58: 86.8 | AJ58: =SUM(AF58:AI58) -> 348.23 | AK58: 83.3 | AL58: 83.9 | AM58: 90.4 | AN58: 84.9 | AO58: =SUM(AK58:AN58) -> 342.5 | AP58: 92 | AQ58: 89 | AR58: 93.3 | AS58: 85.1 | AT58: =SUM(AP58:AS58) -> 359.4 | AU58: 84.5 | AV58: 83.5 | AW58: 78.7 | AX58: 64 | AY58: =SUM(AU58:AX58) -> 310.7 | AZ58: 69 | BA58: 79.4 | BB58: 63.5 | BC58: 66.6 | BD58: =SUM(AZ58:BC58) -> 278.5 | BE58: 52.1 | BF58: 53.3 | BG58: 54.7 | BH58: 52.7 | BI58: =SUM(BE58:BH58) -> 212.8 | BJ58: 42.6 | BK58: 46 | BL58: 42.5 | BM58: 44.4 | BN58: =SUM(BJ58:BM58) -> 175.5 | BO58: 30.7 | BP58: 32.7 | BQ58: 29 | BR58: 29.6 | BS58: =SUM(BO58:BR58) -> 122 | BT58: 24.4 | BU58: 26.8 | BV58: 24.2 | BW58: 25.2 | BX58: =SUM(BT58:BW58) -> 100.6
H59: Forteo | L59: 66.7 | M59: 101.9 | N59: 102.6 | O59: 117.9 | P59: 389.1 | Q59: =Q60+Q61 -> 127.1 | R59: =R60+R61 -> 146 | S59: =S60+S61 -> 149.1 | T59: =T60+T61 -> 172.1 | U59: =U60+U61 -> 594.3 | V59: =V60+V61 -> 153.4 | W59: =W60+W61 -> 177.1 | X59: =X60+X61 -> 180.5 | ... CH59: =CH60+CH61 -> 319.60153 | EX59: Forteo
H60: U.S. (assume limited gx in Aug '19) | L60: 42.2 | M60: 70.8 | N60: 70.4 | O60: 81.2 | P60: 264.6 | Q60: 87.2 | R60: 101 | S60: 104.2 | T60: 123.8 | U60: =SUM(Q60:T60) -> 416.2 | V60: 107.4 | W60: 123.5 | X60: 124.8 | Y60: 138.4 | Z60: =SUM(V60:Y60) -> 494.1 | AA60: 118.3 | AB60: 129.4 | AC60: 117 | AD60: 125.2 | AE60: =SUM(AA60:AD60) -> 489.9 | AF60: 121.8 | AG60: 132 | AH60: 135.1 | AI60: 129.4 | AJ60: =SUM(AF60:AI60) -> 518.3 | AK60: 116.9 | AL60: 131.4 | AM60: 118.7 | AN60: 132 | AO60: =SUM(AK60:AN60) -> 499 | AP60: 111.7 | AQ60: 110.2 | AR60: 110.4 | AS60: 120.8 | AT60: =SUM(AP60:AS60) -> 453.1 | AU60: 121.9 | AV60: 118.2 | AW60: 127.3 | AX60: 120.8 | AY60: =SUM(AU60:AX60) -> 488.2 | AZ60: 111.5 | BA60: 115.8 | BB60: 127.9 | BC60: 156.2 | BD60: =SUM(AZ60:BC60) -> 511.4 | BE60: 100.9 | BF60: 127.9 | BG60: 127.2 | BH60: 183 | BI60: =SUM(BE60:BH60) -> 539 | BJ60: 122 | BK60: 144.6 | BL60: 160.1 | BM60: 185.8 | BN60: =SUM(BJ60:BM60) -> 612.5 | BO60: 148.1 | BP60: 186.4 | BQ60: 206.7 | BR60: 229.3 | BS60: =SUM(BO60:BR60) -> 770.5 | BT60: 177.7 | BU60: 249.8 | BV60: 234.1 | BW60: 303.7 | BX60: =SUM(BT60:BW60) -> 965.3 | BY60: =122.1 -> 122.1 | BZ60: =BU60*(1+BZ290) -> 199.84 | CA60: =BV60*(1+CA290) -> 215.372 | CB60: =BW60*(1+CB290) -> 242.96 | CC60: =SUM(BY60:CB60) -> 780.272 | CD60: =CC60*(1+CD290) -> 624.2176 | CE60: =CD60*(1+CE290) -> 436.95232 | CF60: =CE60*(1+CF290) -> 305.86662 | CG60: =CF60*(1+CG290) -> 214.10664 | CH60: =CG60*(1+CH290) -> 149.87465
H61: ex-US (EU 2019; JPN Aug '19) | L61: 24.5 | M61: 31.1 | N61: 32.2 | O61: 36.7 | P61: 124.5 | Q61: 39.9 | R61: 45 | S61: 44.9 | T61: 48.3 | U61: =SUM(Q61:T61) -> 178.1 | V61: 46 | W61: 53.6 | X61: 55.7 | Y61: 59.8 | Z61: =SUM(V61:Y61) -> 215.1 | AA61: 66.7 | AB61: 77.1 | AC61: 75.7 | AD61: 69.3 | AE61: =SUM(AA61:AD61) -> 288.8 | AF61: 65.7 | AG61: 71.2 | AH61: 78 | AI61: 83.5 | AJ61: =SUM(AF61:AI61) -> 298.4 | AK61: 77.6 | AL61: 78.2 | AM61: 81 | AN61: 94.2 | AO61: =SUM(AK61:AN61) -> 331 | AP61: 104.4 | AQ61: 120.8 | AR61: 129.9 | AS61: 141.6 | AT61: =SUM(AP61:AS61) -> 496.7 | AU61: 149.4 | AV61: 158.2 | AW61: 161.4 | AX61: 193.8 | AY61: =SUM(AU61:AX61) -> 662.8 | AZ61: 170 | BA61: 181.1 | BB61: 178.8 | BC61: 203.6 | BD61: =SUM(AZ61:BC61) -> 733.5 | BE61: 199.5 | BF61: 180.7 | BG61: 205 | BH61: 197.8 | BI61: =SUM(BE61:BH61) -> 783 | BJ61: 171 | BK61: 183.8 | BL61: 188.8 | BM61: 192.1 | BN61: =SUM(BJ61:BM61) -> 735.7 | BO61: 170.5 | BP61: 181.2 | BQ61: 184.5 | BR61: 193.1 | BS61: =SUM(BO61:BR61) -> 729.3 | BT61: 169.8 | BU61: 196.9 | BV61: 207.6 | BW61: 209.5 | BX61: =SUM(BT61:BW61) -> 783.8 | BY61: =191.1 -> 191.1 | BZ61: =BU61*(1+BZ291) -> 206.745 | CA61: =BV61*(1+CA291) -> 213.828 | CB61: =BW61*(1+CB291) -> 219.975 | CC61: =SUM(BY61:CB61) -> 831.648 | CD61: =CC61*(1+CD291) -> 706.9008 | CE61: =CD61*(1+CE291) -> 494.83056 | CF61: =CE61*(1+CF291) -> 346.38139 | CG61: =CF61*(1+CG291) -> 242.46697 | CH61: =CG61*(1+CH291) -> 169.72688
H62: Humatrope | L62: 104.6 | M62: 108.8 | N62: 100.2 | O62: 100.8 | P62: 414.4 | Q62: =Q63+Q64 -> 96.7 | R62: =R63+R64 -> 108 | S62: =S63+S64 -> 101.6 | T62: =T63+T64 -> 109.4 | U62: =U63+U64 -> 415.7 | V62: =V63+V64 -> 107.9 | W62: =W63+W64 -> 113.1 | X62: =X63+X64 -> 105.6 | ... CH62: =CH63+CH64 -> 273.45254 | EX62: Humatrope
H63: U.S. (Dec-14 process patent) | L63: 48.1 | M63: 46.4 | N63: 47.1 | O63: 42.9 | P63: 184.5 | Q63: 48.3 | R63: 52 | S63: 49.3 | T63: 52.7 | U63: =SUM(Q63:T63) -> 202.3 | V63: 56.1 | W63: 54.2 | X63: 51.5 | Y63: 51.9 | Z63: =SUM(V63:Y63) -> 213.7 | AA63: 54.4 | AB63: 55.8 | AC63: 49.1 | AD63: 52.8 | AE63: =SUM(AA63:AD63) -> 212.1 | AF63: 45.9 | AG63: 49.1 | AH63: 50.8 | AI63: 57 | AJ63: =SUM(AF63:AI63) -> 202.8 | AK63: 40.4 | AL63: 46.3 | AM63: 43.2 | AN63: 45.9 | AO63: =SUM(AK63:AN63) -> 175.8 | AP63: 51.7 | AQ63: 46.7 | AR63: 40.9 | AS63: 46 | AT63: =SUM(AP63:AS63) -> 185.3 | AU63: 34.4 | AV63: 42.3 | AW63: 45.7 | AX63: 43.4 | AY63: =SUM(AU63:AX63) -> 165.8 | AZ63: 23.7 | BA63: 35.1 | BB63: 44.8 | BC63: 35.2 | BD63: =SUM(AZ63:BC63) -> 138.8 | BE63: 10.3 | BF63: 41.5 | BG63: 28.8 | BH63: 42.1 | BI63: =SUM(BE63:BH63) -> 122.7 | BJ63: 28.2 | BK63: 32.6 | BL63: 34.7 | BM63: 42 | BN63: =SUM(BJ63:BM63) -> 137.5 | BO63: 25.2 | BP63: 27.3 | BQ63: 30.5 | BR63: 50 | BS63: =SUM(BO63:BR63) -> 133 | BT63: 12.8 | BU63: 51.4 | BV63: 39.7 | BW63: 59.3 | BX63: =SUM(BT63:BW63) -> 163.2 | BY63: =25.7 -> 25.7 | BZ63: =BU63*(1+BZ293) -> 41.12 | CA63: =BV63*(1+CA293) -> 41.685 | CB63: =BW63*(1+CB293) -> 59.3 | CC63: =SUM(BY63:CB63) -> 167.805 | CD63: =CC63*(1+CD293) -> 167.805 | CE63: =CD63*(1+CE293) -> 162.77085 | CF63: =CE63*(1+CF293) -> 157.88772 | CG63: =CF63*(1+CG293) -> 153.15109 | CH63: =CG63*(1+CH293) -> 148.55656
H64: ex-US | L64: 56.5 | M64: 62.4 | N64: 53.1 | O64: 57.9 | P64: 229.9 | Q64: 48.4 | R64: 56 | S64: 52.3 | T64: 56.7 | U64: =SUM(Q64:T64) -> 213.4 | V64: 51.8 | W64: 58.9 | X64: 54.1 | Y64: 62.3 | Z64: =SUM(V64:Y64) -> 227.1 | AA64: 60 | AB64: 67.9 | AC64: 62 | AD64: 66.2 | AE64: =SUM(AA64:AD64) -> 256.1 | AF64: 58.1 | AG64: 60.39 | AH64: 61.1 | AI64: 66.4 | AJ64: =SUM(AF64:AI64) -> 245.99 | AK64: 61.3 | AL64: 61.5 | AM64: 58.1 | AN64: 65.8 | AO64: =SUM(AK64:AN64) -> 246.7 | AP64: 61.1 | AQ64: 64.3 | AR64: 62.2 | AS64: 63.7 | AT64: =SUM(AP64:AS64) -> 251.3 | AU64: 55.8 | AV64: 57.9 | AW64: 56.7 | AX64: 55.5 | AY64: =SUM(AU64:AX64) -> 225.9 | AZ64: 55.4 | BA64: 55.7 | BB64: 51.7 | BC64: 56 | BD64: =SUM(AZ64:BC64) -> 218.8 | BE64: 50.9 | BF64: 53 | BG64: 49.2 | BH64: 49.4 | BI64: =SUM(BE64:BH64) -> 202.5 | BJ64: 43 | BK64: 43.6 | BL64: 42.7 | BM64: 45.4 | BN64: =SUM(BJ64:BM64) -> 174.7 | BO64: 40.4 | BP64: 45.4 | BQ64: 42.2 | BR64: 43.5 | BS64: =SUM(BO64:BR64) -> 171.5 | BT64: 38.9 | BU64: 42.4 | BV64: 41.5 | BW64: 43.9 | BX64: =SUM(BT64:BW64) -> 166.7 | BY64: =40 -> 40 | BZ64: =BU64*(1+BZ294) -> 40.28 | CA64: =BV64*(1+CA294) -> 39.425 | CB64: =BW64*(1+CB294) -> 41.705 | CC64: =SUM(BY64:CB64) -> 161.41 | CD64: =CC64*(1+CD294) -> 153.3395 | CE64: =CD64*(1+CE294) -> 145.67252 | CF64: =CE64*(1+CF294) -> 138.3889 | CG64: =CF64*(1+CG294) -> 131.46945 | CH64: =CG64*(1+CH294) -> 124.89598
H65: Axiron | AP65: =AP66+AP67 -> 0 | AQ65: =AQ66+AQ67 -> 2.2 | AR65: =AR66+AR67 -> 5.2 | AS65: =AS66+AS67 -> 15.5 | AT65: =AT66+AT67 -> 22.9 | AU65: =AU66+AU67 -> 16.3 | AV65: =AV66+AV67 -> 17.7 | AW65: =AW66+AW67 -> 16 | ... BX65: =BX66+BX67 -> 79.6 | EX65: Axiron
H66: U.S. (2/19/2017) | AP66: 0 | AQ66: 2.2 | AR66: 5.2 | AS66: 15.5 | AT66: =SUM(AP66:AS66) -> 22.9 | AU66: 16.3 | AV66: 17.7 | AW66: 16 | AX66: 23.9 | AY66: =SUM(AU66:AX66) -> 73.9 | AZ66: 37 | BA66: 46.7 | BB66: 40.3 | BC66: 53 | BD66: =SUM(AZ66:BC66) -> 177 | BE66: 38.3 | BF66: 45.5 | BG66: 34.5 | BH66: 45.4 | BI66: =SUM(BE66:BH66) -> 163.7 | BJ66: 37.3 | BK66: 30.4 | BL66: 39.6 | BM66: 40.2 | BN66: =SUM(BJ66:BM66) -> 147.5 | BO66: 35.6 | BP66: 27.6 | BQ66: 37.3 | BR66: 38.1 | BS66: =SUM(BO66:BR66) -> 138.6 | BT66: 25.8 | BU66: 35.4 | BV66: 6.4 | BW66: 5.9 | BX66: =SUM(BT66:BW66) -> 73.5
H67: ex-US | AK67: 0 | AL67: 0 | AM67: 0 | AN67: 0 | AT67: =SUM(AP67:AS67) -> 0 | AY67: =SUM(AU67:AX67) -> 0 | AZ67: 0 | BA67: 0.4 | BB67: 0.3 | BC67: 0.9 | BD67: =SUM(AZ67:BC67) -> 1.6 | BE67: 1.2 | BF67: 1.6 | BG67: 1.8 | BH67: 2.2 | BI67: =SUM(BE67:BH67) -> 6.8 | BJ67: 1.8 | BK67: 2 | BL67: 1.8 | BM67: 1.4 | BN67: =SUM(BJ67:BM67) -> 7 | BO67: 1.4 | BP67: 1.7 | BQ67: 1.7 | BR67: 1.9 | BS67: =SUM(BO67:BR67) -> 6.7 | BT67: 1.5 | BU67: 1.4 | BV67: 1.6 | BW67: 1.6 | BX67: =SUM(BT67:BW67) -> 6.1
H68: Tradjenta/Jenta (100% GM, receive 50% GP from BI) | AP68: =AP69+AP70 -> 0 | AQ68: =AQ69+AQ70 -> 5.6 | AR68: =AR69+AR70 -> 2.8 | AS68: =AS69+AS70 -> 6.7 | AT68: =AT69+AT70 -> 15.1 | AU68: =AU69+AU70 -> 12.8 | AV68: =AV69+AV70 -> 13.2 | AW68: =AW69+AW70 -> 22.8 | ... CH68: =CH69+CH70 -> 753.49251 | EX68: Tradjenta/Jenta (100% GM, receive 50% GP from BI)
H69: U.S. (5/2/2025) | AP69: 0 | AQ69: 5.6 | AR69: 0.6 | AS69: 5.4 | AT69: =SUM(AP69:AS69) -> 11.6 | AU69: 9.7 | AV69: 9.3 | AW69: 13.7 | AX69: 23.3 | AY69: =SUM(AU69:AX69) -> 56 | AZ69: 24.4 | BA69: 24 | BB69: 29.1 | BC69: 41.1 | BD69: =SUM(AZ69:BC69) -> 118.6 | BE69: 30.8 | BF69: 36.6 | BG69: 24.1 | BH69: 26.8 | BI69: =SUM(BE69:BH69) -> 118.3 | BJ69: 31.9 | BK69: 33.9 | BL69: 38.4 | BM69: 38.3 | BN69: =SUM(BJ69:BM69) -> 142.5 | BO69: 38.3 | BP69: 48.6 | BQ69: 47.9 | BR69: 31 | BS69: =SUM(BO69:BR69) -> 165.8 | BT69: 45.4 | BU69: 60.4 | BV69: 68.4 | BW69: 39 | BX69: =SUM(BT69:BW69) -> 213.2 | BY69: =54.1 -> 54.1 | BZ69: =BU69*(1+BZ299) -> 63.42 | CA69: =BV69*(1+CA299) -> 68.4 | CB69: =BW69*(1+CB299) -> 68.25 | CC69: =SUM(BY69:CB69) -> 254.17 | CD69: =CC69*(1+CD299) -> 274.5036 | CE69: =CD69*(1+CE299) -> 288.22878 | CF69: =CE69*(1+CF299) -> 293.99336 | CG69: =CF69*(1+CG299) -> 285.17355 | CH69: =CG69*(1+CH299) -> 256.6562
H70: ex-US | AP70: 0 | AQ70: 0 | AR70: 2.2 | AS70: 1.3 | AT70: =SUM(AP70:AS70) -> 3.5 | AU70: 3.1 | AV70: 3.9 | AW70: 9.1 | AX70: 16.6 | AY70: =SUM(AU70:AX70) -> 32.7 | AZ70: 18.2 | BA70: 30.8 | BB70: 35.6 | BC70: 46 | BD70: =SUM(AZ70:BC70) -> 130.6 | BE70: 46.1 | BF70: 53.7 | BG70: 54.8 | BH70: 55.9 | BI70: =SUM(BE70:BH70) -> 210.5 | BJ70: 50.4 | BK70: 46.1 | BL70: 54.3 | BM70: 63.4 | BN70: =SUM(BJ70:BM70) -> 214.2 | BO70: 56.1 | BP70: 72.4 | BQ70: 67.5 | BR70: 74.8 | BS70: =SUM(BO70:BR70) -> 270.8 | BT70: 67.6 | BU70: 81.5 | BV70: 84.9 | BW70: 90.7 | BX70: =SUM(BT70:BW70) -> 324.7 | BY70: =87 -> 87 | BZ70: =BU70*(1+BZ300) -> 101.875 | CA70: =BV70*(1+CA300) -> 103.578 | CB70: =BW70*(1+CB300) -> 107.026 | CC70: =SUM(BY70:CB70) -> 399.479 | CD70: =CC70*(1+CD300) -> 447.41648 | CE70: =CD70*(1+CE300) -> 483.2098 | CF70: =CE70*(1+CF300) -> 512.20239 | CG70: =CF70*(1+CG300) -> 512.20239 | CH70: =CG70*(1+CH300) -> 496.83631
H71: Jardiance/Glyxambi (100% GM, receive 50% GP from BI) | AP71: =AP72+AP73 -> 0 | AQ71: =AQ72+AQ73 -> 5.6 | AR71: =AR72+AR73 -> 2.8 | AS71: =AS72+AS73 -> 6.7 | BG71: =BG72+BG73 -> 4.5 | BH71: =BH72+BH73 -> 5.6 | BI71: =BI72+BI73 -> 10.1 | BJ71: =BJ72+BJ73 -> 19.3 | BK71: =BK72+BK73 -> 11.1 | BL71: =BL72+BL73 -> 15.4 | BM71: =BM72+BM73 -> 14.6 | BN71: =BN72+BN73 -> 60.4 | ... CH71: =CH72+CH73 -> 1759.8203 | EX71: Jardiance/Glyxambi (100% GM, receive 50% GP from BI)
H72: U.S. (4/15/2027) | AP72: 0 | AQ72: 5.6 | AR72: 0.6 | AS72: 5.4 | BG72: 4.4 | BH72: 4.6 | BI72: =SUM(BE72:BH72) -> 9 | BJ72: 15.2 | BK72: 9.9 | BL72: 13 | BM72: 9.6 | BN72: =SUM(BJ72:BM72) -> 47.7 | BO72: 29.7 | BP72: 26 | BQ72: 32.9 | BR72: 55.8 | BS72: =SUM(BO72:BR72) -> 144.4 | BT72: 47.7 | BU72: 66.8 | BV72: 83.8 | BW72: 92.1 | BX72: =SUM(BT72:BW72) -> 290.4 | BY72: =95 -> 95 | BZ72: =BU72*(1+BZ302) -> 123.58 | CA72: =BV72*(1+CA302) -> 142.46 | CB72: =BW72*(1+CB302) -> 151.965 | CC72: =SUM(BY72:CB72) -> 513.005 | CD72: =CC72*(1+CD302) -> 682.29665 | CE72: =CD72*(1+CE302) -> 818.75598 | CF72: =CE72*(1+CF302) -> 917.0067 | CG72: =CF72*(1+CG302) -> 981.19717 | CH72: =CG72*(1+CH302) -> 1030.257
H73: ex-US | AP73: 0 | AQ73: 0 | AR73: 2.2 | AS73: 1.3 | BG73: 0.1 | BH73: 1 | BI73: =SUM(BE73:BH73) -> 1.1 | BJ73: 4.1 | BK73: 1.2 | BL73: 2.4 | BM73: 5 | BN73: =SUM(BJ73:BM73) -> 12.7 | BO73: 8.5 | BP73: 14.1 | BQ73: 14.6 | BR73: 20.4 | BS73: =SUM(BO73:BR73) -> 57.6 | BT73: 26.2 | BU73: 36.3 | BV73: 43.4 | BW73: 51.1 | BX73: =SUM(BT73:BW73) -> 157 | BY73: =56 -> 56 | BZ73: =BU73*(1+BZ303) -> 70.785 | CA73: =BV73*(1+CA303) -> 78.12 | CB73: =BW73*(1+CB303) -> 84.315 | CC73: =SUM(BY73:CB73) -> 289.22 | CD73: =CC73*(1+CD303) -> 404.908 | CE73: =CD73*(1+CE303) -> 526.3804 | CF73: =CE73*(1+CF303) -> 631.65648 | CG73: =CF73*(1+CG303) -> 694.82213 | CH73: =CG73*(1+CH303) -> 729.56323
H74: Trulicity | BH74: =BH75+BH76 -> 10.2 | BI74: =BI75+BI76 -> 10.2 | BJ74: =BJ75+BJ76 -> 18.3 | BK74: =BK75+BK76 -> 44.3 | BL74: =BL75+BL76 -> 73.7 | BM74: =BM75+BM76 -> 112.5 | BN74: =BN75+BN76 -> 248.8 | BO74: =BO75+BO76 -> 143.6 | ... CH74: =CH75+CH76 -> 6048.31 | EX74: Trulicity
H75: U.S. (2026) | BH75: 10.2 | BI75: =SUM(BE75:BH75) -> 10.2 | BJ75: 14.9 | BK75: 37.3 | BL75: 63.2 | BM75: 92.4 | BN75: =SUM(BJ75:BM75) -> 207.8 | BO75: 119.4 | BP75: 161.4 | BQ75: 188.7 | BR75: 268.1 | BS75: =SUM(BO75:BR75) -> 737.6 | BT75: 296.3 | BU75: 380.9 | BV75: 412.9 | BW75: 519.8 | BX75: =SUM(BT75:BW75) -> 1609.9 | BY75: =528.2 -> 528.2 | BZ75: =BU75*(1+BZ305) -> 578.968 | CA75: =BV75*(1+CA305) -> 619.35 | CB75: =BW75*(1+CB305) -> 686.136 | CC75: =SUM(BY75:CB75) -> 2412.654 | CD75: =CC75*(1+CD305) -> 3184.7033 | CE75: =CD75*(1+CE305) -> 3694.2558 | CF75: =CE75*(1+CF305) -> 3989.7963 | CG75: =CF75*(1+CG305) -> 4189.2861 | CH75: =CG75*(1+CH305) -> 4314.9647
H76: ex-US | BH76: 0 | BI76: =SUM(BE76:BH76) -> 0 | BJ76: 3.4 | BK76: 7 | BL76: 10.5 | BM76: 20.1 | BN76: =SUM(BJ76:BM76) -> 41 | BO76: 24.2 | BP76: 39.9 | BQ76: 54.9 | BR76: 69 | BS76: =SUM(BO76:BR76) -> 188 | BT76: 76.6 | BU76: 99.3 | BV76: 114.8 | BW76: 129.2 | BX76: =SUM(BT76:BW76) -> 419.9 | BY76: =150.1 -> 150.1 | BZ76: =BU76*(1+BZ306) -> 163.845 | CA76: =BV76*(1+CA306) -> 183.68 | CB76: =BW76*(1+CB306) -> 200.26 | CC76: =SUM(BY76:CB76) -> 697.885 | CD76: =CC76*(1+CD306) -> 977.039 | CE76: =CD76*(1+CE306) -> 1250.6099 | CF76: =CE76*(1+CF306) -> 1500.7319 | CG76: =CF76*(1+CG306) -> 1650.8051 | CH76: =CG76*(1+CH306) -> 1733.3453
H77: Basaglar (est mid-40s GM, LLY shares 50% of GP with BI in COGS) | BH77: =BH78+BH79 -> 0 | BI77: =BI78+BI79 -> 0 | BJ77: =BJ78+BJ79 -> 0 | BK77: =BK78+BK79 -> 0 | BL77: =BL78+BL79 -> 3.8 | BM77: =BM78+BM79 -> 7.3 | BN77: =BN78+BN79 -> 11.1 | BO77: =BO78+BO79 -> 10.9 | ... CH77: =CH78+CH79 -> 555.53082 | EX77: Basaglar (est mid-40s GM, LLY shares 50% of GP with BI in COGS)
H78: U.S. | BM78: 0 | BO78: 0 | BP78: 0 | BQ78: 0 | BR78: 15.8 | BS78: =SUM(BO78:BR78) -> 15.8 | BT78: 22 | BU78: 59.5 | BV78: 115.2 | BW78: 114.4 | BX78: =SUM(BT78:BW78) -> 311.1 | BY78: =126.7 -> 126.7 | BZ78: =BU78*(1+BZ308) -> 148.75 | CA78: =BV78*(1+CA308) -> 161.28 | CB78: =BW78*(1+CB308) -> 165.88 | CC78: =SUM(BY78:CB78) -> 602.61 | CD78: =CC78*(1+CD308) -> 572.4795 | CE78: =CD78*(1+CE308) -> 457.9836 | CF78: =CE78*(1+CF308) -> 412.18524 | CG78: =CF78*(1+CG308) -> 370.96672 | CH78: =CG78*(1+CH308) -> 333.87004
H79: ex-US | BL79: 3.8 | BM79: 7.3 | BN79: =SUM(BJ79:BM79) -> 11.1 | BO79: 10.9 | BP79: 16.3 | BQ79: 19.4 | BR79: 23.7 | BS79: =SUM(BO79:BR79) -> 70.3 | BT79: 24 | BU79: 27.1 | BV79: 30.5 | BW79: 39.4 | BX79: =SUM(BT79:BW79) -> 121 | BY79: =39.3 -> 39.3 | BZ79: =BU79*(1+BZ309) -> 43.36 | CA79: =BV79*(1+CA309) -> 45.75 | CB79: =BW79*(1+CB309) -> 55.16 | CC79: =SUM(BY79:CB79) -> 183.57 | CD79: =CC79*(1+CD309) -> 211.1055 | CE79: =CD79*(1+CE309) -> 221.66077 | CF79: =CE79*(1+CF309) -> 221.66077 | CG79: =CF79*(1+CG309) -> 221.66077 | CH79: =CG79*(1+CH309) -> 221.66077
H80: Other | L80: 12.8 | M80: 18.4 | N80: 20.8 | O80: 13.5 | P80: 65.5 | Q80: =Q81+Q82 -> 15.6 | R80: =R81+R82 -> 16.6 | S80: =S81+S82 -> 21 | T80: =T81+T82 -> 13.9 | U80: =U81+U82 -> 67.1 | V80: =V81+V82 -> 17.6 | W80: =W81+W82 -> 17.7 | X80: =X81+X82 -> 23.7 | ... CH80: =CH81+CH82 -> 247.54993 | EX80: Other Endocrine
H81: U.S. | L81: 9.2 | M81: 14.8 | N81: 16.8 | O81: 10 | P81: 50.8 | Q81: 11.6 | R81: 13 | S81: 16 | T81: 10.3 | U81: =SUM(Q81:T81) -> 50.9 | V81: 13.6 | W81: 13 | X81: 19.4 | Y81: 14.1 | Z81: =SUM(V81:Y81) -> 60.1 | AA81: 13.8 | AB81: 13 | AC81: 17.5 | AD81: 13.8 | AE81: =SUM(AA81:AD81) -> 58.1 | AF81: 15.8 | AG81: 17.1 | AH81: 20.1 | AI81: 12.7 | AJ81: =SUM(AF81:AI81) -> 65.7 | AK81: 15.4 | AL81: 17.2 | AM81: 28.3 | AN81: 19.3 | AO81: =SUM(AK81:AN81) -> 80.2 | AP81: 17.8 | AQ81: 18.1 | AR81: 26.2 | AS81: 18.1 | AT81: =SUM(AP81:AS81) -> 80.2 | AU81: =AU48-AU51-AU54-AU57-AU60-AU63-AU66-AU69 -> 71.8 | AV81: =AV48-AV51-AV54-AV57-AV60-AV63-AV66-AV69 -> 39.4 | AW81: =AW48-AW51-AW54-AW57-AW60-AW63-AW66-AW69 -> 37.3 | AX81: =AX48-AX51-AX54-AX57-AX60-AX63-AX66-AX69 -> 17 | AY81: =SUM(AU81:AX81) -> 165.5 | AZ81: =AZ48-AZ51-AZ54-AZ57-AZ60-AZ63-AZ66-AZ69 -> 23.4 | BA81: =BA48-BA51-BA54-BA57-BA60-BA63-BA66-BA69 -> 40.9 | BB81: =BB48-BB51-BB54-BB57-BB60-BB63-BB66-BB69 -> 26.2 | BC81: =BC48-BC51-BC54-BC57-BC60-BC63-BC66-BC69 -> 27.8 | BD81: =SUM(AZ81:BC81) -> 118.3 | BE81: =BE48-BE51-BE54-BE57-BE60-BE63-BE66-BE69-BE72 -> 22.8 | BF81: =BF48-BF51-BF54-BF57-BF60-BF63-BF66-BF69-BF72 -> 24.5 | BG81: =BG48-BG51-BG54-BG57-BG60-BG63-BG66-BG69-BG72 -> 30.3 | BH81: =BH48-BH51-BH54-BH57-BH60-BH63-BH66-BH69-BH72-BH75 -> 23.5 | BI81: =SUM(BE81:BH81) -> 101.1 | BJ81: =BJ48-BJ51-BJ54-BJ57-BJ60-BJ63-BJ66-BJ69-BJ72-BJ75-BJ78 -> 25.7 | BK81: =BK48-BK51-BK54-BK57-BK60-BK63-BK66-BK69-BK72-BK75-BK78 -> 24.8 | BL81: =BL48-BL51-BL54-BL57-BL60-BL63-BL66-BL69-BL72-BL75-BL78 -> 41.9 | BM81: =BM48-BM51-BM54-BM57-BM60-BM63-BM66-BM69-BM72-BM75-BM78 -> 23.1 | BN81: =SUM(BJ81:BM81) -> 115.5 | BO81: =BO48-BO51-BO54-BO57-BO60-BO63-BO66-BO69-BO72-BO75-BO78 -> 29.2 | BP81: =BP48-BP51-BP54-BP57-BP60-BP63-BP66-BP69-BP72-BP75-BP78 -> 30.1 | BQ81: =BQ48-BQ51-BQ54-BQ57-BQ60-BQ63-BQ66-BQ69-BQ72-BQ75-BQ78 -> 44.3 | BR81: =BR48-BR51-BR54-BR57-BR60-BR63-BR66-BR69-BR72-BR75-BR78 -> 25.2 | BS81: =SUM(BO81:BR81) -> 128.8 | BT81: =BT48-BT51-BT54-BT57-BT60-BT63-BT66-BT69-BT72-BT75-BT78 -> 32.7 | BU81: =BU48-BU51-BU54-BU57-BU60-BU63-BU66-BU69-BU72-BU75-BU78 -> 31 | BV81: =BV48-BV51-BV54-BV57-BV60-BV63-BV66-BV69-BV72-BV75-BV78 -> 44.6 | BW81: =BW48-BW51-BW54-BW57-BW60-BW63-BW66-BW69-BW72-BW75-BW78 -> 28.7 | BX81: =SUM(BT81:BW81) -> 137 | BY81: =BY48-BY51-BY54-BY57-BY60-BY63-BY66-BY69-BY72-BY75-BY78 -> 38.4 | BZ81: =BU81*(1+BZ311) -> 34.72 | CA81: =BV81*(1+CA311) -> 46.83 | CB81: =BW81*(1+CB311) -> 31.57 | CC81: =SUM(BY81:CB81) -> 151.52 | CD81: =CC81*(1+CD311) -> 157.5808 | CE81: =CD81*(1+CE311) -> 162.30822 | CF81: =CE81*(1+CF311) -> 165.55439 | CG81: =CF81*(1+CG311) -> 167.20993 | CH81: =CG81*(1+CH311) -> 167.20993
